[{"job_id": "100003009054901", "location_code": "hk", "company": "Melaleuca of Asia Ltd Co", "job_title": "Senior/Marketing Officer", "description": "Responsibilities:\n\nTo support Product & Marketing Manager and work as a team to execute product plans and strategy with the ultimate objective of raising brand awareness, brand building and increasing sales;\nTo identify a continuous stream of commercially valuable new products;\nDrive product development, packaging and manage market analysis;\nProduct forecasting and inventory control and management;\nWork closely with internal and external production / QC teams to ensure accurate execution of product development with the right quality and time;\nSupport ad hoc projects when required.\n\nRequirements:\n\n\u00a0 Degree in marketing, business management, nutrition or food science background is preferable;\n\u00a0 Minimum 3 years product experience in retail / FMCG (bottled drinks preferred);\n\u00a0 Solid experience in product marketing is advantageous;\n\u00a0 Good communications skill in Cantonese, Mandarin and English\n\u00a0 Able to independently manage project and drive progress.\n\u00a0 Candidate with more experience will be considered as \"Senior Product Marketing Officer\"\n\n\n\nWe offer 5-day-work week with competitive remuneration and benefit packages to the right candidate. Interested parties please send your application letter, resume, expected salary (quoting Employer Ref:) and availability to\u00a0HR Department at Hung Fook Tong, 8/F, Chuan Kei Factory Building, Nos. 15-23 Kin Hon Street, Kwai Chung, NT., H.K. or e-mail or\u00a0browse our website:\u00a0www.hungfooktong.com\n\nPersonal Information Collection Statement-Applicants\u2019 personal information will be used for the recruitment and employment matters only; information will be kept in strict confidence; information of unsuccessful applicants will be shredded after recruitment process; subject to provisions under the Personal Data (Privacy) Ordinance, applicants have right to access and make corrections of their personal data", "employment_types": ["Full Time", "Permanent"], "selling_points": ["Marketing, Product specialist", "Skincare, essential oil, product development, FMCG", "communications, publications, presentations"], "locations": ["Yau Tsim Mong Area"], "categories": ["Marketing / Public Relations", "Marketing - Brand / Product Management", "Marketing - Direct Marketing", "Marketing - Marketing Communication"], "post_time": "2022-01-17T13:19:16Z", "salary": {"currency": null, "max": null, "min": null, "period": "monthly", "term": null}, "salary_visible": false, "title_keywords": ["marketing officer"], "responsibilities": ["management", "teams", "quality", "inventory control", "market analysis", "ad hoc projects", "plans", "forecasting"], "requirements": {"degrees": ["degree"], "majors": ["business", "marketing", "food science"], "languages": ["cantonese", "english", "mandarin"], "language_level": ["good"], "hard_skills": ["business management"], "soft_skills": ["independently"], "languages_combined": [{"language": "cantonese", "language_level": ["good"]}, {"language": "english", "language_level": ["good"]}, {"language": "mandarin", "language_level": ["good"]}]}, "experience_required": {"duration": ["minimum 3 years"], "field": ["retail", "marketing", "fmcg"]}}, {"job_id": "100003009054100", "location_code": "hk", "company": "OSMA Consulting Limited", "job_title": "Marketing Assistant \u5e02\u573a\u90e8\u4e13\u5458", "description": "Job responsibilities:\u00a0\n\nResponsible for\u00a0Skincare & Essential Oil product line \u00a0\n\nAssist in product development (e.g. labeling, packaging, product formula optimization, etc)\nDevelop communication materials\u00a0\u00a0(e.g. Copy-writing, Videos, Presentation, etc) to communicate product benefits\nAssist in product strategy of our Skincare & Essential Oil products (e.g. market trend updates, pricing and inventory forecast, etc.)\nAssist in publication & catalog preparation\nTo analyze potential product details, product performance data to help product planning \u00a0\n\nJob requirements:\n\nAt least 2\u00a0years of related working experience, preferably\u00a0experience in FMCG, marketing, communications & product management\nGood PC skills in Office especially Excel analysis, PowerPoint.\nKnowledge at design software (e.g. InDesign, Photoshop, illustrator) and basic video editing is preferable\nWorking experience in Skincare / Essential Oil industry is an advantage\nStrong communication in spoken and written English and Mandarin\nProactive, efficient, independent, detail-minded, positive and able to manage multiple projects in parallel\nCandidates with more experience will be considered as Senior Marketing Officer", "employment_types": ["Full Time"], "selling_points": ["High-end Club", "Excellent exposure", "Attractive Package"], "locations": ["Central"], "categories": ["Marketing / Public Relations", "Marketing - Brand / Product Management", "Marketing - General / Support", "Marketing - Marketing Communication"], "post_time": "2022-01-17T08:25:50Z", "salary": {"currency": null, "max": null, "min": null, "period": "monthly", "term": null}, "salary_visible": false, "title_keywords": ["marketing assistant"], "responsibilities": ["communication", "develop"], "requirements": {"degrees": [], "majors": [], "languages": [], "language_level": [], "hard_skills": [], "soft_skills": [], "languages_combined": []}, "experience_required": {"duration": [], "field": []}}, {"job_id": "100003009054885", "location_code": "hk", "company": "In N Out International Corporate Limited", "job_title": "Business Growth Manager & Assistant to Director", "description": "Our Client is a Hong Kong based Fin-tech company with founding members from reputable local family offices and high level seniors of international conglomerates. To market their newly launched financial products, they are looking for qualified individuals to join the their team assisting daily operation.\n\n\u6211\u4eec\u7684\u5ba2\u6237\u662f\u4e00\u5bb6\u603b\u90e8\u4f4d\u4e8e\u9999\u6e2f\u7684\u91d1\u878d\u79d1\u6280\u516c\u53f8\uff0c\u5176\u521b\u59cb\u6210\u5458\u6765\u81ea\u5f53\u5730\u8457\u540d\u7684\u5bb6\u65cf\u529e\u516c\u5ba4\u548c\u56fd\u9645\u4f01\u4e1a\u96c6\u56e2\u7684\u9ad8\u5c42\u3002 \u4e3a\u4e86\u8425\u9500\u4ed6\u4eec\u65b0\u63a8\u51fa\u91d1\u878d\u4ea7\u54c1\uff0c\u4ed6\u4eec\u6b63\u5728\u5bfb\u627e\u5408\u683c\u7684\u4e2a\u4eba\u52a0\u5165\u4ed6\u4eec\u7684\u56e2\u961f\uff0c\u534f\u52a9\u65e5\u5e38\u8fd0\u8425\u3002\n\nResponsibilities:\n1.\u00a0Support Marketing Manager to consolidate promotion plan and coordinate with internal business units;\n2. Assist Marketing Manager to organize any promotion or roadshow event;\n3. Work closely with Business Development team to deliver\u00a0promotion materials to outside parties through both online and offline channels;\n4.\u00a0Deliver all assigned projects with high quality as requested by seniors.\n\nRequirements:\n1. Degree or above;\n2. Excellent communication and interpersonal skills;\n3. Knowledge in social media marketing & website analytics tools will be an advantage;\n4. Good command of English and Mandarin is a plus.\n\n\n\u804c\u8d23\uff1a\n1.\u652f\u6301\u8425\u9500\u7ecf\u7406\u6574\u5408\u63a8\u5e7f\u8ba1\u5212\uff0c\u4e0e\u5185\u90e8\u4e1a\u52a1\u90e8\u95e8\u534f\u8c03\uff1b\n2.\u534f\u52a9\u8425\u9500\u7ecf\u7406\u7ec4\u7ec7\u4efb\u4f55\u4fc3\u9500\u6216\u8def\u6f14\u6d3b\u52a8\uff1b\n3.\u4e0e\u4e1a\u52a1\u53d1\u5c55\u56e2\u961f\u7d27\u5bc6\u5408\u4f5c\uff0c\u901a\u8fc7\u7ebf\u4e0a\u7ebf\u4e0b\u6e20\u9053\u5411\u5916\u754c\u63d0\u4f9b\u5ba3\u4f20\u8d44\u6599\uff1b\n4.\u6309\u7167\u4e0a\u7ea7\u8981\u6c42\uff0c\u9ad8\u8d28\u91cf\u4ea4\u4ed8\u6240\u6709\u5206\u914d\u7684\u9879\u76ee\u3002\n\n\u8981\u6c42\uff1a\n1. \u672c\u79d1\u6216\u4ee5\u4e0a\u5b66\u5386\uff1b\n2. \u4f18\u79c0\u7684\u6c9f\u901a\u548c\u4eba\u9645\u4ea4\u5f80\u80fd\u529b\uff1b\n3. \u719f\u6089\u793e\u4ea4\u5a92\u4f53\u8425\u9500\u548c\u7f51\u7ad9\u5206\u6790\u5de5\u5177\u8005\u4f18\u5148\uff1b\n4. \u82f1\u8bed\u53ca\u666e\u901a\u8bdd\u6d41\u5229\u8005\u4f18\u5148\u3002", "employment_types": ["Full Time"], "selling_points": [], "locations": ["Aberdeen"], "categories": ["Admin & HR", "Personal / Executive Assistant", "Sales, CS & Business Devpt", "Business Development", "Marketing / Public Relations", "Marketing - Brand / Product Management"], "post_time": "2022-01-17T12:37:13Z", "salary": {"currency": null, "max": null, "min": null, "period": "monthly", "term": null}, "salary_visible": false, "title_keywords": ["manager", "director", "assistant"], "responsibilities": ["quality", "plan and coordinate"], "requirements": {"degrees": ["degree or above"], "majors": [], "languages": ["english", "mandarin"], "language_level": ["good command"], "hard_skills": ["analytics tools", "plus"], "soft_skills": ["communication and interpersonal skills"], "languages_combined": [{"language": "english", "language_level": ["good command"]}, {"language": "mandarin", "language_level": ["good command"]}]}, "experience_required": {"duration": [], "field": []}}, {"job_id": "100003009053584", "location_code": "hk", "company": "Whirlpool (Hong Kong) Ltd", "job_title": "Senior Product Marketing Executive", "description": "Job Duties:\n\nExplore new business opportunities and potential growth area of the industry and business\nDrive the company forward by contributing to the expansion project and its operations\nConduct in-depth market research and analyse market trends, pricing and costing\nContribute to internal planning, eg. business strategy, growth, projects and marketing plan etc.\nHandle any ad-hoc assignments, projects and operational support assigned by management.\n\nThis job is not a sales role or a typical business development role, but rather a role that seeks to enhance the business growth and execute the development roadmap of the company.\u00a0We value soft skills more than hard skills. We prefer candidates with 5-12 years working experience.\n\nCompany Culture: Friendly, energetic, flexible, transparent\n\nRequirements:\u00a0\n\nEducation:\u00a0Degree Holder\nWorking Experience: 5\u00a0years working experience or above, preferably with experience in\u00a0business management or assistant to management role.\nPersonality:\u00a0Smart, flexible, detail-minded, proactive, self-motivated and optimistic\nProfessional Strengths:\u00a0Strong business sense, good interpersonal skills, good time management skills, well-organised, ability to problem-solve, and highly responsible\nLanguage:\u00a0Excellent written and spoken Cantonese and English\nComputer Skills:\u00a0Proficient computer skills in Microsoft word, excel, powerpoint, Chinese typing, etc.\nJob Type:\u00a0Full-Time\nWorking Location:\u00a0Aberdeen, Hong Kong Island\n\nWe offer competitive salary and great future prospect in a fast growing company. Salaries commensurate with experience and qualification.\n\nInterested parties, please send your detailed resume with contact number, available date, current and expected salary through \"Apply Now\" button below.", "employment_types": ["Full Time"], "selling_points": ["Creative thinking with multi-tasking ability", "2 yrs exp in marketing, consumer appliances/retail", "Attractive package with Double Pay & Annual Bonus"], "locations": ["Ngau Tau Kok"], "categories": ["Marketing / Public Relations", "Marketing - Brand / Product Management"], "post_time": "2022-01-17T07:12:06Z", "salary": {"currency": null, "max": null, "min": null, "period": "monthly", "term": null}, "salary_visible": false, "title_keywords": ["marketing executive"], "responsibilities": ["management", "operational support", "explore new business opportunities", "operations", "ad-hoc assignments", "market research", "marketing plan", "analyse", "planning"], "requirements": {"degrees": ["degree holder"], "majors": [], "languages": ["cantonese", "english", "chinese"], "language_level": ["excellent", "proficient"], "hard_skills": ["business management", "excel", "microsoft word", "typing", "powerpoint", "computer skills"], "soft_skills": ["flexible", "detail-minded", "self-motivated", "responsible", "business sense", "time management skills", "interpersonal skills", "well-organised", "proactive"], "languages_combined": [{"language": "cantonese", "language_level": ["excellent"]}, {"language": "english", "language_level": ["excellent"]}, {"language": "chinese", "language_level": ["proficient"]}]}, "experience_required": {"duration": ["5 years"], "field": ["management", "business"]}}, {"job_id": "100003009052964", "location_code": "hk", "company": "Telford International Co Ltd", "job_title": "Assistant Brand Manager/ Brand Manager \u2013 Alcoholic Beverage Division", "description": "Manage marketing activities of a number of brands we currently represent\nLocate collaboration partners to drive create content and drive brand awareness\nFrequent contact with global photography media to build global brand awareness\nPlan and coordinate both online and offline marketing activities with distributors to drive sales\nWork closely with sales team to formulate plans to drive business across distributors\nCommunication with global distributors to understand market changes\nManage social media and provide end customer service and support.\nNurture the user community and identify collaboration brands and parties.\nKeep close track of industry news and competitor movements\nAttend local and overseas events when necessary", "employment_types": ["Full Time", "Permanent"], "selling_points": ["University Graduate with Marketing Major", "5 years in Marketing Related Exp. in Alcohol Ind.", "Attractive Package with Excellent Career Path"], "locations": ["Kwai Hing"], "categories": ["Sales, CS & Business Devpt", "Business Development", "Marketing / Public Relations", "Management", "Marketing - Brand / Product Management"], "post_time": "2022-01-17T04:43:06Z", "salary": {"currency": null, "max": null, "min": null, "period": "monthly", "term": null}, "salary_visible": false, "title_keywords": ["manager", "assistant"], "responsibilities": ["drive sales", "social media", "plan and coordinate", "communication", "customer service", "sales team", "contact", "plans"], "requirements": {"degrees": [], "majors": [], "languages": [], "language_level": [], "hard_skills": [], "soft_skills": ["communication", "customer service"], "languages_combined": []}, "experience_required": {"duration": [], "field": []}}, {"job_id": "100003009053032", "location_code": "hk", "company": "PS Group International Ltd", "job_title": "Senior Marketing Executive **URGENT**", "description": "Responsibilities:\n\nProvide administrative support to the marketing team in accordance with the Company\u2019s Policy and Procedural Systems & Practices\nUpdate internal reports, records and documents in marketing department\nData tabulation and analysis\nCompetitive analysis and reporting\nMarket intelligence \u2013 desk research and field research coordination\nMarketing fund budget administration and control\nProvide general support and administrative duties to the team\nAssist in ad-hoc tasks and projects as required\n\nRequirements:\n\nDiploma holder or above with educational background in Statistics, Data Management, Accounting or Business Administration\n1-2 years relevant work experience in marketing, experience in FMCG will be an advantage, fresh graduates will also be considered\nAdvanced skills with MS Office esp. Excel and Powerpoint\nSelf-starter, quick learner,\u00a0logical thinking and organized\nImmediately availability is preferred\n\nWorking location:\u00a0Kwai Chung\n\nStaff Benefit:\n\nDiscretionary Bonus\nMedical & Life Insurance\nAnnual Leave\nPayable Sick Leave\nEncourage continuing education and on-job training\nOpen office working environment\nOffer promotion opportunities and long-term career path\u00a0\n\nWe offer a competitive remuneration package to the right candidate.\u00a0Interested parties\u00a0please click\u00a0\"Apply Now\"\u00a0to submit your application\u00a0or by email to\u00a0hr1 @twcoffee.com\n\n\u00a0(All personal data provided by applicants will be treated in strict confidence and used for employment-related purpose only.)", "employment_types": ["Full Time"], "selling_points": ["Hair Products / Beauty / Trading", "Salon & Beauty Group", "Marketing"], "locations": ["North Point"], "categories": ["Marketing / Public Relations", "Marketing - Brand / Product Management"], "post_time": "2022-01-17T05:15:30Z", "salary": {"currency": null, "max": null, "min": null, "period": "monthly", "term": null}, "salary_visible": false, "title_keywords": ["senior marketing executive"], "responsibilities": ["reporting", "control", "data", "analysis", "systems", "budget", "ad-hoc tasks", "reports", "administrative duties", "coordination", "provide administrative support", "general support", "administration"], "requirements": {"degrees": ["diploma holder"], "majors": ["accounting", "statistics", "business administration"], "languages": [], "language_level": [], "hard_skills": ["excel", "data management", "powerpoint", "ms office"], "soft_skills": ["organized", "advanced", "quick learner"], "languages_combined": []}, "experience_required": {"duration": ["1-2 years"], "field": ["marketing", "fmcg"]}}, {"job_id": "100003009052647", "location_code": "hk", "company": "Telford International Co Ltd", "job_title": "Senior Brand Manager/ Brand Manager - Beverage Division", "description": "Being the key member of the Marketing Team in Hong Kong, the successful candidate will assist to manage both product portfolio and brands for Whirlpool in Hong Kong.\n\nResponsibilities:\n\nImplement marketing plans to drive business and market share position and penetration\n\nCarry out regular market research and benchmarking to translate product needs and brand positioning into activity requirements and opportunities for profitable growth across all drivers.\u00a0\n\nProvide insights to central marketing team to create suitable products and to maximize our competitive advantage\n\nWork closely with management, sales, branding, technical teams, regional offices, factories and OEM suppliers to follow through product development process and ensure the smooth execution of product go to market plans\n\nPrepare new product launch and execute go to market plans including price, distribution and promotions\n\nProvide regular product and price benchmarking activities, alter price and promotion plans to achieve business objectives\n\nMonitor inventory and be a key member of the demand planning process.\u00a0 Run promotions for slow moving inventory if necessary\n\nCommunicate with advertising or media agencies to monitor the delivery of production\n\nWork closely with central marketing team to translate product features into consumer language\n\nWork closely with different sales teams to cater sales needs and leverage marketing tools to maximize sales impact\n\nJob Requirements:\n\nDegree holder in marketing or business disciplines\n\nMinimum 2 years marketing experience, preferably in consumer appliances or retail industry\u00a0\u00a0\n\nGood at project management and time management\n\nCreative thinking with multi-tasking ability\n\nSharp analytical abilities \u2013 critical and numerical reasoning\n\nAbility to lead and take ownership to develop marketing initiatives\n\nStrong negotiation, people management and presentation skills in English, Cantonese and Mandarin\n\nComputer literacy with good proficiency in MS Office, particularly Excel & PowerPoint.\u00a0 Google application is a plus\n\nCreative, high flexibility and able to work under tight deadlines\n\nMore experience can be considered as Assistant Product Marketing Manager\n\nImmediate available is highly preferred\n\nEndless Opportunities\n\nThis role provides a start of a challenging and exciting career for those interested in growing and advancing in a global organization. We offer a challenging purpose, ownership of your role, great team environment and provide the tools to build your capability.\n\nInterested parties should send full resume, salary history with current and expected salary. Data collected will be used for recruitment purposes only. Applicants who are not invited for interviews within 8 weeks may consider their applications unsuccessful.", "employment_types": ["Full Time", "Permanent"], "selling_points": ["Degree holder in marketing, business or related", "5+ years exp. in FMCG/Food & Beverage Marketing", "Brand Management"], "locations": ["Kwai Hing"], "categories": ["Sales, CS & Business Devpt", "Business Development", "Hospitality / F & B", "Food & Beverage", "Marketing / Public Relations", "Marketing - Brand / Product Management"], "post_time": "2022-01-17T03:38:33Z", "salary": {"currency": null, "max": null, "min": null, "period": "monthly", "term": null}, "salary_visible": false, "title_keywords": ["manager"], "responsibilities": ["communicate with", "provide insights", "management", "advertising", "marketing plans", "inventory", "demand planning", "teams", "market research", "monitor", "plans"], "requirements": {"degrees": ["degree holder"], "majors": ["business", "marketing"], "languages": ["cantonese", "english", "mandarin"], "language_level": [], "hard_skills": ["excel", "plus", "powerpoint", "project management", "ms office"], "soft_skills": ["negotiation", "creative", "interested in", "project management", "multi-tasking", "presentation skills", "computer literacy", "time management"], "languages_combined": [{"language": "cantonese", "language_level": []}, {"language": "english", "language_level": []}, {"language": "mandarin", "language_level": []}]}, "experience_required": {"duration": ["minimum 2 years"], "field": ["retail industry", "marketing"]}}, {"job_id": "100003009054442", "location_code": "hk", "company": "E Tag Limited", "job_title": "Senior Digital Marketing Executive", "description": "Responsibilities:\n\nFormulate marketing plan and agree the marketing strategies with brand owners in a viable manner\nAble to initiate and execute marketing and promotional activities in on-& off-trade\nMonitor the brand performance and A&P spend against the target\nReview shipment and depletion forecasts regularly to ensure healthy inventory control\nAble to conduct product training and meet up trade customers when needed\nWilling to work during night and sometimes during weekend for special events\n\n\u00a0Requirements:\n\nUniversity Graduate with preferable marketing as major\nMin. 5 years in marketing, trade marketing or senior sales role in lifestyle industry or other FMCG industry,\u00a0in\u00a0alcohol\u00a0industry is highly preferred\nCommercially sensible with good negotiation skill\nHighly self-motivated, strong team player and do not resist drinking\nGood interpersonal and communication skills\nFluency in written and spoken English and Chinese\nCandidate with less experience will be considered as Assistant Brand Manager\n\n\n\nWe offer attractive remuneration package and career prospects plus 5-day week and medical insurance. Interest parties; please forward your full resume with\u00a0Expected Salary to us.\u00a0\n\nAll data collected shall be solely for recruitment purpose.\n\nWebsite\u00a0\u00a0 : \u00a0\u00a0http://www.telford.com.hk/", "employment_types": ["Full Time"], "selling_points": ["Create and manage all marketing initiatives", "Conceptualize and formulate marketing campaigns", "At least 5 years relevant working experience"], "locations": ["Tsuen Wan Area"], "categories": ["Marketing / Public Relations", "Marketing - Brand / Product Management", "Marketing - Marketing Communication", "Digital Marketing"], "post_time": "2022-01-17T09:39:51Z", "salary": {"currency": null, "max": null, "min": null, "period": "monthly", "term": null}, "salary_visible": false, "title_keywords": ["senior digital marketing executive"], "responsibilities": ["marketing strategies", "review", "monitor", "marketing plan", "inventory control", "promotional activities"], "requirements": {"degrees": ["university graduate"], "majors": ["marketing"], "languages": ["english", "chinese"], "language_level": ["fluency"], "hard_skills": ["fmcg industry"], "soft_skills": ["communication skills", "self-motivated", "negotiation skill", "team player", "interpersonal"], "languages_combined": [{"language": "english", "language_level": ["fluency"]}, {"language": "chinese", "language_level": ["fluency"]}]}, "experience_required": {"duration": [], "field": ["brand"]}}, {"job_id": "100003009054010", "location_code": "hk", "company": "Thinking Group Holding Limited", "job_title": "Assistant Marketing Manager", "description": "Responsibilities:-\n\nPlanning & implementation of various Marketing, communications and branding initiatives\nProvide support for preparing marketing collateral, promotional materials, and advertising on social media and e-marketing systems, such as Facebook, Instagram, eDM, etc.\nManage company website and online sales platform on a day-to-day basis\nOrganization of product launching event/seminar\nKeep abreast of the latest development of marketing trends and various social media platforms\nSupport trade marketing as well as collaborate closely with business partners and product seeding among celebrities, KOL, media, influencers, etc\nAssist in ad-hoc project assigned\n\nRequirements:-\n\nDegree holder in Marketing or Business related disciplines\nAt least\u00a03 years working experience in Marketing\nSolid working experience in FMCG / Hair Products / Beauty / Skincare industry will be an advantage\nWith social media, online advertising & PR event experience will be an advantage\nAble to excel in fast-paced and dynamic environment with tight deadlines\nStrong presentation and interpersonal skill\nGood command of written English and Cantonese\nProficient in PC applications, including MS Word, PowerPoint and Excel;\nImmediate available is preferred", "employment_types": ["Full Time", "Permanent"], "selling_points": ["5 years experience in digital, ecommerce marketing", "Increasing brand awareness and market share", "Responsible for media planning, budgeting, event"], "locations": ["Kwun Tong"], "categories": ["Marketing / Public Relations", "Marketing - Brand / Product Management", "Marketing - Marketing Communication", "Digital Marketing"], "post_time": "2022-01-17T08:53:00Z", "salary": {"currency": null, "max": null, "min": null, "period": "monthly", "term": null}, "salary_visible": false, "title_keywords": ["assistant marketing manager"], "responsibilities": ["collaborate", "social media", "provide support", "trade marketing", "advertising", "ad-hoc", "edm", "systems", "social media platforms", "implementation", "promotional materials", "facebook", "company website", "planning"], "requirements": {"degrees": ["degree holder"], "majors": ["business", "related disciplines", "marketing"], "languages": ["cantonese", "english"], "language_level": ["good command"], "hard_skills": ["excel", "powerpoint", "pc applications", "dynamic", "ms word"], "soft_skills": ["dynamic environment", "presentation", "interpersonal skill"], "languages_combined": [{"language": "cantonese", "language_level": ["good command"]}, {"language": "english", "language_level": ["good command"]}]}, "experience_required": {"duration": ["at least 3 years"], "field": ["social media", "pr", "fmcg", "advertising", "marketing", "beauty"]}}, {"job_id": "100003009052610", "location_code": "hk", "company": "Million (Far East) Limited", "job_title": "Senior Marketing Executive", "description": "Major responsibilities:\n\nCreate and manage all marketing initiatives, advertising, promotion activities and public relations plan\nManage all marketing channels including digital channels\nDriving traffic and conversion to brand websites through proper system, content and SEO, develop and operate SEM initiatives\nConceptualize and formulate regular marketing campaigns; develop marketing materials such as eDM, e-flyers and mail outs\nPlan and manage all marketing communications and collaterals, including web, online and print, maintain company brand communication guidelines and standards\nLiaise with media and potential business partners to explore new promotion channels, joint promotion opportunities and build the brand awareness.\nCompile reports and co-ordinate with different parties for project implementation\nSupport in customer relationship management and assist to handle client inquiries, requests and complaints\n\nRequirements:\n\nBachelor degree in Communication/ Business Administration / Marketing or related disciplines\nAt least\u00a05 years of working experience with substantial experience gained in marketing or PR advertising agency\nSound experience in managing consumer/ trade event independently and developing effective marketing communications\nFamiliar with Google Adwords, Google Analytics and Google Search Console\nKnowledge of Adobe Illustrator, Photoshop, and basic HTML is a plus.\nExcellent in both spoken and written English and Chinese with\u00a0bilingual copywriting,\u00a0as spoken and written other languages will be an advantage\u00a0\nBe able to work under pressure with tight timeline and multi-tasking capability\nWell-presented with excellent interpersonal and communication skills\u00a0\nProficiency in MS applications including PowerPoint & Excel\nImmediate availability is highly preferred\n\nWe offer competitive remuneration package and excellent career development to the right candidates. Interested parties please complete the standard application form by clicking the Apply now button. \u00a0You can also attach your tailored CV and Cover letter with present & expected salary, and state of availability to the Human Resources Department which we will use to review applications.\n\nETG is an equal opportunity employer and welcome applications from all qualified candidates.\u00a0 All information provided will be treated in strict confidentiality and will only be used for recruitment-related purpose.\u00a0 We will retain your application for a maximum period of 4 months.", "employment_types": ["Full Time", "Permanent"], "selling_points": ["Senior Marketing Executive", "Food & Beverage", "Exp. in HORECA, Frozen Meat business preferred"], "locations": ["Kwai Fong"], "categories": ["Marketing / Public Relations", "Marketing - Brand / Product Management", "Marketing - General / Support", "Marketing - Market Research"], "post_time": "2022-01-17T03:32:26Z", "salary": {"currency": null, "max": null, "min": null, "period": "monthly", "term": null}, "salary_visible": false, "title_keywords": ["senior marketing executive"], "responsibilities": ["marketing materials", "management", "seo", "advertising", "edm", "guidelines", "compile reports", "co-ordinate with", "implementation", "develop", "communication", "liaise with", "maintain", "sem", "plan", "marketing campaigns"], "requirements": {"degrees": ["degree", "bachelor"], "majors": ["related disciplines", "marketing", "business administration"], "languages": ["english", "chinese"], "language_level": ["advantage", "excellent"], "hard_skills": ["google analytics", "plus", "excel", "basic", "ms applications", "adwords", "html", "adobe illustrator", "powerpoint", "photoshop"], "soft_skills": ["communication skills", "independently", "communication", "multi-tasking", "interpersonal", "work under pressure"], "languages_combined": [{"language": "english", "language_level": ["excellent", "advantage"]}, {"language": "chinese", "language_level": ["excellent", "advantage"]}]}, "experience_required": {"duration": ["at least 5 years"], "field": ["marketing communications", "marketing", "developing", "pr advertising agency"]}}, {"job_id": "100003009054088", "location_code": "hk", "company": "Euroasia Int'l Medical Group", "job_title": "Marketing Executive /Marketing Manager (Beauty) / \u5e02\u5834\u63a8\u5ee3(\u7f8e\u5bb9)", "description": "Thinking Group, a sole distributor of Audio products & Smart Gadget products including: Ultimate Ears (UE), JBL/ Harman Kardon, Aftershokz......etc. Founded in 1998, its headquarters in HK and branches in Shenzhen & Taiwan. To cope with our continuous expansion, we are seeking qualified candidates to join us.\n\nResponsibilities:\n\nPlanning, organizing, implementing and evaluating annual marketing plan\nBuild up and maintain relationship with media & network channel\nGuide social media strategy for professional audio products, including strategy for B2B and B2C\u00a0communication\nWork with Product and Sales team to promote products and brands\nEvaluating and optimizing marketing and pricing strategies\nAnalyzing market trends and preparing forecasts\nIncreasing brand awareness and market share\nCoordinating marketing strategies with the sales, financial public rekations, and production departments\nResponsible for media planning, budgeting, event management\nRequirements:\n\n\nDegree holder in Marketing / Communications / Business Administration or related disciplines\n3 years of relevant experience in digital or ecommerce marketing\u00a0\nProven ability to solve problems creatively\nStrong interpersonal skills and extremely resourceful\u00a0\nKnowledge of digital platforms for marketing purposes and Web Analytics tools\nGood command of spoken and written English and Chinese, Putonghua is an advantage\nCreative, responsible, analytical and self-motivated\nBenefits:\n\n5 day work\nBank holiday and Birthday leave\nAnnaul leave and Sick leave\nMedical and Dental allowance", "employment_types": ["Full Time", "Permanent"], "selling_points": ["Expertise in Facebook promotion,web analytics", "Minimum 3 years experience in beauty industry", "Excellent planning and project management skills"], "locations": ["Mong Kok"], "categories": ["Beauty Care / Health", "Others", "Marketing / Public Relations", "Marketing - Brand / Product Management", "Others"], "post_time": "2022-01-17T08:21:32Z", "salary": {"currency": null, "max": null, "min": null, "period": "monthly", "term": null}, "salary_visible": false, "title_keywords": ["marketing manager", "marketing executive"], "responsibilities": ["social media", "management", "marketing strategies", "budgeting", "communication", "marketing plan", "maintain", "sales team", "promote products", "audio", "planning"], "requirements": {"degrees": ["degree holder"], "majors": ["related disciplines", "marketing", "business administration", "communications"], "languages": ["putonghua", "english", "chinese"], "language_level": ["advantage", "good command"], "hard_skills": ["web analytics"], "soft_skills": ["self-motivated", "resourceful", "responsible", "solve problems", "interpersonal skills", "web analytics", "creative"], "languages_combined": [{"language": "putonghua", "language_level": ["advantage", "good command"]}, {"language": "english", "language_level": ["good command"]}, {"language": "chinese", "language_level": ["good command"]}]}, "experience_required": {"duration": ["3 years"], "field": ["ecommerce", "digital", "marketing", "relevant experience"]}}, {"job_id": "100003009054021", "location_code": "hk", "company": "Genting Hong Kong Limited", "job_title": "Executive \u2013 Marketing Strategic Planning & Analysis (Marketing)", "description": "Requirements:\n\nExpertise in Facebook promotion,web analytics, google AdWords, SEO\nWorking Experience in Facial, Slimming, Beauty industry is a must\nMinimum 3 years experience in beauty industry\nDegree holder in marketing or related disciplines\nExcellent planning and project management skills\nStrong in digital marketing , social media, SEM\nCreative, dynamic, driven, open-minded and Patience\nExcellent command in English, Cantonese and Mandarin\nChinese typing is a must\n\nInterested parties please send full resume by clicking \"Apply Now\"\u00a0with expected salary or contact H.R. Department by tel:\u00a0 52910110.\n\nAll Personal data collected will be used for recruitment purpose only.", "employment_types": ["Full Time", "Permanent"], "selling_points": ["Focus on marketing planning & analysis", "Loyalty marketing & CRM exp is an advantage", "MNC working environment , stable 5 days work"], "locations": ["Kwun Tong"], "categories": ["Marketing / Public Relations", "Marketing - Brand / Product Management", "Marketing - Direct Marketing", "Marketing - Market Research"], "post_time": "2022-01-17T08:06:47Z", "salary": {"currency": null, "max": null, "min": null, "period": "monthly", "term": null}, "salary_visible": false, "title_keywords": ["executive"], "responsibilities": ["social media", "seo", "project management", "digital marketing", "sem", "facebook", "planning"], "requirements": {"degrees": ["degree holder"], "majors": ["related disciplines", "marketing"], "languages": ["cantonese", "english", "chinese", "mandarin"], "language_level": ["excellent"], "hard_skills": ["seo", "adwords", "typing", "project management", "dynamic", "sem", "web analytics", "facebook"], "soft_skills": ["project management skills", "open-minded", "dynamic", "patience", "web analytics", "creative", "driven"], "languages_combined": [{"language": "cantonese", "language_level": ["excellent"]}, {"language": "english", "language_level": ["excellent"]}, {"language": "chinese", "language_level": []}, {"language": "mandarin", "language_level": ["excellent"]}]}, "experience_required": {"duration": ["minimum 3 years"], "field": ["beauty industry"]}}, {"job_id": "100003009052750", "location_code": "hk", "company": "Telford International Co Ltd", "job_title": "Marketing Executive / Senior Marketing Executive - Beverage Division", "description": "Responsibilities:\n\nDirect report to Marketing Manager\nAssist to achieve brand targets and present the channel strategies to the Sales Team\nReview depletion for replenishment when needed\nAssist the team in A&P budget and review on regular basis\nAssist to prepare and execute promotion plans for specific channels\nExecute marketing programs including wine tastings, wine dinners, fairs, and exhibitions.\nCoordinate event management including logistic, and production of marketing collaterals\nExecute and follow up the agreed A&P activities including print, magazine, online, electronic media and direct mail\nExplore distribution development programs related to trade and corporate customers\n\n\u00a0Requirements:\n\nUniversity graduate, preferably in marketing or communications field\nA minimum of 3 years\u2019 experience in brand marketing or marketing communications of related industry\nAble to work in a fast-paced, multi-cultural environment\nDetail-minded, presentable with good judgment\nAble to work in a team but also independently\nStrong interest and passion in wine is a must. Certificate holder of WSET or related is an advantage\nPro-active, self-motivated, and positive with creative thinking\nGood command of spoken and written English, Cantonese, and Mandarin\nImmediately available preferred\nNext by Wong Chuk Hang MTR station", "employment_types": ["Full Time", "Permanent"], "selling_points": ["Degree in Marketing / Hospitality is preferred", "2-4 years exp. in FMCG or beverage industry", "Sensitive to numbers and strong analytical skills"], "locations": ["Kwai Hing"], "categories": ["Marketing / Public Relations", "Marketing - Brand / Product Management", "Marketing - Direct Marketing", "Marketing - Marketing Communication"], "post_time": "2022-01-17T03:55:34Z", "salary": {"currency": null, "max": null, "min": null, "period": "monthly", "term": null}, "salary_visible": false, "title_keywords": ["senior marketing executive", "marketing executive"], "responsibilities": ["management", "development programs", "review", "budget", "replenishment", "marketing collaterals", "coordinate", "sales team", "plans", "report"], "requirements": {"degrees": ["certificate", "university graduate"], "majors": ["marketing", "communications"], "languages": ["cantonese", "english", "mandarin"], "language_level": ["good command"], "hard_skills": [], "soft_skills": ["detail-minded", "self-motivated", "independently", "passion in", "presentable", "pro-active", "creative", "positive"], "languages_combined": [{"language": "cantonese", "language_level": ["good command"]}, {"language": "english", "language_level": ["good command"]}, {"language": "mandarin", "language_level": ["good command"]}]}, "experience_required": {"duration": ["minimum of 3 years"], "field": ["marketing communications", "marketing", "brand", "related"]}}, {"job_id": "100003009054244", "location_code": "hk", "company": "Jia Group Holdings Limited", "job_title": "Marketing Executive", "description": "Responsibilities\n\n\nFormulate marketing strategies and promotion campaigns\nImplement new product launching campaigns and deliver promotion activities in effective way\n\nDevelop online and offline marketing platforms\n\nImplement digital marketing strategies and adopt innovative tools and techniques\nDevelop and manage professional working relationship with media and business partners\nOther ad-hoc projects as assigned\n\nRequirements\n\n\nDegree holder in Marketing, Communications, or other related disciplines\nAt least 5 years working experience, preferably in retail industry\nA team leader and team player with good business acumen\nDetail-minded with good organization skill\nPleasant, proactive and outgoing personalities\nProficient in written and spoken English and Chinese\n\nWe offer attractive remuneration package to the right candidate.\u00a0 Interested parties, please apply by clicking \"Apply Now\".\n\nPersonal data will be used for recruitment purpose only", "employment_types": ["Full Time", "Permanent"], "selling_points": ["Support daily marketing activities", "Assist in implementation of marketing initiatives", "Min. 1 yr exp. preferably gained in F&B industry"], "locations": ["Central"], "categories": ["Marketing / Public Relations", "Marketing - Brand / Product Management", "Marketing - Direct Marketing", "Marketing - General / Support"], "post_time": "2022-01-17T09:57:39Z", "salary": {"currency": null, "max": null, "min": null, "period": "monthly", "term": null}, "salary_visible": false, "title_keywords": ["marketing executive"], "responsibilities": ["marketing strategies", "digital marketing strategies", "develop", "promotion campaigns", "ad-hoc projects"], "requirements": {"degrees": ["degree holder"], "majors": ["related disciplines", "marketing", "communications"], "languages": ["english", "chinese"], "language_level": ["proficient"], "hard_skills": ["acumen"], "soft_skills": ["detail-minded", "outgoing", "organization skill", "pleasant", "business acumen", "team player", "proactive"], "languages_combined": [{"language": "english", "language_level": ["proficient"]}, {"language": "chinese", "language_level": ["proficient"]}]}, "experience_required": {"duration": ["at least 5 years"], "field": ["retail industry"]}}, {"job_id": "100003009052753", "location_code": "hk", "company": "Memoriki Limited", "job_title": "Marketing Executive (Digital)", "description": "Working location:\u00a0Elite Centre in Kwun Tong\n\nResponsibilities\n\nDevelop and refine VIP programs and promotions to drive sales and penetration\nPlan and implement various VIP programs and collaborate with relevant parties to ensure the smooth execution of the programs\nSupport the strategic planning for member programs, promotions and events, including development of new product strategies, marketing programs and evaluation of customer segmentation to the right products & channels\nAssist with the pre and post event analysis of members programs, promotions and events to identify its effectiveness and recommended improvements for development\nAssist with data analysis and generating reports to support business planning\nPerform other ad hoc projects and assignments as required\n\nRequirements\n\nBachelor degree in Marketing, Business Administration or related disciplines\nMinimum 2 years of relevant working experiences\nProficient in PC skills (MS Word, Excel and PowerPoint)\nSelf-motivated, good communication, interpersonal skills and well-organized\nSolid experience in regional work is a plus\nFluent in spoken and written English, Cantonese and Mandarin\nGood at multi-tasking and strives for excellence\nCandidate with less experience will be considered as Senior Officer\n\nGenting Hong Kong is an Equal Opportunity Employer. All applications received will be treated in strict confidence and be used exclusively for recruitment purpose only. If you are not contacted within four weeks, your application will be retained for a period of 1 year and may be presented for other appropriate positions within this period.", "employment_types": ["Full Time", "Permanent"], "selling_points": ["Happy, fun and harmonious working environment", "5 days work / Flexible working hours", "Monitor and optimize digital advertising campaigns"], "locations": ["Ngau Tau Kok"], "categories": ["Marketing / Public Relations", "Marketing - Brand / Product Management", "Marketing - General / Support", "Digital Marketing"], "post_time": "2022-01-17T03:56:02Z", "salary": {"currency": null, "max": null, "min": null, "period": "monthly", "term": null}, "salary_visible": false, "title_keywords": ["marketing executive"], "responsibilities": ["collaborate with", "strategic planning", "analysis", "develop", "data analysis", "reports", "ad hoc projects", "plan", "evaluation", "drive sales", "planning"], "requirements": {"degrees": ["degree", "bachelor"], "majors": ["related disciplines", "marketing", "business administration"], "languages": ["cantonese", "english", "mandarin"], "language_level": ["fluent"], "hard_skills": ["excel", "plus", "powerpoint", "pc skills", "ms word"], "soft_skills": ["self-motivated", "confidence", "well-organized", "communication", "multi-tasking", "interpersonal skills"], "languages_combined": [{"language": "cantonese", "language_level": ["fluent"]}, {"language": "english", "language_level": ["fluent"]}, {"language": "mandarin", "language_level": ["fluent"]}]}, "experience_required": {"duration": ["minimum 2 years"], "field": []}}, {"job_id": "100003009052166", "location_code": "hk", "company": "ScentAir Technologies (Hong Kong) Limited", "job_title": "Product Marketing Manager", "description": "To support the expansion of our Group, we are currently seeking an experienced\u00a0Marketing Executive individual with strong payroll skills\u00a0to learn to join our Family.\n\n\nSupport daily marketing activities and perform administrative duties\nProvide support on events and promotion campaigns arrangements\nPrepare marketing materials, market researches and ad hoc projects\nAssist in implementation of marketing initiatives, including events, media and promotions\nCoordinate with internal and external parties to ensure smooth execution of the tasks required\nDevise well-rounded strategy plans. This includes but not limited to events, reservations, third party platforms and more\nAssist with ad-hoc assignments as required\n\nIdeal requirements:\n\nDegree in Business, Marketing & Communications, Hospitality Management, or other related disciplines\nMinimum 1 year working experience, preferably gained in F&B industry\nAble to meet tight deadlines and work under pressure in a fast-paced environment\nAbility to work and understand systems such as Mailchimp, Seven rooms and Jot form will be advantageous\nExcellent command of written and spoken English and Chinese\nStrong interpersonal and communication skills\nProficient understanding of design software such as Illustrator and in Design. Other software will be advantageous\nFresh graduates are welcome to apply\nIf you are interested to apply for the above positions, please click apply share your resume with your CURRENT and EXPECTED salary with us.\n\nPeople who are eligible to work in Hong Kong or have a valid Hong Kong work permit/visa will be considered for the above position. If you are passionate about hospitality and are looking for exciting new opportunities, then we want to hear from you!\n\nWe are an equal opportunity employer. Information provided will be treated in strict confidence and will only be used for recruitment-related purposes.", "employment_types": ["Full Time"], "selling_points": ["Product Marketing", "HVAC , Air purification/ fragrance machines", "product localization of  APAC market"], "locations": ["Lai Chi Kok"], "categories": ["Marketing / Public Relations", "Marketing - Brand / Product Management"], "post_time": "2022-01-17T02:19:04Z", "salary": {"currency": null, "max": null, "min": null, "period": "monthly", "term": null}, "salary_visible": false, "title_keywords": ["product marketing manager"], "responsibilities": ["software", "internal and external parties", "design", "communication", "promotion campaigns", "plans", "work under pressure", "implementation", "provide support", "management", "coordinate with", "administrative duties", "payroll", "third party", "prepare marketing materials", "ad-hoc assignments", "systems", "ad hoc projects", "recruitment"], "requirements": {"degrees": ["degree"], "majors": ["hospitality management", "related disciplines", "business", "marketing", "communications"], "languages": ["english", "chinese"], "language_level": ["excellent"], "hard_skills": ["illustrator"], "soft_skills": ["communication skills", "meet tight deadlines", "confidence", "ideal", "fast-paced environment", "smooth", "interpersonal", "passionate about", "work under pressure"], "languages_combined": [{"language": "english", "language_level": ["excellent"]}, {"language": "chinese", "language_level": ["excellent"]}]}, "experience_required": {"duration": ["minimum 1 year"], "field": ["f&b"]}}, {"job_id": "100003009051549", "location_code": "hk", "company": "Imbee Limited", "job_title": "Product Marketing Manager (B2B Saas)", "description": "Hyper-growth tech startup. VC-backed. Competitive package. Remote work. Friendly team. : )\nPlease apply via:\u00a0https://jobs.lever.co/imbeelimited/407e77b8-1f7f-4621-a71f-e3e6710bd820\n\nAbout imBee\nimBee.io\u00a0is the #1 Customer Chat Management Platform - it provides one inbox for all communication channels with best-in-class business tools and workflow automation for brands to scale their business and communicate better externally with customers and internally with teams.\nAs one of the venture-backed, fastest-growing startups in Asia, we serve clients across industries and sizes. Some of our happy clients are insurance giants, telecom enterprises, and SMEs in the e-commerce, retail, education, and medical industry.\nOur Mission\nThe world is becoming more conversational - we\u2019re on a mission to empower businesses to scale on all communications channels effectively.\nWe\u2019re reinventing the way businesses communicate with their customers and teams, from the ground up, so businesses can sell more, accomplish more collaboratively, save more, and build better relationships with customers.\nOur Culture\nWe\u2019re ambitious, collaborative, and fun. We work smart and play hard, and pursue excellence in everything we do. It\u2019s a learning culture that we embrace.\u00a0\nAnd we care about each and everyone in our team - we want to help you achieve your personal goals and be part of this exciting and unforgettable journey.\nYou can enjoy a flexible work environment (remote work), free snacks and beers, game room, and more!\nRole\nYour duties will include promoting products and their features to an organization's target audience. Their duties include studying the company's products, locating key features that will attract customers, and creating integrated metrics-based marketing campaigns for products. In addition to being an outstanding communicator, you will also demonstrate excellent interpersonal and analytical skills.\nResponsibilities\nDevelop positioning and messaging (define and amplify our who, what, why, how)\nDevelop product marketing strategies and create marketing materials that communicate product values\nDevelop the marketing tools and campaigns to attract new prospects and customers\nCultivate user community\nCreate Integrated communication and campaigns (Email marketing, etc.)\nCollaborate with design, product, growth, and sales teams to build outbound strategies and implement them\nCase advocacy program (case studies, testimonials, campaigns, reviews)\nRequirements\nStrong experience in B2B marketing with at least 3 years of accountable, hands-on experience (previously in B2B SaaS - advantage)\nProven outstanding abilities to translate customer needs and market demand into sharp and compelling messaging, content, sales tools, and campaigns to help us meet our business goals\nProven track record of successfully launching and managing cost-effective marketing campaigns with clear ROI focused metrics\nStrong communication and collaboration skills, both verbal and written\nHighly motivated, passionate, self-starter with a can-do attitude", "employment_types": ["Full Time"], "selling_points": [], "locations": ["Kowloon City Area"], "categories": ["Marketing / Public Relations", "Marketing - Brand / Product Management", "Digital Marketing"], "post_time": "2022-01-16T10:10:40Z", "salary": {"currency": "HKD", "max": 44999, "min": 35000, "period": "monthly", "term": null}, "salary_visible": true, "title_keywords": ["product marketing manager"], "responsibilities": ["collaborate with", "marketing strategies", "teams", "design", "develop", "marketing materials", "integrated communication"], "requirements": {"degrees": [], "majors": [], "languages": [], "language_level": [], "hard_skills": [], "soft_skills": ["passionate", "focused", "can-do attitude", "accountable", "clear", "communication", "hands-on", "motivated"], "languages_combined": []}, "experience_required": {"duration": ["at least 3 years"], "field": ["marketing"]}}, {"job_id": "100003009053822", "location_code": "hk", "company": "Squina International Group Limited", "job_title": "Digital Marketing Officer ( e-commerce )", "description": "The Job\u00a0\n\nDevelop and drive the Own Brand concept and strategy, direction and standards and translate into product packaging and communications, also driving for standardisation across the regions\nDevelop long term Own Brand activation calendar to reheat the brands and drive penetration growth\nCoordinate the senior stakeholder alignment on Own Brand and Banner strategies / projects\nLeveraging on the own brand products to drive brand equity and good value propositions\nWork with Commercial team to identify key launches of new products / revamp existing products driving the Own Brand participations in the business\nDevelop impactful promotion concepts and communication plan and work closely with Trade Marketing / Brand Marketing / CRM & Digital teams on a cohesive overall marketing plan\nMonitor and analyze market intelligence to produce marketing propositions and identify strategies for boosting customers' shifting to Own Brands\n\nThe Person\n\nBachelor\u2019s degree in Marketing/ Business Administration or related disciplines\nMinimum 10 years of marketing experience especially in FMCG or retail industries are highly preferred\nStrong in strategic thinking, stakeholder management, result driven with strong leadership skills\nAn open-minded self-starter with abilities to handle multiple projects under tight schedule\nCreative, adaptable, high learning agility, self- motivated with excellent communication and interpersonal skill\nFluency in written and spoken Chinese and English\n\nDFI Retail Group is an equal opportunity employer and responsible for ensuring that all personal information collected from each Candidate presented to DFI Retail Group is used for recruitment purposes only and the personal data will be kept and handled confidentially. We will retain the applications of candidates not selected for a period of no more than 24 months. The data collection process is in accordance with all applicable laws and compliant with the Code of Practice on Human Resource Management.\n\nTo find out more about Our Businesses and Our People, please visit our website: https://www.DFIretailgroup.com\n\n\u00a0\nIssued by The Dairy Farm Company, Limited", "employment_types": ["Full Time", "Permanent"], "selling_points": [], "locations": ["Causeway Bay"], "categories": ["Marketing / Public Relations", "Marketing - Brand / Product Management", "Marketing - Direct Marketing", "Marketing - Market Research"], "post_time": "2022-01-17T07:35:06Z", "salary": {"currency": null, "max": null, "min": null, "period": "monthly", "term": null}, "salary_visible": false, "title_keywords": ["digital marketing officer"], "responsibilities": ["trade marketing", "revamp", "teams", "monitor", "develop", "coordinate", "communication", "marketing plan", "plan", "product packaging"], "requirements": {"degrees": ["degree", "bachelor"], "majors": ["related disciplines", "marketing", "business administration"], "languages": ["english", "chinese"], "language_level": ["fluency"], "hard_skills": ["code", "no"], "soft_skills": ["strategic thinking", "responsible", "adaptable", "open-minded", "leadership skills", "interpersonal skill", "communication", "learning", "motivated", "creative", "driven"], "languages_combined": [{"language": "english", "language_level": ["fluency"]}, {"language": "chinese", "language_level": ["fluency"]}]}, "experience_required": {"duration": ["minimum 10 years"], "field": ["marketing", "retail", "fmcg"]}}, {"job_id": "100003009052556", "location_code": "hk", "company": "AOSource Company Limited", "job_title": "Digital Marketing Manager / Assistant Manager (APAC)   (DM-0117-sh-JDBP)", "description": "Your role\n\nWe are looking for a Senior Marketing Executive to join our Consumer Broadband Marketing team, responsible for digital marketing campaigns.\u00a0 It is a dynamic opportunity for an all rounded marketer to work for a brand which is striving for differentiation and continual growth.\u00a0 Major job duties include:\n\u00a0\n\nAssist in developing and implementing integrated marketing strategy to drive brand awareness and order conversions;\nSupport in the development, enhancement and maintenance of digital communication platforms, including website, social media platforms and mobile app;\nWork with related departments to implement marketing programs and activities;\nPrepare performance analysis report on campaign effectiveness and provide insights for campaign optimization;\nHandle day-to-day operations and other ad-hoc projects as assigned.\n\u00a0\n\nTo succeed in this role\n\nDegree holder preferably in Communication, Marketing or Business related discipline;\nMinimum 3 years relevant experience is required. Experience in advertising or digital media agency is an advantage;\nEssential knowledge of Google Analytics, Google Tag Manager platforms is an advantage;\nGood business sense with strong analytical abilities and presentation skills;\nStrong interpersonal skills, attentive to details and highly motivated;\nAble to work independently;\nExcellent command of written and spoken English and Cantonese;\nLess experience will be considered as Marketing Executive.", "employment_types": ["Full Time", "Permanent"], "selling_points": ["MNC Group", "Digital Marketing /Asia Region/ Social Media", "Exp.in Google Analytics, Google Ads, CRM etc"], "locations": ["Not Specified"], "categories": ["Marketing / Public Relations", "Management", "Marketing - Brand / Product Management", "Digital Marketing"], "post_time": "2022-01-17T03:24:42Z", "salary": {"currency": null, "max": null, "min": null, "period": "monthly", "term": null}, "salary_visible": false, "title_keywords": ["digital marketing manager", "assistant manager"], "responsibilities": ["provide insights", "mobile app", "advertising", "maintenance", "analysis report", "digital marketing campaigns", "social media platforms", "day-to-day operations", "website", "developing", "communication", "ad-hoc projects"], "requirements": {"degrees": ["degree holder"], "majors": ["business", "marketing"], "languages": ["cantonese", "english"], "language_level": ["excellent"], "hard_skills": ["google analytics", "maintenance", "analysis", "mobile", "dynamic"], "soft_skills": ["work independently", "responsible", "business sense", "attentive to details", "communication", "presentation skills", "dynamic", "interpersonal skills", "motivated"], "languages_combined": [{"language": "cantonese", "language_level": ["excellent"]}, {"language": "english", "language_level": ["excellent"]}]}, "experience_required": {"duration": ["minimum 3 years"], "field": ["advertising", "agency", "digital media", "relevant experience", "marketing"]}}, {"job_id": "100003009052663", "location_code": "hk", "company": "Hong Kong Loving Family Limited", "job_title": "Marketing Assistant / Executive", "description": "Are you tired of working overtime?\n\nAre you seeking for\u00a0new opportunities and excitement in workplace?\n\nIf you pursue work-life balance, apply our job now !!!\n\n\n\nOur work covers:\u00a0\n\n- Indoor and Outdoor Events\n\n- Sales Management\n\n- Strategic Planning\n\n- Team Management\u00a0\n\nWhat's special in our workplace:\n\n- Treat our office as your playground\n\n- A group of young and energetic colleagues\n\n- Different workshops, company activities and gamified working atmosphere\n\n- On-the-job training, from sales to management\n\nYou must be:\n\n- Fluent in Cantonese\u00a0\n\n- A good team player\n\n- Outgoing, talkative and creative\n\n-\u00a0Fresh graduates are welcome\n\n\nBring your energy and passion to our workplace NOW !!!", "employment_types": ["Full Time"], "selling_points": [], "locations": ["Shatin Area"], "categories": ["Marketing / Public Relations", "Marketing - Brand / Product Management", "Marketing - Market Research", "Digital Marketing"], "post_time": "2022-01-17T03:39:58Z", "salary": {"currency": null, "max": null, "min": null, "period": "monthly", "term": null}, "salary_visible": false, "title_keywords": ["marketing assistant", "executive"], "responsibilities": ["sales management", "strategic planning", "management"], "requirements": {"degrees": [], "majors": [], "languages": ["cantonese"], "language_level": ["fluent"], "hard_skills": ["workshops"], "soft_skills": ["outgoing", "good team player", "energetic", "creative"], "languages_combined": [{"language": "cantonese", "language_level": ["fluent"]}]}, "experience_required": {"duration": [], "field": []}}, {"job_id": "100003009054089", "location_code": "hk", "company": "Sodexo (Hong Kong) Limited", "job_title": "Marketing Executive / Cooridnator (Ref: PRFP/21)", "description": "Job Duties:\n\nResponsible for food promotions and food program deployments to F&B outlets\nCollect market intelligence in terms of food trend and product performance for strategic planning\nPlan and lead promotions/ food programs to achieve business targets, and evaluate the effectiveness of the activities\nActively involved in coordination of the schedules, logistics and details with both internal and external parties to ensure smooth execution\nAssist company projects as assigned, including deliverables, timeline, cost, prioritization on resources to drive operational efficiency\n\n\u00a0Job Requirements:\u00a0\n\nWith degree / vocational higher diploma in marketing or related discipline\nWith minimum 1-2 years experience of Food and Beverage marketing in hotel or hospitality industries\nFluent in spoken English and Putonghua\nGood computer knowledge in MS Word, Excel and Chinese Word Processing\nProven ability to work in a fast-paced environment\nWell organized, detailed minded and willing to learn\nExcellent communication and interpersonal skills are essential\n\nWe offer competitive remuneration package to the right candidates. Please apply with detailed resume and salary expectations to the Human Resources Department, Sodexo (Hong Kong) Limited by e-mail to hr.hk@ sodexo.com.\u00a0 Please quote PR number on all correspondence.\n\n*Personal data collected is for recruitment purposes only. \u00a0", "employment_types": ["Full Time", "Permanent"], "selling_points": ["Food Promotions & Programs / Marketing Executive", "F&B Outlets, Hotels, Hospitality marketing/PR", "1-2 years experience in F&B marketing"], "locations": ["Yau Tsim Mong Area"], "categories": ["Hospitality / F & B", "Food & Beverage", "Marketing / Public Relations", "Marketing - Brand / Product Management", "Marketing - General / Support"], "post_time": "2022-01-17T08:21:42Z", "salary": {"currency": null, "max": null, "min": null, "period": "monthly", "term": null}, "salary_visible": false, "title_keywords": ["marketing executive"], "responsibilities": ["cost", "strategic planning", "schedules", "internal and external parties", "evaluate", "logistics", "coordination", "plan"], "requirements": {"degrees": ["diploma", "degree"], "majors": ["marketing"], "languages": ["putonghua", "english", "chinese"], "language_level": ["good", "fluent"], "hard_skills": ["excel", "chinese word processing", "ms word"], "soft_skills": ["fast-paced environment", "willing to learn", "well organized", "communication and interpersonal skills", "detailed"], "languages_combined": [{"language": "putonghua", "language_level": ["fluent"]}, {"language": "english", "language_level": ["fluent"]}, {"language": "chinese", "language_level": ["good"]}]}, "experience_required": {"duration": ["minimum 1-2 years"], "field": ["food", "marketing", "hospitality industries"]}}, {"job_id": "100003009052428", "location_code": "hk", "company": "Jeeves (HK) Limited", "job_title": "Marketing Executive", "description": "Job Description\n\nResponsibilities:\n\nFormulate annual marketing plan and strategies for specific brands / sales channels with the assigned budget\nIdentify opportunities, develop and execute advertising, marketing & trade marketing activities in line with brand strategy & objective in on-& off-trade\nMonitor brand performance and manage new product launch and renovation based on market trend and consumer insights\nLiaise with internal and external parties to ensure excellent execution of campaigns, advertisement, joint promotion opportunities and POP development\nReview shipment and depletion forecasts to ensure healthy inventory control\nConduct business review presentations to management regularly.\nConduct product training for internal team and trade partners when needed\n\nRequirements:\n\nDegree holder with 5+ years work experience in branding and trade marketing, preferably in FMCG or F&B industries\nExcellent interpersonal, negotiation and project management skills\nGood numerical sense and strong analytical skills\nSelf-motivated, proactive, strong team player and innovative with strong dedication to result.\nFluency in written and spoken English and Chinese\nComputer Literate; proficient in Microsoft Outlook, Word, Excel and PowerPoint\n\nWe offer attractive remuneration package and career prospects plus 5-day week and medical insurance. Interest parties, please forward your full resume with expected salary to\u00a0apply now.\n\nAll data collected shall be solely for recruitment purpose.\n\nWebsite\u00a0\u00a0 :\u00a0\u00a0\u00a0\u00a0\u00a0\u00a0\u00a0http://www.telford.com.hk/", "employment_types": ["Full Time"], "selling_points": [], "locations": ["Aberdeen"], "categories": ["Marketing / Public Relations", "Marketing - Brand / Product Management", "Public Relations - General / Support", "Digital Marketing"], "post_time": "2022-01-17T03:00:16Z", "salary": {"currency": null, "max": null, "min": null, "period": "monthly", "term": null}, "salary_visible": false, "title_keywords": ["marketing executive"], "responsibilities": ["trade marketing", "management", "advertising", "consumer insights", "budget", "monitor", "renovation", "internal and external parties", "develop", "review", "marketing plan", "presentations", "inventory control", "liaise with"], "requirements": {"degrees": ["degree holder"], "majors": ["marketing"], "languages": ["english", "chinese"], "language_level": ["fluency"], "hard_skills": ["excel", "word", "powerpoint", "analytical skills", "project management", "outlook"], "soft_skills": ["self-motivated", "negotiation", "project management skills", "analytical skills", "innovative", "team player", "proactive", "interpersonal"], "languages_combined": [{"language": "english", "language_level": ["fluency"]}, {"language": "chinese", "language_level": ["fluency"]}]}, "experience_required": {"duration": ["5+ years"], "field": ["f&b", "marketing", "fmcg"]}}, {"job_id": "100003009054819", "location_code": "hk", "company": "E-buy Global Limited", "job_title": "Assistant Marketing Officer (Community Management)", "description": "Responsibilities:\n\n\n\nManage and create content for online platforms (e.g. Website, Social Media, display advertising and digital campaigns) to achieve marketing objectives and to enable smooth collaborations\nAssist in developing overall corporate branding and marketing strategy\nExplore creative promotion and events to generate brand awareness\nDevelop digital marketing strategies and campaigns to achieve traffic and business goals\nAnalyze data, trends and insights to fully optimize all digital platforms.\nCoordinate with internal teams to plan, organize, and execute various marketing events or campaigns\nAssist in ad hoc marketing and event management tasks\n\nRequirements:\n\n\n\nDegree holder in Marketing, Business or related disciplines\nAround 1-2 years of relevant experience, knowledge in GA, SEO is definitely an advantage\nStrong communication and presentation skills\nExcellent in handling and follow up on details, take initiative, independent & responsible\nFluent in both written and spoken English, Cantonese and Mandarin\nExcellent English (in both written & spoken) + communication & copywriting skills\nProficiency in marketing automation technology\nAble to execute email marketing strategies\nFamiliarity with analytical and database tools\n\nWorking location:\u00a0Kwai Chung\n\nStaff Benefit:\n\nDiscretionary Bonus\nMedical & Life Insurance\nAnnual Leave\nPayable Sick Leave\nEncourage continuing education and on-job training\nOpen office working environment\nOffer promotion opportunities and long-term career path\u00a0\n\nWe offer a competitive remuneration package to the right candidate.\u00a0Interested parties\u00a0please click\u00a0\"Apply Now\"\u00a0to submit your application\u00a0or by email to\u00a0hr1 @twcoffee.com\n\n\u00a0(All personal data provided by applicants will be treated in strict confidence and used for employment-related purpose only.)\n\nAdditional Information", "employment_types": ["Full Time"], "selling_points": ["Five-day work week", "Experience in community marketing", "Attention to detail, critical-thinker"], "locations": ["Kwai Hing"], "categories": ["Marketing / Public Relations", "Marketing - Brand / Product Management", "Marketing - Marketing Communication", "E-commerce", "Business Development"], "post_time": "2022-01-17T11:22:05Z", "salary": {"currency": null, "max": null, "min": null, "period": "monthly", "term": null}, "salary_visible": false, "title_keywords": ["assistant marketing officer"], "responsibilities": ["social media", "business goals", "marketing events", "advertising", "digital marketing strategies", "ad hoc", "management", "coordinate with", "website", "developing", "develop", "teams", "digital campaigns", "plan", "analyze data"], "requirements": {"degrees": ["degree holder"], "majors": ["business", "related disciplines", "marketing"], "languages": ["cantonese", "english", "mandarin"], "language_level": ["excellent", "fluent"], "hard_skills": ["seo"], "soft_skills": ["independent", "responsible", "communication", "presentation skills", "initiative"], "languages_combined": [{"language": "cantonese", "language_level": ["fluent"]}, {"language": "english", "language_level": ["excellent", "fluent"]}, {"language": "mandarin", "language_level": ["excellent", "fluent"]}]}, "experience_required": {"duration": ["1-2 years"], "field": ["relevant experience"]}}, {"job_id": "100003009055132", "location_code": "hk", "company": "H.S.Chan Company Limited", "job_title": "Senior Marketing Executive", "description": "Responsibilities\n\nProvide B2B & B2C product marketing materials, product training & knowledge\nManage above the line and below the line communication plan to achieve company strategic objectives\nProvide support marketing functions which includes traditional marketing strategy, digital marketing strategy, new product introduction, and promotional events\nRegular market research studies in Hong Kong and China to evaluate product opportunities\nSupervise and coordinate the preparation, issuance of sales materials, exhibits and promotional events with internal designer, and if necessary third-party contractors\nLiaise with the sales team to identify marketing support needs\nResponsible for development, monitoring and management of PSF marketing budget\nLead and participate in the sourcing of new products from suppliers globally\nCreate annual marketing reviews for suppliers\nPromote positive relations with partners, vendors, and distributors\nTranslation of business documents including Microsoft Office Applications\u00a0(primarily Microsoft Word and PowerPoint)\nMake recommendations to management on the category based on own expertise of the consumer, market and competitors\nEffectively prepare clear messages for senior management\n\nRequirements\n\nBachelor Degree holders\n5+ years\u2019 working experience, preferably in foods sector\nProficient in English, Mandarin and Chinese\nExperience in digital marketing and social media (Facebook, Instagram, Google, Wechat) is necessary\nExperience in E-Commerce will be advantage\nGood communication skills, creative with strong market sense, self-motivated and attentive to details\nAble to meet tight deadlines, multi-task and able to work independently\nWilling to work overtime to achieve\nCheck out HKTVmall online store\nFresco dal Mercato\n\nOfficial company website:\nhttps://www.psf.com.hk", "employment_types": ["Full Time", "Permanent"], "selling_points": [], "locations": ["Kwun Tong"], "categories": ["Marketing / Public Relations", "Marketing - Brand / Product Management", "Marketing - General / Support", "Marketing - Marketing Communication"], "post_time": "2022-01-18T01:19:16Z", "salary": {"currency": null, "max": null, "min": null, "period": "monthly", "term": null}, "salary_visible": false, "title_keywords": ["senior marketing executive"], "responsibilities": ["make recommendations", "provide support", "management", "monitoring", "budget", "market research", "communication", "evaluate", "coordinate", "liaise with", "digital marketing", "sales team", "plan", "marketing materials", "senior management"], "requirements": {"degrees": ["degree", "bachelor"], "majors": [], "languages": ["english", "chinese", "mandarin"], "language_level": ["proficient"], "hard_skills": ["facebook", "e-commerce", "wechat"], "soft_skills": ["communication skills", "self-motivated", "meet tight deadlines", "multi-task", "work independently", "attentive to details", "work overtime", "strong market sense", "creative"], "languages_combined": [{"language": "english", "language_level": ["proficient"]}, {"language": "chinese", "language_level": ["proficient"]}, {"language": "mandarin", "language_level": ["proficient"]}]}, "experience_required": {"duration": ["5+ years"], "field": ["social media", "digital marketing", "e-commerce"]}}, {"job_id": "100003009054080", "location_code": "hk", "company": "Smart Charge", "job_title": "Marketing Executive/ Senior Marketing Executive (Smart Charge)", "description": "Responsibilities:\n\nDevelop a strategy to build and maintain programs and activities that will have a positive impact on the community\nRespond to customers in a timely manner\nMonitor, track and report on feedback and online reviews\nOrganize and manage events to boost brand awareness\nBuild relationships with customers, industry professionals and journalists\nRespond to customers in a timely manner\nCoordinate with Customer Service and Marketing teams to ensure brand consistency\nStay up-to-date with digital technology trends\n\n\u00a0Requirements:\n\nBachelor\u2019s degree in Public Relations, Communications, English, Fundraising, Journalism, or similar\nAt least 2 years of experience in community marketing / community engagement / community management\nExperience planning and leading community initiatives\nAbility to identify and track relevant community KPIs\nAbility to interpret website traffic\nExcellent verbal communication, writing, interpersonal and presentations skills\nAttention to detail, critical-thinker and problem-solver", "employment_types": ["Full Time", "Permanent"], "selling_points": ["Degree in Marketing, Communications or Business", "3-year relevant experience", "Smart Charge - new service brand runs by HKT & CLP"], "locations": ["Quarry Bay"], "categories": ["Marketing / Public Relations", "Management", "Marketing - Brand / Product Management", "Marketing - Marketing Communication"], "post_time": "2022-01-17T08:19:54Z", "salary": {"currency": null, "max": null, "min": null, "period": null, "term": null}, "salary_visible": false, "title_keywords": ["senior marketing executive", "marketing executive"], "responsibilities": ["monitor", "a timely manner", "coordinate with", "develop", "teams", "maintain", "customer service", "brand consistency", "report"], "requirements": {"degrees": ["degree", "bachelor"], "majors": ["journalism", "communications"], "languages": ["english"], "language_level": [], "hard_skills": ["presentations"], "soft_skills": ["communication", "interpersonal", "attention to detail"], "languages_combined": [{"language": "english", "language_level": []}]}, "experience_required": {"duration": ["at least 2 years"], "field": ["management", "marketing", "planning"]}}, {"job_id": "100003009054105", "location_code": "hk", "company": "Profits Fund Fashion Manufacturing Ltd", "job_title": "PR & Marketing Manager", "description": "Responsibilities :\n\nDevelop & implement marketing programs for different retail channels\nPlan sales & promotion budget\nCoordinate / Liaise with Principals for marketing supports\nControl & Monitor the progress of marketing programs\nSupport the execution of online marketing activities in Facebook\nProvide POP support to individual sales channel when necessary\nPurchase planning and inventory control\n\nRequirements :\n\nUniversity graduate with strong interpersonal skills\nProficiency in both written and spoken English and Chinese\nSkillful in PowerPoint / Excel / Word and Chinese Word Processing\nKnowledge of Photoshop, Illustration will be a plus\nResponsive to market changes and having innovative ideas\n\nAppreciate to work with people from different teams\nDetail-oriented and with ability to handle jobs independently\nSolid working experience in Retail / FMCG marketing is preferred\n\nBenefits :\n\n5-day work per week\nDiscretionary bonus\n10 days annual leave, bank holiday and birthday leave\nMedical insurance\nMPF\nStaff purchase discount\n\n\nInterested parties, please send C.V. with expected salary to H.S. Chan Co. Ltd., 7/F, H. S.Chan Building, 4 Hung To Road, Kwun Tong, Kowloon with attention to Ms Rosan Li or by clicking \"Apply Now\"\n\nPersonal data collected will be used for recruitment related purpose only.", "employment_types": ["Full Time"], "selling_points": [], "locations": ["Kwai Fong"], "categories": ["Marketing / Public Relations", "Marketing - Brand / Product Management"], "post_time": "2022-01-17T08:23:55Z", "salary": {"currency": null, "max": null, "min": null, "period": "monthly", "term": null}, "salary_visible": false, "title_keywords": ["marketing manager"], "responsibilities": ["control", "budget", "monitor", "develop", "coordinate", "purchase", "inventory control", "plan", "liaise with", "facebook", "planning"], "requirements": {"degrees": ["university graduate"], "majors": [], "languages": ["english", "chinese"], "language_level": ["proficiency"], "hard_skills": ["excel", "plus", "chinese word processing", "word", "powerpoint", "illustration", "photoshop"], "soft_skills": ["independently", "detail-oriented", "interpersonal skills", "innovative", "responsive"], "languages_combined": [{"language": "english", "language_level": ["proficiency"]}, {"language": "chinese", "language_level": ["proficiency"]}]}, "experience_required": {"duration": [], "field": ["retail", "marketing", "fmcg"]}}, {"job_id": "100003009052533", "location_code": "hk", "company": "ADECCO", "job_title": "Assistant Marketing Coordinator $13K-15K", "description": "Do you want to be a part of something exciting...?\nBased in our Hong Kong organization, the Channel Marketing Executive (Off-Trade)\u00a0will join us on our journey of brewing for a better today and tomorrow.\n\nWhat you'll be doing:\n\n\nCollaborate with the Brand Marketing, Channel Sales and other function on the creation of in-store activation and ensure the channel marketing campaigns are executed on-time-in-full.\nKeep track of the market intelligence and generate valuable consumer / shopper insights.\nIdentify customer & shopper insights and translate insights into business-building opportunities within specific customers/channels.\nResponsible for the production of promotional material for use at points of sales from conceptualization to execution.\nSupervise with outside agencies and merchandisers on the preparation of promotional materials.\nAnalyze the ROI of the marketing activities executed with the customer.\nManage the Channel Marketing budget and ensure all spending are effective and efficient.\nWhat we're looking for:\n\nBachelor's degree in Marketing or Business related discipline.\nAt least 1 - 2 years experience in marketing, experience in FMCG is preferred.\nGood analytical, planning and time management skills.\nStrong communication, presentation and negotiation skills.\nA problem solver with the ability to influence.\u00a0\nAble to work under pressure and to follow the timeline.\nOpen-minded, willing to learn and flexible to changes.\nOrganize and detail-minded.\u00a0\nGood command of both written and spoken English and Chinese.\nWhat you can expect:\nCarlsberg offers competitive salary & benefit such as double pay, discretionary bonus, medical & dental coverage, birthday leave and monthly free beer redemption to successful candidate. We also organize various social recreation activities and employee training and development programs for our team members to join. \u00a0\n\nWelcome to visit our company website https://carlsberghongkong.com.hk\u00a0for more information about Carlsberg.\n\nPersonal data collected will be treated in strictest confidence and only for recruitment purpose. Applicants who are not contacted within 2 months may consider their applications unsuccessful. Carlsberg will retain their applications for a maximum of six months and may refer suitable applicants to other vacancies within the company.", "employment_types": ["Full Time", "Contract"], "selling_points": [], "locations": ["Shatin Area"], "categories": ["Marketing / Public Relations", "Marketing - Brand / Product Management", "Marketing - General / Support", "Others"], "post_time": "2022-01-17T03:21:16Z", "salary": {"currency": null, "max": null, "min": null, "period": "monthly", "term": null}, "salary_visible": false, "title_keywords": ["marketing coordinator", "assistant"], "responsibilities": ["collaborate with", "management", "development programs", "work under pressure", "budget", "communication", "promotional materials", "recruitment", "marketing campaigns", "personal data", "company website", "planning"], "requirements": {"degrees": ["degree", "bachelor"], "majors": ["business", "marketing"], "languages": ["english", "chinese"], "language_level": ["good command"], "hard_skills": [], "soft_skills": ["efficient", "flexible", "detail-minded", "confidence", "problem solver", "responsible", "time management skills", "open-minded", "willing to learn", "communication", "negotiation skills", "presentation", "work under pressure"], "languages_combined": [{"language": "english", "language_level": ["good command"]}, {"language": "chinese", "language_level": ["good command"]}]}, "experience_required": {"duration": ["at least 1 - 2 years"], "field": ["marketing", "fmcg"]}}, {"job_id": "100003009055168", "location_code": "hk", "company": "Zenit (Hong Kong) Company Limited", "job_title": "Branding and Marketing Executive / Senior Marketing Executive", "description": "Manage marketing activities of a number of brands we currently represent\nLocate collaboration partners to drive create content and drive brand awareness\nFrequent contact with global photography media to build global brand awareness\nPlan and coordinate both online and offline marketing activities with distributors to drive sales\nWork closely with sales team to formulate plans to drive business across distributors\nCommunication with global distributors to understand market changes\nManage social media and provide end customer service and support.\nNurture the user community and identify collaboration brands and parties.\nKeep close track of industry news and competitor movements\nAttend local and overseas events when necessary", "employment_types": ["Full Time", "Permanent"], "selling_points": ["5 days work", "Double Pay", "Performance Bonus"], "locations": ["Tsuen Wan Area"], "categories": ["Marketing / Public Relations", "Marketing - Brand / Product Management", "Marketing - Marketing Communication", "Digital Marketing"], "post_time": "2022-01-18T01:36:30Z", "salary": {"currency": null, "max": null, "min": null, "period": "monthly", "term": null}, "salary_visible": false, "title_keywords": ["senior marketing executive", "marketing executive"], "responsibilities": ["drive sales", "social media", "plan and coordinate", "communication", "customer service", "sales team", "contact", "plans"], "requirements": {"degrees": [], "majors": [], "languages": [], "language_level": [], "hard_skills": [], "soft_skills": ["communication", "customer service"], "languages_combined": []}, "experience_required": {"duration": [], "field": []}}, {"job_id": "100003009055169", "location_code": "hk", "company": "Tsit Wing Coffee Co Ltd", "job_title": "Marketing Executive", "description": "Responsibilities:\n\nProvide administrative support to the marketing team in accordance with the Company\u2019s Policy and Procedural Systems & Practices\nUpdate internal reports, records and documents in marketing department\nData tabulation and analysis\nCompetitive analysis and reporting\nMarket intelligence \u2013 desk research and field research coordination\nMarketing fund budget administration and control\nProvide general support and administrative duties to the team\nAssist in ad-hoc tasks and projects as required\n\nRequirements:\n\nDiploma holder or above with educational background in Statistics, Data Management, Accounting or Business Administration\n1-2 years relevant work experience in marketing, experience in FMCG will be an advantage, fresh graduates will also be considered\nAdvanced skills with MS Office esp. Excel and Powerpoint\nSelf-starter, quick learner,\u00a0logical thinking and organized\nImmediately availability is preferred\n\nWorking location:\u00a0Kwai Chung\n\nStaff Benefit:\n\nDiscretionary Bonus\nMedical & Life Insurance\nAnnual Leave\nPayable Sick Leave\nEncourage continuing education and on-job training\nOpen office working environment\nOffer promotion opportunities and long-term career path\u00a0\n\nWe offer a competitive remuneration package to the right candidate.\u00a0Interested parties\u00a0please click\u00a0\"Apply Now\"\u00a0to submit your application\u00a0or by email to\u00a0hr1 @twcoffee.com\n\n\u00a0(All personal data provided by applicants will be treated in strict confidence and used for employment-related purpose only.)", "employment_types": ["Full Time"], "selling_points": [], "locations": ["Kwai Fong"], "categories": ["Marketing / Public Relations", "Marketing - Brand / Product Management", "Marketing - Direct Marketing", "Marketing - General / Support"], "post_time": "2022-01-18T01:36:53Z", "salary": {"currency": null, "max": null, "min": null, "period": "monthly", "term": null}, "salary_visible": false, "title_keywords": ["marketing executive"], "responsibilities": ["reporting", "control", "data", "analysis", "systems", "budget", "ad-hoc tasks", "reports", "administrative duties", "coordination", "provide administrative support", "general support", "administration"], "requirements": {"degrees": ["diploma holder"], "majors": ["accounting", "statistics", "business administration"], "languages": [], "language_level": [], "hard_skills": ["excel", "data management", "powerpoint", "ms office"], "soft_skills": ["organized", "advanced", "quick learner"], "languages_combined": []}, "experience_required": {"duration": ["1-2 years"], "field": ["marketing", "fmcg"]}}, {"job_id": "100003009056146", "location_code": "hk", "company": "Networld Technology Limited", "job_title": "Senior Sales and Marketing Executive", "description": "Major responsibilities:\n\nCreate and manage all marketing initiatives, advertising, promotion activities and public relations plan\nManage all marketing channels including digital channels\nDriving traffic and conversion to brand websites through proper system, content and SEO, develop and operate SEM initiatives\nConceptualize and formulate regular marketing campaigns; develop marketing materials such as eDM, e-flyers and mail outs\nPlan and manage all marketing communications and collaterals, including web, online and print, maintain company brand communication guidelines and standards\nLiaise with media and potential business partners to explore new promotion channels, joint promotion opportunities and build the brand awareness.\nCompile reports and co-ordinate with different parties for project implementation\nSupport in customer relationship management and assist to handle client inquiries, requests and complaints\n\nRequirements:\n\nBachelor degree in Communication/ Business Administration / Marketing or related disciplines\nAt least\u00a05 years of working experience with substantial experience gained in marketing or PR advertising agency\nSound experience in managing consumer/ trade event independently and developing effective marketing communications\nFamiliar with Google Adwords, Google Analytics and Google Search Console\nKnowledge of Adobe Illustrator, Photoshop, and basic HTML is a plus.\nExcellent in both spoken and written English and Chinese with\u00a0bilingual copywriting,\u00a0as spoken and written other languages will be an advantage\u00a0\nBe able to work under pressure with tight timeline and multi-tasking capability\nWell-presented with excellent interpersonal and communication skills\u00a0\nProficiency in MS applications including PowerPoint & Excel\nImmediate availability is highly preferred\n\nWe offer competitive remuneration package and excellent career development to the right candidates. Interested parties please complete the standard application form by clicking the Apply now button. \u00a0You can also attach your tailored CV and Cover letter with present & expected salary, and state of availability to the Human Resources Department which we will use to review applications.\n\nETG is an equal opportunity employer and welcome applications from all qualified candidates.\u00a0 All information provided will be treated in strict confidentiality and will only be used for recruitment-related purpose.\u00a0 We will retain your application for a maximum period of 4 months.", "employment_types": ["Full Time", "Permanent"], "selling_points": ["5-day Work Week, Birthday Leave", "Flexible Working Hour, Wearing Casually", "Medical Insurance, Performance Bonus"], "locations": ["Shatin Area"], "categories": ["Media & Advertising", "Strategic Planning", "Marketing / Public Relations", "Marketing - Brand / Product Management", "Marketing - Marketing Communication"], "post_time": "2022-01-18T03:24:06Z", "salary": {"currency": null, "max": null, "min": null, "period": "monthly", "term": null}, "salary_visible": false, "title_keywords": ["sales and marketing executive"], "responsibilities": ["marketing materials", "management", "seo", "advertising", "edm", "guidelines", "compile reports", "co-ordinate with", "implementation", "develop", "communication", "liaise with", "maintain", "sem", "plan", "marketing campaigns"], "requirements": {"degrees": ["degree", "bachelor"], "majors": ["related disciplines", "marketing", "business administration"], "languages": ["english", "chinese"], "language_level": ["advantage", "excellent"], "hard_skills": ["google analytics", "plus", "excel", "basic", "ms applications", "adwords", "html", "adobe illustrator", "powerpoint", "photoshop"], "soft_skills": ["communication skills", "independently", "communication", "multi-tasking", "interpersonal", "work under pressure"], "languages_combined": [{"language": "english", "language_level": ["excellent", "advantage"]}, {"language": "chinese", "language_level": ["excellent", "advantage"]}]}, "experience_required": {"duration": ["at least 5 years"], "field": ["marketing communications", "marketing", "developing", "pr advertising agency"]}}, {"job_id": "100003009053311", "location_code": "hk", "company": "Altaya Wines Limited", "job_title": "Marketing Executive", "description": "Responsibilities\n\n\nFormulate marketing strategies and promotion campaigns\nImplement new product launching campaigns and deliver promotion activities in effective way\n\nDevelop online and offline marketing platforms\n\nImplement digital marketing strategies and adopt innovative tools and techniques\nDevelop and manage professional working relationship with media and business partners\nOther ad-hoc projects as assigned\n\nRequirements\n\n\nDegree holder in Marketing, Communications, or other related disciplines\nAt least 5 years working experience, preferably in retail industry\nA team leader and team player with good business acumen\nDetail-minded with good organization skill\nPleasant, proactive and outgoing personalities\nProficient in written and spoken English and Chinese\n\nWe offer attractive remuneration package to the right candidate.\u00a0 Interested parties, please apply by clicking \"Apply Now\".\n\nPersonal data will be used for recruitment purpose only", "employment_types": ["Full Time"], "selling_points": ["All round marketing functions", "5 day work per week with Medical & Dental Scheme", "Career Development"], "locations": ["Aberdeen"], "categories": ["Marketing / Public Relations", "Marketing - Brand / Product Management", "Marketing - Marketing Communication", "Public Relations - Event Management"], "post_time": "2022-01-17T06:44:19Z", "salary": {"currency": null, "max": null, "min": null, "period": "monthly", "term": null}, "salary_visible": false, "title_keywords": ["marketing executive"], "responsibilities": ["marketing strategies", "digital marketing strategies", "develop", "promotion campaigns", "ad-hoc projects"], "requirements": {"degrees": ["degree holder"], "majors": ["related disciplines", "marketing", "communications"], "languages": ["english", "chinese"], "language_level": ["proficient"], "hard_skills": ["acumen"], "soft_skills": ["detail-minded", "outgoing", "organization skill", "pleasant", "business acumen", "team player", "proactive"], "languages_combined": [{"language": "english", "language_level": ["proficient"]}, {"language": "chinese", "language_level": ["proficient"]}]}, "experience_required": {"duration": ["at least 5 years"], "field": ["retail industry"]}}, {"job_id": "100003009056517", "location_code": "hk", "company": "Carsac Limited", "job_title": "Marketing Manager", "description": "Working location:\u00a0Elite Centre in Kwun Tong\n\nResponsibilities\n\nDevelop and refine VIP programs and promotions to drive sales and penetration\nPlan and implement various VIP programs and collaborate with relevant parties to ensure the smooth execution of the programs\nSupport the strategic planning for member programs, promotions and events, including development of new product strategies, marketing programs and evaluation of customer segmentation to the right products & channels\nAssist with the pre and post event analysis of members programs, promotions and events to identify its effectiveness and recommended improvements for development\nAssist with data analysis and generating reports to support business planning\nPerform other ad hoc projects and assignments as required\n\nRequirements\n\nBachelor degree in Marketing, Business Administration or related disciplines\nMinimum 2 years of relevant working experiences\nProficient in PC skills (MS Word, Excel and PowerPoint)\nSelf-motivated, good communication, interpersonal skills and well-organized\nSolid experience in regional work is a plus\nFluent in spoken and written English, Cantonese and Mandarin\nGood at multi-tasking and strives for excellence\nCandidate with less experience will be considered as Senior Officer\n\nGenting Hong Kong is an Equal Opportunity Employer. All applications received will be treated in strict confidence and be used exclusively for recruitment purpose only. If you are not contacted within four weeks, your application will be retained for a period of 1 year and may be presented for other appropriate positions within this period.", "employment_types": ["Full Time", "Permanent"], "selling_points": [], "locations": ["North Point"], "categories": ["Marketing / Public Relations", "Marketing - Brand / Product Management"], "post_time": "2022-01-18T04:37:17Z", "salary": {"currency": null, "max": null, "min": null, "period": "monthly", "term": null}, "salary_visible": false, "title_keywords": ["marketing manager"], "responsibilities": ["collaborate with", "strategic planning", "analysis", "develop", "data analysis", "reports", "ad hoc projects", "plan", "evaluation", "drive sales", "planning"], "requirements": {"degrees": ["degree", "bachelor"], "majors": ["related disciplines", "marketing", "business administration"], "languages": ["cantonese", "english", "mandarin"], "language_level": ["fluent"], "hard_skills": ["excel", "plus", "powerpoint", "pc skills", "ms word"], "soft_skills": ["self-motivated", "confidence", "well-organized", "communication", "multi-tasking", "interpersonal skills"], "languages_combined": [{"language": "cantonese", "language_level": ["fluent"]}, {"language": "english", "language_level": ["fluent"]}, {"language": "mandarin", "language_level": ["fluent"]}]}, "experience_required": {"duration": ["minimum 2 years"], "field": []}}, {"job_id": "100003009056483", "location_code": "hk", "company": "DFI Retail Group DFI\u96f6\u552e\u96c6\u5718", "job_title": "Own Brand Marketing Lead, Health & Beauty", "description": "The Job\u00a0\n\nDevelop and drive the Own Brand concept and strategy, direction and standards and translate into product packaging and communications, also driving for standardisation across the regions\nDevelop long term Own Brand activation calendar to reheat the brands and drive penetration growth\nCoordinate the senior stakeholder alignment on Own Brand and Banner strategies / projects\nLeveraging on the own brand products to drive brand equity and good value propositions\nWork with Commercial team to identify key launches of new products / revamp existing products driving the Own Brand participations in the business\nDevelop impactful promotion concepts and communication plan and work closely with Trade Marketing / Brand Marketing / CRM & Digital teams on a cohesive overall marketing plan\nMonitor and analyze market intelligence to produce marketing propositions and identify strategies for boosting customers' shifting to Own Brands\n\nThe Person\n\nBachelor\u2019s degree in Marketing/ Business Administration or related disciplines\nMinimum 10 years of marketing experience especially in FMCG or retail industries are highly preferred\nStrong in strategic thinking, stakeholder management, result driven with strong leadership skills\nAn open-minded self-starter with abilities to handle multiple projects under tight schedule\nCreative, adaptable, high learning agility, self- motivated with excellent communication and interpersonal skill\nFluency in written and spoken Chinese and English\n\nDFI Retail Group is an equal opportunity employer and responsible for ensuring that all personal information collected from each Candidate presented to DFI Retail Group is used for recruitment purposes only and the personal data will be kept and handled confidentially. We will retain the applications of candidates not selected for a period of no more than 24 months. The data collection process is in accordance with all applicable laws and compliant with the Code of Practice on Human Resource Management.\n\nTo find out more about Our Businesses and Our People, please visit our website: https://www.DFIretailgroup.com\n\n\u00a0\nIssued by The Dairy Farm Company, Limited", "employment_types": ["Permanent"], "selling_points": ["Strategic mindset, planning and development", "FMCG, Retail, Marketing", "Leadership, strategic mindset, acute market sense"], "locations": ["Quarry Bay"], "categories": ["Marketing / Public Relations", "Marketing - Brand / Product Management"], "post_time": "2022-01-18T04:32:21Z", "salary": {"currency": null, "max": null, "min": null, "period": "monthly", "term": null}, "salary_visible": false, "title_keywords": ["lead"], "responsibilities": ["trade marketing", "revamp", "teams", "monitor", "develop", "coordinate", "communication", "marketing plan", "plan", "product packaging"], "requirements": {"degrees": ["degree", "bachelor"], "majors": ["related disciplines", "marketing", "business administration"], "languages": ["english", "chinese"], "language_level": ["fluency"], "hard_skills": ["code", "no"], "soft_skills": ["strategic thinking", "responsible", "adaptable", "open-minded", "leadership skills", "interpersonal skill", "communication", "learning", "motivated", "creative", "driven"], "languages_combined": [{"language": "english", "language_level": ["fluency"]}, {"language": "chinese", "language_level": ["fluency"]}]}, "experience_required": {"duration": ["minimum 10 years"], "field": ["marketing", "retail", "fmcg"]}}, {"job_id": "100003009056058", "location_code": "hk", "company": "HKT Consumer Group", "job_title": "Senior Marketing Executive", "description": "Your role\n\nWe are looking for a Senior Marketing Executive to join our Consumer Broadband Marketing team, responsible for digital marketing campaigns.\u00a0 It is a dynamic opportunity for an all rounded marketer to work for a brand which is striving for differentiation and continual growth.\u00a0 Major job duties include:\n\u00a0\n\nAssist in developing and implementing integrated marketing strategy to drive brand awareness and order conversions;\nSupport in the development, enhancement and maintenance of digital communication platforms, including website, social media platforms and mobile app;\nWork with related departments to implement marketing programs and activities;\nPrepare performance analysis report on campaign effectiveness and provide insights for campaign optimization;\nHandle day-to-day operations and other ad-hoc projects as assigned.\n\u00a0\n\nTo succeed in this role\n\nDegree holder preferably in Communication, Marketing or Business related discipline;\nMinimum 3 years relevant experience is required. Experience in advertising or digital media agency is an advantage;\nEssential knowledge of Google Analytics, Google Tag Manager platforms is an advantage;\nGood business sense with strong analytical abilities and presentation skills;\nStrong interpersonal skills, attentive to details and highly motivated;\nAble to work independently;\nExcellent command of written and spoken English and Cantonese;\nLess experience will be considered as Marketing Executive.", "employment_types": ["Full Time"], "selling_points": [], "locations": ["Ngau Tau Kok"], "categories": ["Marketing / Public Relations", "Marketing - Brand / Product Management", "Marketing - General / Support", "Marketing - Marketing Communication"], "post_time": "2022-01-18T03:13:59Z", "salary": {"currency": null, "max": null, "min": null, "period": "monthly", "term": null}, "salary_visible": false, "title_keywords": ["senior marketing executive"], "responsibilities": ["provide insights", "mobile app", "advertising", "maintenance", "analysis report", "digital marketing campaigns", "social media platforms", "day-to-day operations", "website", "developing", "communication", "ad-hoc projects"], "requirements": {"degrees": ["degree holder"], "majors": ["business", "marketing"], "languages": ["cantonese", "english"], "language_level": ["excellent"], "hard_skills": ["google analytics", "maintenance", "analysis", "mobile", "dynamic"], "soft_skills": ["work independently", "responsible", "business sense", "attentive to details", "communication", "presentation skills", "dynamic", "interpersonal skills", "motivated"], "languages_combined": [{"language": "cantonese", "language_level": ["excellent"]}, {"language": "english", "language_level": ["excellent"]}]}, "experience_required": {"duration": ["minimum 3 years"], "field": ["advertising", "agency", "digital media", "relevant experience", "marketing"]}}, {"job_id": "100003009056192", "location_code": "hk", "company": "Code International Limited", "job_title": "Offline Marketing Trainee", "description": "Are you tired of working overtime?\n\nAre you seeking for\u00a0new opportunities and excitement in workplace?\n\nIf you pursue work-life balance, apply our job now !!!\n\n\n\nOur work covers:\u00a0\n\n- Indoor and Outdoor Events\n\n- Sales Management\n\n- Strategic Planning\n\n- Team Management\u00a0\n\nWhat's special in our workplace:\n\n- Treat our office as your playground\n\n- A group of young and energetic colleagues\n\n- Different workshops, company activities and gamified working atmosphere\n\n- On-the-job training, from sales to management\n\nYou must be:\n\n- Fluent in Cantonese\u00a0\n\n- A good team player\n\n- Outgoing, talkative and creative\n\n-\u00a0Fresh graduates are welcome\n\n\nBring your energy and passion to our workplace NOW !!!", "employment_types": ["Full Time"], "selling_points": ["Offline Marketing", "Work Hard Play Hard", "Team Management and Leadership Training"], "locations": ["Wan Chai"], "categories": ["Marketing / Public Relations", "Marketing - Brand / Product Management", "Public Relations - Event Management", "Sales, CS & Business Devpt", "Direct Sales"], "post_time": "2022-01-18T03:31:08Z", "salary": {"currency": null, "max": null, "min": null, "period": "monthly", "term": null}, "salary_visible": false, "title_keywords": ["trainee"], "responsibilities": ["sales management", "strategic planning", "management"], "requirements": {"degrees": [], "majors": [], "languages": ["cantonese"], "language_level": ["fluent"], "hard_skills": ["workshops"], "soft_skills": ["outgoing", "good team player", "energetic", "creative"], "languages_combined": [{"language": "cantonese", "language_level": ["fluent"]}]}, "experience_required": {"duration": [], "field": []}}, {"job_id": "100003009055218", "location_code": "hk", "company": "Ping Shan Foods Company Limited", "job_title": "Product Marketing Executive", "description": "Responsibilities\n\nProvide B2B & B2C product marketing materials, product training & knowledge\nManage above the line and below the line communication plan to achieve company strategic objectives\nProvide support marketing functions which includes traditional marketing strategy, digital marketing strategy, new product introduction, and promotional events\nRegular market research studies in Hong Kong and China to evaluate product opportunities\nSupervise and coordinate the preparation, issuance of sales materials, exhibits and promotional events with internal designer, and if necessary third-party contractors\nLiaise with the sales team to identify marketing support needs\nResponsible for development, monitoring and management of PSF marketing budget\nLead and participate in the sourcing of new products from suppliers globally\nCreate annual marketing reviews for suppliers\nPromote positive relations with partners, vendors, and distributors\nTranslation of business documents including Microsoft Office Applications\u00a0(primarily Microsoft Word and PowerPoint)\nMake recommendations to management on the category based on own expertise of the consumer, market and competitors\nEffectively prepare clear messages for senior management\n\nRequirements\n\nBachelor Degree holders\n5+ years\u2019 working experience, preferably in foods sector\nProficient in English, Mandarin and Chinese\nExperience in digital marketing and social media (Facebook, Instagram, Google, Wechat) is necessary\nExperience in E-Commerce will be advantage\nGood communication skills, creative with strong market sense, self-motivated and attentive to details\nAble to meet tight deadlines, multi-task and able to work independently\nWilling to work overtime to achieve\nCheck out HKTVmall online store\nFresco dal Mercato\n\nOfficial company website:\nhttps://www.psf.com.hk", "employment_types": ["Full Time", "Permanent"], "selling_points": ["5 day work week", "Team player, Team oriented, Hands On Execution", "Passion in Food Industry"], "locations": ["Sheung Wan"], "categories": ["Marketing / Public Relations", "Marketing - Brand / Product Management"], "post_time": "2022-01-18T01:49:39Z", "salary": {"currency": null, "max": null, "min": null, "period": "monthly", "term": null}, "salary_visible": false, "title_keywords": ["marketing executive"], "responsibilities": ["make recommendations", "provide support", "management", "monitoring", "budget", "market research", "communication", "evaluate", "coordinate", "liaise with", "digital marketing", "sales team", "plan", "marketing materials", "senior management"], "requirements": {"degrees": ["degree", "bachelor"], "majors": [], "languages": ["english", "chinese", "mandarin"], "language_level": ["proficient"], "hard_skills": ["facebook", "e-commerce", "wechat"], "soft_skills": ["communication skills", "self-motivated", "meet tight deadlines", "multi-task", "work independently", "attentive to details", "work overtime", "strong market sense", "creative"], "languages_combined": [{"language": "english", "language_level": ["proficient"]}, {"language": "chinese", "language_level": ["proficient"]}, {"language": "mandarin", "language_level": ["proficient"]}]}, "experience_required": {"duration": ["5+ years"], "field": ["social media", "digital marketing", "e-commerce"]}}, {"job_id": "100003009052433", "location_code": "hk", "company": "Carlsberg Brewery H K Ltd", "job_title": "Channel Marketing Executive (Off-Trade)", "description": "Do you want to be a part of something exciting...?\nBased in our Hong Kong organization, the Channel Marketing Executive (Off-Trade)\u00a0will join us on our journey of brewing for a better today and tomorrow.\n\nWhat you'll be doing:\n\n\nCollaborate with the Brand Marketing, Channel Sales and other function on the creation of in-store activation and ensure the channel marketing campaigns are executed on-time-in-full.\nKeep track of the market intelligence and generate valuable consumer / shopper insights.\nIdentify customer & shopper insights and translate insights into business-building opportunities within specific customers/channels.\nResponsible for the production of promotional material for use at points of sales from conceptualization to execution.\nSupervise with outside agencies and merchandisers on the preparation of promotional materials.\nAnalyze the ROI of the marketing activities executed with the customer.\nManage the Channel Marketing budget and ensure all spending are effective and efficient.\nWhat we're looking for:\n\nBachelor's degree in Marketing or Business related discipline.\nAt least 1 - 2 years experience in marketing, experience in FMCG is preferred.\nGood analytical, planning and time management skills.\nStrong communication, presentation and negotiation skills.\nA problem solver with the ability to influence.\u00a0\nAble to work under pressure and to follow the timeline.\nOpen-minded, willing to learn and flexible to changes.\nOrganize and detail-minded.\u00a0\nGood command of both written and spoken English and Chinese.\nWhat you can expect:\nCarlsberg offers competitive salary & benefit such as double pay, discretionary bonus, medical & dental coverage, birthday leave and monthly free beer redemption to successful candidate. We also organize various social recreation activities and employee training and development programs for our team members to join. \u00a0\n\nWelcome to visit our company website https://carlsberghongkong.com.hk\u00a0for more information about Carlsberg.\n\nPersonal data collected will be treated in strictest confidence and only for recruitment purpose. Applicants who are not contacted within 2 months may consider their applications unsuccessful. Carlsberg will retain their applications for a maximum of six months and may refer suitable applicants to other vacancies within the company.", "employment_types": ["Full Time", "Permanent"], "selling_points": ["Ensure channel marketing campaigns are executed", "Market insight to support business growth", "Analyze the ROI of the marketing activities"], "locations": ["Hung Hom"], "categories": ["Marketing / Public Relations", "Marketing - Brand / Product Management", "Marketing - General / Support", "Marketing - Market Research"], "post_time": "2022-01-17T03:00:50Z", "salary": {"currency": null, "max": null, "min": null, "period": "monthly", "term": null}, "salary_visible": false, "title_keywords": ["marketing executive"], "responsibilities": ["collaborate with", "management", "development programs", "work under pressure", "budget", "communication", "promotional materials", "recruitment", "marketing campaigns", "personal data", "company website", "planning"], "requirements": {"degrees": ["degree", "bachelor"], "majors": ["business", "marketing"], "languages": ["english", "chinese"], "language_level": ["good command"], "hard_skills": [], "soft_skills": ["efficient", "flexible", "detail-minded", "confidence", "problem solver", "responsible", "time management skills", "open-minded", "willing to learn", "communication", "negotiation skills", "presentation", "work under pressure"], "languages_combined": [{"language": "english", "language_level": ["good command"]}, {"language": "chinese", "language_level": ["good command"]}]}, "experience_required": {"duration": ["at least 1 - 2 years"], "field": ["marketing", "fmcg"]}}, {"job_id": "100003009052015", "location_code": "hk", "company": "A-Fontane Company Limited", "job_title": "Assistant Marketing Manager/ Marketing Executive", "description": "Responsibilities:\n\nAssist in marketing reports preparation and data analysis, gather insights in customer behavior and business trend to improve the performance and drives sales;\nAssist the Marketing Manager in the preparation of expense report, cost and budget report;\nWork closely with marketing and sales departments in launching new product programs and execution and completion of projects;\nDevelop the marketing plan for products that support in conjunction with Sales & Marketing team, including key activities and budgets to support the acquisition of new customers and retention of existing customers;\nCollaborate with various internal and external parties to ensure smooth execution of event promotion and operation.\nRequirements:\n\nDegree holder in Marketing, Business Administration, or other related discipline;\nMinimum 3 years of working experience in marketing or sales related discipline;\nWork experience in HORECA, Frozen Meat and food Trading business is an advantage;\nExperience in\u00a0Adobe Illustrator, Photoshop, Facebook, Instagram, Twitter, Wechat, and search engine marketing is a plus but not a must;\nProficient in PC applications, including MS Word, PowerPoint and Excel;\n\nCreative and well-organized with excellent analytical and problem-solving skills;\nExcellent communication and presentation skills;\nAble to excel in fast-paced and dynamic environment with tight deadlines;\nSelf-motivated, result-oriented team player;\nProficient in Chinese and English.\n\nWe offer competitive remuneration and fringe benefits including discretionary bonus, medical insurance, annual leave and 5-day work. Interested party please send detailed resume in both Chinese and English version with expected salary & date of availability by clicking \"Apply Now\".\n\nPersonal data will be used for recruitment purpose only.", "employment_types": ["Full Time"], "selling_points": [], "locations": ["Tsuen Wan Area"], "categories": ["Marketing / Public Relations", "Marketing - Brand / Product Management", "Marketing - Marketing Communication", "Digital Marketing"], "post_time": "2022-01-17T01:50:51Z", "salary": {"currency": null, "max": null, "min": null, "period": "monthly", "term": null}, "salary_visible": false, "title_keywords": ["assistant marketing manager", "marketing executive"], "responsibilities": ["collaborate with", "budgets", "cost", "budget", "internal and external parties", "develop", "data analysis", "marketing plan", "reports", "report"], "requirements": {"degrees": ["degree holder"], "majors": ["marketing", "business administration"], "languages": ["english", "chinese"], "language_level": ["proficient"], "hard_skills": ["excel", "plus", "ms word", "problem-solving skills", "powerpoint", "wechat", "adobe illustrator", "pc applications", "dynamic", "facebook", "photoshop"], "soft_skills": ["dynamic environment", "self-motivated", "well-organized", "communication", "presentation skills", "problem-solving skills", "team player", "creative", "result-oriented"], "languages_combined": [{"language": "english", "language_level": ["proficient"]}, {"language": "chinese", "language_level": ["proficient"]}]}, "experience_required": {"duration": ["minimum 3 years"], "field": ["related", "marketing", "business", "food", "trading"]}}, {"job_id": "100003009054279", "location_code": "hk", "company": "Sunny Side Up (Never) Limited", "job_title": "SALES & MARKETING MANAGER", "description": "JOB ROLE AND RESPONSIBILITIES:\n\nAssist in developing and implementing the ATL/BTL marketing campaigns and retail promotional activities to drive the Inchcape approved used car sales.\nAssist in update and maintaining the Inchcape Approved Used Car website content and social media page.\nWork closely with digital team to accelerate the number of digital enquiries and conversion to sales.\nPrepare marketing materials including advertising, digital, social media, and retail event logistics support.\nCollect market and competitive used car market news and trends to facilitate the promotional activity planning.\nConsolidate reports and monitor expenses as per budget assigned\nAssist in any ad-hoc projects as assigned.\nSKILLS AND EXPERIENCE REQUIRED:\n\nMinimum 2 years of experience in fields of marketing, digital marketing/e-Commerce, or event management. Automotive industry experience is welcomed but not a must.\nDiploma holder or above will be an advantage\nGood communication skills in both written and spoken English and Chinese.\nCreative thinking and passionate, able to drive things happen fast.\nCompetent in MS Word, Excel, PowerPoint & Chinese Word-Processing\nSelf-motivated and able to work independently and under pressure\nDetail-minded and able to multi-task in a fast paced, dynamic culture\n\nPersonal data provided by applicants will be used for recruitment purpose only and will be destroyed after 3 months.\n\n", "employment_types": ["Full Time"], "selling_points": ["Degree holder in marketing", "3 yrs exp. in digital marketing", "Knowledge in Google Adwords/Facebook AD manager"], "locations": ["Kwun Tong"], "categories": ["Marketing / Public Relations", "Marketing - Brand / Product Management", "Marketing - General / Support", "Digital Marketing"], "post_time": "2022-01-17T09:19:05Z", "salary": {"currency": null, "max": null, "min": null, "period": "monthly", "term": null}, "salary_visible": false, "title_keywords": ["sales & marketing manager"], "responsibilities": ["budget", "website", "communication", "personal data", "ad-hoc projects", "advertising", "maintaining", "expenses", "monitor", "developing", "logistics", "reports", "marketing campaigns", "social media", "management", "promotional activities", "digital marketing", "prepare marketing materials", "recruitment", "planning"], "requirements": {"degrees": ["diploma holder"], "majors": [], "languages": ["english", "chinese"], "language_level": ["good"], "hard_skills": ["excel", "chinese word-processing", "e-commerce", "powerpoint", "dynamic", "ms word"], "soft_skills": ["passionate", "communication skills", "self-motivated", "work independently", "under pressure", "detail-minded", "multi-task", "competent", "dynamic", "creative"], "languages_combined": [{"language": "english", "language_level": ["good"]}, {"language": "chinese", "language_level": ["good"]}]}, "experience_required": {"duration": ["minimum 2 years"], "field": ["automotive industry", "management", "e-commerce", "marketing", "digital marketing"]}}, {"job_id": "100003009050341", "location_code": "hk", "company": "OTG Onthego Limited", "job_title": "Assistant Marketing Manager / Senior Marketing Officer (Medical insurance)", "description": "This position will be reporting to Chief Transformation Officer PR Asia, as part of the Regional Transformation Office that is being setup. It will also have a dotted line reporting to A&P Effectiveness Director in the Global Business Development team.\n\nJob Purpose:\u00a0\nPernod Ricard is reinforcing its Transformation team in the context of the deployment of Key Digital Programs (KDPs) in the Group and by fostering the digital enablement of teams and digital culture within Pernod Ricard. Specifically, to lead the engagement and drive the delivery roadmap of the KDP Matrix, Pernod Ricard Asia is setting up within its Regional Transformation team a Centre of Excellence (COE) for Marketing Effectiveness, and is looking for a Associate Director, Marketing Effectiveness that will play a key role in this endeavour by being part of the Regional Transformation Team, and by collaborating strongly with the Marketing Effectiveness KDP team, and the PR Asia Marketing, Business Development and Finance teams in delivering business objectives.\u00a0\n\nJob Duties and Responsibilities\nYou will be the expert of Marketing Mix Modelling (MMM), supporting the definition of the regional MATRIX deployment roadmap, managed by HQ Transformation and KDP teams. He/she will then be in charge of supporting the markets during the deployment of the KDP managed from HQ.\nPost-deployment, he/she will be responsible, in close coordination with the Region\u2019s Marketing, Business Development and Finance departments for working with markets and challenging them on the construction of our A&P Effectiveness (leveraging MATRIX) and sharing their expertise in MMM to the Pernod Ricard community.\n\nYou \u00a0will coordinate, enable and support MATRIX deployment and value steering across the region:\n\nRecommending markets for deployment.\nDefining, securing and allocating resources.\nMeasure skill level and ensuring upskilling across the organisation\nReviewing local constraints impact.\nDriving the deployment.\nMonitoring value delivery (budget vs. actual).\u00a0\n\nYou will also foster best practices and insights generation by providing cross market expertise. Over the medium term, the objective is to internalize the skills and competences leveraged through external resources, in order to create an in-house Marketing Efficiency COE, able to fully support markets in the Region. \u00a0\n\nAs the Associate Director, Marketing Effectiveness, you will\n1.\u00a0\u00a0 \u00a0Support MATRIX tool deployment in the Region\n\nCo-design regional roadmap with HQ Transformation and KDP teams, supporting assessment of data availability and maturity of marketing efficiency of markets\nProvide early support during deployment on data collection, simulation providing early upskilling\u00a0\n\n2.\u00a0\u00a0 \u00a0Support MATRIX tool adoption and value delivery in market.\n\nEnsure best use of the tool and full coherence of scenarios proposed with context and execution planned.\nSupport model improvement through highest data quality (incl. with specific workarounds). Monitor roll-out of Extract tool through the region.\nEnsure that there is a clear change plan in place during the key handover period from the KDP team to the local market team. \u00a0\n\n3.\u00a0\u00a0 \u00a0Drive marketing effectiveness improvement through formalization & adoption of best practices.\n\nBe a support for internal teams to analyse results and marketing insights after the handover period (from the KDP team to the internal team).\u00a0\nCooperate with Marketing Department to challenge markets investment scenarios recommended plans, identify best practices and roll them out through the region.\n\n4.\u00a0\u00a0 \u00a0Lead upskilling effort & support implementation of new ways of working with external partners, with a view to internalise those partners skills and expertise, within a PR Asia Marketing Effectiveness COE.\n\u00a0\nYour scope including:\u00a0\n\nInternal stakeholders: Markets (NB: Japan, South Korea), HQ Marketing Effectiveness Manager (KDP Manager), PR Asia Marketing, Business Development and Finance departments, KDP Deployment lead, local market PMO, Data teams etc\u2026\nKey External stakeholders: Consulting companies and freelancers supporting MATRIX deployment.\nJob scope: 100% international.\n\nWe are looking for: A candidate who is able to drive change. Has excellent leadership skills with experience collaborating with cross-functional teams. Has the ability and seniority to challenge KDP teams in the development. Pragmatic and capable to solve complex issues. Positive/can do mindset and solution-oriented. Ability to work with cross-cultural teams.\n\nA candidate expertise in marketing efficiency in terms of planning and execution. Marketing Mix Modeling experience a big plus. Understanding of data science / data modelling. Expert in business stakes understanding. Good knowledge of financial methods and tools. Understands data and software. Understands principles of advanced modeling techniques.\n\nYou will have: \u00a0\n\n10+ years professional experience.\nStrong experience in a leading data and insight consulting firm, with strong customer relationship with FMCG clients.\nExperience in FMCG, ideally Food & Beverage with similar type of Marketing activation and Route to Market.\nExperience in a global/regional role, to understand various market specificities and to have the agility to work with multicultural teams.\n50% travel\u00a0\n\n\n\nJob Posting End Date:\n\nTarget Hire Date:\n\n2022-03-15-07:00\n\nTarget End Date:", "employment_types": ["Full Time"], "selling_points": [], "locations": ["Lai Chi Kok"], "categories": ["Marketing / Public Relations", "Marketing - Brand / Product Management", "Marketing - General / Support", "Marketing - Marketing Communication"], "post_time": "2022-01-16T21:50:25Z", "salary": {"currency": null, "max": null, "min": null, "period": "monthly", "term": null}, "salary_visible": false, "title_keywords": ["assistant marketing manager", "senior marketing officer"], "responsibilities": ["software", "consulting", "data", "coordination with", "budget", "quality", "design", "planning", "plan", "plans", "cooperate with", "teams", "monitor", "implementation", "setup", "reporting", "monitoring", "data collection", "cross-functional teams", "coordinate", "analyse"], "requirements": {"degrees": [], "majors": [], "languages": [], "language_level": [], "hard_skills": ["vs", "plus", "deployment"], "soft_skills": ["capable", "responsible", "advanced", "leadership skills", "clear", "coordination", "organisation", "positive"], "languages_combined": []}, "experience_required": {"duration": ["10+ years"], "field": ["food", "marketing", "consulting", "fmcg"]}}, {"job_id": "100003009050537", "location_code": "hk", "company": "Toshiba Hong Kong Ltd", "job_title": "Assistant Officer/ Officer (Product Marketing)", "description": "Smart Charge, a new service brand runs by HKT and CLP, aims to offer one-stop and hassle-free electric vehicle (EV) charging solutions for end-users and commercial entities in Hong Kong to meet the increasing market demand.\n\nIt is a challenging and dynamic opportunity for an all rounded marketer to work for this brand which is striving for differentiation and continual growth.\n\nThe Job:\n\nThe incumbent will be responsible for business development and marketing of new products and services related to Smart Charge in consumer market. Major job duties include:\n\nAssist the Marketing team in planning of marketing programs to promote Smart Charge service.\nCoordinate closely with various parties and channels with on target customer identification, to ensure smoothly program execution for marketing campaigns and events / roadshows related process and logistics.\nManage communication and campaigns across digital and traditional channels, from online, social media to retail shops and location based activities.\nPreparing marketing collaterals, conduct Marketing campaign performance tracking and evaluation\nEnsure brand messages are synchronized with partners and monitor all marketing campaigns to ensure communications are streamlined and aligned.\nCollect market intelligence, conduct media evaluations and provide analyses/insights to facilitate development of marketing strategy and project assessments\n\n\u00a0The Person:\n\nUniversity graduate in Marketing, Communications, Business Administration or relevant discipline\nMinimum of 3-year experience in of Product, Digital or Service Marketing experience\nGood problem solving skills and able to work under tight timeline\nSelf-motivated and able to accomplish multiple tasks with minimal supervision\nEffective interpersonal and communication skills and able to work with people at all levels\nProficiency in both spoken and written English and Cantonese\nKnowledge or interest in automobile industry and the market trend\n\nIf you have the desire for an exciting and rewarding career, please send us your resume immediately, quoting the reference number, your present and expected salary via email to Human Resources.", "employment_types": ["Full Time", "Permanent"], "selling_points": [], "locations": ["Shatin Area"], "categories": ["Marketing / Public Relations", "Marketing - Brand / Product Management"], "post_time": "2022-01-17T01:00:29Z", "salary": {"currency": null, "max": null, "min": null, "period": "monthly", "term": null}, "salary_visible": false, "title_keywords": ["assistant officer", "officer"], "responsibilities": ["social media", "tracking", "marketing collaterals", "monitor", "coordinate", "communication", "logistics", "marketing campaigns", "evaluation", "planning"], "requirements": {"degrees": ["university graduate"], "majors": ["marketing", "business administration", "communications"], "languages": ["cantonese", "english"], "language_level": ["proficiency"], "hard_skills": ["problem solving skills"], "soft_skills": ["communication skills", "self-motivated", "multiple tasks", "problem solving skills", "interpersonal"], "languages_combined": [{"language": "cantonese", "language_level": ["proficiency"]}, {"language": "english", "language_level": ["proficiency"]}]}, "experience_required": {"duration": ["minimum of 3-year"], "field": ["digital", "marketing"]}}, {"job_id": "100003009052846", "location_code": "hk", "company": "Chase Jewellery Manufactory Limited", "job_title": "Sales and Marketing Executive", "description": "Responsibilities:\n\nTo formulate and implement the overall marketing and product strategies and plans for the Company across the regions in order to achieve the business goals by enhancing corporate branding and its external relations activities, especially in Mainland China, US and Europe\nTo responsible for creating new marketing initiatives in relation to corporate branding, public relations building, sales promotion campaigns and corporate events\nTo identify promotion strategies, keeping abreast and understanding the market to explore new communications platforms in order to support any sales related activities\nTo take charge of production and publication of corporate collaterals such as brochure, website or video so as to develop potential business opportunities\nTo identify the overall product strategy so as to define the position of the Company and the brand in the market, its products and marketing elements and provide concepts for management review\nTo maintain and enhance strong relationships with new and existing clients\u00a0\n\nRequirements:\n\n\nDegree holder or above in Marketing, Communications or related disciplines\nMore than 10 years of relevant experience in marketing, social media, advertising and/or PR; experience in manufacturing industry in garment/textiles field will be strong advantage\nSelf-motivated, creative, presentable, innovative strategic business thinker\nStrong interpersonal and negotiation skills with the ability to liaise with people all levels\nExcellent command of both spoken and written English, Chinese and Mandarin\nImmediate available is highly preferred\u00a0", "employment_types": ["Full Time"], "selling_points": [], "locations": ["Hung Hom"], "categories": ["Marketing / Public Relations", "Marketing - Brand / Product Management", "Sales, CS & Business Devpt", "Wholesale", "E-commerce", "Business Development"], "post_time": "2022-01-17T04:16:26Z", "salary": {"currency": "HKD", "max": 19999, "min": 14000, "period": "monthly", "term": null}, "salary_visible": true, "title_keywords": ["sales and marketing executive"], "responsibilities": ["business goals", "business opportunities", "website", "develop", "promotion campaigns", "maintain", "plans", "publication", "management review"], "requirements": {"degrees": ["degree holder"], "majors": ["related disciplines", "marketing", "communications"], "languages": ["english", "chinese", "mandarin"], "language_level": ["excellent"], "hard_skills": [], "soft_skills": ["self-motivated", "creative", "presentable", "negotiation skills", "innovative", "interpersonal"], "languages_combined": [{"language": "english", "language_level": ["excellent"]}, {"language": "chinese", "language_level": ["excellent"]}, {"language": "mandarin", "language_level": ["excellent"]}]}, "experience_required": {"duration": ["10 years"], "field": ["garment", "social media", "pr", "advertising", "marketing", "relevant experience", "manufacturing industry"]}}, {"job_id": "100003009052851", "location_code": "hk", "company": "VI Group Service Pty Limited", "job_title": "Digital Marketing Executive", "description": "Job Descriptions\nResponsibilities\n\nServicing a portfolio of clients targeting Hong Kong, Greater China and global markets under the guidance of Account Managers\nManaging holistic digital campaigns covering SEM, SEO, Social Media Marketing, Display Advertising, Video Advertising and more to achieve performance goals\nEnsuring smooth campaign delivery and optimizing results based on data analytics\nWorking closely with Sales Team in campaign delivery and revenue growth\nThe Successful Applicant(s)\n\nResult-oriented challenge taker\nQuick learner - must promptly pick up various advertising platforms and our world-class AI system for campaign optimization and reporting\nIndependent and able to perform well under pressure\nDetail-oriented and organized\nPossessing strategic mindset and strong data analytical skills\nPossessing strong communication and interpersonal skills for building client relationships\nGood command of Chinese, English and Putonghua\nDigital agency background / experience in digital marketing preferred but not a must\nCandidates who are certified with Google Ads are strongly preferred", "employment_types": ["Full Time"], "selling_points": ["Google / Facebook ad manager", "Create engaging content for different social media", "Formulate new e-marketing initiatives"], "locations": ["Tsim Sha Tsui"], "categories": ["Marketing / Public Relations", "Marketing - Brand / Product Management", "Marketing - Market Research", "Digital Marketing"], "post_time": "2022-01-17T04:20:22Z", "salary": {"currency": null, "max": null, "min": null, "period": "monthly", "term": null}, "salary_visible": false, "title_keywords": ["digital marketing executive"], "responsibilities": ["guidance", "social media", "reporting", "seo", "advertising", "data", "communication", "sales team", "revenue growth", "sem", "digital campaigns", "digital marketing"], "requirements": {"degrees": [], "majors": [], "languages": ["putonghua", "english", "chinese"], "language_level": ["good command"], "hard_skills": ["seo", "ai", "data analytics", "analytical skills", "sem"], "soft_skills": ["organized", "independent", "quick learner", "detail-oriented", "analytical skills", "communication and interpersonal skills", "smooth", "result-oriented", "perform well under pressure", "world-class"], "languages_combined": [{"language": "putonghua", "language_level": ["good command"]}, {"language": "english", "language_level": ["good command"]}, {"language": "chinese", "language_level": ["good command"]}]}, "experience_required": {"duration": [], "field": ["agency", "digital", "digital marketing"]}}, {"job_id": "100003009052076", "location_code": "hk", "company": "Strawberry Cosmetics (Services) Limited", "job_title": "Digital Marketing Manager", "description": "Neo Derm Group\n\nPioneering in an AI-powered e-commerce and service platform Gratus (www.gratus.com.hk), Neo Derm seeks to offer greater value through fast beauty experience to consumers to fulfil your quest of beautifying lives in a more convenient way.\n\nAs a Product Manager of brand marketing team, you will lead the development of brand equity narration for our top-of-mind brands including Dermes, Reenex, Elyze, Evvus, Vigene and Geneoo, and develop CRM strategies riding on our robust digital platform Gratus.\u00a0\n\nNot only do we offer a world-class working environment at the penthouse of One Island East, our excellent remuneration package and a fast progression path will nurture your personal and professional career development in a long run.\u00a0\n\n\n\nResponsibility\u00a0\n\nManage and analyze performance of social media platforms FB & IG\u00a0to drive new customer and achieve business targets\nManage KOL, free trial and testimonials\nProvide campaign performance analysis and recommendations to optimize performance for the best ROI\n\n\n\nRequirements\n\nexperience in digital marketing, brand marketing, product marketing and/or content management\nexperience in development / management of social media platforms, not limited to Facebook, Instagram, YouTube, WeChat, with successful campaigns\u00a0\n\nAll personal data collected will be treated in strict confidence and be used for recruitment purposes only.", "employment_types": ["Full Time", "Permanent"], "selling_points": [], "locations": ["Shau Kei Wan"], "categories": ["Marketing / Public Relations", "Marketing - Brand / Product Management", "Digital Marketing"], "post_time": "2022-01-17T02:02:23Z", "salary": {"currency": null, "max": null, "min": null, "period": "monthly", "term": null}, "salary_visible": false, "title_keywords": ["digital marketing manager"], "responsibilities": ["analysis", "social media platforms"], "requirements": {"degrees": [], "majors": [], "languages": [], "language_level": [], "hard_skills": ["facebook", "wechat"], "soft_skills": ["confidence"], "languages_combined": []}, "experience_required": {"duration": [], "field": ["social media", "management", "brand", "development", "marketing", "digital marketing"]}}, {"job_id": "100003009052440", "location_code": "hk", "company": "Twin Wealth Biotech Limited", "job_title": "Sales & Marketing Executive", "description": "Responsibilities\n\nCreate, execute and coordinate marketing program materials, communications, graphics, brand website maintenance, digital/social media strategy and events/exhibitions;\nExecute social media marketing ad strategies on Instagram, Facebook, LinkedIn, Pinterest Twitter and YouTube;\nManage and maintain website content using HTML or other web content management interface;\nPrepare media plan, budget summary and execute advertisement campaign with reports;\nReport on the performance of different paid media platform and provide campaign insights to assess campaign effectiveness and identify optimization opportunities;\nCoordinate with Design, PR and Communications and other functional teams to ensure brand consistency and smoothness operations;\nOther ad hoc tasks as assigned.\n\n\u00a0Requirements\n\nDegree holder in marketing or related disciplines;\u00a0\n3 years or above experiences in digital marketing;\nKnowledge in Google Adwords / Facebook AD manager is an advantage;\nKnowledge of Photoshop or AI is an advantage;\nGood communication in spoken and written English and Chinese and Mandarin;\nImmediate available is preferred.", "employment_types": ["Full Time", "Permanent"], "selling_points": [], "locations": ["Central & Western Area"], "categories": ["Beauty Care / Health", "Nutritionist", "Marketing / Public Relations", "Marketing - Brand / Product Management", "Sales, CS & Business Devpt", "Sales - Sales Management"], "post_time": "2022-01-17T03:02:28Z", "salary": {"currency": null, "max": null, "min": null, "period": "monthly", "term": null}, "salary_visible": false, "title_keywords": ["sales & marketing executive"], "responsibilities": ["graphics", "social media", "management", "operations", "budget", "coordinate with", "website maintenance", "website", "design", "coordinate", "teams", "ad hoc tasks", "maintain", "reports", "plan", "facebook", "brand consistency", "report"], "requirements": {"degrees": ["degree holder"], "majors": ["related disciplines", "marketing"], "languages": ["english", "chinese", "mandarin"], "language_level": ["good"], "hard_skills": ["ai", "adwords", "facebook", "photoshop"], "soft_skills": ["communication"], "languages_combined": [{"language": "english", "language_level": ["good"]}, {"language": "chinese", "language_level": ["good"]}, {"language": "mandarin", "language_level": ["good"]}]}, "experience_required": {"duration": ["3 years"], "field": ["digital marketing"]}}, {"job_id": "100003009053983", "location_code": "hk", "company": "Talent Preneur Management Consultancy Co. Limited", "job_title": "Product Manager (Explore Opportunities in the Maternal and Child Market)", "description": "Job Description\n\nManage and create content for social media platforms (including Facebook and Instagram), including copywriting and image creating/editing\nCommunicate with Media and Press on advertorials and PR activities\nAssist in planning, organizing and implementing sales, marketing strategies and event management to drive brand awareness and customer engagement\nAnalyze sales and promotional data for generating insights towards promotion effectiveness\nResponse to online and offline enquiries, as to build and grow the customer community\nHandle other offline ad-hoc projects and assignments as assigned\n\nRequirements\n\nAble to work independently and under pressure to meet tight deadlines\nSelf-motivated, customer-focused and task-oriented\nStrong knowledge in Google Ad Manager, SEO, SEM, Google Analytics and Facebook Ad Manager, EDM tools etc\n3-5 years marketing experience with solid exposure in retail marketing\nKnowledge of graphic designs, photo editing (e.g.: Adobe Illustrator, Photoshop)\u00a0\nImmediate available or short notice is highly preferred", "employment_types": ["Full Time", "Permanent"], "selling_points": [], "locations": ["Shatin Area"], "categories": ["Marketing / Public Relations", "Marketing - Brand / Product Management", "E-commerce", "Business Development", "Product Management / Business Analyst"], "post_time": "2022-01-17T07:54:43Z", "salary": {"currency": null, "max": null, "min": null, "period": "monthly", "term": null}, "salary_visible": false, "title_keywords": ["product manager"], "responsibilities": ["communicate with", "management", "ad-hoc projects", "marketing strategies", "data", "social media platforms", "facebook", "editing", "planning"], "requirements": {"degrees": [], "majors": [], "languages": [], "language_level": [], "hard_skills": ["google analytics", "seo", "adobe illustrator", "sem", "facebook", "photoshop"], "soft_skills": ["work independently", "self-motivated", "customer-focused", "under pressure", "meet tight deadlines"], "languages_combined": []}, "experience_required": {"duration": ["3-5 years"], "field": ["marketing", "retail"]}}, {"job_id": "100003009053660", "location_code": "hk", "company": "ADECCO", "job_title": "Commercial Director, APAC (Personal Care / Skincare)", "description": "We are now looking for a\u00a0Digital Marketing Specialist to join our team. Your\u00a0direct\u00a0responsibilities\u00a0include creating, managing and executing campaign and activations calendar that can build the brand awareness and drive impacts.Manage and create for our online platforms, e.g. website, Facebook, Instagram, WeChat, mobile app, and other digital platforms, as well as planning and execute all brand communications and media actions on all channels.\n\nMAIN RESPONSIBILITIES:\n\n\n\nCreating, managing and executing campaign and activations calendar that can build the brand awareness and drive impacts.\nManage and create content for our online platforms, e.g. website, Facebook, Instagram, WeChat, mobile app, and other digital platforms.\nPlanning and execute all brand communications and media actions on all channels.\nExplore new promotion or collaboration opportunities with relevant partners.\nSupervise all activities related to the brand. Ensuring that messaging and marketing activities are aligned with brand and company values.\nCome up with briefs, manage marketing agency or internal teams for development of brand campaigns and activations.\nManage the communications of third-party partners to drive the brand forward and work with brand influencers for driving the brand and audience reach.\nCollaborating with different teams such as Admissions, Faculty, Facilities, operations etc.\nMonitor the brand health and manage the brand tracking study and generate weekly, monthly performance reports and forecast predictions.\nKeep up on the changes in the industry with competitors and audience insights analysis.\n\nREQUIREMENTS:\n\nStrong project management skills with the ability to supervise multiple projects.\nHas knowledge executing the followings: campaign management, media activities, video production, photo shooting, and partners\u2019 communications management.\nExperience in brand health tracking, market research.\nProficiency with word processing, spreadsheet and presentation software (MS Office/Google)\nAbility to think strategically and come up with campaigns and activations ideas.\nBe an excellent team player, as well as keeping an open mind.\nStrong project management experience, across multiple teams and geographical.\nKnowledge in Adobe photoshop, illustrator, etc, will be an advantage.\nGood personality, positive attitude, able to work independently.\nExcellent command in written & spoken Cantonese and English.\nAt least 2 years of work experiences in the marketing sector, experience in the Education industry will be an advantage.\nProficiency in MS Office Application, Word, Excel, PowerPoint, Google Business Apps and all social media platform.\nCandidate with more experience will be considered for a senior position.\n\nWhy\u00a0IMS?\n\nYou want to have a job you\u2019re actually eager to come to every single day, with people that will inspire and challenge you. This is an outstanding opportunity to see your projects and efforts come to fruition, and feel real ownership on the job.\n\nPerks\n\nSunny space in beautiful Stanley with one of the best views in HK, you\u2019ll feel on holidays every single day!\nA fantastic work environment with lots of learning opportunities\nNot two days are the same when you work on education, prepare to be wowed, moved and inspired on a weekly basis\n\nLocation: Stanley Campus\n\nInterested parties please send full resume with availability\u00a0and expected salary by\u00a0clicking \"APPLY NOW\".\u00a0\n\nPersonal data collected will be used for recruitment purpose only.", "employment_types": ["Full Time", "Permanent"], "selling_points": [], "locations": ["North Point"], "categories": ["Sales, CS & Business Devpt", "Business Development", "Marketing / Public Relations", "Marketing - Brand / Product Management", "Channel / Distribution"], "post_time": "2022-01-17T07:18:24Z", "salary": {"currency": null, "max": null, "min": null, "period": "monthly", "term": null}, "salary_visible": false, "title_keywords": ["personal", "director"], "responsibilities": ["tracking", "mobile app", "performance reports", "operations", "analysis", "teams", "website", "monitor", "executing", "forecast", "facebook", "planning"], "requirements": {"degrees": [], "majors": [], "languages": ["cantonese", "english"], "language_level": ["excellent"], "hard_skills": ["excel", "adobe photoshop", "word processing", "illustrator", "word", "powerpoint", "project management", "spreadsheet", "ms office"], "soft_skills": ["work independently", "project management skills", "positive attitude", "project management", "learning", "think strategically", "team player", "presentation"], "languages_combined": [{"language": "cantonese", "language_level": ["excellent"]}, {"language": "english", "language_level": ["excellent"]}]}, "experience_required": {"duration": ["at least 2 years"], "field": ["brand", "market research", "education", "project management", "marketing"]}}, {"job_id": "100003009051945", "location_code": "hk", "company": "OSIM (HK) Co. Limited", "job_title": "Marketing Executive (5 Days Work)", "description": "Tasks and Responsibilities\n\nResponsible for analyzing the market of HUTCHMED products and therapeutic areas.\u00a0 Analyze, coordinate and support the information needs of preparing new product launch;\nFormulate integrated go-to-market plan of HUTCHMED products and launch tactics to maximize overall opportunity;\nDefine, monitor and achieve key performance metrics in achieving milestone to inform strategy and support execution;\nIntellectual curiosity about all aspects of our customers and business with a strong desire to persist in finding opportunities to maximize our business;\nStructured thinker and critical problem-solver; ability to distill and synthesize complex information from various resources to actionable insights;\nAbility to anticipate and rapidly respond to market and competitive changes in developing and executing brand strategies;\nProactively monitor external data, publications and their impact on future treatment algorithms, as well as potential impact on guidelines and pathways;\nDevelop annual budget and track expenses through the year;\nExperience successfully working in\u00a0cross functional matrix teams;\u00a0\nAbility to challenge the status quo with good rationale and logic; being provocative and creative in a productive fashion;\nMaintain strong compliance with all relevant internal policies, compliance and legal requirements.\n\n\u00a0Experience & Requirements\n\nMinimum of 5 years solid experience in pharmaceutical industry with experience in new product launch;\nBachelor Degree or above in Science;\nMarketing experience including strategy development and tactical execution;\nExcellent interpersonal skill with the ability to build working relations both internally and externally;\nStrong verbal and written communications skills;\nStrong commercial orientation and business acumen;\nStrength managing complexity and multiple competing priorities;\nExperience influencing without direct authority and working successfully with cross-functional teams and multiple agency partners;\nA creative and dynamic team player with strategic and marketing sense;\nExperience in oncology (and immunology) areas is preferred;\nProficiency in both spoken and written English and Chinese;\nJob title is subjected to the candidate\u2019s qualification and experience.\n\n\n\nSalary and benefits will be commensurate with experience.\u00a0Please send detailed resume with\u00a0current and\u00a0expected salary\u00a0by clicking \u201cAPPLY NOW\u201d in the below.\n\nWe are an equal opportunity employer and welcome applications from all qualified candidates. The information provided will be treated in strict confidence and used only for consideration of application for relevant/similar post(s) within the CK Hutchison Group of Companies. Applicants not having heard from us within four weeks from the date of this advertisement may consider their application unsuccessful. All personal data of unsuccessful applicants will be destroyed after the recruitment exercise when no longer required.", "employment_types": ["Full Time", "Permanent"], "selling_points": [], "locations": ["Shatin Area"], "categories": ["Marketing / Public Relations", "Marketing - Brand / Product Management", "Marketing - Direct Marketing", "Others"], "post_time": "2022-01-17T01:35:55Z", "salary": {"currency": null, "max": null, "min": null, "period": "monthly", "term": null}, "salary_visible": false, "title_keywords": ["marketing executive"], "responsibilities": ["data", "guidelines", "policies", "brand strategies", "monitor", "performance metrics", "developing", "develop", "coordinate", "budget", "expenses", "teams", "executing", "maintain", "plan", "compliance"], "requirements": {"degrees": ["degree or above", "bachelor"], "majors": ["science"], "languages": ["english", "chinese"], "language_level": ["proficiency"], "hard_skills": ["dynamic", "acumen"], "soft_skills": ["marketing sense", "interpersonal skill", "dynamic", "business acumen", "team player", "creative"], "languages_combined": [{"language": "english", "language_level": ["proficiency"]}, {"language": "chinese", "language_level": ["proficiency"]}]}, "experience_required": {"duration": ["minimum of 5 years"], "field": ["pharmaceutical", "development", "agency", "marketing"]}}, {"job_id": "100003009051630", "location_code": "hk", "company": "China Telecom Global Limited", "job_title": "Senior Product Marketing Executive/ Assistant Product Marketing Manager", "description": "Responsibilities:\n\nAssist Brand Manager to manage brands / products\u00a0\nTake initiative to develop marketing programs targeted at both consumers and trade customers, and implement a mix of marketing activities\nWork with the sales team to formulate trade promotion strategy and programs for key customers\nBuild up and maintain good relationship with media & agencies\nHandle marketing administrative works including reporting, claims and inventory control\nCoordinate with various departments to ensure promotions and activities are executed\n\nRequirement:\u00a0\n\nDegree in Marketing / Hospitality is preferred\nMin 2-4 years or above working experience preferably in FMCG or beverage industry\nSensitive to numbers and strong analytical skills\nSelf-motivated, fast learner with good multi-tasking skills to meet tight deadlines\nExcellent communication and inter-personal skill\nCandidate with more experience will be considered as Senior Marketing Executive\nImmediate available is preferred\n\n\n\nWe offer attractive remuneration package and career prospects plus 5-day week and medical insurance. Interest parties, please forward your full resume with expected salary to\u00a0apply now.\n\nAll data collected shall be solely for recruitment purpose.\n\nWebsite\u00a0\u00a0 :\u00a0\u00a0\u00a0\u00a0\u00a0\u00a0\u00a0http://www.telford.com.hk/", "employment_types": ["Full Time", "Permanent"], "selling_points": ["Degree holder in Marketing/Business Administration", "Formulate and implement digital marketing strategy", "Competitive salary package"], "locations": ["Wan Chai"], "categories": ["Marketing / Public Relations", "Marketing - Brand / Product Management", "Marketing - Market Research", "Digital Marketing"], "post_time": "2022-01-16T15:45:55Z", "salary": {"currency": null, "max": null, "min": null, "period": "monthly", "term": null}, "salary_visible": false, "title_keywords": ["product marketing manager", "assistant", "marketing executive"], "responsibilities": ["reporting", "coordinate with", "maintain good relationship", "develop", "inventory control", "sales team"], "requirements": {"degrees": ["degree"], "majors": ["hospitality", "marketing"], "languages": [], "language_level": [], "hard_skills": ["analytical skills"], "soft_skills": ["self-motivated", "meet tight deadlines", "analytical skills", "communication", "inter-personal skill", "multi-tasking skills", "sensitive to numbers", "fast learner"], "languages_combined": []}, "experience_required": {"duration": ["min 2-4 years"], "field": ["fmcg", "beverage industry", "marketing"]}}, {"job_id": "100003009052435", "location_code": "hk", "company": "ScentAir Technologies (Hong Kong) Limited", "job_title": "Ancillary Product Specialist/Manager", "description": "Responsibilities:\n\nExecute digital ROI driven marketing campaigns among global markets\nProactively monitor and optimize campaigns spending and performance on Facebook, Google Ads, Unity Ads and other digital platforms on a daily basis\nManage social media pages including Facebook, IG, LINE, etc\nMonitor and control marketing budget and campaign timelines\u00a0\nCoordinate with product team to manage daily digital tactics\nCoordinate with internal designer to produce new creatives with innovative ideas and formats\nClosely communicate with advertising partner and manage agency accounts to ensure performance is delivered\nProduce regular data analysis, market trending research and reporting with associated insights\nPerform Ad-hoc duties occasionally\n\n\u00a0Qualifications & Skills\n\nBachelor Degree in Business, Marketing, Advertising, eCommerce or related disciplines\n2 years of digital marketing experience\nFamiliar with digital marketing tools including Facebook ads manager, social media, 3rd party tracking, LTV modeling, SEO and Google Analytics\nStrong in written and spoken English and Chinese\nJapanese speaker or business level of Japanese is a plus\nMobile app or game relevant working experience is a plus\nStrong report and analytical skills is a plus\nPrioritize workload, manage multiple projects and meet deadlines for various and ad-hoc marketing deliverable\nPerform independently but outstanding team player with a strong sense of ownership and accountability\nExcellent communication, collaboration and planning skills\nCandidate with less experience will be considered as Digital Marketing Assistant\nFresh Graduate are welcome\n\nWe offer attractive remuneration and fringe benefits to the right candidates. Please send us the application by clicking the \"Apply Now\" button, together with a detailed resume, stating the current and expected salary.\n\n(All personal data provided by job applicants are used only for recruitment purposes and will be treated strictly confidential. Unsuccessful applications will be properly disposed within 3 months.)", "employment_types": ["Full Time"], "selling_points": ["Fragrance, Gift & Premium, lifestyle", "passionate lifestyle/ fragrance trend", "Marketing"], "locations": ["Lai Chi Kok"], "categories": ["Marketing / Public Relations", "Marketing - Brand / Product Management"], "post_time": "2022-01-17T03:01:21Z", "salary": {"currency": null, "max": null, "min": null, "period": "monthly", "term": null}, "salary_visible": false, "title_keywords": ["product specialist", "manager"], "responsibilities": ["ad-hoc", "ideas", "budget", "communication", "facebook", "control", "advertising", "mobile app", "monitor", "manage multiple projects", "marketing campaigns", "report", "social media", "reporting", "seo", "coordinate with", "data analysis", "digital marketing", "ad-hoc duties", "tracking", "communicate with", "planning"], "requirements": {"degrees": ["degree", "bachelor", "fresh graduate"], "majors": ["ecommerce", "related disciplines", "business", "marketing"], "languages": ["japanese", "english", "chinese"], "language_level": [], "hard_skills": ["google analytics", "plus", "seo", "analysis", "analytical skills", "mobile", "facebook", "unity"], "soft_skills": ["planning skills", "independently", "accountability", "prioritize", "analytical skills", "communication", "team player", "ad-hoc duties", "meet deadlines", "innovative", "driven"], "languages_combined": [{"language": "japanese", "language_level": []}, {"language": "english", "language_level": []}, {"language": "chinese", "language_level": []}]}, "experience_required": {"duration": ["2 years"], "field": ["digital marketing", "relevant working experience"]}}, {"job_id": "100003009047281", "location_code": "hk", "company": "AsiaWorld-Expo Management Limited", "job_title": "Senior Marketing & Branding Officer", "description": "Job\u00a0Responsibilities:\n\nAble to analyze the market needs in different aspects and take the initiative for new project establishment\nMonitor trend in Maternal and ChildRelated Products/Services and provide market analysis as part of on-going brand management\nResponsible for planning, implementing, and evaluating strategic marketing campaign to achieve business objectives in both HK& Mainland China market\nImplement new product development, marketing campaigns, prepare marketing collaterals and manage digital marketing assets including corporate website, social media platforms, eDM, and SEO/SEM\nPerform ad-hoc projects as assigned\n\nJob Requirements:\n\nBachelor\u2019s degree in biological science, biotechnology, biochemistry, Marketing, E-commerce or equivalent\n4-6 years of Maternal and Child Related Products/Services marketing experience\nA good team head that can take the lead and initiate projects\nPassionate, proactive, details-oriented and achievement oriented\nData sensitive and good analytical skills\nStrong interpersonal and communication skills with the ability to interact with people at all levels professionally\nGood command in Mandarin and English", "employment_types": ["Full Time"], "selling_points": ["Marketing & Branding", "Attractive remuneration package", "Good career path"], "locations": ["Airport Area"], "categories": ["Marketing / Public Relations", "Marketing - Brand / Product Management", "Marketing - General / Support", "Marketing - Marketing Communication"], "post_time": "2022-01-14T02:45:23Z", "salary": {"currency": null, "max": null, "min": null, "period": "monthly", "term": null}, "salary_visible": false, "title_keywords": ["officer"], "responsibilities": ["management", "seo", "edm", "marketing collaterals", "monitor", "website", "social media platforms", "market analysis", "digital marketing", "marketing campaigns", "sem", "ad-hoc projects", "planning"], "requirements": {"degrees": ["degree", "bachelor"], "majors": ["marketing", "biological science", "e-commerce"], "languages": ["english", "mandarin"], "language_level": ["good command"], "hard_skills": ["analytical skills", "e-commerce"], "soft_skills": ["passionate", "communication skills", "analytical skills", "sensitive", "proactive", "interpersonal"], "languages_combined": [{"language": "english", "language_level": ["good command"]}, {"language": "mandarin", "language_level": ["good command"]}]}, "experience_required": {"duration": ["4-6 years"], "field": ["related", "marketing"]}}, {"job_id": "100003009054333", "location_code": "hk", "company": "Orient Fair Development Ltd", "job_title": "Senior Purchasing Executive (Casual & Sports Clothing & Footwear)", "description": "Our client is a global healthcare & pharmacy company, they are now seeking to hire the Head of Commercial & Brand Activation, APAC to join their regional team to support the business expansion in Asia Pacific region.\nJob Responsibilities:\nLead the team to identify new business opportunity and develop new markets to achieve business objectives\nFormulate and implement short-term & long-term business strategy to drive the business growth in Asia Pacific region\nDevelop go-to-market strategies for each specified market with internal departments and business partners (e.g. retailers and distributors)\nWork closely with regional marketing team on development of product launch strategy, promotion activities and trade activation, etc., collect feedback and provide recommendation to facilitate the innovation strategy development & brand positioning\nReview workflow and procedures to ensure operations effectiveness & efficiency; and reinforce the ethics and sales codes of conduct in the team\nDevelop KPI and measurements to sustain the business performance, and provide related action plans for improvement\nConduct market research and analysis to obtain market & consumer insights to support commercial strategy development\nJob Requirements:\n\nBachelor in Business, Marketing or any related disciplines\nOver 10 years in business development and brand management experience from MNC, with skincare/cosmetics/ personal care is an advantage\nExcellent project management skill and result-oriented\nStrong business acumen and entrepreneurial mindset, with proven record in developing new markets\nStrong leadership and people management skills\nExcellent communication and presentation skills with key stakeholders\nInterested parties, please\u00a0CLICK HERE\u00a0to apply the position via Adecco website with your CV, or if you would like to have a further discussion about this role, please contact Cathy Yeung at 852-28996182.", "employment_types": ["Full Time", "Permanent"], "selling_points": ["solid experience in purchasing in sports field", "Casual & Sports Clothing & Footwear,", "Experience in Outdoor Activities"], "locations": ["Kwai Hing"], "categories": ["Marketing / Public Relations", "Marketing - Brand / Product Management", "Merchandising & Purchasing", "Footwear", "Procurement / Purchasing / Sourcing"], "post_time": "2022-01-17T09:11:14Z", "salary": {"currency": null, "max": null, "min": null, "period": null, "term": null}, "salary_visible": false, "title_keywords": ["purchasing executive"], "responsibilities": ["consumer insights", "operations", "conduct market research", "review", "procedures", "analysis", "develop", "provide recommendation", "plans"], "requirements": {"degrees": ["bachelor"], "majors": ["related disciplines", "business", "marketing"], "languages": [], "language_level": [], "hard_skills": ["project management", "acumen"], "soft_skills": ["communication", "presentation skills", "project management skill", "business acumen", "leadership", "result-oriented"], "languages_combined": []}, "experience_required": {"duration": ["10 years"], "field": ["personal care", "management", "business development", "brand"]}}, {"job_id": "100003009039038", "location_code": "hk", "company": "Mott MacDonald Hong Kong Limited", "job_title": "Business Support_Marketing Proposal Advisor", "description": "Our client is a global healthcare & pharmacy company, they are now seeking to hire the Head of Commercial & Brand Activation, APAC to join their regional team to support the business expansion in Asia Pacific region.\nJob Responsibilities:\nLead the team to identify new business opportunity and develop new markets to achieve business objectives\nFormulate and implement short-term & long-term business strategy to drive the business growth in Asia Pacific region\nDevelop go-to-market strategies for each specified market with internal departments and business partners (e.g. retailers and distributors)\nWork closely with regional marketing team on development of product launch strategy, promotion activities and trade activation, etc., collect feedback and provide recommendation to facilitate the innovation strategy development & brand positioning\nReview workflow and procedures to ensure operations effectiveness & efficiency; and reinforce the ethics and sales codes of conduct in the team\nDevelop KPI and measurements to sustain the business performance, and provide related action plans for improvement\nConduct market research and analysis to obtain market & consumer insights to support commercial strategy development\nJob Requirements:\n\nBachelor in Business, Marketing or any related disciplines\nOver 10 years in business development and brand management experience from MNC, with skincare/cosmetics/ personal care is an advantage\nExcellent project management skill and result-oriented\nStrong business acumen and entrepreneurial mindset, with proven record in developing new markets\nStrong leadership and people management skills\nExcellent communication and presentation skills with key stakeholders\nInterested parties, please\u00a0CLICK HERE\u00a0to apply the position via Adecco website with your CV, or if you would like to have a further discussion about this role, please contact Cathy Yeung at 852-28996182.", "employment_types": ["Full Time", "Permanent"], "selling_points": ["Manage end-to-end submission process for bids", "8 years\u2019 experience in marketing / submission", "5 days work, 13th month salary, wellness program"], "locations": ["Ngau Tau Kok"], "categories": ["Marketing / Public Relations", "Marketing - Brand / Product Management", "Marketing - General / Support", "Marketing - Market Research"], "post_time": "2022-01-16T21:50:11Z", "salary": {"currency": null, "max": null, "min": null, "period": "monthly", "term": null}, "salary_visible": false, "title_keywords": ["advisor"], "responsibilities": ["consumer insights", "operations", "conduct market research", "review", "procedures", "analysis", "develop", "provide recommendation", "plans"], "requirements": {"degrees": ["bachelor"], "majors": ["related disciplines", "business", "marketing"], "languages": [], "language_level": [], "hard_skills": ["project management", "acumen"], "soft_skills": ["communication", "presentation skills", "project management skill", "business acumen", "leadership", "result-oriented"], "languages_combined": []}, "experience_required": {"duration": ["10 years"], "field": ["personal care", "management", "business development", "brand"]}}, {"job_id": "100003009052759", "location_code": "hk", "company": "Telford International Co Ltd", "job_title": "Commercial Manager \u2013Wine & Spirits Division", "description": "ScentAir is looking for a product marketing professional for our APAC Marketing Team. This individual contributor will be the subject matter expertise who is able to work closely with US HQ as the voice for product localization of the APAC market and accountable for the product launch roadmap & GTM strategy as well as answering any product related questions to our APAC Team and corporate clients.\n\nJob Description:\n\n8 - 12 years\u2019 work experience in Product Marketing with background in HVAC or any other air purification products and/or fragrance machines would be highly preferred\nServes as the national product specialist for all aspects of fragrance machines and air purification solutions\nDemonstrates deep knowledge of the product functions & differentiations as well as the competitive landscape of the market in the APAC region\nEstablish a price and promotional strategy in line with market needs and responsiveness\nAnalyse internal sales and evaluate market trends as well as competitor analysis to maximize sales efforts\nMonthly review on product sales run rate and work with marketing lead & sales leaders for driving business growth\nAct as project manager to liaise with HQ and local offices for product regionalization/localization, including but not limited to certification to ensure products complying local regulation\nWork with HQ & Regional Training Team to provide product training\nProduct demonstration and presentation pitching to external clients as requested\n\nRequired Qualifications\n\nDegree in Business, Marketing or related disciplines\nResourceful \u2013 search out answers independently, sometimes research is involved to find answers\nStrong project management and ownership for a range of product portfolio while ensuring high quality of deliverable\nAbility to memorize technical information and present with product accuracy \u2013 critical that this is a SME who can talk to a customer with deep technical knowledge\nStrong communication and influential skills to manage customers\u2019 expectation\nFluent in both written and spoken English, Mandarin and Cantonese\nProactive team member who is self-motivated with a can-do attitude and passion\nMust be proficient with current software packages such as Microsoft Word, Excel, Outlook, PowerPoint and CRM tools (i.e., Salesforce)\nStrong interpersonal\u00a0and communication skills, detail-minded, well-organized", "employment_types": ["Full Time", "Permanent"], "selling_points": ["Responsible for Wine & Spirits portfolio", "Hotel, Club & Premium Bar segments", "Min. 5 yrs sales experience in alcoholic industry"], "locations": ["Kwai Hing"], "categories": ["Marketing / Public Relations", "Marketing - Brand / Product Management", "Sales, CS & Business Devpt", "Channel / Distribution", "Sales - Sales Management"], "post_time": "2022-01-17T03:56:37Z", "salary": {"currency": null, "max": null, "min": null, "period": "monthly", "term": null}, "salary_visible": false, "title_keywords": ["manager"], "responsibilities": ["software", "analysis", "review", "quality", "evaluate", "project management", "communication", "liaise with", "sme", "analyse"], "requirements": {"degrees": ["degree"], "majors": ["related disciplines", "business", "marketing"], "languages": ["cantonese", "english", "mandarin"], "language_level": ["fluent"], "hard_skills": ["excel", "microsoft word", "salesforce", "hvac", "analysis", "powerpoint", "project management", "outlook"], "soft_skills": ["detail-minded", "communication skills", "self-motivated", "independently", "resourceful", "can-do attitude", "interpersonal", "deep", "well-organized", "accountable", "team member", "communication", "project management", "influential", "proactive", "presentation"], "languages_combined": [{"language": "cantonese", "language_level": ["fluent"]}, {"language": "english", "language_level": ["fluent"]}, {"language": "mandarin", "language_level": ["fluent"]}]}, "experience_required": {"duration": ["8 - 12 years"], "field": ["marketing"]}}, {"job_id": "100003009051666", "location_code": "hk", "company": "Genfortune Pharmaceuticals Limited", "job_title": "Digital Marketing Executive (5 days)", "description": "Responsibilities:\n\n\nPlan & execute marketing & PR plans, joint promotion campaign, product launch event and PR pitching\nDevelop and update marketing calendar to ensure the consistency with brand\u2019s strategic direction\nPrepare sales & marketing reports and presentation materials\nWork closely with internal and external parties to ensure smooth execution of marketing initiatives\nLiaise with media & advertising agencies and production house for advertising placement & premium production\nEstablish and maintain good network with media, celebrities, KOL & influencers\nDevelop and execute visual merchandising & promotional activities for shops / counters\nPerform ad hoc assignments as required\u00a0\n\nRequirements:\n\nDegree holder in Marketing or Business related disciplines\nAt least\u00a03 years working experience in Marketing\nExperience in Beauty / Skincare / Fragrance industry will be an advantage\nWith social media, online advertising & PR event experience will be an advantage\nStrong presentation and interpersonal skill\nGood command of written English and Cantonese\nAble to take multi-task\n\nCandidate with less experience will be considered as Marketing Executive\n\n\n\n\n\nWe offer 5 days work, attractive salary package including medical scheme & excellent career advancement opportunity to the right candidates. Our office is located in San Po Kong, around 8 minutes walk from\u00a0Diamond Hill MTR\u00a0station. Interested parties please send your full resume with current\u00a0and\u00a0expected salary\u00a0by clicking \"APPLY NOW\".\u00a0\u00a0\n\nwww.artalcosmetic.com\u00a0\n\nPersonal data collected would be used for recruitment purpose only", "employment_types": ["Full Time", "Permanent"], "selling_points": ["E-commerce knowledge", "Familiar with social platforms", "Staff discount/Medical Insurance/Performance bonus"], "locations": ["Quarry Bay"], "categories": ["Marketing / Public Relations", "Marketing - Brand / Product Management", "Marketing - Direct Marketing", "E-commerce", "Marketing - Brand / Product Management"], "post_time": "2022-01-16T21:50:37Z", "salary": {"currency": null, "max": null, "min": null, "period": "monthly", "term": null}, "salary_visible": false, "title_keywords": ["digital marketing executive"], "responsibilities": ["advertising", "internal and external parties", "prepare sales", "merchandising", "develop", "maintain", "reports", "promotional activities", "plan", "visual", "liaise with", "plans", "ad hoc assignments"], "requirements": {"degrees": ["degree holder"], "majors": ["business", "related disciplines", "marketing"], "languages": ["cantonese", "english"], "language_level": ["good command"], "hard_skills": [], "soft_skills": ["multi-task", "presentation", "interpersonal skill"], "languages_combined": [{"language": "cantonese", "language_level": ["good command"]}, {"language": "english", "language_level": ["good command"]}]}, "experience_required": {"duration": ["at least 3 years"], "field": ["social media", "pr", "advertising", "marketing", "beauty"]}}, {"job_id": "100003009052689", "location_code": "hk", "company": "Chanel Hong Kong Limited", "job_title": "Senior Marketing Manager, Watches & Fine Jewellery, Hong Kong & Macau", "description": "Responsibilities:\n\nTo assist the team in planning and executing marketing campaigns, including ATL, BTL, PR, and Online promotion\nOrganize events to maximize product launch awareness and enhance customer relationship\nResponsible for planning and execution of CRM Program for customer acquisition and retention\nPrepare regular reports and insights for business performance review\nTo participate in training programme and presentation\nAssist in any ad hoc duties as requested\n\nRequirements:\n\nDegree holder in Marketing / Communications or related disciplines\nWith 1 - 2 years of working experience in marketing\nProactive, result oriented with a strong sense of responsibility\nWith good presentation skills\nFast-paced with excellent communication and interpersonal skills\nCreative and attention to details\nGood command of spoken and written English, Cantonese and Mandarin\n\nInterested parties, please send your full resume with\u00a0current salary,\u00a0expected salary,\u00a0and\u00a0available date\u00a0either by direct application from JobsDB (Please quote the job title on the subject ) or by WhatsApp:69298297 or by post to Human Resources Department, Unit 8-14 & 22-28, 11/F, Topsail Plaza, 11 On Sum Street, Shek Mun.\n\n\"Personal data collected will be used for recruitment purposes only.\"", "employment_types": ["Full Time"], "selling_points": [], "locations": ["Not Specified"], "categories": ["Marketing / Public Relations", "Marketing - Brand / Product Management", "Others"], "post_time": "2022-01-17T03:42:30Z", "salary": {"currency": null, "max": null, "min": null, "period": "monthly", "term": null}, "salary_visible": false, "title_keywords": ["senior marketing manager"], "responsibilities": ["ad hoc duties", "review", "planning", "reports", "executing", "marketing campaigns", "online promotion"], "requirements": {"degrees": ["degree holder"], "majors": ["related disciplines", "marketing", "communications"], "languages": ["cantonese", "english", "mandarin"], "language_level": ["good command"], "hard_skills": [], "soft_skills": ["creative", "sense of responsibility", "result oriented", "presentation skills", "communication and interpersonal skills", "attention to details", "proactive"], "languages_combined": [{"language": "cantonese", "language_level": ["good command"]}, {"language": "english", "language_level": ["good command"]}, {"language": "mandarin", "language_level": ["good command"]}]}, "experience_required": {"duration": ["1 - 2 years"], "field": ["marketing"]}}, {"job_id": "100003009052278", "location_code": "hk", "company": "Cathay Pacific Airways Ltd", "job_title": "Brand Manager", "description": "Key\u00a0Responsibilities:\n\nFormulate and implement digital marketing strategy to grow customer base and drive global business\nConduct market research and business analysis for a variety of telecommunication products and solutions with an aim to capture market opportunities and customer needs\nConduct Lead Generation programs leveraging both digital and traditional marketing platforms to achieve business objectives\nWork closely with multi-disciplinary teams to boost marketing program results\u00a0\nPerform other duties as assigned by the management\n\n\u00a0Requirements:\n\nDegree holder in Marketing/Business Administration/Data Analytics or related discipline with at least 3 years\u2019 work experience gained from the telecommunications, IT, consultancy or other services industries with track record in digital marketing\nA good understanding of the global telecommunications market and products/solutions\nExperience in developing sales incentive program is definitely an advantage\nExcellent communication, interpersonal and organization skills\nStrong analytical and problem solving skills with good business acumen.\u00a0 Results-oriented, self-motivated and able to cope with a fast pace, dynamic and global operated business environment\nHighly proficient in MS Office including PowerPoint, Excel, Word (including Chinese word processing) and other related applications\nExcellent command of both spoken and written English and Chinese.\u00a0 Fluent Mandarin is an advantage\nQualified candidate with more relevant work experience would be considered as Assistant Product Marketing Manager\n\nWe offer 5 days work, competitive salary package and attractive career development opportunities to the right candidate.\u00a0\n\nInterested parties please email your full resume with your current & expected salary to us.\n\nApplicants not invited for interview within 3 months may assume their applications unsuccessful.\u00a0\n\nIf you are interested in other job opportunities, please check with below career website.\n\nPersonal data collected would be used for recruitment purpose only.\n\n\n\n", "employment_types": ["Full Time", "Permanent"], "selling_points": ["8 years\u2019 experience in Brand, Design", "Development of the Cathay\u2019s brand strategy", "Travel Benefits, 5-day work, Medical Benefits"], "locations": ["Lantau Island"], "categories": ["Design", "Others", "Marketing / Public Relations", "Management", "Marketing - Brand / Product Management"], "post_time": "2022-01-17T02:38:30Z", "salary": {"currency": null, "max": null, "min": null, "period": "monthly", "term": null}, "salary_visible": false, "title_keywords": ["manager"], "responsibilities": ["perform other duties", "management", "conduct market research", "teams", "digital marketing", "business analysis"], "requirements": {"degrees": ["degree holder"], "majors": ["marketing", "business administration", "it", "digital marketing"], "languages": ["english", "chinese", "mandarin"], "language_level": ["advantage", "fluent", "excellent", "proficient"], "hard_skills": ["excel", "chinese word processing", "data analytics", "word", "acumen", "powerpoint", "dynamic", "problem solving skills", "ms office"], "soft_skills": ["self-motivated", "business environment", "organization skills", "communication", "analytical and problem solving skills", "dynamic", "business acumen", "interpersonal"], "languages_combined": [{"language": "english", "language_level": ["excellent"]}, {"language": "chinese", "language_level": ["excellent", "proficient"]}, {"language": "mandarin", "language_level": ["fluent", "advantage"]}]}, "experience_required": {"duration": ["at least 3 years"], "field": ["business administration", "related", "developing", "marketing", "it", "digital marketing", "telecommunications"]}}, {"job_id": "100003009052178", "location_code": "hk", "company": "Hutchison Telecommunications (Hong Kong) Limited", "job_title": "Marketing Executive - Loyalty Marketing", "description": "Position Summary\n\nThe main tasks for the appointee are:\n\nTo assist the Unit Head in driving the overall marketing and communications strategies;\nTo plan the integrated marketing campaigns including events, advertising, digital marketing, school and community outreach, public relations etc to elevate the image of the College and boost student admission;\nTo lead the implementation of the marketing activities and work with different internal or external parties to achieve the goals;\nTo oversee the design and production of advertising and promotional materials, promotional videos/films and digital contents;\nTo generate reports and evaluate the effectiveness of the promotion efforts;\nTo conduct regular research and studies to identify market opportunities and collect feedback from stakeholders;\nTo monitor and lead a small team of marketing and communication;\nTo take up other tasks as assigned by the College\n\nRequirements\n\nApplicants should meet the following requirements:\n\nA Bachelor\u2019s degree in Marketing/Journalism or related discipline\nAt least 5 years of marketing experience in the tertiary education sector or with sales and customer servicing sector. Previous working experience from education sector is preferable.\nExcellent command of English and Chinese (Cantonese and Mandarin)\nExcellent interpersonal and communication skills to interact with different stakeholders and external parties\nA good sense of responsibility and self-motivation\nAble to handle tasks independently with minimum supervision\nAble to adopt a positive attitude to the team\u2019s objectives and maintain collaborative work relationship with team members\nExperience in managing social media platforms and web content is an advantage\nExperience in managing a small team\u00a0\n\nSalary and Fringe Benefits:\n\nInitial appointment will normally be made on a renewable 24-month contract.\n\nRemuneration is competitive and will be based on qualifications and relevant experience. The College offers group medical insurance, staff development support, annual leave and sick leave, and Mandatory Provident Fund to eligible appointee(s).\n\nApplication Procedure:\n\nApplicants are invited to:\n\nSubmit an application letter with a full Curriculum Vitae, and copies of all graduate transcripts, and the names and contact details of three references.\nSpecify in the application letter current/latest salary and expected salary\nSend applications to the Yew Chung College of Early Childhood Education by \"Apply Now\".\nThe College will review applications immediately and applications will be accepted until the posts are filled.\u00a0 Only shortlisted candidates will be contacted.\n\nImportant notes to Applicants:\n\nAppointees will have to undergo a medical examination.\u00a0 Reimbursement of costs subject to a ceiling is applicable.\nLocal applicants will have to undergo a Sexual Conviction Record Check / Overseas applicants will have to present a police report before appointment can be confirmed.\u00a0\n\nThe College also reserves the right to make an appointment by invitation.\n\nPersonal data collected will be used for recruitment-related purposes only.", "employment_types": ["Full Time", "Permanent"], "selling_points": [], "locations": ["Tsing Yi"], "categories": ["Marketing / Public Relations", "Marketing - Brand / Product Management", "Marketing - General / Support", "Marketing - Marketing Communication"], "post_time": "2022-01-17T02:23:28Z", "salary": {"currency": null, "max": null, "min": null, "period": "monthly", "term": null}, "salary_visible": false, "title_keywords": ["marketing executive"], "responsibilities": ["social media platforms", "maintain"], "requirements": {"degrees": ["degree", "bachelor"], "majors": ["journalism", "marketing"], "languages": ["cantonese", "english", "chinese", "mandarin"], "language_level": ["excellent"], "hard_skills": [], "soft_skills": ["communication skills", "self-motivation", "interpersonal", "sense of responsibility"], "languages_combined": [{"language": "cantonese", "language_level": ["excellent"]}, {"language": "english", "language_level": ["excellent"]}, {"language": "chinese", "language_level": ["excellent"]}, {"language": "mandarin", "language_level": ["excellent"]}]}, "experience_required": {"duration": ["at least 5 years"], "field": ["marketing", "education"]}}, {"job_id": "100003009051122", "location_code": "hk", "company": "Fortress", "job_title": "Marketing Officer", "description": "Responsibilities:\u00a0\n\nFormulate marketing plan & agree\u00a0the marketing strategies with brand owners\nDevelop and execute marketing and promotional activities; and prepare POSM for both on-& off-trade\nDevelop and manages marketing budget including forecast, marketing/promotion activity, A&P budget, depletion, shipment and inventory controls\nCoordinate with principals and various departments to ensure the activities are efficiently executed\nMonitor the brand performance and ensure effective control of marketing results\nWilling to work during night\u00a0and sometimes during weekend\u00a0for special events\n\nRequirements:\u00a0\n\nUniversity degree or equivalent \u2013 major in marketing is preferred\n3 years of work experience in marketing senior role; in FMCG industry is preferred\nFluent in written and spoken English and Cantonese\nGood command of written and spoken English and Cantonese\nGood communication and interpersonal skills, with ability\u00a0to work effectively with colleagues in other functions and cultures\nAnalytical and Commercially sensible with good negotiation skill\nHighly self-motivated, strong team player and creative thinker\nComputer proficiency in Microsoft Outlook, Word, Excel,\u00a0and PowerPoint is essential.\nImmediate available or short notice is highly preferred\n\nWe offer attractive remuneration package and career prospects plus 5-day\u00a0week to right\u00a0candidate. Interest parties; please forward your full resume with expected salary to us.\n\n\u00a0All data collected shall be solely for recruitment purpose.\n\n\u00a0Website\u00a0\u00a0\u00a0 :\u00a0\u00a0\u00a0\u00a0\u00a0\u00a0 http://www.telford.com.hk/", "employment_types": ["Full Time"], "selling_points": [], "locations": ["Shatin Area"], "categories": ["Marketing / Public Relations", "Marketing - Brand / Product Management", "Marketing - Marketing Communication"], "post_time": "2022-01-15T03:00:01Z", "salary": {"currency": null, "max": null, "min": null, "period": null, "term": null}, "salary_visible": false, "title_keywords": ["marketing officer"], "responsibilities": ["control", "marketing strategies", "budget", "coordinate with", "monitor", "develop", "marketing plan", "promotional activities", "forecast", "inventory controls"], "requirements": {"degrees": ["university degree"], "majors": ["marketing"], "languages": ["cantonese", "english"], "language_level": ["good command", "fluent"], "hard_skills": ["excel", "fmcg industry", "word", "powerpoint", "outlook"], "soft_skills": ["work effectively", "self-motivated", "communication and interpersonal skills", "negotiation skill", "team player", "creative"], "languages_combined": [{"language": "cantonese", "language_level": ["good command", "fluent"]}, {"language": "english", "language_level": ["good command", "fluent"]}]}, "experience_required": {"duration": ["3 years"], "field": ["marketing"]}}, {"job_id": "100003009054915", "location_code": "hk", "company": "DCH Auriga (Hong Kong) Limited", "job_title": "(Associate) Digital Marketing Manager", "description": "[Job Ref. No.: JD/SPE/MAR2021/01]\n\nFull Time University Graduate or\u00a0Equivalent (Any majors)\u00a0\u5168\u65e5\u5236\u5927\u5b78\u6216\u76f8\u7b49\u7a0b\u5ea6(\u4efb\u4f55\u5b78\u79d1)\u00a0\nMin 3 years solid experience in Purchasing in Sports Chains Store or Department Stores in Hong Kong\u00a0 \u4e09\u5e74\u4ee5\u4e0a\u5728\u9999\u6e2f\u6709\u95dc\u904b\u52d5\u7528\u54c1\u9023\u9396\u5e97\u6216\u767e\u8ca8\u516c\u53f8\u4e4b\u63a1\u8cfc\u7d93\u9a57\nCo-ordinate the management of marketing / branding content \u5177\u7b56\u5283\u53ca\u7d71\u7c4c\u5e02\u5834\u71df\u92b7\u6216\u54c1\u724c\u7ba1\u7406\u4e4b\u7d93\u9a57\nExperience in Outdoor Activities \u5177\u91ce\u5916\u6d3b\u52d5\u7d93\u9a57\nFluent in spoken and written English and Chinese\u00a0\u826f\u597d\u4e2d\u82f1\u6587\u6703\u8a71\u53ca\u66f8\u5beb\u80fd\u529b\nGood Analytical skills in reporting \u826f\u597d\u5206\u6790\u6578\u64da\u80fd\u529b\nProficient in using Excel e.g. Pivot Table, V lookup etc. \u5b70\u6089\u904b\u7528Excel\u7a0b\u5f0f\nWilling to travel to USA / Europe / Japan\u00a0\u9700\u5f80\u7f8e\u00a0/\u00a0\u6b50\u00a0/\u00a0\u65e5\u516c\u5e79\n\n(Without any experience of product management in Hong Kong will\u00a0not be considered\u00a0\u7121\u9999\u6e2f\u5730\u5340\u4e4b\u7522\u54c1\u7ba1\u7406\u7d93\u9a57\u8005\u6055\u4e0d\u8003\u616e)\u00a0\n\n\u655d\u516c\u53f8\u53e6\u6709\u5176\u4ed6\u7a7a\u7f3a\u4f9b\u5177\u5099\u904b\u52d5\u7528\u54c1\u6279\u767c\u6216\u96f6\u552e\u65b9\u9762\u7d93\u9a57\u4eba\u58eb\u7533\u8acb\u3002\n\nInterested parties please click apply now (Please quote the Job Ref. No. in your application)\n\nPersonal data collected will be used for recruitment purpose.", "employment_types": ["Full Time"], "selling_points": [], "locations": ["Kwai Fong"], "categories": ["Marketing / Public Relations", "Marketing - Brand / Product Management", "Marketing - Marketing Communication", "Digital Marketing"], "post_time": "2022-01-17T13:49:21Z", "salary": {"currency": null, "max": null, "min": null, "period": "monthly", "term": null}, "salary_visible": false, "title_keywords": ["digital marketing manager", "associate"], "responsibilities": ["reporting", "management"], "requirements": {"degrees": ["university graduate"], "majors": [], "languages": ["english", "chinese"], "language_level": ["fluent"], "hard_skills": ["excel", "no", "pivot table", "analytical skills"], "soft_skills": ["analytical skills"], "languages_combined": [{"language": "english", "language_level": ["fluent"]}, {"language": "chinese", "language_level": ["fluent"]}]}, "experience_required": {"duration": ["min 3 years"], "field": ["purchasing", "product management"]}}, {"job_id": "100003009054139", "location_code": "hk", "company": "Tai Kwun", "job_title": "Senior Communications Officer  (1-year contract)", "description": "Specific Responsibilities\n\nMarket research on clients\u2019 and projects\u2019 pipelines \u2013 clients\u2019 budgets, timeframe, type of consultancy etc.\nArrange regular clients\u2019 meetings, arrange presentation materials and responsible for chasing follow-up actions\nExternal Connection to Institutions \u2013 Explore opportunity to share Professional Excellence to market\nManage Project sheets in centralized locations for bids\nSupport the work winning functions across APNA to achieve best-for-region outcomes\nCollaborating with the APNA Marketing and Communications Manager and the APNA Senior Communications Advisor, support brand & event activities and production of communications (internal and external) as required for Asia.\nAttend weekly (Monday) APNA Proposal scheduling meeting\nAttend weekly catchup with Marketing and Communications Manager and the APNA Senior Communications Advisor\nUpdate and maintain content for the APNA Win Site; maintaining and updating submission libraries, including identifying best-practice examples and projects, and maintaining and updating capability statements and other marketing presentations.\nUndertake coordination activities for the APNA region as required by the Regional Marketing and Communications Manager, Major Pursuits and Strategy Manager and Senior Communications Advisor.\nSupport the use and maintenance of APNA corporate intranet Compass.\n\nDesired skills and expertise\n\nA minimum of eight years\u2019 experience in marketing, submissions and/or communications\nDemonstrated ability to manage teams in the delivery of submissions or proposal documents\nExperience using Adobe InDesign\nExperience working in a fast-paced, deadline-driven environment\nExperience in development of communications and social media materials\nExperience in managing brand and event activities\nAbility to develop and maintain effective internal and external relationships, including outside of your home office\n\nQualifications and experience\n\nQualifications and/or experience in journalism, marketing or communications (or equivalent) are required.\n\nExperience in an engineering, construction or infrastructure environment will also be highly regarded. If successful in this role you\u2019ll be working on significant projects that shape the communities in which we live. You will build connections with our international colleagues and bring this knowledge to our clients and to their projects. There\u2019s no time like the present to make a change.\n\nWe offer competitive remuneration package including\u00a013th month salary, MPF plan\u00a0and\u00a0group medical insurance for dependents.\n\nInterested parties, please click 'Apply now' to submit your application with full resume including your current and expected salary, or send your full resume to recruitment.MMHK @mottmac.com .\n\nTo explore more opportunities with us, please visit www.mottmac.com/careers.\n\nAll personal data collected will be treated in strict confidence and be used for recruitment purpose only.\u00a0\n\nWe are an equal opportunity employer and value diversity at our company. We do not discriminate, and take positive steps to create an inclusive culture.", "employment_types": ["Full Time", "Temporary", "Contract"], "selling_points": ["Develop and implement PR and communications plan", "Plan and organize media events to promote TK brand", "Handle daily media activities and operations"], "locations": ["Central"], "categories": ["Marketing / Public Relations", "Marketing - Brand / Product Management", "Marketing - Marketing Communication", "Public Relations - Event Management"], "post_time": "2022-01-17T08:32:15Z", "salary": {"currency": null, "max": null, "min": null, "period": "monthly", "term": null}, "salary_visible": false, "title_keywords": ["senior communications officer"], "responsibilities": ["budgets", "social media", "maintaining", "maintenance", "infrastructure", "teams", "market research", "presentations", "develop", "scheduling", "maintain", "coordination"], "requirements": {"degrees": [], "majors": [], "languages": [], "language_level": [], "hard_skills": ["no", "maintenance", "pipelines", "adobe indesign", "presentations", "make", "compass"], "soft_skills": ["coordination", "driven", "presentation", "responsible"], "languages_combined": []}, "experience_required": {"duration": ["minimum of eight years"], "field": ["social media", "brand", "engineering", "development", "infrastructure", "marketing", "construction"]}}, {"job_id": "100003009053037", "location_code": "hk", "company": "Christian Alliance International School", "job_title": "Advancement Officer", "description": "Smart Charge, a new service brand run by HKT and CLP, aims to offer one-stop and hassle-free electric vehicle (EV) charging solutions for end-users and commercial entities in Hong Kong to meet the increasing market demand.\u00a0\n\nIt is a challenging and dynamic opportunity for an all rounded marketer to work for this brand which is striving for differentiation and continual growth.\u00a0\n\nYour role:\n\nExplore partnership opportunities / initiatives and manage day-to-day partnership operations and logistics;\nNurture long term relationships with key strategic partners to foster consistent support to Smart Living products via joint promotions or events, including lead generation events and external corporate events;\nBuild and manage scalable partnership programs to drive broad adoption of Smart Charge products and services;\nCollaborate with various internal and external parties for planning and executing marketing campaigns, including the planning and execution of operation logistic , advertising and communication tools from concept to implementation;\nEnsure marketing messages are synchronized across different business units and monitor\u00a0 marketing campaigns to ensure communications are streamlined and aligned;\nStay informed of news and marketing activities in\u00a0 relevant markets.\u00a0\u00a0\n\nTo succeed in this role:\n\nUniversity graduate in Marketing, Communications, Business Administration or related disciplines;\nMinimum 8 years working experience in Product or Service Marketing and/or related field;\nProven track record of driving partnership strategy, preferably in luxury product industry, prestige members clubs and automotive industries;\nStrong business acumen with exceptional logical thinking, highly motivated and presentable\nDemonstrated initiative and problem solving skills with a service focus\nExcellent communication and interpersonal skills, with ability to work effectively and cross-functionally with people at all levels\nKnowledge or interest in automobile industry\nProficiency in both spoken and written English and Cantonese\nCandidates with more experience will be considered as Assistant Vice President\n\nIf you have the desire for an exciting and rewarding career, please send us your resume immediately, quoting the reference number, your present and expected salary via email to Human Resources.", "employment_types": ["Full Time", "Permanent"], "selling_points": ["Degree in event mgmt, marketing, communication, PR", "3 years\u2019 relevant work experience", "Strong written and verbal communication skills"], "locations": ["Lai Chi Kok"], "categories": ["Marketing / Public Relations", "Marketing - Brand / Product Management", "Marketing - Marketing Communication", "Public Relations - Event Management"], "post_time": "2022-01-17T05:18:20Z", "salary": {"currency": null, "max": null, "min": null, "period": "monthly", "term": null}, "salary_visible": false, "title_keywords": ["officer"], "responsibilities": ["collaborate with", "administration", "advertising", "operations", "internal and external parties", "monitor", "implementation", "communication", "logistics", "executing", "marketing campaigns", "communication tools", "planning"], "requirements": {"degrees": ["university graduate"], "majors": ["related disciplines", "marketing", "business administration", "communications"], "languages": ["cantonese", "english"], "language_level": ["proficiency"], "hard_skills": ["focus", "problem solving skills", "dynamic", "acumen"], "soft_skills": ["work effectively", "focus", "presentable", "communication", "dynamic", "motivated", "communication and interpersonal skills", "business acumen", "problem solving skills", "initiative"], "languages_combined": [{"language": "cantonese", "language_level": ["proficiency"]}, {"language": "english", "language_level": ["proficiency"]}]}, "experience_required": {"duration": ["minimum 8 years"], "field": ["related", "marketing"]}}, {"job_id": "100003009051529", "location_code": "hk", "company": "Ma Belle Jewellery Co Ltd", "job_title": "Senior Officer/ Officer - Branding/ Communications/ Marketing", "description": "Job Description\n\nDevelop and implement digital marketing programs which cover website development, SEO, SEM, social media strategy, content strategy for Greater China, Hong Kong\nManage social media properties (Facebook, Instagram, weibo, wechat, Xiaohongshu, Zhihu etc.), including daily monitoring, posting, and content development\nResponsible for different graphic design & artwork adaptation including poster, leaflets, banners etc\nProvide marketing supports to the team\nAny other ad hoc projects assigned by the Management\n\n\nRequirement\n\nDiploma or above in Journalism, Marketing, Communications, or related field\nAt least 1 year of relevant working experience\nA good team player while being able to work independently\nGood communication skills\nGood command of written and spoken Chinese, Mandarin & English\nKnowledge in Adobe Creative Suite. E.g. Adobe Creative Suite, e.g. Photoshop, illustrator, Dreamweaver, etc\nImmediate availability is highly preferred\nFresh graduates are welcome\n\nBenefit\n\nMedical insurance\nDental insurance\nDiscretionary bonus\nAttractive performance bonus\nFriendly and collaborative work environment\n\nWe offer competitive remuneration package and good prospects to the right candidates. Interested parties please send your full resume with expected salary to our email.\n\nFor more details, please visit our official website: https://hkfamily.com.hk/ and click ''Apply Now'' to join us now!\n\n*Data collected will be kept confidential and used solely for recruitment purposes only.", "employment_types": ["Full Time"], "selling_points": ["Senior Branding Officer/ Officer", "execute conventional & digital marketing campaign", "plan & execute  websites and social media platform"], "locations": ["Tin Hau"], "categories": ["Marketing / Public Relations", "Marketing - Brand / Product Management", "Marketing - Marketing Communication", "Public Relations - Copy-writing"], "post_time": "2022-01-16T08:08:08Z", "salary": {"currency": null, "max": null, "min": null, "period": null, "term": null}, "salary_visible": false, "title_keywords": ["senior officer", "officer"], "responsibilities": ["social media", "management", "seo", "digital marketing programs", "leaflets", "graphic design", "website", "develop", "banners", "ad hoc projects", "sem", "facebook", "daily monitoring"], "requirements": {"degrees": ["diploma or above"], "majors": ["journalism", "marketing", "communications"], "languages": ["english", "chinese", "mandarin"], "language_level": ["good command"], "hard_skills": ["dreamweaver", "illustrator", "adobe creative suite", "photoshop"], "soft_skills": ["communication skills", "good team player", "creative", "work independently"], "languages_combined": [{"language": "english", "language_level": ["good command"]}, {"language": "chinese", "language_level": ["good command"]}, {"language": "mandarin", "language_level": ["good command"]}]}, "experience_required": {"duration": ["at least 1 year"], "field": ["relevant working experience"]}}, {"job_id": "100003009052629", "location_code": "hk", "company": "La Rose Noire Limited", "job_title": "Assistant Sales Manager /Sr Sales Executive - Food Service (for premium pastry ingredient brands)", "description": "Requirements:\n\nDiploma / Associate Degree/ Degree in IT / Web / Graphic / Multimedia Design or related disciplines, better with e-commerce knowledge.\nHands-on experience in Adobe AI and Photoshop proficiently.\nFamiliar with social platforms like: Facebook, Instagram, Wechat and TikTok etc. with strategical mindset.\n\nResponsibilities:\n\nPlanning, designing and executing marketing strategies and create product catalogs.\nResponsible for social platform content (copywriting, photos and videos) via Facebook, Instagram, Wechat and TikTok etc.\nGood at data collection, self-solving ability, able to w\nWork independently.\nExperience in editing videos, familiar with social media advertising and operation is a plus.\u00a0\n\nWe offered benefits to staff:\n\nMedical Insurance\nAnnual Leave\n5-days work\nBank holidays\nDouble Pay\nPerformance bonus\nStaff discount\u00a0\n\nInterested parties please send us your full resume, expected salary and applied position to HR Dept. through APPLY NOW\u00a0\n\nAll information collected is for recruitment purpose only.", "employment_types": ["Full Time", "Permanent"], "selling_points": [], "locations": ["Kowloon Bay"], "categories": ["Hospitality / F & B", "Food & Beverage", "Marketing / Public Relations", "Marketing - Brand / Product Management", "Sales, CS & Business Devpt", "Account Servicing"], "post_time": "2022-01-17T03:36:05Z", "salary": {"currency": null, "max": null, "min": null, "period": "monthly", "term": null}, "salary_visible": false, "title_keywords": ["assistant sales manager", "sales executive"], "responsibilities": ["social media", "marketing strategies", "advertising", "executing", "data collection", "designing", "facebook", "editing", "planning"], "requirements": {"degrees": ["associate degree", "diploma", "degree"], "majors": ["multimedia design", "related disciplines", "it", "e-commerce"], "languages": [], "language_level": [], "hard_skills": ["web", "ai", "e-commerce", "wechat", "adobe", "multimedia", "facebook", "photoshop"], "soft_skills": ["hands-on"], "languages_combined": []}, "experience_required": {"duration": [], "field": []}}, {"job_id": "100003009054531", "location_code": "hk", "company": "Kantar Hong Kong Limited", "job_title": "Research Associate/ Research Executive (Quantitative)", "description": "JEEVES, the Prestigious UK Dry Cleaning franchise is currently looking for a suitable candidate:\n\n\n\nMarketing Executive\u00a0\n\nResponsibilities:\u00a0\n\nAssist in marketing campaigns, promotions and product launches\nDevelop, implement and promote marketing projects to maintain brand image and brand guidelines\nSupport corporate website and mobile app maintenance\nManagement of various digital channels, e.g. eDM, Facebook, Instagram, Linkedin and Youtube\nAct as the main communicator via our social media channels to our audience\nWork closely with the frontline staff and gain customer insight\nOrganise and update in-store display regularly\nVideo and photo-taking for social media content\nLiaise with charities\nLiaise with customer service department as well as sales departments\nFollow up with social media based clients on a regular basis\nWork directly with the head of the team to ensure all necessary promotions, co-events and other relevant news is shared and updated regularly\nMaintain corporate partnerships and co-marketing relationships with new and existing partners\u00a0\n\nRequirements:\u00a0\n\nDegree is prefered\nHolder in Marketing or Brand Management degree preferred\nExcellent written and verbal skills in English and Chinese\nProficiency in Adobe Creative Cloud, e.g. Illustrator and Photoshop. Web design and programming is definitely an advantage\nMust be able to create content with guidance from head of marketing\nGood communications and interpersonal skills\nAble to work independently at times\nMust have good multitasking skills\nMust travel to our retail shops frequently\nAble to travel to meet clients & potential partners in Hong Kong\u00a0\n\nBenefits:\u00a0\n\nBirthday Leave\nPerformance-based bonus\nStaff healthcare\u00a0\nStaff insurance\nStarting 12 days paid annual leave\nLunch provided Monday \u2013 Friday\nPotential for managerial position\u00a0\n\nWebsite:\u00a0http://www.jeeves.com.hk\u00a0\n\nIf you consider yourself as an excellent multi-tasker with outstanding task management, please send a full resume with expected salary and availability by clicking \u201cApply Now\u201d for interview.\n\n\u00a0Personal data will be used for recruitment purpose only.", "employment_types": ["Full Time"], "selling_points": ["Quantitative Research", "Exposure to global leading brands", "Create impact by solving exciting problems"], "locations": ["North Point"], "categories": ["Marketing / Public Relations", "Marketing - Brand / Product Management", "Marketing - General / Support", "Marketing - Market Research"], "post_time": "2022-01-17T16:21:06Z", "salary": {"currency": null, "max": null, "min": null, "period": "monthly", "term": null}, "salary_visible": false, "title_keywords": ["research associate", "executive"], "responsibilities": ["social media", "management", "mobile app", "maintenance", "edm", "marketing projects", "website", "develop", "maintain", "brand guidelines", "social media content", "marketing campaigns", "customer service", "liaise with", "facebook"], "requirements": {"degrees": ["degree"], "majors": ["marketing"], "languages": ["english", "chinese"], "language_level": ["excellent"], "hard_skills": ["web design", "illustrator", "adobe", "programming", "photoshop"], "soft_skills": ["work independently", "creative", "interpersonal skills"], "languages_combined": [{"language": "english", "language_level": ["excellent"]}, {"language": "chinese", "language_level": ["excellent"]}]}, "experience_required": {"duration": [], "field": []}}, {"job_id": "100003009056065", "location_code": "hk", "company": "ConnectedGroup Limited", "job_title": "APAC Market Lead (Sports Brand 40K)", "description": "You will be responsible for:\n\nAssist line manager to set digital and eCME platform to help drive diseases medical education and business grows. Work on the action plans to achieve goals on business.\nWork closely with multi-departments to plan & execute digital transformation projects to reach business goals.\nAlign and execute social media plans from planning to execution, in compliant with brand communication goals and guidelines.\nPlan and execute all digital marketing, including SEO/SEM, display advertising, display remarketing and paid media to increase top of funnel lead creation\nResponsible for ATL/ BTL campaign communication strategy design and landing\nSource, identify and build sustainable partnership with social / digital platforms, KOL, associations and brand advocates in a holistic digital marketing management.\nActively track, measure the effectiveness of digital media efficiency, monitor investment ROI towards paid social clients, and take learning for future plan optimization.\nRegularly monitor social media trends, market insights, explore new digital media platform and tools, and competitor information acquirement.\nExecute branding marketing plan and drive brand growth for assigned brands\nSupport on the development of portfolio budgets, brand plans and manage the spending\nImplement the brand building activities. Maintain brand standards with clear brand positioning\nBuilds collaborative relationships with internal stakeholders & external stakeholders to reach digital marketing strategic goals.\n\n\u00a0You should have:\n\nBS/MS degree in marketing or a healthcare science.\nFamiliar or with high interest in digital marketing, understand the love of internet and mobile internet, and have a certain understanding of brand positioning and marketing.\nHave good planning ability, communication and coordination ability, excellent execution ability, strong sense of responsibility and team spirit.\nSelf-motivated, passionate with the ability to work independently and as part of a team\nClose alignments with business analysts and business stakeholder for maximizing content for customers\nKPI-related mindset with excellent transparent value-driven and sustainable processes\nData analytics platforms and good understanding of technical infrastructures in general.\nGood communication skill both English and Mandarin.\nPreferable with at least one year of digital marketing experience of healthcare products\u00a0\u00a0\n\nAll applications received will be used exclusively for recruitment purposes only. Applicants who are not contacted within 8 weeks should consider their application unsuccessful for the position advertised. Data supplied by applicants will be kept for 6 months", "employment_types": ["Full Time", "Permanent"], "selling_points": ["manage marketing plan", "calendar and execution", "consumer activations"], "locations": ["Not Specified"], "categories": ["Marketing / Public Relations", "Management", "Marketing - Brand / Product Management", "Marketing - General / Support"], "post_time": "2022-01-18T03:14:44Z", "salary": {"currency": null, "max": null, "min": null, "period": "monthly", "term": null}, "salary_visible": false, "title_keywords": ["lead"], "responsibilities": ["business goals", "data", "design", "communication", "maintain", "plan", "plans", "advertising", "monitor", "bs", "marketing plan", "social media", "management", "seo", "digital marketing", "budgets", "guidelines", "recruitment", "sem", "coordination", "planning"], "requirements": {"degrees": ["degree"], "majors": ["science", "marketing"], "languages": ["english", "mandarin"], "language_level": ["good"], "hard_skills": ["mobile", "seo", "sem", "data analytics"], "soft_skills": ["passionate", "self-motivated", "team spirit", "work independently", "responsible", "sense of responsibility", "communication skill", "collaborative", "communication", "clear", "learning", "coordination", "driven"], "languages_combined": [{"language": "english", "language_level": ["good"]}, {"language": "mandarin", "language_level": ["good"]}]}, "experience_required": {"duration": ["at least one year"], "field": ["healthcare", "digital marketing"]}}, {"job_id": "100003009056050", "location_code": "hk", "company": "Chandler Macleod Group (HK) Limited", "job_title": "HR Officer (Branding & Communication)", "description": "Your role:\n\nResponsible for Computer Room Facilities (CRF) & Cabling product management and marketing;\nManage product lines\u2019 revenue and profitability, \u00a0prepare business case and implementation plan for products/services offerings.\nWork closely with sales team to manage sales opportunities, co-ordinate with \u00a0pre-sales and engineering team to prepare pricing and technical proposal.\nResponsible for product and vendor / partner sourcing and liaison to stay leadership in the market.\nKeep abreast of latest market and technology trend in order to enrich products portfolio\nDevelop mechanism to collect feedback from customers in order to enhance solution offering\n\n\u00a0To succeed in this role:\n\nBachelor degree holder of Business, Engineering or related disciplines\nMinimum 5 years of product management and sales / marketing experience\nExperience in Cabling and CRF solution and projects; having product and industry knowledge in Data Centre Management / Structural Cabling / project management will be an advantage\nSelf-initiated, highly motivated, meticulous and result-oriented\nGood negotiation, interpersonal and presentation skills\nGood command of both spoken and written Chinese and English", "employment_types": ["Full Time", "Permanent"], "selling_points": ["Sizable and stable corporation", "Transformation and engagement", "Attractive remuneration package"], "locations": ["Not Specified"], "categories": ["Admin & HR", "HR Director / Manager", "Marketing / Public Relations", "Marketing - Brand / Product Management"], "post_time": "2022-01-18T03:13:39Z", "salary": {"currency": null, "max": null, "min": null, "period": "monthly", "term": null}, "salary_visible": false, "title_keywords": ["hr officer"], "responsibilities": ["management", "data", "co-ordinate with", "implementation", "develop", "project management", "sales team", "plan"], "requirements": {"degrees": ["bachelor degree holder"], "majors": ["related disciplines", "business", "engineering"], "languages": ["english", "chinese"], "language_level": ["good command"], "hard_skills": ["project management", "vendor"], "soft_skills": ["meticulous", "negotiation", "responsible", "project management", "presentation skills", "motivated", "interpersonal", "leadership", "result-oriented"], "languages_combined": [{"language": "english", "language_level": ["good command"]}, {"language": "chinese", "language_level": ["good command"]}]}, "experience_required": {"duration": ["minimum 5 years"], "field": ["product management", "marketing"]}}, {"job_id": "100003009056373", "location_code": "hk", "company": "China Mobile Hong Kong \u4e2d\u570b\u79fb\u52d5\u9999\u6e2f", "job_title": "Product Officer (RCS Products)", "description": "Reporting to the Assistant Marketing Manager, you will\nDevelop and implement PR and communications plan and strategies for Tai Kwun\u2019s brand and programme offerings to strengthen the brand as a centre for heritage and arts\nPlan and organize media events to promote Tai Kwun\u2019s brand that incorporate Tai Kwun\u2019s programme offerings\nDevelop publicity-related content such as key messages, press releases, publicity plans, and other related material as needed\nBuild a constructive working relationship with the local and international media and KOL; pitch thematic and event-based stories to generate positive coverage for Tai Kwun at both brand and programme levels\nHandle daily media activities and operations, including enquiries, photo/video shoot, press release distribution and maintaining press contact lists\nMonitor media coverage and prepare monthly clipping and evaluation reports\n\u00a0\nYou should have/be\nDegree in Communications, Marketing or related disciplines\n5 years\u2019 experience in marketing and communications field with commercial/non-commercial sectors, preferably in arts and culture, and communications industries\nPrevious exposure in PR agencies is highly preferred\nExcellent command of written and spoken English and Cantonese. Putonghua is a plus\nCan-do attitude, good team spirit with excellent execution and planning skill, details oriented and multi-tasking ability. Hands-on experience in translating concepts into actions\nKeen interests in heritage, art and cultural related projects. Curious about the new and creative marketing initiatives around the city and the globe\nA fast learner with strong business acumen and flexible in working long hours at times or during weekends\nInterested parties, please click \"Apply Now\" to submit your application.\n\nPersonal data collected will be used for recruitment purpose only.", "employment_types": ["Full Time", "Permanent"], "selling_points": ["Product Management", "RCS", "3 years of experience"], "locations": ["Kwai Hing"], "categories": ["Information Technology (IT)", "Product Management / Business Analyst", "Marketing / Public Relations", "Marketing - Brand / Product Management", "Marketing - General / Support"], "post_time": "2022-01-18T04:06:00Z", "salary": {"currency": null, "max": null, "min": null, "period": null, "term": null}, "salary_visible": false, "title_keywords": ["officer"], "responsibilities": ["reporting", "maintaining", "operations", "monitor", "develop", "reports", "contact", "plan", "evaluation", "plans", "planning"], "requirements": {"degrees": ["degree"], "majors": ["related disciplines", "marketing", "communications"], "languages": ["cantonese", "putonghua", "english"], "language_level": ["excellent"], "hard_skills": ["plus", "acumen"], "soft_skills": ["flexible", "team spirit", "can-do attitude", "keen", "multi-tasking", "hands-on", "business acumen", "creative", "fast learner", "constructive", "positive"], "languages_combined": [{"language": "cantonese", "language_level": ["excellent"]}, {"language": "putonghua", "language_level": []}, {"language": "english", "language_level": ["excellent"]}]}, "experience_required": {"duration": ["5 years"], "field": ["commercial", "marketing"]}}, {"job_id": "100003009055695", "location_code": "hk", "company": "Hong Kong-Shenzhen Innovation and Technology Park Limited", "job_title": "Associate Director, Marketing & Communications", "description": "(Reference number: S_ATO_95_JB)\n\nJob duties:\n\nCoordinate with the Admissions and Advancement team in executing of all the marketing and fundraising campaign events and reporting preparation, including but not limited to the following: sourcing, drafting publication material, promotion, photo shooting, budgeting and administration\u00a0\nAssist Admissions and Advancement team in cultivating relations within and outside the school community, including but not limited to staff, parents, students and alumni\nMarket the school\u2019s brand and shape the way we connect with our targeted audience via phone, email, in person and other means\nAttend key school functions; prepare, write and post any news copy and social media coverage of the event\nSupport the school in preparing presentations for different marketing events as needed\nUpdate and maintain the school\u2019s website and other publications\nCollect data and maintain a systemic database for analysis\nCoordinate with outside agencies to produce marketing material\nProviding general administrative support as required\nPerform any other duties as assigned by supervisors or management\nBe able to manage ad-hoc projects\n\nJob Requirements:\n\nA recognized degree, preferred in event management, marketing, communications and public relations or related discipline preferably with 3 years\u2019 relevant work experience\nExperience in planning projects from ground work to results delivery in the educational institution, non-profit organization, charitable organization would be an advantage\nHigh proficiency in English. Strong written and verbal communication skills are necessary. Fluency in Mandarin would be an advantage\nArticulate, presentable and possess strong interpersonal skills in order to represent the school\u2019s mission and vision\nSelf-motivated with good analytical skill and be able to work under pressure\nAbility to work effectively independently and as a team member\nDesire to work in a fast-paced environment with the ability to multi task and manage time effectively\nProficient computer skills with experience in MS Word, Excel, Power Point, Adobe Illustrator, Photoshop and InDesign\n\nApplication Details\n\nInterested parties please apply with full resume stating current and expected salary by clicking \u201cApply Now\u201d or email to the Human Resources Department via our employment webpage at\u00a0www.caisbv.edu.hk.\n\nPlease quote the reference number of the post in your application.\n\nAll personal data submitted will be used for recruitment purposes only and all related information will be kept for up to 24 months.", "employment_types": ["Permanent"], "selling_points": [], "locations": ["Shatin Area"], "categories": ["Marketing / Public Relations", "Marketing - Brand / Product Management", "Marketing - General / Support", "Marketing - Marketing Communication"], "post_time": "2022-01-18T02:51:37Z", "salary": {"currency": null, "max": null, "min": null, "period": "monthly", "term": null}, "salary_visible": false, "title_keywords": ["associate director"], "responsibilities": ["any other duties", "data", "budgeting", "website", "maintain", "database", "ad-hoc projects", "administration", "presentations", "marketing material", "publication", "reporting", "social media", "management", "general administrative support", "coordinate with", "executing", "marketing events", "analysis"], "requirements": {"degrees": ["degree"], "majors": ["marketing", "communications"], "languages": ["english", "mandarin"], "language_level": ["fluency", "advantage", "proficiency"], "hard_skills": ["excel", "analytical skill", "indesign", "adobe illustrator", "computer skills", "photoshop", "power point", "ms word"], "soft_skills": ["work effectively", "communication skills", "self-motivated", "analytical skill", "independently", "fast-paced environment", "presentable", "interpersonal skills", "articulate", "team member", "work under pressure"], "languages_combined": [{"language": "english", "language_level": ["proficiency"]}, {"language": "mandarin", "language_level": ["fluency", "advantage"]}]}, "experience_required": {"duration": ["3 years"], "field": ["management", "public relations", "related", "marketing", "planning"]}}, {"job_id": "100003009055892", "location_code": "hk", "company": "Michael Page", "job_title": "APAC Marketing Manager - Luxury Retailer", "description": "CHINA MOBILE HONG KONG COMPANY LIMITED (\"CMHK\") is the wholly-owned subsidiary of China Mobile Limited (HKEx: 941) (NYSE: CHL), which ranks 65th on the Fortune Global 500.\n\nOur company strives to offer superior service experience and to become the preferable digital partner for customers. We are preserving an environment with trust, responsibility and caring. At CMHK, we commit to maximizing people\u2019s potential and paving the way toward success for every striver. We are now inviting high caliber professional to join us.\n\n\u00a0Division: Enterprise Product Centre\n\n\u00a0In this position, you will:\n\nResponsible for the daily operation of 5G RCS product, such as market analysis, budget plan, marketing materials, etc\nWork closely with both internal and external parties on RCS product development and operation\nOther ad-hoc duties as required\n\nTo be successful in this position, you should meet the following requirements:\n\nBachelor Degree or above in Telecommunication, Network, Business Administration or related disciplines\nAt least\u00a03 years\u2019 working experience in telecommunications industry\nDemonstrated skills in relationship building and relationship management\nProficient in MS Office, especially Excel data analysis\nExcellent written and verbal communication skills in both English and Chinese (Mandarin and Cantonese)\n\nWhen you work:\n\n5\u00a0days work\n8 hours/day\n\nWhat you enjoy:\n\nDouble pay\nDiscretionary Performance bonus\nLife insurance\nMedical insurance\nEducation subsidies\nBirthday gift\nMarriage leave\nBirthday leave\nStaff discount\n\nCMHK is committed to be an equal opportunity employer. We offer exceptional benefits package and the opportunity to work in a challenging environment. Personal data provided by applicants will be treated strictly in accordance with our personal data policy and for recruitment purposes only.\n\nPlease submit your application to us by clicking the APPLY NOW button and send your full resume with your availability, current and expected salary to us.\u00a0\n", "employment_types": ["Full Time", "Permanent"], "selling_points": ["Luxury Retailer", "Regional Exposure", "International Working Environment"], "locations": ["Not Specified"], "categories": ["Marketing / Public Relations", "Marketing - Brand / Product Management", "Marketing - Marketing Communication", "Digital Marketing"], "post_time": "2022-01-18T03:03:28Z", "salary": {"currency": null, "max": null, "min": null, "period": "monthly", "term": null}, "salary_visible": false, "title_keywords": ["marketing manager"], "responsibilities": ["management", "budget", "daily operation", "internal and external parties", "data analysis", "communication", "market analysis", "plan", "ad-hoc duties", "marketing materials", "insurance", "administration"], "requirements": {"degrees": ["degree or above", "bachelor"], "majors": ["related disciplines", "business administration"], "languages": ["cantonese", "english", "chinese", "mandarin"], "language_level": ["excellent"], "hard_skills": ["mobile", "analysis", "excel", "ms office"], "soft_skills": ["communication skills", "responsible", "committed", "ad-hoc duties", "superior"], "languages_combined": [{"language": "cantonese", "language_level": ["excellent"]}, {"language": "english", "language_level": ["excellent"]}, {"language": "chinese", "language_level": ["excellent"]}, {"language": "mandarin", "language_level": ["excellent"]}]}, "experience_required": {"duration": ["at least 3 years"], "field": ["telecommunications", "digital"]}}, {"job_id": "100003009048669", "location_code": "hk", "company": "S.F. Express (Hong Kong) Limited", "job_title": "Product Management Executive", "description": "Our client is engaged in the selling of wellness products and is looking for a seasoned Marketing professional to lead a team to drive the business forward\n\nKey Responsibilities\u00a0\n\nManage a team and to formulate marketing strategies to support the firm\u2019s future business growth\nDevelop marketing strategies to promote the firm\u2019s product and brand\nPrepare budgets and forecasts and assist in the development of new initiatives\nDrive monthly, quarterly, and annual promotion and campaign strategy\nSet project priorities, define and rollout market\u2019s marketing plans and provide strategic leadership\nCreation of compelling propositions that are segment and industry-relevant and highlight the company's points of differentiation\nIdentify market-specific growth opportunities and evaluate progress towards goals and timelines\nEnhance, monitor, and evaluate existing marketing initiatives and results\nPerform data analysis on market, competitors, and customer to establish marketing direction\nConduct review and evaluate marketing programs from time to time and make recommendations on program modifications, where necessary\n\n\u00a0Key Requirements:\u00a0\u00a0\n\nBachelor degree in business management, marketing or related disciplines\n\nSolid 8-12 years experience in marketing & communication with a multinational company\nFamiliar with MLM Marketing / Beauty/Health Care/Pharmaceutical Marketing\nProven track record of successfully developing and executing integrated marketing initiatives, particularly promotions/campaigns\nDemonstrates business plan development skills and experience including competitive analysis, SWAT analysis, value proposition, break-even analysis, forecasting, etc.\nStrong data analysis, reporting, research, and problem-solving skills\n\nInterested parties please send your application\u00a0with full career history, current and expected salary by\u00a0clicking\u00a0Apply Now\u00a0button below. Applications will be treated in strict confidence. Personal data collected will be used for recruitment purposes only.", "employment_types": ["Full Time", "Permanent"], "selling_points": ["New products idea generation and market research", "Plan product launching activities", "Sound product development experience"], "locations": ["Tsing Yi"], "categories": ["Marketing / Public Relations", "Marketing - Brand / Product Management", "Marketing - General / Support", "Marketing - Market Research"], "post_time": "2022-01-14T07:00:18Z", "salary": {"currency": null, "max": null, "min": null, "period": "monthly", "term": null}, "salary_visible": false, "title_keywords": ["executive"], "responsibilities": ["make recommendations", "budgets", "marketing strategies", "marketing plans", "review", "monitor", "develop", "evaluate", "data analysis"], "requirements": {"degrees": ["degree", "bachelor"], "majors": ["related disciplines", "business", "marketing"], "languages": [], "language_level": [], "hard_skills": ["business management", "problem-solving skills", "analysis"], "soft_skills": ["communication", "problem-solving skills"], "languages_combined": []}, "experience_required": {"duration": ["8-12 years"], "field": ["business", "development", "marketing", "multinational company"]}}, {"job_id": "100003009051402", "location_code": "hk", "company": "Raze Technology Limited", "job_title": "PR and Marketing Executive", "description": "REQUIREMENTS\n\nDiploma or above in marketing, communications or related disciplines\n2-3 years relevant experience, preferably in retail or digital marketing\nFamiliar with social media networks with online copywriting experience\nStrong knowledge in Google Ads and Google Analytics\nGood communication and presentation skill in English and Chinese\nProficient PC skills (e.g. MS office, Word, Excel, PowerPoint and Chinese Word Processing)\n\nRESPONSIBILITIES:\n\nResponsible for developing the marketing plan and strategy; compiling and monitoring the annual promotion and marketing budget plan;\n\nAssist the Operation team in formulating in-store marketing and promotional activities to drive sales & traffic;\nAlign with the company strategy and objectives, initiate and implement relevant social media platforms such as Website, Facebook & Instagram, etc;\nWork closely with various parties for planning and executing marketing campaigns, including organizing events, preparing sales materials, advertising and communication tools;\nDevelop monthly report and monitor the sales performance of marketing activities;\nExplore joint promotion opportunity with other parties;\nCarry out ad-hoc tasks as assigned by management.\n\nWe offer competitive package including 5-day work, public holiday & medical scheme together with career growth opportunities. Interested parties, please send full resume and expected salary and recent portfolio to Personnel & Administration Department.", "employment_types": ["Full Time", "Permanent"], "selling_points": [], "locations": ["Southern Area"], "categories": ["Marketing / Public Relations", "Marketing - Brand / Product Management", "Public Relations - General / Support", "Digital Marketing"], "post_time": "2022-01-15T14:33:53Z", "salary": {"currency": null, "max": null, "min": null, "period": "monthly", "term": null}, "salary_visible": false, "title_keywords": ["marketing executive"], "responsibilities": ["budget", "social media platforms", "website", "plan", "monthly report", "facebook", "advertising", "sales performance", "monitor", "developing", "develop", "marketing plan", "marketing campaigns", "management", "monitoring", "promotional activities", "executing", "drive sales", "ad-hoc tasks", "communication tools", "planning"], "requirements": {"degrees": ["diploma or above"], "majors": ["related disciplines", "marketing", "communications"], "languages": ["english", "chinese"], "language_level": ["good"], "hard_skills": ["presentation skill", "google analytics", "excel", "chinese word processing", "word", "powerpoint", "pc skills", "ms office"], "soft_skills": ["communication", "presentation skill"], "languages_combined": [{"language": "english", "language_level": ["good"]}, {"language": "chinese", "language_level": ["good"]}]}, "experience_required": {"duration": ["2-3 years"], "field": ["social media", "relevant experience", "digital marketing", "copywriting", "retail"]}}, {"job_id": "100003009055216", "location_code": "hk", "company": "Regent Lane Ltd", "job_title": "Assistant Marketing Manager & Merchandisers & Designers", "description": "Job Responsibilities:\n\nFormulate strategies for new products from idea generation, market research to product launch and implementation\nConduct comprehensive analysis of product performance to identify opportunities and challenges for growth and development\nPlan and drive product launching activities to achieve business targets\nEvaluate the product effectiveness in response to customers\u2019 feedback and follow up issues\nMonitor product development progress; coordinate with internal and external parties to ensure the deadlines are met\nPrepare regular reports and participate in ad hoc assignments\n\nRequirements:\n\nDiploma or above in marketing, logistics or related disciplines.\nAt least 1 year working experience, with experience of product development is a definite advantage.\nGood logical mind-set with excellent communication and project management skills, ability to handle multiple tasks and meet tight deadlines.\nProficient in MS PowerPoint, MS Excel and Chinese Word Processing.\nGood command of both written and spoken Chinese and English, knowledge in Putonghua is a plus.\u00a0\nImmediate candidate is highly preferred\nWe offer attractive remuneration package and fringe benefits to the suitable candidates. Interested parties, please submit your application to us. If you do not want to apply as a JobsDB member, you may send your full resume with your availability, current and expected salaries to recruit01 at sf-express.com\nYou are welcome to visit our website at\u00a0https://htm.sf-express.com/hk/tc/\u00a0for more information about us.\n\nCandidates who are not invited for an interview within 1-month may consider their applications unsuccessful.\nAll personal data provided by job applicants will be used only for recruitment purposes and will be treated strictly confidential. Unsuccessful applications will be retained for a maximum period of 24-month.", "employment_types": ["Full Time"], "selling_points": ["5 mins to MTR", "Attractive Benefits", "Marketing & Promotion Company"], "locations": ["Ngau Tau Kok"], "categories": ["Design", "Graphics", "Marketing / Public Relations", "Marketing - Brand / Product Management", "Merchandising & Purchasing", "Sundries"], "post_time": "2022-01-18T01:49:08Z", "salary": {"currency": null, "max": null, "min": null, "period": "monthly", "term": null}, "salary_visible": false, "title_keywords": ["assistant marketing manager"], "responsibilities": ["analysis", "internal and external parties", "monitor", "implementation", "market research", "coordinate with", "evaluate", "reports", "ad hoc assignments", "plan"], "requirements": {"degrees": ["diploma or above"], "majors": ["related disciplines", "marketing"], "languages": ["putonghua", "english", "chinese"], "language_level": ["good command", "proficient"], "hard_skills": ["plus", "chinese word processing", "project management", "ms excel", "ms powerpoint"], "soft_skills": ["communication", "project management skills", "meet tight deadlines", "handle multiple tasks"], "languages_combined": [{"language": "putonghua", "language_level": ["good command"]}, {"language": "english", "language_level": ["good command"]}, {"language": "chinese", "language_level": ["good command", "proficient"]}]}, "experience_required": {"duration": ["at least 1 year"], "field": ["product development"]}}, {"job_id": "100003009050115", "location_code": "hk", "company": "Swisso Beauty Expert", "job_title": "Marketing Manager / Director", "description": "The Role\nWe are looking for a creative, passionate and enthusiastic PR and Marketing Executive to join our team.\u00a0You will have a chance to work at a fast-paced mission driven company that brings material science to life and benefit the mass. We are bringing business disruption and new hygiene standard to the world with the introduction of new photocatalyst products and services. With the continuous R&D and business innovation, we are thrilled to develop the next generation technology that safeguards everyday life.\n\nResponsibilities\n\n\nAssist to plan, coordinate and implement marketing programs;\nDay-to-day management of media plans, reports and follow up on materials;\nProduce competitive analysis and reports for the relevant consumer and business sectors;\nSupport and work closely with the team on buying executions on a day-to-day basis;\nDevelop engaging, creative content for our social media & e-commerce platform (Including writing, editing and proofreading of the product description, social media feeds, advertising collaterals, SEO contents, etc.);\nAssist in marketing reports preparation and data analysis, gather insights in customer behavior and business trends to improve the performance and drive sales.\n\nRequirements\n\n\nUniversity degree holder in Marketing, Communications, Creative Media, Business or related disciplines;\n1-2 years relevant experience in FMCG/healthcare. Agency background is an advantage;\nProficiency in using Facebook, Instagram, WeChat, Weibo and others to build communities and enhance brand profile;\nStrong market sense and good creativity;\nPatient, pay attention to details and with good communication skills;\nGood command in both written and spoken English, Cantonese and Mandarin.\n\nWe offer the right candidate attractive remuneration package and outstanding prospects for career advancement and development.\u00a0 The right candidate will progress career in a forward thinking and dynamic business with exciting growth plans.\u00a0 If you are qualified and interested, please send your full resume with current & expected salary and availability by clicking \"APPLY\".\n\nAll information collected will be treated as strictly confidential and used for recruitment purposes only. (Only shortlisted candidates will be notified)", "employment_types": ["Full Time"], "selling_points": [], "locations": ["Tsim Sha Tsui"], "categories": ["Beauty Care / Health", "Others", "Marketing / Public Relations", "Marketing - Brand / Product Management", "Digital Marketing"], "post_time": "2022-01-16T21:50:24Z", "salary": {"currency": null, "max": null, "min": null, "period": "monthly", "term": null}, "salary_visible": false, "title_keywords": ["marketing manager", "director"], "responsibilities": ["drive sales", "social media", "advertising", "creative content", "seo", "editing", "analysis", "develop", "coordinate", "day-to-day management", "data analysis", "proofreading", "reports", "plan", "contents", "plans", "e-commerce platform"], "requirements": {"degrees": ["university degree"], "majors": ["creative media", "related disciplines", "business", "marketing", "communications"], "languages": ["cantonese", "english", "mandarin"], "language_level": ["good command"], "hard_skills": ["facebook", "wechat"], "soft_skills": ["communication skills", "attention to details", "patient", "strong market sense", "creative"], "languages_combined": [{"language": "cantonese", "language_level": ["good command"]}, {"language": "english", "language_level": ["good command"]}, {"language": "mandarin", "language_level": ["good command"]}]}, "experience_required": {"duration": ["1-2 years"], "field": ["healthcare", "fmcg", "relevant experience"]}}, {"job_id": "100003009055938", "location_code": "hk", "company": "OtterBox Hong Kong Limited", "job_title": "Social Media Specialist", "description": "\nJob Responsibilities\n\nTake the ownership of the marketing plan development, and create effective promotion strategies to drive interest and new leads in various channel\nManage the tactical execution of marketing campaigns, including sales offer, online/offline communication, digital content creation, video production, etc.\nLead the team to formulate extra sales channel for promotion, including joint promotion, loyalty program, MGM, KOL, etc\nOversee the implementation and budget of digital channel, including SEO/SEM, social media, etc\nUnderstand key marketing performance metrics and tracking tools to provide insights on channel strategies, forecast and competitor analysis\nIdentify the potential area based on CRM and sales analysis, in order to optimize the customer experience on every touchpoint\n\n\u00a0Job Requirement\n\nDegree holder in Business or Marketing or related disciplines\nOver 3 years Digital Marketing experience and proven experience within Social Media\nAt least 3 years work experience in beauty/skincare industry\nFamiliar with Performance Marketing like SEO / SEM, Web Analytics and Facebook ad.\nExperience in building Digital teams, KPI\u2019s processes\nStrong understanding for up-to-date marketing activities across the market\nExcellent planning and project management skills\nCreative, energetic, good interpersonal and communication skills\nExcellent command in English, Cantonese and Mandarin\nCandidate with less experienced will be considered as Assistant Marketing Manager", "employment_types": ["Full Time", "Permanent"], "selling_points": ["Generate high quality content development", "Create social assets", "Assist influencer campaign"], "locations": ["Hung Hom"], "categories": ["Marketing / Public Relations", "Marketing - Brand / Product Management", "Marketing - Marketing Communication", "Digital Marketing"], "post_time": "2022-01-18T03:06:32Z", "salary": {"currency": null, "max": null, "min": null, "period": "monthly", "term": null}, "salary_visible": false, "title_keywords": ["social media specialist"], "responsibilities": ["social media", "provide insights", "seo", "video production", "analysis", "budget", "implementation", "performance metrics", "communication", "marketing plan", "marketing campaigns", "sem", "forecast", "tracking"], "requirements": {"degrees": ["degree holder"], "majors": ["related disciplines", "business", "marketing"], "languages": ["cantonese", "english", "mandarin"], "language_level": ["excellent"], "hard_skills": ["seo", "project management", "sem", "web analytics", "facebook"], "soft_skills": ["communication skills", "creative", "project management skills", "web analytics", "energetic", "interpersonal"], "languages_combined": [{"language": "cantonese", "language_level": ["excellent"]}, {"language": "english", "language_level": ["excellent"]}, {"language": "mandarin", "language_level": ["excellent"]}]}, "experience_required": {"duration": ["3 years", "at least 3 years"], "field": ["social media", "digital marketing", "beauty", "digital"]}}, {"job_id": "100003009052821", "location_code": "hk", "company": "China Mobile Hong Kong \u4e2d\u570b\u79fb\u52d5\u9999\u6e2f", "job_title": "Senior Marketing Executive, Marketing planning (prepaid)", "description": "Sales and Marketing Executive\n\n- Develop and maintain client relationships\n- Organize and attend Jewellery Shows, both in Hong Kong and overseas\n- Collaborate with sales team to develop effective sales strategies\n- Conduct quotations and invoices\n\nRequirement:\n- At least 1 year of sales and marketing experience\n- Basic knowledge of jewellery products\n- Proficient in English writing and speaking\n- Independent, ambitious, can work under pressure\n- Proficient in PC and MS Office applications\n- Attractive remuneration package with 5-days work week, year-end bonus, commission upon reaching sales target\n\n\u92b7\u552e\u53ca\u71df\u92b7\n\n- \u7dad\u7e6b\u5ba2\u6236\u95dc\u4fc2\u548c\u64f4\u5c55\u92b7\u552e\u7248\u5716\n- \u7c4c\u5099\u4e26\u51fa\u5e2d\u9999\u6e2f\u53ca\u6d77\u5916\u73e0\u5bf6\u5c55\u89bd\n- \u8207\u92b7\u552e\u90e8\u540c\u4e8b\u5408\u4f5c\uff0c\u898f\u5283\u4e26\u767c\u5c55\u6709\u6548\u7684\u92b7\u552e\u7b56\u7565\n- \u6839\u64da\u7522\u54c1\u50f9\u683c\u5411\u5ba2\u6236\u767c\u55ae\u4e26\u8ddf\u9032\u00a0\n\n\u8981\u6c42\uff1a\n- \u6700\u5c111\u5e74\u6216\u4ee5\u4e0a\u92b7\u552e\u53ca\u71df\u92b7\u7d93\u9a57\n- \u57fa\u672c\u73e0\u5bf6\u7522\u54c1\u77e5\u8b58\n- \u6d41\u5229\u7684\u82f1\u6587\u8b80\u5beb\u53ca\u5c0d\u8a71\n- \u7368\u7acb\u3001\u6709\u4e0a\u9032\u5fc3\u3001\u5728\u9ad8\u58d3\u74b0\u5883\u4e0b\u4ecd\u7136\u4fdd\u6301\u5de5\u4f5c\u6c34\u6e96\n- \u719f\u6089\u96fb\u8166\u53ca MS Office \u57fa\u672c\u4f7f\u7528\u77e5\u8b58\u53ca\u6280\u80fd\n- \u512a\u8d8a\u5f85\u9047\uff0c5\u5929\u5de5\u4f5c\u5929\u3001\u5e74\u7d42\u82b1\u7d05\u3001\u96a8\u8868\u73fe\u767c\u653e\u4f63\u91d1\uff08\u53ef\u9762\u8ac7\uff09", "employment_types": ["Full Time", "Permanent"], "selling_points": ["14 AL, 5 days work week", "double pay, dis. performance bonus", "Staff SIM, Staff Offer"], "locations": ["Kwai Hing"], "categories": ["Marketing / Public Relations", "Management", "Marketing - Brand / Product Management", "Marketing - Direct Marketing"], "post_time": "2022-01-17T16:20:50Z", "salary": {"currency": null, "max": null, "min": null, "period": null, "term": null}, "salary_visible": false, "title_keywords": ["senior marketing executive"], "responsibilities": ["collaborate with", "year-end", "invoices", "sales target", "develop", "maintain", "sales team", "work under pressure"], "requirements": {"degrees": [], "majors": [], "languages": ["english"], "language_level": ["proficient"], "hard_skills": ["pc", "basic", "ms office"], "soft_skills": ["independent", "work under pressure"], "languages_combined": [{"language": "english", "language_level": ["proficient"]}]}, "experience_required": {"duration": ["at least 1 year"], "field": ["marketing"]}}, {"job_id": "100003009054994", "location_code": "hk", "company": "China Mobile Hong Kong \u4e2d\u570b\u79fb\u52d5\u9999\u6e2f", "job_title": "Assistant Marketing Manager, Quality Management", "description": "CHINA MOBILE HONG KONG COMPANY LIMITED (\"CMHK\") is the wholly-owned subsidiary of China Mobile Limited (HKEx: 941) (NYSE: CHL), which ranks\u00a065th on the Fortune Global 500.\n\nOur company strives to offer superior service experience and to become the preferable digital partner for customers. We are preserving an environment with trust, responsibility and caring. At CMHK, we commit to maximizing people\u2019s potential and paving the way toward success for every striver. We are now inviting high caliber professional to join us.\n\nDivision: Marketing\n\nIn this position, you will:\n\nTo explore the opportunities and provide recommendations/ insight of prepaid business.\nParticipate in the formulation of marketing strategy which is in line with company objectives\nSupport and provide report on customers\u2019 portfolio evaluation, behavior analysis, sales performance to develop appropriate marketing programs.\nWork with internal departments to formulate new products/ service/ offers roll-out campaigns.\nMonitor competitors; keep track on the market trend\nAssist in preparation of presentation materials, written reports and proposals\nOther ad hoc duties assigned by management\n\nTo be successful in this position, you should meet the following requirements:\n\nBachelor\u2019s degree in Business Administration, Marketing or equivalent disciplines\nMinimum 4 years of working experience\u00a0in consumer marketing / technology / Telecom industry\nExperience in implement end to end acquisition program, developing marketing plans and campaigns\nGood understanding in business operations\nGood coordination, project management, multitasking and presentation skills\nKnowledge in IT system is a plus\nSelf-motivated, attention to details, multi-tasking and able to work under pressure\nFluency in written and spoken English, Cantonese and Mandarin\nCandidate with less experience may consider as Marketing Executive\n\nWhen you work:\n\n5 days work\n8 hours/day\n\nWhat you enjoy:\n\nDouble pay\nDiscretionary Performance bonus\nLife insurance\nMedical insurance\nEducation subsidies\nBirthday gift\nMarriage leave\nBirthday leave\nStaff discount\n\nCMHK is committed to be an equal opportunity employer. We offer exceptional benefits package and the opportunity to work in a challenging environment. Personal data provided by applicants will be treated strictly in accordance with our personal data policy and for recruitment purposes only.\n\nPlease submit your application to us by clicking the APPLY NOW button and send your full resume with your availability, current and expected salary to us.", "employment_types": ["Full Time", "Permanent"], "selling_points": ["16 AL, Double pay, Dis. Performance bonus", "5 days work week", "Staff SIM, Staff offer"], "locations": ["Kwai Hing"], "categories": ["Information Technology (IT)", "Product Management / Business Analyst", "Marketing / Public Relations", "Marketing - Brand / Product Management", "Marketing - General / Support"], "post_time": "2022-01-17T16:22:50Z", "salary": {"currency": null, "max": null, "min": null, "period": null, "term": null}, "salary_visible": false, "title_keywords": ["assistant marketing manager"], "responsibilities": ["marketing plans", "operations", "evaluation", "administration", "ad hoc duties", "work under pressure", "sales performance", "monitor", "developing", "develop", "reports", "report", "management", "provide recommendations", "analysis", "preparation of presentation materials", "project management", "coordination", "insurance"], "requirements": {"degrees": ["degree", "bachelor"], "majors": ["marketing", "business administration"], "languages": ["cantonese", "english", "mandarin"], "language_level": ["fluency"], "hard_skills": ["mobile", "analysis", "project management", "plus"], "soft_skills": ["self-motivated", "work under pressure", "project management", "presentation skills", "multi-tasking", "committed", "coordination", "attention to details", "presentation", "superior"], "languages_combined": [{"language": "cantonese", "language_level": ["fluency"]}, {"language": "english", "language_level": ["fluency"]}, {"language": "mandarin", "language_level": ["fluency"]}]}, "experience_required": {"duration": ["minimum 4 years"], "field": ["digital", "marketing", "developing"]}}, {"job_id": "100003009051309", "location_code": "hk", "company": "Miramar Hotel and Investment Company, Limited", "job_title": "Assistant Marketing Manager \u2013 Hotels and Serviced Apartments", "description": "CHINA MOBILE HONG KONG COMPANY LIMITED\u00a0(\"CMHK\") is the wholly-owned subsidiary of China Mobile Limited (HKEx: 941) (NYSE: CHL), which ranks 65th on the Fortune Global 500.\n\nOur company strives to offer superior service experience and to become the preferable digital partner for customers. We are preserving an environment with trust, responsibility and caring. At CMHK, we commit to maximizing people\u2019s potential and paving the way toward success for every striver. We are now inviting high caliber professional to join us.\n\nDivision: Marketing\u00a0 / Home Business Operation Centre / Quality Management\n\nIn this position, you will:\n\nAnalyze complaints data for effective performance monitoring\n\nFormulate marketing policy for the Home Business Division and liaise internal parties for the implementation\nCoordinate and deliver marketing initiatives for different channels and segment to improve the conversion\n\u00a0Actively participate in the business process review to identify problems and drive for improvement\nMake recommendations and preventive actions to Management to improve customer experience and brand building\nPrepare Management and analysis reports on ad hoc and regular basis\nAssist Head of QM to design and implement the performance tracking system across the Company\n\n\u00a0To be successful in this position, you should meet the following requirements:\n\nBachelor's degree or above in Business, Information Technologies, Telecommunication or relevant discipline.\nAt least 5 years relevant customer journey/ customer management experience preferably in Telecommunication industry of which 2 years in supervisory position in fixed services or channel management\nKnowledge\u00a0and working experience in Quality Management/ Customer Service/ Sales Policy & Ordinance will be preferred.\nGood Interpersonal and communications skills.\nProcess management and Project management skills.\nStrong analytical, planning and problem solving skills.\nCustomer Centric and strong desire to work on solutions to exceed customer expectations.\nSelf-motivated and able to work independently and under pressure.\nExcellent written and verbal communication skills in both English and Chinese (Mandarin and Cantonese).\n\n\u00a0When you work:\n5\u00a0days work\n8 hours/day\n\nWhat you enjoy:\n\nDouble pay\nDiscretionary Performance bonus\nLife insurance\nMedical insurance\nEducation subsidies\nBirthday gift\nMarriage leave\nBirthday leave\nStaff discount\n\nCMHK is committed to be an equal opportunity employer. We offer exceptional benefits package and the opportunity to work in a challenging environment. Personal data provided by applicants will be treated strictly in accordance with our personal data policy and for recruitment purposes only.\n\n\n", "employment_types": ["Full Time", "Permanent"], "selling_points": [], "locations": ["Tsim Sha Tsui"], "categories": ["Hospitality / F & B", "Hospitality / Hotel Services", "Marketing / Public Relations", "Marketing - Brand / Product Management", "Public Relations - Event Management"], "post_time": "2022-01-15T07:56:09Z", "salary": {"currency": null, "max": null, "min": null, "period": "monthly", "term": null}, "salary_visible": false, "title_keywords": ["assistant marketing manager"], "responsibilities": ["liaise", "data", "analysis reports", "quality", "design", "communication", "business process", "customer service", "make recommendations", "ad hoc", "implementation", "management", "monitoring", "review", "tracking", "business operation", "coordinate", "project management", "insurance", "internal parties", "planning"], "requirements": {"degrees": ["degree or above", "bachelor"], "majors": ["business"], "languages": ["cantonese", "english", "chinese", "mandarin"], "language_level": ["excellent"], "hard_skills": ["analysis", "mobile", "make", "project management", "problem solving skills"], "soft_skills": ["make recommendations", "communication skills", "self-motivated", "work independently", "under pressure", "project management skills", "committed", "customer service", "problem solving skills", "interpersonal", "superior"], "languages_combined": [{"language": "cantonese", "language_level": ["excellent"]}, {"language": "english", "language_level": ["excellent"]}, {"language": "chinese", "language_level": ["excellent"]}, {"language": "mandarin", "language_level": ["excellent"]}]}, "experience_required": {"duration": ["2 years", "at least 5 years"], "field": ["management", "supervisory", "brand", "channel management", "customer service", "quality management", "digital"]}}, {"job_id": "100003009055905", "location_code": "hk", "company": "Baguio Green Group Limited", "job_title": "Plastic Recycling Site Manager", "description": "The Job\n\nAdminister revenue driven marketing campaigns with effective advertising/communications strategies to monitor relative results\nManage all the marketing collaterals content and production with relevant departments\nDevelop press release and media pitching, handle media enquiries and relations\nIdentify, explore and work with potential business partners for joint promotion/barter opportunities\nUpdate website and all information portals in timely manner\nHandle administrative works (e.g. issue PR, handle invoice, weekly clipping report etc.) and marketing budget monitoring\nThe Requirement\n\nDegree in Communications, Journalism, Languages, Hospitality or related disciplines\nAt least 4 years' relevant working experience in PR/communications field, experience in hospitality industry is an advantage\nProficient with MS office application\nExcellent command of both written and spoken Chinese and English, proficiency in Putonghua is an advantage\nGood presentation, excellent organizing and planning skills\nFlexible, independent and a good\u00a0team player\nAttractive remuneration would be offered to the right candidates.\n\nPlease send your application with expected salary to Human Resources Manager:\n\nBy WhatsApp: 6388-3034 or\nBy Fax: 2722-5555\n\nPersonal data collected will be used for recruitment purpose only. We are an equal opportunity employer.", "employment_types": ["Full Time", "Permanent"], "selling_points": ["Minimum 5-8 years' relevant experience", "Friendly working environment, Work life balance", "16+AL, 5-day work, Birthday Leave etc."], "locations": ["Lai Chi Kok"], "categories": ["Sales, CS & Business Devpt", "Business Development", "Management", "General Management", "Marketing / Public Relations", "Marketing - Brand / Product Management"], "post_time": "2022-01-18T03:04:28Z", "salary": {"currency": null, "max": null, "min": null, "period": "monthly", "term": null}, "salary_visible": false, "title_keywords": ["manager"], "responsibilities": ["advertising", "invoice", "marketing collaterals", "monitor", "website", "budget", "develop", "monitoring", "marketing campaigns", "report"], "requirements": {"degrees": ["degree"], "majors": ["journalism", "related disciplines", "hospitality", "communications"], "languages": ["putonghua", "english", "chinese"], "language_level": ["advantage", "excellent", "proficiency"], "hard_skills": ["whatsapp", "ms office"], "soft_skills": ["flexible", "planning skills", "good team player", "independent", "presentation"], "languages_combined": [{"language": "putonghua", "language_level": ["proficiency", "advantage", "excellent"]}, {"language": "english", "language_level": ["advantage", "excellent"]}, {"language": "chinese", "language_level": ["advantage", "excellent"]}]}, "experience_required": {"duration": ["at least 4 years"], "field": ["hospitality industry", "pr", "relevant working experience"]}}, {"job_id": "100003009056199", "location_code": "hk", "company": "ME Job Personnel Limited", "job_title": "Legal Office / Intellectual Property Officer", "description": "Responsibilities\n\nDrive sales to achieve company's assigned sales target;\nDevelop strategy and content for digital marketing & social media platforms across different markets and to evaluate effectiveness of different marketing campaigns;\nPerform sales analysis and gather market information for sales and marketing strategies' formulation;\nPlan & execute marketing activities for assigned product portfolio to increase brand awareness, expand customer base, engagement and achieve sales target;\nMonitor and maintain good relationship with existing distributors to maximize sales and profits;\nProactively develop new distribution channels to ensure continuous business growth and expand market coverage;\nManage internal designers & work closely with third parties for advertisements' production;\nMonitoring A&P expenditure & product budget;\nOrganize and support exhibitions, events & brand activities year-round\nSupport ad-hoc projects and marketing activities as assigned.\n\nRequirements\n\nUniversity degree holder in Marketing / Health Technology / Nutriology / Biology Chemistry or related discipline;\u00a0 candidate with science background is preferable\nExperience in digital marketing and social media marketing is a must\nCreative, detail oriented, outgoing and result-oriented with excellent interpersonal communication skill;\nProficiency in both spoken and written English and Chinese (Mandarin is an asset);\nAble to work under pressure with multi-tasking skill, willing to learn;\nHigh sense of responsibility, mature and self-initiative;\nExcellent PC skills;\n\nInterested parties please apply in full resume including current and expected salary by clicking\u00a0'Apply Now'.\u00a0To know more about\u00a0us, please visit our company website at\u00a0http://www.healthbank.com.hk.\n\nAll information received will be kept in strict confidence and only be used for employment-related purposes.", "employment_types": ["Full Time"], "selling_points": [], "locations": ["Central"], "categories": ["Professional Services", "Business Analysis / Data Analysis", "Legal & Compliance", "Marketing / Public Relations", "Marketing - Brand / Product Management"], "post_time": "2022-01-18T03:32:00Z", "salary": {"currency": null, "max": null, "min": null, "period": "monthly", "term": null}, "salary_visible": false, "title_keywords": ["property officer"], "responsibilities": ["market information", "marketing strategies", "advertisements", "sales target", "social media platforms", "analysis", "monitor", "monitoring", "develop", "evaluate", "maintain good relationship", "budget", "digital marketing", "marketing campaigns", "plan", "drive sales", "ad-hoc projects"], "requirements": {"degrees": ["university degree"], "majors": ["chemistry", "biology", "marketing"], "languages": ["english", "chinese", "mandarin"], "language_level": ["proficiency"], "hard_skills": ["pc skills"], "soft_skills": ["outgoing", "multi-tasking skill", "interpersonal", "detail oriented", "communication skill", "willing to learn", "high sense of responsibility", "mature", "self-initiative", "creative", "result-oriented", "work under pressure"], "languages_combined": [{"language": "english", "language_level": ["proficiency"]}, {"language": "chinese", "language_level": ["proficiency"]}, {"language": "mandarin", "language_level": []}]}, "experience_required": {"duration": [], "field": ["social media", "marketing", "digital marketing"]}}, {"job_id": "100003009054008", "location_code": "hk", "company": "The Marketing Store Worldwide (Asia) Ltd", "job_title": "Director, Brand Partnerships and Licensing, APMEA", "description": "SCOPE\n\nTo manage and direct the waste and recycling production line, maintenance, repair and improvement of all systems and plants relative to the physical well being and performance of the recycling and sorting factory, under the direction of General Manager and within the guideline of the Group.\n\nPRIMARY RESPONSIBILITIES\n\nTo ensure that all Group policies & procedures are followed and implemented accordingly.\nTo ensure that all local and national statutory regulations pertaining to recycling and sorting practices are adhered and compliance.\nExplore the use of smart technologies / AI to drive continuous improvement of each waste and plastic recycling site.\nTo ensure that all recycling machine are well adjusted, perform and to maximum the productivity.\nTo ensure effective communication between the management and the department and provide a professional, advisory, and executive support service to the General Manager to formulate strategic goals and plan for the production line.\nTo establish contact and good rapport with local authorities; fire bureau, health & hygiene, environment protection, Power plant, water supply, etc.\nTo establish and maintain good working relationships with local contractors who will provide repair and maintenance service, especially during the emergency breakdown of the system.\nTo determine and maintain organizational structure, job descriptions and standards & procedures for the department, and update and review annually. To plan and conduct on the job training, planning for the engineering long term training program.\nTo recruit, institute and develop training programs for all colleagues.\nTo facilitate and promote multitasking among colleagues.\nTo supervise, evaluate colleague\u2019s performance.\nTo prepare and manage a cost-effective operating budget to cover the cost of all maintenance, utilities within the financial parameters set down by the Group budget.\nMade a special capital budget recommendation to include all changes, replacement, and upgrade of equipment required\u3002\nTo develop, implement and maintain a work order system to address routine repairs. Work order procedures developed must address requesting work, reporting work, recording, assignment planning, scheduling, execution, follow up, communication/feedback of work done and historical record keeping.\nTo develop, implement and maintain a preventive maintenance program on all systems, plants, and various architectural features. Program to ensure operation of property is safe, effective and efficient.\nTo develop, implement and maintain energy conservation, tracking program to minimize utility expenses.\nTo regularly reviews and renegotiate as necessary all outside service contracts in areas of responsibility.\nTo maintains and updates all property records, technical drawings, manuals, administrative files, etc.\nTo perform other tasks and duties as assigned by management.\nconduct on-site orientation to new associate and responsible for staff training\n\nQUALIFICATIONS\n\n\nEducation:\n\n\nFormal education from technical institute, preferably with diploma or degree qualification in engineering/computerizing\n\n\n\u00a0Certification:\n\nHigher Diploma or Certificate holder in Building Services, Mechanical Engineering or Electrical Engineering or computerizing or equivalent.\n\nExperience:\n\nMin 8 years working experience in similar capacity, experience in PET recycling production line set up\n\nExperience in Recycling Plant/Factory set up\n\nExperience in plastic recycling\n\n\nExperience in Environment facilities industry\n\nOther:\n\n\nProficient in Microsoft Office Good command of written and spoken English and Chinese.\n\nProblem solving skills.\n\nManagement skills\n\nFor interested parties, please send your full resume with availability, current and expected salary to us. Data collected will be used for recruitment purpose only.", "employment_types": ["Full Time", "Permanent"], "selling_points": ["Solid background on entertainment and licensing", "Lead calendar planning within the region", "Work & align with Global Brand Partnership Team"], "locations": ["Kowloon Bay"], "categories": ["Marketing / Public Relations", "Management", "Marketing - Brand / Product Management", "Marketing - General / Support"], "post_time": "2022-01-17T08:01:56Z", "salary": {"currency": null, "max": null, "min": null, "period": "monthly", "term": null}, "salary_visible": false, "title_keywords": ["director"], "responsibilities": ["regulations", "budget", "executive support", "communication", "maintain", "technical drawings", "plan", "compliance", "expenses", "develop", "other tasks", "reporting", "management", "cost", "service contracts", "review", "procedures", "hygiene", "scheduling", "contact", "tracking", "maintenance", "policies", "systems", "evaluate", "repair", "working relationships", "planning"], "requirements": {"degrees": ["certificate", "diploma", "degree"], "majors": ["electrical engineering", "building services", "engineering", "mechanical engineering"], "languages": ["english", "chinese"], "language_level": ["good command", "proficient"], "hard_skills": ["maintenance", "microsoft office", "ai", "safe", "problem solving skills"], "soft_skills": ["efficient", "responsible", "organizational", "communication", "problem solving skills"], "languages_combined": [{"language": "english", "language_level": ["good command", "proficient"]}, {"language": "chinese", "language_level": ["good command", "proficient"]}]}, "experience_required": {"duration": ["min 8 years"], "field": []}}, {"job_id": "100003009053346", "location_code": "hk", "company": "Omnicom Media Group", "job_title": "Social Content Executive / Social Content Planner (Media & Advertising Field)", "description": "The Marketing Store Worldwide (TMS), a HAVI Company, is a Global Customer Engagement Agency and Sourcing Company, with areas of expertise that include consumer promotions, toys and premiums, shopper marketing, digital platforms and innovation. TMS now ranks among the largest toy manufacturers in the world.\u00a0\n\n\n\nWHAT IS THIS ROLE ABOUT\n\nThe Senior Director, Brand Partnerships and Licensing, APMEA is a key stakeholder of the Global Brand Partnership Team. With a solid background on entertainment and licensing, the Senior Director, Brand Partnerships and Licensing, APMEA will be in charge of successfully leading market Calendar Planning Process while continuously working with the Global Brand Partnership Team to ensure markets alignment with overall McDonald\u2019s Strategy and Business Goals.\n\nAreas of responsibilities include:\n\nLead communications with market\u2019s Happy Meal Client\nLead and develop markets calendar proposals.\nLead and develop industry insights for the market - while supporting global insights reports\nSupport the Global Brand Partnership team with market program performance insights\n\nJob Relationships:\n\nReports to: Vice President, Brand Partnerships\nRelationships and Communications:\u00a0Regular and ongoing interactions with TMS colleague in various agency departments such as: Global Brand Partnership Team, Planning/Strategy, Global Havi Analytics Team, Account Team and TMS counterparts in Asia/MEA/LATAM/Europe\n\nWHAT YOU\u2019LL BRING TO TMS\n\nYouth & Family Calendar Planning (Market)\n\nResponsible for leading all communications with market\u2019s Happy Meal Client.\nResponsible for leading and developing market\u2019s calendar planning recommendations.\nEarn and keep each clients\u2019 respect and confidence as a trusted advisor bringing continuous value to their business.\nAcquire and build-upon knowledge of and be conversant in clients\u2019 business \u2013 their key issues, competitive situation, and industry trends.\nDemonstrate confidence and authority as the day-to-day voice of the agency for assigned projects.\nDevelop and/or leads client presentations for all assigned work/execution.\nAssist in establishing thought leadership/POV specific to a project or initiative.\nParticipate in client meetings to provide a project perspective and input\nLicensing and Entertainment Industry Analytics (Market)\u00a0\nResponsible for tracking market\u2019s local trends: family\u2019s trends, consumer trends.\nResponsible for keeping clients updated on markets entertainment & licensing environment. Proactively develop local insights report to ensure TMS expertise across the globe.\nResponsible for developing markets post-trade show reports\nResponsible for tracking market\u2019s competitive landscape.\u00a0\n\nProgram Performance Analytics (Market)\u00a0\n\nResponsible for tracking market\u2019s program performance.\nSupport Global Brand Partnership team on Global Program Performance report by adding market\u2019s insights and pov.\u00a0\n\nGlobal Brand Partnership Team (Market)\u00a0\n\nDevelop and nurture the relationship with the Global Brand Partnership team by:\nUpdating the team on market\u2019s calendar planning needs\nParticipate from global meetings with recommendations and opportunities to keep expanding agency\u2019s global approach.\nSupport Global Team with markets insights on entertainment & licensing industry as part of the teams\u2019 efforts to provide global insights.\n\n\u00a0SKILLS AND EXPEREINCE WE\u2019D LIKE YOU TO HAVE\u00a0\n\nExperience of working in an integrated agency environment, client side or as a Marketing Manager, Family experience would be of benefit (but not essential)\nAble to lead by example, be solutions orientated with a continuous-learning approach\nEntrepreneurial spirit \u2013 taking and creating opportunities with clients and across the agency alike\nStrong strategic and critical thinking skills with demonstrable track record\nExcellent presentation skills (writing, reviewing and delivering) and ability to express ideas with clarity, confidence and logical reasoning\nAble to work well and prioritise under pressure\nProven ability to develop solutions that address client\u2019s business issues and opportunities\nYou thrive on taking ownership of your projects and deliver best-in-class executions\nSolid experience in an agency-side partnerships role, as either a seasoned Senior Partnerships Manager or Partnership Account Director\nMeticulous attention to detail and passion for understanding & following process. Ability to review and recommend on procedural efficiencies that will help us deliver for our client and partners.\nExperience analysing, synthesizing, and utilising data to make recommendations that drive engagement. Working with a data analyst to do so\nUnderstanding of the agency\u2019s philosophy and vision\nComputer skills (Proficient in Microsoft Word, Excel and PowerPoint + key email, schedule and internet applications, etc.)\nCompetent in accessing online databases and conducting Internet research\nWorks under frequent time pressures and distractions\u00a0\n\nInterested parties please send your full resume with present and expected salary by clicking \"Apply Now\". All personal data will be used for recruitment purpose only.\n\nOnly shortlisted candidates will be contacted.\u00a0\n\nWe are the Marketing Store and we would love to meet you!\u00a0", "employment_types": ["Full Time", "Permanent"], "selling_points": ["Free Shuttle Bus & Free Breakfast", "Birthday, Family Day & Self-Love Day Leave", "5-Day Work Week"], "locations": ["Pok Fu Lam"], "categories": ["Media & Advertising", "Account Servicing", "Marketing / Public Relations", "Marketing - Brand / Product Management", "Public Relations - Copy-writing"], "post_time": "2022-01-17T06:48:53Z", "salary": {"currency": null, "max": null, "min": null, "period": "monthly", "term": null}, "salary_visible": false, "title_keywords": ["executive"], "responsibilities": ["consumer trends", "make recommendations", "business goals", "communications with", "tracking", "ideas", "data", "planning process", "teams", "developing", "presentations", "develop", "review", "reports", "schedule", "databases", "report", "planning"], "requirements": {"degrees": [], "majors": [], "languages": [], "language_level": [], "hard_skills": ["excel", "microsoft word", "presentations", "powerpoint", "make", "computer skills", "databases"], "soft_skills": ["make recommendations", "meticulous", "confidence", "under pressure", "responsible", "passion for", "competent", "prioritise", "presentation skills", "learning", "attention to detail", "leadership", "initiative"], "languages_combined": []}, "experience_required": {"duration": [], "field": ["agency", "marketing"]}}, {"job_id": "100003009053300", "location_code": "hk", "company": "I Connect Company", "job_title": "Qualifying Tax Planning executive", "description": "Scope of Assignment\n\nYour role will be an important member of content team to work with OMG Hong Kong\u2019s clients on how to strategize, create, assess, disseminate, evaluate, and monitor content engagement; not just as an executioner but also a thinker able to take the creative ideas and turn them into something tangible to bring them to life, by using knowledge of platforms and audiences and deliver ideas to completion and engage brands for our clients.\n\nPreferably, you will have experience in managing content planning and execution with great project coordination skill and you are a people person as part of your role will be client management.\u00a0 At least 2 years working experience in advertising, social, creative or media agency will be vital, especially in FMCG brand.\n\nJob Responsibilities:\n\nAssist the Content Specialist in managing all aspects of clients\u2019 content platforms and implementing content strategy across all platforms, including content creation, posting and monitoring social community\nServe as liaison between the client and creative team to track the progression of campaigns\nProvide creative and engaging text, image and video content\nProject Manage and respond to comments and customer queries in a timely manner\nLiaise with various parties including clients and vendors for execution of ideas and quality control of deliverable.\nIdentify and communicate with key bloggers and influencers; experience with KOL management will be a big plus\nMock up preview of social post and copywriting for social post will be an added advantage\nCosting and budgeting campaign and deliverable.\n\nWorking Together\n\nEncourage creativity and inspirational team spirit to build and strengthen agency\u2019s creative culture within the agency.\nDemonstrate an infectious enthusiasm and good team spirit within agency\nand with clients\u2019 working team.\n\nOutward Facing\n\nEngaged with existing and potential clients through day to day interaction.\nTreat client business as you would your own, focusing on results\nTo gain trust and respect from the clients.\nLeads all influencer projects, executing partnerships from outreach\nTo creative deliverables, with in-person support as well\n\nRequirements:\n\nUniversity degree in business, marketing, advertising, communications, or a related field\nUp to date with Social Media Trend and Popular culture in Hong Kong and around the world\nExcellent common sense and strategic thinking.\nQuick thinker and doer with great sense of humor and attitude; pleasant and positive with a \u201cCAN DO\u201d mindset.\nA self-starter, a passion for learning and problem solving.\nKeen learner with great sense of ownership and being able to complete the work independently as well as with the team members.\nAble to work under pressure and tight turnaround.\nSuper detail oriented to ensure output quality of work.\nMust be well organized with timeline and deliverable and have strong communication skills\nProficiency in MS Office. Ability to use Social media mock-up tools such as canva will be added value.\nGood command of spoken and written Cantonese, Mandarin and English\nAble to build a good rapport with clients and vendors in respective and reasonable communications way.\nAble to articulate ideas and thoughts to stakeholders in effective manners.\nCandidate with more experience will be considered as Social Content Planner\nImmediate availability is an advantage\n\nWorking Location: Cyberport (\u6578\u78bc\u6e2f) , Hong Kong\n\nWe offer a 5-day week of work, group medical & life insurance coverage, free shuttle bus to the right candidate. Interested parties please send your application letter and resume by clicking the \u201cApply Now\u201d button.\n\nAll information collected will be used for recruitment only and treated in strict confidence. We will retain the personal data of unsuccessful applicants for future recruitment purpose for a maximum period of 2 years.", "employment_types": ["Full Time", "Permanent"], "selling_points": ["Drive marketing programs", "Monitor sales performance", "Attractive package (allowance, commission, bonus)"], "locations": ["Tai Koo"], "categories": ["Banking / Finance", "Financial Services", "Marketing / Public Relations", "Marketing - Brand / Product Management", "Wealth Management"], "post_time": "2022-01-17T06:43:29Z", "salary": {"currency": "HKD", "max": 54999, "min": 30000, "period": "monthly", "term": null}, "salary_visible": true, "title_keywords": ["executive"], "responsibilities": ["communicate with", "management", "ideas", "budgeting", "comments", "monitoring", "a timely manner", "executing", "quality control", "liaise with", "customer queries"], "requirements": {"degrees": ["university degree"], "majors": ["business", "communications", "marketing"], "languages": ["cantonese", "english", "mandarin"], "language_level": ["good command"], "hard_skills": ["problem solving", "planner", "ms office"], "soft_skills": ["communication skills", "work independently", "strategic thinking", "passion for", "keen", "detail oriented", "well organized", "pleasant", "problem solving", "learning", "articulate", "positive", "work under pressure"], "languages_combined": [{"language": "cantonese", "language_level": ["good command"]}, {"language": "english", "language_level": ["good command"]}, {"language": "mandarin", "language_level": ["good command"]}]}, "experience_required": {"duration": [], "field": []}}, {"job_id": "100003009054295", "location_code": "hk", "company": "CHOW TAI FOOK JEWELLERY CO LTD", "job_title": "Associate, Branding Projects", "description": "Responsibilities:\n\nHandle the production of marketing collaterals and promotional materials to tie in with events and other business needs\nDevise innovative marketing communication campaigns to engage stakeholders and enhance brand awareness\nFormulate in-venue visitors engagement activities and execute during on-site or off-site events as required\nServe as a brand advocate in strengthening and upholding brand identity, including in-venue decoration and outgoing communication materials\nProvide support and collaborate with different teams to achieve dynamic planning across the company\nSupport in team related administrative and logistics as required\n\nRequirements:\n\nDegree Holder in Marketing, Communications, Business or other related disciplines\nAt least 3 years experience in marketing, communications, advertising or event management\nProficient in AI, Photoshop, HTML and CSS is an advantage\nA positive team player, proactive, detail-minded and highly independent\nStrong organizational ability and able to work effectively and efficiently under pressure\nProven writing skills in both English and Chinese\nFluent in English and Chinese, including Mandarin\u00a0\n\nInterested parties please send your full resume stating present & expected salary to HR Department by email to\u00a0hr@ asiaworld-expo.com\nPersonal data collected will be used for recruitment-related purpose only.\nAsiaWorld-Expo Management Limited is an equal opportunities employer.\u00a0", "employment_types": ["Full Time"], "selling_points": ["Branding Projects / Group\u2019s promotion channels", "Branding, marketing, project management", "5-day work"], "locations": ["Kwai Hing"], "categories": ["Marketing / Public Relations", "Marketing - Brand / Product Management", "Public Relations - Copy-writing", "Public Relations - General / Support"], "post_time": "2022-01-17T09:05:12Z", "salary": {"currency": null, "max": null, "min": null, "period": "monthly", "term": null}, "salary_visible": false, "title_keywords": ["associate"], "responsibilities": ["collaborate with", "provide support", "marketing collaterals", "teams", "communication", "promotional materials", "logistics", "planning"], "requirements": {"degrees": ["degree holder"], "majors": ["business", "related disciplines", "marketing", "communications"], "languages": ["english", "chinese", "mandarin"], "language_level": ["fluent"], "hard_skills": ["ai", "writing skills", "html", "css", "photoshop"], "soft_skills": ["detail-minded", "highly independent", "work effectively", "under pressure", "organizational", "writing skills", "team player", "proactive", "positive"], "languages_combined": [{"language": "english", "language_level": ["fluent"]}, {"language": "chinese", "language_level": ["fluent"]}, {"language": "mandarin", "language_level": ["fluent"]}]}, "experience_required": {"duration": ["at least 3 years"], "field": ["management", "marketing", "advertising"]}}, {"job_id": "100003009050756", "location_code": "hk", "company": "International Housewares Retail Company Limited", "job_title": "Marketing Executive / Senior Marketing Executive", "description": "Responsibilities:\n\nResponsible for Wine & Spirits portfolio in\u00a0Hotel, Club & Premium Bar segments\nIdentify potential new outlets and develop plans to enhance business opportunities\nDeliver the KPIs which include new distribution, initiative on brand activation, securing contracts with assigned target outlets\nProvide periodic evaluation of the achievement of outlet depletion, promotion & merchandising projects, etc. & be proactive to remedy if there is discrepancy\nSubmit weekly and monthly activity reports to line manager to monitor the actual performance against targets and objectives\nRequirements:\n\nDegree holder preferable\nMin. 5 years solid sales experience in beer, wine & spirits industry\nCommercially sensible with good negotiation skills\nHighly self-motivated, strong team player and do not resist drinking\nGood communication & interpersonal skills\nAble to work under pressure\nWilling to work on shift and irregular hours", "employment_types": ["Full Time", "Permanent"], "selling_points": ["Experience in loyalty / CRM marketing is a plus", "Market-wide content planning and coordination", "Knowledge of  Photoshop or AI"], "locations": ["Southern Area"], "categories": ["Marketing / Public Relations", "Marketing - Brand / Product Management", "Marketing - General / Support", "Digital Marketing"], "post_time": "2022-01-14T11:17:03Z", "salary": {"currency": null, "max": null, "min": null, "period": "monthly", "term": null}, "salary_visible": false, "title_keywords": ["senior marketing executive", "marketing executive"], "responsibilities": ["contracts", "business opportunities", "merchandising", "monitor", "reports", "develop plans", "evaluation", "kpis"], "requirements": {"degrees": ["degree holder"], "majors": [], "languages": [], "language_level": [], "hard_skills": [], "soft_skills": ["self-motivated", "communication", "negotiation skills", "interpersonal skills", "team player", "work under pressure"], "languages_combined": []}, "experience_required": {"duration": ["5 years"], "field": []}}, {"job_id": "100003009054993", "location_code": "hk", "company": "China Mobile Hong Kong \u4e2d\u570b\u79fb\u52d5\u9999\u6e2f", "job_title": "Product Manager, Smart Home Business", "description": "JOB PURPOSE:\nThis position leads the Marketing team of the WFJ Division in Hong Kong and Macau, responsible for elevating Chanel\u2019s brand equity in the watches and fine jewellery market through building the long-term value of the brand for customers of today and tomorrow. As such, marketing initiatives, especially in client relationship management and events, are key to convey the brand stories and to create an emotional connection with our targeted customer segments. The position will be a key contributor to growing Chanel\u2019s local watches and fine jewellery clientele and establishing the House as the pinnacle of ultimate luxury.\nSTRATEGIC PLANNING & EXECUTION EXCELLENCE\nAs a member of the WFJ leadership team, the position provides thought and operational leadership to drive the achievement of the division\u2019s strategic ambitions. Primary accountabilities include:\nContribute to the definition and implementation of the WFJ strategic plan for HKMO\nDevelop and deliver marketing and communications strategies to synergize watches and jewellery global strategies with consideration of local relevancy\nIdentify challenges and opportunities, propose initiatives and strategic insights to support management decisions and long-term ambitions\nDefine and master the budget at right and accurate level.\nSTAKEHOLDER MANAGEMENT & PARTNERSHIP\nInstill and role-model collaboration with an array of stakeholders in a highly matrixed organization in the following context:\nRetail & Merchandising \u2013 enable the achievement of commmercial objectives through provision of insights, tools, KPIs as well as close collaboration on product launches and marketing programs.\nFashion \u2013 partner with Fashion division to deliver \u201cOne Customer Journey\u201d online and offline. Lead and drive detailed planning and execution of synergized client engagement and visual merchandising plans.\nCommunication - partner with Communications Department to manage PR presence and direct programs to improve brand reputation and recognition. Establish partnership with Media, Digital team and external agency on advertising planning to define priorities and focus. Optimize brand and product exposure through POE platform.\nGlobal & Regional WFJ - proactively interact with global marketing teams and APAC marketing managers in the implementation of worldwide & regional marketing events and activities.\nDevelop staff engagement activities for product launches and collection celebrations in partnership with cross-functional stakeholders\nCLIENT ENGAGEMENT & MARKET INTELLIGENCE\nDifferentiate Chanel from other players in the market through valorizing Chanel\u2019s brand positioning in Watches & Fine Jewellery:\nClient strategy - define WFJ\u2019s client strategy, with clear client engagement objectives and action plans\nClient data & insights \u2013 champion improvement in customer insights through establishing a strong customer database and directing comprehensive studies/analyses of spending habits, trends, boutique traffic, etc.\nMarket intelligence - lead and guide continuous analysis of marketing intelligence on competitive environment, competitor activities and consumer trends.\nClient communications and experience \u2013 strengthen clienteling; ensure unparallel client experience at all touchpoints and in any type of event format; build strong connection with Mainland China as well as Fragrance & Beauty teams to appropriately plan and synchronize client communications.\nExternal partnership \u2013 network with external parties to identify potential partnership opportunities to facilitate client engagement or marketing activities.\nRole Requirements:\nDegree holder, ideally in Business Management, Marketing or related disciplines\nAt least 8-10 years of relevant experience in luxury industry, with sound knowledge of both local and tourist clientele\nBroad, strategic thinker with strong commercial acumen and an analytical mind\nA visionary and people-oriented leader with ability to build a strong team and galvanize without direct authority\nOrganization savvy with a track record of leadership success in a matrix organization\nSeasoned interpersonal and influencing skills\nStrong drive for high quality execution and constantly exceeding expectations\nPassion for arts & culture, luxury lifestyle and aesthetically inclined", "employment_types": ["Full Time", "Permanent"], "selling_points": ["18 AL, Double pay, Performance bonus", "5 days work week", "Staff SIM, Staff offer"], "locations": ["Kwai Hing"], "categories": ["Information Technology (IT)", "Product Management / Business Analyst", "Marketing / Public Relations", "Marketing - Brand / Product Management", "Marketing - General / Support"], "post_time": "2022-01-17T16:22:50Z", "salary": {"currency": null, "max": null, "min": null, "period": null, "term": null}, "salary_visible": false, "title_keywords": ["product manager"], "responsibilities": ["data", "budget", "merchandising", "external parties", "quality", "communication", "plan", "database", "plans", "advertising", "teams", "implementation", "customer insights", "develop", "visual", "kpis", "management", "strategic planning", "consumer trends", "marketing events", "analysis", "planning"], "requirements": {"degrees": ["degree holder", "master"], "majors": ["related disciplines", "business", "marketing"], "languages": [], "language_level": [], "hard_skills": ["business management", "analysis", "visual merchandising", "luxury industry", "focus", "acumen"], "soft_skills": ["responsible", "passion for", "communication", "clear", "comprehensive", "analytical mind", "people-oriented", "visionary", "focus", "accurate", "leadership", "interpersonal", "detailed"], "languages_combined": []}, "experience_required": {"duration": ["at least 8-10 years"], "field": ["relevant experience"]}}, {"job_id": "100003009051752", "location_code": "hk", "company": "Amorepacific Global Operations Limited", "job_title": "Ecommerce Officer (Retail Skincare)", "description": "Responsibilities:\n\nDesign and implement marketing campaigns, through means of in-store POS, social media, mobile app and other channels, to drive awareness, reach and conversion.\nSupport in the development, enhancement and maintenance of digital communication platforms, including website, social media platforms and mobile app.\nImplement activities to drive members\u2019 acquisition and engagement with Membership Campaign.\nBe the active role for market-wide content planning and coordination of digital communication platforms.\nCoordinate with internal stakeholders and external agencies to produce communication materials\nProvide departmental administrative support\nRequirements:\n\nDiploma or above in Marketing or related\u00a0disciplines\n2 years\u2019 working experience in the field of marketing / advertising\nKnowledge of\u00a0 Photoshop\u00a0or AI\nExperience in loyalty / CRM marketing is a plus\nGood communication and interpersonal skills\nGood command in verbal and written Chinese and English (Cantonese and Mandarin)\nCandidate with more experience will be considered as Senior Marketing\u00a0Executive\nImmediate available is highly preferred\u00a0\nWorking Location: Wong Chuk Hang (5 mins walk from MTR Station)\n\n\nWe offer attractive salary and benefits to the right candidates. \u00a0Interested parties please send full resume with present and expected salary\u00a0by clicking \"Apply Now\".\n\n\u00a0(Personal data will be used for recruitment purpose only)", "employment_types": ["Full Time", "Contract"], "selling_points": [], "locations": ["Causeway Bay"], "categories": ["Marketing / Public Relations", "Marketing - Brand / Product Management", "E-commerce", "Business Development", "Marketing - Brand / Product Management"], "post_time": "2022-01-17T00:24:47Z", "salary": {"currency": null, "max": null, "min": null, "period": "monthly", "term": null}, "salary_visible": false, "title_keywords": ["ecommerce officer"], "responsibilities": ["social media", "mobile app", "maintenance", "administrative support", "social media platforms", "coordinate with", "website", "design", "communication", "marketing campaigns", "coordination", "planning"], "requirements": {"degrees": ["diploma or above"], "majors": ["related disciplines", "marketing"], "languages": ["cantonese", "english", "chinese", "mandarin"], "language_level": ["good command"], "hard_skills": ["ai", "plus", "photoshop"], "soft_skills": ["communication and interpersonal skills"], "languages_combined": [{"language": "cantonese", "language_level": ["good command"]}, {"language": "english", "language_level": ["good command"]}, {"language": "chinese", "language_level": ["good command"]}, {"language": "mandarin", "language_level": ["good command"]}]}, "experience_required": {"duration": ["2 years"], "field": ["marketing", "advertising"]}}, {"job_id": "100003009056017", "location_code": "hk", "company": "HKT Enterprise Solutions", "job_title": "Assistant Vice President", "description": "CHINA MOBILE HONG KONG COMPANY LIMITED\u00a0(\"CMHK\") is the wholly-owned subsidiary of China Mobile Limited (HKEx: 941) (NYSE: CHL), which ranks 65th on the Fortune Global 500.\n\nOur company strives to offer superior service experience and to become the preferable digital partner for customers. We are preserving an environment with trust, responsibility and caring. At CMHK, we commit to maximizing people\u2019s potential and paving the way toward success for every striver. We are now inviting high caliber professional to join us.\n\nDivision: Marketing\u00a0 / Smart Home Business Department\n\nIn this position, you will:\n\nResponsible for the design and delivery of household product solutions;\nPromote ecological cooperation and product expansion and cooperation; have practical experience in building a smart furniture ecosystem, have strong upstream terminal or application field customer resources, and be able to quickly build a product system based on the industrial chain;\nResponsible for the B2B2C product integration planning, and cooperate with the corporate sales department to participate in the project competition of real estate developers and industry customers, and formulate product plans;\nThe ability to understand the business goals and high-level requirements and effectively define a systematic solution;\nResponsible for technology solution of home service IT supporting system, smart home products, GPON/IP network enhancement.\nAs technical facial point, create quality deliverables and communicate with appropriate all level audiences;\nCandidate shall coordinate various projects which related to home service IT supporting system, new products release, network enhancement.\n\n\n\nTo be successful in this position, you should meet the following requirements:\n\nBachelor degree holder;\nCAPM/ITIL/PMP certification preferred;\nAt least 5 years of work experience;\nExcellent communication skills, presentation skills, leadership skills and good at teamwork;\nEnergetic, self-motivated, able to work under pressure and independently;\nGood computer skills in Microsoft Office;\nGood command of written and spoken English and Chinese/Putonghua.\nCandidate with\u00a0less experience may consider as Assistant Manager\n\nWhen you work:\n\n5\u00a0days work\n8 hours/day\n\nWhat you enjoy:\n\nDouble pay\nDiscretionary Performance bonus\nLife insurance\nMedical insurance\nEducation subsidies\nBirthday gift\nMarriage leave\nBirthday leave\nStaff discount\n\nCMHK is committed to be an equal opportunity employer. We offer exceptional benefits package and the opportunity to work in a challenging environment. Personal data provided by applicants will be treated strictly in accordance with our personal data policy and for recruitment purposes only.\n\n\n", "employment_types": ["Full Time"], "selling_points": [], "locations": ["Kowloon Bay"], "categories": ["Sales, CS & Business Devpt", "Business Development", "Marketing / Public Relations", "Marketing - Brand / Product Management", "Sales - Sales Management"], "post_time": "2022-01-18T03:11:39Z", "salary": {"currency": null, "max": null, "min": null, "period": "monthly", "term": null}, "salary_visible": false, "title_keywords": ["assistant vice president"], "responsibilities": ["communicate with", "business goals", "work under pressure", "quality", "design", "coordinate", "communication", "plans", "insurance", "cooperate with", "planning"], "requirements": {"degrees": ["bachelor degree holder"], "majors": [], "languages": ["putonghua", "english", "chinese"], "language_level": ["good command"], "hard_skills": ["itil", "microsoft office", "mobile", "ip", "computer skills", "integration", "pmp"], "soft_skills": ["communication skills", "self-motivated", "independently", "responsible", "work under pressure", "leadership skills", "teamwork", "systematic", "committed", "presentation skills", "energetic", "superior"], "languages_combined": [{"language": "putonghua", "language_level": ["good command"]}, {"language": "english", "language_level": ["good command"]}, {"language": "chinese", "language_level": ["good command"]}]}, "experience_required": {"duration": ["at least 5 years"], "field": ["digital"]}}, {"job_id": "100003009054731", "location_code": "hk", "company": "AXA China Region Insurance Company Limited", "job_title": "Wealth Managers", "description": "Responsibilities:\n\nManage daily operations of online shop including generate & update website content\u00a0including product information, promotion, events and etc.\nMaking promotion plan each month based on data analysis (Mainly E-Commerce and assistant for retail shop)\nTrack online sales progress, traffic and click-through rate etc and provide analysis for management review and strategic planning\nMonitor the functionality of the online shops and to assure the timely logistic operation and delivery arrangement.\nPrepare analysis report on sales performance, inventory control and e-Commerce operation efficiency.\nResponsible for online shop stock controlling.\nCreating eCommer banner and product information visual by own\nMaintaining direct online platform (specially HKTV Mall) and WTC eStore\nHandling official WeChat account for branding.\nRequirements:\n\nNot less than 2 year\u00a0experiences\u00a0in digital and eCommerce solution, preferably in FMCG and retail industries.\nGood Knowledge in\u00a0online shop and e-marketplaces operation\nProficient with MS Office; Knowledge of Photoshop/ Illustrator/ Google Analytics/ Internet Technology\nGood Project management skill and independent handle multi-tasks to hit tight deadlines\nProficiency in English and Cantonese\nImmediate available is preferred\nFamiliar with\u00a0popular\u00a0social media\u00a0platform including WeChat\nWe offer competitive remuneration and attractive compensation package to the right candidate.\u00a0\n\n", "employment_types": ["Full Time", "Permanent"], "selling_points": [], "locations": ["Kwun Tong"], "categories": ["Hospitality / F & B", "Others", "Marketing / Public Relations", "Marketing - Brand / Product Management", "Banking / Finance", "Asset Management"], "post_time": "2022-01-17T10:48:11Z", "salary": {"currency": null, "max": null, "min": null, "period": "monthly", "term": null}, "salary_visible": false, "title_keywords": [], "responsibilities": ["strategic planning", "maintaining", "analysis report", "sales performance", "analysis", "monitor", "website", "data analysis", "inventory control", "plan", "visual", "manage daily operations", "management review"], "requirements": {"degrees": [], "majors": [], "languages": ["cantonese", "english"], "language_level": ["proficiency"], "hard_skills": ["google analytics", "illustrator", "wechat", "project management", "ms office", "photoshop"], "soft_skills": ["independent", "multi-tasks", "project management skill"], "languages_combined": [{"language": "cantonese", "language_level": ["proficiency"]}, {"language": "english", "language_level": ["proficiency"]}]}, "experience_required": {"duration": ["2 year"], "field": ["ecommerce", "digital", "fmcg", "retail"]}}, {"job_id": "100003009045876", "location_code": "hk", "company": "The Chinese Manufacturers' Association of Hong Kong", "job_title": "Marketing Executive (EOA2)", "description": "Reports to:\u00a0Head of Brand & Content\nDepartment:\u00a0Brand, Insights & Marketing Communications\u00a0\u00a0\n\nRole Introduction\u00a0\n\nBecoming a brand-led organisation is core to Cathay Pacific strategy, thus placing the brand team at the heart of the company. \u00a0We ensure that we remain true to our brand \u2013 lighting it up at every opportunity; amplifying, enhancing and refining it across every customer and employee touchpoint. Every interaction that our customers and employees have with our brand influences their perception of it. We therefore work on a wonderfully diverse set of projects which will stimulate, challenge and reward any candidate deeply passionate about branding.\u00a0\n\nUnder our brand platform Move Beyond, our purpose is to move people forward in life through our ability to connect them to meaningful people, places and experiences. \u00a0\n\nThe brand team helps to translate this brand promise and strategy into everything that we do. We work with the insights team to really understand our targeted customers\u2019 needs, desires and behaviours, translating the insights into our brand strategy and associated experience.\u00a0\n\nWe are looking for an exceptionally talented Brand Manager, brimming with energy to help the Cathay Group of brands to strengthen over time, build a deeper connection with our customers and a sense of pride internally. This role presents an incredible opportunity to make a significant mark on the brand\u2019s future, the full customer and employee experience, as well as your own branding career.\n\nKey Responsibilities\n\nBrand strategy & translation\n\nSupport Head of Brand & Content on the development of the Cathay\u2019s brand strategy, including brand positioning, segmentation, definition and articulation\nLead a diverse set of projects, with multiple business areas to translate our brand into different parts of the customer and employee experience\nLead Cathay\u2019s brand partnership strategy\nEstablish new processes and guidelines to help define how different areas of the business should interact with and represent the brand\n\nBrand Measurements\n\nWork closely with the insights team to measure the performance of our brand across all customer touch-points, including the items we have rolled out, to identify areas to improve and inoculate our brand\n\nMerchandise & collaterals\n\nLead a team of product designers in the design and development of branded merchandise and collaterals, working closely with marketing and commercial teams from ideation to design\nWork closely with our content team to craft compelling stories to raise awareness on our branded products\n\nBrand identity\n\nManage and preserve the Cathay Pacific Group\u2019s brand identity system, developing new sub-brands as required\nManage aircraft livery design\u00a0\nManage and lead the implementation of our trademark protection strategy\n\nRequirements\n\nWe\u2019re seeking someone who has the experience, passion and drive to bring our brand purpose to life. Someone who is thrilled with ideas and prospects to build love for our brand. We\u2019re looking for someone who is deeply passionate about branding and is brave about ideas, whilst being clear-eyed about what it takes to achieve better work. Holding oneself, and those around you, to high standards and taking pride in the quality of work are prerequisites for this role.\u00a0\n\nThe candidate will have a strong understanding of brand and design, with an ability to clearly articulate design modifications and improvements in accordance with Cathay\u2019s brand proposition.\n\nIn terms of practical experience and qualifications, the candidate should have at least 8 years\u2019 experience in Brand, Design or a Customer Experience Design and hold a bachelor\u2019s degree in marketing, design or communications related field. We are looking for someone who has worked at a branding agency, helping numerous brands bring their brand purpose to life.\u00a0\n\nBeing an exceptional communicator in written and spoken English skills is a must, Chinese would be incredible.\u00a0\n\nFinally, we\u2019re a premium travel lifestyle brand so we\u2019re naturally looking for someone who shares our absolute love for all things travel.\n\nApplication Deadline: 28 January 2022\n\nPersonal & Application Information\n\nCathay Pacific is an Equal Opportunities Employer. Personal data provided by job applicants will be used strictly in accordance with our personal data policy and for recruitment purposes only. Candidates not notified within eight weeks may consider their application unsuccessful. All related information will be kept in our file for up to 24 months. A copy of our Personal Information Collection Statement will be provided upon request by contacting our Data Protection Officer.\n\nPlease note that with effect from 1 December 2021, all employees must be vaccinated in order to access Cathay City and all other Cathay Group Company premises in Hong Kong. Consideration will be given to those who are unable to get vaccinated for valid medical reasons.\n\nApplication Deadline: 28 January 2022", "employment_types": ["Full Time", "Permanent"], "selling_points": [], "locations": ["Central"], "categories": ["Marketing / Public Relations", "Marketing - Brand / Product Management", "Marketing - General / Support", "Public Relations - Event Management"], "post_time": "2022-01-14T06:11:31Z", "salary": {"currency": null, "max": null, "min": null, "period": "monthly", "term": null}, "salary_visible": false, "title_keywords": ["marketing executive"], "responsibilities": ["guidelines", "teams", "developing", "design", "implementation", "lead a team"], "requirements": {"degrees": ["degree", "bachelor"], "majors": ["marketing", "communications", "design"], "languages": ["english", "chinese"], "language_level": [], "hard_skills": [], "soft_skills": ["clear", "articulate", "communicator", "passionate about"], "languages_combined": [{"language": "english", "language_level": []}, {"language": "chinese", "language_level": []}]}, "experience_required": {"duration": ["at least 8 years"], "field": ["related", "marketing", "brand", "design"]}}, {"job_id": "100003009051798", "location_code": "hk", "company": "The Great Eagle Group of Companies", "job_title": "Officer \u2013 Digital Marketing", "description": "Job Responsibilities\n\nPlan and organize membership programs including Seminars, Dinner Reception and Trade Matching programs, etc;\n\nTo conduct project management, and event coordination / supervision;\nManage FB and IG accounts;\nTo provide administrative support to the department;\n\nJob Requirements\n\nUniversity graduate with at least 2 years working experience;\u00a0\nA good team player with strong communication skills and service-oriented minds;\nInitiative and detail-minded with good sense of responsibility;\nGood writing skills in both English and Chinese;\nAble to speak fluent English, Cantonese and Putonghua;\nProficient with MS Office, knowing of Chinese typing is a must;\nBasic photo and video editing skill;\nCandidates with less experience will be considered as Senior Marketing Assistant.\nImmediate available is preferred.\n\nWe offer competitive remuneration and all applications will be treated in strict confidence. If your profile matches the above requirements, please send your full resume including your last and expected salary to us.\n\nData collected will be used for recruitment purpose only.", "employment_types": ["Full Time", "Permanent"], "selling_points": ["Managing marketing promotion", "Execute digital campaign strategy", "Beauty Industry"], "locations": ["Mong Kok"], "categories": ["Media & Advertising", "Strategic Planning", "Beauty Care / Health", "Others", "Marketing / Public Relations", "Marketing - Brand / Product Management"], "post_time": "2022-01-17T01:13:33Z", "salary": {"currency": null, "max": null, "min": null, "period": "monthly", "term": null}, "salary_visible": false, "title_keywords": ["officer", "digital marketing"], "responsibilities": ["provide administrative support", "project management", "coordination", "plan"], "requirements": {"degrees": ["university graduate"], "majors": [], "languages": ["cantonese", "putonghua", "english", "chinese"], "language_level": ["fluent", "proficient", "good"], "hard_skills": ["basic", "typing", "writing skills", "video editing", "ms office"], "soft_skills": ["detail-minded", "communication skills", "good team player", "sense of responsibility", "service-oriented", "writing skills", "initiative"], "languages_combined": [{"language": "cantonese", "language_level": ["fluent"]}, {"language": "putonghua", "language_level": ["fluent"]}, {"language": "english", "language_level": ["fluent", "good"]}, {"language": "chinese", "language_level": ["proficient", "good"]}]}, "experience_required": {"duration": ["at least 2 years"], "field": ["marketing"]}}, {"job_id": "100003009051419", "location_code": "hk", "company": "", "job_title": "Marketing Manager", "description": "Responsibilities:\n\nResponsible for promotion planning including BTL and ATL marketing activities\nExecute and supervise promotion activities & marketing collaterals\nFormulate and implement national advertising, store promotion, joint promotion, licensing plans, events and store visual merchandizing plans\nControl, maintain and review on the marketing projects to assure meeting business objectives, deadlines and working within budget\nCommunicate and align with inter-departments, stores, external vendors and agencies to implement the marketing activities\nLiaise with strategic partners for joint promotion opportunities\n\nRequirements:\u00a0\n\nUniversity graduate in Marketing, Communication or Business\u00a0or related disciplines\u00a0\nA minimum of 3 years\u2019 marketing experience\nSolid exposure in retail environment or FMCG industry\nDynamic and creative to cope with fast-paced working environment\nExcellent communication and organisation skills\nGood command of English & Chinese with strong interpersonal and problem solving skills\nCandidate with less experience will be considered as Assistant Marketing Officer\n\nA rewarding remuneration package will be offered to the successful candidate. Interested parties please forward detailed resume stating expected salary by email to us.\n\nWe are an equal opportunity employer and welcome applications from all qualified candidates. The information provided will be treated in strict confidence and be used only for consideration of your application for relevant / similar posts within the A.S. Watson Group. All personal data of unsuccessful applicants will be destroyed within 12 months from the date of application.", "employment_types": ["Full Time", "Permanent"], "selling_points": [], "locations": ["Central & Western Area"], "categories": ["Marketing / Public Relations", "Marketing - Brand / Product Management", "Marketing - Marketing Communication", "Digital Marketing"], "post_time": "2022-01-15T15:14:29Z", "salary": {"currency": null, "max": null, "min": null, "period": "monthly", "term": null}, "salary_visible": false, "title_keywords": ["marketing manager"], "responsibilities": ["control", "advertising", "marketing collaterals", "review", "marketing projects", "budget", "maintain", "visual", "liaise with", "plans", "planning"], "requirements": {"degrees": ["university graduate"], "majors": ["business", "related disciplines", "marketing"], "languages": ["english", "chinese"], "language_level": ["good command"], "hard_skills": ["dynamic", "fmcg industry", "problem solving skills"], "soft_skills": ["communication", "dynamic", "organisation", "problem solving skills", "creative", "interpersonal"], "languages_combined": [{"language": "english", "language_level": ["good command"]}, {"language": "chinese", "language_level": ["good command"]}]}, "experience_required": {"duration": ["minimum of 3 years"], "field": ["marketing"]}}, {"job_id": "100003009048345", "location_code": "hk", "company": "FUJIFILM Business Innovation Hong Kong Limited", "job_title": "Product Marketing Executive (Ref: EDSHW)", "description": "Responsibilities:\n\nResponsible for managing marketing promotion including but not limited to digital marketing, social media, promotional events and campaigns etc.\nExecute digital campaign strategy such as media buy, social media, Live Streaming, KOL collaboration and track campaign performance with various KPIs\nManage marketing promotion schedule and implement effective strategies to achieve business objectives\nManage campaigns and media buy, digital retainer vendors to ensure tracking, reporting and analytics are functioning optimally\nWork closely with design team to develop and update promotion contents and roll out of marketing campaigns effectively\nExplore new social media and digital marketing channels\nHandle ad hoc duties as assigned\n\nRequirements:\n\nDegree holder or above in Marketing, Communications, Business Administration or other relevant disciplines\nAt least 2 years\u2019 experience in digital marketing, preferable gained in Beauty industry\nCreative, self-motivated and well-organized\nAble to work multi-task and independently within VM guidelines\nGood business sense with passion in beauty industry\nProficiency in MS Office Applications and Chinese Word Process\nGood communication and interpersonal skills at all levels\nGood command of both written and spoken English and Chinese (including Putonghua)\n\nSalary and benefits will be commensurate with qualifications and experience.\u00a0 Interested parties, please send a full resume with present and expected salary, and date available to The Human Resources Department, 32/F., Great Eagle Centre, 23 Harbour Road, Wanchai, Hong Kong or e-mail to us.\u00a0(Please quote the reference no. on the envelope and the covering letter.)\n\nTo know more about us, please visit our website at http://www.greateagle.com.hk.\n\nWe are an equal opportunity employer and welcome applications from all qualified candidates.\n\nPersonal data collected will be treated in strict confidence and used only for recruitment-related purpose. Applicants who have not heard from us within four weeks may consider their applications unsuccessful. All personal data will be destroyed after 12 months.", "employment_types": ["Full Time", "Permanent"], "selling_points": ["Product Life-cycle Management", "Data Analysis", "Marketing Campaign"], "locations": ["Tai Koo"], "categories": ["Marketing / Public Relations", "Marketing - Brand / Product Management", "Marketing - General / Support"], "post_time": "2022-01-14T06:23:18Z", "salary": {"currency": null, "max": null, "min": null, "period": "monthly", "term": null}, "salary_visible": false, "title_keywords": ["marketing executive"], "responsibilities": ["ad hoc duties", "social media", "reporting", "design", "develop", "digital marketing", "schedule", "marketing campaigns", "contents", "kpis", "tracking"], "requirements": {"degrees": ["degree holder"], "majors": ["marketing", "business administration", "communications"], "languages": ["putonghua", "english", "chinese"], "language_level": ["proficiency", "good command"], "hard_skills": ["word", "ms office"], "soft_skills": ["self-motivated", "independently", "multi-task", "business sense", "passion in", "well-organized", "communication and interpersonal skills", "creative"], "languages_combined": [{"language": "putonghua", "language_level": ["good command"]}, {"language": "english", "language_level": ["good command"]}, {"language": "chinese", "language_level": ["proficiency", "good command"]}]}, "experience_required": {"duration": ["at least 2 years"], "field": ["beauty industry", "digital marketing"]}}, {"job_id": "100003009051585", "location_code": "hk", "company": "Medialink Entertainment Limited", "job_title": "Executive - Contract Administration", "description": "Responsibilities:\n\nLead the Marketing Team to execute marketing activities and roadmaps\nDevelop and execute marketing strategies to promote campaigns including but not limited to build relationships with agency, promoting products and services via e-marketing and social media channels\nOptimize digital marketing and revamp corporate website marketing content\nBuild close relationships with business partners and insurance agencies\nEstablish effective marketing direction and strategies for the brand\nPerform any ad-hoc duties as assigned\nRequirements:\n\nBachelor degree with major in Marketing or related discipline\nAt least 5+ years of solid experience in Marketing Management / Digital Marketing / Public Relations\nPrior experience of working at Healthcare / Servicing Industry, B2B / B2C business will be advantageous\u00a0\nExcellent leadership, interpersonal and communication skills and teamwork will be a definite advantage\u00a0\nStrong in digital marketing and social media\nGood command in both spoken and written English and Chinese\nWe offer competitive remuneration package to right candidate.\u00a0 (Data collected will be used solely for the purpose of recruitment.)\nInterested candidates, please contact us at 91742871 for company details before applying.", "employment_types": ["Full Time"], "selling_points": ["Degree / Diploma holder in any disciplines", "2 years exp in Content Distribution & Licensing", "Knowledge in Rights Mgt System & Data Processing"], "locations": ["Tsim Sha Tsui"], "categories": ["Marketing / Public Relations", "Marketing - Brand / Product Management", "Public Relations - General / Support"], "post_time": "2022-01-16T12:57:32Z", "salary": {"currency": null, "max": null, "min": null, "period": "monthly", "term": null}, "salary_visible": false, "title_keywords": ["executive"], "responsibilities": ["social media", "revamp", "marketing strategies", "website", "develop", "digital marketing", "ad-hoc duties", "insurance"], "requirements": {"degrees": ["degree", "bachelor"], "majors": ["marketing"], "languages": ["english", "chinese"], "language_level": ["good command"], "hard_skills": [], "soft_skills": ["communication skills", "teamwork", "leadership", "interpersonal"], "languages_combined": [{"language": "english", "language_level": ["good command"]}, {"language": "chinese", "language_level": ["good command"]}]}, "experience_required": {"duration": ["at least 5+ years"], "field": ["healthcare", "management", "public relations", "servicing industry", "marketing", "digital marketing", "business"]}}, {"job_id": "100003009054897", "location_code": "hk", "company": "Macleans Consulting International Limited", "job_title": "Head of Talent Acquisition & Employer Branding [Biotechnology]", "description": "The Job\nResponsible for product life-cycle management including product launch, marketing strategy and inventory management\nAssist in marketing reports, data tracking, and identifying the areas of improvement and enhancement\nExecute sales and marketing strategy to achieve company\u2019s goals on market share and profitability\nThe Person\nDegree holder/ associate degree holder with minimum 2 years relevant experiences preferably in ICT industry\nExperience in data analysis and marketing report with strong analytical mind\nPositive, disciplined, self-motivated with good interpersonal skill\nProficient in using MS Office application, including Word, Excel and PowerPoint\nMore experience will be considered as Senior Product Marketing Executive\nWe offer career prospect, attractive remuneration and fringe benefits including but not limited to the followings:\n12 days' annual leave\nBlissful leave of maximum 25 days per year (including birthday leave, wedding anniversary leave, children graduation leave, volunteer leave, pet healthcare leave, home purchase, etc)\n5 days work week & bank holiday\nClinical, hospitalization and dental insurance\u00a0\nTo discuss this opportunity further, please send your full resume, current and expected salary to the\u00a0HR Department.\nWe are a equal opportunity employer and welcome applications from all qualified candidates.\u00a0 All information provided will be treated in strict confidence and used for recruitment purposes only.\u00a0 Applicants not hearing from us within six weeks may consider their applications unsuccessful.\u00a0 All data of unsuccessful applications will be destroyed after six months.", "employment_types": ["Full Time", "Permanent"], "selling_points": ["Biotechnology, Energetic Team; Fast-growing", "Regional exposure; MNC+Agency is preferred", "Fluent English & Chinese Speaking"], "locations": ["Not Specified"], "categories": ["Admin & HR", "HR Director / Manager", "Recruitment / Executive Search", "Marketing / Public Relations", "Marketing - Brand / Product Management"], "post_time": "2022-01-18T02:52:20Z", "salary": {"currency": null, "max": null, "min": null, "period": "monthly", "term": null}, "salary_visible": false, "title_keywords": [], "responsibilities": ["management", "data", "inventory management", "reports", "tracking"], "requirements": {"degrees": ["associate degree", "degree holder"], "majors": [], "languages": [], "language_level": [], "hard_skills": ["excel", "analysis", "word", "powerpoint", "ms office"], "soft_skills": ["self-motivated", "analytical mind", "positive", "interpersonal skill"], "languages_combined": []}, "experience_required": {"duration": ["minimum 2 years"], "field": ["ict industry", "data analysis", "analytical", "marketing"]}}, {"job_id": "100003009044762", "location_code": "hk", "company": "Tech Vision System Limited", "job_title": "Marketing Executive", "description": "Responsibilities:\n\nMaintain accurate database and filing of license agreements and relevant documents\nManage and maintain database of Rights Management System and Electronic Data Processing\nReview and vet contract deal terms in business agreements\nPrepare and draft business agreements\nCo-ordinate with external parties and different business teams in regional offices for contract administration tasks\nPerform other ad-hoc tasks / projects as required\nRequirements:\u00a0\n\nDegree or Diploma holder in any disciplines\nAt least 2 years solid administrative experience in Content distribution and Licensing industry preferable\nKnowledge in Rights Management System and Data Processing would definitely be an advantage\nAttention to details with strong communication and problem-solving skills\nExcellent organizational skills with the ability to multi-task\nGood command of written and spoken of English and Chinese is required\nCandidate with more experience will be considered as Senior Executive\nWe offer 5-day work week, medical scheme, discretionary bonus and good career prospect to the right candidate. Interested parties, please send full resume with present & expected salaries and date availability to HR & Admin Department by \u201cApply Now\u201d below.\n", "employment_types": ["Full Time", "Permanent"], "selling_points": ["Medical insurance & Performance bonus", "Opportunity for growth", "5 Day Work, stable environment"], "locations": ["Wong Tai Sin Area"], "categories": ["Information Technology (IT)", "Hardware", "Marketing / Public Relations", "Marketing - Brand / Product Management", "Marketing - General / Support"], "post_time": "2022-01-13T06:11:24Z", "salary": {"currency": null, "max": null, "min": null, "period": "monthly", "term": null}, "salary_visible": false, "title_keywords": ["marketing executive"], "responsibilities": ["management", "co-ordinate with", "contract administration", "ad-hoc tasks", "review", "external parties", "teams", "data processing", "maintain", "database"], "requirements": {"degrees": ["diploma holder", "degree"], "majors": ["any disciplines"], "languages": ["english", "chinese"], "language_level": ["good command"], "hard_skills": ["problem-solving skills", "processing"], "soft_skills": ["organizational skills", "multi-task", "communication", "attention to details", "problem-solving skills"], "languages_combined": [{"language": "english", "language_level": ["good command"]}, {"language": "chinese", "language_level": ["good command"]}]}, "experience_required": {"duration": ["at least 2 years"], "field": ["administrative"]}}, {"job_id": "100003009053500", "location_code": "hk", "company": "Antibac International Co., Limited", "job_title": "\u7522\u54c1\u63a8\u5ee3\u54e1", "description": "About our client\nA Fast-growing Global Biotechnology company, its headquarter is in Hong Kong with offices in APAC & Europe, who is seeking a NEW Team Head about talent acquisition & employer branding, reports to the Chief People Officer (Global).\n\nEnergetic, move fast and variety of recruiting methods\nCorporate in-house + Agency experience is preferred\nFluent English and Chinese Speaking\nComfortable with some hands-on operations\n\nResponsibilities\n\n\nFormulate and implement disruptive talent acquisition strategies and build talent pipeline for future organization growth;\nOversee a team of passionate talent acquisition specialists and full cycle recruiting processes;\nSpearhead our employer brand building with an aim to make it a global brand, while bringing awareness to local communities and networks;\nDrive talent and business outcomes as a manpower and organisation structure advisor & HRBP to the company;\nCreate a game changing and technology driven innovative talent acquisition processes and candidate experience.\nRequirements\nPrevious experience leading a Talent Acquisition function for an international company, with agency experience is a plus;\n\nProven track record of success in high growth organization with a variety of recruiting methods including direct sourcing, social recruiting and traditional methods, experience in Biotechnology / Life-Sciences recruitment is a plus;\nRich experience in building employer brand supported by positive business outcome;\nExcellent written and verbal communication skills in English & Chinese;\nComfortable with hands-on tasks and fast-paced working environment.\nTo apply, please click on the \u2018Apply Now\u2019 button or contact Nick Chow at (852) 3502-2637 for a confidential discussion. Alternatively, email your resume (with your notice period, current and expected salary) to\u00a0nick.chow@macleansgroup .com\n\nYour interest will be treated in strict confidence and only shortlisted candidates will be notified.\n", "employment_types": ["Full Time"], "selling_points": [], "locations": ["Wan Chai"], "categories": ["Hospitality / F & B", "Others", "Marketing / Public Relations", "Marketing - Brand / Product Management", "Others"], "post_time": "2022-01-17T07:04:03Z", "salary": {"currency": null, "max": null, "min": null, "period": "monthly", "term": null}, "salary_visible": false, "title_keywords": [], "responsibilities": [], "requirements": {"degrees": [], "majors": [], "languages": ["english", "chinese"], "language_level": ["excellent"], "hard_skills": ["plus"], "soft_skills": ["communication skills", "hands-on", "confidence", "positive"], "languages_combined": [{"language": "english", "language_level": ["excellent"]}, {"language": "chinese", "language_level": ["excellent"]}]}, "experience_required": {"duration": [], "field": ["agency", "business", "recruitment", "brand"]}}, {"job_id": "100003009050163", "location_code": "hk", "company": "Ricoh Hong Kong Limited", "job_title": "Marketing Communications Specialist", "description": "Responsibilities\n\n-\u00a0\u00a0\u00a0\u00a0\u00a0\u00a0\u00a0 Provide support on the day-to-day central marketing activities and operations\n\n-\u00a0\u00a0\u00a0\u00a0\u00a0\u00a0\u00a0 Handle social media postings, communicate with influencers and promoted our brand and products\n\n-\u00a0\u00a0\u00a0\u00a0\u00a0\u00a0\u00a0 Provide operation support on both online and office events and other marketing promotions\n\n-\u00a0\u00a0\u00a0\u00a0\u00a0\u00a0\u00a0 Meet with customers and participate in local exhibitions\n\n-\u00a0\u00a0\u00a0\u00a0\u00a0\u00a0\u00a0 Team admin & reporting tasks\n\n-\u00a0\u00a0\u00a0\u00a0\u00a0\u00a0\u00a0 Assist in ad hoc duties when required\n\nRequirements\n\n\u00a0-\u00a0\u00a0\u00a0\u00a0\u00a0\u00a0\u00a0 Diploma or equivalent qualification\n\n-\u00a0\u00a0\u00a0\u00a0\u00a0\u00a0\u00a0 Good written and spoken communication skills in English and Chinese / Mandarin\n\n-\u00a0\u00a0\u00a0\u00a0\u00a0\u00a0\u00a0 1-2 years relevant working experience\n\n-\u00a0\u00a0\u00a0\u00a0\u00a0\u00a0\u00a0 Proficiency in MS office, Adobe Photoshop and illustrator is preferred\n\n-\u00a0\u00a0\u00a0\u00a0\u00a0\u00a0\u00a0 Independent and good team player\n\n-\u00a0\u00a0\u00a0\u00a0\u00a0\u00a0\u00a0 Well organized, pro-active and self-motivated\n\n-\u00a0\u00a0\u00a0\u00a0\u00a0\u00a0\u00a0 Immediate availability is an advantage", "employment_types": ["Full Time", "Permanent"], "selling_points": ["Work with Products and Solutions Marketing Team", "4 years of relevant experience in B2B marketing", "Experienced in Digital Marketing"], "locations": ["Kowloon Bay"], "categories": ["Marketing / Public Relations", "Marketing - Brand / Product Management", "Marketing - Marketing Communication", "Digital Marketing"], "post_time": "2022-01-15T19:11:41Z", "salary": {"currency": null, "max": null, "min": null, "period": "monthly", "term": null}, "salary_visible": false, "title_keywords": ["specialist"], "responsibilities": ["communicate with", "social media", "provide support", "reporting", "ad hoc duties", "operations", "marketing promotions"], "requirements": {"degrees": ["diploma"], "majors": [], "languages": ["english", "chinese", "mandarin"], "language_level": ["good"], "hard_skills": ["adobe photoshop", "illustrator", "ms office"], "soft_skills": ["communication skills", "good team player", "self-motivated", "independent", "well organized", "pro-active"], "languages_combined": [{"language": "english", "language_level": ["good"]}, {"language": "chinese", "language_level": ["good"]}, {"language": "mandarin", "language_level": ["good"]}]}, "experience_required": {"duration": ["1-2 years"], "field": ["relevant working experience"]}}, {"job_id": "100003009046466", "location_code": "hk", "company": "Reckitt Benckiser Hong Kong Limited", "job_title": "Marketing Manager", "description": "\n\u5730\u5340\uff1a\u9285\u947c\u7063\u00a0 \u00a0\u00a0\n\u8077\u8cac\uff1a \u4e00\u822c\u63a8\u5ee3\u54e1\u5de5\u4f5c (\u7a7a\u6c23\u6de8\u5316\u7522\u54c1)\n\u8cc7\u6b77\uff1a \u6c92\u6709\u5b78\u6b77\u8981\u6c42; 1\u5e74\u7d93\u9a57; \u826f\u597d\u7cb5\u8a9e; \u4e00\u822c\u666e\u901a\u8a71; \u4e00\u822c\u82f1\u8a9e; \u61c2\u95b1\u8b80\u4e2d\u6587; \u5b88\u6642\uff0c\u6709\u8cac\u4efb\u611f\uff0c\u559c\u6b61\u8207\u5ba2\u4eba\u6e9d\u901a\uff0c\u6709\u8010\u6027\n\u5f85\u9047\uff1a \u6bcf\u6708$8,500 - $15,000, \u6709\u4f63\u91d1, \u8868\u73fe\u734e\u91d1 \u53ca\u71df\u696d\u734e\u91d1, \u4e2d\u534812\u6642\u81f3\u4e0b\u53488\u6642, \u6bcf\u9031\u5de5\u4f5c6\u5929,\u8f2a\u4f11, \u6bcf\u5929\u5de5\u4f5c 8 \u5c0f\u6642\n\u7533\u8acb\u9808\u77e5\uff1a\u6c42\u8077\u8005\u53ef\u96fb\u90f5(Apply Now)\u5c65\u6b77\u8868\u7d66ANTIBAC INTERNATIONAL CO., LIMITED\u3002\u5982\u8981\u7d22\u53d6\u6536\u96c6\u500b\u4eba\u8cc7\u6599\u8072\u660e, \u8acb\u8207\u9ec3 \u5c0f\u59d0(Email)\u806f\u7d61\u3002\n\n", "employment_types": ["Full Time", "Permanent"], "selling_points": ["8 years marketing experience", "2 years' experience as people manager", "Able to demonstrate outstanding marketing skills"], "locations": ["Causeway Bay"], "categories": ["Marketing / Public Relations", "Marketing - Brand / Product Management"], "post_time": "2022-01-13T11:29:52Z", "salary": {"currency": null, "max": null, "min": null, "period": "monthly", "term": null}, "salary_visible": false, "title_keywords": ["marketing manager"], "responsibilities": [], "requirements": {"degrees": [], "majors": [], "languages": [], "language_level": [], "hard_skills": [], "soft_skills": [], "languages_combined": []}, "experience_required": {"duration": [], "field": []}}, {"job_id": "100003009056372", "location_code": "hk", "company": "China Mobile Hong Kong \u4e2d\u570b\u79fb\u52d5\u9999\u6e2f", "job_title": "Assistant Product Manager (Industry Development)", "description": "The Job:\n\nWork closely with Products and Solutions Marketing Team to drive the leads of the specific products and solutions\nCoordinate with vendors for the design and production of corporate collaterals, promotional materials and advertisement such as brochure, leaflet, flyer, website, video, social media post etc.\nLiaise with agencies to implement corporate and lead generation events and webinars\nPlan and execute digital marketing campaigns and drip campaigns through the marketing automation platform\nPerform ad-hoc duties as assigned\nThe Person:\n\nBachelor\u2019s Degree in Marketing, Business Administration or related discipline\u3000\nMinimum 4 years of relevant experience in B2B marketing communications, preferably in IT industry\nExperience in Digital Marketing is a must\nSound knowledge in Production, Event Management, Marketing Automation and Digital Analytics is an advantage\u3000\nSelf-motivated, able to work independently and handle multi-tasks\u3000\nExcellent English and Chinese in both written and verbal communications\nWe offer 5-day work, attractive remuneration and benefits package to the right candidate.\n\nInterested parties please forward your full resume (in Microsoft Word or PDF format) with current and expect salary to the\u00a0Human Resources & Facilities Services, Ricoh Hong Kong Limited, by clicking \"Apply Now\".\nInformation provided will be treated in strict confidence and only be used for recruitment related purposes. All personal data of unsuccessful candidates will be destroyed on completion of the recruitment exercise.", "employment_types": ["Full Time", "Permanent"], "selling_points": ["3 year experience", "Good Benefits", "Property Technology, IoT, Education"], "locations": ["Kwai Hing"], "categories": ["Sales, CS & Business Devpt", "Business Development", "Information Technology (IT)", "Product Management / Business Analyst", "Marketing / Public Relations", "Marketing - Brand / Product Management"], "post_time": "2022-01-18T04:05:59Z", "salary": {"currency": null, "max": null, "min": null, "period": null, "term": null}, "salary_visible": false, "title_keywords": ["assistant product manager"], "responsibilities": ["social media", "digital marketing campaigns", "leaflet", "coordinate with", "website", "design", "promotional materials", "plan", "ad-hoc duties", "liaise with"], "requirements": {"degrees": ["degree", "bachelor"], "majors": ["marketing", "business administration"], "languages": ["english", "chinese"], "language_level": ["excellent"], "hard_skills": [], "soft_skills": ["self-motivated", "work independently", "multi-tasks"], "languages_combined": [{"language": "english", "language_level": ["excellent"]}, {"language": "chinese", "language_level": ["excellent"]}]}, "experience_required": {"duration": ["minimum 4 years"], "field": ["marketing communications", "it", "relevant experience", "digital marketing"]}}]