[{"job_id": "100003009051863", "location_code": "hk", "company": "Vigers Appraisal and Consulting Limited", "job_title": "ANALYST, RESEARCH & MARKETING (Fresh graduates are welcome)", "description": "Key Responsibilities:\nTo focus on developing regular research papers for HK and China property-related markets\nTo provide daily market research support to internal departments, include compiling information and writing reports such as sector studies, demand/supply analysis, etc\nTo assist in compiling property research materials\nTo perform real estate sector research and update the property market / economic / statistics regularly\nConduct analysis of research studies and create coherent presentations\n\u00a0Any other ad hoc projects\nRequirements:\nDegree in Economics / Business\u00a0or related disciplines;\n1-2 years' research experience is preferred. Fresh graduate\u00a0with excellent writing skills are\u00a0 also welcome.\nHave a sound understanding of property markets and good analytical mind would be an advantage.\nLove writing and presenting;\nComputer literate ( in MS Word, Excel, Powerpoint etc );\nBe self-motivated & well-organised, diligent & presentable,\u00a0with a high sense of responsibility, and\u00a0able to work independently & multi-tasked.\nExcellent proficiency in English and Chinese is a must\nYou are required to apply with your cover letter and latest CV. A written test is required when you are invited for an\u00a0interview.\n\nAttractive salaries will commensurate with qualification and experience. Interested parties, please send your resume, date of availability, current and expected salary to Human Resources Department, Vigers Appraisal and\u00a0Consulting Limited, 27/F\u00a0Standard Chartered Tower, Millennium City 1, 388 Kwun Tong Road, Kowloon under \u201cPrivate & Confidential\u201d.\n\n(Personal data collected would be used for recruitment purpose only)", "employment_types": ["Full Time", "Permanent"], "selling_points": [], "locations": ["Ngau Tau Kok"], "categories": ["Professional Services", "Business Analysis / Data Analysis", "Marketing / Public Relations", "Marketing - Market Research", "Property / Real Estate", "Property Consultancy"], "post_time": "2022-01-17T01:24:48Z", "salary": {"currency": null, "max": null, "min": null, "period": "monthly", "term": null}, "salary_visible": false, "title_keywords": ["analyst"], "responsibilities": ["analysis", "developing", "market research", "presentations", "reports", "ad hoc projects", "research studies"], "requirements": {"degrees": ["degree", "fresh graduate"], "majors": ["business", "related disciplines", "economics"], "languages": ["english", "chinese"], "language_level": ["excellent", "proficiency"], "hard_skills": ["powerpoint", "excel", "writing skills", "ms word"], "soft_skills": ["self-motivated", "work independently", "high sense of responsibility", "diligent", "writing skills", "presentable", "analytical mind", "multi-tasked", "well-organised"], "languages_combined": [{"language": "english", "language_level": ["proficiency", "excellent"]}, {"language": "chinese", "language_level": ["proficiency", "excellent"]}]}, "experience_required": {"duration": ["1-2 years"], "field": ["research"]}}, {"job_id": "100003009054933", "location_code": "hk", "company": "Sun Hung Kai Properties Ltd", "job_title": "SENIOR RESEARCH MANAGER", "description": "Requirements:\n\n\nBachelor\u2019s degree in Statistics, Psychology, Sociology, Languages, Marketing or related disciplines\nMinimum 15 years\u2019 quantitative & qualitative research experience with at least 5 years at managerial level\nGood knowledge on property & retail markets and social analytics in HK & Mainland China\nStrong leadership skills, self-motivated, good work ethnic with positive attitude\nGood project management skills including planning & execution\nGood presentation and report writing skills\nProven English proficiency and fluent Putonghua\nProficiency with SPSS, Excel & PowerPoint. Knowledge on SQL and VBA an advantage\nWilling to work overtime and on public holidays, as well as under pressure\n\nResponsibilities:\n\n\nLead the research & fieldwork team to conduct quantitative, qualitative & social analytics research projects for Hong Kong, Mainland China & Overseas markets in a quality, timely and cost-effective manner\nLead & manage regular customer research reports, ad hoc & new projects and social & digital data analysis to provide findings, insights and recommendations for management or other business units of the Group\nLiaise and coordinate with external vendors/agencies to conduct quantitative and qualitative market research projects in Mainland China\n\nGood remuneration and attractive fringe benefits will be offered to the successful applicant. Interested parties please apply with full resume, present and expected salary, available date by clicking \"Apply Now\".\n\nWe are an equal opportunity employer and welcome applications from all qualified candidates. All personal data collected will be used for recruitment purpose only.\u00a0 Applicants not hearing from us within 3 months may consider their applications unsuccessful.\u00a0 All personal data collected will be destroyed within 24 months.", "employment_types": ["Full Time", "Permanent"], "selling_points": ["Lead research & fieldwork team for HK & PRC proj", "Manage social & digital data analysis", "Willing to work overtime and on public holidays"], "locations": ["Wan Chai"], "categories": ["Professional Services", "Business Analysis / Data Analysis", "Marketing / Public Relations", "Marketing - Market Research", "Property / Real Estate", "Others"], "post_time": "2022-01-17T14:23:18Z", "salary": {"currency": null, "max": null, "min": null, "period": null, "term": null}, "salary_visible": false, "title_keywords": ["manager"], "responsibilities": ["liaise", "cost", "management", "ad hoc", "research projects", "quality", "coordinate with", "market research", "data analysis", "reports"], "requirements": {"degrees": ["degree", "bachelor"], "majors": ["sociology", "psychology", "statistics", "related disciplines", "marketing"], "languages": ["putonghua", "english"], "language_level": ["proficiency", "fluent"], "hard_skills": ["excel", "vba", "powerpoint", "writing skills", "sql", "project management"], "soft_skills": ["self-motivated", "work overtime", "under pressure", "project management skills", "leadership skills", "writing skills", "positive attitude", "presentation"], "languages_combined": [{"language": "putonghua", "language_level": ["fluent", "proficiency"]}, {"language": "english", "language_level": ["proficiency"]}]}, "experience_required": {"duration": ["at least 5 years", "minimum 15 years"], "field": ["managerial", "research"]}}, {"job_id": "100003009052200", "location_code": "hk", "company": "IPSOS Asia Limited", "job_title": "Senior / Research Executive - Qualitative", "description": "Responsibilities:\n\nIdentify and rectify errors from the air traffic data based on multiple rule sets and logics\n\nLiaise with both internal and external parties to clarify errors identified\n\nSafeguard data integrity and maintain data consistency and accuracy to the highest level\n\nMonitor data trends and data changes for anomies\n\nProduce regular traffic reports for AA departments, external business partners and various government departments\n\nConduct market research and provide analytical support to traffic forecast\n\nProvide market intelligence on specific topics as required\n\nRequirements:\n\nDegree holder in Mathematics, Statistics, Economics, Business, Research or any other discipline\n\nA minimum of 1 year experience, preferably in business and market research or quantitative analysis\n\nExperience in aviation industry is an advantage\n\nGood command of spoken and written English and Chinese", "employment_types": ["Full Time", "Permanent"], "selling_points": ["Story telling", "Qualitative research", "Research project execution"], "locations": ["Hung Hom"], "categories": ["Media & Advertising", "Editorial / Journalism", "Marketing / Public Relations", "Marketing - General / Support", "Marketing - Market Research"], "post_time": "2022-01-17T02:26:13Z", "salary": {"currency": null, "max": null, "min": null, "period": "monthly", "term": null}, "salary_visible": false, "title_keywords": ["executive"], "responsibilities": ["data", "conduct market research", "internal and external parties", "monitor", "reports", "maintain data", "forecast", "liaise with"], "requirements": {"degrees": ["degree holder"], "majors": ["business", "mathematics", "economics", "statistics"], "languages": ["english", "chinese"], "language_level": ["good command"], "hard_skills": ["analysis"], "soft_skills": [], "languages_combined": [{"language": "english", "language_level": ["good command"]}, {"language": "chinese", "language_level": ["good command"]}]}, "experience_required": {"duration": ["minimum of 1 year"], "field": ["business", "market research"]}}, {"job_id": "100003009052194", "location_code": "hk", "company": "IPSOS", "job_title": "Research Executive - Healthcare (Quantitative & Qualitative)", "description": "Research Associate (Quantitative)\n\nTop-tier market research agency that is progressive and people focused\nExposure to global leading brands and work variety\nCreate impact by solving exciting problems for diverse clientele\n\nKantar is now seeking confident, inspiring and inquisitive individuals as a Research Associate (Quantitative). \u00a0If you are looking for fun and variety in your everyday work, with an insatiable appetite to try new things and new challenges \u2013 this could be the role for you.\n\nYour job and career:\n\nWork across an exciting mix of brands, industries, and research projects\nAssist in delivering end-to-end quantitative projects with support from senior team members, including project design, proposal writing, planning and research analysis on research projects.\nCoordinate with clients and support client relationships to provide the highest level of servicing\nPut on your creative hat and share your new ideas to find better ways to service clients\nProvide administrative and digital support to the team\nDevelop your professional competence as an insight consultant to clients\u2019 business and marketing challenges.\n\nYou are:\n\nCurious and open minded\nPassionate, enthusiastic team player, and willing to accept responsibility and accountability for work\nSelf-starter, who can manage your own work, projects, prioritize tasks and understand the importance of meeting deadlines.\nStrong analytical thinking and problem-solving skills, with excellent attention to detail\nMulti-tasking and working under pressure come naturally to you.\u00a0\n\nYou have:\n\nUniversity degree, preferably with a major in Business, Marketing, Sociology, Psychology, Philosophy or English\nWorking experience is preferred but not a must\nBasic understanding of quantitative research processes and analysis tools would be an advantage\nGood command in both written and spoken English and Chinese (both Cantonese and Mandarin)\nExceptional written communication \u2013 ability to articulate ideas and present information in an effective way.\nA desire to learn and improve professional competence and knowledge, through formal and informal training\nHigh competence in MS Office, especially PowerPoint\n\nWhat we can offer to you\u2026\n\nThe opportunity to work at the world\u2019s leading technology-enabled data, insights and consultancy company that you can be proud to work for (and brag to your friends about)\nAn international company with presence across the globe, providing the opportunity to work in different markets\nA company continually investing in innovative, digitally focused research solutions that reflect the changing needs of our clients\nFacial coding technology to measure people\u2019s emotional response to advertising\nUsing AI to predict effectiveness of advertising or forecasting future trends for brands\nFully automated intelligence platforms that integrate all sources of data\nHuge variety in the work you do so you won\u2019t get bored \u2013 every day is different!\nLot\u2019s of clients to choose from as we work with many top tier brands locally, regionally and globally\nExposure to a broad spectrum of areas within insights as we cover many domain areas like brand, creative, media & digital, customer experience, analytics, innovation just to name a few\nA diverse and inclusive team, many of whom are from different cultures and backgrounds\nA team that not only values, but encourages individual\u2019s opinions and expression of your ideas\nLot\u2019s and lot\u2019s of learning opportunities aimed at building your knowledge and broadening your skills both professionally and personally e.g. learning tips & tricks on Excel or Powerpoint to learning how to become a better presenter\nA friendly and sociable team that works hard, but also knows how to have fun! Not to mention a cool office with a great view\u2026\n\nCandidates with more experience may be considered as Research Executive (Quantitative). Immediate availability is highly preferred.\n\nFor more details, please visit:\u00a0http://www.kantar.com\n\nInterested parties, please send full resume with expected salary by clicking APPLY NOW. All personal data and applications will be treated in strictly confidential and used for recruitment purpose only.", "employment_types": ["Full Time", "Permanent"], "selling_points": ["Data analysis", "Quantitative and Qualitative research", "Project Management"], "locations": ["Hung Hom"], "categories": ["Marketing / Public Relations", "Marketing - General / Support", "Marketing - Market Research"], "post_time": "2022-01-17T02:26:09Z", "salary": {"currency": null, "max": null, "min": null, "period": "monthly", "term": null}, "salary_visible": false, "title_keywords": ["executive"], "responsibilities": ["ideas", "advertising", "research projects", "data", "analysis", "market research", "design", "develop", "communication", "coordinate with clients", "coding", "planning", "forecasting", "research analysis"], "requirements": {"degrees": ["university degree"], "majors": ["psychology", "business", "sociology", "marketing"], "languages": ["cantonese", "english", "chinese", "mandarin"], "language_level": ["good command"], "hard_skills": ["excel", "basic", "fun", "ai", "analysis", "cool", "powerpoint", "problem-solving skills", "ms office"], "soft_skills": ["under pressure", "focused", "communication", "articulate", "team player", "confident", "presenter", "diverse", "open minded", "creative", "passionate", "sociable", "prioritize", "friendly", "attention to detail", "enthusiastic", "progressive", "problem-solving skills", "accountability", "multi-tasking", "learning", "inspiring", "innovative"], "languages_combined": [{"language": "cantonese", "language_level": ["good command"]}, {"language": "english", "language_level": ["good command"]}, {"language": "chinese", "language_level": ["good command"]}, {"language": "mandarin", "language_level": ["good command"]}]}, "experience_required": {"duration": [], "field": ["digital", "media", "research", "brand"]}}, {"job_id": "100003009054446", "location_code": "hk", "company": "Yougov PLC", "job_title": "Executive/ Associate Manager - Business Development (Market Research)", "description": "Are you looking for a career at one of the world\u2019s largest research organizations?\u00a0\n\nTo cope with the transformation of the research industry and also support our rapidly growing business, we are looking for talents to work with us, who will be provided valuable exposure to a wide spectrum of industries, innovative tools & platforms and insightful analytical frameworks in Hong Kong as well as the APAC region.\n\nWe are looking for a Research Executive to manage projects throughout the entire process from research designs, to draft questionnaires, analyze data and produce deliverables.\u00a0 Fresh graduates are welcome!\n\nDepending on experience, candidates may also be considered for the role of Senior Research Executive.\n\nRole & Responsibilities:\n\nPrepare screeners and invitation letters for recruitment.\nDeliver fieldwork briefing to ensure the interviewers are clear about the purposes and logic of the flow of the screening questionnaires.\nLiaise with fieldwork operations to ensure the progress of recruitment is well communicated and monitored to minimize disruption of delays.\nDesign discussion guides to ensure they prompt meaning findings and are actionable.\nProvide moderation for basic qualitative methodologies, such as focus groups and in-depth interviews.\nAssist senior members on the logistical organization of focus groups.\nAssist senior members on analysis and draft report to present easy-to-read and meaningful linkage to conclusions.\nAssist in proposal preparation and cost estimation to achieve competitiveness and cost effectiveness.\nAssist senior members on ad hoc projects as assigned.\n\n\u00a0Person Specification\n\n\u00a0Qualification:\n\nFresh Graduate\nUniversity degree holder, preferably with major in Psychology, Sociology, Marketing or Languages\n\n\u00a0Knowledge:\n\nMarketing and business learning / knowledge an advantage\nKnowledge of basic qualitative research methodologies\n\n\u00a0Skill:\n\nHold some methodologies on remarking research and techniques\nExcellent command of written English and spoken English and Cantonese\nGood analytical and problem-solving skill\nA positive and proactive team player with good communication skills\nCheerful and sensible personality with good inter-personal skills\nMeticulous, able to handle multiple tasks efficiently and in an organized way\n\n\u00a0Other Requirements:\n\nWillingness to work beyond office hours when required\n\nWe are committed to equality, treating people fairly, promoting a positive and inclusive working environment, and ensuring diversity of people and views. We recognize that this is important for our business success - a more diverse workforce will enable us to reflect better and understand the world we research and ultimately deliver better research and insight to our clients. We understand the importance of choice and offer a blended work environment - office and work from home.\n\nCome to join us if you consider yourself agile, bold, collaborative, determined, and entrepreneurial!\n\nSend us your application to us\u00a0and we will reach back to you for a chat!\n\n\n\n\nAll information collected will be used for recruitment purposes only. The Company may retain applications for future openings or other appropriate positions within the Company. Resumes received will be destroyed within 12 months.", "employment_types": ["Permanent"], "selling_points": [], "locations": ["Not Specified"], "categories": ["Sales, CS & Business Devpt", "Business Development", "Marketing / Public Relations", "Marketing - Market Research", "Others"], "post_time": "2022-01-17T09:40:03Z", "salary": {"currency": null, "max": null, "min": null, "period": null, "term": null}, "salary_visible": false, "title_keywords": ["executive", "associate manager"], "responsibilities": ["cost", "cost estimation", "operations", "analysis", "letters", "design", "communication", "recruitment", "ad hoc projects", "liaise with", "report"], "requirements": {"degrees": [], "majors": [], "languages": [], "language_level": [], "hard_skills": ["agile"], "soft_skills": ["agile", "determined", "collaborative", "bold", "committed", "diverse", "willingness to work", "positive"], "languages_combined": []}, "experience_required": {"duration": [], "field": []}}, {"job_id": "100003009052197", "location_code": "hk", "company": "IPSOS Asia Limited", "job_title": "Temporary Research Assistant (Temp to Perm)", "description": "Are you looking for a career in within one of the world\u2019s largest research organization?\n\nTo cope with the transformation of the research industry and also support our rapidly growing business, we are looking for talents to work with us, who will be provided valuable exposure to a wide spectrum of industries, innovative tools & platforms and insightful analytical frameworks in Hong Kong as well as the APAC region.\n\n\nWe are looking for a Research Executive to manage projects throughout the entire process from research designs, to draft questionnaires, analyze data and produce deliverables.\u00a0 Fresh graduates are welcome!\n\nDepending on experience, candidates may also be considered for the role of Senior Research Executive.\n\nRole Objective / Purpose\n\nThis is an entry level which starts with supporting their respective teams on day to day project implementation. Those with relevant experience may be considered for senior executive position.\n\nThe nitty-gritty:\n\nRole & Responsibilities\uff1a\n\nSupport contents creation for pitches\nPrepare and check research materials, platforms\nMonitor project progress and quality\nAssist in analysis and report preparation\nData management (e.g. respondent list cleaning)\nConduct quantitative interviews with doctors or patients\nWork on qualitative verbatim transcripts or content analysis\nCollect fieldwork materials from doctor\u2019s clinic\nMaterials translation\n\n\u00a0\u00a0Qualification\uff1a\n\n\nFresh graduate\nUniversity degree holder in any discipline (advantage if related to public health, nutrition, finance, marketing, international studies)\nExcellent spoken and written English; Putonghua a plus\n\nWork Location: Whampoa\n\nWe are committed to equality, treating people fairly, promoting a positive and inclusive working environment, and ensuring diversity of people and views. We recognize that this is important for our business success - a more diverse workforce will enable us to reflect better and understand the world we research and ultimately deliver better research and insight to our clients. We understand the importance of choice and offer a blended work environment - office and work from home.\n\nCome to join us if you consider yourself\u00a0agile, bold, collaborative, determined, and entrepreneurial!\u00a0\n\nSend us your application to us\u00a0and we will reach back to you for a chat!\n\n\n\nAll personal information collected will be used for recruitment purposes only. Resumes will be destroyed 12 months after date of receipt.", "employment_types": ["Full Time", "Part Time", "Permanent", "Temporary", "Contract", "Internship", "Freelance"], "selling_points": ["Data analysis", "Quantitative research", "Project Management"], "locations": ["Hung Hom"], "categories": ["Professional Services", "Business Analysis / Data Analysis", "Marketing / Public Relations", "Marketing - General / Support", "Marketing - Market Research"], "post_time": "2022-01-17T02:26:11Z", "salary": {"currency": null, "max": null, "min": null, "period": "monthly", "term": null}, "salary_visible": false, "title_keywords": ["research assistant"], "responsibilities": ["management", "monitor project progress", "data", "analysis", "teams", "implementation", "quality", "manage projects", "cleaning", "contents", "analyze data", "report"], "requirements": {"degrees": ["university degree", "fresh graduate"], "majors": ["finance", "public health", "marketing"], "languages": ["putonghua", "english"], "language_level": ["excellent"], "hard_skills": ["translation", "analysis", "data management", "plus"], "soft_skills": ["innovative"], "languages_combined": [{"language": "putonghua", "language_level": []}, {"language": "english", "language_level": ["excellent"]}]}, "experience_required": {"duration": [], "field": ["research", "relevant experience"]}}, {"job_id": "100003009052198", "location_code": "hk", "company": "IPSOS Asia Limited", "job_title": "Sr./Research Manager (Quantitative)", "description": "The Role\n\nYou will be marketing and driving the growth of YouGov\u2019s business, selling our exciting and innovative products and solutions. You will be working closely and supported by other internal departments to achieve your sales goal and generate new business for Hong Kong.\n\nWhat will I be delivering?\n\nAs a core member of the Business Development team, you will be working towards reaching an individual revenue target, you will do this by:\n\nActively identify new potential customers to sell our exciting and innovative products and solutions\nProactively prospecting, identifying, qualifying and exploring new potential business opportunities through cold calling and networking\nActively build good relationships with existing clients, exploring renewals and up-selling opportunities.\u00a0\nOversee, prepare, and deliver presentations of our solutions to potential clients\nIn charge of your personal target and take ownership in achieving the set-target\nWorking closely with other BU members to generate end-to-end solutions for your clients.\n\nWhat\u2019s in it for me?\n\nYou will join us as a core member of our expanding sales team, working with a group of dynamic and energetic individuals in the Asia Pacific region\nYou will have the chance to network with many senior business leaders across a variety of industries\nYou will working with companies to make better and more informed decisions though the purchase of\u00a0our market leading data and insights products and solutions\nQualifications\n\nWhat do I need to bring with me?\n\nDemonstrated knowledge and experience\n\nExcellent understanding of marketing issues related to consumer brands in Hong Kong\u00a0and across APAC\nMust have experience in the\u00a0media, advertising OR market research industry\nMust have experience in\u00a0new business B2B sales\nSeniority will be allocated based on interview performance and prior experience\nSales hunting experience\u00a0with the mentality of \u2018customer-first\u2019 approach\n\nTechnical skills and qualifications\n\nPreferably a bachelor\u2019s degree in business administration, marketing or related disciplines preferable\nStrong project management experience a plus\nExcellent written, oral and electronic communication skills\nCantonese language is must\nAbility to do client presentations to senior management\n\nBehavioral competencies\n\nA self-starter disposition and an entrepreneurial spirit, aspiring and results-oriented individual\nAbility to persuade, negotiate and work with a high level of autonomy\nGood listening skills to ensure the client's interest is captured correctly\nProblem Solver", "employment_types": ["Full Time", "Permanent"], "selling_points": ["Quantitative Research", "Report Writing", "Proposal Writing"], "locations": ["Hung Hom"], "categories": ["Professional Services", "Business Analysis / Data Analysis", "Marketing / Public Relations", "Marketing - General / Support", "Marketing - Market Research"], "post_time": "2022-01-17T02:26:12Z", "salary": {"currency": null, "max": null, "min": null, "period": "monthly", "term": null}, "salary_visible": false, "title_keywords": ["manager"], "responsibilities": ["advertising", "data", "business opportunities", "market research", "presentations", "communication", "project management", "purchase", "sales team", "senior management", "administration"], "requirements": {"degrees": ["degree", "bachelor"], "majors": ["related disciplines", "marketing", "business administration"], "languages": ["cantonese"], "language_level": [], "hard_skills": ["plus", "presentations", "goal", "make", "dynamic", "project management"], "soft_skills": ["communication skills", "oral", "problem solver", "innovative", "project management", "dynamic", "technical skills", "energetic"], "languages_combined": [{"language": "cantonese", "language_level": []}]}, "experience_required": {"duration": [], "field": ["advertising", "market research", "project management", "business", "media"]}}, {"job_id": "100003009052199", "location_code": "hk", "company": "IPSOS Asia Limited", "job_title": "Senior / Research Executive - Quantitative", "description": "Are you looking for a career at one of the world\u2019s largest research organizations?\u00a0\n\nTo cope with the transformation of the research industry and also support our rapidly growing business, we are looking for talents to work with us, who will be provided valuable exposure to a wide spectrum of industries, innovative tools & platforms and insightful analytical frameworks in Hong Kong as well as the APAC region.\n\nWe are looking for a Temporary Research Assistant to support projects throughout the entire process.\n\n\n\nKey Responsibility:\n\nLiaise with internal teams and counterparts to ensure projects run smoothly, on time, and within budget\nCommunicate with project management and operations teams to positively impact project outcome\nCoordinate and manage data entry of project costs into internal costing program based on research target specifications\nAssist in analyzing research data and secondary sources to deliver stories and narratives to focus on data insights\nSupport content creation for pitches, proposal preparation and delivery by using Ipsos solutions and tools\n\nQualifications:\n\nUniversity degree holder in any discipline\nAnalytical skills and data literacy required\nStrong team player with a positive attitude\nAbility to work in a fast-paced environment\nGood organization and communication skills essential\n\nWe are committed to equality, treating people fairly, promoting a positive and inclusive working environment, and ensuring diversity of people and views. We recognize that this is important for our business success - a more diverse workforce will enable us to reflect better and understand the world we research and ultimately deliver better research and insight to our clients. We understand the importance of choice and offer a blended work environment - office and work from home.\n\nCome to join us if you consider yourself\u00a0agile, bold, collaborative, determined, and entrepreneurial!\n\nSend us your application\u00a0and we will reach back to you for a chat!", "employment_types": ["Full Time", "Permanent"], "selling_points": ["Data analysis", "Quantitative research", "Project Management"], "locations": ["Hung Hom"], "categories": ["Marketing / Public Relations", "Marketing - General / Support", "Marketing - Market Research"], "post_time": "2022-01-17T02:26:12Z", "salary": {"currency": null, "max": null, "min": null, "period": "monthly", "term": null}, "salary_visible": false, "title_keywords": ["executive"], "responsibilities": ["communicate with", "support projects", "data entry", "data", "operations", "budget", "teams", "coordinate", "project management", "communication", "specifications", "liaise with", "costs"], "requirements": {"degrees": ["university degree"], "majors": [], "languages": [], "language_level": [], "hard_skills": ["project management", "focus", "agile", "analytical skills"], "soft_skills": ["communication skills", "agile", "determined", "fast-paced environment", "collaborative", "bold", "analytical skills", "positive attitude", "project management", "committed", "team player", "diverse", "focus", "innovative", "positive"], "languages_combined": []}, "experience_required": {"duration": [], "field": []}}, {"job_id": "100003009052851", "location_code": "hk", "company": "VI Group Service Pty Limited", "job_title": "Digital Marketing Executive", "description": "Are you looking for a career at one of the world\u2019s largest research organizations?\u00a0\nTo cope with the transformation of the research industry and also support our rapidly growing business, we are looking for talents to work with us, who will be provided valuable exposure to a wide spectrum of industries, innovative tools & platforms and insightful analytical frameworks in Hong Kong as well as the APAC region.\nWe are currently looking for a Research Manager to work collaboratively to assist with uncovering and communicating key insights, contexts, and actionable strategies. \u00a0This opportunity to join a globally renowned market research organization can provide valuable experience to anyone with a passion for research.\nDepending on experience, candidates may be considered for the role of Senior Research Manager.\nKey Responsibilities:\nManage and coordinate all aspects of the research process - questionnaire writing, research design, analysis and presentation, and preparation of reports based on client objectives\nProvide strategic advice to help the client understand the research questions or methodologies to address key business challenges\nMaintain project budget and work with the team to ensure smooth operation of studies\nMaintain/ strengthen client relationships and leverage solutions to provide advice on research design, insights, and implications\nContent creation for pitches, proposal preparation, and delivery by using Ipsos solutions and tools\nLiaise regularly with all key internal parties and counterparts to ensure that reliable results are delivered to the client in a timely, cost-efficient manner\nCoach juniors to build their research skills and knowledge to ensure the quality of service\n\u00a0Qualifications:\nUniversity degree holder in any discipline\nAt least 3 years of market research experience at a research agency\nAbility to manage complex, multi-faceted project budgets and to create, manage, and commit to a project\nStrong leadership skills in interactions with junior members and clients\nHighly motivated, self-directed and capable of working within tight deadlines\nExcellent written & verbal communication skills with well-developed interpersonal and presentation skills\nWe are committed to equality, treating people fairly, promoting a positive and inclusive working environment, and ensuring diversity of people and views. We recognize that this is important for our business success - a more diverse workforce will enable us to reflect better and understand the world we research and ultimately deliver better research and insight to our clients. We understand the importance of choice and offer a blended work environment - office and work from home.\n\nCome to join us if you consider yourself\u00a0agile, bold, collaborative, determined, and entrepreneurial!\n\nSend us your application to us\u00a0and we will reach back to you for a chat!", "employment_types": ["Full Time"], "selling_points": ["Google / Facebook ad manager", "Create engaging content for different social media", "Formulate new e-marketing initiatives"], "locations": ["Tsim Sha Tsui"], "categories": ["Marketing / Public Relations", "Marketing - Brand / Product Management", "Marketing - Market Research", "Digital Marketing"], "post_time": "2022-01-17T04:20:22Z", "salary": {"currency": null, "max": null, "min": null, "period": "monthly", "term": null}, "salary_visible": false, "title_keywords": ["digital marketing executive"], "responsibilities": ["liaise", "budgets", "cost", "analysis", "budget", "quality", "market research", "design", "coordinate", "communication", "maintain", "reports", "provide advice", "questionnaire", "internal parties"], "requirements": {"degrees": ["university degree"], "majors": [], "languages": [], "language_level": [], "hard_skills": ["analysis", "agile"], "soft_skills": ["capable", "agile", "leadership skills", "collaborative", "bold", "efficient", "determined", "committed", "diverse", "smooth", "reliable", "interpersonal", "presentation", "communication skills", "positive", "research skills", "passion for", "timely", "presentation skills", "motivated", "innovative"], "languages_combined": []}, "experience_required": {"duration": ["at least 3 years"], "field": ["agency", "research", "market research"]}}, {"job_id": "100003009054021", "location_code": "hk", "company": "Genting Hong Kong Limited", "job_title": "Executive \u2013 Marketing Strategic Planning & Analysis (Marketing)", "description": "Are you looking for a career at one of the world\u2019s largest research organizations?\u00a0\n\nTo cope with the transformation of the research industry and also support our rapidly growing business, we are looking for talents to work with us, who will be provided valuable exposure to a wide spectrum of industries, innovative tools & platforms and insightful analytical frameworks in Hong Kong as well as the APAC region.\n\nWe are looking for a Research Executive to manage projects throughout the entire process from research designs, to draft questionnaires, analyze data and produce deliverables.\u00a0Fresh graduates are welcome!\n\nDepending on experience, candidates may also be considered for the role of\u00a0Senior Research Executive.\n\nKey Responsibility:\n\nLiaise with internal teams and counterparts to ensure projects run smoothly, on time, and within budget\nCommunicate with project management and operations teams to positively impact project outcome\nCoordinate and manage data entry of project costs into internal costing program based on research target specifications\nAssist in analyzing research data and secondary sources to deliver stories and narratives to focus on data insights\nSupport content creation for pitches, proposal preparation and delivery by using Ipsos solutions and tools\n\nQualifications:\n\n\n\nFresh graduate\nUniversity degree holder in any discipline\n1-2 years marketing research experience and correlative marketing experience\nAnalytical skills and data literacy required\nStrong team player with a positive attitude\nAbility to work in a fast-paced environment\nGood organization and communication skills essential\n\nWe are committed to equality, treating people fairly, promoting a positive and inclusive working environment, and ensuring diversity of people and views. We recognize that this is important for our business success - a more diverse workforce will enable us to reflect better and understand the world we research and ultimately deliver better research and insight to our clients. We understand the importance of choice and offer a blended work environment - office and work from home.\n\nCome to join us if you consider yourself\u00a0agile, bold, collaborative, determined, and entrepreneurial!\n\nSend us your application\u00a0and we will reach back to you for a chat!", "employment_types": ["Full Time", "Permanent"], "selling_points": ["Focus on marketing planning & analysis", "Loyalty marketing & CRM exp is an advantage", "MNC working environment , stable 5 days work"], "locations": ["Kwun Tong"], "categories": ["Marketing / Public Relations", "Marketing - Brand / Product Management", "Marketing - Direct Marketing", "Marketing - Market Research"], "post_time": "2022-01-17T08:06:47Z", "salary": {"currency": null, "max": null, "min": null, "period": "monthly", "term": null}, "salary_visible": false, "title_keywords": ["executive"], "responsibilities": ["communicate with", "data entry", "data", "operations", "budget", "teams", "coordinate", "liaise with", "project management", "specifications", "marketing research", "manage projects", "communication", "analyze data", "costs"], "requirements": {"degrees": ["university degree", "fresh graduate"], "majors": [], "languages": [], "language_level": [], "hard_skills": ["project management", "focus", "agile", "analytical skills"], "soft_skills": ["communication skills", "agile", "determined", "fast-paced environment", "collaborative", "bold", "analytical skills", "positive attitude", "project management", "committed", "team player", "diverse", "focus", "innovative", "positive"], "languages_combined": []}, "experience_required": {"duration": ["1-2 years"], "field": ["research", "marketing"]}}, {"job_id": "100003009039038", "location_code": "hk", "company": "Mott MacDonald Hong Kong Limited", "job_title": "Business Support_Marketing Proposal Advisor", "description": "About our Client\n\nOur client is a listed conglomerate with good reputation, they are currently looking for a Research Officer for their Group Research team.\n\nAbout the Role\n\nAs a Group level research team to support all the business entities on quantitative / qualitative research & surveys projects\nAs a Research project lead to liaise with all the stakeholders with both internal and external parties on research requirement\nIs responsible for compiling timely research & analytical reports to all the BUs\nManage & drive quantitative / qualitative research and social analytics for HK & Mainland China projects, from conducting interviews, reporting and recommendations\n\nClick \"Apply Now\" to apply for this position or call Jessky Lee at +852 3180 4930 for a confidential discussion. All information collected will be kept in strict confidence and will be used for recruitment purpose only.", "employment_types": ["Full Time", "Permanent"], "selling_points": ["Manage end-to-end submission process for bids", "8 years\u2019 experience in marketing / submission", "5 days work, 13th month salary, wellness program"], "locations": ["Ngau Tau Kok"], "categories": ["Marketing / Public Relations", "Marketing - Brand / Product Management", "Marketing - General / Support", "Marketing - Market Research"], "post_time": "2022-01-16T21:50:11Z", "salary": {"currency": null, "max": null, "min": null, "period": "monthly", "term": null}, "salary_visible": false, "title_keywords": ["advisor"], "responsibilities": ["reporting", "internal and external parties", "conducting interviews", "reports", "recruitment", "liaise with"], "requirements": {"degrees": [], "majors": [], "languages": [], "language_level": [], "hard_skills": [], "soft_skills": ["timely", "confidence", "responsible"], "languages_combined": []}, "experience_required": {"duration": [], "field": []}}, {"job_id": "100003009054023", "location_code": "hk", "company": "Ztore HK Limited", "job_title": "Growth Graduate Trainee", "description": "Working location:\u00a0Elite Centre in Kwun Tong\n\nResponsibilities\n\nDevelop and refine VIP programs and promotions to drive sales and penetration\nPlan and implement various VIP programs and collaborate with relevant parties to ensure the smooth execution of the programs\nSupport the strategic planning for member programs, promotions and events, including development of new product strategies, marketing programs and evaluation of customer segmentation to the right products & channels\nAssist with the pre and post event analysis of members programs, promotions and events to identify its effectiveness and recommended improvements for development\nAssist with data analysis and generating reports to support business planning\nPerform other ad hoc projects and assignments as required\n\nRequirements\n\nBachelor degree in Marketing, Business Administration or related disciplines\nMinimum 2 years of relevant working experiences\nProficient in PC skills (MS Word, Excel and PowerPoint)\nSelf-motivated, good communication, interpersonal skills and well-organized\nSolid experience in regional work is a plus\nFluent in spoken and written English, Cantonese and Mandarin\nGood at multi-tasking and strives for excellence\nCandidate with less experience will be considered as Senior Officer\n\nGenting Hong Kong is an Equal Opportunity Employer. All applications received will be treated in strict confidence and be used exclusively for recruitment purpose only. If you are not contacted within four weeks, your application will be retained for a period of 1 year and may be presented for other appropriate positions within this period.", "employment_types": ["Full Time"], "selling_points": ["High-flyer. T-shaped talent. Quick to management", "Develop business relationships and cooperation", "bringing in opinions, ideas and insights"], "locations": ["Lai Chi Kok"], "categories": ["Marketing / Public Relations", "Marketing - Market Research", "E-commerce", "Business Development", "Management", "Management Trainee"], "post_time": "2022-01-17T08:07:10Z", "salary": {"currency": null, "max": null, "min": null, "period": "monthly", "term": null}, "salary_visible": false, "title_keywords": ["graduate trainee"], "responsibilities": ["collaborate with", "strategic planning", "analysis", "develop", "data analysis", "reports", "ad hoc projects", "plan", "evaluation", "drive sales", "planning"], "requirements": {"degrees": ["degree", "bachelor"], "majors": ["related disciplines", "marketing", "business administration"], "languages": ["cantonese", "english", "mandarin"], "language_level": ["fluent"], "hard_skills": ["excel", "plus", "powerpoint", "pc skills", "ms word"], "soft_skills": ["self-motivated", "confidence", "well-organized", "communication", "multi-tasking", "interpersonal skills"], "languages_combined": [{"language": "cantonese", "language_level": ["fluent"]}, {"language": "english", "language_level": ["fluent"]}, {"language": "mandarin", "language_level": ["fluent"]}]}, "experience_required": {"duration": ["minimum 2 years"], "field": []}}, {"job_id": "100003009053822", "location_code": "hk", "company": "Squina International Group Limited", "job_title": "Digital Marketing Officer ( e-commerce )", "description": "Job Descriptions\nResponsibilities\n\nServicing a portfolio of clients targeting Hong Kong, Greater China and global markets under the guidance of Account Managers\nManaging holistic digital campaigns covering SEM, SEO, Social Media Marketing, Display Advertising, Video Advertising and more to achieve performance goals\nEnsuring smooth campaign delivery and optimizing results based on data analytics\nWorking closely with Sales Team in campaign delivery and revenue growth\nThe Successful Applicant(s)\n\nResult-oriented challenge taker\nQuick learner - must promptly pick up various advertising platforms and our world-class AI system for campaign optimization and reporting\nIndependent and able to perform well under pressure\nDetail-oriented and organized\nPossessing strategic mindset and strong data analytical skills\nPossessing strong communication and interpersonal skills for building client relationships\nGood command of Chinese, English and Putonghua\nDigital agency background / experience in digital marketing preferred but not a must\nCandidates who are certified with Google Ads are strongly preferred", "employment_types": ["Full Time", "Permanent"], "selling_points": [], "locations": ["Causeway Bay"], "categories": ["Marketing / Public Relations", "Marketing - Brand / Product Management", "Marketing - Direct Marketing", "Marketing - Market Research"], "post_time": "2022-01-17T07:35:06Z", "salary": {"currency": null, "max": null, "min": null, "period": "monthly", "term": null}, "salary_visible": false, "title_keywords": ["digital marketing officer"], "responsibilities": ["guidance", "social media", "reporting", "seo", "advertising", "data", "communication", "sales team", "revenue growth", "sem", "digital campaigns", "digital marketing"], "requirements": {"degrees": [], "majors": [], "languages": ["putonghua", "english", "chinese"], "language_level": ["good command"], "hard_skills": ["seo", "ai", "data analytics", "analytical skills", "sem"], "soft_skills": ["organized", "independent", "quick learner", "detail-oriented", "analytical skills", "communication and interpersonal skills", "smooth", "result-oriented", "perform well under pressure", "world-class"], "languages_combined": [{"language": "putonghua", "language_level": ["good command"]}, {"language": "english", "language_level": ["good command"]}, {"language": "chinese", "language_level": ["good command"]}]}, "experience_required": {"duration": [], "field": ["agency", "digital", "digital marketing"]}}, {"job_id": "100003009052663", "location_code": "hk", "company": "Hong Kong Loving Family Limited", "job_title": "Marketing Assistant / Executive", "description": "Specific Responsibilities\n\nMarket research on clients\u2019 and projects\u2019 pipelines \u2013 clients\u2019 budgets, timeframe, type of consultancy etc.\nArrange regular clients\u2019 meetings, arrange presentation materials and responsible for chasing follow-up actions\nExternal Connection to Institutions \u2013 Explore opportunity to share Professional Excellence to market\nManage Project sheets in centralized locations for bids\nSupport the work winning functions across APNA to achieve best-for-region outcomes\nCollaborating with the APNA Marketing and Communications Manager and the APNA Senior Communications Advisor, support brand & event activities and production of communications (internal and external) as required for Asia.\nAttend weekly (Monday) APNA Proposal scheduling meeting\nAttend weekly catchup with Marketing and Communications Manager and the APNA Senior Communications Advisor\nUpdate and maintain content for the APNA Win Site; maintaining and updating submission libraries, including identifying best-practice examples and projects, and maintaining and updating capability statements and other marketing presentations.\nUndertake coordination activities for the APNA region as required by the Regional Marketing and Communications Manager, Major Pursuits and Strategy Manager and Senior Communications Advisor.\nSupport the use and maintenance of APNA corporate intranet Compass.\n\nDesired skills and expertise\n\nA minimum of eight years\u2019 experience in marketing, submissions and/or communications\nDemonstrated ability to manage teams in the delivery of submissions or proposal documents\nExperience using Adobe InDesign\nExperience working in a fast-paced, deadline-driven environment\nExperience in development of communications and social media materials\nExperience in managing brand and event activities\nAbility to develop and maintain effective internal and external relationships, including outside of your home office\n\nQualifications and experience\n\nQualifications and/or experience in journalism, marketing or communications (or equivalent) are required.\n\nExperience in an engineering, construction or infrastructure environment will also be highly regarded. If successful in this role you\u2019ll be working on significant projects that shape the communities in which we live. You will build connections with our international colleagues and bring this knowledge to our clients and to their projects. There\u2019s no time like the present to make a change.\n\nWe offer competitive remuneration package including\u00a013th month salary, MPF plan\u00a0and\u00a0group medical insurance for dependents.\n\nInterested parties, please click 'Apply now' to submit your application with full resume including your current and expected salary, or send your full resume to recruitment.MMHK @mottmac.com .\n\nTo explore more opportunities with us, please visit www.mottmac.com/careers.\n\nAll personal data collected will be treated in strict confidence and be used for recruitment purpose only.\u00a0\n\nWe are an equal opportunity employer and value diversity at our company. We do not discriminate, and take positive steps to create an inclusive culture.", "employment_types": ["Full Time"], "selling_points": [], "locations": ["Shatin Area"], "categories": ["Marketing / Public Relations", "Marketing - Brand / Product Management", "Marketing - Market Research", "Digital Marketing"], "post_time": "2022-01-17T03:39:58Z", "salary": {"currency": null, "max": null, "min": null, "period": "monthly", "term": null}, "salary_visible": false, "title_keywords": ["marketing assistant", "executive"], "responsibilities": ["budgets", "social media", "maintaining", "maintenance", "infrastructure", "teams", "market research", "presentations", "develop", "scheduling", "maintain", "coordination"], "requirements": {"degrees": [], "majors": [], "languages": [], "language_level": [], "hard_skills": ["no", "maintenance", "pipelines", "adobe indesign", "presentations", "make", "compass"], "soft_skills": ["coordination", "driven", "presentation", "responsible"], "languages_combined": []}, "experience_required": {"duration": ["minimum of eight years"], "field": ["social media", "brand", "engineering", "development", "infrastructure", "marketing", "construction"]}}, {"job_id": "100003009055054", "location_code": "hk", "company": "Amoy Food Ltd", "job_title": "Senior Marketing Executive", "description": "WHY\u00a0are we looking for this position?\n\nAs a fast-growing company in the young but prosperous E-commerce industry in Hong Kong, we are actively building a high talent density team to nurture future young stars specialized in this thriving industry as well as in entrepreneurship. We are looking for like-minded talents to join us in making constructive changes to our society outside the traditional financial or medical sector by contributing in innovative and high-impact company level projects.\n\nHOW\u00a0will you perform in this position?\n\nBe an engine to drive the development and growth of the business through different initiatives\nBe a bridge to connect cross-functional teams to work together smoothly in projects\nBe a listener to understand the needs of different stakeholders and look for the best solution to the problem\nBe a catalyst to the team by bringing in opinions, ideas and insights from multiple perspectives\nBe an adapter to adjust with the fast-changing markets and works in an agile manner\nBe a trailblazer to take on new challenges and explore the unknown\nWHAT duties will you be responsible for?\n\n\nDrive company\u2019s new growth initiatives and push forward the development\nCoordinate projects that involve cross-functional teams to work together\nCommunicate well with different internal teams such as sourcing, product, operation to ensure things are on the right path\nParticipate in cross-functional teams meeting to understand their situation and needs\nAnalyze the performance of initiatives and provide improvement plans to different parties\nDevelop business relationships and cooperation with key business partners\nWHAT will you gain?\n\nExposure across multiple functions, e.g., marketing, sourcing, business development, etc.\nOpportunity to learn and develop in a dynamic Retail/E-Commerce industry\nFlexibility to work and explore without heavy restrictions\nA company culture that encourages knowledge sharing, learning from failure and personal growth\nColleagues that are fun and friendly but willing to challenge each other for the good of the team\nRelax office environment and flexible working hours\nRequirements:\n\nBachelor\u2019s degree in any discipline, fresh graduates are also welcome!\u00a0 \u00a0Strong communication and interpersonal skills\nDetail-minded, responsible, multi-tasking with good organizational skills\nWilling to go for an extra mile for the good of the project/team\nProvide your insights/idea and drive your project proactively\u00a0\nAble to work under high pressure and fast-paced working environment\nEager to learn new knowledge and be adaptable to changes\nAble to finish your work independently and also play an assisting role to the team\nPassion in E-Commerce/Retail/Startup industry\nGood command of written and spoken English and Chinese", "employment_types": ["Full Time", "Permanent"], "selling_points": ["Plan and drive marketing activities", "3-4 years\u2019 relevant experience in FMCG", "5-day week, Shuttle bus, Double pay, Bonus etc."], "locations": ["Tai Po Area"], "categories": ["Marketing / Public Relations", "Marketing - General / Support", "Marketing - Market Research", "Digital Marketing"], "post_time": "2022-01-18T00:58:24Z", "salary": {"currency": null, "max": null, "min": null, "period": "monthly", "term": null}, "salary_visible": false, "title_keywords": ["senior marketing executive"], "responsibilities": ["ideas", "teams", "develop", "coordinate", "communication", "plans", "cross-functional teams"], "requirements": {"degrees": ["degree", "bachelor"], "majors": [], "languages": ["english", "chinese"], "language_level": ["good command"], "hard_skills": ["agile", "fun", "e-commerce", "dynamic", "go"], "soft_skills": ["flexible", "detail-minded", "organizational skills", "work independently", "agile", "responsible", "passion in", "adaptable", "eager to learn", "multi-tasking", "dynamic", "learning", "friendly", "communication and interpersonal skills", "work under high pressure", "innovative", "constructive"], "languages_combined": [{"language": "english", "language_level": ["good command"]}, {"language": "chinese", "language_level": ["good command"]}]}, "experience_required": {"duration": [], "field": []}}, {"job_id": "100003009052433", "location_code": "hk", "company": "Carlsberg Brewery H K Ltd", "job_title": "Channel Marketing Executive (Off-Trade)", "description": "RESPONSIBILITY\n\n\n\nHandle website and online marketing,\u00a0Optimize online promotion mix by managing different social media platforms including Facebook, Instagram, Weibo, WeChat, YouTube, etc., and understanding their strengths and weaknesses\nDeploy brand image strategies, brand building and maximize brand exposure\u00a0\nSupport preparation, implementation and execution of marketing programs\u00a0\nAssist all brand building activities and joint promotions to enhance company visibility and awareness\u00a0\nDevelop editorial coverage to increase brand awareness such as leaflets, advertisements, catalogues, press releases, media kits, direct mails, brand presentations, website / social media contents etc.\nPerform other ad-hoc projects as assigned\nREQUIREMENT\nDegree holder in Marketing or related disciplines\nMinimum 2 years of solid experiences in online marketing, retail industry will be advantage\u00a0\nExcellent communication and writing skill\u00a0\nGood command of English & Chinese with strong interpersonal and problem solving skills\nIndependent, well organized and detail-minded\u00a0\nGood knowledge in online marketing landscape, Experience in online media would be an advantage\nImmediate availability will be an advantage\n\nCompetitive package will be offered to the right candidate including 5-day week, attendance incentive, birthday leave, free goods allowance, medical plan etc. Interested parties, please send resume with expect salary and date of availability. Please visit our website: www.squina.com\n\nAll the personal data collected will be used for recruitment purpose only.", "employment_types": ["Full Time", "Permanent"], "selling_points": ["Ensure channel marketing campaigns are executed", "Market insight to support business growth", "Analyze the ROI of the marketing activities"], "locations": ["Hung Hom"], "categories": ["Marketing / Public Relations", "Marketing - Brand / Product Management", "Marketing - General / Support", "Marketing - Market Research"], "post_time": "2022-01-17T03:00:50Z", "salary": {"currency": null, "max": null, "min": null, "period": "monthly", "term": null}, "salary_visible": false, "title_keywords": ["marketing executive"], "responsibilities": ["social media", "advertisements", "leaflets", "social media platforms", "website", "implementation", "develop", "presentations", "contents", "deploy", "facebook", "ad-hoc projects", "online promotion"], "requirements": {"degrees": ["degree holder"], "majors": ["related disciplines", "marketing"], "languages": ["english", "chinese"], "language_level": ["good command"], "hard_skills": ["problem solving skills", "writing skill"], "soft_skills": ["detail-minded", "independent", "well organized", "writing skill", "communication", "problem solving skills", "interpersonal"], "languages_combined": [{"language": "english", "language_level": ["good command"]}, {"language": "chinese", "language_level": ["good command"]}]}, "experience_required": {"duration": ["minimum 2 years"], "field": ["retail industry", "marketing", "media"]}}, {"job_id": "100003009047484", "location_code": "hk", "company": "The University of Hong Kong", "job_title": "Research Assistant II (Ref.: 511333)", "description": "Responsibilities:\n\nCollect market intelligence in terms of market trend and product performance for strategic marketing planning\nPlan and drive marketing activities to achieve business targets, and evaluate the effectiveness of the activities\nWork closely with internal and external parties to develop ATL & BTL campaigns\nImplement social media strategy, develop social content, handle online promotion & management\nCompile regular reports and participate in ad hoc assignments and projects\n\n\u00a0Requirements:\n\nUniversity degree in Marketing or related discipline\n3-4 years\u2019 relevant experience in FMCG / retail industry/ advertising (Fresh\u00a0graduate will also be\u00a0considered)\u00a0\u00a0\nProactive, detail-oriented and willing to work under pressure and take up new challenges\nGood business sense, logical mind-set with good communication and project management skills, and ability to handle multiple tasks and meet tight deadlines\nProficiency in both written and spoken English and Chinese, as well as computer applications, particularly MS Excel, Powerpoint and Chinese Word Processing\nImmediate available is preferable\nCandidates with less experience will be considered as Marketing Executive\n\nWe offer 5-day work, double pay, year-end discretionary bonus, and excellent career development opportunities to the right candidate.\u00a0 Interested parties please send your resume with current & expected salary and date of availability by clicking \u201cApply Now\u201d.\u00a0 For enquiries, please contact our Recruitment Whatsapp Hotline at 55458814.\u00a0 For more details, please visit www.amoy.com.\n\nAll applications will be treated in strict confidence and retained for 6 months for recruitment purposes only.\u00a0\n\n\n", "employment_types": ["Full Time"], "selling_points": ["Applicants should possess a Bachelor\u2019s degree", "assist in clinical research on pregnancy", "have a good command of English and Cantonese"], "locations": ["Not Specified"], "categories": ["Education", "Others", "Marketing / Public Relations", "Marketing - Market Research", "Medical Services", "Others"], "post_time": "2022-01-14T03:16:05Z", "salary": {"currency": null, "max": null, "min": null, "period": "monthly", "term": null}, "salary_visible": false, "title_keywords": ["research assistant"], "responsibilities": ["strategic marketing planning", "social media", "management", "internal and external parties", "develop", "evaluate", "reports", "ad hoc assignments", "plan", "online promotion"], "requirements": {"degrees": ["university degree", "fresh graduate"], "majors": ["marketing"], "languages": ["english", "chinese"], "language_level": ["proficiency"], "hard_skills": ["project management", "ms excel", "chinese word processing", "powerpoint"], "soft_skills": ["meet tight deadlines", "business sense", "project management skills", "detail-oriented", "communication", "handle multiple tasks", "proactive", "work under pressure"], "languages_combined": [{"language": "english", "language_level": ["proficiency"]}, {"language": "chinese", "language_level": ["proficiency"]}]}, "experience_required": {"duration": ["3-4 years"], "field": ["retail industry", "fmcg", "advertising", "marketing", "relevant experience"]}}, {"job_id": "100003009047438", "location_code": "hk", "company": "The University of Hong Kong", "job_title": "Research Assistant I/II (Ref.: 511395)", "description": "Responsibilities:\u00a0\n\n\nCreate engaging content for different social media platforms and marketing campaigns\nClosely monitor online campaigns and formulate new e-marketing initiatives to generate sales and brand awareness\nMonitor and evaluate campaign performance, assess digital campaign trends, prepare, and handle reporting/data analysis & identify growth opportunities\nHelp grow social media account followers (including Facebook, Instagram, Youtube, Pinterest etc.)\nTranslation and copywriting works for English - Chinese (Traditional)\nOther ad-hoc projects as assigned by management\n\n\u00a0Requirements:\n\nDegree in Marketing, Communication, Journalism, Information Systems or business related discipline\nAbout 2 years\u2019 experience in (digital) marketing\nGood command of Chinese and English copywriting\nGood knowledge of SEO is highly preferred\nExperience with social media, Google Adwords, Google Analytics, email campaigns, facebook Ad Manager is a plus but not essential\nHands-on experience in web CMS is an advantage\nHands-on experience in Illustrator, Photoshop & other graphic and interactive design tools\nKnowledge in photography and video shooting and editing is a plus but not essential\nEnergetic, pro-active, self-motivated and able to work independently\nExcellent communication and interpersonal skills\n\nWe offer attractive remuneration packages to successful candidates:\n\nCompetitive monthly salary commensurate with experience;\nHealth Insurances (Both Medical & Dental);\nFive-day work;\nPaid vacation days;\nIn-house training;\nUnique opportunity for career and self-development.\nIf you are interested in this challenging role, we look forward to discussing this opportunity with you further.\u00a0Interested parties, please submit your application by clicking the apply button.\n\n\nPersonal data collected will be used for recruitment purposes only.\n\n\n\n", "employment_types": ["Full Time"], "selling_points": ["possess a Bachelor\u2019s degree or above", "with experience in computer programming", "with experience in  data management"], "locations": ["Not Specified"], "categories": ["Education", "Others", "Information Technology (IT)", "Others", "Marketing / Public Relations", "Marketing - Market Research"], "post_time": "2022-01-14T03:05:54Z", "salary": {"currency": null, "max": null, "min": null, "period": "monthly", "term": null}, "salary_visible": false, "title_keywords": ["research assistant"], "responsibilities": ["reporting", "social media", "management", "social media platforms", "monitor", "evaluate", "data analysis", "marketing campaigns", "facebook", "ad-hoc projects"], "requirements": {"degrees": ["degree"], "majors": ["journalism", "marketing", "business"], "languages": ["english", "chinese"], "language_level": ["good command"], "hard_skills": ["google analytics", "plus", "seo", "web", "adwords", "illustrator", "facebook", "photoshop"], "soft_skills": ["self-motivated", "work independently", "communication", "hands-on", "communication and interpersonal skills", "pro-active", "energetic"], "languages_combined": [{"language": "english", "language_level": ["good command"]}, {"language": "chinese", "language_level": ["good command"]}]}, "experience_required": {"duration": ["2 years"], "field": ["social media", "design", "graphic", "marketing", "digital"]}}, {"job_id": "100003009052610", "location_code": "hk", "company": "Million (Far East) Limited", "job_title": "Senior Marketing Executive", "description": "Responsibilities:\n\nTake part in\u00a0research projects coordination, quality assurance and data processing\nCoordinate different projects with external clients and interviewers/ mystery shoppers\nPrepare findings and\u00a0analysis reports for clients\n\n\u00a0Requirements:\n\nHigher Diploma or above\nProficient in Microsoft Office\nGood Chinese typing skill\nDetail-oriented, proactive with good communication skills\n\n\u00a0For more information about our company, please visit our website: http://www.tiptop.com.hk/\n\nPersonal data collected will be used for recruitment purpose only.", "employment_types": ["Full Time", "Permanent"], "selling_points": ["Senior Marketing Executive", "Food & Beverage", "Exp. in HORECA, Frozen Meat business preferred"], "locations": ["Kwai Fong"], "categories": ["Marketing / Public Relations", "Marketing - Brand / Product Management", "Marketing - General / Support", "Marketing - Market Research"], "post_time": "2022-01-17T03:32:26Z", "salary": {"currency": null, "max": null, "min": null, "period": "monthly", "term": null}, "salary_visible": false, "title_keywords": ["senior marketing executive"], "responsibilities": ["research projects", "analysis reports", "quality", "data processing", "coordinate", "coordination"], "requirements": {"degrees": ["higher diploma or above"], "majors": [], "languages": ["chinese"], "language_level": ["good"], "hard_skills": ["typing", "microsoft office"], "soft_skills": ["communication skills", "proactive", "detail-oriented"], "languages_combined": [{"language": "chinese", "language_level": ["good"]}]}, "experience_required": {"duration": [], "field": []}}, {"job_id": "100003009049017", "location_code": "hk", "company": "Tiptop Consultants Ltd", "job_title": "Research Executive (Project)", "description": "Degree holder in Real Estate, Surveying, Business Administration or related disciplines\n1-2 years' relevant experience in leasing / marketing of shopping malls with major developers\nTo handle daily leasing activities including new lettings, tenancy renewals, direct marketing and tenancy administrative work\nTo coordinate and follow-up premises takeover / handover\nTo conduct market research and compile reports\nSelf-motivated and dynamic with good communication and presentation skills\nFluent in written and spoken English and Chinese\nWe offer salary and benefits commensurate with qualifications and experience. Please send a full resume with contact number and expected salary to General Manager - Human Resources & Administration, Hutchison Property Group Limited, 3/F., One Harbourfront, 18 Tak Fung Street, Hunghom, Kowloon (Please quote reference on envelope) or by clicking \"Apply Now\".\nWe are an equal opportunity employer and welcome applications from all qualified candidates. The information provided will be treated in strict confidence and be used only for consideration of your application for relevant/similar post(s).\n\nApplicants not hearing from us within six weeks from the date of advertisement may consider their applications unsuccessful. All personal data of unsuccessful applicants will be destroyed after the recruitment exercise when no longer required.", "employment_types": ["Full Time", "Permanent"], "selling_points": ["Research projects coordination", "Projects quality assurance", "Research findings preparation"], "locations": ["Lai Chi Kok"], "categories": ["Professional Services", "Business Consultancy", "Marketing / Public Relations", "Marketing - General / Support", "Marketing - Market Research"], "post_time": "2022-01-14T07:55:41Z", "salary": {"currency": null, "max": null, "min": null, "period": "monthly", "term": null}, "salary_visible": false, "title_keywords": ["executive"], "responsibilities": ["administrative work", "compile reports", "conduct market research", "coordinate", "communication", "administration"], "requirements": {"degrees": ["degree holder"], "majors": ["related disciplines", "business administration", "surveying"], "languages": ["english", "chinese"], "language_level": ["fluent"], "hard_skills": ["dynamic"], "soft_skills": ["communication", "self-motivated", "dynamic", "presentation skills"], "languages_combined": [{"language": "english", "language_level": ["fluent"]}, {"language": "chinese", "language_level": ["fluent"]}]}, "experience_required": {"duration": ["1-2 years"], "field": ["marketing", "relevant experience"]}}, {"job_id": "100003009043208", "location_code": "hk", "company": "Hutchison Property Group Limited", "job_title": "ASSISTANT MARKETING OFFICER [Ref. AMO-HK]", "description": "Job Purpose\nTo develop and implement effective marketing plans to generate quality traffic and spending to maximize tenant turnover growth at both local and tourist markets.\n\n\nKey Responsibilities\n\nPlan and execute monthly/festive programs and activities.\nImplement effective and efficient O2O, interactive and digital initiatives, in supporting the overall branding and traffic Effective content curation which matches with the retail leasing portfolio strategy.\nProactively liaise with strategic partners on tactical campaigns to drive new customers and work with tenants on driving special offers and value-added services to shoppers.\nDevelop detail tactics and ensure excellent execution of marketing programs that generate traffic, stimulate shopper spending to maximize tenant turnover growth and support retail portfolio strategy.\nEnsure seamless communication with vendors and internal departments (eg. Leasing and Property Management) which drive excellent execution.\nRegularly assess effectiveness of marketing program.\nCarefully keep track on marketing expenses by program and ensure within plan or latest forecast.\nCollect, compile, analyse and share market intelligence on macro-trends, consumer behaviour and activities of competitive shopping malls.\nConstantly looks for innovation in program execution from promotional tactic to new medium and creative approach.\n\nSkills, Qualifications and Experience Requirements\n\nDegree holder with at least 6 years\u2019 marketing and communications experience\nExperience in shopping malls and/or retail marketing would be a definite advantage.\nGood connection with strategic partners, e.g. Banks, online payment platforms.\nProven track record of 3rd party co-op campaigns on driving new database and sales opportunity to the business\nStrong analytical and problem-solving skills, mature, self-motivated and result-oriented\nStrong communication, interpersonal, project management and data analysis skills.\nSelf-initiative, creative and detail-oriented.\nStrong sense of responsibility and eager to learn.\nGood in both written and spoken English and Chinese.\nWilling to work on weekends and public holidays.\n\nAn attractive remuneration package will be offered to the right candidate. Interested parties please press \"Apply now\".\n\nHysan is an equal opportunity employer.\u00a0 All information collected will be kept in strict confidence and used solely for recruitment related purposes within the Hysan Group Companies.\n\nYou may get to know more about us through www.hysan.com.hk", "employment_types": ["Full Time", "Permanent"], "selling_points": ["Degree holder", "1-2 years' experience", "To handle daily leasing activities"], "locations": ["Hung Hom"], "categories": ["Marketing / Public Relations", "Marketing - General / Support", "Marketing - Market Research", "Property / Real Estate", "Property Consultancy"], "post_time": "2022-01-17T11:24:48Z", "salary": {"currency": null, "max": null, "min": null, "period": null, "term": null}, "salary_visible": false, "title_keywords": ["assistant marketing officer"], "responsibilities": ["management", "marketing plans", "expenses", "quality", "develop", "communication", "project management", "payment", "data analysis", "plan", "forecast", "liaise with", "database", "analyse"], "requirements": {"degrees": ["degree holder"], "majors": ["marketing", "communications"], "languages": ["english", "chinese"], "language_level": ["good"], "hard_skills": ["problem-solving skills", "macro", "analysis", "project management"], "soft_skills": ["efficient", "self-motivated", "interpersonal", "sense of responsibility", "mature", "detail-oriented", "communication", "project management", "eager to learn", "self-initiative", "problem-solving skills", "creative", "result-oriented"], "languages_combined": [{"language": "english", "language_level": ["good"]}, {"language": "chinese", "language_level": ["good"]}]}, "experience_required": {"duration": ["at least 6 years"], "field": ["marketing", "retail"]}}, {"job_id": "100003009053799", "location_code": "hk", "company": "Hysan Development Co Ltd", "job_title": "Assistant Manager, Event & Promotions", "description": "Job Summary\n\nThis role is responsible for conducting research on real estate sectors in the Greater China region and supporting other service lines.\n\n\u00a0Responsibilities\n\n\nProvide analysis on the Hong Kong and Chinese Mainland property markets\nProduce market reports for external and internal distribution\nDevelop and maintain property market and related databases\nPrepare project and pitching presentation materials\nUndertake daily tasks in the Research & Consultancy Dept\u00a0\n\nRequirements\n\n\n\nDegree in real estate, finance, economics, statistics or a related discipline\nAt least 1-2 years\u2019 relevant experience in property / economic research or consultancy\nA team player who can also work independently\nStrong research & analytical skills and strategic thinking\nSelf-motivated\nGood knowledge of the Hong Kong property market preferred\nExcellent spoken and written English and Cantonese, Mandarin is an advantage\nProficient in MS Word, Excel, PowerPoint and Chinese word processing\n\nCandidates with more experience will be considered for the position of Senior Analyst.\n\n\n\nWe will offer an attractive remuneration package to the right candidate. Interested parties please click \"Apply Now\" below to submit your full r\u00e9sum\u00e9 with available date, and current and expected salaries to the Human Resources Department.\n\nTo learn more about working at Knight Frank, please click here to view our corporate video.\n\nYou are encouraged to read our digital brochure \u201cWhy Knight Frank\u201d to understand how we attract and inspire people to join our exceptional firm.\n\nKnight Frank is an equal opportunity employer. All information submitted will be treated in the strictest confidence and used only for recruitment purposes in accordance with our personal data policy.", "employment_types": ["Full Time", "Permanent"], "selling_points": ["Develop and implement effective marketing plans", "Degree holder with 6 years relevant experience", "5-day work, 14-day AL, Dental, Double Pay + Bonus"], "locations": ["Causeway Bay"], "categories": ["Marketing / Public Relations", "Marketing - Market Research", "Others", "Digital Marketing"], "post_time": "2022-01-17T07:31:55Z", "salary": {"currency": null, "max": null, "min": null, "period": "monthly", "term": null}, "salary_visible": false, "title_keywords": ["assistant manager,"], "responsibilities": ["analysis", "develop", "maintain", "reports", "databases"], "requirements": {"degrees": ["degree"], "majors": ["finance", "economics", "statistics"], "languages": ["cantonese", "english", "chinese", "mandarin"], "language_level": ["advantage", "excellent", "proficient"], "hard_skills": ["excel", "chinese word processing", "powerpoint", "analytical skills", "ms word"], "soft_skills": ["self-motivated", "work independently", "strategic thinking", "analytical skills", "team player"], "languages_combined": [{"language": "cantonese", "language_level": ["excellent"]}, {"language": "english", "language_level": ["excellent"]}, {"language": "chinese", "language_level": ["proficient"]}, {"language": "mandarin", "language_level": ["advantage", "excellent"]}]}, "experience_required": {"duration": ["at least 1-2 years"], "field": ["research", "relevant experience"]}}, {"job_id": "100003009054914", "location_code": "hk", "company": "Cathay Pacific Services Limited", "job_title": "Assistant Project Manager", "description": "Responsibilities:\n\nContribute to strategy and business model design of the business development projects, in particular Greater Bay Area, e-commerce business segment\n\u00a0Assist the Project Manager to organize the needs/requirements from different stakeholders and organize them into an actionable plan\nSupport overall project management execution and work streams deliverables (e.g. project planning, milestones execution and monitoring)\nCoordinate with different stakeholders to organize the project expectations\nEvaluate and identify challenges and utilizes resources to solve problems\nOrganize and track all project documents\nSupport design of project details and solutions through interpreting analysis findings, market information and working with relevant stakeholders (e.g operations, Engineering, IT)\nConduct research and propose initiatives to support the key business development project\u00a0\nKeep abreast on latest technology / best practices within the industry and deliver changes to support the strategy formulation\n\n\u00a0\nRequirements:\n\n\n\nAccredited university bachelor or master degrees\nMinimum 5 years relevant experience preferably in the logistics or consultancy industry, of which minimum 2 years in a supervisory level or above\nPRC exposure is an advantage\nSolid experience in strategic planning, market research and project management\nStrategic thinking mind-set to propose business development initiatives and strategy\nExcellent presentation skills, able to articulate complex ideas in simple terms\nAn effective communicator to interact with people at all levels and in multicultural environment with strong influencing and interpersonal skills\nExtensive PowerPoint knowledge and skills\nHighly motivated and strong perseverance\n\nTo apply, you may simply click the \"Apply Online\" or\u00a0email your confidential resume with date of availability, current and expected salary to\u00a0recruitment @cpsl.com.hk. Applicants not contacted within 6 weeks may consider their applications unsuccessful.\n\nCathay Pacific Services Limited is an Equal Opportunities Employer. Personal data provided by job applicants will be used strictly in accordance with our personal data policy and for recruitment purposes only. Candidates not notified within six weeks may consider their application unsuccessful. All related information will be kept in our file for up to 24 months.\n\n", "employment_types": ["Full Time", "Permanent"], "selling_points": ["Contribute to business development projects", "PRC exposure", "Project Management"], "locations": ["Airport Area"], "categories": ["Transportation & Logistics", "Freight Forwarding", "Marketing / Public Relations", "Marketing - Market Research", "E-commerce", "Business Development"], "post_time": "2022-01-17T13:41:12Z", "salary": {"currency": null, "max": null, "min": null, "period": "monthly", "term": null}, "salary_visible": false, "title_keywords": ["assistant project manager"], "responsibilities": ["project planning", "market information", "operations", "analysis", "monitoring", "coordinate with", "design", "evaluate", "project management", "project documents", "plan", "conduct research"], "requirements": {"degrees": ["bachelor", "master"], "majors": [], "languages": [], "language_level": [], "hard_skills": ["simple", "project management", "powerpoint"], "soft_skills": ["strategic thinking", "project management", "presentation skills", "motivated", "interpersonal skills", "articulate", "communicator", "extensive"], "languages_combined": []}, "experience_required": {"duration": ["minimum 2 years", "minimum 5 years"], "field": ["market research", "project management", "logistics", "relevant experience", "supervisory level", "planning"]}}, {"job_id": "100003009050154", "location_code": "hk", "company": "Magic Search Limited", "job_title": "CRM Analyst (Premium Lifestyle Brand)", "description": "CHINA MOBILE HONG KONG COMPANY LIMITED\u00a0(\"CMHK\") is the wholly-owned subsidiary of China Mobile Limited (HKEx: 941) (NYSE: CHL), which ranks 47th on the Fortune Global 500.\n\nOur company strives to offer superior service experience and to become the preferable digital partner for customers. We are preserving an environment with trust, responsibility and caring. At CMHK, we commit to maximizing people\u2019s potential and paving the way toward success for every striver. We are now inviting high caliber professional to join us.\n\nDivision: Customer Service Division\n\nIn this position, you will:\n\n\nAssist in formulating customer retention strategy to meet KPI on churn management\nConduct customer behavior analysis to provide business insights\nPerform customer segmentation analysis and churn report to spot high churn propensity segments\nConsolidate market survey and competitor\u2019s benchmarking reports\nPlan, implement, monitor and evaluate customer retention programs to reduce customer churn\nDesign reactive retention tools for customer retention\nPrepare customer call list and communication means\nPrepare quality reports, proposal and presentation materials\nAssist in any ad hoc assignments assigned by manager\n\nTo be successful in this position, you should meet the following requirements:\n\nDegree holder in Marketing, Business Administration, Statistics or related disciplines\n5 years\u2019 experience in Marketing, Customer Retention or Analysis, preferably in telecom industry\nStrong analytical ability with good project management and report writing skills is a must\nDetail-minded with good interpersonal skills\nExcellent in Cantonese & English. Mandarin is a plus\nProficient in MS Office ( Excel, Word, PowerPoint and Access) and Chinese Words Processing\nLess experience would considered as Market Data Analyst\u00a0\n\nWhen you work:\n\n5 days work\n8 hours per day\n\nWhat you enjoy:\n\nDouble pay\nDiscretionary bonus\nLife insurance\nMedical insurance\nEducation subsidies\nBirthday gift\nBirthday leave\nStaff discount\n\nCMHK is committed to be an equal opportunity employer. We offer exceptional benefits package and the opportunity to work in a challenging environment. Personal data provided by applicants will be treated strictly in accordance with our personal data policy and for recruitment purposes only.\n\nPlease submit your application to us by clicking\u00a0the\u00a0APPLY NOW\u00a0button and send your full resume with your availability, current and expected salary to us.", "employment_types": ["Full Time"], "selling_points": ["CRM Analysis", "SQL", "EDM"], "locations": ["Not Specified"], "categories": ["Professional Services", "Business Analysis / Data Analysis", "Marketing / Public Relations", "Marketing - Market Research", "Marketing - Marketing Communication"], "post_time": "2022-01-14T09:53:05Z", "salary": {"currency": null, "max": null, "min": null, "period": "monthly", "term": null}, "salary_visible": false, "title_keywords": ["crm analyst"], "responsibilities": ["administration", "management", "analysis", "monitor", "quality", "design", "evaluate", "communication", "project management", "customer service", "reports", "ad hoc assignments", "plan", "insurance", "market data", "report"], "requirements": {"degrees": ["degree holder"], "majors": ["related disciplines", "statistics", "marketing", "business administration"], "languages": ["cantonese", "english", "chinese", "mandarin"], "language_level": ["excellent", "proficient"], "hard_skills": ["excel", "plus", "words", "analysis", "word", "writing skills", "powerpoint", "mobile", "project management", "processing", "ms office"], "soft_skills": ["detail-minded", "writing skills", "communication", "project management", "committed", "customer service", "interpersonal skills", "presentation", "superior"], "languages_combined": [{"language": "cantonese", "language_level": ["excellent"]}, {"language": "english", "language_level": ["excellent"]}, {"language": "chinese", "language_level": ["proficient"]}, {"language": "mandarin", "language_level": []}]}, "experience_required": {"duration": ["5 years"], "field": ["digital", "marketing"]}}, {"job_id": "100003009050977", "location_code": "hk", "company": "Hong Kong Science & Technology Parks Corporation", "job_title": "Assistant Manager, Intelligence Research [JDB/AMIR/220114]", "description": "Our client is a global consumer products brand. They are now hiring a senior manager to focus on consumer insights across the global market.\n\n\nJob Duties:\n\nBuild deep shopper insights capabilities and use state-of-the-art, fit-for-purpose tools and methodologies including digital commerce.\n\n\nExecute regional shopper insights research learning plan including any online activation testing and localize insights for the priority markets\n\n\nSupport regional learning plan and innovation development in collaboration with regional team\n\n\nIdentify distinctive shopper behaviour that can be leveraged to drive conversion. Partner with local category and Customer teams to turn insights into action.\n\n\nAnalyse business and shopper data to identify shopper & customer insights\nUnderstand the shopper journey to identify relevant shopping moments to target\nConduct regular research on site-specific UX for priority retailers across Europe\nCodify needs to Inform and develop digital capabilities to driver iterative testing and efficiency.\n\n\nJob Qualifcation:\n\n\n\nDegree holder with a strong category and insights background in blue chip international FMCG/consumer products company\nDigital experience and/or the understanding of developing activations to unlock impulse considered a plus.\nCategory & Shopper Acumen, Financial & Analytical Acumen, Customer Execution and Measurement, Digital Commerce Acumen\nAbility to navigate complex situations in a multi-cultural environment and challenge the status quo with a can do attitude\n\n\n\nInterested individuals please send CV (word format) to Eleanor Chan (Eleanor . Chan @connectedgroup.com) for more information", "employment_types": ["Full Time"], "selling_points": [], "locations": ["Shatin Area"], "categories": ["Marketing / Public Relations", "Management", "Marketing - Market Research", "Others"], "post_time": "2022-01-14T12:24:06Z", "salary": {"currency": null, "max": null, "min": null, "period": "monthly", "term": null}, "salary_visible": false, "title_keywords": ["assistant manager,"], "responsibilities": ["consumer insights", "data", "teams", "customer insights", "developing", "testing", "develop", "measurement", "plan", "analyse"], "requirements": {"degrees": ["degree holder"], "majors": [], "languages": [], "language_level": [], "hard_skills": ["inform", "plus", "word", "focus", "acumen"], "soft_skills": ["focus", "deep", "learning"], "languages_combined": []}, "experience_required": {"duration": [], "field": ["digital", "developing"]}}, {"job_id": "100003009054951", "location_code": "hk", "company": "Kin Shun Information Technology Limited", "job_title": "Senior Marketing & Public Relations Manager", "description": "Responsibilities:\n\u00a0In view of the rapid expansion and continuous growth of the Corporation, we are looking for a high-calibre to support the Business Development team bringing the top-notch global Innovation and Technology (I&T)\u00a0companies to set up research and development operation in HKSTP.\nMajor responsibilities are listed below:\nSource and identify potential start-ups & scales-ups to business development team for engagement through research in the key market intelligence platform.\nLead research to understand emerging innovations and technologies across Biotech, Property Technology AI & Robotic, Smart Mobility, Fintech, Microelectronics, Industry 4.0 sectors.\nDelivers reports and makes insights/recommendations of key findings to improve business outcomes and support growth strategy initiatives.\nSummarize and consolidate the information into actionable items.\nKeep abreast of the latest technology trend across the global.\nDevelop strong partnerships with cross-functional teams.\nPerforms other related duties as assigned.\nRequirements:\u00a0\nBachelor\u2019s degree in business, Marketing, Data Science, Statistics, or related field required.\nMinimum 5+ years experience in market research or related field, engineering background is preferred.\nExcellent organizational skills and attention to detail.\nSuperior research and analytical skills.\nAbility to translate complex concepts and methodologies into easily understood language.\nExcellent project management and business writing skills.\nExcellent interpersonal, presentation and communication skills.\nCreative, self-driven and customer-oriented.\nProficient in both written and spoken English and Chinese (including Putonghua)\nCandidates with more experience may be considered as manager.\n[This position is open for referral by Recruitment agencies. The profile should be sent to our HR email address\u00a0a g e n c y c v @ h k s t p . o r g]\nWe offer market competitive compensation, 5-day work week, and generous benefits including medical and life insurance; and voluntary contribution in addition to the legal minimum MPF.\u00a0 To apply, please send your full resume with current and expected salary to the Human Resources & Office Administration Department, Hong Kong Science and Technology Parks Corporation, 5/F, Building 5E, 5 Science Park East Avenue, Hong Kong Science Park, Hong Kong or, by email via \"Apply Now\"\u00a0on or before 27 January 2022.\u00a0 \u00a0Please quote the reference number on the email subject/envelope and the application letter.\u00a0\u00a0\nPersonal data provided will be treated in strict confidence and used for recruitment purpose only.\u00a0 All personal data collected will be used strictly in accordance with employer\u2019s personal data policies, you can access to HKSTP\u2019s Personal Information Collection Statement at https://www.hkstp.org/hkstp_web/en/hkstp/personal-information-collection-statement-recruitment\nApplicants not invited for interview within four weeks after application deadline may consider their applications unsuccessful.\u00a0 Personal data of unsuccessful applicants will be retained for a maximum of two years.\u00a0\nwww.hkstp.org", "employment_types": ["Full Time", "Permanent"], "selling_points": [], "locations": ["Lai Chi Kok"], "categories": ["Media & Advertising", "Creative / Design", "Marketing / Public Relations", "Marketing - Market Research"], "post_time": "2022-01-17T14:54:46Z", "salary": {"currency": null, "max": null, "min": null, "period": "monthly", "term": null}, "salary_visible": false, "title_keywords": ["manager"], "responsibilities": ["reports", "cross-functional teams", "develop"], "requirements": {"degrees": ["degree", "bachelor"], "majors": ["data science", "business", "statistics", "marketing"], "languages": ["putonghua", "english", "chinese"], "language_level": ["proficient"], "hard_skills": ["writing skills", "analytical skills", "project management", "c", "r"], "soft_skills": ["organizational skills", "communication skills", "presentation", "driven", "writing skills", "analytical skills", "project management", "customer-oriented", "attention to detail", "creative", "interpersonal", "superior"], "languages_combined": [{"language": "putonghua", "language_level": []}, {"language": "english", "language_level": ["proficient"]}, {"language": "chinese", "language_level": ["proficient"]}]}, "experience_required": {"duration": ["minimum 5+ years"], "field": ["related", "engineering", "market research"]}}, {"job_id": "100003009056064", "location_code": "hk", "company": "Wong\u2019s Electronics Company Limited", "job_title": "Assistant Manager, Marketing and Research Analytics", "description": "Role Summary:\n\nWith the aim to diversify our business, our management is actively developing opportunities in other business sectors.\u00a0\n\nTo copy with our growth, we are looking for a high caliber candidate for the position of Assistant Manager, Marketing and Research Analytics.\n\nResponsibilities:\n\nResponsible for all-round market research across different potential industries including data collection, figures analysis and market trend forecast;\nConduct in-depth analysis covering business models, customers\u2019 preferences and needs, branding and risk assessment;\nProvide regular market intelligence and competitors analysis for strategic planning and decision making;\nPrepare periodical reports in sales performance analysis, budgeting, costing and forecasting;\nPerform ad-hoc tasks as required.\n\n\u00a0Requirements:\n\nDegree holder in Business Administration, Marketing, Finance or related discipline;\nMinimum 5 years of experience in market research and data analysis;\nKnowledge and experience in merger & acquisition, franchise, emerging business is highly preferred;\nStrong business sense, analytical, detail-oriented and self-initiative;\nEnthusiastic, sensitive in market changes and future trends, able to use initiative to come up with new ideas;\nGood command of spoken and written English, Cantonese and Putonghua;\nAble to travel when required.", "employment_types": ["Full Time", "Permanent"], "selling_points": ["All-round market research", "Data analysis", "5 days work week"], "locations": ["Ngau Tau Kok"], "categories": ["Marketing / Public Relations", "Marketing - General / Support", "Marketing - Market Research", "Sales, CS & Business Devpt", "Sales Administration"], "post_time": "2022-01-18T03:14:43Z", "salary": {"currency": null, "max": null, "min": null, "period": "monthly", "term": null}, "salary_visible": false, "title_keywords": ["assistant manager,"], "responsibilities": ["strategic planning", "sales performance", "analysis", "budgeting", "ad-hoc tasks", "market research", "reports", "forecast", "data collection", "forecasting"], "requirements": {"degrees": ["degree holder"], "majors": ["finance", "marketing", "business administration"], "languages": ["cantonese", "putonghua", "english"], "language_level": ["good command"], "hard_skills": ["analysis"], "soft_skills": ["business sense", "detail-oriented", "self-initiative", "enthusiastic", "initiative", "sensitive"], "languages_combined": [{"language": "cantonese", "language_level": ["good command"]}, {"language": "putonghua", "language_level": ["good command"]}, {"language": "english", "language_level": ["good command"]}]}, "experience_required": {"duration": ["minimum 5 years"], "field": ["data analysis", "business", "market research"]}}, {"job_id": "100003009055970", "location_code": "hk", "company": "Airport Authority Hong Kong", "job_title": "Research Officer, Corporate Planning", "description": "Responsibilities:\n\nIdentify and rectify errors from the air traffic data based on multiple rule sets and logics\n\nLiaise with both internal and external parties to clarify errors identified\n\nSafeguard data integrity and maintain data consistency and accuracy to the highest level\n\nMonitor data trends and data changes for anomies\n\nProduce regular traffic reports for AA departments, external business partners and various government departments\n\nConduct market research and provide analytical support to traffic forecast\n\nProvide market intelligence on specific topics as required\n\nRequirements:\n\nDegree holder in Mathematics, Statistics, Economics, Business, Research or any other discipline\n\nA minimum of 1 year experience, preferably in business and market research or quantitative analysis\n\nExperience in aviation industry is an advantage\n\nGood command of spoken and written English and Chinese", "employment_types": ["Full Time"], "selling_points": ["Identify errors from the air traffic data", "Monitor data trends and data changes for anomies", "Conduct market research and produce traffic report"], "locations": ["Airport Area"], "categories": ["Professional Services", "Business Analysis / Data Analysis", "Marketing / Public Relations", "Marketing - Market Research", "Sciences, Lab, R&D", "Research & Development (R&D)"], "post_time": "2022-01-18T03:08:28Z", "salary": {"currency": null, "max": null, "min": null, "period": "monthly", "term": null}, "salary_visible": false, "title_keywords": ["research officer"], "responsibilities": ["data", "conduct market research", "internal and external parties", "monitor", "reports", "maintain data", "forecast", "liaise with"], "requirements": {"degrees": ["degree holder"], "majors": ["business", "mathematics", "economics", "statistics"], "languages": ["english", "chinese"], "language_level": ["good command"], "hard_skills": ["analysis"], "soft_skills": [], "languages_combined": [{"language": "english", "language_level": ["good command"]}, {"language": "chinese", "language_level": ["good command"]}]}, "experience_required": {"duration": ["minimum of 1 year"], "field": ["business", "market research"]}}, {"job_id": "100003009054531", "location_code": "hk", "company": "Kantar Hong Kong Limited", "job_title": "Research Associate/ Research Executive (Quantitative)", "description": "Research Associate (Quantitative)\n\nTop-tier market research agency that is progressive and people focused\nExposure to global leading brands and work variety\nCreate impact by solving exciting problems for diverse clientele\n\nKantar is now seeking confident, inspiring and inquisitive individuals as a Research Associate (Quantitative). \u00a0If you are looking for fun and variety in your everyday work, with an insatiable appetite to try new things and new challenges \u2013 this could be the role for you.\n\nYour job and career:\n\nWork across an exciting mix of brands, industries, and research projects\nAssist in delivering end-to-end quantitative projects with support from senior team members, including project design, proposal writing, planning and research analysis on research projects.\nCoordinate with clients and support client relationships to provide the highest level of servicing\nPut on your creative hat and share your new ideas to find better ways to service clients\nProvide administrative and digital support to the team\nDevelop your professional competence as an insight consultant to clients\u2019 business and marketing challenges.\n\nYou are:\n\nCurious and open minded\nPassionate, enthusiastic team player, and willing to accept responsibility and accountability for work\nSelf-starter, who can manage your own work, projects, prioritize tasks and understand the importance of meeting deadlines.\nStrong analytical thinking and problem-solving skills, with excellent attention to detail\nMulti-tasking and working under pressure come naturally to you.\u00a0\n\nYou have:\n\nUniversity degree, preferably with a major in Business, Marketing, Sociology, Psychology, Philosophy or English\nWorking experience is preferred but not a must\nBasic understanding of quantitative research processes and analysis tools would be an advantage\nGood command in both written and spoken English and Chinese (both Cantonese and Mandarin)\nExceptional written communication \u2013 ability to articulate ideas and present information in an effective way.\nA desire to learn and improve professional competence and knowledge, through formal and informal training\nHigh competence in MS Office, especially PowerPoint\n\nWhat we can offer to you\u2026\n\nThe opportunity to work at the world\u2019s leading technology-enabled data, insights and consultancy company that you can be proud to work for (and brag to your friends about)\nAn international company with presence across the globe, providing the opportunity to work in different markets\nA company continually investing in innovative, digitally focused research solutions that reflect the changing needs of our clients\nFacial coding technology to measure people\u2019s emotional response to advertising\nUsing AI to predict effectiveness of advertising or forecasting future trends for brands\nFully automated intelligence platforms that integrate all sources of data\nHuge variety in the work you do so you won\u2019t get bored \u2013 every day is different!\nLot\u2019s of clients to choose from as we work with many top tier brands locally, regionally and globally\nExposure to a broad spectrum of areas within insights as we cover many domain areas like brand, creative, media & digital, customer experience, analytics, innovation just to name a few\nA diverse and inclusive team, many of whom are from different cultures and backgrounds\nA team that not only values, but encourages individual\u2019s opinions and expression of your ideas\nLot\u2019s and lot\u2019s of learning opportunities aimed at building your knowledge and broadening your skills both professionally and personally e.g. learning tips & tricks on Excel or Powerpoint to learning how to become a better presenter\nA friendly and sociable team that works hard, but also knows how to have fun! Not to mention a cool office with a great view\u2026\n\nCandidates with more experience may be considered as Research Executive (Quantitative). Immediate availability is highly preferred.\n\nFor more details, please visit:\u00a0http://www.kantar.com\n\nInterested parties, please send full resume with expected salary by clicking APPLY NOW. All personal data and applications will be treated in strictly confidential and used for recruitment purpose only.", "employment_types": ["Full Time"], "selling_points": ["Quantitative Research", "Exposure to global leading brands", "Create impact by solving exciting problems"], "locations": ["North Point"], "categories": ["Marketing / Public Relations", "Marketing - Brand / Product Management", "Marketing - General / Support", "Marketing - Market Research"], "post_time": "2022-01-17T16:21:06Z", "salary": {"currency": null, "max": null, "min": null, "period": "monthly", "term": null}, "salary_visible": false, "title_keywords": ["research associate", "executive"], "responsibilities": ["ideas", "advertising", "research projects", "data", "analysis", "market research", "design", "develop", "communication", "coordinate with clients", "coding", "planning", "forecasting", "research analysis"], "requirements": {"degrees": ["university degree"], "majors": ["psychology", "business", "sociology", "marketing"], "languages": ["cantonese", "english", "chinese", "mandarin"], "language_level": ["good command"], "hard_skills": ["excel", "basic", "fun", "ai", "analysis", "cool", "powerpoint", "problem-solving skills", "ms office"], "soft_skills": ["under pressure", "focused", "communication", "articulate", "team player", "confident", "presenter", "diverse", "open minded", "creative", "passionate", "sociable", "prioritize", "friendly", "attention to detail", "enthusiastic", "progressive", "problem-solving skills", "accountability", "multi-tasking", "learning", "inspiring", "innovative"], "languages_combined": [{"language": "cantonese", "language_level": ["good command"]}, {"language": "english", "language_level": ["good command"]}, {"language": "chinese", "language_level": ["good command"]}, {"language": "mandarin", "language_level": ["good command"]}]}, "experience_required": {"duration": [], "field": ["digital", "media", "research", "brand"]}}, {"job_id": "100003009056011", "location_code": "hk", "company": "KOS International Limited", "job_title": "(Sr) Research Officer - Qualitative / Quantitative (in-house)", "description": "About our Client\n\nOur client is a listed conglomerate with good reputation, they are currently looking for a Research Officer for their Group Research team.\n\nAbout the Role\n\nAs a Group level research team to support all the business entities on quantitative / qualitative research & surveys projects\nAs a Research project lead to liaise with all the stakeholders with both internal and external parties on research requirement\nIs responsible for compiling timely research & analytical reports to all the BUs\nManage & drive quantitative / qualitative research and social analytics for HK & Mainland China projects, from conducting interviews, reporting and recommendations\n\nClick \"Apply Now\" to apply for this position or call Jessky Lee at +852 3180 4930 for a confidential discussion. All information collected will be kept in strict confidence and will be used for recruitment purpose only.", "employment_types": ["Full Time", "Permanent"], "selling_points": ["Looking for a career change?", "Good project management skills", "Innovative & Creative Role"], "locations": ["Wan Chai"], "categories": ["Marketing / Public Relations", "Marketing - Market Research"], "post_time": "2022-01-18T03:11:23Z", "salary": {"currency": null, "max": null, "min": null, "period": "monthly", "term": null}, "salary_visible": false, "title_keywords": ["research officer"], "responsibilities": ["reporting", "internal and external parties", "conducting interviews", "reports", "recruitment", "liaise with"], "requirements": {"degrees": [], "majors": [], "languages": [], "language_level": [], "hard_skills": [], "soft_skills": ["timely", "confidence", "responsible"], "languages_combined": []}, "experience_required": {"duration": [], "field": []}}, {"job_id": "100003009056428", "location_code": "hk", "company": "Digioo Limited", "job_title": "Digital Trainee / Account Executive", "description": "Job Descriptions\nResponsibilities\n\nServicing a portfolio of clients targeting Hong Kong, Greater China and global markets under the guidance of Account Managers\nManaging holistic digital campaigns covering SEM, SEO, Social Media Marketing, Display Advertising, Video Advertising and more to achieve performance goals\nEnsuring smooth campaign delivery and optimizing results based on data analytics\nWorking closely with Sales Team in campaign delivery and revenue growth\nThe Successful Applicant(s)\n\nResult-oriented challenge taker\nQuick learner - must promptly pick up various advertising platforms and our world-class AI system for campaign optimization and reporting\nIndependent and able to perform well under pressure\nDetail-oriented and organized\nPossessing strategic mindset and strong data analytical skills\nPossessing strong communication and interpersonal skills for building client relationships\nGood command of Chinese, English and Putonghua\nDigital agency background / experience in digital marketing preferred but not a must\nCandidates who are certified with Google Ads are strongly preferred", "employment_types": ["Full Time"], "selling_points": ["Managing holistic digital campaigns", "Ensuring campaign delivery & optimizing results", "Digital agency background / experience"], "locations": ["Mong Kok"], "categories": ["Marketing / Public Relations", "Marketing - Brand / Product Management", "Marketing - Market Research", "Digital Marketing"], "post_time": "2022-01-18T04:16:49Z", "salary": {"currency": null, "max": null, "min": null, "period": "monthly", "term": null}, "salary_visible": false, "title_keywords": ["account executive", "trainee"], "responsibilities": ["guidance", "social media", "reporting", "seo", "advertising", "data", "communication", "sales team", "revenue growth", "sem", "digital campaigns", "digital marketing"], "requirements": {"degrees": [], "majors": [], "languages": ["putonghua", "english", "chinese"], "language_level": ["good command"], "hard_skills": ["seo", "ai", "data analytics", "analytical skills", "sem"], "soft_skills": ["organized", "independent", "quick learner", "detail-oriented", "analytical skills", "communication and interpersonal skills", "smooth", "result-oriented", "perform well under pressure", "world-class"], "languages_combined": [{"language": "putonghua", "language_level": ["good command"]}, {"language": "english", "language_level": ["good command"]}, {"language": "chinese", "language_level": ["good command"]}]}, "experience_required": {"duration": [], "field": ["agency", "digital", "digital marketing"]}}, {"job_id": "100003009042482", "location_code": "hk", "company": "Knight Frank Petty Ltd", "job_title": "Analyst, Research & Consultancy", "description": "Job Summary\n\nThis role is responsible for conducting research on real estate sectors in the Greater China region and supporting other service lines.\n\n\u00a0Responsibilities\n\n\nProvide analysis on the Hong Kong and Chinese Mainland property markets\nProduce market reports for external and internal distribution\nDevelop and maintain property market and related databases\nPrepare project and pitching presentation materials\nUndertake daily tasks in the Research & Consultancy Dept\u00a0\n\nRequirements\n\n\n\nDegree in real estate, finance, economics, statistics or a related discipline\nAt least 1-2 years\u2019 relevant experience in property / economic research or consultancy\nA team player who can also work independently\nStrong research & analytical skills and strategic thinking\nSelf-motivated\nGood knowledge of the Hong Kong property market preferred\nExcellent spoken and written English and Cantonese, Mandarin is an advantage\nProficient in MS Word, Excel, PowerPoint and Chinese word processing\n\nCandidates with more experience will be considered for the position of Senior Analyst.\n\n\n\nWe will offer an attractive remuneration package to the right candidate. Interested parties please click \"Apply Now\" below to submit your full r\u00e9sum\u00e9 with available date, and current and expected salaries to the Human Resources Department.\n\nTo learn more about working at Knight Frank, please click here to view our corporate video.\n\nYou are encouraged to read our digital brochure \u201cWhy Knight Frank\u201d to understand how we attract and inspire people to join our exceptional firm.\n\nKnight Frank is an equal opportunity employer. All information submitted will be treated in the strictest confidence and used only for recruitment purposes in accordance with our personal data policy.", "employment_types": ["Full Time", "Permanent"], "selling_points": ["Produce research and analysis reports", "Provide analysis on the Real Estate Market", "1 - 2 years' research experience in property field"], "locations": ["Wan Chai"], "categories": ["Professional Services", "Business Analysis / Data Analysis", "Marketing / Public Relations", "Marketing - Market Research", "Property / Real Estate", "Property Consultancy"], "post_time": "2022-01-12T07:41:04Z", "salary": {"currency": null, "max": null, "min": null, "period": "monthly", "term": null}, "salary_visible": false, "title_keywords": ["analyst"], "responsibilities": ["analysis", "develop", "maintain", "reports", "databases"], "requirements": {"degrees": ["degree"], "majors": ["finance", "economics", "statistics"], "languages": ["cantonese", "english", "chinese", "mandarin"], "language_level": ["advantage", "excellent", "proficient"], "hard_skills": ["excel", "chinese word processing", "powerpoint", "analytical skills", "ms word"], "soft_skills": ["self-motivated", "work independently", "strategic thinking", "analytical skills", "team player"], "languages_combined": [{"language": "cantonese", "language_level": ["excellent"]}, {"language": "english", "language_level": ["excellent"]}, {"language": "chinese", "language_level": ["proficient"]}, {"language": "mandarin", "language_level": ["advantage", "excellent"]}]}, "experience_required": {"duration": ["at least 1-2 years"], "field": ["research", "relevant experience"]}}, {"job_id": "100003009049735", "location_code": "hk", "company": "China Mobile Hong Kong \u4e2d\u570b\u79fb\u52d5\u9999\u6e2f", "job_title": "Senior Market Data Analyst - Retention", "description": "CHINA MOBILE HONG KONG COMPANY LIMITED\u00a0(\"CMHK\") is the wholly-owned subsidiary of China Mobile Limited (HKEx: 941) (NYSE: CHL), which ranks 47th on the Fortune Global 500.\n\nOur company strives to offer superior service experience and to become the preferable digital partner for customers. We are preserving an environment with trust, responsibility and caring. At CMHK, we commit to maximizing people\u2019s potential and paving the way toward success for every striver. We are now inviting high caliber professional to join us.\n\nDivision: Customer Service Division\n\nIn this position, you will:\n\n\nAssist in formulating customer retention strategy to meet KPI on churn management\nConduct customer behavior analysis to provide business insights\nPerform customer segmentation analysis and churn report to spot high churn propensity segments\nConsolidate market survey and competitor\u2019s benchmarking reports\nPlan, implement, monitor and evaluate customer retention programs to reduce customer churn\nDesign reactive retention tools for customer retention\nPrepare customer call list and communication means\nPrepare quality reports, proposal and presentation materials\nAssist in any ad hoc assignments assigned by manager\n\nTo be successful in this position, you should meet the following requirements:\n\nDegree holder in Marketing, Business Administration, Statistics or related disciplines\n5 years\u2019 experience in Marketing, Customer Retention or Analysis, preferably in telecom industry\nStrong analytical ability with good project management and report writing skills is a must\nDetail-minded with good interpersonal skills\nExcellent in Cantonese & English. Mandarin is a plus\nProficient in MS Office ( Excel, Word, PowerPoint and Access) and Chinese Words Processing\nLess experience would considered as Market Data Analyst\u00a0\n\nWhen you work:\n\n5 days work\n8 hours per day\n\nWhat you enjoy:\n\nDouble pay\nDiscretionary bonus\nLife insurance\nMedical insurance\nEducation subsidies\nBirthday gift\nBirthday leave\nStaff discount\n\nCMHK is committed to be an equal opportunity employer. We offer exceptional benefits package and the opportunity to work in a challenging environment. Personal data provided by applicants will be treated strictly in accordance with our personal data policy and for recruitment purposes only.\n\nPlease submit your application to us by clicking\u00a0the\u00a0APPLY NOW\u00a0button and send your full resume with your availability, current and expected salary to us.", "employment_types": ["Full Time", "Permanent"], "selling_points": ["Formulate customer retention strategy", "Conduct customer behavior, segmentation analysis", "Consolidate market survey"], "locations": ["Kwai Hing"], "categories": ["Marketing / Public Relations", "Marketing - Brand / Product Management", "Marketing - Market Research"], "post_time": "2022-01-14T09:10:54Z", "salary": {"currency": null, "max": null, "min": null, "period": null, "term": null}, "salary_visible": false, "title_keywords": ["data analyst"], "responsibilities": ["administration", "management", "analysis", "monitor", "quality", "design", "evaluate", "communication", "project management", "customer service", "reports", "ad hoc assignments", "plan", "insurance", "market data", "report"], "requirements": {"degrees": ["degree holder"], "majors": ["related disciplines", "statistics", "marketing", "business administration"], "languages": ["cantonese", "english", "chinese", "mandarin"], "language_level": ["excellent", "proficient"], "hard_skills": ["excel", "plus", "words", "analysis", "word", "writing skills", "powerpoint", "mobile", "project management", "processing", "ms office"], "soft_skills": ["detail-minded", "writing skills", "communication", "project management", "committed", "customer service", "interpersonal skills", "presentation", "superior"], "languages_combined": [{"language": "cantonese", "language_level": ["excellent"]}, {"language": "english", "language_level": ["excellent"]}, {"language": "chinese", "language_level": ["proficient"]}, {"language": "mandarin", "language_level": []}]}, "experience_required": {"duration": ["5 years"], "field": ["digital", "marketing"]}}, {"job_id": "100003009056063", "location_code": "hk", "company": "ConnectedGroup Limited", "job_title": "Global Senior Manager, Customer & Insights (FMCG 1.3M)", "description": "Our client is a global consumer products brand. They are now hiring a senior manager to focus on consumer insights across the global market.\n\n\nJob Duties:\n\nBuild deep shopper insights capabilities and use state-of-the-art, fit-for-purpose tools and methodologies including digital commerce.\n\n\nExecute regional shopper insights research learning plan including any online activation testing and localize insights for the priority markets\n\n\nSupport regional learning plan and innovation development in collaboration with regional team\n\n\nIdentify distinctive shopper behaviour that can be leveraged to drive conversion. Partner with local category and Customer teams to turn insights into action.\n\n\nAnalyse business and shopper data to identify shopper & customer insights\nUnderstand the shopper journey to identify relevant shopping moments to target\nConduct regular research on site-specific UX for priority retailers across Europe\nCodify needs to Inform and develop digital capabilities to driver iterative testing and efficiency.\n\n\nJob Qualifcation:\n\n\n\nDegree holder with a strong category and insights background in blue chip international FMCG/consumer products company\nDigital experience and/or the understanding of developing activations to unlock impulse considered a plus.\nCategory & Shopper Acumen, Financial & Analytical Acumen, Customer Execution and Measurement, Digital Commerce Acumen\nAbility to navigate complex situations in a multi-cultural environment and challenge the status quo with a can do attitude\n\n\n\nInterested individuals please send CV (word format) to Eleanor Chan (Eleanor . Chan @connectedgroup.com) for more information", "employment_types": ["Full Time", "Permanent"], "selling_points": ["drive insights and foresight", "portfolio strategies", "influencing senior stakeholders"], "locations": ["Not Specified"], "categories": ["Marketing / Public Relations", "Marketing - Market Research"], "post_time": "2022-01-18T03:14:39Z", "salary": {"currency": null, "max": null, "min": null, "period": "monthly", "term": null}, "salary_visible": false, "title_keywords": ["senior manager"], "responsibilities": ["consumer insights", "data", "teams", "customer insights", "developing", "testing", "develop", "measurement", "plan", "analyse"], "requirements": {"degrees": ["degree holder"], "majors": [], "languages": [], "language_level": [], "hard_skills": ["inform", "plus", "word", "focus", "acumen"], "soft_skills": ["focus", "deep", "learning"], "languages_combined": []}, "experience_required": {"duration": [], "field": ["digital", "developing"]}}, {"job_id": "100003009051784", "location_code": "hk", "company": "Keysen (LPB) Management Services Limited", "job_title": "Buying Assistant", "description": "Responsibilities:\n\nSupport the Buyer in all aspects of the buying process and merchandise management including monitoring stock allocation, warehouse schedules and deliveries, and other logistics administration\nAssist in analyzing market trends, merchandise assortment and sales performance on merchandise categories\nPrepare PO analysis report and weekly ordering report\nLiaise with own purchase brand for PO placement with approved OTB budget weekly\nFollow up on order confirmation, ensure prompt delivery, and manage stock re-allocation\nPerform ad hoc duties as assigned\n\nRequirements:\n\nDegree holder in Business Administration or any related disciplines\n1-2 years of experience in buying counter management in beauty store\nHands-on experience in managing multiple own bought brands is highly preferred\nProactive, detail-oriented, self-motivated and able to work under pressure\nGood communication and interpersonal skills\nProficient in MS Office Applications and Chinese Word Processing\nStrong business sense with passion in beauty industry\nGood command of both written and spoken English and Chinese\n\nSalary and benefits will be commensurate with qualifications and experience.\u00a0 Interested parties, please send a full resume with present and expected salary, and date available to The Human Resources Department, 32/F., Great Eagle Centre, 23 Harbour Road, Wanchai, Hong Kong or e-mail to us.\u00a0(Please quote the reference no. on the envelope and the covering letter.)\n\nTo know more about us, please visit our website at http://www.greateagle.com.hk.\n\nWe are an equal opportunity employer and welcome applications from all qualified candidates.\n\nPersonal data collected will be treated in strict confidence and used only for recruitment-related purpose. Applicants who have not heard from us within four weeks may consider their applications unsuccessful. All personal data will be destroyed after 12 months.", "employment_types": ["Full Time", "Permanent"], "selling_points": ["Buying process and merchandise management", "PO analysis", "Beauty store"], "locations": ["Mong Kok"], "categories": ["Beauty Care / Health", "Others", "Marketing / Public Relations", "Marketing - Market Research", "Merchandising & Purchasing", "Procurement / Purchasing / Sourcing"], "post_time": "2022-01-17T01:07:06Z", "salary": {"currency": null, "max": null, "min": null, "period": "monthly", "term": null}, "salary_visible": false, "title_keywords": ["buying assistant"], "responsibilities": ["ad hoc duties", "management", "schedules", "stock allocation", "sales performance", "monitoring", "analysis report", "budget", "otb", "purchase", "logistics", "liaise with", "report", "administration"], "requirements": {"degrees": ["degree holder"], "majors": ["related disciplines", "business administration"], "languages": ["english", "chinese"], "language_level": ["good command", "proficient"], "hard_skills": ["chinese word processing", "ms office"], "soft_skills": ["self-motivated", "business sense", "passion in", "detail-oriented", "hands-on", "communication and interpersonal skills", "proactive", "work under pressure"], "languages_combined": [{"language": "english", "language_level": ["good command"]}, {"language": "chinese", "language_level": ["good command", "proficient"]}]}, "experience_required": {"duration": ["1-2 years"], "field": ["management", "beauty"]}}, {"job_id": "100003009053988", "location_code": "hk", "company": "Kantar Hong Kong Limited", "job_title": "ACCOUNT EXECUTIVE / SENIOR ACCOUNT EXECUTIVE (Kantar Profiles)", "description": "Location / Team\n\nHong Kong, Greater China team, Profiles Division\n\nThe Opportunity\n\nThe Account Executive/ Senior Account Executive will support the Account Directors in the servicing of a range of established clients for various daily sales support functions, such as project consultation, feasibility assessment, pricing, proposal writing, business partners\u2019 liaison and sales admin tasks etc. He or she will also work alongside the Account Managers and Account Directors on new business development responsibilities, such as attending client meetings, presentations, trade shows and other networking events. A team financial target would be given.\n\nThis role would require a high degree of independency and would fit someone with an ambition to become a consultative business developer in the market research and/or professional services industry.\n\nWhat you\u2019ll need to have\u2026\n\n1+ year data collection experience in the market research industry; or strong record under a B2B business development environment, ideally in a digital related industry\nCommercial, Business, Marketing or IT degrees ideal\nExperiences in dealing with multinational clients and suppliers, ideally in MNEs\nAbility to manage multiple tasks whilst working in a fast-paced environment\nExcellent communication (both oral and written), attention to detail and deal closing skills are essential\nHighly Numerate and analytical\nAdept with Microsoft:\u00a0 Word, Excel, Outlook, PowerPoint and the Internet\nFluent in English, Cantonese, and Mandarin\nCandidate with more experience, will be considered as Associate Account Manager\nFresh graduates will also be considered", "employment_types": ["Full Time"], "selling_points": ["Project consultation", "Proposal writing", "Attending networking events"], "locations": ["North Point"], "categories": ["Marketing / Public Relations", "Marketing - Market Research"], "post_time": "2022-01-17T07:56:49Z", "salary": {"currency": null, "max": null, "min": null, "period": "monthly", "term": null}, "salary_visible": false, "title_keywords": ["account executive", "senior account executive"], "responsibilities": ["communication", "data collection", "market research", "presentations"], "requirements": {"degrees": ["degree"], "majors": ["business", "market research"], "languages": ["cantonese", "english", "mandarin"], "language_level": ["fluent"], "hard_skills": ["excel", "sales support", "word", "presentations", "powerpoint", "outlook"], "soft_skills": ["oral", "multiple tasks", "fast-paced environment", "communication", "attention to detail", "adept", "ideal"], "languages_combined": [{"language": "cantonese", "language_level": ["fluent"]}, {"language": "english", "language_level": ["fluent"]}, {"language": "mandarin", "language_level": ["fluent"]}]}, "experience_required": {"duration": ["1+ year"], "field": ["market research"]}}, {"job_id": "100003009047662", "location_code": "hk", "company": "PEI Media (Hong Kong) Co., Limited", "job_title": "Graduate Research Associate", "description": "REPORTS TO\n\nHead of Private Markets Research\n\nRELATES TO\n\nDirector of Research & Analytics, Research Managers, Research Associates (London, HK and NYC)\n\nRESPONSIBLE FOR\n\nCreating and maintaining high-quality information and intelligence on the activities of fund managers in private markets.\n\nRole\nThe research associate forms part of a global team responsible for the research and maintenance of several online intelligence services that track the flow of capital between investors (LPs) and fund managers (GPs) active in the alternative asset classes.\n\nWe strive to ensure that opportunities to work and develop at PEI Media are fair, inclusive, and open to all. We welcome applications from all qualified candidates, regardless of age, disability, gender identity, or gender expression, race, ethnicity, religion or belief, sex, sexual orientation, or any other equality characteristic.\n\nPEI Media supports flexible working arrangements, and we welcome career returners.\n\nRequirements\n\nResearch\nBuilding and maintaining written and data-driven profiles of managers in private markets for publication in our online products\n\n\nUsing online sources, including company websites, regulatory filings and news sources to maintain up-to-date and accurate intelligence\n\n\nTelephone interviews with senior executives at fund management firms to determine their current and future fundraising plans\n\n\nTranslation of phone conversations with senior executives into the accurate input of data and intelligence\nAiding the execution of plans to improve the quality of research conducted on private market funds and managers by PEI\u2019s research team globally\nAiding the execution of plans to expand the numbers of private market funds and managers tracked by PEI\u2019s research team globally\nWriting\nWriting high quality factual copy to summarize the latest fundraising market updates\nWriting high quality data-led analysis pieces relating to managers of alternative asset funds and the fundraising environment\nData & Analysis\nBecoming expert in how best to interpret and present data in chart and graph form\nWorking as part of a team to rank the largest institutions in private markets\nWorking as a team to survey market participants and analyzing the results for publication across PEI\u2019s editorial titles\nKnowledge\nMaintaining an excellent knowledge of alternative assets through reading multiple intelligence sources to spot trends and contribute ideas for analysis\nUsing the above knowledge, the candidate will be expected to become a specialist in the following fields: private equity, private debt and the secondaries market\nThe balance of the above tasks, along with other duties, will vary.\nThe role demands first-rate organizational skills, excellent verbal and written communication and an analytical mind. The ability to focus and a keen eye for detail are essential to ensure that we maintain accuracy and a high quality of output. The research associate also needs to be comfortable with processes and must be thorough in his/her work.\nKey relationships\nThe research associate will work with a team of research associates within the local office and will be expected to build relationships with colleagues in other offices.\u00a0 The research associate will also need to build relationships with editorial, sales, event and marketing staff members where necessary.\nThe research associate is responsible for building relationships with senior contacts in the industry through telephone and e-mail correspondence and occasional face-to-face meetings.\nExperience/knowledge required\nThe role would suit individuals with highly developed written and research skills, high levels of self-motivation, excellent verbal communication skills and the ability to understand the dynamics of the industry so as to have informed conversations with its players. Past experience within a research role is useful, but not necessary.\nThe role also demands attention to detail and patience so that work is completed on time and to the required standard. Multitasking and strong time management skills are also essential.\nThe successful candidate must have excellent spoken and written English skills and be degree educated. Proficiency in Japanese, Korean, or Chinese is advantageous.\nThe role demands excellent research skills. The post holder should be inquisitive and have a proactive, methodological and enthusiastic approach to work.\nA working knowledge of and interest in financial services would be a distinct advantage. The potential to grasp the dynamics of the private markets industry is also required. The ability to work on one\u2019s own initiative whilst\u00a0maintaining close and effective relationships within a\u00a0team is needed.\n\nFresh graduates are welcome.\n\nKey success measures\nMeeting agreed deadlines\nBuilding strong relationships with key players within the candidate\u2019s specialization fields\nMeeting agreed targets of numbers of institutions researched and updated\nAccuracy of data researched, both from an individual and team level\nMaintenance of an enthusiastic and positive attitude towards work\n\nBenefits\n\n\n20 days\u2019 annual leave, employee will receive an extra one day of holiday after two full calendar years of service\nMedical insurance coverage after passing probation\nEmployee Assistance Programme to enhance employee\u2019s wellbeing\nDental plan provided to employee at a discounted price\nVolunteer leave in service to an approved charitable or community organisation\nFlexible working hours, including options to work from home", "employment_types": ["Full Time", "Permanent"], "selling_points": [], "locations": ["Central"], "categories": ["Banking / Finance", "Financial Services", "Professional Services", "Business Analysis / Data Analysis", "Marketing / Public Relations", "Marketing - Market Research"], "post_time": "2022-01-14T07:34:26Z", "salary": {"currency": null, "max": null, "min": null, "period": "monthly", "term": null}, "salary_visible": false, "title_keywords": ["research associate"], "responsibilities": ["company websites", "management", "ideas", "maintenance", "maintaining", "data", "other duties", "analysis", "maintain accuracy", "quality", "develop", "communication", "maintain", "reports", "plans", "publication"], "requirements": {"degrees": ["degree"], "majors": [], "languages": ["japanese", "english", "chinese", "korean"], "language_level": ["excellent", "proficiency"], "hard_skills": ["maintenance", "analysis", "translation", "focus", "private equity"], "soft_skills": ["organizational skills", "communication", "self-motivation", "patience", "focus", "keen", "analytical mind", "initiative", "communication skills", "eye for detail", "attention to detail", "enthusiastic", "accurate", "active", "driven", "flexible", "research skills", "responsible", "time management skills", "positive attitude", "thorough", "proactive"], "languages_combined": [{"language": "japanese", "language_level": ["proficiency"]}, {"language": "english", "language_level": ["excellent"]}, {"language": "chinese", "language_level": ["proficiency"]}, {"language": "korean", "language_level": ["proficiency"]}]}, "experience_required": {"duration": [], "field": ["research"]}}, {"job_id": "100003009054788", "location_code": "hk", "company": "Peterson Group Management Limited", "job_title": "ASSISTANT ASSET OFFICER", "description": "Responsibilities:\nResponsible for handling daily leasing administration works for the real estate assets including leasing enquiries from agents and prospects\nPerform administration works on leasing matters such as tenancy\u00a0agreements, license agreements and other related duties for Office/Retail portfolios\nHandling tenant\u2019s enquiry, rental billing and collection\nUndertake leasing negotiation and build good relationship with existing and potential tenants\nLiaise with agents and prospects and coordinate with departments on new letting and renewal cases\nPrepare leasing documents and coordinate relevant legal documents\nConduct market search, analyze rental information and prepare leasing reports\nAssist the management in preparing reports and presentation materials\nWorking closely with the leasing team to provide smooth and professional services to tenants\nOversee the building management services provided by appointed management agents\nCoordinate with internal departments for building and facilities management matters\nPerform any ad hoc responsibilities as assigned\nRequirements:\n\nDegree holder in Real Estate/Marketing/Business Administration/Translation/ Communications or related disciplines\nMinimum 2 years\u2019 experience in retail leasing; Relevant experience with major developers is an advantage\nSounds experience and knowledge on building management areas\nPleasant, open-minded and proactive character with positive attitude\nResponsible, initiative, well-organized and eager to learn new things\nGood business and logical sense\nGood team player as well as able to work independently\nGood command of written and spoken English and Chinese\nProficiency in MS Word, Excel & PowerPoint\nCandidate with more experience will be considered as Asset Officer\nWe offer an attractive compensation package, bank holidays, medical benefits and paid examination leave to the right candidate\n\n\nInterested candidates please send your detailed resume with present and expected salary by clicking the \u201cApply Now\u201d button for submission.\n\nEmployment application data held by the Group will be treated in strict confidence and used only for recruitment purposes. Applicants who are not contacted within 2 months may consider their applications unsuccessful. The Group will retain the applications for a maximum period of one year and may refer suitable applicants to other vacancies within the Group.", "employment_types": ["Full Time", "Permanent"], "selling_points": [], "locations": ["Central"], "categories": ["Admin & HR", "Clerical / Admin Staff", "Marketing / Public Relations", "Marketing - Market Research", "Property / Real Estate", "Others"], "post_time": "2022-01-17T11:05:21Z", "salary": {"currency": null, "max": null, "min": null, "period": "monthly", "term": null}, "salary_visible": false, "title_keywords": ["officer", "assistant"], "responsibilities": ["ad hoc responsibilities", "management", "coordinate with", "good relationship", "coordinate", "building management", "reports", "preparing reports", "liaise with", "administration"], "requirements": {"degrees": ["degree holder"], "majors": ["related disciplines", "marketing", "business administration", "communications"], "languages": ["english", "chinese"], "language_level": ["good command"], "hard_skills": ["powerpoint", "translation", "excel", "ms word"], "soft_skills": ["good team player", "work independently", "responsible", "open-minded", "well-organized", "pleasant", "positive attitude", "eager to learn", "proactive", "initiative"], "languages_combined": [{"language": "english", "language_level": ["good command"]}, {"language": "chinese", "language_level": ["good command"]}]}, "experience_required": {"duration": ["minimum 2 years"], "field": ["management", "retail", "relevant experience"]}}, {"job_id": "100003009049773", "location_code": "hk", "company": "Chow Sang Sang Holdings International Limited", "job_title": "Business and Data Analyst", "description": "Responsibilities:\n\nParticipate in business intelligence projects, including designing and creating dashboards, reports or other data delivery solutions\nTransform business users\u2019 requirements into the constructive ideas for data visualization, including the design of data structure and dashboard layouts\nCoordinate internally the BI\u2019s system development, maintenance and enhancements with users and technical departments\nPrepare reports and analysis, provide partners with business insights to support the strategic decisions\nManage BI-related documentation, administrative works & other tool maintenance tasks\nPerform other ad-hoc analyses as assigned\n\nRequirements:\n\nDegree holder, preferably in Statistics, Quantitative Analysis, MIS, Business Administration or other equivalent\n2-3 years relevant experience in BI development, data/business analysis or related fields\nExperience in Qilkview/Nprinting is definitely an advantage\nExcellent in Excel or other analytical tools.\nExperience in retail industry preferred\nGood interpersonal and communication skills, able to work collaboratively with business partners at different levels\nSelf-motivated, enthusiastic, able to work independently with a can-do attitude under a fast-changing environment\nStrong data analytical skill and able to communicate findings effectively with business partners\nInterest in continuously learning by actively seeking opportunities to enrich knowledge and new skills\nGood command of Cantonese, Mandarin and English\nWe offer 5-day-work week with competitive remuneration packages to the right candidate. Interested parties please send your CV with EXPECTED SALARY through the below application procedure.\n\n(Personal data will be used by Chow Sang Sang (CSS) for recruitment only. CSS may refer suitable applications to other vacancies within CSS and its associated companies. We will retain unsuccessful applications for a maximum period of 24 months.)", "employment_types": ["Full Time", "Permanent"], "selling_points": ["Participate in business intelligence projects", "Design of data structure and dashboard layouts", "2-3 years relevant experience in BI development"], "locations": ["Cheung Sha Wan"], "categories": ["Professional Services", "Business Analysis / Data Analysis", "Information Technology (IT)", "Product Management / Business Analyst", "Marketing / Public Relations", "Marketing - Market Research"], "post_time": "2022-01-14T09:13:01Z", "salary": {"currency": null, "max": null, "min": null, "period": "monthly", "term": null}, "salary_visible": false, "title_keywords": ["data analyst"], "responsibilities": ["ad-hoc", "ideas", "visualization", "maintenance", "data", "related documentation", "analysis", "design", "maintenance tasks", "coordinate", "reports", "designing", "prepare reports"], "requirements": {"degrees": ["degree holder"], "majors": ["statistics", "business administration"], "languages": ["cantonese", "english", "mandarin"], "language_level": ["good command"], "hard_skills": ["excel", "analysis", "bi", "analytical skill"], "soft_skills": ["communication skills", "self-motivated", "work independently", "analytical skill", "can-do attitude", "learning", "enthusiastic", "interpersonal"], "languages_combined": [{"language": "cantonese", "language_level": ["good command"]}, {"language": "english", "language_level": ["good command"]}, {"language": "mandarin", "language_level": ["good command"]}]}, "experience_required": {"duration": ["2-3 years"], "field": ["retail industry", "related", "development", "relevant experience", "business analysis"]}}, {"job_id": "100003009053833", "location_code": "hk", "company": "Joy Enterprises Limited", "job_title": "Senior Marketing Officer / Assistant Marketing Manager", "description": "Job Description\n\nResponsibilities:\n\nAssist on executing digital marketing campaigns including social media and display advertising\nManage and create content for the social media platforms in China (including xiahongshu\u5c0f\u7d05\u66f8, Wechat and Weibo), including copywriting and image creating/editing\nClosely monitor social media channels for timely response to comments and inquiries from audiences\nOrganize, create, launch and monitor On/Offline campaigns and formulate up to date e-marketing initiatives to generate sales and brand awareness\nAssist in video production: research & conceptualizing ideas, video shooting and editing\nAssist on analyzing the marketing results to optimize customer experience across multiple channels: offline to online and vice versa\nPerform ad-hoc projects as assigned\n\nRequirements:\n\nDegree holder in Marketing or related disciplines\nPreferably 2-3 years of relevant experience, fresh graduates with keen interest in Beauty Treatment sense and digital marketing will also be considered\nPrior experience in a FMCG /cosmetic and beauty industry.\nExcellent skills in graphic design software such as Photoshop/Illustrator.\nCoordinate and execute product photography shoots or short videos.\nCreative thinking, energetic, self-motivated, independent and able to handle multiple projects\nGood communication skills in both Chinese & English, Mandarin is an advantage\n\nPlease apply in confidence with\u00a0full resume, expected salary and availability\u00a0by clicking \u201cApply Now\u201d button.\n\nYou are invited to visit our website at:\u00a0https://www.swissobeauty.com/\n\nThe information provided will be used for selection purpose only. All information of unsuccessful applicants will be destroyed within six months.", "employment_types": ["Full Time"], "selling_points": [], "locations": ["Mong Kok"], "categories": ["Marketing / Public Relations", "Marketing - Direct Marketing", "Marketing - Market Research", "Marketing - Marketing Communication"], "post_time": "2022-01-17T07:36:13Z", "salary": {"currency": null, "max": null, "min": null, "period": "monthly", "term": null}, "salary_visible": false, "title_keywords": ["assistant marketing manager", "senior marketing officer"], "responsibilities": ["social media", "ad-hoc projects", "advertising", "ideas", "video production", "digital marketing campaigns", "social media platforms", "monitor", "comments", "video shooting", "executing", "editing", "conceptualizing"], "requirements": {"degrees": ["degree holder"], "majors": ["related disciplines", "marketing"], "languages": ["english", "chinese", "mandarin"], "language_level": ["advantage", "good"], "hard_skills": ["illustrator", "photoshop"], "soft_skills": ["communication skills", "self-motivated", "confidence", "independent", "creative", "keen", "energetic"], "languages_combined": [{"language": "english", "language_level": ["good"]}, {"language": "chinese", "language_level": ["good"]}, {"language": "mandarin", "language_level": ["advantage", "good"]}]}, "experience_required": {"duration": ["2-3 years"], "field": ["fmcg", "beauty industry", "relevant experience", "beauty", "digital marketing"]}}, {"job_id": "100003009055351", "location_code": "hk", "company": "Champion Land Properties Limited", "job_title": "Leasing Manager - Hong Kong Gold Coast", "description": "The successful candidate will join a vibrant team of young leasing professionals to handle all leasing activities including new lettings, renewals, direct marketing, market research, budget preparation and tenancy administration of a large scale development. Further duties include coordinating premises takeover and handover, fitting-out and renovation management and handling enquiries and complaints.\nRequirements:\nUniversity degree or related professional qualifications\nMinimum 8 years or above leasing experience with 3 years in managerial position\nProactive, customer oriented, and have an eagerness to learn\nGood interpersonal communication and presentation skills\nGood command of spoken and written English and Chinese. Proficiency in Putonghua will be an advantage\nGood computer skills\nWill be based in gold coast with abundant fringe benefits\nPerform duty during weekends and public holiday is required\nWe offer attractive remuneration packages commensurate with experience and qualifications. If you aspire to an exciting and rewarding career, send your resume immediately, quoting your present and expected salaries by clicking the button\u00a0\u201cApply Now\u201d.\nIf the applicant does not receive a response by\u00a017 February 2022, the application will be considered unsuccessful. Please read our Personal Information Collection Statement at\u00a0https://www.sino.com/en-US/Careers/Personal-Information-Collection-Statement\u00a0before submitting your application. Information provided by applicants will be treated in strict confidence and used for recruitment purposes only.", "employment_types": ["Full Time", "Permanent"], "selling_points": [], "locations": ["Not Specified"], "categories": ["Sales, CS & Business Devpt", "Customer Service - Manager", "Marketing / Public Relations", "Marketing - Direct Marketing", "Marketing - Market Research"], "post_time": "2022-01-18T02:23:44Z", "salary": {"currency": null, "max": null, "min": null, "period": "monthly", "term": null}, "salary_visible": false, "title_keywords": ["leasing manager"], "responsibilities": ["management", "renovation", "budget", "market research", "communication", "administration"], "requirements": {"degrees": ["university degree"], "majors": [], "languages": ["putonghua", "english", "chinese"], "language_level": ["advantage", "proficiency", "good command"], "hard_skills": ["computer skills", "professional qualifications"], "soft_skills": ["communication", "presentation skills", "proactive", "interpersonal"], "languages_combined": [{"language": "putonghua", "language_level": ["proficiency", "advantage"]}, {"language": "english", "language_level": ["good command"]}, {"language": "chinese", "language_level": ["good command"]}]}, "experience_required": {"duration": ["3 years", "minimum 8 years"], "field": ["managerial"]}}, {"job_id": "100003009051836", "location_code": "hk", "company": "China Mobile Hong Kong \u4e2d\u570b\u79fb\u52d5\u9999\u6e2f", "job_title": "(Senior) Customer Service Planning Specialist", "description": "CHINA MOBILE HONG KONG COMPANY LIMITED (\"CMHK\") is the wholly-owned subsidiary of China Mobile Limited (HKEx: 941) (NYSE: CHL), which ranks 65th on the Fortune Global 500.\n\nOur company strives to offer superior service experience and to become the preferable digital partner for customers. We are preserving an environment with trust, responsibility and caring. At CMHK, we commit to maximizing people\u2019s potential and paving the way toward success for every striver. We are now inviting high caliber professional to join us.\n\n\n\nDepartment: Customer Service Planning Department\n\n\n\nIn this position, you will:\n\n\nParticipate in company\u2019s marketing projects and share ideas from customer\u2019s point of view, ensure the service process and after-sales service could meet customer expectation as well as maintain the accuracy of knowledge base\nConduct service benchmarking from different aspects to identify service improvement initiatives\nAnalyze customer feedback and narrow the gap between intended and actual customer experience; assist Customer Service Manager to deploy strategic plans that drive for cross-departments effort to improve total customer satisfaction\nInnovate new ideas on service workflow and policy as well as expand the online service channel\nHandle general departmental reporting and procedure manual\n\nTo be successful in this position, you should meet the following requirements:\n\nDiploma holder or above\n2 years of relevant customer service experience preferably in telecom industry\nGood interpersonal communication skills, self-motivated and able to work under pressure\nExperience in account servicing/ quality assurance/ project management will be an advantage\nHands-on experience in Frontpage and other graphical software is preferable\nGood command of spoken & written English & Chinese\nCandidate with more experience will considered as Senior Customer Service Planning Specialist\n\nWhen you work:\n\n5 days work\n8 hours/day\n\n\n\u00a0What you enjoy:\n\nDouble pay\nDiscretionary Performance bonus\nLife insurance\nMedical insurance\nMeal allowance\nEducation subsidies\nBirthday gift\nMarriage leave\nBirthday leave\nStaff discount\n\n\n\nCMHK is committed to be an equal opportunity employer. We offer exceptional benefits package and the opportunity to work in a challenging environment. Personal data provided by applicants will be treated strictly in accordance with our personal data policy and for recruitment purposes only.", "employment_types": ["Full Time", "Permanent"], "selling_points": ["Customer Service Process Planning", "Conduct Market Research on services", "Analyze customer feedback"], "locations": ["Kwai Hing"], "categories": ["Sales, CS & Business Devpt", "Customer Service - Supervisor / Officer", "Marketing / Public Relations", "Marketing - Market Research"], "post_time": "2022-01-17T01:19:39Z", "salary": {"currency": null, "max": null, "min": null, "period": null, "term": null}, "salary_visible": false, "title_keywords": ["specialist", "customer service"], "responsibilities": ["reporting", "ideas", "strategic plans", "software", "work under pressure", "customer service experience", "quality", "marketing projects", "communication", "project management", "after-sales service", "customer service", "maintain", "deploy", "insurance", "planning"], "requirements": {"degrees": ["diploma holder"], "majors": [], "languages": ["english", "chinese"], "language_level": ["good command"], "hard_skills": ["mobile", "project management", "gap"], "soft_skills": ["communication skills", "self-motivated", "work under pressure", "project management", "hands-on", "customer service", "committed", "interpersonal", "superior"], "languages_combined": [{"language": "english", "language_level": ["good command"]}, {"language": "chinese", "language_level": ["good command"]}]}, "experience_required": {"duration": ["2 years"], "field": ["account servicing", "project management", "customer service", "planning", "digital", "quality assurance"]}}, {"job_id": "100003009051412", "location_code": "hk", "company": "Medifast (Hong Kong) Limited", "job_title": "Marketing Executive / Marketing Assistant", "description": "Job Responsibilities:\n\nAssist in\u00a0developing tactical marketing strategies which align with the business plan\nCreate\u00a0story and content for marketing collaterals include website, eShop, EDM and social media platforms like FB, IG, WeChat\nPrepare\u00a0marketing collaterals, trainings, presentations, tent cards, posters, etc.\nConduct\u00a0market intelligence & marketing analysis on marketing campaigns\nBuild\u00a0relationships with clients and develop new target segments\nLiaise\u00a0and connect closely with internal stakeholders, external agencies and business partners on marketing activities and projects\nHandle\u00a0departmental hotline, answer customer enquiries and follow-up\nProvide\u00a0support to Marketing Department on daily operation and all marketing events and promotions\nPerform any ad-hoc duties as assigned\nJob Requirements:\n\nBachelor degree / Higher Diploma in Marketing or business related discipline is preferred\nAt least 2 years of relevant experience in Marketing\nPrior\u00a0experience in healthcare, servicing, insurance and brokerage industry is advantageous\nKnowledge\u00a0of website, SEO, SEM practices and social media metrics\nUp-to-date\u00a0on the latest trends and technologies in digital marketing\nIndependent,\u00a0responsible, detail-oriented, good time management, a dedicated team player and self-motivated\nGood command in written English and Chinese\nImmediately available will be advantageous\nCandidate with less experience will be considered as Marketing Assistant\nWe offer competitive remuneration package to right candidate. Please submit your resume with expected salary to HR Department (Data collected will be used for the purpose of recruitment only.)", "employment_types": ["Full Time", "Permanent"], "selling_points": [], "locations": ["Causeway Bay"], "categories": ["Marketing / Public Relations", "Marketing - General / Support", "Marketing - Market Research", "Marketing - Marketing Communication"], "post_time": "2022-01-15T15:14:05Z", "salary": {"currency": null, "max": null, "min": null, "period": "monthly", "term": null}, "salary_visible": false, "title_keywords": ["marketing assistant", "marketing executive"], "responsibilities": ["liaise", "marketing events", "provide support", "marketing strategies", "edm", "customer enquiries", "analysis", "marketing collaterals", "social media platforms", "developing", "website", "presentations", "develop", "daily operation", "marketing campaigns", "ad-hoc duties", "business plan"], "requirements": {"degrees": ["diploma", "degree", "bachelor"], "majors": ["business", "marketing"], "languages": ["english", "chinese"], "language_level": ["good command"], "hard_skills": ["seo", "sem"], "soft_skills": ["self-motivated", "independent", "responsible", "detail-oriented", "team player", "time management"], "languages_combined": [{"language": "english", "language_level": ["good command"]}, {"language": "chinese", "language_level": ["good command"]}]}, "experience_required": {"duration": ["at least 2 years"], "field": ["healthcare", "brokerage", "marketing", "relevant experience", "insurance"]}}, {"job_id": "100003009051288", "location_code": "hk", "company": "Hutchison Telecommunications (Hong Kong) Limited", "job_title": "Marketing Executive", "description": "Responsibilities:\n\nConsolidate and analyze customer behavioral data, generate insights from in-depth analysis\nIdentify market segment opportunities and formulate the upsell / retention strategy of each segment\nMonitor subscriber base and revenue movement, analyze the usage behavioral change before and after program\nWork with cross-functional departments for the segmentation of marketing programs, performing data quality checking and measuring the program effectiveness\nMeasure, report and analyze marketing program effectiveness, keep track of inbase performance with company KPIs\nCollect market intelligence on competitors' offer\nSupport for ad hoc assignments and projects\n\nRequirements:\n\nDegree holder in Marketing, Quantitative Analysis, Business Studies or related disciplines\nAt least 2 years working experience in telecom, banking or insurance products\u00a0\nDetail-oriented and self-motivated\nStrong numerical sense\nGood communication, interpersonal and presentation skills\nSkills of customer segmentation and data analysis would be an advantage\n\nApart from competitive remuneration package and exciting opportunity for career development within the Group, we provide attractive employee benefits such as free company shuttle, free company SIM card and preferential SIM plan offers, comprehensive medical & insurance schemes, as well as full range of other employee well-being provisions.\u00a0\n\nInterested parties, please apply with full resume, present and expected salary, by clicking \u201cAPPLY NOW\u201d. Please quote the reference number on the e-mail subject.\n\nWe are an equal opportunity employer and welcome applications from all qualified candidates. Personal data collected will be treated in the strictest confidence and handled confidentially by authorised personnel for recruitment-related purposes only within the CK Hutchison Group of companies. The personal data of unsuccessful applicants will be destroyed after the recruitment exercise pursuant to the requirements of the Personal Data (Privacy) Ordinance in Hong Kong.", "employment_types": ["Full Time", "Permanent"], "selling_points": [], "locations": ["Tsing Yi"], "categories": ["Marketing / Public Relations", "Marketing - Brand / Product Management", "Marketing - General / Support", "Marketing - Market Research"], "post_time": "2022-01-15T07:17:39Z", "salary": {"currency": null, "max": null, "min": null, "period": "monthly", "term": null}, "salary_visible": false, "title_keywords": ["marketing executive"], "responsibilities": ["quality checking", "data", "analysis", "monitor", "ad hoc assignments", "kpis", "report"], "requirements": {"degrees": ["degree holder"], "majors": ["business", "related disciplines", "marketing"], "languages": [], "language_level": [], "hard_skills": ["analysis"], "soft_skills": ["self-motivated", "detail-oriented", "communication", "presentation skills", "comprehensive", "interpersonal"], "languages_combined": []}, "experience_required": {"duration": ["at least 2 years"], "field": ["insurance products", "banking"]}}, {"job_id": "100003009054340", "location_code": "hk", "company": "CITIC Pacific Limited", "job_title": "Senior Officer - Property Development", "description": "Responsibilities\n\nAssist the feasibility studies to explore property investment and development opportunities\nCarry out site visits, due diligence exercises, conduct market research for in-depth review and analysis\nProvide professional support in managing the leasing portfolio and develpment projects\nPrepare investment appraisals, management reports and presentations and etc\nReview and analyze market information, news on town planning and property developments\nRequirements\n\nDegree holder or above in Surveying\nMHKIS or relevant professional qualifications\nMinimum 5 years' relevant experience with at least 3 years in property developers\nFamiliar with planning and land policies in Hong Kong\nProficiency in both spoken and written Chinese and English. Fluent in Putonghua\nAnalytical, attention to details, willing to learn and good interpersonal skills\nPlease visit our\u00a0Career Website\u00a0for more information.\n\nInterested parties may submit your application by clicking the\u00a0\"Apply Now\"\u00a0button.\n\n\nAll information provided by applicants will be treated in strict confidence and used only for recruitment purpose. Applicants who are not contacted may consider their application unsuccessful. CITIC Pacific will retain the applications for a maximum period of one year during which applications may also be referred to other vacancies of CITIC Pacific Limited including its subsidiaries or affiliates.", "employment_types": ["Full Time", "Permanent"], "selling_points": ["5-day work, from 9am to 5pm", "Attractive remuneration package", "Comprehensive medical plan covering dependents"], "locations": ["Admiralty"], "categories": ["Building & Construction", "Building / Construction / QS", "Marketing / Public Relations", "Marketing - Market Research", "Property / Real Estate", "Others"], "post_time": "2022-01-17T09:12:27Z", "salary": {"currency": null, "max": null, "min": null, "period": "monthly", "term": null}, "salary_visible": false, "title_keywords": ["senior officer"], "responsibilities": ["due diligence", "market information", "conduct market research", "review", "analysis", "presentations", "management reports", "planning"], "requirements": {"degrees": ["degree holder"], "majors": ["surveying"], "languages": ["putonghua", "english", "chinese"], "language_level": ["proficiency", "fluent"], "hard_skills": ["professional qualifications"], "soft_skills": ["willing to learn", "attention to details", "interpersonal skills"], "languages_combined": [{"language": "putonghua", "language_level": ["fluent"]}, {"language": "english", "language_level": ["proficiency"]}, {"language": "chinese", "language_level": ["proficiency"]}]}, "experience_required": {"duration": ["at least 3 years", "minimum 5 years"], "field": ["property developers", "relevant experience"]}}, {"job_id": "100003009051589", "location_code": "hk", "company": "Apegen Limited", "job_title": "Event Assistant (5-days work , Central)", "description": "Event Assistant (5-days work)\n\nJob code: JD-EEPA\n\nThe opportunity ahead:\n\nAs an Event Assistant, you are passionate about achieving excellence in customer service and committed to provide superior supports to event coordination and logistics management. It is an ideal opportunity to sharpen your customer service and enhance your communication skills.\n\nCommunication Skills / Language proficiency\n\n10 / 10\n\nEducation Background\n\n7 / 10\n\nQuick Responses / Multitasking\n\n8 / 10\n\nTeam Spirit\n\n9 / 10\n\nRelated Experience\n\n5 / 10\n\nResponsibilities included:\n\nBased on the nature of different events, work in a team on planning, arranging and coordinating each project\nAssist with planning and execution of event programs\nAssist with preparation of communication and public relation materials such as brochures, flyers and invitations\nHelp on gather information and conduct research on each project to achieve quality event productions\nCommunicate via telephone and email with clients / medias to promote upcoming events\u00a0\nHandle client enquiries and request with grace and manner\nProvide supports on administrative tasks such as filing, basic book keeping, and ad hoc tasks\n\nRequirements:\n\nHigher Diploma or Degree holder, preferable in Marketing, Communication, Journalism, Business Administration, Event Management, Public Relation and other related fields\n1 year work experience is preferred but not necessary. Experienced candidates may be considered for senior positions\nUniversity Fresh graduate is welcomed\nStrong communication and customer service skills\nHighly motivated self-starter who takes initiative with minimal supervision\nWillingness to learn; ability to multi-task and complete several assignments with tight deadlines\nFluent in speaking and strong at writing both English and Chinese (Cantonese and Mandarin)\nProficient in Microsoft Office (Word, Excel, PowerPoint) application\nHK permanent citizen only\nImmediately available\n\nApply for this job\n\nPlease send us resume in DOC/DOCX format with Expected salary", "employment_types": ["Full Time", "Contract"], "selling_points": ["Organize and coordinate international-scale events", "PR & IR Events", "5 working days, with OT"], "locations": ["Wan Chai Area"], "categories": ["Admin & HR", "Clerical / Admin Staff", "Marketing / Public Relations", "Marketing - Market Research", "Public Relations - Event Management"], "post_time": "2022-01-16T21:50:29Z", "salary": {"currency": null, "max": null, "min": null, "period": "monthly", "term": null}, "salary_visible": false, "title_keywords": ["event assistant"], "responsibilities": ["quality", "ad hoc tasks", "communication", "administrative tasks", "conduct research", "planning"], "requirements": {"degrees": ["diploma", "fresh graduate", "degree holder"], "majors": ["journalism", "marketing", "business administration"], "languages": ["cantonese", "english", "chinese", "mandarin"], "language_level": ["fluent"], "hard_skills": ["excel", "word", "powerpoint", "microsoft office"], "soft_skills": ["customer service skills", "multi-task", "communication", "motivated", "initiative"], "languages_combined": [{"language": "cantonese", "language_level": ["fluent"]}, {"language": "english", "language_level": ["fluent"]}, {"language": "chinese", "language_level": ["fluent"]}, {"language": "mandarin", "language_level": ["fluent"]}]}, "experience_required": {"duration": ["1 year"], "field": []}}, {"job_id": "100003009051630", "location_code": "hk", "company": "China Telecom Global Limited", "job_title": "Senior Product Marketing Executive/ Assistant Product Marketing Manager", "description": "Key\u00a0Responsibilities:\n\nFormulate and implement digital marketing strategy to grow customer base and drive global business\nConduct market research and business analysis for a variety of telecommunication products and solutions with an aim to capture market opportunities and customer needs\nConduct Lead Generation programs leveraging both digital and traditional marketing platforms to achieve business objectives\nWork closely with multi-disciplinary teams to boost marketing program results\u00a0\nPerform other duties as assigned by the management\n\n\u00a0Requirements:\n\nDegree holder in Marketing/Business Administration/Data Analytics or related discipline with at least 3 years\u2019 work experience gained from the telecommunications, IT, consultancy or other services industries with track record in digital marketing\nA good understanding of the global telecommunications market and products/solutions\nExperience in developing sales incentive program is definitely an advantage\nExcellent communication, interpersonal and organization skills\nStrong analytical and problem solving skills with good business acumen.\u00a0 Results-oriented, self-motivated and able to cope with a fast pace, dynamic and global operated business environment\nHighly proficient in MS Office including PowerPoint, Excel, Word (including Chinese word processing) and other related applications\nExcellent command of both spoken and written English and Chinese.\u00a0 Fluent Mandarin is an advantage\nQualified candidate with more relevant work experience would be considered as Assistant Product Marketing Manager\n\nWe offer 5 days work, competitive salary package and attractive career development opportunities to the right candidate.\u00a0\n\nInterested parties please email your full resume with your current & expected salary to us.\n\nApplicants not invited for interview within 3 months may assume their applications unsuccessful.\u00a0\n\nIf you are interested in other job opportunities, please check with below career website.\n\nPersonal data collected would be used for recruitment purpose only.\n\n\n\n", "employment_types": ["Full Time", "Permanent"], "selling_points": ["Degree holder in Marketing/Business Administration", "Formulate and implement digital marketing strategy", "Competitive salary package"], "locations": ["Wan Chai"], "categories": ["Marketing / Public Relations", "Marketing - Brand / Product Management", "Marketing - Market Research", "Digital Marketing"], "post_time": "2022-01-16T15:45:55Z", "salary": {"currency": null, "max": null, "min": null, "period": "monthly", "term": null}, "salary_visible": false, "title_keywords": ["product marketing manager", "assistant", "marketing executive"], "responsibilities": ["perform other duties", "management", "conduct market research", "teams", "digital marketing", "business analysis"], "requirements": {"degrees": ["degree holder"], "majors": ["marketing", "business administration", "it", "digital marketing"], "languages": ["english", "chinese", "mandarin"], "language_level": ["advantage", "fluent", "excellent", "proficient"], "hard_skills": ["excel", "chinese word processing", "data analytics", "word", "acumen", "powerpoint", "dynamic", "problem solving skills", "ms office"], "soft_skills": ["self-motivated", "business environment", "organization skills", "communication", "analytical and problem solving skills", "dynamic", "business acumen", "interpersonal"], "languages_combined": [{"language": "english", "language_level": ["excellent"]}, {"language": "chinese", "language_level": ["excellent", "proficient"]}, {"language": "mandarin", "language_level": ["fluent", "advantage"]}]}, "experience_required": {"duration": ["at least 3 years"], "field": ["business administration", "related", "developing", "marketing", "it", "digital marketing", "telecommunications"]}}, {"job_id": "100003009042654", "location_code": "hk", "company": "Headsearch21 Consultancy Ltd", "job_title": "Marketing Executive/ Senior Marketing Executive(Event, Exhibition, 5 days, Double Pay, 09:00-17:30)", "description": "Our client,\u00a0an international exhibition organizer and trade magazines publisher, is now seeking for high caliber candidate to fill up the following position:\n\nResponsibilities:\u00a0\n\nTo handle sales and marketing of international trade fairs held in China\nResearch, plan and execute buyers\u2019 promotion campaign\nRecruit targeted trade visitors through ATL & BTL channels\nPlanning and coordinating exhibition events in China\u00a0\nResponsible for coming up strategies and project plans, identifying and opening up new opportunities for further development of the exhibition by staying close to customers and market.\u00a0\nWork closely with promotional partners, advertising and PR agencies on marketing and brand building activities\n\nRequirements:\u00a0\u00a0\n\nBachelor degree holder in Marketing, Communication, Business or related disciplines\u00a0\nAt least\u00a03 year related work experience in exhibition/ event/ promotion management\nGood commutation skills and management skills\u00a0\nFluent in English is a must\nOccasional travel is required\n\nInterested parties, please click\u00a0 \u201capply now\u201d or send your resume with current and expected salary in MS word format to cv @headsearch21.com.\n\nFor more information please contact Ms.\u00a0Candy Lai\u00a0at +852 3188 3070.\u00a0\n\nRef#:\u00a0CA01005\n\nAll information collected will be treated in strict confidence and be used for recruitment purpose only\n\nCompany Web-Site:\u00a0www.headsearch21.com\u00a0\nHotline: (852) 3188 3070", "employment_types": ["Full Time", "Permanent"], "selling_points": ["Degree holder in Marketing, Communication", "Experience in handle exhibition, events", "Double Pay, 5 Working Days"], "locations": ["Not Specified"], "categories": ["Marketing / Public Relations", "Marketing - Market Research", "Marketing - Marketing Communication", "Public Relations - Event Management"], "post_time": "2022-01-12T08:16:14Z", "salary": {"currency": null, "max": null, "min": null, "period": "monthly", "term": null}, "salary_visible": false, "title_keywords": ["marketing executive"], "responsibilities": ["plans", "advertising", "plan", "planning"], "requirements": {"degrees": ["bachelor degree holder"], "majors": ["business", "related disciplines", "marketing"], "languages": ["english"], "language_level": ["fluent"], "hard_skills": [], "soft_skills": ["communication"], "languages_combined": [{"language": "english", "language_level": ["fluent"]}]}, "experience_required": {"duration": ["at least 3 year"], "field": ["related", "management"]}}, {"job_id": "100003009039589", "location_code": "hk", "company": "Sun Hung Kai Properties Ltd", "job_title": "RESEARCH OFFICER", "description": "Requirements:\n\n\nBachelor\u2019s degree in real estate, business, economics or a related discipline\nMinimum 4 years' work experience, preferably in research field\nStrong analytical and problem-solving skills with good numerical sense\nA team player with strong initiatives\nGood Chinese and English writing and fluent Putonghua\n\nResponsibilities:\n\n\nConduct data processing and analysis, market research and ad hoc analysis as to the Group's business\nProvide administrative support to the team\n\n(Candidates with less experience will be considered for Assistant Research Officer.)\n\nGood remuneration and attractive fringe benefits will be offered to the successful applicant. Interested parties please apply with full resume, present and expected salary, available date by clicking \"Apply Now\".\n\nFor further information, please visit our company website:\u00a0www.shkp.com.\n\nWe are an equal opportunity employer and welcome applications from all qualified candidates. All personal data collected will be used for recruitment purpose only.\u00a0 Applicants not hearing from us within 3 months may consider their applications unsuccessful.\u00a0 All personal data collected will be destroyed within 24 months.", "employment_types": ["Full Time", "Permanent"], "selling_points": ["Bachelor's degree with 4 years' work experience", "Conduct data processing, analysis, market research", "Provide administrative support to the team"], "locations": ["Wan Chai"], "categories": ["Admin & HR", "Clerical / Admin Staff", "Marketing / Public Relations", "Marketing - Market Research", "Property / Real Estate", "Others"], "post_time": "2022-01-11T10:10:12Z", "salary": {"currency": null, "max": null, "min": null, "period": null, "term": null}, "salary_visible": false, "title_keywords": ["research officer"], "responsibilities": ["ad hoc", "analysis", "market research", "data processing", "provide administrative support"], "requirements": {"degrees": ["degree", "bachelor"], "majors": ["economics", "business"], "languages": ["putonghua", "english", "chinese"], "language_level": ["fluent", "good"], "hard_skills": ["problem-solving skills"], "soft_skills": ["problem-solving skills", "team player"], "languages_combined": [{"language": "putonghua", "language_level": ["fluent", "good"]}, {"language": "english", "language_level": ["good"]}, {"language": "chinese", "language_level": ["good"]}]}, "experience_required": {"duration": ["minimum 4 years"], "field": ["research"]}}, {"job_id": "100003009054932", "location_code": "hk", "company": "Sun Hung Kai Properties Ltd", "job_title": "ASSISTANT MANAGER \u2013 LOGISTICS PORTFOLIO LEASING", "description": "Sun Hung Kai Properties Limited owns an industrial & logistics portfolio with GFA over 5 million sq.ft. and a parking portfolio. We are now seeking for high caliber candidates to join us to grow the portfolios and participate in the leasing, acquisition and disposal management activities along the life cycle of various asset classes.\n\n\nRequirements:\n\nBachelor\u2019s degree in business, logistics, surveying or related disciplines\nMinimum 5 years experiences in leasing & marketing of logistics, industrial or commercial properties\nExperiences in relationship development and management with logistics players and MNCs will be an advantage\nProven track record in partnership development, new tenant sourcing & retention\nProactive individual with good understandings of corporate real estate and logistics industry\nFluent in English, Mandarin and Cantonese\n\nResponsibilities:\n\n\nResponsible for the business development and leasing activities of the warehousing facilities and other logistics projects\nConduct market research, financial analysis and compile reports & presentation\nAcquire new potential tenants through associations, marketing events, referrals and business connections\nRelationship management with clients and property agencies\nPrepare pitching proposal and response RFPs for corporate clients\n\n(Candidates with more experience will be considered for more senior positions.)\n\nGood remuneration and attractive fringe benefits will be offered to the successful applicant. Interested parties please apply with full resume, present and expected salary, available date by clicking \"Apply Now\".\n\nWe are an equal opportunity employer and welcome applications from all qualified candidates. All personal data collected will be used for recruitment purpose only.\u00a0 Applicants not hearing from us within 3 months may consider their applications unsuccessful.\u00a0 All personal data collected will be destroyed within 24 months.", "employment_types": ["Full Time", "Permanent"], "selling_points": ["Warehousing facilities & logistics leasing", "Partnership development, new tenant sourcing", "Relationship management with property agencies"], "locations": ["Wan Chai"], "categories": ["Sales, CS & Business Devpt", "Business Development", "Marketing / Public Relations", "Marketing - Market Research", "Property / Real Estate", "Others"], "post_time": "2022-01-17T14:22:21Z", "salary": {"currency": null, "max": null, "min": null, "period": null, "term": null}, "salary_visible": false, "title_keywords": ["assistant manager", "logistics"], "responsibilities": ["warehousing", "marketing events", "management", "compile reports", "conduct market research", "financial analysis", "logistics"], "requirements": {"degrees": ["degree", "bachelor"], "majors": ["related disciplines", "business", "surveying"], "languages": ["cantonese", "english", "mandarin"], "language_level": ["fluent"], "hard_skills": [], "soft_skills": ["proactive"], "languages_combined": [{"language": "cantonese", "language_level": ["fluent"]}, {"language": "english", "language_level": ["fluent"]}, {"language": "mandarin", "language_level": ["fluent"]}]}, "experience_required": {"duration": ["minimum 5 years"], "field": ["management", "development", "commercial", "marketing", "logistics"]}}, {"job_id": "100003009049125", "location_code": "hk", "company": "Centaline Property Agency Ltd", "job_title": "Executive Assistant/ Marketing Clerk", "description": "Responsibilities:\n\nWork under the Marketing Department of Centaline Industrial/Office/Retail\nAssist in data research and analysis, prepare document or business proposal\u00a0for conference meetings\nAssist in market promotions such as follow up the advertisement of Industrial/Office/Retail properties\nProvide clerical support for Licensed Salesperson or Licensed Estate Agent to facilitate their needs of marketing promotions\nWork Location: Kwun Tong / Wan Chai\n\nRequirements:\n\nMatriculated\u00a0or above with at least 1-2 years\u2019 work experience\nGood command of English, Chinese and Mandarin is advantage\nGood communication skills, hard-working, responsible and able to work under pressure\nGood PC knowledge, including MS Word, Excel and Chinese Word Processing\nImmediate available is preferred\n\nWe provide its members\u00a0with professional training, attractive remuneration package and excellent career prospects.\u00a0 For application, please send full resume with present and expected salary to Human Resources Department, 5/F., Tower 1, New World Tower, 18 Queen' s Road Central, Hong Kong\n\nFor more information about us, please visit our website at: www.centanet.com\n\nData collected will be used for recruitment purpose only", "employment_types": ["Full Time", "Permanent"], "selling_points": ["Data searching and analysis", "Responsible for reports preparation", "Form 5 or above with 1-2 years work experience"], "locations": ["Wan Chai"], "categories": ["Marketing / Public Relations", "Marketing - Market Research", "Others"], "post_time": "2022-01-14T08:09:06Z", "salary": {"currency": null, "max": null, "min": null, "period": "monthly", "term": null}, "salary_visible": false, "title_keywords": ["executive assistant", "clerk"], "responsibilities": ["provide clerical support", "analysis", "marketing promotions", "data"], "requirements": {"degrees": [], "majors": [], "languages": [], "language_level": [], "hard_skills": [], "soft_skills": [], "languages_combined": []}, "experience_required": {"duration": [], "field": []}}, {"job_id": "100003009047944", "location_code": "hk", "company": "ProJob21.com Limited", "job_title": "Ecommerce Analyst (Data Specialist)", "description": "NY home d\u00e9cor DTC eCommerce\nAgile Culture & Robust Business Expansion\nWeb Analytics / Crave for new initiatives\nThe Role\n\nJoin a fun and high-achieving small team and be part of the global strategic hub to drive business and sustainability values for a beautifully designed and environmental-friendly New York home d\u00e9cor brand\nThe team is on a mission to make a material difference to do good for the people and the planet, engage artisans from around the world to support local communities\nWith ambition to map out the exciting journey to grow the business, this is an expansion hire in Hong Kong\nYou will be the web, user, and business analytics expert, helping to turn data into insights and business decisions\nYou will also work together with marketing, product, and operations to help keep track and ensure alignment on the e-commerce plan, be part of the customer experience to strategize CRM programs, work with tech /data teams to automate process when possible; collect industry market intelligence and provide recommendations\nBenefits: flexible hours, chic working space, 20 days+ leave\n\nThe Person\n\nDegree holder with about 2-5 years\u2019 experience as a data/ business analyst for online retailer, marketplace, or e-commerce brand\nPassionate about home d\u00e9cor/sustainable wellness living\nSelf-starter with high standards and attention to details\nSolid knowledge in web analytics (e.g. Shopify Analytic, Glew Analytic, Google Analytic, Social Analytic), user journey analysis and good business acumen\nSavvy in data analysis and visualization tools (such as Excel, Access, Power BI, PowerPoint)\nFluent in written and speaking Chinese (Both Cantonese and Putonghua) and English\nEarly availability preferred\n\nInterested candidates, please email your update resume (in MS WORD format) with current and expected salary to us soonest.\n\nAlso come visit ProJOB21 www.ProJob21.com to discover other exciting career opportunities!\n\nAll information received will be kept in strict confidence and used for employment-related purposes only.", "employment_types": ["Permanent"], "selling_points": [], "locations": ["Not Specified"], "categories": ["Professional Services", "Business Analysis / Data Analysis", "Marketing / Public Relations", "Marketing - Market Research", "E-commerce", "Product Management / Business Analyst"], "post_time": "2022-01-14T04:20:16Z", "salary": {"currency": null, "max": null, "min": null, "period": "monthly", "term": null}, "salary_visible": false, "title_keywords": ["analyst", "data specialist"], "responsibilities": ["data", "operations", "teams", "provide recommendations", "plan"], "requirements": {"degrees": [], "majors": [], "languages": [], "language_level": [], "hard_skills": ["small", "agile", "fun", "web", "e-commerce", "make", "web analytics"], "soft_skills": ["web analytics", "friendly", "agile", "robust"], "languages_combined": []}, "experience_required": {"duration": [], "field": ["tech", "marketing", "e-commerce"]}}, {"job_id": "100003009056225", "location_code": "hk", "company": "Yue Xiu Apt Parking Limited", "job_title": "\u5e02\u52d9\u4e3b\u4efb", "description": "\u8077\u8cac\uff1a\n\n\u767c\u6398\u65b0\u5e02\u5834\u53ca\u65b0\u5ba2\u6236\uff0c\u4e26\u767c\u5c55\u7dad\u8b77\u5ba2\u6236\u95dc\u4fc2\n\u8ca0\u8cac\u9032\u884c\u505c\u8eca\u5834\u5e02\u5834\u8abf\u7814\u4e26\u5236\u5b9a\u5e02\u5834\u7b56\u7565\n\u8ca0\u8cac\u5354\u52a9\u8eca\u5834\u6295\u6a19\u3001\u6210\u672c\u8a08\u7b97\u53ca\u5408\u540c\u7ba1\u7406\n\u8655\u7406\u696d\u4e3b\u53ca\u5ba2\u6236\u7684\u8aee\u8a62\u3001\u6295\u8a34\uff0c\u78ba\u4fdd\u5340\u57df\u505c\u8eca\u5834\u7684\u65e5\u5e38\u71df\u904b\n\u5728\u9810\u7b97\u7bc4\u570d\u5167\u63a7\u5236\u5730\u5340\u505c\u8eca\u5834\u7684\u71df\u904b\u6210\u672c\n\u6d41\u7a0b\u4e8b\u9805\u7684\u5448\u5831\uff0c\u4e00\u822c\u6587\u66f8\u8655\u7406\n\n\u8981\u6c42\uff1a\n\n1\u5e74\u4ee5\u4e0a\u5de5\u4f5c\u7d93\u9a57\uff0c\u5177\u505c\u8eca\u5834\u7ba1\u7406\u3001\u7269\u696d\u7ba1\u7406\u8005\u53ca\u5e02\u5834\u7d93\u9a57\u8005\u512a\u5148\n\u9700\u5177\u76f8\u95dc\u7ba1\u7406\u6587\u6191\u53ca\u5b78\u6b77\u8b49\u66f8\n\u5177\u4e00\u822c\u96fb\u8166\u64cd\u4f5c\u77e5\u8b58\u53ca\u4f7f\u7528\n\u826f\u597d\u4e2d\u3001\u82f1\u6587\u66f8\u5beb\u53ca\u8a9e\u8a00\u80fd\u529b\n\u6709\u99d5\u99db\u57f7\u7167\u53ca\u6709\u79c1\u5bb6\u8eca\u512a\u5148\u8003\u616e\n\u80fd\u7acb\u5373\u4e0a\u73ed\u8005\u512a\u5148\u8003\u616e\n\n\u6709\u610f\u8005\u8acb\u5c07\u500b\u4eba\u4e2d\u3001\u82f1\u6587\u7c21\u6b77\u96fb\u90f5\u81f3\"Apply Now\"\n\n\u6240\u6709\u7533\u8acb\u53ea\u4f5c\u62db\u8058\u4e4b\u7528\u4e26\u5c07\u4e88\u7d55\u5c0d\u4fdd\u5bc6\uff1b\u672a\u7372\u53d6\u9304\u8005\u7684\u6240\u6709\u8cc7\u6599\u5c07\u65bc 6\u500b\u5167\u92b7\u6bc0\u3002", "employment_types": ["Full Time", "Permanent"], "selling_points": ["\u767c\u6398\u65b0\u5e02\u5834\u53ca\u65b0\u5ba2\u6236\uff0c\u4e26\u767c\u5c55\u7dad\u8b77\u5ba2\u6236\u95dc\u4fc2\uff0c\u8ca0\u8cac\u9032\u884c\u505c\u8eca\u5834\u5e02\u5834\u8abf\u7814\u4e26\u5236\u5b9a\u5e02\u5834\u7b56\u7565", "\u8ca0\u8cac\u5354\u52a9\u8eca\u5834\u6295\u6a19\u3001\u6210\u672c\u8a08\u7b97\u53ca\u5408\u540c\u7ba1\u7406\uff0c\u8655\u7406\u696d\u4e3b\u53ca\u5ba2\u6236\u7684\u8aee\u8a62\u3001\u6295\u8a34\uff0c\u78ba\u4fdd\u5340\u57df\u505c\u8eca\u5834\u7684\u65e5\u5e38\u71df\u904b", "1\u5e74\u4ee5\u4e0a\u5de5\u4f5c\u7d93\u9a57\uff0c\u5177\u505c\u8eca\u5834\u7ba1\u7406\u3001\u7269\u696d\u7ba1\u7406\u8005\u53ca\u5e02\u5834\u7d93\u9a57\u8005\u512a\u5148\uff0c\u9700\u5177\u76f8\u95dc\u7ba1\u7406\u6587\u6191\u53ca\u5b78\u6b77\u8b49\u66f8"], "locations": ["Not Specified"], "categories": ["Sales, CS & Business Devpt", "Business Development", "Marketing / Public Relations", "Marketing - Market Research", "Property / Real Estate", "Property Management"], "post_time": "2022-01-18T03:39:23Z", "salary": {"currency": null, "max": null, "min": null, "period": "monthly", "term": null}, "salary_visible": false, "title_keywords": [], "responsibilities": [], "requirements": {"degrees": [], "majors": [], "languages": [], "language_level": [], "hard_skills": [], "soft_skills": [], "languages_combined": []}, "experience_required": {"duration": [], "field": []}}, {"job_id": "100003009049613", "location_code": "hk", "company": "Top Recruit", "job_title": "Associate Consultant", "description": "Job Duties:\n\n\u0178\u00a0\u00a0 Develop financial and operational analysis and processes\n\n\u0178\u00a0\u00a0 Conduct in-depth market, sector, and industry research\n\n\u0178\u00a0\u00a0 Analyze clients investment portfolio and financial needs\n\n\u0178\u00a0\u00a0 Keep updating on global investment market\n\n\u0178\u00a0\u00a0 Respond to clients questions and concerns in a timely manner\n\nJob Requirements:\n\n\u0178\u00a0\u00a0 School certificate or above\n\n\u0178\u00a0\u00a0 Hong Kong permanent resident or holding valid working visa (IANG)\n\n\u0178\u00a0\u00a0 Proficient in Excel, Word, and Powerpoint\n\n\u0178\u00a0\u00a0 Aggressive, self-motivated and willing to learn\n\n\u0178\u00a0\u00a0 Good command of Cantonese, Mandarin and English\n\n\u0178\u00a0\u00a0 Have financial working experience will be an advantage\n\nWe offer:\n\n\u0178\u00a0\u00a0 Attractive remuneration package\n\n\u0178\u00a0\u00a0 Five working days per week\n\n\u0178\u00a0\u00a0 Friendly and professional working environment\n\n\u0178\u00a0\u00a0 Well-structured and comprehensive training program\n\n\u0178\u00a0\u00a0 Professional management supports and assistance", "employment_types": ["Full Time", "Permanent"], "selling_points": ["Bachelor degree or above", "Proficient in Excel, Word, and Powerpoint", "Good command of Cantonese, Mandarin and English"], "locations": ["Sai Ying Pun"], "categories": ["Banking / Finance", "Financial Services", "Marketing / Public Relations", "Marketing - Market Research", "Wealth Management"], "post_time": "2022-01-14T08:58:08Z", "salary": {"currency": null, "max": null, "min": null, "period": "monthly", "term": null}, "salary_visible": false, "title_keywords": ["associate", "consultant"], "responsibilities": ["analysis", "a timely manner", "develop"], "requirements": {"degrees": ["certificate"], "majors": [], "languages": ["cantonese", "english", "mandarin"], "language_level": ["good command"], "hard_skills": ["excel", "word", "powerpoint"], "soft_skills": ["self-motivated", "willing to learn"], "languages_combined": [{"language": "cantonese", "language_level": ["good command"]}, {"language": "english", "language_level": ["good command"]}, {"language": "mandarin", "language_level": ["good command"]}]}, "experience_required": {"duration": [], "field": ["financial"]}}, {"job_id": "100003009051324", "location_code": "hk", "company": "Antnergy Social Resources", "job_title": "Graduate Trainee (5 days)", "description": "Our client is one of the major financial institutions that offers consultation service in wealth management, comprehensive financial strategies as well as premium financing service to high net worth asset clients throughout Hong Kong, Greater China and Asia Pacific Regions. They are looking for a role in market expansion and work closely with clients.\n\nThis is a Golden opportunity to experience the Asset and Risk Management Industry. We believe in providing a high quality training of financial services that fosters continuous professional development to high new worth individuals and proven to significantly enhance client\u2019s portfolio.\n\nCandidates who are looking for an opportunity where provide professional training support to experience the business environment and career development are welcome to join our program:\n\nResponsibilities:\u00a0\n\nExperience the valued communication training from the industry\u2019s leading performers.\nPractice on asset management, project finance, research and analysis skills\nComplete project and task to illustrate understanding the value of asset and risk management.\n\nRequirements:\n\nFinal\u00a0year\u00a0students/ Fresh graduates\nIANG holders are welcome!\n\nInterested parties please\u00a0click\u00a0Apply Now.", "employment_types": ["Full Time"], "selling_points": ["5 stars office building, 1min from MTR, 21D leaves", "early leave on Friday, friendly & pro colleagues", "5 day work, travel allowance, incentive trips"], "locations": ["Quarry Bay"], "categories": ["Banking / Finance", "Financial Services", "Marketing / Public Relations", "Marketing - Market Research", "Management", "Management Trainee"], "post_time": "2022-01-15T08:38:30Z", "salary": {"currency": null, "max": null, "min": null, "period": "monthly", "term": null}, "salary_visible": false, "title_keywords": ["graduate trainee"], "responsibilities": ["communication", "analysis", "management", "asset management"], "requirements": {"degrees": [], "majors": [], "languages": [], "language_level": [], "hard_skills": [], "soft_skills": [], "languages_combined": []}, "experience_required": {"duration": [], "field": []}}, {"job_id": "100003008807572", "location_code": "hk", "company": "Osmium Consulting Group Limited", "job_title": "CRM Data Analyst", "description": "Responsibilities:\n\nUnderstand the business of CRM and platform product ecosystem, design and develop KPI dashboards and reports ( Tableau, etc ), establish the foundation for all key metrics tracking to evaluate overall effectiveness\nCreate actionable insights and provide campaign optimization recommendations for the CRM team through data extraction and transformation processes using data analytics tools ( SQL, R, Python, etc )\nHypothesize and perform exploratory customer analysis ( customer life cycle analysis, customer segmentation, campaign attribution, A / B testing, RFM analysis, customer behavioral modeling, funnel analysis, CLV, etc. ), ability to transform unstructured data into clear business opportunities\nDevelop best practices of customer targeting strategy for customer lifecycle campaigns ( activation, retention, upsell, cross-sell, churn management, etc ) through data-driven methods\nPartner with data engineering / tech team, ability to plan data requirements and priority pipelines to maintain CRM data landscapes with accuracy and efficiency\nPerform deep-dive statistical analysis and develop data models that can be used for long-term optimization\nAd-hoc support on campaign audience targeting list and key campaign analysis\nStreamline data workflow to improve efficiency in operational processes\nActively Monitor metrics trends or patterns and troubleshoot operation gaps in a timely manners\nShare learnings and results with stakeholders of all seniority and create a data-driven environment within the team\nRequirements\n1+ years of experience as data analyst\nExperience in e-commerce, retail, consulting, tech company, financial services is desirable\nBachelor\u2019s degree in business administration, marketing, business analytics, statistics, economics, mathematics, or quant related fields\nFamiliar with Python / R\nProficient in visualization tools like Tableau, Power BI, Mixpanel or similar tools\nExperience with CRM Tools such as Braze / Hubspot / Salesforce\nStrong business acumen and good at problem-solving, have a good understanding of customer analytics techniques ( customer lifecycle, RFM modeling, clustering segmentation, conversion prediction, etc ), basic statistical concepts such as hypothesis testing, regression is required.\nGood communication skills, effectively communicate ideas and requirements to technical and non-technical audiences\nHighly motivated with a can-do attitude, ability to think creatively and strategically for evolving data-driven solutions\nA team player and able to work independently with minimal supervision\nAttention to details and precision\nPassionate about the crypto / blockchain industry is a strong plus\n\n\n\n", "employment_types": ["Full Time", "Permanent"], "selling_points": ["Crypto", "Work From Home", "Great Benefits"], "locations": ["Others"], "categories": ["Marketing / Public Relations", "Marketing - Market Research", "Digital Marketing", "Information Technology (IT)", "Data Scientist"], "post_time": "2022-01-13T07:47:09Z", "salary": {"currency": "HKD", "max": 29999, "min": 20000, "period": "monthly", "term": null}, "salary_visible": true, "title_keywords": ["data analyst"], "responsibilities": ["ad-hoc", "analytics tools", "management", "data", "analysis", "business opportunities", "design and develop", "monitor", "testing", "evaluate", "develop", "maintain", "reports", "troubleshoot", "plan", "tracking"], "requirements": {"degrees": ["degree", "bachelor"], "majors": ["mathematics", "business administration", "economics", "statistics", "marketing", "business analytics"], "languages": [], "language_level": [], "hard_skills": ["blockchain", "plus", "bi", "salesforce", "basic", "crypto", "e-commerce", "problem-solving", "tableau", "python", "r", "acumen"], "soft_skills": ["communication skills", "work independently", "can-do attitude", "problem-solving", "motivated", "attention to details", "business acumen", "team player", "driven", "passionate about"], "languages_combined": []}, "experience_required": {"duration": ["1+ years"], "field": ["consulting", "e-commerce", "tech", "financial services", "retail"]}}, {"job_id": "100003009050024", "location_code": "hk", "company": "Mani Limited", "job_title": "LICENSING EXECUTIVE", "description": "Responsibilities:\n\n\n\nAssist Licensing Manager in managing existing licensees and expand current licensing portfolio.\nPrepare documents and regular reports for the licensing process, and consolidate license agreements.\nWork closely with licensees to ensure their business and marketing strategies are aligned with company and brand policies.\nWork with marketing team to maximize product exposure, increase brand awareness and bolster company positioning.\nRequirements:\n\nDegree holder in Business Administration, Marketing or related discipline.\nMin. 3 years working experience in licensing business, preferably in character licensing.\nSound understanding of proper licensing strategies formulation.\nProactive, well-organized, and attentive to details.\nExcellent command in English and Chinese.\nProficiency in Microsoft Office Applications.\n\nWe offer 5-day work, attractive remuneration package and a challenging environment for professionals with immediate availability. Interested parties please send email with current and expected salary for application.\n\n\n\nFor more information about our company, please visit our facebook :\u00a0https://www.facebook.com/tclubfanshk/\n\n", "employment_types": ["Full Time", "Permanent"], "selling_points": [], "locations": ["Lai Chi Kok"], "categories": ["Marketing / Public Relations", "Marketing - Brand / Product Management", "Marketing - Direct Marketing", "Marketing - Market Research"], "post_time": "2022-01-14T09:39:00Z", "salary": {"currency": null, "max": null, "min": null, "period": "monthly", "term": null}, "salary_visible": false, "title_keywords": ["licensing executive"], "responsibilities": ["policies", "marketing strategies", "reports", "prepare documents"], "requirements": {"degrees": ["degree holder"], "majors": ["marketing", "business administration"], "languages": ["english", "chinese"], "language_level": ["excellent"], "hard_skills": ["microsoft office"], "soft_skills": ["proactive", "well-organized", "attentive to details"], "languages_combined": [{"language": "english", "language_level": ["excellent"]}, {"language": "chinese", "language_level": ["excellent"]}]}, "experience_required": {"duration": ["3 years"], "field": ["business"]}}, {"job_id": "100003009048361", "location_code": "hk", "company": "PARKnSHOP", "job_title": "Senior Marketing Executive (CRM)", "description": "You can enjoy:\u00a0\nComprehensive Medical and Life insurance coverage, including your spouse and children\nExclusive company pension schemes\nMarriage, Maternity and Paternity Leave\nExclusive shopping discount, Bazaar Sales for our people only\u00a0\nProfessional training and career advancement opportunities\nConvenient office location, less than 5 min. walk from MTR\nContemporary workplace with Onsite Clinic, Lactation Rooms, free drinks and chill out areas\nWell-equipped Gym inside our office building, plus fitness and interest class packages\nFree round-trip lunchtime shuttle bus services to Shatin\nResponsibilities:\n\nDevelop and execute CRM campaign and promotion\nPlan and execute loyalty program and engagement activity\nLiaise with strategic partners for joint promotion opportunities\nDesign marketing activities and store promotion in various store banners\nCoordinate with internal and external parties on POSM design, production and to ensure excellent execution of campaigns\nRequirements:\nUniversity graduate in Marketing or related disciplines\n4 years working experience in marketing, preferably in retail or FMCG industry\nDynamic, creative to cope with fast-paced working environment and able to work under pressure\nExcellent communication and organisation skills\nExcellent command of English & Chinese with strong interpersonal and problem solving skills\nLess experience will be considered as Marketing Executive\nAn attractive salary and benefit package will be offered. Interested parties please forward detailed resume stating expected salary to: People Department, PARKnSHOP (HK) Limited, Watson House, 1-5 Wo Liu Hang Road, Fo Tan, N.T. or email to us.\n\n\nWe are an equal opportunity employer and welcome applications from all qualified candidates. The information provided will be treated in strict confidence and be used only for consideration of your application for relevant / similar posts within the A.S. Watson Group. All personal data of unsuccessful applicants will be destroyed within 12 months from the date of application.", "employment_types": ["Full Time", "Permanent"], "selling_points": [], "locations": ["Shatin Area"], "categories": ["Marketing / Public Relations", "Marketing - Market Research", "Marketing - Marketing Communication"], "post_time": "2022-01-14T06:25:31Z", "salary": {"currency": null, "max": null, "min": null, "period": "monthly", "term": null}, "salary_visible": false, "title_keywords": ["senior marketing executive"], "responsibilities": ["internal and external parties", "coordinate with", "design", "develop", "banners", "plan", "liaise with"], "requirements": {"degrees": ["university graduate"], "majors": ["related disciplines", "marketing"], "languages": ["english", "chinese"], "language_level": ["excellent"], "hard_skills": ["dynamic", "fmcg industry", "problem solving skills"], "soft_skills": ["communication", "dynamic", "organisation", "problem solving skills", "creative", "interpersonal", "work under pressure"], "languages_combined": [{"language": "english", "language_level": ["excellent"]}, {"language": "chinese", "language_level": ["excellent"]}]}, "experience_required": {"duration": ["4 years"], "field": ["marketing", "retail", "fmcg"]}}, {"job_id": "100003009054943", "location_code": "hk", "company": "Sun Hung Kai Properties Ltd", "job_title": "MANAGER - SALES & MARKETING", "description": "Requirements:\n\n\nBachelor\u2019s degree or above\n10 years\u2019 experience, preferably in sales & marketing of residential properties in property developers\nKnowledge in DMC preferred\nAttentive to details, customer-oriented and organized\nGood communication and interpersonal skills\nProficient in English and Chinese\nAble to meet tight deadlines and work under pressure\nWilling to work overtime and irregular hours\n\nResponsibilities:\n\n\nAssist in formulation and implementation of sales strategies for residential property projects\nAssist in project launch preparation and implement strategy work including preparation and production of relevant sales documents and organize sales brochures and PR / media campaigns, etc.\nConduct market research and analysis\nArrange sales office logistics\nWork with business associates such as advertising agencies, contractors and estate agents, etc to strive for successful launch of projects\nProvide after-sale services to customers\n\n(Candidates with less experience will be considered for junior position.)\n\nGood remuneration and attractive fringe benefits will be offered to the successful applicant. Interested parties please apply with full resume, present and expected salary, available date by clicking \"Apply Now\".\n\nFor further information, please visit our company website: http://www.shkp.com/.\n\n\nWe are an equal opportunity employer and welcome applications from all qualified candidates. All personal data collected will be used for recruitment purpose only.\u00a0 Applicants not hearing from us within 3 months may consider their applications unsuccessful.\u00a0 All personal data collected will be destroyed within 24 months.", "employment_types": ["Full Time", "Permanent"], "selling_points": ["Sales & marketing of residential properties", "Knowledge in DMC preferred", "Willing to work overtime and irregular hours"], "locations": ["Wan Chai"], "categories": ["Marketing / Public Relations", "Marketing - Market Research", "Marketing - Marketing Communication", "Sales, CS & Business Devpt", "Sales - Real Estate"], "post_time": "2022-01-17T14:34:57Z", "salary": {"currency": null, "max": null, "min": null, "period": null, "term": null}, "salary_visible": false, "title_keywords": ["manager", "sales"], "responsibilities": ["advertising", "conduct market research", "analysis", "organize sales", "implementation", "logistics"], "requirements": {"degrees": ["degree or above", "bachelor"], "majors": [], "languages": ["english", "chinese"], "language_level": ["proficient"], "hard_skills": [], "soft_skills": ["organized", "meet tight deadlines", "work overtime", "attentive to details", "customer-oriented", "communication and interpersonal skills", "work under pressure"], "languages_combined": [{"language": "english", "language_level": ["proficient"]}, {"language": "chinese", "language_level": ["proficient"]}]}, "experience_required": {"duration": ["10 years"], "field": ["property developers", "marketing"]}}, {"job_id": "100003009051997", "location_code": "hk", "company": "Sumitomo Mitsui Banking Corporation", "job_title": "SENIOR ASSOCIATE - CORPORATE ADVISORY DEPARTMENT", "description": "Job Duties & Responsibilities:\n\nProvide support to the marketing team in cross-border deals for mainly Japanese clients, duties include\ncollecting information from various sources such as Bloomberg, SPEEDA and company HP\nintegrating information into sophisticated proposal for the customers\u2019 business and\nproviding valuable information to the customers through meetings\nCollaborate with HK branch and others in East Asia Division as well as Corporate Advisory Departments in Tokyo, China and others\nProvide administrative assistance for the department\nHandle ad hoc duties as assigned\n\nRequirements:\n\nDegree holder\nA good team player with good communication, interpersonal and presentation skills\n3-4 years of industry / market research experience preferably in technology sector\nJapanese Language Proficiency Test N1 Level\nGood command of both spoken and written English and Mandarin\nCandidate with less experience will be considered for an associate position\n\nPlease apply with detailed resume stating latest and expected salary by email via \u201cApply Now\u201d.\u00a0\n\nSMBC is an equal opportunity employer. We are committed to fostering a diversified and inclusive workplace and removing barriers to provide equal access to employment.\n\nApplication details will be used only for recruitment purposes, and will be destroyed after 1 year. Applicants not contacted after 6 weeks may consider their applications unsuccessful.", "employment_types": ["Full Time"], "selling_points": ["Provide support to the marketing team", "Degree holder", "3-4 years of industry / market research experience"], "locations": ["Central"], "categories": ["Admin & HR", "Others", "Marketing / Public Relations", "Marketing - Market Research", "Others"], "post_time": "2022-01-17T01:51:23Z", "salary": {"currency": null, "max": null, "min": null, "period": null, "term": null}, "salary_visible": false, "title_keywords": ["senior associate"], "responsibilities": ["collaborate with", "provide support", "administrative assistance", "ad hoc duties"], "requirements": {"degrees": ["degree holder"], "majors": [], "languages": ["japanese", "english", "mandarin"], "language_level": ["proficiency", "good command"], "hard_skills": [], "soft_skills": ["good team player", "communication", "committed", "presentation skills", "interpersonal", "detailed"], "languages_combined": [{"language": "japanese", "language_level": ["proficiency"]}, {"language": "english", "language_level": ["good command"]}, {"language": "mandarin", "language_level": ["good command"]}]}, "experience_required": {"duration": ["3-4 years"], "field": ["market research"]}}, {"job_id": "100003009047219", "location_code": "hk", "company": "Maxx Marketing Limited", "job_title": "Account Executive", "description": "Responsibilities:\n\nConduct analysis on a regular basis, analyze customer demand for banking products and services, collect market information, gain insight into market trends, plan and manage strategies for each customer segment\nAssist in regular customer behavior and business analysis of each customer segment, including but not limited to using various analytical tools to provide information on the segmentation and customer behavior changes\nAssist in formulating and implementing the high and mid customer segment strategies, including sales scripts and training material, to achieve the business targets\nAssist in the launch of various marketing promotions such as customer acquisition, cross-selling, up-selling, aiming to develop potential/high value customer segmentation, and to monitor the target achievement for each promotion on a regular basis\nAccording to customer's needs and deepening of the product penetration, establish and recommend the product portfolio and pricing strategy for specific customer segment\nConduct post campaign evaluation and analysis; deliver timely and right cross-sell plan, closely align with external partner to maximize business result\nEnsure the effective communication between departments in order to achieve targets for each initiative\nProactively working with product managers and channel management, aiming to improve customer revenue contribution, and ensure marketing management strategies are properly implemented\nWorking along the bank strategy and cross collaboration with partners, proactively recommend and review effective measures to improve revenue and achieve targets for the Bank\n\nRequirements:\n\nDegree or above in Business Administration, Marketing, Finance, Statistics or related disciplines\n8 years or above experience in financial industry\nA mature self-starter with strong drive, motivation and committed with good business sense and problem solving skills\nExcellent communication and presentation skills with good command of both written and spoken English and Chinese, knowledge of Mandarin would be a definite advantage\nProficiency in MS Excel and Access\nLess experience will be considered as Segment Management Manager\n\nWe offer competitive remuneration package and comprehensive fringe benefits including medical and life insurance, and different types of allowances to the right candidate. Interested parties, please submit your application online. For details, please visit our website\u00a0http://www.bochk.com\n\nData collected would be used for recruitment purposes only. It might also be disclosed to our subsidiaries or Associated Companies to process the information for appointment. Applicants who do not hear from us within 8 weeks may consider their application unsuccessful and their data will be destroyed within 12 months of receipt.", "employment_types": ["Full Time", "Permanent"], "selling_points": [], "locations": ["Lai Chi Kok"], "categories": ["Marketing / Public Relations", "Marketing - Brand / Product Management", "Marketing - Market Research", "Sales, CS & Business Devpt", "Account Servicing"], "post_time": "2022-01-14T02:37:57Z", "salary": {"currency": null, "max": null, "min": null, "period": "monthly", "term": null}, "salary_visible": false, "title_keywords": ["account executive"], "responsibilities": ["achieve targets", "management", "market information", "evaluation", "analysis", "review", "monitor", "develop", "communication", "marketing promotions", "plan", "banking", "business analysis"], "requirements": {"degrees": ["degree or above"], "majors": ["business administration", "finance", "statistics", "related disciplines", "marketing"], "languages": ["english", "chinese", "mandarin"], "language_level": ["advantage", "excellent", "good command"], "hard_skills": ["problem solving skills", "ms excel"], "soft_skills": ["business sense", "mature", "communication", "committed", "presentation skills", "comprehensive", "problem solving skills"], "languages_combined": [{"language": "english", "language_level": ["advantage", "excellent", "good command"]}, {"language": "chinese", "language_level": ["advantage", "excellent", "good command"]}, {"language": "mandarin", "language_level": ["advantage", "excellent", "good command"]}]}, "experience_required": {"duration": ["8 years"], "field": ["management", "financial industry"]}}, {"job_id": "100003009048401", "location_code": "hk", "company": "MTR Corporation Limited", "job_title": "Marketing Supervisor (Ref: 22000024)", "description": "Responsibilities\n\nSupervise the MTR Merchandising and Souvenirs\u2019 sales operation and performance, product procurement and development, financial administration, stock inventory and distribution logistics as well as support development and distribution of publicity materials (both online and offline)\nLiaise with external and internal parties on the execution of MTR Merchandising and Souvenirs\u2019 sales promotions, including creative agencies, suppliers, laboratory test companies, etc.\u00a0\nAssist in sales and promotion to MTR Mobile users and internal staff\nHandle daily enquiries and complaints related to MTR Merchandising and Souvenirs\u2019 sales business and provide possible resolutions and execution\n\nRequirements\n\nDegree in Marketing / Business Administration or a related discipline\u00a0\nA minimum of 2 year\u2019s relevant experience in marketing\nGood teamwork, organising, interpersonal and communication skills\nProficiency in written and spoken English and Chinese is essential\u00a0\n\nApplications\n\nYou are invited to apply online via http://www.mtr.com.hk/mtr_job_en or send in your CV stating the position (with reference number) you are applying for by mail to Human Resource Management Department, MTR Corporation, G.P.O. Box 9916, Hong Kong on or before\u00a027\u00a0January 2022.\u00a0\n\nFor other job openings, please visit MTR Corporation's website for more details. All information provided by applicants will be treated in strict confidence and used for recruitment purpose only.\n\nAll personal data of unsuccessful applicants will be retained for 12 months for future recruitment purpose and will then be destroyed.", "employment_types": ["Full Time"], "selling_points": ["Supervise the MTR Merchandising", "Degree in Marketing / Business Administration", "A minimum of 2 year\u2019s relevant experience"], "locations": ["Others"], "categories": ["Marketing / Public Relations", "Marketing - General / Support", "Marketing - Market Research", "Marketing - Marketing Communication"], "post_time": "2022-01-14T06:28:15Z", "salary": {"currency": null, "max": null, "min": null, "period": "monthly", "term": null}, "salary_visible": false, "title_keywords": ["supervisor"], "responsibilities": ["inventory", "merchandising", "logistics", "liaise with", "internal parties", "administration"], "requirements": {"degrees": ["degree"], "majors": ["marketing", "business administration"], "languages": ["english", "chinese"], "language_level": ["proficiency"], "hard_skills": [], "soft_skills": ["communication skills", "confidence", "teamwork", "interpersonal"], "languages_combined": [{"language": "english", "language_level": ["proficiency"]}, {"language": "chinese", "language_level": ["proficiency"]}]}, "experience_required": {"duration": ["minimum of 2 year"], "field": ["marketing", "relevant experience"]}}, {"job_id": "100003009048475", "location_code": "hk", "company": "WHARF CHINA ESTATES LIMITED \u4e5d\u9f8d\u5009\u4e2d\u570b\u7f6e\u696d\u6709\u9650\u516c\u53f8", "job_title": "BUSINESS MANAGER", "description": "Responsibilities:\n\nSupport management for the preparation of budget & business planning, financial analysis and management reporting of the Mainland investment property, with a focus in Chongqing\nPerform financial analysis and business modelling to facilitate business reviews, management decision making on business, financial trends and new opportunities\nIdentify issues, discuss and work closely with relevant departments and cross functional teams to analyze and review the financial and operational performance\nWork on quantitative and qualitative study to understand customers and mall performance\nProvide support on the regular update of business performance reports\nAssist in ad hoc projects as assigned\n\nRequirements:\n\nUniversity graduates in Business Administration/ Accounting/ Finance/ Economics/ Statistics or related disciplines\nAt least 5 years of experience with track record in conducting business analysis for management reporting, marketing research, business consulting, data analytics/ intelligence\nExperience in retail/ FMCG/ shopping mall is highly preferred, research agency background an added advantage\nStrong business acumen with excellent interpersonal and presentation skills\nProactive, detail-oriented, sensitive to numbers, and able to work under tight deadlines in a dynamic business environment\nExcellent command in written and spoken\u00a0English and Chinese\nProficient in MS Excel and PowerPoint\n\nWe offer competitive remuneration package that commensurate with experience and qualifications.\u00a0 Interested parties are invited to send full resume stating contact telephone number, date available, present and expected salary to our recruitment email address.", "employment_types": ["Full Time", "Permanent"], "selling_points": ["Preparation of budget and business planning", "Perform financial analysis and business modelling", "Experience in retail / FMCG / shopping mall"], "locations": ["Not Specified"], "categories": ["Professional Services", "Business Analysis / Data Analysis", "Sales, CS & Business Devpt", "Business Development", "Marketing / Public Relations", "Marketing - Market Research"], "post_time": "2022-01-15T03:49:59Z", "salary": {"currency": null, "max": null, "min": null, "period": "monthly", "term": null}, "salary_visible": false, "title_keywords": ["manager"], "responsibilities": ["management", "provide support", "performance reports", "budget", "teams", "review", "financial analysis", "ad hoc projects", "management reporting", "planning"], "requirements": {"degrees": [], "majors": [], "languages": ["english", "chinese"], "language_level": ["excellent"], "hard_skills": ["data analytics", "analysis", "powerpoint", "ms excel", "dynamic", "acumen"], "soft_skills": ["business environment", "detail-oriented", "presentation skills", "dynamic", "business acumen", "sensitive to numbers", "proactive", "interpersonal"], "languages_combined": [{"language": "english", "language_level": ["excellent"]}, {"language": "chinese", "language_level": ["excellent"]}]}, "experience_required": {"duration": ["at least 5 years"], "field": ["management", "research", "fmcg", "consulting", "agency", "marketing", "business", "business analysis", "retail"]}}, {"job_id": "100003009047736", "location_code": "hk", "company": "Public Bank (Hong Kong) Ltd", "job_title": "Officer \u2013 Digital Transformation (General) (Ref: SO-ODTG)", "description": "Coordinate the implementation of information and technological transformation solutions and initiatives.\nConduct market survey and product analysis in response to latest digital products and services features offered by other financial institutions via online media, engagement with customers\nCollaborate with I.T. Department and the relevant departments / business users pertaining to all digital transformation related projects\nSupport the hotline and handle customers\u2019 enquires related to digital banking services.\nSecondary education with minimum 3 years of relevant experience in banking industry\nGood communication skills in both English and Chinese (including Cantonese & Mandarin)\nGood interpersonal and coordination skills\nProficient in MS Office applications (MS Word and Excel)\n\nTo apply, interested parties please follow the application methods available in the Bank\u2019s career website https://www.publicbank.com.hk/en/aboutus/careeropportunities. You can send us your resume quoting our job reference number together with present & expected salary (a must) to the Human Resources Department by email or fax at 2815 3157 or by post to Human Resources Department, 12/F, Public Bank Centre, 120 Des Voeux Road Central, Hong Kong. You may also visit our career website for other career opportunities available within our Group.\n\nPersonal data collected will be used for recruitment purpose only and will be treated in accordance with the Bank\u2019s Personal Information Collection Statement, a copy of which has been available in the Bank\u2019s career website.", "employment_types": ["Full Time", "Permanent"], "selling_points": [], "locations": ["Not Specified"], "categories": ["Banking / Finance", "Analyst", "Others", "Marketing / Public Relations", "Marketing - Market Research"], "post_time": "2022-01-15T03:49:03Z", "salary": {"currency": null, "max": null, "min": null, "period": null, "term": null}, "salary_visible": false, "title_keywords": ["officer"], "responsibilities": ["collaborate with", "analysis", "implementation", "coordinate", "communication", "coordination", "banking"], "requirements": {"degrees": ["secondary education"], "majors": [], "languages": ["cantonese", "english", "chinese", "mandarin"], "language_level": ["good"], "hard_skills": ["ms word", "excel", "analysis", "ms office"], "soft_skills": ["communication skills", "coordination skills", "interpersonal"], "languages_combined": [{"language": "cantonese", "language_level": ["good"]}, {"language": "english", "language_level": ["good"]}, {"language": "chinese", "language_level": ["good"]}, {"language": "mandarin", "language_level": ["good"]}]}, "experience_required": {"duration": ["minimum 3 years"], "field": ["banking industry", "relevant experience", "education"]}}, {"job_id": "100003009049309", "location_code": "hk", "company": "Tulipland Group Limited", "job_title": "Sales Marketing event Assistant \u5e02\u5834\u6d3b\u52d5\u52a9\u7406", "description": "Job responsibilities:\n-Assist in the planning and management of different business activities\n-Evaluate and monitor the performance of business activities\n-Conduct goal-oriented market research under the guidance of the head of the marketing team\n-Production of promotions and materials (posters, leaflets, brochures)\n-Handling temporary projects as needed\n\nQualifications\n-University degree or are currently studying.\n-Active, proactive, independent and careful, full of enthusiasm for work\n-Good interpersonal communication skills and ability to work independently\n-Fluent in Mandarin and Cantonese", "employment_types": ["Full Time"], "selling_points": [], "locations": ["Tsim Sha Tsui"], "categories": ["Marketing / Public Relations", "Marketing - Market Research"], "post_time": "2022-01-14T08:26:13Z", "salary": {"currency": "HKD", "max": 24999, "min": 17000, "period": "monthly", "term": null}, "salary_visible": true, "title_keywords": ["event assistant", "sales"], "responsibilities": ["guidance", "management", "leaflets", "market research", "communication", "monitor the performance", "business activities", "planning"], "requirements": {"degrees": ["degree"], "majors": [], "languages": ["cantonese", "mandarin"], "language_level": [], "hard_skills": ["goal"], "soft_skills": ["communication skills", "work independently", "careful", "independent", "proactive", "interpersonal"], "languages_combined": [{"language": "cantonese", "language_level": []}, {"language": "mandarin", "language_level": []}]}, "experience_required": {"duration": [], "field": []}}, {"job_id": "100003009039922", "location_code": "hk", "company": "csl.", "job_title": "Marketing & Customer Analyst (research focus)", "description": "Marketing & Customer Analyst\n\nAs a team member of Customer Data Analytics Team, you will be responsible for generation of actionable recommendations by synergizing insights from research, customer feedback and customer data to support business growth and enhance customer engagement. This role is suitable for those who are interested in developing his/her career in using fact-based data-driven approach to influence business decisions.\n\nYour role\n\nManage market research initiatives from beginning to end using a variety of quantitative and qualitative research methods, including questionnaire design, online survey platform set up, data processing and result reporting\nCollect and organize data from various sources to facilitate market analysis\nManage customer engagement panel to support internal marketing initiatives\nManage customer feedback platform to support channel operations in enhancing customer experience\nAssist in ad hoc analysis and other duties as required\n\nTo succeed in this role\n\nUniversity graduate in Business, Statistics or other related fields\n1-2 year\u2019s working experience in market research or customer data analysis\nStrong numeric sense, analytical skill\nAbility to use analysis tools, including SPSS (knowledge in syntax is an advantage) and Access\nKnowledge on Python or Tableau is a plus\nAbility to work independently and willing to take challenge\nEffective communication in written and spoken English and Chinese\nComputer proficiency in MS PowerPoint, Word, Excel (Advanced Excel)\n\nHKT is an equal opportunity employer and welcomes applications from all qualified candidates. Information provided will be treated in strict confidence and will only be used for recruitment-related purposes.\nPersonal data provided by job applicants will be used strictly in accordance with the employer's privacy statement (www.hkt.com/privacy-statement), a copy of which will be provided immediately upon request.", "employment_types": ["Full Time"], "selling_points": ["generation of actionable recommendations", "fact-based data-driven approach", "deliveries of regular customer engagement research"], "locations": ["Quarry Bay"], "categories": ["Marketing / Public Relations", "Marketing - Market Research"], "post_time": "2022-01-11T15:27:13Z", "salary": {"currency": null, "max": null, "min": null, "period": "monthly", "term": null}, "salary_visible": false, "title_keywords": ["analyst"], "responsibilities": ["reporting", "ad hoc", "other duties", "data", "operations", "analysis", "market research", "developing", "customer data", "design", "data processing", "communication", "market analysis", "recruitment", "questionnaire", "personal data"], "requirements": {"degrees": ["university graduate"], "majors": ["business", "statistics"], "languages": ["english", "chinese"], "language_level": [], "hard_skills": ["excel", "analytical skill", "plus", "data analytics", "analysis", "word", "tableau", "python", "ms powerpoint", "processing"], "soft_skills": ["analytical skill", "work independently", "confidence", "advanced", "responsible", "interested in", "communication", "team member", "driven"], "languages_combined": [{"language": "english", "language_level": []}, {"language": "chinese", "language_level": []}]}, "experience_required": {"duration": ["1-2 year"], "field": ["data analysis", "market research"]}}, {"job_id": "100003009048018", "location_code": "hk", "company": "Oriental International Systems Co Ltd", "job_title": "Full Time / Part Time Sales and Marketing Executive", "description": "Responsibilities\n\nCommunicating with teams regarding project needs and goals\nContributing to the planning and implementation of projects\nSupporting the coordination and management of projects\nKeeping track of and reporting on project progress\nResearching information as required\nPerforming other duties assigned by the Business Manager in an orderly and efficient manner\nConducting administrative duties such as preparing invoices, estimates, scheduling meetings, etc\n\u00a0Requirements\u00a0\nFresh graduate or 2years+ working experience in a related fields, marketing, information system or business communication\nHighly organised and able to multitask\nStrong attention to detail and problem-solving skills\nExcellent communication skills in both Chinese and English, both verbal and written\nProficiency in any management and website software\nAble to work independently and as part of a team\n\nPlease submit your resume with current and expected salary. All applications will be treated strictly confidential for recruitment purpose only.", "employment_types": ["Full Time", "Part Time"], "selling_points": ["Preferably with knowledge in computer language", "5 working days with a competitive salary", "Fresh graduate will also be considered"], "locations": ["Kwun Tong"], "categories": ["Information Technology (IT)", "Network & System", "Marketing / Public Relations", "Marketing - Market Research", "Sales, CS & Business Devpt", "Tele-sales (Telemarketing)"], "post_time": "2022-01-14T04:31:51Z", "salary": {"currency": null, "max": null, "min": null, "period": "monthly", "term": null}, "salary_visible": false, "title_keywords": ["sales and marketing executive"], "responsibilities": ["reporting", "management", "invoices", "other duties", "teams", "project progress", "implementation of projects", "scheduling", "communicating with", "administrative duties", "coordination", "planning"], "requirements": {"degrees": ["fresh graduate"], "majors": ["business", "marketing"], "languages": ["english", "chinese"], "language_level": ["excellent"], "hard_skills": ["problem-solving skills", "information system"], "soft_skills": ["communication skills", "work independently", "communication", "multitask", "attention to detail", "organised", "problem-solving skills"], "languages_combined": [{"language": "english", "language_level": ["excellent"]}, {"language": "chinese", "language_level": ["excellent"]}]}, "experience_required": {"duration": [], "field": ["related", "marketing", "business"]}}, {"job_id": "100003009051358", "location_code": "hk", "company": "Changetic Limited", "job_title": "Assistant Project Manager", "description": "Responsibilities:\n\n\nDevelop digital strategy, manage and implement on digital campaign to achieve new sales target\nLead and support all digital performance acquisition projects\nKeep track of digital initiatives\u2019 KPIs and advise business insights for optimization\nOn-going optimization to achieve KPI target\nEffectively manage campaign budget spend by implementing relevant media strategies and keeping track of budget pacing, updating the strategy, and troubleshoot accordingly\nProduce and develop reports on monthly campaign performance, audiences, creative analysis\nRegular competitor research to monitor what other companies are doing\nDevelop content for paid advertising and organic social post\nCoordinate and build strong relationships with internal & external stakeholders to optimize the outcome\nManage agencies to ensure smooth execution of projects\nHandle ad-hoc projects\n\n\n\nRequirements:\n\nDegree holder in Marketing, Digital or related disciplines\nWith 6 - 8 years of experience in digital marketing, preferably from Telecommunications company\nHands on experience on Google Adwords, Facebook Ad Manager\nComfortable with data and familiar with analytic tools e.g. Adobe analytics, Google Search console, Google analytics\nSolid experience on performance marketing, with independent ability to take on campaign executions\nDigital savvy, with specific proficiency at MS Suite: Excel, Word, PowerPoint\nAble to produce high quality work within a fast paced, dynamic environment\nFluent in written and spoken Chinese and English\nCandidates from both in-house and performance marketing agencies are welcome\n\n\n\nApart from competitive remuneration package and exciting opportunity for career development within the Group, we provide attractive employee benefits such as free company shuttle, free company SIM card and preferential SIM plan offers, comprehensive medical & insurance schemes, as well as full range of other employee well-being provisions.\u00a0\n\nInterested parties, please send in your profile with your salary expectation to career@ hthk.com\u00a0\n\nWe are an equal opportunity employer and welcome applications from all qualified candidates. Personal data collected will be treated in the strictest confidence and handled confidentially by authorised personnel for recruitment-related purposes only within the CK Hutchison Group of companies. The personal data of unsuccessful applicants will be destroyed after the recruitment exercise pursuant to the requirements of the Personal Data (Privacy) Ordinance in Hong Kong.", "employment_types": ["Full Time", "Permanent"], "selling_points": ["5-day work week", "Professional working environment", "Strong personal and professional growth"], "locations": ["Sheung Wan"], "categories": ["Professional Services", "Business Consultancy", "Sales, CS & Business Devpt", "Business Development", "Marketing / Public Relations", "Marketing - Market Research"], "post_time": "2022-01-15T10:54:23Z", "salary": {"currency": null, "max": null, "min": null, "period": "monthly", "term": null}, "salary_visible": false, "title_keywords": ["assistant project manager"], "responsibilities": ["advertising", "sales target", "budget", "analysis", "monitor", "develop", "coordinate", "reports", "troubleshoot", "kpis", "ad-hoc projects"], "requirements": {"degrees": ["degree holder"], "majors": ["related disciplines", "marketing"], "languages": ["english", "chinese"], "language_level": ["fluent"], "hard_skills": ["google analytics", "excel", "adwords", "word", "powerpoint", "adobe", "dynamic", "facebook"], "soft_skills": ["comprehensive", "dynamic environment", "hands on", "independent"], "languages_combined": [{"language": "english", "language_level": ["fluent"]}, {"language": "chinese", "language_level": ["fluent"]}]}, "experience_required": {"duration": ["6 - 8 years"], "field": ["telecommunications", "marketing", "digital marketing"]}}, {"job_id": "100003009051284", "location_code": "hk", "company": "Hutchison Telecommunications (Hong Kong) Limited", "job_title": "Assistant Marketing Manager (Online Acquisition)", "description": "Responsibilities:\n\nInitiate, develop and implement assigned digital marketing campaigns and related projects\nKnowledge in SEO optimization to increase search ranking and search demand captures by our owned channels. Code development framework knowledge is a plus\nDrive planning and rolling out of O2O marketing campaigns and prepare post campaign report for analysis\nCoordinate with internal departments and partners on the development and implement of CRM program strategy and mechanics, program branding, loyalty system, digital ecosystem, app, website\nIdentify trends and insights, optimize the performance of SEO/SEM; direct marketing channels e.g. eDM, SMS, MMS etc, to achieve KPI\nAchieve sales target in order to increase the Company\u2019s revenue and market share\nCoordinate and build strong relationships with internal & external stakeholders to optimize the outcome\nAble to produce high quality work within a fast paced, dynamic environment\nHandle ad-hoc projects\nRequirements\n\nDegree holder in Marketing, e-Commerce, multi-media or related disciplines\n6 - 8 years of experience working at a respectable digital agency or digital marketing team of a recognized brand\nSolid understanding of key marketing tech/tools included but not limited to: Facebook Ads, Google Adwords, Google Analytics, Adobe analytics, Google Search console\nBasic knowledge in SQL, data management and data visualization tools, such as Oracle, Tableau, etc. Hands on experience with data integration and system applications projects\nDigital savvy, with specific proficiency at MS Suite: Excel, Word, PowerPoint\nFluent in written and spoken Chinese and English\nCandidates from both in-house and agency are welcome\nExcellent Project Management skills and communication skills\nGood negotiation and interpersonal skills, and ability to engage a wide range of stakeholders to agree on scope and requirements\n\n\n\nApart from competitive remuneration package and exciting opportunity for career development within the Group, we provide attractive employee benefits such as free company shuttle, free company SIM card and preferential SIM plan offers, comprehensive medical & insurance schemes, as well as full range of other employee well-being provisions.\u00a0\n\nInterested parties, please send in your profile with your salary expectation to career@ hthk.com\u00a0\n\nWe are an equal opportunity employer and welcome applications from all qualified candidates. Personal data collected will be treated in the strictest confidence and handled confidentially by authorised personnel for recruitment-related purposes only within the CK Hutchison Group of companies. The personal data of unsuccessful applicants will be destroyed after the recruitment exercise pursuant to the requirements of the Personal Data (Privacy) Ordinance in Hong Kong.", "employment_types": ["Full Time", "Permanent"], "selling_points": [], "locations": ["Tsing Yi"], "categories": ["Marketing / Public Relations", "Marketing - Direct Marketing", "Marketing - General / Support", "Marketing - Market Research"], "post_time": "2022-01-15T07:17:38Z", "salary": {"currency": null, "max": null, "min": null, "period": "monthly", "term": null}, "salary_visible": false, "title_keywords": ["assistant marketing manager"], "responsibilities": ["seo", "edm", "digital marketing campaigns", "analysis", "sales target", "coordinate with", "website", "quality", "develop", "coordinate", "marketing campaigns", "sem", "report", "ad-hoc projects", "planning"], "requirements": {"degrees": ["degree holder"], "majors": ["related disciplines", "marketing", "e-commerce"], "languages": ["english", "chinese"], "language_level": ["fluent"], "hard_skills": ["google analytics", "excel", "basic", "data management", "e-commerce", "adwords", "word", "tableau", "powerpoint", "sql", "project management", "adobe", "data visualization", "integration", "facebook", "oracle"], "soft_skills": ["communication skills", "negotiation", "project management skills", "hands on", "interpersonal skills", "comprehensive"], "languages_combined": [{"language": "english", "language_level": ["fluent"]}, {"language": "chinese", "language_level": ["fluent"]}]}, "experience_required": {"duration": ["6 - 8 years"], "field": ["brand", "agency", "digital marketing", "digital", "team"]}}, {"job_id": "100003009051286", "location_code": "hk", "company": "Hutchison Telecommunications (Hong Kong) Limited", "job_title": "Assistant Marketing Manager (SEO, O2O)", "description": "Job Responsibilities:\n\nFormulate strategies for new products from idea generation, market research to product launch and implementation\nConduct comprehensive analysis of product performance to identify opportunities and challenges for growth and development\nPlan and drive product launching activities to achieve business targets\nEvaluate the product effectiveness in response to customers\u2019 feedback and follow up issues\nMonitor product development progress; coordinate with internal and external parties to ensure the deadlines are met\nPrepare regular reports and participate in ad hoc assignments\n\nRequirements:\n\nDiploma or above in marketing, logistics or related disciplines.\nAt least 1 year working experience, with experience of product development is a definite advantage.\nGood logical mind-set with excellent communication and project management skills, ability to handle multiple tasks and meet tight deadlines.\nProficient in MS PowerPoint, MS Excel and Chinese Word Processing.\nGood command of both written and spoken Chinese and English, knowledge in Putonghua is a plus.\u00a0\nImmediate candidate is highly preferred\nWe offer attractive remuneration package and fringe benefits to the suitable candidates. Interested parties, please submit your application to us. If you do not want to apply as a JobsDB member, you may send your full resume with your availability, current and expected salaries to recruit01 at sf-express.com\nYou are welcome to visit our website at\u00a0https://htm.sf-express.com/hk/tc/\u00a0for more information about us.\n\nCandidates who are not invited for an interview within 1-month may consider their applications unsuccessful.\nAll personal data provided by job applicants will be used only for recruitment purposes and will be treated strictly confidential. Unsuccessful applications will be retained for a maximum period of 24-month.", "employment_types": ["Full Time", "Permanent"], "selling_points": [], "locations": ["Tsing Yi"], "categories": ["Marketing / Public Relations", "Marketing - Direct Marketing", "Marketing - General / Support", "Marketing - Market Research"], "post_time": "2022-01-15T07:17:38Z", "salary": {"currency": null, "max": null, "min": null, "period": "monthly", "term": null}, "salary_visible": false, "title_keywords": ["assistant marketing manager"], "responsibilities": ["analysis", "internal and external parties", "monitor", "implementation", "market research", "coordinate with", "evaluate", "reports", "ad hoc assignments", "plan"], "requirements": {"degrees": ["diploma or above"], "majors": ["related disciplines", "marketing"], "languages": ["putonghua", "english", "chinese"], "language_level": ["good command", "proficient"], "hard_skills": ["plus", "chinese word processing", "project management", "ms excel", "ms powerpoint"], "soft_skills": ["communication", "project management skills", "meet tight deadlines", "handle multiple tasks"], "languages_combined": [{"language": "putonghua", "language_level": ["good command"]}, {"language": "english", "language_level": ["good command"]}, {"language": "chinese", "language_level": ["good command", "proficient"]}]}, "experience_required": {"duration": ["at least 1 year"], "field": ["product development"]}}, {"job_id": "100003009048669", "location_code": "hk", "company": "S.F. Express (Hong Kong) Limited", "job_title": "Product Management Executive", "description": "Requirements:\n\n\nBachelor\u2019s degree in statistics, mathematics, marketing or a related discipline\nMinimum 5 years\u2019 experience in market research in Hong Kong & China with qualitative research experience preferred\nKnowledge on residential property and retail market in HK & Mainland China preferred\nProficiency with SPSS, Excel & Powerpoint. Knowledge on SQL and VBA an advantage\nProven English proficiency and fluent Putonghua\nGood communication, analytical and time management skills\nProactive, independent and detail-minded\nWilling to work overtime and on public holidays, as well as under pressure\n\nResponsibilities:\n\n\nDesign and conduct quantitative surveys on residential properties markets, shopping malls in HK and Mainland and other Group's business so as to understand market sentiment and customer behaviors & needs\nLiaise with internal departments and external research agencies on research requirement\nAssist in leveraging large amount of data by using SQL, VBA or some big data tools\nCompile timely research & analytical reports\n\nGood remuneration and attractive fringe benefits will be offered to the successful applicant.\u00a0 Interested parties please apply with full resume, present and expected salary, available date by clicking \" Apply Now\".\n\nFor further information, please visit our company website:\u00a0www.shkp.com.\n\nWe are an equal opportunity employer and welcome applications from all qualified candidates. All personal data collected will be used for recruitment purpose only.\u00a0 Applicants not hearing from us within 3 months may consider their applications unsuccessful.\u00a0 All personal data collected will be destroyed within 24 months.", "employment_types": ["Full Time", "Permanent"], "selling_points": ["New products idea generation and market research", "Plan product launching activities", "Sound product development experience"], "locations": ["Tsing Yi"], "categories": ["Marketing / Public Relations", "Marketing - Brand / Product Management", "Marketing - General / Support", "Marketing - Market Research"], "post_time": "2022-01-14T07:00:18Z", "salary": {"currency": null, "max": null, "min": null, "period": "monthly", "term": null}, "salary_visible": false, "title_keywords": ["executive"], "responsibilities": ["data", "big data", "design", "reports", "liaise with"], "requirements": {"degrees": ["degree", "bachelor"], "majors": ["mathematics", "marketing", "statistics"], "languages": ["putonghua", "english"], "language_level": ["proficiency", "fluent"], "hard_skills": ["sql", "excel", "vba", "powerpoint"], "soft_skills": ["detail-minded", "work overtime", "independent", "under pressure", "time management skills", "communication", "proactive"], "languages_combined": [{"language": "putonghua", "language_level": ["fluent", "proficiency"]}, {"language": "english", "language_level": ["proficiency"]}]}, "experience_required": {"duration": ["minimum 5 years"], "field": ["research", "market research"]}}, {"job_id": "100003009039666", "location_code": "hk", "company": "Sun Hung Kai Properties Ltd", "job_title": "RESEARCH OFFICER \u2013 MARKET RESEARCH", "description": "Responsibilities:\n\nDevelop & implement upsell & loyalty programs\nDesign workflow and support daily operation of each program campaign\nPrepare analytical reports for result monitoring\nLiaise with colleagues from different departments, suppliers and partners\nCompetitor activity monitoring\n\nRequirements:\n\nBachelor\u2019s Degree Holder\nGood planning, data analysis and reporting skills\nAttention to details and willing to work under pressure\nFamiliar with Excel, Word and PowerPoint\nKnowledge on customer segmentation and digital marketing is highly preferred\u00a0\nFluent in written and spoken English & Chinese\n\nCreative thinking and out-going\nAble to work well as part of a team & independently\n\nApart from competitive remuneration package and exciting opportunity for career development within the Group, we provide attractive employee benefits such as free company shuttle, free company SIM card and preferential SIM plan offers, comprehensive medical & insurance schemes, as well as full range of other employee well-being provisions.\u00a0\n\nInterested parties, please apply with full resume, present and expected salary, by clicking \u201cAPPLY NOW\u201d. Please quote the reference number on the e-mail subject.\n\nWe are an equal opportunity employer and welcome applications from all qualified candidates. Personal data collected will be treated in the strictest confidence and handled confidentially by authorised personnel for recruitment-related purposes only within the CK Hutchison Group of companies. The personal data of unsuccessful applicants will be destroyed after the recruitment exercise pursuant to the requirements of the Personal Data (Privacy) Ordinance in Hong Kong.", "employment_types": ["Full Time", "Permanent"], "selling_points": ["Degree with 5 years' market research experience", "Conduct quantitative surveys on properties markets", "Willing to work overtime and on public holidays"], "locations": ["Wan Chai"], "categories": ["Marketing / Public Relations", "Marketing - Market Research", "Others", "Property / Real Estate", "Others"], "post_time": "2022-01-11T10:25:27Z", "salary": {"currency": null, "max": null, "min": null, "period": null, "term": null}, "salary_visible": false, "title_keywords": ["research officer"], "responsibilities": ["monitoring", "daily operation", "design", "develop", "reports", "liaise with"], "requirements": {"degrees": ["bachelor", "degree holder"], "majors": [], "languages": ["english", "chinese"], "language_level": ["fluent"], "hard_skills": ["excel", "analysis", "word", "powerpoint"], "soft_skills": ["independently", "comprehensive", "attention to details", "creative", "work under pressure"], "languages_combined": [{"language": "english", "language_level": ["fluent"]}, {"language": "chinese", "language_level": ["fluent"]}]}, "experience_required": {"duration": [], "field": []}}, {"job_id": "100003009050703", "location_code": "hk", "company": "Hutchison Telecommunications (Hong Kong) Limited", "job_title": "Corporate Marketing Executive \u2013 Business Planning & Retention", "description": "Reporting to the Publicity and Fundraising Manager and be responsible for the following areas:\n\n\u00a0Responsibilities\n\nImplement communications, media and fundraising strategies.\nIncrease Organization\u2019s exposure both in social media and traditional media.\nDevelop and maintain Organization\u2019s publication, website and social media.\nBuild and maintain positive rapport with stakeholders.\nLiaise with vendors to produce marketing materials.\nPerform ad hoc duties as assigned.\u00a0\n\nRequirements\u00a0\n\nDegree in Marketing, Communications, Journalism, Public Relations or related discipline. \u00a0\nAt least 3 years\u2019 relevant work experience.\nProficiency in website, digital and social media applications.\nGood command of both written and spoken English and Chinese.\nGood interpersonal and communication skills, ability to work with people of all levels.\nAble to work independently and under pressure.\n\nOur salary and benefits are competitive in the field of local NGOs. We sincerely invite people who share the same commitment to children and youth service as ours, to express interest by sending your application with full resume by email click \"Apply Now\" to apply for this position.\n\n(Short-listed candidates will be requested to undergo Sexual Conviction Record Check operated by the Hong Kong Police Force. All information provided will only be used for recruitment related purpose.)", "employment_types": ["Full Time", "Permanent"], "selling_points": [], "locations": ["Tsing Yi"], "categories": ["Marketing / Public Relations", "Marketing - Market Research", "Marketing - Marketing Communication", "Digital Marketing"], "post_time": "2022-01-14T11:13:26Z", "salary": {"currency": null, "max": null, "min": null, "period": "monthly", "term": null}, "salary_visible": false, "title_keywords": ["marketing executive"], "responsibilities": ["marketing materials", "social media", "ad hoc duties", "website", "develop", "maintain", "liaise with", "publication"], "requirements": {"degrees": ["degree"], "majors": ["journalism", "marketing", "communications"], "languages": ["english", "chinese"], "language_level": ["good command"], "hard_skills": ["social media applications"], "soft_skills": ["communication skills", "work independently", "under pressure", "interpersonal"], "languages_combined": [{"language": "english", "language_level": ["good command"]}, {"language": "chinese", "language_level": ["good command"]}]}, "experience_required": {"duration": ["at least 3 years"], "field": []}}, {"job_id": "100003009046220", "location_code": "hk", "company": "The Hong Kong Student Aid Society Limited", "job_title": "Publicity and Fundraising Officer (HO/PFO/2021069)", "description": "Job Description\n\nTo assist in planning, developing and executing comprehensive sales & marketing\u00a0plans\nTo organize & handle daily sales & marketing activities and PR events\nTo assist in digital marketing related projects\nTo conduct marketing research\nTo prepare various reports & analysis and PowerPoint presentations\nTo handle ad-hoc assignments\n\nJob Requirements\n\nDegree\u00a0holder in Marketing or related disciplines\n3 years of\u00a0relevant experience\nProficient in MS Office application, especially in PowerPoint\nGood presentation and communications skills\nExcellent\u00a0command\u00a0of written and spoken English and Chinese, including Putonghua\u00a0\n\nInterested parties, please click \"APPLY NOW\" and send us your full resume, stating date available, present\u00a0and expected salary.\n\n\n(Applicant without stating the expected salary will not be considered)\n\nAll data collected will be used for recruitment purpose only and will be treated as strictly confidential.\u00a0 All unsuccessful applications will be destroyed upon completion of the selection process.\n\nOur website: www.aprentalshk.com\u00a0", "employment_types": ["Full Time", "Contract"], "selling_points": [], "locations": ["Kwun Tong"], "categories": ["Marketing / Public Relations", "Marketing - Market Research", "Marketing - Marketing Communication"], "post_time": "2022-01-13T10:01:42Z", "salary": {"currency": null, "max": null, "min": null, "period": "monthly", "term": null}, "salary_visible": false, "title_keywords": ["fundraising officer"], "responsibilities": ["marketing plans", "ad-hoc assignments", "analysis", "developing", "presentations", "marketing research", "executing", "digital marketing", "reports", "sales & marketing activities", "planning"], "requirements": {"degrees": ["degree holder"], "majors": ["related disciplines", "marketing"], "languages": ["putonghua", "english", "chinese"], "language_level": ["excellent"], "hard_skills": ["powerpoint", "ms office"], "soft_skills": ["presentation"], "languages_combined": [{"language": "putonghua", "language_level": ["excellent"]}, {"language": "english", "language_level": ["excellent"]}, {"language": "chinese", "language_level": ["excellent"]}]}, "experience_required": {"duration": ["3 years"], "field": ["relevant experience"]}}, {"job_id": "100003009047376", "location_code": "hk", "company": "AP Rentals Limited", "job_title": "Sales & Marketing Officer", "description": "Responsibilities:\n\nPrepare reports for primary sector including consumption table, analytical reports of property transaction etc.\nHandle and coordinate with the promotions of projects, such as preparing proposal for Tendering as Sole Agent\nLiaise with Developer for updates of leasing properties\nAc hoc tasks as assigned by Administrative Team\n\nRequirements:\n\nFor 5 or above\n1-2 years' relevant work experience\nGood\u00a0command of written Chinese\nProficient in MS Excel and Powerpoint\nImmediate available is preferred\n\nWe provide its members\u00a0with professional training, attractive remuneration package and excellent career prospects.\u00a0 For application, please send full resume with present and expected salary to Human Resources Department, 5/F., Tower 1, New World Tower, 18 Queen' s Road Central, Hong Kong\n\nFor more information about us, please visit our website at: www.centanet.com\n\nData collected will be used for recruitment purpose only", "employment_types": ["Full Time", "Permanent"], "selling_points": [], "locations": ["Yuen Long"], "categories": ["Marketing / Public Relations", "Marketing - General / Support", "Marketing - Market Research", "Marketing - Marketing Communication"], "post_time": "2022-01-14T02:56:36Z", "salary": {"currency": null, "max": null, "min": null, "period": "monthly", "term": null}, "salary_visible": false, "title_keywords": ["sales", "marketing officer"], "responsibilities": ["coordinate with", "tendering", "liaise with", "reports", "prepare reports"], "requirements": {"degrees": [], "majors": [], "languages": ["chinese"], "language_level": ["good command"], "hard_skills": ["ms excel", "powerpoint"], "soft_skills": [], "languages_combined": [{"language": "chinese", "language_level": ["good command"]}]}, "experience_required": {"duration": ["1-2 years"], "field": []}}, {"job_id": "100003009049126", "location_code": "hk", "company": "Centaline Property Agency Ltd", "job_title": "Executive", "description": "Key Responsibilities\n\nProvide editorial and event management support in all publicity related assignments;\nSupport the department in English and Chinese editorial needs, including corporate materials and marketing write-ups;\nAct as key liaison between external stakeholders and internal departments to ensure communication objective are met;\nSupervise the team in day-to-day assignments and manage departmental calendar effectively;\nSupport building digital capability across the enterprise and act as custodian of all online assets;\nResearch and collect information on industry and public affairs to keep the company abreast of market developments;\nAssist in ad-hoc projects as assigned.\n\nRequirement\n\nBachelor Degree holder, preferably in Translations, English Studies, Mass Communications or related disciplines;\nMinimum 10 years of solid experience in media, corporate communications, public affairs, or research and analysis, preferably in sizable company or news outlet;\nAt least 2 years\u2019 experience in supervisory role in reputable organization is preferred;\nExcellent command of written and spoken English and Chinese, conversant in Mandarin is preferred;\nStrong PC skills, familiar with creative software is preferable;\nMust have solid media experience and proven track record in handling large scale events;\nGood interpersonal and communications skills; team player and meticulous;\nCandidate with lesser experience will be considered for an Assistant Manager position.\n\nWe offer long-term career prospect and competitive remuneration package to the appointed candidate. Please apply in confidence with your detailed resume stating your current and expected salary to\u00a0Group Human Resources Department\n\nby email to\u00a0recruit(at)shuntakgroup.com\n\nor mail to\u00a0Penthouse 39/F, West Tower, Shun Tak Centre, 200 Connaught Road Central, Hong Kong\n\n(Please quote reference number and applied position)\n\nThe information supplied by the applicants will be used in accordance with the Personal Data (Privacy) Policy of Shun Tak Group (a copy of which will be provided upon request). Only shortlisted candidates will be notified.\n\n\nwww.shuntakgroup.com", "employment_types": ["Full Time", "Permanent"], "selling_points": ["Data searching and analysis", "Responsible for reports preparation", "Form 5 or above with 1-2 years work experience"], "locations": ["Central"], "categories": ["Marketing / Public Relations", "Marketing - Market Research", "Others"], "post_time": "2022-01-14T08:09:06Z", "salary": {"currency": null, "max": null, "min": null, "period": "monthly", "term": null}, "salary_visible": false, "title_keywords": ["executive"], "responsibilities": ["communication", "management", "ad-hoc projects"], "requirements": {"degrees": ["bachelor degree holder"], "majors": ["related disciplines", "communications"], "languages": ["english", "chinese", "mandarin"], "language_level": ["excellent"], "hard_skills": ["analysis", "pc skills"], "soft_skills": ["meticulous", "team player", "creative", "interpersonal"], "languages_combined": [{"language": "english", "language_level": ["excellent"]}, {"language": "chinese", "language_level": ["excellent"]}, {"language": "mandarin", "language_level": ["excellent"]}]}, "experience_required": {"duration": ["at least 2 years", "minimum 10 years"], "field": ["supervisory", "research", "media"]}}, {"job_id": "100003009049058", "location_code": "hk", "company": "Shun Tak Holdings Ltd", "job_title": "Manager, Corporate Communications (Ref. STHL1714)", "description": "Job Description\n\n\nCopywriting for NUU Mobile will lead the strategic storytelling responsibility in creating original, culturally vibrant, brand engagement: from top level campaign concepts, to arrange media advertising, and everything in between.\nPlay an instrumental role in shaping the expression of the NUU Mobile brand.\nBring ideas to life and convey our marketing messages to our target audiences.\nExecute and shepherd concepts from conception and executive buy-in through all stages of creative development, production and post-production\u2014ensuring faithful execution, quality, and brand consistency all the way.\nSeek to push the brand and our marketing practice into new media, experimenting, testing and tracking.\nQualifications\n\nDegree in Fine Arts, Communication Design, Advertising or equivalent practical experience.\n5+ years of writing and creative direction experience at a creative agency;\nExceptional conceptual and written storytelling talent;\nProven experience developing strategically grounded, creative ideas across digital and traditional media, for major consumer brands;\nA strong and diverse portfolio of original advertising and brand engagement work, including digital, video, and new media;\nExpert understanding of creative considerations across print, website, mobile, online advertising, social media, video, and so on;\nAbility to thoughtfully and persuasively articulate creative concepts to cross-functional teams;\nProficiency in creative and productivity applications: Photoshop, InDesign, Keynote/PowerPoint/Google Slides;\nExperience in technology, consumer technology or consumer lifestyle categories;\nTravelling is required and will stay in USA at least 6 months per year.", "employment_types": ["Full Time"], "selling_points": ["Provide editorial and event management support", "Corporate materials and marketing write-ups", "Supervise the team in day-to-day assignments"], "locations": ["Sheung Wan"], "categories": ["Marketing / Public Relations", "Marketing - Market Research", "Marketing - Marketing Communication", "Public Relations - Copy-writing"], "post_time": "2022-01-14T08:00:11Z", "salary": {"currency": null, "max": null, "min": null, "period": "monthly", "term": null}, "salary_visible": false, "title_keywords": ["manager"], "responsibilities": ["social media", "creative ideas", "advertising", "ideas", "quality", "developing", "design", "testing", "communication", "website", "brand consistency", "online advertising", "cross-functional teams", "tracking"], "requirements": {"degrees": ["degree"], "majors": ["fine arts", "design"], "languages": [], "language_level": [], "hard_skills": ["mobile", "indesign", "powerpoint", "photoshop"], "soft_skills": ["communication", "diverse", "articulate", "creative", "instrumental"], "languages_combined": []}, "experience_required": {"duration": ["5+ years"], "field": ["advertising", "agency", "developing", "design", "writing", "digital", "media"]}}, {"job_id": "100003009050884", "location_code": "hk", "company": "Sun Cupid Technology (HK) Ltd", "job_title": "Web Design/Creative Director", "description": "Data Analyst\n\nAs\u00a0a\u00a0member of our data analytics team in csl,\u00a0you will responsible for target database list generation, data extraction, campaign tracking, business performance reporting, customer data analysis and provide fact-based data driven insights on customer behavior to support and drive business initiatives.\n\nYour role\n\nPerform data extraction to fulfill marketing programs\u2019 requirements\nCompile regular and customized reports related to business performance, service usage and customer analysis\nApply statistical modeling to identify business opportunities and areas for improvement\nPerform campaign tracking, assist in execution of standard data mapping jobs and verify data sets\nReveal and uncover insights by exploring and mining structured and unstructured data\nProvide ongoing database support for segment marketing activities with well mechanism in maintaining an accurate and up-to-date database\nConduct user acceptance test of in-house-developed applications, as well as develop supervised and unsupervised machine learning models\nApply analytical methods and algorithms to build data products that generate business insights and improve operational efficiency\n\nTo succeed in this role\n\nUniversity graduate in Statistics, Computer Science, Information Technology, Data Science, Engineering or other relevant disciplines\n1\u00a0- 3 years' working experience in programming, data extraction, MIS\nProficiency in relational databases - SQL,\u00a0SAS, VBA\u00a0and FoxPro, with\u00a0knowledge and\u00a0experience on\u00a0Cognos, Excel, Python, Java, Java script\nPractical experience in working with BI visualization tools (e.g. Qlik View, Qlik Sense,\u00a0Tableau)\u00a0is an advantage\nTechnical knowledge on different server operating systems is preferred\nGood analytical and problem solving skills, able to work under tight timeline\nSelf-motivated and able to accomplish multiple tasks with minimal supervision\nGood\u00a0interpersonal and communication skills and\u00a0able to work with people at all levels\nGood command in both spoken and written English\n\nCandidate with more experience will be considered for the position of\u00a0Senior Data Analyst.\n\nHKT is an equal opportunity employer and welcomes applications from all qualified candidates. Information provided will be treated in strict confidence and will only be used for recruitment-related purposes.\nPersonal data provided by job applicants will be used strictly in accordance with the employer's privacy statement (www.hkt.com/privacy-statement), a copy of which will be provided immediately upon request.", "employment_types": ["Full Time", "Permanent"], "selling_points": [], "locations": ["Lai Chi Kok"], "categories": ["Media & Advertising", "Creative / Design", "Marketing / Public Relations", "Marketing - Market Research", "Digital Marketing"], "post_time": "2022-01-14T11:38:57Z", "salary": {"currency": null, "max": null, "min": null, "period": "monthly", "term": null}, "salary_visible": false, "title_keywords": ["creative director"], "responsibilities": ["reporting", "business initiatives", "identify business opportunities", "maintaining", "data", "visualization", "analysis", "develop", "communication", "reports", "recruitment", "database", "customer data", "databases", "personal data", "operating systems", "tracking"], "requirements": {"degrees": ["university graduate"], "majors": ["data science", "engineering", "statistics", "information technology", "computer science"], "languages": ["english"], "language_level": ["good command"], "hard_skills": ["vba", "excel", "java", "java script", "bi", "server", "sas", "data analytics", "analysis", "tableau", "sql", "foxpro", "databases", "programming", "python", "problem solving skills"], "soft_skills": ["communication skills", "self-motivated", "confidence", "accurate", "responsible", "multiple tasks", "interpersonal", "analytical and problem solving skills", "learning", "structured", "driven"], "languages_combined": [{"language": "english", "language_level": ["good command"]}]}, "experience_required": {"duration": ["1 - 3 years"], "field": ["sql", "programming"]}}, {"job_id": "100003009039924", "location_code": "hk", "company": "csl.", "job_title": "Data Analyst", "description": "Responsibilities\n\nUnderstand research users\u2019 business questions and translate into a valid research study with clear research objectives\nPerform both quantitative and qualitative customer analyses with innovative and actionable solutions\nProvide customer segmentation analysis and identify threats and opportunities for each customer group\nGenerate insights from vast volume internal customer data, match with market research to provide a holistic view on the whole customer journey\nWork closely with research users, vendors and other key stakeholders on project coordination, evaluation of performance and brainstorm action plans\n\n\u00a0Requirements\n\nUniversity graduates of marketing or related disciplines with minimum 1 year\u2019s relevant experience in research and data analysis.\nStrong project management skill and experience in research execution including quality assurance\nStrong in PC skills (excel, powerpoint)\nKnowledge in statistical tools (COGNOS, SPSS, R) or data visualization tool (Tableau) will be an advantage\nProficient in both Chinese and English writing\nGood team player, outgoing, self-motivated, flexible and independent", "employment_types": ["Full Time"], "selling_points": ["Perform data extraction", "Fulfill marketing programs\u2019 requirements", "Reveal and uncover insights"], "locations": ["Quarry Bay"], "categories": ["Professional Services", "Business Analysis / Data Analysis", "Marketing / Public Relations", "Marketing - Market Research"], "post_time": "2022-01-11T15:29:28Z", "salary": {"currency": null, "max": null, "min": null, "period": "monthly", "term": null}, "salary_visible": false, "title_keywords": ["data analyst"], "responsibilities": ["project coordination", "analysis", "market research", "customer data", "evaluation", "plans"], "requirements": {"degrees": [], "majors": [], "languages": ["english", "chinese"], "language_level": ["proficient"], "hard_skills": ["excel", "analysis", "powerpoint", "tableau", "project management", "data visualization", "r", "pc skills"], "soft_skills": ["outgoing", "flexible", "good team player", "self-motivated", "independent", "project management skill"], "languages_combined": [{"language": "english", "language_level": ["proficient"]}, {"language": "chinese", "language_level": ["proficient"]}]}, "experience_required": {"duration": ["minimum 1 year"], "field": ["research", "related", "data analysis", "project management", "marketing", "relevant experience", "quality assurance"]}}, {"job_id": "100003009038902", "location_code": "hk", "company": "SmarTone Telecommunications Limited", "job_title": "Research Executive", "description": "Responsibilities:\n\n\nPlan and execute marketing mix of mobile services business\nDesign pricing and marketing offers, go-to-market plan, channel-specific promotions, customer acquisition & retention tactics\nManage online subscription platforms & performance\nCoordinate with internal & external stakeholders to deliver marketing plans\nReview program effectiveness and assist to drive for KPI achievement as assigned\n\nRequirements:\n\nDegree holder in Marketing / Business or related disciplines\nOver 6 years of relevant working experience. Exposure in telecom and/or banking industries are preferred\nAgile with ability to manage multiple tasks\nGood project management skills\nStrong business sense with good presentation skills\u00a0\n\nApart from competitive remuneration package and exciting opportunity for career development within the Group, we provide attractive employee benefits such as free company shuttle, free company SIM card and preferential SIM plan offers, comprehensive medical & insurance schemes, as well as full range of other employee well-being provisions.\u00a0\n\nInterested parties, please send in your profile with your salary expectation to connie.chong@ hthk.com\u00a0\n\nWe are an equal opportunity employer and welcome applications from all qualified candidates. Personal data collected will be treated in the strictest confidence and handled confidentially by authorised personnel for recruitment-related purposes only within the CK Hutchison Group of companies. The personal data of unsuccessful applicants will be destroyed after the recruitment exercise pursuant to the requirements of the Personal Data (Privacy) Ordinance in Hong Kong.", "employment_types": ["Full Time"], "selling_points": ["Understand research users\u2019 business questions", "Perform both quantitative and qualitative analyses", "Work closely with key stakeholders"], "locations": ["Ngau Tau Kok"], "categories": ["Marketing / Public Relations", "Marketing - General / Support", "Marketing - Market Research"], "post_time": "2022-01-11T08:06:40Z", "salary": {"currency": null, "max": null, "min": null, "period": "monthly", "term": null}, "salary_visible": false, "title_keywords": ["executive"], "responsibilities": ["marketing plans", "review", "coordinate with", "design", "plan"], "requirements": {"degrees": ["degree holder"], "majors": ["business", "related disciplines", "marketing"], "languages": [], "language_level": [], "hard_skills": ["project management", "agile"], "soft_skills": ["agile", "business sense", "multiple tasks", "project management skills", "presentation skills", "comprehensive"], "languages_combined": []}, "experience_required": {"duration": ["6 years"], "field": ["relevant working experience"]}}, {"job_id": "100003009051283", "location_code": "hk", "company": "Hutchison Telecommunications (Hong Kong) Limited", "job_title": "Assistant Growth Marketing Manager", "description": "CHINA MOBILE HONG KONG COMPANY LIMITED (\"CMHK\") is the wholly-owned subsidiary of China Mobile Limited (HKEx: 941) (NYSE: CHL), which ranks 65th on the Fortune Global 500.\n\nOur company strives to offer superior service experience and to become the preferable digital partner for customers. We are preserving an environment with trust, responsibility and caring. At CMHK, we commit to maximizing people\u2019s potential and paving the way toward success for every striver. We are now inviting high caliber professional to join us.\n\n\n\nDepartment: Customer Service Planning Department\n\n\n\nIn this position, you will:\n\n\nParticipate in company\u2019s marketing projects and share ideas from customer\u2019s point of view, ensure the service process and after-sales service could meet customer expectation as well as maintain the accuracy of knowledge base\nConduct service benchmarking from different aspects to identify service improvement initiatives\nAnalyze customer feedback and narrow the gap between intended and actual customer experience; assist Customer Service Manager to deploy strategic plans that drive for cross-departments effort to improve total customer satisfaction\nInnovate new ideas on service workflow and policy as well as expand the online service channel\nHandle general departmental reporting and procedure manual\n\nTo be successful in this position, you should meet the following requirements:\n\nDiploma holder or above\n2 years of relevant customer service experience preferably in telecom industry\nGood interpersonal communication skills, self-motivated and able to work under pressure\nExperience in account servicing/ quality assurance/ project management will be an advantage\nHands-on experience in Frontpage and other graphical software is preferable\nGood command of spoken & written English & Chinese\nCandidate with more experience will considered as Senior Customer Service Planning Specialist\n\nWhen you work:\n\n5 days work\n8 hours/day\n\n\n\u00a0What you enjoy:\n\nDouble pay\nDiscretionary Performance bonus\nLife insurance\nMedical insurance\nMeal allowance\nEducation subsidies\nBirthday gift\nMarriage leave\nBirthday leave\nStaff discount\n\n\n\nCMHK is committed to be an equal opportunity employer. We offer exceptional benefits package and the opportunity to work in a challenging environment. Personal data provided by applicants will be treated strictly in accordance with our personal data policy and for recruitment purposes only.", "employment_types": ["Full Time", "Permanent"], "selling_points": [], "locations": ["Tsing Yi"], "categories": ["Marketing / Public Relations", "Marketing - Direct Marketing", "Marketing - General / Support", "Marketing - Market Research"], "post_time": "2022-01-15T07:17:38Z", "salary": {"currency": null, "max": null, "min": null, "period": "monthly", "term": null}, "salary_visible": false, "title_keywords": ["marketing manager", "assistant"], "responsibilities": ["reporting", "ideas", "strategic plans", "software", "work under pressure", "customer service experience", "quality", "marketing projects", "communication", "project management", "after-sales service", "customer service", "maintain", "deploy", "insurance", "planning"], "requirements": {"degrees": ["diploma holder"], "majors": [], "languages": ["english", "chinese"], "language_level": ["good command"], "hard_skills": ["mobile", "project management", "gap"], "soft_skills": ["communication skills", "self-motivated", "work under pressure", "project management", "hands-on", "customer service", "committed", "interpersonal", "superior"], "languages_combined": [{"language": "english", "language_level": ["good command"]}, {"language": "chinese", "language_level": ["good command"]}]}, "experience_required": {"duration": ["2 years"], "field": ["account servicing", "project management", "customer service", "planning", "digital", "quality assurance"]}}, {"job_id": "100003009049741", "location_code": "hk", "company": "China Mobile Hong Kong \u4e2d\u570b\u79fb\u52d5\u9999\u6e2f", "job_title": "(Senior) Customer Service Planning Specialist", "description": "Looking for candidate with distinguished academic & scholarly achievements to join a leading think tank as policy researcher.\n\nClient Details\n\nA leading think tank with a mission to foster Hong Kong's long-term competitiveness and quality of life through public policy advocacy\n\nDescription\n\nPerform research on assigned policy areas such as economic development, land supply, education, youth policy, healthcare, and innovation.\nAct as project manager and provide leadership to interns, graduates, and junior staff\n\nProfile\n\nThe candidate should have an excellent academic record and intellectually curious. Three to four (3-4) years of relevant experience in policy analysis or policy research is required. Excellent quantitative and qualitative analysis skills, as well as strong written communication in English and Chinese, are essential in this role.\n\nJob Offer\n\nExcellent platform to perform duties as an influencer of public policy that impact Hong Kong's long-term future\n\nTo apply online please click the 'Apply' button below. For a confidential discussion about this role please contact Anthony Lau on +852 3412 4851.", "employment_types": ["Full Time", "Permanent"], "selling_points": ["Customer Service Process Planning", "Conduct Market Research on services", "Analyze customer feedback"], "locations": ["Kwai Hing"], "categories": ["Sales, CS & Business Devpt", "Customer Service - Supervisor / Officer", "Marketing / Public Relations", "Marketing - Market Research"], "post_time": "2022-01-14T09:11:23Z", "salary": {"currency": null, "max": null, "min": null, "period": null, "term": null}, "salary_visible": false, "title_keywords": ["specialist", "customer service"], "responsibilities": ["communication", "analysis", "quality", "contact"], "requirements": {"degrees": [], "majors": [], "languages": ["english", "chinese"], "language_level": ["excellent"], "hard_skills": ["analysis"], "soft_skills": ["communication", "perform duties", "leadership"], "languages_combined": [{"language": "english", "language_level": ["excellent"]}, {"language": "chinese", "language_level": ["excellent"]}]}, "experience_required": {"duration": [], "field": ["research", "relevant experience"]}}, {"job_id": "100003009046441", "location_code": "hk", "company": "Michael Page", "job_title": "Policy Researcher - Think Tank (Top 1% Globally)", "description": "Degree holder in Real Estate, Surveying, Business Administration or related disciplines\n8 years\u2019 relevant experience in the sales and marketing of overseas properties\nExperience/knowledge in the UK property market\nTo assist in developing sales and marketing strategies and managing sales administration for overseas properties of the Group\nTo organize, implement and monitor sales and marketing activities\nTo conduct market research and generate pricing strategy\nExcellent communication and interpersonal skills\nFluent in written and spoken English and Chinese\n\nWe offer salary and benefits commensurate with qualifications and experience. Please send a full resume with contact number and expected salary to General Manager - Human Resources & Administration, Hutchison Property Group Limited, 3/F., One Harbourfront, 18 Tak Fung Street, Hunghom, Kowloon (Please quote reference on envelope) or by clicking \"Apply Now\".\n\nWe are an equal opportunity employer and welcome applications from all qualified candidates. The information provided will be treated in strict confidence and be used only for consideration of your application for relevant/similar post(s).\n\nApplicants not hearing from us within six weeks from the date of advertisement may consider their applications unsuccessful. All personal data of unsuccessful applicants will be destroyed after the recruitment exercise when no longer required.", "employment_types": ["Full Time", "Permanent"], "selling_points": ["Top 1% Think Tank Globally", "Policy analysis and research", "Previous experience not required"], "locations": ["Not Specified"], "categories": ["Marketing / Public Relations", "Marketing - Market Research", "Public Relations - Copy-writing"], "post_time": "2022-01-13T11:11:53Z", "salary": {"currency": null, "max": null, "min": null, "period": "monthly", "term": null}, "salary_visible": false, "title_keywords": ["researcher"], "responsibilities": ["sales administration", "marketing strategies", "conduct market research", "monitor", "developing", "communication", "administration"], "requirements": {"degrees": ["degree holder"], "majors": ["related disciplines", "business administration", "surveying"], "languages": ["english", "chinese"], "language_level": ["fluent"], "hard_skills": [], "soft_skills": ["communication and interpersonal skills"], "languages_combined": [{"language": "english", "language_level": ["fluent"]}, {"language": "chinese", "language_level": ["fluent"]}]}, "experience_required": {"duration": ["8 years"], "field": ["marketing", "relevant experience"]}}, {"job_id": "100003009050241", "location_code": "hk", "company": "Hong Kong Trade Development Council", "job_title": "Project Executive", "description": "Description\n\nJ.P. Morgan Asset Management and Private Bank is seeking a talented\u00a0AWM\u00a0APAC Head of Social Media & Advertising\u00a0to join the Integrated Media and Performance Analytics team. The role's focus will be to build out the regional social media and advertising capabilities and strategy for 2 different lines of business - Asset Management and Private Bank.\n\nThe role will be tasked to oversee the design and implementation of our regional social media and advertising strategy, while providing the necessary local oversight for our agency partners and stakeholders. This person will oversee development of our end-to-end social media and advertising experience to build our brand and maximize client engagement throughout the purchase funnel. They will work closely with their global peers to develop and institute processes and drive best-practices adoption.\n\nThis individual will be responsible for working with local marketing managers and agency teams to design cohesive multi-touch, multi-channel programs aligned and delivering against the objectives of each marketing group. The successful individual will possess a strong understanding of the APAC social media landscape and working knowledgeof the mechanics of social media within larger multichannel campaigns. This person will also work with digital and design specialists, senior management, as well as analytics teams in the optimization of these campaigns.\n\nThe individual should be performance driven and analytically inclined. Experience building direct and indirect (agency) teams is important, as are project management and interpersonal skills. With a successful model in place in the other parts of the globe, this individual will be key in establishing the Integrated Media Team's presence in the APAC region.\n\nResponsibilities Include\n\nPartner with stakeholders, subject matter experts (SMEs) and the relevant digital teams to deliver engaging digital experiences for various audiences and client segments\nDesign and execute social media campaigns working with cross-functional teams to deliver exceptional client engagement across a suite of owned-media properties\nCollaborate with marketing partners to ensure a seamless and coordinated social media and advertising support\nDefine campaign KPIs and leverage campaign analytics to determine success criteria, efficacy and ongoing optimization opportunities\nDeliver measurable improvements against agreed upon KPIs and define best practices by ongoing measurement and documentation\nManage the sourcing and creation of content required to deliver engaging social media experiences\nPartner with other specialist digital teams for development, design/UX, content, analytics to support social media efforts\nDirect a team of social media specialists to create, build, and publish across our digital channels\nSupport strategy definition, supervise the planning and ongoing activities including maintaining the quality and consistency across all digital externally facing properties and communications\nQualifications\n\nAt least 7 years of social media and/or advertising experience, including the development of strategy, media buying, and tactical optimization of channels\nExperience in the development and management of internal and agency teams\nMedia agency side experience is a big plus, preferably on brands with a performance marketing mindset\nKnowledge of local social media platforms (WeChat, Snowball, WhatsApp, Instagram, etc.)\nStrong time management and organization skills; able to maintain a high quality of work in a deadline driven environment\nProactive with a high level of attention to detail; quick learner who can adapt to changing priorities\nA strong understanding of social media best practices and related digital user experience\nTeam player, with a very strong work ethic and high energy level\nMust demonstrate initiative and ownership of assigned responsibilities\nAbility to translate technical or SME specific information to communicate business impact / benefit effectively to non-technical stakeholders\nMust be able to establish strong relationship with the business and project stakeholders to ensure that business goals are met\nExcellent communication skills and the ability to interact confidently with all levels of management\nJPMorgan Chase & Co., one of the oldest financial institutions, offers innovative financial solutions to millions of consumers, small businesses and many of the world's most prominent corporate, institutional and government clients under the J.P. Morgan and Chase brands. Our history spans over 200 years and today we are a leader in investment banking, consumer and small business banking, commercial banking, financial transaction processing and asset management.\n\nWe recognize that our people are our strength and the diverse talents they bring to our global workforce are directly linked to our success. We are an equal opportunity employer and place a high value on diversity and inclusion at our company. We do not discriminate on the basis of any protected attribute, including race, religion, color, national origin, gender, sexual orientation, gender identity, gender expression, age, marital or veteran status, pregnancy or disability, or any other basis protected under applicable law. In accordance with applicable law, we make reasonable accommodations for applicants' and employees' religious practices and beliefs, as well as any mental health or physical disability needs.\n\nThe health and safety of our colleagues, candidates, clients and communities has been a top priority in light of the COVID-19 pandemic. JPMorgan Chase was awarded the \"WELL Health-Safety Rating\" for all of our 6,200 locations globally based on our operational policies, maintenance protocols, stakeholder engagement and emergency plans to address a post-COVID-19 environment.\n\nAs a part of our commitment to health and safety, we have implemented various COVID-related health and safety requirements for our workforce. These requirements may include sharing information in the firm's vaccine record tool, vaccination or regular testing, mask wearing, social distancing and daily health checks. Requirements may change in the future with the evolving public health landscape. JPMorgan Chase will consider accommodation requests.\n\nEqual Opportunity Employer/Disability/Veterans\n\nInterested parties please click \u201cApply Now\u201d to apply job.\n\nAll applications applied through our system will be delivered directly to the advertiser and privacy of personal data of the applicant will be ensured with security.", "employment_types": ["Full Time", "Permanent"], "selling_points": ["Promote HK Service to the world", "Customer Service and Event Management", "Coordinate trade events"], "locations": ["Wan Chai"], "categories": ["Marketing / Public Relations", "Marketing - General / Support", "Marketing - Market Research", "Public Relations - Event Management"], "post_time": "2022-01-14T10:00:14Z", "salary": {"currency": null, "max": null, "min": null, "period": "monthly", "term": null}, "salary_visible": false, "title_keywords": ["project executive"], "responsibilities": ["collaborate with", "business goals", "social media platforms", "quality", "design", "communication", "purchase", "maintain", "sme", "plans", "senior management", "advertising", "social media campaigns", "maintaining", "teams", "implementation", "measurement", "develop", "user experience", "testing", "banking", "kpis", "social media", "management", "transaction processing", "documentation", "cross-functional teams", "maintenance", "policies", "project management", "asset management", "planning"], "requirements": {"degrees": [], "majors": [], "languages": [], "language_level": [], "hard_skills": ["small", "plus", "maintenance", "wechat", "project management", "whatsapp", "make", "snowball", "documentation", "focus", "processing"], "soft_skills": ["initiative", "communication skills", "proactive", "responsible", "cohesive", "quick learner", "innovative", "project management", "diverse", "team player", "interpersonal skills", "attention to detail", "work ethic", "organization skills", "focus", "time management", "driven"], "languages_combined": []}, "experience_required": {"duration": ["at least 7 years"], "field": ["social media", "management", "advertising", "brand", "agency", "development", "related", "project management", "marketing", "media buying", "digital", "media"]}}, {"job_id": "100003009047145", "location_code": "hk", "company": "JPMorgan Chase Bank, N.A.", "job_title": "AWM APAC Regional Social Media & Advertising Team Lead", "description": "\u00b7 Sales and marketing activities\n\n\u00b7 Create new business opportunities, explore new customers and manage customer database.\n\n\u00b7 Actively seek out new sales opportunities through cold calling\n\n\u00b7 Be articulated to explain the product and its benefits over telephone", "employment_types": ["Full Time"], "selling_points": [], "locations": ["Not Specified"], "categories": ["Marketing / Public Relations", "Marketing - Market Research", "Marketing - Marketing Communication", "Others"], "post_time": "2022-01-14T02:27:15Z", "salary": {"currency": null, "max": null, "min": null, "period": "monthly", "term": null}, "salary_visible": false, "title_keywords": ["lead"], "responsibilities": ["business opportunities", "database"], "requirements": {"degrees": [], "majors": [], "languages": [], "language_level": [], "hard_skills": [], "soft_skills": [], "languages_combined": []}, "experience_required": {"duration": [], "field": []}}, {"job_id": "100003009045874", "location_code": "hk", "company": "I.T Apparels Limited", "job_title": "CRM Assistant (REF : JDB-IT-CRMA)", "description": "Accountabilities \u2013 Key Result Areas\n\n\nSupport in developing and implementing digital marketing and thematic campaigns to support e-commerce business goals and development\nUnderstand e-commerce competitiveness and customer behavior in respective markets via data analytics to maximize digital marketing efficiency\nResponsible for customer database management, delivering report analysis on a regular basis on digital marketing performance results, customer segmentation and online purchase behavior to support e-commerce digital marketing strategy and CRM enhancement\nSupport in execution and end-to end logistics of various digital CRM plans and programs by coordinating with internal departments on digital marketing communication composition such as eDM, SMS, social media communication, etc.\nSupport on other ad-hoc duties as assigned\n\nExperience / Qualification Requirements\n\n\nDegree holder in E-commerce/ Marketing/ Marketing Analytics/ Statistics and other related discipline\nMinimum one year of experience in Marketing/ CRM Analytics, with e-commerce or online CRM management exposure is highly preferred\nWith outstanding spoken and written communication skills in English and Chinese (Cantonese and Mandarin)\nWith experience working in MNC or international business environment will be advantageous\nWith passion and interest in e-commerce and fashion business\nAnalytical minded, logical, and adaptable to fast paced environment and meeting tight deadlines\n\nCompetitive remuneration and benefit package will be offered to the right candidate. Please submit your application by clicking \"Apply Now\" below.\n\nAll data collected is for recruitment purpose only.\n\nSure you want to know more about our company and brands, simply follow our\n\nWEBSITE at http://www.ithk.com\u00a0 \u00a0 \u00a0 \u00a0 \u00a0 \u00a0\n\u00a0 \u00a0 \u00a0 \u00a0 \u00a0 \u00a0 \u00a0 \u00a0 \u00a0 \u00a0 \u00a0 \u00a0 \u00a0 \u00a0 \u00a0 \u00a0 \u00a0 \u00a0 \u00a0 \u00a0 \u00a0 \u00a0 \u00a0 \u00a0 \u00a0 \u00a0 \u00a0 \u00a0\u00a0\nFACEBOOK at\u00a0http://www.facebook.com/I.Ttheofficialpage\u00a0 \u00a0 \u00a0 \u00a0\n\u00a0 \u00a0 \u00a0 \u00a0 \u00a0 \u00a0 \u00a0 \u00a0 \u00a0 \u00a0\u00a0\nINSTAGRAM at http://instagram.com/ithk\u00a0 \u00a0 \u00a0 \u00a0 \u00a0\n\u00a0 \u00a0 \u00a0 \u00a0 \u00a0 \u00a0 \u00a0 \u00a0 \u00a0 \u00a0 \u00a0 \u00a0 \u00a0 \u00a0 \u00a0 \u00a0 \u00a0 \u00a0 \u00a0 \u00a0 \u00a0 \u00a0 \u00a0\nWEIBO at\u00a0http://e.weibo.com/ithongkong", "employment_types": ["Full Time", "Permanent"], "selling_points": ["Minimum 1 year of experience in CRM Analytics", "Responsible for customer database management", "Fresh Graduate will also be considered"], "locations": ["Southern Area"], "categories": ["Marketing / Public Relations", "Marketing - Market Research", "Digital Marketing", "E-commerce", "Marketing - Brand / Product Management"], "post_time": "2022-01-13T09:00:21Z", "salary": {"currency": null, "max": null, "min": null, "period": "monthly", "term": null}, "salary_visible": false, "title_keywords": ["crm assistant"], "responsibilities": ["social media", "business goals", "management", "data", "edm", "analysis", "developing", "website", "communication", "purchase", "digital marketing", "logistics", "database", "ad-hoc duties", "recruitment", "plans", "facebook", "report"], "requirements": {"degrees": ["degree holder"], "majors": ["marketing", "statistics", "e-commerce"], "languages": ["cantonese", "english", "chinese", "mandarin"], "language_level": [], "hard_skills": ["data analytics", "analysis", "facebook", "e-commerce"], "soft_skills": ["communication skills", "meeting tight deadlines", "responsible", "adaptable", "communication", "ad-hoc duties", "business environment"], "languages_combined": [{"language": "cantonese", "language_level": []}, {"language": "english", "language_level": []}, {"language": "chinese", "language_level": []}, {"language": "mandarin", "language_level": []}]}, "experience_required": {"duration": ["minimum one year"], "field": ["business", "management", "marketing", "e-commerce"]}}, {"job_id": "100003009039533", "location_code": "hk", "company": "Price.com.hk Limited", "job_title": "Marketing Manager", "description": "Join us to create new values to the online offline commerce communities\n\nPrice.com.hk, being one of the most popular online platforms* in Hong Kong, strives to bring extra values to merchants and consumers by not only connecting them seamlessly with our state-of-the-art technology but co-creating a community that encourages a more user centric shopping experience combined with the application of big data analytics.\n\n\nWe start with a goal to minimize market information costs incurred upon consumers allowing them to find their favorite products easier and faster and at the same time enable merchants to successfully run their brick and click strategies to reach their targeted consumers at the lowest cost possible. Today, we are serving 2M+ monthly unique visitors. We cannot accomplish that without working together with individuals who are passionate about what they do.\n\n*According to Alexa, Price.com.hk is one of the top 25 most frequently visited sites in Hong Kong. https://www.alexa.com/siteinfo/price.com.hk\n\nYour role with us involves:\n\nInitiate and implement wide range of e-commerce promotion and campaigns\nManage sales & marketing activities\nDrive trade marketing strategy,\u00a0and develop programs based on retail and merchant insights\nResponsible for B2C and B2B communication, including both online and offline\nResearch, study and consolidate market trend in the digital industry\nCoordinate with media partners to ensure successful implementation of campaigns\nIdentify and approach business partners to develop joint promotions\n\nAs an employer, our role is to empower you by bringing your true talents and best self to this dynamic digital world and the people we serve. We welcome individuals from all backgrounds, ideally with skills and traits as below:\n\nProactive, critical, analytical and detail-oriented\nDegree holder, preferable Marketing, Communication, Social Science or equivalent\nMinimum 6 years of relevant working experience\nWell-organized, self-motivated and able to work in a fast-paced environment\nExcellent communication and presentation skills\nGood Knowledge of Google Adwords and Google Analytics\nFluent written and spoken Cantonese and English\nKnowledge in 3C products would be an advantage\nCandidates with less experience will be considered as Associate Marketing Manager\n\nBe part of us, you will enjoy:\n\nDiscretionary Bonus\n5-day Work Week\nFlexible Working Hour\nBirthday, Marriage, Maternity and Paternity Leave\nBirthday Gift\nMedical Insurance\nMonthly Birthday Party\nTeam Event and Team Building Activities\nHappy and Dynamic Environment\nCasual Dress Code\n\nWorking Location: Kwun Tong (5 minutes from Kwun Tong MTR station)\n\nInterested parties, please click \"Apply now\" to submit your resume with the availability and expected salary to us.\n\nPersonal data collected will be kept strictly confidential and only be used for recruitment related purpose.\n", "employment_types": ["Full Time", "Permanent"], "selling_points": ["Fast Growing Industry", "An Expanding E-Commerce Company", "Offer Training & Development"], "locations": ["Kwun Tong"], "categories": ["Marketing / Public Relations", "Marketing - Brand / Product Management", "Marketing - Market Research", "Marketing - Marketing Communication"], "post_time": "2022-01-11T10:01:20Z", "salary": {"currency": null, "max": null, "min": null, "period": "monthly", "term": null}, "salary_visible": false, "title_keywords": ["marketing manager"], "responsibilities": ["cost", "market information", "trade marketing", "big data", "coordinate with", "implementation", "develop", "communication", "sales & marketing activities", "insurance", "costs"], "requirements": {"degrees": ["degree holder"], "majors": ["science", "marketing"], "languages": ["cantonese", "english"], "language_level": ["fluent"], "hard_skills": ["google analytics", "e-commerce", "adwords", "data analytics", "goal", "dynamic", "code"], "soft_skills": ["flexible", "self-motivated", "dynamic environment", "responsible", "fast-paced environment", "well-organized", "unique", "detail-oriented", "communication", "presentation skills", "dynamic", "proactive", "passionate about"], "languages_combined": [{"language": "cantonese", "language_level": ["fluent"]}, {"language": "english", "language_level": ["fluent"]}]}, "experience_required": {"duration": ["minimum 6 years"], "field": ["marketing", "relevant working experience"]}}, {"job_id": "100003009048126", "location_code": "hk", "company": "Page Personnel", "job_title": "Business Development Coordinator - US based law firm", "description": "Excellent opportunity for marketing professionals to develop their career in the legal sector.\n\nClient Details\n\nOur client is a one of the most well-known law firms headquartered in the US, with over 20 years' experience. With over 60 employees and fee earners in Hong Kong, they provide clients with professional legal advises and services.\n\nDescription\n\nExecute business development and marketing plans\nPrepare pitches and tenders in English and Chinese for lawyers\nLiaise with BD & marketing team to deliver high quality events, both internal and external\nConduct market research, document preparation and media monitoring\nAssist in preparing information for directory submissions, league tables and awards\nPrepare up-to-date materials for internal platforms\nRequire translation work for BD initiatives\n\nProfile\n\nDegree in Law, Business, Law or other related discipline\nAt least 2 years of pitch writing and event marketing experiences,preferably in legal or professional services field\nExcellent command of spoken and written English, Mandarin and Cantonese\nGood communication and relationship building\nSelf-motivated and able to learn things in no time and fast pace environment\n\nJob Offer\n\nAttractive remuneration package\nRotation opportunities\nStable working hour\nFull medical coverage\nPaid annual leaves\n\nTo apply online please click the 'Apply' button below. For a confidential discussion about this role please contact Jayne Hon on +852 3602 2440", "employment_types": ["Full Time", "Permanent"], "selling_points": ["Reputable law firm with all rounded training", "Excellent career progression", "Attract salary package"], "locations": ["Not Specified"], "categories": ["Marketing / Public Relations", "Marketing - Market Research", "Marketing - Marketing Communication", "Public Relations - Copy-writing"], "post_time": "2022-01-14T05:06:02Z", "salary": {"currency": "HKD", "max": 29999, "min": 20000, "period": "monthly", "term": null}, "salary_visible": true, "title_keywords": ["coordinator"], "responsibilities": ["marketing plans", "conduct market research", "monitoring", "quality", "develop", "communication", "contact", "liaise with"], "requirements": {"degrees": ["degree"], "majors": ["business", "law"], "languages": ["cantonese", "english", "chinese", "mandarin"], "language_level": ["excellent"], "hard_skills": ["translation", "no"], "soft_skills": ["communication", "self-motivated", "stable"], "languages_combined": [{"language": "cantonese", "language_level": ["excellent"]}, {"language": "english", "language_level": ["excellent"]}, {"language": "chinese", "language_level": []}, {"language": "mandarin", "language_level": ["excellent"]}]}, "experience_required": {"duration": ["at least 2 years", "20 years"], "field": ["marketing", "writing", "legal"]}}, {"job_id": "100003009043126", "location_code": "hk", "company": "Magic Compass Pty Limited", "job_title": "Performance Marketing Executive (Oversea Market\uff09", "description": "Responsibilities:\n\nResponsible for Google, Facebook ad Manager and Applovin account optimization\nUse Firebase, Google Analytics, appsflyer to analysis platform data\nMaximize brand awareness and leads generation including Google, Facebook.,etc\nResponsible for routine paid marketing & Performance marketing,\u00a0keep tracking advertising performance result, and provide data analyst reports for promotion\u00a0\nDevelop all digital advertising ads to achieve desired goals\nMonitor and evaluate campaign performance, assess digital campaign trends, provide solutions and identify growth opportunities\u00a0\n\n\u00a0Requirements:\n\n\nBachelor Degree in Marketing, Statistics or related discipline\nAt least 2 years hands on experience with paid online marketing tools such as Facebook, Google, etc.\nWell-versed with oversea online marketing e.g. Indian,\u00a0Africa,\u00a0Southeast Asia\nDigital marketing experience gained\u00a0 in advertising/marketing agency/E-Commerce is a huge plus\nFluent in\u00a0 English and Mandarin\u00a0\n\nAll personal information provided by applicant will be treated in strict confidence and used solely for recruitment purposes. The personal information will be used strictly in accordance with Magic Compass Pty Limited's personal data policies, a copy of which will be provided upon request. It is possible that information about the applicant or the applicant\u2019s application will be shared with Magic Compass Pty Limited and its related companies. Magic Compass Pty Limited will retain all applications no longer than 24 months after which the documents will be destroyed.", "employment_types": ["Full Time", "Permanent"], "selling_points": ["Digital and Performance Marketing", "Google, Facebook and Applovin", "Stable working environment"], "locations": ["Tsim Sha Tsui"], "categories": ["Marketing / Public Relations", "Marketing - Market Research", "Digital Marketing"], "post_time": "2022-01-12T09:51:42Z", "salary": {"currency": null, "max": null, "min": null, "period": "monthly", "term": null}, "salary_visible": false, "title_keywords": ["marketing executive"], "responsibilities": ["advertising", "data", "analysis", "monitor", "provide solutions", "develop", "evaluate", "reports", "facebook", "tracking"], "requirements": {"degrees": ["degree", "bachelor"], "majors": ["marketing", "statistics"], "languages": ["english", "mandarin"], "language_level": ["fluent"], "hard_skills": ["no", "plus", "e-commerce", "facebook", "compass"], "soft_skills": ["hands on", "confidence"], "languages_combined": [{"language": "english", "language_level": ["fluent"]}, {"language": "mandarin", "language_level": ["fluent"]}]}, "experience_required": {"duration": ["at least 2 years"], "field": ["advertising", "e-commerce", "agency", "marketing", "digital marketing"]}}, {"job_id": "100003009025548", "location_code": "hk", "company": "Dah Chong Hong (Motor Service Centre) Limited", "job_title": "Assistant Business Development Officer \u2013 Automotive Parts", "description": "Responsibilities:\n\nResponsible for sales report, data analysis, market research, proposal preparation and order follow up\nAssist manager to explore potential business opportunities and handle business development projects\nLiaise with internal and external parties to deliver smooth and effective workflow\nHandle ad hoc projects as assigned\u00a0\n\n\u00a0Requirements:\n\nUniversity graduate in Business Management, Marketing or related discipline\n2 years relevant experience, preferably in automotive parts or engineering field\nGood command of written and spoken English and Chinese\nGood analytical, communications and presentation skills\nWell versed in Internet & Office applications\nCandidate with relevant experience in Motor industry will be considered as Officer\n\nBeing part of the largest motor group in Hong Kong with a portfolio of major motor brands, we offer attractive salary, discretionary bonus, medical benefits and generous fringe benefits together with good career prospect to the successful candidate. For interested parties, please send your resume stating expected salary by clicking \"Apply Now\".\n\nWe are an equal opportunities employer. Personal data collected will be treated in strict confidence and used for recruitment purposes only. All applications may be considered for other suitable positions with DCH Group / CITIC Pacific Group and the personal data collected will be deleted from our files after 6 months from the date of application.\n\nPlease visit our website at\u00a0http://www.dchmsc.com", "employment_types": ["Full Time", "Permanent"], "selling_points": [], "locations": ["Kowloon Bay"], "categories": ["Sales, CS & Business Devpt", "Business Development", "Marketing / Public Relations", "Marketing - Market Research", "Sales Administration"], "post_time": "2022-01-14T03:17:25Z", "salary": {"currency": null, "max": null, "min": null, "period": "monthly", "term": null}, "salary_visible": false, "title_keywords": ["business development officer", "assistant"], "responsibilities": ["sales report", "business opportunities", "internal and external parties", "market research", "data analysis", "ad hoc projects", "liaise with"], "requirements": {"degrees": ["university graduate"], "majors": ["business", "marketing"], "languages": ["english", "chinese"], "language_level": ["good command"], "hard_skills": ["business management", "office applications"], "soft_skills": ["presentation skills"], "languages_combined": [{"language": "english", "language_level": ["good command"]}, {"language": "chinese", "language_level": ["good command"]}]}, "experience_required": {"duration": ["2 years"], "field": ["relevant experience", "engineering"]}}, {"job_id": "100003009041982", "location_code": "hk", "company": "Guru Online", "job_title": "Senior Project Executive (Global Team)", "description": "What You Will Be Doing:\n\nHelp develop marketing strategies and creative ideas;\nManage social media projects (channel include but are not limited to Facebook, Instagram, YouTube and TikTok)\nWork closely with vendors / internal teams to ideate, plan and execute digital marketing campaign projects;\nCommunicate closely with clients, identify and solve problems with professional solutions;\nConduct market research, develop content plan and create social media content.\n\n\u00a0What You Need for this Position:\n\nDegree or above in Business, Advertising, Communication,\u00a0Marketing, Journalism, Media, project management or related disciplines;\nFluent in both written and spoken English, Mandarin and Cantonese;\nExcellent communication, interpersonal and negotiation skills is a must;\nPassionate and have good knowledge in social media and new media;\nGreat marketing sense, multi-tasking and time management;\nWilling to take challenges and attention to details;\nProficient\u00a0in MS office application\nExperience in project management and strategic marketing, preferably in managing social media projects and creative campaigns is a plus;\nBeing capable of creating visual content is a plus;\nInternational exposure/ experience in China is definitely an advantage\n\n\u00a0Benefits We Offer:\n\n\u00a05 days\u2019\u00a0work\nQuarterly Performance Bonus\nMedical Coverage including Dental\nFlexible Working Hours\nOvertime\u00a0Meal\u00a0and Transportation allowance\nBirthday, Wedding, Graduation and other special leaves\nFun, young and joyful environment\u00a0\n\n\u00a0Be a GURU, be our next great hire.\u00a0APPLY NOW!\n\n*All information will be treated as confidential and used solely for recruitment purposes.", "employment_types": ["Full Time", "Permanent"], "selling_points": ["Plan and execute the marketing campaigns", "international exposure/ experience", "Fun, Young working environment"], "locations": ["Kwun Tong"], "categories": ["Marketing / Public Relations", "Marketing - Market Research", "Public Relations - General / Support", "Digital Marketing"], "post_time": "2022-01-12T04:59:49Z", "salary": {"currency": null, "max": null, "min": null, "period": "monthly", "term": null}, "salary_visible": false, "title_keywords": ["senior project executive"], "responsibilities": ["social media", "creative ideas", "management", "marketing strategies", "advertising", "conduct market research", "teams", "develop", "communication", "project management", "digital marketing", "social media content", "plan", "visual", "facebook"], "requirements": {"degrees": ["degree or above"], "majors": ["journalism", "project management", "related disciplines", "business", "marketing"], "languages": ["cantonese", "english", "mandarin"], "language_level": ["fluent"], "hard_skills": ["facebook", "project management", "plus", "ms office"], "soft_skills": ["passionate", "marketing sense", "capable", "communication", "solve problems", "project management", "negotiation skills", "multi-tasking", "time management", "attention to details", "creative", "interpersonal"], "languages_combined": [{"language": "cantonese", "language_level": ["fluent"]}, {"language": "english", "language_level": ["fluent"]}, {"language": "mandarin", "language_level": ["fluent"]}]}, "experience_required": {"duration": [], "field": ["project management", "marketing", "social media"]}}, {"job_id": "100003009048096", "location_code": "hk", "company": "Chinachem Group", "job_title": "Assistant Officer \u2013 Property Sales", "description": "Responsibilities:\nAssist in formulation and implementation of sales logistics plan for the launch of residential property projects\nCompile reports and conduct market research & analysis as well as data processing on Hong Kong residential market\nHandle daily sales administration matters and logistics arrangement in sales office\nPrepare sales documents as required under the Residential Properties (First-hand Sales) Ordinance and pre-sales application\nAssist in handling general enquiries from potential customers\nRequirements:\nDegree holder in Surveying / Marketing or related disciplines\nAt least 1 years\u2019 experience preferably in sales of residential properties in property developers with the knowledge in Residential Properties (First-hand Sales) Ordinance\nAttentive to details, customer-oriented, organized with good teamwork\nEnergetic, self-motivated with good interpersonal and analytical skills\nAble to work independently\nProficient in written and spoken English and Chinese", "employment_types": ["Full Time", "Permanent"], "selling_points": ["Residential property projects", "Compile reports and conduct market research", "Residential Properties(First-hand Sales)Ordinance"], "locations": ["Not Specified"], "categories": ["Marketing / Public Relations", "Marketing - Market Research", "Property / Real Estate", "Others", "Sales, CS & Business Devpt", "Sales - Real Estate"], "post_time": "2022-01-14T06:28:33Z", "salary": {"currency": null, "max": null, "min": null, "period": "monthly", "term": null}, "salary_visible": false, "title_keywords": ["assistant officer", "sales"], "responsibilities": ["sales administration", "compile reports", "logistics arrangement", "conduct market research", "analysis", "prepare sales", "implementation", "data processing", "logistics", "plan"], "requirements": {"degrees": ["degree holder"], "majors": ["related disciplines", "marketing", "surveying"], "languages": ["english", "chinese"], "language_level": ["proficient"], "hard_skills": ["analytical skills"], "soft_skills": ["organized", "self-motivated", "work independently", "attentive to details", "teamwork", "analytical skills", "customer-oriented", "energetic", "interpersonal"], "languages_combined": [{"language": "english", "language_level": ["proficient"]}, {"language": "chinese", "language_level": ["proficient"]}]}, "experience_required": {"duration": ["at least 1 years"], "field": ["property developers"]}}, {"job_id": "100003009043785", "location_code": "hk", "company": "Sanrio Wave Hong Kong Company Limited", "job_title": "Marketing Assistant Officer (Strategic Planning)", "description": "\u00a0Responsibilities:\u00a0\n\nPlan, organize and execute company's anniversary projects and\u00a0promotion activities including but not limited to character planning, character ranking marketing ideas, etc by giving creative and strategic initiatives\u00a0\nSupport the team to formulate and monitor digital or social media marketing campaign to achieve marketing objectives\u00a0\nConduct market research\u00a0and arrange evaluation and analysis of marketing activities\u00a0\nProvide support to Business Teams including but not limited to Global Retail, Event & Facility, Licensing and Branding Development Teams.\u00a0\nHandle media and customers\u2019 enquiries and relations\u00a0\nSupport the team on budget & forecast on character\u00a0anniversary\u00a0projects\u00a0\nProvide administrative support such as business project\u00a0consolidation\u00a0and updated sharing of market information\u00a0\n\nRequirements:\u00a0\n\nUniversity degree in Marketing/ Communications/ E-Business/ Interactive Media or relevant disciplines\u00a0\nAt least 2 years of relevant experience in managing brand, character related event or performance in multinational company, experience in brand planning will be an advantage\u00a0\nGood understanding of the character industry and license business is preferred\u00a0\nGood knowledge on e-commerce, B2B, B2C and social media related executions and planning\u00a0\nExcellent knowledge in PC operations including MS Word, Excel and Chinese Word Processing\u00a0\nProficiency in Adobe Illustrator and Photoshop\u00a0\nSelf-motivated, mature and be able to work independently\u00a0\nMore experience will be considered as Officer\u00a0\nImmediate availability is preferred\u00a0\n\nApplication Procedure:\n\nWe offer attractive remuneration package, competitive salary include double pay, medical scheme and dental insurance to the right candidate. Interested parties, please send your resume quoting with reference number, current and expected salary to the HR & Admin Division via Jobsdb.\n\nAll information received will be kept in strict confidence and only for employment-related purpose. Only short-listed candidates will be invited for interview.\u00a0", "employment_types": ["Full Time", "Permanent"], "selling_points": ["Digital Business and Social Media exposure", "Marketing and Planning in character industry", "Happy and fun working environment"], "locations": ["Kwun Tong"], "categories": ["Marketing / Public Relations", "Marketing - Brand / Product Management", "Marketing - Market Research", "Digital Marketing"], "post_time": "2022-01-13T01:56:37Z", "salary": {"currency": null, "max": null, "min": null, "period": "monthly", "term": null}, "salary_visible": false, "title_keywords": ["marketing assistant officer"], "responsibilities": ["social media", "provide support", "market information", "ideas", "conduct market research", "analysis", "monitor", "teams", "budget", "plan", "evaluation", "forecast", "provide administrative support", "support the team", "planning"], "requirements": {"degrees": ["university degree"], "majors": ["business", "marketing", "communications"], "languages": ["chinese"], "language_level": ["excellent"], "hard_skills": ["excel", "chinese word processing", "e-commerce", "pc operations", "adobe illustrator", "photoshop", "ms word"], "soft_skills": ["self-motivated", "work independently", "mature"], "languages_combined": [{"language": "chinese", "language_level": ["excellent"]}]}, "experience_required": {"duration": ["at least 2 years"], "field": ["multinational company", "brand", "related", "relevant experience", "planning"]}}, {"job_id": "100003009039534", "location_code": "hk", "company": "Price.com.hk Limited", "job_title": "Associate Marketing Manager / Senior Marketing Executive", "description": "Join us to create new values to the online offline commerce communities\n\nPrice.com.hk, being one of the most popular online platforms* in Hong Kong, strives to bring extra values to merchants and consumers by not only connecting them seamlessly with our state-of-the-art technology but co-creating a community that encourages a more user centric shopping experience combined with the application of big data analytics.\n\nWe start with a goal to minimize market information costs incurred upon consumers allowing them to find their favorite products easier and faster and at the same time enable merchants to successfully run their brick and click strategies to reach their targeted consumers at the lowest cost possible. Today, we are serving 2M+ monthly unique visitors. We cannot accomplish that without working together with individuals who are passionate about what they do.\n\n*According to Alexa, Price.com.hk is one of the top 25 most frequently visited sites in Hong Kong. https://www.alexa.com/siteinfo/price.com.hk\n\nYour role with us involves:\n\nAssist Marketing Manager on digital marketing, forecasting, site content optimization, email marketing and CRM\nImplement a wide range of promotion and marketing programs, including online and offline promotions, events\nParticipate in sales & marketing activities\nDrive trade marketing strategy, build and implement campaigns and programmes based on retails/merchants understanding\nResponsible for B2C and B2B communication, including both online and offline\nResearch, study and consolidate market trends in the digital industry\nCoordinate with media partners to ensure successful implementation of campaigns\nIdentify and approach business partners to develop joint promotions\n\nAs an employer, our role is to empower you by bringing your true talents and best self to this dynamic digital world and people we serve. We welcome individuals from all backgrounds, ideally with skills and traits as below:\n\nMinimum 4 years of relevant working experience\nDegree holder in Marketing, Communication or related disciplines\nProactive, critical, analytical and detail-oriented\nWell-organized, self-motivated and able to work in a fast-paced environment\nExcellent communication and presentation skills\nKnowledge of Google Adwords and Google Analytics\nFluent written and spoken Cantonese and English\nCandidates with less experience will be considered as Senior Marketing Executive\n\nBe part of us, you will enjoy:\n\nDiscretionary Bonus\n5-day Work Week\nFlexible Working Hour\nBirthday, Marriage, Maternity and Paternity Leave\nBirthday Gift\nMedical Insurance\nMonthly Birthday Party\nTeam Event and Team Building Activities\nHappy and Dynamic Environment\nCasual Dress Code\n\nWorking Location: Kwun Tong (5 minutes from Kwun Tong MTR station)\n\nInterested parties, please click \"Apply now\" to submit your resume with the\u00a0availability and expected salary\u00a0to us.\n\nPersonal data collected will be kept strictly confidential and only be used for recruitment related purposes.", "employment_types": ["Full Time", "Permanent"], "selling_points": ["Fast Growing Industry", "An Expanding E-Commerce Company", "Offer Training & Development"], "locations": ["Kwun Tong"], "categories": ["Marketing / Public Relations", "Marketing - Brand / Product Management", "Marketing - Market Research", "Marketing - Marketing Communication"], "post_time": "2022-01-11T10:01:20Z", "salary": {"currency": null, "max": null, "min": null, "period": "monthly", "term": null}, "salary_visible": false, "title_keywords": ["marketing manager", "associate", "senior marketing executive"], "responsibilities": ["cost", "market information", "trade marketing", "big data", "coordinate with", "implementation", "develop", "communication", "digital marketing", "insurance", "sales & marketing activities", "forecasting", "costs"], "requirements": {"degrees": ["degree holder"], "majors": ["related disciplines", "marketing"], "languages": ["cantonese", "english"], "language_level": ["fluent"], "hard_skills": ["google analytics", "adwords", "data analytics", "goal", "dynamic", "code"], "soft_skills": ["flexible", "self-motivated", "dynamic environment", "responsible", "fast-paced environment", "well-organized", "unique", "detail-oriented", "communication", "presentation skills", "dynamic", "proactive", "passionate about"], "languages_combined": [{"language": "cantonese", "language_level": ["fluent"]}, {"language": "english", "language_level": ["fluent"]}]}, "experience_required": {"duration": ["minimum 4 years"], "field": ["marketing", "relevant working experience"]}}, {"job_id": "100003009041985", "location_code": "hk", "company": "Guru Online", "job_title": "Digital Marketing Assistant", "description": "What You Will Be Doing:\n\nFormulate insightful strategies and creative ideas to meet clients\u2019 objectives, ensure successful execution, flow and end-result.\nPrepare documents to pitch clients, e.g. marketing plan, schedule, budget etc.;\nPresent ideas to clients together with the Account Management Team, if necessary;\nAssist in project management and coordinate communication with both internal and\u00a0external parties.\n\n\u00a0What You Need for this Position:\n\nBachelor\u2019s degree\u00a0in\u00a0advertising,\u00a0Mass\u00a0Communication,\u00a0Marketing or related disciplines;\nGood marketing sense, multi-tasking and good management;\nA good team player, able and flexible to work with people of different cultures;\nExcellent command of Mandarin and English;\nProficient\u00a0in MS PowerPoint and Excel\n\n\u00a0Benefits We Offer:\n\n\u00a05 days\u2019\u00a0work\nQuarterly Performance Bonus\nMedical Coverage including Dental\nFlexible Working Hours\nOvertime\u00a0Meal\u00a0and Transportation allowance\nBirthday, Wedding, Graduation and other special leaves\nFun, young and joyful environment\u00a0\n\n\u00a0Be a GURU, be our next great hire.\u00a0APPLY NOW!\n\n*All information will be treated as confidential and used solely for recruitment purposes.", "employment_types": ["Full Time", "Permanent"], "selling_points": ["Help develop creative digital marketing campaign", "Birthday, Graduation and other special leaves", "On job training is provided"], "locations": ["Kwun Tong"], "categories": ["Marketing / Public Relations", "Marketing - Market Research", "Public Relations - General / Support", "Digital Marketing"], "post_time": "2022-01-12T04:59:50Z", "salary": {"currency": null, "max": null, "min": null, "period": "monthly", "term": null}, "salary_visible": false, "title_keywords": ["digital marketing", "assistant"], "responsibilities": ["management team", "creative ideas", "management", "ideas", "advertising", "budget", "internal and external parties", "coordinate", "marketing plan", "project management", "communication", "schedule", "prepare documents"], "requirements": {"degrees": ["degree", "bachelor"], "majors": ["related disciplines", "marketing"], "languages": ["english", "mandarin"], "language_level": ["excellent"], "hard_skills": ["project management", "ms powerpoint", "excel"], "soft_skills": ["flexible", "good team player", "marketing sense", "communication", "project management", "multi-tasking", "creative"], "languages_combined": [{"language": "english", "language_level": ["excellent"]}, {"language": "mandarin", "language_level": ["excellent"]}]}, "experience_required": {"duration": [], "field": []}}, {"job_id": "100003009052447", "location_code": "hk", "company": "Orient Overseas Container Line Ltd (OOCL)", "job_title": "Assistant / Deputy Manager, Strategic Planning, Trans-Atlantic Trade (Ref: AMDM/SP/TAT)", "description": "Responsibilities:\n\nTo review and optimize TAT network efficiency & vessel deployment strategy in conjunction with commercial requirement\nTo resolve commercial/traffic\u2019s concerns from network perspective\nTo conduct market research and analysis projects to assist the strategic planning for the trade; provide analytical works to support day-to-day commercial decisions\nTo prepare KPI reports on performance evaluation and analysis; yield assessment for various market segments\nTo monitor cost and risk exposure\nTo prepare marketing/PR promotion\nTo support Strategic Planning on reporting and perform other ad hoc task and project as assigned\n\n\u00a0Requirements:\n\nUniversity graduate in Business/Logistics and related disciplines\nMinimum 3 years\u2019 relevant working experience in Container Liner Shipping Company\nGood communication, analytical and problem solving skills\nAble to work independently and team-oriented\nProficiency in spoken and written English and Chinese; Putonghua is a plus\nCompetency in Windows applications\n\n\nInterested parties please send your application letter with detailed resume and expected salary by clicking\u00a0\"Apply Now\" .\n(Data collected will be used for recruitment purpose only.)", "employment_types": ["Full Time", "Permanent"], "selling_points": ["To review and optimize TAT network efficiency", "University graduate in Business/Logistics", "Minimum 3 years\u2019 relevant working experience"], "locations": ["Wan Chai"], "categories": ["Transportation & Logistics", "Shipping", "Marketing / Public Relations", "Marketing - Market Research", "Sales, CS & Business Devpt", "Others"], "post_time": "2022-01-17T03:03:52Z", "salary": {"currency": null, "max": null, "min": null, "period": "monthly", "term": null}, "salary_visible": false, "title_keywords": ["deputy manager", "assistant"], "responsibilities": ["reporting", "cost", "ad hoc", "strategic planning", "analysis", "conduct market research", "review", "monitor", "reports", "evaluation"], "requirements": {"degrees": ["university graduate"], "majors": ["related disciplines", "business"], "languages": ["putonghua", "english", "chinese"], "language_level": ["proficiency"], "hard_skills": ["problem solving skills", "container", "plus"], "soft_skills": ["communication", "analytical and problem solving skills", "work independently"], "languages_combined": [{"language": "putonghua", "language_level": []}, {"language": "english", "language_level": ["proficiency"]}, {"language": "chinese", "language_level": ["proficiency"]}]}, "experience_required": {"duration": ["minimum 3 years"], "field": ["relevant working experience"]}}, {"job_id": "100003009043108", "location_code": "hk", "company": "B.S.C. COLOURLIVING LIMITED", "job_title": "Marketing Assistant", "description": "Responsibilities:\n\nProvide full support to marketing team on marketing events and campaigns, promotion and online materials update etc\nSupport the marketing team daily operation and working with various departments for execution\nPerform marketing research and prepare presentation materials\nAssist to maintain branding continuity on all marketing initiatives\nAssist in ad hoc projects as assigned from time to time\n\n\u00a0Requirements:\n\nDegree holder in Marketing, Advertising, Business Administration or related disciplines\nMin. 1 year working experience in Digital Marketing or Marketing industry; experience related to lifestyle or luxury interior brands is preferred\nKnowledge in social media marketing & website analytics tools will be a strong advantage\nSelf-motivated, well-organized, adaptable character with high learning ability\nEnjoy working in a fast-paced organization\nGood command of both written and spoken English and Chinese\n\nWe offer attractive remuneration package and comprehensive fringe benefits,\u00a0including\u00a014 days annual leave,\u00a0medical insurance and discretionary bonus\u00a0to the right candidate.\n\nInterested parties please apply with full resume, expected salary and quoting the Job Ref. No. on the subject line to\u00a0Human Resources Department, 19th Floor, Sino Favour Centre, 1 On Yip Street, Chaiwan, Hong Kong, or by\u00a0clicking the \"Apply Now\".\u00a0For more information about us, please visit our websites at\u00a0http://www.bschk.com\u00a0and\u00a0http://www.colourliving.com.\n\n\nPersonal data collected will be used for recruitment purpose only.", "employment_types": ["Full Time", "Permanent"], "selling_points": ["Provide support to Marketing Team", "Degree in Mkt, Advertising or related disciplines", "5-day work week & 14-day of annual leave"], "locations": ["Chai Wan"], "categories": ["Marketing / Public Relations", "Marketing - Brand / Product Management", "Marketing - Market Research", "Marketing - Marketing Communication"], "post_time": "2022-01-12T09:49:45Z", "salary": {"currency": null, "max": null, "min": null, "period": "monthly", "term": null}, "salary_visible": false, "title_keywords": ["marketing assistant"], "responsibilities": ["marketing events", "daily operation", "marketing research", "maintain", "ad hoc projects"], "requirements": {"degrees": ["degree holder"], "majors": ["related disciplines", "marketing", "business administration"], "languages": ["english", "chinese"], "language_level": ["good command"], "hard_skills": ["analytics tools"], "soft_skills": ["self-motivated", "learning ability", "adaptable", "enjoy working", "well-organized", "comprehensive"], "languages_combined": [{"language": "english", "language_level": ["good command"]}, {"language": "chinese", "language_level": ["good command"]}]}, "experience_required": {"duration": ["1 year"], "field": ["related", "marketing", "digital marketing"]}}, {"job_id": "100003009043999", "location_code": "hk", "company": "Amorepacific Hong Kong Co Ltd", "job_title": "Senior Business Analyst", "description": "Key Responsibilities\n\nWork as business partners to support Brand Function to deliver their business goal; Ensure effective strategy implementation and monitoring performance\nExecute business performance analytics including implement modeling development and refinement to maximize customer retention and value, gather customer insights through data mining and analysis, identify up-sell & cross-sell opportunities to increase customer value\nWork closely with Brand Function to design customer journeys, conduct customer segmentation and best targeting tactics as well as effectiveness evaluation.\nProduce reporting analytics to enable identification of key trends or issues in the Business / Operating Unit that necessitate further analysis and discussion\nConnect with Headquarter Strategy Team on different aspect of the business e.g. analysis of internal financial information and external economic condition and its impact on business operations, future market outlook etc.\nSupport in Dashboards development including data modelling and design\nAny ad hoc activities arising\u00a0 \u00a0\n\nKey Stakeholders\n\nThis position\u2019s primary interfaces are (engagement, interaction, etc)\n\n\nLocal: Brand GM, Brand Marketing & Operation Team, Finance Operation Team, HR Team\nHQ: Strategy Team\n\nRequirements:\n\nDegree in Business, Statistics or Mathematics related field\n4-5 years working experience in business/data analysis or business intelligence preferably gained from Retail Industry\nStrong business acumen and analytical skillset\nEnjoy challenges and willing to push back & confront status quo when necessary\nExcellent communication, interpersonal & influencing skills\nAbility to work independently & effectively with all levels within an organization\nHigh proficient in SQL, MS Excel.\nExperience in statistical tool e.g. SPSS and BI tools e.g. Tableau is highly preferred.\u00a0 Knowledge in Salesforce Marketing Cloud will be a plus.\n\nCandidate with less experience will be considered as Business Analyst.\n\n\n\n\nWe offer opportunities for development in addition to a competitive remuneration and benefit package to the right candidate. Interested parties please click \"Apply Now\" for application.\n\nPersonal data provided by job applicants will be used strictly for recruitment purpose only.", "employment_types": ["Full Time", "Permanent"], "selling_points": ["Work closely with Brand to design customer journey", "Execute business performance analytics", "4-5 years working experience in business analysis"], "locations": ["Wan Chai"], "categories": ["Accounting", "Financial Analyst", "Professional Services", "Business Analysis / Data Analysis", "Marketing / Public Relations", "Marketing - Market Research"], "post_time": "2022-01-13T02:44:45Z", "salary": {"currency": null, "max": null, "min": null, "period": "monthly", "term": null}, "salary_visible": false, "title_keywords": ["senior business analyst"], "responsibilities": ["reporting", "ad hoc", "data", "operations", "analysis", "monitoring", "customer insights", "implementation", "design", "hr", "evaluation", "data mining"], "requirements": {"degrees": ["degree"], "majors": ["mathematics", "business", "statistics"], "languages": [], "language_level": [], "hard_skills": ["plus", "bi", "salesforce", "analysis", "tableau", "sql", "ms excel", "business intelligence", "acumen"], "soft_skills": ["business acumen", "work independently", "interpersonal", "communication"], "languages_combined": []}, "experience_required": {"duration": ["4-5 years"], "field": ["data analysis", "business", "retail industry"]}}, {"job_id": "100003009044216", "location_code": "hk", "company": "CT-INC. Limited", "job_title": "Marketing Assistant / Executive", "description": "Responsibilities:\n\nProvide full support to marketing team on marketing events and campaigns, promotion, and online materials update etc\nConduct market research and identify market opportunities\nSupport the marketing team daily operation and working with various departments for execution\nManage social media properties\nDevelop marketing collateral such as DMs, leaflets, and videos etc\nSupport in marketing reports, coordination, and administrations\nPerform ad-hoc project as required.\nRequirements:\n\nHigh Diploma or degree holder in Marketing, business administration, translation, or related discipline with 1 to 2 years\u2019 relevant working experience in marketing\nGood command of both written English and Chinese\nGood data analytical, interpersonal and communication skills\nSelf-motivated, detail-oriented, well-organized, and able to work under pressure\nCandidates with less experience will be considered as Marketing Executive\nImmediate availability is an advantage\nFresh graduates are welcome\n\nYou will enjoy Benefit\n\n5 Days Work\n14 days Annual Leave\nDouble Pay\nPerformance Discretionary bonus \u00a0\nMedical Coverage\nFriendly and collaborative work environment", "employment_types": ["Full Time", "Permanent"], "selling_points": ["Stable and fast-growing business", "Support marketing team daily operation", "Immediately available"], "locations": ["Lai Chi Kok"], "categories": ["Marketing / Public Relations", "Marketing - Market Research", "Marketing - Marketing Communication", "Public Relations - General / Support"], "post_time": "2022-01-13T03:25:38Z", "salary": {"currency": null, "max": null, "min": null, "period": "monthly", "term": null}, "salary_visible": false, "title_keywords": ["marketing assistant", "executive"], "responsibilities": ["ad-hoc", "marketing events", "social media", "leaflets", "conduct market research", "daily operation", "develop", "reports", "coordination"], "requirements": {"degrees": ["high diploma", "degree holder"], "majors": ["marketing", "business administration"], "languages": ["english", "chinese"], "language_level": ["good command"], "hard_skills": ["translation"], "soft_skills": ["communication skills", "self-motivated", "well-organized", "collaborative", "detail-oriented", "friendly", "interpersonal", "work under pressure"], "languages_combined": [{"language": "english", "language_level": ["good command"]}, {"language": "chinese", "language_level": ["good command"]}]}, "experience_required": {"duration": ["1 to 2 years"], "field": ["related", "marketing", "business administration", "relevant working experience"]}}, {"job_id": "100003009035368", "location_code": "hk", "company": "HKT Enterprise Solutions", "job_title": "Senior Market Analyst", "description": "Your\u00a0role\n\nYou will work in the Marketing Data Analytic Team.\u00a0 The major responsibility of this role is to provide high quality insight and facilitate decision making process on business side through data mining and analysis. Major responsibilities include but not limited to the following:\n\nHandle large sets of data to analysis the customer behavior and identify new market opportunities and retention strategies\nPrepare regular management report & dashboards on business performance metrics\nAnalyze marketing trend and identify customer needs by building data-driven attribution models\nConduct market research projects to analyze competitors, determine brand perceptions evaluate market penetration; understand customer satisfaction\nProvide ROI analysis of all marketing campaigns and sales activities (maximize effectiveness)\nPerform UAT, data testing and monitor project execution to maintain data integrity of marketing data mart\nSupport ad-hoc projects as assigned\n\nTo succeed this role\n\nDegree holder in Marketing or Statistics related discipline\n3 years\u2019 solid experience in data analytics, data mining and customer segmentation with strong programming skill in SQL and Python\nFamiliar in Datamart, BI Dashboard and visualization tool such as Qliksense and Tableau\nWorking experience in telecommunication / mobile / Banking/ IT industry is preferred\nA marketing expert who possesses a core strength of strategic thinking\nGood analytical skill and detail-oriented\nExcellent interpersonal and communication skills as well as good command of both written and spoken English and Cantonese", "employment_types": ["Full Time"], "selling_points": [], "locations": ["Quarry Bay"], "categories": ["Banking / Finance", "Analyst", "Information Technology (IT)", "DBA", "Marketing / Public Relations", "Marketing - Market Research"], "post_time": "2022-01-10T06:56:23Z", "salary": {"currency": null, "max": null, "min": null, "period": "monthly", "term": null}, "salary_visible": false, "title_keywords": ["analyst"], "responsibilities": ["visualization", "data", "conduct market research", "quality", "communication", "data mining", "ad-hoc projects", "uat", "monitor", "testing", "marketing campaigns", "banking", "management report", "maintain data", "sales activities", "analyze marketing trend", "analysis", "performance metrics", "evaluate"], "requirements": {"degrees": ["degree holder"], "majors": ["marketing", "statistics"], "languages": ["cantonese", "english"], "language_level": ["excellent", "good command"], "hard_skills": ["analytical skill", "bi", "data analytics", "analysis", "tableau", "python", "sql", "mobile", "programming", "data mining"], "soft_skills": ["communication skills", "analytical skill", "strategic thinking", "integrity", "detail-oriented", "interpersonal", "driven", "decision making"], "languages_combined": [{"language": "cantonese", "language_level": ["excellent", "good command"]}, {"language": "english", "language_level": ["excellent", "good command"]}]}, "experience_required": {"duration": ["3 years"], "field": ["sql", "it", "programming", "banking"]}}]