[{"job_id": "100003009054100", "location_code": "hk", "company": "OSMA Consulting Limited", "job_title": "Marketing Assistant \u5e02\u573a\u90e8\u4e13\u5458", "description": "Our Client is a Hong Kong based Fin-tech company with founding members from reputable local family offices and high level seniors of international conglomerates. To market their newly launched financial products, they are looking for qualified individuals to join the their team assisting daily operation.\n\n\u6211\u4eec\u7684\u5ba2\u6237\u662f\u4e00\u5bb6\u603b\u90e8\u4f4d\u4e8e\u9999\u6e2f\u7684\u91d1\u878d\u79d1\u6280\u516c\u53f8\uff0c\u5176\u521b\u59cb\u6210\u5458\u6765\u81ea\u5f53\u5730\u8457\u540d\u7684\u5bb6\u65cf\u529e\u516c\u5ba4\u548c\u56fd\u9645\u4f01\u4e1a\u96c6\u56e2\u7684\u9ad8\u5c42\u3002 \u4e3a\u4e86\u8425\u9500\u4ed6\u4eec\u65b0\u63a8\u51fa\u91d1\u878d\u4ea7\u54c1\uff0c\u4ed6\u4eec\u6b63\u5728\u5bfb\u627e\u5408\u683c\u7684\u4e2a\u4eba\u52a0\u5165\u4ed6\u4eec\u7684\u56e2\u961f\uff0c\u534f\u52a9\u65e5\u5e38\u8fd0\u8425\u3002\n\nResponsibilities:\n1.\u00a0Support Marketing Manager to consolidate promotion plan and coordinate with internal business units;\n2. Assist Marketing Manager to organize any promotion or roadshow event;\n3. Work closely with Business Development team to deliver\u00a0promotion materials to outside parties through both online and offline channels;\n4.\u00a0Deliver all assigned projects with high quality as requested by seniors.\n\nRequirements:\n1. Degree or above;\n2. Excellent communication and interpersonal skills;\n3. Knowledge in social media marketing & website analytics tools will be an advantage;\n4. Good command of English and Mandarin is a plus.\n\n\n\u804c\u8d23\uff1a\n1.\u652f\u6301\u8425\u9500\u7ecf\u7406\u6574\u5408\u63a8\u5e7f\u8ba1\u5212\uff0c\u4e0e\u5185\u90e8\u4e1a\u52a1\u90e8\u95e8\u534f\u8c03\uff1b\n2.\u534f\u52a9\u8425\u9500\u7ecf\u7406\u7ec4\u7ec7\u4efb\u4f55\u4fc3\u9500\u6216\u8def\u6f14\u6d3b\u52a8\uff1b\n3.\u4e0e\u4e1a\u52a1\u53d1\u5c55\u56e2\u961f\u7d27\u5bc6\u5408\u4f5c\uff0c\u901a\u8fc7\u7ebf\u4e0a\u7ebf\u4e0b\u6e20\u9053\u5411\u5916\u754c\u63d0\u4f9b\u5ba3\u4f20\u8d44\u6599\uff1b\n4.\u6309\u7167\u4e0a\u7ea7\u8981\u6c42\uff0c\u9ad8\u8d28\u91cf\u4ea4\u4ed8\u6240\u6709\u5206\u914d\u7684\u9879\u76ee\u3002\n\n\u8981\u6c42\uff1a\n1. \u672c\u79d1\u6216\u4ee5\u4e0a\u5b66\u5386\uff1b\n2. \u4f18\u79c0\u7684\u6c9f\u901a\u548c\u4eba\u9645\u4ea4\u5f80\u80fd\u529b\uff1b\n3. \u719f\u6089\u793e\u4ea4\u5a92\u4f53\u8425\u9500\u548c\u7f51\u7ad9\u5206\u6790\u5de5\u5177\u8005\u4f18\u5148\uff1b\n4. \u82f1\u8bed\u53ca\u666e\u901a\u8bdd\u6d41\u5229\u8005\u4f18\u5148\u3002", "employment_types": ["Full Time"], "selling_points": ["High-end Club", "Excellent exposure", "Attractive Package"], "locations": ["Central"], "categories": ["Marketing / Public Relations", "Marketing - Brand / Product Management", "Marketing - General / Support", "Marketing - Marketing Communication"], "post_time": "2022-01-17T08:25:50Z", "salary": {"currency": null, "max": null, "min": null, "period": "monthly", "term": null}, "salary_visible": false, "title_keywords": ["marketing assistant"], "responsibilities": ["quality", "plan and coordinate"], "requirements": {"degrees": ["degree or above"], "majors": [], "languages": ["english", "mandarin"], "language_level": ["good command"], "hard_skills": ["analytics tools", "plus"], "soft_skills": ["communication and interpersonal skills"], "languages_combined": [{"language": "english", "language_level": ["good command"]}, {"language": "mandarin", "language_level": ["good command"]}]}, "experience_required": {"duration": [], "field": []}}, {"job_id": "100003009053682", "location_code": "hk", "company": "Adsale Exhibition Services Ltd", "job_title": "Assistant Project Executive - Marketing Communications", "description": "Responsibilities:\n\nTo support Product & Marketing Manager and work as a team to execute product plans and strategy with the ultimate objective of raising brand awareness, brand building and increasing sales;\nTo identify a continuous stream of commercially valuable new products;\nDrive product development, packaging and manage market analysis;\nProduct forecasting and inventory control and management;\nWork closely with internal and external production / QC teams to ensure accurate execution of product development with the right quality and time;\nSupport ad hoc projects when required.\n\nRequirements:\n\n\u00a0 Degree in marketing, business management, nutrition or food science background is preferable;\n\u00a0 Minimum 3 years product experience in retail / FMCG (bottled drinks preferred);\n\u00a0 Solid experience in product marketing is advantageous;\n\u00a0 Good communications skill in Cantonese, Mandarin and English\n\u00a0 Able to independently manage project and drive progress.\n\u00a0 Candidate with more experience will be considered as \"Senior Product Marketing Officer\"\n\n\n\nWe offer 5-day-work week with competitive remuneration and benefit packages to the right candidate. Interested parties please send your application letter, resume, expected salary (quoting Employer Ref:) and availability to\u00a0HR Department at Hung Fook Tong, 8/F, Chuan Kei Factory Building, Nos. 15-23 Kin Hon Street, Kwai Chung, NT., H.K. or e-mail or\u00a0browse our website:\u00a0www.hungfooktong.com\n\nPersonal Information Collection Statement-Applicants\u2019 personal information will be used for the recruitment and employment matters only; information will be kept in strict confidence; information of unsuccessful applicants will be shredded after recruitment process; subject to provisions under the Personal Data (Privacy) Ordinance, applicants have right to access and make corrections of their personal data", "employment_types": ["Full Time"], "selling_points": ["5-day work week; double pay with bonus", "Assist different projects, planning to execution", "2 years solid experience in Marketing"], "locations": ["North Point"], "categories": ["Marketing / Public Relations", "Marketing - General / Support", "Marketing - Marketing Communication", "Public Relations - Event Management"], "post_time": "2022-01-17T07:20:30Z", "salary": {"currency": null, "max": null, "min": null, "period": "monthly", "term": null}, "salary_visible": false, "title_keywords": ["project executive", "assistant"], "responsibilities": ["management", "teams", "quality", "inventory control", "market analysis", "ad hoc projects", "plans", "forecasting"], "requirements": {"degrees": ["degree"], "majors": ["business", "marketing", "food science"], "languages": ["cantonese", "english", "mandarin"], "language_level": ["good"], "hard_skills": ["business management"], "soft_skills": ["independently"], "languages_combined": [{"language": "cantonese", "language_level": ["good"]}, {"language": "english", "language_level": ["good"]}, {"language": "mandarin", "language_level": ["good"]}]}, "experience_required": {"duration": ["minimum 3 years"], "field": ["retail", "marketing", "fmcg"]}}, {"job_id": "100003009054244", "location_code": "hk", "company": "Jia Group Holdings Limited", "job_title": "Marketing Executive", "description": "(Ref : EXH-MCAPE-005-2022)\n\nResponsibilities:\n\nAssist in different kinds of projects from planning to execution, e.g. events, video/animation, live stream, design.\nProvide support to marketing campaigns through ATL & BTL channels.\nPrepare promotion materials, eDMs, printed & online advertisements as well as reports.\nWork closely with internal cross-functional teams and external parties to generate different marketing assets and ensure execution.\nAssist ad hoc project when required.\n\n\u00a0Requirements:\n\nDegree\u00a0holder with at least 2\u00a0years solid experience in Marketing, preferably in advertising agency/ exhibition industry, with digital marketing experience is an advantage.\nExcellent in written and spoken English and Chinese ( incl. Putonghua).\nMature, pro-active, self-motivated, well organized and detail-oriented.\nA team player with good communication skills\u00a0 and able to work under multitasking environment.\nBasic knowledge of producing eDM, artwork editing and promotion via Social Media are preferable.\nOccasional mainland China trips are required.\n\nWe offer attractive remuneration package including 5-day work, double pay, medical insurance, medical check-up, birthday leave, training and excellent development prospect to the right candidate.\u00a0Interested parties please send full resume with expected salary, availability and contact no. to\u00a0The Human Resources & Administration Manager\u00a0by fax :\u00a03586-0196\u00a0or click\u00a0APPLY NOW.\u00a0 \u201cPlease quote our job reference\u201d\u00a0\n\nCorporate Website : www.adsale.com.hk\n\n(All personal data will be used for recruitment purpose only)", "employment_types": ["Full Time", "Permanent"], "selling_points": ["Support daily marketing activities", "Assist in implementation of marketing initiatives", "Min. 1 yr exp. preferably gained in F&B industry"], "locations": ["Central"], "categories": ["Marketing / Public Relations", "Marketing - Brand / Product Management", "Marketing - Direct Marketing", "Marketing - General / Support"], "post_time": "2022-01-17T09:57:39Z", "salary": {"currency": null, "max": null, "min": null, "period": "monthly", "term": null}, "salary_visible": false, "title_keywords": ["marketing executive"], "responsibilities": ["provide support", "edms", "internal cross-functional teams", "ad hoc", "advertisements", "external parties", "design", "reports", "marketing campaigns", "animation", "planning"], "requirements": {"degrees": ["degree holder"], "majors": ["marketing", "digital marketing"], "languages": ["putonghua", "english", "chinese"], "language_level": ["excellent"], "hard_skills": ["basic"], "soft_skills": ["communication skills", "self-motivated", "well organized", "mature", "detail-oriented", "pro-active", "team player"], "languages_combined": [{"language": "putonghua", "language_level": []}, {"language": "english", "language_level": ["excellent"]}, {"language": "chinese", "language_level": ["excellent"]}]}, "experience_required": {"duration": ["at least 2 years"], "field": ["marketing", "digital marketing", "advertising agency"]}}, {"job_id": "100003009054147", "location_code": "hk", "company": "Moonzen Brewery Company Limited", "job_title": "Marketing Executive", "description": "Responsible for supporting Team Supervisor in the implementation of various projects, in particular cultural exchange projects.\u00a0 Duties include project coordination and logistics, liaison with artists and different parties, preparation of online and offline publicity materials, committee papers and meetings, as well as general administrative work.\n\nRequirements:\n\nA university degree with at least 3-year experience in project coordination, preferably in arts sectors\nStrong analytical skill, well-organised and detail-oriented\nAble to work under pressure and strong adaptability to situations\nA good team player with good interpersonal and communication skills\nGood command of written and spoken English, Cantonese and Putonghua\nProficiency in PC operations (MS based applications and Chinese Word Processing)\nWell understanding and strong interest in arts scene in Hong Kong will be an advantage\n\nSalary offered will be commensurate with qualifications and experience. Interested persons, please send CV with details on education and work experience, stating salary history and expected salary, and indicating your earliest availability to the Human Resources Department, 10/F, 1063 King\u2019s Road, Quarry Bay, Hong Kong no later than 7 February 2022.\u00a0 Please quote the job reference on the envelope.\n\n\u00a0Applicants not invited for interview within 16 weeks from the closing date for application may assume that their applications are unsuccessful.\u00a0 Personal data collected will be treated in strictest confidence and will only be used for recruitment purposes. HKADC reserves the right to consider late applications and not to make appointment for the post advertised.\u00a0 We do not accept applications through e-mail or fax.\n\n\u00a0\nHKADC is an Equal Opportunities Employer", "employment_types": ["Full Time"], "selling_points": ["Proactive and engaging personality is essential", "A team mixing local and foreign members", "Benefit: Unlimited fresh craft beer!"], "locations": ["Kwun Tong"], "categories": ["Marketing / Public Relations", "Marketing - General / Support"], "post_time": "2022-01-17T08:33:30Z", "salary": {"currency": "HKD", "max": 19999, "min": 17000, "period": "monthly", "term": null}, "salary_visible": true, "title_keywords": ["marketing executive"], "responsibilities": ["administrative work", "project coordination", "operations", "implementation", "communication", "logistics", "recruitment", "personal data", "work under pressure"], "requirements": {"degrees": ["university degree"], "majors": [], "languages": ["cantonese", "putonghua", "english", "chinese"], "language_level": ["proficiency", "good command"], "hard_skills": ["analytical skill", "no", "chinese word processing", "pc operations", "make", "ms based applications", "exchange"], "soft_skills": ["communication skills", "analytical skill", "good team player", "confidence", "responsible", "detail-oriented", "adaptability", "coordination", "well-organised", "interpersonal", "work under pressure"], "languages_combined": [{"language": "cantonese", "language_level": ["good command"]}, {"language": "putonghua", "language_level": ["good command"]}, {"language": "english", "language_level": ["good command"]}, {"language": "chinese", "language_level": ["proficiency"]}]}, "experience_required": {"duration": ["at least 3-year"], "field": ["human resources", "education"]}}, {"job_id": "100003009054440", "location_code": "hk", "company": "Carsac Limited", "job_title": "Sales & Marketing Assistant", "description": "To support the expansion of our Group, we are currently seeking an experienced\u00a0Marketing Executive individual with strong payroll skills\u00a0to learn to join our Family.\n\n\nSupport daily marketing activities and perform administrative duties\nProvide support on events and promotion campaigns arrangements\nPrepare marketing materials, market researches and ad hoc projects\nAssist in implementation of marketing initiatives, including events, media and promotions\nCoordinate with internal and external parties to ensure smooth execution of the tasks required\nDevise well-rounded strategy plans. This includes but not limited to events, reservations, third party platforms and more\nAssist with ad-hoc assignments as required\n\nIdeal requirements:\n\nDegree in Business, Marketing & Communications, Hospitality Management, or other related disciplines\nMinimum 1 year working experience, preferably gained in F&B industry\nAble to meet tight deadlines and work under pressure in a fast-paced environment\nAbility to work and understand systems such as Mailchimp, Seven rooms and Jot form will be advantageous\nExcellent command of written and spoken English and Chinese\nStrong interpersonal and communication skills\nProficient understanding of design software such as Illustrator and in Design. Other software will be advantageous\nFresh graduates are welcome to apply\nIf you are interested to apply for the above positions, please click apply share your resume with your CURRENT and EXPECTED salary with us.\n\nPeople who are eligible to work in Hong Kong or have a valid Hong Kong work permit/visa will be considered for the above position. If you are passionate about hospitality and are looking for exciting new opportunities, then we want to hear from you!\n\nWe are an equal opportunity employer. Information provided will be treated in strict confidence and will only be used for recruitment-related purposes.", "employment_types": ["Full Time", "Permanent"], "selling_points": [], "locations": ["North Point"], "categories": ["Marketing / Public Relations", "Marketing - General / Support"], "post_time": "2022-01-17T09:34:15Z", "salary": {"currency": null, "max": null, "min": null, "period": "monthly", "term": null}, "salary_visible": false, "title_keywords": ["marketing assistant", "sales"], "responsibilities": ["software", "internal and external parties", "design", "communication", "promotion campaigns", "plans", "work under pressure", "implementation", "provide support", "management", "coordinate with", "administrative duties", "payroll", "third party", "prepare marketing materials", "ad-hoc assignments", "systems", "ad hoc projects", "recruitment"], "requirements": {"degrees": ["degree"], "majors": ["hospitality management", "related disciplines", "business", "marketing", "communications"], "languages": ["english", "chinese"], "language_level": ["excellent"], "hard_skills": ["illustrator"], "soft_skills": ["communication skills", "meet tight deadlines", "confidence", "ideal", "fast-paced environment", "smooth", "interpersonal", "passionate about", "work under pressure"], "languages_combined": [{"language": "english", "language_level": ["excellent"]}, {"language": "chinese", "language_level": ["excellent"]}]}, "experience_required": {"duration": ["minimum 1 year"], "field": ["f&b"]}}, {"job_id": "100003009055135", "location_code": "hk", "company": "Ocean Park Corporation", "job_title": "Contract Social Media Content Creator (Marketing Department)", "description": "Overview:\nCoordinating with sales and brewing team, the primary function of the Marketing Executive position is the creation and execution of a comprehensive marketing plan for Moonzen Brewery. The candidate will report to the Assistant General Manager of the brewery, with the support of an outsourced designer.\n\nJob Duties:\n\nAssist to develop the annual marketing plan including strategy, goals, budget and tactics\nPrepare and manage all marketing materials, website updates, and social media presence on behalf of the Company, including business meeting pitches and presentations etc\nBe the last point of contact with deliverables before they are published/distributed ensuring all formatting, aesthetics and content are in\u2010line with brewery standards and expectations\nProactively generate opportunities to advance the brewery\u2019s brand via online and offline channels including but not limited to digital media, speaking, conference participation and other forms of advertising\nMaintain a keen understanding of industry trends affecting clients and make appropriate recommendations regarding communication strategy surrounding them\nEvaluate opportunities for partnerships, sponsorships and advertising on an on-going basis\nMonitor, analyze and communicate marketing results/planning on a monthly and quarterly basis\nCoordinate all marketing and public relations activities, including media inquiries and interview requests\nRequirements:\n\nLove of craft beer\nProven track record designing and executing successful marketing & PR campaigns at both a local and international level\nGeneral knowledge of F&B scene in HK\nDemonstrate ability to think creatively and independently\nExceptional writing and editing skills with general design knowledge / experience, and the ability to create and assemble attractive marketing materials\nStrong work ethic and motivation to succeed\nPossess strong organizational skills and attention to detail necessary to prioritize multiple initiatives and projects\nSolid working knowledge and experience of Powerpoint, Word, Excel, PDF, Facebook, Instagram, LinkedIn, Google Analytics, Adobe InDesign or Adobe CC, etc.\nDemonstrate a professional level of verbal, written and listening skills in English and Cantonese\nWork well with a diverse, fast-paced and dynamic team\nBA degree in Marketing, Advertising, Communications or a related discipline\nCreative, confident, assertive, proactive attitude with \u2018can-do\u2019 mindset\nA minimum of one year of marketing & PR experience, either employed as in-house or consulting role\nKnowledge in F&B or alcohol beverages production facilities will be considered a plus\nAvailability: from Feb 7th, 2022\nIf you are interested in joining the journey with Moonzen, please send your resume and cover letter by clicking \"Apply Now\".", "employment_types": ["Temporary", "Contract"], "selling_points": ["Social Media Content Creator", "Marketing", "Digital Marketing"], "locations": ["Aberdeen"], "categories": ["Media & Advertising", "Editorial / Journalism", "Marketing / Public Relations", "Marketing - General / Support", "Digital Marketing"], "post_time": "2022-01-18T01:22:33Z", "salary": {"currency": null, "max": null, "min": null, "period": "monthly", "term": null}, "salary_visible": false, "title_keywords": [], "responsibilities": ["social media", "advertising", "budget", "monitor", "website", "presentations", "develop", "communication", "marketing plan", "evaluate", "maintain", "coordinate", "contact", "formatting", "marketing materials", "planning"], "requirements": {"degrees": ["degree"], "majors": ["marketing", "communications"], "languages": ["cantonese", "english"], "language_level": [], "hard_skills": ["excel", "google analytics", "plus", "adobe indesign", "word", "powerpoint", "dynamic", "adobe cc", "facebook"], "soft_skills": ["confident", "organizational skills", "independently", "proactive", "assertive", "interested in", "prioritize", "diverse", "dynamic", "attention to detail", "work ethic", "can-do", "creative"], "languages_combined": [{"language": "cantonese", "language_level": []}, {"language": "english", "language_level": []}]}, "experience_required": {"duration": ["minimum of one year"], "field": ["pr", "consulting", "design", "marketing", "writing", "editing"]}}, {"job_id": "100003009052227", "location_code": "hk", "company": "ORIENTAL  HUMAN RESOURCES LIMITED", "job_title": "Marketing Executive", "description": "Responsibilities\n\n\nProvide clerical and administration support to sales and marketing team\nCompile sales related reports & update advertising and promotion records\nPrepare marketing collaterals & arrange visual display\nUpdate marketing content to social media platforms\nHandle customer enquiries & maintain customer relationship program\nOther ad-hoc projects as assigned\n\nRequirements\n\n\nDiploma or above in Business related discipline\nAt least 2 years working experience in retail industry\nProficient in computer skills, particular Microsoft Excel, Adobe Photoshop and Illustrator\nGood command in both written and spoken English and Chinese\nWell-organized, detail-oriented and multi-tasking\nGood interpersonal and communication skills\nImmediate available will be an advantage\n\n\nWe offer attractive remuneration package to the right candidate.\u00a0 Interested parties, please apply by clicking \"Apply Now\".\n\nPersonal data will be used for recruitment purpose only", "employment_types": ["Full Time"], "selling_points": [], "locations": ["North Point"], "categories": ["Media & Advertising", "Others", "Marketing / Public Relations", "Marketing - General / Support", "Marketing - Marketing Communication"], "post_time": "2022-01-17T02:30:56Z", "salary": {"currency": null, "max": null, "min": null, "period": "monthly", "term": null}, "salary_visible": false, "title_keywords": ["marketing executive"], "responsibilities": ["advertising", "handle customer enquiries", "marketing collaterals", "social media platforms", "maintain", "reports", "visual", "ad-hoc projects", "administration"], "requirements": {"degrees": ["diploma or above"], "majors": ["business"], "languages": ["english", "chinese"], "language_level": ["good command"], "hard_skills": ["adobe photoshop", "computer skills", "illustrator", "microsoft excel"], "soft_skills": ["communication skills", "well-organized", "detail-oriented", "multi-tasking", "interpersonal"], "languages_combined": [{"language": "english", "language_level": ["good command"]}, {"language": "chinese", "language_level": ["good command"]}]}, "experience_required": {"duration": ["at least 2 years"], "field": ["retail industry"]}}, {"job_id": "100003009053819", "location_code": "hk", "company": "Grandmama Store Limited", "job_title": "Sales & Marketing Executive", "description": "Responsibilities:\n\nThe contract period will be until 30 June 2022\n\n1.Creating, editing, enhancing, promoting and supporting the implementations of digital contents/communication inclusive of a wide variety/broad spectrum of different media and creative promotional contents for different events and promotions taking place within the Park's existing and future social media platforms (e.g. Facebook, Instagram, YouTube, TikTok and many other popular social media platforms in Hong Kong);\n\n2.Creating and/or co-creating popular social media contents by following the latest local vibes while arousing interests of the general public of Hong Kong. Those working for this \"Creative Team of Story-telling\" should demonstrate good understandings of the Park's core values, being, Conservation & Education, and demonstrate the ability to create the relevant/heart-warming social media contents to better connect Ocean Park with the general public of Hong Kong general public, our precious guests;\n\n3.Supporting the promotion of OPC Corporate App and other creative content development initiatives all aims at better public penetrations, and more importantly public engagement\n\nRequirements\n\nFresh Graduates in any disciplines will be considered; yet candidates with Higher Diploma or above in Marketing and Digital Marketing or related disciplines will be a Plus (non-marketing major and/or candidates with lower academic qualifications will also be considered provided they can showcase their well-received past creations published on social media)\nCandidates with 1-year work experience in related field (candidates with no working experiences will be considered provided they can showcase their well-received past creations published on social media)\nSuper Creative is a MUST\nKnowledge in Photoshop and video editing software skills\nIndependent and detail minded with strong sense of responsibility\nComputer literacy in Excel, Word and Chinese Word processing\nGood command of both written and spoken English and Chinese\nFresh Graduates with strong interest in digital marketing and creative social media content development are also welcomed\n\nApplications including details of qualifications, working experience, expected salary, contact telephone number and address should be applied via:\u00a0http://careers.oceanpark.com.hk\u00a0--> Job opening --> Part time/ Short-term.\n\nApplicants not contacted within six weeks may consider their application unsuccessful. Personal data collected will be used for recruitment-related purpose only.", "employment_types": ["Full Time"], "selling_points": [], "locations": ["Kwun Tong"], "categories": ["Admin & HR", "Others", "Marketing / Public Relations", "Marketing - General / Support", "Others"], "post_time": "2022-01-17T07:34:42Z", "salary": {"currency": null, "max": null, "min": null, "period": "monthly", "term": null}, "salary_visible": false, "title_keywords": ["sales & marketing executive"], "responsibilities": ["social media", "creative content", "social media platforms", "communication", "contents", "facebook", "editing"], "requirements": {"degrees": ["higher diploma or above"], "majors": ["related disciplines", "marketing", "digital marketing"], "languages": ["english", "chinese"], "language_level": ["good command"], "hard_skills": ["excel", "no", "plus", "chinese word processing", "word", "video editing", "photoshop"], "soft_skills": ["computer literacy", "creative", "independent", "sense of responsibility"], "languages_combined": [{"language": "english", "language_level": ["good command"]}, {"language": "chinese", "language_level": ["good command"]}]}, "experience_required": {"duration": ["1-year"], "field": ["related", "social media"]}}, {"job_id": "100003009055132", "location_code": "hk", "company": "H.S.Chan Company Limited", "job_title": "Senior Marketing Executive", "description": "\n\u8077\u8cac\u63cf\u8ff0\n\u4e3b\u8981\u8077\u8cac:\n- \u5206\u6790\u884c\u92b7\u6578\u64da\u53ca\u92b7\u552e\u5831\u544a\n- \u898f\u5283\u4e26\u57f7\u884c\u7dda\u4e0a\u7dda\u4e0b\u884c\u92b7\u6d3b\u52d5\n- \u5354\u52a9\u7814\u767c\u65b0\u7522\u54c1\n- \u7ba1\u7406\u5e97\u8216\u7684\u793e\u4ea4\u5a92\u9ad4\u8cec\u865f\n- \u6eff\u8db3\u92b7\u552e\u696d\u52d9\u76ee\u6a19\n\u5165\u8077\u8981\u6c42:\n- \u51771-2\u5e74\u884c\u92b7\u76f8\u95dc\u5de5\u4f5c\u7d93\u9a57\n- \u6709\u79ae\u8c8c\u3001\u5c0d\u5de5\u4f5c\u6709\u71b1\u8aa0\n- \u5177\u7a4d\u6975\u7684\u5de5\u4f5c\u614b\u5ea6\u53ca\u8cac\u4efb\u611f\n- \u5177\u826f\u597d\u5718\u968a\u610f\u8b58\u3001\u8457\u91cd\u7d30\u7bc0\n- \u80fd\u5920\u6210\u719f\u7368\u7acb\u5b8c\u6210\u5de5\u4f5c\n- \u80fd\u540c\u6642\u8655\u7406\u591a\u9805\u4efb\u52d9,\u8655\u4e8b\u6709\u689d\u7406\n- \u64c1\u6709\u826f\u597d\u4e2d\u82f1\u8a9e\u95b1\u8b80\u80fd\u529b\n- \u5c0dDigital Marketing\u6709\u7d93\u9a57\u8005\u512a\u5148\n- \u61c2\u4f7f\u7528AI\u53ca\u526a\u7247\u62cd\u651d\u512a\u5148\n\u798f\u5229\n- \u2022 \u54e1\u5de5\u8cfc\u7269\u512a\u60e0\n- \u9280\u884c\u5047\u671f\n- \u751f\u65e5\u5047\n- \u91ab\u7642\u798f\u5229\n- \u5e74\u5c3e\u82b1\u7d05(\u8996\u4e4e\u5de5\u4f5c\u8868\u73fe)\n\u4e0a\u73ed\u5730\u9ede:\u89c0\u5858 / \u65fa\u89d2 / \u5c16\u6c99\u5480\n\u6709\u610f\u8005\u8acb\u5c07\u7c21\u5c65\u6b77\u4e36\u8fd1\u7167\u53ca\u7406\u60f3\u85aa\u91d1\u96fb\u90f5\u7d66\u6211\u5011\n\u5de5\u4f5c\u985e\u578b: \u5168\u8077, \u9577\u671f\n\u85aa\u916c: $18,000.00\u81f3$20,000.00(\u6bcf\u6708)\n\u5de5\u4f5c\u985e\u578b: \u5168\u8077, \u9577\u5de5\n\u85aa\u916c: $18,000.00\u81f3$20,000.00(\u6bcf\u6708)\n\u6642\u9593:\n\u2022 \u65e5\u73ed\n\u798f\u5229:\n\u2022 \u54e1\u5de5\u8cfc\u7269\u512a\u60e0\n\u9060\u7a0b\u5de5\u4f5c:\n\u2022 \u5426\n\n", "employment_types": ["Full Time", "Permanent"], "selling_points": [], "locations": ["Kwun Tong"], "categories": ["Marketing / Public Relations", "Marketing - Brand / Product Management", "Marketing - General / Support", "Marketing - Marketing Communication"], "post_time": "2022-01-18T01:19:16Z", "salary": {"currency": null, "max": null, "min": null, "period": "monthly", "term": null}, "salary_visible": false, "title_keywords": ["senior marketing executive"], "responsibilities": [], "requirements": {"degrees": [], "majors": [], "languages": [], "language_level": [], "hard_skills": [], "soft_skills": [], "languages_combined": []}, "experience_required": {"duration": [], "field": []}}, {"job_id": "100003009052610", "location_code": "hk", "company": "Million (Far East) Limited", "job_title": "Senior Marketing Executive", "description": "Your role\n\nTo assist Process Planning Manager in strategy implementation on various eCS platforms\nTo coordinate with internal teams (i.e. Marketing, Legal, IT, etc.) to plan and execute enhancements on the eCS platforms\nTo conduct user acceptance test (UAT) before actual roll-out\nTo perform quality checks on the e-platforms and compile weekly analytical reports for management review\nTo coordinate and execute various promotion items (i.e. posters, online banners, etc.) and activities (i.e. lucky draw, Facebook activities, etc.) for stimulating registration and usage of the eCS platforms\n\nTo succeed in this role\n\nDegree or diploma in Marketing / Business Administration / Information System or related disciplines\nPreferably with at least 1-year working experience in telecom industry\nProficient in Adobe Photoshop and MS Office applications will be an advantage\nGood interpersonal and communication skills\nDetail-oriented and able to work independently under tight schedule\nGood command of verbal and written communication, in both English and Chinese\nFresh graduates will also be considered", "employment_types": ["Full Time", "Permanent"], "selling_points": ["Senior Marketing Executive", "Food & Beverage", "Exp. in HORECA, Frozen Meat business preferred"], "locations": ["Kwai Fong"], "categories": ["Marketing / Public Relations", "Marketing - Brand / Product Management", "Marketing - General / Support", "Marketing - Market Research"], "post_time": "2022-01-17T03:32:26Z", "salary": {"currency": null, "max": null, "min": null, "period": "monthly", "term": null}, "salary_visible": false, "title_keywords": ["senior marketing executive"], "responsibilities": ["administration", "uat", "teams", "coordinate with", "implementation", "quality", "coordinate", "banners", "communication", "reports", "schedule", "plan", "facebook", "management review", "planning"], "requirements": {"degrees": ["diploma", "degree"], "majors": ["related disciplines", "marketing", "business administration"], "languages": ["english", "chinese"], "language_level": ["good command"], "hard_skills": ["facebook", "adobe photoshop", "information system", "ms office"], "soft_skills": ["communication skills", "work independently", "detail-oriented", "communication", "interpersonal"], "languages_combined": [{"language": "english", "language_level": ["good command"]}, {"language": "chinese", "language_level": ["good command"]}]}, "experience_required": {"duration": ["at least 1-year"], "field": []}}, {"job_id": "100003009055054", "location_code": "hk", "company": "Amoy Food Ltd", "job_title": "Senior Marketing Executive", "description": "You can enjoy:\u00a0\n\nComprehensive Medical and Life Insurance coverage, including your spouse and children\nExclusive company pension schemes\nMarriage, Maternity and Paternity Leave\nExclusive shopping discount, Bazaar Sales for our people only\nProfessional training and career advancement opportunities\nConvenient office location, less than 5 min. walk from MTR\nContemporary workplace with Onsite Clinic, Lactation Rooms, free drinks and chill out areas\nWell-equipped Gym inside our office building, plus fitness and interest class packages\nFree round-trip lunchtime shuttle bus services to Shatin\n\nResponsibilities:\n\nDevelop and execute marketing campaigns, promotion activities and events on both offline and online channels\nCoordinate with internal and external parties on instore POSM, TVC or other promotion materials\nLiaise with media and agencies for media planning\nManage A&P budget and effectiveness of advertising and promotions campaigns\nHandle any ad hoc projects / tasks as assigned\n\nRequirements:\n\nBachelor degree in Marketing or business-related disciplines\nMinimum 4 years related experience, preferably in FMCG industry\nDynamic, creative to cope with fast-paced working environment and able to work under pressure\nGood communication and interpersonal skills\nProficient in both written and spoken English and Chinese\nCandidate with less experience can be considered as Marketing Executive\n\nAn attractive salary and benefit package will be offered. Interested parties please forward detailed resume stating expected salary to: People Department, PARKnSHOP (HK) Limited, Watson House, 1-5 Wo Liu Hang Road, Fo Tan, N.T. or email to us or click \u201cApply Now\u201d.\n\nWe are an equal opportunity employer and welcome applications from all qualified candidates. The information provided will be treated in strict confidence and be used only for consideration of your application for relevant / similar posts within the A.S. Watson Group. All personal data of unsuccessful applicants will be destroyed within 12 months from the date of application.", "employment_types": ["Full Time", "Permanent"], "selling_points": ["Plan and drive marketing activities", "3-4 years\u2019 relevant experience in FMCG", "5-day week, Shuttle bus, Double pay, Bonus etc."], "locations": ["Tai Po Area"], "categories": ["Marketing / Public Relations", "Marketing - General / Support", "Marketing - Market Research", "Digital Marketing"], "post_time": "2022-01-18T00:58:24Z", "salary": {"currency": null, "max": null, "min": null, "period": "monthly", "term": null}, "salary_visible": false, "title_keywords": ["senior marketing executive"], "responsibilities": ["online channels", "advertising", "internal and external parties", "coordinate with", "budget", "develop", "ad hoc projects", "marketing campaigns", "liaise with", "planning"], "requirements": {"degrees": ["degree", "bachelor"], "majors": ["business", "related disciplines", "marketing"], "languages": ["english", "chinese"], "language_level": ["proficient"], "hard_skills": ["dynamic", "fmcg industry"], "soft_skills": ["dynamic", "creative", "communication and interpersonal skills", "work under pressure"], "languages_combined": [{"language": "english", "language_level": ["proficient"]}, {"language": "chinese", "language_level": ["proficient"]}]}, "experience_required": {"duration": ["minimum 4 years"], "field": ["related", "fmcg", "marketing"]}}, {"job_id": "100003009052533", "location_code": "hk", "company": "ADECCO", "job_title": "Assistant Marketing Coordinator $13K-15K", "description": "Responsibilities :\n\nDevelop & implement marketing programs for different retail channels\nPlan sales & promotion budget\nCoordinate / Liaise with Principals for marketing supports\nControl & Monitor the progress of marketing programs\nSupport the execution of online marketing activities in Facebook\nProvide POP support to individual sales channel when necessary\nPurchase planning and inventory control\n\nRequirements :\n\nUniversity graduate with strong interpersonal skills\nProficiency in both written and spoken English and Chinese\nSkillful in PowerPoint / Excel / Word and Chinese Word Processing\nKnowledge of Photoshop, Illustration will be a plus\nResponsive to market changes and having innovative ideas\n\nAppreciate to work with people from different teams\nDetail-oriented and with ability to handle jobs independently\nSolid working experience in Retail / FMCG marketing is preferred\n\nBenefits :\n\n5-day work per week\nDiscretionary bonus\n10 days annual leave, bank holiday and birthday leave\nMedical insurance\nMPF\nStaff purchase discount\n\n\nInterested parties, please send C.V. with expected salary to H.S. Chan Co. Ltd., 7/F, H. S.Chan Building, 4 Hung To Road, Kwun Tong, Kowloon with attention to Ms Rosan Li or by clicking \"Apply Now\"\n\nPersonal data collected will be used for recruitment related purpose only.", "employment_types": ["Full Time", "Contract"], "selling_points": [], "locations": ["Shatin Area"], "categories": ["Marketing / Public Relations", "Marketing - Brand / Product Management", "Marketing - General / Support", "Others"], "post_time": "2022-01-17T03:21:16Z", "salary": {"currency": null, "max": null, "min": null, "period": "monthly", "term": null}, "salary_visible": false, "title_keywords": ["marketing coordinator", "assistant"], "responsibilities": ["control", "budget", "monitor", "develop", "coordinate", "purchase", "inventory control", "plan", "liaise with", "facebook", "planning"], "requirements": {"degrees": ["university graduate"], "majors": [], "languages": ["english", "chinese"], "language_level": ["proficiency"], "hard_skills": ["excel", "plus", "chinese word processing", "word", "powerpoint", "illustration", "photoshop"], "soft_skills": ["independently", "detail-oriented", "interpersonal skills", "innovative", "responsive"], "languages_combined": [{"language": "english", "language_level": ["proficiency"]}, {"language": "chinese", "language_level": ["proficiency"]}]}, "experience_required": {"duration": [], "field": ["retail", "marketing", "fmcg"]}}, {"job_id": "100003009054026", "location_code": "hk", "company": "Ponder Deep Limited", "job_title": "Customer Service / Digital Marketing Assistant - Startup", "description": "Responsibilities:\n\nCollect market intelligence in terms of market trend and product performance for strategic marketing planning\nPlan and drive marketing activities to achieve business targets, and evaluate the effectiveness of the activities\nWork closely with internal and external parties to develop ATL & BTL campaigns\nImplement social media strategy, develop social content, handle online promotion & management\nCompile regular reports and participate in ad hoc assignments and projects\n\n\u00a0Requirements:\n\nUniversity degree in Marketing or related discipline\n3-4 years\u2019 relevant experience in FMCG / retail industry/ advertising (Fresh\u00a0graduate will also be\u00a0considered)\u00a0\u00a0\nProactive, detail-oriented and willing to work under pressure and take up new challenges\nGood business sense, logical mind-set with good communication and project management skills, and ability to handle multiple tasks and meet tight deadlines\nProficiency in both written and spoken English and Chinese, as well as computer applications, particularly MS Excel, Powerpoint and Chinese Word Processing\nImmediate available is preferable\nCandidates with less experience will be considered as Marketing Executive\n\nWe offer 5-day work, double pay, year-end discretionary bonus, and excellent career development opportunities to the right candidate.\u00a0 Interested parties please send your resume with current & expected salary and date of availability by clicking \u201cApply Now\u201d.\u00a0 For enquiries, please contact our Recruitment Whatsapp Hotline at 55458814.\u00a0 For more details, please visit www.amoy.com.\n\nAll applications will be treated in strict confidence and retained for 6 months for recruitment purposes only.\u00a0\n\n\n", "employment_types": ["Full Time", "Permanent"], "selling_points": ["A startup in rapid growth stages", "Fast growing new industry", "Working together with the founding core team"], "locations": ["Kwun Tong"], "categories": ["Sales, CS & Business Devpt", "Customer Service - Supervisor / Officer", "Marketing / Public Relations", "Marketing - General / Support"], "post_time": "2022-01-17T08:07:54Z", "salary": {"currency": null, "max": null, "min": null, "period": "monthly", "term": null}, "salary_visible": false, "title_keywords": ["customer service", "digital marketing", "assistant"], "responsibilities": ["strategic marketing planning", "social media", "management", "internal and external parties", "develop", "evaluate", "reports", "ad hoc assignments", "plan", "online promotion"], "requirements": {"degrees": ["university degree", "fresh graduate"], "majors": ["marketing"], "languages": ["english", "chinese"], "language_level": ["proficiency"], "hard_skills": ["project management", "ms excel", "chinese word processing", "powerpoint"], "soft_skills": ["meet tight deadlines", "business sense", "project management skills", "detail-oriented", "communication", "handle multiple tasks", "proactive", "work under pressure"], "languages_combined": [{"language": "english", "language_level": ["proficiency"]}, {"language": "chinese", "language_level": ["proficiency"]}]}, "experience_required": {"duration": ["3-4 years"], "field": ["retail industry", "fmcg", "advertising", "marketing", "relevant experience"]}}, {"job_id": "100003009053883", "location_code": "hk", "company": "Thinking Group Holding Limited", "job_title": "Marketing Executive", "description": "Customer Service / Digital Marketing Assistant - Startup\n\nAbout Us\n\nWe are a growing startup in online education. We run a platform that enables teachers and students to learn anywhere, anytime live in our virtual classroom. Our mission is to make skills learning more accessible, more affordable and more effective to everyone.\n\nWe\u2019re looking for a digital assistant marketing person to join our team. This position will be responsible for developing and executing marketing task to grow the user base of our platform.\n\nJob Highlights\n\n\n\nMulti tasking role\nNew and Existing customer acquisition and relationship management\nWith 1-2 years' experience in customer services\nRecommend appropriate courses to new and existing customers\nNew and existing teachers\u2019 review, recruitment and orientation\nAdministrative tasks\nSupporting various marketing projects\u00a0\nJob Description\n\n\nResponsibilities:\n\nUndertake daily administrative tasks including handling enquiries / complaints (Whatsapp/ Social Media / Phone calls)\nSupporting role in organizing various marketing projects\nAssist in the development of digital marketing, social media strategies, new customer acquisition; including SEO / SEM, planning and overseeing of social media campaigns\nIdentify trends and insights, and optimise spend and performance based on the insights\nMeasure and report performance of all implemented digital marketing campaigns\nKeeping up to date with the latest trends and best practices in online marketing and measurement\nSupport the creation of publication contents, ensure digital media contents is up to date, deliver consistent messages, proper usage of the RMHC trademarks and is measured against clear KPIs\nAd hoc duties per assigned including answering online enquiries; new and Existing customer acquisition and relationship management\nDevelop and understanding and knowledge of existing courses to make appropriate courses recommendations\u00a0 to new and existing customers\nNew and existing teachers\u2019 review, recruitment and orientation\nBrainstorm new and creative growth strategies\nRequirements:\u00a0\n\n\nDiploma / Degree holder\n1-2 years of marketing or e-commerce experience is an advantage\nKnowledge in digital marketing, e-commerce and emerging digital technology, social trends and insights preferable\nExcellent spoken and written skills in English and Chinese (Cantonese and Mandarin)\nOrganized, flexible, be able to deal with multiple projects & meet tight deadlines\nHands on experience in digital analytic tools, managing digital content, email, SMS, CRM and social marketing an advantage\nSomeone with understands the energy and passion needed of any successful startup team\n\nAs a startup in rapid growth stages, we offer excellent career development opportunities to unleash your potential, overseas posting and competitive remuneration package.\n\nInterested parties please apply with your full resume stating present and expected salary by clicking \"Apply Now\".\u00a0 Only short-listed candidates will be contacted.", "employment_types": ["Full Time", "Permanent"], "selling_points": ["1-2 years experience with marketing / social media", "Knowledge of Google ads., Copy writing, Social Med", "Familar with audio products is an advantage"], "locations": ["Kwun Tong"], "categories": ["Marketing / Public Relations", "Marketing - General / Support", "Marketing - Marketing Communication", "Digital Marketing"], "post_time": "2022-01-17T08:51:49Z", "salary": {"currency": null, "max": null, "min": null, "period": "monthly", "term": null}, "salary_visible": false, "title_keywords": ["marketing executive"], "responsibilities": ["phone calls", "ad hoc duties", "social media campaigns", "digital marketing campaigns", "measurement", "develop", "kpis", "publication", "report", "social media", "management", "seo", "review", "marketing projects", "digital marketing", "contents", "administrative tasks", "recruitment", "sem", "social media strategies", "planning"], "requirements": {"degrees": ["diploma", "degree holder"], "majors": [], "languages": ["cantonese", "english", "chinese", "mandarin"], "language_level": ["excellent"], "hard_skills": ["rapid", "e-commerce"], "soft_skills": ["flexible", "organized", "meet tight deadlines", "hands on"], "languages_combined": [{"language": "cantonese", "language_level": ["excellent"]}, {"language": "english", "language_level": ["excellent"]}, {"language": "chinese", "language_level": ["excellent"]}, {"language": "mandarin", "language_level": ["excellent"]}]}, "experience_required": {"duration": ["1-2 years"], "field": ["digital", "marketing", "digital content", "e-commerce"]}}, {"job_id": "100003009053589", "location_code": "hk", "company": "Guidepoint Global Hong Kong Limited", "job_title": "Regional Marketing Coordinator", "description": "Responsibilities:\n\n\n\nManage and create content for online platforms (e.g. Website, Social Media, display advertising and digital campaigns) to achieve marketing objectives and to enable smooth collaborations\nAssist in developing overall corporate branding and marketing strategy\nExplore creative promotion and events to generate brand awareness\nDevelop digital marketing strategies and campaigns to achieve traffic and business goals\nAnalyze data, trends and insights to fully optimize all digital platforms.\nCoordinate with internal teams to plan, organize, and execute various marketing events or campaigns\nAssist in ad hoc marketing and event management tasks\n\nRequirements:\n\n\n\nDegree holder in Marketing, Business or related disciplines\nAround 1-2 years of relevant experience, knowledge in GA, SEO is definitely an advantage\nStrong communication and presentation skills\nExcellent in handling and follow up on details, take initiative, independent & responsible\nFluent in both written and spoken English, Cantonese and Mandarin\nExcellent English (in both written & spoken) + communication & copywriting skills\nProficiency in marketing automation technology\nAble to execute email marketing strategies\nFamiliarity with analytical and database tools\n\nWorking location:\u00a0Kwai Chung\n\nStaff Benefit:\n\nDiscretionary Bonus\nMedical & Life Insurance\nAnnual Leave\nPayable Sick Leave\nEncourage continuing education and on-job training\nOpen office working environment\nOffer promotion opportunities and long-term career path\u00a0\n\nWe offer a competitive remuneration package to the right candidate.\u00a0Interested parties\u00a0please click\u00a0\"Apply Now\"\u00a0to submit your application\u00a0or by email to\u00a0hr1 @twcoffee.com\n\n\u00a0(All personal data provided by applicants will be treated in strict confidence and used for employment-related purpose only.)\n\nAdditional Information", "employment_types": ["Full Time"], "selling_points": [], "locations": ["Not Specified"], "categories": ["Admin & HR", "Others", "Marketing / Public Relations", "Marketing - General / Support", "Others"], "post_time": "2022-01-17T07:12:46Z", "salary": {"currency": null, "max": null, "min": null, "period": "monthly", "term": null}, "salary_visible": false, "title_keywords": ["marketing coordinator"], "responsibilities": ["social media", "business goals", "marketing events", "advertising", "digital marketing strategies", "ad hoc", "management", "coordinate with", "website", "developing", "develop", "teams", "digital campaigns", "plan", "analyze data"], "requirements": {"degrees": ["degree holder"], "majors": ["business", "related disciplines", "marketing"], "languages": ["cantonese", "english", "mandarin"], "language_level": ["excellent", "fluent"], "hard_skills": ["seo"], "soft_skills": ["independent", "responsible", "communication", "presentation skills", "initiative"], "languages_combined": [{"language": "cantonese", "language_level": ["fluent"]}, {"language": "english", "language_level": ["excellent", "fluent"]}, {"language": "mandarin", "language_level": ["excellent", "fluent"]}]}, "experience_required": {"duration": ["1-2 years"], "field": ["relevant experience"]}}, {"job_id": "100003009052273", "location_code": "hk", "company": "Lubuds F&B Group", "job_title": "Marketing Executive", "description": "Thinking Group, a sole distributor of Audio products & Smart Gadget products including: Ultimate Ears (UE), JBL/ Harman Kardon, Aftershokz, Ticwatch ....etc. Founded in 1998, its headquarters in HK and branches in Shenzhen & Taiwan. To cope with our continuous expansion, we are seeking qualified candidates to join us.\n\nResponsibilities:\n\n\nManage and update corporate marketing materials (e.g. company website, brochures, newsletter, etc.)\nWorking with social media platform content update and content writing\nFamiliar with shopline\nDevelop, execute and track Social Media platforms promotional campaigns\nMonitor competitors\u2019 marketing campaign and prepare competitive analysis\nComfortable in small business model and fast changing environment\nManage and communicate with KOL\nConducting market analysis to identify the target audience\nAssist in ad-hoc projects and administrative tasks\n\nRequirements:\n\n\nProactive, Self-motivated, independent and result driven\nA minimum of 1-2 years experience with marketing or social media related knowledge\nGood presentation and communication skills (both spoken and written English & Cantonese) liaise with both internal and external parties on developing and producing marketing materials\nGood team player\nKnowledge of Google ads., Copy writing, Social Media\nKnowledge of Ad network (e.g. Google ads, facebook.......)\nFamilar with audio products is an advantage\nFresh graduate are welcome as Marketing assistant\n\nBenefits:\n\n5 Days work\u00a0\nAnnual leave and Sick leave\nBank holiday and Birthday leave\u00a0\nMedical and Dental allowance", "employment_types": ["Full Time", "Permanent"], "selling_points": [], "locations": ["Aberdeen"], "categories": ["Marketing / Public Relations", "Marketing - General / Support", "Marketing - Marketing Communication", "Public Relations - General / Support"], "post_time": "2022-01-17T02:37:34Z", "salary": {"currency": null, "max": null, "min": null, "period": "monthly", "term": null}, "salary_visible": false, "title_keywords": ["marketing executive"], "responsibilities": ["communicate with", "social media", "analysis", "social media platforms", "monitor", "develop", "market analysis", "marketing materials", "ad-hoc projects", "administrative tasks", "company website"], "requirements": {"degrees": ["fresh graduate"], "majors": ["marketing"], "languages": ["cantonese", "english"], "language_level": ["good"], "hard_skills": ["facebook"], "soft_skills": ["communication skills", "self-motivated", "good team player", "independent", "driven", "proactive", "presentation"], "languages_combined": [{"language": "cantonese", "language_level": ["good"]}, {"language": "english", "language_level": ["good"]}]}, "experience_required": {"duration": ["minimum of 1-2 years"], "field": ["related", "social media", "marketing"]}}, {"job_id": "100003009053034", "location_code": "hk", "company": "PS Group International Ltd", "job_title": "Marketing Executive - Group & Beauty Services Division **URGENT**", "description": "\nThis position can be based in Hong Kong or Singapore.\nOverview:\nGuidepoint\u2019s growing Marketing team is responsible for building and expanding the Guidepoint brand. As the storytellers of Guidepoint, the Marketing team executes marketing plans that generate leads, nurture existing clients, and raise overall brand awareness within our 3 main audiences; clients, advisors and employees.\nThe Regional Marketing Coordinator works as part of a regional and global Marketing team to execute marketing and communications initiatives for our offices across the APAC Region, including Hong Kong, Shanghai, Singapore, Mumbai, Sydney, Tokyo and Seoul.\nWhat You\u2019ll Do:\n\u2022 Work closely with the Regional Marketing Manager to plan and execute a marketing, communications and PR strategy to grow brand awareness and boost our business in offices across the APAC region.\n\u2022 Coordinate with the global Marketing and Design teams to run integrated programs including content marketing, thought leadership, lead generation, and digital and social media\n\u2022 Create and market press releases to key social and traditional media outlets relevant to our client base\n\u2022 Support the organization of engaging client events\n\u2022 Develop targeted email campaigns in coordination with the Sales and Client Service teams\n\u2022 Further develop existing sales collateral, marketing materials and client presentations\nWhat You Have:\nBachelor's degree required (Marketing, Communications, English, and/or Business major a plus)\n\u2022 1-3 years\u2019 experience in global B2B marketing, PR and/or communications with experience in digital marketing\n\u2022 A desire to work in a fast-paced, entrepreneurial environment\u2014willing to build up this broad-ranged function and to contribute to the continued success of Guidepoint\n\u2022 A consultative approach with a strategic vision and sense for innovative marketing solutions\n\u2022 Demonstrated skills, knowledge and experience in the execution of creative marketing, including direct mail, email marketing, and full-scale campaigns\n\u2022 Must have both solid writing & interpersonal skills; aptitude for numbers\n\u2022 Working knowledge of Adobe Creative Cloud, Salesforce, and Pardot recommended\n\u2022 Fluency in English and Chinese is essential; knowledge of an additional Asian language such as Japanese or Korean is a plus\nWhat We Have:\n\u2022 Competitive compensation\n\u2022 Entrepreneurial environment, autonomy and fast decisions\n\u2022 Casual work environment and compelling people\n\u2022 Flexible work arrangement\n\u2022 Centrally located office\nInterested parties please click Apply Now to apply job.\n\n", "employment_types": ["Full Time"], "selling_points": ["Beauty Group", "Participate in all rounded marketing campaigns", "5 day Week"], "locations": ["North Point"], "categories": ["Marketing / Public Relations", "Marketing - General / Support"], "post_time": "2022-01-17T05:16:01Z", "salary": {"currency": null, "max": null, "min": null, "period": "monthly", "term": null}, "salary_visible": false, "title_keywords": ["marketing executive"], "responsibilities": ["social media", "communications with", "marketing plans", "coordination with", "teams", "coordinate with", "design", "develop", "presentations", "client base", "digital marketing", "plan", "marketing materials"], "requirements": {"degrees": ["degree", "bachelor"], "majors": ["business", "marketing", "communications"], "languages": ["japanese", "english", "chinese", "korean"], "language_level": ["fluency"], "hard_skills": ["plus", "adobe", "salesforce", "presentations"], "soft_skills": ["flexible", "creative", "responsible", "interpersonal skills", "coordination", "innovative", "leadership"], "languages_combined": [{"language": "japanese", "language_level": []}, {"language": "english", "language_level": ["fluency"]}, {"language": "chinese", "language_level": ["fluency"]}, {"language": "korean", "language_level": []}]}, "experience_required": {"duration": ["1-3 years"], "field": ["pr", "marketing", "digital marketing"]}}, {"job_id": "100003009052433", "location_code": "hk", "company": "Carlsberg Brewery H K Ltd", "job_title": "Channel Marketing Executive (Off-Trade)", "description": "Responsibilities:-\n\nAssist in implement marketing plan to drive business and build corporate and brand image for the Group & Beauty Division including the retail services brand of \"PRIVATE i Skincare Centre\" and \"Naillian\".\nPlan, develop, implement and evaluate marketing programs / sales driving campaigns to acquire new customers and achieve sales target\nPlan and execute all web, social media platform and other online marketing activities\nConduct business analysis to monitor and evaluate the effectiveness of marketing campaign\nSource and liaise with business partners for joint promotions, provide market intelligence and carry out market researches\nProvide ad-hoc and day-to-day marketing support for the Group cross team promotion\nRequirements:-\n\nDiploma / Bachelor Degree in Marketing, Communication, Business or related discipline\nMinimum of 2 years relevant marketing experience in service or retail industry, especially in skincare & beauty industry is a definite advantage\nGood understanding in digital marketing, e.g, SEO, SEM, Facebook, IG etc. will be an advantage\nA good team-player, possessing excellent interpersonal, organization & communication skills\nA good thinker with sharp business acumen and possesses strong planning, and analytical skills\nHighly committed and is eager to drive forward initiatives and achieving results\nExcellent command of both written and spoken English and Chinese\nImmediate available is highly preferred", "employment_types": ["Full Time", "Permanent"], "selling_points": ["Ensure channel marketing campaigns are executed", "Market insight to support business growth", "Analyze the ROI of the marketing activities"], "locations": ["Hung Hom"], "categories": ["Marketing / Public Relations", "Marketing - Brand / Product Management", "Marketing - General / Support", "Marketing - Market Research"], "post_time": "2022-01-17T03:00:50Z", "salary": {"currency": null, "max": null, "min": null, "period": "monthly", "term": null}, "salary_visible": false, "title_keywords": ["marketing executive"], "responsibilities": ["ad-hoc", "social media", "sales target", "monitor", "develop", "evaluate", "marketing plan", "liaise with", "plan", "business analysis"], "requirements": {"degrees": ["diploma", "degree", "bachelor"], "majors": ["business", "marketing"], "languages": ["english", "chinese"], "language_level": ["excellent"], "hard_skills": ["seo", "analytical skills", "sem", "facebook", "acumen"], "soft_skills": ["communication skills", "team-player", "analytical skills", "communication", "committed", "business acumen", "interpersonal"], "languages_combined": [{"language": "english", "language_level": ["excellent"]}, {"language": "chinese", "language_level": ["excellent"]}]}, "experience_required": {"duration": ["minimum of 2 years"], "field": ["retail industry", "beauty industry", "marketing"]}}, {"job_id": "100003009055112", "location_code": "hk", "company": "Autotoll Limited", "job_title": "Marketing and Communications Officer (PR/ Promotion focus)", "description": "Responsibilities:\u00a0\u00a0\nResponsible and optimization of overseas advertisement channels such as Google, Facebook and Instagram\nSolid experience with social media including blogs, Instagram, Facebook, etc.\nProvide and execute marketing plans including strategy, budget, goals of the project launches\nManager all-rounded marketing and promotion campaigns covering (both online & offline promotions, e-marketing, social media campaign, website updates and consumer experience enhancement)\nOrganize product seeding among celebrities, KOL, media, influencers\nResearch and monitor the strategies of competitors and adjust project plan\nManage brand positioning and product design, online activities planning and promotion for the platforms\n\nRequirements:\n\nDegree or above in Business, Advertising, Marketing, Communications, E-commerce, Project Management, PR or related discipline;\n3 years or above solid experience in marketing / project management\nGood knowledge or experience in HTML, Search Engine Marketing and SEO is an advantage\nKnowledge in\u00a0Google Analytics/ Google Ads/ Facebook Ads Manager tools is a must - Proficient in spoken and written English and Chinese\nEnergetic, self-motivated, detail-oriented, passionate,\u00a0results-oriented and able to work under pressure\nGreat communication and management skills\n\nInterested Candidates,\u00a0please send your\u00a0full resume with your recent photo,\u00a0current & expected salary\u00a0by e-mail to\u00a0hr @moderndentallab.com.\nAll personal data collected will be used for recruitment and employment related purpose only.", "employment_types": ["Full Time", "Permanent"], "selling_points": ["Degree holder with 2 year + exp.", "Knowledge/ experience in automotive industry", "5-day work, bank holiday, AL & medical plan"], "locations": ["Kowloon Bay"], "categories": ["Marketing / Public Relations", "Marketing - General / Support", "Public Relations - General / Support", "Others"], "post_time": "2022-01-18T01:15:16Z", "salary": {"currency": null, "max": null, "min": null, "period": "monthly", "term": null}, "salary_visible": false, "title_keywords": ["communications officer"], "responsibilities": ["social media", "marketing plans", "budget", "monitor", "website", "project plan", "promotion campaigns", "product design", "facebook", "planning"], "requirements": {"degrees": ["degree or above"], "majors": ["e-commerce", "project management", "business", "marketing", "communications"], "languages": ["english", "chinese"], "language_level": ["proficient"], "hard_skills": ["google analytics", "seo", "e-commerce", "html", "project management", "facebook"], "soft_skills": ["passionate", "self-motivated", "detail-oriented", "communication", "project management", "energetic", "work under pressure"], "languages_combined": [{"language": "english", "language_level": ["proficient"]}, {"language": "chinese", "language_level": ["proficient"]}]}, "experience_required": {"duration": ["3 years"], "field": ["project management", "marketing"]}}, {"job_id": "100003009043208", "location_code": "hk", "company": "Hutchison Property Group Limited", "job_title": "ASSISTANT MARKETING OFFICER [Ref. AMO-HK]", "description": "About The Role:\n\nAssist the team in planning, monitoring and implementing all marketing-related campaigns for a newly granted Government contract, including but not limited to brand building campaign, publicity and public relations activities.\nPrepare marketing reports, analysis, proposals & presentations for internal & external parties.\nWrite, edit and disseminate a variety of communications including press releases, App & website content, newsletter, social media and online feeds.\nHandle the public enquiries and complaints from stakeholders.\nWork with PR agencies in the planning and execution of public engagement activities, including but not limited to press conferences, seminars, roadshows etc. or\nWork with creative or digital agencies/ designers in the production of marketing materials and social content, including but not limited to video, copywriting, sound bite, print/ digital ads, poster, flyer etc. AND Development of digital campaign for the new acquisition\n\nAbout You:\n\nBachelor\u00a0Degree in Marketing, Communication, Public Relations or related disciplines.\nAt least 2 years\u2019 relevant work experience preferably in the fields of marketing communications / public relations / advertising/ digital marketing.\nProactive, independent with excellent time management skills and ability to work under pressure.\nGood proficiency both in written and spoken English and Chinese.\nKnowledge/ experience in automotive industry is a plus.\u00a0\n\nWhat you can get from us:\n\nOn-the-job training, learning and development provided\nExecutive workshops, interest class, corporate purchase discount offered by SHKP\nCompetitive salary and annual leaves\nFlexible working opportunities\n\nInterested parties, please send full resume with\u00a0expected salary\u00a0and\u00a0available date\u00a0to Human Resources and Administration Department by e-mail or by fax 2111 9459.\n\n(Data collected will be used for recruitment purpose only.)", "employment_types": ["Full Time", "Permanent"], "selling_points": ["Degree holder", "1-2 years' experience", "To handle daily leasing activities"], "locations": ["Hung Hom"], "categories": ["Marketing / Public Relations", "Marketing - General / Support", "Marketing - Market Research", "Property / Real Estate", "Property Consultancy"], "post_time": "2022-01-17T11:24:48Z", "salary": {"currency": null, "max": null, "min": null, "period": null, "term": null}, "salary_visible": false, "title_keywords": ["assistant marketing officer"], "responsibilities": ["social media", "management", "advertising", "work under pressure", "analysis", "monitoring", "external parties", "website", "presentations", "communication", "conferences", "purchase", "reports", "digital marketing", "marketing materials", "planning"], "requirements": {"degrees": ["degree", "bachelor"], "majors": ["related disciplines", "marketing"], "languages": ["english", "chinese"], "language_level": ["proficiency", "good"], "hard_skills": ["workshops", "analysis", "presentations", "plus"], "soft_skills": ["flexible", "proactive", "independent", "time management skills", "communication", "learning", "creative", "work under pressure"], "languages_combined": [{"language": "english", "language_level": ["proficiency", "good"]}, {"language": "chinese", "language_level": ["proficiency", "good"]}]}, "experience_required": {"duration": ["at least 2 years"], "field": ["automotive industry", "public relations", "advertising", "marketing communications", "digital marketing"]}}, {"job_id": "100003009052056", "location_code": "hk", "company": "CR Care Company Limited", "job_title": "Marketing Executive - CRM", "description": "Job Descriptions: \u00a0\n\nHandle customers' enquiries, provide product information;\nFollow customers' developments and provide advices;\nArrange customer-visit and build up relationship;\u00a0\nPrepare sales reports, analysis and sales forecast;\nAssist managers in various kinds of sales-related programs;\nAssist in ad hoc duties as assigned, i.e. market research, survey, etc.;\nProvide supporting in marketing activities and events\n\nRequirements\uff1a\n\nDegree holder is preferred;\nOversea University graduate or above\u00a0is welcome;\nMinimum 1 year working experience preferred;\nGood communication skills with analytical mind;\nA self-confident, customer-oriented, outgoing energetic team player with good learning attitude are preferred;\nGood command of spoken and written English & Chinese (Cantonese and Mandarin);\n\n\u00a0We Offer:\n\n5 days work\u00a0\nGuaranteed Basic\u00a0Income + Monthly Bonus + Year-end Bonus\nA fast-paced environment where continuous learning keeps us competitive\nFlexible healthcare packages, including hospitalisation and outpatient benefits\n\nWe offer competitive remuneration and benefits, holidays, stable working environment to the right candidates. Interested parties please click \"Apply\u00a0Now\" and send your\u00a0full resume\u00a0with expected salary\u00a0to\u00a0us.\n\n*All personal data collected will be kept strictly confidential and used for recruitment-related purpose only.", "employment_types": ["Full Time"], "selling_points": [], "locations": ["Shatin Area"], "categories": ["Marketing / Public Relations", "Marketing - General / Support"], "post_time": "2022-01-17T01:59:09Z", "salary": {"currency": null, "max": null, "min": null, "period": "monthly", "term": null}, "salary_visible": false, "title_keywords": ["marketing executive"], "responsibilities": ["ad hoc duties", "provide advices", "analysis", "prepare sales", "market research", "assist managers", "reports", "forecast"], "requirements": {"degrees": ["university graduate or above", "degree holder"], "majors": [], "languages": ["cantonese", "english", "chinese", "mandarin"], "language_level": ["good command"], "hard_skills": [], "soft_skills": ["confident", "communication skills", "outgoing", "customer-oriented", "analytical mind", "learning", "team player", "energetic"], "languages_combined": [{"language": "cantonese", "language_level": ["good command"]}, {"language": "english", "language_level": ["good command"]}, {"language": "chinese", "language_level": ["good command"]}, {"language": "mandarin", "language_level": ["good command"]}]}, "experience_required": {"duration": ["minimum 1 year"], "field": []}}, {"job_id": "100003009052573", "location_code": "hk", "company": "Trade Connects (Asia) Company", "job_title": "Marketing & Branding Assistant", "description": "Job Description and responsibilities:\n\n\u00a0\u00a0\u00a0\u00a0\u00a0\u00a0 Manage and monitor the company\u2019s official website, Facebook, Instagram etc\n\u00a0\u00a0\u00a0\u00a0\u00a0\u00a0 Design contents of social media performs\n\u00a0\u00a0\u00a0\u00a0\u00a0\u00a0 Devise marketing strategies and execute marketing plans\n\u00a0\u00a0\u00a0\u00a0\u00a0\u00a0 Coordinate with online marketing agencies and website developers\n\u00a0\u00a0\u00a0\u00a0\u00a0\u00a0 Assist the operation team in daily operation\n\u00a0\u00a0\u00a0\u00a0\u00a0\u00a0 Data entry and filing\n\u00a0\u00a0\u00a0\u00a0\u00a0\u00a0 Assist ad hoc projects and perform other duties as assigned\n\nRequirements:\n\n\u00a0\u00a0\u00a0\u00a0\u00a0\u00a0 Relevant experience in sales and marketing\n\u00a0\u00a0\u00a0\u00a0\u00a0\u00a0 Written and verbal communication skills in Chinese & English\n\u00a0\u00a0\u00a0\u00a0\u00a0\u00a0 Proficiency with MS Word, Excel, PowerPoint, Photoshop and Chinese Word\u00a0 \u00a0 \u00a0 \u00a0 \u00a0 \u00a0 \u00a0 \u00a0 \u00a0Processing\n\u00a0\u00a0\u00a0\u00a0\u00a0\u00a0 Experience in handling different social media accounts\n\u00a0\u00a0\u00a0\u00a0\u00a0\u00a0 Creative and good communication skills", "employment_types": ["Full Time", "Permanent"], "selling_points": [], "locations": ["Not Specified"], "categories": ["Admin & HR", "Clerical / Admin Staff", "Marketing / Public Relations", "Marketing - General / Support", "Others", "Student / Fresh Graduate / No Experience"], "post_time": "2022-01-17T06:15:08Z", "salary": {"currency": null, "max": null, "min": null, "period": "monthly", "term": null}, "salary_visible": false, "title_keywords": ["assistant"], "responsibilities": ["social media", "perform other duties", "data entry and filing", "marketing strategies", "marketing plans", "monitor", "website", "design", "coordinate with", "daily operation", "ad hoc projects", "contents", "facebook"], "requirements": {"degrees": [], "majors": [], "languages": ["english", "chinese"], "language_level": ["proficiency"], "hard_skills": ["excel", "ms word", "word", "powerpoint", "processing", "photoshop"], "soft_skills": ["communication skills", "creative"], "languages_combined": [{"language": "english", "language_level": []}, {"language": "chinese", "language_level": ["proficiency"]}]}, "experience_required": {"duration": [], "field": ["social media", "marketing", "relevant experience"]}}, {"job_id": "100003009052144", "location_code": "hk", "company": "Federation of Hong Kong Industries", "job_title": "Assistant Manager / Senior Officer, Corporate Communication (Ref: PRCD/AM/CC)", "description": "Job Requirements\n\nBachelor Degree of Business or related disciplines\nPrevious experience in internship program is preferable\nPassionate, self-motivated, dynamics and responsible\nDetail-oriented, adaptable, energetic and good team player\nComputer literate in using MS Word, Excel and PowerPoint\nProficient in communication of English and Mandarin\nImmediate available is a definite advantage\n\nJob Responsibilities\n\nProvide support on marketing functions and promotion campaigns\nHandle branding activities and joint promotion programs with vendors\nResponsible for market research and preparing presentation materials\nAssist in the execution of marketing strategies to drive market awareness\n\nExcellent development prospects and attractive fringe benefits will be offered to the right candidates. Interested parties, please send full resume with last & expected salary and date of available by clicking \u2018Apply Now\u2019", "employment_types": ["Full Time"], "selling_points": ["Corporate Communication", "Corporate Affairs", "5 day work week"], "locations": ["Cheung Sha Wan"], "categories": ["Marketing / Public Relations", "Marketing - General / Support", "Public Relations - Event Management"], "post_time": "2022-01-17T03:33:49Z", "salary": {"currency": null, "max": null, "min": null, "period": "monthly", "term": null}, "salary_visible": false, "title_keywords": ["assistant manager", "senior officer"], "responsibilities": ["provide support", "promotion campaigns", "marketing strategies", "market research"], "requirements": {"degrees": ["degree", "bachelor"], "majors": ["related disciplines", "business"], "languages": ["english", "mandarin"], "language_level": ["proficient"], "hard_skills": ["excel", "powerpoint", "ms word"], "soft_skills": ["passionate", "self-motivated", "good team player", "responsible", "adaptable", "detail-oriented", "communication", "energetic"], "languages_combined": [{"language": "english", "language_level": ["proficient"]}, {"language": "mandarin", "language_level": ["proficient"]}]}, "experience_required": {"duration": [], "field": []}}, {"job_id": "100003009052397", "location_code": "hk", "company": "Zebra Strategic Outsource Solution Ltd", "job_title": "Marketing Assistant (Business Management & Customer Experience)", "description": "Responsibilities : -\n\nHandling general administrative and clerical duties.\nKeeping staff attendance record.\nAnswering phone calls.\n\nRequirements : -\n\nF.5 Level or above, 1 year working experience.\nAssociate / HD / Degree fresh graduate will also be considered.\n\n\u00a0 Interested parties, please apply via Quick Apply or Non Members Apply", "employment_types": ["Full Time", "Contract"], "selling_points": [], "locations": ["Kowloon Bay"], "categories": ["Marketing / Public Relations", "Management", "Marketing - General / Support", "Public Relations - General / Support"], "post_time": "2022-01-17T02:56:57Z", "salary": {"currency": null, "max": null, "min": null, "period": "monthly", "term": null}, "salary_visible": false, "title_keywords": ["marketing assistant"], "responsibilities": ["attendance", "phone calls"], "requirements": {"degrees": ["degree", "fresh graduate"], "majors": [], "languages": [], "language_level": [], "hard_skills": [], "soft_skills": [], "languages_combined": []}, "experience_required": {"duration": ["1 year"], "field": []}}, {"job_id": "100003009052200", "location_code": "hk", "company": "IPSOS Asia Limited", "job_title": "Senior / Research Executive - Qualitative", "description": "Responsibilities :\n\nPropose and implement marketing / promotional programs with clients\nCo-ordinate sales & marketing projects and conduct event management\nResponsible to prepare, design and review all marketing materials including website content, layout, brochures, posters and sales materials\nWork closely with clients, vendors, designers, sales team and internal parties\nPerform ad-hoc projects as assigned\n\nRequirements :\n\nDegree holder in Marketing or related disciplines\n2-3 years marketing experience, experience in media / publication will be an advantage\nGood command of spoken and written English and Chinese\nstrong sense of responsibility, well-organized, self-motivated with excellent communication skills\nImmediately available is preferred\n\n\n\nApplication Method\n\nWe offer competitive salary, discretionary bonus, 5-day work week, public holidays and fringe benefits. Interested parties, please send full resume with expected salary to\u00a0ORIENTAL HUMAN RESOURCES LIMITED\u00a0by clicking \"Apply now\" ;\u00a0or\u00a0fax to 3600 1900\u00a0( Please quote reference on the application letter )\n\n\u00a0\nPersonal Information Collection Statement\n\nPersonal data collected will be treated in accordance with our Personal Data Policy and handled in strict confidence by authorized personnel for recruitment related purpose only.\n\non.cc", "employment_types": ["Full Time", "Permanent"], "selling_points": ["Story telling", "Qualitative research", "Research project execution"], "locations": ["Hung Hom"], "categories": ["Media & Advertising", "Editorial / Journalism", "Marketing / Public Relations", "Marketing - General / Support", "Marketing - Market Research"], "post_time": "2022-01-17T02:26:13Z", "salary": {"currency": null, "max": null, "min": null, "period": "monthly", "term": null}, "salary_visible": false, "title_keywords": ["executive"], "responsibilities": ["management", "review", "marketing projects", "design", "website", "sales team", "marketing materials", "ad-hoc projects", "internal parties"], "requirements": {"degrees": ["degree holder"], "majors": ["related disciplines", "marketing"], "languages": ["english", "chinese"], "language_level": ["good command"], "hard_skills": [], "soft_skills": ["communication skills", "self-motivated", "well-organized", "sense of responsibility"], "languages_combined": [{"language": "english", "language_level": ["good command"]}, {"language": "chinese", "language_level": ["good command"]}]}, "experience_required": {"duration": ["2-3 years"], "field": ["marketing", "media"]}}, {"job_id": "100003009049434", "location_code": "hk", "company": "Job House Personnel Consultants", "job_title": "Clerk  (5-day Job)", "description": "Responsibilities\n\n\nAssist in planning and implementing effective integrated marketing campaigns\nConduct market research and analysis, and prepare relevant marketing/training materials\nDevelop and implement creative content on traditional and digital platforms to meet marketing objectives, including SEO copywriting, advertisement, advertorial and video scriptwriting, etc.\nAssist in planning, managing, executing, generating social contents and managing performance in various social platforms.\nSupport in content translation, including corporate/project materials, marketing write-ups, etc.\nEvent planning, organizing, and on-site support\nCoordinate with other departments on various communication and client servicing projects\nHandle and assist in ad-hoc projects as assigned\nWork closely with external firms and vendors for materials production\nMonitor corporate branding applications across marketing materials to deliver quality corporate brand image consistently\n\nQualifications\n\nBachelor's degree or equivalent\nProficiency in English, Cantonese, and Mandarin\u00a0\nExcellent communication skills, both oral and written\nHighly advanced skills of Microsoft office tools\nProactive, problem-solving attitude and strong interpersonal\nAbility of multitasking, prioritizing and working with deadlines\u00a0\nAdaptable, embracing, and supportive to change\n\nWhy Walton\n\nAligning with a pioneer and industry leader in the land based real estate investment industry\nCompetitive salary package\nFriendly and professional working environment\nFun, energetic co-workers who share the same core values and strategies\n\nInterested candidates are invited to forward a resume by clicking apply now.\n\nPlease visit\u00a0Walton.com for company information.\n\nWe would like to thank all applicants for their interest in this position; however, only those selected for interviews will be contacted.", "employment_types": ["Full Time", "Permanent"], "selling_points": [], "locations": ["Tuen Mun Area"], "categories": ["Admin & HR", "Clerical / Admin Staff", "Marketing / Public Relations", "Marketing - General / Support", "Others", "Student / Fresh Graduate / No Experience"], "post_time": "2022-01-15T19:11:38Z", "salary": {"currency": null, "max": null, "min": null, "period": "monthly", "term": null}, "salary_visible": false, "title_keywords": ["clerk"], "responsibilities": ["seo", "creative content", "conduct market research", "analysis", "coordinate with", "monitor", "quality", "develop", "communication", "executing", "marketing campaigns", "contents", "marketing materials", "ad-hoc projects", "planning"], "requirements": {"degrees": ["degree", "bachelor"], "majors": [], "languages": ["cantonese", "english", "mandarin"], "language_level": ["proficiency"], "hard_skills": ["seo", "fun", "microsoft office", "problem-solving", "analysis", "translation"], "soft_skills": ["communication skills", "oral", "proactive", "supportive", "advanced", "adaptable", "problem-solving", "communication", "energetic", "friendly", "creative", "interpersonal", "prioritizing"], "languages_combined": [{"language": "cantonese", "language_level": ["proficiency"]}, {"language": "english", "language_level": ["proficiency"]}, {"language": "mandarin", "language_level": ["proficiency"]}]}, "experience_required": {"duration": [], "field": []}}, {"job_id": "100003009054141", "location_code": "hk", "company": "Walton International Group Limited", "job_title": "Marketing Executive", "description": "Plan and implement integrated Marketing campaigns strategically\nDrive\u00a0marketing innovation with internal and external stakeholders to accelerate new member acquisition, demand generation and user/customer engagement programs\nExplore and liaise various joint promotion to strengthen AME brand image and achieve company goals\nWork with Marketing team, Store Management team and Business units to develop Marketing\u00a0/\u00a0Sales materials and Store supporting\nDesign, develop and produce marketing collaterals, include but not limited to ATL, BTL, Digital platforms and Event Management\nAssist in ad-hoc project\nRequirements:\n\nBachelor\u2019s degree or above in Marketing, Business Administration or other related disciplines\nAt least 2 years' relevant experience in Marketing, Corporate Communication or\u00a0Brand Management\nAble to translate ideas into actions and detailed planning\nExcellent communication, presentation and interpersonal skills\nStrong business acumen, strategic mindset, detailed oriented, creative and passionate in agile environment\nA problem solver with a keen sense to event management and in-depth knowledge of marketing technologies in the brand landscape\nProficiency in MS Office applications and Chinese Word Processing\nGood command of spoken and written English and Chinese, knowledge of Putonghua is an advantage", "employment_types": ["Full Time", "Permanent"], "selling_points": [], "locations": ["Admiralty"], "categories": ["Marketing / Public Relations", "Marketing - General / Support"], "post_time": "2022-01-17T08:32:49Z", "salary": {"currency": null, "max": null, "min": null, "period": "monthly", "term": null}, "salary_visible": false, "title_keywords": ["marketing executive"], "responsibilities": ["liaise", "management team", "management", "ad-hoc", "ideas", "marketing collaterals", "design", "develop", "communication", "planning", "marketing campaigns", "plan", "administration"], "requirements": {"degrees": ["degree or above", "bachelor"], "majors": ["related disciplines", "marketing", "business administration"], "languages": ["putonghua", "english", "chinese"], "language_level": ["advantage", "proficiency", "good command"], "hard_skills": ["chinese word processing", "ms office", "agile", "acumen"], "soft_skills": ["passionate", "detailed oriented", "agile", "problem solver", "keen", "communication", "interpersonal skills", "business acumen", "creative", "presentation", "detailed"], "languages_combined": [{"language": "putonghua", "language_level": ["good command"]}, {"language": "english", "language_level": ["advantage", "good command"]}, {"language": "chinese", "language_level": ["advantage", "proficiency", "good command"]}]}, "experience_required": {"duration": ["at least 2 years"], "field": ["management", "brand", "corporate communication", "marketing", "relevant experience"]}}, {"job_id": "100003009055368", "location_code": "hk", "company": "Hung Fook Tong Holdings Limited", "job_title": "Product Marketing Officer (HRD-adv-22-001)", "description": "Responsibilities:\n\nTo support Product & Marketing Manager and work as a team to execute product plans and strategy with the ultimate objective of raising brand awareness, brand building and increasing sales;\nTo identify a continuous stream of commercially valuable new products;\nDrive product development, packaging and manage market analysis;\nProduct forecasting and inventory control and management;\nWork closely with internal and external production / QC teams to ensure accurate execution of product development with the right quality and time;\nSupport ad hoc projects when required.\n\nRequirements:\n\n\u00a0 Degree in marketing, business management, nutrition or food science background is preferable;\n\u00a0 Minimum 3 years product experience in retail / FMCG (bottled drinks preferred);\n\u00a0 Solid experience in product marketing is advantageous;\n\u00a0 Good communications skill in Cantonese, Mandarin and English\n\u00a0 Able to independently manage project and drive progress.\n\u00a0 Candidate with more experience will be considered as \"Senior Product Marketing Officer\"\n\n\n\nWe offer 5-day-work week with competitive remuneration and benefit packages to the right candidate. Interested parties please send your application letter, resume, expected salary (quoting Employer Ref:) and availability to\u00a0HR Department at Hung Fook Tong, 8/F, Chuan Kei Factory Building, Nos. 15-23 Kin Hon Street, Kwai Chung, NT., H.K. or e-mail or\u00a0browse our website:\u00a0www.hungfooktong.com\n\nPersonal Information Collection Statement-Applicants\u2019 personal information will be used for the recruitment and employment matters only; information will be kept in strict confidence; information of unsuccessful applicants will be shredded after recruitment process; subject to provisions under the Personal Data (Privacy) Ordinance, applicants have right to access and make corrections of their personal data", "employment_types": ["Full Time"], "selling_points": ["Execute product plans and strategy", "product experience in retail/FMCG", "5 day works,flexible working hour"], "locations": ["Kwai Hing"], "categories": ["Manufacturing", "Product Development / Management", "Marketing / Public Relations", "Marketing - Brand / Product Management", "Marketing - General / Support"], "post_time": "2022-01-18T02:21:03Z", "salary": {"currency": null, "max": null, "min": null, "period": "monthly", "term": null}, "salary_visible": false, "title_keywords": ["marketing officer"], "responsibilities": ["management", "teams", "quality", "inventory control", "market analysis", "ad hoc projects", "plans", "forecasting"], "requirements": {"degrees": ["degree"], "majors": ["business", "marketing", "food science"], "languages": ["cantonese", "english", "mandarin"], "language_level": ["good"], "hard_skills": ["business management"], "soft_skills": ["independently"], "languages_combined": [{"language": "cantonese", "language_level": ["good"]}, {"language": "english", "language_level": ["good"]}, {"language": "mandarin", "language_level": ["good"]}]}, "experience_required": {"duration": ["minimum 3 years"], "field": ["retail", "marketing", "fmcg"]}}, {"job_id": "100003009055157", "location_code": "hk", "company": "Hong Kong Arts Development Council", "job_title": "International Programmes Officer (Job ref: IPO-2207-JDB)", "description": "Responsible for supporting Team Supervisor in the implementation of various projects, in particular cultural exchange projects.\u00a0 Duties include project coordination and logistics, liaison with artists and different parties, preparation of online and offline publicity materials, committee papers and meetings, as well as general administrative work.\n\nRequirements:\n\nA university degree with at least 3-year experience in project coordination, preferably in arts sectors\nStrong analytical skill, well-organised and detail-oriented\nAble to work under pressure and strong adaptability to situations\nA good team player with good interpersonal and communication skills\nGood command of written and spoken English, Cantonese and Putonghua\nProficiency in PC operations (MS based applications and Chinese Word Processing)\nWell understanding and strong interest in arts scene in Hong Kong will be an advantage\n\nSalary offered will be commensurate with qualifications and experience. Interested persons, please send CV with details on education and work experience, stating salary history and expected salary, and indicating your earliest availability to the Human Resources Department, 10/F, 1063 King\u2019s Road, Quarry Bay, Hong Kong no later than 7 February 2022.\u00a0 Please quote the job reference on the envelope.\n\n\u00a0Applicants not invited for interview within 16 weeks from the closing date for application may assume that their applications are unsuccessful.\u00a0 Personal data collected will be treated in strictest confidence and will only be used for recruitment purposes. HKADC reserves the right to consider late applications and not to make appointment for the post advertised.\u00a0 We do not accept applications through e-mail or fax.\n\n\u00a0\nHKADC is an Equal Opportunities Employer", "employment_types": ["Full Time", "Permanent"], "selling_points": [], "locations": ["Quarry Bay"], "categories": ["Admin & HR", "Clerical / Admin Staff", "Others", "Entertainment - Artists / Singers / Musicians", "Marketing / Public Relations", "Marketing - General / Support"], "post_time": "2022-01-18T03:27:39Z", "salary": {"currency": null, "max": null, "min": null, "period": "monthly", "term": null}, "salary_visible": false, "title_keywords": ["officer"], "responsibilities": ["administrative work", "project coordination", "operations", "implementation", "communication", "logistics", "recruitment", "personal data", "work under pressure"], "requirements": {"degrees": ["university degree"], "majors": [], "languages": ["cantonese", "putonghua", "english", "chinese"], "language_level": ["proficiency", "good command"], "hard_skills": ["analytical skill", "no", "chinese word processing", "pc operations", "make", "ms based applications", "exchange"], "soft_skills": ["communication skills", "analytical skill", "good team player", "confidence", "responsible", "detail-oriented", "adaptability", "coordination", "well-organised", "interpersonal", "work under pressure"], "languages_combined": [{"language": "cantonese", "language_level": ["good command"]}, {"language": "putonghua", "language_level": ["good command"]}, {"language": "english", "language_level": ["good command"]}, {"language": "chinese", "language_level": ["proficiency"]}]}, "experience_required": {"duration": ["at least 3-year"], "field": ["human resources", "education"]}}, {"job_id": "100003009055747", "location_code": "hk", "company": "HKT Consumer Group", "job_title": "Sales & Process Planning Officer", "description": "Your role\n\nTo assist Process Planning Manager in strategy implementation on various eCS platforms\nTo coordinate with internal teams (i.e. Marketing, Legal, IT, etc.) to plan and execute enhancements on the eCS platforms\nTo conduct user acceptance test (UAT) before actual roll-out\nTo perform quality checks on the e-platforms and compile weekly analytical reports for management review\nTo coordinate and execute various promotion items (i.e. posters, online banners, etc.) and activities (i.e. lucky draw, Facebook activities, etc.) for stimulating registration and usage of the eCS platforms\n\nTo succeed in this role\n\nDegree or diploma in Marketing / Business Administration / Information System or related disciplines\nPreferably with at least 1-year working experience in telecom industry\nProficient in Adobe Photoshop and MS Office applications will be an advantage\nGood interpersonal and communication skills\nDetail-oriented and able to work independently under tight schedule\nGood command of verbal and written communication, in both English and Chinese\nFresh graduates will also be considered", "employment_types": ["Full Time"], "selling_points": [], "locations": ["Shatin Area"], "categories": ["Sales, CS & Business Devpt", "Call Centre", "Marketing / Public Relations", "Marketing - General / Support"], "post_time": "2022-01-18T02:55:07Z", "salary": {"currency": null, "max": null, "min": null, "period": "monthly", "term": null}, "salary_visible": false, "title_keywords": ["sales & process planning officer"], "responsibilities": ["administration", "uat", "teams", "coordinate with", "implementation", "quality", "coordinate", "banners", "communication", "reports", "schedule", "plan", "facebook", "management review", "planning"], "requirements": {"degrees": ["diploma", "degree"], "majors": ["related disciplines", "marketing", "business administration"], "languages": ["english", "chinese"], "language_level": ["good command"], "hard_skills": ["facebook", "adobe photoshop", "information system", "ms office"], "soft_skills": ["communication skills", "work independently", "detail-oriented", "communication", "interpersonal"], "languages_combined": [{"language": "english", "language_level": ["good command"]}, {"language": "chinese", "language_level": ["good command"]}]}, "experience_required": {"duration": ["at least 1-year"], "field": []}}, {"job_id": "100003009055209", "location_code": "hk", "company": "PARKnSHOP", "job_title": "Senior Marketing Executive", "description": "You can enjoy:\u00a0\n\nComprehensive Medical and Life Insurance coverage, including your spouse and children\nExclusive company pension schemes\nMarriage, Maternity and Paternity Leave\nExclusive shopping discount, Bazaar Sales for our people only\nProfessional training and career advancement opportunities\nConvenient office location, less than 5 min. walk from MTR\nContemporary workplace with Onsite Clinic, Lactation Rooms, free drinks and chill out areas\nWell-equipped Gym inside our office building, plus fitness and interest class packages\nFree round-trip lunchtime shuttle bus services to Shatin\n\nResponsibilities:\n\nDevelop and execute marketing campaigns, promotion activities and events on both offline and online channels\nCoordinate with internal and external parties on instore POSM, TVC or other promotion materials\nLiaise with media and agencies for media planning\nManage A&P budget and effectiveness of advertising and promotions campaigns\nHandle any ad hoc projects / tasks as assigned\n\nRequirements:\n\nBachelor degree in Marketing or business-related disciplines\nMinimum 4 years related experience, preferably in FMCG industry\nDynamic, creative to cope with fast-paced working environment and able to work under pressure\nGood communication and interpersonal skills\nProficient in both written and spoken English and Chinese\nCandidate with less experience can be considered as Marketing Executive\n\nAn attractive salary and benefit package will be offered. Interested parties please forward detailed resume stating expected salary to: People Department, PARKnSHOP (HK) Limited, Watson House, 1-5 Wo Liu Hang Road, Fo Tan, N.T. or email to us or click \u201cApply Now\u201d.\n\nWe are an equal opportunity employer and welcome applications from all qualified candidates. The information provided will be treated in strict confidence and be used only for consideration of your application for relevant / similar posts within the A.S. Watson Group. All personal data of unsuccessful applicants will be destroyed within 12 months from the date of application.", "employment_types": ["Full Time", "Permanent"], "selling_points": [], "locations": ["Shatin Area"], "categories": ["Marketing / Public Relations", "Marketing - General / Support", "Marketing - Marketing Communication", "Others"], "post_time": "2022-01-18T01:46:19Z", "salary": {"currency": null, "max": null, "min": null, "period": "monthly", "term": null}, "salary_visible": false, "title_keywords": ["senior marketing executive"], "responsibilities": ["online channels", "advertising", "internal and external parties", "coordinate with", "budget", "develop", "ad hoc projects", "marketing campaigns", "liaise with", "planning"], "requirements": {"degrees": ["degree", "bachelor"], "majors": ["business", "related disciplines", "marketing"], "languages": ["english", "chinese"], "language_level": ["proficient"], "hard_skills": ["dynamic", "fmcg industry"], "soft_skills": ["dynamic", "creative", "communication and interpersonal skills", "work under pressure"], "languages_combined": [{"language": "english", "language_level": ["proficient"]}, {"language": "chinese", "language_level": ["proficient"]}]}, "experience_required": {"duration": ["minimum 4 years"], "field": ["related", "fmcg", "marketing"]}}, {"job_id": "100003009055161", "location_code": "hk", "company": "Tsit Wing Coffee Co Ltd", "job_title": "Digital Marketing Executive", "description": "Responsibilities:\n\n\n\nManage and create content for online platforms (e.g. Website, Social Media, display advertising and digital campaigns) to achieve marketing objectives and to enable smooth collaborations\nAssist in developing overall corporate branding and marketing strategy\nExplore creative promotion and events to generate brand awareness\nDevelop digital marketing strategies and campaigns to achieve traffic and business goals\nAnalyze data, trends and insights to fully optimize all digital platforms.\nCoordinate with internal teams to plan, organize, and execute various marketing events or campaigns\nAssist in ad hoc marketing and event management tasks\n\nRequirements:\n\n\n\nDegree holder in Marketing, Business or related disciplines\nAround 1-2 years of relevant experience, knowledge in GA, SEO is definitely an advantage\nStrong communication and presentation skills\nExcellent in handling and follow up on details, take initiative, independent & responsible\nFluent in both written and spoken English, Cantonese and Mandarin\nExcellent English (in both written & spoken) + communication & copywriting skills\nProficiency in marketing automation technology\nAble to execute email marketing strategies\nFamiliarity with analytical and database tools\n\nWorking location:\u00a0Kwai Chung\n\nStaff Benefit:\n\nDiscretionary Bonus\nMedical & Life Insurance\nAnnual Leave\nPayable Sick Leave\nEncourage continuing education and on-job training\nOpen office working environment\nOffer promotion opportunities and long-term career path\u00a0\n\nWe offer a competitive remuneration package to the right candidate.\u00a0Interested parties\u00a0please click\u00a0\"Apply Now\"\u00a0to submit your application\u00a0or by email to\u00a0hr1 @twcoffee.com\n\n\u00a0(All personal data provided by applicants will be treated in strict confidence and used for employment-related purpose only.)\n\nAdditional Information", "employment_types": ["Full Time", "Permanent"], "selling_points": [], "locations": ["Kwai Fong"], "categories": ["Marketing / Public Relations", "Marketing - Brand / Product Management", "Marketing - General / Support", "Digital Marketing"], "post_time": "2022-01-18T01:34:01Z", "salary": {"currency": null, "max": null, "min": null, "period": "monthly", "term": null}, "salary_visible": false, "title_keywords": ["digital marketing executive"], "responsibilities": ["social media", "business goals", "marketing events", "advertising", "digital marketing strategies", "ad hoc", "management", "coordinate with", "website", "developing", "develop", "teams", "digital campaigns", "plan", "analyze data"], "requirements": {"degrees": ["degree holder"], "majors": ["business", "related disciplines", "marketing"], "languages": ["cantonese", "english", "mandarin"], "language_level": ["excellent", "fluent"], "hard_skills": ["seo"], "soft_skills": ["independent", "responsible", "communication", "presentation skills", "initiative"], "languages_combined": [{"language": "cantonese", "language_level": ["fluent"]}, {"language": "english", "language_level": ["excellent", "fluent"]}, {"language": "mandarin", "language_level": ["excellent", "fluent"]}]}, "experience_required": {"duration": ["1-2 years"], "field": ["relevant experience"]}}, {"job_id": "100003009056376", "location_code": "hk", "company": "Modern Dental Laboratory Company Limited", "job_title": "Project Executive", "description": "Responsibilities:\u00a0\u00a0\nResponsible and optimization of overseas advertisement channels such as Google, Facebook and Instagram\nSolid experience with social media including blogs, Instagram, Facebook, etc.\nProvide and execute marketing plans including strategy, budget, goals of the project launches\nManager all-rounded marketing and promotion campaigns covering (both online & offline promotions, e-marketing, social media campaign, website updates and consumer experience enhancement)\nOrganize product seeding among celebrities, KOL, media, influencers\nResearch and monitor the strategies of competitors and adjust project plan\nManage brand positioning and product design, online activities planning and promotion for the platforms\n\nRequirements:\n\nDegree or above in Business, Advertising, Marketing, Communications, E-commerce, Project Management, PR or related discipline;\n3 years or above solid experience in marketing / project management\nGood knowledge or experience in HTML, Search Engine Marketing and SEO is an advantage\nKnowledge in\u00a0Google Analytics/ Google Ads/ Facebook Ads Manager tools is a must - Proficient in spoken and written English and Chinese\nEnergetic, self-motivated, detail-oriented, passionate,\u00a0results-oriented and able to work under pressure\nGreat communication and management skills\n\nInterested Candidates,\u00a0please send your\u00a0full resume with your recent photo,\u00a0current & expected salary\u00a0by e-mail to\u00a0hr @moderndentallab.com.\nAll personal data collected will be used for recruitment and employment related purpose only.", "employment_types": ["Full Time", "Permanent"], "selling_points": ["Optimization of overseas advertisement channels", "Enjoy Social Media & English copywriting", "Genuine interest in SEO / Digital Marketing"], "locations": ["Lai Chi Kok"], "categories": ["Marketing / Public Relations", "Marketing - General / Support", "Public Relations - Copy-writing", "Digital Marketing"], "post_time": "2022-01-18T04:06:25Z", "salary": {"currency": null, "max": null, "min": null, "period": "monthly", "term": null}, "salary_visible": false, "title_keywords": ["project executive"], "responsibilities": ["social media", "marketing plans", "budget", "monitor", "website", "project plan", "promotion campaigns", "product design", "facebook", "planning"], "requirements": {"degrees": ["degree or above"], "majors": ["e-commerce", "project management", "business", "marketing", "communications"], "languages": ["english", "chinese"], "language_level": ["proficient"], "hard_skills": ["google analytics", "seo", "e-commerce", "html", "project management", "facebook"], "soft_skills": ["passionate", "self-motivated", "detail-oriented", "communication", "project management", "energetic", "work under pressure"], "languages_combined": [{"language": "english", "language_level": ["proficient"]}, {"language": "chinese", "language_level": ["proficient"]}]}, "experience_required": {"duration": ["3 years"], "field": ["project management", "marketing"]}}, {"job_id": "100003009056529", "location_code": "hk", "company": "Manulife (International) Limited", "job_title": "Administrative coordinator - \u884c\u653f\u52a9\u7406\uff08Latest*\uff09", "description": "Responsibilities:\n\nWork with departments to coordinate the project progress;\nAssist or represent the Managers, negotiate and follow up tasks with customers and partners;\nPrepare correspondence documents, reports, etc.;\nAssist in company meetings/ event organising\u00a0\n\n\nRequirements:\u00a0\n\nHigh diploma or above in business & communications, administration, public relations or related disciplines;\u00a0\nAt least 1 year relevant working experience\uff1b\nGood command of written and spoken English and Chinese;\nStrong interpersonal and communication skills, high teamwork spirit;\nGood knowledge of MS Office\n\n\nBenefits:\n\n5-day work week\nDiscretionary bonus\nMedical insurance\nMarriage, birthday and family care leave\n\n\n\n\u5d17\u4f4d\u8077\u8cac\uff1a\n\n\u8ca0\u8cac\u8ddf\u9032\u516c\u53f8\u8ca0\u8cac\u4eba\u76f8\u95dc\u5de5\u4f5c\u3001\u4e0b\u9054\u53ca\u8ddf\u8e64\u548c\u843d\u5be6\u60c5\u6cc1\uff1b\n\u5354\u52a9\u6216\u4ee3\u8868\u7d93\u7406\uff0c\u8207\u5ba2\u6236\u548c\u5408\u4f5c\u5925\u4f34\u5354\u5546\u548c\u8ddf\u9032\u4efb\u52d9\uff1b\n\u8ca0\u8cac\u5354\u52a9\u516c\u53f8\u8d77\u8349\u6587\u5b57\u6750\u6599\uff0c\u4ee5\u53ca\u6703\u8b70\u7d00\u8981\u3001\u7c21\u5831\u7b49\uff1b\n\u8ca0\u8cac\u516c\u53f8\u6703\u8b70\u4e8b\u52d9\u6e96\u5099\u5de5\u4f5c\uff0c\u4e26\u53c3\u8207\u516c\u53f8\u91cd\u8981\u6d3b\u52d5\u7684\u7d44\u7e54\u5b89\u6392\u5de5\u4f5c\uff1b\n\n\n\u5165\u8077\u8981\u6c42\uff1a\n\nHKCEE \u6216 DSE \u4e94\u79d1\u5408\u683c\uff0c\u9ad8\u7d1a\u6587\u6191\u6216\u4ee5\u4e0a\u5b78\u6b77\n1\u5e74\u76f8\u95dc\u5de5\u4f5c\u7d93\u9a57\uff1b\n\u826f\u597d\u7684\u82f1\u6587\u548c\u4e2d\u6587\u53e3\u8a9e\u53ca\u66f8\u5beb\u80fd\u529b;\n\u5177\u6709\u826f\u597d\u7684\u6e9d\u901a\u3001\u5354\u8abf\u80fd\u529b\uff0c\u826f\u597d\u5718\u968a\u5408\u4f5c\u7cbe\u795e\uff1b\n\u719f\u6089MS Office\n\n\n\u798f\u5229\uff1a\n\n5\u5929\u5de5\u4f5c\u9031\n\u82b1\u7d05\n\u91ab\u7642\u4fdd\u96aa\n\u5a5a\u59fb\uff0c\u751f\u65e5\u548c\u5bb6\u5ead\u8b77\u7406\u5047", "employment_types": ["Full Time", "Part Time", "Permanent", "Temporary", "Internship"], "selling_points": ["Provide professional  administrative support", "1 year + relevant working experience", "Monthly salary 15k-20k, double pay, discretionary"], "locations": ["Ngau Tau Kok"], "categories": ["Admin & HR", "Administration / Operation Manager", "Sales, CS & Business Devpt", "Customer Service - Supervisor / Officer", "Marketing / Public Relations", "Marketing - General / Support"], "post_time": "2022-01-18T04:40:42Z", "salary": {"currency": "HKD", "max": 19999, "min": 14000, "period": "monthly", "term": null}, "salary_visible": true, "title_keywords": ["coordinator"], "responsibilities": ["coordinate", "reports", "project progress"], "requirements": {"degrees": ["high diploma or above"], "majors": ["related disciplines", "business", "communications"], "languages": ["english", "chinese"], "language_level": ["good command"], "hard_skills": ["ms office"], "soft_skills": ["communication skills", "teamwork spirit", "interpersonal"], "languages_combined": [{"language": "english", "language_level": ["good command"]}, {"language": "chinese", "language_level": ["good command"]}]}, "experience_required": {"duration": ["at least 1 year"], "field": ["relevant working experience"]}}, {"job_id": "100003009054578", "location_code": "hk", "company": "Manulife (International) Limited", "job_title": "Customer Services Officer", "description": "Job Descriptions: \u00a0\n\nHandle customers' enquiries, provide product information;\nFollow customers' developments and provide advices;\nArrange customer-visit and build up relationship;\u00a0\nPrepare sales reports, analysis and sales forecast;\nAssist managers in various kinds of sales-related programs;\nAssist in ad hoc duties as assigned, i.e. market research, survey, etc.;\nProvide supporting in marketing activities and events\n\nRequirements\uff1a\n\nDegree holder is preferred;\nOversea University graduate or above\u00a0is welcome;\nMinimum 1 year working experience preferred;\nGood communication skills with analytical mind;\nA self-confident, customer-oriented, outgoing energetic team player with good learning attitude are preferred;\nGood command of spoken and written English & Chinese (Cantonese and Mandarin);\n\n\u00a0We Offer:\n\n5 days work\u00a0\nGuaranteed Basic\u00a0Income + Monthly Bonus + Year-end Bonus\nA fast-paced environment where continuous learning keeps us competitive\nFlexible healthcare packages, including hospitalisation and outpatient benefits\n\nWe offer competitive remuneration and benefits, holidays, stable working environment to the right candidates. Interested parties please click \"Apply\u00a0Now\" and send your\u00a0full resume\u00a0with expected salary\u00a0to\u00a0us.\n\n*All personal data collected will be kept strictly confidential and used for recruitment-related purpose only.", "employment_types": ["Full Time", "Permanent"], "selling_points": ["Guaranteed Basic Income\uff08$15Kto $20K\uff09", "5 days work", "Monthly Bonus + Year-end Bonus"], "locations": ["Not Specified"], "categories": ["Sales, CS & Business Devpt", "Business Development", "Customer Service - Supervisor / Officer", "Marketing / Public Relations", "Marketing - General / Support"], "post_time": "2022-01-17T10:04:48Z", "salary": {"currency": "HKD", "max": 19999, "min": 14000, "period": "monthly", "term": null}, "salary_visible": true, "title_keywords": ["customer services officer"], "responsibilities": ["ad hoc duties", "provide advices", "analysis", "prepare sales", "market research", "assist managers", "reports", "forecast"], "requirements": {"degrees": ["university graduate or above", "degree holder"], "majors": [], "languages": ["cantonese", "english", "chinese", "mandarin"], "language_level": ["good command"], "hard_skills": [], "soft_skills": ["confident", "communication skills", "outgoing", "customer-oriented", "analytical mind", "learning", "team player", "energetic"], "languages_combined": [{"language": "cantonese", "language_level": ["good command"]}, {"language": "english", "language_level": ["good command"]}, {"language": "chinese", "language_level": ["good command"]}, {"language": "mandarin", "language_level": ["good command"]}]}, "experience_required": {"duration": ["minimum 1 year"], "field": []}}, {"job_id": "100003009053389", "location_code": "hk", "company": "The Store House Limited", "job_title": "Marketing and Administrative Executive", "description": "Job Description and responsibilities:\n\n\u00a0\u00a0\u00a0\u00a0\u00a0\u00a0 Manage and monitor the company\u2019s official website, Facebook, Instagram etc\n\u00a0\u00a0\u00a0\u00a0\u00a0\u00a0 Design contents of social media performs\n\u00a0\u00a0\u00a0\u00a0\u00a0\u00a0 Devise marketing strategies and execute marketing plans\n\u00a0\u00a0\u00a0\u00a0\u00a0\u00a0 Coordinate with online marketing agencies and website developers\n\u00a0\u00a0\u00a0\u00a0\u00a0\u00a0 Assist the operation team in daily operation\n\u00a0\u00a0\u00a0\u00a0\u00a0\u00a0 Data entry and filing\n\u00a0\u00a0\u00a0\u00a0\u00a0\u00a0 Assist ad hoc projects and perform other duties as assigned\n\nRequirements:\n\n\u00a0\u00a0\u00a0\u00a0\u00a0\u00a0 Relevant experience in sales and marketing\n\u00a0\u00a0\u00a0\u00a0\u00a0\u00a0 Written and verbal communication skills in Chinese & English\n\u00a0\u00a0\u00a0\u00a0\u00a0\u00a0 Proficiency with MS Word, Excel, PowerPoint, Photoshop and Chinese Word\u00a0 \u00a0 \u00a0 \u00a0 \u00a0 \u00a0 \u00a0 \u00a0 \u00a0Processing\n\u00a0\u00a0\u00a0\u00a0\u00a0\u00a0 Experience in handling different social media accounts\n\u00a0\u00a0\u00a0\u00a0\u00a0\u00a0 Creative and good communication skills", "employment_types": ["Full Time", "Permanent"], "selling_points": [], "locations": ["Sai Wan"], "categories": ["Marketing / Public Relations", "Marketing - General / Support"], "post_time": "2022-01-17T07:03:26Z", "salary": {"currency": null, "max": null, "min": null, "period": "monthly", "term": null}, "salary_visible": false, "title_keywords": ["administrative executive"], "responsibilities": ["social media", "perform other duties", "data entry and filing", "marketing strategies", "marketing plans", "monitor", "website", "design", "coordinate with", "daily operation", "ad hoc projects", "contents", "facebook"], "requirements": {"degrees": [], "majors": [], "languages": ["english", "chinese"], "language_level": ["proficiency"], "hard_skills": ["excel", "ms word", "word", "powerpoint", "processing", "photoshop"], "soft_skills": ["communication skills", "creative"], "languages_combined": [{"language": "english", "language_level": []}, {"language": "chinese", "language_level": ["proficiency"]}]}, "experience_required": {"duration": [], "field": ["social media", "marketing", "relevant experience"]}}, {"job_id": "100003009053286", "location_code": "hk", "company": "Asia Motion E-Sports Limited", "job_title": "Senior Sales and Marketing Officer/Assistant Sales & Marketing Manager", "description": "Plan and implement integrated Marketing campaigns strategically\nDrive\u00a0marketing innovation with internal and external stakeholders to accelerate new member acquisition, demand generation and user/customer engagement programs\nExplore and liaise various joint promotion to strengthen AME brand image and achieve company goals\nWork with Marketing team, Store Management team and Business units to develop Marketing\u00a0/\u00a0Sales materials and Store supporting\nDesign, develop and produce marketing collaterals, include but not limited to ATL, BTL, Digital platforms and Event Management\nAssist in ad-hoc project\nRequirements:\n\nBachelor\u2019s degree or above in Marketing, Business Administration or other related disciplines\nAt least 2 years' relevant experience in Marketing, Corporate Communication or\u00a0Brand Management\nAble to translate ideas into actions and detailed planning\nExcellent communication, presentation and interpersonal skills\nStrong business acumen, strategic mindset, detailed oriented, creative and passionate in agile environment\nA problem solver with a keen sense to event management and in-depth knowledge of marketing technologies in the brand landscape\nProficiency in MS Office applications and Chinese Word Processing\nGood command of spoken and written English and Chinese, knowledge of Putonghua is an advantage", "employment_types": ["Full Time", "Permanent"], "selling_points": [], "locations": ["Kwai Fong"], "categories": ["Sales, CS & Business Devpt", "Business Development", "Marketing / Public Relations", "Marketing - General / Support", "Marketing - Marketing Communication"], "post_time": "2022-01-17T06:47:28Z", "salary": {"currency": null, "max": null, "min": null, "period": "monthly", "term": null}, "salary_visible": false, "title_keywords": ["sales & marketing manager", "assistant", "senior sales", "marketing officer"], "responsibilities": ["liaise", "management team", "management", "ad-hoc", "ideas", "marketing collaterals", "design", "develop", "communication", "planning", "marketing campaigns", "plan", "administration"], "requirements": {"degrees": ["degree or above", "bachelor"], "majors": ["related disciplines", "marketing", "business administration"], "languages": ["putonghua", "english", "chinese"], "language_level": ["advantage", "proficiency", "good command"], "hard_skills": ["chinese word processing", "ms office", "agile", "acumen"], "soft_skills": ["passionate", "detailed oriented", "agile", "problem solver", "keen", "communication", "interpersonal skills", "business acumen", "creative", "presentation", "detailed"], "languages_combined": [{"language": "putonghua", "language_level": ["good command"]}, {"language": "english", "language_level": ["advantage", "good command"]}, {"language": "chinese", "language_level": ["advantage", "proficiency", "good command"]}]}, "experience_required": {"duration": ["at least 2 years"], "field": ["management", "brand", "corporate communication", "marketing", "relevant experience"]}}, {"job_id": "100003009052471", "location_code": "hk", "company": "Fugro Technical Services Limited", "job_title": "Sales Executive", "description": "Responsibilities:\n\nLiaise with overseas customers in order confirmation and handle their daily enquiries;\nCommunicate with China factories and internal parties;\nEnsure accurate and on-time production orders, order status reports and delivery time schedule, etc;\nCoordinate samples development and delivery on time and prepare for customer presentation;\nFollow up the whole merchandising process from product development until production;\nPrepare product related documents and reports;\nHandle ad hoc assignments as required.\n\nRequirements:\n\nHigh diploma or above in Sales and Marketing or related discipline;\nMinimum 2 years experience of merchandising or\u00a0manufacturing\u00a0trading in TOYS\u00a0;\nFamiliar with US & EU market will be advantage;\nStrong interpersonal and time management skill;\nWell-organized, self-motivated, flexible and able to work independently;\nGood PC skill (MS Word, Excel, PowerPoint & Chinese WP is essential);\nImmediate available is preferred.\n\nAttractive salary package will be offered to the right candidates.\u00a0\n\nInterested parties. Please send your full resume including current and expected salary by clicking \u201cApply Now\u201d.\u00a0\u00a0 Personal data will be collected for recruitment purpose only.\n\nLearn us more at www.winfun.com", "employment_types": ["Full Time"], "selling_points": [], "locations": ["Tuen Mun Area"], "categories": ["Engineering", "Others", "Marketing / Public Relations", "Marketing - General / Support"], "post_time": "2022-01-17T03:06:58Z", "salary": {"currency": null, "max": null, "min": null, "period": "monthly", "term": null}, "salary_visible": false, "title_keywords": ["sales executive"], "responsibilities": ["communicate with", "related documents", "merchandising", "coordinate", "reports", "schedule", "ad hoc assignments", "liaise with", "internal parties"], "requirements": {"degrees": ["high diploma or above"], "majors": ["marketing"], "languages": ["chinese"], "language_level": ["good"], "hard_skills": ["excel", "chinese wp", "powerpoint", "pc skill", "ms word"], "soft_skills": ["flexible", "self-motivated", "work independently", "well-organized", "time management skill", "interpersonal"], "languages_combined": [{"language": "chinese", "language_level": ["good"]}]}, "experience_required": {"duration": ["minimum 2 years"], "field": ["toys", "manufacturing", "merchandising", "trading"]}}, {"job_id": "100003009054948", "location_code": "hk", "company": "Pearl Lam Galleries Limited", "job_title": "PR & Communications Executive / Manager", "description": "Responsibilities:\n\nProvide administrative support to the marketing team in accordance with the Company\u2019s Policy and Procedural Systems & Practices\nUpdate internal reports, records and documents in marketing department\nData tabulation and analysis\nCompetitive analysis and reporting\nMarket intelligence \u2013 desk research and field research coordination\nMarketing fund budget administration and control\nProvide general support and administrative duties to the team\nAssist in ad-hoc tasks and projects as required\n\nRequirements:\n\nDiploma holder or above with educational background in Statistics, Data Management, Accounting or Business Administration\n1-2 years relevant work experience in marketing, experience in FMCG will be an advantage, fresh graduates will also be considered\nAdvanced skills with MS Office esp. Excel and Powerpoint\nSelf-starter, quick learner,\u00a0logical thinking and organized\nImmediately availability is preferred\n\nWorking location:\u00a0Kwai Chung\n\nStaff Benefit:\n\nDiscretionary Bonus\nMedical & Life Insurance\nAnnual Leave\nPayable Sick Leave\nEncourage continuing education and on-job training\nOpen office working environment\nOffer promotion opportunities and long-term career path\u00a0\n\nWe offer a competitive remuneration package to the right candidate.\u00a0Interested parties\u00a0please click\u00a0\"Apply Now\"\u00a0to submit your application\u00a0or by email to\u00a0hr1 @twcoffee.com\n\n\u00a0(All personal data provided by applicants will be treated in strict confidence and used for employment-related purpose only.)", "employment_types": ["Full Time"], "selling_points": ["Young and good knowledge in social media platforms", "Excellent written English & Chinese", "Proficiency in Mac OS, MS Office, Adobe Pr/Ai/Ps"], "locations": ["Central & Western Area"], "categories": ["Media & Advertising", "Creative / Design", "Design", "Multi-media", "Marketing / Public Relations", "Marketing - General / Support"], "post_time": "2022-01-17T14:54:35Z", "salary": {"currency": null, "max": null, "min": null, "period": "monthly", "term": null}, "salary_visible": false, "title_keywords": ["executive", "manager"], "responsibilities": ["reporting", "control", "data", "analysis", "systems", "budget", "ad-hoc tasks", "reports", "administrative duties", "coordination", "provide administrative support", "general support", "administration"], "requirements": {"degrees": ["diploma holder"], "majors": ["accounting", "statistics", "business administration"], "languages": [], "language_level": [], "hard_skills": ["excel", "data management", "powerpoint", "ms office"], "soft_skills": ["organized", "advanced", "quick learner"], "languages_combined": []}, "experience_required": {"duration": ["1-2 years"], "field": ["marketing", "fmcg"]}}, {"job_id": "100003009052178", "location_code": "hk", "company": "Hutchison Telecommunications (Hong Kong) Limited", "job_title": "Marketing Executive - Loyalty Marketing", "description": "\u200b\n\nResponsibilities:\n\nReporting to senior leadership, this role will assume responsibilities for spearheading marketing and communications strategy and execution for the Park. \u00a0Other major functions of this job include:\nDevelop integrated marketing and communications strategy that supports and advances the brand awareness and advocacy of the Park and drives positive mindshare that can contribute to the development of the ecosystem in the Park;\u00a0\nDrive external relationships and proactive engagement with local and international stakeholders including relevant government departments, regulatory bodies, universities, R&D institutions, industry leaders and NGOs to lobby for their support for the Park\u2019s vision and strategic imperatives;\u00a0\nSupport business development activities through organizing industry, marketing and community events which engage and appeal to local and overseas tech ventures and startups, incubators, accelerators and top entrepreneurs and talents as well as facilitating partnerships, business matching and corporate engagements;\nResponsible for public affairs, issue and crisis management; taking a proactive role in identifying potential issues, evaluating reputation risks and providing recommendations and communications plans for the senior management;\u00a0\nDevelop compelling messaging for corporate announcements and speaking platforms; and work closely with the Park\u2019s Chairperson, CEO and other senior leaders to develop content assets, not limited to keynote presentations, social media posts, thought leadership pieces spanning across paid, owned and earned media platforms;\nPerform other duties and tasks assigned by Supervisor and CEO.\n\nRequirements:\n\nDegree in Marketing, Communications, Business or related subjects, with at least 12 years of experience in PR, communications, business development and marketing positions, preferably gained in MNC / sizable companies.\nStrong track record in strategic brand management, reputation management and stakeholder engagements for respected companies preferably with presence in Greater China, Greater Bay Area and/or globally.\nGood understanding and appreciation of technology trends. \u00a0Ability to work with global and local technology ventures and startups and provide value-added advice and support to them for promoting their innovations.\nProfound understanding and hands-on experience on government relations and excellent in strategic thinking and able to drive the Park\u2019s corporate narratives that align with various business priorities.\nPossess the ability to work with diverse categories of stakeholders and excellent communications skills that can command impact when interacting with industry players, academia, board members and other key stakeholders etc.\nStrong business acumen, problem solving and leadership skills with excellent command of spoken/written English and Chinese (including Putonghua).", "employment_types": ["Full Time", "Permanent"], "selling_points": [], "locations": ["Tsing Yi"], "categories": ["Marketing / Public Relations", "Marketing - Brand / Product Management", "Marketing - General / Support", "Marketing - Marketing Communication"], "post_time": "2022-01-17T02:23:28Z", "salary": {"currency": null, "max": null, "min": null, "period": "monthly", "term": null}, "salary_visible": false, "title_keywords": ["marketing executive"], "responsibilities": ["reporting", "social media", "perform other duties", "presentations", "develop", "plans", "senior management", "crisis management"], "requirements": {"degrees": ["degree"], "majors": ["business", "marketing", "communications"], "languages": ["putonghua", "english", "chinese"], "language_level": ["excellent"], "hard_skills": ["problem solving", "sizable companies", "acumen"], "soft_skills": ["strategic thinking", "leadership skills", "problem solving", "diverse", "hands-on", "business acumen"], "languages_combined": [{"language": "putonghua", "language_level": ["excellent"]}, {"language": "english", "language_level": ["excellent"]}, {"language": "chinese", "language_level": ["excellent"]}]}, "experience_required": {"duration": ["at least 12 years"], "field": ["pr", "related", "business development", "business", "marketing"]}}, {"job_id": "100003009054089", "location_code": "hk", "company": "Sodexo (Hong Kong) Limited", "job_title": "Marketing Executive / Cooridnator (Ref: PRFP/21)", "description": "Job Duties:\n\nResponsible for food promotions and food program deployments to F&B outlets\nCollect market intelligence in terms of food trend and product performance for strategic planning\nPlan and lead promotions/ food programs to achieve business targets, and evaluate the effectiveness of the activities\nActively involved in coordination of the schedules, logistics and details with both internal and external parties to ensure smooth execution\nAssist company projects as assigned, including deliverables, timeline, cost, prioritization on resources to drive operational efficiency\n\n\u00a0Job Requirements:\u00a0\n\nWith degree / vocational higher diploma in marketing or related discipline\nWith minimum 1-2 years experience of Food and Beverage marketing in hotel or hospitality industries\nFluent in spoken English and Putonghua\nGood computer knowledge in MS Word, Excel and Chinese Word Processing\nProven ability to work in a fast-paced environment\nWell organized, detailed minded and willing to learn\nExcellent communication and interpersonal skills are essential\n\nWe offer competitive remuneration package to the right candidates. Please apply with detailed resume and salary expectations to the Human Resources Department, Sodexo (Hong Kong) Limited by e-mail to hr.hk@ sodexo.com.\u00a0 Please quote PR number on all correspondence.\n\n*Personal data collected is for recruitment purposes only. \u00a0", "employment_types": ["Full Time", "Permanent"], "selling_points": ["Food Promotions & Programs / Marketing Executive", "F&B Outlets, Hotels, Hospitality marketing/PR", "1-2 years experience in F&B marketing"], "locations": ["Yau Tsim Mong Area"], "categories": ["Hospitality / F & B", "Food & Beverage", "Marketing / Public Relations", "Marketing - Brand / Product Management", "Marketing - General / Support"], "post_time": "2022-01-17T08:21:42Z", "salary": {"currency": null, "max": null, "min": null, "period": "monthly", "term": null}, "salary_visible": false, "title_keywords": ["marketing executive"], "responsibilities": ["cost", "strategic planning", "schedules", "internal and external parties", "evaluate", "logistics", "coordination", "plan"], "requirements": {"degrees": ["diploma", "degree"], "majors": ["marketing"], "languages": ["putonghua", "english", "chinese"], "language_level": ["good", "fluent"], "hard_skills": ["excel", "chinese word processing", "ms word"], "soft_skills": ["fast-paced environment", "willing to learn", "well organized", "communication and interpersonal skills", "detailed"], "languages_combined": [{"language": "putonghua", "language_level": ["fluent"]}, {"language": "english", "language_level": ["fluent"]}, {"language": "chinese", "language_level": ["good"]}]}, "experience_required": {"duration": ["minimum 1-2 years"], "field": ["food", "marketing", "hospitality industries"]}}, {"job_id": "100003009052617", "location_code": "hk", "company": "Forsters & Company", "job_title": "e-Commerce Assistant", "description": "Requirements\n\nHigher Diploma/Diploma in e-Commerce, Marketing or equivalent\n1-2 years experience in e-Commerce and online sales operation\nKnowledge of operating social media platforms e.g. Facebook, IG, website\nWell-versed in using MS Word, Excel, PowerPoint, Chinese WP\nSelf-motivated, energetic, flexible and sense of responsibilities\nGood command of English and fair in spoken Mandarin\nImmediate available is a definite advantage\n\nResponsibilities\n\nHandle the daily smooth operation of e-Commerce sales platforms\nUpdate content of online platforms such as new products posting and promotion\nLiaise with e-Commerce partners such as HKTV Mall, Shopify on sales operation\nPerform sales enquiries & logistics issues and ad hoc tasks as assigned\n\nWe offer attractive remuneration package and promising career prospect to the right candidates. Interested parties please send full resume with expected/last salary and date of available by clicking \u2018Apply Now\u2019", "employment_types": ["Full Time", "Permanent"], "selling_points": [], "locations": ["Not Specified"], "categories": ["Marketing / Public Relations", "Marketing - General / Support", "E-commerce", "Business Development", "Marketing - Brand / Product Management"], "post_time": "2022-01-17T06:15:34Z", "salary": {"currency": null, "max": null, "min": null, "period": "monthly", "term": null}, "salary_visible": false, "title_keywords": ["assistant"], "responsibilities": ["liaise with", "ad hoc tasks", "logistics"], "requirements": {"degrees": ["diploma"], "majors": ["marketing", "e-commerce"], "languages": ["english", "chinese", "mandarin"], "language_level": ["good command"], "hard_skills": ["excel", "chinese wp", "e-commerce", "powerpoint", "facebook", "ms word"], "soft_skills": ["flexible", "self-motivated", "energetic", "sense of responsibilities"], "languages_combined": [{"language": "english", "language_level": ["good command"]}, {"language": "chinese", "language_level": []}, {"language": "mandarin", "language_level": ["good command"]}]}, "experience_required": {"duration": ["1-2 years"], "field": ["online sales", "operation", "e-commerce"]}}, {"job_id": "100003009052266", "location_code": "hk", "company": "6C Technology Limited", "job_title": "Sales & Marketing Officer", "description": "Responsibilities:\n\nAssist in marketing reports preparation and data analysis, gather insights in customer behavior and business trend to improve the performance and drives sales;\nAssist the Marketing Manager in the preparation of expense report, cost and budget report;\nWork closely with marketing and sales departments in launching new product programs and execution and completion of projects;\nDevelop the marketing plan for products that support in conjunction with Sales & Marketing team, including key activities and budgets to support the acquisition of new customers and retention of existing customers;\nCollaborate with various internal and external parties to ensure smooth execution of event promotion and operation.\nRequirements:\n\nDegree holder in Marketing, Business Administration, or other related discipline;\nMinimum 3 years of working experience in marketing or sales related discipline;\nWork experience in HORECA, Frozen Meat and food Trading business is an advantage;\nExperience in\u00a0Adobe Illustrator, Photoshop, Facebook, Instagram, Twitter, Wechat, and search engine marketing is a plus but not a must;\nProficient in PC applications, including MS Word, PowerPoint and Excel;\n\nCreative and well-organized with excellent analytical and problem-solving skills;\nExcellent communication and presentation skills;\nAble to excel in fast-paced and dynamic environment with tight deadlines;\nSelf-motivated, result-oriented team player;\nProficient in Chinese and English.\n\nWe offer competitive remuneration and fringe benefits including discretionary bonus, medical insurance, annual leave and 5-day work. Interested party please send detailed resume in both Chinese and English version with expected salary & date of availability by clicking \"Apply Now\".\n\nPersonal data will be used for recruitment purpose only.", "employment_types": ["Full Time", "Part Time", "Permanent", "Temporary", "Contract", "Internship", "Freelance"], "selling_points": [], "locations": ["Tai Po Area"], "categories": ["Marketing / Public Relations", "Marketing - General / Support", "Sales, CS & Business Devpt", "Sales - Sales Management", "E-commerce", "Marketing - Brand / Product Management"], "post_time": "2022-01-17T02:36:38Z", "salary": {"currency": null, "max": null, "min": null, "period": "monthly", "term": null}, "salary_visible": false, "title_keywords": ["sales", "marketing officer"], "responsibilities": ["collaborate with", "budgets", "cost", "budget", "internal and external parties", "develop", "data analysis", "marketing plan", "reports", "report"], "requirements": {"degrees": ["degree holder"], "majors": ["marketing", "business administration"], "languages": ["english", "chinese"], "language_level": ["proficient"], "hard_skills": ["excel", "plus", "ms word", "problem-solving skills", "powerpoint", "wechat", "adobe illustrator", "pc applications", "dynamic", "facebook", "photoshop"], "soft_skills": ["dynamic environment", "self-motivated", "well-organized", "communication", "presentation skills", "problem-solving skills", "team player", "creative", "result-oriented"], "languages_combined": [{"language": "english", "language_level": ["proficient"]}, {"language": "chinese", "language_level": ["proficient"]}]}, "experience_required": {"duration": ["minimum 3 years"], "field": ["related", "marketing", "business", "food", "trading"]}}, {"job_id": "100003009053447", "location_code": "hk", "company": "Madcradle Online Limited", "job_title": "(Senior) Business Development Executive", "description": "Your Role\n\nWe are looking for a Marketing Executive to join our Consumer Broadband Marketing team, responsible for Customer Retention.\u00a0 It is a dynamic opportunity for an all rounded marketer to work for a brand which is striving for differentiation and continual growth.\u00a0 Major job duties include:\n\nImplement marketing campaigns for customer base revenue generation and retention\nSupport regular marketing activities and prepare promotion materials, including DM, eDM etc.\nWork closely with internal parties to ensure launch of marketing campaign timely\nCompile business performance reports and monitor marketing campaign effectiveness\nSupport business and consumer insight analysis, translate findings into insights and actions\nAssist in premium stock management and redemption fulfillment\nHandle day-to-day operations and other ad-hoc projects as assigned\n\nTo Succeed in This Role\n\nUniversity graduate in any discipline\nMinimum 2 years working experience in consumer marketing, CRM or business analysis\nGood business sense with strong analytical abilities and presentation skills\nStrong interpersonal skills, attentive to details and highly motivated\nAble to work independently\nExcellent command of written and spoken English and Cantonese\nLess experience will be considered as Marketing Assistant", "employment_types": ["Full Time", "Permanent"], "selling_points": ["Locate new clients & follow up sales lead", "Assist to execute inhouse marketing plan", "Manage clients\u2019 Marketing & advertising projects"], "locations": ["Kwun Tong"], "categories": ["Sales, CS & Business Devpt", "Business Development", "Marketing / Public Relations", "Marketing - Direct Marketing", "Marketing - General / Support"], "post_time": "2022-01-17T06:59:53Z", "salary": {"currency": null, "max": null, "min": null, "period": "monthly", "term": null}, "salary_visible": false, "title_keywords": ["business development executive"], "responsibilities": ["stock management", "performance reports", "edm", "analysis", "fulfillment", "monitor", "day-to-day operations", "marketing campaigns", "business analysis", "ad-hoc projects", "internal parties"], "requirements": {"degrees": ["university graduate"], "majors": [], "languages": ["cantonese", "english"], "language_level": ["excellent"], "hard_skills": ["analysis", "dynamic"], "soft_skills": ["work independently", "responsible", "business sense", "attentive to details", "timely", "presentation skills", "dynamic", "interpersonal skills", "motivated"], "languages_combined": [{"language": "cantonese", "language_level": ["excellent"]}, {"language": "english", "language_level": ["excellent"]}]}, "experience_required": {"duration": ["minimum 2 years"], "field": ["business analysis", "marketing"]}}, {"job_id": "100003009053443", "location_code": "hk", "company": "Sunpower Production Limited", "job_title": "Senior Sales Executive, Sales & Marketing", "description": "We are now looking for a\u00a0Digital Marketing Specialist to join our team. Your\u00a0direct\u00a0responsibilities\u00a0include creating, managing and executing campaign and activations calendar that can build the brand awareness and drive impacts.Manage and create for our online platforms, e.g. website, Facebook, Instagram, WeChat, mobile app, and other digital platforms, as well as planning and execute all brand communications and media actions on all channels.\n\nMAIN RESPONSIBILITIES:\n\n\n\nCreating, managing and executing campaign and activations calendar that can build the brand awareness and drive impacts.\nManage and create content for our online platforms, e.g. website, Facebook, Instagram, WeChat, mobile app, and other digital platforms.\nPlanning and execute all brand communications and media actions on all channels.\nExplore new promotion or collaboration opportunities with relevant partners.\nSupervise all activities related to the brand. Ensuring that messaging and marketing activities are aligned with brand and company values.\nCome up with briefs, manage marketing agency or internal teams for development of brand campaigns and activations.\nManage the communications of third-party partners to drive the brand forward and work with brand influencers for driving the brand and audience reach.\nCollaborating with different teams such as Admissions, Faculty, Facilities, operations etc.\nMonitor the brand health and manage the brand tracking study and generate weekly, monthly performance reports and forecast predictions.\nKeep up on the changes in the industry with competitors and audience insights analysis.\n\nREQUIREMENTS:\n\nStrong project management skills with the ability to supervise multiple projects.\nHas knowledge executing the followings: campaign management, media activities, video production, photo shooting, and partners\u2019 communications management.\nExperience in brand health tracking, market research.\nProficiency with word processing, spreadsheet and presentation software (MS Office/Google)\nAbility to think strategically and come up with campaigns and activations ideas.\nBe an excellent team player, as well as keeping an open mind.\nStrong project management experience, across multiple teams and geographical.\nKnowledge in Adobe photoshop, illustrator, etc, will be an advantage.\nGood personality, positive attitude, able to work independently.\nExcellent command in written & spoken Cantonese and English.\nAt least 2 years of work experiences in the marketing sector, experience in the Education industry will be an advantage.\nProficiency in MS Office Application, Word, Excel, PowerPoint, Google Business Apps and all social media platform.\nCandidate with more experience will be considered for a senior position.\n\nWhy\u00a0IMS?\n\nYou want to have a job you\u2019re actually eager to come to every single day, with people that will inspire and challenge you. This is an outstanding opportunity to see your projects and efforts come to fruition, and feel real ownership on the job.\n\nPerks\n\nSunny space in beautiful Stanley with one of the best views in HK, you\u2019ll feel on holidays every single day!\nA fantastic work environment with lots of learning opportunities\nNot two days are the same when you work on education, prepare to be wowed, moved and inspired on a weekly basis\n\nLocation: Stanley Campus\n\nInterested parties please send full resume with availability\u00a0and expected salary by\u00a0clicking \"APPLY NOW\".\u00a0\n\nPersonal data collected will be used for recruitment purpose only.", "employment_types": ["Full Time"], "selling_points": [], "locations": ["Not Specified"], "categories": ["Admin & HR", "Others", "Marketing / Public Relations", "Marketing - General / Support", "Others"], "post_time": "2022-01-17T06:59:52Z", "salary": {"currency": null, "max": null, "min": null, "period": "monthly", "term": null}, "salary_visible": false, "title_keywords": ["senior sales executive", "sales"], "responsibilities": ["tracking", "mobile app", "performance reports", "operations", "analysis", "teams", "website", "monitor", "executing", "forecast", "facebook", "planning"], "requirements": {"degrees": [], "majors": [], "languages": ["cantonese", "english"], "language_level": ["excellent"], "hard_skills": ["excel", "adobe photoshop", "word processing", "illustrator", "word", "powerpoint", "project management", "spreadsheet", "ms office"], "soft_skills": ["work independently", "project management skills", "positive attitude", "project management", "learning", "think strategically", "team player", "presentation"], "languages_combined": [{"language": "cantonese", "language_level": ["excellent"]}, {"language": "english", "language_level": ["excellent"]}]}, "experience_required": {"duration": ["at least 2 years"], "field": ["brand", "market research", "education", "project management", "marketing"]}}, {"job_id": "100003009051989", "location_code": "hk", "company": "BUDA Surveying Ltd", "job_title": "Marketing Assistant Officer", "description": "Our client is a listed energy company. They are looking for an Assistant Marketing Coordinator to support their team.\n\nJob Responsibilities:\n\nAs a team member focus on ECO fun project\nPlanning, design & implementation of ECO fun project\nLiaising with both internal and external parties to conduct the task\nAnalyse, monitoring & evaluation on the project\nHandle enquires from different parties\nSupport ad-hoc task from other team\n\nJob Requirements:\n\nBachelor degree or above in business or other relevant disciplines\nGood command of English and Chinese language skills\nWilling to learn\nGood communication skill\nAt least 3 years of work experience\nWell organized, strong interpersonal skills, team player, self-starter and able to work under pressure\nStrong problem solving and interpersonal skills\nProficient in Microsoft Office applications; familiar with SAP would be an advantage\n\n\n\nInterested parties, please\u00a0CLICK HERE\u00a0to apply online.\n\nPlease note that only short-listed candidates will be notified. All information gathered will be treated in strict confidence and solely used for recruitment purposes.", "employment_types": ["Full Time", "Part Time", "Temporary"], "selling_points": [], "locations": ["Kwai Hing"], "categories": ["Marketing / Public Relations", "Marketing - General / Support", "Others", "Student / Fresh Graduate / No Experience"], "post_time": "2022-01-17T01:46:24Z", "salary": {"currency": null, "max": null, "min": null, "period": "monthly", "term": null}, "salary_visible": false, "title_keywords": ["marketing assistant officer"], "responsibilities": ["ad-hoc", "evaluation", "internal and external parties", "monitoring", "liaising with", "implementation", "design", "analyse", "planning"], "requirements": {"degrees": ["degree or above", "bachelor"], "majors": ["business"], "languages": ["english", "chinese"], "language_level": ["good command"], "hard_skills": ["problem solving", "sap", "microsoft office"], "soft_skills": ["communication skill", "willing to learn", "well organized", "problem solving", "interpersonal skills", "team player", "work under pressure"], "languages_combined": [{"language": "english", "language_level": ["good command"]}, {"language": "chinese", "language_level": ["good command"]}]}, "experience_required": {"duration": ["at least 3 years"], "field": []}}, {"job_id": "100003009054001", "location_code": "hk", "company": "T & Y Biologics Investment Limited", "job_title": "Marketing - Senior Officer/ Assistant Manager (Petmacy \u5bf5\u7269\u85e5\u599d)", "description": "Job Description\n\nLocate new business opportunities as potential digital marketing products both independently and under the guidance of team leader;\nProspecting, identifying and acquiring new HK based clients for selling online marketing advertising solutions (e.g. WeChat/China Advertising/China KOLs,etc);\nFollow up sales Leads, prepare sales pitch and agreements with marketing team;\nMaintain good relationships with clients, regular review and up-selling various advertising solutions to enhance their advertising performance/effect;\nExecute inhouse media investment plan by working closely with Marketing Director to enhance the market impact of Our Company;\nManage clients\u2019 projects, including defining deliverables, schedule and setting milestones, resources planning, coordinating internal resources, expectation management, launch, KPI tracking and post-campaign evaluation, etc.\n\nThe Successful Applicant\n\n1-4 years Sales or Marketing / Advertising / PR experience;\nOnline-media savvy is a big advantage;\nKnowledge in China media (social media, KOLs, Tencent, Douyin, Xiaohongshu, Video platform, etc), but not a must, training will be delivered;\nCreative, Dynamic, embracing changes personally;\nGood communication skills in both English & Chinese;\nImmediate availability is preferred;\nCandidate with higher qualification and relevant working experience will be considered as Senior Business Development Executive / Assistant Business Development Manager.\n\nWhat's On Offer\n\nAttractive Remuneration Package and Benefits\nIncentive & commission schemes will be offered\n5-day work\nBank Holidays and other special leave (e.g. Birthday Leave, Wedding Leave and Family Leave, etc.)\nMedical Insurance\nSales and Product training will be provided\nTeam Building Activities\nOpportunity for Job Promotion\nFriendly Work Environment\nInterest parties please send your CV with availability, current and expected salary to us.\n\n**Personal data collected will be used for recruitment purpose only**\n", "employment_types": ["Full Time", "Permanent"], "selling_points": ["Lead a small team to provide management support", "Develop Promotion Calendar", "Create and support marketing campaigns"], "locations": ["Kwun Tong"], "categories": ["Marketing / Public Relations", "Management", "Marketing - Direct Marketing", "Marketing - General / Support"], "post_time": "2022-01-17T08:00:53Z", "salary": {"currency": null, "max": null, "min": null, "period": "monthly", "term": null}, "salary_visible": false, "title_keywords": ["senior officer", "assistant manager"], "responsibilities": ["guidance", "management", "tracking", "advertising", "social media", "business opportunities", "prepare sales", "regular review", "communication", "maintain", "digital marketing", "schedule", "plan", "evaluation", "planning"], "requirements": {"degrees": [], "majors": [], "languages": ["english", "chinese"], "language_level": ["good"], "hard_skills": ["dynamic", "wechat"], "soft_skills": ["communication skills", "dynamic", "independently", "creative"], "languages_combined": [{"language": "english", "language_level": ["good"]}, {"language": "chinese", "language_level": ["good"]}]}, "experience_required": {"duration": ["1-4 years"], "field": ["pr", "advertising", "business development", "relevant working experience", "marketing"]}}, {"job_id": "100003009052197", "location_code": "hk", "company": "IPSOS Asia Limited", "job_title": "Temporary Research Assistant (Temp to Perm)", "description": "\nJob Description\nResponsibilities:\n\u2022 Make outbound calls/ cold call to exploit business opportunities and increase market share.\n\u2022 Explore potential customers and maintain good relationships with key customers.\n\u2022 Sales-oriented with strong commitment towards sales target achievement.\n\u2022 Work closely with sales manager/ management to provide regular feedback for sales and services improvement.\n\u2022 Prepare sales reports, analysis and sales forecast.\n\u2022 Setting up meetings with potential clients.\n\u2022 Liaise with internal teams such as project management and design team.\nRequirements:\n\u2022 Work experience with technical background in Printing products/ Packaging Printing / Paper Products/ Telecommunications field is preferred.\n\u2022 Good command of writing and spoken English & Cantonese.\nFamiliar with MS Office (i.e. Excel, Word).\n\u2022 Good leaner, stable, good communication & negotiation skills.\n\u2022 Aggressive, proactive and hard working.\n\u2022 Applicants with more experience will be considered as Assistant Manager.\n\u2022 Newly graduated is welcome.\nWe offer basic salary plus commission based on sales accomplished.\nInterested parties, please send full resume with expected salary to Apply Now and Apply Now .\n*Personal data will be used for recruitment purpose only.\n\n", "employment_types": ["Full Time", "Part Time", "Permanent", "Temporary", "Contract", "Internship", "Freelance"], "selling_points": ["Data analysis", "Quantitative research", "Project Management"], "locations": ["Hung Hom"], "categories": ["Professional Services", "Business Analysis / Data Analysis", "Marketing / Public Relations", "Marketing - General / Support", "Marketing - Market Research"], "post_time": "2022-01-17T02:26:11Z", "salary": {"currency": null, "max": null, "min": null, "period": "monthly", "term": null}, "salary_visible": false, "title_keywords": ["research assistant"], "responsibilities": ["management", "sales target", "business opportunities", "prepare sales", "analysis", "teams", "design", "project management", "maintain", "reports", "forecast", "liaise with"], "requirements": {"degrees": [], "majors": [], "languages": ["cantonese", "english"], "language_level": ["good command"], "hard_skills": ["excel", "word", "ms office"], "soft_skills": ["hard working", "communication", "negotiation skills", "stable", "proactive"], "languages_combined": [{"language": "cantonese", "language_level": ["good command"]}, {"language": "english", "language_level": ["good command"]}]}, "experience_required": {"duration": [], "field": ["telecommunications"]}}, {"job_id": "100003009053261", "location_code": "hk", "company": "AA Choice Personnel Consultancy Limited", "job_title": "Non-Ethnic Chinese Activity Coordinator - Urdu or NEC Speaking (5 days)", "description": "JOB ROLE AND RESPONSIBILITIES:\n\nParticipate in aftersales operations development projects\nPlan and conduct marketing campaigns & activities to strengthen market position\nManage and analyse sales and market data for strategic planning\nAssist in exploring new business opportunities\nCoordinate ad hoc projects and service campaigns\n\nSKILLS AND EXPERIENCE REQUIRED:\n\nBachelor degree holder in Business, Automotive or related disciplines\nMinimum 2 years relevant experience\nStrong passion on the automotive industry\nOut-going personality with innovative mindset\nA good team player with positive work attitude and self-motivation\nExcellent command of written and spoken English and Chinese\nExcellent command of PC application experiences in statistical analysis\nHolder of valid driver license no. 1 & 2 is an advantage\n\n\nPersonal data provided by applicants will be used for recruitment purpose only", "employment_types": ["Full Time", "Contract"], "selling_points": ["Urdu or other NEC languages", "Able to communicate in Chinese and English", "Government Contract, fresh graduate welcome"], "locations": ["Wan Chai"], "categories": ["Admin & HR", "Clerical / Admin Staff", "Public / Civil", "Civil Services", "Marketing / Public Relations", "Marketing - General / Support"], "post_time": "2022-01-17T06:36:20Z", "salary": {"currency": null, "max": null, "min": null, "period": "monthly", "term": null}, "salary_visible": false, "title_keywords": ["coordinator"], "responsibilities": ["strategic planning", "operations", "business opportunities", "analysis", "coordinate", "ad hoc projects", "recruitment", "marketing campaigns", "plan", "personal data", "market data", "analyse"], "requirements": {"degrees": ["bachelor degree holder"], "majors": ["related disciplines", "business"], "languages": ["english", "chinese"], "language_level": ["excellent"], "hard_skills": ["pc", "no", "statistical analysis"], "soft_skills": ["self-motivation", "good team player", "innovative", "positive work attitude"], "languages_combined": [{"language": "english", "language_level": ["excellent"]}, {"language": "chinese", "language_level": ["excellent"]}]}, "experience_required": {"duration": ["minimum 2 years"], "field": ["relevant experience"]}}, {"job_id": "100003009054185", "location_code": "hk", "company": "Smartech International Marketing Limited", "job_title": "Sales and Marketing Officer/Assistant", "description": "Job Description:\n\nHandle full cycle recruitment process, including ad posting, screening CV, shortlisting candidates and salary negotiation\nBuild and maintain good relationship with clients\nArrange roster and on-broad arrangement for candidates\nPrepare regular monthly and weekly reports\nManage ad-hoc task/project as assigned by supervisors\nDevelop good understanding of our clients and maintain good relationship with them\n\nRequirement:\n\nHigher Diploma/ Bachelor's degree holder in any discipline\nPossess good communication and interpersonal skills\nFluent in English, Mandarin is an advantage\nStrong sense of client servicing, pro-active and willing to take up responsibilities\nEager to learn and able to work independently\nPassionate in client servicing and recruitment industry\nImmediate available is highly preferred\nFresh graduate is welcome\n\n\u00a0Interested parties, please email your CV with expected salary to\u00a0yanmi.leung@manpowergrc.hk\u00a0", "employment_types": ["Full Time"], "selling_points": ["Sales & Marketing", "Guarantee income", "Special + performance bonus"], "locations": ["Quarry Bay"], "categories": ["Marketing / Public Relations", "Marketing - General / Support", "Marketing - Marketing Communication", "Sales, CS & Business Devpt", "Retail Sales"], "post_time": "2022-01-17T08:42:32Z", "salary": {"currency": null, "max": null, "min": null, "period": "monthly", "term": null}, "salary_visible": false, "title_keywords": ["assistant", "sales", "marketing officer"], "responsibilities": ["ad-hoc", "weekly reports", "develop", "maintain good relationship", "recruitment process"], "requirements": {"degrees": ["diploma", "bachelor", "fresh graduate", "degree holder"], "majors": [], "languages": ["english", "mandarin"], "language_level": ["advantage", "fluent"], "hard_skills": [], "soft_skills": ["passionate", "work independently", "eager to learn", "communication and interpersonal skills", "pro-active"], "languages_combined": [{"language": "english", "language_level": ["advantage", "fluent"]}, {"language": "mandarin", "language_level": ["advantage", "fluent"]}]}, "experience_required": {"duration": [], "field": []}}, {"job_id": "100003009048078", "location_code": "hk", "company": "iPR Ogilvy Limited", "job_title": "Co-ordinator (Marketing Communications)", "description": "Responsibilities:\n\nAssist in preparing CRM strategies to maximize business opportunities\nAssist in CRM promotions to drive customer loyalty and business\nDatabase management to prepare regular reports and insights on business performance, marketing intelligence, customer experience and program effectiveness\nAssistant ongoing system enhancement\nCommunication and work independently with internal and external parties\nAssist in marketing projects assigned\n\nRequirements:\u00a0\n\nUniversity graduate in marketing, communications or related disciplines\nMinimum 2 year relevant experience in retail / FMCG industry\nWith experience in CRM / loyalty marketing and etc.\nExcellent communication, organization and coordination, self-motivated, initiative, good ability to prioritize tasks efficiently and effectively\nPatient, positive, independent, creative, energetic and a good team player\nGood command in spoken and written English, Cantonese and Mandarin\nProficient in PC skills (MS Word/Excel/Power Point/Chinese Work Processing\nImmediate available is preferred\n\nWe offer 5-day work week, discretionary bonus, medical insurance, annual leave and staff purchase discount. Interested parties, please send full resume with current & expected salary and the date of availability by click \u201cApply Now\u201d or mail to Human Resources Department, CR Care Co. Ltd., 8/F., Pak Sik Godown No. 2, 15-29 Wo Shui St., Fotan, Shatin, N.T.\n\n(All information collected will be used for recruitment related purpose only.)", "employment_types": ["Full Time", "Permanent"], "selling_points": ["Support Marketing Comm. services", "Degree holder", "Excellent communication skills"], "locations": ["Wan Chai"], "categories": ["Marketing / Public Relations", "Marketing - General / Support", "Marketing - Marketing Communication", "Public Relations - Event Management"], "post_time": "2022-01-14T04:43:44Z", "salary": {"currency": null, "max": null, "min": null, "period": "monthly", "term": null}, "salary_visible": false, "title_keywords": [], "responsibilities": ["management", "business opportunities", "internal and external parties", "marketing projects", "communication", "reports", "database"], "requirements": {"degrees": ["university graduate"], "majors": ["related disciplines", "marketing", "communications"], "languages": ["cantonese", "english", "chinese", "mandarin"], "language_level": ["good command", "proficient"], "hard_skills": ["excel", "processing", "fmcg industry", "power point", "pc skills", "ms word"], "soft_skills": ["self-motivated", "good team player", "independent", "prioritize", "communication", "energetic", "coordination", "patient", "creative", "initiative", "positive"], "languages_combined": [{"language": "cantonese", "language_level": ["good command"]}, {"language": "english", "language_level": ["good command"]}, {"language": "chinese", "language_level": ["proficient"]}, {"language": "mandarin", "language_level": ["good command"]}]}, "experience_required": {"duration": ["minimum 2 year"], "field": ["marketing", "retail", "relevant experience", "fmcg"]}}, {"job_id": "100003009055561", "location_code": "hk", "company": "Chandler Macleod Group (HK) Limited", "job_title": "Senior/ Marketing Executive (Financial Services)", "description": "Responsibilities:\n\n\n\n\nResponsible for all marketing related issue, not limited to liaising and coordinating with external parties for the preparation and delivery of marketing communication materials, marketing events or other related marketing activities\nDesign and execute production and publication of marketing collaterals (e.g. brochure, face sheet, website, video, presentations) from sketch\nManage all the marketing & public relations activities including e-marketing, seminars organization and other award and sponsorship programs\nMaintain on-going content and platform maintenance of company website, campaign minisite and social media platforms\nAssist Marketing Manager to drive and implement strategic PR campaigns for brand positioning and enhancing brand image and awareness\nAssist in any ad-hoc tasks or duties as requested\n\nRequirements:\n\n\n\n\nDegree holder in marketing/communications or business-related discipline\nMinimum 1 years of relevant working experience, preferably in professional services provider/financial services\nKnowledge of SEO, social media (Linkedln, Wechat etc) and analytics reporting\nGood project management skills, with attention to detail and quality\nStrong customer and results oriented, with ability to interact effectively at all levels with sensitivity\nSelf-starter and able to prioritize workloads effectively, able to work independently as well as be a team player\nProficient with MS office, Excel and PowerPoint\nGood command of both spoken and written Chinese and English", "employment_types": ["Full Time", "Permanent"], "selling_points": ["Multinational Working Environment", "Genuine Development Opportunity", "A Growing Business"], "locations": ["Not Specified"], "categories": ["Marketing / Public Relations", "Marketing - Direct Marketing", "Marketing - General / Support", "Digital Marketing"], "post_time": "2022-01-18T02:43:21Z", "salary": {"currency": null, "max": null, "min": null, "period": "monthly", "term": null}, "salary_visible": false, "title_keywords": ["marketing executive"], "responsibilities": ["marketing events", "maintenance", "ad-hoc tasks", "external parties", "marketing collaterals", "website", "design", "presentations", "communication", "social media platforms", "maintain", "company website", "publication"], "requirements": {"degrees": ["degree holder"], "majors": ["business", "marketing", "communications"], "languages": ["english", "chinese"], "language_level": ["good command"], "hard_skills": ["excel", "seo", "powerpoint", "wechat", "project management", "ms office"], "soft_skills": ["work independently", "able to prioritize", "project management skills", "sensitivity", "attention to detail", "team player"], "languages_combined": [{"language": "english", "language_level": ["good command"]}, {"language": "chinese", "language_level": ["good command"]}]}, "experience_required": {"duration": ["minimum 1 years"], "field": ["financial services", "relevant working experience"]}}, {"job_id": "100003009054751", "location_code": "hk", "company": "Starlite Holdings Limited", "job_title": "PR and Marketing Manager", "description": "Responsibilities:\n\nDevelop PR and branding, marketing strategies for the Center from scratch;\nDesign, execute and perform tracking of PR, branding and marketing programs;\nPromote the Center through different channels including website, e-newsletter, social media, printed and electronic media, etc;\nHandle PR and media relations such as interviews and media activities; maintain good relations with the media;\nCollaborate and communicate with the University partners, local and overseas research collaborators, and the industry to promote our company.\nOrganize various kinds of events and workshops e.g. conferences, award ceremonies, seminars, public events, planning, budget control, execution and event logistics\n\nRequirements:\n\nA bachelor or higher degree preferably in business, communication, marketing, public relations, or science;\n\u00a0At least 5 years\u2019\u00a0experience in PR or marketing fields and experience in social media and writing would be an advantage;\nSmart,\u00a0mature, organized with pleasant personality and\u00a0strong interpersonal skills;\nAttentive to details, creative, independent, proactive and flexible to meet tight schedule;\nPossess excellent communication skills, media relations experience and network;\nProficiency in the design and production of marketing materials; Basic knowledge of graphic design and proficient in Adobe Photoshop, Illustrator and PowerPoint;\nGood command of spoken & written English and Chinese.\n\nWe offer a competitive package & career prospect to the right candidate. Qualified and interested parties, please send application quoting the above reference number and detailing contact information, education and employment background, and salary expectation via : \u201cAPPLY NOW\u201d\n\nOnly shortlisted candidates will be contacted. For more information, please be welcome to visit our \uff1awebsite: www.hkstarlite.com /\u00a0\u00a0https://teamgreenworld.net/\n\nPersonal data provided will be used for consideration of your application for the applied position and other suitable vacancies in the Starlite Group.", "employment_types": ["Full Time", "Permanent"], "selling_points": ["Five-day work week", "Medical insurance", "Immediately available is highly preferred"], "locations": ["Wong Tai Sin Area"], "categories": ["Marketing / Public Relations", "Marketing - General / Support", "Public Relations - Event Management", "Public Relations - General / Support"], "post_time": "2022-01-17T10:53:35Z", "salary": {"currency": null, "max": null, "min": null, "period": "monthly", "term": null}, "salary_visible": false, "title_keywords": ["marketing manager"], "responsibilities": ["collaborate", "social media", "communicate with", "marketing strategies", "website", "design", "develop", "conferences", "maintain", "planning", "logistics", "budget control", "tracking"], "requirements": {"degrees": ["degree", "bachelor"], "majors": ["science", "business", "marketing"], "languages": ["english", "chinese"], "language_level": ["good command"], "hard_skills": ["adobe photoshop", "basic", "illustrator", "powerpoint"], "soft_skills": ["flexible", "organized", "communication skills", "proactive", "independent", "attentive to details", "mature", "pleasant", "communication", "interpersonal skills", "creative"], "languages_combined": [{"language": "english", "language_level": ["good command"]}, {"language": "chinese", "language_level": ["good command"]}]}, "experience_required": {"duration": ["at least 5 years"], "field": ["social media", "pr", "marketing", "writing", "media"]}}, {"job_id": "100003009046087", "location_code": "hk", "company": "The Hong Kong Institute Of Bankers", "job_title": "Officer - Projects and Events", "description": "In order to cope with our company expansion, we are looking for the following candidate:\n\nJob responsibilities:\n-Handle sales and marketing activities\n-Support internal parties to fulfill challenging duties\n-Follow up orders and after sales services\n-Explore new clients\n-Organize and participate in promotion events\n\n\nRequirements:\n-Degree holder or High Diploma with 2 years of working experience\n-Well-organized,outgoing,and a good team player\n-Good command of English, Mandarin and Cantonese\n-Good PC Knowledge (Prefer Photoshop and Adobe Illustrator)\n-Experience in public relations and sales activities is a plus\n\n\nWe offer:\nGuarantee income + commission\nSpecial + performance bonus\nOn-the-job\u00a0training\nStaff purchase discount\n\n\n* FRESH GRADUATES and less working experiences will be considered as sales and marketing assistant.", "employment_types": ["Full Time", "Permanent"], "selling_points": ["Great development opportunity", "Membership Benefit and Events", "Banking & Finance Institution"], "locations": ["Sheung Wan"], "categories": ["Marketing / Public Relations", "Marketing - General / Support", "Public Relations - Event Management", "Public Relations - General / Support"], "post_time": "2022-01-16T21:50:15Z", "salary": {"currency": null, "max": null, "min": null, "period": "monthly", "term": null}, "salary_visible": false, "title_keywords": ["officer"], "responsibilities": ["internal parties"], "requirements": {"degrees": ["high diploma"], "majors": [], "languages": ["cantonese", "english", "mandarin"], "language_level": [], "hard_skills": ["adobe illustrator", "pc knowledge", "plus", "photoshop"], "soft_skills": ["outgoing", "organized", "good team player"], "languages_combined": [{"language": "cantonese", "language_level": []}, {"language": "english", "language_level": []}, {"language": "mandarin", "language_level": []}]}, "experience_required": {"duration": ["2 years"], "field": []}}, {"job_id": "100003009054102", "location_code": "hk", "company": "Endeavour Search Limited", "job_title": "Associate Director (Marketing & Corporate Communications) - HK & GBA Presences", "description": "To provide high-quality deliverables in marketing campaign and communications to HKIB members and stakeholders by supporting the Marketing, Membership & Events (MME) Team to enhance Membership engagement and build brand awareness. \u00a0\n\nJob Responsibilities\n\nProvide administrative support to projects and events covering conferences, awards, seminars and government funded activities targeting different stakeholders\nHandle registration, payment, CRM entries, enquiries relating to MME projects and events targeting different stakeholders ranging from senior secondary schools & university students; current and potential banking practitioners at different seniority\nProvide draft write-ups including event invitations, messages to members, social media posts, pre and post-event promotions, etc.\nSolicit cross-team support and collaborate with vendors to ensure smooth execution\nHandle any ad-hoc projects or tasks assigned by supervisors\n\u00a0\n\nJob Requirements\n\nUniversity degree holder or above, preferably in marketing or event management\nMinimum 3 years of experience preferably from marketing or event management\nStrong communications skills and attention to details\nProactive and a good team player\nOutgoing, curious and resourceful\nExcellent English and Chinese writing skills\nFluent in spoken English, Cantonese and Putonghua\nGood PC skills including MS Office, Adobe and simple website editing\nCandidates with more experience will be considered for the Senior Officer position\n\nInterested parties may send in your application together with a detailed resume stating your\u00a0academic results, present & expected salaries, date of availability\u00a0and contact phone number by clicking\u00a0\"Apply Now\"\n\nApplicants are welcome to visit our website:\u00a0www.hkib.org\u00a0for further information about the institute.\n\n(All information provided will be treated in strict confidence and used solely for recruitment purposes)", "employment_types": ["Full Time", "Permanent"], "selling_points": ["Stable, long term career development", "Semi-government technology organization", "Fluent English & Mandarin"], "locations": ["Shatin Area"], "categories": ["Marketing / Public Relations", "Marketing - General / Support", "Marketing - Marketing Communication", "Public Relations - General / Support"], "post_time": "2022-01-17T08:23:22Z", "salary": {"currency": null, "max": null, "min": null, "period": "monthly", "term": null}, "salary_visible": false, "title_keywords": ["associate director"], "responsibilities": ["collaborate with", "social media", "conferences", "payment", "banking", "provide administrative support", "ad-hoc projects"], "requirements": {"degrees": ["university degree"], "majors": ["marketing"], "languages": ["cantonese", "putonghua", "english", "chinese"], "language_level": ["excellent", "fluent"], "hard_skills": ["simple", "writing skills", "adobe", "pc skills", "ms office"], "soft_skills": ["outgoing", "good team player", "resourceful", "writing skills", "attention to details", "proactive"], "languages_combined": [{"language": "cantonese", "language_level": ["fluent"]}, {"language": "putonghua", "language_level": ["fluent"]}, {"language": "english", "language_level": ["excellent", "fluent"]}, {"language": "chinese", "language_level": ["excellent"]}]}, "experience_required": {"duration": ["minimum 3 years"], "field": ["management", "marketing"]}}, {"job_id": "100003009055688", "location_code": "hk", "company": "Manpower Services (Hong Kong) Limited", "job_title": "Sales Executive/Analyst_ Mining/Smelter", "description": "Job Duties:\n\nSupport senior management in sales activities\u00a0\nAnalysis of the commodity\u00a0market development in China/other countries\nConduct feasibility and potential profitability analysis of the new product lines\nServe the assigned corporate account for business development\n\nRequirements:\n\nDegree holder with good knowledge of physical commodities trading (raw materials, energy, metals, and minerals)\nExperience in the commodity industry in both analytical and trading aspects\u00a0\nExperience in the letter of credit and handling physical trading contracts\nProfessional presentation and analytical skills\nGood written skills\nFluent English and Mandarin\n\nInterested parties, please write to charlton.chan@manpowergrc.hk", "employment_types": ["Permanent"], "selling_points": ["Knowledge of smelter and mining", "Professional written & presentation skills", "Very Fluent English & Mandarin"], "locations": ["Central & Western Area"], "categories": ["Transportation & Logistics", "Documentary Credit / Bills Processing", "Marketing / Public Relations", "Marketing - General / Support", "Sales, CS & Business Devpt", "Sales - Sales Management"], "post_time": "2022-01-18T02:51:12Z", "salary": {"currency": null, "max": null, "min": null, "period": "monthly", "term": null}, "salary_visible": false, "title_keywords": ["analyst", "sales executive"], "responsibilities": ["sales activities", "senior management", "analysis"], "requirements": {"degrees": ["degree holder"], "majors": [], "languages": ["english", "mandarin"], "language_level": ["fluent"], "hard_skills": ["analytical skills"], "soft_skills": ["presentation", "analytical skills"], "languages_combined": [{"language": "english", "language_level": ["fluent"]}, {"language": "mandarin", "language_level": ["fluent"]}]}, "experience_required": {"duration": [], "field": ["trading", "analytical"]}}, {"job_id": "100003009053748", "location_code": "hk", "company": "Fullteam Information Technology Limited", "job_title": "Digital Marketing Assistant - Part time", "description": "Responsibilities:\n\nResponsible for following up tenders / quotations / proposals;\nLiaise with various project teams to facilitate the preparation of tender and quotation submissions;\nMaintain good relationships with existing clients and follow up with prospects;\nAssist in organising seminars and business development activities as needed;\nPerform administrative and marketing duties as assigned.\n\n\nRequirements:\n\nBachelor\u2019s degree in Marketing, Engineering, Environmental Services or related disciplines;\nMinimum of 2 years of relating work experience, preferably in an engineering, environmental services or construction industry;\nBusiness development experience preferred;\nProactive and customer-oriented and a good team player;\nMust have demonstrated strong interpersonal skills and ability to build relationships at all levels.", "employment_types": ["Full Time"], "selling_points": [], "locations": ["Kwun Tong"], "categories": ["Admin & HR", "Others", "Marketing / Public Relations", "Marketing - General / Support", "Others"], "post_time": "2022-01-17T07:27:27Z", "salary": {"currency": null, "max": null, "min": null, "period": "monthly", "term": null}, "salary_visible": false, "title_keywords": ["digital marketing", "assistant"], "responsibilities": ["quotation", "teams", "maintain", "tender", "liaise with"], "requirements": {"degrees": ["degree", "bachelor"], "majors": ["related disciplines", "marketing", "engineering"], "languages": [], "language_level": [], "hard_skills": [], "soft_skills": ["good team player", "customer-oriented", "proactive", "interpersonal skills"], "languages_combined": []}, "experience_required": {"duration": ["minimum of 2 years"], "field": ["construction industry", "environmental", "engineering", "business development"]}}, {"job_id": "100003009049711", "location_code": "hk", "company": "BNI Association Limited", "job_title": "Marketing and Administration Executive", "description": "\nResponsibilities:\n\u2022 implement online marketing activities and explore new digital marketing channels\n\u2022 assisting in SEO and SEM\n\u2022 assist in company EDM\n\u2022 administrate and update the company websites\nRequirements:\n\u2022 post secondary education or training in digital marketing, graphic design is an advantage\n\u2022 good at graphic design is an advantage\n\u2022 have eperience in email marketing & data analytic\n\u2022 Good English and Chinese writing skill\n\u2022 knowledge in photoshops, AI, video editing software, EDM tools\nOffer:\n$60.00 - $80.00 per hours\nMondat to Friday\n10:00 - 13:00 or 14:00 - 17:00\nPls contact : +852-39572480\nEmail:Apply Now\nFULLTEAM INFORMATION TECHNOLOGY LIMITED\n\n", "employment_types": ["Full Time"], "selling_points": ["F.7 or above, Marketing, Training, Event", "Full Time, Double Pay+, Bank Holiday", "Provide Medical, Office location near CWB MTR"], "locations": ["Causeway Bay"], "categories": ["Marketing / Public Relations", "Marketing - General / Support", "Sales, CS & Business Devpt", "Others", "Others", "Student / Fresh Graduate / No Experience"], "post_time": "2022-01-14T09:08:12Z", "salary": {"currency": null, "max": null, "min": null, "period": "monthly", "term": null}, "salary_visible": false, "title_keywords": ["administration executive"], "responsibilities": ["company websites", "seo", "edm", "digital marketing", "sem"], "requirements": {"degrees": ["secondary education"], "majors": ["graphic design", "digital marketing"], "languages": ["english", "chinese"], "language_level": ["good"], "hard_skills": ["ai", "video editing", "writing skill"], "soft_skills": ["writing skill"], "languages_combined": [{"language": "english", "language_level": ["good"]}, {"language": "chinese", "language_level": ["good"]}]}, "experience_required": {"duration": [], "field": []}}, {"job_id": "100003009050858", "location_code": "hk", "company": "Hong Kong Green Building Council Limited", "job_title": "Marketing Executive", "description": "Established in 2009, Hong Kong Green Building Council (\u201cthe Council\u201d) is the leading body, co-founded by four major construction industry and environmental organisations, driving the market transformation towards green and sustainable buildings in Hong Kong through engagement with the industry, the government and broader community.\n\nHKGBC is expanding its secretariat team in line with its positioning as Hong Kong's leading member-based body dedicated to green building development, with opening for the post of Marketing Executive:\n\nJob Description\n\nAssisting the Head of Marketing, to plan, organise and execute all marketing related duties including:\n\nKey Roles:\n\nTo organise and follow through the planning, budget control, execution and logistic arrangements of various types of events, including large scale international and regional conferences, award presentations, press conferences, exhibitions, public campaigns, seminars and site visits, etc.\nTo manage corporate communications channels, including corporate website and email marketing, etc.\nTo assist in develop various online and offline marketing collaterals from conception, content development to layout design\nTo prepare editorial contents such as council announcement, speeches, presentations, monthly e-newsletter, etc.\nTo assist in being the brand guardian and promoting the brand of the HKGBC\nTo manage the various membership database and related registration and renewal\nTo assist in initiatives related to membership promotion and sponsorship programme\nTo handle membership or external enquiries and administration\nTo provide secretariat support to the related Standing Committee(s)\nTo support the team in other activities as required and necessary\n\nRequirements:\n\nDegree holder in Marketing, or related disciplines\n1 to 3 years of working experience, preferably in marketing or events industry\nGood command of written and spoken English and Chinese\nProficiency in Adobe Photoshop, Illustrator and knowledge in HTML would be an advantage\nDiligent and detail-oriented\nGood project management skills, multi-tasking and able to meet tight deadlines\nA team player with good interpersonal, organising and communication skills\n\n\u00a0How to Apply\n\nThe Council is an equal opportunity employer and offers attractive career prospects and remuneration to our staff. Recruitment will be initially under contract terms of two years with the possibility of converting to a permanent post. Interested applicants please apply by sending full resume with date of availability, present and expected salary, contact telephone number, as well as results of public examinations to the Executive Director, Hong Kong Green Building Council via e-mail careers @ hkgbc.org.hk, or by post to 1/F, Jockey Club Environmental Building, 77 Tat Chee Avenue, Kowloon Tong, Hong Kong. Please state the position you want to apply for on the envelope.\n\n(N.B. Application with incomplete information as requested above may not be considered.)\n\nApplicants who do not receive a response within six weeks from the date of this advertisement may consider their applications filed for future reference. Personal data will be used strictly for recruitment related purposes only and retained for no more than six months.", "employment_types": ["Full Time", "Contract"], "selling_points": [], "locations": ["Kowloon City Area"], "categories": ["Marketing / Public Relations", "Marketing - General / Support", "Marketing - Marketing Communication", "Public Relations - Event Management"], "post_time": "2022-01-14T11:34:19Z", "salary": {"currency": null, "max": null, "min": null, "period": "monthly", "term": null}, "salary_visible": false, "title_keywords": ["marketing executive"], "responsibilities": ["administration", "external enquiries", "marketing collaterals", "layout design", "website", "presentations", "develop", "conferences", "plan", "contents", "database", "budget control", "support the team", "planning"], "requirements": {"degrees": ["degree holder"], "majors": ["related disciplines", "marketing"], "languages": ["english", "chinese"], "language_level": ["good command"], "hard_skills": ["no", "adobe photoshop", "illustrator", "html", "project management"], "soft_skills": ["communication skills", "meet tight deadlines", "project management skills", "diligent", "detail-oriented", "multi-tasking", "team player", "interpersonal"], "languages_combined": [{"language": "english", "language_level": ["good command"]}, {"language": "chinese", "language_level": ["good command"]}]}, "experience_required": {"duration": ["1 to 3 years"], "field": ["marketing"]}}, {"job_id": "100003009039038", "location_code": "hk", "company": "Mott MacDonald Hong Kong Limited", "job_title": "Business Support_Marketing Proposal Advisor", "description": "Specific Responsibilities\n\nMarket research on clients\u2019 and projects\u2019 pipelines \u2013 clients\u2019 budgets, timeframe, type of consultancy etc.\nArrange regular clients\u2019 meetings, arrange presentation materials and responsible for chasing follow-up actions\nExternal Connection to Institutions \u2013 Explore opportunity to share Professional Excellence to market\nManage Project sheets in centralized locations for bids\nSupport the work winning functions across APNA to achieve best-for-region outcomes\nCollaborating with the APNA Marketing and Communications Manager and the APNA Senior Communications Advisor, support brand & event activities and production of communications (internal and external) as required for Asia.\nAttend weekly (Monday) APNA Proposal scheduling meeting\nAttend weekly catchup with Marketing and Communications Manager and the APNA Senior Communications Advisor\nUpdate and maintain content for the APNA Win Site; maintaining and updating submission libraries, including identifying best-practice examples and projects, and maintaining and updating capability statements and other marketing presentations.\nUndertake coordination activities for the APNA region as required by the Regional Marketing and Communications Manager, Major Pursuits and Strategy Manager and Senior Communications Advisor.\nSupport the use and maintenance of APNA corporate intranet Compass.\n\nDesired skills and expertise\n\nA minimum of eight years\u2019 experience in marketing, submissions and/or communications\nDemonstrated ability to manage teams in the delivery of submissions or proposal documents\nExperience using Adobe InDesign\nExperience working in a fast-paced, deadline-driven environment\nExperience in development of communications and social media materials\nExperience in managing brand and event activities\nAbility to develop and maintain effective internal and external relationships, including outside of your home office\n\nQualifications and experience\n\nQualifications and/or experience in journalism, marketing or communications (or equivalent) are required.\n\nExperience in an engineering, construction or infrastructure environment will also be highly regarded. If successful in this role you\u2019ll be working on significant projects that shape the communities in which we live. You will build connections with our international colleagues and bring this knowledge to our clients and to their projects. There\u2019s no time like the present to make a change.\n\nWe offer competitive remuneration package including\u00a013th month salary, MPF plan\u00a0and\u00a0group medical insurance for dependents.\n\nInterested parties, please click 'Apply now' to submit your application with full resume including your current and expected salary, or send your full resume to recruitment.MMHK @mottmac.com .\n\nTo explore more opportunities with us, please visit www.mottmac.com/careers.\n\nAll personal data collected will be treated in strict confidence and be used for recruitment purpose only.\u00a0\n\nWe are an equal opportunity employer and value diversity at our company. We do not discriminate, and take positive steps to create an inclusive culture.", "employment_types": ["Full Time", "Permanent"], "selling_points": ["Manage end-to-end submission process for bids", "8 years\u2019 experience in marketing / submission", "5 days work, 13th month salary, wellness program"], "locations": ["Ngau Tau Kok"], "categories": ["Marketing / Public Relations", "Marketing - Brand / Product Management", "Marketing - General / Support", "Marketing - Market Research"], "post_time": "2022-01-16T21:50:11Z", "salary": {"currency": null, "max": null, "min": null, "period": "monthly", "term": null}, "salary_visible": false, "title_keywords": ["advisor"], "responsibilities": ["budgets", "social media", "maintaining", "maintenance", "infrastructure", "teams", "market research", "presentations", "develop", "scheduling", "maintain", "coordination"], "requirements": {"degrees": [], "majors": [], "languages": [], "language_level": [], "hard_skills": ["no", "maintenance", "pipelines", "adobe indesign", "presentations", "make", "compass"], "soft_skills": ["coordination", "driven", "presentation", "responsible"], "languages_combined": []}, "experience_required": {"duration": ["minimum of eight years"], "field": ["social media", "brand", "engineering", "development", "infrastructure", "marketing", "construction"]}}, {"job_id": "100003009056371", "location_code": "hk", "company": "China Mobile Hong Kong \u4e2d\u570b\u79fb\u52d5\u9999\u6e2f", "job_title": "Senior Product Officer (SME Products)", "description": "CHINA MOBILE HONG KONG COMPANY LIMITED (\"CMHK\") is the wholly-owned subsidiary of China Mobile Limited (HKEx: 941) (NYSE: CHL), which ranks 65th on the Fortune Global 500.\n\nOur company strives to offer superior service experience and to become the preferable digital partner for customers. We are preserving an environment with trust, responsibility and caring. At CMHK, we commit to maximizing people\u2019s potential and paving the way toward success for every striver. We are now inviting high caliber professional to join us.\n\n\u00a0Division: Enterprise Product Centre\n\n\u00a0In this position, you will:\n\nResponsible for the presales of SME product, such as product presentation, customer needs analysis and bidding support\nGood at communicating with various customers, writing technical proposal, tender bidding supporting and contract preparing\nAbility to translate client's requirements into feasible solutions\nWork closely with sales team to visit customers, develop and explore business opportunity\nCollaborate with product development teams to design and deliver a competitive and comprehensive solutions to solve customer business requirements\n\nTo be successful in this position, you should meet the following requirements:\n\nBachelor Degree or above in Telecommunication, Information technology, Marketing or related disciplines\n3-5 years\u2019 working experience with 2 years of experience on application software\nCustomer-oriented with excellent consultative communication skill\nKnowledge in SAAS product is preferred\nExceptional professional communication skills. Excellent written and verbal communication skills in both English and Chinese (Mandarin and Cantonese)\nProfessional certificates (i.e. NADP\\PMP) would be definitely an advantage\nImmediate available is preferred\n\nWhen you work:\n\n5\u00a0days work\n8 hours/day\n\nWhat you enjoy:\n\nDouble pay\nDiscretionary Performance bonus\nLife insurance\nMedical insurance\nEducation subsidies\nBirthday gift\nMarriage leave\nBirthday leave\nStaff discount\n\nCMHK is committed to be an equal opportunity employer. We offer exceptional benefits package and the opportunity to work in a challenging environment. Personal data provided by applicants will be treated strictly in accordance with our personal data policy and for recruitment purposes only.\n\nPlease submit your application to us by clicking the APPLY NOW button and send your full resume with your availability, current and expected salary to us.", "employment_types": ["Full Time", "Permanent"], "selling_points": ["Product Management", "SME", "3 years of experience"], "locations": ["Kwai Hing"], "categories": ["Information Technology (IT)", "Product Management / Business Analyst", "Marketing / Public Relations", "Marketing - Brand / Product Management", "Marketing - General / Support"], "post_time": "2022-01-18T04:05:59Z", "salary": {"currency": null, "max": null, "min": null, "period": null, "term": null}, "salary_visible": false, "title_keywords": ["officer"], "responsibilities": ["collaborate with", "software", "analysis", "teams", "design", "develop", "communication", "communicating with", "sales team", "tender", "sme", "insurance"], "requirements": {"degrees": ["degree or above", "bachelor"], "majors": ["related disciplines", "marketing", "information technology"], "languages": ["cantonese", "english", "chinese", "mandarin"], "language_level": ["excellent"], "hard_skills": ["mobile", "analysis"], "soft_skills": ["communication skills", "responsible", "communication skill", "committed", "customer-oriented", "comprehensive", "presentation", "superior"], "languages_combined": [{"language": "cantonese", "language_level": ["excellent"]}, {"language": "english", "language_level": ["excellent"]}, {"language": "chinese", "language_level": ["excellent"]}, {"language": "mandarin", "language_level": ["excellent"]}]}, "experience_required": {"duration": ["2 years", "3-5 years"], "field": ["digital"]}}, {"job_id": "100003009055671", "location_code": "hk", "company": "Dah Chong Hong, Limited", "job_title": "Assistant Operation Officer", "description": "Responsibilities:\n\nResponsible for budget plans, trade promotion plans initiation and implementation.\nPrepare sales data analysis to evaluate brand performance.\nWork closely with the internal parties such as sales team to execute the marketing strategies\nPlay a critical role dealing with local key chains and the existing oversea suppliers\nProvide sales administration support\nBuild rapport relationship with both internal and external partners\nAny ad hoc assignments from management\n\nRequirements:\n\nHKCEE / HKDSE or above, with 1-2 years relevant experience\u00a0for (FMCG) trade marketing;\nProactive, creative and innovative with strong dedication to result;\nExcellent communication and presentation skills;\nFamiliar with MS Application and Chinese Word Processing and Photoshop;\nProficient in written and spoken English and Chinese.\n\nPlease send your application with resume and expected salary to The HR Manager, Dah Chong Hong, Ltd, 8/F, DCH Building, 20 Kai Cheung Road, Kowloon Bay by post or email to click\u00a0\"Apply Now\".\n\n\u00a0We are equal opportunities employer. Applicants who are not invited within 2 months may consider their application unsuccessful. All applicants may be considered for other suitable positions with DCH Group / CITIC Pacific Group and will be deleted from our files after 6 months from the date of application.", "employment_types": ["Full Time", "Permanent"], "selling_points": [], "locations": ["Kowloon Bay"], "categories": ["Marketing / Public Relations", "Marketing - General / Support", "Marketing - Marketing Communication"], "post_time": "2022-01-18T02:50:37Z", "salary": {"currency": null, "max": null, "min": null, "period": "monthly", "term": null}, "salary_visible": false, "title_keywords": ["operation officer", "assistant"], "responsibilities": ["sales administration", "management", "marketing strategies", "budget", "prepare sales", "implementation", "data analysis", "evaluate", "sales team", "ad hoc assignments", "plans", "internal parties"], "requirements": {"degrees": ["hkdse"], "majors": ["marketing"], "languages": ["english", "chinese"], "language_level": ["proficient"], "hard_skills": ["chinese word processing", "photoshop", "ms application"], "soft_skills": ["creative", "innovative", "communication", "presentation skills", "proactive"], "languages_combined": [{"language": "english", "language_level": ["proficient"]}, {"language": "chinese", "language_level": ["proficient"]}]}, "experience_required": {"duration": ["1-2 years"], "field": ["fmcg", "relevant experience", "marketing"]}}, {"job_id": "100003009054279", "location_code": "hk", "company": "Sunny Side Up (Never) Limited", "job_title": "SALES & MARKETING MANAGER", "description": "Responsibilities\n\nCreate, execute and coordinate marketing program materials, communications, graphics, brand website maintenance, digital/social media strategy and events/exhibitions;\nExecute social media marketing ad strategies on Instagram, Facebook, LinkedIn, Pinterest Twitter and YouTube;\nManage and maintain website content using HTML or other web content management interface;\nPrepare media plan, budget summary and execute advertisement campaign with reports;\nReport on the performance of different paid media platform and provide campaign insights to assess campaign effectiveness and identify optimization opportunities;\nCoordinate with Design, PR and Communications and other functional teams to ensure brand consistency and smoothness operations;\nOther ad hoc tasks as assigned.\n\n\u00a0Requirements\n\nDegree holder in marketing or related disciplines;\u00a0\n3 years or above experiences in digital marketing;\nKnowledge in Google Adwords / Facebook AD manager is an advantage;\nKnowledge of Photoshop or AI is an advantage;\nGood communication in spoken and written English and Chinese and Mandarin;\nImmediate available is preferred.", "employment_types": ["Full Time"], "selling_points": ["Degree holder in marketing", "3 yrs exp. in digital marketing", "Knowledge in Google Adwords/Facebook AD manager"], "locations": ["Kwun Tong"], "categories": ["Marketing / Public Relations", "Marketing - Brand / Product Management", "Marketing - General / Support", "Digital Marketing"], "post_time": "2022-01-17T09:19:05Z", "salary": {"currency": null, "max": null, "min": null, "period": "monthly", "term": null}, "salary_visible": false, "title_keywords": ["sales & marketing manager"], "responsibilities": ["graphics", "social media", "management", "operations", "budget", "coordinate with", "website maintenance", "website", "design", "coordinate", "teams", "ad hoc tasks", "maintain", "reports", "plan", "facebook", "brand consistency", "report"], "requirements": {"degrees": ["degree holder"], "majors": ["related disciplines", "marketing"], "languages": ["english", "chinese", "mandarin"], "language_level": ["good"], "hard_skills": ["ai", "adwords", "facebook", "photoshop"], "soft_skills": ["communication"], "languages_combined": [{"language": "english", "language_level": ["good"]}, {"language": "chinese", "language_level": ["good"]}, {"language": "mandarin", "language_level": ["good"]}]}, "experience_required": {"duration": ["3 years"], "field": ["digital marketing"]}}, {"job_id": "100003009056064", "location_code": "hk", "company": "Wong\u2019s Electronics Company Limited", "job_title": "Assistant Manager, Marketing and Research Analytics", "description": "Role Summary:\n\nWith the aim to diversify our business, our management is actively developing opportunities in other business sectors.\u00a0\n\nTo copy with our growth, we are looking for a high caliber candidate for the position of Assistant Manager, Marketing and Research Analytics.\n\nResponsibilities:\n\nResponsible for all-round market research across different potential industries including data collection, figures analysis and market trend forecast;\nConduct in-depth analysis covering business models, customers\u2019 preferences and needs, branding and risk assessment;\nProvide regular market intelligence and competitors analysis for strategic planning and decision making;\nPrepare periodical reports in sales performance analysis, budgeting, costing and forecasting;\nPerform ad-hoc tasks as required.\n\n\u00a0Requirements:\n\nDegree holder in Business Administration, Marketing, Finance or related discipline;\nMinimum 5 years of experience in market research and data analysis;\nKnowledge and experience in merger & acquisition, franchise, emerging business is highly preferred;\nStrong business sense, analytical, detail-oriented and self-initiative;\nEnthusiastic, sensitive in market changes and future trends, able to use initiative to come up with new ideas;\nGood command of spoken and written English, Cantonese and Putonghua;\nAble to travel when required.", "employment_types": ["Full Time", "Permanent"], "selling_points": ["All-round market research", "Data analysis", "5 days work week"], "locations": ["Ngau Tau Kok"], "categories": ["Marketing / Public Relations", "Marketing - General / Support", "Marketing - Market Research", "Sales, CS & Business Devpt", "Sales Administration"], "post_time": "2022-01-18T03:14:43Z", "salary": {"currency": null, "max": null, "min": null, "period": "monthly", "term": null}, "salary_visible": false, "title_keywords": ["assistant manager,"], "responsibilities": ["strategic planning", "sales performance", "analysis", "budgeting", "ad-hoc tasks", "market research", "reports", "forecast", "data collection", "forecasting"], "requirements": {"degrees": ["degree holder"], "majors": ["finance", "marketing", "business administration"], "languages": ["cantonese", "putonghua", "english"], "language_level": ["good command"], "hard_skills": ["analysis"], "soft_skills": ["business sense", "detail-oriented", "self-initiative", "enthusiastic", "initiative", "sensitive"], "languages_combined": [{"language": "cantonese", "language_level": ["good command"]}, {"language": "putonghua", "language_level": ["good command"]}, {"language": "english", "language_level": ["good command"]}]}, "experience_required": {"duration": ["minimum 5 years"], "field": ["data analysis", "business", "market research"]}}, {"job_id": "100003009056404", "location_code": "hk", "company": "Neo Derm (HK) Ltd", "job_title": "Marketing Executive/ Senior Executive (Social/ Influencer), Reenex", "description": "Neo Derm Group\n\nPioneering in an AI-powered e-commerce and service platform Gratus (www.gratus.com.hk), Neo Derm seeks to offer greater value through fast beauty experience to consumers to fulfil your quest of beautifying lives in a more convenient way.\n\nAs a Product Manager of brand marketing team, you will lead the development of brand equity narration for our top-of-mind brands including Dermes, Reenex, Elyze, Evvus, Vigene and Geneoo, and develop CRM strategies riding on our robust digital platform Gratus.\u00a0\n\nNot only do we offer a world-class working environment at the penthouse of One Island East, our excellent remuneration package and a fast progression path will nurture your personal and professional career development in a long run.\u00a0\n\n\n\nResponsibility\u00a0\n\nManage and analyze performance of social media platforms FB & IG\u00a0to drive new customer and achieve business targets\nManage KOL, free trial and testimonials\nProvide campaign performance analysis and recommendations to optimize performance for the best ROI\n\n\n\nRequirements\n\nexperience in digital marketing, brand marketing, product marketing and/or content management\nexperience in development / management of social media platforms, not limited to Facebook, Instagram, YouTube, WeChat, with successful campaigns\u00a0\n\nAll personal data collected will be treated in strict confidence and be used for recruitment purposes only.", "employment_types": ["Full Time", "Permanent"], "selling_points": ["Top-of-mind Brand", "Digitalization and data-driven working environment", "Career Development"], "locations": ["Tai Koo"], "categories": ["Marketing / Public Relations", "Marketing - Brand / Product Management", "Marketing - General / Support", "Marketing - Marketing Communication"], "post_time": "2022-01-18T04:11:07Z", "salary": {"currency": "HKD", "max": 24999, "min": 20000, "period": "monthly", "term": null}, "salary_visible": true, "title_keywords": ["senior executive", "marketing executive"], "responsibilities": ["analysis", "social media platforms"], "requirements": {"degrees": [], "majors": [], "languages": [], "language_level": [], "hard_skills": ["facebook", "wechat"], "soft_skills": ["confidence"], "languages_combined": []}, "experience_required": {"duration": [], "field": ["social media", "management", "brand", "development", "marketing", "digital marketing"]}}, {"job_id": "100003009048828", "location_code": "hk", "company": "Dah Chong Hong, Limited", "job_title": "Marketing Executive", "description": "The incumbent will be responsible for a series of marketing initiatives for the assigned brands or product portfolio as below.\n\nResponsibilities :\n\nFormulate and implement of marketing programs\nControl and monitor of all marketing activities and promotions\nEvaluate the effectiveness of marketing and promotion programs\nLiaison and communicate with Principals\nWork closely with the internal parties such as Key Account team\nPerform inventory control and order planning\nConduct price analysis and sales analysis\n\nThe ideal candidate should be :\n\nUniversity graduate in Marketing or related disciplines\nAt least 1-2 years relevant experience in marketing. Exposure in food/beverage product is an advantage\nResponsible, analytical, independent, self-motivated with excellent communication skills and able to work under pressure\nGood command of spoken and written English and Chinese\nProficiency in MS Office\n\nPlease send your application with resume and expected salary to The HR Manager, Sims Trading Co. Ltd, 8/F, DCH Building, 20 Kai Cheung Road, Kowloon Bay\u00a0or submit your application online by clicking\u00a0\"Apply Now\"\n\nInformation provided will be kept for the purpose of selection within the company and only shortlisted candidates will be contacted. All applications will be retained for a maximum period of 6 months.", "employment_types": ["Full Time", "Permanent"], "selling_points": [], "locations": ["Kowloon Bay"], "categories": ["Marketing / Public Relations", "Marketing - Brand / Product Management", "Marketing - General / Support", "Others"], "post_time": "2022-01-14T07:22:04Z", "salary": {"currency": null, "max": null, "min": null, "period": "monthly", "term": null}, "salary_visible": false, "title_keywords": ["marketing executive"], "responsibilities": ["communicate with", "control", "work under pressure", "analysis", "hr", "monitor", "evaluate", "communication", "inventory control", "internal parties", "planning"], "requirements": {"degrees": ["university graduate"], "majors": ["related disciplines", "marketing"], "languages": ["english", "chinese"], "language_level": ["good command"], "hard_skills": ["analysis", "ms office"], "soft_skills": ["communication skills", "self-motivated", "independent", "responsible", "work under pressure", "ideal"], "languages_combined": [{"language": "english", "language_level": ["good command"]}, {"language": "chinese", "language_level": ["good command"]}]}, "experience_required": {"duration": ["at least 1-2 years"], "field": ["marketing", "relevant experience"]}}, {"job_id": "100003009046447", "location_code": "hk", "company": "BlessVision Foundation Limited", "job_title": "Project Officer (marketing & fundraising)", "description": "BlessVision Foundation is a registered charitable organization in HK. We based on Christian values to provide charitable works, life education and humanitarian care. Through media productions, to spread Jesus\u2019 love and support to those are vulnerable from different nationalities. To promote human wellness in body, mind, society and spirit levels.To cope with our continued growth, we are looking for a right candidate to join us.\n\nResponsibilities:\n\n\nProject coordination to initiate collaboration opportunities with different corporate partners/ organizations, to support and liaise with concerned parties and community caring programs.\nTo prepare fundraising proposals, applications, design programs and run campaigns for caring programs/sponsorship support.\nPlan, budget and draft proposal, monitor progress & prepare reports for media and caring projects.\nPrepare and draft educational and promotional materials, e.g. exhibition, movie, leaflet, Facebook / Instagram post, website content etc.\nPerform copywriting of communications and publicity materials including social media content, press invitations, press releases, event speeches, media editorials, websites etc.\nRequirements:\n\n\nTertiary qualifications or above (Journalism / Communications / Marketing / Event management is preferred) with minimum 2 years relevant working experience\nExcellent command of written English and Chinese; fluent in spoken English, Cantonese and Putonghua preferred.\nCheerful personality with excellent interpersonal skills and customer service skills \u2013 able to interact with all different kinds of people\nProficient in online marketing strategies and marketing channels\nProject organizing experience - strong skills on project planning, financing, implementation and evaluation is preferred\nProficient in MS applications, Google-powered business tools (email, calendar, docs), Chinese Word processing, Photoshop etc.\nMultitasking and analytical skills\nCan work under pressure and capable to handle ad-hoc matters\nOut-door work is necessary\nWith caring heart by Jesus\u2019 love\nStrong commitment to the mission, vision and values of BlessVision Foundation\nInterest parties please email your full resume with present & expected salary and state the date of availability.", "employment_types": ["Full Time"], "selling_points": ["Marketing and fundraising strategies", "Project coordination with corporate parties", "With caring heart by Jesus\u2019 love"], "locations": ["Ngau Tau Kok"], "categories": ["Media & Advertising", "Strategic Planning", "Marketing / Public Relations", "Marketing - General / Support", "Public / Civil", "Social Services - Community / Non-profit Organization"], "post_time": "2022-01-14T06:25:46Z", "salary": {"currency": null, "max": null, "min": null, "period": "monthly", "term": null}, "salary_visible": false, "title_keywords": ["project officer"], "responsibilities": ["prepare reports", "project coordination", "monitor progress", "budget", "leaflet", "website", "design", "promotional materials", "social media content", "plan", "liaise with", "facebook"], "requirements": {"degrees": [], "majors": [], "languages": ["cantonese", "putonghua", "english", "chinese"], "language_level": ["proficient", "excellent", "fluent"], "hard_skills": ["chinese word processing", "ms applications", "analytical skills", "photoshop"], "soft_skills": ["customer service skills", "cheerful", "capable", "analytical skills", "interpersonal skills", "work under pressure"], "languages_combined": [{"language": "cantonese", "language_level": ["fluent"]}, {"language": "putonghua", "language_level": ["fluent"]}, {"language": "english", "language_level": ["excellent", "fluent"]}, {"language": "chinese", "language_level": ["proficient", "excellent"]}]}, "experience_required": {"duration": ["minimum 2 years"], "field": ["management", "financing", "relevant working experience", "marketing", "planning"]}}, {"job_id": "100003009054531", "location_code": "hk", "company": "Kantar Hong Kong Limited", "job_title": "Research Associate/ Research Executive (Quantitative)", "description": "Research Associate (Quantitative)\n\nTop-tier market research agency that is progressive and people focused\nExposure to global leading brands and work variety\nCreate impact by solving exciting problems for diverse clientele\n\nKantar is now seeking confident, inspiring and inquisitive individuals as a Research Associate (Quantitative). \u00a0If you are looking for fun and variety in your everyday work, with an insatiable appetite to try new things and new challenges \u2013 this could be the role for you.\n\nYour job and career:\n\nWork across an exciting mix of brands, industries, and research projects\nAssist in delivering end-to-end quantitative projects with support from senior team members, including project design, proposal writing, planning and research analysis on research projects.\nCoordinate with clients and support client relationships to provide the highest level of servicing\nPut on your creative hat and share your new ideas to find better ways to service clients\nProvide administrative and digital support to the team\nDevelop your professional competence as an insight consultant to clients\u2019 business and marketing challenges.\n\nYou are:\n\nCurious and open minded\nPassionate, enthusiastic team player, and willing to accept responsibility and accountability for work\nSelf-starter, who can manage your own work, projects, prioritize tasks and understand the importance of meeting deadlines.\nStrong analytical thinking and problem-solving skills, with excellent attention to detail\nMulti-tasking and working under pressure come naturally to you.\u00a0\n\nYou have:\n\nUniversity degree, preferably with a major in Business, Marketing, Sociology, Psychology, Philosophy or English\nWorking experience is preferred but not a must\nBasic understanding of quantitative research processes and analysis tools would be an advantage\nGood command in both written and spoken English and Chinese (both Cantonese and Mandarin)\nExceptional written communication \u2013 ability to articulate ideas and present information in an effective way.\nA desire to learn and improve professional competence and knowledge, through formal and informal training\nHigh competence in MS Office, especially PowerPoint\n\nWhat we can offer to you\u2026\n\nThe opportunity to work at the world\u2019s leading technology-enabled data, insights and consultancy company that you can be proud to work for (and brag to your friends about)\nAn international company with presence across the globe, providing the opportunity to work in different markets\nA company continually investing in innovative, digitally focused research solutions that reflect the changing needs of our clients\nFacial coding technology to measure people\u2019s emotional response to advertising\nUsing AI to predict effectiveness of advertising or forecasting future trends for brands\nFully automated intelligence platforms that integrate all sources of data\nHuge variety in the work you do so you won\u2019t get bored \u2013 every day is different!\nLot\u2019s of clients to choose from as we work with many top tier brands locally, regionally and globally\nExposure to a broad spectrum of areas within insights as we cover many domain areas like brand, creative, media & digital, customer experience, analytics, innovation just to name a few\nA diverse and inclusive team, many of whom are from different cultures and backgrounds\nA team that not only values, but encourages individual\u2019s opinions and expression of your ideas\nLot\u2019s and lot\u2019s of learning opportunities aimed at building your knowledge and broadening your skills both professionally and personally e.g. learning tips & tricks on Excel or Powerpoint to learning how to become a better presenter\nA friendly and sociable team that works hard, but also knows how to have fun! Not to mention a cool office with a great view\u2026\n\nCandidates with more experience may be considered as Research Executive (Quantitative). Immediate availability is highly preferred.\n\nFor more details, please visit:\u00a0http://www.kantar.com\n\nInterested parties, please send full resume with expected salary by clicking APPLY NOW. All personal data and applications will be treated in strictly confidential and used for recruitment purpose only.", "employment_types": ["Full Time"], "selling_points": ["Quantitative Research", "Exposure to global leading brands", "Create impact by solving exciting problems"], "locations": ["North Point"], "categories": ["Marketing / Public Relations", "Marketing - Brand / Product Management", "Marketing - General / Support", "Marketing - Market Research"], "post_time": "2022-01-17T16:21:06Z", "salary": {"currency": null, "max": null, "min": null, "period": "monthly", "term": null}, "salary_visible": false, "title_keywords": ["research associate", "executive"], "responsibilities": ["ideas", "advertising", "research projects", "data", "analysis", "market research", "design", "develop", "communication", "coordinate with clients", "coding", "planning", "forecasting", "research analysis"], "requirements": {"degrees": ["university degree"], "majors": ["psychology", "business", "sociology", "marketing"], "languages": ["cantonese", "english", "chinese", "mandarin"], "language_level": ["good command"], "hard_skills": ["excel", "basic", "fun", "ai", "analysis", "cool", "powerpoint", "problem-solving skills", "ms office"], "soft_skills": ["under pressure", "focused", "communication", "articulate", "team player", "confident", "presenter", "diverse", "open minded", "creative", "passionate", "sociable", "prioritize", "friendly", "attention to detail", "enthusiastic", "progressive", "problem-solving skills", "accountability", "multi-tasking", "learning", "inspiring", "innovative"], "languages_combined": [{"language": "cantonese", "language_level": ["good command"]}, {"language": "english", "language_level": ["good command"]}, {"language": "chinese", "language_level": ["good command"]}, {"language": "mandarin", "language_level": ["good command"]}]}, "experience_required": {"duration": [], "field": ["digital", "media", "research", "brand"]}}, {"job_id": "100003008993981", "location_code": "hk", "company": "Fung Omni Services (HK) Limited", "job_title": "Supervior - Business Development (e-Commence)", "description": "Responsibilities:\n\nPrepare eCommerce marketplace sales analysis, top selling items and support purchasing of brands products\nSupport customer quotation preparation, business development calls and business pipeline analyses\nSupport in developing\u00a0and proposing\u00a0solutions to meet client\u2019s requirements\nPlan business meetings, record meeting minutes and inform related parties and resources for close follow-up.\nMaintain an up-to-date customer database and filing system.\nPrepare business reviews and compile management reports and data analyses.\nSupport in collecting, analyzing and evaluating market information.\nRequirements:\u00a0\n\nBachelor Degree holder in business administration, marketing or relevant disciplines\n1-3 years\u2019 solid digital marketing, business development experience\u00a0\n\nA good team player with solid interpersonal skills to deal with internal and external partners\nStrong computer literacy\nGood analytical, conceptual thinking, and problem-solving skills\nGood command of English and Mandarin, both spoken and written\nNative Mandarin speaker is required\nKnowledge of eCommerce preferred experience in China marketing is also ideal\n\n", "employment_types": ["Full Time"], "selling_points": ["1-2 years experience in sales/business development", "E-Commence", "Business Development"], "locations": ["Shatin Area"], "categories": ["Transportation & Logistics", "Others", "Marketing / Public Relations", "Marketing - General / Support", "E-commerce", "Business Development"], "post_time": "2022-01-18T01:04:41Z", "salary": {"currency": null, "max": null, "min": null, "period": null, "term": null}, "salary_visible": false, "title_keywords": [], "responsibilities": ["market information", "data", "analysis", "quotation", "developing", "management reports", "maintain", "plan", "database", "client\u2019s requirements"], "requirements": {"degrees": ["bachelor degree holder"], "majors": ["marketing", "business administration"], "languages": ["english", "mandarin"], "language_level": ["native", "good command"], "hard_skills": ["problem-solving skills"], "soft_skills": ["good team player", "computer literacy", "interpersonal skills", "problem-solving skills", "ideal"], "languages_combined": [{"language": "english", "language_level": ["good command"]}, {"language": "mandarin", "language_level": ["native", "good command"]}]}, "experience_required": {"duration": ["1-3 years"], "field": ["ecommerce", "business development", "digital marketing", "marketing"]}}, {"job_id": "100003009048345", "location_code": "hk", "company": "FUJIFILM Business Innovation Hong Kong Limited", "job_title": "Product Marketing Executive (Ref: EDSHW)", "description": "The Job\nResponsible for product life-cycle management including product launch, marketing strategy and inventory management\nAssist in marketing reports, data tracking, and identifying the areas of improvement and enhancement\nExecute sales and marketing strategy to achieve company\u2019s goals on market share and profitability\nThe Person\nDegree holder/ associate degree holder with minimum 2 years relevant experiences preferably in ICT industry\nExperience in data analysis and marketing report with strong analytical mind\nPositive, disciplined, self-motivated with good interpersonal skill\nProficient in using MS Office application, including Word, Excel and PowerPoint\nMore experience will be considered as Senior Product Marketing Executive\nWe offer career prospect, attractive remuneration and fringe benefits including but not limited to the followings:\n12 days' annual leave\nBlissful leave of maximum 25 days per year (including birthday leave, wedding anniversary leave, children graduation leave, volunteer leave, pet healthcare leave, home purchase, etc)\n5 days work week & bank holiday\nClinical, hospitalization and dental insurance\u00a0\nTo discuss this opportunity further, please send your full resume, current and expected salary to the\u00a0HR Department.\nWe are a equal opportunity employer and welcome applications from all qualified candidates.\u00a0 All information provided will be treated in strict confidence and used for recruitment purposes only.\u00a0 Applicants not hearing from us within six weeks may consider their applications unsuccessful.\u00a0 All data of unsuccessful applications will be destroyed after six months.", "employment_types": ["Full Time", "Permanent"], "selling_points": ["Product Life-cycle Management", "Data Analysis", "Marketing Campaign"], "locations": ["Tai Koo"], "categories": ["Marketing / Public Relations", "Marketing - Brand / Product Management", "Marketing - General / Support"], "post_time": "2022-01-14T06:23:18Z", "salary": {"currency": null, "max": null, "min": null, "period": "monthly", "term": null}, "salary_visible": false, "title_keywords": ["marketing executive"], "responsibilities": ["management", "data", "inventory management", "reports", "tracking"], "requirements": {"degrees": ["associate degree", "degree holder"], "majors": [], "languages": [], "language_level": [], "hard_skills": ["excel", "analysis", "word", "powerpoint", "ms office"], "soft_skills": ["self-motivated", "analytical mind", "positive", "interpersonal skill"], "languages_combined": []}, "experience_required": {"duration": ["minimum 2 years"], "field": ["ict industry", "data analysis", "analytical", "marketing"]}}, {"job_id": "100003009049287", "location_code": "hk", "company": "SEEK Asia (JobsDB)", "job_title": "Senior Marketing Executive (1 year contract)", "description": "The Role\n\nReporting to Head of Marketing, this exciting role sits within the Marketing Department at SEEK Asia. The primary focus of the role is to be responsible for taking ownership and initiative in jobseeker and/or employer engagement strategies planning and implementation. This position plays an integral part in the success of our team\u2019s long-term vision, and represents a brand-new opportunity. We are looking for someone with a proven ability to adapt to a changing environment, and be a change champion, with the role evolving over time, as we progress through our technological & operational transformation.\n\nKey Responsibilities:\n\n\u00b7 Assist to launching and optimizing jobseeker and employer marketing campaigns.\n\n\u00b7 Assist to compile presentation decks and reports on campaign design, data tracking, and deliver other miscellaneous marketing tasks, including but not limited to ongoing acquisition, loyalty and engagement tasks.\n\n\u00b7 Effective Chinese and English copywriting skills to develop both online/ offline collaterals, and sale kits.\n\n\u00b7 As owner of CRM automation daily operations, work with brand owners to deliver regular and ad-hoc eDM and other automated communication to members.\n\n\u00b7 With creative mindset, business acumen and strong consumer centric insights, work with content team and agency to fine tuning social and articles content that engage users and convert business results.\n\n\u00b7 Able to work with sale team, regional and cross-functional teams.\n\n\u00b7 With knowledge of effective multi-channel strategies & tools for brands, such as CRM, eDM, Social, Partnership, Mobile etc to drive online traffic, jobseeker/ employer engagement and conversions.\n\nQualifications\nSo, what we are looking for?\n\nThe successful candidate will have:\n\n\u00b7 University degree holder.\n\n\u00b7 Minimum 2 years' experience preferably in e-commence, internet media or advertising agency, CRM related areas (Salesforce experience is highly preferred) and/or analytics, with a proven track record in driving brand awareness, considerations and conversions through effective strategy.\n\n\u00b7 You are a true believer of quality and always looking for opportunities to sharpen your marketing planning and analysis skills. With your high commercial acumen, you hope to deliver great value of business partnering support to both internal and external stakeholders.\n\n\u00b7 You are deeply passionate about technology and eager to learn new things.\n\n\u00b7 You are an extraordinary team player. You are responsible, supportive and collaborative. You say \u201cwe\u201d more than \u201cI\u201d. While engaging in discussions, you actively listen and bring valuable thoughts or opinions to the table when the \u201cEureka\u201d moment strikes!\n\n\u00b7 To you, the thought of bringing productivity to the next level sparks joy. You are someone who constantly puts on different thinking hats to find ways in improving existing processes, automating mundane tasks and shaping practices for the better.", "employment_types": ["Full Time", "Contract"], "selling_points": ["Our motto: Improving Lives through Better Careers", "Company Values: We Care, We Aim High, We Deliver", "Customized Career Development Opportunities"], "locations": ["Quarry Bay"], "categories": ["Marketing / Public Relations", "Marketing - General / Support", "Marketing - Marketing Communication", "Digital Marketing"], "post_time": "2022-01-14T08:22:57Z", "salary": {"currency": null, "max": null, "min": null, "period": "monthly", "term": null}, "salary_visible": false, "title_keywords": ["senior marketing executive"], "responsibilities": ["ad-hoc", "reporting", "tracking", "advertising", "data", "edm", "analysis", "quality", "implementation", "design", "develop", "communication", "daily operations", "reports", "marketing campaigns", "cross-functional teams", "planning"], "requirements": {"degrees": ["university degree"], "majors": [], "languages": ["english", "chinese"], "language_level": [], "hard_skills": ["hope", "salesforce", "analysis", "mobile", "focus", "joy", "acumen"], "soft_skills": ["supportive", "responsible", "creative mindset", "collaborative", "communication", "eager to learn", "team player", "consumer centric", "business acumen", "focus", "initiative", "presentation", "passionate about"], "languages_combined": [{"language": "english", "language_level": []}, {"language": "chinese", "language_level": []}]}, "experience_required": {"duration": ["minimum 2 years"], "field": ["related", "brand", "media", "advertising agency"]}}, {"job_id": "100003009053996", "location_code": "hk", "company": "AnsWing\u2019s", "job_title": "Administrative Executive  ($17K ~ $25K)", "description": "Guaranteed Basic Income ($17K ~ $25K)\n\n5 days work with Double Pay\n\nTravel Allowance + Medical Insurance\n\nResponsibilities\n\n\u00a0Perform general office administrative and clerical supports\n\nSupport Senior Manager in the preparation of all documentations\n\nManage schedules, appointments and meetings\n\nReview and sort incoming emails and mails for relevant functions\n\nPlan and manage record keeping activities when required\n\nHandle and maintain confidential information and documents\n\n\n3Requirements\u00a0\n\nBachelor degree or above\n\nDetail-oriented, well-organized, excellent communication skills\n\nExcellent interpersonal skills to deal with all levels of people\n\nHigh proficiency in MS Office including Excel, Word, PowerPoint etc\n\nHigh proficiency of both spoken and written English, Cantonese and Mandarins\n\nImmediate available is preferred", "employment_types": ["Full Time", "Internship"], "selling_points": ["5-days Work Incentive Package +Be professionalism", "Provide professional administrative support", "Fresh graduate + any work experienced are welcome"], "locations": ["Not Specified"], "categories": ["Admin & HR", "Personal / Executive Assistant", "Marketing / Public Relations", "Marketing - General / Support", "Sales, CS & Business Devpt", "Sales Administration"], "post_time": "2022-01-17T07:59:13Z", "salary": {"currency": "HKD", "max": 24999, "min": 17000, "period": "monthly", "term": null}, "salary_visible": true, "title_keywords": ["administrative executive"], "responsibilities": ["manage record", "schedules", "review", "maintain", "plan"], "requirements": {"degrees": ["degree or above", "bachelor"], "majors": [], "languages": ["cantonese", "english"], "language_level": ["proficiency"], "hard_skills": ["excel", "word", "powerpoint", "ms office"], "soft_skills": ["communication skills", "well-organized", "interpersonal skills", "detail-oriented"], "languages_combined": [{"language": "cantonese", "language_level": ["proficiency"]}, {"language": "english", "language_level": ["proficiency"]}]}, "experience_required": {"duration": [], "field": []}}, {"job_id": "100003009050756", "location_code": "hk", "company": "International Housewares Retail Company Limited", "job_title": "Marketing Executive / Senior Marketing Executive", "description": "Responsibilities:\n\nDesign and implement marketing campaigns, through means of in-store POS, social media, mobile app and other channels, to drive awareness, reach and conversion.\nSupport in the development, enhancement and maintenance of digital communication platforms, including website, social media platforms and mobile app.\nImplement activities to drive members\u2019 acquisition and engagement with Membership Campaign.\nBe the active role for market-wide content planning and coordination of digital communication platforms.\nCoordinate with internal stakeholders and external agencies to produce communication materials\nProvide departmental administrative support\nRequirements:\n\nDiploma or above in Marketing or related\u00a0disciplines\n2 years\u2019 working experience in the field of marketing / advertising\nKnowledge of\u00a0 Photoshop\u00a0or AI\nExperience in loyalty / CRM marketing is a plus\nGood communication and interpersonal skills\nGood command in verbal and written Chinese and English (Cantonese and Mandarin)\nCandidate with more experience will be considered as Senior Marketing\u00a0Executive\nImmediate available is highly preferred\u00a0\nWorking Location: Wong Chuk Hang (5 mins walk from MTR Station)\n\n\nWe offer attractive salary and benefits to the right candidates. \u00a0Interested parties please send full resume with present and expected salary\u00a0by clicking \"Apply Now\".\n\n\u00a0(Personal data will be used for recruitment purpose only)", "employment_types": ["Full Time", "Permanent"], "selling_points": ["Experience in loyalty / CRM marketing is a plus", "Market-wide content planning and coordination", "Knowledge of  Photoshop or AI"], "locations": ["Southern Area"], "categories": ["Marketing / Public Relations", "Marketing - Brand / Product Management", "Marketing - General / Support", "Digital Marketing"], "post_time": "2022-01-14T11:17:03Z", "salary": {"currency": null, "max": null, "min": null, "period": "monthly", "term": null}, "salary_visible": false, "title_keywords": ["senior marketing executive", "marketing executive"], "responsibilities": ["social media", "mobile app", "maintenance", "administrative support", "social media platforms", "coordinate with", "website", "design", "communication", "marketing campaigns", "coordination", "planning"], "requirements": {"degrees": ["diploma or above"], "majors": ["related disciplines", "marketing"], "languages": ["cantonese", "english", "chinese", "mandarin"], "language_level": ["good command"], "hard_skills": ["ai", "plus", "photoshop"], "soft_skills": ["communication and interpersonal skills"], "languages_combined": [{"language": "cantonese", "language_level": ["good command"]}, {"language": "english", "language_level": ["good command"]}, {"language": "chinese", "language_level": ["good command"]}, {"language": "mandarin", "language_level": ["good command"]}]}, "experience_required": {"duration": ["2 years"], "field": ["marketing", "advertising"]}}, {"job_id": "100003009044599", "location_code": "hk", "company": "Hutchison Property Group Limited", "job_title": "ASSISTANT SALES & MARKETING MANAGER \u2013 OVERSEAS PROPERTY [Ref. AMM-UK]", "description": "Degree holder in Real Estate, Surveying, Business Administration or related disciplines\n8 years\u2019 relevant experience in the sales and marketing of overseas properties\nExperience/knowledge in the UK property market\nTo assist in developing sales and marketing strategies and managing sales administration for overseas properties of the Group\nTo organize, implement and monitor sales and marketing activities\nTo conduct market research and generate pricing strategy\nExcellent communication and interpersonal skills\nFluent in written and spoken English and Chinese\n\nWe offer salary and benefits commensurate with qualifications and experience. Please send a full resume with contact number and expected salary to General Manager - Human Resources & Administration, Hutchison Property Group Limited, 3/F., One Harbourfront, 18 Tak Fung Street, Hunghom, Kowloon (Please quote reference on envelope) or by clicking \"Apply Now\".\n\nWe are an equal opportunity employer and welcome applications from all qualified candidates. The information provided will be treated in strict confidence and be used only for consideration of your application for relevant/similar post(s).\n\nApplicants not hearing from us within six weeks from the date of advertisement may consider their applications unsuccessful. All personal data of unsuccessful applicants will be destroyed after the recruitment exercise when no longer required.", "employment_types": ["Full Time", "Permanent"], "selling_points": ["Degree holder", "8 years' relevant experience", "Assist in sales & marketing of overseas properties"], "locations": ["Hung Hom"], "categories": ["Marketing / Public Relations", "Marketing - General / Support", "Marketing - Market Research", "Property / Real Estate", "Property Consultancy"], "post_time": "2022-01-16T21:50:23Z", "salary": {"currency": null, "max": null, "min": null, "period": null, "term": null}, "salary_visible": false, "title_keywords": ["sales & marketing manager", "assistant"], "responsibilities": ["sales administration", "marketing strategies", "conduct market research", "monitor", "developing", "communication", "administration"], "requirements": {"degrees": ["degree holder"], "majors": ["related disciplines", "business administration", "surveying"], "languages": ["english", "chinese"], "language_level": ["fluent"], "hard_skills": [], "soft_skills": ["communication and interpersonal skills"], "languages_combined": [{"language": "english", "language_level": ["fluent"]}, {"language": "chinese", "language_level": ["fluent"]}]}, "experience_required": {"duration": ["8 years"], "field": ["marketing", "relevant experience"]}}, {"job_id": "100003009049120", "location_code": "hk", "company": "Centaline Property Agency Ltd", "job_title": "Senior / Marketing Officer (REF: PRM)", "description": "Responsibilities:\n\nCo-ordinate and liaise with both internal and external parties for implementation of\u00a0 marketing projects, events and press conference, etc.\u00a0\nAssist sales directors in planning and implementing advertising and marketing campaigns for development projects, newly released or second-hand, local or overseas.\nWork with designers to prepare online or print materials.\nCo-ordinate all kinds of marketing materials with good project management skills .\nOutdoor work is required.\n\nRequirements:\n\nDegree holder in Marketing or other related disciplines\u00a0\n3-5 year's or above related work experience in Marketing field\u00a0\nPleasant, proactive and independent with good time management and communication skills\u00a0\nProficiency in MS Office\nGood command of both written English and Chinese\u00a0\nKnowledge on maintaining social media platform is an advantage\nAttentive to detail, good team player\nWilling to work under pressure and overtime\u00a0\nBusiness travel may require", "employment_types": ["Full Time", "Permanent"], "selling_points": ["co-ordinate marketing events", "implement advertising", "Degree holder in Marketing"], "locations": ["Central"], "categories": ["Marketing / Public Relations", "Marketing - Brand / Product Management", "Marketing - General / Support", "Marketing - Marketing Communication"], "post_time": "2022-01-14T08:09:04Z", "salary": {"currency": null, "max": null, "min": null, "period": "monthly", "term": null}, "salary_visible": false, "title_keywords": ["marketing officer"], "responsibilities": ["marketing materials", "outdoor work", "advertising", "internal and external parties", "marketing projects", "implementation", "project management", "marketing campaigns", "liaise with", "planning"], "requirements": {"degrees": ["degree holder"], "majors": ["related disciplines", "marketing"], "languages": ["english", "chinese"], "language_level": ["good command"], "hard_skills": ["ms office"], "soft_skills": ["communication skills", "good team player", "proactive", "independent", "attentive to detail", "pleasant", "time management", "work under pressure"], "languages_combined": [{"language": "english", "language_level": ["good command"]}, {"language": "chinese", "language_level": ["good command"]}]}, "experience_required": {"duration": ["3-5 year"], "field": ["related", "marketing"]}}, {"job_id": "100003009053394", "location_code": "hk", "company": "Megaman Asia Ltd", "job_title": "IT Manager", "description": "\nOur Company is a well-established electronic products supplier which sells in different countries. We are looking for high caliber candidates for the position.\n\u00a0 Responsibilities:\n\u2022 Support local users of Office, warehouse, shop and users from other region s\n\u2022 Maintain systems and data in a desirable and operational status\n\u2022 Manage IT asset, budget and expenses\n\u2022 Administrate Microsoft servers, AD, MSSQL, ASP Web, Microsoft Windows, Office 365, VMware, Veeam, Firewall, VPN, antivirus and some other applications\n\u2022 Support system implementation of SAP\nRequirements:\n\n\u2022 Higher diploma or above in IT, Computer Science or related disciplines\n\u2022 Work independently or with supporting vendors\n\u2022 5 \u2013 8 years of working experience in network/server administration\n\u2022 Knowledgeable in HR, ERP, WMS & POS\n\u2022 Flexible to adopt new technologies and knowledge\n\u2022 Self-motivated, organized, flexible with a can-do attitude\n\u2022 Good communication, analytical, project management & problem solving skills;\n\u2022 Detail-minded, committed to work and able to prioritize effectively\n\u2022 Conversant with spoken and written English, Cantonese and Mandarin\n\u2022 Applicants with less experiences will be considered as Assistant IT Manager\nApplications without expected salary and insufficient information will not be processed\n\n", "employment_types": ["Full Time"], "selling_points": [], "locations": ["Kwun Tong"], "categories": ["Admin & HR", "Others", "Marketing / Public Relations", "Marketing - General / Support", "Others"], "post_time": "2022-01-17T06:55:06Z", "salary": {"currency": null, "max": null, "min": null, "period": "monthly", "term": null}, "salary_visible": false, "title_keywords": ["it manager"], "responsibilities": ["data", "expenses", "budget", "systems", "implementation", "maintain"], "requirements": {"degrees": ["higher diploma or above"], "majors": ["related disciplines", "it", "computer science"], "languages": ["cantonese", "english", "mandarin"], "language_level": [], "hard_skills": ["pos", "server administration", "erp", "project management", "problem solving skills"], "soft_skills": ["flexible", "organized", "work independently", "self-motivated", "detail-minded", "able to prioritize", "can-do attitude", "communication", "project management", "committed", "problem solving skills"], "languages_combined": [{"language": "cantonese", "language_level": []}, {"language": "english", "language_level": []}, {"language": "mandarin", "language_level": []}]}, "experience_required": {"duration": ["8 years"], "field": ["it", "server administration"]}}, {"job_id": "100003009048401", "location_code": "hk", "company": "MTR Corporation Limited", "job_title": "Marketing Supervisor (Ref: 22000024)", "description": "Responsibilities\n\nSupervise the MTR Merchandising and Souvenirs\u2019 sales operation and performance, product procurement and development, financial administration, stock inventory and distribution logistics as well as support development and distribution of publicity materials (both online and offline)\nLiaise with external and internal parties on the execution of MTR Merchandising and Souvenirs\u2019 sales promotions, including creative agencies, suppliers, laboratory test companies, etc.\u00a0\nAssist in sales and promotion to MTR Mobile users and internal staff\nHandle daily enquiries and complaints related to MTR Merchandising and Souvenirs\u2019 sales business and provide possible resolutions and execution\n\nRequirements\n\nDegree in Marketing / Business Administration or a related discipline\u00a0\nA minimum of 2 year\u2019s relevant experience in marketing\nGood teamwork, organising, interpersonal and communication skills\nProficiency in written and spoken English and Chinese is essential\u00a0\n\nApplications\n\nYou are invited to apply online via http://www.mtr.com.hk/mtr_job_en or send in your CV stating the position (with reference number) you are applying for by mail to Human Resource Management Department, MTR Corporation, G.P.O. Box 9916, Hong Kong on or before\u00a027\u00a0January 2022.\u00a0\n\nFor other job openings, please visit MTR Corporation's website for more details. All information provided by applicants will be treated in strict confidence and used for recruitment purpose only.\n\nAll personal data of unsuccessful applicants will be retained for 12 months for future recruitment purpose and will then be destroyed.", "employment_types": ["Full Time"], "selling_points": ["Supervise the MTR Merchandising", "Degree in Marketing / Business Administration", "A minimum of 2 year\u2019s relevant experience"], "locations": ["Others"], "categories": ["Marketing / Public Relations", "Marketing - General / Support", "Marketing - Market Research", "Marketing - Marketing Communication"], "post_time": "2022-01-14T06:28:15Z", "salary": {"currency": null, "max": null, "min": null, "period": "monthly", "term": null}, "salary_visible": false, "title_keywords": ["supervisor"], "responsibilities": ["inventory", "merchandising", "logistics", "liaise with", "internal parties", "administration"], "requirements": {"degrees": ["degree"], "majors": ["marketing", "business administration"], "languages": ["english", "chinese"], "language_level": ["proficiency"], "hard_skills": [], "soft_skills": ["communication skills", "confidence", "teamwork", "interpersonal"], "languages_combined": [{"language": "english", "language_level": ["proficiency"]}, {"language": "chinese", "language_level": ["proficiency"]}]}, "experience_required": {"duration": ["minimum of 2 year"], "field": ["marketing", "relevant experience"]}}, {"job_id": "100003009054926", "location_code": "hk", "company": "Apass International Hong Kong Company Limited", "job_title": "(Assistant) Merchandising Officer - FMCG / Food", "description": "Our\u00a0client is a well-established food distributor representing a number of prestigious Japanese FMCG/food brands and having good market share in Hong Kong.\u00a0\nIn line with their business development, they now require a responsible and detail-minded talent to join their team as Merchandising Officer.\u00a0 The caliber with less years of relavant working experiences will be considered as Assistant Merchandising Officer.\n\n\u00a0Responsibilities:\n\nHandle merchandising & sourcing matters, such as purchasing, suppliers, inventory;\nResponsible for logistics/warehouse operation and stock-take operation regularly;\nCoordinate in purchasing operation with Japan or overseas offices;\nHandle shipping cost calculation, quality control on products importing to Hong Kong;\nAssist in marketing events & regular stock operations\n\nRequirements:\n\nTertiary education in buying/purchasing or business relating discipline;\nAt least 5 years working experience in purchasing/product control, especially in Food & Beverage / Retailing industry;\nGood command in spoken English and Cantonese;\nExcellent language literacy (both spoken and written) in Japanese is highly preferable;\nProficient in MS Office, Sage Accpac knowledge an advantage;\nDetailed-minded and good problem solving skills with strong sense of responsibility", "employment_types": ["Full Time", "Permanent"], "selling_points": ["Established food discributor of many famous brands", "Great exposure-purchase, marketing & merchandising", "Dynamic Japanese culture & utilise language skill"], "locations": ["Others"], "categories": ["Transportation & Logistics", "Shipping", "Marketing / Public Relations", "Marketing - General / Support", "Merchandising & Purchasing", "Procurement / Purchasing / Sourcing"], "post_time": "2022-01-17T14:06:55Z", "salary": {"currency": null, "max": null, "min": null, "period": "monthly", "term": null}, "salary_visible": false, "title_keywords": ["officer", "merchandising", "assistant"], "responsibilities": ["marketing events", "cost", "shipping", "operations", "inventory", "merchandising", "coordinate", "logistics", "quality control"], "requirements": {"degrees": [], "majors": [], "languages": ["cantonese", "japanese", "english"], "language_level": ["excellent", "good command"], "hard_skills": ["accpac", "problem solving skills", "ms office"], "soft_skills": ["problem solving skills", "sense of responsibility", "detailed"], "languages_combined": [{"language": "cantonese", "language_level": ["good command"]}, {"language": "japanese", "language_level": ["excellent"]}, {"language": "english", "language_level": ["good command"]}]}, "experience_required": {"duration": ["at least 5 years"], "field": ["purchasing", "food"]}}, {"job_id": "100003009056400", "location_code": "hk", "company": "Regal Hotels International", "job_title": "Digital Creative Director", "description": "Job Description\n\nResponsibilities\n\nHead of the internal Design Team. Lead on execution and supervise the progress of design, visual, video and webpage creations\nWork closely with the Marketing Team and conceptualize the Creative Idea based on the requirements on the design brief\nDevelop digital materials, like animations, illustrations, logos, typefaces, banners and other designs\nSupervise video and photo productions, including shooting, retouching and editing\nBeing the team\u2019s \u201cgo-to-person\u201d and coordinate the design requirement and schedule with different internal departments\nBeing the company\u2019s \u201cdesign gatekeeper\u201d and ensure all the designs are up to standard and visually on-brand\n\n\u00a0Requirements\n\nHigher diploma or above in Graphic / Multimedia Design or related disciplines\nMinimum 5 years solid working design experience in graphic, typography, photo retouch, branding, online ads, video and website, etc.\nExcellent knowledge in Photoshop, After Effect, Premiere, Illustrator and InDesign\nGood knowledge in content consumption, internet as well as design trends\nGood knowledge in coding, GDN banner, social media, video editing and UI design software\nCandidate with experience gained from agencies are highly preferred\nStrong communication skills and managerial experience\nMulticultural, high on creativity & willingness to learn\nGood command of spoken and written English & Chinese", "employment_types": ["Full Time"], "selling_points": ["Graphic, typography, photo retouch, branding", "Design visual video and webpage creations", "GDN banner, social media, video editing. UI design"], "locations": ["Causeway Bay"], "categories": ["Marketing / Public Relations", "Marketing - Brand / Product Management", "Marketing - General / Support", "Others"], "post_time": "2022-01-18T04:10:15Z", "salary": {"currency": null, "max": null, "min": null, "period": "monthly", "term": null}, "salary_visible": false, "title_keywords": ["creative director"], "responsibilities": ["retouching", "design", "develop", "coordinate", "banners", "animations", "schedule", "visual", "editing"], "requirements": {"degrees": ["higher diploma or above"], "majors": ["multimedia design", "related disciplines"], "languages": ["english", "chinese"], "language_level": ["good command"], "hard_skills": ["indesign", "illustrator", "premiere", "video editing", "multimedia", "after effect", "photoshop"], "soft_skills": ["communication skills"], "languages_combined": [{"language": "english", "language_level": ["good command"]}, {"language": "chinese", "language_level": ["good command"]}]}, "experience_required": {"duration": ["minimum 5 years"], "field": ["managerial", "photo", "video", "design", "graphic"]}}, {"job_id": "100003009054186", "location_code": "hk", "company": "Konew Financial Express Ltd", "job_title": "Manager, Partnership & CRM", "description": "Main Duties & Responsibilities:\n\n\nIdentify potential partnership opportunities for new mobile app business (CRM)\nFormulate agile and effective partnership exploration and retention, CRM and reward management strategy to achieve the business target and members' satisfaction\nUtilise data intelligence to pursue strategic planning and initiate continuous membership engagement projects\nExplore market trends and develop product value propositions from time to time\nConduct regular reports of data analysis to evaluate effectiveness and optimise business direction\nMake recommendation, raise demands of the product development and liaise with fintech team to achieve continuous product realisation\nSupport any ad-hoc projects and tasks as assigned by superior\n\nRequirements:\n\nBachelor Degree, preferably in Marketing / Digital Communications related discipline, or equivalent\nMinimum 8 years' relevant experience in partnership and loyalty program with at least 3 years in supervisory role\nProven track record of rewards management of loyalty program\nExcellent negotiation, interpersonal and presentation skills\nStrong business acumen with excellent problem solving and data analytical skills\nExcellent command of spoken and written English and Chinese\nCandidate with less experience will be considered as Assistant Manager\n\nWe offer:\n\nDiscretionary bonus\nMedical insurance\nDental insurance\nHardship allowance\nCompetitive annual leave days\nBirthday leave\nAnniversary leave\nPerformance reward days\nStudy leave\nMarriage leave\nCompassionate leave\n\nHow to apply:\n\nInterested parties, please send your resume stating your expected salary to Human Capital Department\u00a0by clicking \"APPLY NOW\".\n\n(We are an equal opportunity employer.\u00a0 Personal data collected will be used for recruitment purpose only.\u00a0 The unsuccessful applications will be destroyed after 6 months.)", "employment_types": ["Full Time", "Permanent"], "selling_points": ["Identify potential partnership opportunities", "Formulate effective partnership exploration", "Initiate continuous membership engagement projects"], "locations": ["Central"], "categories": ["Sales, CS & Business Devpt", "Business Development", "Marketing / Public Relations", "Marketing - General / Support"], "post_time": "2022-01-17T08:44:01Z", "salary": {"currency": null, "max": null, "min": null, "period": "monthly", "term": null}, "salary_visible": false, "title_keywords": ["manager"], "responsibilities": ["management", "mobile app", "strategic planning", "make recommendation", "data", "develop", "data analysis", "evaluate", "reports", "liaise with", "ad-hoc projects"], "requirements": {"degrees": ["degree", "bachelor"], "majors": ["marketing", "communications"], "languages": ["english", "chinese"], "language_level": ["excellent"], "hard_skills": ["problem solving", "analytical skills", "acumen"], "soft_skills": ["negotiation", "analytical skills", "problem solving", "presentation skills", "business acumen", "interpersonal"], "languages_combined": [{"language": "english", "language_level": ["excellent"]}, {"language": "chinese", "language_level": ["excellent"]}]}, "experience_required": {"duration": ["at least 3 years", "minimum 8 years"], "field": ["supervisory", "relevant experience"]}}, {"job_id": "100003009044762", "location_code": "hk", "company": "Tech Vision System Limited", "job_title": "Marketing Executive", "description": "Responsibilities\n\n-\u00a0\u00a0\u00a0\u00a0\u00a0\u00a0\u00a0 Provide support on the day-to-day central marketing activities and operations\n\n-\u00a0\u00a0\u00a0\u00a0\u00a0\u00a0\u00a0 Handle social media postings, communicate with influencers and promoted our brand and products\n\n-\u00a0\u00a0\u00a0\u00a0\u00a0\u00a0\u00a0 Provide operation support on both online and office events and other marketing promotions\n\n-\u00a0\u00a0\u00a0\u00a0\u00a0\u00a0\u00a0 Meet with customers and participate in local exhibitions\n\n-\u00a0\u00a0\u00a0\u00a0\u00a0\u00a0\u00a0 Team admin & reporting tasks\n\n-\u00a0\u00a0\u00a0\u00a0\u00a0\u00a0\u00a0 Assist in ad hoc duties when required\n\nRequirements\n\n\u00a0-\u00a0\u00a0\u00a0\u00a0\u00a0\u00a0\u00a0 Diploma or equivalent qualification\n\n-\u00a0\u00a0\u00a0\u00a0\u00a0\u00a0\u00a0 Good written and spoken communication skills in English and Chinese / Mandarin\n\n-\u00a0\u00a0\u00a0\u00a0\u00a0\u00a0\u00a0 1-2 years relevant working experience\n\n-\u00a0\u00a0\u00a0\u00a0\u00a0\u00a0\u00a0 Proficiency in MS office, Adobe Photoshop and illustrator is preferred\n\n-\u00a0\u00a0\u00a0\u00a0\u00a0\u00a0\u00a0 Independent and good team player\n\n-\u00a0\u00a0\u00a0\u00a0\u00a0\u00a0\u00a0 Well organized, pro-active and self-motivated\n\n-\u00a0\u00a0\u00a0\u00a0\u00a0\u00a0\u00a0 Immediate availability is an advantage", "employment_types": ["Full Time", "Permanent"], "selling_points": ["Medical insurance & Performance bonus", "Opportunity for growth", "5 Day Work, stable environment"], "locations": ["Wong Tai Sin Area"], "categories": ["Information Technology (IT)", "Hardware", "Marketing / Public Relations", "Marketing - Brand / Product Management", "Marketing - General / Support"], "post_time": "2022-01-13T06:11:24Z", "salary": {"currency": null, "max": null, "min": null, "period": "monthly", "term": null}, "salary_visible": false, "title_keywords": ["marketing executive"], "responsibilities": ["communicate with", "social media", "provide support", "reporting", "ad hoc duties", "operations", "marketing promotions"], "requirements": {"degrees": ["diploma"], "majors": [], "languages": ["english", "chinese", "mandarin"], "language_level": ["good"], "hard_skills": ["adobe photoshop", "illustrator", "ms office"], "soft_skills": ["communication skills", "good team player", "self-motivated", "independent", "well organized", "pro-active"], "languages_combined": [{"language": "english", "language_level": ["good"]}, {"language": "chinese", "language_level": ["good"]}, {"language": "mandarin", "language_level": ["good"]}]}, "experience_required": {"duration": ["1-2 years"], "field": ["relevant working experience"]}}, {"job_id": "100003009055899", "location_code": "hk", "company": "Metro Broadcast Corporation Ltd", "job_title": "Sales Support Officer (Ref#: SSO)", "description": "Job requirements:\n\nDegree holder in Marketing, Business Administration or related disciplines\nMinimum 1-2 years' experience in digital marketing, media advertising or related field\nAttention to details, able to work under tight timeline and multi-task independently\nWell-organized and a good team player\nProficiency in MS Office applications (Word, Excel, Powerpoint)\nGood command of spoken and written English and Chinese\nLess related experience will be considered as junior position\nImmediate available is highly preferable\n\n\u00a0Job description:\n\nAssist sales team to handle sales orders including order processing, account servicing and documentation work\nAssist sales team to plan, organize and monitor sales campaigns\nWork closely with New Media to coordinate content update of digital platforms\nPrepare post-campaign reports with analysis of campaign effectiveness, data insights and project outcomes.\nHandle ad-hoc tasks assigned by Management\u00a0\nIf you are interested and have the required qualification, please send your full resume together with expected salary in confidence to the HR & Admin. Dept., Metro Broadcast Corp. Ltd., Basement 2, Site 6, Whampoa Garden, Hunghom, Kln.\n\n\nAll information provided will be treated in strict confidence and be used solely for consideration of your application. Personal data of unsuccessful applicants will be destroyed after the recruitment exercise. (Please quote our reference no. for the position applied on the envelop)", "employment_types": ["Full Time", "Permanent"], "selling_points": [], "locations": ["Hung Hom"], "categories": ["Marketing / Public Relations", "Marketing - General / Support", "Media & Advertising", "Broadcasting - TV / Radio", "Sales, CS & Business Devpt", "Account Servicing"], "post_time": "2022-01-18T03:03:56Z", "salary": {"currency": null, "max": null, "min": null, "period": null, "term": null}, "salary_visible": false, "title_keywords": ["sales support officer"], "responsibilities": ["management", "data", "analysis", "ad-hoc tasks", "monitor", "hr", "coordinate", "sales team", "reports", "order processing", "plan", "documentation", "recruitment", "personal data"], "requirements": {"degrees": ["degree holder"], "majors": ["related disciplines", "marketing", "business administration"], "languages": ["english", "chinese"], "language_level": ["good command"], "hard_skills": ["excel", "word", "powerpoint", "ms office"], "soft_skills": ["good team player", "independently", "multi-task", "well-organized", "attention to details"], "languages_combined": [{"language": "english", "language_level": ["good command"]}, {"language": "chinese", "language_level": ["good command"]}]}, "experience_required": {"duration": ["minimum 1-2 years"], "field": ["related", "advertising", "digital marketing", "media"]}}, {"job_id": "100003009051191", "location_code": "hk", "company": "Mindset Asia Limited", "job_title": "Marketing Expert - Industrial/Manufacturing sector", "description": "Responsibilities:\n\nSupport and assist \u00a0in the planning and execution of the marketing and advertising campaigns\nRender quality works in copywriting and translation\u00a0 for marketing materials including press releases, invitations and catalogues\nFoster close working relationship with journalists and editors of international and local media\nCreate and develop contents for social media channels and ensure they are updated accordingly and timely\nConduct market researches and evaluate the effectiveness of all marketing activities\nLogistic support fordifferent events and campaigns\nAssist in ad-hoc projects as assigned\nHandle general clients\u2019 enquiries when necessary during the auction seasons\n\n\nRequirements:\n\n3\u00a0years\u00a0or above\u00a0of\u00a0work experience in press and marketing field\nExperience in translation, copyediting or copywriting will be an advantage, preferably from the field of art\nGood command of both written and spoken Cantonese, Putonghua and English\nExperience in handling different social media accounts\nMulti-tasking skills, attentive to details\u00a0and able to work under pressure\nStrong proficiency with MS Word, Excel,\u00a0PowerPoint\u00a0and Chinese Word Processing\nExcellent time management skills, ability to meet deadlines;\nTravel required when necessary\n\nPersonal data collected will be used for recruitment purpose only\n\nOnly shortlisted candidates will be notified.", "employment_types": ["Full Time"], "selling_points": [], "locations": ["Not Specified"], "categories": ["Marketing / Public Relations", "Management", "Marketing - Brand / Product Management", "Marketing - General / Support"], "post_time": "2022-01-15T04:29:50Z", "salary": {"currency": null, "max": null, "min": null, "period": "monthly", "term": null}, "salary_visible": false, "title_keywords": [], "responsibilities": ["social media", "quality", "logistic support", "develop", "evaluate", "contents", "marketing materials", "ad-hoc projects", "advertising campaigns", "planning"], "requirements": {"degrees": [], "majors": [], "languages": ["cantonese", "putonghua", "english", "chinese"], "language_level": ["proficiency", "good command"], "hard_skills": ["excel", "chinese word processing", "powerpoint", "translation", "ms word"], "soft_skills": ["attentive to details", "time management skills", "multi-tasking skills", "meet deadlines", "work under pressure"], "languages_combined": [{"language": "cantonese", "language_level": ["good command"]}, {"language": "putonghua", "language_level": ["good command"]}, {"language": "english", "language_level": ["good command"]}, {"language": "chinese", "language_level": ["proficiency"]}]}, "experience_required": {"duration": ["3 years"], "field": ["copywriting", "social media", "marketing"]}}, {"job_id": "100003009049514", "location_code": "hk", "company": "Tokyo Chuo Auction Hongkong Company Limited", "job_title": "Marketing and Communication Officer", "description": "Responsibilities\n\n\u00a0The successful candidate will be involved in providing PR services to a client portfolio of blue-chip multinationals that represents leaders and fast growing organizations in the corporate, technology and consumer disciplines.\u00a0\n\n\u00a0Requirements\n\nUniversity graduate, preferably in Journalism, Communications or English Language\nWith PR/communications/social and digital media experience is an advantage\nGood understanding of and relations with media\u00a0\u00a0\nExcellent English and Chinese language skills\nSelf-starter,\u00a0quick learner,\u00a0responsible with good working attitude\nProactive, creative, good team spirit with a can-do attitude\nAble and willing to work under pressure\u00a0\n\nInterested parties please apply by clicking \"Apply Now\" together with your resume, cover letter and salary expectation.\n\nAll information collected will be used for recruitment purposes only", "employment_types": ["Full Time", "Permanent"], "selling_points": ["Assist in planning and implementing PR promotions", "Prepare marketing and PR collaterals", "Coordinate advertising campaign"], "locations": ["Central & Western Area"], "categories": ["Marketing / Public Relations", "Marketing - General / Support", "Marketing - Marketing Communication", "Public Relations - Event Management"], "post_time": "2022-01-14T08:47:08Z", "salary": {"currency": null, "max": null, "min": null, "period": "monthly", "term": null}, "salary_visible": false, "title_keywords": ["communication officer"], "responsibilities": [], "requirements": {"degrees": ["university graduate"], "majors": ["journalism", "communications"], "languages": ["english", "chinese"], "language_level": ["excellent"], "hard_skills": [], "soft_skills": ["good working attitude", "team spirit", "creative", "responsible", "can-do attitude", "quick learner", "proactive", "work under pressure"], "languages_combined": [{"language": "english", "language_level": ["excellent"]}, {"language": "chinese", "language_level": ["excellent"]}]}, "experience_required": {"duration": [], "field": ["pr", "digital media"]}}, {"job_id": "100003009052194", "location_code": "hk", "company": "IPSOS", "job_title": "Research Executive - Healthcare (Quantitative & Qualitative)", "description": "Are you looking for a career in within one of the world\u2019s largest research organization?\n\nTo cope with the transformation of the research industry and also support our rapidly growing business, we are looking for talents to work with us, who will be provided valuable exposure to a wide spectrum of industries, innovative tools & platforms and insightful analytical frameworks in Hong Kong as well as the APAC region.\n\n\nWe are looking for a Research Executive to manage projects throughout the entire process from research designs, to draft questionnaires, analyze data and produce deliverables.\u00a0 Fresh graduates are welcome!\n\nDepending on experience, candidates may also be considered for the role of Senior Research Executive.\n\nRole Objective / Purpose\n\nThis is an entry level which starts with supporting their respective teams on day to day project implementation. Those with relevant experience may be considered for senior executive position.\n\nThe nitty-gritty:\n\nRole & Responsibilities\uff1a\n\nSupport contents creation for pitches\nPrepare and check research materials, platforms\nMonitor project progress and quality\nAssist in analysis and report preparation\nData management (e.g. respondent list cleaning)\nConduct quantitative interviews with doctors or patients\nWork on qualitative verbatim transcripts or content analysis\nCollect fieldwork materials from doctor\u2019s clinic\nMaterials translation\n\n\u00a0\u00a0Qualification\uff1a\n\n\nFresh graduate\nUniversity degree holder in any discipline (advantage if related to public health, nutrition, finance, marketing, international studies)\nExcellent spoken and written English; Putonghua a plus\n\nWork Location: Whampoa\n\nWe are committed to equality, treating people fairly, promoting a positive and inclusive working environment, and ensuring diversity of people and views. We recognize that this is important for our business success - a more diverse workforce will enable us to reflect better and understand the world we research and ultimately deliver better research and insight to our clients. We understand the importance of choice and offer a blended work environment - office and work from home.\n\nCome to join us if you consider yourself\u00a0agile, bold, collaborative, determined, and entrepreneurial!\u00a0\n\nSend us your application to us\u00a0and we will reach back to you for a chat!\n\n\n\nAll personal information collected will be used for recruitment purposes only. Resumes will be destroyed 12 months after date of receipt.", "employment_types": ["Full Time", "Permanent"], "selling_points": ["Data analysis", "Quantitative and Qualitative research", "Project Management"], "locations": ["Hung Hom"], "categories": ["Marketing / Public Relations", "Marketing - General / Support", "Marketing - Market Research"], "post_time": "2022-01-17T02:26:09Z", "salary": {"currency": null, "max": null, "min": null, "period": "monthly", "term": null}, "salary_visible": false, "title_keywords": ["executive"], "responsibilities": ["management", "monitor project progress", "data", "analysis", "teams", "implementation", "quality", "manage projects", "cleaning", "contents", "analyze data", "report"], "requirements": {"degrees": ["university degree", "fresh graduate"], "majors": ["finance", "public health", "marketing"], "languages": ["putonghua", "english"], "language_level": ["excellent"], "hard_skills": ["translation", "analysis", "data management", "plus"], "soft_skills": ["innovative"], "languages_combined": [{"language": "putonghua", "language_level": []}, {"language": "english", "language_level": ["excellent"]}]}, "experience_required": {"duration": [], "field": ["research", "relevant experience"]}}, {"job_id": "100003009053468", "location_code": "hk", "company": "High Fashion Group", "job_title": "Marketing & Product Development Manager", "description": "Responsibilities:\u00a0\n\nAcquire the latest trends of the market, Develop and explore new business opportunities in overseas market\nConduct planning, execution and communication of a development strategy that meets and exceeds financial goal\nDevelop new customers for company, visit customers on a regular basis, maintain good relationship with customers\nDrive effective and efficient communication between fabric, development and production teams to ensure that contract, budgets and development schedules are targeted\nFormulating marketing and sales strategies, implementing action plans to achieve business KPI objectives\n\nRequirements:\u00a0\u00a0\n\nDegree / Diploma in Textiles and Clothing, Design or related disciplines\nRich customer resources, has ability to develop new customers and new market\n8+ year\u2019s solid experience in handling ladies high fashion or sporty fashion mainly in US or European market\nPresentable, pro-active, energetic, global vision, judgmental marketing insight, aggressive with good communication skills\nBase in HK, willing to travel occasionally\n\nWe offer an attractive package, good prospects and fringe benefits to the right candidate. Interested parties, please apply with full resume, current and expected salary to: Group Human Resources Manager of High Fashion Group. By click below \"APPLY NOW\"(in MS Word format), or by mail: 11/F., High Fashion Centre, 1-11 Kwai Hei Street, Kwai Chung, New Territories\n\n(The information received will be used for consideration of employment only and all personal data supplied will be destroyed within 6 months.)", "employment_types": ["Full Time", "Permanent"], "selling_points": ["5 days, bonus, medical & life insurance", "Lunch allowance, birthday leave", "Flexible working hours"], "locations": ["Kwai Fong"], "categories": ["Manufacturing", "Garment / Textile", "Product Development / Management", "Marketing / Public Relations", "Marketing - General / Support"], "post_time": "2022-01-17T07:01:07Z", "salary": {"currency": null, "max": null, "min": null, "period": "monthly", "term": null}, "salary_visible": false, "title_keywords": ["product development manager"], "responsibilities": ["budgets", "explore new business opportunities", "schedules", "teams", "maintain good relationship", "communication", "develop", "plans", "planning"], "requirements": {"degrees": ["diploma", "degree"], "majors": ["related disciplines", "design"], "languages": [], "language_level": [], "hard_skills": [], "soft_skills": ["communication skills", "energetic", "pro-active", "presentable"], "languages_combined": []}, "experience_required": {"duration": ["8+ year"], "field": []}}, {"job_id": "100003009047983", "location_code": "hk", "company": "Venchi HK Limited", "job_title": "Part-time Marketing Assistant", "description": "To provide high-quality deliverables in marketing campaign and communications to HKIB members and stakeholders by supporting the Marketing, Membership & Events (MME) Team to enhance Membership engagement and build brand awareness. \u00a0\n\nJob Responsibilities\n\nProvide administrative support to projects and events covering conferences, awards, seminars and government funded activities targeting different stakeholders\nHandle registration, payment, CRM entries, enquiries relating to MME projects and events targeting different stakeholders ranging from senior secondary schools & university students; current and potential banking practitioners at different seniority\nProvide draft write-ups including event invitations, messages to members, social media posts, pre and post-event promotions, etc.\nSolicit cross-team support and collaborate with vendors to ensure smooth execution\nHandle any ad-hoc projects or tasks assigned by supervisors\n\u00a0\n\nJob Requirements\n\nUniversity degree holder or above, preferably in marketing or event management\nMinimum 3 years of experience preferably from marketing or event management\nStrong communications skills and attention to details\nProactive and a good team player\nOutgoing, curious and resourceful\nExcellent English and Chinese writing skills\nFluent in spoken English, Cantonese and Putonghua\nGood PC skills including MS Office, Adobe and simple website editing\nCandidates with more experience will be considered for the Senior Officer position\n\nInterested parties may send in your application together with a detailed resume stating your\u00a0academic results, present & expected salaries, date of availability\u00a0and contact phone number by clicking\u00a0\"Apply Now\"\n\nApplicants are welcome to visit our website:\u00a0www.hkib.org\u00a0for further information about the institute.\n\n(All information provided will be treated in strict confidence and used solely for recruitment purposes)", "employment_types": ["Part Time", "Contract", "Internship"], "selling_points": ["Part time", "Marketing Intern", "2-3 days per week"], "locations": ["Wan Chai"], "categories": ["Admin & HR", "Clerical / Admin Staff", "Marketing / Public Relations", "Marketing - General / Support", "Public Relations - General / Support"], "post_time": "2022-01-14T04:24:47Z", "salary": {"currency": null, "max": null, "min": null, "period": "monthly", "term": null}, "salary_visible": false, "title_keywords": ["marketing assistant"], "responsibilities": ["collaborate with", "social media", "conferences", "payment", "banking", "provide administrative support", "ad-hoc projects"], "requirements": {"degrees": ["university degree"], "majors": ["marketing"], "languages": ["cantonese", "putonghua", "english", "chinese"], "language_level": ["excellent", "fluent"], "hard_skills": ["simple", "writing skills", "adobe", "pc skills", "ms office"], "soft_skills": ["outgoing", "good team player", "resourceful", "writing skills", "attention to details", "proactive"], "languages_combined": [{"language": "cantonese", "language_level": ["fluent"]}, {"language": "putonghua", "language_level": ["fluent"]}, {"language": "english", "language_level": ["excellent", "fluent"]}, {"language": "chinese", "language_level": ["excellent"]}]}, "experience_required": {"duration": ["minimum 3 years"], "field": ["management", "marketing"]}}, {"job_id": "100003009049488", "location_code": "hk", "company": "The Hong Kong Institute Of Bankers", "job_title": "Officer - Marketing, Membership & Events", "description": "Job Description:\n\n\nProvide administrative support to the Marketing Department\nAssist in\u00a0tender preparation and service contract management for business development\nAct as primary contact with clients and handle all aspects of account-servicing\nAssist in ad hoc projects as assigned\nRequirements:\n\n\nHKDSE / Form\u00a05 or above\n1 year relevant experience in sales and marketing or account-servicing is an absolute advantage\nSelf-motivated, analytical and attentive to details\nGood command of both written and spoken English and Chinese\nProficiency in MS Word, Excel, PowerPoint and Chinese word processing\nImmediate available is highly preferable\nCandidate with more experience will be considered as Assistant Marketing Officer\nFresh Graduates are welcome\nWe treasure human resources as our most valuable asset. We offer 5-day work week, attractive remuneration package and career advancement opportunities to the right candidate. Interested parties please send full resume with your present and expected salary by one of the following means:\n\nEmail:\u00a0whhr @waihong.com.hk\u00a0or Click \u201cApply Now\u201d\n\nFax\u00a0\u00a0 : 2786 8563\n\nMail: Unit 813, 8/F, Chevalier Commercial Centre, 8 Wang Hoi Road, Kowloon Bay, Kowloon\n\nPlease quote our reference no. on subject line of the email / fax / envelopecover.\nWaihong is an equal opportunity employer and welcomes applications from all qualified candidates. Personal data provided by job applicants will be used strictly in accordance with the employer's personal data policies, a copy of which will be provided immediately upon request.", "employment_types": ["Full Time", "Permanent"], "selling_points": ["Great development opportunity", "Membership Benefit and Events", "Banking & Finance Institution"], "locations": ["Sheung Wan"], "categories": ["Marketing / Public Relations", "Marketing - General / Support", "Public Relations - Event Management", "Public Relations - General / Support"], "post_time": "2022-01-14T08:44:27Z", "salary": {"currency": null, "max": null, "min": null, "period": "monthly", "term": null}, "salary_visible": false, "title_keywords": ["officer"], "responsibilities": ["contract management", "ad hoc projects", "contact", "tender preparation", "provide administrative support"], "requirements": {"degrees": ["hkdse", "form 5 or above"], "majors": [], "languages": ["english", "chinese"], "language_level": ["proficiency", "good command"], "hard_skills": ["excel", "chinese word processing", "powerpoint", "ms word"], "soft_skills": ["self-motivated", "attentive to details"], "languages_combined": [{"language": "english", "language_level": ["good command"]}, {"language": "chinese", "language_level": ["proficiency", "good command"]}]}, "experience_required": {"duration": ["1 year"], "field": ["marketing", "relevant experience"]}}, {"job_id": "100003009043038", "location_code": "hk", "company": "Waihong Environmental Services Limited", "job_title": "Marketing Assistant (Ref: MKT0101)", "description": "Responsibilities:\n\nCoordinate and implement projects and events related to business development and marketing\nManage key accounts in an organized and professional manner, actively engage clients through proactive follow-up actions and delivering quality services\nLiaise with internal departments and external parties for formulation and implementation of business development activities\nAssist in system setting\nProvide administrative support to the team\nPerform other ad hoc duties as assigned\n\nRequirement:\n\nDegree in Marketing, Business Administration or related disciplines\nAt least 1 year solid working experience in business development in Medical or insurance sector\nWilling to work in fast-paced environment with tight schedule and embrace the changes\nEnthusiastic, initiative, detail minded and able to work independently\nMature, flexible, hard working with good problem solving skills\nGood interpersonal and communication skills\nGood working attitude and be a good team player\nProficiency in MS Office (Excel, PowerPoint, Chinese Word Processing, etc.)\nGood command of both written and spoken English and Chinese\nCandidate with more experience will be considered to Senior position\n\nWe offer attractive package to the right candidate. Please apply with full resume stating\u00a0present & expected salary\u00a0and date available to: The Human Resources Department by\u00a0clicking\u00a0APPLY NOW.", "employment_types": ["Full Time", "Permanent"], "selling_points": [], "locations": ["Kowloon Bay"], "categories": ["Admin & HR", "Clerical / Admin Staff", "Sales, CS & Business Devpt", "Business Development", "Marketing / Public Relations", "Marketing - General / Support"], "post_time": "2022-01-12T09:37:07Z", "salary": {"currency": null, "max": null, "min": null, "period": "monthly", "term": null}, "salary_visible": false, "title_keywords": ["marketing assistant"], "responsibilities": ["ad hoc duties", "external parties", "quality", "professional manner", "implementation", "coordinate", "liaise with", "provide administrative support"], "requirements": {"degrees": ["degree"], "majors": ["related disciplines", "marketing", "business administration"], "languages": ["english", "chinese"], "language_level": ["proficiency", "good command"], "hard_skills": ["excel", "chinese word processing", "powerpoint", "problem solving skills", "ms office"], "soft_skills": ["flexible", "communication skills", "work independently", "good working attitude", "good team player", "hard working", "mature", "work in fast-paced environment", "enthusiastic", "problem solving skills", "interpersonal", "initiative"], "languages_combined": [{"language": "english", "language_level": ["good command"]}, {"language": "chinese", "language_level": ["proficiency", "good command"]}]}, "experience_required": {"duration": ["at least 1 year"], "field": ["business development", "insurance", "medical"]}}, {"job_id": "100003009056370", "location_code": "hk", "company": "China Mobile Hong Kong \u4e2d\u570b\u79fb\u52d5\u9999\u6e2f", "job_title": "Assistant Product Manager (IoT Products)", "description": "Responsibilities:\n\nConsolidate and analyze customer behavioral data, generate insights from in-depth analysis\nIdentify market segment opportunities and formulate the upsell / retention strategy of each segment\nMonitor subscriber base and revenue movement, analyze the usage behavioral change before and after program\nWork with cross-functional departments for the segmentation of marketing programs, performing data quality checking and measuring the program effectiveness\nMeasure, report and analyze marketing program effectiveness, keep track of inbase performance with company KPIs\nCollect market intelligence on competitors' offer\nSupport for ad hoc assignments and projects\n\nRequirements:\n\nDegree holder in Marketing, Quantitative Analysis, Business Studies or related disciplines\nAt least 2 years working experience in telecom, banking or insurance products\u00a0\nDetail-oriented and self-motivated\nStrong numerical sense\nGood communication, interpersonal and presentation skills\nSkills of customer segmentation and data analysis would be an advantage\n\nApart from competitive remuneration package and exciting opportunity for career development within the Group, we provide attractive employee benefits such as free company shuttle, free company SIM card and preferential SIM plan offers, comprehensive medical & insurance schemes, as well as full range of other employee well-being provisions.\u00a0\n\nInterested parties, please apply with full resume, present and expected salary, by clicking \u201cAPPLY NOW\u201d. Please quote the reference number on the e-mail subject.\n\nWe are an equal opportunity employer and welcome applications from all qualified candidates. Personal data collected will be treated in the strictest confidence and handled confidentially by authorised personnel for recruitment-related purposes only within the CK Hutchison Group of companies. The personal data of unsuccessful applicants will be destroyed after the recruitment exercise pursuant to the requirements of the Personal Data (Privacy) Ordinance in Hong Kong.", "employment_types": ["Full Time", "Permanent"], "selling_points": ["Product Management", "IoT", "3 years of experience"], "locations": ["Kwai Hing"], "categories": ["Information Technology (IT)", "Product Management / Business Analyst", "Marketing / Public Relations", "Marketing - Brand / Product Management", "Marketing - General / Support"], "post_time": "2022-01-18T04:05:59Z", "salary": {"currency": null, "max": null, "min": null, "period": null, "term": null}, "salary_visible": false, "title_keywords": ["assistant product manager"], "responsibilities": ["quality checking", "data", "analysis", "monitor", "ad hoc assignments", "kpis", "report"], "requirements": {"degrees": ["degree holder"], "majors": ["business", "related disciplines", "marketing"], "languages": [], "language_level": [], "hard_skills": ["analysis"], "soft_skills": ["self-motivated", "detail-oriented", "communication", "presentation skills", "comprehensive", "interpersonal"], "languages_combined": []}, "experience_required": {"duration": ["at least 2 years"], "field": ["insurance products", "banking"]}}, {"job_id": "100003009051288", "location_code": "hk", "company": "Hutchison Telecommunications (Hong Kong) Limited", "job_title": "Marketing Executive", "description": "Requirements:\u00a0\n\nWork with senior management to develop proposal content and prepare document\nCoordinate internally the design, selection, purchase and distribution of proposed materials\nCoordinate externally with suppliers and source new vendors for on-going projects\nArrange procurement and deliverable schedule\nAssist in maintaining the marketing database\nAssist the marketing team in regular daily operation and any other ad hoc tasks\n\nResponsibilities:\n\nDegree Holder in business, marketing or related discipline.\nMinimum 1-2 years of marketing experience.\u00a0\nTakes initiative, energetic and able to handle multi assignments.\nCommunicates the progress of work to management regularly\nWell organized, hard working and\u00a0able to work under pressure\nGood communication skill with fluent command of English and Mandarin\nProficiency in MS Office and Chinese Word Processing\nFresh graduates are welcome to apply\n\nWe offer comprehensive package and a team-oriented environment. If you are seeking a dynamic career in industry-leading firm, please send us your full resume.\n\nPlease visit www.fusion.com.hk for more information.\n\n(Data collected would be used for recruitment purpose only)", "employment_types": ["Full Time", "Permanent"], "selling_points": [], "locations": ["Tsing Yi"], "categories": ["Marketing / Public Relations", "Marketing - Brand / Product Management", "Marketing - General / Support", "Marketing - Market Research"], "post_time": "2022-01-15T07:17:39Z", "salary": {"currency": null, "max": null, "min": null, "period": "monthly", "term": null}, "salary_visible": false, "title_keywords": ["marketing executive"], "responsibilities": ["communication", "management", "work under pressure"], "requirements": {"degrees": [], "majors": [], "languages": [], "language_level": [], "hard_skills": [], "soft_skills": [], "languages_combined": []}, "experience_required": {"duration": [], "field": []}}, {"job_id": "100003009049707", "location_code": "hk", "company": "Fusion Design Limited", "job_title": "MARKETING ASSISTANT", "description": "Job Responsibilities:\n\nAssist in\u00a0developing tactical marketing strategies which align with the business plan\nCreate\u00a0story and content for marketing collaterals include website, eShop, EDM and social media platforms like FB, IG, WeChat\nPrepare\u00a0marketing collaterals, trainings, presentations, tent cards, posters, etc.\nConduct\u00a0market intelligence & marketing analysis on marketing campaigns\nBuild\u00a0relationships with clients and develop new target segments\nLiaise\u00a0and connect closely with internal stakeholders, external agencies and business partners on marketing activities and projects\nHandle\u00a0departmental hotline, answer customer enquiries and follow-up\nProvide\u00a0support to Marketing Department on daily operation and all marketing events and promotions\nPerform any ad-hoc duties as assigned\nJob Requirements:\n\nBachelor degree / Higher Diploma in Marketing or business related discipline is preferred\nAt least 2 years of relevant experience in Marketing\nPrior\u00a0experience in healthcare, servicing, insurance and brokerage industry is advantageous\nKnowledge\u00a0of website, SEO, SEM practices and social media metrics\nUp-to-date\u00a0on the latest trends and technologies in digital marketing\nIndependent,\u00a0responsible, detail-oriented, good time management, a dedicated team player and self-motivated\nGood command in written English and Chinese\nImmediately available will be advantageous\nCandidate with less experience will be considered as Marketing Assistant\nWe offer competitive remuneration package to right candidate. Please submit your resume with expected salary to HR Department (Data collected will be used for the purpose of recruitment only.)", "employment_types": ["Full Time", "Permanent"], "selling_points": ["Fresh graduates are welcome to apply", "Good communication & interpersonal skill", "Degree Holder"], "locations": ["North Point"], "categories": ["Marketing / Public Relations", "Marketing - Direct Marketing", "Marketing - General / Support", "Marketing - Marketing Communication"], "post_time": "2022-01-14T09:07:57Z", "salary": {"currency": null, "max": null, "min": null, "period": "monthly", "term": null}, "salary_visible": false, "title_keywords": ["marketing assistant"], "responsibilities": ["liaise", "marketing events", "provide support", "marketing strategies", "edm", "customer enquiries", "analysis", "marketing collaterals", "social media platforms", "developing", "website", "presentations", "develop", "daily operation", "marketing campaigns", "ad-hoc duties", "business plan"], "requirements": {"degrees": ["diploma", "degree", "bachelor"], "majors": ["business", "marketing"], "languages": ["english", "chinese"], "language_level": ["good command"], "hard_skills": ["seo", "sem"], "soft_skills": ["self-motivated", "independent", "responsible", "detail-oriented", "team player", "time management"], "languages_combined": [{"language": "english", "language_level": ["good command"]}, {"language": "chinese", "language_level": ["good command"]}]}, "experience_required": {"duration": ["at least 2 years"], "field": ["healthcare", "brokerage", "marketing", "relevant experience", "insurance"]}}, {"job_id": "100003009051412", "location_code": "hk", "company": "Medifast (Hong Kong) Limited", "job_title": "Marketing Executive / Marketing Assistant", "description": "Responsibilities:\n\nPrepare frontlines user requirement for new process design, and perform UAT to ensure process launch smoothly\nReview system logic and follow through system enhancements for increasing frontlines' effectiveness and productivity\nConduct regular compliance check for daily operations of different sales channels\n\n\nRequirements:\n\nUniversity graduate with minimum\u00a02 years\u2019 relevant experience in telecommunication field\nExperience in process management or project coordination for sales & customer service functions\nExperience in RPA\n\nInterested parties please apply with full resume stating present and expected salary.\n\nSmarTone is an equal-opportunity employer.\u00a0 All data supplied will be kept in strict confidence and will be used for employment related purpose.\u00a0 We may transfer such data to any agent, contractor or third party who provides services to us with respect to matters relating to your application. Only short-listed candidates will be contacted.\n\u00a0\n\nYou are welcome to visit our website : smartone.com", "employment_types": ["Full Time", "Permanent"], "selling_points": [], "locations": ["Causeway Bay"], "categories": ["Marketing / Public Relations", "Marketing - General / Support", "Marketing - Market Research", "Marketing - Marketing Communication"], "post_time": "2022-01-15T15:14:05Z", "salary": {"currency": null, "max": null, "min": null, "period": "monthly", "term": null}, "salary_visible": false, "title_keywords": ["marketing assistant", "marketing executive"], "responsibilities": ["user requirement", "uat", "review", "compliance", "design", "daily operations"], "requirements": {"degrees": ["university graduate"], "majors": [], "languages": [], "language_level": [], "hard_skills": ["rpa"], "soft_skills": ["customer service", "coordination"], "languages_combined": []}, "experience_required": {"duration": ["minimum 2 years"], "field": ["management", "customer service", "relevant experience"]}}, {"job_id": "100003009053109", "location_code": "hk", "company": "SmarTone Telecommunications Limited", "job_title": "Senior Sales Operations Officer / Sales Operations Officer", "description": "Key Responsibilities\n\nPlan, organise and manage major company events in physical, hybrid or virtual formats. Devise strategic implementation plan\nDevelop and implement strategic planning to create an integrated event experience. Curate programmes and activities to align Cyberport\u2019s public missions and to enhance its position and brand as thought leadership and industry voice in the region\nProvide full support on wide spectrum of event management including but not limited to project scheduling, speaker co-ordination, programme development, stage management, promotion and advertising, marketing collaterals, stage production, manpower management, onsite logistics, as well as market research and procurement\nPlan, source and incorporate innovative event elements to enhance traction and attendee experience, including digital/stage gimmicks, interactive games, incentives, event platforms/solutions etc.\nDrive attendance and positive publicity through integrated marketing & communications in conjunction with Branding & Corporate Communications teams to achieve best synergies, incl. event content marketing and distribution via effective channels for maximum audience engagement & impact\nExplore, solicit and follow up potential collaborations, partnerships and sponsorships opportunities for better event synergy\nLiaise and work closely with different business units, agencies/vendors, Government or public bodies and industry organisations\nManage marketing budget and monitor event P/L\n\nRequirements\n\nDegree in marketing, journalism, mass communications, public relations or related discipline\nMinimum 10 years relevant working experience in corporate/event management, event production & marketing, corporate communications, marketing communication and / or public relations with hands-on experience in physical, hybrid and virtual events ideally from sizable organization/public bodies and preferably from technology sector\nAll-round experience & proven track record in planning and managing large scale industry conference and events a must\nKnowledge and experience in hybrid/ virtual events, event platforms/technologies, creative digital elements, stage management, cross-platform marketing and user experience is essential\nConnection with industry associations, chambers of commerce, industry organisations and speakers bureau for potential collaborations, sponsorship solicitation, and/or speakers invitations a plus\nStrong event and project management skills, especially hybrid events\nGood understanding of technicality & acumen on integrated event platforms, registration and EDM systems and virtual event setup\nA fast mover and strategic thinker with who possess new normal agility with excellent efficiency and strategic focus\nA relationship-builder and team player with excellent interpersonal and negotiation skills\nExcellent command of written and spoken English and Chinese (Cantonese and Putonghua)\nOutstanding project management and organisational skills\nAble to work effectively under pressure and deliver high quality work under tight deadlines/ schedules\nDetail-oriented with exceptional strengths in multi-tasking\nA self-motivated team player with strong can-do attitude\nCreative, analytical and well-organised\n\nThe position is on a renewable 2-year fixed-term contract, subject to performance and operational needs, the position will convert into open contract after 2 years.\n\nWe offer competitive package to the right candidate. Interested party please click\u00a0Apply Now\u00a0to apply on or before 11 February 2022\u00a0in confidence with full resume in Word document, stating present and expected salary, and available date\u00a0and quote the reference.\u00a0\n\nApplicants who do not hear from us by 25 February 2022\u00a0may assume that their applications are unsuccessful.\n\nFurther information about the Cyberport is available at\u00a0http://www.cyberport.hk", "employment_types": ["Full Time", "Permanent"], "selling_points": ["Prepare user requirement for new process design", "Review system logic and perform UAT", "Conduct regular compliance check"], "locations": ["Ngau Tau Kok"], "categories": ["Marketing / Public Relations", "Marketing - General / Support", "Sales, CS & Business Devpt", "Sales - Sales Management", "Sales Administration"], "post_time": "2022-01-17T05:52:55Z", "salary": {"currency": null, "max": null, "min": null, "period": "monthly", "term": null}, "salary_visible": false, "title_keywords": ["sales", "operations officer", "senior sales"], "responsibilities": ["liaise", "attendance", "management", "advertising", "strategic planning", "marketing collaterals", "teams", "implementation", "market research", "develop", "budget", "monitor", "logistics", "project scheduling", "plan"], "requirements": {"degrees": ["degree"], "majors": ["journalism", "marketing", "communications"], "languages": ["cantonese", "putonghua", "english", "chinese"], "language_level": ["excellent"], "hard_skills": ["project management", "plus", "focus", "acumen"], "soft_skills": ["work effectively", "self-motivated", "under pressure", "can-do attitude", "project management skills", "detail-oriented", "communication", "project management", "hands-on", "team player", "negotiation skills", "organisational skills", "multi-tasking", "well-organised", "focus", "creative", "interpersonal"], "languages_combined": [{"language": "cantonese", "language_level": ["excellent"]}, {"language": "putonghua", "language_level": ["excellent"]}, {"language": "english", "language_level": ["excellent"]}, {"language": "chinese", "language_level": ["excellent"]}]}, "experience_required": {"duration": ["minimum 10 years"], "field": ["management", "public relations", "sizable organization", "relevant working experience", "marketing", "digital", "planning"]}}, {"job_id": "100003009052841", "location_code": "hk", "company": "Hong Kong Cyberport Management Co Ltd", "job_title": "Manager - Corporate Marketing (Ref# MCM220117J)", "description": "Job Description\n\nManage and create content for social media platforms (including Facebook and Instagram), including copywriting and image creating/editing\nCommunicate with Media and Press on advertorials and PR activities\nAssist in planning, organizing and implementing sales, marketing strategies and event management to drive brand awareness and customer engagement\nAnalyze sales and promotional data for generating insights towards promotion effectiveness\nResponse to online and offline enquiries, as to build and grow the customer community\nHandle other offline ad-hoc projects and assignments as assigned\n\nRequirements\n\nAble to work independently and under pressure to meet tight deadlines\nSelf-motivated, customer-focused and task-oriented\nStrong knowledge in Google Ad Manager, SEO, SEM, Google Analytics and Facebook Ad Manager, EDM tools etc\n3-5 years marketing experience with solid exposure in retail marketing\nKnowledge of graphic designs, photo editing (e.g.: Adobe Illustrator, Photoshop)\u00a0\nImmediate available or short notice is highly preferred", "employment_types": ["Full Time", "Permanent", "Contract"], "selling_points": ["Manage major company events", "strategic planning to create an event experience", "Build collaborations, partnerships and sponsorship"], "locations": ["Pok Fu Lam"], "categories": ["Marketing / Public Relations", "Marketing - General / Support", "Marketing - Marketing Communication", "Public Relations - Event Management"], "post_time": "2022-01-17T04:14:05Z", "salary": {"currency": null, "max": null, "min": null, "period": "monthly", "term": null}, "salary_visible": false, "title_keywords": ["manager"], "responsibilities": ["communicate with", "management", "ad-hoc projects", "marketing strategies", "data", "social media platforms", "facebook", "editing", "planning"], "requirements": {"degrees": [], "majors": [], "languages": [], "language_level": [], "hard_skills": ["google analytics", "seo", "adobe illustrator", "sem", "facebook", "photoshop"], "soft_skills": ["work independently", "self-motivated", "customer-focused", "under pressure", "meet tight deadlines"], "languages_combined": []}, "experience_required": {"duration": ["3-5 years"], "field": ["marketing", "retail"]}}, {"job_id": "100003009050341", "location_code": "hk", "company": "OTG Onthego Limited", "job_title": "Assistant Marketing Manager / Senior Marketing Officer (Medical insurance)", "description": "Are you looking for a career at one of the world\u2019s largest research organizations?\u00a0\n\nTo cope with the transformation of the research industry and also support our rapidly growing business, we are looking for talents to work with us, who will be provided valuable exposure to a wide spectrum of industries, innovative tools & platforms and insightful analytical frameworks in Hong Kong as well as the APAC region.\n\nWe are looking for a Research Executive to manage projects throughout the entire process from research designs, to draft questionnaires, analyze data and produce deliverables.\u00a0Fresh graduates are welcome!\n\nDepending on experience, candidates may also be considered for the role of\u00a0Senior Research Executive.\n\nKey Responsibility:\n\nLiaise with internal teams and counterparts to ensure projects run smoothly, on time, and within budget\nCommunicate with project management and operations teams to positively impact project outcome\nCoordinate and manage data entry of project costs into internal costing program based on research target specifications\nAssist in analyzing research data and secondary sources to deliver stories and narratives to focus on data insights\nSupport content creation for pitches, proposal preparation and delivery by using Ipsos solutions and tools\n\nQualifications:\n\n\n\nFresh graduate\nUniversity degree holder in any discipline\n1-2 years marketing research experience and correlative marketing experience\nAnalytical skills and data literacy required\nStrong team player with a positive attitude\nAbility to work in a fast-paced environment\nGood organization and communication skills essential\n\nWe are committed to equality, treating people fairly, promoting a positive and inclusive working environment, and ensuring diversity of people and views. We recognize that this is important for our business success - a more diverse workforce will enable us to reflect better and understand the world we research and ultimately deliver better research and insight to our clients. We understand the importance of choice and offer a blended work environment - office and work from home.\n\nCome to join us if you consider yourself\u00a0agile, bold, collaborative, determined, and entrepreneurial!\n\nSend us your application\u00a0and we will reach back to you for a chat!", "employment_types": ["Full Time"], "selling_points": [], "locations": ["Lai Chi Kok"], "categories": ["Marketing / Public Relations", "Marketing - Brand / Product Management", "Marketing - General / Support", "Marketing - Marketing Communication"], "post_time": "2022-01-16T21:50:25Z", "salary": {"currency": null, "max": null, "min": null, "period": "monthly", "term": null}, "salary_visible": false, "title_keywords": ["assistant marketing manager", "senior marketing officer"], "responsibilities": ["communicate with", "data entry", "data", "operations", "budget", "teams", "coordinate", "liaise with", "project management", "specifications", "marketing research", "manage projects", "communication", "analyze data", "costs"], "requirements": {"degrees": ["university degree", "fresh graduate"], "majors": [], "languages": [], "language_level": [], "hard_skills": ["project management", "focus", "agile", "analytical skills"], "soft_skills": ["communication skills", "agile", "determined", "fast-paced environment", "collaborative", "bold", "analytical skills", "positive attitude", "project management", "committed", "team player", "diverse", "focus", "innovative", "positive"], "languages_combined": []}, "experience_required": {"duration": ["1-2 years"], "field": ["research", "marketing"]}}, {"job_id": "100003009052199", "location_code": "hk", "company": "IPSOS Asia Limited", "job_title": "Senior / Research Executive - Quantitative", "description": "ACW Distribution (HK) Limited\u00a0is a Value-Added Distribution corporation for leading Enterprise Solutions in the Asia-Pacific region since 1986. We create IT solutions by integrating the \"Best-of-Breed\" \u200bproducts in the market and delivering them to the end user via an extensive network of trained and certified channel partners in the region.\u00a0Please follow our\u00a0social media\u00a0pages to get recent update:\u00a0\n\nFacebook:\u00a0https://www.facebook.com/ACWDHK/\nLinkedIn:\u00a0https://www.linkedin.com/company/acw-distribution-hk-limited/\nMeWe:\u00a0https://mewe.com/p/acwdistributionhklimited\nYouTube:\u00a0https://www.youtube.com/channel/UCvsDmyxikBjraB69-7hmELQ/featured\n\nTo support our expansion, we invite high caliber professionals to join us.\n\n\n\nJob Responsibilities\n\nAssist supervisor to:\u00a0\n\n\nPlan and execute online and offline marketing activities and sales promotional activities\nBuild and Maintain brand awareness & engagement through different digital platforms (e.g.\u00a0SEM, Facebook, LinkedIn, corporate website)\nCoordinate with internal and external parties for supporting various types of marketing programs\nDesign a promotion plan for respective IT brands that link back to the overall brand objectives\nTrack the effectiveness of respective promotion programs within budget and timeline\nDraft promotion message of marketing campaigns as well as brochures, incentive program, bundle offer, etc.\nAssist in database management and telemarketing project for the company\nHandle any ad hoc project assigned by the team\n\n\n\nJob Requirements\n\n\n1-2 years relevant experience in field marketing / event marketing / or IT product marketing\nDegree in Marketing / Business / Communication or equivalent is preferred\nCreative, innovative, open to new ideas, challenges and change\nWilling to be a good team player\nAbility to perform multi-tasks with meeting deadline while having good negotiation skill\nGood written and verbal communication and presentation skills in English and Chinese\n\n\nWe offer competitive\u00a0remuneration\u00a0package and attractive employee benefits including 5-day work, 12-14 annual leave, medical leave, medical insurance, bank holiday, on-job training, education allowance and discretionary bonus.\n\nInterested parties shall submit your application to \"APPLY NOW\" or HR @ acw-group.com.hk.\n\nAll information will be treated in the strictest confidence and used only for recruitment purposes. Applicants not invited for interview within four weeks from the date of the posting may consider their applications unsuccessful. Unsuccessful applications will be destroyed after the recruitment exercise.\u00a0", "employment_types": ["Full Time", "Permanent"], "selling_points": ["Data analysis", "Quantitative research", "Project Management"], "locations": ["Hung Hom"], "categories": ["Marketing / Public Relations", "Marketing - General / Support", "Marketing - Market Research"], "post_time": "2022-01-17T02:26:12Z", "salary": {"currency": null, "max": null, "min": null, "period": "monthly", "term": null}, "salary_visible": false, "title_keywords": ["executive"], "responsibilities": ["management", "ad hoc", "internal and external parties", "coordinate with", "website", "design", "budget", "maintain", "promotional activities", "sem", "plan", "marketing campaigns", "facebook", "database"], "requirements": {"degrees": ["degree"], "majors": ["business", "marketing"], "languages": ["english", "chinese"], "language_level": ["good"], "hard_skills": [], "soft_skills": ["good team player", "multi-tasks", "innovative", "communication", "presentation skills", "negotiation skill", "creative"], "languages_combined": [{"language": "english", "language_level": ["good"]}, {"language": "chinese", "language_level": ["good"]}]}, "experience_required": {"duration": ["1-2 years"], "field": ["marketing", "relevant experience", "it"]}}, {"job_id": "100003009049660", "location_code": "hk", "company": "ACW Distribution (HK) Ltd", "job_title": "Marketing Executive (IT Company)", "description": "Job descriptions\nAssist in all marketing activities including digital, App marketing, event and other marketing programs\nCreate ongoing promotional and product content across different channels\nProcess good knowledge in video editing and production\nLiaise with internal and external parties to ensure execution for online and offline\u00a0marketing campaigns in driving brand awareness and promoting customer engagement\nRequirements\nHigher Diploma in Marketing / Digital Marketing/ Communications or related discipline\n3\u00a0years of relevant working experience, preferably from financial industry\nGood command of written and spoken English and Chinese (including Mandarin)\nProficient computer literacy, MS Office, Excel, PowerPoint and video editing software\nDetailed minded, self-motivated and a good team player\nCandidate with more experience will be considered as Senior Marketing Officer\nAttractive salary and fringe benefits package will be provided to the right candidate. Please send a full resume with contact number and expected salary by clicking 'Apply Now'.\nData collected will be kept confidential and will be used for recruitment purposes only.", "employment_types": ["Full Time", "Permanent"], "selling_points": ["Deep dive in physical and virtual events", "Exposure with international IT brands", "Work-life balance with open team culture"], "locations": ["North Point"], "categories": ["Marketing / Public Relations", "Marketing - Brand / Product Management", "Marketing - General / Support", "Digital Marketing"], "post_time": "2022-01-14T09:01:53Z", "salary": {"currency": null, "max": null, "min": null, "period": "monthly", "term": null}, "salary_visible": false, "title_keywords": ["marketing executive"], "responsibilities": ["internal and external parties", "video editing", "marketing campaigns", "liaise with", "product content"], "requirements": {"degrees": ["diploma"], "majors": ["marketing", "digital marketing", "communications"], "languages": ["english", "chinese", "mandarin"], "language_level": ["good command"], "hard_skills": ["video editing", "excel", "powerpoint", "ms office"], "soft_skills": ["computer literacy", "self-motivated", "good team player", "detailed"], "languages_combined": [{"language": "english", "language_level": ["good command"]}, {"language": "chinese", "language_level": ["good command"]}, {"language": "mandarin", "language_level": ["good command"]}]}, "experience_required": {"duration": ["3 years"], "field": ["marketing", "financial industry", "relevant working experience"]}}, {"job_id": "100003009052070", "location_code": "hk", "company": "Keysen (LPB) Management Services Limited", "job_title": "Sales Manager", "description": "The Marketing Store Worldwide (TMS), a HAVI Company, is a Global Customer Engagement Agency and Sourcing Company, with areas of expertise that include consumer promotions, toys and premiums, shopper marketing, digital platforms and innovation. TMS now ranks among the largest toy manufacturers in the world.\u00a0\n\n\n\nWHAT IS THIS ROLE ABOUT\n\nThe Senior Director, Brand Partnerships and Licensing, APMEA is a key stakeholder of the Global Brand Partnership Team. With a solid background on entertainment and licensing, the Senior Director, Brand Partnerships and Licensing, APMEA will be in charge of successfully leading market Calendar Planning Process while continuously working with the Global Brand Partnership Team to ensure markets alignment with overall McDonald\u2019s Strategy and Business Goals.\n\nAreas of responsibilities include:\n\nLead communications with market\u2019s Happy Meal Client\nLead and develop markets calendar proposals.\nLead and develop industry insights for the market - while supporting global insights reports\nSupport the Global Brand Partnership team with market program performance insights\n\nJob Relationships:\n\nReports to: Vice President, Brand Partnerships\nRelationships and Communications:\u00a0Regular and ongoing interactions with TMS colleague in various agency departments such as: Global Brand Partnership Team, Planning/Strategy, Global Havi Analytics Team, Account Team and TMS counterparts in Asia/MEA/LATAM/Europe\n\nWHAT YOU\u2019LL BRING TO TMS\n\nYouth & Family Calendar Planning (Market)\n\nResponsible for leading all communications with market\u2019s Happy Meal Client.\nResponsible for leading and developing market\u2019s calendar planning recommendations.\nEarn and keep each clients\u2019 respect and confidence as a trusted advisor bringing continuous value to their business.\nAcquire and build-upon knowledge of and be conversant in clients\u2019 business \u2013 their key issues, competitive situation, and industry trends.\nDemonstrate confidence and authority as the day-to-day voice of the agency for assigned projects.\nDevelop and/or leads client presentations for all assigned work/execution.\nAssist in establishing thought leadership/POV specific to a project or initiative.\nParticipate in client meetings to provide a project perspective and input\nLicensing and Entertainment Industry Analytics (Market)\u00a0\nResponsible for tracking market\u2019s local trends: family\u2019s trends, consumer trends.\nResponsible for keeping clients updated on markets entertainment & licensing environment. Proactively develop local insights report to ensure TMS expertise across the globe.\nResponsible for developing markets post-trade show reports\nResponsible for tracking market\u2019s competitive landscape.\u00a0\n\nProgram Performance Analytics (Market)\u00a0\n\nResponsible for tracking market\u2019s program performance.\nSupport Global Brand Partnership team on Global Program Performance report by adding market\u2019s insights and pov.\u00a0\n\nGlobal Brand Partnership Team (Market)\u00a0\n\nDevelop and nurture the relationship with the Global Brand Partnership team by:\nUpdating the team on market\u2019s calendar planning needs\nParticipate from global meetings with recommendations and opportunities to keep expanding agency\u2019s global approach.\nSupport Global Team with markets insights on entertainment & licensing industry as part of the teams\u2019 efforts to provide global insights.\n\n\u00a0SKILLS AND EXPEREINCE WE\u2019D LIKE YOU TO HAVE\u00a0\n\nExperience of working in an integrated agency environment, client side or as a Marketing Manager, Family experience would be of benefit (but not essential)\nAble to lead by example, be solutions orientated with a continuous-learning approach\nEntrepreneurial spirit \u2013 taking and creating opportunities with clients and across the agency alike\nStrong strategic and critical thinking skills with demonstrable track record\nExcellent presentation skills (writing, reviewing and delivering) and ability to express ideas with clarity, confidence and logical reasoning\nAble to work well and prioritise under pressure\nProven ability to develop solutions that address client\u2019s business issues and opportunities\nYou thrive on taking ownership of your projects and deliver best-in-class executions\nSolid experience in an agency-side partnerships role, as either a seasoned Senior Partnerships Manager or Partnership Account Director\nMeticulous attention to detail and passion for understanding & following process. Ability to review and recommend on procedural efficiencies that will help us deliver for our client and partners.\nExperience analysing, synthesizing, and utilising data to make recommendations that drive engagement. Working with a data analyst to do so\nUnderstanding of the agency\u2019s philosophy and vision\nComputer skills (Proficient in Microsoft Word, Excel and PowerPoint + key email, schedule and internet applications, etc.)\nCompetent in accessing online databases and conducting Internet research\nWorks under frequent time pressures and distractions\u00a0\n\nInterested parties please send your full resume with present and expected salary by clicking \"Apply Now\". All personal data will be used for recruitment purpose only.\n\nOnly shortlisted candidates will be contacted.\u00a0\n\nWe are the Marketing Store and we would love to meet you!\u00a0", "employment_types": ["Full Time", "Permanent"], "selling_points": ["Beauty Industry", "Support marketing activities", "Retail or FMCG industry"], "locations": ["Mong Kok"], "categories": ["Beauty Care / Health", "Others", "Marketing / Public Relations", "Marketing - Brand / Product Management", "Marketing - General / Support"], "post_time": "2022-01-17T02:01:41Z", "salary": {"currency": null, "max": null, "min": null, "period": "monthly", "term": null}, "salary_visible": false, "title_keywords": ["sales manager"], "responsibilities": ["consumer trends", "make recommendations", "business goals", "communications with", "tracking", "ideas", "data", "planning process", "teams", "developing", "presentations", "develop", "review", "reports", "schedule", "databases", "report", "planning"], "requirements": {"degrees": [], "majors": [], "languages": [], "language_level": [], "hard_skills": ["excel", "microsoft word", "presentations", "powerpoint", "make", "computer skills", "databases"], "soft_skills": ["make recommendations", "meticulous", "confidence", "under pressure", "responsible", "passion for", "competent", "prioritise", "presentation skills", "learning", "attention to detail", "leadership", "initiative"], "languages_combined": []}, "experience_required": {"duration": [], "field": ["agency", "marketing"]}}, {"job_id": "100003009042220", "location_code": "hk", "company": "Techtronic Industries Co Ltd", "job_title": "Marketing Executive  (English & Korean Speaking)", "description": "Responsibilities:\n\nAssist in implementing and coordinating marketing communications activities, global and regional.\nEvents management \u2013coordinate the webinar, conferences, roundtables, etc\nLiaise in development of marketing collateral based on brand standards, for both HQ and regional marketing teams.\nManage inventory and distribution logistics of branded premium gifts and group level collateral for both HQ and regional marketing team.\nProvide assistance and support to Office Manager with office administrative work & receptionist support.\u00a0\nAssist with ad hoc task to support the business as and when required\n\nRequirements:\n\nDegree holder in Marketing or business-related disciplines\nMinimum of 2 years relevant experience, preferably with China market knowledge.\u00a0\nAgency background or in-house marketing role managing global brands preferred\nAble to work independently. Dynamic, creative, resourceful, reliable, passionate, multi-tasking individual with the capability to articulate business objectives in a compelling manner\nStrong interpersonal skills in communicating with people from different backgrounds and at all levels, both internally and externally\nStrong team player with excellent project management and time management.\nProficiency in MS Office, skills in Photoshop and Adobe InDesign is an advantage\nExcellent command of both written and spoken English, Mandarin and Cantonese\nImmediate available is highly preferred\n\nInterested parties, please send your application with your current & expected salary and date availability with full resume to Human Resources Department by clicking \"Apply Now\".", "employment_types": ["Full Time", "Permanent"], "selling_points": ["Support Marketing campaigns and activities", "Manage and maintain digital channel", "Good communication skill"], "locations": ["Kwai Hing"], "categories": ["Marketing / Public Relations", "Marketing - Brand / Product Management", "Marketing - General / Support", "Digital Marketing"], "post_time": "2022-01-12T06:39:49Z", "salary": {"currency": null, "max": null, "min": null, "period": "monthly", "term": null}, "salary_visible": false, "title_keywords": ["marketing executive"], "responsibilities": ["liaise", "management", "ad hoc", "administrative work", "inventory", "teams", "coordinate", "conferences", "logistics", "provide assistance"], "requirements": {"degrees": ["degree holder"], "majors": ["business", "related disciplines", "marketing"], "languages": ["cantonese", "english", "mandarin"], "language_level": ["excellent"], "hard_skills": ["adobe indesign", "project management", "dynamic", "ms office", "photoshop"], "soft_skills": ["passionate", "work independently", "creative", "resourceful", "time management", "project management", "multi-tasking", "dynamic", "interpersonal skills", "articulate", "team player", "reliable"], "languages_combined": [{"language": "cantonese", "language_level": ["excellent"]}, {"language": "english", "language_level": ["excellent"]}, {"language": "mandarin", "language_level": ["excellent"]}]}, "experience_required": {"duration": ["minimum of 2 years"], "field": ["relevant experience"]}}]