[{"job_id": "100003009053682", "location_code": "hk", "company": "Adsale Exhibition Services Ltd", "job_title": "Assistant Project Executive - Marketing Communications", "description": "(Ref : EXH-MCAPE-005-2022)\n\nResponsibilities:\n\nAssist in different kinds of projects from planning to execution, e.g. events, video/animation, live stream, design.\nProvide support to marketing campaigns through ATL & BTL channels.\nPrepare promotion materials, eDMs, printed & online advertisements as well as reports.\nWork closely with internal cross-functional teams and external parties to generate different marketing assets and ensure execution.\nAssist ad hoc project when required.\n\n\u00a0Requirements:\n\nDegree\u00a0holder with at least 2\u00a0years solid experience in Marketing, preferably in advertising agency/ exhibition industry, with digital marketing experience is an advantage.\nExcellent in written and spoken English and Chinese ( incl. Putonghua).\nMature, pro-active, self-motivated, well organized and detail-oriented.\nA team player with good communication skills\u00a0 and able to work under multitasking environment.\nBasic knowledge of producing eDM, artwork editing and promotion via Social Media are preferable.\nOccasional mainland China trips are required.\n\nWe offer attractive remuneration package including 5-day work, double pay, medical insurance, medical check-up, birthday leave, training and excellent development prospect to the right candidate.\u00a0Interested parties please send full resume with expected salary, availability and contact no. to\u00a0The Human Resources & Administration Manager\u00a0by fax :\u00a03586-0196\u00a0or click\u00a0APPLY NOW.\u00a0 \u201cPlease quote our job reference\u201d\u00a0\n\nCorporate Website : www.adsale.com.hk\n\n(All personal data will be used for recruitment purpose only)", "employment_types": ["Full Time"], "selling_points": ["5-day work week; double pay with bonus", "Assist different projects, planning to execution", "2 years solid experience in Marketing"], "locations": ["North Point"], "categories": ["Marketing / Public Relations", "Marketing - General / Support", "Marketing - Marketing Communication", "Public Relations - Event Management"], "post_time": "2022-01-17T07:20:30Z", "salary": {"currency": null, "max": null, "min": null, "period": "monthly", "term": null}, "salary_visible": false, "title_keywords": ["project executive", "assistant"], "responsibilities": ["provide support", "edms", "internal cross-functional teams", "ad hoc", "advertisements", "external parties", "design", "reports", "marketing campaigns", "animation", "planning"], "requirements": {"degrees": ["degree holder"], "majors": ["marketing", "digital marketing"], "languages": ["putonghua", "english", "chinese"], "language_level": ["excellent"], "hard_skills": ["basic"], "soft_skills": ["communication skills", "self-motivated", "well organized", "mature", "detail-oriented", "pro-active", "team player"], "languages_combined": [{"language": "putonghua", "language_level": []}, {"language": "english", "language_level": ["excellent"]}, {"language": "chinese", "language_level": ["excellent"]}]}, "experience_required": {"duration": ["at least 2 years"], "field": ["marketing", "digital marketing", "advertising agency"]}}, {"job_id": "100003009054102", "location_code": "hk", "company": "Endeavour Search Limited", "job_title": "Associate Director (Marketing & Corporate Communications) - HK & GBA Presences", "description": "Executive Summary:\n\n\u2022 Our client is a growing innovation & technology organization with a strong presence across the Hong Kong and Greater Bay areas.\n\u2022 The successful candidate will be the key business leader to drive marketing communication success and be responsible for corporate communications and media relations.\n\u2022 Highly competitive remuneration package will be offered to the right candidate; This is a unique career opportunity to ride on the booming technology industry growth across Hong Kong and GBA in the next 5-10 years\n\u2022 Proven commercial background with major government or business organizations with Great China exposure a strong plus\n\nMajor Responsibilities:\n\n\u2022 Reporting to CEO, this role will assume responsibilities for spearheading marketing and communications strategy and execution\n\u2022 Develop integrated marketing and communications strategy that supports and advances the brand awareness and drives positive public image that can contribute to the development of the organization\u2019s ecosystem\n\u2022 Drive external relationships and proactive engagement with local and international stakeholders including relevant government departments, regulatory bodies, universities, R&D institutions, industry leaders and NGOs to lobby to support the organization's vision and strategic imperatives\n\u2022 Support business development activities through organizing industry, marketing and community events which engage and appeal to local and overseas tech ventures and startups, incubators, accelerators and top entrepreneurs and talents as well as facilitating partnerships, business matching and corporate engagements\n\u2022 Responsible for public affairs, issue and crisis management; taking a proactive role in identifying potential issues, evaluating reputation risks and providing recommendations and communications plans for the senior management\n\u2022 Develop compelling messaging for corporate announcements and speaking platforms; and work closely with the organization's senior leaders to develop content assets, not limited to keynote presentations, social media posts, thought leadership pieces spanning across paid, owned and earned media platforms\n\u2022 Perform other duties and tasks assigned by CEO.\n\u2003\n\nKey Requirements:\n\n\u2022 Degree in Marketing, Communications, Business, or related subjects, with at least 12-15 years of experience in PR, communications, business development and marketing positions, preferably gained in MNC / sizable companies.\n\u2022 Strong track record in strategic brand management, reputation management and stakeholder engagements for respected companies preferably with presence in Greater China, Greater Bay Area and/or globally.\n\u2022 Good understanding and appreciation of technology trends. Ability to work with global and local technology ventures and startups and provide value-added advice and support to them for promoting their innovations.\n\u2022 Profound understanding and hands-on experience on government relations and excellent in strategic thinking and able to drive corporate narratives that align with various business priorities.\n\u2022 Possess the ability to work with diverse categories of stakeholders and excellent communications skills that can command impact when interacting with industry players, academia, board members and other key stakeholders etc.\n\u2022 Strong business acumen, problem solving and leadership skills with excellent command of spoken/written English and Chinese (including excellent fluency in Mandarin).\n\nTo apply, please send your CV in word document to Gloria(a)endeavourasia.com or call Gloria at 3956-1829 for a confidential discussion.", "employment_types": ["Full Time", "Permanent"], "selling_points": ["Stable, long term career development", "Semi-government technology organization", "Fluent English & Mandarin"], "locations": ["Shatin Area"], "categories": ["Marketing / Public Relations", "Marketing - General / Support", "Marketing - Marketing Communication", "Public Relations - General / Support"], "post_time": "2022-01-17T08:23:22Z", "salary": {"currency": null, "max": null, "min": null, "period": "monthly", "term": null}, "salary_visible": false, "title_keywords": ["associate director"], "responsibilities": ["reporting", "social media", "perform other duties", "presentations", "develop", "plans", "senior management", "crisis management"], "requirements": {"degrees": ["degree"], "majors": ["business", "marketing", "communications"], "languages": ["english", "chinese", "mandarin"], "language_level": ["fluency", "excellent"], "hard_skills": ["problem solving", "sizable companies", "word", "acumen"], "soft_skills": ["strategic thinking", "leadership skills", "problem solving", "diverse", "hands-on", "business acumen"], "languages_combined": [{"language": "english", "language_level": ["fluency", "excellent"]}, {"language": "chinese", "language_level": ["fluency", "excellent"]}, {"language": "mandarin", "language_level": ["fluency", "excellent"]}]}, "experience_required": {"duration": ["at least 12-15 years"], "field": ["pr", "related", "business development", "business", "marketing"]}}, {"job_id": "100003009054100", "location_code": "hk", "company": "OSMA Consulting Limited", "job_title": "Marketing Assistant \u5e02\u573a\u90e8\u4e13\u5458", "description": "Our Client is a Hong Kong based Fin-tech company with founding members from reputable local family offices and high level seniors of international conglomerates. To market their newly launched financial products, they are looking for qualified individuals to join the their team assisting daily operation.\n\n\u6211\u4eec\u7684\u5ba2\u6237\u662f\u4e00\u5bb6\u603b\u90e8\u4f4d\u4e8e\u9999\u6e2f\u7684\u91d1\u878d\u79d1\u6280\u516c\u53f8\uff0c\u5176\u521b\u59cb\u6210\u5458\u6765\u81ea\u5f53\u5730\u8457\u540d\u7684\u5bb6\u65cf\u529e\u516c\u5ba4\u548c\u56fd\u9645\u4f01\u4e1a\u96c6\u56e2\u7684\u9ad8\u5c42\u3002 \u4e3a\u4e86\u8425\u9500\u4ed6\u4eec\u65b0\u63a8\u51fa\u91d1\u878d\u4ea7\u54c1\uff0c\u4ed6\u4eec\u6b63\u5728\u5bfb\u627e\u5408\u683c\u7684\u4e2a\u4eba\u52a0\u5165\u4ed6\u4eec\u7684\u56e2\u961f\uff0c\u534f\u52a9\u65e5\u5e38\u8fd0\u8425\u3002\n\nResponsibilities:\n1.\u00a0Support Marketing Manager to consolidate promotion plan and coordinate with internal business units;\n2. Assist Marketing Manager to organize any promotion or roadshow event;\n3. Work closely with Business Development team to deliver\u00a0promotion materials to outside parties through both online and offline channels;\n4.\u00a0Deliver all assigned projects with high quality as requested by seniors.\n\nRequirements:\n1. Degree or above;\n2. Excellent communication and interpersonal skills;\n3. Knowledge in social media marketing & website analytics tools will be an advantage;\n4. Good command of English and Mandarin is a plus.\n\n\n\u804c\u8d23\uff1a\n1.\u652f\u6301\u8425\u9500\u7ecf\u7406\u6574\u5408\u63a8\u5e7f\u8ba1\u5212\uff0c\u4e0e\u5185\u90e8\u4e1a\u52a1\u90e8\u95e8\u534f\u8c03\uff1b\n2.\u534f\u52a9\u8425\u9500\u7ecf\u7406\u7ec4\u7ec7\u4efb\u4f55\u4fc3\u9500\u6216\u8def\u6f14\u6d3b\u52a8\uff1b\n3.\u4e0e\u4e1a\u52a1\u53d1\u5c55\u56e2\u961f\u7d27\u5bc6\u5408\u4f5c\uff0c\u901a\u8fc7\u7ebf\u4e0a\u7ebf\u4e0b\u6e20\u9053\u5411\u5916\u754c\u63d0\u4f9b\u5ba3\u4f20\u8d44\u6599\uff1b\n4.\u6309\u7167\u4e0a\u7ea7\u8981\u6c42\uff0c\u9ad8\u8d28\u91cf\u4ea4\u4ed8\u6240\u6709\u5206\u914d\u7684\u9879\u76ee\u3002\n\n\u8981\u6c42\uff1a\n1. \u672c\u79d1\u6216\u4ee5\u4e0a\u5b66\u5386\uff1b\n2. \u4f18\u79c0\u7684\u6c9f\u901a\u548c\u4eba\u9645\u4ea4\u5f80\u80fd\u529b\uff1b\n3. \u719f\u6089\u793e\u4ea4\u5a92\u4f53\u8425\u9500\u548c\u7f51\u7ad9\u5206\u6790\u5de5\u5177\u8005\u4f18\u5148\uff1b\n4. \u82f1\u8bed\u53ca\u666e\u901a\u8bdd\u6d41\u5229\u8005\u4f18\u5148\u3002", "employment_types": ["Full Time"], "selling_points": ["High-end Club", "Excellent exposure", "Attractive Package"], "locations": ["Central"], "categories": ["Marketing / Public Relations", "Marketing - Brand / Product Management", "Marketing - General / Support", "Marketing - Marketing Communication"], "post_time": "2022-01-17T08:25:50Z", "salary": {"currency": null, "max": null, "min": null, "period": "monthly", "term": null}, "salary_visible": false, "title_keywords": ["marketing assistant"], "responsibilities": ["quality", "plan and coordinate"], "requirements": {"degrees": ["degree or above"], "majors": [], "languages": ["english", "mandarin"], "language_level": ["good command"], "hard_skills": ["analytics tools", "plus"], "soft_skills": ["communication and interpersonal skills"], "languages_combined": [{"language": "english", "language_level": ["good command"]}, {"language": "mandarin", "language_level": ["good command"]}]}, "experience_required": {"duration": [], "field": []}}, {"job_id": "100003009054901", "location_code": "hk", "company": "Melaleuca of Asia Ltd Co", "job_title": "Senior/Marketing Officer", "description": "Job responsibilities:\u00a0\n\nResponsible for\u00a0Skincare & Essential Oil product line \u00a0\n\nAssist in product development (e.g. labeling, packaging, product formula optimization, etc)\nDevelop communication materials\u00a0\u00a0(e.g. Copy-writing, Videos, Presentation, etc) to communicate product benefits\nAssist in product strategy of our Skincare & Essential Oil products (e.g. market trend updates, pricing and inventory forecast, etc.)\nAssist in publication & catalog preparation\nTo analyze potential product details, product performance data to help product planning \u00a0\n\nJob requirements:\n\nAt least 2\u00a0years of related working experience, preferably\u00a0experience in FMCG, marketing, communications & product management\nGood PC skills in Office especially Excel analysis, PowerPoint.\nKnowledge at design software (e.g. InDesign, Photoshop, illustrator) and basic video editing is preferable\nWorking experience in Skincare / Essential Oil industry is an advantage\nStrong communication in spoken and written English and Mandarin\nProactive, efficient, independent, detail-minded, positive and able to manage multiple projects in parallel\nCandidates with more experience will be considered as Senior Marketing Officer", "employment_types": ["Full Time", "Permanent"], "selling_points": ["Marketing, Product specialist", "Skincare, essential oil, product development, FMCG", "communications, publications, presentations"], "locations": ["Yau Tsim Mong Area"], "categories": ["Marketing / Public Relations", "Marketing - Brand / Product Management", "Marketing - Direct Marketing", "Marketing - Marketing Communication"], "post_time": "2022-01-17T13:19:16Z", "salary": {"currency": null, "max": null, "min": null, "period": "monthly", "term": null}, "salary_visible": false, "title_keywords": ["marketing officer"], "responsibilities": ["communication", "develop"], "requirements": {"degrees": [], "majors": [], "languages": [], "language_level": [], "hard_skills": [], "soft_skills": [], "languages_combined": []}, "experience_required": {"duration": [], "field": []}}, {"job_id": "100003009052841", "location_code": "hk", "company": "Hong Kong Cyberport Management Co Ltd", "job_title": "Manager - Corporate Marketing (Ref# MCM220117J)", "description": "Your role:\u00a0\n\nAs one of the key players in Marketing Communications Team of the HKT Consumer Group, your key role is to assist your supervisor to plan and execute integrated online and offline marketing communications campaigns for different lines of business.\n\nCoordinate advertising and promotional campaigns with agencies and internal stakeholders to ensure smooth implementation of the campaigns to meet business goals & pre-aligned KPIs.\nAct as an internal gatekeeper of Google Analytics to ensure campaign backend setup and campaign data in good hands.\nAssist supervisor to prepare performance analysis report on campaign effectiveness via Google Analytics and/or Google Ads platforms, provide insights for campaign optimizations.\nAssist supervisor to manage content development across digital and social media channels.\n\nTo succeed in this role:\n\nDegree holder preferably in Communications, Marketing or Business related discipline\n3+ years relevant experience is required. Experience in advertising or digital media agency is an advantage.\nEssential knowledge of Facebook Ads, Google Analytics, Google Tag Manager and Google Ads platforms is a must.\nDetailed-minded with good analytical skills. Strong attention to detail in crafting spreadsheets and presentation reports.\nA proactive team player with strong communication and interpersonal skills\nGood command of both written and spoken English and Chinese\nHigh level of Microsoft Office proficiency especially Excel and PowerPoint", "employment_types": ["Full Time", "Permanent", "Contract"], "selling_points": ["Manage major company events", "strategic planning to create an event experience", "Build collaborations, partnerships and sponsorship"], "locations": ["Pok Fu Lam"], "categories": ["Marketing / Public Relations", "Marketing - General / Support", "Marketing - Marketing Communication", "Public Relations - Event Management"], "post_time": "2022-01-17T04:14:05Z", "salary": {"currency": null, "max": null, "min": null, "period": "monthly", "term": null}, "salary_visible": false, "title_keywords": ["manager"], "responsibilities": ["provide insights", "business goals", "social media", "advertising", "data", "analysis report", "implementation", "coordinate", "communication", "reports", "plan", "kpis", "facebook", "setup"], "requirements": {"degrees": ["degree holder"], "majors": ["business", "marketing", "communications"], "languages": ["english", "chinese"], "language_level": ["good command"], "hard_skills": ["google analytics", "excel", "microsoft office", "analysis", "powerpoint", "analytical skills", "facebook"], "soft_skills": ["analytical skills", "communication and interpersonal skills", "attention to detail", "smooth", "team player", "proactive", "presentation", "detailed"], "languages_combined": [{"language": "english", "language_level": ["good command"]}, {"language": "chinese", "language_level": ["good command"]}]}, "experience_required": {"duration": ["3+ years"], "field": ["agency", "advertising", "digital media", "relevant experience"]}}, {"job_id": "100003009056018", "location_code": "hk", "company": "HKT Consumer Group", "job_title": "Senior Marketing Communications Executive", "description": "Responsibilities\n\nAssist in launching corporate activities and ESG programs\nSupport project execution, event organization, logistics arrangement, data management, etc.\nDevelop, edit and translate external communications materials (online and offline) including but not limited to, press release, newsletter, speeches, website content and presentation materials\nMonitor and update Company website and external communications platforms\nLiaise and coordinate with both internal and external stakeholders, including but not limited to overseas offices of the Group\nProvide administrative support and coordination work for the department\nOther ad hoc projects as required\n\nRequirements\n\nDegree holder in communications, language and linguistics, translation, journalism or related disciplines\nAt least 3 years of working experience in corporate communications in listed companies and / or financial PR agency\nExperience in results announcement and ESG reporting at a listed company would be an advantage\nStrong in creative writing and content generation\nExcellent command of written and spoken English and Chinese (including Mandarin); High proficiency in Japanese would be an advantage\nSelf-starter, detail-minded, well-organized and committed to excellence\n\nWe offer 5-day work week, on-the-job development program and rewarding career opportunities for ambitious individuals who are looking for challenges. If you aspire to an exciting and rewarding career, send your resume immediately with your present and expected salary.\n\n(All personal data collected will be used for recruitment purpose only.)", "employment_types": ["Full Time"], "selling_points": [], "locations": ["Quarry Bay"], "categories": ["Marketing / Public Relations", "Marketing - Marketing Communication"], "post_time": "2022-01-18T03:11:43Z", "salary": {"currency": null, "max": null, "min": null, "period": "monthly", "term": null}, "salary_visible": false, "title_keywords": ["marketing communications executive"], "responsibilities": ["liaise", "management", "data", "logistics arrangement", "monitor", "website", "coordinate with", "develop", "ad hoc projects", "coordination", "provide administrative support", "company website"], "requirements": {"degrees": ["degree holder"], "majors": ["journalism", "related disciplines", "communications"], "languages": ["japanese", "english", "chinese", "mandarin"], "language_level": ["advantage", "excellent", "proficiency"], "hard_skills": ["translation"], "soft_skills": ["detail-minded", "committed", "creative", "well-organized"], "languages_combined": [{"language": "japanese", "language_level": ["proficiency", "advantage"]}, {"language": "english", "language_level": ["excellent"]}, {"language": "chinese", "language_level": ["excellent"]}, {"language": "mandarin", "language_level": ["excellent"]}]}, "experience_required": {"duration": ["at least 3 years"], "field": ["agency", "pr", "financial"]}}, {"job_id": "100003009054765", "location_code": "hk", "company": "Tam Jai International Co. Limited", "job_title": "Corporate Communications Officer", "description": "Key Responsibilities\n\nPlan, organise and manage major company events in physical, hybrid or virtual formats. Devise strategic implementation plan\nDevelop and implement strategic planning to create an integrated event experience. Curate programmes and activities to align Cyberport\u2019s public missions and to enhance its position and brand as thought leadership and industry voice in the region\nProvide full support on wide spectrum of event management including but not limited to project scheduling, speaker co-ordination, programme development, stage management, promotion and advertising, marketing collaterals, stage production, manpower management, onsite logistics, as well as market research and procurement\nPlan, source and incorporate innovative event elements to enhance traction and attendee experience, including digital/stage gimmicks, interactive games, incentives, event platforms/solutions etc.\nDrive attendance and positive publicity through integrated marketing & communications in conjunction with Branding & Corporate Communications teams to achieve best synergies, incl. event content marketing and distribution via effective channels for maximum audience engagement & impact\nExplore, solicit and follow up potential collaborations, partnerships and sponsorships opportunities for better event synergy\nLiaise and work closely with different business units, agencies/vendors, Government or public bodies and industry organisations\nManage marketing budget and monitor event P/L\n\nRequirements\n\nDegree in marketing, journalism, mass communications, public relations or related discipline\nMinimum 10 years relevant working experience in corporate/event management, event production & marketing, corporate communications, marketing communication and / or public relations with hands-on experience in physical, hybrid and virtual events ideally from sizable organization/public bodies and preferably from technology sector\nAll-round experience & proven track record in planning and managing large scale industry conference and events a must\nKnowledge and experience in hybrid/ virtual events, event platforms/technologies, creative digital elements, stage management, cross-platform marketing and user experience is essential\nConnection with industry associations, chambers of commerce, industry organisations and speakers bureau for potential collaborations, sponsorship solicitation, and/or speakers invitations a plus\nStrong event and project management skills, especially hybrid events\nGood understanding of technicality & acumen on integrated event platforms, registration and EDM systems and virtual event setup\nA fast mover and strategic thinker with who possess new normal agility with excellent efficiency and strategic focus\nA relationship-builder and team player with excellent interpersonal and negotiation skills\nExcellent command of written and spoken English and Chinese (Cantonese and Putonghua)\nOutstanding project management and organisational skills\nAble to work effectively under pressure and deliver high quality work under tight deadlines/ schedules\nDetail-oriented with exceptional strengths in multi-tasking\nA self-motivated team player with strong can-do attitude\nCreative, analytical and well-organised\n\nThe position is on a renewable 2-year fixed-term contract, subject to performance and operational needs, the position will convert into open contract after 2 years.\n\nWe offer competitive package to the right candidate. Interested party please click\u00a0Apply Now\u00a0to apply on or before 11 February 2022\u00a0in confidence with full resume in Word document, stating present and expected salary, and available date\u00a0and quote the reference.\u00a0\n\nApplicants who do not hear from us by 25 February 2022\u00a0may assume that their applications are unsuccessful.\n\nFurther information about the Cyberport is available at\u00a0http://www.cyberport.hk", "employment_types": ["Full Time", "Permanent"], "selling_points": ["Strong in creative writing and content generation", "Excellent command of written and spoken English", "Exp. in listed companies or financial PR agencies"], "locations": ["Lai Chi Kok"], "categories": ["Media & Advertising", "Editorial / Journalism", "Marketing / Public Relations", "Marketing - Marketing Communication", "Public Relations - Copy-writing"], "post_time": "2022-01-17T10:58:55Z", "salary": {"currency": null, "max": null, "min": null, "period": "monthly", "term": null}, "salary_visible": false, "title_keywords": ["corporate communications officer"], "responsibilities": ["liaise", "attendance", "management", "advertising", "strategic planning", "marketing collaterals", "teams", "implementation", "market research", "develop", "budget", "monitor", "logistics", "project scheduling", "plan"], "requirements": {"degrees": ["degree"], "majors": ["journalism", "marketing", "communications"], "languages": ["cantonese", "putonghua", "english", "chinese"], "language_level": ["excellent"], "hard_skills": ["project management", "plus", "focus", "acumen"], "soft_skills": ["work effectively", "self-motivated", "under pressure", "can-do attitude", "project management skills", "detail-oriented", "communication", "project management", "hands-on", "team player", "negotiation skills", "organisational skills", "multi-tasking", "well-organised", "focus", "creative", "interpersonal"], "languages_combined": [{"language": "cantonese", "language_level": ["excellent"]}, {"language": "putonghua", "language_level": ["excellent"]}, {"language": "english", "language_level": ["excellent"]}, {"language": "chinese", "language_level": ["excellent"]}]}, "experience_required": {"duration": ["minimum 10 years"], "field": ["management", "public relations", "sizable organization", "relevant working experience", "marketing", "digital", "planning"]}}, {"job_id": "100003009055992", "location_code": "hk", "company": "KOS International Limited", "job_title": "Assistant Manager - Communications & Events (Up to 40K)", "description": "About the Client\n\nOur client is a world renowned professional accounting body with 19 offices around the world. To cope with their expansion plans, they are now inviting an Assistant Manager, Communications and Events to join their events team in Hong Kong.\n\nAbout the Role\n\nReporting to the Senior Manager - Communications, Marketing and Events, you are responsible for heading up prominent annual events in the Greater Bay Area for the organization, from conceptualisation, planning, execution and operations management of events. You will engage members through the organization of various committee events and across the year including industry or business related, educational, wellness, member application and webinars. Working closely with business development, member services and professional development teams, you will ensure event projects are in line with the strategic direction of the organization. Most importantly, you will be the key touchpoint with Chinese Central government representatives in Hong Kong.\n\nRequirements\n\nMinimum bachelor's degree holder in marketing or event related discipline\nMinimum 5 years solid event/project coordination working experience\nStrong Greater Bay Area event experience is highly preferred\nHave strong communication, copywriting and project management skills\nGood team player, detail-minded, highly organized, and flexible\nProficient in both written and spoken Chinese (Cantonese and Mandarin), and English\nTraveling is required when needed\n\nClick \"Apply Now\" to apply for this position or call Steven Leung at +852 3180 4939 for a confidential discussion. All information collected will be kept in strict confidence and will be used for recruitment purpose only.", "employment_types": ["Full Time", "Permanent"], "selling_points": ["Great development opportunity", "Professional accounting body", "Greater Bay event focus"], "locations": ["Not Specified"], "categories": ["Marketing / Public Relations", "Marketing - Marketing Communication", "Public Relations - Event Management", "Others"], "post_time": "2022-01-18T03:10:18Z", "salary": {"currency": null, "max": null, "min": null, "period": "monthly", "term": null}, "salary_visible": false, "title_keywords": ["assistant manager"], "responsibilities": ["reporting", "management", "project coordination", "operations", "teams", "communication", "project management", "recruitment", "plans", "planning"], "requirements": {"degrees": ["bachelor", "degree holder"], "majors": ["marketing"], "languages": ["cantonese", "english", "chinese", "mandarin"], "language_level": ["proficient"], "hard_skills": ["project management"], "soft_skills": ["detail-minded", "organized", "good team player", "flexible", "confidence", "responsible", "project management skills", "communication", "coordination"], "languages_combined": [{"language": "cantonese", "language_level": ["proficient"]}, {"language": "english", "language_level": ["proficient"]}, {"language": "chinese", "language_level": ["proficient"]}, {"language": "mandarin", "language_level": ["proficient"]}]}, "experience_required": {"duration": ["minimum 5 years"], "field": []}}, {"job_id": "100003009052671", "location_code": "hk", "company": "Hong Kong Family Welfare Society", "job_title": "Communications Assistant", "description": "Reporting to the Assistant Marketing Manager, you will\nDevelop and implement PR and communications plan and strategies for Tai Kwun\u2019s brand and programme offerings to strengthen the brand as a centre for heritage and arts\nPlan and organize media events to promote Tai Kwun\u2019s brand that incorporate Tai Kwun\u2019s programme offerings\nDevelop publicity-related content such as key messages, press releases, publicity plans, and other related material as needed\nBuild a constructive working relationship with the local and international media and KOL; pitch thematic and event-based stories to generate positive coverage for Tai Kwun at both brand and programme levels\nHandle daily media activities and operations, including enquiries, photo/video shoot, press release distribution and maintaining press contact lists\nMonitor media coverage and prepare monthly clipping and evaluation reports\n\u00a0\nYou should have/be\nDegree in Communications, Marketing or related disciplines\n5 years\u2019 experience in marketing and communications field with commercial/non-commercial sectors, preferably in arts and culture, and communications industries\nPrevious exposure in PR agencies is highly preferred\nExcellent command of written and spoken English and Cantonese. Putonghua is a plus\nCan-do attitude, good team spirit with excellent execution and planning skill, details oriented and multi-tasking ability. Hands-on experience in translating concepts into actions\nKeen interests in heritage, art and cultural related projects. Curious about the new and creative marketing initiatives around the city and the globe\nA fast learner with strong business acumen and flexible in working long hours at times or during weekends\nInterested parties, please click \"Apply Now\" to submit your application.\n\nPersonal data collected will be used for recruitment purpose only.", "employment_types": ["Full Time", "Contract"], "selling_points": ["Update website & assist with promotional materials", "Admin support for procurement & stock management", "Maintain the Society\u2019s CRM system"], "locations": ["Wan Chai"], "categories": ["Marketing / Public Relations", "Marketing - Marketing Communication"], "post_time": "2022-01-17T03:49:52Z", "salary": {"currency": null, "max": null, "min": null, "period": "monthly", "term": null}, "salary_visible": false, "title_keywords": ["assistant"], "responsibilities": ["reporting", "maintaining", "operations", "monitor", "develop", "reports", "contact", "plan", "evaluation", "plans", "planning"], "requirements": {"degrees": ["degree"], "majors": ["related disciplines", "marketing", "communications"], "languages": ["cantonese", "putonghua", "english"], "language_level": ["excellent"], "hard_skills": ["plus", "acumen"], "soft_skills": ["flexible", "team spirit", "can-do attitude", "keen", "multi-tasking", "hands-on", "business acumen", "creative", "fast learner", "constructive", "positive"], "languages_combined": [{"language": "cantonese", "language_level": ["excellent"]}, {"language": "putonghua", "language_level": []}, {"language": "english", "language_level": ["excellent"]}]}, "experience_required": {"duration": ["5 years"], "field": ["commercial", "marketing"]}}, {"job_id": "100003009054139", "location_code": "hk", "company": "Tai Kwun", "job_title": "Senior Communications Officer  (1-year contract)", "description": "\u200b\n\nResponsibilities:\n\nReporting to senior leadership, this role will assume responsibilities for spearheading marketing and communications strategy and execution for the Park. \u00a0Other major functions of this job include:\nDevelop integrated marketing and communications strategy that supports and advances the brand awareness and advocacy of the Park and drives positive mindshare that can contribute to the development of the ecosystem in the Park;\u00a0\nDrive external relationships and proactive engagement with local and international stakeholders including relevant government departments, regulatory bodies, universities, R&D institutions, industry leaders and NGOs to lobby for their support for the Park\u2019s vision and strategic imperatives;\u00a0\nSupport business development activities through organizing industry, marketing and community events which engage and appeal to local and overseas tech ventures and startups, incubators, accelerators and top entrepreneurs and talents as well as facilitating partnerships, business matching and corporate engagements;\nResponsible for public affairs, issue and crisis management; taking a proactive role in identifying potential issues, evaluating reputation risks and providing recommendations and communications plans for the senior management;\u00a0\nDevelop compelling messaging for corporate announcements and speaking platforms; and work closely with the Park\u2019s Chairperson, CEO and other senior leaders to develop content assets, not limited to keynote presentations, social media posts, thought leadership pieces spanning across paid, owned and earned media platforms;\nPerform other duties and tasks assigned by Supervisor and CEO.\n\nRequirements:\n\nDegree in Marketing, Communications, Business or related subjects, with at least 12 years of experience in PR, communications, business development and marketing positions, preferably gained in MNC / sizable companies.\nStrong track record in strategic brand management, reputation management and stakeholder engagements for respected companies preferably with presence in Greater China, Greater Bay Area and/or globally.\nGood understanding and appreciation of technology trends. \u00a0Ability to work with global and local technology ventures and startups and provide value-added advice and support to them for promoting their innovations.\nProfound understanding and hands-on experience on government relations and excellent in strategic thinking and able to drive the Park\u2019s corporate narratives that align with various business priorities.\nPossess the ability to work with diverse categories of stakeholders and excellent communications skills that can command impact when interacting with industry players, academia, board members and other key stakeholders etc.\nStrong business acumen, problem solving and leadership skills with excellent command of spoken/written English and Chinese (including Putonghua).", "employment_types": ["Full Time", "Temporary", "Contract"], "selling_points": ["Develop and implement PR and communications plan", "Plan and organize media events to promote TK brand", "Handle daily media activities and operations"], "locations": ["Central"], "categories": ["Marketing / Public Relations", "Marketing - Brand / Product Management", "Marketing - Marketing Communication", "Public Relations - Event Management"], "post_time": "2022-01-17T08:32:15Z", "salary": {"currency": null, "max": null, "min": null, "period": "monthly", "term": null}, "salary_visible": false, "title_keywords": ["senior communications officer"], "responsibilities": ["reporting", "social media", "perform other duties", "presentations", "develop", "plans", "senior management", "crisis management"], "requirements": {"degrees": ["degree"], "majors": ["business", "marketing", "communications"], "languages": ["putonghua", "english", "chinese"], "language_level": ["excellent"], "hard_skills": ["problem solving", "sizable companies", "acumen"], "soft_skills": ["strategic thinking", "leadership skills", "problem solving", "diverse", "hands-on", "business acumen"], "languages_combined": [{"language": "putonghua", "language_level": ["excellent"]}, {"language": "english", "language_level": ["excellent"]}, {"language": "chinese", "language_level": ["excellent"]}]}, "experience_required": {"duration": ["at least 12 years"], "field": ["pr", "related", "business development", "business", "marketing"]}}, {"job_id": "100003009055209", "location_code": "hk", "company": "PARKnSHOP", "job_title": "Senior Marketing Executive", "description": "\u00a0Responsibilities\nDevelop press kit and media pitching materials\nHandle and follow up with press requests and enquiries\u00a0\u00a0\nWrite articles for magazines, journals and e-newsletters\nManage the design and contents of marketing materials e.g., leaflet, posters, banners and PowerPoint\nOrganize and implement events and promotional campaigns including exhibitions, road shows, seminars, workshops, talks and ceremonies\nManage and create contents for corporate website, production of corporate video and premiums and social media platforms including Facebook, Instagram and LinkedIn\nManage customer database and develop digital marketing campaign e.g., eDM, SEM, SEO\nArrange meetings and explore collaboration opportunities with educational bodies and NGO for joint promotion\nOther ad-hoc projects as assigned\n\nRequirements\n\n\n\nDegree holder in Journalism, Public Relations, Communications, Marketing or related disciplines\nMinimum 2 years\u2019 related experiences\nBackground in journalism is an advantage\nExperiences with education bodies and NGO will be an advantage\nExcellent command of written and spoken English and Chinese\nProficient in MS Officer, PowerPoint, Excel and Chinese Work Processing\nExperiences in using Photoshop, AI and InDesign will be an added advantage\nStrong knowledge and understanding of social media platforms\nHigh multi-tasking ability and can work under pressure and tight deadlines\nA team player with strong interpersonal and communication skills\nImmediately available preferred", "employment_types": ["Full Time", "Permanent"], "selling_points": [], "locations": ["Shatin Area"], "categories": ["Marketing / Public Relations", "Marketing - General / Support", "Marketing - Marketing Communication", "Others"], "post_time": "2022-01-18T01:46:19Z", "salary": {"currency": null, "max": null, "min": null, "period": "monthly", "term": null}, "salary_visible": false, "title_keywords": ["senior marketing executive"], "responsibilities": ["ad-hoc projects", "seo", "edm", "leaflet", "social media platforms", "website", "design", "develop", "banners", "digital marketing", "database", "contents", "marketing materials", "facebook", "sem", "arrange meetings"], "requirements": {"degrees": ["degree holder"], "majors": ["journalism", "related disciplines", "marketing", "communications"], "languages": ["english", "chinese"], "language_level": ["excellent", "proficient"], "hard_skills": ["excel", "ai", "indesign", "powerpoint", "processing", "photoshop"], "soft_skills": ["communication skills", "multi-tasking", "team player", "interpersonal", "work under pressure"], "languages_combined": [{"language": "english", "language_level": ["excellent"]}, {"language": "chinese", "language_level": ["excellent", "proficient"]}]}, "experience_required": {"duration": ["minimum 2 years"], "field": ["related", "education"]}}, {"job_id": "100003009055695", "location_code": "hk", "company": "Hong Kong-Shenzhen Innovation and Technology Park Limited", "job_title": "Associate Director, Marketing & Communications", "description": "\u200b\n\nResponsibilities:\n\nReporting to senior leadership, this role will assume responsibilities for spearheading marketing and communications strategy and execution for the Park. \u00a0Other major functions of this job include:\nDevelop integrated marketing and communications strategy that supports and advances the brand awareness and advocacy of the Park and drives positive mindshare that can contribute to the development of the ecosystem in the Park;\u00a0\nDrive external relationships and proactive engagement with local and international stakeholders including relevant government departments, regulatory bodies, universities, R&D institutions, industry leaders and NGOs to lobby for their support for the Park\u2019s vision and strategic imperatives;\u00a0\nSupport business development activities through organizing industry, marketing and community events which engage and appeal to local and overseas tech ventures and startups, incubators, accelerators and top entrepreneurs and talents as well as facilitating partnerships, business matching and corporate engagements;\nResponsible for public affairs, issue and crisis management; taking a proactive role in identifying potential issues, evaluating reputation risks and providing recommendations and communications plans for the senior management;\u00a0\nDevelop compelling messaging for corporate announcements and speaking platforms; and work closely with the Park\u2019s Chairperson, CEO and other senior leaders to develop content assets, not limited to keynote presentations, social media posts, thought leadership pieces spanning across paid, owned and earned media platforms;\nPerform other duties and tasks assigned by Supervisor and CEO.\n\nRequirements:\n\nDegree in Marketing, Communications, Business or related subjects, with at least 12 years of experience in PR, communications, business development and marketing positions, preferably gained in MNC / sizable companies.\nStrong track record in strategic brand management, reputation management and stakeholder engagements for respected companies preferably with presence in Greater China, Greater Bay Area and/or globally.\nGood understanding and appreciation of technology trends. \u00a0Ability to work with global and local technology ventures and startups and provide value-added advice and support to them for promoting their innovations.\nProfound understanding and hands-on experience on government relations and excellent in strategic thinking and able to drive the Park\u2019s corporate narratives that align with various business priorities.\nPossess the ability to work with diverse categories of stakeholders and excellent communications skills that can command impact when interacting with industry players, academia, board members and other key stakeholders etc.\nStrong business acumen, problem solving and leadership skills with excellent command of spoken/written English and Chinese (including Putonghua).", "employment_types": ["Permanent"], "selling_points": [], "locations": ["Shatin Area"], "categories": ["Marketing / Public Relations", "Marketing - Brand / Product Management", "Marketing - General / Support", "Marketing - Marketing Communication"], "post_time": "2022-01-18T02:51:37Z", "salary": {"currency": null, "max": null, "min": null, "period": "monthly", "term": null}, "salary_visible": false, "title_keywords": ["associate director"], "responsibilities": ["reporting", "social media", "perform other duties", "presentations", "develop", "plans", "senior management", "crisis management"], "requirements": {"degrees": ["degree"], "majors": ["business", "marketing", "communications"], "languages": ["putonghua", "english", "chinese"], "language_level": ["excellent"], "hard_skills": ["problem solving", "sizable companies", "acumen"], "soft_skills": ["strategic thinking", "leadership skills", "problem solving", "diverse", "hands-on", "business acumen"], "languages_combined": [{"language": "putonghua", "language_level": ["excellent"]}, {"language": "english", "language_level": ["excellent"]}, {"language": "chinese", "language_level": ["excellent"]}]}, "experience_required": {"duration": ["at least 12 years"], "field": ["pr", "related", "business development", "business", "marketing"]}}, {"job_id": "100003009053329", "location_code": "hk", "company": "ALBA Integrated Waste Solutions (Hong Kong) Limited", "job_title": "Marketing and Communications Officer", "description": "\u00a0Responsibilities\nDevelop press kit and media pitching materials\nHandle and follow up with press requests and enquiries\u00a0\u00a0\nWrite articles for magazines, journals and e-newsletters\nManage the design and contents of marketing materials e.g., leaflet, posters, banners and PowerPoint\nOrganize and implement events and promotional campaigns including exhibitions, road shows, seminars, workshops, talks and ceremonies\nManage and create contents for corporate website, production of corporate video and premiums and social media platforms including Facebook, Instagram and LinkedIn\nManage customer database and develop digital marketing campaign e.g., eDM, SEM, SEO\nArrange meetings and explore collaboration opportunities with educational bodies and NGO for joint promotion\nOther ad-hoc projects as assigned\n\nRequirements\n\n\n\nDegree holder in Journalism, Public Relations, Communications, Marketing or related disciplines\nMinimum 2 years\u2019 related experiences\nBackground in journalism is an advantage\nExperiences with education bodies and NGO will be an advantage\nExcellent command of written and spoken English and Chinese\nProficient in MS Officer, PowerPoint, Excel and Chinese Work Processing\nExperiences in using Photoshop, AI and InDesign will be an added advantage\nStrong knowledge and understanding of social media platforms\nHigh multi-tasking ability and can work under pressure and tight deadlines\nA team player with strong interpersonal and communication skills\nImmediately available preferred", "employment_types": ["Full Time", "Permanent"], "selling_points": ["Degree holder in related disciplines", "Background in journalism", "Immediately available preferred"], "locations": ["Lai Chi Kok"], "categories": ["Marketing / Public Relations", "Marketing - Marketing Communication"], "post_time": "2022-01-17T06:46:29Z", "salary": {"currency": null, "max": null, "min": null, "period": "monthly", "term": null}, "salary_visible": false, "title_keywords": ["communications officer"], "responsibilities": ["ad-hoc projects", "seo", "edm", "leaflet", "social media platforms", "website", "design", "develop", "banners", "digital marketing", "database", "contents", "marketing materials", "facebook", "sem", "arrange meetings"], "requirements": {"degrees": ["degree holder"], "majors": ["journalism", "related disciplines", "marketing", "communications"], "languages": ["english", "chinese"], "language_level": ["excellent", "proficient"], "hard_skills": ["excel", "ai", "indesign", "powerpoint", "processing", "photoshop"], "soft_skills": ["communication skills", "multi-tasking", "team player", "interpersonal", "work under pressure"], "languages_combined": [{"language": "english", "language_level": ["excellent"]}, {"language": "chinese", "language_level": ["excellent", "proficient"]}]}, "experience_required": {"duration": ["minimum 2 years"], "field": ["related", "education"]}}, {"job_id": "100003009055390", "location_code": "hk", "company": "Yew Chung College of Early Childhood Education Limited", "job_title": "Manager (Institutional Advancement and Marketing)", "description": "Position Summary\n\nThe main tasks for the appointee are:\n\nTo assist the Unit Head in driving the overall marketing and communications strategies;\nTo plan the integrated marketing campaigns including events, advertising, digital marketing, school and community outreach, public relations etc to elevate the image of the College and boost student admission;\nTo lead the implementation of the marketing activities and work with different internal or external parties to achieve the goals;\nTo oversee the design and production of advertising and promotional materials, promotional videos/films and digital contents;\nTo generate reports and evaluate the effectiveness of the promotion efforts;\nTo conduct regular research and studies to identify market opportunities and collect feedback from stakeholders;\nTo monitor and lead a small team of marketing and communication;\nTo take up other tasks as assigned by the College\n\nRequirements\n\nApplicants should meet the following requirements:\n\nA Bachelor\u2019s degree in Marketing/Journalism or related discipline\nAt least 5 years of marketing experience in the tertiary education sector or with sales and customer servicing sector. Previous working experience from education sector is preferable.\nExcellent command of English and Chinese (Cantonese and Mandarin)\nExcellent interpersonal and communication skills to interact with different stakeholders and external parties\nA good sense of responsibility and self-motivation\nAble to handle tasks independently with minimum supervision\nAble to adopt a positive attitude to the team\u2019s objectives and maintain collaborative work relationship with team members\nExperience in managing social media platforms and web content is an advantage\nExperience in managing a small team\u00a0\n\nSalary and Fringe Benefits:\n\nInitial appointment will normally be made on a renewable 24-month contract.\n\nRemuneration is competitive and will be based on qualifications and relevant experience. The College offers group medical insurance, staff development support, annual leave and sick leave, and Mandatory Provident Fund to eligible appointee(s).\n\nApplication Procedure:\n\nApplicants are invited to:\n\nSubmit an application letter with a full Curriculum Vitae, and copies of all graduate transcripts, and the names and contact details of three references.\nSpecify in the application letter current/latest salary and expected salary\nSend applications to the Yew Chung College of Early Childhood Education by \"Apply Now\".\nThe College will review applications immediately and applications will be accepted until the posts are filled.\u00a0 Only shortlisted candidates will be contacted.\n\nImportant notes to Applicants:\n\nAppointees will have to undergo a medical examination.\u00a0 Reimbursement of costs subject to a ceiling is applicable.\nLocal applicants will have to undergo a Sexual Conviction Record Check / Overseas applicants will have to present a police report before appointment can be confirmed.\u00a0\n\nThe College also reserves the right to make an appointment by invitation.\n\nPersonal data collected will be used for recruitment-related purposes only.", "employment_types": ["Full Time", "Contract"], "selling_points": ["Marketing and Communications Manager", "Experience in education sector is preferable", "Working location in Aberdeen"], "locations": ["Aberdeen"], "categories": ["Marketing / Public Relations", "Marketing - Brand / Product Management", "Marketing - Marketing Communication", "Digital Marketing"], "post_time": "2022-01-18T02:26:22Z", "salary": {"currency": null, "max": null, "min": null, "period": "monthly", "term": null}, "salary_visible": false, "title_keywords": ["manager"], "responsibilities": ["social media platforms", "maintain"], "requirements": {"degrees": ["degree", "bachelor"], "majors": ["journalism", "marketing"], "languages": ["cantonese", "english", "chinese", "mandarin"], "language_level": ["excellent"], "hard_skills": [], "soft_skills": ["communication skills", "self-motivation", "interpersonal", "sense of responsibility"], "languages_combined": [{"language": "cantonese", "language_level": ["excellent"]}, {"language": "english", "language_level": ["excellent"]}, {"language": "chinese", "language_level": ["excellent"]}, {"language": "mandarin", "language_level": ["excellent"]}]}, "experience_required": {"duration": ["at least 5 years"], "field": ["marketing", "education"]}}, {"job_id": "100003009054934", "location_code": "hk", "company": "Sun Hung Kai Properties Ltd", "job_title": "PUBLIC AFFAIRS MANAGER", "description": "Requirements:\n\n\nUniversity degree or above\nA minimum of 10 years\u2019 experience in public affairs/ community liaison work in statutory bodies or sizable corporations or equivalent\nExcellent interpersonal and communication skills, able to establish working relationships with all levels of people\nAttention to details and can work under tight timeline\nGood command of English and Chinese\n\nResponsibilities:\n\n\nEstablish, strengthen and maintain a close working relationship with the Company\u2019s stakeholders, in particular government officials, political and community leaders, resident groups and key opinion leaders\nReach out to, liaise and engage with the Company\u2019s stakeholders with a view to advancing the Company\u2019s interest in development projects, businesses and operations\nMonitor public affairs developments which may affect or have an impact on the Company\u2019s interest and take appropriate/necessary actions to address the issues\nParticipate in and support the Company\u2019s public affairs and community services and related activities\nAny other duties and projects as assigned by supervisors\n\nGood remuneration and attractive fringe benefits will be offered to the successful applicant. Interested parties please apply with full resume, present and expected salary, available date by clicking \"Apply Now\".\n\nWe are an equal opportunity employer and welcome applications from all qualified candidates. All personal data collected will be used for recruitment purpose only.\u00a0 Applicants not hearing from us within 3 months may consider their applications unsuccessful.\u00a0 All personal data collected will be destroyed within 24 months.", "employment_types": ["Full Time", "Permanent"], "selling_points": ["Exp in public affairs / community liaison work", "Work with the Company\u2019s stakeholders", "Monitor public affairs developments"], "locations": ["Wan Chai"], "categories": ["Marketing / Public Relations", "Marketing - Marketing Communication", "Public Relations - General / Support", "Public / Civil", "Social Services - Community / Non-profit Organization"], "post_time": "2022-01-17T14:24:18Z", "salary": {"currency": null, "max": null, "min": null, "period": null, "term": null}, "salary_visible": false, "title_keywords": ["manager"], "responsibilities": ["liaise", "any other duties", "operations", "monitor", "maintain"], "requirements": {"degrees": ["degree or above"], "majors": [], "languages": ["english", "chinese"], "language_level": ["good command"], "hard_skills": [], "soft_skills": ["communication skills", "interpersonal", "attention to details"], "languages_combined": [{"language": "english", "language_level": ["good command"]}, {"language": "chinese", "language_level": ["good command"]}]}, "experience_required": {"duration": ["minimum of 10 years"], "field": []}}, {"job_id": "100003009050163", "location_code": "hk", "company": "Ricoh Hong Kong Limited", "job_title": "Marketing Communications Specialist", "description": "The Job:\n\nWork closely with Products and Solutions Marketing Team to drive the leads of the specific products and solutions\nCoordinate with vendors for the design and production of corporate collaterals, promotional materials and advertisement such as brochure, leaflet, flyer, website, video, social media post etc.\nLiaise with agencies to implement corporate and lead generation events and webinars\nPlan and execute digital marketing campaigns and drip campaigns through the marketing automation platform\nPerform ad-hoc duties as assigned\nThe Person:\n\nBachelor\u2019s Degree in Marketing, Business Administration or related discipline\u3000\nMinimum 4 years of relevant experience in B2B marketing communications, preferably in IT industry\nExperience in Digital Marketing is a must\nSound knowledge in Production, Event Management, Marketing Automation and Digital Analytics is an advantage\u3000\nSelf-motivated, able to work independently and handle multi-tasks\u3000\nExcellent English and Chinese in both written and verbal communications\nWe offer 5-day work, attractive remuneration and benefits package to the right candidate.\n\nInterested parties please forward your full resume (in Microsoft Word or PDF format) with current and expect salary to the\u00a0Human Resources & Facilities Services, Ricoh Hong Kong Limited, by clicking \"Apply Now\".\nInformation provided will be treated in strict confidence and only be used for recruitment related purposes. All personal data of unsuccessful candidates will be destroyed on completion of the recruitment exercise.", "employment_types": ["Full Time", "Permanent"], "selling_points": ["Work with Products and Solutions Marketing Team", "4 years of relevant experience in B2B marketing", "Experienced in Digital Marketing"], "locations": ["Kowloon Bay"], "categories": ["Marketing / Public Relations", "Marketing - Brand / Product Management", "Marketing - Marketing Communication", "Digital Marketing"], "post_time": "2022-01-15T19:11:41Z", "salary": {"currency": null, "max": null, "min": null, "period": "monthly", "term": null}, "salary_visible": false, "title_keywords": ["specialist"], "responsibilities": ["social media", "digital marketing campaigns", "leaflet", "coordinate with", "website", "design", "promotional materials", "plan", "ad-hoc duties", "liaise with"], "requirements": {"degrees": ["degree", "bachelor"], "majors": ["marketing", "business administration"], "languages": ["english", "chinese"], "language_level": ["excellent"], "hard_skills": [], "soft_skills": ["self-motivated", "work independently", "multi-tasks"], "languages_combined": [{"language": "english", "language_level": ["excellent"]}, {"language": "chinese", "language_level": ["excellent"]}]}, "experience_required": {"duration": ["minimum 4 years"], "field": ["marketing communications", "it", "relevant experience", "digital marketing"]}}, {"job_id": "100003009053311", "location_code": "hk", "company": "Altaya Wines Limited", "job_title": "Marketing Executive", "description": "Responsibilities:\n\nDirect report to Marketing Manager\nAssist to achieve brand targets and present the channel strategies to the Sales Team\nReview depletion for replenishment when needed\nAssist the team in A&P budget and review on regular basis\nAssist to prepare and execute promotion plans for specific channels\nExecute marketing programs including wine tastings, wine dinners, fairs, and exhibitions.\nCoordinate event management including logistic, and production of marketing collaterals\nExecute and follow up the agreed A&P activities including print, magazine, online, electronic media and direct mail\nExplore distribution development programs related to trade and corporate customers\n\n\u00a0Requirements:\n\nUniversity graduate, preferably in marketing or communications field\nA minimum of 3 years\u2019 experience in brand marketing or marketing communications of related industry\nAble to work in a fast-paced, multi-cultural environment\nDetail-minded, presentable with good judgment\nAble to work in a team but also independently\nStrong interest and passion in wine is a must. Certificate holder of WSET or related is an advantage\nPro-active, self-motivated, and positive with creative thinking\nGood command of spoken and written English, Cantonese, and Mandarin\nImmediately available preferred\nNext by Wong Chuk Hang MTR station", "employment_types": ["Full Time"], "selling_points": ["All round marketing functions", "5 day work per week with Medical & Dental Scheme", "Career Development"], "locations": ["Aberdeen"], "categories": ["Marketing / Public Relations", "Marketing - Brand / Product Management", "Marketing - Marketing Communication", "Public Relations - Event Management"], "post_time": "2022-01-17T06:44:19Z", "salary": {"currency": null, "max": null, "min": null, "period": "monthly", "term": null}, "salary_visible": false, "title_keywords": ["marketing executive"], "responsibilities": ["management", "development programs", "review", "budget", "replenishment", "marketing collaterals", "coordinate", "sales team", "plans", "report"], "requirements": {"degrees": ["certificate", "university graduate"], "majors": ["marketing", "communications"], "languages": ["cantonese", "english", "mandarin"], "language_level": ["good command"], "hard_skills": [], "soft_skills": ["detail-minded", "self-motivated", "independently", "passion in", "presentable", "pro-active", "creative", "positive"], "languages_combined": [{"language": "cantonese", "language_level": ["good command"]}, {"language": "english", "language_level": ["good command"]}, {"language": "mandarin", "language_level": ["good command"]}]}, "experience_required": {"duration": ["minimum of 3 years"], "field": ["marketing communications", "marketing", "brand", "related"]}}, {"job_id": "100003009054080", "location_code": "hk", "company": "Smart Charge", "job_title": "Marketing Executive/ Senior Marketing Executive (Smart Charge)", "description": "Smart Charge, a new service brand runs by HKT and CLP, aims to offer one-stop and hassle-free electric vehicle (EV) charging solutions for end-users and commercial entities in Hong Kong to meet the increasing market demand.\n\nIt is a challenging and dynamic opportunity for an all rounded marketer to work for this brand which is striving for differentiation and continual growth.\n\nThe Job:\n\nThe incumbent will be responsible for business development and marketing of new products and services related to Smart Charge in consumer market. Major job duties include:\n\nAssist the Marketing team in planning of marketing programs to promote Smart Charge service.\nCoordinate closely with various parties and channels with on target customer identification, to ensure smoothly program execution for marketing campaigns and events / roadshows related process and logistics.\nManage communication and campaigns across digital and traditional channels, from online, social media to retail shops and location based activities.\nPreparing marketing collaterals, conduct Marketing campaign performance tracking and evaluation\nEnsure brand messages are synchronized with partners and monitor all marketing campaigns to ensure communications are streamlined and aligned.\nCollect market intelligence, conduct media evaluations and provide analyses/insights to facilitate development of marketing strategy and project assessments\n\n\u00a0The Person:\n\nUniversity graduate in Marketing, Communications, Business Administration or relevant discipline\nMinimum of 3-year experience in of Product, Digital or Service Marketing experience\nGood problem solving skills and able to work under tight timeline\nSelf-motivated and able to accomplish multiple tasks with minimal supervision\nEffective interpersonal and communication skills and able to work with people at all levels\nProficiency in both spoken and written English and Cantonese\nKnowledge or interest in automobile industry and the market trend\n\nIf you have the desire for an exciting and rewarding career, please send us your resume immediately, quoting the reference number, your present and expected salary via email to Human Resources.", "employment_types": ["Full Time", "Permanent"], "selling_points": ["Degree in Marketing, Communications or Business", "3-year relevant experience", "Smart Charge - new service brand runs by HKT & CLP"], "locations": ["Quarry Bay"], "categories": ["Marketing / Public Relations", "Management", "Marketing - Brand / Product Management", "Marketing - Marketing Communication"], "post_time": "2022-01-17T08:19:54Z", "salary": {"currency": null, "max": null, "min": null, "period": null, "term": null}, "salary_visible": false, "title_keywords": ["senior marketing executive", "marketing executive"], "responsibilities": ["social media", "tracking", "marketing collaterals", "monitor", "coordinate", "communication", "logistics", "marketing campaigns", "evaluation", "planning"], "requirements": {"degrees": ["university graduate"], "majors": ["marketing", "business administration", "communications"], "languages": ["cantonese", "english"], "language_level": ["proficiency"], "hard_skills": ["problem solving skills"], "soft_skills": ["communication skills", "self-motivated", "multiple tasks", "problem solving skills", "interpersonal"], "languages_combined": [{"language": "cantonese", "language_level": ["proficiency"]}, {"language": "english", "language_level": ["proficiency"]}]}, "experience_required": {"duration": ["minimum of 3-year"], "field": ["digital", "marketing"]}}, {"job_id": "100003009054185", "location_code": "hk", "company": "Smartech International Marketing Limited", "job_title": "Sales and Marketing Officer/Assistant", "description": "Client Details\n\nOur client is the US leading consumer electronic provider. Currently they are expanding in Hong Kong and seeking for a high calibre to be responsible to oversee their business.\n\nResponsibilities\u00a0\n\nIdentify new business opportunity that are aligned with our company values and establish programs to drive business growth.\u00a0\nBuild strong long-term relationships with potential partners and help strengthen brand identity across launch markets\nHelp develop marketing strategies and execute go-to-market plans to drive performance KPIs\nIdentify, develop, and/or manage the creation of\u00a0collateral to support sales, account management, and demand generation\n\nRequirements\u00a0\n\nUniversity graduate in business, marketing discipline\u00a0\nAt lease 3 years of experience in Partnership/business development/marketing in consumer electronic\u00a0\nMature, responsible, trustworthy, self-motivated, pleasant, and passionate\u00a0\nGood interpersonal and communication skills in both spoken and written English\u00a0\nInternational experience will be an advantages\nFamiliar with MS Word, Excel and Outlook. Chinese word processing preferred\n\nIf you would like to apply for this role or find out more, please contact\u00a0Boris LAW\u00a0on 2847 9960 or apply online with your latest CV in word format with expected salary, quoting the job role \u2013 Partnership Manager. Kindly note that only shortlisted candidates will be notified.", "employment_types": ["Full Time"], "selling_points": ["Sales & Marketing", "Guarantee income", "Special + performance bonus"], "locations": ["Quarry Bay"], "categories": ["Marketing / Public Relations", "Marketing - General / Support", "Marketing - Marketing Communication", "Sales, CS & Business Devpt", "Retail Sales"], "post_time": "2022-01-17T08:42:32Z", "salary": {"currency": null, "max": null, "min": null, "period": "monthly", "term": null}, "salary_visible": false, "title_keywords": ["assistant", "sales", "marketing officer"], "responsibilities": ["management", "marketing strategies", "develop", "kpis", "plans"], "requirements": {"degrees": ["university graduate"], "majors": ["business", "marketing"], "languages": ["english", "chinese"], "language_level": ["good"], "hard_skills": ["excel", "chinese word processing", "word", "outlook", "ms word"], "soft_skills": ["passionate", "communication skills", "self-motivated", "trustworthy", "responsible", "mature", "pleasant", "interpersonal"], "languages_combined": [{"language": "english", "language_level": ["good"]}, {"language": "chinese", "language_level": []}]}, "experience_required": {"duration": ["3 years"], "field": ["business development", "marketing"]}}, {"job_id": "100003009054326", "location_code": "hk", "company": "Wellesley Associates Limited", "job_title": "Business Development & Marketing Manager - US Smart Technology", "description": "\u00a0Ref. No.: JDB/HLD11/CCO\n\nDegree in\u00a0Public Relations, Journalism, Marketing / Digital Marketing, English / Chinese Language or related disciplines\nMinimum 2 years'experience in Public Relations, media, or digital / marketing communications in a sizable organization or consultancy\nRelevant working experience in corporate communications includingmedia / stakeholder relations,CSR,events management, copy writing and translation, collateral / video production\nProficiency in MS office including Word, Excel, PowerPoint, and Photoshop\nInternet and social media savvy\nRelevant experience in marketing / digital marketing, website and social media management will be considered a merit\nVery strong English and Chinese language skills and fluency in Putonghua\nAttractive salary and fringe benefits will be offered to the successful candidates. Please apply with full resume by mail to\u00a0Human Resources Department, Henderson Land Development Co. Ltd., 71/F, Two International Finance Centre, 8 Finance Street, Central, Hong Kong\u00a0or by fax at\u00a02905 1855\u00a0or visit our homepage at\u00a0http://www.hld.com\u00a0or\u00a0by clicking \"Apply Now\".\n(Please quote the ref. no. on letter)\u00a0\n\nPersonal data provided by job applicants will be used for recruitment purpose only.", "employment_types": ["Full Time"], "selling_points": ["US company", "Partnership Marketing", "Consumer electronic / Smart Drive"], "locations": ["Not Specified"], "categories": ["Sales, CS & Business Devpt", "Business Development", "Marketing / Public Relations", "Marketing - General / Support", "Marketing - Marketing Communication"], "post_time": "2022-01-17T09:10:00Z", "salary": {"currency": null, "max": null, "min": null, "period": "monthly", "term": null}, "salary_visible": false, "title_keywords": ["marketing manager"], "responsibilities": ["social media", "management", "video production", "website", "digital marketing"], "requirements": {"degrees": ["degree"], "majors": ["journalism", "related disciplines", "marketing", "digital marketing"], "languages": ["putonghua", "english", "chinese"], "language_level": ["fluency"], "hard_skills": ["excel", "no", "word", "powerpoint", "photoshop", "translation", "ms office"], "soft_skills": [], "languages_combined": [{"language": "putonghua", "language_level": ["fluency"]}, {"language": "english", "language_level": ["fluency"]}, {"language": "chinese", "language_level": []}]}, "experience_required": {"duration": [], "field": ["social media", "management", "video production", "relevant working experience", "marketing", "relevant experience", "writing", "digital marketing"]}}, {"job_id": "100003009050256", "location_code": "hk", "company": "Henderson Land Development Company Limited", "job_title": "CORPORATE COMMUNICATIONS OFFICER", "description": "Reporting to Deputy General Manager, the successful candidate will support management of the Customer Relations Department, with a strong focus on fostering and deepening relationships with customers to enhance the \u2018Sino Experience\u2019.\u00a0Additionally, the incumbent will drive communication projects as assigned, including but not limited to ESG projects, community services and initiatives, media relations, event management, as well as editorial and production of corporate collaterals and website management.\nRequirements\nDegree in Business Administration, Marketing, Communications or related disciplines\nMinimum 8 years of working experience, preferably in sizeable organizations\nStrong project management and analytical skills\nExcellent communication, interpersonal and organizing skills\nA team player while being able to work independently under pressure and meet tight deadlines\nExcellent command of both written and spoken English and Chinese\nCandidate with less experience will be considered as Assistant Manager\nWe offer attractive remuneration packages commensurate with experience and qualifications. If you aspire to an exciting and rewarding career, send your resume immediately, quoting your present and expected salaries by clicking the button\u00a0\u201cApply Now\u201d.\nIf the applicant does not receive a response by\u00a017 February 2022, the application will be considered unsuccessful. Please read our Personal Information Collection Statement at\u00a0https://www.sino.com/en-US/Careers/Personal-Information-Collection-Statement\u00a0before submitting your application. Information provided by applicants will be treated in strict confidence and used for recruitment purposes only.", "employment_types": ["Full Time", "Permanent"], "selling_points": ["Medical Allowance", "Education Allowance", "Free Lunch"], "locations": ["Central"], "categories": ["Marketing / Public Relations", "Marketing - Marketing Communication", "Public Relations - Event Management", "Public Relations - General / Support"], "post_time": "2022-01-14T10:02:41Z", "salary": {"currency": null, "max": null, "min": null, "period": "monthly", "term": null}, "salary_visible": false, "title_keywords": ["corporate communications officer"], "responsibilities": ["reporting", "management", "website", "communication", "project management", "administration"], "requirements": {"degrees": ["degree"], "majors": ["related disciplines", "marketing", "business administration", "communications"], "languages": ["english", "chinese"], "language_level": ["excellent"], "hard_skills": ["project management", "focus", "analytical skills"], "soft_skills": ["work independently", "meet tight deadlines", "under pressure", "analytical skills", "communication", "project management", "team player", "focus", "interpersonal"], "languages_combined": [{"language": "english", "language_level": ["excellent"]}, {"language": "chinese", "language_level": ["excellent"]}]}, "experience_required": {"duration": ["minimum 8 years"], "field": ["management"]}}, {"job_id": "100003009056117", "location_code": "hk", "company": "Champion Land Properties Limited", "job_title": "Manager (Customer Relations) (Ref: M-CR)", "description": "You will be responsible for:\n\nAssist line manager to set digital and eCME platform to help drive diseases medical education and business grows. Work on the action plans to achieve goals on business.\nWork closely with multi-departments to plan & execute digital transformation projects to reach business goals.\nAlign and execute social media plans from planning to execution, in compliant with brand communication goals and guidelines.\nPlan and execute all digital marketing, including SEO/SEM, display advertising, display remarketing and paid media to increase top of funnel lead creation\nResponsible for ATL/ BTL campaign communication strategy design and landing\nSource, identify and build sustainable partnership with social / digital platforms, KOL, associations and brand advocates in a holistic digital marketing management.\nActively track, measure the effectiveness of digital media efficiency, monitor investment ROI towards paid social clients, and take learning for future plan optimization.\nRegularly monitor social media trends, market insights, explore new digital media platform and tools, and competitor information acquirement.\nExecute branding marketing plan and drive brand growth for assigned brands\nSupport on the development of portfolio budgets, brand plans and manage the spending\nImplement the brand building activities. Maintain brand standards with clear brand positioning\nBuilds collaborative relationships with internal stakeholders & external stakeholders to reach digital marketing strategic goals.\n\n\u00a0You should have:\n\nBS/MS degree in marketing or a healthcare science.\nFamiliar or with high interest in digital marketing, understand the love of internet and mobile internet, and have a certain understanding of brand positioning and marketing.\nHave good planning ability, communication and coordination ability, excellent execution ability, strong sense of responsibility and team spirit.\nSelf-motivated, passionate with the ability to work independently and as part of a team\nClose alignments with business analysts and business stakeholder for maximizing content for customers\nKPI-related mindset with excellent transparent value-driven and sustainable processes\nData analytics platforms and good understanding of technical infrastructures in general.\nGood communication skill both English and Mandarin.\nPreferable with at least one year of digital marketing experience of healthcare products\u00a0\u00a0\n\nAll applications received will be used exclusively for recruitment purposes only. Applicants who are not contacted within 8 weeks should consider their application unsuccessful for the position advertised. Data supplied by applicants will be kept for 6 months", "employment_types": ["Full Time", "Permanent"], "selling_points": [], "locations": ["Not Specified"], "categories": ["Marketing / Public Relations", "Marketing - Marketing Communication", "Public Relations - Event Management", "Others"], "post_time": "2022-01-18T03:21:15Z", "salary": {"currency": null, "max": null, "min": null, "period": "monthly", "term": null}, "salary_visible": false, "title_keywords": ["manager"], "responsibilities": ["business goals", "data", "design", "communication", "maintain", "plan", "plans", "advertising", "monitor", "bs", "marketing plan", "social media", "management", "seo", "digital marketing", "budgets", "guidelines", "recruitment", "sem", "coordination", "planning"], "requirements": {"degrees": ["degree"], "majors": ["science", "marketing"], "languages": ["english", "mandarin"], "language_level": ["good"], "hard_skills": ["mobile", "seo", "sem", "data analytics"], "soft_skills": ["passionate", "self-motivated", "team spirit", "work independently", "responsible", "sense of responsibility", "communication skill", "collaborative", "communication", "clear", "learning", "coordination", "driven"], "languages_combined": [{"language": "english", "language_level": ["good"]}, {"language": "mandarin", "language_level": ["good"]}]}, "experience_required": {"duration": ["at least one year"], "field": ["healthcare", "digital marketing"]}}, {"job_id": "100003009054915", "location_code": "hk", "company": "DCH Auriga (Hong Kong) Limited", "job_title": "(Associate) Digital Marketing Manager", "description": "Responsibilities:\n\n- Responsible for full range of sales and marketing activities\u00a0\n\n- Handling enquiries by phone, email and business meetings\n\n- Develop sales network,\u00a0good customer relationship and service\n\n- Work closely with\u00a0external parties\n\n\nRequirements:\n\n- High Dip in Engineering, Sales and Marketing, IT or related disciplines.\n\n- Interest in Marketing / Sales\u00a0\n\n- Proactive, self disciplined with good time management\n\n\n- Good PC skills in MS Office\u00a0\n\nInterested parties please send full resume with expected salary and availability to us.\n", "employment_types": ["Full Time"], "selling_points": [], "locations": ["Kwai Fong"], "categories": ["Marketing / Public Relations", "Marketing - Brand / Product Management", "Marketing - Marketing Communication", "Digital Marketing"], "post_time": "2022-01-17T13:49:21Z", "salary": {"currency": null, "max": null, "min": null, "period": "monthly", "term": null}, "salary_visible": false, "title_keywords": ["digital marketing manager", "associate"], "responsibilities": ["external parties", "develop"], "requirements": {"degrees": ["high dip"], "majors": ["related disciplines", "marketing", "it", "engineering"], "languages": [], "language_level": [], "hard_skills": ["pc skills", "ms office"], "soft_skills": ["time management", "proactive"], "languages_combined": []}, "experience_required": {"duration": [], "field": []}}, {"job_id": "100003009055238", "location_code": "hk", "company": "Shun Tung Electric Co Ltd", "job_title": "Sales and Marketing Assistant", "description": "Job Description\n\nManage and create content for social media platforms (including Facebook and Instagram), including copywriting and image creating/editing\nCommunicate with Media and Press on advertorials and PR activities\nAssist in planning, organizing and implementing sales, marketing strategies and event management to drive brand awareness and customer engagement\nAnalyze sales and promotional data for generating insights towards promotion effectiveness\nResponse to online and offline enquiries, as to build and grow the customer community\nHandle other offline ad-hoc projects and assignments as assigned\n\nRequirements\n\nAble to work independently and under pressure to meet tight deadlines\nSelf-motivated, customer-focused and task-oriented\nStrong knowledge in Google Ad Manager, SEO, SEM, Google Analytics and Facebook Ad Manager, EDM tools etc\n3-5 years marketing experience with solid exposure in retail marketing\nKnowledge of graphic designs, photo editing (e.g.: Adobe Illustrator, Photoshop)\u00a0\nImmediate available or short notice is highly preferred", "employment_types": ["Full Time"], "selling_points": [], "locations": ["Kwai Hing"], "categories": ["Engineering", "Others", "Marketing / Public Relations", "Marketing - Marketing Communication", "Sales, CS & Business Devpt", "Sales - Sales Management"], "post_time": "2022-01-18T01:54:36Z", "salary": {"currency": null, "max": null, "min": null, "period": "monthly", "term": null}, "salary_visible": false, "title_keywords": ["sales and marketing assistant"], "responsibilities": ["communicate with", "management", "ad-hoc projects", "marketing strategies", "data", "social media platforms", "facebook", "editing", "planning"], "requirements": {"degrees": [], "majors": [], "languages": [], "language_level": [], "hard_skills": ["google analytics", "seo", "adobe illustrator", "sem", "facebook", "photoshop"], "soft_skills": ["work independently", "self-motivated", "customer-focused", "under pressure", "meet tight deadlines"], "languages_combined": []}, "experience_required": {"duration": ["3-5 years"], "field": ["marketing", "retail"]}}, {"job_id": "100003009050341", "location_code": "hk", "company": "OTG Onthego Limited", "job_title": "Assistant Marketing Manager / Senior Marketing Officer (Medical insurance)", "description": "Responsibilities:\n\n\nPlan & execute marketing & PR plans, joint promotion campaign, product launch event and PR pitching\nDevelop and update marketing calendar to ensure the consistency with brand\u2019s strategic direction\nPrepare sales & marketing reports and presentation materials\nWork closely with internal and external parties to ensure smooth execution of marketing initiatives\nLiaise with media & advertising agencies and production house for advertising placement & premium production\nEstablish and maintain good network with media, celebrities, KOL & influencers\nDevelop and execute visual merchandising & promotional activities for shops / counters\nPerform ad hoc assignments as required\u00a0\n\nRequirements:\n\nDegree holder in Marketing or Business related disciplines\nAt least\u00a03 years working experience in Marketing\nExperience in Beauty / Skincare / Fragrance industry will be an advantage\nWith social media, online advertising & PR event experience will be an advantage\nStrong presentation and interpersonal skill\nGood command of written English and Cantonese\nAble to take multi-task\n\nCandidate with less experience will be considered as Marketing Executive\n\n\n\n\n\nWe offer 5 days work, attractive salary package including medical scheme & excellent career advancement opportunity to the right candidates. Our office is located in San Po Kong, around 8 minutes walk from\u00a0Diamond Hill MTR\u00a0station. Interested parties please send your full resume with current\u00a0and\u00a0expected salary\u00a0by clicking \"APPLY NOW\".\u00a0\u00a0\n\nwww.artalcosmetic.com\u00a0\n\nPersonal data collected would be used for recruitment purpose only", "employment_types": ["Full Time"], "selling_points": [], "locations": ["Lai Chi Kok"], "categories": ["Marketing / Public Relations", "Marketing - Brand / Product Management", "Marketing - General / Support", "Marketing - Marketing Communication"], "post_time": "2022-01-16T21:50:25Z", "salary": {"currency": null, "max": null, "min": null, "period": "monthly", "term": null}, "salary_visible": false, "title_keywords": ["assistant marketing manager", "senior marketing officer"], "responsibilities": ["advertising", "internal and external parties", "prepare sales", "merchandising", "develop", "maintain", "reports", "promotional activities", "plan", "visual", "liaise with", "plans", "ad hoc assignments"], "requirements": {"degrees": ["degree holder"], "majors": ["business", "related disciplines", "marketing"], "languages": ["cantonese", "english"], "language_level": ["good command"], "hard_skills": [], "soft_skills": ["multi-task", "presentation", "interpersonal skill"], "languages_combined": [{"language": "cantonese", "language_level": ["good command"]}, {"language": "english", "language_level": ["good command"]}]}, "experience_required": {"duration": ["at least 3 years"], "field": ["social media", "pr", "advertising", "marketing", "beauty"]}}, {"job_id": "100003009044365", "location_code": "hk", "company": "Adaka & Company", "job_title": "Senior Marketing Executive (5 days work)", "description": "You love challenges, you don\u2019t follow rules but create them, you have a million\u00a0ideas and wish to bring them alive, you want to make a difference and most of\u00a0all you want to work at a place that inspires. If truly you are such a rebellion,\u00a0Networld wants you!\n\nNetworld Technology is a highly celebrated online technology innovator in\u00a0Hong Kong, we facilitate human and business interaction through our 3\u00a0famous online portals: Discuss, Uwants and Price, each of them an awards\u00a0winning leader in the industry.\n\nWe all know the digital world is an ever-changing place, and we strive to\u00a0improve our products in every possible way. If you are tech-savvy, creative\u00a0and passionate, join us at Networld on this fun, challenging and exhausting\u00a0journey!\n\nTo know more about us, you can click the links below:\n\nNetworld\nWebsite:\u00a0https://www.networld.hk/\nFacebook Page:\u00a0https://bit.ly/2pF9Dov\n\nDiscuss\nWebsite:\u00a0https://www.discuss.com.hk/\nFacebook Page:\u00a0https://bit.ly/1XuiCnX\n\nUwants\nWebsite:\u00a0https://www.uwants.com/\nFacebook Page:\u00a0https://bit.ly/1Mt4cUw\n\nWho are we looking for?\n\nFirst and foremost, we're looking for people that fit Networld. People that are committed, communicative and resourceful. If you're enthusiastic about whatever you're working on and you have the right mindset, we might have the right job for you.\n\nYour role within our TEAM:\n\nCoordinate with the sales team to evaluate project performance and take appropriate action to drive the business and achieve business KPI such as cost control, productivity, conversion rate, etc\nDrive and manage online and digital campaigns and design action plans, manage budgets and review business development, marketing related campaign results, reports and data for its effectiveness\nLead marketing team to execute digital marketing strategies across social media, website, content and eDMs to increase online engagement\nResearch, study and consolidate market trends in the digital industry\nLiaise with internal and external parties to ensure the smooth execution of marketing programs and good communication\n\n\nSkills and traits of you:\n\nAt least 3 years working experience in sales and marketing, preferably with experience in digital industry\nCandidate with less experience will be considered as Sales and Marketing Executive\nDegree Holder in Marketing, Communications, Advertising or related discipline\nFundamental understanding of digital measurement and tracking, digital display and programmatic media\nSales, Business Development or Account Servicing experience would be an advantage\nGood command of both written and spoken English and Chinese\nCreative, attention to details , strong analytical skills\n\nBe part of us, you will enjoy:\n\nDiscretionary Bonus\n5-day Work Week\nFlexible Working Hour\nBirthday Leave\nBirthday Gift\nMedical Insurance\nMonthly Birthday Party\nTeam Event and Team Building Activities\nFree Snack & Beverage\nHappy and dynamic environment\nWearing Casually\n\nInterested parties, please click \"Apply now\" to submit your resume with the\u00a0availability and expected salary\u00a0to us.\n\nWorking Location:\u00a0Shatin (5 minutes from Shek Mun MTR station)\n\n(Personal data collected will be treated in the strictly confidential and only be used for recruitment related purpose.)", "employment_types": ["Full Time", "Permanent"], "selling_points": ["5 days work, birthday leave, free goods", "Cosmetic, skin care & hair care products", "Marketing & PR"], "locations": ["Kowloon Bay"], "categories": ["Marketing / Public Relations", "Marketing - Brand / Product Management", "Marketing - Marketing Communication", "Digital Marketing"], "post_time": "2022-01-16T21:50:20Z", "salary": {"currency": null, "max": null, "min": null, "period": "monthly", "term": null}, "salary_visible": false, "title_keywords": ["senior marketing executive"], "responsibilities": ["ideas", "data", "internal and external parties", "website", "design", "communication", "liaise with", "plans", "facebook", "digital marketing strategies", "advertising", "measurement", "reports", "digital campaigns", "social media", "edms", "review", "coordinate with", "tracking", "budgets", "evaluate", "sales team", "cost control", "insurance"], "requirements": {"degrees": ["degree holder"], "majors": ["marketing", "communications"], "languages": ["english", "chinese"], "language_level": ["good command"], "hard_skills": ["fun", "analytical skills", "make", "dynamic", "facebook"], "soft_skills": ["passionate", "flexible", "dynamic environment", "resourceful", "analytical skills", "communication", "committed", "smooth", "attention to details", "enthusiastic", "creative"], "languages_combined": [{"language": "english", "language_level": ["good command"]}, {"language": "chinese", "language_level": ["good command"]}]}, "experience_required": {"duration": ["at least 3 years"], "field": ["marketing", "digital industry", "account servicing", "business development"]}}, {"job_id": "100003009056146", "location_code": "hk", "company": "Networld Technology Limited", "job_title": "Senior Sales and Marketing Executive", "description": "Sun Hung Kai Properties Limited owns an industrial & logistics portfolio with GFA over 5 million sq.ft. and a parking portfolio. We are now seeking for high caliber candidates to join us to grow the portfolios and participate in the leasing & asset management activities along the life cycle of various asset classes.\n\nRequirements:\n\nBachelor\u2019s degree in business, marketing, surveying or related disciplines\nMinimum 12 years sales & leasing experiences in corporate real estate, preferably from major developers, funds, corporations or advisory firms.\nCompetent in client origination, sales & leasing management.\nExperiences in logistic client development & management will be an advantage\nExcellent interpersonal , communication and negotiation skills\nGood spoken and written English, Cantonese and Mandarin\nResponsibilities:\n\nLead a team of leasing specialist to handle the business development and leasing activities of the industrial and logistics portfolios\nParticipate in direct business development with existing tenants, logistics players, corporations and government bodies\nFormulate strategic tenancy and marketing plans for the portfolio to achieve the business objectives\nIdentify opportunities to enhance the trade-mix and brand positioning\nSupervise the preparation of regular asset management & marketing plans, business performance and management reports\nPrepare reports & investment memorandum to senior management for investments and divestments\n(Candidates with more experiences will be considered for Assistant General Manager.)\n\n\n\nGood remuneration and attractive fringe benefits will be offered to the successful applicant. Interested parties please apply with full resume, present and expected salary, available date by clicking \u201cApply Now\u201d.\n\nFor further information, please visit our company website:\u00a0http://www.shkp.com/.\n\nWe are an equal opportunity employer and welcome applications from all qualified candidates. All personal data collected will be used for recruitment purpose only.\u00a0 Applicants not hearing from us within 3 months may consider their applications unsuccessful.\u00a0 All personal data collected will be destroyed within 24 months.\n\n\n", "employment_types": ["Full Time", "Permanent"], "selling_points": ["5-day Work Week, Birthday Leave", "Flexible Working Hour, Wearing Casually", "Medical Insurance, Performance Bonus"], "locations": ["Shatin Area"], "categories": ["Media & Advertising", "Strategic Planning", "Marketing / Public Relations", "Marketing - Brand / Product Management", "Marketing - Marketing Communication"], "post_time": "2022-01-18T03:24:06Z", "salary": {"currency": null, "max": null, "min": null, "period": "monthly", "term": null}, "salary_visible": false, "title_keywords": ["sales and marketing executive"], "responsibilities": ["marketing plans", "lead a team", "management reports", "logistics", "prepare reports", "senior management", "asset management"], "requirements": {"degrees": ["degree", "bachelor"], "majors": ["related disciplines", "business", "surveying", "marketing"], "languages": ["cantonese", "english", "mandarin"], "language_level": ["good"], "hard_skills": [], "soft_skills": ["communication", "negotiation skills", "interpersonal", "competent"], "languages_combined": [{"language": "cantonese", "language_level": ["good"]}, {"language": "english", "language_level": ["good"]}, {"language": "mandarin", "language_level": ["good"]}]}, "experience_required": {"duration": ["minimum 12 years"], "field": ["development", "management"]}}, {"job_id": "100003009054927", "location_code": "hk", "company": "Sun Hung Kai Properties Ltd", "job_title": "SENIOR MANAGER / ASSISTANT GENERAL MANAGER \u2013 INDUSTRIAL & LOGISTICS PORTFOLIO LEASING & MANAGEMENT", "description": "We are currently seeking to appoint a Communications Manager to join us to help shape and define our PR and Social Media Strategy.\u00a0 The position has the flexibility to be located in our Hong Kong studio.\u00a0\u00a0 If you are passionate about working in a dynamic international architectural design practice, we would love to hear from you.\n\nAll candidates must have:\n\nMin 8 years\u2019 experience in communications within the architectural/buildings related and/or media industry;\nDegree in journalism or communications, English, art, architecture or related fields;\nExcellent skills, knowledge and experience in the planning and execution of PR and communication strategies and activities across Mainland China and internationally;\n\u00a0Experience in social media knowledge experience across all channels (ie. WeChat, LinkedIn, Instagram, Twitter etc\u2026);\nProfessional manner and approachable, and able to work with initiative and unsupervised;\nAbility to\u00a0 compose well and review media content (write up and visuals for publications, releases and social media);\nProficiency in Microsoft Office packages and Creative Suite software;\n\u00a0Excellent graphic eye and attention to detail to the execution of press materials;\nFluency in both English and Mandarin Chinese is essential for the role\n\n\n\nPlease apply by submitting\u00a0your CV and cover letter stating your location preferences, availability, and salary expectations via the JOIN on our website\u00a0http://www.10design.co/contact/join\u00a0OR, apply here.\n\n10 Design is an Equal Opportunity Employer.\u00a0\u00a0\u00a0\u00a0\u00a0\u00a0\u00a0\u00a0\u00a0\u00a0\u00a0\u00a0\u00a0\u00a0\u00a0\u00a0\u00a0\u00a0\u00a0\u00a0\u00a0\u00a0\u00a0\u00a0\u00a0\u00a0\u00a0\u00a0\u00a0\u00a0\u00a0\u00a0\u00a0\u00a0\u00a0\u00a0\u00a0\u00a0\n\nwww.10design.co", "employment_types": ["Full Time", "Permanent"], "selling_points": ["12 yrs sales, leasing exp in corporate real estate", "Industrial, logistics & carpark portfolios", "Leasing, asset management, marketing"], "locations": ["Wan Chai"], "categories": ["Sales, CS & Business Devpt", "Business Development", "Marketing / Public Relations", "Marketing - Marketing Communication", "Property / Real Estate", "Others"], "post_time": "2022-01-17T14:07:12Z", "salary": {"currency": null, "max": null, "min": null, "period": "monthly", "term": null}, "salary_visible": false, "title_keywords": ["senior manager", "assistant general manager", "logistics"], "responsibilities": ["social media", "software", "review", "professional manner", "website", "design", "communication", "contact", "architecture", "planning"], "requirements": {"degrees": ["degree"], "majors": ["journalism", "art", "communications", "architecture"], "languages": ["mandarin chinese", "english"], "language_level": ["fluency"], "hard_skills": ["microsoft office", "creative suite", "dynamic", "wechat"], "soft_skills": ["approachable", "communication", "dynamic", "attention to detail", "creative", "initiative", "passionate about"], "languages_combined": [{"language": "mandarin chinese", "language_level": ["fluency"]}, {"language": "english", "language_level": ["fluency"]}]}, "experience_required": {"duration": ["min 8 years"], "field": ["social media", "pr", "related", "media", "planning"]}}, {"job_id": "100003009052015", "location_code": "hk", "company": "A-Fontane Company Limited", "job_title": "Assistant Marketing Manager/ Marketing Executive", "description": "Responsibilities:\n\n\n\nTo provide English and Chinese copy writing for a full range of editing, proofreading and translating various marketing collaterals including user manual, brochure, press release, print advertisement, corporate, etc.\nCoordinating, implementing and managing various marketing campaigns including Advertising, PR, Event, Print and Joint Promotion.\nLiaising closely with internal teams including Design, Sales, Promotion and Purchasing, to ensure effective communication and to progress all marketing campaigns at each stage, from information gathering to concepts, from copy writing to production\n\nRequirements:\n\n\n\nDegree Holder in Languages, Communications, Journalism, Marketing or Public Relations\nAt least 2 years' solid experience in writing position Strong interest in social media industry\nPassionate, detailed mind, proactive/ outgoing, self & team motivated and willing to take responsibilities\nCreative, willing to take up challenge", "employment_types": ["Full Time"], "selling_points": [], "locations": ["Tsuen Wan Area"], "categories": ["Marketing / Public Relations", "Marketing - Brand / Product Management", "Marketing - Marketing Communication", "Digital Marketing"], "post_time": "2022-01-17T01:50:51Z", "salary": {"currency": null, "max": null, "min": null, "period": "monthly", "term": null}, "salary_visible": false, "title_keywords": ["assistant marketing manager", "marketing executive"], "responsibilities": ["advertising", "marketing collaterals", "teams", "design", "communication", "proofreading", "marketing campaigns", "editing"], "requirements": {"degrees": ["degree holder"], "majors": ["journalism", "marketing", "communications"], "languages": [], "language_level": [], "hard_skills": [], "soft_skills": ["passionate", "outgoing", "proactive", "creative", "motivated", "detailed mind"], "languages_combined": []}, "experience_required": {"duration": ["at least 2 years"], "field": ["social media", "writing"]}}, {"job_id": "100003009055562", "location_code": "hk", "company": "Chandler Macleod Group (HK) Limited", "job_title": "Copywriter (Professional Service/ Beauty/ Retail)", "description": "Thinking Group, a sole distributor of Audio products & Smart Gadget products including: Ultimate Ears (UE), JBL/ Harman Kardon, Aftershokz, Ticwatch ....etc. Founded in 1998, its headquarters in HK and branches in Shenzhen & Taiwan. To cope with our continuous expansion, we are seeking qualified candidates to join us.\n\nResponsibilities:\n\n\nManage and update corporate marketing materials (e.g. company website, brochures, newsletter, etc.)\nWorking with social media platform content update and content writing\nFamiliar with shopline\nDevelop, execute and track Social Media platforms promotional campaigns\nMonitor competitors\u2019 marketing campaign and prepare competitive analysis\nComfortable in small business model and fast changing environment\nManage and communicate with KOL\nConducting market analysis to identify the target audience\nAssist in ad-hoc projects and administrative tasks\n\nRequirements:\n\n\nProactive, Self-motivated, independent and result driven\nA minimum of 1-2 years experience with marketing or social media related knowledge\nGood presentation and communication skills (both spoken and written English & Cantonese) liaise with both internal and external parties on developing and producing marketing materials\nGood team player\nKnowledge of Google ads., Copy writing, Social Media\nKnowledge of Ad network (e.g. Google ads, facebook.......)\nFamilar with audio products is an advantage\nFresh graduate are welcome as Marketing assistant\n\nBenefits:\n\n5 Days work\u00a0\nAnnual leave and Sick leave\nBank holiday and Birthday leave\u00a0\nMedical and Dental allowance", "employment_types": ["Full Time", "Permanent"], "selling_points": ["Multinational Working Environment", "Genuine Development Opportunity", "A Growing Business"], "locations": ["Not Specified"], "categories": ["Marketing / Public Relations", "Marketing - Marketing Communication", "Public Relations - Copy-writing", "Digital Marketing"], "post_time": "2022-01-18T02:43:26Z", "salary": {"currency": null, "max": null, "min": null, "period": "monthly", "term": null}, "salary_visible": false, "title_keywords": ["copywriter"], "responsibilities": ["communicate with", "social media", "analysis", "social media platforms", "monitor", "develop", "market analysis", "marketing materials", "ad-hoc projects", "administrative tasks", "company website"], "requirements": {"degrees": ["fresh graduate"], "majors": ["marketing"], "languages": ["cantonese", "english"], "language_level": ["good"], "hard_skills": ["facebook"], "soft_skills": ["communication skills", "self-motivated", "good team player", "independent", "driven", "proactive", "presentation"], "languages_combined": [{"language": "cantonese", "language_level": ["good"]}, {"language": "english", "language_level": ["good"]}]}, "experience_required": {"duration": ["minimum of 1-2 years"], "field": ["related", "social media", "marketing"]}}, {"job_id": "100003009053883", "location_code": "hk", "company": "Thinking Group Holding Limited", "job_title": "Marketing Executive", "description": "Requirements:\n\n\nBachelor's degree, preferably in marketing or business administration\n6 - 10 years' experience in office leasing with major developers\nGood understanding of the office leasing market\nFamiliar with leasing procedures and relevant legal documentation\nStrong interpersonal skills and able to communicate well with business partners\nProven English proficiency and good Putonghua will be an advantage\nPro-active attitude and good team player\n\n\nResponsibilities:\n\n\nResponsible for handling daily leasing enquiries, lease negotiation, marketing, tenancy administration, co-ordination with property management and other related duties for a portfolio of office premises\n\n(Candidates with less experience will be considered for more junior positions.)\n\nGood remuneration and attractive fringe benefits will be offered to the successful applicant. Interested parties please apply with full resume, present and expected salary, available date by clicking \u201cApply Now\u201d.\n\nFor further information, please visit our company website: http://www.shkp.com/.\n\n\nWe are an equal opportunity employer and welcome applications from all qualified candidates. All personal data collected will be used for recruitment purpose only.\u00a0 Applicants not hearing from us within 3 months may consider their applications unsuccessful.\u00a0 All personal data collected will be destroyed within 24 months.", "employment_types": ["Full Time", "Permanent"], "selling_points": ["1-2 years experience with marketing / social media", "Knowledge of Google ads., Copy writing, Social Med", "Familar with audio products is an advantage"], "locations": ["Kwun Tong"], "categories": ["Marketing / Public Relations", "Marketing - General / Support", "Marketing - Marketing Communication", "Digital Marketing"], "post_time": "2022-01-17T08:51:49Z", "salary": {"currency": null, "max": null, "min": null, "period": "monthly", "term": null}, "salary_visible": false, "title_keywords": ["marketing executive"], "responsibilities": ["management", "administration"], "requirements": {"degrees": ["degree", "bachelor"], "majors": ["marketing", "business administration"], "languages": ["putonghua", "english"], "language_level": ["advantage", "proficiency", "good"], "hard_skills": ["documentation"], "soft_skills": ["good team player", "interpersonal skills", "pro-active"], "languages_combined": [{"language": "putonghua", "language_level": ["good", "proficiency", "advantage"]}, {"language": "english", "language_level": ["proficiency", "advantage"]}]}, "experience_required": {"duration": ["6 - 10 years"], "field": []}}, {"job_id": "100003009054942", "location_code": "hk", "company": "Sun Hung Kai Properties Ltd", "job_title": "MANAGER / ASSISTANT MANAGER \u2013 OFFICE LEASING", "description": "Plan and implement integrated Marketing campaigns strategically\nDrive\u00a0marketing innovation with internal and external stakeholders to accelerate new member acquisition, demand generation and user/customer engagement programs\nExplore and liaise various joint promotion to strengthen AME brand image and achieve company goals\nWork with Marketing team, Store Management team and Business units to develop Marketing\u00a0/\u00a0Sales materials and Store supporting\nDesign, develop and produce marketing collaterals, include but not limited to ATL, BTL, Digital platforms and Event Management\nAssist in ad-hoc project\nRequirements:\n\nBachelor\u2019s degree or above in Marketing, Business Administration or other related disciplines\nAt least 2 years' relevant experience in Marketing, Corporate Communication or\u00a0Brand Management\nAble to translate ideas into actions and detailed planning\nExcellent communication, presentation and interpersonal skills\nStrong business acumen, strategic mindset, detailed oriented, creative and passionate in agile environment\nA problem solver with a keen sense to event management and in-depth knowledge of marketing technologies in the brand landscape\nProficiency in MS Office applications and Chinese Word Processing\nGood command of spoken and written English and Chinese, knowledge of Putonghua is an advantage", "employment_types": ["Full Time", "Permanent"], "selling_points": ["Bachelor degree with exp in office leasing", "Office leasing, tenancy administration, marketing", "Co-ordination with property management"], "locations": ["Wan Chai"], "categories": ["Marketing / Public Relations", "Marketing - Marketing Communication", "Property / Real Estate", "Property Management", "Others"], "post_time": "2022-01-17T14:33:35Z", "salary": {"currency": null, "max": null, "min": null, "period": null, "term": null}, "salary_visible": false, "title_keywords": ["assistant manager", "manager"], "responsibilities": ["liaise", "management team", "management", "ad-hoc", "ideas", "marketing collaterals", "design", "develop", "communication", "planning", "marketing campaigns", "plan", "administration"], "requirements": {"degrees": ["degree or above", "bachelor"], "majors": ["related disciplines", "marketing", "business administration"], "languages": ["putonghua", "english", "chinese"], "language_level": ["advantage", "proficiency", "good command"], "hard_skills": ["chinese word processing", "ms office", "agile", "acumen"], "soft_skills": ["passionate", "detailed oriented", "agile", "problem solver", "keen", "communication", "interpersonal skills", "business acumen", "creative", "presentation", "detailed"], "languages_combined": [{"language": "putonghua", "language_level": ["good command"]}, {"language": "english", "language_level": ["advantage", "good command"]}, {"language": "chinese", "language_level": ["advantage", "proficiency", "good command"]}]}, "experience_required": {"duration": ["at least 2 years"], "field": ["management", "brand", "corporate communication", "marketing", "relevant experience"]}}, {"job_id": "100003009053286", "location_code": "hk", "company": "Asia Motion E-Sports Limited", "job_title": "Senior Sales and Marketing Officer/Assistant Sales & Marketing Manager", "description": "Responsibilities:\nAssist department head in the brand building and marketing analysis\nManage reports and data systematically\nFollow up with the customers enquiries and comments\nPrepare the needed documents and check list of marketing team as per request of department head\nPrepare documents of restaurant marketing presentations\nGathering information of competitive culinary brand benchmarks\nPrepare analysis and research data related to sales\nLiaise with management office of different shopping malls for collaboration and promotion\n\nRequirements:\nUniversity graduate in Marketing or related disciplines\nAt least 3 years of marketing working experience\nHas experience in Food and Beverage industry is required\nPossess strong analytical skill and numerical sense\nProficient in MS Office Word, Excel, PowerPoint and Chinese Word Processing\nHigh initiative, willing to learn and good teamwork spirit\nSelf-motivated and as a good team member with excellent communication skills\nGood command in spoken and written English and Chinese (Cantonese and Putonghua)", "employment_types": ["Full Time", "Permanent"], "selling_points": [], "locations": ["Kwai Fong"], "categories": ["Sales, CS & Business Devpt", "Business Development", "Marketing / Public Relations", "Marketing - General / Support", "Marketing - Marketing Communication"], "post_time": "2022-01-17T06:47:28Z", "salary": {"currency": null, "max": null, "min": null, "period": "monthly", "term": null}, "salary_visible": false, "title_keywords": ["sales & marketing manager", "assistant", "senior sales", "marketing officer"], "responsibilities": ["management", "data", "analysis", "comments", "presentations", "reports", "liaise with", "prepare documents"], "requirements": {"degrees": ["university graduate"], "majors": ["related disciplines", "marketing"], "languages": ["cantonese", "putonghua", "english", "chinese"], "language_level": ["good command", "proficient"], "hard_skills": ["excel", "analytical skill", "chinese word processing", "word", "powerpoint", "ms office"], "soft_skills": ["communication skills", "self-motivated", "analytical skill", "willing to learn", "teamwork spirit", "team member", "initiative"], "languages_combined": [{"language": "cantonese", "language_level": ["good command"]}, {"language": "putonghua", "language_level": ["good command"]}, {"language": "english", "language_level": ["good command"]}, {"language": "chinese", "language_level": ["good command", "proficient"]}]}, "experience_required": {"duration": ["at least 3 years"], "field": ["food", "marketing", "beverage industry"]}}, {"job_id": "100003009052273", "location_code": "hk", "company": "Lubuds F&B Group", "job_title": "Marketing Executive", "description": "Our client is a luxury retailer with worldwide presence. They are currently growing their global business and they are looking for an APAC Marketing Manager to join their dynamic team.\n\nClient Details\n\nOur client is a luxury retailer with worldwide presence. They are currently growing their global business and they are looking for an APAC Marketing Manager to join their dynamic team.\n\nDescription\n\nOur client is a luxury watches brand with worldwide presence. They are currently growing their global business and they are looking for an APAC Marketing Manager to join their dynamic team. The position is the key driver to develop marketing strategy and campaign, work closely with external parties and internal global PR team.\n\nProfile\n\nThe successful candidate would be an experienced marketing manager from luxury industry (brands or retailers) or other e-commerce platforms. Candidate with luxury goods portfolio will be considered first. Our client is looking for someone who has strong presentation skills and hands on experience of marketing plan implementation. Fluency in English and Cantonese is required. Degree level qualification in marketing, media studies, or other related subjects is preferred.\n\nJob Offer\n\nWork for a global company that provides you with opportunity to expand your career. You will be provided with an attractive salary package and compensation.\n\nTo apply online please click the 'Apply' button below. For a confidential discussion about this role please contact Smania Wu on +852 3412 4858.", "employment_types": ["Full Time", "Permanent"], "selling_points": [], "locations": ["Aberdeen"], "categories": ["Marketing / Public Relations", "Marketing - General / Support", "Marketing - Marketing Communication", "Public Relations - General / Support"], "post_time": "2022-01-17T02:37:34Z", "salary": {"currency": null, "max": null, "min": null, "period": "monthly", "term": null}, "salary_visible": false, "title_keywords": ["marketing executive"], "responsibilities": ["external parties", "e-commerce platforms", "implementation", "develop", "marketing plan", "contact"], "requirements": {"degrees": ["degree"], "majors": ["marketing"], "languages": ["cantonese", "english"], "language_level": ["fluency"], "hard_skills": ["dynamic", "e-commerce", "luxury industry"], "soft_skills": ["presentation skills", "dynamic", "hands on"], "languages_combined": [{"language": "cantonese", "language_level": ["fluency"]}, {"language": "english", "language_level": ["fluency"]}]}, "experience_required": {"duration": [], "field": ["marketing"]}}, {"job_id": "100003009055892", "location_code": "hk", "company": "Michael Page", "job_title": "APAC Marketing Manager - Luxury Retailer", "description": "\u00a0Social Media Executive\u00a0(Welcome Fresh Grad)\n\n\u00a0\n\n\u00a06 days per week on shift ; the\u00a0working schedule is\u00a0either:\n\n- from 7:00 am to 3:00 pm\n\u00a0or\n- from 3:00 pm to 11:00 pm\u00a0\n\n\u00a0\u00a0Job Description\n\nCo-ordinate and Analyze data from social monitoring tools\nConduct market research and studies including but not limited to social media content\nPrepare Marketing Research Summary (Chinese)\nAssist in preparing analytic reports\nPerform ad-hoc tasks and projects as assigned\n\nJob Requirement\n\nHigher Diploma\u00a0in Chinese, Journalism, Marketing, or equivalent\n\nFresh grad welcome.\nProficient in written Chinese.\nFamiliar with social media platforms.\nWell-organized, responsible and self-motivated;\nImmediate availability is preferred\n\nBenefits\n\nYoung team with relaxing culture\nWork-life balanced with minimal OT\nCozy and casual working environment\nCompetitive salary and benefits package\nBirthday Leave\n\nInterested parties please send\u00a0full CV with the cover letter and your Expected Salary to Mr. Ho at\u00a0recruit@ hkvlogger.com\n\nAll information collected will be treated as strictly confidential.", "employment_types": ["Full Time", "Permanent"], "selling_points": ["Luxury Retailer", "Regional Exposure", "International Working Environment"], "locations": ["Not Specified"], "categories": ["Marketing / Public Relations", "Marketing - Brand / Product Management", "Marketing - Marketing Communication", "Digital Marketing"], "post_time": "2022-01-18T03:03:28Z", "salary": {"currency": null, "max": null, "min": null, "period": "monthly", "term": null}, "salary_visible": false, "title_keywords": ["marketing manager"], "responsibilities": ["conduct market research", "monitoring", "ad-hoc tasks", "marketing research", "social media content", "reports", "analyze data"], "requirements": {"degrees": ["diploma"], "majors": ["journalism", "marketing"], "languages": ["chinese"], "language_level": ["proficient"], "hard_skills": [], "soft_skills": ["self-motivated", "well-organized", "responsible"], "languages_combined": [{"language": "chinese", "language_level": ["proficient"]}]}, "experience_required": {"duration": [], "field": []}}, {"job_id": "100003009054051", "location_code": "hk", "company": "Social Monitoring Limited", "job_title": "Market Research Executive (Welcome Fresh Grad)", "description": "Responsibilities:\n\nSupport and assist \u00a0in the planning and execution of the marketing and advertising campaigns\nRender quality works in copywriting and translation\u00a0 for marketing materials including press releases, invitations and catalogues\nFoster close working relationship with journalists and editors of international and local media\nCreate and develop contents for social media channels and ensure they are updated accordingly and timely\nConduct market researches and evaluate the effectiveness of all marketing activities\nLogistic support fordifferent events and campaigns\nAssist in ad-hoc projects as assigned\nHandle general clients\u2019 enquiries when necessary during the auction seasons\n\n\nRequirements:\n\n3\u00a0years\u00a0or above\u00a0of\u00a0work experience in press and marketing field\nExperience in translation, copyediting or copywriting will be an advantage, preferably from the field of art\nGood command of both written and spoken Cantonese, Putonghua and English\nExperience in handling different social media accounts\nMulti-tasking skills, attentive to details\u00a0and able to work under pressure\nStrong proficiency with MS Word, Excel,\u00a0PowerPoint\u00a0and Chinese Word Processing\nExcellent time management skills, ability to meet deadlines;\nTravel required when necessary\n\nPersonal data collected will be used for recruitment purpose only\n\nOnly shortlisted candidates will be notified.", "employment_types": ["Full Time"], "selling_points": ["Conduct market research and studies", "Work-life balanced with minimal OT", "Medical Coverage, Birthday leave"], "locations": ["Kwun Tong"], "categories": ["Marketing / Public Relations", "Marketing - Market Research", "Marketing - Marketing Communication", "Others", "Student / Fresh Graduate / No Experience"], "post_time": "2022-01-17T08:12:42Z", "salary": {"currency": null, "max": null, "min": null, "period": "monthly", "term": null}, "salary_visible": false, "title_keywords": ["executive"], "responsibilities": ["social media", "quality", "logistic support", "develop", "evaluate", "contents", "marketing materials", "ad-hoc projects", "advertising campaigns", "planning"], "requirements": {"degrees": [], "majors": [], "languages": ["cantonese", "putonghua", "english", "chinese"], "language_level": ["proficiency", "good command"], "hard_skills": ["excel", "chinese word processing", "powerpoint", "translation", "ms word"], "soft_skills": ["attentive to details", "time management skills", "multi-tasking skills", "meet deadlines", "work under pressure"], "languages_combined": [{"language": "cantonese", "language_level": ["good command"]}, {"language": "putonghua", "language_level": ["good command"]}, {"language": "english", "language_level": ["good command"]}, {"language": "chinese", "language_level": ["proficiency"]}]}, "experience_required": {"duration": ["3 years"], "field": ["copywriting", "social media", "marketing"]}}, {"job_id": "100003009049514", "location_code": "hk", "company": "Tokyo Chuo Auction Hongkong Company Limited", "job_title": "Marketing and Communication Officer", "description": "Responsibilities:\n\nAssist in supporting and managing the day to day operations of a website / e-commerce business, include CMS, content, SEO, online shop, and customer engagement / support\nSupport marketing cloud operation including customer journey building, automation, email and sms preparation and customer engagement / support\nAssist in planning and implementation of marketing campaigns and promotion activities including but not limited to social media, blogs, KOLs, PR, media\nSupport in data and analytical tasks to run reports, create insights, and optimize marketing campaigns\nSupport in preparing, updating marketing materials (content/visuals), maintain, and drive brand awareness via online and offline marketing\nSupport event planning and operations, including but not limited to material sourcing, vendor coordination, logistics, rsvp\nWork closely with internal and external parties to facilitate smooth implementation and operation of marketing strategies on digital, traditional marketing and event coordination\nHandle other ad hoc projects assigned\n\nRequirements:\n\nDegree holder or above in Communication, Language, Literature, Marketing, Business or related disciplines\n1 - 3 years\u2019 experience in marketing or digital technology, preferable gained in managing external agencies / vendors / recent grads with solid intern experience are welcome\nHands-on experience in online and offline marketing and e-commerce\nWell-organized with ability to prioritize and multi-task\nSelf-motivated, result-oriented and attentive to details\nGood project management, interpersonal skills and communication skills\nGood command of both written and spoken English and Chinese\n\nSalary and benefits will be commensurate with qualifications and experience.\u00a0 Interested parties, please send a full resume with present and expected salary, and date available to The Human Resources Department, 32/F., Great Eagle Centre, 23 Harbour Road, Wan chai, Hong Kong or e-mail to us.\u00a0(Please quote the reference no. on the envelope and the covering letter.)\n\nTo know more about us, please visit our website at http://www.greateagle.com.hk.\n\nWe are an equal opportunity employer and welcome applications from all qualified candidates.\n\nPersonal data collected will be treated in strict confidence and used only for recruitment-related purpose. Applicants who have not heard from us within four weeks may consider their applications unsuccessful. All personal data will be destroyed after 12 months.", "employment_types": ["Full Time", "Permanent"], "selling_points": ["Assist in planning and implementing PR promotions", "Prepare marketing and PR collaterals", "Coordinate advertising campaign"], "locations": ["Central & Western Area"], "categories": ["Marketing / Public Relations", "Marketing - General / Support", "Marketing - Marketing Communication", "Public Relations - Event Management"], "post_time": "2022-01-14T08:47:08Z", "salary": {"currency": null, "max": null, "min": null, "period": "monthly", "term": null}, "salary_visible": false, "title_keywords": ["communication officer"], "responsibilities": ["social media", "seo", "day to day operations", "marketing strategies", "data", "operations", "internal and external parties", "implementation", "website", "maintain", "reports", "logistics", "marketing campaigns", "coordination", "marketing materials", "ad hoc projects", "planning"], "requirements": {"degrees": ["recent grads", "degree holder"], "majors": ["business", "related disciplines", "marketing"], "languages": ["english", "chinese"], "language_level": ["good command"], "hard_skills": ["project management", "e-commerce"], "soft_skills": ["communication skills", "self-motivated", "multi-task", "attentive to details", "well-organized", "prioritize", "communication", "project management", "hands-on", "interpersonal skills", "result-oriented"], "languages_combined": [{"language": "english", "language_level": ["good command"]}, {"language": "chinese", "language_level": ["good command"]}]}, "experience_required": {"duration": ["1 - 3 years"], "field": ["digital", "marketing", "e-commerce"]}}, {"job_id": "100003009054929", "location_code": "hk", "company": "Sun Hung Kai Properties Ltd", "job_title": "ASSISTANT MANAGER \u2013 INDUSTRIAL PORTFOLIO LEASING", "description": "Job Summary\n\nThe position is responsible for a wide range of external and internal communication initiatives to elevate the corporate brand as well as supporting all service line marketing needs.\n\nResponsibilities\n\nDevelop and implement marketing templates to maintain brand consistency across all service lines in Greater China\nCopywriting and translation of internal and external communications including advertisements, print and digital collateral, speeches, and website and social media content\nCoordinate and produce corporate collaterals including flyers, brochures, staff CVs, eDMs, and industry award submissions\nLiaise with marketing agencies on marketing initiatives, advert placement, and sponsorship programmes\nCoordinate production of corporate premiums, and manage stock levels and related marketing expenses\nCoordinate staff photography and assist in the production of corporate videos\nOrganise corporate events including cocktail parties, seminars, sponsored events, CSR events, and media exhibitions\n\nRequirements\n\n\nDegree holder in Marketing, Languages, Communication, Journalism or a related discipline\n\u00a0At least 3 years\u2019 relevant experience in marketing and communications\nExcellent creative copywriting skills in English and Chinese\nGood communication, presentation, and interpersonal skills\nMust work well both independently and as part of a team\nAble to work under pressure and meet deadlines\nFluent in both written and spoken English and Cantonese, Mandarin is a plus\nHigh proficiency in MS Word, Excel, PowerPoint and Chinese word processing\n\nCandidates with more experience will be considered for the position of Assistant Manager.\n\nWe will offer an attractive remuneration package to the right candidate. Interested parties please click \"Apply Now\" below to submit your full resume with available date, and current and expected salaries to the Human Resources Department.\n\n\nTo learn more about working at Knight Frank, please click\u00a0here\u00a0to view our corporate video.\n\nYou are encouraged to read our digital brochure \u201cWhy Knight Frank\u201d to understand how we attract and inspire people to join our exceptional firm.\n\nKnight Frank is an equal opportunity employer. All information submitted will be treated in the strictest confidence and used only for recruitment purposes in accordance with our personal data policy.\u00a0", "employment_types": ["Full Time", "Permanent"], "selling_points": ["Exp in leasing of industrial/ commercial portfolio", "Partnership development, new tenant sourcing", "Marketing and promotional activities"], "locations": ["Wan Chai"], "categories": ["Sales, CS & Business Devpt", "Business Development", "Marketing / Public Relations", "Marketing - Marketing Communication", "Property / Real Estate", "Others"], "post_time": "2022-01-17T14:16:59Z", "salary": {"currency": null, "max": null, "min": null, "period": null, "term": null}, "salary_visible": false, "title_keywords": ["assistant manager"], "responsibilities": ["edms", "advertisements", "expenses", "website", "develop", "coordinate", "maintain", "social media content", "liaise with", "brand consistency"], "requirements": {"degrees": ["degree holder"], "majors": ["journalism", "marketing"], "languages": ["cantonese", "english", "chinese", "mandarin"], "language_level": ["excellent", "proficiency", "fluent"], "hard_skills": ["excel", "plus", "chinese word processing", "powerpoint", "ms word"], "soft_skills": ["independently", "communication", "interpersonal skills", "meet deadlines", "creative", "presentation", "work under pressure"], "languages_combined": [{"language": "cantonese", "language_level": ["fluent"]}, {"language": "english", "language_level": ["excellent", "fluent"]}, {"language": "chinese", "language_level": ["excellent", "proficiency"]}, {"language": "mandarin", "language_level": ["fluent"]}]}, "experience_required": {"duration": ["at least 3 years"], "field": ["marketing", "relevant experience"]}}, {"job_id": "100003009049564", "location_code": "hk", "company": "Knight Frank Petty Ltd", "job_title": "Senior Officer, Marketing & Communications", "description": "Responsibilities:\n\nHandle the public enquiries and complaints from stakeholders.\nCommunicate and liaise with different members or relevant authorities.\n\nRequirements:\n\nDegree in Communication, Marketing or equivalent\nMinimum 3 years of relevant working experience in construction industry\nWell-versed in MS office applications (e.g. Word, Excel, PowerPoint, etc.) and Chinese word processing\nGood command of written and spoken English and Chinese\nLess experience will be considered as Assistant Officer\n\nWe offer attractive remuneration package with comprehensive fringe benefits to the right candidates. Interested parties please send resume with day-time contact number, expected salary and quoting Ref. No. to Human Resources Manager, 29/F., China Overseas Building, 139 Hennessy Road, Wanchai, Hong Kong or e-mail or fax to 2528 2840.\n\nInterested parties are invited to visit our website (www.cscechk.com/en) for more information.\n\nApplicants who are not invited within 2 months may consider their applications unsuccessful. All information provided by applicants will be treated in strict confidence and used only for recruitment purposes. Applicants may be considered for other suitable positions within the China Overseas Group and its related companies for one-year period, thereafter which their personal data will be destroyed.\n\nServing The Community \u3002 Prospering Hong Kong", "employment_types": ["Full Time", "Permanent"], "selling_points": ["Elevate the corporate brand", "Copywriting and translation", "Organise corporate events"], "locations": ["Wan Chai"], "categories": ["Marketing / Public Relations", "Marketing - Brand / Product Management", "Marketing - Marketing Communication", "Digital Marketing"], "post_time": "2022-01-14T08:53:50Z", "salary": {"currency": null, "max": null, "min": null, "period": "monthly", "term": null}, "salary_visible": false, "title_keywords": ["senior officer"], "responsibilities": ["liaise with"], "requirements": {"degrees": ["degree"], "majors": ["marketing"], "languages": ["english", "chinese"], "language_level": ["good command"], "hard_skills": ["excel", "chinese word processing", "word", "powerpoint", "ms office"], "soft_skills": ["communication"], "languages_combined": [{"language": "english", "language_level": ["good command"]}, {"language": "chinese", "language_level": ["good command"]}]}, "experience_required": {"duration": ["minimum 3 years"], "field": ["construction industry", "relevant working experience"]}}, {"job_id": "100003009055404", "location_code": "hk", "company": "China State Construction Engineering (Hong Kong) Limited", "job_title": "Senior/ Public Relations Officer (site based)", "description": "Key Responsibilities\n\nProvide editorial and event management support in all publicity related assignments;\nSupport the department in English and Chinese editorial needs, including corporate materials and marketing write-ups;\nAct as key liaison between external stakeholders and internal departments to ensure communication objective are met;\nSupervise the team in day-to-day assignments and manage departmental calendar effectively;\nSupport building digital capability across the enterprise and act as custodian of all online assets;\nResearch and collect information on industry and public affairs to keep the company abreast of market developments;\nAssist in ad-hoc projects as assigned.\n\nRequirement\n\nBachelor Degree holder, preferably in Translations, English Studies, Mass Communications or related disciplines;\nMinimum 10 years of solid experience in media, corporate communications, public affairs, or research and analysis, preferably in sizable company or news outlet;\nAt least 2 years\u2019 experience in supervisory role in reputable organization is preferred;\nExcellent command of written and spoken English and Chinese, conversant in Mandarin is preferred;\nStrong PC skills, familiar with creative software is preferable;\nMust have solid media experience and proven track record in handling large scale events;\nGood interpersonal and communications skills; team player and meticulous;\nCandidate with lesser experience will be considered for an Assistant Manager position.\n\nWe offer long-term career prospect and competitive remuneration package to the appointed candidate. Please apply in confidence with your detailed resume stating your current and expected salary to\u00a0Group Human Resources Department\n\nby email to\u00a0recruit(at)shuntakgroup.com\n\nor mail to\u00a0Penthouse 39/F, West Tower, Shun Tak Centre, 200 Connaught Road Central, Hong Kong\n\n(Please quote reference number and applied position)\n\nThe information supplied by the applicants will be used in accordance with the Personal Data (Privacy) Policy of Shun Tak Group (a copy of which will be provided upon request). Only shortlisted candidates will be notified.\n\n\nwww.shuntakgroup.com", "employment_types": ["Full Time", "Permanent"], "selling_points": ["Handle the public enquiries and complaints", "Minimum 3 yrs relevant exp in contruction industry", "Double pay, bonus, attractive benefit package"], "locations": ["Not Specified"], "categories": ["Building & Construction", "Building / Construction / QS", "Marketing / Public Relations", "Marketing - Marketing Communication", "Public Relations - General / Support"], "post_time": "2022-01-18T02:28:21Z", "salary": {"currency": null, "max": null, "min": null, "period": "monthly", "term": null}, "salary_visible": false, "title_keywords": ["officer"], "responsibilities": ["communication", "management", "ad-hoc projects"], "requirements": {"degrees": ["bachelor degree holder"], "majors": ["related disciplines", "communications"], "languages": ["english", "chinese", "mandarin"], "language_level": ["excellent"], "hard_skills": ["analysis", "pc skills"], "soft_skills": ["meticulous", "team player", "creative", "interpersonal"], "languages_combined": [{"language": "english", "language_level": ["excellent"]}, {"language": "chinese", "language_level": ["excellent"]}, {"language": "mandarin", "language_level": ["excellent"]}]}, "experience_required": {"duration": ["at least 2 years", "minimum 10 years"], "field": ["supervisory", "research", "media"]}}, {"job_id": "100003009049058", "location_code": "hk", "company": "Shun Tak Holdings Ltd", "job_title": "Manager, Corporate Communications (Ref. STHL1714)", "description": "Diploma or above in Communications, Public Relations, Journalism or related disciplines\nMinimum 5 years\u2019 relevant experience in the field of corporate communications, fundraising, event management, publishing and editing\nGood communication skills in both written and spoken English, Chinese and Mandarin\nProficient in MS Office applications\nCandidates with less experience will be considered as Corporate Communications and Fundraising Officer\nContract period : 2022/2/4 to 2022/5/31\nThe appointment will be made on a fixed-term contract basis. Interested candidates are invited to apply by sending full resume with current salary, expected salary and date available to Human Resources Department, Pok Oi Hospital Board, UG/F., Pok Oi Hospital Jockey Club Care & Attention Home Building, Au Tau, Yuen Long or by email via \"Apply Now\"\u00a0on or before 26 January 2022.\u00a0 For more details of Pok Oi Hospital, please visit our website http://www.pokoi.org.hk.\n\u00a0(All personal data collected from applicants will be kept confidential and used for employment-related purpose only. \u00a0The Board is an equal opportunity employer.)", "employment_types": ["Full Time"], "selling_points": ["Provide editorial and event management support", "Corporate materials and marketing write-ups", "Supervise the team in day-to-day assignments"], "locations": ["Sheung Wan"], "categories": ["Marketing / Public Relations", "Marketing - Market Research", "Marketing - Marketing Communication", "Public Relations - Copy-writing"], "post_time": "2022-01-14T08:00:11Z", "salary": {"currency": null, "max": null, "min": null, "period": "monthly", "term": null}, "salary_visible": false, "title_keywords": ["manager"], "responsibilities": ["communication", "management", "editing"], "requirements": {"degrees": ["diploma or above"], "majors": ["journalism", "related disciplines", "communications"], "languages": ["english", "chinese", "mandarin"], "language_level": ["good"], "hard_skills": ["ms office"], "soft_skills": ["communication skills"], "languages_combined": [{"language": "english", "language_level": ["good"]}, {"language": "chinese", "language_level": ["good"]}, {"language": "mandarin", "language_level": ["good"]}]}, "experience_required": {"duration": ["minimum 5 years"], "field": ["management", "publishing", "relevant experience", "editing"]}}, {"job_id": "100003009048934", "location_code": "hk", "company": "Pok Oi Hospital", "job_title": "Temporary Senior Corporate Communications and Fundraising Officer (Ref: BOD/SCCFO/Temp)", "description": "Responsibilities:\n\nSupport the execution for loyalty campaigns to boost awareness and redemption rate\nDevelop effective customer communications\nFoster good business relationships with internal and external stakeholders to ensure smooth execution\nTrack and analyze campaign result and take remedial action when needed\nPrepare MI and management report on a regular basis\n\nRequirements:\n\nDegree holder in Marketing, Quantitative Analysis, Business Studies or related disciplines\nAt least 3 years working experience, preferably in loyalty marketing\u00a0\nStrong analytical mind and interpersonal communication skills\nOpen minded, hardworking and resilient\n\nApart from competitive remuneration package and exciting opportunity for career development within the Group, we provide attractive employee benefits such as free company shuttle, free company SIM card and preferential SIM plan offers, comprehensive medical & insurance schemes, as well as full range of other employee well-being provisions.\u00a0\n\nInterested parties, please apply with full resume, present and expected salary, by clicking \u201cAPPLY NOW\u201d. Please quote the reference number on the e-mail subject.\n\nWe are an equal opportunity employer and welcome applications from all qualified candidates. Personal data collected will be treated in the strictest confidence and handled confidentially by authorised personnel for recruitment-related purposes only within the CK Hutchison Group of companies. The personal data of unsuccessful applicants will be destroyed after the recruitment exercise pursuant to the requirements of the Personal Data (Privacy) Ordinance in Hong Kong.", "employment_types": ["Contract"], "selling_points": ["Good communication skills", "Diploma or above in Communications", "Minimum 5 years\u2019 relevant experience"], "locations": ["Not Specified"], "categories": ["Media & Advertising", "Editorial / Journalism", "Marketing / Public Relations", "Marketing - Marketing Communication", "Others"], "post_time": "2022-01-14T07:47:09Z", "salary": {"currency": null, "max": null, "min": null, "period": "monthly", "term": null}, "salary_visible": false, "title_keywords": ["fundraising officer"], "responsibilities": ["management report", "develop"], "requirements": {"degrees": ["degree holder"], "majors": ["business", "related disciplines", "marketing"], "languages": [], "language_level": [], "hard_skills": ["analysis"], "soft_skills": ["communication skills", "analytical mind", "comprehensive", "open minded", "interpersonal", "hardworking"], "languages_combined": []}, "experience_required": {"duration": ["at least 3 years"], "field": ["marketing"]}}, {"job_id": "100003009055671", "location_code": "hk", "company": "Dah Chong Hong, Limited", "job_title": "Assistant Operation Officer", "description": "Draft internal and external communications to raise awareness of Company Formation\u00a0(\u201cCF\u201d) campaigns, products and services, regulatory updates, etc., including social media posts.\nSupport the delivery of day-to-day operational marketing and communications programmes and campaigns that enable CF to engage internal colleagues and external clients and other external stakeholders (regulators/referral channels); includes drafting messaging, eDM assembling, tracking and generating post-campaign metric reports, etc.\nSupport the CF Marketing Manager and internal subject matter experts on running internal trainings and external client webinars, includes logistics and tracking and generating post-event metrics reports.\nWork closely with the global editorial team to help deliver and execute CF thought leadership campaigns.\nMaintain good working relationships with CF key stakeholders and the Group Marketing team to assist on the execution of marketing deliverables.\nWork with the Group Product and Sector Marketing team to help integrate CF into relevant Sector Marketing campaigns and support bespoke product marketing campaigns to win new clients.\nStay on top of Group Marketing brand refresh updates (brand guidelines, tone of voice, processes) and apply new standard across CF marketing deliverables.\nSupport research campaigns/competitor analysis.\nSupport the CF Marketing Manager in coordinating event logistics for sponsorships, meetings, speaking engagements, seminars/conferences, tradeshows, webinars and other off-site activities.\nDevelop an understanding of the business and strategic objectives for CF.\nDevelop a high-level understanding of the CF products and services.\nMaintain knowledge and understanding of the industry business landscapes including sector insights, regulatory changes and emerging trends.\nSupport the maintenance of the business intranet site, including the update and maintenance.\nProduce suitable, accurate and well-presented PowerPoint, Excel and Word documents where required.\nSupport CF Marketing Manager and Head of Communications on any ad hoc duties as assigned.\n\nRequirements:\n\nBachelor\u2019s degree, preferably in Marketing, Communications, or Business\nWith at least 2 years of relevant marketing or communications experience\nGood experience in monitoring social media platforms\nExperience with marketing automation platforms (such as Hubspot) would be an advantage\nNative level in written and oral English\nFluency in additional languages would be a further asset, e.g. Mandarin\nChinese word processing skills would be beneficial\nSelf-starter with the ability to work independently as individual contributor and in a global team based in multiple time zones\nExcellent interpersonal and communication skills collaborating effectively with a wide variety of colleagues\nStrong organisational skills with attention to detail\nAbility to work under pressure and in a fast-paced environment\nGood problem-solving skills, ability to prioritize and manage competing deadlines\nWe offer an attractive package with benefits for the right candidate and long term career prospect.\n\n\nPersonal data collected will be used for recruitment purpose only.\n\nOnly shortlisted candidates will be contacted and all applications will be treated in strict confidence.", "employment_types": ["Full Time", "Permanent"], "selling_points": [], "locations": ["Kowloon Bay"], "categories": ["Marketing / Public Relations", "Marketing - General / Support", "Marketing - Marketing Communication"], "post_time": "2022-01-18T02:50:37Z", "salary": {"currency": null, "max": null, "min": null, "period": "monthly", "term": null}, "salary_visible": false, "title_keywords": ["operation officer", "assistant"], "responsibilities": ["site activities", "social media platforms", "communication", "maintain", "brand guidelines", "work under pressure", "ad hoc duties", "develop", "conferences", "logistics", "reports", "marketing campaigns", "social media", "edm", "monitoring", "tracking", "maintenance", "analysis", "working relationships"], "requirements": {"degrees": ["degree", "bachelor"], "majors": ["business", "marketing", "communications"], "languages": ["english", "chinese", "mandarin"], "language_level": ["native"], "hard_skills": ["excel", "chinese word processing", "maintenance", "analysis", "word", "powerpoint", "problem-solving skills"], "soft_skills": ["communication skills", "oral", "work independently", "fast-paced environment", "prioritize", "organisational skills", "attention to detail", "problem-solving skills", "accurate", "leadership", "interpersonal", "work under pressure"], "languages_combined": [{"language": "english", "language_level": ["native"]}, {"language": "chinese", "language_level": []}, {"language": "mandarin", "language_level": []}]}, "experience_required": {"duration": ["at least 2 years"], "field": ["social media", "marketing"]}}, {"job_id": "100003009048195", "location_code": "hk", "company": "Vistra (Hong Kong) Limited", "job_title": "Senior Marketing & Communications Executive", "description": "Your role:\n\nTo assist in planning and carrying out integrated online and offline advertising campaigns to support business goals & brand KPIs\nTo handle execution and follow through to ensure smooth operation and target achievement in accordance to the media plan\nTo work with internal business units and external partners such as advertising agency, media agency and partners\nTo analyze and evaluate the effectiveness of media advertising campaigns for different brands\n\nTo succeed in this role:\n\nDegree holder preferably in Communications, Marketing or Business related discipline\n2-4 years of experience is required, preferably in media agency\nA proactive team player with strong communication and interpersonal skills\nIndependent, detailed-oriented and highly organized with strong sense of responsibility\nGood command of both written and spoken English and Chinese\nProficiency in MS Office e.g. MS Word, Excel and PowerPoint\n\nIf you have the desire for an exciting and rewarding career, please send us your resume immediately, quoting the reference number, your present and expected salary via email or fax to Human Resources.", "employment_types": ["Full Time", "Permanent"], "selling_points": ["Marketing function for Professional Service firm", "Digital marketing and webinar experience required", "Global marketing exposure"], "locations": ["Causeway Bay"], "categories": ["Marketing / Public Relations", "Marketing - General / Support", "Marketing - Marketing Communication", "Digital Marketing"], "post_time": "2022-01-14T05:49:20Z", "salary": {"currency": null, "max": null, "min": null, "period": "monthly", "term": null}, "salary_visible": false, "title_keywords": ["senior marketing & communications executive"], "responsibilities": ["business goals", "advertising", "evaluate", "communication", "plan", "kpis", "advertising campaigns", "planning"], "requirements": {"degrees": ["degree holder"], "majors": ["business", "marketing", "communications"], "languages": ["english", "chinese"], "language_level": ["good command"], "hard_skills": ["ms word", "excel", "powerpoint", "ms office"], "soft_skills": ["organized", "independent", "sense of responsibility", "communication and interpersonal skills", "smooth", "team player", "proactive", "detailed"], "languages_combined": [{"language": "english", "language_level": ["good command"]}, {"language": "chinese", "language_level": ["good command"]}]}, "experience_required": {"duration": ["2-4 years"], "field": ["agency", "media"]}}, {"job_id": "100003009050217", "location_code": "hk", "company": "HKT Consumer Group", "job_title": "Marketing Communications Executive", "description": "Responsibilities:\n\nAssist Brand Manager to manage brands / products\u00a0\nTake initiative to develop marketing programs targeted at both consumers and trade customers, and implement a mix of marketing activities\nWork with the sales team to formulate trade promotion strategy and programs for key customers\nBuild up and maintain good relationship with media & agencies\nHandle marketing administrative works including reporting, claims and inventory control\nCoordinate with various departments to ensure promotions and activities are executed\n\nRequirement:\u00a0\n\nDegree in Marketing / Hospitality is preferred\nMin 2-4 years or above working experience preferably in FMCG or beverage industry\nSensitive to numbers and strong analytical skills\nSelf-motivated, fast learner with good multi-tasking skills to meet tight deadlines\nExcellent communication and inter-personal skill\nCandidate with more experience will be considered as Senior Marketing Executive\nImmediate available is preferred\n\n\n\nWe offer attractive remuneration package and career prospects plus 5-day week and medical insurance. Interest parties, please forward your full resume with expected salary to\u00a0apply now.\n\nAll data collected shall be solely for recruitment purpose.\n\nWebsite\u00a0\u00a0 :\u00a0\u00a0\u00a0\u00a0\u00a0\u00a0\u00a0http://www.telford.com.hk/", "employment_types": ["Full Time"], "selling_points": [], "locations": ["Quarry Bay"], "categories": ["Marketing / Public Relations", "Marketing - Brand / Product Management", "Marketing - General / Support", "Marketing - Marketing Communication"], "post_time": "2022-01-14T09:57:08Z", "salary": {"currency": null, "max": null, "min": null, "period": "monthly", "term": null}, "salary_visible": false, "title_keywords": ["marketing communications executive"], "responsibilities": ["reporting", "coordinate with", "maintain good relationship", "develop", "inventory control", "sales team"], "requirements": {"degrees": ["degree"], "majors": ["hospitality", "marketing"], "languages": [], "language_level": [], "hard_skills": ["analytical skills"], "soft_skills": ["self-motivated", "meet tight deadlines", "analytical skills", "communication", "inter-personal skill", "multi-tasking skills", "sensitive to numbers", "fast learner"], "languages_combined": []}, "experience_required": {"duration": ["min 2-4 years"], "field": ["fmcg", "beverage industry", "marketing"]}}, {"job_id": "100003009052750", "location_code": "hk", "company": "Telford International Co Ltd", "job_title": "Marketing Executive / Senior Marketing Executive - Beverage Division", "description": "Business Development Manager (Digital Marketing)\n\nWhat are you going to do as a Business Development Manager?\n\nAs a business development manager, you would be responsible to pitch new clients, provide consultative advice, analyze the business needs, develop strategic solutions and the media plans.\n\nWhat is offered to you as a Business Development Manager?\n\n* Young, energetic, flexible & international workplace\n* Comprehensive medical insurance\n* Competitive base salary + commission\n\nWhat is expected of you?\n\n* 2-5 years digital marketing solutions selling experience\n* Cantonese Native Speaker, Excellent communication skills in English & Mandarin\n* Bachelor's Degree in any discipline\n\nWhere are you going to work?\n\nYou are going to work in an international marketing consultancy with teams. This is a perfect opportunity for young and energetic candidates with a strong sales-driven mind B2B selling experience. If you are interested, apply now. For more information, contact us at cristy.ngan@ambitiouspeople.com", "employment_types": ["Full Time", "Permanent"], "selling_points": ["Degree in Marketing / Hospitality is preferred", "2-4 years exp. in FMCG or beverage industry", "Sensitive to numbers and strong analytical skills"], "locations": ["Kwai Hing"], "categories": ["Marketing / Public Relations", "Marketing - Brand / Product Management", "Marketing - Direct Marketing", "Marketing - Marketing Communication"], "post_time": "2022-01-17T03:55:34Z", "salary": {"currency": null, "max": null, "min": null, "period": "monthly", "term": null}, "salary_visible": false, "title_keywords": ["senior marketing executive", "marketing executive"], "responsibilities": ["teams", "develop", "communication", "digital marketing", "contact", "plans", "insurance"], "requirements": {"degrees": ["degree", "bachelor"], "majors": [], "languages": ["cantonese", "english", "mandarin"], "language_level": ["native", "excellent"], "hard_skills": [], "soft_skills": ["flexible", "communication skills", "responsible", "comprehensive", "energetic", "driven"], "languages_combined": [{"language": "cantonese", "language_level": ["native", "excellent"]}, {"language": "english", "language_level": ["native", "excellent"]}, {"language": "mandarin", "language_level": ["native", "excellent"]}]}, "experience_required": {"duration": ["2-5 years"], "field": ["digital marketing"]}}, {"job_id": "100003009055835", "location_code": "hk", "company": "Ambitious People Group", "job_title": "Business Development Manager (Digital Marketing))", "description": "RESEARCH OFFICE\n\nExecutive Officer (PR0256/21-22)\n\nThe Office is looking for a number of meticulous teamplayers. The candidate will perform the following duties:\n\nSupport the University\u2019s research initiatives and enhance its research culture and engagement;\nSupport the development of the interdisciplinary research labs and the hiring of labs\u2019 members;\nDevelop and enhance the existing websites and contribute in various social media platforms and external liaison;\nPromote research-related events/activities, including but not limited to talks, programmes, conferences, tour visits, interviews, symposiums and exhibitions, etc.;\nProvide support in forging industrial/academic partnerships;\nPromote research communication and publicity;\nProvide support in committee work; and\nCarry out ad hoc tasks as assigned.\nApplicants should possess:\n\nA recognised degree in Public Relations & Communications, Language Studies or related disciplines preferred;\nAt least four years of relevant experience;\nAn excellent command of written and spoken English and Chinese (including Putonghua), and relevant editing and multimedia production skills;\nProactivity, maturity, meticulousness, readiness to accept challenges, capability in multitasking and independence at work;\nStrong communication and interpersonal skills, good analytical ability and a strong sense of responsibility;\nAbility to work under tight timelines; and\nProficiency in a wide range of computing applications.\nInitial appointment will be offered on a fixed-term contract of 2 years. Re-appointment thereafter will be subject to mutual agreement.\n\nSalary will be commensurate with qualifications and experience.\n\nApplication Procedure:\n\nApplicants are invited to submit their applications at the HKBU e-Recruitment System (jobs.hkbu.edu.hk). Those not invited for interview 8 weeks after the closing date may consider their applications unsuccessful. Details of the University\u2019s Personal Information Collection Statement can be found at http://hro.hkbu.edu.hk/pics.\n\nThe University reserves the right not to make an appointment for the post advertised, and the appointment will be made according to the terms and conditions then applicable at the time of offer.\n\nClosing date: 27 January 2022", "employment_types": ["Full Time", "Permanent"], "selling_points": ["Digital Marketing", "Business Development", "Account Servicing"], "locations": ["Not Specified"], "categories": ["Sales, CS & Business Devpt", "Business Development", "Marketing / Public Relations", "Marketing - Marketing Communication", "Digital Marketing"], "post_time": "2022-01-18T02:59:48Z", "salary": {"currency": "HKD", "max": 29999, "min": 25000, "period": "monthly", "term": null}, "salary_visible": true, "title_keywords": ["business development manager", "digital marketing"], "responsibilities": ["provide support", "social media platforms", "ad hoc tasks", "develop", "communication", "conferences", "recruitment", "committee work", "editing"], "requirements": {"degrees": ["degree"], "majors": ["related disciplines", "communications"], "languages": ["putonghua", "english", "chinese"], "language_level": ["excellent"], "hard_skills": ["make", "multimedia"], "soft_skills": ["communication", "meticulous", "communication and interpersonal skills", "sense of responsibility"], "languages_combined": [{"language": "putonghua", "language_level": ["excellent"]}, {"language": "english", "language_level": ["excellent"]}, {"language": "chinese", "language_level": ["excellent"]}]}, "experience_required": {"duration": ["at least four years"], "field": ["relevant experience"]}}, {"job_id": "100003009048482", "location_code": "hk", "company": "Hong Kong Baptist University", "job_title": "Executive Officer (PR0256/21-22)", "description": "Key Responsibilities:\nInitiate and implement publicity campaigns to promote the Company's mission and achievements through multiple communication channels\nDevelop, edit and translate a full range of Chinese and English PR materials, such as speeches, press releases, presentations, advertorials, annual reports, success stories of Cyberport companies etc.\nBe the gate keeper of corporate PR messages\u00a0\nHandle media enquiries; maintain good relationship with the media to maximise positive coverage for the Company\nWork with different teams to formulate story angles, develop key messages and talking points for corporate events, industry activities and visits to ensure effective delivery of corporate positioning and messages\u00a0\nSupport senior executives for media activities and public speaking opportunities\nCoordinate with internal and external parties for the production of corporate publications\nConduct research with regards to updates of industry trends and government policies\nEngage the digital tech companies in Cyberport; support the promotion of their innovation and leverage on their work to raise the brand awareness of Cyberport\nPerform other duties as assigned\n\u00a0Requirements:\nBachelor's degree in Languages, Translation, Communications, Journalism or related discipline\nGood qualification in language subjects preferred\nMinimum 8 years of relevant experience across different communications functions, such as media relations, stakeholder\u2019s engagement, copywriting, production of annual report and corporate literature etc.\nStrong connection with local and regional media with proven track record in formulating story angles and conducting media pitching\nSolid experience in planning and implementing integrated communication campaigns across different channels, both the traditional and new media platforms\nGood understanding of the Innovation & Technology industry as well as related government policies an advantage\nExceptional command of written and spoken Chinese and English \u00a0\nSelf-motivated and detail-minded with good project management ability\nDetail-minded and independent with strong analytical mind\nAble to demonstrate problem-solving skills\nTeam player and self-motivated with can-do spirit\nCandidate with less experience will be considered for assistant manager role.\u00a0\n\u00a0\nThe position is on a 2-year fixed-term renewable contract.\n\n\nWe offer competitive package to the right candidate. Interested party please click\u00a0Apply Now\u00a0to apply on or before 11 Feb 2022 in confidence with full resume in Word document, stating present and expected salary, and available date\u00a0and quote the reference.\u00a0\n\nApplicants who do not hear from us by 25 Feb 2022 may assume that their applications are unsuccessful.\n\nFurther information about the Cyberport is available at\u00a0http://www.cyberport.hk\n\n\n", "employment_types": ["Full Time"], "selling_points": ["Support the University\u2019s research initiatives", "Contribute in various social media platforms", "Relevant editing and multimedia production skills"], "locations": ["Kowloon City"], "categories": ["Education", "Others", "Marketing / Public Relations", "Marketing - Marketing Communication", "Public Relations - Event Management"], "post_time": "2022-01-14T06:39:02Z", "salary": {"currency": null, "max": null, "min": null, "period": "monthly", "term": null}, "salary_visible": false, "title_keywords": ["executive officer"], "responsibilities": ["perform other duties", "policies", "internal and external parties", "teams", "coordinate with", "presentations", "maintain good relationship", "communication", "develop", "reports", "conduct research"], "requirements": {"degrees": ["degree", "bachelor"], "majors": ["journalism", "communications"], "languages": ["english", "chinese"], "language_level": [], "hard_skills": ["problem-solving skills", "translation", "project management"], "soft_skills": ["detail-minded", "self-motivated", "independent", "communication", "project management", "analytical mind", "can-do", "problem-solving skills", "team player"], "languages_combined": [{"language": "english", "language_level": []}, {"language": "chinese", "language_level": []}]}, "experience_required": {"duration": ["minimum 8 years"], "field": ["copywriting", "relevant experience", "media", "planning"]}}, {"job_id": "100003009049882", "location_code": "hk", "company": "Hong Kong Cyberport Management Co Ltd", "job_title": "Manager - Corporate Communications (Ref# M-CC220114J)", "description": "One of our clients, a insurance company is currently seeking a suitable candidate to join their elite team.\n\n\n\nCommunications Manager, IT & Digital team (1 year contract)\n\nJob Highlights\n\n3-8 years\u2019 experience in creating written content in different media\nExcellent writing and storytelling skills in English and Chinese\n\nJob Description\n\nThis role develops all internal and external communication from the IT & Digital team,\u00a0including CTO, to ensure the message is consistent and engaging to end users. The role\u00a0facilitates a culture of agile, as well as shares impact and benefits of\u00a0advanced technologies in leading insurance company. The job holder is also responsible to face off external Partners (e.g.\u00a0FinTech companies, organizations) on communication and event management.)\u00a0\u00a0\n\nResponsibilities:\n\nGather updates and stories to prepare regular internal newsletters in IT organization and regular update from CTO\nCollect feedback and data analytics (e.g. internal surveys), and proactively revise communications and content management for different channels and formats\nHost internal events for IT & Digital Teams\nCoordinate with external parties on communication and event managements\nManage content of CTO official Social Media accounts\nDrive TDA\u00a0\n\nRequirements:\n\nBachelor\u2019s degree or above in Information Management, Communication, Public Relations, Business, Journalism or related discipline\n3-8 years\u2019 relevant experience in creating written and video content in different media\nPreferably with technologies, insurance, branding or marketing exposures\nExcellent writing and storytelling skills, preferably with experience in creating script, video brief and storyboard\nProficiency in Chinese word processing, Microsoft Word, Excel, PowerPoint\nGood communication skills in both spoken and written English and Cantonese. Putonghua is desirable\nTeam player with good interpersonal and problem-solving skills\n\nInterested parties, please forward your resume in WORD FORMAT to us by clicking here Computer Recruitment Consultants Ltd or fax to 2528-9091.\u00a0\u00a0 The information provided by candidates will be treated in strict CONFIDENTIAL and will only be used for recruitment purpose\u00a0", "employment_types": ["Full Time", "Permanent", "Contract"], "selling_points": ["Implement publicity campaigns and promote", "Engage the community companies", "To raise the brand awareness"], "locations": ["Pok Fu Lam"], "categories": ["Marketing / Public Relations", "Marketing - Marketing Communication", "Public Relations - Copy-writing", "Public Relations - Event Management"], "post_time": "2022-01-14T09:23:20Z", "salary": {"currency": null, "max": null, "min": null, "period": "monthly", "term": null}, "salary_visible": false, "title_keywords": ["manager"], "responsibilities": ["communication"], "requirements": {"degrees": [], "majors": [], "languages": [], "language_level": [], "hard_skills": [], "soft_skills": [], "languages_combined": []}, "experience_required": {"duration": [], "field": []}}, {"job_id": "100003009050245", "location_code": "hk", "company": "Computer Recruitment Consultants Ltd", "job_title": "Communications Manager, IT & Digital team", "description": "What we offer\u00a0:\n\n\u2022 Competitive package & Performance Bonus\n\u2022 Medical insurance including dental insurance\n\u2022 13+ days Annual Leave\n\u2022 Good working environment &\u00a0Free drinks and snack\n\u2022 Company events\u00a0\uff08Group party, Christmas Party etc.\uff09\n\n\nJob Responsibilities :\n\nDevelop strategic digital marketing initiatives to achieve business targets including but not limited to YouTube, Facebook, Twitter, Instagram, etc online platforms\nResponsible for content marketing including but not limited to brand communication, product features and marketing strategies on various social media platforms\nImplement and optimize online marketing campaign by analyzing customers\u2019 behavior and latest market trends to maximize the usersactivity\nAnalyze and review the performance of social media platforms regularly, ie content, fans count and interactive\nProvide insights and suggestions for improvements and optimizations\n\nJob Requirements :\n\nBachelor degree or above, preferably in advertising, marketing, business or related disciplines\nMinimum 3 years of work experience, experience in Financial industry is an advantage\nPractical experience & familiar with the operation of new media platforms\nExperience in operation team management is an advantage\nFamiliar with KOL marketing and operation. With KOL platforms connections is an advantage", "employment_types": ["Full Time"], "selling_points": ["Degree in Information Management, Communication", "3-8 years exp. in creating written & video content", "Proficiency in English and Chinese word processing"], "locations": ["Not Specified"], "categories": ["Marketing / Public Relations", "Marketing - Marketing Communication", "Public Relations - Copy-writing"], "post_time": "2022-01-14T10:00:29Z", "salary": {"currency": null, "max": null, "min": null, "period": "monthly", "term": null}, "salary_visible": false, "title_keywords": ["manager"], "responsibilities": [], "requirements": {"degrees": [], "majors": [], "languages": [], "language_level": [], "hard_skills": [], "soft_skills": [], "languages_combined": []}, "experience_required": {"duration": [], "field": []}}, {"job_id": "100003009053872", "location_code": "hk", "company": "Deep Sea Network Technology Limited", "job_title": "Digital Marketing Officer", "description": "Responsibilities\n\n\u00a0The successful candidate will be involved in providing PR services to a client portfolio of blue-chip multinationals that represents leaders and fast growing organizations in the corporate, technology and consumer disciplines.\u00a0\n\n\u00a0Requirements\n\nUniversity graduate, preferably in Journalism, Communications or English Language\nWith PR/communications/social and digital media experience is an advantage\nGood understanding of and relations with media\u00a0\u00a0\nExcellent English and Chinese language skills\nSelf-starter,\u00a0quick learner,\u00a0responsible with good working attitude\nProactive, creative, good team spirit with a can-do attitude\nAble and willing to work under pressure\u00a0\n\nInterested parties please apply by clicking \"Apply Now\" together with your resume, cover letter and salary expectation.\n\nAll information collected will be used for recruitment purposes only", "employment_types": ["Full Time", "Permanent"], "selling_points": ["3 years of work experience in Digital Marketing", "Customer & Brand Experience", "Proficient in Data analysis"], "locations": ["Tsim Sha Tsui"], "categories": ["Media & Advertising", "Media Buying", "Marketing / Public Relations", "Marketing - Marketing Communication", "Digital Marketing"], "post_time": "2022-01-17T07:39:56Z", "salary": {"currency": null, "max": null, "min": null, "period": "monthly", "term": null}, "salary_visible": false, "title_keywords": ["digital marketing officer"], "responsibilities": [], "requirements": {"degrees": ["university graduate"], "majors": ["journalism", "communications"], "languages": ["english", "chinese"], "language_level": ["excellent"], "hard_skills": [], "soft_skills": ["good working attitude", "team spirit", "creative", "responsible", "can-do attitude", "quick learner", "proactive", "work under pressure"], "languages_combined": [{"language": "english", "language_level": ["excellent"]}, {"language": "chinese", "language_level": ["excellent"]}]}, "experience_required": {"duration": [], "field": ["pr", "digital media"]}}, {"job_id": "100003009053091", "location_code": "hk", "company": "Timothy Oulton Hong Kong Limited", "job_title": "Sales Executive, Retail", "description": "Have you got a passion for interiors and luxury, the ability to dazzle customers and create an incredible customer experience? This is your chance to be part of a growing award-winning Luxury Retailer!\n\nTimothy Oulton, a global luxury retailer is looking for energetic and self-driven sales professional to join our growing team.\n\nWhat can you expect from us :\n\nAttractive commission\nA chance to build it from the ground up \u2013 test yourself yet be part of an unique global footprint of more than 54 stores globally\nCreative people, unconventional approach to work and everything\nA great culture of highly engaged team & enthusiastic people in a fast-growing SME environment\nStructured product and customer service training from time to time\nAttractive remuneration package including:\n\n15 days Annual Leave in addition to all HK Statutory Holidays\n1 day Birthday Leave\nMedical, Travel & Life Insurance\nHousing Reimbursement\nMonthly Commission and Quarterly Bonus\n\nSales Ambassador - Store location in Central / South Horizon / TST K11 Musea\n\n\n\nResponsibilities\n\nMeet & Greet customers at the Store\nIntroduce products to match the customers's home & personal needs\nAchieve the assigned sales budgets, KPIS and objectives set by the Manager\nManagement of own pipeline, with consistent measured follow up, reporting updates daily, in morning meeting\nDeliver the Timothy Oulton retail experience consistently through\u00a0 exellent customer service and retail theatre as per the defined guidelines.\nComplete understanding and execution of product knowledge and inspiring product demonstration like an expert and as per defined guidelines product and room set training.\nAccurately process customer orders by ensuring personalized service including order follow-ups, updates or complaint handling, building up long lasting business replationships with customers, colleagues and manager with 100% effort\nHandle any customer complaints/returns and provide timely solutions and regular follow-ups and updates.\u00a0\nEnsure the store display is maintained and executed as per defined plan and guidelines.\u00a0Understand and facilitate all operational functions of\u00a0 the company\u2019s Point-of-Sale system\nGrow the customer's database\u00a0\nEnsure personalized service including quotations and order follow-up.\nAttend training meetings; boarding school and seminars as required and instructed by the Store manager.\nSupport team members in any way that is required to ensure that the team delivers exellent results.\n\nEssential skills\n\n\nAt least 1-2 years' sales experience in retail / hospitality / service organization; knowledge of or experience in Ambassador/ furniture/home furnishings will be advantageous\nPassionate to achieve results and grow sales\nAbility to influence and persuade in order to achieve goals\nExcellent interpersonal skills\nAbility to plan and prioritize own time well to maximize effectiveness.\nAnalytical and numerical skills\nGood communication skills with a sense of personal presentation and grooming consistent with global lifestyle retail standards\nOutstanding written and spoken English, and local language skills\nComputer literate, confident with Microsoft package\n\nPersonal Attributes\n\nCustomer focused\nA flexible attitude to working time; willing to work weekends and later evenings as per retail hours\nHigh energy levels with a desire to succeed\nStrong level of integrity\nA \"can and will do\" attitude\nSelf-starter and motivated\nPassion for the products and the brand\nIf you are passionate about Sales and customer services, drop in your application and have a chat!\n\n\nMeanwhile, don\u2019t forget to visit us on http://www.timothyoulton.com for a dazzling experience!", "employment_types": ["Full Time", "Part Time", "Permanent"], "selling_points": ["15 days AL in addition to all Public Holiday", "Medical, Travel & Life Insurance", "Monthly Commission and Quarterly Bonus"], "locations": ["Southern Area"], "categories": ["Hospitality / F & B", "Hospitality / Hotel Services", "Marketing / Public Relations", "Marketing - Marketing Communication", "Sales, CS & Business Devpt", "Retail Sales"], "post_time": "2022-01-17T05:44:57Z", "salary": {"currency": null, "max": null, "min": null, "period": "monthly", "term": null}, "salary_visible": false, "title_keywords": ["sales executive"], "responsibilities": ["budgets", "management", "reporting", "customer complaints", "guidelines", "customer services", "communication", "customer service", "plan", "database", "sme", "kpis", "insurance"], "requirements": {"degrees": [], "majors": [], "languages": ["english"], "language_level": [], "hard_skills": ["numerical skills"], "soft_skills": ["focused", "customer service", "passionate about", "confident", "integrity", "interpersonal skills", "creative", "presentation", "passionate", "communication skills", "unique", "prioritize", "enthusiastic", "energetic", "driven", "flexible", "passion for", "timely", "motivated", "inspiring", "structured"], "languages_combined": [{"language": "english", "language_level": []}]}, "experience_required": {"duration": ["at least 1-2 years"], "field": ["retail", "customer service"]}}, {"job_id": "100003009050905", "location_code": "hk", "company": "Sun Cupid Technology (HK) Ltd", "job_title": "Branding and Media Manager", "description": "Responsibilities:\n\nDerive, Implement, and raise brand awareness and strengthen the brands marketing strategies campaigns to achieve business goal and marketing objectives mainly in USA.\nResponsible for market research, analysis sales data, monitor brand performance and market trends\nDevelop and grow effective digital marketing and online media strategies within social communities via livestreams, affiliate programs and assist in influencers management in USA.\nOwn and manage official Shop platforms including FB, IG, and etc.\nAnalyze online data, social media performance, audience behavior and conversion funnel to provide effective recommendations and insights\nStay up-to-date with the latest digital and social media trends. Adopt new innovations as appropriate and market best practices.\nMaintain and monitor daily operations of multimedia contents\nDevelop, identify and implement different kinds of marketing activities to obtain fans growth, viral topics and gain customers engagement\nCreate innovative and attention-grabbing content for brand website, social media platforms, including but not limited to Facebook and Instagram\nEnsure and evaluate all content and writing meets the brand communication standards\n\nRequirements:\n\nDegree holder\u00a0in business/marketing related area\nUnderstanding of Digital Media buying, including IO, DSP, social media, Search in USA and other country\nStrong analytical and Gathering data skills, highly numerate and comfortable with data processing and interpretation.\nSolid and proven digital marketing Experience with successful campaigns, brand building and positioning.\nWith 5 years\u2019 work experience in Product Marketing/Brand Management/PR/Digital Marketing/Market Research, with branding in digital marketing and social media platforms\nAnalyze and build brand equity through a consumer centric mindset\nLocalize global/international plans and strategies for local success\nTranslate brand elements into plans and go-to-market strategies with campaigns across on and off-line platforms.\nMeasure and report performance of all marketing campaigns and assess ROI and KPIs.\nMonitor and oversee new and ongoing marketing and advertising market trends, research consumer markets and competitors' activities.\nMonitor product distribution and consumer reactions.\nFollow and promote a test-and-learn culture to constantly find new opportunities for growth and optimization.\nDevelop and manage brand position,\u00a0sales, and marketing strategies\u00a0for the assigned brand\nStrong sense for lifestyle trends including cell phone and consumer electronics\nHave a good network of online media partners, influencers, KOLs, bloggers in oversea such as USA.", "employment_types": ["Full Time", "Permanent"], "selling_points": [], "locations": ["Lai Chi Kok"], "categories": ["Marketing / Public Relations", "Management", "Marketing - Brand / Product Management", "Marketing - Marketing Communication"], "post_time": "2022-01-14T11:43:10Z", "salary": {"currency": null, "max": null, "min": null, "period": "monthly", "term": null}, "salary_visible": false, "title_keywords": ["manager"], "responsibilities": ["social media", "management", "marketing strategies", "raise brand awareness", "data", "analysis", "social media platforms", "monitor", "market research", "website", "develop", "evaluate", "communication", "daily operations", "maintain", "digital marketing", "contents", "facebook"], "requirements": {"degrees": ["degree holder"], "majors": ["business", "marketing"], "languages": [], "language_level": [], "hard_skills": ["go", "processing", "io"], "soft_skills": ["consumer centric"], "languages_combined": []}, "experience_required": {"duration": ["5 years"], "field": ["social media", "pr", "management", "brand", "market research", "marketing", "digital marketing"]}}, {"job_id": "100003009051779", "location_code": "hk", "company": "The Great Eagle Group of Companies", "job_title": "Multi-media Designer", "description": "Responsibilities:\n\nPlan and execute design but not limited to photo retouch, design layout and other marketing materials\nDevelop creative idea and concepts to various platform including digital positing with social media\nWork closely with internal and external stakeholders for the executive of projects\nCoordinate and manage progress tracking, resources and budget management\nHandle other ad hoc projects assigned\n\nRequirements:\n\nDegree holder in Multimedia Design, Arts, Visual Arts or any related disciplines\nMinimum 3 years\u2019 relevant working experience, preferably gained in advertising or branding agency with digital focus experience\nPositive, true team player, open-minded and a strong sense of responsibility are essential.\nProficient in Adobe Creative Suite, Photoshop, Illustrator and InDesign\nHands-on experience in UX design software such as Adobe XD, InVision and UXPin\nGood presentation, interpersonal and communication skills\nGood team player and self-motivated\nGood command of both written and spoken English and Chinese\n\nSalary and benefits will be commensurate with qualifications and experience.\u00a0 Interested parties, please send a full resume with present and expected salary, and date available to The Human Resources Department, 32/F., Great Eagle Centre, 23 Harbour Road, Wan chai, Hong Kong or e-mail to US.\u00a0(Please quote the reference no. on the envelope and the covering letter.)\n\nTo know more about us, please visit our website at http://www.greateagle.com.hk.\n\nWe are an equal opportunity employer and welcome applications from all qualified candidates.\n\nPersonal data collected will be treated in strict confidence and used only for recruitment-related purpose. Applicants who have not heard from us within four weeks may consider their applications unsuccessful. All personal data will be destroyed after 12 months.", "employment_types": ["Full Time", "Permanent"], "selling_points": ["Plan and execute design for marketing materials", "Digital positing", "Proficient in Adobe Creative Suite, Photoshop etc."], "locations": ["Wan Chai"], "categories": ["Design", "Multi-media", "Marketing / Public Relations", "Marketing - Marketing Communication", "Digital Marketing"], "post_time": "2022-01-17T01:04:00Z", "salary": {"currency": null, "max": null, "min": null, "period": "monthly", "term": null}, "salary_visible": false, "title_keywords": ["designer"], "responsibilities": ["social media", "management", "budget", "design", "develop", "coordinate", "photo retouch", "ad hoc projects", "plan", "marketing materials", "tracking"], "requirements": {"degrees": ["degree holder"], "majors": ["multimedia design", "related disciplines"], "languages": ["english", "chinese"], "language_level": ["good command"], "hard_skills": ["adobe xd", "indesign", "illustrator", "multimedia", "focus", "adobe creative suite", "photoshop"], "soft_skills": ["communication skills", "good team player", "self-motivated", "sense of responsibility", "interpersonal", "open-minded", "hands-on", "team player", "focus", "creative", "presentation", "positive"], "languages_combined": [{"language": "english", "language_level": ["good command"]}, {"language": "chinese", "language_level": ["good command"]}]}, "experience_required": {"duration": ["minimum 3 years"], "field": ["advertising", "agency", "relevant working experience", "design", "digital"]}}, {"job_id": "100003009051419", "location_code": "hk", "company": "", "job_title": "Marketing Manager", "description": "Responsibilities:\n\nLead the Marketing Team to execute marketing activities and roadmaps\nDevelop and execute marketing strategies to promote campaigns including but not limited to build relationships with agency, promoting products and services via e-marketing and social media channels\nOptimize digital marketing and revamp corporate website marketing content\nBuild close relationships with business partners and insurance agencies\nEstablish effective marketing direction and strategies for the brand\nPerform any ad-hoc duties as assigned\nRequirements:\n\nBachelor degree with major in Marketing or related discipline\nAt least 5+ years of solid experience in Marketing Management / Digital Marketing / Public Relations\nPrior experience of working at Healthcare / Servicing Industry, B2B / B2C business will be advantageous\u00a0\nExcellent leadership, interpersonal and communication skills and teamwork will be a definite advantage\u00a0\nStrong in digital marketing and social media\nGood command in both spoken and written English and Chinese\nWe offer competitive remuneration package to right candidate.\u00a0 (Data collected will be used solely for the purpose of recruitment.)\nInterested candidates, please contact us at 91742871 for company details before applying.", "employment_types": ["Full Time", "Permanent"], "selling_points": [], "locations": ["Central & Western Area"], "categories": ["Marketing / Public Relations", "Marketing - Brand / Product Management", "Marketing - Marketing Communication", "Digital Marketing"], "post_time": "2022-01-15T15:14:29Z", "salary": {"currency": null, "max": null, "min": null, "period": "monthly", "term": null}, "salary_visible": false, "title_keywords": ["marketing manager"], "responsibilities": ["social media", "revamp", "marketing strategies", "website", "develop", "digital marketing", "ad-hoc duties", "insurance"], "requirements": {"degrees": ["degree", "bachelor"], "majors": ["marketing"], "languages": ["english", "chinese"], "language_level": ["good command"], "hard_skills": [], "soft_skills": ["communication skills", "teamwork", "leadership", "interpersonal"], "languages_combined": [{"language": "english", "language_level": ["good command"]}, {"language": "chinese", "language_level": ["good command"]}]}, "experience_required": {"duration": ["at least 5+ years"], "field": ["healthcare", "management", "public relations", "servicing industry", "marketing", "digital marketing", "business"]}}, {"job_id": "100003009047995", "location_code": "hk", "company": "KPMG Executive Recruitment Limited", "job_title": "Head of Public Relations", "description": "The Roles\n\nCoordinate, execute and support a variety of corporate and marketing communications activities, public relations and promotion initiatives;\nDrive and deliver a range of marketing communication materials, including but not limited to speeches, press release and media kit, corporate collaterals and enewsletter, editorial and publishing projects, marketing and social media content, surveys and research, etc.;\nMonitor and uphold branding and corporate identity of HKDC and its affiliated programmes;\nManage corporate assets including printed collaterals, digital, visual and video content and online platforms e.g. website, social media channels and email database;\nWork with internal and external parties for the production of HKDC Annual Report, publications and marketing collaterals;\nEffectively handle the logistics and coordination of corporate visits and and provide onsite support to corporate events / activities;\nWork with internal stakeholders and external parties and vendors on a variety of HKDC initiatives;\nManage the overall communication plan and logistics of the corporate membership and partnership programmes; and\nCarry out other ad hoc projects and duties as assigned.\n\n\u00a0\u00a0Requirements\n\nUniversity graduate in Marketing, Communications, Journalism or Translation;\nMinimum 5 years of relevant work experience in marketing, corporate communications or public relations;\nExcellent copywriting and translation skills in both English and Chinese, with fluent spoken English, Cantonese and Putonghua;\nDigital savvy, creative and passionate about communications, with sound knowledge of different social media and communications platforms and trends;\nA self-motivated team-player with strong attention to detail; and\nMature, outgoing multi-tasker with good organisational and project management skills.\n\n\nInterested parties are invited to apply by sending your resume with full details of education, work experience, current & expected salary, contact telephone number and earliest available date to the Human Resources Office, Hong Kong Design Centre, Unit 602, 6/F, Mill 5, The Mills, 45 Pak Tin Par Street, Tsuen Wan or by clicking \u201cApply Now\u201d or email to:\u00a0hr[@]hkdesigncentre.org\u00a0on or before 28 January 2022. HKDC reserves the right not to make appointment for the post(s) advertised. Only short-listed candidates will be notified. All information received will be kept in strict confidence for six months and data will only be used for recruitment purpose.", "employment_types": ["Full Time"], "selling_points": ["Degree holder with Marketing, Communications etc.", "12+years of exp in corporate communications", "In charge corporate communication&PR matters"], "locations": ["Not Specified"], "categories": ["Marketing / Public Relations", "Marketing - Direct Marketing", "Marketing - Marketing Communication"], "post_time": "2022-01-14T04:33:34Z", "salary": {"currency": null, "max": null, "min": null, "period": "monthly", "term": null}, "salary_visible": false, "title_keywords": [], "responsibilities": ["data", "internal and external parties", "marketing collaterals", "website", "external parties", "design", "communication", "social media content", "database", "plan", "monitor", "logistics", "visual", "report", "social media", "contact", "coordinate", "project management", "ad hoc projects", "recruitment", "coordination"], "requirements": {"degrees": ["university graduate"], "majors": ["journalism", "marketing", "communications"], "languages": ["cantonese", "putonghua", "english", "chinese"], "language_level": ["excellent", "fluent"], "hard_skills": ["translation", "project management", "wan", "make"], "soft_skills": ["outgoing", "self-motivated", "confidence", "team-player", "project management skills", "mature", "communication", "coordination", "attention to detail", "creative", "passionate about"], "languages_combined": [{"language": "cantonese", "language_level": ["excellent", "fluent"]}, {"language": "putonghua", "language_level": ["excellent", "fluent"]}, {"language": "english", "language_level": ["excellent", "fluent"]}, {"language": "chinese", "language_level": ["excellent", "fluent"]}]}, "experience_required": {"duration": ["minimum 5 years"], "field": ["public relations", "design", "education", "marketing", "human resources"]}}, {"job_id": "100003009051103", "location_code": "hk", "company": "Hong Kong Design Centre Limited", "job_title": "Senior Project Executive \u2013 Marketing Communications", "description": "We are inviting high caliber to join us for an exciting career opportunity and be part of a company that believes in innovation and sustainability.\n\nResponsibilities:\n\n\n\nMultimedia production\u00a0\u2013 Develop and execute visual display such as\u00a0video, photos, graphic designs, presentation slides, webpage layouts etc.; assist in setting design directions and storyboards\nSocial media \u2013\u00a0Manage Group-level corporate social media accounts including but not limited to Facebook, Instagram, LinkedIn and YouTube; monitor channel performance; assist in content planning to drive engagement\nPR support\u00a0\u2013 Support routine media monitoring; maintain newsroom content\nKnowledge management \u2013\u00a0Maintain libraries of corporate materials and information to uphold good housekeeping and promote productivity\n\nRequirements:\n\n\nDegree or higher diploma preferably in design, creative media, communications, Fine arts, language or related disciplines\nAt least 1 year of related working experience, candidates with more experiences will be considered as Officer, Corporate Communications\nExperience preferred in Adobe suite (Premiere Pro, Photoshop, Illustrator) or other visual editing software\nFluent in spoken English, Mandarin and Cantonese\nGood command on written English and Chinese (Simplified and Traditional)\nAble to travel for business occasionally to mainland China and southeast Asia\nKeen eyes for aesthetics and attentive to details\nStrong sense of time management and priority\n\nLearn about Esquel and its eCulture values at\u00a0www.esquel.com\n\nData collected will be used for recruitment purpose only and will be kept for 24 months.\n\nAll applications will be treated in strict confidence.", "employment_types": ["Full Time"], "selling_points": [], "locations": ["Tsuen Wan Area"], "categories": ["Media & Advertising", "Editorial / Journalism", "Marketing / Public Relations", "Marketing - Marketing Communication", "Public Relations - Copy-writing"], "post_time": "2022-01-15T02:17:27Z", "salary": {"currency": null, "max": null, "min": null, "period": "monthly", "term": null}, "salary_visible": false, "title_keywords": ["senior project executive"], "responsibilities": ["social media", "management", "housekeeping", "monitoring", "graphic designs", "monitor", "design", "develop", "planning", "maintain", "visual", "facebook", "storyboards"], "requirements": {"degrees": ["diploma", "degree"], "majors": ["creative media", "fine arts", "design", "related disciplines", "communications"], "languages": ["cantonese", "english", "chinese", "mandarin"], "language_level": ["good command", "fluent"], "hard_skills": ["illustrator", "visual editing", "adobe", "premiere pro", "photoshop"], "soft_skills": ["confidence", "creative", "attentive to details", "keen", "time management"], "languages_combined": [{"language": "cantonese", "language_level": ["fluent"]}, {"language": "english", "language_level": ["good command", "fluent"]}, {"language": "chinese", "language_level": ["good command"]}, {"language": "mandarin", "language_level": ["fluent"]}]}, "experience_required": {"duration": ["at least 1 year"], "field": ["related", "editing"]}}, {"job_id": "100003009045316", "location_code": "hk", "company": "Esquel Enterprises Limited", "job_title": "Assistant Officer / Officer, Corporate Communications", "description": "Team Description\n\nThe Communication Control Group (CCG) is a global function residing in the distribution business of J.P. Morgan Asset Management. Its mission is to deliver a framework and service that empowers the entire global asset management business to generate and disseminate regulatory compliant communications in the most effective and timely manner to our retail, intermediary and institutional clients. To achieve this, the group needs to actively engage with other functions across the distribution business: marketing, sales and client services, and the product desks. The team also retains a close partnership with the compliance organization as well as the CCG teams in US and EMEA.\n\nAs part of APAC CCG, the CCG member based in Japan acts in a role of Marketing Compliance taking the lead to safeguard the business by providing advice and guidance in preparing compliant communications in accordance with both the external rules and regulations and the internal firm-wide policies and the control mechanism. The role also assists on the marketing related governance topics to help facilitate effective and prudent practices that contribute to the long-term success of the business.\n\nThe role will have a reporting line to Head of APAC CCG; and will partner closely amongst teams across APAC and Global.\n\nJob Description\n\nAs a member of the APAC CCG you will be responsible for working with the distribution business and product desks to ensure their client communications are subject to the appropriate, and most efficient, levels of control and oversight. Youwill need a thorough understanding of marketing regulations, a strong sense of collaboration and conviction, and core communication skills in order to clearly and concisely guide the business. The role will have a regional coverage and review marketing materials disseminated predominantly in Japan and some of the markets in Asia Pacific.\n\nYour Key Responsibilities Will Include\n\nReview of medium and high risk client communications/marketing materials for the retail, intermediary and institutional client base such as print ad, client presentations, brochures, digital properties and new communication templates.\nPro-active engagement in the review of globally distributed client communications\nOversight of low risk materials self-certified by the business\nProvide the business with day-to-day up-front content advice\nInvolvement with the preparation and delivery of marketing training across the business.\nHelp ensure that all areas of the business have appropriate policies and procedures in place\nRegulatory filing as required\nMaintain an up to date knowledge of the regulatory environment and an awareness of the evolving mediums and methods used for marketing activities\nQualification\n\nEssential Experience / Knowledge / Competencies\n\nGood academic or professional qualifications\nProven experience in a similar role either within the business, legal, compliance, controls department or within a regulator in relation to asset management products and services\nExperience reviewing social media and digital communications\nExperience working with a system based communication review process\nClear and concise communicator with strong collaboration skills\nSelf-starter with the ability to multi-task and priorities workload\nStrong attention to detail and quality\nOrganized and efficient working well under pressure and within tight deadlines\nAttention to detail and high level of accuracy and conviction are essential\nFluent in English, and fluent in Mandarin would be a plus\nFluent in Japanese on native level is essential and a holder of Internal Control Officer or Sales Representative Officer under JSDA (Japan Securities Dealers Association) rules would be a plus\nDesirable Experience / Knowledge\n\nA practical working knowledge of all asset classes and financial instruments\nExperience working with the Documentum workflow tool\nExperience working within a large global organization\nWe recognize that our people are our strength and the diverse talents they bring to our global workforce are directly linked to our success. We are an equal opportunity employer and place a high value on diversity and inclusion at our company. We do not discriminate on the basis of any protected attribute, including race, religion, color, national origin, gender, sexual orientation, gender identity, gender expression, age, marital or veteran status, pregnancy or disability, or any other basis protected under applicable law. In accordance with applicable law, we make reasonable accommodations for applicants' and employees' religious practices and beliefs, as well as any mental health or physical disability needs.\n\nInterested parties please click \u201cApply Now\u201d to apply job.\n\nAll applications applied through our system will be delivered directly to the advertiser and privacy of personal data of the applicant will be ensured with security.", "employment_types": ["Full Time", "Permanent"], "selling_points": ["Multimedia production", "Social media & PR support", "Premiere Pro, PS, Illustrator"], "locations": ["Wan Chai"], "categories": ["Design", "Multi-media", "Marketing / Public Relations", "Marketing - Marketing Communication", "Public Relations - Copy-writing"], "post_time": "2022-01-13T07:36:25Z", "salary": {"currency": null, "max": null, "min": null, "period": "monthly", "term": null}, "salary_visible": false, "title_keywords": ["assistant officer", "officer"], "responsibilities": ["regulations", "guidance", "control", "reporting", "social media", "policies", "compliance", "teams", "review", "presentations", "procedures", "communication", "quality", "client base", "maintain", "marketing materials", "internal control", "asset management"], "requirements": {"degrees": [], "majors": [], "languages": ["japanese", "english", "mandarin"], "language_level": ["native", "fluent"], "hard_skills": ["plus", "professional qualifications", "presentations", "make", "internal control"], "soft_skills": ["efficient", "communication skills", "organized", "multi-task", "under pressure", "responsible", "timely", "communication", "clear", "diverse", "thorough", "attention to detail", "pro-active", "communicator"], "languages_combined": [{"language": "japanese", "language_level": ["fluent", "native"]}, {"language": "english", "language_level": ["fluent"]}, {"language": "mandarin", "language_level": ["fluent"]}]}, "experience_required": {"duration": [], "field": ["social media", "legal", "compliance", "business", "digital", "asset management"]}}, {"job_id": "100003009047121", "location_code": "hk", "company": "JPMorgan Chase Bank, N.A.", "job_title": "APAC Communication Control Group, Communications Manager, Vice President /", "description": "Work closely with commercial teams to plan and execute marketing initiatives to support business development and brand building in North Asia\nOperate and manage local digital touch points including local website, social media and e-publications (WeChat, LinkedIn, client newsletter, etc.)\nOptimize digital touch points\u2019 performance in terms of content planning vs. publishing schedule\nContent management:\n\u00a0 \u00a0 \u00a0 \u00a0 \u00a0 \u00a0 \u00a0 \u00a0- Coordinate with professional teams for local content collection on regular basis\n\u00a0 \u00a0 \u00a0 \u00a0 \u00a0 \u00a0 \u00a0 \u00a0- Able to write up non-technical social media short pieces, such as event review\n\u00a0 \u00a0 \u00a0 \u00a0 \u00a0 \u00a0 \u00a0 \u00a0- Able to translate or localize Group insights article\n\nProactively identify digital marketing tools or channels best suit for business development or branding purpose\nManaging events in various scales and formats. Capable of the end-to-end event arrangement including internal and external invitation, webinar/digital platforms operation, communication and facilitation with external event partners, logistics for physical events, leads collection & result tracking, etc.\nWork together on brand merchandise on seasonal basis, especially for HK market\nCoordinate with Group marketing based in UK or US for country level implementation of global projects, including branding and marketing collateral localization and local communications\nAny projects or tasks as assigned by supervisor located in Shanghai\nRequirements:\n\nDegree in Marketing, Business or related discipline\nWith at least 3-5 years of relevant experience on marketing communications\nProfessional services, financial services or B2B marketing background is preferred\nKnowledge and experiences on WeChat\u00a0Corporate\u00a0Account\u00a0management/operation is a must\nStrong in written and spoken English and Chinese (including Mandarin)\nDetail-oriented and responsive with efficient delivery, quick learning capability, multitasking capability, proactive and can-do working attitude\nGood interpersonal & communication skills\nComfortable working as an individual contributor with reporting line to supervisor located in Shanghai\nGood at MS Office and virtual collaboration tools (e.g. Teams)\nWe offer an attractive package with benefits for the right candidate and long term career prospect.\n\n\nPersonal data collected will be used for recruitment purpose only.\n\nOnly shortlisted candidates will be contacted and all applications will be treated in strict confidence.", "employment_types": ["Full Time"], "selling_points": [], "locations": ["Not Specified"], "categories": ["Banking / Finance", "Financial Services", "Others", "Marketing / Public Relations", "Marketing - Marketing Communication"], "post_time": "2022-01-14T02:22:58Z", "salary": {"currency": null, "max": null, "min": null, "period": "monthly", "term": null}, "salary_visible": false, "title_keywords": ["vice president", "manager"], "responsibilities": ["social media", "management", "tracking", "reporting", "review", "teams", "website", "coordinate with", "implementation", "communication", "digital marketing", "schedule", "plan", "logistics", "planning"], "requirements": {"degrees": ["degree"], "majors": ["business", "marketing"], "languages": ["english", "chinese", "mandarin"], "language_level": [], "hard_skills": ["vs", "ms office", "wechat"], "soft_skills": ["efficient", "communication skills", "capable", "detail-oriented", "communication", "learning", "can-do", "proactive", "responsive", "interpersonal"], "languages_combined": [{"language": "english", "language_level": []}, {"language": "chinese", "language_level": []}, {"language": "mandarin", "language_level": []}]}, "experience_required": {"duration": ["at least 3-5 years"], "field": ["marketing communications", "operation", "relevant experience", "account management"]}}, {"job_id": "100003009048194", "location_code": "hk", "company": "Vistra (Hong Kong) Limited", "job_title": "Assistant Manager, Marketing (Commercial North Asia)", "description": "Do you think outside the box? Are you a dynamic storyteller who loves beauty products and is\u00a0passionate about digital marketing? You may be the person we are looking for!\n\nThe successful candidate will be responsible for managing the company\u2019s media platforms such as, Facebook, Instagram, Tiktok, Youtube and Naver. You will be able to learn how to use intelligence tool like Hootsuite and OneSignal to manage the platforms better.\n\n\u00a0Roles and responsibilities:\n\nManage campaigns across all social media platforms\u00a0to achieve designated business goals\nResponsible for content\u00a0creation and storytelling on social media channels\u00a0to produce creative, well written, rich and engaging social media content to maximize ROI and increase brand awareness\nDay-to-day tasks includes performance report consolidation, postings on Social Media and app push scheduling\nManage partnership with KOLs, including incentive offering, posting arrangement and payment settlement\n\nRequirements:\n\nExperience in media marketing with 1-2 years relevant experiences\nFresh graduates are also welcome\nBachelor\u2019s degree in communications, marketing or related field\nUnderstanding of APAC markets such as Hong Kong, Australia, New Zealand, Singapore is preferred\nExcellent written and spoken English and\u00a0Traditional Chinese, particularly in creating content for Asian markets\nA passion in digital marketing and beauty e-commerce\nHigh project management skills with attention to detail and ability to multi-task\nA good team player", "employment_types": ["Full Time", "Permanent"], "selling_points": ["Marketing function for Professional Service firm", "Digital marketing and webinar experience required", "Regional marketing exposure provided"], "locations": ["Causeway Bay"], "categories": ["Marketing / Public Relations", "Marketing - General / Support", "Marketing - Marketing Communication", "Digital Marketing"], "post_time": "2022-01-14T05:49:19Z", "salary": {"currency": null, "max": null, "min": null, "period": "monthly", "term": null}, "salary_visible": false, "title_keywords": ["assistant manager,"], "responsibilities": ["social media", "business goals", "social media platforms", "scheduling", "payment", "social media content", "maximize roi", "report"], "requirements": {"degrees": ["degree", "bachelor"], "majors": ["marketing", "communications"], "languages": ["english", "chinese"], "language_level": ["excellent"], "hard_skills": ["project management", "e-commerce"], "soft_skills": ["good team player", "multi-task", "passion in", "project management skills", "attention to detail"], "languages_combined": [{"language": "english", "language_level": ["excellent"]}, {"language": "chinese", "language_level": ["excellent"]}]}, "experience_required": {"duration": ["1-2 years"], "field": ["marketing", "media"]}}, {"job_id": "100003009052072", "location_code": "hk", "company": "Strawberry Cosmetics (Services) Limited", "job_title": "Digital Marketing Executive \u2013 Social Media", "description": "Responsibilities\n\nInitiate and implement corporate communications strategies to build brand awareness\nPrepare materials for globalized campaigns\nPrepare press releases, and corporate materials, including presentations, brochures,\u00a0web content, newsletters, etc\nCopywriting for both print and digital\u00a0marketing collaterals\nOrganize and coordinate press conferences\nEstablish and maintain good relationship with media\nCoordinate and liaise with KOL and influencers\u00a0to promote all brands for the group\nFollow up shooting or video-taking\nConduct research and collect\u00a0materials for joining external company awards\nUndertake ad hoc projects as assigned\n\nRequirements:\n\nDegree in Language / Translation / Journalism / PR / Communications Marketing or relevant disciplines\n3+ years of relevant experience\nExperience in media relations and editor/reporter is preferred\nGood team player, energetic and passionate\nExcellent command of written English and Chinese is essential\nGood communication and interpersonal skills\nCandidates with less experience will be considered as Assistant Corporate Communications Officer\u00a0\nFresh graduates are also welcome\u00a0 \u00a0 \u00a0\nImmediate availability is highly preferred\n\n\u00a0We Offer:\n\n\u00a0 \u00a05-day work week\n\u00a0 \u00a0Competitive Salary Package\n\u00a0 \u00a013 months' Guaranteed Salary\n\u00a0 \u00a0Performance Incentives\n\u00a0 \u00a0Group Medical Scheme\n\u00a0 \u00a0Birthday Leave\n\u00a0 \u00a0Free Lunch\n\u00a0 \u00a0Energetic & Dynamic Culture\n\n\nInterested parties, please send your detailed resume, availability, present and expected salary to Human Resources Department by clicking \u201cApply Now\u201d.\n\nPersonal data collected will be used for recruitment purpose only.", "employment_types": ["Full Time", "Permanent"], "selling_points": [], "locations": ["Shau Kei Wan"], "categories": ["Marketing / Public Relations", "Marketing - Direct Marketing", "Marketing - Marketing Communication", "Digital Marketing"], "post_time": "2022-01-17T02:01:58Z", "salary": {"currency": null, "max": null, "min": null, "period": "monthly", "term": null}, "salary_visible": false, "title_keywords": ["digital marketing executive"], "responsibilities": ["presentations", "maintain good relationship", "coordinate", "conferences", "digital marketing", "ad hoc projects", "liaise with", "conduct research"], "requirements": {"degrees": ["degree"], "majors": ["journalism", "marketing", "communications"], "languages": ["english", "chinese"], "language_level": ["excellent"], "hard_skills": ["translation"], "soft_skills": ["passionate", "good team player", "energetic", "communication and interpersonal skills"], "languages_combined": [{"language": "english", "language_level": ["excellent"]}, {"language": "chinese", "language_level": ["excellent"]}]}, "experience_required": {"duration": ["3+ years"], "field": ["editor", "reporter", "relevant experience", "media"]}}, {"job_id": "100003009046106", "location_code": "hk", "company": "Uni-China (Business) Management Limited", "job_title": "Corporate Communications Officer/ Assistant Corporate Communications Officer", "description": "You love challenges, you don\u2019t follow rules but create them, you have a million\u00a0ideas and wish to bring them alive, you want to make a difference and most of\u00a0all you want to work at a place that inspires. If truly you are such a rebellion,\u00a0Networld wants you!\n\nNetworld Technology is a highly celebrated online technology innovator in\u00a0Hong Kong, we facilitate human and business interaction through our 3\u00a0famous online portals: Discuss, Uwants and Price, each of them an awards\u00a0winning leader in the industry.\n\nWe all know the digital world is an ever-changing place, and we strive to\u00a0improve our products in every possible way. If you are tech-savvy, creative\u00a0and passionate, join us at Networld on this fun, challenging and exhausting\u00a0journey!\n\nTo know more about us, you can click the links below:\n\nNetworld\nWebsite:\u00a0https://www.networld.hk/\nFacebook Page:\u00a0https://bit.ly/2pF9Dov\n\nDiscuss\nWebsite:\u00a0https://www.discuss.com.hk/\nFacebook Page:\u00a0https://bit.ly/1XuiCnX\n\nUwants\nWebsite:\u00a0https://www.uwants.com/\nFacebook Page:\u00a0https://bit.ly/1Mt4cUw\n\nPrice\nWebsite:\u00a0https://www.price.com.hk/\nFacebook Page:\u00a0https://bit.ly/1VkYTJx\n\nYour role within our TEAM:\n\nHandle customer inquiries and service requests in a good manner.\nCommunicate with internal parties to suggest the improvements, analyze the problems and resolve customer report issues\nManaging the daily operations of company products, marketing campaigns, contents and copy-writing\nSupporting the marketing team for content creations including articles, social media, eNews, app push and etc.\nInitiate research, establish any potential marketing campaigns with potential partners to achieve company\u2019s goal and objectives\nWork as backup to other team members as needed\n\n\nSkills and traits of you:\n\nHigher Diploma or above, preferable in Marketing, Business or other related subjects\nMinimum 1 year relevant experience,\u00a0fresh graduate will also be considered\nSound knowledge in major social media platforms\nGood command of both written and spoken English and Chinese\nExcellent communications and interpersonal skills\nSelf-motivated and able to work independently and under pressure\nGood Chinese and English typing (30-40 wpm or above)\n\nBe part of us, you will enjoy:\n\nDiscretionary Bonus\n5-day Work Week\nFlexible Working Hour\nBirthday Leave\nBirthday Gift\nMedical Insurance\nMonthly Birthday Party\nTeam Event and Team Building Activities\nFree Snack & Beverage\nHappy and dynamic environment\nWearing Casually\n\nInterested parties, please click \"Apply now\" to submit your resume with the\u00a0availability and expected salary\u00a0to us.\n\nWorking Location:\u00a0Shatin (5 minutes from Shek Mun MTR station)\n\n(Personal data collected will be treated in the strictly confidential and only be used for recruitment related purpose.)", "employment_types": ["Full Time", "Permanent"], "selling_points": ["Corporate Communications / PR", "English and Chinese Copywriting", "13 months' Guaranteed Salary + Bonus"], "locations": ["Lai Chi Kok"], "categories": ["Marketing / Public Relations", "Marketing - Brand / Product Management", "Marketing - Marketing Communication", "Public Relations - Copy-writing"], "post_time": "2022-01-13T09:38:35Z", "salary": {"currency": null, "max": null, "min": null, "period": "monthly", "term": null}, "salary_visible": false, "title_keywords": ["corporate communications officer", "assistant corporate communications officer"], "responsibilities": ["social media", "ideas", "customer inquiries", "social media platforms", "website", "daily operations", "contents", "communicate with internal parties", "marketing campaigns", "facebook", "insurance", "report"], "requirements": {"degrees": ["higher diploma or above", "fresh graduate"], "majors": ["business", "marketing"], "languages": ["english", "chinese"], "language_level": ["good command", "good"], "hard_skills": ["fun", "typing", "make", "goal", "dynamic", "facebook"], "soft_skills": ["passionate", "flexible", "self-motivated", "work independently", "under pressure", "dynamic environment", "interpersonal skills", "creative"], "languages_combined": [{"language": "english", "language_level": ["good command"]}, {"language": "chinese", "language_level": ["good", "good command"]}]}, "experience_required": {"duration": ["minimum 1 year"], "field": ["relevant experience"]}}, {"job_id": "100003009056147", "location_code": "hk", "company": "Networld Technology Limited", "job_title": "Product Operation Coordinator", "description": "Company Profile\nOur client is a well-established Hong Kong Listed Company with multiple businesses across the globe. They are now looking for a Digital Marketing Manager to join their team to cope with the digital advancement.\u00a0\n\n\nJob Responsibilities\n\nPlan and execute marketing content and campaigns, including social media content, copywriting, website ecommerce and app campaigns\nDevelop digital marketing strategies and on brand campaigns to drive revenue\u00a0\nFormulate\u00a0online strategy for build branding and marketing planning\nResponsible for reporting, analytics, dashboards and provide insights for improving digital key metrics\nLiaise with external agencies to optimize go-to-market strategy and sustain growth for across regions\n\nRequirements\n\nBachelor\u2019s Degree in Marketing, Business Management or related fields\nAt least 3-year of relevant experience, especially in Digital Marketing\nPractical experience Google Analytics and comfortable with data visualization tool such as PowerBI\nMotivated self-starter and good project management skill\nProficiency in both spoken and written English and Chinese\n\n\n\n\nAll information provided will be treated in strict confidence and used solely for recruitment purpose.\n\nFor more job opportunities, please visit our website:\u00a0https://npsl.com.hk/\n\n\n\n", "employment_types": ["Full Time", "Permanent"], "selling_points": ["Birthday Leave, Monthly Birthday Party", "Birthday Gift, Medical Insurance, Wearing Casually", "Monthly Birthday Party, Free Snack & Beverage"], "locations": ["Shatin Area"], "categories": ["Sales, CS & Business Devpt", "Customer Service - Supervisor / Officer", "Marketing / Public Relations", "Marketing - Marketing Communication", "Account Servicing"], "post_time": "2022-01-18T03:24:07Z", "salary": {"currency": null, "max": null, "min": null, "period": "monthly", "term": null}, "salary_visible": false, "title_keywords": ["coordinator"], "responsibilities": ["reporting", "provide insights", "digital marketing strategies", "website", "develop", "social media content", "plan", "liaise with", "planning"], "requirements": {"degrees": ["degree", "bachelor"], "majors": ["business", "marketing"], "languages": ["english", "chinese"], "language_level": ["proficiency"], "hard_skills": ["business management", "google analytics", "project management", "data visualization"], "soft_skills": ["motivated", "confidence", "project management skill"], "languages_combined": [{"language": "english", "language_level": ["proficiency"]}, {"language": "chinese", "language_level": ["proficiency"]}]}, "experience_required": {"duration": ["at least 3-year"], "field": ["relevant experience", "digital marketing"]}}, {"job_id": "100003009055171", "location_code": "hk", "company": "NP Solution Limited", "job_title": "Digital Marketing Manager - Hong Kong Listed Company", "description": "The Role\n\nReporting to Head of Marketing, this exciting role sits within the Marketing Department at SEEK Asia. The primary focus of the role is to be responsible for taking ownership and initiative in jobseeker and/or employer engagement strategies planning and implementation. This position plays an integral part in the success of our team\u2019s long-term vision, and represents a brand-new opportunity. We are looking for someone with a proven ability to adapt to a changing environment, and be a change champion, with the role evolving over time, as we progress through our technological & operational transformation.\n\nKey Responsibilities:\n\n\u00b7 Assist to launching and optimizing jobseeker and employer marketing campaigns.\n\n\u00b7 Assist to compile presentation decks and reports on campaign design, data tracking, and deliver other miscellaneous marketing tasks, including but not limited to ongoing acquisition, loyalty and engagement tasks.\n\n\u00b7 Effective Chinese and English copywriting skills to develop both online/ offline collaterals, and sale kits.\n\n\u00b7 As owner of CRM automation daily operations, work with brand owners to deliver regular and ad-hoc eDM and other automated communication to members.\n\n\u00b7 With creative mindset, business acumen and strong consumer centric insights, work with content team and agency to fine tuning social and articles content that engage users and convert business results.\n\n\u00b7 Able to work with sale team, regional and cross-functional teams.\n\n\u00b7 With knowledge of effective multi-channel strategies & tools for brands, such as CRM, eDM, Social, Partnership, Mobile etc to drive online traffic, jobseeker/ employer engagement and conversions.\n\nQualifications\nSo, what we are looking for?\n\nThe successful candidate will have:\n\n\u00b7 University degree holder.\n\n\u00b7 Minimum 2 years' experience preferably in e-commence, internet media or advertising agency, CRM related areas (Salesforce experience is highly preferred) and/or analytics, with a proven track record in driving brand awareness, considerations and conversions through effective strategy.\n\n\u00b7 You are a true believer of quality and always looking for opportunities to sharpen your marketing planning and analysis skills. With your high commercial acumen, you hope to deliver great value of business partnering support to both internal and external stakeholders.\n\n\u00b7 You are deeply passionate about technology and eager to learn new things.\n\n\u00b7 You are an extraordinary team player. You are responsible, supportive and collaborative. You say \u201cwe\u201d more than \u201cI\u201d. While engaging in discussions, you actively listen and bring valuable thoughts or opinions to the table when the \u201cEureka\u201d moment strikes!\n\n\u00b7 To you, the thought of bringing productivity to the next level sparks joy. You are someone who constantly puts on different thinking hats to find ways in improving existing processes, automating mundane tasks and shaping practices for the better.", "employment_types": ["Full Time"], "selling_points": ["Hong Kong Listed Company", "Dynamic Working Environment", "Competitive Package | Work Life Balance"], "locations": ["Not Specified"], "categories": ["Marketing / Public Relations", "Management", "Marketing - Marketing Communication", "Digital Marketing"], "post_time": "2022-01-18T01:37:11Z", "salary": {"currency": null, "max": null, "min": null, "period": "monthly", "term": null}, "salary_visible": false, "title_keywords": ["digital marketing manager"], "responsibilities": ["ad-hoc", "reporting", "tracking", "advertising", "data", "edm", "analysis", "quality", "implementation", "design", "develop", "communication", "daily operations", "reports", "marketing campaigns", "cross-functional teams", "planning"], "requirements": {"degrees": ["university degree"], "majors": [], "languages": ["english", "chinese"], "language_level": [], "hard_skills": ["hope", "salesforce", "analysis", "mobile", "focus", "joy", "acumen"], "soft_skills": ["supportive", "responsible", "creative mindset", "collaborative", "communication", "eager to learn", "team player", "consumer centric", "business acumen", "focus", "initiative", "presentation", "passionate about"], "languages_combined": [{"language": "english", "language_level": []}, {"language": "chinese", "language_level": []}]}, "experience_required": {"duration": ["minimum 2 years"], "field": ["related", "brand", "media", "advertising agency"]}}, {"job_id": "100003009051525", "location_code": "hk", "company": "Ma Belle Jewellery Co Ltd", "job_title": "Assistant Manager/Senior Officer \u2013 Customer Relationship Management (CRM)", "description": "Assistant Manager/Senior Officer\u2013 Customer Relationship Management (CRM)\nBased at our Hong Kong headquarters, you will be a team member to interact and work closely with a professional team delegated for the assigned distinguished jewellery brands.\nIf you have the right attitudes and aspirations of develop yourself in luxury retail will receive our investment in your career.\n\u00a0The Job\nCreate and develop\u00a0CRM Strategy and unique customer journey to enable seamless engagement\nImplement membership program to drive sales and enhance customer loyalty through interactive activities and unique experiences\nManage and analyze customer database for formulating, driving and delivering creative CRM events and promotion plans\nStudy and conduct analysis for pre and post campaign, members' behavior and create customer life-cycle recommendation models to drive cross-selling\nCollaborate with internal team & external agency to ensure excellent execution of overall CRM promotion\nImplement and support O2O Strategies to develop customer communications via omni-channels, including shop level, website, mobile App, eDM, SMS as well as internal and external platforms\nThe Person\nDegree holder in Marketing or Communications with minimum 3 years experience in CRM field from luxury industry is a plus\nStrong communications skills with entrepreneurial spirit\nCreative, energetic, dynamic and pro-active\nDetail oriented, analytical and sensitive to numbers\nGood connections with local agencies and vendors\nAttractive remuneration package will be offered to the right candidate. Please email full resume with current and expected salary to us\nPersonal data collected will be used for recruitment purposes only and will be treated in strict confidence.\u00a0 Applicants not invited for interview within 16 weeks may consider their applications unsuccessful and all information submitted will be destroyed.\n\u00a0", "employment_types": ["Full Time", "Permanent"], "selling_points": ["Create & Develop CRM Strategy, Data Analyze", "Plan and Enhance Membership Program", "Customer Recruitment and Re-Activation"], "locations": ["Tin Hau"], "categories": ["Marketing / Public Relations", "Marketing - Brand / Product Management", "Marketing - Marketing Communication", "Digital Marketing"], "post_time": "2022-01-16T08:05:51Z", "salary": {"currency": null, "max": null, "min": null, "period": null, "term": null}, "salary_visible": false, "title_keywords": ["assistant manager", "senior officer"], "responsibilities": ["collaborate with", "mobile app", "edm", "analysis", "website", "develop", "plans", "database", "drive sales"], "requirements": {"degrees": ["degree holder"], "majors": ["marketing", "communications"], "languages": [], "language_level": [], "hard_skills": ["plus", "luxury industry", "dynamic"], "soft_skills": ["confidence", "creative", "detail oriented", "dynamic", "pro-active", "sensitive to numbers", "energetic"], "languages_combined": []}, "experience_required": {"duration": ["minimum 3 years"], "field": ["marketing"]}}, {"job_id": "100003009042451", "location_code": "hk", "company": "West Kowloon Cultural District Authority", "job_title": "Senior Communications and Public Affairs Officer (Ref: R3095)", "description": "You will be a team member under Public Engagement stream in Communications and Public Affairs Department of the Authority.\nYou will be responsible for:\norganizing events/programmes for youth engagement and community outreach of the District;\ncoordinating with arts and cultural programme partners, District Councils, community groups, NGOs or other government organizations for public engagement community outreach collaborations;\nliaising with external and internal stakeholders for organizing events and delegation visits;\nworking with external agencies, outsourced vendors and community partners on public engagement and community outreach initiatives as necessary; and\ndriving and executing ad-hoc communications projects when required.\nYou should:\npossess a recognized university degree or above in Public Relations, Journalism, Communications or related discipline;\nhave 3-5 years of relevant and solid experience in in corporate social responsibility, community engagement public relations, events management, media relations and corporate communications;\nhave solid experience in engaging government bodies, District Councils, NGOs and community groups;\nhave strong interpersonal and communications skills, good team player, multi-tasking, able to meet tight deadlines and work under pressure, creative and dynamic;\nable to execute projects independently with guidance to achieve the engagement objectives and demonstrate strong attention to details and have a flexible approach to work;\nhave excellent written and spoken English and Chinese; proficient in Putonghua will be an advantage; and\nable to work irregular hours at weekends and public holidays if required.\nFor interested parties, please submit your application with detailed CV on or before 26 January 2022. Applicants are encouraged to submit their applications as soon as possible.\u00a0 The review of applications will continue until the post is filled.\nData collected will only be used for job application processing. Your data may be accessed by our appointed recruitment consultants who have agreed to keep confidence of all personal data in not less than the standards applicable to us. Applicants not being invited for interview within 4 weeks from the submission date may assume their applications unsuccessful.\nAll related information will be kept up to 24 months and all personal data will be destroyed afterwards.\nFor more information\nhttp://www.westkowloon.hk or contact\nMs. Yuki Ha at 2200-3786", "employment_types": ["Full Time"], "selling_points": ["Organise events/programmes for youth engagement", "Liase with stakeholder for organising events", "Work with partner for community outreach programme"], "locations": ["Tsim Sha Tsui"], "categories": ["Marketing / Public Relations", "Marketing - General / Support", "Marketing - Marketing Communication", "Public Relations - Event Management"], "post_time": "2022-01-12T11:33:52Z", "salary": {"currency": null, "max": null, "min": null, "period": null, "term": null}, "salary_visible": false, "title_keywords": ["officer"], "responsibilities": ["ad-hoc", "guidance", "management", "liaising with", "executing", "work under pressure"], "requirements": {"degrees": ["degree or above"], "majors": ["journalism", "communications"], "languages": ["putonghua", "english", "chinese"], "language_level": ["advantage", "excellent", "proficient"], "hard_skills": ["dynamic"], "soft_skills": ["flexible", "good team player", "meet tight deadlines", "independently", "creative", "responsible", "multi-tasking", "dynamic", "attention to details", "team member", "interpersonal", "work under pressure"], "languages_combined": [{"language": "putonghua", "language_level": ["proficient", "advantage"]}, {"language": "english", "language_level": ["excellent"]}, {"language": "chinese", "language_level": ["excellent"]}]}, "experience_required": {"duration": ["3-5 years"], "field": ["management", "public relations", "media", "corporate social responsibility"]}}, {"job_id": "100003009047281", "location_code": "hk", "company": "AsiaWorld-Expo Management Limited", "job_title": "Senior Marketing & Branding Officer", "description": "Responsibilities:\n\nHandle the production of marketing collaterals and promotional materials to tie in with events and other business needs\nDevise innovative marketing communication campaigns to engage stakeholders and enhance brand awareness\nFormulate in-venue visitors engagement activities and execute during on-site or off-site events as required\nServe as a brand advocate in strengthening and upholding brand identity, including in-venue decoration and outgoing communication materials\nProvide support and collaborate with different teams to achieve dynamic planning across the company\nSupport in team related administrative and logistics as required\n\nRequirements:\n\nDegree Holder in Marketing, Communications, Business or other related disciplines\nAt least 3 years experience in marketing, communications, advertising or event management\nProficient in AI, Photoshop, HTML and CSS is an advantage\nA positive team player, proactive, detail-minded and highly independent\nStrong organizational ability and able to work effectively and efficiently under pressure\nProven writing skills in both English and Chinese\nFluent in English and Chinese, including Mandarin\u00a0\n\nInterested parties please send your full resume stating present & expected salary to HR Department by email to\u00a0hr@ asiaworld-expo.com\nPersonal data collected will be used for recruitment-related purpose only.\nAsiaWorld-Expo Management Limited is an equal opportunities employer.\u00a0", "employment_types": ["Full Time"], "selling_points": ["Marketing & Branding", "Attractive remuneration package", "Good career path"], "locations": ["Airport Area"], "categories": ["Marketing / Public Relations", "Marketing - Brand / Product Management", "Marketing - General / Support", "Marketing - Marketing Communication"], "post_time": "2022-01-14T02:45:23Z", "salary": {"currency": null, "max": null, "min": null, "period": "monthly", "term": null}, "salary_visible": false, "title_keywords": ["officer"], "responsibilities": ["collaborate with", "provide support", "marketing collaterals", "teams", "communication", "promotional materials", "logistics", "planning"], "requirements": {"degrees": ["degree holder"], "majors": ["business", "related disciplines", "marketing", "communications"], "languages": ["english", "chinese", "mandarin"], "language_level": ["fluent"], "hard_skills": ["ai", "writing skills", "html", "css", "photoshop"], "soft_skills": ["detail-minded", "highly independent", "work effectively", "under pressure", "organizational", "writing skills", "team player", "proactive", "positive"], "languages_combined": [{"language": "english", "language_level": ["fluent"]}, {"language": "chinese", "language_level": ["fluent"]}, {"language": "mandarin", "language_level": ["fluent"]}]}, "experience_required": {"duration": ["at least 3 years"], "field": ["management", "marketing", "advertising"]}}, {"job_id": "100003009049287", "location_code": "hk", "company": "SEEK Asia (JobsDB)", "job_title": "Senior Marketing Executive (1 year contract)", "description": "Requirements:\u00a0\n\nWork with senior management to develop proposal content and prepare document\nCoordinate internally the design, selection, purchase and distribution of proposed materials\nCoordinate externally with suppliers and source new vendors for on-going projects\nArrange procurement and deliverable schedule\nAssist in maintaining the marketing database\nAssist the marketing team in regular daily operation and any other ad hoc tasks\n\nResponsibilities:\n\nDegree Holder in business, marketing or related discipline.\nMinimum 1-2 years of marketing experience.\u00a0\nTakes initiative, energetic and able to handle multi assignments.\nCommunicates the progress of work to management regularly\nWell organized, hard working and\u00a0able to work under pressure\nGood communication skill with fluent command of English and Mandarin\nProficiency in MS Office and Chinese Word Processing\nFresh graduates are welcome to apply\n\nWe offer comprehensive package and a team-oriented environment. If you are seeking a dynamic career in industry-leading firm, please send us your full resume.\n\nPlease visit www.fusion.com.hk for more information.\n\n(Data collected would be used for recruitment purpose only)", "employment_types": ["Full Time", "Contract"], "selling_points": ["Our motto: Improving Lives through Better Careers", "Company Values: We Care, We Aim High, We Deliver", "Customized Career Development Opportunities"], "locations": ["Quarry Bay"], "categories": ["Marketing / Public Relations", "Marketing - General / Support", "Marketing - Marketing Communication", "Digital Marketing"], "post_time": "2022-01-14T08:22:57Z", "salary": {"currency": null, "max": null, "min": null, "period": "monthly", "term": null}, "salary_visible": false, "title_keywords": ["senior marketing executive"], "responsibilities": ["communication", "management", "work under pressure"], "requirements": {"degrees": [], "majors": [], "languages": [], "language_level": [], "hard_skills": [], "soft_skills": [], "languages_combined": []}, "experience_required": {"duration": [], "field": []}}, {"job_id": "100003009049707", "location_code": "hk", "company": "Fusion Design Limited", "job_title": "MARKETING ASSISTANT", "description": "You will be a team member under Public Engagement stream in Communications and Public Affairs Department of the Authority.\n\nYou will be responsible for:\n\nassisting in developing public engagement strategy and driving community outreach initiatives so as to enhance the public understanding of the work of the Authority and foster support from local community;\nplanning, leading and organizing community outreach programmes and initiatives of the District;\ncultivating relations and liaising with government organizations, arts and cultural programme partners, and NGO/community groups;\ncoordinating communication materials for Consultation Panel and liaising with the Working Group under Consultation Panel on youth and community engagement initiatives and programme review;\narranging visits and preparing communications materials including press releases, speeches, and presentation materials, etc;\nhandling and coordinating responses to enquiries from community groups, District Councils when required;\nassisting in message development, internal and external stakeholders\u2019 liaison in crisis communications and issues handling; and\ndriving and executing ad-hoc communications projects when required.\n\nYou should:\n\npossess a recognized university degree or above in Public Relations, Journalism, Communications or related discipline;\nhave at least 5 years of relevant and solid experience in public relations, events management, media relations, corporate communications, corporate social responsibility and community engagement;\nhave proven experience in engaging government bodies, NGOs, community groups; arts and culture groups;\npossess strong interpersonal and communication skills, be a good team player with creativity and dynamism, attention to details, and able to multi-task and meet tight deadlines and work under pressure;\nbe able to plan, execute and manage projects independently to achieve the communications goals;\nhave high adaptability to an environment of volatility, uncertainty, complexity and ambiguity;\nbe passionate about arts and culture; and\nhave excellent spoken and written English and Chinese; be proficient in Putonghua.\n\nFor interested parties, please submit your application with detailed CV on or before 26 January 2022. Applicants are encouraged to submit their applications as soon as possible.\u00a0 The review of applications will continue until the post is filled.\n\nData collected will only be used for job application processing. Your data may be accessed by our appointed recruitment consultants who have agreed to keep confidence of all personal data in not less than the standards applicable to us. Applicants not being invited for interview within 4 weeks from the submission date may assume their applications unsuccessful.\n\nAll related information will be kept up to 24 months and all personal data will be destroyed afterwards.\n\nFor more information\nhttp://www.westkowloon.hk or contact\nMs. Yuki Ha at 2200-3786", "employment_types": ["Full Time", "Permanent"], "selling_points": ["Fresh graduates are welcome to apply", "Good communication & interpersonal skill", "Degree Holder"], "locations": ["North Point"], "categories": ["Marketing / Public Relations", "Marketing - Direct Marketing", "Marketing - General / Support", "Marketing - Marketing Communication"], "post_time": "2022-01-14T09:07:57Z", "salary": {"currency": null, "max": null, "min": null, "period": "monthly", "term": null}, "salary_visible": false, "title_keywords": ["marketing assistant"], "responsibilities": ["ad-hoc", "management", "work under pressure", "review", "liaising with", "developing", "communication", "executing", "manage projects", "plan", "planning"], "requirements": {"degrees": ["degree or above"], "majors": ["journalism", "communications"], "languages": ["putonghua", "english", "chinese"], "language_level": ["excellent", "proficient"], "hard_skills": [], "soft_skills": ["communication skills", "good team player", "meet tight deadlines", "multi-task", "independently", "responsible", "interpersonal", "communication", "adaptability", "attention to details", "team member", "presentation", "passionate about", "work under pressure"], "languages_combined": [{"language": "putonghua", "language_level": ["proficient"]}, {"language": "english", "language_level": ["excellent"]}, {"language": "chinese", "language_level": ["excellent"]}]}, "experience_required": {"duration": ["at least 5 years"], "field": ["management", "public relations", "media", "corporate social responsibility"]}}, {"job_id": "100003009042442", "location_code": "hk", "company": "West Kowloon Cultural District Authority", "job_title": "Assistant Manager, Communications and Public Affairs (Ref: R2948)", "description": "JOCKEY CLUB DESIGN INSTITUTE FOR SOCIAL INNOVATION\nCommunity Engagement Officer (Ref. 22011406-E)\nJockey Club Design Institute for Social Innovation is a unit aims at providing an innovative and human-centred platform to envision a better life in the society, connecting people with passion and nurturing doers of all ages to innovate with collective wisdom to enable impactful action.\u00a0\n\nDuties\nThe appointee will be required to:\n(a) formulate and execute effective marketing programmes;\n(b) organize events including preparation of promotion and event materials, pre-event logistic arrangements, on-site event management, etc.;\n(c) work closely with internal and external parties to facilitate the smooth implementation of marketing activities;\n(d) manage the digital communication channels, including website, social media, etc.;\n(e) assist in the development of the Institute\u2019s publicity, corporate branding and image-building;\n(f)\u00a0 engage a spectrum of community groups including senior citizens and non-governmental organizations; and\n(g) perform any other duties as assigned by the Director of the Jockey Club Design Institute for Social Innovation and the Project Managers.\nQualifications\nApplicant should:\n(a)\u00a0 have a recognised degree, preferably in Marketing, Communications, Advertising, Journalism or related disciplines;\n(b)\u00a0 have at least five years of marketing and communications experience;\n(c) have an excellent command of both written and spoken English and Chinese, including Putonghua;\n(d) have good communication, liaison and organizational skills;\n(e) be a good team player with a strong sense of responsibility and capable of handling multi tasks;\n(f) be highly motivated with strong initiatives, innovative and attentive to details;\n(g) demonstrate the ability to work under pressure;\n(h) have proficiency in MS Office applications, contemporary design applications (e.g. Adobe Photoshop and Illustrator, etc.) and Chinese word processing; and\n(i) have strong media network in local news or feature pages being an advantage.\nShortlisted candidates will be invited to sit for a written test.\nApplication\nPlease send a completed application form by post to Human Resources Office, 13/F, Li Ka Shing Tower, The Hong Kong Polytechnic University, Hung Hom, Kowloon, Hong Kong or via email by clicking \"Apply Now\"\u00a0 Application forms can be downloaded from https://www.polyu.edu.hk/hro/careers/guidelines_and_forms/forms.\u00a0 If a separate curriculum vitae is to be provided, please still complete the application form which will help speed up the recruitment process.\u00a0 Consideration of applications will commence on 21 January 2022 until the position is filled.\u00a0 The University\u2019s Personal Information Collection Statement for recruitment can be found at https://www.polyu.edu.hk/hro/careers/guidelines_and_forms/pics_for_recruitment.\nPolyU is an equal opportunity employer committed to diversity and inclusivity.\u00a0 All qualified applicants will receive consideration for employment without regard to gender, ethnicity, nationality, family status or physical or mental disabilities.", "employment_types": ["Full Time"], "selling_points": ["Assist in developing public engagement strategy", "Plan and lead community outreach programmes", "Arrange visits and prepare communications material"], "locations": ["Tsim Sha Tsui"], "categories": ["Marketing / Public Relations", "Marketing - General / Support", "Marketing - Marketing Communication", "Public Relations - Event Management"], "post_time": "2022-01-12T11:28:46Z", "salary": {"currency": null, "max": null, "min": null, "period": null, "term": null}, "salary_visible": false, "title_keywords": ["assistant manager,"], "responsibilities": ["social media", "management", "any other duties", "advertising", "internal and external parties", "implementation", "design", "website", "communication", "recruitment", "recruitment process", "work under pressure"], "requirements": {"degrees": ["degree"], "majors": ["journalism", "related disciplines", "marketing", "communications"], "languages": ["putonghua", "english", "chinese"], "language_level": ["excellent"], "hard_skills": ["chinese word processing", "adobe photoshop", "illustrator", "c", "ms office"], "soft_skills": ["organizational skills", "good team player", "capable", "attentive to details", "sense of responsibility", "communication", "committed", "motivated", "smooth", "innovative", "work under pressure"], "languages_combined": [{"language": "putonghua", "language_level": ["excellent"]}, {"language": "english", "language_level": ["excellent"]}, {"language": "chinese", "language_level": ["excellent"]}]}, "experience_required": {"duration": ["at least five years"], "field": ["marketing"]}}, {"job_id": "100003009050962", "location_code": "hk", "company": "The Hong Kong Polytechnic University", "job_title": "Community Engagement Officer", "description": "We are looking for a seasoned senior leader who is passionate to join the largest Innovation and Technology eco-system in Hong Kong.\u00a0 The successful incumbent shall possess strong leadership to lead and drive the team to ideate, plan and implement high level flagship events, conferences, exhibitions, community engagement programme and new business initiatives to support the continuous growth of the Corporation and to elevate the vibrancy and diversity of the Science Park community.\u00a0 He / she has to be a strategic thinker and planner, a great problem solver, and is goal getting, result driven, innovative, co-creative, energetic, collaborative, enthusiastic; and bold to tackle and overcome challenges to deliver remarkable results.\nResponsibilities:\nIdeating, content curating, brand positioning, budgeting, planning, promoting and managing high-quality and influential B2B & B2C events to achieve the Corporate objectives\nLead and drive the team to meet and even exceed targeted goals, accomplish high quality and remarkable outcomes and manage to propose and make strategical, timely and decisive directions and changes in the dynamic environment\nMaster impactful marketing and promotional assets; research, analyse, interpret and present latest marketing trend and data in a world perspective\nStrategically plan and deliver engagement initiatives to build a vibrant and actively engaging community among the partner companies in the Science Park eco-system\nContent curate and manage digital platforms including websites and social media for specified events and programmes\nPerform any other duties as assigned by supervisors\nRequirements:\nBachelor degree in Business Administration, Marketing, Communication or other related disciplines\n10 years relevant experience in event marketing and management, preferably gained in sizable / MNC corporations with at least 3 years of solid team leadership\nProven track record in ideating, content curating and managing high level, large-scale & impactful events, and mastering professional, trendy and effective marketing promotional assets\nStrong business sense, thorough understanding of the latest world marketing trend and rich experience in digital and content marketing\nStrong leadership demonstration of tackling challenges, accomplishing remarkable results and growing the team\nInnovative, idea-driven, goal-getting, dynamic, self-motivated, detailed-oriented and is able to work under tight schedule\nProficient in both verbal and written English and Chinese, including Cantonese and Putonghua\nStrong industry network with excellent interpersonal and communications skills\nWe offer market competitive compensation, 5-day work week, and generous benefits including medical and life insurance; and voluntary contribution in addition to the legal minimum MPF.\u00a0 To apply, please send your full resume with current and expected salary to the Human Resources & Office Administration Department, Hong Kong Science and Technology Parks Corporation, 5/F, Building 5E, 5 Science Park East Avenue, Hong Kong Science Park, Hong Kong or, by email via \"Apply Now\"\u00a0on or before 27 January 2022.\u00a0 \u00a0Please quote the reference number on the email subject/envelope and the application letter.\u00a0\nPersonal data provided will be treated in strict confidence and used for recruitment purpose only.\u00a0 All personal data collected will be used strictly in accordance with employer\u2019s personal data policies, you can access to HKSTP\u2019s Personal Information Collection Statement at https://www.hkstp.org/hkstp_web/en/hkstp/personal-information-collection-statement-recruitment\nApplicants not invited for interview within four weeks after application deadline may consider their applications unsuccessful.\u00a0 Personal data of unsuccessful applicants will be retained for a maximum of two years.\u00a0\nwww.hkstp.org", "employment_types": ["Full Time"], "selling_points": [], "locations": ["Not Specified"], "categories": ["Media & Advertising", "Editorial / Journalism", "Marketing / Public Relations", "Marketing - Marketing Communication", "Public Relations - Event Management"], "post_time": "2022-01-14T12:05:23Z", "salary": {"currency": null, "max": null, "min": null, "period": "monthly", "term": null}, "salary_visible": false, "title_keywords": ["officer"], "responsibilities": ["social media", "any other duties", "data", "budgeting", "quality", "planning", "marketing trend", "plan", "analyse"], "requirements": {"degrees": ["degree", "bachelor"], "majors": ["related disciplines", "marketing", "business administration"], "languages": ["cantonese", "putonghua", "english", "chinese"], "language_level": ["proficient"], "hard_skills": ["goal", "dynamic"], "soft_skills": ["self-motivated", "business sense", "interpersonal", "communication", "dynamic", "thorough", "innovative", "leadership", "driven", "detailed"], "languages_combined": [{"language": "cantonese", "language_level": []}, {"language": "putonghua", "language_level": []}, {"language": "english", "language_level": ["proficient"]}, {"language": "chinese", "language_level": ["proficient"]}]}, "experience_required": {"duration": ["at least 3 years", "10 years"], "field": ["management", "business", "marketing", "relevant experience", "digital", "team"]}}, {"job_id": "100003009047519", "location_code": "hk", "company": "HKBN Enterprise Solutions HK Limited", "job_title": "Senior Officer - Marketing Communications (Copywriting)", "description": "The Job:\n\nDevelop corporate communications and public relations plans aligning with the company\u2019s vision, missions and development strategies;\nTo initiate corporate communications, PR and CSR strategies, generate creative ideas and implement effective campaigns to enhance corporate image and brand awareness, and responsible for management profiling;\nOversee corporate branding as the brand gatekeeper of the bank;\nResponsible for the content strategies and development of all PR and corporate materials, including corporate website and social media (wechat, Facebook, Youtube etc), group newsletters, press materials, corporate communication materials including but not limited to corporate presentation deck, video, corporate premiums and so on;\nAssist in handling international and China media enquiries and follow up interviews\u2019 opportunities;\nBuild and maintain strong relationships with media and business partners as well as internal stakeholders;\nWork closely with the team on media sponsorship opportunities, including top industry award submissions;\nLead planning on advertising and SEO initiatives to maximize corporate/product branding in the market;\nWork on crisis management to develop communications and timely reaction plan whenever necessary;\nWork closely with partnership and events team to organize signature group events and support in areas like management speeches, onsite support and press relations;\nAssist in team building and manage PR agencies, budget and expenses;\nEnsure that all regulatory and legal & compliance requirements and standards are met;\nCreate a cohesive content and campaign strategy for employee engagement;\nProvide strategic guidance and solutions to firm management and other internal clients on internal communications strategies;\nDevelop and oversee intranet stories, office communications, posters and digital signage and staff events, etc.\n\nRequirements:\n\nOver 8 years of professional corporate communications and PR experience, with strong media, columnists and KOLs in financial sectors in HK, mainland China and international;\nExcellent writing and oral communication skills in both Chinese and English is a must;\nCrisis management experience in financial sector is preferred;\nA good team leader and player with exceptional interpersonal skills;\nDegree holders in communications, journalism, business administration, or marketing preferred;\nCan work well in a dynamic, rapidly changing workplace; mature and flexible with entrepreneurial mind-set and can-do attitude;\nStrong Chinese writing skills in financial sector are required.\n\nWe provide attractive remuneration package and fringe benefits for the right candidate. Interested parties please send detailed resume with current and expected salaries to\u00a0Human Resources Department i) by mail: 22/F, Li Po Chun Chambers, 189 Des Voeux Road Central, HK; ii) by fax: 2537 5431;\u00a0or iii) by using \"APPLY NOW\".\n\nPlease quote the reference in the application. If application is submitted in hard copy format, it should be placed in a sealed envelope marked \u201cConfidential\u201d. All applications will be treated in strict confidence and personal data provided by job applications will be used for recruitment purposes only. A copy of our Personal Information Collection Statement will be available upon request.", "employment_types": ["Full Time", "Permanent"], "selling_points": ["Experienced in creating content for various media", "Excellent in Chinese & English content writing", "Talent-first culture & Life-Work Priority"], "locations": ["Kowloon Bay"], "categories": ["Media & Advertising", "Creative / Design", "Marketing / Public Relations", "Marketing - Marketing Communication", "Public Relations - Copy-writing"], "post_time": "2022-01-14T03:22:04Z", "salary": {"currency": null, "max": null, "min": null, "period": "monthly", "term": null}, "salary_visible": false, "title_keywords": ["senior officer"], "responsibilities": ["social media", "creative ideas", "management", "advertising", "seo", "guidance", "budget", "expenses", "website", "compliance", "develop", "communication", "maintain", "plan", "plans", "facebook", "crisis management", "planning"], "requirements": {"degrees": ["degree"], "majors": ["journalism", "marketing", "business administration", "communications"], "languages": ["english", "chinese"], "language_level": ["excellent"], "hard_skills": ["dynamic", "writing skills"], "soft_skills": ["flexible", "communication skills", "oral", "can-do attitude", "mature", "writing skills", "dynamic", "interpersonal skills", "good team leader"], "languages_combined": [{"language": "english", "language_level": ["excellent"]}, {"language": "chinese", "language_level": ["excellent"]}]}, "experience_required": {"duration": ["8 years"], "field": ["pr", "management", "kols", "media", "financial"]}}, {"job_id": "100003009043233", "location_code": "hk", "company": "Haitong International Securities Group Limited", "job_title": "Vice President to Senior Vice President - Corporate Communications, Executive Committee Office", "description": "A day in the life:\n\nCreate blog articles, guides, reports, webpages, and various other types of digital content\nSupport ideation of content for our websites and social media\nWork with the wider Marketing and Sales teams across various offices to meet content needs\nAnalyze and provide insights based on our multiple marketing streams data\nOther ad hoc duties as required\n\n\nWhat you\u2019ll need:\n\nNative level English (additional languages are a plus, but not necessary)\nExcellent editing skills with high level grammar and spelling ability\nPassion for, and experience with, writing online copy\nA working knowledge of analytical tools (e.g. Google Analytics)\nFamiliarity with Search Engine Optimization is a plus\nAn interest in website coding, or experience with HTML, WordPress, and CMS\nA degree in Marketing, Business, Communications, or related subject is preferred\nWillingness to learn\n\n\nThe perks:\n\nCompetitive salary\nMedical insurance\n5 day work week\nGenerous annual leave\nWork-life balance and a relaxed working culture\n\n\nInterested parties, please send your CV by clicking \u201cApply Now\u201d. All applications received will be used strictly for selection purposes only.", "employment_types": ["Full Time", "Permanent"], "selling_points": [], "locations": ["Sheung Wan"], "categories": ["Marketing / Public Relations", "Management", "Marketing - Marketing Communication", "Public Relations - Event Management"], "post_time": "2022-01-12T10:19:03Z", "salary": {"currency": null, "max": null, "min": null, "period": null, "term": null}, "salary_visible": false, "title_keywords": ["vice president", "executive"], "responsibilities": ["ad hoc duties", "social media", "provide insights", "data", "teams", "website", "coding", "reports", "editing", "insurance"], "requirements": {"degrees": ["degree"], "majors": ["business", "marketing", "communications"], "languages": ["english"], "language_level": ["native"], "hard_skills": ["google analytics", "plus", "wordpress", "html"], "soft_skills": ["passion for"], "languages_combined": [{"language": "english", "language_level": ["native"]}]}, "experience_required": {"duration": [], "field": ["writing"]}}, {"job_id": "100003009052159", "location_code": "hk", "company": "Pacific Prime Insurance Brokers Ltd", "job_title": "Content Creator (5 day work)", "description": "Established in 2009, Hong Kong Green Building Council (\u201cthe Council\u201d) is the leading body, co-founded by four major construction industry and environmental organisations, driving the market transformation towards green and sustainable buildings in Hong Kong through engagement with the industry, the government and broader community.\nHKGBC is expanding its secretariat team in line with its positioning as Hong Kong's leading member-based body dedicated to green building development, with opening for the post of Project Executive:\nKey Roles:\nReport to the Head of Marketing, Project Manager and Senior Project Executive;\nCoordinate with internal departments, external parties and schools for organising and executing various public education events, trainings, tours and workshops;\nSupport the preparation of promotional materials including videos, training kits, presentation materials, advertorials and proposals for school engagement activities;\nAssist the planning and implementation of online and offline promotional campaigns;\nLiaise with vendors including consultants, PR agencies, production houses, etc. to ensure quality and timeliness of deliverables for events and campaigns;\nSupport all reporting, invoicing and logistics works;\nPerform any other duties as assigned.\n\u00a0Requirements:\nBachelor\u2019s degree holder in Communications, Marketing, Public Relations or related disciplines with minimum 2 years relevant working experience.\nExcellent command of both written and spoken English and Cantonese. Fluency in Mandarin would be an advantage;\nGrade C or above in Use of English in HKALE and Grade C (Syl. B) / Level 4 or above in English in HKCEE or Grade 5 or above in English in DSE would be an asset\nDetailed-mined, versatile and naturally outgoing with strong communication skills\nAbility to work both independently and collaboratively with the team;\nSelf-motivated with a strong sense of responsibility and able to work under pressure;\nProficient in PC applications including MS Office, Chinese word processing and database management;\nKnowledge of Adobe Photoshop, Illustrator and Dreamweaver would be an advantage.\u00a0\u00a0\n\u00a0How to Apply\nThe Council is an equal opportunity employer and offers attractive career prospects and remuneration to our staff. Recruitment will be initially under contract terms from commencement date to 30 June 2023. Interested applicants please apply by sending\u00a0full resume with date of availability, present and expected salary, contact telephone number, as well as results of public examinations\u00a0to the\u00a0Executive Director, Hong Kong Green Building Council\u00a0via e-mail\u00a0careers@ hkgbc.org.hk, or by post to\u00a01/F, Jockey Club Environmental Building, 77 Tat Chee Avenue, Kowloon Tong, Hong Kong. Please state the position you want to apply for on the envelope.\n(N.B. Application with incomplete information as requested above may not be considered.)\nApplicants who do not receive a response within six weeks from the date of this advertisement may consider their applications filed for future reference. Personal data will be used strictly for recruitment related purposes only and retained for no more than six months.", "employment_types": ["Full Time", "Permanent"], "selling_points": ["Exciting Digital Content Creator opportunity", "Write articles and website content", "Competitive pay & medical insurance"], "locations": ["Not Specified"], "categories": ["Media & Advertising", "Editorial / Journalism", "Marketing / Public Relations", "Marketing - Marketing Communication", "Professional Services", "Translation"], "post_time": "2022-01-17T02:17:34Z", "salary": {"currency": null, "max": null, "min": null, "period": "monthly", "term": null}, "salary_visible": false, "title_keywords": [], "responsibilities": ["any other duties", "external parties", "quality", "communication", "promotional materials", "database", "liaise with", "personal data", "work under pressure", "implementation", "logistics", "report", "reporting", "management", "coordinate with", "executing", "contact", "invoicing", "recruitment", "planning"], "requirements": {"degrees": ["bachelor", "dse", "degree holder"], "majors": ["related disciplines", "marketing", "communications"], "languages": ["cantonese", "english", "chinese", "mandarin"], "language_level": ["fluency", "advantage", "excellent", "proficient"], "hard_skills": ["no", "chinese word processing", "adobe photoshop", "illustrator", "pc applications", "c", "dreamweaver", "workshops", "ms office"], "soft_skills": ["outgoing", "communication skills", "self-motivated", "independently", "sense of responsibility", "work under pressure", "versatile", "presentation", "detailed"], "languages_combined": [{"language": "cantonese", "language_level": ["excellent"]}, {"language": "english", "language_level": ["excellent"]}, {"language": "chinese", "language_level": ["proficient"]}, {"language": "mandarin", "language_level": ["fluency", "advantage"]}]}, "experience_required": {"duration": ["minimum 2 years"], "field": ["related", "public relations", "marketing", "relevant working experience"]}}, {"job_id": "100003009046284", "location_code": "hk", "company": "Hong Kong Green Building Council Limited", "job_title": "Senior Marketing & PR Executive", "description": "Job Highlights\n\u00a0\u904b\u7528\u793e\u4ea4\u5a92\u9ad4\u5438\u5f15\u5ba2\u6e90\n\u00a0\u6708\u85aa\u5e73\u574720K-28K (\u53e6\u6709\u984d\u5916\u734e\u91d1\u53ca\u4f63\u91d1)\n\u00a0\u5de5\u4f5c\u6027\u8cea\u5f48\u6027\uff0c\u6536\u5165\u7121\u4e0a\u9650\nJob Description\n\n\n\u00a0\u60f3\u6435\u5230\u771f\u6b63\u53ef\u4ee5Work-Life Balance\u5605\u5de5\n\n\u00a0\u60f3\u591a\u52de\u591a\u5f97\uff0c\u5514\u8981\u88ab\u525d\u524a\n\u00a0\u8aa0\u9080\u60f3\u81ea\u5df1\u63a7\u5236\u5de5\u6642\u53ca\u6536\u5165\u7684\u4f60\n\n#IG/FB Marketing Sales #\u7db2\u7d61\u71df\u92b7 #20K-28K\n\n\n\n\u597d\u60f3\u8a66\u5413\u505a\u751f\u610f\uff0c\u4f46\u53c8\u672a\u5920\u8cc7\u672c\u3002\n\u597d\u60f3\u5275\u4e00\u756a\u4e8b\u696d\uff0c\u4f46\u4efd\u5de5\u7747\u5514\u5230\u672a\u4f86\u9ede\u884c\u3002\n\u5e7e\u500b\u539f\u672c\u4f86\u81ea\u5514\u540c\u884c\u696d\uff0c\u5514\u540c\u80cc\u666f\u5605\u5e74\u8f15\u4eba\n\u5e7e\u5e74\u5167\u90fd\u80fd\u5920\u64c1\u6709\u904e\u767e\u842c\u5e74\u85aa\u5605\u771f\u5be6\u6545\u4e8b\u3002\n\u7121\u8ad6\u4f60\u6700\u5f8c\u52a0\u5514\u52a0\u5165\uff0c\u90fd\u6b61\u8fce\u7d04\u898b\n\u807d\u5413\u6211\u5730\u5605\u6210\u529f\u6545\u4e8b\uff0c\u8a71\u5514\u5b9a\u90fd\u53ef\u4ee5\u555f\u767c\u57cb\u4f60\uff1a\uff09\n\n\u73fe\u8aa0\u62db\u80af\u640f\u80af\u505a\uff0c\u5514\u6015\u5931\u6557\u5605\u4f60\u53c3\u8207\uff0c\u4e00\u9f4a\u5bd3\u5de5\u4f5c\u65bc\u5a1b\u6a02\uff01\n\n\u5de5\u4f5c\u7bc4\u7587\uff1a\n\n\u6bcf\u65e5\u4ee5IG/FB Marketing\u5de5\u4f5c\u70ba\u4e3b\uff0c\u6216\u4ee5\u5275\u610f\u69cb\u601d\u65b0Marketing\u65b9\u5f0f\n\n\u6bcf\u65e5Update\u53ca\u5206\u4eab\u5de5\u4f5c\u65e5\u5e38/\u7406\u8ca1\u6559\u5b78/\u8cc7\u8a0a\n\n\u5f48\u6027\u81ea\u4e3b\u5605\u5de5\u4f5c\u6a21\u5f0f\u3002\n\n\u798f\u5229\uff1a\n\n\u6bcf\u6708\u6d25\u8cbc\uff0b\u8c50\u539a\u4f63\u91d1\uff0c\u4e00\u5e7413\u6b21\u82b1\u7d05\uff0c\u4f63\u91d1\u6536\u5165\u53ef\u904e\u767e\u842c\u4e00\u5e74\uff0c\u6536\u5165\u7121\u4e0a\u9650\n\n\u5e95\u85aaHKD$8,000 - 30,000\u00a0(\u8996\u4e4e\u904e\u4f4f\u5de5\u4f5c\u7d93\u9a57\uff0f\u5b78\u6b77\uff09\n\n\u5c08\u696d\u53ca\u5b8c\u5584\u5165\u8077\u57f9\u8a13\uff0c\u826f\u597d\u6649\u5347\u5236\u5ea6\n\n\u4e00\u5e74\u5169\u6b21\u516c\u53f8\u65c5\u884c\u734e\u8cde\n\n\u5f48\u6027\u4e0a\u73ed\u5de5\u4f5c\uff0c\u4e0d\u8a2d\u5927\u5047\u9650\u5236\uff0c\u6c92\u6709\u696d\u7e3e\u58d3\u529b\n\n\u8981\u6c42\uff1a\n\n\u4e2d\u4e94\u7562\u696d\u53ca\u516c\u958b\u8003\u8a66\u4e94\u79d1\u5408\u683c\n\n\u6709\u826f\u597d\u7684\u4eba\u969b\u95dc\u4fc2\uff0c\u597d\u52d5\uff0c\u6709\u5275\u610f\uff0c\u611b\u8207\u4eba\u4ea4\u969b\n\n\u611b\u6e9d\u901a\uff0c\u4e3b\u52d5\uff0c\u6562\u65bc\u63a5\u53d7\u6311\u6230\n\n\u7d93\u9a57\u4e0d\u62d8\uff0c\u4e0d\u9650\u5e74\u9f61\uff0c\u6b61\u8fce\u61c9\u5c46\u7562\u696d\u751f\n\n*******\u6709\u610f\u8005\u8acb\u7acb\u523b\u9ede\u64caApply Now\u4ee5\u5b89\u6392\u9762\u8a66\u00a0**********\n\n\n", "employment_types": ["Full Time", "Contract"], "selling_points": [], "locations": ["Kowloon City Area"], "categories": ["Media & Advertising", "Editorial / Journalism", "Marketing / Public Relations", "Marketing - Marketing Communication", "Public Relations - Event Management"], "post_time": "2022-01-13T10:16:39Z", "salary": {"currency": null, "max": null, "min": null, "period": "monthly", "term": null}, "salary_visible": false, "title_keywords": ["executive"], "responsibilities": [], "requirements": {"degrees": [], "majors": [], "languages": [], "language_level": [], "hard_skills": [], "soft_skills": [], "languages_combined": []}, "experience_required": {"duration": [], "field": []}}, {"job_id": "100003009055116", "location_code": "hk", "company": "Sparklife Company", "job_title": "#\u597d\u73a9 #IG/FB Marketing Sales #\u7db2\u7d61\u71df\u92b7 #20K-28K", "description": "Our client, a pioneer in organizing exhibitions,\u00a0is now looking for Marketing Communication Executive (Project) (Event) (PR)\n\nMarketing Communication Executive (Project) (Event) (1)\n\nJob Responsibilities\n\nResearch vendors\nNegotiate with vendors to achieve the most favorable terms\nManage all event operations (preparing venue, invitations etc.)\nDo final checks at the day of the event (e.g. tables, technology) to ensure everything meets standards\nOversee event happenings and act quickly to resolve problems\nEvaluate event\u2019s success and submit reports\n\nJob Requirements\n\nHigher diploma in Marketing, Communications, Public Relations, Journalism or relevant field\nProficiency in MS Office\nExcellent verbal and written communication skills\nGood presentation skills\n\nMarketing Communication Executive (Project) (Event) (2)\n\nJob Responsibilities\n\nCoordinate the design of promotional material and distribute in online and offline channels\nAdvertise company and products/services on various media\nCraft and send regular newsletters with company updates\nMonitor corporate website and social media pages and address clients\u2019 queries\nGather customer feedback to inform sales and product teams\n\nJob Requirements\n\nHigher diploma in Marketing, Communications, Public Relations, Journalism or relevant field\nProficiency in MS Office\nExcellent verbal and written communication skills\nGood presentation skills\n\nMarketing Communication Executive (PR)\n\nJob Responsibilities\n\nWriting and producing presentations and press releases\nDealing with enquiries from the public, the press, and related organisations\nOrganising and attending promotional events such as press conferences, open days, exhibitions, tours and visits\nLiaising with clients, managerial and journalistic staff about budgets, timescales and objectives\n\nJob Requirements\n\nHigher diploma in Marketing, Communications, Public Relations, Journalism or relevant field\nProficiency in MS Office\nExcellent verbal and written communication skills\nGood presentation skills\n\nInterested parties, please CLICK HERE to apply online.\n\nOr if you would like to have a further discussion about this role, please Whatsapp Hoyin Siu at 9862 0297.\n\nPlease note that only short-listed candidates will be notified. All information gathered will be treated in strict confidence and solely used for recruitment purposes.", "employment_types": ["Full Time", "Part Time", "Permanent", "Temporary", "Internship", "Freelance"], "selling_points": [], "locations": ["Kwun Tong"], "categories": ["Marketing / Public Relations", "Marketing - Marketing Communication"], "post_time": "2022-01-18T01:15:42Z", "salary": {"currency": "HKD", "max": 29999, "min": 20000, "period": "monthly", "term": null}, "salary_visible": true, "title_keywords": ["sales"], "responsibilities": ["evaluate", "operations", "reports"], "requirements": {"degrees": ["diploma"], "majors": ["journalism", "marketing", "communications"], "languages": [], "language_level": [], "hard_skills": ["inform", "presentations", "ms office"], "soft_skills": ["communication", "communication skills", "presentation skills"], "languages_combined": []}, "experience_required": {"duration": [], "field": []}}, {"job_id": "100003009045954", "location_code": "hk", "company": "ADECCO", "job_title": "Marketing Communication Executive (Project) (Event) (PR) (16K-25K)", "description": "Job Responsibilities:\n\nCommunicate with internal business units to support sales\u2019 need and implement marketing plan\nUplift brand awareness by maintaining international media relationship and grow digital presence\nImplement marketing events for HGC international business units, including conferences, webinars, customer networking events, etc.\nCoordinate with designer and copywriter to create social media content, videos, blogs, etc.\nPrepare marketing collaterals, including corporate presentation, brochure, website, newsletter, marketing campaigns\nSupport Ad-hoc tasks as required\n\nJob Requirements:\n\nDegree in marketing, marketing communications, business management or related discipline\n\nProficiency in English, both written and spoken. Proficiency in Mandarin is an advantage.\n\nFlexibility to communicate with colleagues/ vendors in a different time zones\n\nWe offer competitive salary package and career development opportunity. Free company coach is provided.\u00a0 Interested parties, please quote our reference number and apply with full resume, present and expected salary, by clicking \u201cAPPLY NOW\u201d.\u00a0\n\nWe are an equal opportunity employer and welcome applications from all qualified candidates. Information provided will be treated in strict confidence and only be used for consideration of your application for the relevant post within HGC Global Communications Limited. Personal data provided by job applicants will be used strictly according to our Personal Information Collection Statement, a copy of which will be available upon written request. Information of unsuccessful candidates will be destroyed within six months.", "employment_types": ["Full Time"], "selling_points": [], "locations": ["North Point"], "categories": ["Marketing / Public Relations", "Marketing - General / Support", "Marketing - Marketing Communication", "Public Relations - Event Management"], "post_time": "2022-01-13T09:14:12Z", "salary": {"currency": "HKD", "max": 19999, "min": 14000, "period": "monthly", "term": null}, "salary_visible": true, "title_keywords": ["executive"], "responsibilities": ["communicate with", "marketing events", "maintaining", "ad-hoc tasks", "marketing collaterals", "coordinate with", "website", "marketing plan", "conferences", "social media content", "marketing campaigns"], "requirements": {"degrees": ["degree"], "majors": ["marketing communications", "marketing", "business"], "languages": ["english", "mandarin"], "language_level": ["advantage", "proficiency"], "hard_skills": ["business management"], "soft_skills": [], "languages_combined": [{"language": "english", "language_level": ["proficiency"]}, {"language": "mandarin", "language_level": ["proficiency", "advantage"]}]}, "experience_required": {"duration": [], "field": []}}, {"job_id": "100003009050122", "location_code": "hk", "company": "HGC Global Communications Limited", "job_title": "Marketing Manager - International Business", "description": "You can enjoy:\u00a0\nComprehensive Medical and Life insurance coverage, including your spouse and children\nExclusive company pension schemes\nMarriage, Maternity and Paternity Leave\nExclusive shopping discount, Bazaar Sales for our people only\u00a0\nProfessional training and career advancement opportunities\nConvenient office location, less than 5 min. walk from MTR\nContemporary workplace with Onsite Clinic, Lactation Rooms, free drinks and chill out areas\nWell-equipped Gym inside our office building, plus fitness and interest class packages\nFree round-trip lunchtime shuttle bus services to Shatin\nResponsibilities:\n\nDevelop and execute CRM campaign and promotion\nPlan and execute loyalty program and engagement activity\nLiaise with strategic partners for joint promotion opportunities\nDesign marketing activities and store promotion in various store banners\nCoordinate with internal and external parties on POSM design, production and to ensure excellent execution of campaigns\nRequirements:\nUniversity graduate in Marketing or related disciplines\n4 years working experience in marketing, preferably in retail or FMCG industry\nDynamic, creative to cope with fast-paced working environment and able to work under pressure\nExcellent communication and organisation skills\nExcellent command of English & Chinese with strong interpersonal and problem solving skills\nLess experience will be considered as Marketing Executive\nAn attractive salary and benefit package will be offered. Interested parties please forward detailed resume stating expected salary to: People Department, PARKnSHOP (HK) Limited, Watson House, 1-5 Wo Liu Hang Road, Fo Tan, N.T. or email to us.\n\n\nWe are an equal opportunity employer and welcome applications from all qualified candidates. The information provided will be treated in strict confidence and be used only for consideration of your application for relevant / similar posts within the A.S. Watson Group. All personal data of unsuccessful applicants will be destroyed within 12 months from the date of application.", "employment_types": ["Full Time", "Permanent"], "selling_points": ["Develop digital presence to the brand", "Degree holder in marketing/communication", "Social media exposure"], "locations": ["Tsing Yi"], "categories": ["Marketing / Public Relations", "Marketing - Brand / Product Management", "Marketing - Marketing Communication", "Digital Marketing"], "post_time": "2022-01-14T09:48:49Z", "salary": {"currency": null, "max": null, "min": null, "period": "monthly", "term": null}, "salary_visible": false, "title_keywords": ["marketing manager"], "responsibilities": ["internal and external parties", "coordinate with", "design", "develop", "banners", "plan", "liaise with"], "requirements": {"degrees": ["university graduate"], "majors": ["related disciplines", "marketing"], "languages": ["english", "chinese"], "language_level": ["excellent"], "hard_skills": ["dynamic", "fmcg industry", "problem solving skills"], "soft_skills": ["communication", "dynamic", "organisation", "problem solving skills", "creative", "interpersonal", "work under pressure"], "languages_combined": [{"language": "english", "language_level": ["excellent"]}, {"language": "chinese", "language_level": ["excellent"]}]}, "experience_required": {"duration": ["4 years"], "field": ["marketing", "retail", "fmcg"]}}, {"job_id": "100003009048361", "location_code": "hk", "company": "PARKnSHOP", "job_title": "Senior Marketing Executive (CRM)", "description": "Responsibilities:\n\nResponsible for online and social media marketing\nPlan, organize and implement PR promotions\n\nRequirements:\n\n\nDegree holder in PR / Communications, Marketing or relevant disciplines\nAt least 1-2 years\u2019 relevant working experience, preferably in online marketing agencies, PR agencies or media\nExcellent interpersonal and communication skills in both written and spoken English & Chinese\nGood organization, independent with minimum supervision, ability to work under pressure and working on Public Holidays are required\nShopping mall promotion and on-line marketing experience, good knowledge in computer and internet applications are essential\n\nWe offer competitive salary package that will be commensurate with experience and qualifications. Interested parties are invited to send full resume stating contact telephone number, date available, present and expected salary to our recruitment email address.\n\n(Personal data provided will be used strictly in accordance with the Company\u2019s personal data policy which is available upon request.)", "employment_types": ["Full Time", "Permanent"], "selling_points": [], "locations": ["Shatin Area"], "categories": ["Marketing / Public Relations", "Marketing - Market Research", "Marketing - Marketing Communication"], "post_time": "2022-01-14T06:25:31Z", "salary": {"currency": null, "max": null, "min": null, "period": "monthly", "term": null}, "salary_visible": false, "title_keywords": ["senior marketing executive"], "responsibilities": ["social media", "plan"], "requirements": {"degrees": ["degree holder"], "majors": ["marketing", "communications"], "languages": ["english", "chinese"], "language_level": ["excellent"], "hard_skills": [], "soft_skills": ["communication skills", "independent", "interpersonal", "work under pressure"], "languages_combined": [{"language": "english", "language_level": ["excellent"]}, {"language": "chinese", "language_level": ["excellent"]}]}, "experience_required": {"duration": ["at least 1-2 years"], "field": ["media", "pr", "marketing", "relevant working experience"]}}, {"job_id": "100003009044896", "location_code": "hk", "company": "Harbour City Estates Ltd", "job_title": "ASSISTANT PROMOTIONS & MARKETING OFFICER (Ref: PR & Social Media Focus)", "description": "We Offer:\u00a0\n\n5-day work week\n6 days vaccination leave\nWork from home arrangement\nGroup medical, group life, body check and dental insurance coverage\n14 days annual leave up\nOvertime Allowance\nCompetitive pay and Discretionary bonus\nFriendly working environment with dynamic and talented team members\nSmart and casual attire (Monday to Friday)\nLearning and development opportunities\nConvenient office located near Tsim Sha Tsui MTR station\u00a0\n\nResponsibilities:\n\nAssist in credit card programs planning, implementation and post-program performance tracking\u00a0\nMerchant liaison for card offering and spending programs\nSource and launch merchant partnership offers relevant and good for the Company's business\nMonitor and research on market trend and competitors' activities\nPerform ad hoc duties or projects as assigned\n\nRequirements:\n\nDegree or above in marketing or related discipline\u00a0\nMinimum 1 year of working experience with Marketing experience, preferable in Financial Services, Insurance or Banking industry\nProficient in both written and spoken English and Chinese (both Cantonese and Mandarin)\nSound knowledge of Microsoft Office applications and Chinese Word Processing\nGood communication skills and well-organized with good sense of responsibility\u00a0\n\nWe offer 5-day work week, comprehensive training and rewarding career opportunities for ambitious individuals who are looking for challenges.\n\nInterested parties please send your application with our reference number and CV with expected salary and availability to \"Apply Now\".\n\n(All personal data collected will be used for recruitment purpose only.)", "employment_types": ["Full Time", "Permanent"], "selling_points": ["Degree holder in PR or related discipline", "At least 1-2 years\u2019 relevant working experience", "Excellent interpersonal and communication skills"], "locations": ["Tsim Sha Tsui"], "categories": ["Marketing / Public Relations", "Marketing - Marketing Communication", "Public Relations - General / Support", "Others"], "post_time": "2022-01-15T03:49:23Z", "salary": {"currency": null, "max": null, "min": null, "period": null, "term": null}, "salary_visible": false, "title_keywords": ["assistant", "marketing officer"], "responsibilities": [], "requirements": {"degrees": [], "majors": [], "languages": [], "language_level": [], "hard_skills": [], "soft_skills": [], "languages_combined": []}, "experience_required": {"duration": [], "field": []}}, {"job_id": "100003009049061", "location_code": "hk", "company": "AEON CREDIT SERVICE (ASIA) CO., LTD.", "job_title": "Senior Officer / Assistant Manager  - Marketing & Promotion (Job Ref:202122-76)", "description": "Responsibilities:\n\nLead the execution of marketing programs from start to finish, leveraging internal support and driving collaboration\nAnalyze customer insights, consumer trends, market analysis, and marketing best practices to build successful strategies\nWorking in partnership with the R&D team, develop product briefs and guide innovative direction to meet objectives for all product innovation and reinvention\nPresent ideas and final deliverables to internal and external teams, and communicate with senior leaders about marketing programs, strategies, and sales impact\nP&L responsibilities. Create, maintain, and conduct analytics sales/ profitability monitoring for assigned categories. Extract insights for future planning, complete with actionable proposals and recommendations\nWorking closely with Operation team on go-to-market plan. Leverage strong store network and well developed online platform to maximize transactions with consumers and contribute to improve CX\nManage ATL & BTL materials to promote Saint Honore brand image as well as festive and cake & bakery products. Create, maintain brand contents across multiple channels, and digital platforms\nDrive collaboration with external agencies and in-house designers to produce advertising, promotion, packaging and visual merchandising materials, as well as construct effective media plans and support PR and market research initiatives.\n\u00a0Requirements:\nUniversity graduate in Marketing, Business or related discipline;\nOver 10 years of solid experience in Retail, F&B or FMCG markets with 5 years supervisor experience gained from F&B industry is must;\nStrong analytical, organization and communication, effective time and project management skills;\nPassionate with food products development a definite asset.\n\u00a0Candidate with less experience will be considered as Assistant Marketing Manager.\n\n\nInterested parties, please forward your resume stating salary expectation and available date to us.\u00a0\nFor more information of Saint Honore Cake Shop, please visit\u00a0www.cr-asia.com\nAll applications will be treated in the strictest confidence. Personal data provided will be used for recruitment purpose only. The information collected might also be disclosed to other associated companies of the Fung Group for job matching of similar vacancies.\nThe provision of full and complete information in support of your application is necessary for selection purposes. Applicant has the right to request access to and correction of personal data collected from him/her in writing to the Human Resource Manager by post to P.O. Box 92408, Tsim Sha Tsui Post Office, Hong Kong.", "employment_types": ["Full Time", "Permanent"], "selling_points": ["Under AEON Group and Listed Co. in Hong Kong", "Financial Services Industry with WFH arrangement", "Permanent position. Good working environment TST"], "locations": ["Tsim Sha Tsui"], "categories": ["Marketing / Public Relations", "Marketing - Brand / Product Management", "Marketing - General / Support", "Marketing - Marketing Communication"], "post_time": "2022-01-14T08:00:47Z", "salary": {"currency": null, "max": null, "min": null, "period": "monthly", "term": null}, "salary_visible": false, "title_keywords": ["senior officer", "assistant manager"], "responsibilities": ["ideas", "merchandising", "transactions", "maintain", "plan", "plans", "advertising", "customer insights", "teams", "p&l", "develop", "visual", "monitoring", "market analysis", "contents", "consumer trends", "communicate with", "market research", "planning"], "requirements": {"degrees": ["university graduate"], "majors": ["business", "marketing"], "languages": [], "language_level": [], "hard_skills": ["project management"], "soft_skills": ["communication", "project management skills", "passionate"], "languages_combined": []}, "experience_required": {"duration": ["5 years", "10 years"], "field": ["f&b", "retail", "marketing", "fmcg"]}}, {"job_id": "100003009050218", "location_code": "hk", "company": "Saint Honore Cake Shop Ltd", "job_title": "Marketing Manager (Marketing and Category Management)", "description": "The incumbent will be responsible for the leasing & marketing execution and operation role mainly for 99 Pui To Road, an industrial building in Tuen Mun. They will also be involved in leasing activities in the same building and also other commercial, residential and industrial units in the Group.\n\nResponsibilities:\n\nOne man band for all marketing tasks including website modifications, weekly social media posts, designing and implementing online and physical marketing materials e.g. flyers, pamphlets, posters etc.\nOrganizing regular tenant events e.g. Christmas etc.\nProcurement and design of gifts and other marketing giveaways\nAssist in planning, developing and executing promotions and leasing strategies of the Company's property projects in Hong Kong\nConduct market research to develop an understanding of the competition, opportunities and customers\nDevelop and maintain good relationship with customers and estate agents\nLeasing of industrial and commercial units, including cold calling corporate tenants and agents\n\nRequirements:\n\nDegree holder or related disciplines with at least 3 years of marketing or leasing experience\nWorking knowledge of Adobe Photoshop and AI preferred for designing of marketing materials\nLeasing experience in commercial and industrial sectors a plus\nProactive, strong sense of responsibility, energetic, willing to learn\nGood interpersonal, communication and negotiation skills\nGood command of written/spoken English and Chinese with conversational Mandarin\nProficiency in MS Office applications\n\nWe offer attractive remuneration package, such as contract-end gratuity, discretionary performance bonus, medical & dental insurance, transport expense reimbursements etc. to the suitable candidate.", "employment_types": ["Full Time"], "selling_points": ["Lead the execution of marketing programs", "5 yrs supervisor exp. gained from F&B industry", "Passionate with food products development"], "locations": ["Shatin Area"], "categories": ["Marketing / Public Relations", "Management", "Marketing - Brand / Product Management", "Marketing - Marketing Communication"], "post_time": "2022-01-14T09:57:12Z", "salary": {"currency": null, "max": null, "min": null, "period": null, "term": null}, "salary_visible": false, "title_keywords": ["marketing manager"], "responsibilities": ["social media", "conduct market research", "website", "design", "developing", "develop", "maintain good relationship", "executing", "designing", "marketing materials", "planning"], "requirements": {"degrees": ["degree holder"], "majors": ["related disciplines", "marketing"], "languages": ["english", "chinese", "mandarin"], "language_level": ["conversational", "good command"], "hard_skills": ["plus", "adobe photoshop", "ms office", "ai"], "soft_skills": ["proactive", "sense of responsibility", "willing to learn", "communication", "negotiation skills", "energetic", "interpersonal"], "languages_combined": [{"language": "english", "language_level": ["good command"]}, {"language": "chinese", "language_level": ["good command"]}, {"language": "mandarin", "language_level": ["conversational", "good command"]}]}, "experience_required": {"duration": ["at least 3 years"], "field": ["related", "commercial", "marketing"]}}, {"job_id": "100003009046191", "location_code": "hk", "company": "Sage Properties Limited", "job_title": "Marketing & Leasing Officer", "description": "Responsibilities:\nManage online marketing platforms, including website, social media, media advertising and offline marketing collateral.\nMonitor social media interactions, issues and sentiment, respond to enquiries and comments.\nPlan and organize social media marketing campaigns, online advertising and events.\nDevelop promotion activities and materials.\nCoordinate and execute marketing tactics and action plans to achieve business goals.\nAssist in inventory control and coordinate the delivery arrangement.\nPrepare marketing research to improve marketing intelligence.\n\nRequirements:\n\nA Good personality, Positive attitude, well-organized, proactive, creative and result oriented.\nGood knowledge in social media platforms, Facebook, Instagram , youtube, google analytics, adv management.\u00a0\nHigh diploma or above in marketing, media, communications or related disciplines.\nAt least 1 year experience in marketing, strong understanding in social media for branding, mother and baby industry is an advantage.\nGood Chinese writing skills, Mandarin speaker is a plus.\nProficient in MS office and computer skills. Basic knowledge of design software (such as Photoshop/ Illustrator) is an advantage.\nCandidates with more experience will be consider as Senior Marketing Executive.\nBenefits:\n\n5-days work\nPerformance bonus\nStaff Discount on products\nMaternity Leave\nWe offer an attractive remuneration package to successful candidate. Please send your CV with full details including previous job experiences, expected salary, current salary and available date.\n\n\n\u00a0Personal information collected will be used for recruitment purpose only.", "employment_types": ["Full Time"], "selling_points": [], "locations": ["Wan Chai"], "categories": ["Marketing / Public Relations", "Marketing - General / Support", "Marketing - Marketing Communication", "Property / Real Estate", "Property Management"], "post_time": "2022-01-13T09:53:34Z", "salary": {"currency": null, "max": null, "min": null, "period": "monthly", "term": null}, "salary_visible": false, "title_keywords": ["leasing officer"], "responsibilities": ["social media", "business goals", "advertising", "comments", "monitor", "website", "develop", "coordinate", "marketing research", "inventory control", "plan", "marketing campaigns", "plans", "online advertising"], "requirements": {"degrees": ["high diploma or above"], "majors": ["related disciplines", "marketing", "communications"], "languages": ["chinese", "mandarin"], "language_level": ["good"], "hard_skills": ["google analytics", "plus", "basic", "illustrator", "writing skills", "computer skills", "photoshop", "facebook", "ms office"], "soft_skills": ["creative", "well-organized", "writing skills", "positive attitude", "result oriented", "proactive"], "languages_combined": [{"language": "chinese", "language_level": ["good"]}, {"language": "mandarin", "language_level": ["good"]}]}, "experience_required": {"duration": ["at least 1 year"], "field": ["social media", "marketing"]}}, {"job_id": "100003009049251", "location_code": "hk", "company": "New Faith Enterprise Company", "job_title": "Social Media Executive", "description": "Responsibilities:\n\nResponsible for planning, organizing and implementing promotional & marketing campaigns, art and cultural exhibitions, for the mall as well as the tenants\nHandle the preparation works and provide event logistics support for the whole marketing and promotion planning process\nPerform other duties as assigned\n\nRequirements:\n\nDegree holder in Marketing or related disciplines\nAt least 1-2 years\u2019 relevant working experience, preferably in event management\n\nExcellent interpersonal and communication skills in both written and spoken English & Chinese\nGood organizational skills, independent with minimum supervision, ability to work under pressure and working on festive holidays are required\nShopping mall promotion, O2O marketing and good knowledge in computer are essential\n\nWe offer competitive salary package that will be commensurate with experience and qualifications. Interested parties are invited to send full resume stating contact telephone number, date available, present and expected salary to our recruitment email address.\n\n(Personal data provided will be used strictly in accordance with the Company\u2019s personal data policy which is available upon request.)", "employment_types": ["Full Time"], "selling_points": [], "locations": ["Wong Tai Sin Area"], "categories": ["Marketing / Public Relations", "Marketing - Brand / Product Management", "Marketing - Marketing Communication", "Digital Marketing"], "post_time": "2022-01-15T03:50:16Z", "salary": {"currency": null, "max": null, "min": null, "period": "monthly", "term": null}, "salary_visible": false, "title_keywords": ["social media executive"], "responsibilities": ["perform other duties", "planning process", "logistics", "marketing campaigns", "planning"], "requirements": {"degrees": ["degree holder"], "majors": ["related disciplines", "marketing"], "languages": ["english", "chinese"], "language_level": ["excellent"], "hard_skills": [], "soft_skills": ["communication skills", "organizational skills", "independent", "interpersonal", "work under pressure"], "languages_combined": [{"language": "english", "language_level": ["excellent"]}, {"language": "chinese", "language_level": ["excellent"]}]}, "experience_required": {"duration": ["at least 1-2 years"], "field": ["management", "relevant working experience"]}}, {"job_id": "100003009050654", "location_code": "hk", "company": "Links International", "job_title": "Marketing Admin / Coordinator (One year contract)", "description": "Responsibilities\n\nSupervise the MTR Merchandising and Souvenirs\u2019 sales operation and performance, product procurement and development, financial administration, stock inventory and distribution logistics as well as support development and distribution of publicity materials (both online and offline)\nLiaise with external and internal parties on the execution of MTR Merchandising and Souvenirs\u2019 sales promotions, including creative agencies, suppliers, laboratory test companies, etc.\u00a0\nAssist in sales and promotion to MTR Mobile users and internal staff\nHandle daily enquiries and complaints related to MTR Merchandising and Souvenirs\u2019 sales business and provide possible resolutions and execution\n\nRequirements\n\nDegree in Marketing / Business Administration or a related discipline\u00a0\nA minimum of 2 year\u2019s relevant experience in marketing\nGood teamwork, organising, interpersonal and communication skills\nProficiency in written and spoken English and Chinese is essential\u00a0\n\nApplications\n\nYou are invited to apply online via http://www.mtr.com.hk/mtr_job_en or send in your CV stating the position (with reference number) you are applying for by mail to Human Resource Management Department, MTR Corporation, G.P.O. Box 9916, Hong Kong on or before\u00a027\u00a0January 2022.\u00a0\n\nFor other job openings, please visit MTR Corporation's website for more details. All information provided by applicants will be treated in strict confidence and used for recruitment purpose only.\n\nAll personal data of unsuccessful applicants will be retained for 12 months for future recruitment purpose and will then be destroyed.", "employment_types": ["Full Time", "Permanent"], "selling_points": ["Fortune Global 500 Companies", "Under Marketing CRM Department", "Immediate / Short notice preferred"], "locations": ["Not Specified"], "categories": ["Marketing / Public Relations", "Marketing - General / Support", "Marketing - Marketing Communication", "Others"], "post_time": "2022-01-14T11:07:15Z", "salary": {"currency": "HKD", "max": 16999, "min": 14000, "period": "monthly", "term": null}, "salary_visible": true, "title_keywords": ["coordinator", "admin"], "responsibilities": ["inventory", "merchandising", "logistics", "liaise with", "internal parties", "administration"], "requirements": {"degrees": ["degree"], "majors": ["marketing", "business administration"], "languages": ["english", "chinese"], "language_level": ["proficiency"], "hard_skills": [], "soft_skills": ["communication skills", "confidence", "teamwork", "interpersonal"], "languages_combined": [{"language": "english", "language_level": ["proficiency"]}, {"language": "chinese", "language_level": ["proficiency"]}]}, "experience_required": {"duration": ["minimum of 2 year"], "field": ["marketing", "relevant experience"]}}, {"job_id": "100003009048401", "location_code": "hk", "company": "MTR Corporation Limited", "job_title": "Marketing Supervisor (Ref: 22000024)", "description": "Jobs Highlights\n\nYoung international team with visionary mission\nFast track advancement opportunities\nFlexible working hours\n\nJob Descriptions\n\nJoin Us if you are :\n\nNative English Speakers especially overseas born Chinese\nBachelor's degree holder in any discipline, business-related disciplines preferred\nMature, self-motivated and willing to learn\nPositive, self-driven attitude to strive for excellence\n\nWe offer:\n\nBasic salary plus attractive commission package and comprehensive fringe benefits\nWell-structured and comprehensive training programs\n1 to 1 mentorship\nOpportunity to explore both individual and corporate business\nGain accreditation from the internationally acclaimed Million Dollar Round Table (MDRT) association.\nIncentive trips and overseas business conventions\nflexible training and working hours\n\nWe are a growing & leading international team, committed to nurture candidates who are passionate and dedicated in delivering qualitative services to different entities. We focus on exploring the tremendous potential EXPAT MARKET in Hong Kong through professional manner, where as many are of limited exposure to the concepts of risk and wealth management.\n\nWe provide opportunities on career development, achievements recognition and massive support within our ever-growing multi-cultural team.\n\nPersonal development is the key to a successful career.\n\nJob Nature :\n\nIdentify & cater for the financial needs of\u00a0 High-Net-Worth clients'\nConsultation on risk management, wealth protection, investment, MPF, retirement planning\nCorporate solution planning and employee benefits solutions for corporate clients\nUpdate clients with financial market news\nProvide quality after-sales services to maintain good customer relationship\n\nWe offer excellent career prospects and attractive remuneration package to the right candidates. Interested candidates please send your details with current and expected salary to us NOW.\n\nIf you have any queries on this position, please feel free to contact us through e-mail. The information provided by applicants will be treated in strict confidence and used solely for recruitment purpose. All applicants' information will be destroyed after 12 months.", "employment_types": ["Full Time"], "selling_points": ["Supervise the MTR Merchandising", "Degree in Marketing / Business Administration", "A minimum of 2 year\u2019s relevant experience"], "locations": ["Others"], "categories": ["Marketing / Public Relations", "Marketing - General / Support", "Marketing - Market Research", "Marketing - Marketing Communication"], "post_time": "2022-01-14T06:28:15Z", "salary": {"currency": null, "max": null, "min": null, "period": "monthly", "term": null}, "salary_visible": false, "title_keywords": ["supervisor"], "responsibilities": [], "requirements": {"degrees": ["bachelor", "degree holder"], "majors": ["related disciplines", "business"], "languages": ["english", "chinese"], "language_level": ["native"], "hard_skills": [], "soft_skills": ["flexible", "self-motivated", "willing to learn", "mature", "visionary", "strive for excellence", "driven", "positive"], "languages_combined": [{"language": "english", "language_level": ["native"]}, {"language": "chinese", "language_level": ["native"]}]}, "experience_required": {"duration": [], "field": []}}, {"job_id": "100003009046302", "location_code": "hk", "company": "Profile Search and Selection", "job_title": "Senior Digital Communication Manager", "description": "KNOWLEDGE TRANSFER AND ENTREPRENEURSHIP OFFICE\n\nProject Officer (two posts) (Ref. 22011403-JCS)\n\nDuties\n\nThe appointees will work under the Branding and Marketing Division and be required to:\n\n(a) implement and organize marketing events and activities, such as banquets, ceremonies, seminars, conferences, competitions, exhibitions, press conferences, delegation visits, etc.;\n\n(b) liaise and coordinate with relevant parties to ensure successful delivery of projects;\n\n(c) provide administrative support to the University\u2019s societies, committees, trade associations and meetings;\n\n(d) maintain website and social media channels;\n\n(e) prepare reports and project documentations including proposals and budget; and\n\n(f) perform any other duties as may be assigned by the Director of the Office or his delegates.\n\nWorking on irregular hours including evenings, Saturdays and Sundays, and occasional travel outside Hong Kong may be required.\n\nQualifications\n\nApplicants should:\n\n(a) have a recognized degree preferably in Communication, Marketing or Event Management, plus at least three years\u2019 relevant post-qualification working experience; or a recognized certificate or diploma or an equivalent qualification preferably in the said disciplines plus at least five years\u2019 relevant post-qualification working experience;\n\n(b) have sound knowledge of computer software applications, preferably with knowledge of and experience in MS Office applications;\n\n(c) have a good command of both written and spoken English and Chinese, with fluency in Putonghua being an advantage;\n\n(d) have good planning, organizational and problem-solving skills;\n\n(e) be attentive to details and a good team player;\n\n(f) be able to work independently and meet tight deadlines; and\n\n(g) have good interpersonal and communication skills.\n\nShortlisted candidates will be invited to sit for a written test.\n\nApplicants who have responded to the previous advertisement need not re-apply.\n\nRemuneration and Conditions of Service\n\nA highly competitive remuneration package will be offered.\u00a0 Appointment will be on a one-year gratuity-bearing contract.\u00a0\u00a0 Applicants should state their current and expected salary in the application.\u00a0\n\nApplication\n\nPlease send a completed application form by post to Human Resources Office, 13/F, Li Ka Shing Tower, The Hong Kong Polytechnic University, Hung Hom, Kowloon, Hong Kong or via email by clicking \"Apply Now\". Application forms can be downloaded from https://www.polyu.edu.hk/hro/careers/guidelines_and_forms/forms. If a separate curriculum vitae is to be provided, please still complete the application form which will help speed up the recruitment process. Consideration of applications will commence on 21 January 2022 until the positions are filled. The University\u2019s Personal Information Collection Statement for recruitment can be found at https://www.polyu.edu.hk/hro/careers/guidelines_and_forms/pics_for_recruitment.\n\nPolyU is an equal opportunity employer committed to diversity and inclusivity.\u00a0 All qualified applicants will receive consideration for employment without regard to gender, ethnicity, nationality, family status or physical or mental disabilities.", "employment_types": ["Full Time", "Permanent"], "selling_points": ["Digital Marketing", "Internal Communication", "Global Asset Manager"], "locations": ["Not Specified"], "categories": ["Marketing / Public Relations", "Marketing - Brand / Product Management", "Marketing - Marketing Communication", "Digital Marketing"], "post_time": "2022-01-13T10:23:53Z", "salary": {"currency": null, "max": null, "min": null, "period": "monthly", "term": null}, "salary_visible": false, "title_keywords": ["manager"], "responsibilities": ["liaise", "marketing events", "social media", "any other duties", "prepare reports", "management", "software", "budget", "coordinate with", "website", "communication", "conferences", "maintain", "recruitment", "provide administrative support", "recruitment process", "planning"], "requirements": {"degrees": ["certificate", "diploma", "degree"], "majors": ["marketing"], "languages": ["putonghua", "english", "chinese"], "language_level": ["fluency", "advantage", "good command"], "hard_skills": ["plus", "c", "problem-solving skills", "documentations", "ms office"], "soft_skills": ["communication skills", "good team player", "work independently", "meet tight deadlines", "attentive to details", "organizational", "communication", "committed", "problem-solving skills", "interpersonal"], "languages_combined": [{"language": "putonghua", "language_level": ["fluency", "advantage", "good command"]}, {"language": "english", "language_level": ["advantage", "good command"]}, {"language": "chinese", "language_level": ["advantage", "good command"]}]}, "experience_required": {"duration": ["at least five years", "at least three years"], "field": ["management", "marketing", "post-qualification"]}}, {"job_id": "100003009041976", "location_code": "hk", "company": "Steve Leung Designers Ltd", "job_title": "Senior Communications Executive/ Communications Executive", "description": "\u5c97\u4f4d\u804c\u8d23\uff1a\n\n1\u3001\u5236\u8ba2\u9500\u552e\u7b56\u7565\uff1a\u8fdb\u884c\u5e02\u573a\u9884\u6d4b\uff0c\u5236\u8ba2\u62d3\u5c55\u53ca\u92b7\u552e\u7b56\u7565\n\n2\u3001\u6267\u884c\u9500\u552e\u7b56\u7565\uff0c\u7ba1\u7406\u5e76\u6307\u5bfc\u9500\u552e\u56e2\u961f\uff0c\u8fbe\u6210\u5e02\u573a\u76ee\u6807\u3001\u5b8c\u6210\u56de\u6b3e\n\n3\u3001\u9500\u552e\u4f53\u7cfb\u7ba1\u7406\uff1a\u6839\u636e\u516c\u53f8\u9500\u552e\u7b56\u7565\uff0c\u5efa\u7acb\u9500\u552e\u7f51\u7edc\u53ca\u6e20\u9053\u7ba1\u7406\n\n4\u3001\u5e02\u573a\u63a8\u5e7f\uff1a\u5efa\u7acb\u7cbe\u51c6\u7684\u5e02\u573a\u63a8\u5e7f\u6d3b\u52a8\uff0c\u8425\u9020\u5e02\u573a\u73af\u5883\uff0c\u63d0\u5347\u9879\u76ee\u4e0e\u4ea7\u54c1\u54c1\u724c\uff0c\u652f\u6301\u9500\u552e\u589e\u957f\n\n5\u3001\u5ba2\u6237\u5173\u7cfb\u7ba1\u7406\uff1a\u901a\u8fc7\u5404\u79cd\u670d\u52a1\u6d3b\u52a8\u63d0\u9ad8\u5ba2\u6237\u6ee1\u610f\u5ea6\uff0c\u5de9\u56fa\u5ba2\u6237\u5173\u7cfb\u5e73\u53f0\uff0c\u638c\u63e1\u7ec8\u7aef\u5ba2\u6237\n\n\u4efb\u804c\u8981\u6c42\uff1a\n\n1\u3001\u672c\u79d1\u53ca\u4ee5\u4e0a\u5b66\u5386\uff0c5\u5e74\u4ee5\u4e0a\u5546\u4e1a\u9879\u76ee\u3001\u516c\u5bd3\u8425\u9500\u8d1f\u8d23\u4eba\u7ecf\u9a8c\n\n2\u3001\u5177\u77e5\u540d\u5f00\u53d1\u5546\u4e00\u3001\u4e8c\u7ebf\u57ce\u5e02\u5927\u578b\u7efc\u5408\u4f53\u9879\u76ee\u7d93\u9a57\n\n3\u3001\u654f\u9510\u7684\u5e02\u573a\u610f\u8bc6\u3001\u5e94\u53d8\u80fd\u529b\u3001\u72ec\u7acb\u5f00\u62d3\u5e02\u573a\u7684\u80fd\u529b\n\n4\u3001\u4f18\u79c0\u7684\u56e2\u961f\u80fd\u529b\u3001\u5b66\u4e60\u80fd\u529b\u3001\u6c9f\u901a\u80fd\u529b\u3001\u534f\u8c03\u80fd\u529b\u548c\u9886\u5bfc\u6c34\u5e73\uff0c\u5584\u4e8e\u534f\u8c03\u8425\u9500\u56e2\u961f\n\n5\u3001\u5177\u5907\u77e5\u540d\u623f\u5730\u4ea7\u9805\u76ee\u6210\u529f\u64cd\u76e4\u53ca\u9500\u552e\u4e1a\u7ee9\u80cc\u666f\u8005\u4f18\u5148", "employment_types": ["Full Time"], "selling_points": [], "locations": ["Kowloon Bay"], "categories": ["Marketing / Public Relations", "Marketing - Brand / Product Management", "Marketing - Marketing Communication", "Public Relations - Event Management"], "post_time": "2022-01-12T04:57:18Z", "salary": {"currency": null, "max": null, "min": null, "period": "monthly", "term": null}, "salary_visible": false, "title_keywords": ["executive"], "responsibilities": [], "requirements": {"degrees": [], "majors": [], "languages": [], "language_level": [], "hard_skills": [], "soft_skills": [], "languages_combined": []}, "experience_required": {"duration": [], "field": []}}, {"job_id": "100003009056012", "location_code": "hk", "company": "Match Talent Limited", "job_title": "\u623f\u5730\u4ea7\u8425\u9500\u603b\u76d1", "description": "Responsibilities:\n\nYou will be responsible for managing and engaging with the organization\u2019s online community (Discord, Telegram, Twitter, Instagram, Facebook, Youtube, etc.) in a way that builds brand awareness and a sense of community\nYou will work cross-functionally with partners while focusing on engagement, enjoyment, and growth\nEngage with DeFi, Crypto and NFT communities daily through various online channels: Discord, Telegram, Twitter, etc\nIncrease brand awareness and community engagement\u00a0\nListen, gather and share the community\u2019s feedback and opinions with the team\nTrack community sentiment and provide actionable reports and recommendations\nRespond to user questions, comments, and concerns in a timely manner\nEnforce strict community rules, identify and remove bots\nHelp build and scale data pipelines for a rapidly growing global organization\nHelp build social/community measurement, attribution, and modeling\nBuild and maintain BI/dashboards and reports and also respond to ad-hoc requests\n\nRequirements:\n\n1-3 years of community management experience in managing online communities on Telegram and Discord\nThis person MUST have actual experience in the blockchain, crypto, and NFT space\nProven record of community engagement and management in the crypto, DeFi space\nStrong experience with Telegram and Discord is a must\nExcellent written and verbal communication skills\nExperience identifying and delivering helpful community content\nA creative, strategic approach to community growth and engagement", "employment_types": ["Full Time", "Permanent"], "selling_points": ["Strong Real Estate Company", "13 months pay", "Five-day work"], "locations": ["Others - China"], "categories": ["Marketing / Public Relations", "Management", "Marketing - Marketing Communication", "Property / Real Estate", "Others"], "post_time": "2022-01-18T03:11:30Z", "salary": {"currency": "HKD", "max": 159999, "min": 120000, "period": "monthly", "term": null}, "salary_visible": true, "title_keywords": [], "responsibilities": ["online channels", "data", "comments", "a timely manner", "measurement", "maintain", "reports", "ad-hoc requests", "facebook"], "requirements": {"degrees": [], "majors": [], "languages": [], "language_level": [], "hard_skills": ["blockchain", "crypto"], "soft_skills": ["communication skills", "creative"], "languages_combined": []}, "experience_required": {"duration": ["1-3 years"], "field": ["management"]}}, {"job_id": "100003009047989", "location_code": "hk", "company": "IPG Mediabrands (HK) Limited", "job_title": "Media Buyer / Senior Buyer (Buying & Operation Team)", "description": "Requirements:\n\n\nBachelor\u2019s degree, preferably major in Marketing / Business Administration / Event Management\nSome marketing or administration experience preferred, fresh graduates will also be considered\nFamiliar with PC software e.g. MS Word, Excel & Chinese Word Processing\nKnowledge in using Photoshop, Illustrator and HTML would be an advantage\nWilling to work overtime, irregular hours and during weekends / public holidays\nProven English proficiency\n\nResponsibilities:\n\n\nProvide administrative support to mall promotions team\nPrepare and organize marketing materials\nManage warehouse, inventory and procurement logistics\nLiaise with vendors and contractors\nWork closely with agencies and tenants in promoting the shopping mall\n\n(Candidates with more experience will be considered for Assistant Promotions Officer.)\n\nGood remuneration and attractive fringe benefits will be offered to the successful applicant. Interested parties please apply with full resume, present and expected salary, available date by clicking \"Apply Now\".\n\nFor further information, please visit our company website: www.shkp.com.\n\nWe are an equal opportunity employer and welcome applications from all qualified candidates. All personal data collected will be used for recruitment purpose only.\u00a0 Applicants not hearing from us within 3 months may consider their applications unsuccessful.\u00a0 All personal data collected will be destroyed within 24 months.", "employment_types": ["Full Time"], "selling_points": [], "locations": ["Quarry Bay"], "categories": ["Media & Advertising", "Account Servicing", "Media Buying", "Marketing / Public Relations", "Marketing - Marketing Communication"], "post_time": "2022-01-14T04:40:43Z", "salary": {"currency": null, "max": null, "min": null, "period": "monthly", "term": null}, "salary_visible": false, "title_keywords": [], "responsibilities": ["marketing materials", "inventory", "liaise with", "logistics", "provide administrative support"], "requirements": {"degrees": ["degree", "bachelor"], "majors": ["marketing", "business administration"], "languages": ["english", "chinese"], "language_level": ["proficiency"], "hard_skills": ["excel", "chinese word processing", "ms word", "illustrator", "html", "pc", "photoshop"], "soft_skills": ["work overtime"], "languages_combined": [{"language": "english", "language_level": ["proficiency"]}, {"language": "chinese", "language_level": []}]}, "experience_required": {"duration": [], "field": ["marketing", "administration"]}}, {"job_id": "100003009046060", "location_code": "hk", "company": "The Hong Kong Institute Of Bankers", "job_title": "Officer - Marketing Communications", "description": "Our client is a well-regarded FMCG Brand. They are currently expanding their global business and seeking for a Digital Marketing Manager to join their global marketing team.\n\nClient Details\n\nOur client is a well-regarded FMCG Brand. They are currently expanding their global business and seeking for a Digital Marketing Manager to join their global marketing team. The position is the team leader to plan and implement global digital marketing campaigns and work closely with global team to develop digital marketing frameworks.\n\nDescription\n\nOur client is a well-regarded FMCG Brand. They are currently expanding their global business and seeking for a Digital Marketing Manager to join their global marketing team. The position is the team leader to plan and implement global digital marketing campaigns and work closely with global team to develop digital marketing frameworks.\n\nProfile\n\nThe successful candidate would be an experienced marketing manager for multinational company. Candidate with FMCG, Health and Beauty or pharmaceutical portfolio will be considered first. Our client is looking for a creative and brand thinking person with outstanding leadership skill to join them as a team leader. Public speaking and presentation ability are highly valued to this role. Fluency in English and Cantonese is required. Degree level qualification in marketing, business studies, or other related subjects is preferred.\n\nJob Offer\n\nWork for a global company that provides you with opportunity to expand your career. You will be provided with an attractive salary package and compensation.\n\nTo apply online please click the 'Apply' button below. For a confidential discussion about this role please contact Smania Wu on +852 3412 4858.", "employment_types": ["Full Time", "Permanent"], "selling_points": ["objectives of branding & promotion campaigns", "Draft stakeholders\u2019 communication", "Support production of Institute\u2019s publications"], "locations": ["Sheung Wan"], "categories": ["Marketing / Public Relations", "Marketing - Brand / Product Management", "Marketing - General / Support", "Marketing - Marketing Communication"], "post_time": "2022-01-13T09:30:52Z", "salary": {"currency": null, "max": null, "min": null, "period": "monthly", "term": null}, "salary_visible": false, "title_keywords": ["officer"], "responsibilities": ["digital marketing campaigns", "develop", "digital marketing", "contact", "plan"], "requirements": {"degrees": ["degree"], "majors": ["business", "marketing"], "languages": ["cantonese", "english"], "language_level": ["fluency"], "hard_skills": [], "soft_skills": ["leadership skill", "creative", "presentation"], "languages_combined": [{"language": "cantonese", "language_level": ["fluency"]}, {"language": "english", "language_level": ["fluency"]}]}, "experience_required": {"duration": [], "field": []}}, {"job_id": "100003009051221", "location_code": "hk", "company": "Match Talent Limited", "job_title": "Community Manager (NFT)", "description": "Job Responsibilities:\n\nAssist in\u00a0developing tactical marketing strategies which align with the business plan\nCreate\u00a0story and content for marketing collaterals include website, eShop, EDM and social media platforms like FB, IG, WeChat\nPrepare\u00a0marketing collaterals, trainings, presentations, tent cards, posters, etc.\nConduct\u00a0market intelligence & marketing analysis on marketing campaigns\nBuild\u00a0relationships with clients and develop new target segments\nLiaise\u00a0and connect closely with internal stakeholders, external agencies and business partners on marketing activities and projects\nHandle\u00a0departmental hotline, answer customer enquiries and follow-up\nProvide\u00a0support to Marketing Department on daily operation and all marketing events and promotions\nPerform any ad-hoc duties as assigned\nJob Requirements:\n\nBachelor degree / Higher Diploma in Marketing or business related discipline is preferred\nAt least 2 years of relevant experience in Marketing\nPrior\u00a0experience in healthcare, servicing, insurance and brokerage industry is advantageous\nKnowledge\u00a0of website, SEO, SEM practices and social media metrics\nUp-to-date\u00a0on the latest trends and technologies in digital marketing\nIndependent,\u00a0responsible, detail-oriented, good time management, a dedicated team player and self-motivated\nGood command in written English and Chinese\nImmediately available will be advantageous\nCandidate with less experience will be considered as Marketing Assistant\nWe offer competitive remuneration package to right candidate. Please submit your resume with expected salary to HR Department (Data collected will be used for the purpose of recruitment only.)", "employment_types": ["Part Time", "Contract", "Freelance"], "selling_points": ["Increase brand awareness and community engagement", "Creative, strategic approach to community growth", "Flexibility working hours"], "locations": ["Central"], "categories": ["Marketing / Public Relations", "Marketing - Marketing Communication", "Public Relations - Copy-writing", "Digital Marketing"], "post_time": "2022-01-15T05:15:11Z", "salary": {"currency": null, "max": null, "min": null, "period": "monthly", "term": null}, "salary_visible": false, "title_keywords": ["manager"], "responsibilities": ["liaise", "marketing events", "provide support", "marketing strategies", "edm", "customer enquiries", "analysis", "marketing collaterals", "social media platforms", "developing", "website", "presentations", "develop", "daily operation", "marketing campaigns", "ad-hoc duties", "business plan"], "requirements": {"degrees": ["diploma", "degree", "bachelor"], "majors": ["business", "marketing"], "languages": ["english", "chinese"], "language_level": ["good command"], "hard_skills": ["seo", "sem"], "soft_skills": ["self-motivated", "independent", "responsible", "detail-oriented", "team player", "time management"], "languages_combined": [{"language": "english", "language_level": ["good command"]}, {"language": "chinese", "language_level": ["good command"]}]}, "experience_required": {"duration": ["at least 2 years"], "field": ["healthcare", "brokerage", "marketing", "relevant experience", "insurance"]}}, {"job_id": "100003009046555", "location_code": "hk", "company": "Sun Hung Kai Properties Ltd", "job_title": "ASSISTANT PROMOTIONS OFFICER / PROMOTIONS ASSISTANT - SHOPPING MALL", "description": "We are seeking a motivated professional who is experienced in government policy and advocacy to enhance our efforts in promoting environmental sustainability to business and other stakeholders in Hong Kong. The role will supervise and manage research and run high impact collaborative projects with key players to influence the public policy framework.\u00a0\n\nKey Responsibilities:\n\n\nIdentify priority environmental issues that will benefit from advocacy to Government by the business community\nProactively prepare government policy submissions or reports, and formulate responses to public consultations\nDevise, execute, steer research and business collaborative projects including preparation of research reports, guides, tools, and programmes in collaboration with other internal departments, where appropriate\nDevelop quality content for events and facilitate discussions at conferences, seminars etc. relating to public policy and advocacy topics\nFormulate quality content for communications initiatives and write opinion pieces\nManage BEC\u2019s Advisory Groups to obtain members engagement in and input into policy advocacy topics\nLiaise and maintain good relations with members, government officials, NGOs and other stakeholders on public policy and advocacy areas\nBuild and manage relationships with key BEC partners\nPrepare and manage team budget and seek to raise funds as necessary\nLead and supervise team members including interns\n\nRequirements:\n\n\nBachelor\u2019s degree or above in Environmental Management, Public Policy or related disciplines\nA minimum of 10 years working experience, with at least 5 in environmental and sustainability related areas or in public policy research\nPossess passion in environmental management as a career and drive to promote sustainability as a corporate value\nExcellent written and spoken English. Ability to speak (Cantonese) and write Chinese is an advantage\nExcellent skills in policy submission preparation and report writing\nExcellent presentation, interpersonal and communication skills\nExcellent analytical and prioritisation skills\nVersatile with strong ability to multi-task and work under pressure\nA team player\n\nHow to Apply:\u00a0\n\nBEC is an equal opportunity employer and offers attractive career prospects to the successful candidate. Please click \u201cAPPLY NOW\u201d to submit your full resume including current and expected salary and date of availability.\n\nApplicants who do not hear from us within 6 weeks from the date of this advertisement may consider their applications unsuccessful. All information received including the CVs will be filed for future reference.\u00a0 Personal data will be used strictly for recruitment related purposes only and retained for no more than six months.", "employment_types": ["Full Time", "Permanent"], "selling_points": ["Prepare and organize marketing activities", "Handle public relations work of the activities", "Work closely with agencies and tenants"], "locations": ["Not Specified"], "categories": ["Marketing / Public Relations", "Marketing - Marketing Communication", "Public Relations - Event Management", "Others", "Student / Fresh Graduate / No Experience"], "post_time": "2022-01-13T13:54:45Z", "salary": {"currency": null, "max": null, "min": null, "period": null, "term": null}, "salary_visible": false, "title_keywords": ["officer", "assistant"], "responsibilities": ["liaise", "budget", "quality", "environmental issues", "supervise team members", "develop", "conferences", "government policy", "reports", "maintain"], "requirements": {"degrees": ["degree or above", "bachelor"], "majors": ["related disciplines", "public policy"], "languages": ["cantonese", "english", "chinese"], "language_level": ["advantage", "excellent"], "hard_skills": ["no"], "soft_skills": ["communication skills", "multi-task", "passion in", "versatile", "presentation", "team player", "interpersonal", "work under pressure"], "languages_combined": [{"language": "cantonese", "language_level": ["advantage"]}, {"language": "english", "language_level": ["excellent"]}, {"language": "chinese", "language_level": ["advantage"]}]}, "experience_required": {"duration": ["minimum of 10 years"], "field": ["related", "research", "environmental", "sustainability"]}}, {"job_id": "100003009055828", "location_code": "hk", "company": "Michael Page", "job_title": "Digital Marketing Manager - FMCG Global Marketing", "description": "Assistant\n\nThe Hong Kong Investment Funds Association (\u201cHKIFA\u201d) is a non-profit-making organization that represents the fund management industry in Hong Kong.\u00a0 www.hkifa.org.hk.\u00a0 We aim to recruit a high caliber candidate who will play a key role in the following areas.\n\nResponsibilities:\n\nThe main responsibilities include, amongst others:\n\nl\u00a0\u00a0Provide support to meetings (including planning, preparing agendas/papers, managing meeting logistics, taking minutes/notes, and following up to implement the decisions reached at meetings);\n\nl\u00a0\u00a0Perform desk-top research related to specific topics, and prepare papers/reports accordingly;\n\nl\u00a0\u00a0Liaise with member firms to solicit and collate inputs to prepare consultation responses and prepare reports/white papers for submission to the authorities/regulators or other stakeholder groups;\n\nl\u00a0\u00a0Assist in website/social media maintenance, and prepare materials for posting; and\n\nl\u00a0\u00a0Assist in administrative/ad hoc tasks as required.\n\nAttributes and qualities:\n\nl\u00a0\u00a0University graduate;\n\nl\u00a0Experience in capital markets and ESG a plus; \u00a0\n\nl\u00a0\u00a0Strong writing skills \u2013 both English and Chinese;\n\nl\u00a0\u00a0Proactive, detail-oriented and be able to take on multi-tasks; and\n\nl\u00a0\u00a0Have excellent PC skills.\n\nInterested parties please email to Hong Kong Investment Funds Association", "employment_types": ["Full Time", "Permanent"], "selling_points": ["Digital Marketing", "Global Exposure", "Career Growth Opportunities"], "locations": ["Not Specified"], "categories": ["Marketing / Public Relations", "Management", "Marketing - Marketing Communication", "Digital Marketing"], "post_time": "2022-01-18T02:59:27Z", "salary": {"currency": null, "max": null, "min": null, "period": "monthly", "term": null}, "salary_visible": false, "title_keywords": ["digital marketing manager"], "responsibilities": ["social media", "management", "provide support", "prepare reports", "maintenance", "ad hoc tasks", "website", "logistics", "reports", "liaise with", "planning"], "requirements": {"degrees": ["university graduate"], "majors": [], "languages": ["english", "chinese"], "language_level": [], "hard_skills": ["plus", "pc skills", "maintenance", "writing skills"], "soft_skills": ["multi-tasks", "proactive", "writing skills", "detail-oriented"], "languages_combined": [{"language": "english", "language_level": []}, {"language": "chinese", "language_level": []}]}, "experience_required": {"duration": [], "field": ["capital markets"]}}, {"job_id": "100003009051412", "location_code": "hk", "company": "Medifast (Hong Kong) Limited", "job_title": "Marketing Executive / Marketing Assistant", "description": "Job Description\uff1a\u00a0\n\nThis position is responsible for providing secretarial support to the Senior Director of company's agency team, on handling paperwork, scheduling meetings and preparing meeting material.\u00a0\n\n\nResponsibilities:\u00a0\n\n\u2022 Provide a full spectrum of secretarial and administrative support to Senior Director, including typing of documents, emails and reports, etc.\n\u2022 Manage and organise daily schedules and business appointment, etc.\n\u2022 Providing administrative support, etc.\u00a0\n\u2022 Recruiting management for the team\n\n\nRequirements:\u00a0\n\n\u2022 Ability to multi-tasking, prioritise and adjust with change\n\u2022 Willing to learn, actively handle tasks and have strong mobility\n\u2022 Ability to manage sensitive and confidential information with discretion and diplomacy\n\u2022 Proficiency in Microsoft Office Suite (Outlook, Word, Excel, PowerPoint)\n\u2022 Mandarin, Cantonese and English fluency, both written and verbal are required\n\n\u00a0", "employment_types": ["Full Time", "Permanent"], "selling_points": [], "locations": ["Causeway Bay"], "categories": ["Marketing / Public Relations", "Marketing - General / Support", "Marketing - Market Research", "Marketing - Marketing Communication"], "post_time": "2022-01-15T15:14:05Z", "salary": {"currency": null, "max": null, "min": null, "period": "monthly", "term": null}, "salary_visible": false, "title_keywords": ["marketing assistant", "marketing executive"], "responsibilities": ["management", "administrative support", "schedules", "providing secretarial support", "scheduling", "reports"], "requirements": {"degrees": [], "majors": [], "languages": ["cantonese", "english", "mandarin"], "language_level": ["fluency"], "hard_skills": ["excel", "word", "powerpoint", "microsoft office suite", "outlook"], "soft_skills": ["willing to learn", "prioritise", "multi-tasking", "sensitive", "mobility"], "languages_combined": [{"language": "cantonese", "language_level": ["fluency"]}, {"language": "english", "language_level": ["fluency"]}, {"language": "mandarin", "language_level": ["fluency"]}]}, "experience_required": {"duration": [], "field": []}}, {"job_id": "100003009049649", "location_code": "hk", "company": "Business Environment Council Limited", "job_title": "Head - Policy & Research (Job ref. no.:BEC/2022/1-JB)", "description": "Responsibilities:\n\nCo-ordinate and liaise with both internal and external parties for implementation of\u00a0 marketing projects, events and press conference, etc.\u00a0\nAssist sales directors in planning and implementing advertising and marketing campaigns for development projects, newly released or second-hand, local or overseas.\nWork with designers to prepare online or print materials.\nCo-ordinate all kinds of marketing materials with good project management skills .\nOutdoor work is required.\n\nRequirements:\n\nDegree holder in Marketing or other related disciplines\u00a0\n3-5 year's or above related work experience in Marketing field\u00a0\nPleasant, proactive and independent with good time management and communication skills\u00a0\nProficiency in MS Office\nGood command of both written English and Chinese\u00a0\nKnowledge on maintaining social media platform is an advantage\nAttentive to detail, good team player\nWilling to work under pressure and overtime\u00a0\nBusiness travel may require", "employment_types": ["Full Time", "Permanent"], "selling_points": ["A minimum of 10 years working experience", "At least 5 in environmental & sustainability areas", "Possess passion in environmental mgt as a career"], "locations": ["Kowloon City"], "categories": ["Sciences, Lab, R&D", "Environmental Science / Waste Management", "Marketing / Public Relations", "Marketing - Marketing Communication", "Research & Development (R&D)"], "post_time": "2022-01-14T10:38:21Z", "salary": {"currency": null, "max": null, "min": null, "period": "monthly", "term": null}, "salary_visible": false, "title_keywords": [], "responsibilities": ["marketing materials", "outdoor work", "advertising", "internal and external parties", "marketing projects", "implementation", "project management", "marketing campaigns", "liaise with", "planning"], "requirements": {"degrees": ["degree holder"], "majors": ["related disciplines", "marketing"], "languages": ["english", "chinese"], "language_level": ["good command"], "hard_skills": ["ms office"], "soft_skills": ["communication skills", "good team player", "proactive", "independent", "attentive to detail", "pleasant", "time management", "work under pressure"], "languages_combined": [{"language": "english", "language_level": ["good command"]}, {"language": "chinese", "language_level": ["good command"]}]}, "experience_required": {"duration": ["3-5 year"], "field": ["related", "marketing"]}}, {"job_id": "100003009051519", "location_code": "hk", "company": "Hong Kong Investment Funds Association", "job_title": "Assistant", "description": "Our client is a reputable bank in Hong Kong, is looking for a high caliber to join the group.,\n\nResponsibilities:\n\nManager programs and events execution to deliver corporate communication strategies and public affairs management.\nEnhance branding and corporate image of the Bank by maintaining strong relationships with media, business partners, and internal & external stakeholders.\nHandle all internal and external corporate literature including corporate website, social media, press releases, corporate publications and other presentation materials.\n\nRequirements:\n\nDegree holder in Communications, Journalism, Public Relations or Marketing related disciplines.\nAt least 5-8 years of solid experience in related fields.\nExcellent planning and organizational skills with strong time and project management.\nGood team player with strong analytical capability and presentation skills.\nSelf-motivated and proactive in taking the initiative, able to work under pressure and meet tight deadlines.\nStrong proficiency in both written and verbal communication skills in English and Chinese including Putonghua is a must.\nCandidates with less experience will be considered as Corporate Communications Manager.\n\nInterested parties please direct contact Ms Eppie Lee at 3997 3928 or contact eppie[at]connersconsulting[dot]com\n\nOnly shortlisted candidates will be notified.\u00a0\nApplicants who are not contacted within two weeks may consider their applications unsuccessful.\nAll data collected will be used for recruitment purpose only & will be used strictly confidential.\n\nConners Consulting Limited\n\n2005 Kai Tak Commercial Building 317 Des Voeux Road Central Hong Kong\nTel: (852) 3996 8090\u00a0\nWebsite:\u00a0http://www.connersconsulting.com/", "employment_types": ["Full Time"], "selling_points": ["excellent writing skills - Eng/Chin", "multi-tasks, detail-oriented", "excellent PC skills"], "locations": ["Central"], "categories": ["Accounting", "Accounting Clerk / Supervisor", "Finance / Accounting Manager", "Marketing / Public Relations", "Marketing - Marketing Communication"], "post_time": "2022-01-16T21:50:28Z", "salary": {"currency": null, "max": null, "min": null, "period": "monthly", "term": null}, "salary_visible": false, "title_keywords": ["assistant"], "responsibilities": ["social media", "management", "maintaining", "website", "communication"], "requirements": {"degrees": ["degree holder"], "majors": ["journalism", "related disciplines", "marketing", "communications"], "languages": ["putonghua", "english", "chinese"], "language_level": ["proficiency"], "hard_skills": ["project management"], "soft_skills": ["organizational skills", "self-motivated", "good team player", "meet tight deadlines", "communication skills", "project management", "presentation skills", "proactive", "initiative", "work under pressure"], "languages_combined": [{"language": "putonghua", "language_level": []}, {"language": "english", "language_level": ["proficiency"]}, {"language": "chinese", "language_level": ["proficiency"]}]}, "experience_required": {"duration": ["at least 5-8 years"], "field": ["related"]}}, {"job_id": "100003009054972", "location_code": "hk", "company": "Icon Wealth Management Company", "job_title": "Personal Assistant to Director", "description": "Duties\nResponsible for writing, editing, and proofreading marketing materials\u00a0\nPrepare and analyze information and data for new business development and project management\nPerform general reception duties and administrative support to office daily operation\nManage enquiries from internal and external parties\nWork on ad-hoc projects and perform any other duties as assigned.\nRequirements\n\n\nA Bachelor\u2019s degree or equivalent\nExcellent written and spoken English skills\nCompetent PC skills in MS Word, Excel, Powerpoint, and Chinese and English word processing\nExcellent analytical, problem-solving and communication skills\nGood organisational and interpersonal skills\nSelf-motivated, attentive to details and multi-task oriented\nAbility to work under tight schedule is essential\nSalary and Conditions of Service\nRemuneration package will be highly competitive, commensurate with qualifications and experience.\u00a0 Initial appointment will be made on a fixed-term contract.\nWhat you enjoy\n5-day work with stable hours\n18 days annual leave\nMedical and Dental Insurance\nPublic holidays\nCompensation leave\nMPF scheme\nGreat platform to learn and develop new skills in an encouraging environment\nFriendly team\nExcellent office environment (Newly renovated)\nShuttle bus from various locations in Hong Kong\nRecreational facilities in Science Park\nInformation and Application\nInterested parties please apply with full resume including expected salary and available date through email.\nApplications will receive full consideration and only shortlisted and selected applicants will be contacted.\nAn applicant who does not hear from us within 1 month after an interview may assume his/her application is not selected.\nAll information provided by applicants will be treated in strict confidence and used for recruitment purpose only.\u00a0 All personal data of unsuccessful applicants will be retained for 12 months for future recruitment purpose and will then be destroyed.", "employment_types": ["Full Time", "Permanent"], "selling_points": ["Good in English, Mandarin and Cantonese", "Willing to learn, good at multitasking", "All-rounded pre-job and on-job trainings"], "locations": ["North Point"], "categories": ["Admin & HR", "Personal / Executive Assistant", "Education", "Tutor / Instructor", "Marketing / Public Relations", "Marketing - Marketing Communication"], "post_time": "2022-01-17T16:22:39Z", "salary": {"currency": "HKD", "max": 19999, "min": 14000, "period": "monthly", "term": null}, "salary_visible": true, "title_keywords": ["director", "personal assistant"], "responsibilities": ["any other duties", "ad-hoc projects", "data", "administrative support", "internal and external parties", "daily operation", "project management", "proofreading", "marketing materials", "editing"], "requirements": {"degrees": ["degree", "bachelor"], "majors": [], "languages": ["english", "chinese"], "language_level": ["excellent"], "hard_skills": ["excel", "chinese and english word processing", "problem-solving", "scheme", "powerpoint", "pc skills", "ms word"], "soft_skills": ["communication skills", "self-motivated", "attentive to details", "competent", "multi-task oriented", "problem-solving", "interpersonal skills", "friendly", "stable"], "languages_combined": [{"language": "english", "language_level": ["excellent"]}, {"language": "chinese", "language_level": []}]}, "experience_required": {"duration": [], "field": []}}, {"job_id": "100003009049120", "location_code": "hk", "company": "Centaline Property Agency Ltd", "job_title": "Senior / Marketing Officer (REF: PRM)", "description": "Responsibilities:\u00a0\n\nImplementing marketing activities to achieve the business goals for assigned brands / product\nAssist to plan and manage all kinds of marketing activities and promotion materials (ATL, BTL, Online, exhibition, seminar, PR events, in-store, etc.)\nCoordinating with internal and external parties to ensure excellent execution of marketing and promotion activities\nEvaluating and monitoring the performance of promotional campaigns\nClosely monitor the market trend and competitor information of the product category\u00a0\nPrepare reports and presentations for management\n\nRequirements:\n\nDegree holder in Marketing, Business Administration or related discipline\nMinimum 2 years' relevant experience in Healthcare / FMCG industry\nExperience for handling key accounts will be a definite advantage\nProactive, creative and attentive to details\nStrong in communicating with people at all levels, both\u00a0internally and externally\nProficient in written and spoken English and Chinese\nCandidates with more experience will be considered as Marketing Officer\n\nAll applications received will be used exclusively for recruitment purposes only. Applicants who are not contacted within 8 weeks should consider their application unsuccessful for the position advertised. Data supplied by applicants will be kept for 6 months.", "employment_types": ["Full Time", "Permanent"], "selling_points": ["co-ordinate marketing events", "implement advertising", "Degree holder in Marketing"], "locations": ["Central"], "categories": ["Marketing / Public Relations", "Marketing - Brand / Product Management", "Marketing - General / Support", "Marketing - Marketing Communication"], "post_time": "2022-01-14T08:09:04Z", "salary": {"currency": null, "max": null, "min": null, "period": "monthly", "term": null}, "salary_visible": false, "title_keywords": ["marketing officer"], "responsibilities": ["business goals", "management", "internal and external parties", "monitor", "monitoring", "presentations", "plan", "prepare reports"], "requirements": {"degrees": ["degree holder"], "majors": ["marketing", "business administration"], "languages": ["english", "chinese"], "language_level": ["proficient"], "hard_skills": ["fmcg industry"], "soft_skills": ["proactive", "creative", "attentive to details"], "languages_combined": [{"language": "english", "language_level": ["proficient"]}, {"language": "chinese", "language_level": ["proficient"]}]}, "experience_required": {"duration": ["minimum 2 years"], "field": ["healthcare", "fmcg", "relevant experience", "marketing"]}}, {"job_id": "100003009048056", "location_code": "hk", "company": "Hong Kong Baptist University", "job_title": "Executive Officer (PR0472/21-22)", "description": "Responsibilities:\u00a0\n\n\n\nFormulating and implementing both online/offline marketing strategies and action plan to meet the budget of the assigned category of HK, PRC and Southeast Asia business\nDeveloping advertising and promotion activations with execution and tracking excellence\nReview the performance of existing product and NPI performance with recommendation to accelerate performance\nA&P ownership with discipline tracking of the spending tie with plan\nCommunicate and extent good relationships with external parties, including on-line media, vendors, KOL & platform partners\nWork closely with internal business units including in-house design, operation and Sales teams, to ensure digital strategy is aligned with all online/offline marketing strategies and comply with prevailing governance standards\nExplore new and effective digital channels for building and marketing promotions in HK, PRC and Southeast Asia market to improve sales & brand awareness for the company\nConduct market research to understand the HK, PRC and Southeast Asia market and monitor competitors\u2019 activities\nPrepare copywriting of media and marketing materials, including brochures, marketing campaigns, E-newsletter and websites\n\n\n\nRequirements:\n\n\n\nBachelor\u2019s Degree in Marketing and Business Management preferred\nAs least 5 years of brand management / consumer marketing experience in HK, PRC and Southeast Asia market, preferably in health supplement / FMCG\nInterpersonal and communication skills and teamwork\nExperience on dealing with agency is preferable\nHave network with media, marketing agency and design production is a plus\nGood understanding of learning and development trends and best practices in HK, PRC and Southeast Asia market\nProficient computer skills in Word, Excel and PowerPoint applications\nExcellent command of written and spoken English and Chinese, including Mandarin\nImmediately availability is highly preferred", "employment_types": ["Full Time"], "selling_points": ["Administer Lab's projects and grants applications", "Coordinate Lab's engagement activities", "Possess a recognised relevant bachelor's degree"], "locations": ["Kowloon City"], "categories": ["Education", "Others", "Marketing / Public Relations", "Marketing - Direct Marketing", "Marketing - Marketing Communication"], "post_time": "2022-01-14T04:37:11Z", "salary": {"currency": null, "max": null, "min": null, "period": "monthly", "term": null}, "salary_visible": false, "title_keywords": ["executive officer"], "responsibilities": ["advertising", "marketing strategies", "conduct market research", "budget", "review", "developing", "external parties", "design", "teams", "monitor", "marketing promotions", "plan", "marketing campaigns", "marketing materials", "tracking"], "requirements": {"degrees": ["degree", "bachelor"], "majors": ["business", "marketing"], "languages": ["english", "chinese", "mandarin"], "language_level": ["excellent"], "hard_skills": ["business management", "excel", "plus", "word", "powerpoint", "computer skills"], "soft_skills": ["communication skills", "teamwork", "interpersonal", "learning"], "languages_combined": [{"language": "english", "language_level": ["excellent"]}, {"language": "chinese", "language_level": ["excellent"]}, {"language": "mandarin", "language_level": ["excellent"]}]}, "experience_required": {"duration": ["least 5 years"], "field": ["management", "fmcg", "brand", "agency", "marketing"]}}]