[{"job_id": "100003009054901", "location_code": "hk", "company": "Melaleuca of Asia Ltd Co", "job_title": "Senior/Marketing Officer", "description": "Job responsibilities:\u00a0\n\nResponsible for\u00a0Skincare & Essential Oil product line \u00a0\n\nAssist in product development (e.g. labeling, packaging, product formula optimization, etc)\nDevelop communication materials\u00a0\u00a0(e.g. Copy-writing, Videos, Presentation, etc) to communicate product benefits\nAssist in product strategy of our Skincare & Essential Oil products (e.g. market trend updates, pricing and inventory forecast, etc.)\nAssist in publication & catalog preparation\nTo analyze potential product details, product performance data to help product planning \u00a0\n\nJob requirements:\n\nAt least 2\u00a0years of related working experience, preferably\u00a0experience in FMCG, marketing, communications & product management\nGood PC skills in Office especially Excel analysis, PowerPoint.\nKnowledge at design software (e.g. InDesign, Photoshop, illustrator) and basic video editing is preferable\nWorking experience in Skincare / Essential Oil industry is an advantage\nStrong communication in spoken and written English and Mandarin\nProactive, efficient, independent, detail-minded, positive and able to manage multiple projects in parallel\nCandidates with more experience will be considered as Senior Marketing Officer", "employment_types": ["Full Time", "Permanent"], "selling_points": ["Marketing, Product specialist", "Skincare, essential oil, product development, FMCG", "communications, publications, presentations"], "locations": ["Yau Tsim Mong Area"], "categories": ["Marketing / Public Relations", "Marketing - Brand / Product Management", "Marketing - Direct Marketing", "Marketing - Marketing Communication"], "post_time": "2022-01-17T13:19:16Z", "salary": {"currency": null, "max": null, "min": null, "period": "monthly", "term": null}, "salary_visible": false, "title_keywords": ["marketing officer"], "responsibilities": ["communication", "develop"], "requirements": {"degrees": [], "majors": [], "languages": [], "language_level": [], "hard_skills": [], "soft_skills": [], "languages_combined": []}, "experience_required": {"duration": [], "field": []}}, {"job_id": "100003009053053", "location_code": "hk", "company": "\u8a69\u7433\u63a7\u80a1\u96c6\u5718\u6709\u9650\u516c\u53f8", "job_title": "Senior Marketing Executive (5 days work)", "description": "Responsibilities:\n\nResponsibilities the online marketing activities and website contents to capture profitable growth;\nFormulate and implement customized annual promotion plan, ensure to meet the business target and maximize the brand image exposure within the budget;\nPlan and develop the loyalty program, marketing campaigns, CRM initiatives to optimize profitability;\nMonitor business results and campaigns effectiveness;\nKeep track the market trend and competitors promotional and marketing programs/ activities;\u00a0 \u00a0 \u00a0 \u00a0\nPerform ad hoc assignments.\n\nRequirements:\n\n\nBachelor Degree in Marketing or related disciplines;\nMinimum 3 years experience in Beauty centre / reatil is an advantage;\nA good team player with strong communication and interpersonal skills;\nAttention in details with analytical and presentation skills;\nEnergetic, proactive, creative with a good sense in beauty;\nGood command in spoken and written English, Cantonese and Mandarin;\nCandidates with less experience will be considered as Marketing Executive;\nImmediately available is highly preferred\u00a0\n\nWorking Location: Lai Chi Kok\n\nWe offer 5-day work and a competitive\u00a0salary and benefits\u00a0package\u00a0for the right candidate. To apply online please click the 'Apply' button below with your resume, current & expected salary, and availability to us.\n\nPersonal data collected will be treated in strict confidence and be used for recruitment purposes only.", "employment_types": ["Full Time"], "selling_points": ["Experience in beauty industry is an advantage", "Dynamic environment", "Immediate available is preferred"], "locations": ["Lai Chi Kok"], "categories": ["Marketing / Public Relations", "Marketing - Direct Marketing", "Marketing - General / Support", "Digital Marketing"], "post_time": "2022-01-17T05:24:57Z", "salary": {"currency": null, "max": null, "min": null, "period": "monthly", "term": null}, "salary_visible": false, "title_keywords": ["senior marketing executive"], "responsibilities": ["budget", "monitor", "website", "develop", "ad hoc assignments", "plan", "contents", "marketing campaigns"], "requirements": {"degrees": ["degree", "bachelor"], "majors": ["related disciplines", "marketing"], "languages": ["cantonese", "english", "mandarin"], "language_level": ["good command"], "hard_skills": [], "soft_skills": ["good team player", "proactive", "creative", "presentation skills", "communication and interpersonal skills", "energetic"], "languages_combined": [{"language": "cantonese", "language_level": ["good command"]}, {"language": "english", "language_level": ["good command"]}, {"language": "mandarin", "language_level": ["good command"]}]}, "experience_required": {"duration": ["minimum 3 years"], "field": ["marketing", "beauty"]}}, {"job_id": "100003009054244", "location_code": "hk", "company": "Jia Group Holdings Limited", "job_title": "Marketing Executive", "description": "To support the expansion of our Group, we are currently seeking an experienced\u00a0Marketing Executive individual with strong payroll skills\u00a0to learn to join our Family.\n\n\nSupport daily marketing activities and perform administrative duties\nProvide support on events and promotion campaigns arrangements\nPrepare marketing materials, market researches and ad hoc projects\nAssist in implementation of marketing initiatives, including events, media and promotions\nCoordinate with internal and external parties to ensure smooth execution of the tasks required\nDevise well-rounded strategy plans. This includes but not limited to events, reservations, third party platforms and more\nAssist with ad-hoc assignments as required\n\nIdeal requirements:\n\nDegree in Business, Marketing & Communications, Hospitality Management, or other related disciplines\nMinimum 1 year working experience, preferably gained in F&B industry\nAble to meet tight deadlines and work under pressure in a fast-paced environment\nAbility to work and understand systems such as Mailchimp, Seven rooms and Jot form will be advantageous\nExcellent command of written and spoken English and Chinese\nStrong interpersonal and communication skills\nProficient understanding of design software such as Illustrator and in Design. Other software will be advantageous\nFresh graduates are welcome to apply\nIf you are interested to apply for the above positions, please click apply share your resume with your CURRENT and EXPECTED salary with us.\n\nPeople who are eligible to work in Hong Kong or have a valid Hong Kong work permit/visa will be considered for the above position. If you are passionate about hospitality and are looking for exciting new opportunities, then we want to hear from you!\n\nWe are an equal opportunity employer. Information provided will be treated in strict confidence and will only be used for recruitment-related purposes.", "employment_types": ["Full Time", "Permanent"], "selling_points": ["Support daily marketing activities", "Assist in implementation of marketing initiatives", "Min. 1 yr exp. preferably gained in F&B industry"], "locations": ["Central"], "categories": ["Marketing / Public Relations", "Marketing - Brand / Product Management", "Marketing - Direct Marketing", "Marketing - General / Support"], "post_time": "2022-01-17T09:57:39Z", "salary": {"currency": null, "max": null, "min": null, "period": "monthly", "term": null}, "salary_visible": false, "title_keywords": ["marketing executive"], "responsibilities": ["software", "internal and external parties", "design", "communication", "promotion campaigns", "plans", "work under pressure", "implementation", "provide support", "management", "coordinate with", "administrative duties", "payroll", "third party", "prepare marketing materials", "ad-hoc assignments", "systems", "ad hoc projects", "recruitment"], "requirements": {"degrees": ["degree"], "majors": ["hospitality management", "related disciplines", "business", "marketing", "communications"], "languages": ["english", "chinese"], "language_level": ["excellent"], "hard_skills": ["illustrator"], "soft_skills": ["communication skills", "meet tight deadlines", "confidence", "ideal", "fast-paced environment", "smooth", "interpersonal", "passionate about", "work under pressure"], "languages_combined": [{"language": "english", "language_level": ["excellent"]}, {"language": "chinese", "language_level": ["excellent"]}]}, "experience_required": {"duration": ["minimum 1 year"], "field": ["f&b"]}}, {"job_id": "100003009054001", "location_code": "hk", "company": "T & Y Biologics Investment Limited", "job_title": "Marketing - Senior Officer/ Assistant Manager (Petmacy \u5bf5\u7269\u85e5\u599d)", "description": "Job Description\n\nThis role will work closely with Associate Director - Brand Marketing to build, strengthen and grow the Petmacy brand in HK and China region. The role will support to drive product marketing and consumer engagement initiatives to increase awareness, recruit new customer and drive conversion and transaction.\n\nPetmacy\u00a0\u5bf5\u7269\u85e5\u599d - T & Y Biologics Investment Limited\u00a0\n\nAbout Petmacy : Established by TnY Biotechnology Investment Co., Ltd. in 2018, the group is committed to sourcing worldwide high-quality pet food, pet necessities and manufacturing pet supplements for pets in HK.\n\nIn 2018, the Group cooperated with Watsons Hong Kong to launch \"Wats Petmacy\", which are now available in more than 130 locations. Of which, 2 \u201cWats Patmacy\u201d flagships store are located In Tseung Kwan O Plaza and Aberdeen Centre. In the future, the Group will actively continue to develop its pet products business and market through different channels and cooperation platforms.\n\nKey Roles & Responsibilities\n\nWork collaboratively with a range of internal and external stakeholders including social media team, Event team, Product marketing team, Sales, legal and external agencies.\nFully understand customer journey and hit the customer at right time\nLead a small team of 2 to provide project management support to set marketing calendar, initiate and execute marketing campaigns. Work closely with product marketing team to understand each of the brands under Petmacy and drive awareness and transaction.\nDevelop Promotion Calendar for chain stores, shops and ecommerce shop. Create and support marketing campaigns to drive sales and traffic.\nMeasure and report performance of all marketing campaigns\nCollaborate with different parties (Eg. IT) for e-commerce platform revamping\nSupport offline media placement with agency for various campaigns including OOH, print, Direct Mail etc. Event support may be needed occasionally.\nLead implementation and execution CRM campaign communications to retain customer\n\n\n\nWhat you must have\n\nUniversity Degree, preferably in Marketing, Communications, Business or related field. At least 4 years relevant working experience in a similar capacity, preferably in FMCG or ecommerce industry\nKnowledge of the latest growth practices including paid acquisition, technical SEO, SEM, etc.\nStrong analytical skills with the ability to interpret and utilize data to guide and shape campaigns\nStrong written and verbal communication skills with the ability to compile and present cohesive reports with clear action items and insights\nWith CRM project management experience is a plus\nWith good FMCG based media relationship is a plus\n\n\nThis is a very rewarding and exciting opportunity. We offer an attractive remuneration to the successful candidate(s). Please forward your\u00a0resume with\u00a0present and expected salary\u00a0by clicking\u00a0\u201cApply Now\u201d\u00a0for further consideration.\n\n**All information collected will be treated in strict confidence and will only be used for recruitment related purpose.**", "employment_types": ["Full Time", "Permanent"], "selling_points": ["Lead a small team to provide management support", "Develop Promotion Calendar", "Create and support marketing campaigns"], "locations": ["Kwun Tong"], "categories": ["Marketing / Public Relations", "Management", "Marketing - Direct Marketing", "Marketing - General / Support"], "post_time": "2022-01-17T08:00:53Z", "salary": {"currency": null, "max": null, "min": null, "period": "monthly", "term": null}, "salary_visible": false, "title_keywords": ["senior officer", "assistant manager"], "responsibilities": ["collaborate with", "social media", "seo", "data", "lead a small team", "quality", "implementation", "develop", "communication", "project management", "reports", "marketing campaigns", "sem", "drive sales", "e-commerce platform", "report"], "requirements": {"degrees": ["university degree"], "majors": ["business", "marketing", "communications"], "languages": [], "language_level": [], "hard_skills": ["small", "plus", "seo", "e-commerce", "analytical skills", "project management", "sem"], "soft_skills": ["communication skills", "cohesive", "analytical skills", "clear", "committed", "project management"], "languages_combined": []}, "experience_required": {"duration": ["at least 4 years"], "field": ["ecommerce", "project management", "fmcg", "relevant working experience"]}}, {"job_id": "100003009055169", "location_code": "hk", "company": "Tsit Wing Coffee Co Ltd", "job_title": "Marketing Executive", "description": "Responsibilities:\n\nProvide administrative support to the marketing team in accordance with the Company\u2019s Policy and Procedural Systems & Practices\nUpdate internal reports, records and documents in marketing department\nData tabulation and analysis\nCompetitive analysis and reporting\nMarket intelligence \u2013 desk research and field research coordination\nMarketing fund budget administration and control\nProvide general support and administrative duties to the team\nAssist in ad-hoc tasks and projects as required\n\nRequirements:\n\nDiploma holder or above with educational background in Statistics, Data Management, Accounting or Business Administration\n1-2 years relevant work experience in marketing, experience in FMCG will be an advantage, fresh graduates will also be considered\nAdvanced skills with MS Office esp. Excel and Powerpoint\nSelf-starter, quick learner,\u00a0logical thinking and organized\nImmediately availability is preferred\n\nWorking location:\u00a0Kwai Chung\n\nStaff Benefit:\n\nDiscretionary Bonus\nMedical & Life Insurance\nAnnual Leave\nPayable Sick Leave\nEncourage continuing education and on-job training\nOpen office working environment\nOffer promotion opportunities and long-term career path\u00a0\n\nWe offer a competitive remuneration package to the right candidate.\u00a0Interested parties\u00a0please click\u00a0\"Apply Now\"\u00a0to submit your application\u00a0or by email to\u00a0hr1 @twcoffee.com\n\n\u00a0(All personal data provided by applicants will be treated in strict confidence and used for employment-related purpose only.)", "employment_types": ["Full Time"], "selling_points": [], "locations": ["Kwai Fong"], "categories": ["Marketing / Public Relations", "Marketing - Brand / Product Management", "Marketing - Direct Marketing", "Marketing - General / Support"], "post_time": "2022-01-18T01:36:53Z", "salary": {"currency": null, "max": null, "min": null, "period": "monthly", "term": null}, "salary_visible": false, "title_keywords": ["marketing executive"], "responsibilities": ["reporting", "control", "data", "analysis", "systems", "budget", "ad-hoc tasks", "reports", "administrative duties", "coordination", "provide administrative support", "general support", "administration"], "requirements": {"degrees": ["diploma holder"], "majors": ["accounting", "statistics", "business administration"], "languages": [], "language_level": [], "hard_skills": ["excel", "data management", "powerpoint", "ms office"], "soft_skills": ["organized", "advanced", "quick learner"], "languages_combined": []}, "experience_required": {"duration": ["1-2 years"], "field": ["marketing", "fmcg"]}}, {"job_id": "100003009056193", "location_code": "hk", "company": "Code International Limited", "job_title": "Event & Roadshow Marketing Trainee", "description": "Job Duties:\n\nTo assist clients in increasing brand awareness and boosting sales performance through events, exhibitions and roadshows\nTo ensure the smooth operation of the events and roadshows by providing on-site support and engaging in sales activities\nTo take part in team development and management by recruiting new people, as well as providing support and coaching to the new people\n\n\nWhat We Offer:\n\nOverseas exchange opportunities (e.g. Malaysia, Korea, Singapore, Bali, Thailand and Taiwan, etc)\nFriendly and joyful working environment with strong team culture\nDiversified workshops and team activities\nSupport in career development and career growth\nHierarchical training from sales to leadership and management\n\nJob Requirements:\n\nFluent Cantonese is a must\nOutgoing, presentable, talkative and self-motivated\nExcellent communication and collaboration skills\nDiploma or above in any disciplines\nFresh graduates are welcome\n\nJoin Us NOW !!!", "employment_types": ["Full Time"], "selling_points": ["Event & Roadshow Marketing", "Indoor & Outdoor Events", "Friendly and joyful working environment"], "locations": ["Wan Chai Area"], "categories": ["Marketing / Public Relations", "Marketing - Direct Marketing", "Public Relations - Event Management", "Sales, CS & Business Devpt", "Direct Sales"], "post_time": "2022-01-18T03:31:08Z", "salary": {"currency": null, "max": null, "min": null, "period": "monthly", "term": null}, "salary_visible": false, "title_keywords": ["trainee"], "responsibilities": ["sales performance", "management", "sales activities", "providing support"], "requirements": {"degrees": [], "majors": [], "languages": [], "language_level": [], "hard_skills": [], "soft_skills": [], "languages_combined": []}, "experience_required": {"duration": [], "field": []}}, {"job_id": "100003009054021", "location_code": "hk", "company": "Genting Hong Kong Limited", "job_title": "Executive \u2013 Marketing Strategic Planning & Analysis (Marketing)", "description": "Working location:\u00a0Elite Centre in Kwun Tong\n\nResponsibilities\n\nDevelop and refine VIP programs and promotions to drive sales and penetration\nPlan and implement various VIP programs and collaborate with relevant parties to ensure the smooth execution of the programs\nSupport the strategic planning for member programs, promotions and events, including development of new product strategies, marketing programs and evaluation of customer segmentation to the right products & channels\nAssist with the pre and post event analysis of members programs, promotions and events to identify its effectiveness and recommended improvements for development\nAssist with data analysis and generating reports to support business planning\nPerform other ad hoc projects and assignments as required\n\nRequirements\n\nBachelor degree in Marketing, Business Administration or related disciplines\nMinimum 2 years of relevant working experiences\nProficient in PC skills (MS Word, Excel and PowerPoint)\nSelf-motivated, good communication, interpersonal skills and well-organized\nSolid experience in regional work is a plus\nFluent in spoken and written English, Cantonese and Mandarin\nGood at multi-tasking and strives for excellence\nCandidate with less experience will be considered as Senior Officer\n\nGenting Hong Kong is an Equal Opportunity Employer. All applications received will be treated in strict confidence and be used exclusively for recruitment purpose only. If you are not contacted within four weeks, your application will be retained for a period of 1 year and may be presented for other appropriate positions within this period.", "employment_types": ["Full Time", "Permanent"], "selling_points": ["Focus on marketing planning & analysis", "Loyalty marketing & CRM exp is an advantage", "MNC working environment , stable 5 days work"], "locations": ["Kwun Tong"], "categories": ["Marketing / Public Relations", "Marketing - Brand / Product Management", "Marketing - Direct Marketing", "Marketing - Market Research"], "post_time": "2022-01-17T08:06:47Z", "salary": {"currency": null, "max": null, "min": null, "period": "monthly", "term": null}, "salary_visible": false, "title_keywords": ["executive"], "responsibilities": ["collaborate with", "strategic planning", "analysis", "develop", "data analysis", "reports", "ad hoc projects", "plan", "evaluation", "drive sales", "planning"], "requirements": {"degrees": ["degree", "bachelor"], "majors": ["related disciplines", "marketing", "business administration"], "languages": ["cantonese", "english", "mandarin"], "language_level": ["fluent"], "hard_skills": ["excel", "plus", "powerpoint", "pc skills", "ms word"], "soft_skills": ["self-motivated", "confidence", "well-organized", "communication", "multi-tasking", "interpersonal skills"], "languages_combined": [{"language": "cantonese", "language_level": ["fluent"]}, {"language": "english", "language_level": ["fluent"]}, {"language": "mandarin", "language_level": ["fluent"]}]}, "experience_required": {"duration": ["minimum 2 years"], "field": []}}, {"job_id": "100003009052909", "location_code": "hk", "company": "Telford International Co Ltd", "job_title": "Assistant Brand Manager / Senior Marketing Executive - Beer Division", "description": "Responsibilities:\n\nTo assist the team in planning and executing marketing campaigns, including ATL, BTL, PR, and Online promotion\nOrganize events to maximize product launch awareness and enhance customer relationship\nResponsible for planning and execution of CRM Program for customer acquisition and retention\nPrepare regular reports and insights for business performance review\nTo participate in training programme and presentation\nAssist in any ad hoc duties as requested\n\nRequirements:\n\nDegree holder in Marketing / Communications or related disciplines\nWith 1 - 2 years of working experience in marketing\nProactive, result oriented with a strong sense of responsibility\nWith good presentation skills\nFast-paced with excellent communication and interpersonal skills\nCreative and attention to details\nGood command of spoken and written English, Cantonese and Mandarin\n\nInterested parties, please send your full resume with\u00a0current salary,\u00a0expected salary,\u00a0and\u00a0available date\u00a0either by direct application from JobsDB (Please quote the job title on the subject ) or by WhatsApp:69298297 or by post to Human Resources Department, Unit 8-14 & 22-28, 11/F, Topsail Plaza, 11 On Sum Street, Shek Mun.\n\n\"Personal data collected will be used for recruitment purposes only.\"", "employment_types": ["Full Time", "Permanent"], "selling_points": ["University Degree in Marketing", "3 yrs work experience in marketing senior role", "Attractive Package with Excellent Career Path"], "locations": ["Kwai Hing"], "categories": ["Sales, CS & Business Devpt", "Business Development", "Marketing / Public Relations", "Marketing - Brand / Product Management", "Marketing - Direct Marketing"], "post_time": "2022-01-17T04:30:24Z", "salary": {"currency": null, "max": null, "min": null, "period": "monthly", "term": null}, "salary_visible": false, "title_keywords": ["senior marketing executive", "manager", "assistant"], "responsibilities": ["ad hoc duties", "review", "planning", "reports", "executing", "marketing campaigns", "online promotion"], "requirements": {"degrees": ["degree holder"], "majors": ["related disciplines", "marketing", "communications"], "languages": ["cantonese", "english", "mandarin"], "language_level": ["good command"], "hard_skills": [], "soft_skills": ["creative", "sense of responsibility", "result oriented", "presentation skills", "communication and interpersonal skills", "attention to details", "proactive"], "languages_combined": [{"language": "cantonese", "language_level": ["good command"]}, {"language": "english", "language_level": ["good command"]}, {"language": "mandarin", "language_level": ["good command"]}]}, "experience_required": {"duration": ["1 - 2 years"], "field": ["marketing"]}}, {"job_id": "100003009051945", "location_code": "hk", "company": "OSIM (HK) Co. Limited", "job_title": "Marketing Executive (5 Days Work)", "description": "Job brief\nTo cope with our growth, we are looking for a Marketing Executive to join our team to manage day to day marketing plan & development.\n\nJob Highlights\nProficiency in web analytics and reporting tools with 1-2 years related experience. Immediate available is highly preferred.\n\nResponsibilities:\n- Assist in planning, developing and implementing marketing campaigns within budget and on schedule to achieve target metrics\n- Support the full spectrum of marketing activities\n- Conduct research and analyse data to identify audiences and competitors\n- Maintain website, evaluating performance, and looking at data analytics\n- Responsible for copywriting and translation of press releases, newsletter, publicity materials and other marketing materials\n- Update databases using customer relationship management (CRM) system\n- Create and manage document control and correspondence folders for all projects\n- Implement marketing document procedures in line with the Document Management System\n- Ensure all documentation is provided in accordance with the agreed formatting requirements\n- Other ad-hoc projects as assigned\n\nRequirements:\n- Bachelor's degree in marketing or journalism or related field\n- 1 - 2 years of relevant experience\n- Strong research, analytical and planning skills\n- Well organized and fast learner\n- High adaptability and flexibility\n- Attention to details and ability to work under tight timeline and multi-task independently\n- Proficiency in web analytics and reporting tools (Google Analytics/Webtrends/Adobe Analytics/Salesforce or equivalent)\n- Excellent command of both written and spoken English and Chinese, preferably with proficiency in Putonghua\n- Proficient in MS Office (Word, Excel & Power Point)\n- Immediate available is highly preferred", "employment_types": ["Full Time", "Permanent"], "selling_points": [], "locations": ["Shatin Area"], "categories": ["Marketing / Public Relations", "Marketing - Brand / Product Management", "Marketing - Direct Marketing", "Others"], "post_time": "2022-01-17T01:35:55Z", "salary": {"currency": null, "max": null, "min": null, "period": "monthly", "term": null}, "salary_visible": false, "title_keywords": ["marketing executive"], "responsibilities": ["management", "control", "documentation", "ad-hoc projects", "data", "budget", "procedures", "developing", "website", "maintain", "schedule", "marketing campaigns", "analyse", "marketing materials", "databases", "formatting", "conduct research", "planning"], "requirements": {"degrees": ["degree", "bachelor"], "majors": ["journalism", "marketing"], "languages": ["putonghua", "english", "chinese"], "language_level": ["excellent", "proficiency"], "hard_skills": ["google analytics", "excel", "salesforce", "word", "adobe", "web analytics", "power point", "ms office"], "soft_skills": ["planning skills", "independently", "multi-task", "well organized", "adaptability", "attention to details", "web analytics", "fast learner"], "languages_combined": [{"language": "putonghua", "language_level": ["proficiency", "excellent"]}, {"language": "english", "language_level": ["excellent"]}, {"language": "chinese", "language_level": ["excellent"]}]}, "experience_required": {"duration": ["1 - 2 years"], "field": ["relevant experience"]}}, {"job_id": "100003009056142", "location_code": "hk", "company": "\u4fe1\u5c71\u5be6\u696d\u6709\u9650\u516c\u53f8", "job_title": "Marketing Executive", "description": "Responsibilities:\n\nAssist Brand Manager to manage brands / products\u00a0\nTake initiative to develop marketing programs targeted at both consumers and trade customers, and implement a mix of marketing activities\nWork with the sales team to formulate trade promotion strategy and programs for key customers\nBuild up and maintain good relationship with media & agencies\nHandle marketing administrative works including reporting, claims and inventory control\nCoordinate with various departments to ensure promotions and activities are executed\n\nRequirement:\u00a0\n\nDegree in Marketing / Hospitality is preferred\nMin 2-4 years or above working experience preferably in FMCG or beverage industry\nSensitive to numbers and strong analytical skills\nSelf-motivated, fast learner with good multi-tasking skills to meet tight deadlines\nExcellent communication and inter-personal skill\nCandidate with more experience will be considered as Senior Marketing Executive\nImmediate available is preferred\n\n\n\nWe offer attractive remuneration package and career prospects plus 5-day week and medical insurance. Interest parties, please forward your full resume with expected salary to\u00a0apply now.\n\nAll data collected shall be solely for recruitment purpose.\n\nWebsite\u00a0\u00a0 :\u00a0\u00a0\u00a0\u00a0\u00a0\u00a0\u00a0http://www.telford.com.hk/", "employment_types": ["Full Time"], "selling_points": ["Hong Kong Science Park", "1-2 years related experience", "Immediate available is highly preferred"], "locations": ["Shatin Area"], "categories": ["Marketing / Public Relations", "Marketing - Direct Marketing"], "post_time": "2022-01-18T03:23:40Z", "salary": {"currency": null, "max": null, "min": null, "period": "monthly", "term": null}, "salary_visible": false, "title_keywords": ["marketing executive"], "responsibilities": ["reporting", "coordinate with", "maintain good relationship", "develop", "inventory control", "sales team"], "requirements": {"degrees": ["degree"], "majors": ["hospitality", "marketing"], "languages": [], "language_level": [], "hard_skills": ["analytical skills"], "soft_skills": ["self-motivated", "meet tight deadlines", "analytical skills", "communication", "inter-personal skill", "multi-tasking skills", "sensitive to numbers", "fast learner"], "languages_combined": []}, "experience_required": {"duration": ["min 2-4 years"], "field": ["fmcg", "beverage industry", "marketing"]}}, {"job_id": "100003009053968", "location_code": "hk", "company": "Gain Miles Assurance Consultants Limited", "job_title": "Assistant Manager \u2013 Content Marketing", "description": "\u2022 At least 1 years working experience\n\u2022 Good management and leadership skills are a plus\n\u2022 Have coaching and training experiences will have added advantage\n\u2022 Mature, stable and presentable\n\u2022 Proficiency in spoken and written Chinese and Hong Kong ID card holder\n\u2022 Less experience will be considered Assistant Manager\n\u2022 Enjoy working with people, good communication skills\n\u2022 Willing to learn and easy to adapt to a new work environment\n\u2022 Finance, marketing and sales experience are a plus\n\u2022 Scope includes individual financial and retirement planning, wealth management, corporate clients, MPF, group medical, high net-worth clients,\n\u2022 Customers base can be provided\n\u2022 First year income can exceed $400,000\n\u00a0\nWe offer comprehensive trainings (tailor made & best in class), flexible work schedule, bank holidays, 5 weeks annual leaves, medical benefits, overseas convention, preferred mortgage rate, attractive remuneration package with attractive bonus structure and generous fringe benefits to the right candidate.\nIf you are determined to develop your career with a promising company, please submit your resume with confidence to our recruitment manager Mr. Ryan Lee by clicking \u2018Apply Now\u2019, send email to ryan_cl_lee@manulife .com.hk or call/whats app 6088 8842 or a meeting.\nOnly short-listed candidates will be contacted. All applicant information is treated confidentially; personal data collection is only for recruitment selection purposes.\nThe recruitment offer is subject to the terms & conditions as stipulated in the agreement to be signed.", "employment_types": ["Full Time", "Permanent"], "selling_points": ["Content marketing", "financial service", "marketing channels"], "locations": ["Not Specified"], "categories": ["Marketing / Public Relations", "Marketing - Direct Marketing", "Public Relations - Event Management", "Others"], "post_time": "2022-01-17T07:51:55Z", "salary": {"currency": null, "max": null, "min": null, "period": "monthly", "term": null}, "salary_visible": false, "title_keywords": ["assistant manager"], "responsibilities": ["management", "mpf", "develop", "communication", "recruitment", "schedule", "personal data", "planning"], "requirements": {"degrees": [], "majors": [], "languages": ["chinese"], "language_level": ["proficiency"], "hard_skills": ["id", "plus"], "soft_skills": ["flexible", "communication skills", "confidence", "determined", "enjoy working", "leadership skills", "willing to learn", "mature", "presentable", "comprehensive", "stable"], "languages_combined": [{"language": "chinese", "language_level": ["proficiency"]}]}, "experience_required": {"duration": ["at least 1 years"], "field": ["finance", "marketing", "training"]}}, {"job_id": "100003009054910", "location_code": "hk", "company": "Ryan CHi-Leung Lee", "job_title": "** URGENT FOR BUSINESS DEVELOPMENT MANAGER, MPF SALES AND MARKETING **", "description": "Responsibilities:\n\n\nTo manage digital marketing platforms to drive traffic and conversion\nTo promote company product and services to potential customer through B2B phone calls\nTo coordinate with innovative team for marketing events and campaigns and assist in copy-writing\nTo handle inquiries from customer via email, phone, WhatsApp\nTo assist in ad hoc projects as assigned\n\n\n\nRequirements:\n\n\nMinimum to work 1.5 days per week\nDSE / higher diploma / degree holders are all welcomed\nExperience in PR / Marketing / Telesales would be a privilege\nGood command in written and spoken English and Cantonese\nResponsible and detail-minded\n\n\n\nInterested parties, please submit your application by clicking \u201cApply Now\u201d or through \"Joboffer\" app;\nOr simply WhatsApp 92886650 (https://wa.me/message/M24M4MRDAA34E1).", "employment_types": ["Full Time", "Part Time", "Contract", "Internship"], "selling_points": [], "locations": ["Ngau Tau Kok"], "categories": ["Accounting", "Accountant", "Insurance", "Insurance Agent / Broker", "Marketing / Public Relations", "Marketing - Direct Marketing"], "post_time": "2022-01-17T13:34:07Z", "salary": {"currency": "HKD", "max": 69999, "min": 25000, "period": "monthly", "term": null}, "salary_visible": true, "title_keywords": ["business development manager", "sales"], "responsibilities": ["marketing events", "coordinate with", "ad hoc projects", "digital marketing", "phone calls"], "requirements": {"degrees": ["diploma", "degree", "dse"], "majors": [], "languages": ["cantonese", "english"], "language_level": ["good command"], "hard_skills": [], "soft_skills": ["detail-minded", "responsible"], "languages_combined": [{"language": "cantonese", "language_level": ["good command"]}, {"language": "english", "language_level": ["good command"]}]}, "experience_required": {"duration": [], "field": ["pr", "marketing", "telesales"]}}, {"job_id": "100003009056416", "location_code": "hk", "company": "Quality People Resources Limited", "job_title": "Part-time Marketing Assistant (Internship)", "description": "We are looking for a highly driven and motivated Senior\u00a0Marketing Executive, Campaign to join our yuu team based in Hong Kong. The Marketing Team drives the growth and marketing strategies at yuu and aims to making yuu the no.1 digital platform in online services and customer loyalty. With yuu\u2019s ultra-high brand awareness and its mega size retail partnership network, your work will directly make an impact to a high population of HKers. Candidate with deeper experience can be considered a Senior Marketing Executive position.\n\nAbout the team\n\nThe Marketing Campaign team are the PICs of marketing campaigns end-to-end, from ideation through to execution. You will take part in developing consumer-centric CRM and or advertising campaign strategies and executions for different business verticals, including loyalty campaigns across multiple brands, yuu brand communications and other new yuu services.\n\nOur Job\n\nWork directly with Marketing Director and Marketing Manager, with the opportunity to take ownership of marketing projects\nThe role will be varied; supporting the entire team on a number of digital projects encompassing daily communication of our promotions and in addition to helping with offline marketing and partnership communications\nYou will be required to produce scheduled CRM communications in brand\u2019s tone and manner and lead the compilation of regular reports with key outcomes and learnings\nManage creative briefs and prepare promotional materials on both online and traditional advertising\nManage ad hoc promotions and requests with efficiency\n\nOur Role\n\nProactive, self-motivated and ready to contribute anytime\nUniversity degree in business, marketing, PR / communications or related areas\nWith 1-3 years working experience\nSociable character and positive attitude towards new challenges\nEstablish and maintain relationships with internal departments\nWork closely with the team to support the daily communication management and handle ad hoc requests\nExcellent communication and interpersonal skills, fluency in both English and Cantonese\nExperience in CRM and/or loyalty programme, or eCommerce definitely an advantage\nAdaptable in a fast-paced environment\n\n\u201cDFI Retail Group is responsible for ensuring that all personal information collected from each Candidate presented to DFI Retail Group is used for recruitment purposes only and the data collection process is in accordance with all applicable laws and compliant with the Code of Practice on Human Resource Management.\n\nTo find out more about Our Businesses and Our People, please visit our website: https://www.DFIretailgroup.com\n\nWe are an equal opportunity employer. Personal data collected will be kept and handled confidentially by authorised personnel for recruitment purposes only. We will retain the applications of candidates not selected for a period of no more than 24 months. A copy of our Privacy Policy can be accessed by visiting our Company website.\u201d\n\nIssued by The Dairy Farm Company, Limited", "employment_types": ["Full Time", "Part Time", "Permanent", "Temporary", "Contract", "Internship", "Freelance"], "selling_points": [], "locations": ["Yau Ma Tei"], "categories": ["Admin & HR", "HR Supporting Staff", "Marketing / Public Relations", "Marketing - Direct Marketing", "Digital Marketing"], "post_time": "2022-01-18T04:14:16Z", "salary": {"currency": "HKD", "max": 369, "min": 240, "period": "hourly", "term": null}, "salary_visible": true, "title_keywords": ["marketing assistant", "internship"], "responsibilities": ["maintain relationships", "management", "advertising", "marketing strategies", "ad hoc", "ad hoc requests", "developing", "digital platform", "marketing projects", "communication", "website", "promotional materials", "reports", "recruitment", "marketing campaigns", "data collection", "personal data", "company website"], "requirements": {"degrees": ["university degree"], "majors": ["business", "communications", "marketing"], "languages": ["cantonese", "english"], "language_level": ["fluency", "excellent"], "hard_skills": ["make", "no", "code"], "soft_skills": ["self-motivated", "proactive", "responsible", "adaptable", "fast-paced environment", "sociable", "communication", "positive attitude", "motivated", "communication and interpersonal skills", "creative", "driven"], "languages_combined": [{"language": "cantonese", "language_level": ["fluency", "excellent"]}, {"language": "english", "language_level": ["fluency", "excellent"]}]}, "experience_required": {"duration": ["1-3 years"], "field": ["ecommerce", "marketing"]}}, {"job_id": "100003009055766", "location_code": "hk", "company": "", "job_title": "Digital Marketing Executive (Graphics & Copy)", "description": "Do you think outside the box? Are you a dynamic storyteller who loves beauty products and is\u00a0passionate about digital marketing? You may be the person we are looking for!\n\nThe successful candidate will be responsible for managing the company\u2019s media platforms such as, Facebook, Instagram, Tiktok, Youtube and Naver. You will be able to learn how to use intelligence tool like Hootsuite and OneSignal to manage the platforms better.\n\n\u00a0Roles and responsibilities:\n\nManage campaigns across all social media platforms\u00a0to achieve designated business goals\nResponsible for content\u00a0creation and storytelling on social media channels\u00a0to produce creative, well written, rich and engaging social media content to maximize ROI and increase brand awareness\nDay-to-day tasks includes performance report consolidation, postings on Social Media and app push scheduling\nManage partnership with KOLs, including incentive offering, posting arrangement and payment settlement\n\nRequirements:\n\nExperience in media marketing with 1-2 years relevant experiences\nFresh graduates are also welcome\nBachelor\u2019s degree in communications, marketing or related field\nUnderstanding of APAC markets such as Hong Kong, Australia, New Zealand, Singapore is preferred\nExcellent written and spoken English and\u00a0Traditional Chinese, particularly in creating content for Asian markets\nA passion in digital marketing and beauty e-commerce\nHigh project management skills with attention to detail and ability to multi-task\nA good team player", "employment_types": ["Full Time", "Permanent"], "selling_points": ["Manage & Create daily social media ads & posts", "Develop & execute E-Marketing ideas strategically", "Create & Design Graphics & Copy for Social Media"], "locations": ["Kwun Tong"], "categories": ["Media & Advertising", "Creative / Design", "Design", "Multi-media", "Marketing / Public Relations", "Marketing - Direct Marketing"], "post_time": "2022-01-18T02:55:52Z", "salary": {"currency": null, "max": null, "min": null, "period": "monthly", "term": null}, "salary_visible": false, "title_keywords": ["digital marketing executive"], "responsibilities": ["social media", "business goals", "social media platforms", "scheduling", "payment", "social media content", "maximize roi", "report"], "requirements": {"degrees": ["degree", "bachelor"], "majors": ["marketing", "communications"], "languages": ["english", "chinese"], "language_level": ["excellent"], "hard_skills": ["project management", "e-commerce"], "soft_skills": ["good team player", "multi-task", "passion in", "project management skills", "attention to detail"], "languages_combined": [{"language": "english", "language_level": ["excellent"]}, {"language": "chinese", "language_level": ["excellent"]}]}, "experience_required": {"duration": ["1-2 years"], "field": ["marketing", "media"]}}, {"job_id": "100003009052072", "location_code": "hk", "company": "Strawberry Cosmetics (Services) Limited", "job_title": "Digital Marketing Executive \u2013 Social Media", "description": "Responsibilities:\u00a0\n\nFormulate marketing plan & agree\u00a0the marketing strategies with brand owners\nDevelop and execute marketing and promotional activities; and prepare POSM for both on-& off-trade\nDevelop and manages marketing budget including forecast, marketing/promotion activity, A&P budget, depletion, shipment and inventory controls\nCoordinate with principals and various departments to ensure the activities are efficiently executed\nMonitor the brand performance and ensure effective control of marketing results\nWilling to work during night\u00a0and sometimes during weekend\u00a0for special events\n\nRequirements:\u00a0\n\nUniversity degree or equivalent \u2013 major in marketing is preferred\n3 years of work experience in marketing senior role; in FMCG industry is preferred\nFluent in written and spoken English and Cantonese\nGood command of written and spoken English and Cantonese\nGood communication and interpersonal skills, with ability\u00a0to work effectively with colleagues in other functions and cultures\nAnalytical and Commercially sensible with good negotiation skill\nHighly self-motivated, strong team player and creative thinker\nComputer proficiency in Microsoft Outlook, Word, Excel,\u00a0and PowerPoint is essential.\nImmediate available or short notice is highly preferred\n\nWe offer attractive remuneration package and career prospects plus 5-day\u00a0week to right\u00a0candidate. Interest parties; please forward your full resume with expected salary to us.\n\n\u00a0All data collected shall be solely for recruitment purpose.\n\n\u00a0Website\u00a0\u00a0\u00a0 :\u00a0\u00a0\u00a0\u00a0\u00a0\u00a0 http://www.telford.com.hk/", "employment_types": ["Full Time", "Permanent"], "selling_points": [], "locations": ["Shau Kei Wan"], "categories": ["Marketing / Public Relations", "Marketing - Direct Marketing", "Marketing - Marketing Communication", "Digital Marketing"], "post_time": "2022-01-17T02:01:58Z", "salary": {"currency": null, "max": null, "min": null, "period": "monthly", "term": null}, "salary_visible": false, "title_keywords": ["digital marketing executive"], "responsibilities": ["control", "marketing strategies", "budget", "coordinate with", "monitor", "develop", "marketing plan", "promotional activities", "forecast", "inventory controls"], "requirements": {"degrees": ["university degree"], "majors": ["marketing"], "languages": ["cantonese", "english"], "language_level": ["good command", "fluent"], "hard_skills": ["excel", "fmcg industry", "word", "powerpoint", "outlook"], "soft_skills": ["work effectively", "self-motivated", "communication and interpersonal skills", "negotiation skill", "team player", "creative"], "languages_combined": [{"language": "cantonese", "language_level": ["good command", "fluent"]}, {"language": "english", "language_level": ["good command", "fluent"]}]}, "experience_required": {"duration": ["3 years"], "field": ["marketing"]}}, {"job_id": "100003009053833", "location_code": "hk", "company": "Joy Enterprises Limited", "job_title": "Senior Marketing Officer / Assistant Marketing Manager", "description": "Job Description\n\nResponsibilities:\n\nAssist on executing digital marketing campaigns including social media and display advertising\nManage and create content for the social media platforms in China (including xiahongshu\u5c0f\u7d05\u66f8, Wechat and Weibo), including copywriting and image creating/editing\nClosely monitor social media channels for timely response to comments and inquiries from audiences\nOrganize, create, launch and monitor On/Offline campaigns and formulate up to date e-marketing initiatives to generate sales and brand awareness\nAssist in video production: research & conceptualizing ideas, video shooting and editing\nAssist on analyzing the marketing results to optimize customer experience across multiple channels: offline to online and vice versa\nPerform ad-hoc projects as assigned\n\nRequirements:\n\nDegree holder in Marketing or related disciplines\nPreferably 2-3 years of relevant experience, fresh graduates with keen interest in Beauty Treatment sense and digital marketing will also be considered\nPrior experience in a FMCG /cosmetic and beauty industry.\nExcellent skills in graphic design software such as Photoshop/Illustrator.\nCoordinate and execute product photography shoots or short videos.\nCreative thinking, energetic, self-motivated, independent and able to handle multiple projects\nGood communication skills in both Chinese & English, Mandarin is an advantage\n\nPlease apply in confidence with\u00a0full resume, expected salary and availability\u00a0by clicking \u201cApply Now\u201d button.\n\nYou are invited to visit our website at:\u00a0https://www.swissobeauty.com/\n\nThe information provided will be used for selection purpose only. All information of unsuccessful applicants will be destroyed within six months.", "employment_types": ["Full Time"], "selling_points": [], "locations": ["Mong Kok"], "categories": ["Marketing / Public Relations", "Marketing - Direct Marketing", "Marketing - Market Research", "Marketing - Marketing Communication"], "post_time": "2022-01-17T07:36:13Z", "salary": {"currency": null, "max": null, "min": null, "period": "monthly", "term": null}, "salary_visible": false, "title_keywords": ["assistant marketing manager", "senior marketing officer"], "responsibilities": ["social media", "ad-hoc projects", "advertising", "ideas", "video production", "digital marketing campaigns", "social media platforms", "monitor", "comments", "video shooting", "executing", "editing", "conceptualizing"], "requirements": {"degrees": ["degree holder"], "majors": ["related disciplines", "marketing"], "languages": ["english", "chinese", "mandarin"], "language_level": ["advantage", "good"], "hard_skills": ["illustrator", "photoshop"], "soft_skills": ["communication skills", "self-motivated", "confidence", "independent", "creative", "keen", "energetic"], "languages_combined": [{"language": "english", "language_level": ["good"]}, {"language": "chinese", "language_level": ["good"]}, {"language": "mandarin", "language_level": ["advantage", "good"]}]}, "experience_required": {"duration": ["2-3 years"], "field": ["fmcg", "beauty industry", "relevant experience", "beauty", "digital marketing"]}}, {"job_id": "100003009055285", "location_code": "hk", "company": "Job-Box Personnel", "job_title": "Graduate Trainee Program (Welcome Fresh grad. / IANG Student)", "description": "The Role and Responsibilities:\n\nOn-the-job training to established related asset management expertise.\nPreparing investment portfolio and global market analysis.\nTo develop investment strategies to achieve client\u2019s short-term and long-term financial objectives.\nOn going manage client\u2019s portfolios according to client\u2019s financial goals.\nPreparing different scheme of investment proposal and portfolio review report.\nIdentify client objectives and offer appropriate financial consultancy.\n\nRequirements:\n\nBachelor degree holder or above in all disciplines\nInnovative and a good team player\nFluency in Cantonese, English and Mandarin\nGood communication and interpersonal skills\nArticulate and detail oriented, ability to multitask in a fast paced environment.\u00a0\n\nJob Offer:\n\nPersonal development and growth opportunities.\nContinuous Learning Sponsorship, medical benefits.\n5 day work week.\n\nWe offer a competitive salary and benefits package and the professional advantages of a dynamic environment that supports your development and recognizes your achievements.\n\nInterested individuals please send your detailed resume and expected salary by clicking\u00a0\"Apply Now\". Only candidates who are authorized to work in Hong Kong will be considered.\n\nAll personal data provided will only be used for recruitment purpose only. Information of candidates not selected will be destroyed in 3 months.", "employment_types": ["Full Time", "Permanent", "Internship"], "selling_points": ["5 day work,17-20 annual leave, Performance bonus", "Continuous Learning Sponsorship, medical benefits", "Personal development and growth opportunities"], "locations": ["Eastern Area"], "categories": ["Banking / Finance", "Private Banking", "Marketing / Public Relations", "Marketing - Direct Marketing", "Others", "Student / Fresh Graduate / No Experience"], "post_time": "2022-01-18T02:03:06Z", "salary": {"currency": "HKD", "max": 19999, "min": 17000, "period": "monthly", "term": null}, "salary_visible": true, "title_keywords": ["graduate trainee"], "responsibilities": ["investment strategies", "preparing investment portfolio", "global market analysis", "develop", "investment proposal", "portfolio review report", "manage client\u2019s portfolios", "asset management"], "requirements": {"degrees": ["bachelor degree holder"], "majors": [], "languages": ["cantonese", "english", "mandarin"], "language_level": ["fluency"], "hard_skills": [], "soft_skills": ["good team player", "detail oriented", "communication and interpersonal skills", "articulate", "ability to multitask", "innovative"], "languages_combined": [{"language": "cantonese", "language_level": ["fluency"]}, {"language": "english", "language_level": ["fluency"]}, {"language": "mandarin", "language_level": ["fluency"]}]}, "experience_required": {"duration": [], "field": []}}, {"job_id": "100003009054127", "location_code": "hk", "company": "Clover Display Limited", "job_title": "Sales Engineer", "description": "Responsibilities\n\n\nSupport marketing & Sales activities\nDevelop new business & distribution channels\nConduct market study, research, provide pre & post sales support\n\nRequirements\n\nHigher Diploma or above in Science subject\nAt least 1 year or above working experience with technical sense is preferable\nGood command of written and spoken English\nGood communication skill and self-motivated", "employment_types": ["Full Time"], "selling_points": ["Five-day work, bank holiday, free lunch", "Work in HK, not stated in PRC", "Medical insurance, Attractive Performance bonus"], "locations": ["Wong Tai Sin Area"], "categories": ["Engineering", "Manufacturing & Production", "Marketing / Public Relations", "Marketing - Brand / Product Management", "Marketing - Direct Marketing"], "post_time": "2022-01-17T08:31:19Z", "salary": {"currency": null, "max": null, "min": null, "period": "monthly", "term": null}, "salary_visible": false, "title_keywords": ["sales engineer"], "responsibilities": ["sales activities", "develop new business"], "requirements": {"degrees": ["higher diploma or above"], "majors": ["science"], "languages": ["english"], "language_level": ["good command"], "hard_skills": [], "soft_skills": ["self-motivated", "communication skill"], "languages_combined": [{"language": "english", "language_level": ["good command"]}]}, "experience_required": {"duration": ["at least 1 year"], "field": []}}, {"job_id": "100003009053822", "location_code": "hk", "company": "Squina International Group Limited", "job_title": "Digital Marketing Officer ( e-commerce )", "description": "RESPONSIBILITY\n\n\n\nHandle website and online marketing,\u00a0Optimize online promotion mix by managing different social media platforms including Facebook, Instagram, Weibo, WeChat, YouTube, etc., and understanding their strengths and weaknesses\nDeploy brand image strategies, brand building and maximize brand exposure\u00a0\nSupport preparation, implementation and execution of marketing programs\u00a0\nAssist all brand building activities and joint promotions to enhance company visibility and awareness\u00a0\nDevelop editorial coverage to increase brand awareness such as leaflets, advertisements, catalogues, press releases, media kits, direct mails, brand presentations, website / social media contents etc.\nPerform other ad-hoc projects as assigned\nREQUIREMENT\nDegree holder in Marketing or related disciplines\nMinimum 2 years of solid experiences in online marketing, retail industry will be advantage\u00a0\nExcellent communication and writing skill\u00a0\nGood command of English & Chinese with strong interpersonal and problem solving skills\nIndependent, well organized and detail-minded\u00a0\nGood knowledge in online marketing landscape, Experience in online media would be an advantage\nImmediate availability will be an advantage\n\nCompetitive package will be offered to the right candidate including 5-day week, attendance incentive, birthday leave, free goods allowance, medical plan etc. Interested parties, please send resume with expect salary and date of availability. Please visit our website: www.squina.com\n\nAll the personal data collected will be used for recruitment purpose only.", "employment_types": ["Full Time", "Permanent"], "selling_points": [], "locations": ["Causeway Bay"], "categories": ["Marketing / Public Relations", "Marketing - Brand / Product Management", "Marketing - Direct Marketing", "Marketing - Market Research"], "post_time": "2022-01-17T07:35:06Z", "salary": {"currency": null, "max": null, "min": null, "period": "monthly", "term": null}, "salary_visible": false, "title_keywords": ["digital marketing officer"], "responsibilities": ["social media", "advertisements", "leaflets", "social media platforms", "website", "implementation", "develop", "presentations", "contents", "deploy", "facebook", "ad-hoc projects", "online promotion"], "requirements": {"degrees": ["degree holder"], "majors": ["related disciplines", "marketing"], "languages": ["english", "chinese"], "language_level": ["good command"], "hard_skills": ["problem solving skills", "writing skill"], "soft_skills": ["detail-minded", "independent", "well organized", "writing skill", "communication", "problem solving skills", "interpersonal"], "languages_combined": [{"language": "english", "language_level": ["good command"]}, {"language": "chinese", "language_level": ["good command"]}]}, "experience_required": {"duration": ["minimum 2 years"], "field": ["retail industry", "marketing", "media"]}}, {"job_id": "100003009054232", "location_code": "hk", "company": "Fsc Consultant Limited", "job_title": "Sales, CS & Business Development Executive - 5 Days - Excellent Benefits - (15-21K)", "description": "Requirements :\n\nHigher Dip / Bachelor degree holder or above in all disciplines\nThose with lesser qualification will also be considered\nFresh Graduate will also be considered\nExcellent communication and presentation skills\nSelf-disciplined, self-motivated, proactive and hardworking\n\nResponsibilities\u00a0:\n\nTo assist the Sales, CS & Business Development\u00a0Department to implement after- sales support service\nBasic salary plus commission offered\nProactively identify clients\u2019 needs and development\nMaintain good account relationship with existing and potential clients;\n\nWe offer:\n\nAttractive remuneration package and staff benefits\nOpportunities for professional and personal development\nCreative & friendly working environment\nFive-days work\n\nDouble Pay\n\nAnnual Leave\n\nPaid Sick Leave, Medical Benefits, Year End Bonus\n\n\nInterested parties please send your applicant letter or resume by clicking \"Apply Now\" button.", "employment_types": ["Full Time", "Permanent"], "selling_points": ["5 days, Transportation allowance", "Education allowance,Housing allowance,Medical", "14 Days annual leave, Year end bonus"], "locations": ["Central & Western Area"], "categories": ["Sales, CS & Business Devpt", "Customer Service - Supervisor / Officer", "Marketing / Public Relations", "Marketing - Direct Marketing", "Marketing - General / Support"], "post_time": "2022-01-17T08:52:21Z", "salary": {"currency": null, "max": null, "min": null, "period": "monthly", "term": null}, "salary_visible": false, "title_keywords": ["business development executive", "sales"], "responsibilities": ["maintain", "assist the sales"], "requirements": {"degrees": ["dip", "fresh graduate", "bachelor degree holder"], "majors": [], "languages": [], "language_level": [], "hard_skills": [], "soft_skills": ["self-motivated", "communication", "presentation skills", "proactive", "hardworking"], "languages_combined": []}, "experience_required": {"duration": [], "field": []}}, {"job_id": "100003009047709", "location_code": "hk", "company": "Bluesky Cosmetics Limited", "job_title": "Marketing Officer/Assistant (Full-time / Part-time)", "description": "The successful candidate will join a vibrant team of young leasing professionals to handle all leasing activities including new lettings, renewals, direct marketing, market research, budget preparation and tenancy administration of a large scale development. Further duties include coordinating premises takeover and handover, fitting-out and renovation management and handling enquiries and complaints.\nRequirements:\nUniversity degree or related professional qualifications\nMinimum 8 years or above leasing experience with 3 years in managerial position\nProactive, customer oriented, and have an eagerness to learn\nGood interpersonal communication and presentation skills\nGood command of spoken and written English and Chinese. Proficiency in Putonghua will be an advantage\nGood computer skills\nWill be based in gold coast with abundant fringe benefits\nPerform duty during weekends and public holiday is required\nWe offer attractive remuneration packages commensurate with experience and qualifications. If you aspire to an exciting and rewarding career, send your resume immediately, quoting your present and expected salaries by clicking the button\u00a0\u201cApply Now\u201d.\nIf the applicant does not receive a response by\u00a017 February 2022, the application will be considered unsuccessful. Please read our Personal Information Collection Statement at\u00a0https://www.sino.com/en-US/Careers/Personal-Information-Collection-Statement\u00a0before submitting your application. Information provided by applicants will be treated in strict confidence and used for recruitment purposes only.", "employment_types": ["Full Time", "Part Time"], "selling_points": ["Analyze the impact of marketing campaigns", "Higher diploma or above in Business Management", "12 days annual Leave / Medical Benefit"], "locations": ["Tsim Sha Tsui"], "categories": ["Marketing / Public Relations", "Marketing - Direct Marketing", "Marketing - General / Support", "Marketing - Marketing Communication"], "post_time": "2022-01-14T04:22:29Z", "salary": {"currency": null, "max": null, "min": null, "period": "monthly", "term": null}, "salary_visible": false, "title_keywords": ["assistant", "marketing officer"], "responsibilities": ["management", "renovation", "budget", "market research", "communication", "administration"], "requirements": {"degrees": ["university degree"], "majors": [], "languages": ["putonghua", "english", "chinese"], "language_level": ["advantage", "proficiency", "good command"], "hard_skills": ["computer skills", "professional qualifications"], "soft_skills": ["communication", "presentation skills", "proactive", "interpersonal"], "languages_combined": [{"language": "putonghua", "language_level": ["proficiency", "advantage"]}, {"language": "english", "language_level": ["good command"]}, {"language": "chinese", "language_level": ["good command"]}]}, "experience_required": {"duration": ["3 years", "minimum 8 years"], "field": ["managerial"]}}, {"job_id": "100003009055351", "location_code": "hk", "company": "Champion Land Properties Limited", "job_title": "Leasing Manager - Hong Kong Gold Coast", "description": "Job Responsibilities:\n\n1. To promote our wide range products\u00a0of Audio Visual / Video Conference System.\n\n2. Explore new business opportunities and well planning of sales strategies.\n\n3. Lead and manage multiple concurrent projects to achieve the target.\n\n4.\u00a0 Provide professional advice to strengthen customer loyalty.\n\n\nJob Requirements:\n\n1. Degree holder or above\u00a0with 2 years sales experience in AV, VC, AIoT Solutions.\n\u00a0 \u00a0 (Less experience can apply the post of Account Executive.)\n\n2.\u00a0Good communication, presentation, and problem -solving skills.\n\n3. Fluent spoken & written English, Mandarin & Cantonese.\n\n4. Outgoing, aggressive, responsible and proactive character.\n\n5.\u00a0Can work independently.\u00a0\n\n6. Oversea travel is required.\n\n7. Immediate available is highly preferred.\u00a0\u00a0\n\nWe Offer:\n\n5 days work\nDiscretionary performance bonus\nOn the job training\nBirthday Leave\nEducation Allowance\nTransportation subsidy\nCareer advancement opportunities\n\nWe offer attractive remuneration package to the right candidates. Interested parties, please email full resume with current and expected salary by click \u201cApply Now\u201d.\u00a0\n", "employment_types": ["Full Time", "Permanent"], "selling_points": [], "locations": ["Not Specified"], "categories": ["Sales, CS & Business Devpt", "Customer Service - Manager", "Marketing / Public Relations", "Marketing - Direct Marketing", "Marketing - Market Research"], "post_time": "2022-01-18T02:23:44Z", "salary": {"currency": null, "max": null, "min": null, "period": "monthly", "term": null}, "salary_visible": false, "title_keywords": ["leasing manager"], "responsibilities": ["audio", "planning", "explore new business opportunities", "visual"], "requirements": {"degrees": ["degree holder"], "majors": [], "languages": ["cantonese", "english", "mandarin"], "language_level": ["fluent"], "hard_skills": ["vc"], "soft_skills": ["outgoing", "work independently", "responsible", "communication", "proactive", "presentation"], "languages_combined": [{"language": "cantonese", "language_level": ["fluent"]}, {"language": "english", "language_level": ["fluent"]}, {"language": "mandarin", "language_level": ["fluent"]}]}, "experience_required": {"duration": ["2 years"], "field": []}}, {"job_id": "100003009037670", "location_code": "hk", "company": "Wai Yuen Tong Medicine Co Ltd", "job_title": "Senior Marketing Executive", "description": "\u00a0\u00a0\u00a0\u00a0\u00a0\u00a0\u00a0\u00a0\u00a0\u00a0\u00a0\u00a0\u00a0\u00a0\u00a0\u00a0\u00a0\u00a0\u00a0\u00a0\u00a0\u00a0\u00a0\u00a0\u00a0\u00a0\u00a0\u00a0\u00a0\u00a0\u00a0\u00a0\u00a0\u00a0\u00a0\u00a0\u00a0\u00a0 \u7d66\u5922\u60f3\u4e00\u500b\u6a5f\u6703\uff01\u6210\u5c31\u672a\u4f86\uff01\n\n\u6211\u5011\u76ee\u6a19\u00a0:\u00a0\u548c\u6709\u5fd7\u6210\u70ba\u512a\u79c0\u4f01\u696d\u5bb6\u7684\u9752\u5e74\u624d\u4fca\u6210\u70ba\u5408\u4f5c\u5925\u4f34\uff0c\u5354\u52a9\u4ed6\u5011\u65bc\u8ca1\u5bcc\u7b56\u5283\u884c\u696d\u4e0a\u5275\u7acb\u6301\u7e8c\u6210\u9577\u7684\u500b\u4eba\u4e8b\u696d\uff0c\u6211\u5011\u6295\u5165\u5927\u91cf\u8cc7\u6e90\u63a8\u52d5\u66f4\u5feb\u901f\u9054\u5230\u696d\u5167\u8a8d\u53ef\u80fd\u4e4b\u6700\u9ad8\u6c34\u5e73 - \u767e\u842c\u5713\u5353\u6703\u6703\u54e1\u8cc7\u683c\uff0c\u7372\u53d6\u53ef\u89c0\u6536\u5165\uff0c\u540c\u6642\u5de5\u4f5c\u548c\u751f\u6d3b\u7a6b\u4ea6\u53d6\u5f97\u5e73\u8861\u3002\n\n\u6211\u5011\u670d\u52d9\uff1a\u500b\u4eba\u65b9\u9762 - \u7406\u8ca1\u7b56\u5283\u3001\u7406\u8ca1\u98a8\u96aa\u7ba1\u7406\u3001\u8ca1\u5bcc\u589e\u503c\u914d\u7f6e\u3001\u8ca1\u5bcc\u50b3\u627f\u3001\u57fa\u91d1\u6295\u8cc7\u3001MPF\u3001\u500b\u4eba\u4fdd\u96aa / \u4f01\u696d\u65b9\u9762 : \u516c\u53f8\u4fdd\u96aa\u3001\u8981\u54e1\u4fdd\u96aa\u3001\u8cac\u4efb\u4fdd\u96aa\u7b49\u3002\n\n\u6211\u5011\u9700\u8981\uff1a\u9ad8\u7d1a\u6587\u6191 +\u5de5\u4f5c\u7d93\u9a57\uff0c\u5927\u5b78\u5b78\u58eb\u6216\u4ee5\u4e0a\uff0c\u6709\u4f01\u696d\u5bb6\u7cbe\u795e\u5275\u696d\u5bb6\u614b\u5ea6\uff0c\u76ee\u6a19\u70ba\u672c\uff0c\u71b1\u8aa0\u6a02\u89c0\n\n\u6211\u5011\u63d0\u4f9b\uff1a\u999624\u500b\u6708\u7279\u9ad8\u6d25\u8cbc+2\u9805\u4f63\u91d1+9\u9805\u82b1\u7d05\uff0c\u767e\u842c\u5713\u5353\u6703\u734e\u91d1\uff0c\u53ca\u7279\u5feb\u6649\u5347\u7ba1\u7406\u5c64\u767c\u5c55\u5718\u968a\uff0c\u5efa\u7acb\u500b\u4eba\u4f01\u696d\uff0c\u914d\u5408\u7531MDRT\u6210\u54e1,\u8ca1\u52d9\u7b56\u5283\u5e2b\u8f14\u52a9\u4e0b\u6210\u9577\n\n\u4f60\u7684\u6536\u7a6b\u00a0 : \u7121\u4e0a\u9650\u6536\u5165\u4e26\u4eab\u6709\u81ea\u4e3b\u767c\u5c55\u7a7a\u9593\uff0c\u512a\u8cea\u751f\u6d3b\uff0c\u53cb\u5584\u8077\u5834\uff0c\u5be6\u73fe\u4eba\u751f\u4e0d\u76ee\u6a19\u7406\u60f3\n\n\u6b61\u8fce\u96fb\u6216whatsapp96336822 \u8521\u5148\u751f\u67e5\u8a62", "employment_types": ["Full Time", "Permanent"], "selling_points": ["With relevant marketing experience", "Well-organized, proactive, detailed minded", "Good command in written Chinese, English"], "locations": ["Kowloon Bay"], "categories": ["Marketing / Public Relations", "Marketing - Brand / Product Management", "Marketing - Direct Marketing", "Marketing - Marketing Communication"], "post_time": "2022-01-15T03:49:12Z", "salary": {"currency": null, "max": null, "min": null, "period": "monthly", "term": null}, "salary_visible": false, "title_keywords": ["senior marketing executive"], "responsibilities": [], "requirements": {"degrees": [], "majors": [], "languages": [], "language_level": [], "hard_skills": [], "soft_skills": [], "languages_combined": []}, "experience_required": {"duration": [], "field": []}}, {"job_id": "100003009056157", "location_code": "hk", "company": "Right Choice Financial Service", "job_title": "Management Trainee / Wealth Management Manager \u7406\u8ca1\u7b56\u5283\u7d93\u7406", "description": "Job Descriptions\n\nManage social media platforms to increase customer engagement and arouse potential customers\u2019 interest\nExecute campaigns and advertisements on marketing platforms such as Google, FB, and IG, and develop strategies to optimize Sales content\nWork closely hand in hand with Sales Department\nProvide sales and administrative support\nAchieve higher levels of business goals to enable your advancement.\n\nBenefits\u00a0\n\nCompetitive remuneration package\nYoung and energetic working environment\nCareer advancement programme sponsorship\nClear career path and fast-track promotion\nMedical benefits and training allowances\n\nRequirements\n\nHigh Diploma or above\nExperience in marketing/sales\nProactive with positive mindset, excellent interpersonal & communication skill\nSolid Management skills is an absolute advantage\nWilling to learn and face challenges\nGood command of written and spoken English and Chinese", "employment_types": ["Full Time", "Internship"], "selling_points": [], "locations": ["Kwun Tong"], "categories": ["Insurance", "Insurance Agent / Broker", "Marketing / Public Relations", "Marketing - Direct Marketing", "Sales, CS & Business Devpt", "Direct Sales"], "post_time": "2022-01-18T03:26:33Z", "salary": {"currency": null, "max": null, "min": null, "period": "monthly", "term": null}, "salary_visible": false, "title_keywords": ["\u7406\u8ca1\u7b56\u5283\u7d93\u7406", "management trainee", "wealth management manager"], "responsibilities": ["business goals", "develop strategies", "administrative support", "advertisements", "social media platforms"], "requirements": {"degrees": [], "majors": [], "languages": [], "language_level": [], "hard_skills": [], "soft_skills": [], "languages_combined": []}, "experience_required": {"duration": [], "field": []}}, {"job_id": "100003009051275", "location_code": "hk", "company": "Keep With Faith Company", "job_title": "Digital Marketing Executive", "description": "Job Description\n\nLocate new business opportunities as potential digital marketing products both independently and under the guidance of team leader;\nProspecting, identifying and acquiring new HK based clients for selling online marketing advertising solutions (e.g. WeChat/China Advertising/China KOLs,etc);\nFollow up sales Leads, prepare sales pitch and agreements with marketing team;\nMaintain good relationships with clients, regular review and up-selling various advertising solutions to enhance their advertising performance/effect;\nExecute inhouse media investment plan by working closely with Marketing Director to enhance the market impact of Our Company;\nManage clients\u2019 projects, including defining deliverables, schedule and setting milestones, resources planning, coordinating internal resources, expectation management, launch, KPI tracking and post-campaign evaluation, etc.\n\nThe Successful Applicant\n\n1-4 years Sales or Marketing / Advertising / PR experience;\nOnline-media savvy is a big advantage;\nKnowledge in China media (social media, KOLs, Tencent, Douyin, Xiaohongshu, Video platform, etc), but not a must, training will be delivered;\nCreative, Dynamic, embracing changes personally;\nGood communication skills in both English & Chinese;\nImmediate availability is preferred;\nCandidate with higher qualification and relevant working experience will be considered as Senior Business Development Executive / Assistant Business Development Manager.\n\nWhat's On Offer\n\nAttractive Remuneration Package and Benefits\nIncentive & commission schemes will be offered\n5-day work\nBank Holidays and other special leave (e.g. Birthday Leave, Wedding Leave and Family Leave, etc.)\nMedical Insurance\nSales and Product training will be provided\nTeam Building Activities\nOpportunity for Job Promotion\nFriendly Work Environment\nInterest parties please send your CV with availability, current and expected salary to us.\n\n**Personal data collected will be used for recruitment purpose only**\n", "employment_types": ["Full Time", "Permanent"], "selling_points": ["Handle customers enquires", "Manage social media channel feedback and data supp", "Clear career path with attractive bonus"], "locations": ["Not Specified"], "categories": ["Marketing / Public Relations", "Marketing - Direct Marketing", "Others", "Student / Fresh Graduate / No Experience", "Digital Marketing"], "post_time": "2022-01-15T07:02:55Z", "salary": {"currency": null, "max": null, "min": null, "period": "monthly", "term": null}, "salary_visible": false, "title_keywords": ["digital marketing executive"], "responsibilities": ["guidance", "management", "tracking", "advertising", "social media", "business opportunities", "prepare sales", "regular review", "communication", "maintain", "digital marketing", "schedule", "plan", "evaluation", "planning"], "requirements": {"degrees": [], "majors": [], "languages": ["english", "chinese"], "language_level": ["good"], "hard_skills": ["dynamic", "wechat"], "soft_skills": ["communication skills", "dynamic", "independently", "creative"], "languages_combined": [{"language": "english", "language_level": ["good"]}, {"language": "chinese", "language_level": ["good"]}]}, "experience_required": {"duration": ["1-4 years"], "field": ["pr", "advertising", "business development", "relevant working experience", "marketing"]}}, {"job_id": "100003009053447", "location_code": "hk", "company": "Madcradle Online Limited", "job_title": "(Senior) Business Development Executive", "description": "There\u2019s NO NEXT TIME. It\u2019s NOW or NEVER!\n\nWhat you have to do:\n\n-\u00a0\u00a0\u00a0\u00a0\u00a0\u00a0 Attending roadshow and events\n\n-\u00a0\u00a0\u00a0\u00a0\u00a0\u00a0 Providing friendly customer service\n\n-\u00a0\u00a0\u00a0\u00a0\u00a0\u00a0 Working closely with the teams\n\n-\u00a0\u00a0\u00a0\u00a0\u00a0\u00a0 Planning project and territory\n\n-\u00a0\u00a0\u00a0\u00a0\u00a0\u00a0 Being joyful and have fun during happy hour\n\nWhat kind of people we are looking for:\n\n-\u00a0 \u00a0 \u00a0 Outgoing and Strong interpersonal skills\n\n-\u00a0 \u00a0 \u00a0 Responsible and Punctual\n\n-\u00a0 \u00a0 \u00a0 Brave enough to accept challenges and rejections\n\n-\u00a0 \u00a0 \u00a0 Hold every single opportunity\n\n-\u00a0 \u00a0 \u00a0 Fluent in Cantonese\n\nWhat we will offer:\n\n-\u00a0 \u00a0 \u00a0 Individual Trainer to conduct on-the-job training and guidance\n\n-\u00a0 \u00a0 \u00a0 Amazing co-working space (with the handsome boss)\n\n-\u00a0 \u00a0 \u00a0 Travel opportunity for exposing (every 3 - 4month)\n\n- \u00a0\u00a0\u00a0\u00a0\u00a0Fast track career programs from sales to management\n\n-\u00a0 \u00a0 \u00a0 A large group of new friends\n\n-\u00a0 \u00a0 \u00a0 Team activities / Happy hour after work\n\nChoose A Job You Love, and You Will Never Have to Work a Day in Your Life.\n\nJOIN US NOW!\u00a0https://royalty.hk/", "employment_types": ["Full Time", "Permanent"], "selling_points": ["Locate new clients & follow up sales lead", "Assist to execute inhouse marketing plan", "Manage clients\u2019 Marketing & advertising projects"], "locations": ["Kwun Tong"], "categories": ["Sales, CS & Business Devpt", "Business Development", "Marketing / Public Relations", "Marketing - Direct Marketing", "Marketing - General / Support"], "post_time": "2022-01-17T06:59:53Z", "salary": {"currency": null, "max": null, "min": null, "period": "monthly", "term": null}, "salary_visible": false, "title_keywords": ["business development executive"], "responsibilities": ["customer service", "teams", "planning"], "requirements": {"degrees": [], "majors": [], "languages": ["cantonese"], "language_level": ["fluent"], "hard_skills": ["no", "fun"], "soft_skills": ["outgoing", "responsible", "customer service", "friendly", "interpersonal skills"], "languages_combined": [{"language": "cantonese", "language_level": ["fluent"]}]}, "experience_required": {"duration": [], "field": []}}, {"job_id": "100003009052750", "location_code": "hk", "company": "Telford International Co Ltd", "job_title": "Marketing Executive / Senior Marketing Executive - Beverage Division", "description": "Responsibilities:\n\nAssist Brand Manager to manage brands / products\u00a0\nTake initiative to develop marketing programs targeted at both consumers and trade customers, and implement a mix of marketing activities\nWork with the sales team to formulate trade promotion strategy and programs for key customers\nBuild up and maintain good relationship with media & agencies\nHandle marketing administrative works including reporting, claims and inventory control\nCoordinate with various departments to ensure promotions and activities are executed\n\nRequirement:\u00a0\n\nDegree in Marketing / Hospitality is preferred\nMin 2-4 years or above working experience preferably in FMCG or beverage industry\nSensitive to numbers and strong analytical skills\nSelf-motivated, fast learner with good multi-tasking skills to meet tight deadlines\nExcellent communication and inter-personal skill\nCandidate with more experience will be considered as Senior Marketing Executive\nImmediate available is preferred\n\n\n\nWe offer attractive remuneration package and career prospects plus 5-day week and medical insurance. Interest parties, please forward your full resume with expected salary to\u00a0apply now.\n\nAll data collected shall be solely for recruitment purpose.\n\nWebsite\u00a0\u00a0 :\u00a0\u00a0\u00a0\u00a0\u00a0\u00a0\u00a0http://www.telford.com.hk/", "employment_types": ["Full Time", "Permanent"], "selling_points": ["Degree in Marketing / Hospitality is preferred", "2-4 years exp. in FMCG or beverage industry", "Sensitive to numbers and strong analytical skills"], "locations": ["Kwai Hing"], "categories": ["Marketing / Public Relations", "Marketing - Brand / Product Management", "Marketing - Direct Marketing", "Marketing - Marketing Communication"], "post_time": "2022-01-17T03:55:34Z", "salary": {"currency": null, "max": null, "min": null, "period": "monthly", "term": null}, "salary_visible": false, "title_keywords": ["senior marketing executive", "marketing executive"], "responsibilities": ["reporting", "coordinate with", "maintain good relationship", "develop", "inventory control", "sales team"], "requirements": {"degrees": ["degree"], "majors": ["hospitality", "marketing"], "languages": [], "language_level": [], "hard_skills": ["analytical skills"], "soft_skills": ["self-motivated", "meet tight deadlines", "analytical skills", "communication", "inter-personal skill", "multi-tasking skills", "sensitive to numbers", "fast learner"], "languages_combined": []}, "experience_required": {"duration": ["min 2-4 years"], "field": ["fmcg", "beverage industry", "marketing"]}}, {"job_id": "100003009056074", "location_code": "hk", "company": "DFI Retail Group DFI\u96f6\u552e\u96c6\u5718", "job_title": "Senior Marketing Executive - yuu", "description": "We are looking for a highly driven and motivated Senior\u00a0Marketing Executive, Campaign to join our yuu team based in Hong Kong. The Marketing Team drives the growth and marketing strategies at yuu and aims to making yuu the no.1 digital platform in online services and customer loyalty. With yuu\u2019s ultra-high brand awareness and its mega size retail partnership network, your work will directly make an impact to a high population of HKers. Candidate with deeper experience can be considered a Senior Marketing Executive position.\n\nAbout the team\n\nThe Marketing Campaign team are the PICs of marketing campaigns end-to-end, from ideation through to execution. You will take part in developing consumer-centric CRM and or advertising campaign strategies and executions for different business verticals, including loyalty campaigns across multiple brands, yuu brand communications and other new yuu services.\n\nOur Job\n\nWork directly with Marketing Director and Marketing Manager, with the opportunity to take ownership of marketing projects\nThe role will be varied; supporting the entire team on a number of digital projects encompassing daily communication of our promotions and in addition to helping with offline marketing and partnership communications\nYou will be required to produce scheduled CRM communications in brand\u2019s tone and manner and lead the compilation of regular reports with key outcomes and learnings\nManage creative briefs and prepare promotional materials on both online and traditional advertising\nManage ad hoc promotions and requests with efficiency\n\nOur Role\n\nProactive, self-motivated and ready to contribute anytime\nUniversity degree in business, marketing, PR / communications or related areas\nWith 1-3 years working experience\nSociable character and positive attitude towards new challenges\nEstablish and maintain relationships with internal departments\nWork closely with the team to support the daily communication management and handle ad hoc requests\nExcellent communication and interpersonal skills, fluency in both English and Cantonese\nExperience in CRM and/or loyalty programme, or eCommerce definitely an advantage\nAdaptable in a fast-paced environment\n\n\u201cDFI Retail Group is responsible for ensuring that all personal information collected from each Candidate presented to DFI Retail Group is used for recruitment purposes only and the data collection process is in accordance with all applicable laws and compliant with the Code of Practice on Human Resource Management.\n\nTo find out more about Our Businesses and Our People, please visit our website: https://www.DFIretailgroup.com\n\nWe are an equal opportunity employer. Personal data collected will be kept and handled confidentially by authorised personnel for recruitment purposes only. We will retain the applications of candidates not selected for a period of no more than 24 months. A copy of our Privacy Policy can be accessed by visiting our Company website.\u201d\n\nIssued by The Dairy Farm Company, Limited", "employment_types": ["Permanent"], "selling_points": [], "locations": ["Tai Koo"], "categories": ["Marketing / Public Relations", "Marketing - Direct Marketing"], "post_time": "2022-01-18T03:14:54Z", "salary": {"currency": null, "max": null, "min": null, "period": "monthly", "term": null}, "salary_visible": false, "title_keywords": ["senior marketing executive"], "responsibilities": ["maintain relationships", "management", "advertising", "marketing strategies", "ad hoc", "ad hoc requests", "developing", "digital platform", "marketing projects", "communication", "website", "promotional materials", "reports", "recruitment", "marketing campaigns", "data collection", "personal data", "company website"], "requirements": {"degrees": ["university degree"], "majors": ["business", "communications", "marketing"], "languages": ["cantonese", "english"], "language_level": ["fluency", "excellent"], "hard_skills": ["make", "no", "code"], "soft_skills": ["self-motivated", "proactive", "responsible", "adaptable", "fast-paced environment", "sociable", "communication", "positive attitude", "motivated", "communication and interpersonal skills", "creative", "driven"], "languages_combined": [{"language": "cantonese", "language_level": ["fluency", "excellent"]}, {"language": "english", "language_level": ["fluency", "excellent"]}]}, "experience_required": {"duration": ["1-3 years"], "field": ["ecommerce", "marketing"]}}, {"job_id": "100003009052396", "location_code": "hk", "company": "Knight Recruitment Services Limited", "job_title": "Digital Marketing Specialist (HK$28K-$35K x 13m; International Digital Agency; Tsim Sha Tsui)", "description": "Digital Marketing Specialist (HK$28K-$35K x 13m; International Digital Agency; Tsim Sha Tsui)\n\nOur client is a large International Digital Agency, they are currently looking for a\u00a0Digital Marketing Specialist to join their growing team.\n\nKey Responsibilities:\n\nDevelop, optimise and execute digital marketing strategies via social media, instant messengers or any new media platforms etc. to enhance performance of various business divisions\nManage client's online acquisition channels including Instagram, Facebook, LinkedIn, Pinterest, Twitter and YouTube etc.\u00a0\nPrepare media plan, budget summary and execute advertisement campaign with reports\nFamiliarity and know-how on web site development techniques, Content Management Systems (CMS), server responses, end-users\u2019 experience and conversion optimization.\nUtilize all functionalities of implementation tools, which include Google Analytics, Google Adwords, Google Keyword Tool, Keyword ranking tools, SEOmoz tools, Link Research Tools, Webmaster tools etc.\nLiaise with regional SEO/SEM teams, clients and search engines representatives to provide effective solution. \u2022Assist team manager on SEO elements implementation, both semantic and technical level.\n\nRequirements:\n\nUniversity graduate in Digital Marketing, Marketing, Communication or Business related disciplines\n4 years relevant work experience; digital experience in luxury/FMCG field preferred\u00a0\nSolid knowledge of website and marketing analytics tools (e.g. google analytics,\u00a0Google AdWords, Facebook ad manager etc.)\nCreative, flexible, and sensitive to marketing trend\u00a0\nGood analytical skill in resolving problems and multi-tasking\u00a0\nStrong on team work with proactive and collaborative manner\nFluent in both spoken and written English and Chinese (Cantonese/Mandarin)\n\nFor more information, please send your resume complete with cover letter to: yuki.wan@ knightrecruits.com\n\nData collected will be used for recruitment purposes only. Personal data provided by job applicants will be used strictly in accordance with the Personal Data (Privacy) Ordinance. We regret that only the shortlisted candidates will be notified.", "employment_types": ["Full Time", "Permanent"], "selling_points": ["HK$28K-$35K x 13month", "International Digital Agency", "Tsim Sha Tsui, 5 Day"], "locations": ["Tsim Sha Tsui"], "categories": ["Media & Advertising", "Strategic Planning", "Marketing / Public Relations", "Marketing - Direct Marketing", "Digital Marketing"], "post_time": "2022-01-17T02:56:59Z", "salary": {"currency": null, "max": null, "min": null, "period": "monthly", "term": null}, "salary_visible": false, "title_keywords": ["digital marketing specialist"], "responsibilities": ["social media", "management", "digital marketing strategies", "seo", "budget", "systems", "implementation", "teams", "develop", "reports", "plan", "sem", "liaise with", "facebook"], "requirements": {"degrees": ["university graduate"], "majors": ["business", "related disciplines", "marketing", "digital marketing"], "languages": ["cantonese", "english", "chinese", "mandarin"], "language_level": ["fluent"], "hard_skills": ["analytics tools", "google analytics", "analytical skill", "adwords", "facebook"], "soft_skills": ["flexible", "analytical skill", "proactive", "collaborative", "communication", "sensitive to", "multi-tasking", "creative"], "languages_combined": [{"language": "cantonese", "language_level": []}, {"language": "english", "language_level": ["fluent"]}, {"language": "chinese", "language_level": ["fluent"]}, {"language": "mandarin", "language_level": []}]}, "experience_required": {"duration": ["4 years"], "field": ["digital", "fmcg"]}}, {"job_id": "100003009056350", "location_code": "hk", "company": "Sky-Tech (I.T.) Management Limited", "job_title": "Account Manager / Account Executive", "description": "Job Responsibilities:\n\n1. To promote our wide range products\u00a0of Audio Visual / Video Conference System.\n\n2. Explore new business opportunities and well planning of sales strategies.\n\n3. Lead and manage multiple concurrent projects to achieve the target.\n\n4.\u00a0 Provide professional advice to strengthen customer loyalty.\n\n\nJob Requirements:\n\n1. Degree holder or above\u00a0with 2 years sales experience in AV, VC, AIoT Solutions.\n\u00a0 \u00a0 (Less experience can apply the post of Account Executive.)\n\n2.\u00a0Good communication, presentation, and problem -solving skills.\n\n3. Fluent spoken & written English, Mandarin & Cantonese.\n\n4. Outgoing, aggressive, responsible and proactive character.\n\n5.\u00a0Can work independently.\u00a0\n\n6. Oversea travel is required.\n\n7. Immediate available is highly preferred.\u00a0\u00a0\n\nWe Offer:\n\n5 days work\nDiscretionary performance bonus\nOn the job training\nBirthday Leave\nEducation Allowance\nTransportation subsidy\nCareer advancement opportunities\n\nWe offer attractive remuneration package to the right candidates. Interested parties, please email full resume with current and expected salary by click \u201cApply Now\u201d.\u00a0\n", "employment_types": ["Full Time", "Permanent"], "selling_points": ["To Provide Suitable Enviroment for Employees", "To Build up a Great Own Career Path", "To Widen the Scoop and Horizon"], "locations": ["Central & Western Area"], "categories": ["Information Technology (IT)", "Hardware", "Marketing / Public Relations", "Marketing - Direct Marketing", "Sales, CS & Business Devpt", "Direct Sales"], "post_time": "2022-01-18T04:08:17Z", "salary": {"currency": null, "max": null, "min": null, "period": "monthly", "term": null}, "salary_visible": false, "title_keywords": ["account executive", "account manager"], "responsibilities": ["audio", "planning", "explore new business opportunities", "visual"], "requirements": {"degrees": ["degree holder"], "majors": [], "languages": ["cantonese", "english", "mandarin"], "language_level": ["fluent"], "hard_skills": ["vc"], "soft_skills": ["outgoing", "work independently", "responsible", "communication", "proactive", "presentation"], "languages_combined": [{"language": "cantonese", "language_level": ["fluent"]}, {"language": "english", "language_level": ["fluent"]}, {"language": "mandarin", "language_level": ["fluent"]}]}, "experience_required": {"duration": ["2 years"], "field": []}}, {"job_id": "100003009050078", "location_code": "hk", "company": "Royalty HK Limited", "job_title": "Marketing and Promotion Trainee - (Entry Level)", "description": "There\u2019s NO NEXT TIME. It\u2019s NOW or NEVER!\n\nWhat you have to do:\n\n-\u00a0\u00a0\u00a0\u00a0\u00a0\u00a0 Attending roadshow and events\n\n-\u00a0\u00a0\u00a0\u00a0\u00a0\u00a0 Providing friendly customer service\n\n-\u00a0\u00a0\u00a0\u00a0\u00a0\u00a0 Working closely with the teams\n\n-\u00a0\u00a0\u00a0\u00a0\u00a0\u00a0 Planning project and territory\n\n-\u00a0\u00a0\u00a0\u00a0\u00a0\u00a0 Being joyful and have fun during happy hour\n\nWhat kind of people we are looking for:\n\n-\u00a0 \u00a0 \u00a0 Outgoing and Strong interpersonal skills\n\n-\u00a0 \u00a0 \u00a0 Responsible and Punctual\n\n-\u00a0 \u00a0 \u00a0 Brave enough to accept challenges and rejections\n\n-\u00a0 \u00a0 \u00a0 Hold every single opportunity\n\n-\u00a0 \u00a0 \u00a0 Fluent in Cantonese\n\nWhat we will offer:\n\n-\u00a0 \u00a0 \u00a0 Individual Trainer to conduct on-the-job training and guidance\n\n-\u00a0 \u00a0 \u00a0 Amazing co-working space (with the handsome boss)\n\n-\u00a0 \u00a0 \u00a0 Travel opportunity for exposing (every 3 - 4month)\n\n- \u00a0\u00a0\u00a0\u00a0\u00a0Fast track career programs from sales to management\n\n-\u00a0 \u00a0 \u00a0 A large group of new friends\n\n-\u00a0 \u00a0 \u00a0 Team activities / Happy hour after work\n\nChoose A Job You Love, and You Will Never Have to Work a Day in Your Life.\n\nJOIN US NOW!\u00a0https://royalty.hk/", "employment_types": ["Full Time"], "selling_points": ["On-the-job Training (Individual Trainer)", "Overseas training opportunities", "Welcome fresh graduates"], "locations": ["Wan Chai"], "categories": ["Marketing / Public Relations", "Marketing - Direct Marketing", "Sales, CS & Business Devpt", "Sales - Sales Management", "Direct Sales"], "post_time": "2022-01-15T03:50:49Z", "salary": {"currency": "HKD", "max": 19999, "min": 14000, "period": "monthly", "term": null}, "salary_visible": true, "title_keywords": ["trainee"], "responsibilities": ["customer service", "teams", "planning"], "requirements": {"degrees": [], "majors": [], "languages": ["cantonese"], "language_level": ["fluent"], "hard_skills": ["no", "fun"], "soft_skills": ["outgoing", "responsible", "customer service", "friendly", "interpersonal skills"], "languages_combined": [{"language": "cantonese", "language_level": ["fluent"]}]}, "experience_required": {"duration": [], "field": []}}, {"job_id": "100003009054411", "location_code": "hk", "company": "Royale International Couriers Limited", "job_title": "Digital Marketing Executive/Officer", "description": "Job Description\nJoin us and you\u2019ll shape more than just your career\n\nLet\u2019s talk about the job\n\nIf you enjoy working on a far-reaching dimension of projects that will help flourish business, you\u2019ll fit right in. Here are some things you can expect from Royalty marketing team.\n\n\nJob Overview:\n\n-\u00a0\u00a0\u00a0\u00a0\u00a0\u00a0 Identify market opportunities to boost up consumer sales on a face-to-face level\n\n-\u00a0\u00a0\u00a0\u00a0\u00a0\u00a0 Participate in direct marketing and sales strategy by interacting face to face with customers including indoor and outdoor events\n\n-\u00a0\u00a0\u00a0\u00a0\u00a0\u00a0 Evaluate effectiveness of marketing efforts, and make adjustments\n\n-\u00a0\u00a0\u00a0\u00a0\u00a0\u00a0 Ensure that multiple field market tactics all provide a consistent message\n\n-\u00a0\u00a0\u00a0\u00a0\u00a0\u00a0 Train teams in effective communication and presentation skills\n\n\n\nJob Highlights:\n\n-\u00a0\u00a0\u00a0\u00a0\u00a0\u00a0 Extensive, multifaceted training\n\n-\u00a0\u00a0\u00a0\u00a0\u00a0\u00a0 Weekly bonus (competitive compensation, bonuses, recognition and rewards)\n\n-\u00a0\u00a0\u00a0\u00a0\u00a0\u00a0 Leaders training course\n\n-\u00a0\u00a0\u00a0\u00a0\u00a0\u00a0 Advance career driven environment\n\nRequirements:\n\n-\u00a0\u00a0\u00a0\u00a0\u00a0\u00a0 Diploma holder or equivalent;\n\n-\u00a0\u00a0\u00a0\u00a0\u00a0\u00a0 With working experience in sales or marketing in an advantage;\n\n-\u00a0\u00a0\u00a0\u00a0\u00a0\u00a0 Creative, analytical, well-organized and excellent communication skills;\n\n-\u00a0\u00a0\u00a0\u00a0\u00a0\u00a0 Self-motivated and hardworking\n\n-\u00a0\u00a0\u00a0\u00a0\u00a0\u00a0 Fluent in Cantonese", "employment_types": ["Full Time", "Permanent"], "selling_points": ["Major handling Direct Email Marketing Campaign", "Good at Marketing Database + Automation Technology", "Multi-cultural environment; B2B Email Marketing"], "locations": ["Kowloon Bay"], "categories": ["Marketing / Public Relations", "Marketing - Direct Marketing", "Marketing - Marketing Communication", "Digital Marketing"], "post_time": "2022-01-17T09:26:16Z", "salary": {"currency": null, "max": null, "min": null, "period": "monthly", "term": null}, "salary_visible": false, "title_keywords": ["officer", "digital marketing executive"], "responsibilities": ["evaluate", "teams", "communication"], "requirements": {"degrees": ["diploma holder"], "majors": [], "languages": ["cantonese"], "language_level": ["fluent"], "hard_skills": [], "soft_skills": ["communication skills", "self-motivated", "well-organized", "creative", "hardworking"], "languages_combined": [{"language": "cantonese", "language_level": ["fluent"]}]}, "experience_required": {"duration": [], "field": ["marketing"]}}, {"job_id": "100003009051949", "location_code": "hk", "company": "OSIM (HK) Co. Limited", "job_title": "Digital Marketing Executive ( 5 Days Work)", "description": "CHINA MOBILE HONG KONG COMPANY LIMITED (\"CMHK\") is the wholly-owned subsidiary of China Mobile Limited (HKEx: 941) (NYSE: CHL), which ranks\u00a065th on the Fortune Global 500.\n\nOur company strives to offer superior service experience and to become the preferable digital partner for customers. We are preserving an environment with trust, responsibility and caring. At CMHK, we commit to maximizing people\u2019s potential and paving the way toward success for every striver. We are now inviting high caliber professional to join us.\n\nDivision: Marketing\n\nIn this position, you will:\n\nTo explore the opportunities and provide recommendations/ insight of prepaid business.\nParticipate in the formulation of marketing strategy which is in line with company objectives\nSupport and provide report on customers\u2019 portfolio evaluation, behavior analysis, sales performance to develop appropriate marketing programs.\nWork with internal departments to formulate new products/ service/ offers roll-out campaigns.\nMonitor competitors; keep track on the market trend\nAssist in preparation of presentation materials, written reports and proposals\nOther ad hoc duties assigned by management\n\nTo be successful in this position, you should meet the following requirements:\n\nBachelor\u2019s degree in Business Administration, Marketing or equivalent disciplines\nMinimum 4 years of working experience\u00a0in consumer marketing / technology / Telecom industry\nExperience in implement end to end acquisition program, developing marketing plans and campaigns\nGood understanding in business operations\nGood coordination, project management, multitasking and presentation skills\nKnowledge in IT system is a plus\nSelf-motivated, attention to details, multi-tasking and able to work under pressure\nFluency in written and spoken English, Cantonese and Mandarin\nCandidate with less experience may consider as Marketing Executive\n\nWhen you work:\n\n5 days work\n8 hours/day\n\nWhat you enjoy:\n\nDouble pay\nDiscretionary Performance bonus\nLife insurance\nMedical insurance\nEducation subsidies\nBirthday gift\nMarriage leave\nBirthday leave\nStaff discount\n\nCMHK is committed to be an equal opportunity employer. We offer exceptional benefits package and the opportunity to work in a challenging environment. Personal data provided by applicants will be treated strictly in accordance with our personal data policy and for recruitment purposes only.\n\nPlease submit your application to us by clicking the APPLY NOW button and send your full resume with your availability, current and expected salary to us.", "employment_types": ["Full Time", "Permanent"], "selling_points": [], "locations": ["Shatin Area"], "categories": ["Marketing / Public Relations", "Marketing - Direct Marketing", "Others", "E-commerce", "Marketing - Brand / Product Management"], "post_time": "2022-01-17T01:36:24Z", "salary": {"currency": null, "max": null, "min": null, "period": "monthly", "term": null}, "salary_visible": false, "title_keywords": ["digital marketing executive"], "responsibilities": ["marketing plans", "operations", "evaluation", "administration", "ad hoc duties", "work under pressure", "sales performance", "monitor", "developing", "develop", "reports", "report", "management", "provide recommendations", "analysis", "preparation of presentation materials", "project management", "coordination", "insurance"], "requirements": {"degrees": ["degree", "bachelor"], "majors": ["marketing", "business administration"], "languages": ["cantonese", "english", "mandarin"], "language_level": ["fluency"], "hard_skills": ["mobile", "analysis", "project management", "plus"], "soft_skills": ["self-motivated", "work under pressure", "project management", "presentation skills", "multi-tasking", "committed", "coordination", "attention to details", "presentation", "superior"], "languages_combined": [{"language": "cantonese", "language_level": ["fluency"]}, {"language": "english", "language_level": ["fluency"]}, {"language": "mandarin", "language_level": ["fluency"]}]}, "experience_required": {"duration": ["minimum 4 years"], "field": ["digital", "marketing", "developing"]}}, {"job_id": "100003009052821", "location_code": "hk", "company": "China Mobile Hong Kong \u4e2d\u570b\u79fb\u52d5\u9999\u6e2f", "job_title": "Senior Marketing Executive, Marketing planning (prepaid)", "description": "Responsibilities:\n\nCreate attractive content and manage promotion in social media platform\nPreform brand building and formulate marketing strategies through comprehensive understanding of market needs\nImplement marketing and promotion activities on online & offline channel with a focus on SEO optimization\nAnalyze the impact of marketing campaigns and prepare measurement reports\n\n\u00a0Requirements:\n\nHigher diploma or above in Business Management, Marketing or other related disciplines\n2 years or above experience\nResourceful, positive thinking, creative, self-motivated, well organized and multi-tasking\nGood command of spoken and written in both English and Chinese (Mandarin and Cantonese)\n\nBenefits:\n\n12 days annual Leave\nMedical Benefit\n5 days working per week\nPerformance bonus\n\nSalary:\n\n\n18K -20K\n\nJoin us now:\n\nPlease send full resume stating your academic qualifications, career history, availability with current and expected salary to: The HR Dept.\n\nWebsite: oulaccosmetics.com /\u00a0blueskycolors.com", "employment_types": ["Full Time", "Permanent"], "selling_points": ["14 AL, 5 days work week", "double pay, dis. performance bonus", "Staff SIM, Staff Offer"], "locations": ["Kwai Hing"], "categories": ["Marketing / Public Relations", "Management", "Marketing - Brand / Product Management", "Marketing - Direct Marketing"], "post_time": "2022-01-17T16:20:50Z", "salary": {"currency": null, "max": null, "min": null, "period": null, "term": null}, "salary_visible": false, "title_keywords": ["senior marketing executive"], "responsibilities": ["social media", "seo", "marketing strategies", "measurement", "reports", "marketing campaigns"], "requirements": {"degrees": ["higher diploma or above"], "majors": ["related disciplines", "business", "marketing"], "languages": ["cantonese", "english", "chinese", "mandarin"], "language_level": ["good command"], "hard_skills": ["business management"], "soft_skills": ["self-motivated", "resourceful", "well organized", "positive thinking", "multi-tasking", "creative"], "languages_combined": [{"language": "cantonese", "language_level": ["good command"]}, {"language": "english", "language_level": ["good command"]}, {"language": "chinese", "language_level": ["good command"]}, {"language": "mandarin", "language_level": ["good command"]}]}, "experience_required": {"duration": ["2 years"], "field": []}}, {"job_id": "100003009054474", "location_code": "hk", "company": "Radica Systems Limited", "job_title": "Associate Account Director", "description": "RADICA was founded in 2000, headquartered in Hong Kong with 2 regional offices at Guangzhou and Shanghai. We develop eMarketing Communication automation solutions to our clients ranging from international luxury brands, Fortune 500 to the publicly listed companies. We focus on growing the value of their customer database by making wise use of data analytics in direct marketing. Over 300 enterprises are using our database marketing platform to deliver millions of Digital Communications to their customers every day.\u00a0\n\n\n\u00a0WHAT YOU'LL DO:\u00a0\u00a0\n\nTo lead a team of account executives and designers, developing content marketing, analyzing multi-channels\u2019 effectiveness, and maximizing clients\u2019 customer lifecycle value, ensure high quality of project deliverables for clients\nTo develop CRM & e-marketing consulting proposals & presentation to clients\nTo plan & design Marketing automation journey with the proposal preparation, implementation planning\u00a0& periodical review\nAchieve client's KPIs through the application of creativity, data insight and applicable marketing technology.\nManage account\u2019 P&L to ensure the delivery is executed on time and on budget\nProactively perform regular eMarketing benchmarking research, monitor digital marketing & CRM trends, develop new service scope is a good plus\nProvide on-the-job training and coaching to team members\n\nWHAT QUALIFICATIONS YOU NEED TO GET:\u00a0 \u00a0 \u00a0\u00a0\n\n\u00a0Degree in Business Administration, Marketing or related disciplines\n\u00a0Minimum 7 years of experience in digital marketing, data analysis and project management\nHands-on experience & proven track records in digital and multi-channel e-marketing projects\nStrong knowledge of database management, data analysis, segmentation & marketing automation which drives positive results\nExcellent leadership and people management skills\nStrong business sense, communication & organizational skill\nGood command of both written Chinese and English\nDetail-minded and self-motivated with strong communication, interpersonal and analytical skills\nSometimes travel to China is expected after pandemic\nMore experienced candidate may consider as Account Director\n\nWHAT YOU WILL LOVE ABOUT US:\u00a0\n\nGreat Company Culture. Dynamic working environment\n23 Days Paid Leave\nFlexible working hours. Free snack bar and drinks in office\nEntitle Medical Insurance, Health Check-up/ Dental allowance\nEntitle training subsidy. Take the class, be equipped, get reimbursed\n\n\n\n\n\n~~~~ \u00a0 Data makes our life more meaningful ~~~~\n\nData held by the company relating to employment applications will be kept confidential and used only for processing applications. Applications who are not contacted within 1 month may consider their applications unsuccessful.\n\nAll personal data of unsuccessful applicants will be retained for a maximum period of two years and may refer suitable applicants to other vacancies within the company.", "employment_types": ["Full Time", "Permanent"], "selling_points": ["Expertise in Database Marketing & automation", "Dynamic and flexible working environment", "Team Leader and regional exposure"], "locations": ["Lai Chi Kok"], "categories": ["Media & Advertising", "Account Servicing", "Marketing / Public Relations", "Marketing - Direct Marketing", "Digital Marketing"], "post_time": "2022-01-17T09:42:34Z", "salary": {"currency": null, "max": null, "min": null, "period": "monthly", "term": null}, "salary_visible": false, "title_keywords": ["associate", "account director"], "responsibilities": ["consulting", "data", "budget", "quality", "design", "communication", "database", "plan", "personal data", "administration", "monitor", "developing", "implementation", "develop", "p&l", "kpis", "management", "review", "marketing projects", "data analysis", "digital marketing", "project deliverables", "lead a team", "project management", "insurance", "planning"], "requirements": {"degrees": ["degree"], "majors": ["related disciplines", "marketing", "business administration"], "languages": ["english", "chinese"], "language_level": ["good command"], "hard_skills": ["plus", "data analytics", "analysis", "analytical skills", "project management", "dynamic", "focus", "processing"], "soft_skills": ["detail-minded", "flexible", "self-motivated", "organizational skill", "business sense", "analytical skills", "communication", "project management", "hands-on", "dynamic", "focus", "interpersonal", "leadership", "presentation", "positive"], "languages_combined": [{"language": "english", "language_level": ["good command"]}, {"language": "chinese", "language_level": ["good command"]}]}, "experience_required": {"duration": ["minimum 7 years"], "field": ["data analysis", "project management", "marketing", "digital marketing", "digital"]}}, {"job_id": "100003009051666", "location_code": "hk", "company": "Genfortune Pharmaceuticals Limited", "job_title": "Digital Marketing Executive (5 days)", "description": "Requirements:\n\nDiploma / Associate Degree/ Degree in IT / Web / Graphic / Multimedia Design or related disciplines, better with e-commerce knowledge.\nHands-on experience in Adobe AI and Photoshop proficiently.\nFamiliar with social platforms like: Facebook, Instagram, Wechat and TikTok etc. with strategical mindset.\n\nResponsibilities:\n\nPlanning, designing and executing marketing strategies and create product catalogs.\nResponsible for social platform content (copywriting, photos and videos) via Facebook, Instagram, Wechat and TikTok etc.\nGood at data collection, self-solving ability, able to w\nWork independently.\nExperience in editing videos, familiar with social media advertising and operation is a plus.\u00a0\n\nWe offered benefits to staff:\n\nMedical Insurance\nAnnual Leave\n5-days work\nBank holidays\nDouble Pay\nPerformance bonus\nStaff discount\u00a0\n\nInterested parties please send us your full resume, expected salary and applied position to HR Dept. through APPLY NOW\u00a0\n\nAll information collected is for recruitment purpose only.", "employment_types": ["Full Time", "Permanent"], "selling_points": ["E-commerce knowledge", "Familiar with social platforms", "Staff discount/Medical Insurance/Performance bonus"], "locations": ["Quarry Bay"], "categories": ["Marketing / Public Relations", "Marketing - Brand / Product Management", "Marketing - Direct Marketing", "E-commerce", "Marketing - Brand / Product Management"], "post_time": "2022-01-16T21:50:37Z", "salary": {"currency": null, "max": null, "min": null, "period": "monthly", "term": null}, "salary_visible": false, "title_keywords": ["digital marketing executive"], "responsibilities": ["social media", "marketing strategies", "advertising", "executing", "data collection", "designing", "facebook", "editing", "planning"], "requirements": {"degrees": ["associate degree", "diploma", "degree"], "majors": ["multimedia design", "related disciplines", "it", "e-commerce"], "languages": [], "language_level": [], "hard_skills": ["web", "ai", "e-commerce", "wechat", "adobe", "multimedia", "facebook", "photoshop"], "soft_skills": ["hands-on"], "languages_combined": []}, "experience_required": {"duration": [], "field": []}}, {"job_id": "100003009055160", "location_code": "hk", "company": "", "job_title": "Business Development Manager (Apply to IANG applicant)", "description": "\u00a0 \u00a0 \u00a0 \u00a0 \u00a0 \u00a0 \u00a0 \u00a0 \u00a0 \u00a0 \u00a0 \u00a0 \u00a0 \u00a0 \u00a0 \u00a0 \u00a0 \u00a0 \u00a0 \u00a0 \u00a0 \u00a0 \u00a0 \u00a0 \u00a0 (Limited quota and subject to stop plan)\n\nIn this role, you will\nmonitor sales growth,\u00a0capture financial needs with prompt follow up on analytically driven leads\nengage end to end customer service including needs identification, solution recommendations, application fulfillment, and follows up\nmanage individual insurance portfolio to ensure the customer satisfaction and persistency\nestablish effective working relationships with teams in order to ensure a consistent approach.\nbuild and maintain a positive team culture, through ensuring quality business referrals and referral skills among team members, and contributing to product knowledge and skills sharing\nEnjoy team activities, such as local charity, learn cantonese, movie day, and BBQ night with team members.\nWe are looking for:\nUniversity degree holder or above, preferably in sales and finance, less experienced will be considered as Financial Planning Officer\u00a0\nBeing ambitious in developing your own career with independence\nEntrepreneurship, achievement orientation, initiative and customer services orientation\nExcellent interpersonal, communications, presentation skills\nEnjoy stay in Hong Kong and work with local/oversea graduate trainee, work smart, play hard.\nImmediately available preferred\u00a0\nWe offer:\nExcellent and fast track career path\u00a0\nComprehensive and professional on job training\nAttractive package with month allowance, performance bonus and annual bonus\u00a0\nLuxurious annual overseas conferences\u00a0\nGroup life and group medical\u00a0\nInterested parties please call Ms Tracy Au at 9254-8810 for confidential conservation.", "employment_types": ["Full Time", "Permanent", "Contract", "Freelance"], "selling_points": [], "locations": ["Kwun Tong"], "categories": ["Banking / Finance", "Retail Banking", "Insurance", "Insurance Agent / Broker", "Marketing / Public Relations", "Marketing - Direct Marketing"], "post_time": "2022-01-18T01:33:44Z", "salary": {"currency": null, "max": null, "min": null, "period": "monthly", "term": null}, "salary_visible": false, "title_keywords": ["business development manager"], "responsibilities": ["fulfillment", "monitor", "teams", "quality", "developing", "customer services", "customer service", "maintain", "plan", "working relationships", "insurance", "planning"], "requirements": {"degrees": ["university degree"], "majors": ["finance"], "languages": ["cantonese"], "language_level": [], "hard_skills": ["charity"], "soft_skills": ["prompt", "driven", "presentation skills", "customer service", "work smart", "interpersonal", "initiative", "positive"], "languages_combined": [{"language": "cantonese", "language_level": []}]}, "experience_required": {"duration": [], "field": []}}, {"job_id": "100003009045908", "location_code": "hk", "company": "Reasonable Software House Limited", "job_title": "Management Trainee", "description": "Reasonable Software House Limited \u601d\u9f4a\u8edf\u4ef6\u6709\u9650\u516c\u53f8\n\nReasonable is a one of the largest email marketing software as service in Hong Kong and southern China, headquartered in Hong Kong with branches in Shenzhen, Guangzhou, Beijing and Shanghai.\u00a0Reasonable sent 4000 million emails and is a fast growing company. Reasonable is Microsoft Certified Partner, PayPal China/HK Partner and graduate company of HK Science & Technlogy Park IncuTech programme.\u00a0\n\nIf you love internet technology and digital marketing, let's join us.\u00a0\n\nProgramme details\n\nOur management trainee programme is a fast track training programme to advance your career to be our future management team and leader. To develop the trainees\u2019 functional competence and to strengthen their professional skills, we will provide trainees with opportunities to gain all-round exposure, including cross-departmental attachment training, external training courses, working in different office in different cities\u00a0and on-the-job coaching, etc. You will be able to learn:\n\nBusiness sense\nBusiness workflow and project management\nPractical knowledge in Advertising and Sales stream\nProfessional marketing skills\n\nREQUIREMENTS\n- Fresh Graduates will be considered\n- Knowledge in online marketing (e.g. SEO, Email Marketing, Social Media) is an advantage\n- Strong communication skills with sense of work prioritization and outgoing personality\n- Fluent in both spoken and written Chinese and English, Mandarin is an added advantage\n- Immediate available is an advantage\n\nBENEFITS\nMPF / Medical Insurance /\u00a0Free Snacks / Weekly Team Lunch / Happy Working Environment\n\nWe provide attractive remuneration package and practical training to the right candidate(s). Interested\u00a0individuals may send your cover letter and resume with expected salary to HR dept hr[at]reasonable.hk. Collected personal data is used for recruitment purpose only.\n\n", "employment_types": ["Full Time", "Permanent"], "selling_points": ["email marketing, digital marketing", "reseller network", "SEO, SEM"], "locations": ["Sham Shui Po Area"], "categories": ["Media & Advertising", "Account Servicing", "Marketing / Public Relations", "Marketing - Direct Marketing", "Others", "Student / Fresh Graduate / No Experience"], "post_time": "2022-01-13T09:04:50Z", "salary": {"currency": "HKD", "max": 24999, "min": 20000, "period": "monthly", "term": null}, "salary_visible": true, "title_keywords": ["management trainee"], "responsibilities": ["management team", "management", "social media", "advertising", "software", "seo", "develop", "communication", "project management", "digital marketing"], "requirements": {"degrees": [], "majors": [], "languages": ["english", "chinese", "mandarin"], "language_level": ["advantage", "fluent"], "hard_skills": ["project management", "marketing skills", "seo"], "soft_skills": ["communication skills", "project management", "outgoing personality", "business sense"], "languages_combined": [{"language": "english", "language_level": ["fluent"]}, {"language": "chinese", "language_level": ["fluent"]}, {"language": "mandarin", "language_level": ["advantage", "fluent"]}]}, "experience_required": {"duration": [], "field": []}}, {"job_id": "100003009045771", "location_code": "hk", "company": "Three Commas Group Limited", "job_title": "Senior Digital Marketing Executive", "description": "Job Highlights\n\nDigital Marketing Campaigns\nOnline Advertising Campaigns (SEO/SEM)\nSocial Media & Content Writing\n\n\nJob Description\n\nImplement corporate marketing and thematic programs to support business goals & brand KPIs for a portfolio of brand\nDevelop digital marketing and social media content calendar, integrate social media strategies, digital and event campaigns align with brand objectives\nSupport the execution of various online marketing initiatives and end-to end logistics including direct mailings, eDM, SMS, copywriting, social media brand marketing, interactive online campaign development, etc.\nLiaise with potential collaboration for new partnership opportunities and engagement campaigns\nManage digital marketing campaign budget, oversee campaign executions and post-campaign evaluations\nEnsure all digital marketing campaigns roll out effectively and successfully aligned with brand initiatives fulfilling business objectives and goals\u00a0\nIdentify, evaluate, and take actions to improve campaigns' effectiveness, efficiency, and quality of service\nAssist in planning, developing and implementing marketing strategies and campaign to build brand awareness and to fuel our development.\nConducting business trends and market analysis to develop marketing programs and launch campaigns.\nPrepare creative and write-up for content marketing/ online promotion/ digital campaign\nMeasure and evaluate performance of digital marketing strategies with obtainable analytical tools Requirements\n\n\nExperience / Qualification Requirements\n\nDegree holder in Marketing and related discipline\nMinimum of 2 years' solid experience in digital brand marketing\nExcellent bi-lingual creative writing and communication skills in English and Chinese\nExtensive digital ads experience (Google Analytics, Social ads, LinkedIn ads & Amazon Analytics)\nProfound knowledge in Design software and video editing software such as photoshop, AI, Premiere, After effect\nCreative, able to work with conceptual ideas and convert to innovative execution\nConfident, independent, presentable and comfortable in working with multiple stakeholders\nSpeed and able to hit deadlines that you set for yourself\nCandidates with less experience will be considered as Digital Marketing Executive\n\nCompetitive remuneration and benefit package will be offered to the right candidate. Please submit your application by clicking \"Apply Now\" below.", "employment_types": ["Full Time", "Contract"], "selling_points": [], "locations": ["Wan Chai"], "categories": ["Marketing / Public Relations", "Marketing - Direct Marketing", "Digital Marketing", "E-commerce", "Marketing - Brand / Product Management"], "post_time": "2022-01-13T08:37:22Z", "salary": {"currency": null, "max": null, "min": null, "period": "monthly", "term": null}, "salary_visible": false, "title_keywords": ["senior digital marketing executive"], "responsibilities": ["business goals", "budget", "quality", "social media content", "liaise with", "digital marketing strategies", "digital marketing campaigns", "developing", "develop", "logistics", "kpis", "social media", "marketing strategies", "edm", "market analysis", "digital marketing", "online promotion", "evaluate", "social media strategies", "planning"], "requirements": {"degrees": ["degree holder"], "majors": ["marketing"], "languages": ["english", "chinese"], "language_level": ["excellent"], "hard_skills": ["google analytics", "bi", "amazon", "ai", "premiere", "video editing", "after effect", "photoshop"], "soft_skills": ["confident", "communication skills", "independent", "innovative", "presentable", "creative", "extensive"], "languages_combined": [{"language": "english", "language_level": ["excellent"]}, {"language": "chinese", "language_level": ["excellent"]}]}, "experience_required": {"duration": ["minimum of 2 years"], "field": ["digital", "marketing", "digital marketing", "brand"]}}, {"job_id": "100003009046621", "location_code": "hk", "company": "Reasonable Software House Limited", "job_title": "IT Management Trainee", "description": "Triumph is one of the world\u2019s largest intimate apparel companies. It enjoys a presence in over 120 countries with the core brands Triumph\u00ae and sloggi\u00ae. Globally, the company serves 40,000 wholesale customers and sells its products in 4,050\u00a0controlled points of sale as well as via several own online shops. The Triumph Group is a member of the Business Social Compliance Initiative (BSCI).\n\nLearn more about Triumph on:\n\nwww.triumph.com\n\nwww.linkedin.com/company/triumph-international/\n\n\u00a0Our Local Sales\u00a0 Department at Triumph Internaionl Ltd at\u00a0 Kowloon Bay\u00a0 is looking immediately for a highly motivated\u00a0CRM Specialist, Hong Kong and Macau\n\nRoles & Responsibilities:\n\nHandle\u00a0day-to-day operations of Customer Relationship Management (CRM) programs in terms of execution of CRM communications and database maintenance\nAcknowledge customer concerns and evaluate the quality of service via various Customer Experience Management projects\nSupport in CRM data analytic and prepare KPI reports to enhance the effectiveness of CRM activities\nProvide consumer insights based on regular customer segmentation analysis\nSupport CRM system development and enhancement projects\nAssist in developing & executing Customer Relationship Management (CRM)\u00a0strategies\u00a0in line with overall marketing and promotional strategies and budget control\nLiaise with 3rd\u00a0parties / vendor to achieve target of members acquisition\u00a0\u00a0\u00a0\u00a0\n\nYour ideal profile:\n\nAt least 2 years' solid experience in CRM/ Marketing\nAnalytical and critical thinker with sound problem solving skills\nProficient in all Microsoft applications\u00a0\nDetailed minded and with strong sense in data analysis and interpretation\nStrong interpersonal skills, presentable with outgoing personality and be able to work independently\nGood command of both written and spoken English and Cantonese. Mandarin is an asset\nCandidates with less experience can be considered as CRM Officer\u00a0\n\nWe offer an opportunity in a fast paced organization which gives those looking for a challenge the possibility to grow with the company and shape the future.\n\nWe are a family owned company with strong values, operating at a global level with key markets in Germany, Japan and China - where our iconic brands, Sloggi and Triumph, continue to delight our consumers.\n\nTriumph Group is committed to employing a diverse workforce. Qualified applicants will receive consideration without regard to race, color, religion, sex, national origin, age, sexual orientation, gender identity, gender expression, veteran status, or disability.\u00a0\n\nIf you are seeking a great opportunity to develop your career, please send us your application letter and CV in English, diplomas and expected salary range by clicking on Apply.\u00a0", "employment_types": ["Full Time", "Permanent"], "selling_points": ["email marketing, digital marketing, programming", "reseller network", "SEO, SEM"], "locations": ["Sham Shui Po Area"], "categories": ["Information Technology (IT)", "Software Development", "Marketing / Public Relations", "Marketing - Direct Marketing", "Others", "Student / Fresh Graduate / No Experience"], "post_time": "2022-01-13T16:50:01Z", "salary": {"currency": "HKD", "max": 24999, "min": 20000, "period": "monthly", "term": null}, "salary_visible": true, "title_keywords": ["management trainee"], "responsibilities": ["management", "consumer insights", "maintenance", "data", "analysis", "compliance", "day-to-day operations", "quality", "developing", "develop", "evaluate", "data analysis", "reports", "executing", "database", "liaise with", "enhancement projects", "budget control"], "requirements": {"degrees": [], "majors": [], "languages": ["cantonese", "english", "mandarin"], "language_level": ["good command"], "hard_skills": ["microsoft applications", "maintenance", "analysis", "vendor", "problem solving skills"], "soft_skills": ["outgoing personality", "work independently", "detailed", "presentable", "committed", "diverse", "motivated", "interpersonal skills", "controlled", "problem solving skills", "initiative", "ideal"], "languages_combined": [{"language": "cantonese", "language_level": ["good command"]}, {"language": "english", "language_level": ["good command"]}, {"language": "mandarin", "language_level": []}]}, "experience_required": {"duration": ["at least 2 years"], "field": ["management", "marketing"]}}, {"job_id": "100003009045369", "location_code": "hk", "company": "Triumph International Services (APAC) Limited", "job_title": "CRM Specialist, Hong Kong and Macau markets", "description": "Responsibilities:\n\nResponsibilities the online marketing activities and website contents to capture profitable growth;\nFormulate and implement customized annual promotion plan, ensure to meet the business target and maximize the brand image exposure within the budget;\nPlan and develop the loyalty program, marketing campaigns, CRM initiatives to optimize profitability;\nMonitor business results and campaigns effectiveness;\nKeep track the market trend and competitors promotional and marketing programs/ activities;\u00a0 \u00a0 \u00a0 \u00a0\nPerform ad hoc assignments.\n\nRequirements:\n\n\nBachelor Degree in Marketing or related disciplines;\nMinimum 3 years experience in Beauty centre / reatil is an advantage;\nA good team player with strong communication and interpersonal skills;\nAttention in details with analytical and presentation skills;\nEnergetic, proactive, creative with a good sense in beauty;\nGood command in spoken and written English, Cantonese and Mandarin;\nCandidates with less experience will be considered as Marketing Executive;\nImmediately available is highly preferred\u00a0\n\nWorking Location: Lai Chi Kok\n\nWe offer 5-day work and a competitive\u00a0salary and benefits\u00a0package\u00a0for the right candidate. To apply online please click the 'Apply' button below with your resume, current & expected salary, and availability to us.\n\nPersonal data collected will be treated in strict confidence and be used for recruitment purposes only.", "employment_types": ["Full Time", "Permanent"], "selling_points": ["Day to day operations of CRM program", "CRM data analytic", "Prepare KPI report"], "locations": ["Kowloon Bay"], "categories": ["Marketing / Public Relations", "Marketing - Direct Marketing"], "post_time": "2022-01-13T07:45:00Z", "salary": {"currency": null, "max": null, "min": null, "period": "monthly", "term": null}, "salary_visible": false, "title_keywords": ["specialist"], "responsibilities": ["budget", "monitor", "website", "develop", "ad hoc assignments", "plan", "contents", "marketing campaigns"], "requirements": {"degrees": ["degree", "bachelor"], "majors": ["related disciplines", "marketing"], "languages": ["cantonese", "english", "mandarin"], "language_level": ["good command"], "hard_skills": [], "soft_skills": ["good team player", "proactive", "creative", "presentation skills", "communication and interpersonal skills", "energetic"], "languages_combined": [{"language": "cantonese", "language_level": ["good command"]}, {"language": "english", "language_level": ["good command"]}, {"language": "mandarin", "language_level": ["good command"]}]}, "experience_required": {"duration": ["minimum 3 years"], "field": ["marketing", "beauty"]}}, {"job_id": "100003009039478", "location_code": "hk", "company": "\u8a69\u7433\u63a7\u80a1\u96c6\u5718\u6709\u9650\u516c\u53f8", "job_title": "Senior Marketing Executive (5 days work)", "description": "We are looking for a hands-on, self-driven, committed, detail-minded, and result-oriented individual to drive and manage the sales & online marketing activities for Reasonable.\u00a0\n\n\nResponsibilities:\n\nPlan and execute sales activities\uff08B2B) to explore new business opportunities with achievement on sales target\nGive regular daily sales calls, e-promotions, and quotations to potential new clients actively\nResponsible for market database research and exhibition visit for ongoing prospecting\nEnsure efficient sales strategy to maintain long-term relationships with corporate clients\nOther ad hoc duties related to sales & marketing\n\nRequirements:\n\nExperience in the sales field will be an advantage\nInterested in developing careers in Marketing and Marketing Technology.\nWilling to learn, ambitious and outgoing personality\nProficient in both written and spoken English, Chinese, Mandarin is an added advantage\nProficient in MS Word, Excel, Powerpoint\nBe a team player with good presentation, interpersonal, organizing, and communication skills\nFresh Graduates / Higher Diploma / Associate Degree holders will be considered\nImmediate availability is an advantage\n\nBenefits\n\nCompetitive remuneration packages, MPF, Medical & dental coverage\nModern, comfortable, and attractive working environment", "employment_types": ["Full Time"], "selling_points": ["Experience in beauty industry is an advantage", "Dynamic environment", "Immediate available is preferred"], "locations": ["Lai Chi Kok"], "categories": ["Marketing / Public Relations", "Marketing - Direct Marketing", "Marketing - General / Support", "Digital Marketing"], "post_time": "2022-01-11T09:54:30Z", "salary": {"currency": null, "max": null, "min": null, "period": "monthly", "term": null}, "salary_visible": false, "title_keywords": ["senior marketing executive"], "responsibilities": ["ad hoc duties", "explore new business opportunities", "sales target", "maintain", "plan", "database"], "requirements": {"degrees": ["associate degree", "diploma"], "majors": [], "languages": ["english", "chinese", "mandarin"], "language_level": ["advantage", "proficient"], "hard_skills": ["excel", "powerpoint", "ms word"], "soft_skills": ["outgoing personality", "communication skills", "interested in", "willing to learn", "team player", "interpersonal", "presentation"], "languages_combined": [{"language": "english", "language_level": ["advantage", "proficient"]}, {"language": "chinese", "language_level": ["advantage", "proficient"]}, {"language": "mandarin", "language_level": ["advantage", "proficient"]}]}, "experience_required": {"duration": [], "field": []}}, {"job_id": "100003009047995", "location_code": "hk", "company": "KPMG Executive Recruitment Limited", "job_title": "Head of Public Relations", "description": "Key Responsibilities:\n\nFormulate marketing objectives and strategies that fits the strategic direction and tie with category growth ambition and target\nDevelop marketing plans to strengthen brand positioning, consumer preference and drive conversion\nInitiate and implement strong advertising plan and marketing activations for brands and new product launch; consistently review and renovate execution plans to strive better performance\nEvaluate brand campaign and new launches performance constantly; develop KPI measurement tracking system and recommend action plans to accelerate performance to bridge gap\nHave deep understanding of brand and business dynamics and prepare for future insights generation to capture growth opportunities and step ahead competition\nActively explores new brand opportunities through multiple analyses including consumer trend analysis & market observation; translate into actionable insights and recommend to Management\nControl and optimize the approved marketing spending to achieve business and marketing objectives including P&L and market share\nWork closely with Regional team to drive strategic brand platform and initiatives development\nLead cross-functional team cooperation including Sales, Trade Marketing, Digital, Supply Chain, Regulatory, R&D etc. to push through the launches and execution plan\nMotivates and coaches the subordinates to grow up as high performer\nAssists Marketing Director in taking up responsibilities in the assigned divisional projects\nPerform ad-hoc duties as required\n\n\u00a0Key Requirements:\n\nMinimum 10 years\u2019 marketing experience in FMCG with at least 4 years at supervisory level\nWith proven track record to drive campaigns across digital and social platforms to enrich brand experience and engage consumers. Good understanding on digital & social landscape\nWork experience in regional marketing team is a plus\nHighly agile, flexible and open-minded with can-do attitude and eager to strive for excellence\nExcellent communication skill, able to communicate with all levels\nStrong strategic and analytical thinking\nExcellent command of spoken and written English and Chinese\nPC knowledge and application\nWays to apply:\u00a0\nInterested parties please send your detailed resume stating your available date, current & expected salary to Human Resources Manager, by clicking the \u201cAPPLY NOW\u201d button below.\n\nAll information provided by applicants will be treated in strict confidence and used only for recruitment purposes. If you do not provide the information mentioned in the advertisement, we may not be able to assess your job application. You have the right to request access to, and correction of, your personal data held by us and you may lodge such request with our Data Protection Officer at pdpo@ vitasoy.com, but any such data access request will only be processed after the completion of the recruitment process.", "employment_types": ["Full Time"], "selling_points": ["Degree holder with Marketing, Communications etc.", "12+years of exp in corporate communications", "In charge corporate communication&PR matters"], "locations": ["Not Specified"], "categories": ["Marketing / Public Relations", "Marketing - Direct Marketing", "Marketing - Marketing Communication"], "post_time": "2022-01-14T04:33:34Z", "salary": {"currency": null, "max": null, "min": null, "period": "monthly", "term": null}, "salary_visible": false, "title_keywords": [], "responsibilities": ["management", "control", "advertising", "trade marketing", "marketing plans", "analysis", "review", "measurement", "p&l", "develop", "evaluate", "plan", "ad-hoc duties", "plans", "tracking"], "requirements": {"degrees": [], "majors": [], "languages": ["english", "chinese"], "language_level": ["excellent"], "hard_skills": ["pc knowledge", "plus", "agile"], "soft_skills": ["flexible", "agile", "can-do attitude", "open-minded", "communication skill", "strive for excellence"], "languages_combined": [{"language": "english", "language_level": ["excellent"]}, {"language": "chinese", "language_level": ["excellent"]}]}, "experience_required": {"duration": ["at least 4 years", "minimum 10 years"], "field": ["fmcg", "brand", "digital", "marketing", "supervisory level", "team"]}}, {"job_id": "100003009045907", "location_code": "hk", "company": "Reasonable Software House Limited", "job_title": "Sales and Marketing Manager", "description": "Background of Project:\n\nOur project works against the expanding digital and social divides between the resourceful and under-resourced. We believe that all youth regardless of background or upbringing, given the opportunity, can be creative in solving problems and contribute to the future technology economy.\u00a0\n\nIn collaboration with HKU and PolyU, this project brings Computational Thinking and Design Thinking to the under-resourced youth in schools where students are at the risk of being left behind in the STEM race, worsened by the COVID-19 pandemic.\u00a0\n\u00a0\n\nProject Description:\n\nWe are expanding our project by engaging 100+ secondary schools in using our coding platform to enhance the teaching and learning of basic visual programming. Account Service Executive responsibilities include discovering and pursuing new sales prospect, handle customers queries and maintain customer satisfaction. You will help us meet and surpass business expectations and contribute to our organization\u2019s rapid and sustainable growth. For more information, please visit our website\u00a0http://projectc-ygn.org\n\n\u00a0\n\u00a0Key Responsibilities:\n\nConduct market research to identify selling possibilities and evaluate customer needs\nActively seeking out new sales opportunities through cold calling, face to face meeting and networking\nSetting up meetings with potential clients and listening to their wishes and concerns\nPrepare and deliver appropriate presentations on products and services\nHandle complaints or objections\nCreate frequent progress reviews and reports\nCoordinate and participate on behalf of the organization in exhibitions\u00a0 or conferences\nCollaborate with team members to achieve better results\nGather feedback from customers or prospects and share with internal teams\n\n\u00a0Qualifications:\n\nTertiary education\n2-4 years working experience\nBasic computer and coding knowledge essential\nFast learner and passion for networking\nSelf-motivated with a results-driven approach\nAptitude in delivering attractive presentations\n\n\u00a0Application:\u00a0\n\nFor interested parties, please apply with full resume, stating clearly current and expected salary, to Human Resources Department, Youth Global Network Limited, 14th Floor, Breakthrough Centre, 191 Woosung Street, Jordan, Kowloon. or\u00a0email to APPLY\n\n\nAll information provided will be treated with strictest confidence & used for recruitment purposes only. All unsuccessful applications will be kept for a period of no longer than two years after completion of the recruitment exercise.\u00a0", "employment_types": ["Full Time", "Permanent"], "selling_points": ["Email and Digital Marketing, Sales and Marketing", "Corporate Sales, Media Sales, Solution Sales", "Good Presentation Skill, Interpersonal Skill"], "locations": ["Sham Shui Po Area"], "categories": ["Sales, CS & Business Devpt", "Business Development", "Marketing / Public Relations", "Marketing - Direct Marketing", "Digital Marketing"], "post_time": "2022-01-13T09:04:49Z", "salary": {"currency": "HKD", "max": 29999, "min": 20000, "period": "monthly", "term": null}, "salary_visible": true, "title_keywords": ["marketing manager", "sales"], "responsibilities": ["collaborate with", "conduct market research", "teams", "website", "coding", "design", "evaluate", "presentations", "handle complaints", "maintain", "reports", "coordinate", "conferences", "visual"], "requirements": {"degrees": [], "majors": [], "languages": [], "language_level": [], "hard_skills": ["presentations", "basic", "programming", "rapid"], "soft_skills": ["self-motivated", "resourceful", "passion for", "learning", "creative", "fast learner", "driven"], "languages_combined": []}, "experience_required": {"duration": ["2-4 years"], "field": []}}, {"job_id": "100003009045127", "location_code": "hk", "company": "Vitasoy International Holdings Ltd", "job_title": "Marketing Manager", "description": "A leading furniture & decoration retail & online stores is \u201cURGENTLY\u201d seeking for:\n\nSenior / Marketing Manager\n\nResponsibilities:\n\nManage the global marketing budget and reporting for both online and offline\nManage marketing processes, briefs and oversell all brand creative from templates, signage and multi-media to lookbook and catalogue creation and production\nLiaise with KOLs, Customer Service, Design Departments to create editorial and content for the lookbook and social channels\nManage and coordinate photoshoots for corporate sales and design departments\nResponsible for all copywriting and copy approvals inclusive of headlines, taglines, body copy, product text, social captions, edms, blogs, editorials, catalogues, company presentations, press release, etc.\nConsumer analysis segmentation, brand positioning, Marco and Micro Trends, annual marketing imperatives / aims and objectives, key strategies and tactics to achieve and align with business targets, company vision, mission and brand promise\nResponsible for Internal Marketing and CSR\nExecute and manage HK Marketing for B2B and B2C\nManage and oversee salesforce loyalty program and implementation across all regions\nManage and oversee ecomm sites and customers journeys for both B2B and B2C\n\nRequirements:\n\nDegree in Marketing, Public Relations or related disciplines\nMinimum 8 years in a Marketing / Brand managerial role\nHas in-depth market knowledge of HK market, ideally furniture & accessories (or home furnishings), ability to drive exponential increase of brand followers\nGravitas & excellent communicator\nB2B and B2C retail marketing experience\nExcellent copywriting and communication skills in English, Cantonese & Mandarin\nContent creation and creative brand experience\nAnalytical, data driven, strategic thinker\nAbility to multi task across a variety of businesses and regions with an international mindset\nKnowledge of salesforce, magento, netsuite, a bonus\n\n*Interested parties, please send full resume with current & expected salary & date available in MS WORD FORMAT ONLY to email: \u00a0jobs@HKETERNITY. com \u00a0\u00a0\u00a0or fax to 3527 0634\n\nHotline: (852) 3542 5082\n\nFor more jobs, please visit our website: www.hketernity.com\n\nWe are welcome applicants resend resumes to us even you have applied jobs in our company before.\n\n(Personal data submitted are for recruitment purpose only.)", "employment_types": ["Full Time"], "selling_points": ["Formulate marketing objectives and strategies", "Initiate and implement strong advertising plan", "Minimum 10 years\u2019 marketing experience in FMCG"], "locations": ["Tuen Mun Area"], "categories": ["Marketing / Public Relations", "Management", "Marketing - Brand / Product Management", "Marketing - Direct Marketing"], "post_time": "2022-01-13T07:15:03Z", "salary": {"currency": null, "max": null, "min": null, "period": "monthly", "term": null}, "salary_visible": false, "title_keywords": ["marketing manager"], "responsibilities": ["reporting", "edms", "analysis", "budget", "implementation", "design", "presentations", "coordinate", "customer service", "liaise with", "catalogue"], "requirements": {"degrees": ["degree"], "majors": ["related disciplines", "marketing"], "languages": ["cantonese", "english", "mandarin"], "language_level": ["excellent"], "hard_skills": ["salesforce"], "soft_skills": ["communication skills", "communicator", "creative", "driven"], "languages_combined": [{"language": "cantonese", "language_level": ["excellent"]}, {"language": "english", "language_level": ["excellent"]}, {"language": "mandarin", "language_level": ["excellent"]}]}, "experience_required": {"duration": [], "field": ["retail", "brand", "content creation", "marketing"]}}, {"job_id": "100003009042127", "location_code": "hk", "company": "Youth Global Network Limited", "job_title": "Business Development Executive (1 year contract)", "description": "An exciting opportunity has arisen for an experienced, enthusiastic and passionate Assistant Trade Marketing Manager to join our nutritional team. Core job responsibilities include the followings:\nDesign promotional materials and maintains contacts with the Key Accounts and Distribution Channels, in order to supervise all promotional activities\nDevelop and drive sales execution to improve the in-store performance of all programs to increase product presence\nDevelop tools to monitor trade marketing investments and initiatives execution and evaluate spending effectiveness\nSupport manager to develop and deliver of new product launch plans for trade\nCoordinate and communicate product, price and pack changes between Sales & Marketing\nImplement, monitor and improve processes to link all trade marketing activities\nWork with superior to supervise Promoters and Merchandisers team\nEvaluate market/channel performance by using market track data, customer scan information and internal shipment sales.\nRequirements\nUniversity graduate with a minimum of 6 years\u2019 experience in trade marketing, preferable in FMCG sector\nStrong project management, presentation & interpersonal skills\nStrong analytic in business data management and drive value-adding insights\nBudget management experience is required\nProactive and able to work under stress\nAble to promote cross functional effectiveness\nDecision making oriented & able to quickly react to changing environment.\nFluent in Cantonese, English and Mandarin\nInterested parties, please send your profile with present and expected salary by clicking \"Apply Now\"\n\nPersonal data collected will be used for recruitment purposes only.", "employment_types": ["Full Time", "Contract"], "selling_points": ["Account Service Executive", "Actively seeking out new sales opportunities", "Cold calling, face to face meeting and networking"], "locations": ["Tsim Sha Tsui"], "categories": ["Education", "Others", "Marketing / Public Relations", "Marketing - Direct Marketing", "Sales, CS & Business Devpt", "Account Servicing"], "post_time": "2022-01-12T06:19:12Z", "salary": {"currency": null, "max": null, "min": null, "period": "monthly", "term": null}, "salary_visible": false, "title_keywords": ["business development executive"], "responsibilities": ["trade marketing", "shipment sales", "data", "monitor", "design", "develop", "evaluate", "coordinate", "promotional materials", "promotional activities", "plans", "drive sales"], "requirements": {"degrees": ["university graduate"], "majors": ["marketing"], "languages": ["cantonese", "english", "mandarin"], "language_level": ["fluent"], "hard_skills": ["project management", "budget management", "data management", "react"], "soft_skills": ["project management", "interpersonal skills", "proactive", "presentation", "decision making"], "languages_combined": [{"language": "cantonese", "language_level": ["fluent"]}, {"language": "english", "language_level": ["fluent"]}, {"language": "mandarin", "language_level": ["fluent"]}]}, "experience_required": {"duration": ["minimum of 6 years"], "field": ["management", "marketing", "fmcg"]}}, {"job_id": "100003009046406", "location_code": "hk", "company": "Eternity Consultants (HK) Ltd", "job_title": "Senior / Marketing Manager", "description": "This is an exciting opportunity for an outstanding candidate who is passionate and responsible to develop and implement CRM solutions to engage, retain, upsell & recruit customers, and leverage insight and data.\n\n\n\n\nVIP & CRM Program management\u00a0\n\n\nPlan and deliver CRM strategies across the brand for both online and offline encouraging customer retention, improving customer loyalty and promoting the brand;\nDesign loyalty program, customer journey automation & CRM activities to engage customers, build sustainable growth on membership lifetime value;\nTurn data of customer analytic & customer journey mapping into actionable customer insights maximize commercial opportunities;\nWork closely with sales and planning \u00a0departments to ensure the CRM works effectively and ensure smooth execution of in-store promotion;\nEnsuring CRM communications and database segmentation effectiveness for targeted marketing activities in respect to local & overseas customers\u2019 purchase behaviours;\nManage and monitor data acquisition strategy.\n\nStrategic partnership\n\nDevelop and execute\u00a0partnership acquisition\u00a0strategies with\u00a0potential partners in bank, retail, hotel, and other sectors;\nTo strengthen the loyalty program's variety, maximize the program's popularity, and assist the Sales team to achieve revenue target of the overall business;\nManage program's\u00a0communications content\u00a0including\u00a0social media, website, eDM & SMS;\nManaging overall\u00a0inventory level\u00a0to ensure the effective operation of the loyalty program;\nConduct regular reports for internal review.\n\nShopping Mall Promotion\n\nWork with shopping malls to support business needs with various collaboration;\nLiaise with internal parties and landlords for organizing marketing and promotion events at the shopping mall to enhance quality traffic and business revenue.\n\nRequirements and Qualifications\n\nBachelor\u2019s degree required, preferably in Marketing, Communication, Public Relations,\u00a0 Business Statistics, Information System Management or related discipline;\nProven track record of managing CRM data systems, implementing CRM program and campaign management;\n4+ years relevant work experience in a fashion/beauty retail environment;\nGood knowledge in data-driven and CRM-focused mindset is a must;\nHighly organized and detail-minded. \u00a0Comfortable working under tight deadlines and managing multiple projects simultaneously;\nObsessed with customers and experience with campaign measurements (effectiveness/ efficiency);\nStrong analytical mind with good report writing skills, and able to transform data into actionable insight;\nExcellent written and verbal English and Chinese communication skills is a must;\nCandidate with less experience will be considered as \"Marketing Executive\".\nWe offer excellent career prospects, competitive salary and fringe benefits to the right candidate.\u00a0 Please apply in strict confidence by sending personal resume together with salary expected and date available\n\nby email to:\u00a0h r d _ h n @ h a r v e y n i c h o l s . c o m . h k\nWe are an equal opportunity employer and welcome applications from all qualified candidates. Personal data provided by job applicants will be used strictly in accordance with our personal data policy and for recruitment purposes only. Candidates not notified within eight weeks may consider their application unsuccessful. All related information will be kept in our file for up to 24 months. A copy of our Personal Information Collection Statement will be provided upon request by contacting our Human Resources Division.", "employment_types": ["Full Time", "Permanent"], "selling_points": ["Marketing process, brief & oversell brand creative", "Consumer analysis segmentation, brand positioning", "Manage & oversee ecomm sites & customers journeys"], "locations": ["Not Specified"], "categories": ["Marketing / Public Relations", "Marketing - Brand / Product Management", "Marketing - Direct Marketing", "Digital Marketing"], "post_time": "2022-01-13T10:52:03Z", "salary": {"currency": null, "max": null, "min": null, "period": "monthly", "term": null}, "salary_visible": false, "title_keywords": ["marketing manager"], "responsibilities": ["data", "inventory", "quality", "website", "design", "communication", "purchase", "plan", "database", "liaise with", "assist the sales", "customer insights", "monitor", "develop", "reports", "support business needs", "report", "social media", "management", "edm", "review", "campaign management", "systems", "multiple projects", "internal parties", "planning"], "requirements": {"degrees": ["degree", "bachelor"], "majors": ["business", "marketing", "statistics"], "languages": ["english", "chinese"], "language_level": ["excellent"], "hard_skills": ["information system", "writing skills"], "soft_skills": ["passionate", "organized", "detail-minded", "communication skills", "responsible", "focused", "writing skills", "communication", "analytical mind", "smooth", "driven"], "languages_combined": [{"language": "english", "language_level": ["excellent"]}, {"language": "chinese", "language_level": ["excellent"]}]}, "experience_required": {"duration": ["4+ years"], "field": ["retail", "beauty", "marketing"]}}, {"job_id": "100003009050348", "location_code": "hk", "company": "Abbott Laboratories Ltd.", "job_title": "Assistant Trade Marketing Manager", "description": "Responsibilities:\n\nDevelop and manage execution all-rounded marketing and promotion campaign covering (both online and offline promotions, e-marketing, social media campaign and joint promotions with third parties)\n\nAnalyze customer insights, consumer trends, market analysis, and marketing best practices to build successful strategies\nDrive and implement strategic PR campaigns for brand positioning and enhancing brand image and awareness\nAlign with the company strategy and objectives, initiate and implement relevant online and social media platforms\nDevelop content strategy and social media plan to maximize the brand exposure\nTo initiate and implement CRM strategy and programs\n\nRequirements:\n\nDegree holder in Business, Marketing, eCommerce or a related field\nMinimum 5 years' experience in Marketing with retail exposure\nExcellent marketing planning and writing skills\nGood network with the media, press and KOL is preferred\nSense of urgency and good project management skills\nA good team player, proactive, creative, independent, detail-minded\nExcellent interpersonal and communication skills with very positive attitude\n\nInterested parties, please apply with full resume, stating date available, present and expected salary to\u00a0Human Resources & Administration Department by clicking 'Apply Now'.\n\nPersonal Data provided in the employment applications will be treated as strictly confidential and used only for recruitment purpose.\u00a0 All unsuccessful applications will be destroyed upon completion of the selection process.", "employment_types": ["Full Time", "Permanent"], "selling_points": [], "locations": ["Eastern Area"], "categories": ["Marketing / Public Relations", "Marketing - Direct Marketing", "Marketing - General / Support", "Sales, CS & Business Devpt", "Channel / Distribution"], "post_time": "2022-01-15T03:51:01Z", "salary": {"currency": null, "max": null, "min": null, "period": "monthly", "term": null}, "salary_visible": false, "title_keywords": ["marketing manager", "assistant"], "responsibilities": ["consumer trends", "social media", "social media platforms", "customer insights", "develop", "market analysis", "plan"], "requirements": {"degrees": ["degree holder"], "majors": ["ecommerce", "business", "marketing"], "languages": [], "language_level": [], "hard_skills": ["project management", "writing skills"], "soft_skills": ["detail-minded", "communication skills", "good team player", "independent", "creative", "urgency", "project management skills", "writing skills", "positive attitude", "proactive", "interpersonal"], "languages_combined": []}, "experience_required": {"duration": ["minimum 5 years"], "field": ["marketing", "retail"]}}, {"job_id": "100003009051022", "location_code": "hk", "company": "Harvey Nichols (Hong Kong) Limited", "job_title": "Senior Marketing Executive", "description": "Requirements:\n\nUniversity Degree\nFresh graduates without experience at work are also welcome\nProficiency in both spoken and written English and Chinese is essential, or at least be excellent in English\nGood communication and presentation skills with strong analytical mind\nWith positive, aggressive, self-motivated, out-going and sociable personality\n\nAreas of Responsibility\u00a0 \u00a0\u00a0\n\nTo assist the Management to develop and implement marketing programs and events in line with the corporate business goal\nTo liaise with customers and internal department for smooth running of our operation\nTo assist in business development for local and overseas markets\nTo prepare distribution agreements, marketing-related documents, presentation materials, update products literatures/flyers etc.\nHandle various other ad hoc duties as required\n\nWe offer commensurable salary to successful candidates or to be negotiated.\n\nInterested parties please send applications with detailed information and EXPECTED\u00a0SALARY\u00a0by email to Mr. Ho.", "employment_types": ["Full Time", "Permanent"], "selling_points": ["Plan+deliver CRM strategies&design loyalty program", "Develop+execute partnership acquisition strategies", "4+ yrs relevant exp.in fashion/beaty retail"], "locations": ["Tsim Sha Tsui"], "categories": ["Marketing / Public Relations", "Marketing - Brand / Product Management", "Marketing - Direct Marketing", "Marketing - Marketing Communication"], "post_time": "2022-01-15T01:13:14Z", "salary": {"currency": null, "max": null, "min": null, "period": "monthly", "term": null}, "salary_visible": false, "title_keywords": ["senior marketing executive"], "responsibilities": ["ad hoc duties", "management", "related documents", "develop", "liaise with"], "requirements": {"degrees": ["university degree"], "majors": [], "languages": ["english", "chinese"], "language_level": ["proficiency", "excellent"], "hard_skills": [], "soft_skills": ["self-motivated", "sociable", "communication", "presentation skills", "analytical mind", "positive"], "languages_combined": [{"language": "english", "language_level": ["proficiency", "excellent"]}, {"language": "chinese", "language_level": ["proficiency", "excellent"]}]}, "experience_required": {"duration": [], "field": []}}, {"job_id": "100003009042352", "location_code": "hk", "company": "Crocodile Garments Limited", "job_title": "Assistant Marketing Manager", "description": "Responsibilities\n\nPlanning, developing and managing the overall digital marketing strategy, working plan and implementation, to support the overall marketing strategy\nStay up to date with the latest digital marketing trend and best practices, conducting regular marketing research and competitor study and providing suggestions for improvement\nPlan and execute digital marketing campaign and advertisement for brand, product and business promotion\nOversee all the TPLHK's social media accounts (Facebook, Wechat, Linkedin, etc.)\nManage the creative and copywriting for online marketing materials and contents, including social media newsfeed, banners, images, videos and eDM\nWork closely with IT and other department for corporate website content management\n\nRequirements\n\nDegree holder in Marketing, Business Administration, e-Commerce, Design, Communications or related disciplines\n5-8 years' of digital marketing experience, experience with digital agency will be a plus\nCreative and strategic thinker; has the ability to think out-of-the-box and leads with solutions\nIn depth knowledge of digital marketing channels, with hands-on experience with SEO, Google Analytics, Google Ads, Facebook Ads Manager and CRM software\nGood command of written and spoken English, Chinese & Mandarin\nCandidate with less experience will be considered as Senior Officer\n\nApplication\n\nInterested parties please send a detailed resume, stating current and expected salary to Human Resources Department.\n\nInformation supplied will be treated in strict confidence and used in accordance with the Personal Data (Privacy) Ordinance. Applicants not invited for interview within 6 weeks may consider their applications unsuccessful.", "employment_types": ["Full Time", "Permanent"], "selling_points": ["All-rounded marketing", "PR campaigns / CRM", "Marketing planning"], "locations": ["Kwun Tong"], "categories": ["Marketing / Public Relations", "Marketing - Direct Marketing", "Others", "Digital Marketing"], "post_time": "2022-01-12T07:09:11Z", "salary": {"currency": null, "max": null, "min": null, "period": "monthly", "term": null}, "salary_visible": false, "title_keywords": ["assistant marketing manager"], "responsibilities": ["social media", "management", "edm", "implementation", "developing", "website", "banners", "marketing research", "digital marketing", "plan", "contents", "marketing materials", "facebook", "planning"], "requirements": {"degrees": ["degree holder"], "majors": ["business administration", "e-commerce", "design", "related disciplines", "marketing", "communications"], "languages": ["english", "chinese", "mandarin"], "language_level": ["good command"], "hard_skills": ["google analytics", "plus", "seo", "e-commerce", "facebook"], "soft_skills": ["hands-on", "creative"], "languages_combined": [{"language": "english", "language_level": ["good command"]}, {"language": "chinese", "language_level": ["good command"]}, {"language": "mandarin", "language_level": ["good command"]}]}, "experience_required": {"duration": ["5-8 years"], "field": ["agency", "digital", "digital marketing"]}}, {"job_id": "100003009050487", "location_code": "hk", "company": "BioZone Scientific International Limited", "job_title": "Marketing Executive", "description": "Our client, a Global FMCG Firm, is looking for an Assistant Trade Marketing Manager to head up the Trade Marketing Initiatives for a Consumer Health Brand.\n\nThis is a Number Healthcare Brand, this company provides a stable environment with great prospect.\n\nResponsibilities:\n\nTo develop trade marketing activities for key chains, and general trade.\nTo analyze sales data and indicate potential opportunities and develop trade marketing strategy\nTo develop promotion plan & programs, specifically for targeted customers\nTo provide space management presentation, and solution for gain volume and share objectives\nRequirements:\n\nUniversity graduate. \u00a0Preference is given to business administration or statistics.\nAt least 4 years of trade marketing / category management / key account / sales experience in FMCG\nStrong experience in data analysis, planogram, MS Office and communication skills\nExcellent English and Chinese\nKey Account background and wishes to change job is welcome to apply.\n480K \u2013 550K per annual", "employment_types": ["Full Time"], "selling_points": [], "locations": ["Cheung Sha Wan"], "categories": ["Marketing / Public Relations", "Marketing - Direct Marketing", "Marketing - General / Support", "Digital Marketing"], "post_time": "2022-01-14T10:30:23Z", "salary": {"currency": null, "max": null, "min": null, "period": "monthly", "term": null}, "salary_visible": false, "title_keywords": ["marketing executive"], "responsibilities": ["trade marketing", "management", "data", "develop", "plan"], "requirements": {"degrees": ["university graduate"], "majors": [], "languages": ["english", "chinese"], "language_level": ["excellent"], "hard_skills": ["analysis", "ms office"], "soft_skills": ["communication skills"], "languages_combined": [{"language": "english", "language_level": ["excellent"]}, {"language": "chinese", "language_level": ["excellent"]}]}, "experience_required": {"duration": ["at least 4 years"], "field": ["data analysis", "management", "marketing", "fmcg"]}}, {"job_id": "100003009046313", "location_code": "hk", "company": "China Taiping Life Insurance (Hong Kong) Company Limited", "job_title": "Assistant Manager / Manager, Digital Marketing", "description": "\u6e96\u5099\u597d\u8fce\u63a5\u4e0d\u4e00\u6a23\u7684\u5e73\u51e1\uff1f\n\u60f3\u64fa\u812b\u671d\u4e5d\u665a\u516d\u6c89\u60b6\u5de5\u4f5c\uff0c\u7531\u88ab\u5de5\u4f5c\u91cd\u91cd\u675f\u7e1b\uff0c\u5230\u53ef\u4ee5\u81ea\u4e3b\u751f\u6d3b\uff1f\n\u52a0\u5165\u6211\u5011\uff0c\u8b93\u6211\u5011\u4e26\u80a9\u524d\u884c\u3002\n\n**\u5c08\u696d\u767c\u5c55\n\n\n\u57f9\u990a\u5ba2\u4eba\u7406\u8ca1\u89c0\u5ff5\n\n\u63d0\u4f9b\u7406\u8ca1\u5831\u544a\u7d66\u5ba2\u6236\uff0c\u5305\u62ec\u98a8\u96aa\u7ba1\u7406\u548c\u8ca1\u5bcc\u7ba1\u7406\u00a0\n\u5b9a\u671f\u70ba\u5ba2\u4eba\u8ddf\u9032\u4fdd\u55ae\u670d\u52d9\uff0c\u5305\u62ec\u7d22\u511f\u3001\u5b9a\u671f\u6aa2\u8a0e\u00a0\n\n\u70ba\u5ba2\u4eba\u6574\u5408MPF\n\n\u63d0\u4f9b\u4e00\u822c\u4fdd\u96aa\u7522\u54c1\u670d\u52d9\n\n\u4e86\u89e3\u793e\u6703\u7d93\u6fdf\u65b0\u805e\n\u8003\u53d6\u5c08\u696d\u8cc7\u683c\uff0c\u5982\u8a8d\u53ef\u8ca1\u52d9\u7b56\u5283\u5e2b\u00a0(CFP)\n\n**\u8c50\u539a\u56de\u5831\n\n\u9999\u6e2f\u4eba\u5718\u968a\n\n24\u500b\u6708\u8ca1\u52d9\u652f\u63f4 (\u6bcf\u6708\u6d25\u8cbc\u905415,000\u81f340,000)+\u00a0\u7121\u4e0a\u9650\u4f63\u91d1\n\u6bcf\u5e749\u6b21\u82b1\u7d05\n\n\u5168\u65b9\u4f4d\u5728\u8077\u5c08\u696d\u57f9\u8a13\n\u5f48\u6027\u5de5\u4f5c\u6642\u9593\uff0c\u81ea\u4e3b\u500b\u4eba\u751f\u610f\uff0c\u9054\u81f3\u5de5\u4f5c\u8207\u751f\u6d3b\u5e73\u8861\n\u5718\u9ad4\u91ab\u7642\u4fdd\u969c\u00a0& \u9000\u4f11\u91d1\n\u696d\u7e3e\u734e\u8cde\u53ef\u514d\u8cbb\u53c3\u52a0\u6d77\u5916\u65c5\u904a\u53ca\u6703\u8b70\n\u5efa\u7acb\u53ca\u7ba1\u7406\u5c08\u696d\u71df\u696d\u5718\u968a\n\n\u00a0**\u62db\u52df\u5c0d\u8c61\n\n\nHKID holder \u5fc5\u9808\u6301\u6709\u9999\u6e2f\u8eab\u5206\u8b49\n\u61c9\u5c46\u5927\u5c08\u7562\u696d\u751f/ \u526f\u5b78\u58eb\u7562\u696d\u751f/ \u9ad8\u7d1a\u6587\u6191\u7562\u696d\u751f\n\u878d\u5165\u5718\u968a,\u00a0\u771f\u8aa0\u5b78\u7fd2,\u00a0\u5de5\u4f5c\u52e4\u529b,\u00a0\u5fc3\u614b\u6b63\u9762\n\u826f\u597d\u6e9d\u901a\u6280\u5de7\n\n\u6709\u8208\u8da3\u7533\u8acb\u8005\u8acb\u6309Apply Now \u7533\u8acb\u3002\n[\u6240\u6536\u96c6\u7684\u500b\u4eba\u8cc7\u6599\u53ea\u4f5c\u62db\u8058\u7528\u9014]", "employment_types": ["Full Time"], "selling_points": ["Support the operations of social media", "5-8 years' relevant working experience", "Attractive remuneration package"], "locations": ["North Point"], "categories": ["Insurance", "Others", "Marketing / Public Relations", "Marketing - Direct Marketing", "Digital Marketing"], "post_time": "2022-01-13T10:25:05Z", "salary": {"currency": null, "max": null, "min": null, "period": "monthly", "term": null}, "salary_visible": false, "title_keywords": ["assistant manager", "manager", "digital marketing"], "responsibilities": [], "requirements": {"degrees": [], "majors": [], "languages": [], "language_level": [], "hard_skills": [], "soft_skills": [], "languages_combined": []}, "experience_required": {"duration": [], "field": []}}, {"job_id": "100003009051069", "location_code": "hk", "company": "Talent Blue Search Limited", "job_title": "Assistant Trade Marketing Manager \u2013 US Healthcare Brand", "description": "RESEARCH OFFICE\nHong Kong Baptist University has been awarded funding under Job Creation Scheme 2.0 supported by the Government to create employment opportunities amidst the deteriorating economy due to the pandemic.\nThe Research Office now invites applications for the following position:\nExecutive Officer (PR0472/21-22)\nSupport research development in the six transdisciplinary laboratories\nAdminister Lab's projects and grants applications;\nCoordinate Lab's engagement activities;\nSupport Lab's development and coordinate internal and external collaborations; and\nSupport research website enhancement.\nApplicants should possess a recognised relevant bachelor's degree with relevant work experience. They should have good interpersonal, communication and organisational skills and a good command of written and spoken English and Chinese (including Putonghua).\nThe Office may appoint candidates to positions different from what they have applied for to suit its operational needs.\nThe appointment will be offered on a fixed-term contract of one year.\nApplication Procedure:\nApplicants are invited to submit their applications at the HKBU e-Recruitment System (jobs.hkbu.edu.hk). Those not invited for interview 8 weeks after submission of application may consider their applications unsuccessful. Details of the University's Personal Information Collection Statement can be found at http://hro.hkbu.edu.hk/pics.\nThe University reserves the right not to make an appointment for the post advertised, and the appointment will be made according to the terms and conditions applicable at the time of offer.\nReview of applications is ongoing until the position is filled.", "employment_types": ["Full Time", "Permanent"], "selling_points": ["Assist Trade Marketing Manager US Healthcare Brand", "Lead a Brand Category Management Store Visibility", "No. 1 Leader 480K \u2013 550K per annual"], "locations": ["North Point"], "categories": ["Marketing / Public Relations", "Marketing - Brand / Product Management", "Marketing - Direct Marketing", "Sales, CS & Business Devpt", "Channel / Distribution"], "post_time": "2022-01-15T01:43:32Z", "salary": {"currency": "HKD", "max": 44999, "min": 30000, "period": "monthly", "term": null}, "salary_visible": true, "title_keywords": ["marketing manager", "assistant"], "responsibilities": ["review", "website", "coordinate", "communication", "recruitment"], "requirements": {"degrees": ["degree", "bachelor"], "majors": [], "languages": ["putonghua", "english", "chinese"], "language_level": ["good command", "good"], "hard_skills": ["make", "scheme"], "soft_skills": ["communication", "organisational skills", "interpersonal"], "languages_combined": [{"language": "putonghua", "language_level": ["good command", "good"]}, {"language": "english", "language_level": ["good command", "good"]}, {"language": "chinese", "language_level": ["good command", "good"]}]}, "experience_required": {"duration": [], "field": []}}, {"job_id": "100003009054428", "location_code": "hk", "company": "AXA China Region Insurance Company Limited", "job_title": "AXA Prime Program Trainee \u7ba1\u7406\u57f9\u8a13\u751f", "description": "Responsibilities:\n\n\n\nAssist Licensing Manager in managing existing licensees and expand current licensing portfolio.\nPrepare documents and regular reports for the licensing process, and consolidate license agreements.\nWork closely with licensees to ensure their business and marketing strategies are aligned with company and brand policies.\nWork with marketing team to maximize product exposure, increase brand awareness and bolster company positioning.\nRequirements:\n\nDegree holder in Business Administration, Marketing or related discipline.\nMin. 3 years working experience in licensing business, preferably in character licensing.\nSound understanding of proper licensing strategies formulation.\nProactive, well-organized, and attentive to details.\nExcellent command in English and Chinese.\nProficiency in Microsoft Office Applications.\n\nWe offer 5-day work, attractive remuneration package and a challenging environment for professionals with immediate availability. Interested parties please send email with current and expected salary for application.\n\n\n\nFor more information about our company, please visit our facebook :\u00a0https://www.facebook.com/tclubfanshk/\n\n", "employment_types": ["Full Time"], "selling_points": ["\u9ad8\u5f48\u6027\u5de5\u4f5c\u6642\u9593\uff0c\u8457\u91cd\u5de5\u4f5c\u8207\u751f\u6d3b\u5e73\u8861", "\u5168\u65b9\u4f4d\u5728\u8077\u5c08\u696d\u57f9\u8a13", "\u6b61\u8fce\u61c9\u5c46\u5927\u5b78\u7562\u696d\u751f\u52a0\u76df"], "locations": ["Kwun Tong"], "categories": ["Marketing / Public Relations", "Marketing - Direct Marketing", "Others", "Student / Fresh Graduate / No Experience", "Sales, CS & Business Devpt", "Sales Administration"], "post_time": "2022-01-17T09:33:06Z", "salary": {"currency": null, "max": null, "min": null, "period": "monthly", "term": null}, "salary_visible": false, "title_keywords": ["trainee"], "responsibilities": ["policies", "marketing strategies", "reports", "prepare documents"], "requirements": {"degrees": ["degree holder"], "majors": ["marketing", "business administration"], "languages": ["english", "chinese"], "language_level": ["excellent"], "hard_skills": ["microsoft office"], "soft_skills": ["proactive", "well-organized", "attentive to details"], "languages_combined": [{"language": "english", "language_level": ["excellent"]}, {"language": "chinese", "language_level": ["excellent"]}]}, "experience_required": {"duration": ["3 years"], "field": ["business"]}}, {"job_id": "100003009049561", "location_code": "hk", "company": "Chow Sang Sang Holdings International Limited", "job_title": "Executive - CRM", "description": "Our client is a private investment group with a large portfolio of retail outlets and other real estate assets.\n\nKPMG is a global network of professional services firms providing Audit, Tax and Advisory services. KPMG Executive Search and Recruitment,\u00a0is a business unit of KPMG China and is one of the few recruitment consultancy firms in Hong Kong that is part of a large professional organisation.\u00a0 We work alongside a group of professionals and advisors who provide us with a high level of insights and awareness about a wide range of businesses and professions. We support the clients and aim to provide a pleasant working experience for the clients and candidates.\u00a0\n\nResponsibilities\n\nResponsible for all corporate communication and public relations matters including employer branding, etc.\nFormulate the corporate communication strategies and plans to help achieve the company\u2019s objectives an enhance its brand propositions\nStrategically manage media enquires and concerns, and provide crisis management advice when necessary\nLead the preparation of corporate communication materials, ensure the accurate presentation of information and maintenance of corporate image\nMaintain professional relationship with business partners, media and key stakeholders to upgrade the brand and create market awareness\nEnsure the overall marketing content, guidelines and commercial messaging are fully integrated into business\nDevelop and maintain strategic partnerships with media and key stakeholders\n\nRequirements\n\nA bachelor\u2019s degree in Marketing, Communications or Business related disciplines\nAt least 12 years of experience in corporate communications / employer branding / digital marketing\nProven experience in employer branding to create market awareness\nStrong leadership, communication and stakeholder management skills\nSolid understanding of the business world, with keen business sense\nExcellent command of written and spoken English and Cantonese\n\nTo apply, please send your CV with expected salary to Ms. Michelle Li by clicking below \"APPLY NOW\" button or 8th Floor, Prince\u2019s Building, 10 Chater Road, Central, Hong Kong. By submitting your application, you agree to receive communications from us and agree our Personal Information Collection Statement in the following link: www.kpmg.com.cn/KER-opportunities\n\n@2022 KPMG Executive Recruitment Limited, a Hong Kong limited liability company and a member firm of the KPMG network of independent member firms affiliated\u00a0", "employment_types": ["Full Time", "Permanent"], "selling_points": ["Implement CRM initiatives to achieve goals", "Develop CRM policies and execution guidelines", "Min 3 yrs exp,preferably in luxury retail industry"], "locations": ["Cheung Sha Wan"], "categories": ["Sales, CS & Business Devpt", "Customer Service - Supervisor / Officer", "Marketing / Public Relations", "Marketing - Brand / Product Management", "Marketing - Direct Marketing"], "post_time": "2022-01-14T08:57:18Z", "salary": {"currency": null, "max": null, "min": null, "period": "monthly", "term": null}, "salary_visible": false, "title_keywords": ["executive"], "responsibilities": ["maintenance", "guidelines", "develop", "communication", "maintain", "plans", "crisis management"], "requirements": {"degrees": ["degree", "bachelor"], "majors": ["business", "related disciplines", "marketing", "communications"], "languages": ["cantonese", "english"], "language_level": ["excellent"], "hard_skills": [], "soft_skills": ["independent", "business sense", "keen", "communication", "leadership"], "languages_combined": [{"language": "cantonese", "language_level": ["excellent"]}, {"language": "english", "language_level": ["excellent"]}]}, "experience_required": {"duration": ["at least 12 years"], "field": ["digital marketing"]}}, {"job_id": "100003009041243", "location_code": "hk", "company": "Deep Sea Network Technology Limited", "job_title": "Marketing Officer", "description": "Job Responsibilities\n\nResponsible for optimizing overseas advertising channels such as Google, Facebook, Twitter\nProvide & execute budget plan and advertising plan\nAnalyze the marketing strategies of competitors and propose responsive plan\nControl the marketing cost effectiveness by considering operation need\nResult-oriented, prepare weekly analysis and reports\n\nJob Requirements\n\nBachelor degree or above, preferably in advertising, marketing, business or related disciplines\nMinimum 3 years marketing experience, experience in Financial industry is an advantage\nHands on experience in media buying, excellent in data analysis, well use of marketing analytics\u00a0tools\uff08Google Analytics, Similarweb\uff09\nBasic knowledge of online marketing is a must\nWell versed in communication with media\nExcellent communication & coordination skills, can work under pressure and results-oriented\n\nWhat we offer\u00a0:\n\n\u2022 Competitive package & Performance Bonus\n\u2022 Medical insurance including dental insurance\n\u2022 13+ days Annual Leave\n\u2022\u00a0Good working environment &\u00a0Free drinks and snack\u00a0\u00a0\n\u2022\u00a0Company events\u00a0\uff08Group party, Christmas Party etc.\uff09", "employment_types": ["Full Time", "Permanent"], "selling_points": ["3 years of experience in promotion", "Knowledge of various online promotion", "Great Career Growth"], "locations": ["Tsim Sha Tsui"], "categories": ["Marketing / Public Relations", "Marketing - Brand / Product Management", "Marketing - Direct Marketing", "Digital Marketing"], "post_time": "2022-01-12T03:47:00Z", "salary": {"currency": null, "max": null, "min": null, "period": "monthly", "term": null}, "salary_visible": false, "title_keywords": ["marketing officer"], "responsibilities": ["control", "cost", "advertising", "marketing strategies", "analysis", "budget", "reports", "plan", "facebook"], "requirements": {"degrees": ["degree or above", "bachelor"], "majors": ["business", "related disciplines", "marketing"], "languages": [], "language_level": [], "hard_skills": ["analysis", "basic"], "soft_skills": ["communication", "hands on", "coordination skills", "work under pressure"], "languages_combined": []}, "experience_required": {"duration": ["minimum 3 years"], "field": ["data analysis", "marketing", "financial industry", "media buying"]}}, {"job_id": "100003009046625", "location_code": "hk", "company": "SPC Executive & Professional Recruitment", "job_title": "Assistant Product Manager & Senior Marketing Executive (Health & Beauty Industry)", "description": "Assistant Product Manager & Senior Marketing Executive\n\n\n\nASSISTANT PRODUCT MANAGER\u00a0\u00a0\u00a0\n\nRequirements:\n\nMinimum 5 years working experience of\u00a0product marketing in Health & Beauty industry (Health & Beauty Supplement)\nPlan, implement ATL, BTL and online promotion\u00a0\nImplement new product launch, product development, budget control and joint promotions\u00a0\u00a0\nFormulate marketing strategies and brand building campaigns\nManage digital marketing platforms and social media channels\nKey account management\nCopy writing and content management\nCandidate with more experience will be considered as a Product Manager\u00a0\n\n\nSENIOR MARKETING EXECUTIVE\u00a0\u00a0\n\nRequirements:\n\nMinimum 3 years working experiences of product marketing in\u00a0Health & Beauty industry (Health & Beauty Supplement)\nAssisting\u00a0with new product launch and product development\nPlan and implement ATL, BTL and online promotion\nManage assigned product portfolio and product marketing campaigns\nFormulate and execute digital marketing strategies\nPlan and manage social media platforms\nContent management and copy writing\nKOLs coordination, market research and competitive analysis\n\n\n\n\n\nInterested parties, please send your full resume with current and expected salary via\u00a0APPLY NOW. Please note that only short-listed candidates will be notified.(Data collected will be treated in strict confidence and used for recruitment purpose only)", "employment_types": ["Full Time", "Permanent"], "selling_points": ["New Product Launch, Marketing Campaigns", "Product Marketing, Brand Building", "Product Development, Digital Marketing Strategies"], "locations": ["Not Specified"], "categories": ["Marketing / Public Relations", "Marketing - Brand / Product Management", "Marketing - Direct Marketing", "Marketing - Marketing Communication"], "post_time": "2022-01-13T17:33:29Z", "salary": {"currency": null, "max": null, "min": null, "period": "monthly", "term": null}, "salary_visible": false, "title_keywords": ["assistant product manager", "senior marketing executive"], "responsibilities": ["social media", "management", "marketing strategies", "digital marketing strategies", "analysis", "social media platforms", "market research", "digital marketing", "plan", "marketing campaigns", "coordination", "budget control", "online promotion"], "requirements": {"degrees": [], "majors": [], "languages": [], "language_level": [], "hard_skills": ["analysis"], "soft_skills": ["coordination"], "languages_combined": []}, "experience_required": {"duration": ["minimum 5 years", "minimum 3 years"], "field": ["beauty industry", "marketing", "beauty"]}}, {"job_id": "100003009038246", "location_code": "hk", "company": "", "job_title": "Assistant Marketing Officer", "description": "Responsibilities\n\nDevelop and implement effective marketing programs within schedule\nFormulate and proof-read marketing materials, ensuring valid, current and accurate content\nMake use of social media platform to promote company branding and new products\nCommunicate with shops, suppliers and internal work parties to implement various events and marketing functions\nProvide administrative support and assist ad hoc projects\n\nRequirements\n\nDegree holder in Marketing or related disciplines\n2-3 years\u2019 marketing experience in retail industry is preferred\nProficient PC skills, with knowledge of Photoshop and Illustrator would be an advantage\nStrong communication\u00a0skills, independent and detail-minded\nGood command of spoken and written English, Chinese\nImmediately available is highly preferred\nMore experience will be considered as Marketing Officer\nInterested candidates, please contact us at 94352209 for company details before applying.", "employment_types": ["Full Time", "Permanent"], "selling_points": ["Degree holder", "2 years\u2019 marketing experience", "Implement marketing programs"], "locations": ["Not Specified"], "categories": ["Marketing / Public Relations", "Marketing - Brand / Product Management", "Marketing - Direct Marketing", "Marketing - General / Support"], "post_time": "2022-01-11T06:24:47Z", "salary": {"currency": null, "max": null, "min": null, "period": "monthly", "term": null}, "salary_visible": false, "title_keywords": ["assistant marketing officer"], "responsibilities": ["communicate with", "social media", "develop", "ad hoc projects", "schedule", "marketing materials", "provide administrative support"], "requirements": {"degrees": ["degree holder"], "majors": ["related disciplines", "marketing"], "languages": ["english", "chinese"], "language_level": ["good command"], "hard_skills": ["pc skills", "illustrator", "photoshop"], "soft_skills": ["detail-minded", "communication skills", "independent"], "languages_combined": [{"language": "english", "language_level": ["good command"]}, {"language": "chinese", "language_level": ["good command"]}]}, "experience_required": {"duration": ["2-3 years"], "field": ["retail industry", "marketing"]}}, {"job_id": "100003009044883", "location_code": "hk", "company": "Harbour City Estates Ltd", "job_title": "LEASING OFFICER (OFFICE)", "description": "Responsibilities:\n\nHandle the marketing and leasing matters of high class office premises\nLiaise with real estate agents\nAnalyze market trends and prepare leasing reports\n\nRequirements:\n\nUniversity graduates or equivalent in related disciplines\nAt least 3 years' solid experience in office premises leasing, preferably in developer companies\u00a0\nGood command of written and spoken English and Chinese, fluency in Mandarin is an advantage.\n\nWe offer competitive remuneration package that commensurate with experience and qualifications. Interested parties are invited to send full resume stating contact telephone number, date available, present and expected salary to our recruitment email address.\n\n\n(Personal data provided will be used strictly in accordance with the Company's personal data policy which is available upon request.)\u00a0", "employment_types": ["Full Time", "Permanent"], "selling_points": ["Handle the marketing and leasing matters", "Liaise with real estate agents", "At least 3 years' solid experience"], "locations": ["Tsim Sha Tsui"], "categories": ["Sales, CS & Business Devpt", "Business Development", "Marketing / Public Relations", "Marketing - Direct Marketing", "Property / Real Estate", "Property Consultancy"], "post_time": "2022-01-15T03:49:21Z", "salary": {"currency": null, "max": null, "min": null, "period": null, "term": null}, "salary_visible": false, "title_keywords": ["leasing officer"], "responsibilities": ["liaise with", "reports"], "requirements": {"degrees": [], "majors": [], "languages": ["english", "chinese", "mandarin"], "language_level": ["fluency", "advantage", "good command"], "hard_skills": [], "soft_skills": [], "languages_combined": [{"language": "english", "language_level": ["fluency", "advantage", "good command"]}, {"language": "chinese", "language_level": ["fluency", "advantage", "good command"]}, {"language": "mandarin", "language_level": ["fluency", "advantage", "good command"]}]}, "experience_required": {"duration": ["at least 3 years"], "field": ["developer"]}}, {"job_id": "100003009051376", "location_code": "hk", "company": "", "job_title": "Marketing Executive/Asst. Marketing Executive", "description": "A degree holder or Higher Diploma in Marketing or Engineering.\nWorking experience in Marketing & Sales of electronic product is preferrable.\nKnowledge in manufacturing field is preferrable.\nGood communication skills in written & spoken English, Cantonese and Mandarin.\nProficiency in computer skills including Microsoft Word, Excel and Powerpoint, Knowledge of Chinese Word Processing would be an advantage.\nExcellent communication and presentation skills.\nFresh graduates will also be considered.\n\n\n\nWe offer attractive remuneration package to the successful candidates.\u00a0\n\n(All data collected is used for recruitment purpose only.)\n\nInterested candidates, please contact us at 29515648 for company details before applying.", "employment_types": ["Full Time", "Permanent"], "selling_points": [], "locations": ["Kwun Tong Area"], "categories": ["Marketing / Public Relations", "Marketing - Direct Marketing", "Marketing - General / Support", "Marketing - Marketing Communication"], "post_time": "2022-01-15T12:35:12Z", "salary": {"currency": null, "max": null, "min": null, "period": "monthly", "term": null}, "salary_visible": false, "title_keywords": ["marketing executive"], "responsibilities": ["communication"], "requirements": {"degrees": ["diploma", "degree holder"], "majors": ["marketing", "engineering"], "languages": ["cantonese", "english", "chinese", "mandarin"], "language_level": ["advantage", "proficiency", "good"], "hard_skills": ["excel", "microsoft word", "chinese word processing", "powerpoint", "computer skills"], "soft_skills": ["communication", "communication skills", "presentation skills"], "languages_combined": [{"language": "cantonese", "language_level": ["good"]}, {"language": "english", "language_level": ["good"]}, {"language": "chinese", "language_level": ["advantage", "proficiency"]}, {"language": "mandarin", "language_level": ["good"]}]}, "experience_required": {"duration": [], "field": ["marketing"]}}, {"job_id": "100003009054480", "location_code": "hk", "company": "AXA China Region Insurance Company Limited", "job_title": "AXA Prime Program Trainee", "description": "Ready to meet different life?\nWant to leave the routine office work, from being heavily bondage by work, to become control own life\u00a0autonomously?\nJoin us, and we will walk together.\n\n**Professional development\nEducate clients mindset on investment and insurance products\nRecommend the right product to the right customers to fulfill Risk & Wealth Management\nRegular Review with clients including Claims and goals setting\n\nMPF Consulting & Integration\nGeneral Insurance Service\nIn-depth\u00a0understanding of current Socioeconomic Environment\n\n**Profitable return\n\nHongKongerTeam\n\n24 months financial support (Monthly support from 15,000 to 40,000) + Unlimited Commission\n9 bonus every year\nAll-rounded on-Job Training\nGroup Medical & MPF\nCompany convention to an overseas trip\nBuild up Team and Leadership\n\n**Requirements\n\nHKID holder\nUniversity Degree Holder/ Associate-Degree Holder/ High-Diploma\u00a0Holder\nTeam Spirit, Sincere on learning, hard-working, Positive thinking & attitude\nGood communication skill\n\n**If you wanna join us, please click \u201c Apply \u201d and work with us, you will never get alone.\n[All personal information collected would be used for recruitment purpose only.]\n\n", "employment_types": ["Full Time"], "selling_points": ["You seek for Work - Life balance here", "We will teach the skill when you start up here", "Office in Kwun Tong. Fluent in English or Canton"], "locations": ["Kwun Tong"], "categories": ["Sales, CS & Business Devpt", "Business Development", "Marketing / Public Relations", "Marketing - Direct Marketing", "Others", "Student / Fresh Graduate / No Experience"], "post_time": "2022-01-17T09:43:09Z", "salary": {"currency": null, "max": null, "min": null, "period": "monthly", "term": null}, "salary_visible": false, "title_keywords": ["trainee"], "responsibilities": ["control", "management", "mpf", "consulting", "regular review", "communication", "recruitment", "insurance"], "requirements": {"degrees": ["diploma holder", "university degree", "degree holder"], "majors": [], "languages": [], "language_level": [], "hard_skills": ["integration"], "soft_skills": ["team spirit", "sincere", "communication skill", "positive thinking", "learning", "hard-working", "leadership"], "languages_combined": []}, "experience_required": {"duration": [], "field": []}}, {"job_id": "100003009033162", "location_code": "hk", "company": "SANGPKS", "job_title": "Financial Consultant & Management Trainees", "description": "We Are One Of The Biggest Insurance Company\n\nWe Provide:\n- Ideal Performance Bonus\n-Attractive Packages\n-5days per week\n-Medical Insurance\n\nJob Requirements:\n-F.5 or above\n-Good Communication Skills\n-Basic Computer Skills\n\nJob Responsibilities:\n-Follow up customers\n-Customer\u2019s developments and provide advices\n-Follow up sales orders\n-Promote new products\n-Independent and optimistic personality\u00a0", "employment_types": ["Full Time", "Permanent"], "selling_points": ["\uff15 DAYS WORK", "15- 25K", "-Medical Insurance / - Ideal Performance Bonus"], "locations": ["Not Specified"], "categories": ["Marketing / Public Relations", "Marketing - Direct Marketing", "Sales, CS & Business Devpt", "Account Servicing", "Management", "Management Trainee"], "post_time": "2022-01-15T03:49:11Z", "salary": {"currency": null, "max": null, "min": null, "period": "monthly", "term": null}, "salary_visible": false, "title_keywords": ["consultant"], "responsibilities": [], "requirements": {"degrees": [], "majors": [], "languages": [], "language_level": [], "hard_skills": [], "soft_skills": [], "languages_combined": []}, "experience_required": {"duration": [], "field": []}}, {"job_id": "100003009048506", "location_code": "hk", "company": "HARRIMAN LEASING LIMITED", "job_title": "LEASING MANAGER (RETAIL)", "description": "The successful candidate will be responsible for the retail leasing of Times Square & Plaza Hollywood.\u00a0 Responsibilities include formulation and implementation of leasing strategy, negotiation and conclusion of tenancies, maintaining excellent relationship with tenants and real estate agents, analyzing market trend and budget forecast and preparation.\n\nApplicants should be University graduates in related discipline with over 8 years' practical experience (preferably gained in property developer) in high class retail premises leasing, 5 of which at supervisory level.\u00a0 The ideal candidate should have solid experience in handling leasing, legal documents as well as dealing with reputable brands and property management practitioners independently.\u00a0 He/she should possess strong negotiation and communication skills in both written and spoken Chinese and English, be resourceful and conversant with retail market.\n\nWe offer 5-day week and competitive salary package commensurate with experience and qualifications. Interested parties are invited to send full resume stating contact telephone number, date available, present and expected salary to our recruitment email address.\n\n\u00a0(Personal data provided will be used strictly in accordance with the Company\u2019s personal data policy which is available upon request.)", "employment_types": ["Full Time", "Permanent"], "selling_points": ["Formulation and implementation of leasing strategy", "Analyzing market trend and budget forecast", "8 years' experience in retail leasing"], "locations": ["Causeway Bay"], "categories": ["Sales, CS & Business Devpt", "Business Development", "Marketing / Public Relations", "Marketing - Direct Marketing", "Property / Real Estate", "Property Consultancy"], "post_time": "2022-01-15T03:50:00Z", "salary": {"currency": null, "max": null, "min": null, "period": null, "term": null}, "salary_visible": false, "title_keywords": ["leasing manager"], "responsibilities": ["management", "maintaining", "budget", "implementation", "communication", "forecast"], "requirements": {"degrees": [], "majors": [], "languages": ["english", "chinese"], "language_level": [], "hard_skills": [], "soft_skills": ["communication skills", "independently", "negotiation", "responsible", "resourceful", "ideal"], "languages_combined": [{"language": "english", "language_level": []}, {"language": "chinese", "language_level": []}]}, "experience_required": {"duration": ["8 years"], "field": ["management", "legal", "related", "developer", "retail", "supervisory level"]}}, {"job_id": "100003009038652", "location_code": "hk", "company": "Manpower Services (Hong Kong) Limited", "job_title": "Senior Marketing Coordinator / Associate Marketing Specialist (17.5K-22K)", "description": "Our client, a multinational company, is looking for a\u00a0Senior Marketing Coordinator / Associate Marketing Specialist to support their digital engagement team.\n\nResponsibilities\n\nDigital content implementation\nSupport content lead(s) to manage and implement\u00a0company website content editing and creation tasks, in line with specific business and commercial projects, to improve digital engagement experience for small and medium customer segments\nWork and align with designated content authoring teams in US/EU, localization team in EU and respective regional/local stakeholders, to follow through the content update/ development process, from briefing document preparation, request submission, test pages checking and validation, review and approval coordination, to overall time and quality management of the project\nWork with and support SEO lead to apply SEO practices to new content projects, or support on-going content optimization for existing content portals, in alignment with divisional digital strategy to improve visibility among prospects, new and existing customers to drive business results\nMonitor, review and evaluate results and performance to assess content effectiveness, and drive continuous enhancement that leads to improved business results as required\nProject management and reporting\nEnsure timely and quality completion of content development and implementation\nKeep content lead(s) updated on the content implementation progress and timeline\n\nRequirements\u00a0 \u00a0 \u00a0 \u00a0 \u00a0 \u00a0 \u00a0\n\nDiploma or above in marketing or related field\nAt least 1-2 years of work experience in marketing, or multi-national companies a plus\nKnowledge and experience in content marketing, web content development and graphic design an advantage\nCommunicate well and concisely in written and verbal English, with internal audiences and external vendors overseas\nEffective project and time management, solid tactical implementation skills\nWell organized, attention to details\nMulti-tasking and ability to meet tight deadline\nWilling to take initiatives with strong sense of ownership\nAble to work & learn independently, while can also work effectively in teams and maintain a sharing, supportive attitude\n\nInterested parties please send your full resume to yan.chan@manpowergrc.hk\u00a0or by clicking \"Apply Now\".", "employment_types": ["Contract"], "selling_points": ["Digital content implementation", "Project management", "Content Marketing"], "locations": ["Southern Area"], "categories": ["Marketing / Public Relations", "Marketing - Direct Marketing", "Marketing - General / Support", "Marketing - Marketing Communication"], "post_time": "2022-01-11T07:35:31Z", "salary": {"currency": null, "max": null, "min": null, "period": "monthly", "term": null}, "salary_visible": false, "title_keywords": ["marketing coordinator", "associate", "marketing specialist"], "responsibilities": ["reporting", "management", "seo", "review", "teams", "checking", "implementation", "quality", "monitor", "evaluate", "project management", "coordination", "editing", "company website"], "requirements": {"degrees": ["diploma or above"], "majors": ["marketing"], "languages": ["english"], "language_level": [], "hard_skills": ["plus", "web"], "soft_skills": ["work effectively", "supportive", "independently", "well organized", "multi-tasking", "meet tight deadline", "attention to details", "time management"], "languages_combined": [{"language": "english", "language_level": []}]}, "experience_required": {"duration": ["at least 1-2 years"], "field": ["graphic design", "marketing", "content development"]}}, {"job_id": "100003009041410", "location_code": "hk", "company": "Audemars Piguet (Hong Kong) Limited", "job_title": "Senior Trade Marketing Executive", "description": "Scope of Work\n\n1.\u00a0\u00a0General Marketing\n\nCollaboratively plan and implement 360 marketing and communication strategy to achieve the brand\u2019s goals and objectives\nLiaise with retail partners to develop strategic co-op boutique animation\nManage and control the Trade Tools budget, and optimize budget processes\n2.\u00a0Visual Merchandising\n\nManage annual orders and inventory of trade tools including retail accessories, publications, PLV, gifts\nManage distribution and support implementation of trade tools in all POS\nImplement global visual merchandising programs in all POS and develop custom animations and materials as needed. Supervise productions to ensure quality is up to standard\nCoordinate window installation and dismantling according to global calendar with additional adaptation for local festivities\nOrganize and maintain photo library for theme, launch displays and basic merchandising\nProcure qualitative vendors and ensure process is in compliance to company guidelines\nSupport new BTQ/POS openings in arrangement of trade tool materials\nRegularly monitor conditions of visual merchandizing and PLV in all POS and manage replacement/replenishment to ensure alignment with brand image. Travel to POS as needed to ensure proper visibility and that brand guidelines are adhered\nTrain and coach frontline retail staff on VM standards and guidelines\nMaintain communication with retail staff to address VM needs in a timely manner\nShare VM quality and design feedback and recommendations with HQ team and local team\nCompile competitive reports and post-animation reports\n\u00a03.\u00a0Events\n\nSupport AP House animation/Pop-up/Event implementation as well as replenishment of Events marketing materials (PLV, Gifts, Bags, ..) Support Event & Promotion Manager in visual merchandising and decorations at in-store and offsite events\n4. Gift Development\n\nManage development of local gifts (eg Mid-Autumn festival, CNY, Christmas, etc), ensuring they are in line with the brand image and relevant to audience.\nOversee and assist in the logistic of gift delivery\nManage the corporate gift order and storage. To keep proper record of the gift inventory\nMaintain close communication with HQ for local gift concept development and production\nManage locally developed gifts orders from other markets around the world\nProcure qualitative vendors and ensure process is in compliance to company guidelines.\nOthers\n\nProvide support for ad hoc marketing projects when required\n\nQualification\u00a0:\n\nMinimum 5 years of experience related to visual merchandising and trade marketing\nFlexibility to work additional hours during VM wave change and event periods\nLuxury goods experience preferred\n\nPersonal Skills\u00a0:\n\nAttention to details and exceptional organizational skills\nAbility to work as a team as well as work independently\nProject management and problem-solving skills\nAgility, creativity, flexibility and problem-solving skills\nAbility to work in a fast-paced and collaborative environment\nWork efficiency and ability to multi-task\nExcellent interpersonal and communications skills", "employment_types": ["Full Time"], "selling_points": ["Ability to work in a fast-paced environment", "A good team player, able to work independently", "Luxury goods experience preferred"], "locations": ["Central"], "categories": ["Marketing / Public Relations", "Marketing - Brand / Product Management", "Marketing - Direct Marketing", "Marketing - Marketing Communication"], "post_time": "2022-01-12T03:51:15Z", "salary": {"currency": null, "max": null, "min": null, "period": "monthly", "term": null}, "salary_visible": false, "title_keywords": ["marketing executive"], "responsibilities": ["inventory", "budget", "merchandising", "quality", "design", "communication", "maintain", "brand guidelines", "animations", "plan", "liaise with", "ap", "control", "ad hoc", "compliance", "monitor", "implementation", "develop", "reports", "visual", "installation", "provide support", "marketing projects", "trade marketing", "guidelines", "a timely manner", "replenishment", "company guidelines", "coordinate", "project management", "marketing materials", "animation"], "requirements": {"degrees": [], "majors": [], "languages": [], "language_level": [], "hard_skills": ["ap", "merchandizing", "basic", "pos", "visual merchandising", "project management", "problem-solving skills"], "soft_skills": ["organizational skills", "work independently", "multi-task", "work as a team", "timely", "collaborative", "communication", "project management", "attention to details", "problem-solving skills", "interpersonal"], "languages_combined": []}, "experience_required": {"duration": ["minimum 5 years"], "field": ["related", "marketing", "merchandising"]}}, {"job_id": "100003009050088", "location_code": "hk", "company": "China Construction Bank (Asia) Corporation Limited", "job_title": "FVP/VP, Segment Marketing", "description": "Job Description:\u00a0\n\n\nDesign and deliver creative customer centric and customer value management (CVM) marketing strategies, product cross-selling, retention and other portfolio growth campaigns by addressing segment characteristics to improve customer profitability, customer loyalty and product penetration rates and to deliver the business objectives of marketing strategy\nDrive contextual marketing initiatives to address consumer needs and purchase journey through in-depth data analysis, meaningful insights generation and timely delivery\nDrive and implement integrated marketing communication strategies and initiatives, including segment driven marketing campaign, product launches, banking product promotions, through-the-line advertising campaigns, customer events and the production of related marketing collaterals\nCollaborate with key internal stakeholders and effectively manage agency, vendor and supplier relationships to maximize service delivery\nEfficiently manage cost control, marketing calendar, call list summary and business analysis to support thorough evaluation of marketing strategy and campaign effectiveness\nRequirements:\u00a0\n\n\nUniversity degree in business studies, preferably in marketing or equivalent\nAt least 10 years of solid experience in marketing role within capacity of banking, wealth management or segment and profound integrated marketing campaign management functions\nStrong planning, analytical, negotiation and project management skills together with well-polished program design and management abilities with good business sense and attentive to details in efficient manner\nExperienced in liaising with external business partner and supplier and seasoned in directing and managing advertising plan and agency works\nStrong interpersonal and communication skill to work, interact with cross-function teams and facilitate business interactions and proven capability to motivate team members\nProven effectiveness as a self-starter who can work independently and in a team environment with ability to think both creatively and strategically, multi-task and to establish and drive high priority initiatives\nGood command of spoken and written English and Chinese, Mandarin is an advantage\nCandidates with less experience will be considered as Vice President.\nPlease send your application with both current and expected salary.\u00a0\u00a0\n\nApplicants who are not contacted within 8 weeks may consider their applications unsuccessful and their personal data will be retained by the bank for a period up to two years.\nAll information provided by applicants will be used for recruitment purposes only and will be used strictly in accordance with the bank\u2019s personal data policies, a copy of which will be provided upon request.", "employment_types": ["Full Time", "Permanent"], "selling_points": ["segment marketing", "stable team", "at least 10 years of solid experience in marketing"], "locations": ["Kowloon Bay"], "categories": ["Marketing / Public Relations", "Marketing - Brand / Product Management", "Marketing - Direct Marketing", "Marketing - General / Support"], "post_time": "2022-01-14T09:45:31Z", "salary": {"currency": null, "max": null, "min": null, "period": "monthly", "term": null}, "salary_visible": false, "title_keywords": [], "responsibilities": ["collaborate with", "service delivery", "management", "marketing strategies", "evaluation", "marketing collaterals", "design", "data analysis", "communication", "purchase", "cost control", "banking", "business analysis", "advertising campaigns"], "requirements": {"degrees": ["university degree"], "majors": ["business", "marketing"], "languages": ["english", "chinese", "mandarin"], "language_level": ["advantage", "good command"], "hard_skills": ["project management"], "soft_skills": ["efficient", "work independently", "multi-task", "negotiation", "attentive to details", "business sense", "project management skills", "communication skill", "interpersonal"], "languages_combined": [{"language": "english", "language_level": ["advantage", "good command"]}, {"language": "chinese", "language_level": ["advantage", "good command"]}, {"language": "mandarin", "language_level": ["good command"]}]}, "experience_required": {"duration": ["at least 10 years"], "field": ["management", "marketing", "banking"]}}, {"job_id": "100003009043339", "location_code": "hk", "company": "Wang On Properties Limited", "job_title": "Assistant Marketing Manager", "description": "Responsibilities:\n\nSupport strategic marketing solutions to achieve business goals for all group businesses in wide range of sectors including but not limited to retail, F&B and wet market businesses.\nExecute joint promotions and crossover with third parties for brand building\nCoordinate with internal departments / tenants / vendors on the development of marketing/CRM strategy and mechanics\nMonitor and implement marketing and CRM program strategy and mechanics, program branding, apps, websites and other marketing materials.\nEnsure the quality of all campaigns / promotions including but not limited to outputs of marketing agencies.\nGenerate market analysis to develop marketing programs and analyze the effectiveness of campaigns and promotions\n\nRequirements:\n\nDegree in Business Administration / Marketing / Communications or related discipline\nMinimum 4 years\u2019 relevant working experience\nKnowledge to design and produce marketing materials would be advantageous\nStrong relationship, connection with media and good business connection to explore opportunities with different strategic partners\nSelf-motivated, independent, detail-minded and capable to work under pressure\nExcellent organizational and interpersonal skills\nGood written and spoken English, Chinese and Putonghua\nImmediate available is highly preferred\n\nWe offer competitive remuneration package, our benefits include:\n\nPerformance bonus\nEducation subsidy\nProfessional membership fee sponsorship\nLife & medical insurance\nMarriage Leave, Compassionate Leave, Examination Leave etc.\nPublic holidays\nStaff purchase discount\n\nInterested parties please send full resume with\u00a0present and expected salary\u00a0to Human Resources Department by clicking \"Apply Now\" or via email recruit @woproperties.com\n\n(Information provided will be treated in strict confidence and will only be used for recruitment-related purposes.)\n\n\n", "employment_types": ["Full Time", "Permanent"], "selling_points": [], "locations": ["Kowloon Bay"], "categories": ["Marketing / Public Relations", "Marketing - Brand / Product Management", "Marketing - Direct Marketing", "Marketing - Marketing Communication"], "post_time": "2022-01-12T10:54:50Z", "salary": {"currency": null, "max": null, "min": null, "period": "monthly", "term": null}, "salary_visible": false, "title_keywords": ["assistant marketing manager"], "responsibilities": ["business goals", "quality", "coordinate with", "monitor", "develop", "market analysis", "marketing materials"], "requirements": {"degrees": ["degree"], "majors": ["marketing", "business administration", "communications"], "languages": ["putonghua", "english", "chinese"], "language_level": ["good"], "hard_skills": [], "soft_skills": ["detail-minded", "self-motivated", "independent", "capable", "organizational", "interpersonal skills", "work under pressure"], "languages_combined": [{"language": "putonghua", "language_level": ["good"]}, {"language": "english", "language_level": ["good"]}, {"language": "chinese", "language_level": ["good"]}]}, "experience_required": {"duration": ["minimum 4 years"], "field": ["relevant working experience"]}}, {"job_id": "100003009048943", "location_code": "hk", "company": "Heep Hong Society", "job_title": "Assistant Corporate Development Manager (MDP)", "description": "Responsibilities:\n\nFormulate strategies and implement donor recruitment and retention programmes and initiatives to achieve the Society\u2019s fundraising goals\nLead and motivate a team of staff to manage fundraising programmes and activities, especially the face-to-face programme\nAssist to recruit fundraising staffs and to provide relevant training programmes to increase productivity and improve sales performance\nAssist to develop and manage public and donor database; and provide strategic and analytic insights, reports and recommendations\nManage teammates to handle and execute exhibitions / fundraising events including planning, liaising and solicitation with exhibitors, suppliers and venues etc.\nDevise and implement outreach strategies, initiatives, activities and events to attract and engage public partners; and enhance brand awareness and engagement\nAssist to copy write fundraising and donor communications including newsletters, invitations, direct and online appeals, solicitations, acknowledgements, proposals, etc.\n\nRequirements:\n\nTertiary qualification in business administration, sales, marketing or related discipline\nMinimum 4 years\u2019 experience in fundraising, sales, coaching and marketing, with at least 2 years\u2019 in supervisory role gained from NGO or fundraising agencies\nSolid experience in managing a sales team or face-to-face monthly giving programme would be an asset\u00a0\nGood knowledge of fundraising in NGO is desirable\u00a0\nStrong leadership with excellent interpersonal and motivational skills\nHighly analytical with solid exposure in database management would be highly desirable\nGood organizational and planning skills, ability to work under pressure\nExcellent communications and presentation skills, including the ability to communicate fluently and professionally in English and Chinese\u00a0\nInterested to contribute to help others in need\n\nWe provide equal employment opportunities to all employees and applicants. For interested parties, please click\u00a0\u201cApply Now\u201d.\n\n(Personal data collected will be used for recruitment purpose only)", "employment_types": ["Full Time"], "selling_points": ["Donor recruitment, fundraising, event management", "Tertiary qualification in Bus. Admin./Marketing", "Min. 4 yrs' experience in fundraising & sales"], "locations": ["Ngau Tau Kok"], "categories": ["Marketing / Public Relations", "Marketing - Brand / Product Management", "Marketing - Direct Marketing", "Public Relations - Event Management"], "post_time": "2022-01-14T11:49:57Z", "salary": {"currency": null, "max": null, "min": null, "period": "monthly", "term": null}, "salary_visible": false, "title_keywords": ["manager", "assistant"], "responsibilities": ["improve sales performance", "develop", "manage teammates", "reports", "recruitment", "database", "planning"], "requirements": {"degrees": [], "majors": [], "languages": ["english", "chinese"], "language_level": ["excellent"], "hard_skills": [], "soft_skills": ["organizational and planning skills", "presentation skills", "leadership", "interpersonal", "work under pressure"], "languages_combined": [{"language": "english", "language_level": ["excellent"]}, {"language": "chinese", "language_level": ["excellent"]}]}, "experience_required": {"duration": ["minimum 4 years", "at least 2 years"], "field": ["supervisory", "marketing", "team"]}}, {"job_id": "100003009044880", "location_code": "hk", "company": "Harbour City Estates Ltd", "job_title": "ASSISTANT LEASING MANAGER / SENIOR LEASING OFFICER (RETAIL)", "description": "Responsibilities:\n\n\nTo handle the marketing and leasing matters of high class RETAIL premises\nTo liaise with real estate agents\nTo analyse market trends and prepare leasing reports\nRequirements:\n\nUniversity graduates in related discipline\nAt least\u00a06 years' solid experience in retail leasing\nGood command of written and spoken English and Chinese\nCandidates with more experience will be considered as Assistant Leasing Manager\n\nWe offer competitive remuneration package that commensurate with experience and qualifications. Interested parties are invited to send full resume stating contact telephone number, date available, present and expected salary to our recruitment email address.\n\n(Personal data provided will be used strictly in accordance with the Company's personal data policy which is available upon request.)", "employment_types": ["Full Time", "Permanent"], "selling_points": ["At least 6 years' solid exp. in retail leasing", "To liaise with real estate agents", "To analyse market trends & prepare leasing report"], "locations": ["Tsim Sha Tsui"], "categories": ["Sales, CS & Business Devpt", "Business Development", "Marketing / Public Relations", "Marketing - Direct Marketing", "Property / Real Estate", "Property Management"], "post_time": "2022-01-15T03:49:21Z", "salary": {"currency": null, "max": null, "min": null, "period": null, "term": null}, "salary_visible": false, "title_keywords": ["assistant leasing manager", "senior leasing officer"], "responsibilities": ["liaise with", "reports", "analyse"], "requirements": {"degrees": [], "majors": [], "languages": ["english", "chinese"], "language_level": ["good command"], "hard_skills": [], "soft_skills": [], "languages_combined": [{"language": "english", "language_level": ["good command"]}, {"language": "chinese", "language_level": ["good command"]}]}, "experience_required": {"duration": ["at least 6 years"], "field": ["retail"]}}, {"job_id": "100003003745507", "location_code": "hk", "company": "Suburfarm Investment & Trading Co Ltd", "job_title": "Administrator (Sales & Technical Support)  (5 days work)", "description": "Responsibilities\n\nTo handle day-to day clerical duties\n\nTo assist in preparing quotation, tender, report and related sales document\n\nTo assist in order coordination, after sales service and related sales activities\n\nTo handle incoming phone calls and enquiries\n\nTo provide the administration support to Sales and Technical Team\n\nRequirements\n\nHigh Diploma or Degree Holder\n\nNew graduates can be considered\n\nGood command of both spoken and written Chinese and English\n\nProficiency in MS Office\n\nAttention to details, self-motivated, able to work independently and under pressure\n\nGood interpersonal and organizational skills\n\nOccasionally out of office support tasks are required\n\nOffice location: Tsuen Wan area\n\nWe offer 5-days work, medical insurance, 12 days annual leave, in-house training and attractive salary package to the right candidate.\n\nInterested parties please send detailed resume with applying position.\n\nAll applications received will be used strictly for selection purposes only.", "employment_types": ["Full Time", "Permanent"], "selling_points": [], "locations": ["Tsuen Wan Area"], "categories": ["Sales, CS & Business Devpt", "Business Development", "Marketing / Public Relations", "Marketing - Direct Marketing", "Medical Services", "Others"], "post_time": "2022-01-13T08:11:13Z", "salary": {"currency": null, "max": null, "min": null, "period": "monthly", "term": null}, "salary_visible": false, "title_keywords": ["technical support", "administrator", "sales"], "responsibilities": ["administration", "sales activities", "quotation", "incoming phone calls", "coordination", "tender", "report"], "requirements": {"degrees": ["high diploma", "degree holder"], "majors": [], "languages": ["english", "chinese"], "language_level": ["good command"], "hard_skills": ["wan", "ms office"], "soft_skills": ["organizational skills", "self-motivated", "work independently", "under pressure", "attention to details", "interpersonal"], "languages_combined": [{"language": "english", "language_level": ["good command"]}, {"language": "chinese", "language_level": ["good command"]}]}, "experience_required": {"duration": [], "field": []}}, {"job_id": "100003009043700", "location_code": "hk", "company": "Perfect Medical Health Management Limited", "job_title": "Digital Marketing Manager", "description": "Pursue a Career with Impact\n\nAt Perfect Medical, we dare to envision, and we strive for perfection.\u00a0\n\nPerfect Medical is a leading Medical Beauty Group with over 100 treatment centers worldwide. With our passion for innovation and breakthroughs, our business\u2019 global footprint has been extending from Hong Kong Headquarter to China, Macau, Australia and Singapore with over 2,000 employees across regions.\n\nTo cope with the Company\u2019s rapid expansion, we are currently looking for high caliber and visionary candidates to join our team as\u00a0Digital Marketing Manager\n\n\n\nResponsibilities:\n\n\nLead a team of marketers who are responsible for digital\u00a0campaigns execution\u00a0\nDrive digital performance across Hong Kong, Macau, Australia & Singapore\nPlan and\u00a0monitor\u00a0the company\u2019s SEO and SEM management\nGather market intelligence on post-campaign results, consumer insights, media landscape and competitive activity to drive best practice strategy and performance optimizations\nWork closely IT team on tracking and tagging, and to explore and enhance the customer journey, customer experience, product functions and product features in the digital channels\nProvide report analysis including tracking budgets and timelines to control campaign ROI\nPerform any other ad hoc duties as assigned\n\n\n\nRequirements:\n\nDegree in communications, marketing, journalism or a related area\n7 years of experience in digital marketing, communications or related discipline\nExpert with Google Marketing Platform (e.g. SA360, DV360, Campaign Manager), Facebook Ads Manager and Programmatic platforms\nTarget-oriented, proactive, fast-paced with strong communication, presentation, and interpersonal skills\nUnderstanding of web analytic metrics\nPassionate to work with creative team on ideas and strong in problem solving\nImmediate availability is highly preferred\nCandidate with more experience will be considered as Senior Digital Marketing Manager", "employment_types": ["Full Time", "Permanent"], "selling_points": ["SEO, SEM, Social Media, online media", "Performance Marketing", "Young and energetic environment"], "locations": ["Yau Tsim Mong Area"], "categories": ["Marketing / Public Relations", "Marketing - Direct Marketing", "Digital Marketing"], "post_time": "2022-01-13T01:32:20Z", "salary": {"currency": null, "max": null, "min": null, "period": "monthly", "term": null}, "salary_visible": false, "title_keywords": ["digital marketing manager"], "responsibilities": ["ad hoc duties", "budgets", "management", "control", "seo", "consumer insights", "analysis", "monitor", "lead a team", "digital campaigns", "plan", "sem", "report", "tracking"], "requirements": {"degrees": ["degree"], "majors": ["journalism", "marketing", "communications"], "languages": [], "language_level": [], "hard_skills": ["problem solving", "facebook", "web"], "soft_skills": ["passionate", "creative", "communication", "problem solving", "interpersonal skills", "proactive", "presentation"], "languages_combined": []}, "experience_required": {"duration": ["7 years"], "field": ["related", "digital marketing"]}}, {"job_id": "100003009043173", "location_code": "hk", "company": "OSIM (HK) Co. Limited", "job_title": "Digital Marketing Executive ( 5 Days Work)", "description": "Responsibilities:\n\nResponsible for content management of the brand website and other e-commerce channels\nAssist the team to plan and execute online promotion campaigns\n\nManage social media channels in order to meet the targeted KPI\nPlan and monitor company\u2019s SEO and SEM management\n\nParticipate and communicate with headquarters in website enhancement\nAssist in performance analysis in all digital channels\nAssist in any ad hoc duties as requested\n\nRequirements:\n\nDegree holder in Marketing / Communications e-commerce or related disciplines\nWith 1 - 2 years of solid experience in online marketing\n\nExperience in Google analytics is an advantage\nProactive, results-oriented with a strong sense of responsibility\nFast-paced with excellent communication and interpersonal skills\nCreative and attention to details\nGood command of spoken and written English, Cantonese, and Mandarin\n\n\nInterested parties, please send your full resume with\u00a0current salary,\u00a0expected salary,\u00a0and\u00a0available date\u00a0either by direct application from JobsDB (Please quote the job title on the subject ) or by WhatsApp:69298297 or by post to Human Resources Department, Unit 8-14 & 22-28, 11/F, Topsail Plaza, 11 On Sum Street, Shek Mun.\n\"Personal data collected will be used for recruitment purposes only.\"", "employment_types": ["Full Time", "Permanent"], "selling_points": [], "locations": ["Shatin Area"], "categories": ["Marketing / Public Relations", "Marketing - Direct Marketing", "Others", "E-commerce", "Marketing - Brand / Product Management"], "post_time": "2022-01-12T10:00:42Z", "salary": {"currency": null, "max": null, "min": null, "period": "monthly", "term": null}, "salary_visible": false, "title_keywords": ["digital marketing executive"], "responsibilities": ["communicate with", "social media", "management", "ad hoc duties", "seo", "analysis", "monitor", "website", "plan", "sem", "online promotion"], "requirements": {"degrees": ["degree holder"], "majors": ["related disciplines", "marketing", "communications", "e-commerce"], "languages": ["cantonese", "english", "mandarin"], "language_level": ["good command"], "hard_skills": ["google analytics", "e-commerce"], "soft_skills": ["creative", "sense of responsibility", "communication and interpersonal skills", "attention to details", "proactive"], "languages_combined": [{"language": "cantonese", "language_level": ["good command"]}, {"language": "english", "language_level": ["good command"]}, {"language": "mandarin", "language_level": ["good command"]}]}, "experience_required": {"duration": ["1 - 2 years"], "field": ["marketing"]}}, {"job_id": "100003009045909", "location_code": "hk", "company": "Reasonable Software House Limited \u601d\u9f4a\u8edf\u4ef6\u6709\u9650\u516c\u53f8", "job_title": "Business Development Manager", "description": "Job Summary\nThe priority of the Business Development Manager is the crucial one for Reasonable Software House Limited's business with the ambition to expand or the necessity to diversify its clientele.\u00a0\u00a0\n\nJob Duties:\n\nGenerate business leads and follow up on sales opportunities\u00a0\nWork towards monthly sales targets and KPI's\nArrange meetings with clients and carry our product demonstrations\nMaintain relationships with clients and address their needs effectively\n\nRequirements:\u00a0\n\nMinimum 2 years business development experience\nStrong communication and interpersonal skills\nDiligent, aggressive and result-oriented\nNice to have but not a must:\nExperience in software or (internet) marketing industry\nKnowledge in email marketing/ digital marketing/ e-commerce\nProven sales track record of bringing in new business and a natural ability to drive sales\n\nA highly competitive salary commensurate with qualifications and experience will be offered, in addition to annual leave and medical benefits.\n\nTo apply, please submit cover letter and resume to hr[at]reasonable.hk.", "employment_types": ["Full Time", "Permanent"], "selling_points": ["Attractive salary (basic + commission)", "No ceiling commission", "Diligent and sales-oriented"], "locations": ["Lai Chi Kok"], "categories": ["Sales, CS & Business Devpt", "Business Development", "Marketing / Public Relations", "Marketing - Direct Marketing", "Others", "Student / Fresh Graduate / No Experience"], "post_time": "2022-01-13T09:04:50Z", "salary": {"currency": "HKD", "max": 34999, "min": 25000, "period": "monthly", "term": null}, "salary_visible": true, "title_keywords": ["business development manager"], "responsibilities": ["maintain relationships", "arrange meetings"], "requirements": {"degrees": [], "majors": [], "languages": [], "language_level": [], "hard_skills": ["nice", "e-commerce"], "soft_skills": ["communication and interpersonal skills", "diligent", "result-oriented"], "languages_combined": []}, "experience_required": {"duration": ["minimum 2 years"], "field": ["business development", "marketing"]}}, {"job_id": "100003009037349", "location_code": "hk", "company": "Olens", "job_title": "Marketing Executive/ marketing officer (e-Commerce & retail)", "description": "Job Description:\n\nAssist Manager in the development and execution of marketing strategies and promotion plans for online and offline\nCoordinate and execute marketing tactics and action plans to achieve business goals\nGeneral online marketing duties\nOrganize and plan marketing campaigns, online and offline to generate new business\nResponsible for preparing marketing promotion materials\nPerform analysis on sales performance and promotion effectiveness with the objective in identifying market insights and sales opportunities\nAnalyze the online to offline sales performance and roll out effective activities, promotion or other action plan to reach business target\nMonitor performance, prepare report and insight for impression and conversion improvement\nContent Creation through Blogs, Facebook, Instagram,\u00a0Twitter and YouTube\nCreative Advertisement: Google AdWords, Analytics, Shopping, Forums\nResponsible for the promotion of the website and development of the online sales on the local and oversea market\n\n\u00a0Requirements:\n\nHigh Diploma or above in Marketing/E-commerce or related discipline\nMinimum 1 years\u00a0retail, product or digital marketing experience\nSensitive to the market trend with strong online marketing sense\nProficient in both spoken and written English and Mandarin\nPassionate about marketing, social media, health food, skincare and lifestyle brands\nMature, good team player, well-organized and able to work independently to meet schedules\nImmediate available is highly preferable\nFresh grad will also be considerable\n\n\u00a0Working Hours:\n\n5 days work week (Mon to Fri)\nWorking time: 10:00am - 7:00pm\n\nBenefits:\n\nWe offer 5-day work week, pleasant working environment, competitive remuneration package, staff discount, on the job training and career advancement to the right candidates\n\nWe offer competitive remuneration package to the right candidate. \u00a0Interested parties please send your full resume with expected salary to us.", "employment_types": ["Full Time"], "selling_points": [], "locations": ["Kwai Hing"], "categories": ["Marketing / Public Relations", "Marketing - Brand / Product Management", "Marketing - Direct Marketing", "Marketing - General / Support"], "post_time": "2022-01-11T02:35:19Z", "salary": {"currency": null, "max": null, "min": null, "period": "monthly", "term": null}, "salary_visible": false, "title_keywords": ["marketing officer", "marketing executive"], "responsibilities": ["business goals", "prepare report", "marketing strategies", "sales performance", "analysis", "monitor performance", "website", "coordinate", "plan", "marketing campaigns", "plans", "facebook"], "requirements": {"degrees": ["high diploma or above"], "majors": ["marketing", "e-commerce"], "languages": ["english", "mandarin"], "language_level": ["proficient"], "hard_skills": ["e-commerce"], "soft_skills": ["good team player", "work independently", "marketing sense", "well-organized", "mature", "sensitive to", "passionate about"], "languages_combined": [{"language": "english", "language_level": ["proficient"]}, {"language": "mandarin", "language_level": ["proficient"]}]}, "experience_required": {"duration": ["minimum 1 years"], "field": ["retail", "digital marketing"]}}, {"job_id": "100003009041955", "location_code": "hk", "company": "VST Computers (HK) Ltd", "job_title": "Marketing Assistant", "description": "Requirement\n\nDegree in Public Relations, Marketing, Communications, journalism or related business disciplines\nMinimum 3\u00a0years of experience in marketing experience\nTo plan & co-ordinate the event for the project\nImplementing marketing plan\u00a0& marketing activities for brand development\nGood interpersonal and communication skills\nGood command of written and spoken English and Chinese\nPC knowledge in Photoshop or AI is preferable\nProficient in using MS Office application, including Word, Excel & PowerPoint\nIndependent, able to work under pressure\nSelf-initiative team player and willing to work under pressure\n\nThe scopes of responsibilities are:\n\n- Assist in planning and executing marketing plans, advertising and promotion activities\n\n- Company website and social media platforms updating and monitoring\n\n- Contact with media for advertising and articles writing\n\n- Liaison with service providers on development and production of marketing collaterals\n\n- Provide assistance in ad hoc projects assigned\n\nWe offer five (5) days\u2019 work an attractive remuneration package to the right candidate.\u00a0Interested parties please send full resume and expected salary by Clicking \"Apply Now\"\u00a0\n\nPersonal data provided by applicants will be used strictly for recruitment purpose only.", "employment_types": ["Full Time"], "selling_points": [], "locations": ["Sheung Wan"], "categories": ["Marketing / Public Relations", "Marketing - Direct Marketing", "Marketing - General / Support", "Marketing - Marketing Communication"], "post_time": "2022-01-12T04:50:16Z", "salary": {"currency": null, "max": null, "min": null, "period": "monthly", "term": null}, "salary_visible": false, "title_keywords": ["marketing assistant"], "responsibilities": ["advertising", "marketing plans", "social media platforms", "monitoring", "marketing collaterals", "executing", "contact", "ad hoc projects", "provide assistance", "company website", "planning"], "requirements": {"degrees": ["degree"], "majors": ["journalism", "marketing", "communications", "business"], "languages": ["english", "chinese"], "language_level": ["good command"], "hard_skills": ["excel", "ai", "word", "powerpoint", "photoshop", "pc knowledge", "ms office"], "soft_skills": ["communication skills", "independent", "self-initiative", "team player", "interpersonal", "work under pressure"], "languages_combined": [{"language": "english", "language_level": ["good command"]}, {"language": "chinese", "language_level": ["good command"]}]}, "experience_required": {"duration": ["minimum 3 years"], "field": ["marketing"]}}, {"job_id": "100003009048447", "location_code": "hk", "company": "HARRIMAN LEASING LIMITED", "job_title": "ASSISTANT LEASING MANAGER (RETAIL)", "description": "Responsibilities:\n\nFormulate the leasing strategy and assist in trade mix planning\nHandle the marketing and leasing matters of high class\u00a0RETAIL\u00a0premises including\u00a0Times Square\u00a0&\u00a0Plaza Hollywood\nLiaise with real estate agents\nAnalyze market trends\nPrepare leasing reports\n\nRequirements:\n\nUniversity graduates or equivalent in real estate or related disciplines\nAt least 6 years' solid experience in property leasing, preferably in retail premises\nGood command of written and spoken English, Chinese and Putonghua\nProficient in MS applications\nCandidates with less experience will be considered as Senior Leasing Officer\n\nWe offer 5-day week and competitive salary package commensurate with experience and qualifications. Interested parties are invited to send full resume stating contact telephone number, date available, present and expected salary by clicking the \u201cApply Now\u201d button below.\n\n(Personal data provided will be used strictly in accordance with the Company\u2019s personal data policy which is available upon request.)", "employment_types": ["Full Time", "Permanent"], "selling_points": ["Handle retail leasing-Times Square,Plaza Hollywood", "6 years' solid experience in retail leasing", "University graduates in related disciplines"], "locations": ["Not Specified"], "categories": ["Sales, CS & Business Devpt", "Business Development", "Marketing / Public Relations", "Marketing - Direct Marketing", "Property / Real Estate", "Property Consultancy"], "post_time": "2022-01-15T03:49:59Z", "salary": {"currency": null, "max": null, "min": null, "period": null, "term": null}, "salary_visible": false, "title_keywords": ["assistant leasing manager"], "responsibilities": ["liaise with", "reports", "planning"], "requirements": {"degrees": [], "majors": [], "languages": ["putonghua", "english", "chinese"], "language_level": ["good command"], "hard_skills": ["ms applications"], "soft_skills": [], "languages_combined": [{"language": "putonghua", "language_level": ["good command"]}, {"language": "english", "language_level": ["good command"]}, {"language": "chinese", "language_level": ["good command"]}]}, "experience_required": {"duration": ["at least 6 years"], "field": ["retail"]}}, {"job_id": "100003009042590", "location_code": "hk", "company": "ESD Services Limited (ESDlife)", "job_title": "eCommerce Executive", "description": "You will:\n\nThe incumbent will be responsible for day-to-day operational duties for our eCommerce platforms, covering website product and content management, order management and customer services support as listed below:\n\n\nProvide sales administrative support including market analysis, product update, and management report\nManage and coordinate the product sourcing, supplier relationship of the eCommerce business\nPerform business development and growth on CRM program\nPrepare sales report and forecast analysis\nHandle specific merchants account for product launch and promotion support\nWork with the team closely to achieve company sales target\n\nYou should have / be:\n\n\nUniversity graduate in Business, Marketing or related disciplines\nAt least 1 years\u2019 experience in consumer product or health product category\nGood understanding of online shopping business and latest trends\nExperience in online advertising especially in SEM and SEO is an advantage\nCRM experience with basic knowledge of Web Analytic, experience in analytic tools (e.g. Google Analytic) is preferred\nProficiency in MS Excel and Internet application usage\nExcellent command of both spoken and written Chinese, English and Mandarin\nCandidate with less experience will be considered for the position 'Assistant eCommerce Executive'\n\nIn addition, you will be able to:\n\n\nEnjoy an attractive and competitive remuneration package\nReceive training and development opportunities\n\n\u00a0Please send in your application by email to click \"APPLY NOW'\u00a0or by mail to the\u00a0Human Resources Department, ESD Services Limited, Unit 1209, 12/F, Two Harbourfront, 22 Tak Fung Street, Hung Hom, Kowloon.\n\nTo know more about us, please visit our website\nhttp://corporate.esdlife.com/\nhttps://health.esdlife.com/shop/hk/\n\n\nWe are an equal opportunity employer and welcome applications from all qualified candidates. The information provided will be treated in strict confidence and used only for consideration of application for relevant/similar post(s) within the Hutchison Group of Companies.\n\nApplicants not having heard from us within four weeks from the date of this advertisement may consider their application unsuccessful. All personal data of unsuccessful applicants will be destroyed after the recruitment exercise when no longer required.", "employment_types": ["Full Time", "Permanent"], "selling_points": [], "locations": ["Hung Hom"], "categories": ["Marketing / Public Relations", "Marketing - Direct Marketing", "E-commerce", "Marketing - Brand / Product Management", "Sales, CS & Business Devpt", "Sales Administration"], "post_time": "2022-01-12T08:06:02Z", "salary": {"currency": null, "max": null, "min": null, "period": "monthly", "term": null}, "salary_visible": false, "title_keywords": ["ecommerce executive"], "responsibilities": ["website", "personal data", "online advertising", "esd", "sales target", "prepare sales", "customer services", "sales administrative support", "forecast", "management report", "operational duties", "report", "management", "seo", "market analysis", "order management", "analysis", "coordinate", "recruitment", "sem"], "requirements": {"degrees": ["university graduate"], "majors": ["related disciplines", "business", "marketing"], "languages": ["english", "chinese", "mandarin"], "language_level": ["excellent"], "hard_skills": ["no", "seo", "basic", "web", "analysis", "ms excel", "sem"], "soft_skills": ["confidence", "responsible"], "languages_combined": [{"language": "english", "language_level": ["excellent"]}, {"language": "chinese", "language_level": ["excellent"]}, {"language": "mandarin", "language_level": ["excellent"]}]}, "experience_required": {"duration": ["at least 1 years"], "field": ["ecommerce", "advertising", "consumer product"]}}, {"job_id": "100003009035899", "location_code": "hk", "company": "RADIAN Laboratory Limited", "job_title": "Operations and Marketing Executive(s)", "description": "Full-time \u00b7 Entry level \u00b7 Internet\n\nWe are looking for:\n- Several crypto-savvy Talents (if you are not, we will make you one) who enjoys the prospect of working on Web3, Social and Dating products\n- Fresh graduates are welcomed if you have an active imagination with quick learning abilities\nPrerequisites:\n- Basic digital marketing skills\n- You understand how to build audiences and have some experience (even basic) in product-marketing\nYou are a great fit for this job if you:\n- Have a great command of English, additional languages are desirable\n- Have excellent written, presentation, and verbal communication skills, including the ability to communicate complex concepts clearly and simply\n- Knowledge of website analytics tools, eg. Google Analytics, Google Keyword Planner etc. is a plus\n- Basic Design Skills\n\nYou are one of us if:\n- You are comfortable with navigating ambiguity and shifting priorities\n- You are extremely organized with a hawk eye for detail\n-\u00a0You have exceptional communication skills\n- You are proactive and curious with a demonstrable ability to figure things out on your own\nResponsibilities:\n- Organizing content creation that\u2019s shareable cross-channel for different events and promotions taking place existing and future social media platforms (e.g., Twitter, Telegram, Facebook, Instagram, and YouTube etc.)\n- Work closely with COO and content marketing to craft stories that showcase the organization's value proposition through all channels\n- Communicating value propositions and creative messaging of products by managing external communications channels, interacting with communities on social media platforms\n- Identifying and nurturing opportunities with media outlets\n- Working with the team in the execution of campaigns to target customers\n- Develop, test, and report on relevant KPIs for all marketing activities", "employment_types": ["Full Time"], "selling_points": [], "locations": ["Tsim Sha Tsui"], "categories": ["Admin & HR", "Administration / Operation Manager", "Marketing / Public Relations", "Marketing - Direct Marketing", "Digital Marketing"], "post_time": "2022-01-10T08:42:13Z", "salary": {"currency": null, "max": null, "min": null, "period": "monthly", "term": null}, "salary_visible": false, "title_keywords": ["operations"], "responsibilities": ["social media platforms", "develop", "kpis", "facebook", "report"], "requirements": {"degrees": [], "majors": [], "languages": ["english"], "language_level": [], "hard_skills": ["planner", "analytics tools", "marketing skills", "google analytics", "basic", "plus"], "soft_skills": ["organized", "communication skills", "eye for detail", "proactive", "presentation"], "languages_combined": [{"language": "english", "language_level": []}]}, "experience_required": {"duration": [], "field": ["marketing"]}}, {"job_id": "100003009043311", "location_code": "hk", "company": "Harbridge Partners Limited", "job_title": "Assistant Manager", "description": "Title:\u00a0 \u00a0 \u00a0 \u00a0 \u00a0 \u00a0 \u00a0 \u00a0 \u00a0 \u00a0 \u00a0 \u00a0 \u00a0Assistant Manager\n\nLocation:\u00a0\u00a0\u00a0\u00a0\u00a0 \u00a0\u00a0\u00a0\u00a0\u00a0\u00a0\u00a0\u00a0\u00a0\u00a0 Hong Kong\n\nBackground: \u00a0\u00a0\u00a0\u00a0\u00a0\u00a0\u00a0\u00a0\u00a0\n\nOur client is a pre eminent global consultancy and business services group, that is the market leader in its field. Due to strong growth plans, the Company Formations and Services division is seeking a well experience social media and internet marketing guru.\n\nResponsibilities:\n\nWork closely with commercial teams to plan and execute marketing initiatives to support business development and branding building in North Asia.\nOperate and manage local digital touch points including local website, social media and e-publications (WeChat, Linkedin, client newsletter, etc.).\nOptimize digital touch points\u2019 performance in terms of content planning vs. publishing schedule.\nContent managemen\n\no\u00a0\u00a0 Coordinate with professional teams for local content collection on regular basis\n\no\u00a0\u00a0 Able to write up non-technical social media short pieces, such as event review\n\no\u00a0\u00a0 Able to translate or localise Group insights articles for local markets\n\no\u00a0\u00a0 Proactively identify digital marketing tools or channels best suit for business development or branding purpose.\n\n\n\nManaging events in various scales and formats. Capable of the end-to-end event arrangement including internal and external invitation, webinar/digital platforms operation, communication and facilitation with external event partners, logistics for physical events, leads collection & resulting tracking, etc.\nWork together on brand merchandise on seasonal basis, esp. for HK market\nCoordinate with Group marketing based in UK or US for country level implementation of global projects, including branding and marketing collateral localization and local communications.\n\nRequirements:\n\nUniversity graduate.\n3-5 years\u2019 working experience on marketing communication. Professional services, financial service background or B2B marketing background is preferred, more experience is to be considered higher position\nKnowledge and experiences on WeChat Corporate Account management/operation is a must.\nDetail-oriented and responsive with efficient delivery, quick learning capability, multitasking capability, proactive and can-do working attitude\nGood interpersonal skills\nGood at MS Office and virtual collaboration tools (e.g. Teams)\nProficient both in written and spoken English and Chinese\n\nWork Benefits/ Work Environment:\n\nGreat Career progression.\nGreat Training and Career Path\nGreat\u00a0MPF Pension Scheme\nGood Work Life Balance\nGreat working hours\n\nHarbridge Partners Limited\nEmployment Agency Licence:\u00a0 65522", "employment_types": ["Full Time", "Permanent"], "selling_points": ["Manager,Social Media,Commercial Teams,WeChat,HK", "Execute marketing,Branding building in North Asia", "Detail-oriented&Responsive with efficient delivery"], "locations": ["Central & Western Area"], "categories": ["Marketing / Public Relations", "Marketing - Brand / Product Management", "Marketing - Direct Marketing", "Digital Marketing"], "post_time": "2022-01-12T23:26:19Z", "salary": {"currency": null, "max": null, "min": null, "period": "monthly", "term": null}, "salary_visible": false, "title_keywords": ["assistant manager"], "responsibilities": ["social media", "tracking", "review", "teams", "website", "coordinate with", "implementation", "communication", "digital marketing", "schedule", "plan", "logistics", "planning"], "requirements": {"degrees": ["university graduate"], "majors": [], "languages": ["english", "chinese"], "language_level": ["proficient"], "hard_skills": ["ms office", "wechat"], "soft_skills": ["efficient", "detail-oriented", "communication", "learning", "interpersonal skills", "can-do", "proactive", "responsive"], "languages_combined": [{"language": "english", "language_level": ["proficient"]}, {"language": "chinese", "language_level": ["proficient"]}]}, "experience_required": {"duration": ["3-5 years"], "field": ["operation", "marketing", "account management", "financial"]}}, {"job_id": "100003009044111", "location_code": "hk", "company": "Ambitious People Group", "job_title": "Affiliate Marketing Manager (MNC)", "description": "What are you going to do as an Affiliate Marketing Manager?\n\nYou are going to work in an eCommerce businesses with affiliate marketing services in Hong Kong. As an Affiliate Marketing Manager, you are responsible for acquiring new partnership. You need to set up SEO best practice and execute digital campaigns to boost online sales. We expect a hands-on Affiliate Marketing Manager to grow the business!\n\nWhat is offered to you as an Affiliate Marketing Manager?\n\n* High base salary\n* Career growth opportunity\n* work from home scheme\n\nWhat is expected of you?\n\n* Bachelor/ Master degree in Ecommerce, Marketing, statistics, or related discipline;\n* 2-3 years of experience in Affiliate Marketing, background in agency is a plus\n* Good understanding of other digital channels including Search and Social\n* Sound knowledge of Google products the and ad- serving/tracking process\n* Strong in communication\n* Proficient in English. Chinese is a plus\n* Immediately Available is a plus\n\nWhere are you going to work?\n\nYou will be working in a fast-paced environment with all brilliant, creative, and young talents from different cultural backgrounds. Apply now or directly send your resume to yuki.cheung@ambitiouspeople.com!\n\n", "employment_types": ["Full Time", "Permanent"], "selling_points": ["High base salary", "Dynamic working environment", "Career growth opportunities"], "locations": ["Not Specified"], "categories": ["Marketing / Public Relations", "Marketing - Brand / Product Management", "Marketing - Direct Marketing", "Digital Marketing"], "post_time": "2022-01-13T03:05:50Z", "salary": {"currency": null, "max": null, "min": null, "period": "monthly", "term": null}, "salary_visible": false, "title_keywords": ["marketing manager"], "responsibilities": ["communication", "seo", "digital campaigns", "tracking"], "requirements": {"degrees": ["bachelor", "master degree"], "majors": ["ecommerce", "marketing", "statistics"], "languages": ["english", "chinese"], "language_level": ["proficient"], "hard_skills": ["plus", "seo", "scheme"], "soft_skills": ["responsible", "fast-paced environment", "communication", "hands-on", "creative"], "languages_combined": [{"language": "english", "language_level": ["proficient"]}, {"language": "chinese", "language_level": []}]}, "experience_required": {"duration": ["2-3 years"], "field": ["agency", "marketing"]}}, {"job_id": "100003009038786", "location_code": "hk", "company": "BridgeBuilder Company Limited", "job_title": "Marketing Communication Executive", "description": "Job Description\n\nFlexSystem, the leading solution provider in Hong Kong is consistently growing, now we are recruiting this Marketing Communication Executive to join our business.\n\n\n\n\nThe jobholder is responsible for providing information and conducting statistical analysis to achieve various marketing objectives.\n\n\n\n\nKey Responsibilities:\n\nDevelop the content strategy for promoting various IT solutions, including but not limited to Human Resources Management System, Financial Management System\n\nDevelop and oversee an integrated publishing schedule\n\nResearch topics that resonate with our IT solutions\n\nOptimize the website for SEO and conversions\n\nSupport the marketing team with English/Chinese language proofreading, editing, translating, etc.\n\nAssist to organize events\n\n\n\n\nRequirements\n\nDegree holder in Translation, Marketing, Business Administration, Communications or any other related discipline preferred\n\n1-3 years relevant experience in marketing, digital marketing communications\n\nExperience in Food & Beverage, Restaurant, hotel marketing is an advantage\u00a0\n\nSelf-motivated, independent and well-organized with attention to details\n\nGood command of written and spoken English and Cantonese\n\nImmediately available is preferable", "employment_types": ["Full Time"], "selling_points": ["Digital contents creation for IT solutions", "Develop content strategy across different channels", "Stable work environment"], "locations": ["Kwai Hing"], "categories": ["Marketing / Public Relations", "Marketing - Direct Marketing"], "post_time": "2022-01-11T07:48:29Z", "salary": {"currency": null, "max": null, "min": null, "period": "monthly", "term": null}, "salary_visible": false, "title_keywords": ["executive"], "responsibilities": ["management", "seo", "analysis", "website", "develop", "communication", "proofreading", "schedule", "editing"], "requirements": {"degrees": ["degree holder"], "majors": ["marketing", "business administration", "communications"], "languages": ["cantonese", "english"], "language_level": ["good command"], "hard_skills": ["translation"], "soft_skills": ["self-motivated", "independent", "well-organized", "attention to details"], "languages_combined": [{"language": "cantonese", "language_level": ["good command"]}, {"language": "english", "language_level": ["good command"]}]}, "experience_required": {"duration": ["1-3 years"], "field": ["restaurant", "marketing", "relevant experience", "digital marketing", "food"]}}, {"job_id": "100003009044443", "location_code": "hk", "company": "PERSOL Hong Kong", "job_title": "Sales & Marketing Executive (Jewelry Manufacturer/ Tsim Sha Tsui/ Fresh graduates OK!)", "description": "Our client,\u00a0a\u00a0Japanese jewelry trading company, is now seeking for a high caliber individual to join their team as\u00a0Sales & Marketing Executive (Ref No: #44301)\n\nJob Descriptions:\n\nCooperate with internal designers firmly to make sure advertising campaigns are running smoothly\nSustain a mature and healthy relationship with clients to develop new business opportunities\nCoordinate and supervise promotional activities like KOL events, etc.\u00a0\nSustain and update social media platform to improve customers' experience\u00a0\nHandle orders, sales and aftersales services professionally to enhance branding\nOther ad-hoc duties assigned by Department Manager or Director\n\n\u00a0Requirements:\n\nHigh Diploma or above holder in Business, Marketing, Media, Communication or related discipline\nMinimum with 1 - 2 years of marketing related experience in any industry\nProficiency in MS Word and Excel, Chinese word processing and Adobe Illustrator Artwork\nExcellent communication skills with good command of both spoken & written English and Mandarin\nknowledge in Japanese is an bonus\nEnthusiasm towards jewelry trading, ability to handle pressure and good time management\n\nBenefits:\n\n5 Days Work\u00a0\nDouble Pay\nDiscretionary Bonus\nBanking Holidays\nMedical Insurance\nTransportation allowance\u00a0\n\nInterested parties please quote\u00a0#44301\u00a0and send your application via email to\u00a0Apply Now.\u00a0For any enquiries, please do not hesitate to contact me at\u00a0(852) 2971-2520.\n\nPlease note that only short listed candidate will be notified.\n\nWe also have various job vacancies from our well-established clients in all kinds of fields, please feel free to contact us. We are always willing to give you support on your career development.\n\nAll information received will be treated in strict confidence and used for recruitment purpose only. Only shortlisted candidates will be notified.", "employment_types": ["Full Time"], "selling_points": ["Japanese jewelry trading company", "Fresh graduates or less experienced are considered", "salary up to 17k"], "locations": ["Tsim Sha Tsui"], "categories": ["Marketing / Public Relations", "Marketing - Brand / Product Management", "Marketing - Direct Marketing", "Marketing - General / Support"], "post_time": "2022-01-13T04:05:45Z", "salary": {"currency": null, "max": null, "min": null, "period": "monthly", "term": null}, "salary_visible": false, "title_keywords": ["sales & marketing executive"], "responsibilities": ["social media", "develop new business", "coordinate", "promotional activities", "ad-hoc duties", "cooperate with", "advertising campaigns"], "requirements": {"degrees": ["high diploma or above"], "majors": ["business", "marketing"], "languages": ["japanese", "english", "chinese", "mandarin"], "language_level": ["proficiency", "good command", "excellent"], "hard_skills": ["excel", "chinese word processing", "adobe illustrator", "ms word"], "soft_skills": ["communication", "communication skills", "time management"], "languages_combined": [{"language": "japanese", "language_level": []}, {"language": "english", "language_level": ["good command", "excellent"]}, {"language": "chinese", "language_level": ["proficiency"]}, {"language": "mandarin", "language_level": ["good command", "excellent"]}]}, "experience_required": {"duration": ["1 - 2 years"], "field": ["related", "marketing"]}}, {"job_id": "100003009042306", "location_code": "hk", "company": "HKT Consumer Group", "job_title": "Customer Data Analyst", "description": "Your role:\n\nResponsible for lead generation and prepare tracking reports to support various marketing campaigns;\nDevelop Dashboards to facilitate efficient data analysis for product performance, customer profiles and campaign effectiveness;\nConduct quantitative analysis and data mining to support management decisions and provide data-driven recommendations;\nOrganize and prepare regular\u00a0reports relating to business performance and service usage;\nConduct user acceptance test of in-house-developed applications.\n\nTo succeed in this role\n\nUniversity graduate in Computer Science, Information Technology, Data Science, Statistics or relevant discipline;\n3 \u2013 4 years\u2019 relevant experience, preferably in data analysis, database programming or database management\nProficient in SAS, SQL, Python or other data mining tools;\nPractical experience in data visualization tools (e.g. Qlik View/Sense, Power BI or Tableau);\nGood analytical and problem solving skills, able to work under tight timeline;\nSelf-motivated and able to accomplish multiple tasks with minimal supervision;\nGood\u00a0interpersonal and communication skills and\u00a0able to work with people at all levels;\nGood command in both spoken and written English;\nCandidate with less experience will be considered for the position of Senior Customer Data Analyst.\n\nHKT is an equal opportunity employer and welcomes applications from all qualified candidates. Information provided will be treated in strict confidence and will only be used for recruitment-related purposes. Personal data provided by job applicants will be used strictly in accordance with the employer's privacy statement (http://www.hkt.com/privacy-statement), a copy of which will be provided immediately upon request.", "employment_types": ["Full Time"], "selling_points": [], "locations": ["Quarry Bay"], "categories": ["Professional Services", "Business Analysis / Data Analysis", "Marketing / Public Relations", "Marketing - Direct Marketing"], "post_time": "2022-01-12T06:56:58Z", "salary": {"currency": null, "max": null, "min": null, "period": "monthly", "term": null}, "salary_visible": false, "title_keywords": ["data analyst"], "responsibilities": ["management", "visualization", "power bi", "data", "analysis", "customer data", "develop", "data analysis", "communication", "reports", "recruitment", "marketing campaigns", "database", "data mining", "personal data", "tracking"], "requirements": {"degrees": ["university graduate"], "majors": ["data science", "statistics", "computer science", "information technology"], "languages": ["english"], "language_level": ["good command"], "hard_skills": ["bi", "sas", "analysis", "tableau", "python", "sql", "database programming", "data visualization", "data mining", "problem solving skills"], "soft_skills": ["efficient", "communication skills", "self-motivated", "confidence", "responsible", "multiple tasks", "analytical and problem solving skills", "interpersonal", "driven"], "languages_combined": [{"language": "english", "language_level": ["good command"]}]}, "experience_required": {"duration": ["4 years"], "field": ["data analysis", "database management", "relevant experience", "programming", "database"]}}, {"job_id": "100003009040928", "location_code": "hk", "company": "Hu Yi Global Information Hong Kong Limited", "job_title": "Senior Marketing and Business Development Executive (3+ Marketing /Digital & Event Marketing)", "description": "Assist in developing, planning and implementing Online and Offline marketing strategies, campaigns and promotional activities for the company group\nSupport marketing campaigns in different aspects including advertising, digital marketing, events, partnership and public relations\nDemonstrates creativity and hands-on experience with a strategic mindset to ensure marketing goals and business needs are met\nConsolidation of reports, monitor expenses as per budget assigned\nOther ad hoc tasks to support the team;\n\n\nRequirements\nTertiary education in\u00a0Marketing, Business Administration or related disciplines\nMinimum 3 years working experience in Marketing / Events / Advertising / Public Relations Management\nSuperior problem-solving, organizational, communication and interpersonal skills\u00a0\nFlexible attitudes and willing to accept challenges, attention to details\nIndependent, able to work under pressure and meet tight deadline\nExcellent command of spoken and written English & Chinese\nGood analytical skills and able to conduct desktop research\nExperience with Adobe / Google Ads/Analytics, Facebook Ad Manager or equivalent tools is preferred\nProficient in MS Applications and Chinese word processing\n\nAbout GigGik\n\nFounded in 2020, GigGik Technology Limited is a start-up recruitment platform under HU YI Global group.\nWe dedicate to provide an effective and reliable recruitment channels to both candidates and recruiters. A new recruitment platform \"GigGik\" is developed by our company, clients can use the brand-new gTLD 'www.brand name.\u62db\u8058' (https://www.giggik.com/tc/companies) to ensure that there will be a trusted resource and employer branding between companies and candidates.\nSecondly, we aim to solve the recruitment problems that the most HR faces. Through the 1-stop recruitment process online with the platform, companies can reduce the human resources cost and speech up the talent match.\n\nWorking Location :\n\nKowloon Bay\n\nWe offer attractive remuneration and career opportunities to the right candidate. Interested parties please send detailed\u00a0CV\u00a0and\u00a0PORTFOLIO (if you have)\u00a0with\u00a0expected and present SALARY\u00a0to our HR department.\nThere will be a\u00a0job test\u00a0before interview.\n\nPersonal data collected will be used for recruitment purpose only.\n\nWelcome to browse our website:\u00a0https://www.giggik.com/", "employment_types": ["Full Time"], "selling_points": [], "locations": ["Kowloon Bay"], "categories": ["Marketing / Public Relations", "Management", "Marketing - Direct Marketing", "Digital Marketing"], "post_time": "2022-01-12T03:13:50Z", "salary": {"currency": null, "max": null, "min": null, "period": "monthly", "term": null}, "salary_visible": false, "title_keywords": ["business development executive"], "responsibilities": ["budget", "communication", "facebook", "administration", "work under pressure", "advertising", "expenses", "monitor", "developing", "reports", "marketing campaigns", "management", "cost", "marketing strategies", "ad hoc tasks", "promotional activities", "digital marketing", "recruitment process", "support the team", "hr", "recruitment", "planning"], "requirements": {"degrees": [], "majors": [], "languages": ["english", "chinese"], "language_level": ["excellent", "proficient"], "hard_skills": ["ms applications", "chinese word processing", "problem-solving", "analytical skills", "adobe", "facebook"], "soft_skills": ["flexible", "independent", "work under pressure", "organizational", "problem-solving", "analytical skills", "hands-on", "communication and interpersonal skills", "attention to details", "meet tight deadline", "reliable", "superior"], "languages_combined": [{"language": "english", "language_level": ["excellent"]}, {"language": "chinese", "language_level": ["excellent", "proficient"]}]}, "experience_required": {"duration": ["minimum 3 years"], "field": ["management", "public relations", "advertising", "business", "marketing"]}}, {"job_id": "100003009041403", "location_code": "hk", "company": "Michael Page", "job_title": "Marketing Director - Health and Wellness Brand", "description": "Our client is a well-regarded Health and Wellness Brand. They are currently expanding their business and seeking for a Marketing Director to join their dynamic marketing team.\n\nClient Details\n\nOur client is a well-regarded Health and Wellness Brand. They are currently expanding their business and seeking for a Marketing Director to join their dynamic marketing team.\n\nDescription\n\nOur client is a well-regarded health and wellness brand. They are currently expanding their business and seeking for a Marketing Director to join their dynamic marketing team. The position is the team leader to develop strategic marketing framework and execution plans including digital, event management, data analysis and product training.\n\nProfile\n\nThe successful candidate would be an experienced marketing manager for multinational company. Candidate with FMCG, Health and Beauty or pharmaceutical portfolio will be considered first. Our client is looking for a creative and brand thinking person with outstanding leadership skill to join them as a team leader. Public speaking and presentation ability are highly valued to this role. Fluency in English and Cantonese is required. Degree level qualification in marketing, business studies, or other related subjects is preferred.\n\nJob Offer\n\nWork for a global company that provides you with opportunity to expand your career. You will be provided with an attractive salary package and compensation.\n\nTo apply online please click the 'Apply' button below. For a confidential discussion about this role please contact Smania Wu on +852 3412 4858.", "employment_types": ["Full Time", "Permanent"], "selling_points": ["Global Health and Wellness Brand", "Strategic Leadership Role", "Fast Growing Business"], "locations": ["Not Specified"], "categories": ["Marketing / Public Relations", "Management", "Marketing - Direct Marketing", "Marketing - Marketing Communication"], "post_time": "2022-01-12T03:50:41Z", "salary": {"currency": null, "max": null, "min": null, "period": "monthly", "term": null}, "salary_visible": false, "title_keywords": ["marketing director"], "responsibilities": ["management", "develop", "data analysis", "contact", "plans"], "requirements": {"degrees": ["degree"], "majors": ["business", "marketing"], "languages": ["cantonese", "english"], "language_level": ["fluency"], "hard_skills": ["analysis", "dynamic"], "soft_skills": ["presentation", "leadership skill", "dynamic", "creative"], "languages_combined": [{"language": "cantonese", "language_level": ["fluency"]}, {"language": "english", "language_level": ["fluency"]}]}, "experience_required": {"duration": [], "field": []}}, {"job_id": "100003009042092", "location_code": "hk", "company": "Right Choice Financial Service", "job_title": "Management Trainee / Wealth Management Manager \u7406\u8ca1\u7b56\u5283\u7d93\u7406", "description": "\u00a0\u00a0\u00a0\u00a0\u00a0\u00a0\u00a0\u00a0\u00a0\u00a0\u00a0\u00a0\u00a0\u00a0\u00a0\u00a0\u00a0\u00a0\u00a0\u00a0\u00a0\u00a0\u00a0\u00a0\u00a0\u00a0\u00a0\u00a0\u00a0\u00a0\u00a0\u00a0\u00a0\u00a0\u00a0\u00a0\u00a0\u00a0 \u7d66\u5922\u60f3\u4e00\u500b\u6a5f\u6703\uff01\u6210\u5c31\u672a\u4f86\uff01\n\n\u6211\u5011\u76ee\u6a19\u00a0:\u00a0\u548c\u6709\u5fd7\u6210\u70ba\u512a\u79c0\u4f01\u696d\u5bb6\u7684\u9752\u5e74\u624d\u4fca\u6210\u70ba\u5408\u4f5c\u5925\u4f34\uff0c\u5354\u52a9\u4ed6\u5011\u65bc\u8ca1\u5bcc\u7b56\u5283\u884c\u696d\u4e0a\u5275\u7acb\u6301\u7e8c\u6210\u9577\u7684\u500b\u4eba\u4e8b\u696d\uff0c\u6211\u5011\u6295\u5165\u5927\u91cf\u8cc7\u6e90\u63a8\u52d5\u66f4\u5feb\u901f\u9054\u5230\u696d\u5167\u8a8d\u53ef\u80fd\u4e4b\u6700\u9ad8\u6c34\u5e73 - \u767e\u842c\u5713\u5353\u6703\u6703\u54e1\u8cc7\u683c\uff0c\u7372\u53d6\u53ef\u89c0\u6536\u5165\uff0c\u540c\u6642\u5de5\u4f5c\u548c\u751f\u6d3b\u7a6b\u4ea6\u53d6\u5f97\u5e73\u8861\u3002\n\n\u6211\u5011\u670d\u52d9\uff1a\u500b\u4eba\u65b9\u9762 - \u7406\u8ca1\u7b56\u5283\u3001\u7406\u8ca1\u98a8\u96aa\u7ba1\u7406\u3001\u8ca1\u5bcc\u589e\u503c\u914d\u7f6e\u3001\u8ca1\u5bcc\u50b3\u627f\u3001\u57fa\u91d1\u6295\u8cc7\u3001MPF\u3001\u500b\u4eba\u4fdd\u96aa / \u4f01\u696d\u65b9\u9762 : \u516c\u53f8\u4fdd\u96aa\u3001\u8981\u54e1\u4fdd\u96aa\u3001\u8cac\u4efb\u4fdd\u96aa\u7b49\u3002\n\n\u6211\u5011\u9700\u8981\uff1a\u9ad8\u7d1a\u6587\u6191 +\u5de5\u4f5c\u7d93\u9a57\uff0c\u5927\u5b78\u5b78\u58eb\u6216\u4ee5\u4e0a\uff0c\u6709\u4f01\u696d\u5bb6\u7cbe\u795e\u5275\u696d\u5bb6\u614b\u5ea6\uff0c\u76ee\u6a19\u70ba\u672c\uff0c\u71b1\u8aa0\u6a02\u89c0\n\n\u6211\u5011\u63d0\u4f9b\uff1a\u999624\u500b\u6708\u7279\u9ad8\u6d25\u8cbc+2\u9805\u4f63\u91d1+9\u9805\u82b1\u7d05\uff0c\u767e\u842c\u5713\u5353\u6703\u734e\u91d1\uff0c\u53ca\u7279\u5feb\u6649\u5347\u7ba1\u7406\u5c64\u767c\u5c55\u5718\u968a\uff0c\u5efa\u7acb\u500b\u4eba\u4f01\u696d\uff0c\u914d\u5408\u7531MDRT\u6210\u54e1,\u8ca1\u52d9\u7b56\u5283\u5e2b\u8f14\u52a9\u4e0b\u6210\u9577\n\n\u4f60\u7684\u6536\u7a6b\u00a0 : \u7121\u4e0a\u9650\u6536\u5165\u4e26\u4eab\u6709\u81ea\u4e3b\u767c\u5c55\u7a7a\u9593\uff0c\u512a\u8cea\u751f\u6d3b\uff0c\u53cb\u5584\u8077\u5834\uff0c\u5be6\u73fe\u4eba\u751f\u4e0d\u76ee\u6a19\u7406\u60f3\n\n\u6b61\u8fce\u96fb\u6216whatsapp96336822 \u8521\u5148\u751f\u67e5\u8a62", "employment_types": ["Full Time", "Internship"], "selling_points": [], "locations": ["Kwun Tong"], "categories": ["Insurance", "Insurance Agent / Broker", "Marketing / Public Relations", "Marketing - Direct Marketing", "Sales, CS & Business Devpt", "Direct Sales"], "post_time": "2022-01-12T06:04:27Z", "salary": {"currency": null, "max": null, "min": null, "period": "monthly", "term": null}, "salary_visible": false, "title_keywords": ["\u7406\u8ca1\u7b56\u5283\u7d93\u7406", "management trainee", "wealth management manager"], "responsibilities": [], "requirements": {"degrees": [], "majors": [], "languages": [], "language_level": [], "hard_skills": [], "soft_skills": [], "languages_combined": []}, "experience_required": {"duration": [], "field": []}}, {"job_id": "100003009050317", "location_code": "hk", "company": "Nanyang Commercial Bank, Limited", "job_title": "Strategic Planning Manager - Institutional Promotion (Ref: LD8028-IP-JDB)", "description": "Work on the portfolio with the RMs and identify business opportunities to achieve competitive edge for deposits and employee banking services. Assist to formulate and implement personal customer segment strategies to achieve the business targets and improve customer experience. Design and monitor the implementation of segment business plans through initiatives/ activities on acquisition, cross-selling, service upgrade, customer loyalty and retention, etc. Work with various internal and external stakeholders to meet customers\u2019 needs from a holistic perspective. Design appropriate sales tools to facilitate frontline to achieve the planned business targets and objectives. Collect and analyze data and feedbacks from time to time and make business recommendations for continuous improvement.\n\nRequirements:\n\nDegree or above with major in Business Administration, Marketing, Finance or related discipline;\nAt least 5 years working experience in banking industry; experience in customer segmentation, marketing, or product management is preferred;\nWith sales experience in retail banking and familiar with banking products and operations/services enhancement will be an advantage;\nA good team player with strong business acumen and analytical skills;\nExcellent communication and presentation skills;\nProficient in both spoken and written English and Chinese, fluent in Putonghua is preferable.\n\nIf you are flexible enough and zeal for a harmonious and supportive working environment where enables you to grow and succeed professionally, please send a full resume indicating your public examination results (HKCEE and HKALE / HKDSE), your present and expected salary and quoting reference number attention to\u00a0Talent Acquisition Division, Nanyang Commercial Bank, 151 Des Voeux Road Central, Hong Kong or apply through email. For details, please visit https://www.ncb.com.hk/ and select the page Recruit.\n\nWe are an Equal Opportunities Employer. Data collected would be used for recruitment purposes only. Applicants who do not hear from us within 8 weeks may consider their applications unsuccessful and their data will be destroyed within 12 months of receipt.", "employment_types": ["Full Time", "Permanent"], "selling_points": ["At least 5 years working experience in banking", "formulate and implement personal customer segment", "With sales experience in retail banking"], "locations": ["Central & Western Area"], "categories": ["Banking / Finance", "Retail Banking", "Marketing / Public Relations", "Marketing - Brand / Product Management", "Marketing - Direct Marketing"], "post_time": "2022-01-14T10:06:52Z", "salary": {"currency": null, "max": null, "min": null, "period": "monthly", "term": null}, "salary_visible": false, "title_keywords": ["manager"], "responsibilities": ["management", "identify business opportunities", "data", "operations", "monitor", "implementation", "design", "business plans", "communication", "recruitment", "banking", "analyze data", "administration"], "requirements": {"degrees": ["degree or above", "hkdse"], "majors": ["finance", "marketing", "business administration"], "languages": ["putonghua", "english", "chinese"], "language_level": ["fluent", "proficient"], "hard_skills": ["make", "analytical skills", "acumen"], "soft_skills": ["flexible", "good team player", "supportive", "harmonious", "analytical skills", "communication", "presentation skills", "business acumen"], "languages_combined": [{"language": "putonghua", "language_level": ["fluent", "proficient"]}, {"language": "english", "language_level": ["fluent", "proficient"]}, {"language": "chinese", "language_level": ["fluent", "proficient"]}]}, "experience_required": {"duration": ["at least 5 years"], "field": ["banking industry", "retail banking", "product management", "business", "marketing", "banking"]}}, {"job_id": "100003009043332", "location_code": "hk", "company": "", "job_title": "Marketing Manager", "description": "Responsibilities:\n\nInitiate, develop and implement all-round strategic marketing activities for commercial properties\nIdentify marketing opportunities and work out joint promotions and crossover with third parties for brand building\nCoordinate with internal departments / tenants / vendors on the development of marketing/CRM strategy and mechanics\nOversee and implement marketing and CRM program strategy and mechanics, program branding, apps, websites and other marketing materials.\nEnsure the quality of all campaigns / promotions\nGenerate market analysis to develop marketing programs and analyze the effectiveness of campaigns and promotions and provide insights for enhancement\n\nRequirements:\n\nDegree in Marketing / Communications / PR or related discipline\nMinimum 8 years\u2019 solid and relevant working experience\nProven track record in strategic marketing management and brand management in shopping mall is highly preferred\nProven experience in digital marketing would be advantageous\nProven experience to design and produce marketing materials would be advantageous\nStrong relationship, connection with media and good business connection to explore opportunities with different strategic partners\nSelf-motivated, independent, detail-minded and capable to work under pressure \uf06c Excellent organizational and interpersonal skills\nGood written and spoken English, Chinese and Putonghua\nImmediate available is highly preferred\nLess experience will be considered as Assistant Marketing Manager\nWe offer competitive remuneration package to successful candidates.\n\nInterested candidates, please contact us at 55345056 for company details before applying.\n\n(Information provided will be treated in strict confidence and will only be used for recruitment-related purposes.)", "employment_types": ["Full Time", "Permanent"], "selling_points": [], "locations": ["Kwun Tong Area"], "categories": ["Marketing / Public Relations", "Marketing - Brand / Product Management", "Marketing - Direct Marketing", "Marketing - Marketing Communication"], "post_time": "2022-01-12T10:54:48Z", "salary": {"currency": null, "max": null, "min": null, "period": "monthly", "term": null}, "salary_visible": false, "title_keywords": ["marketing manager"], "responsibilities": ["provide insights", "quality", "coordinate with", "develop", "market analysis", "marketing materials"], "requirements": {"degrees": ["degree"], "majors": ["marketing", "communications"], "languages": ["putonghua", "english", "chinese"], "language_level": ["good"], "hard_skills": [], "soft_skills": ["detail-minded", "self-motivated", "independent", "capable", "organizational", "interpersonal skills", "work under pressure"], "languages_combined": [{"language": "putonghua", "language_level": ["good"]}, {"language": "english", "language_level": ["good"]}, {"language": "chinese", "language_level": ["good"]}]}, "experience_required": {"duration": ["minimum 8 years"], "field": ["marketing", "digital marketing", "relevant working experience", "design"]}}, {"job_id": "100003009034254", "location_code": "hk", "company": "Royal Pearl Materials Group Limited", "job_title": "Marketing Executive/ Assistant Marketing Executive", "description": "Job Responsibilities\n\n\nDevelop New Business\nOrder follow up\nOrganize and Participate Exhibitions\nPerform Sales and Marketing Activities\n\nRequirements:\n\n\nF. 7 or above with min 2 years relevant experience\nAggressive, responsible and detail minded\nA good team player\nExcellent communication skill\nFluent in both written and spoken English is a must\nGood PC skills in MS office\n\n** Fresh Graduate will be considered as Assistant Marketing Executive\n\nInterested parties, pls send your resume with expected salary and available date email via \"Apply Now\"", "employment_types": ["Full Time", "Permanent"], "selling_points": [], "locations": ["Tsim Sha Tsui"], "categories": ["Sales, CS & Business Devpt", "Business Development", "Manufacturing", "Jewelry", "Marketing / Public Relations", "Marketing - Direct Marketing"], "post_time": "2022-01-11T02:06:08Z", "salary": {"currency": null, "max": null, "min": null, "period": "monthly", "term": null}, "salary_visible": false, "title_keywords": ["assistant marketing executive", "marketing executive"], "responsibilities": ["develop new business"], "requirements": {"degrees": ["fresh graduate"], "majors": ["marketing"], "languages": ["english"], "language_level": ["fluent"], "hard_skills": ["pc skills", "ms office"], "soft_skills": ["good team player", "communication skill", "responsible"], "languages_combined": [{"language": "english", "language_level": ["fluent"]}]}, "experience_required": {"duration": ["min 2 years"], "field": ["relevant experience"]}}, {"job_id": "100003009040056", "location_code": "hk", "company": "China Mobile Hong Kong \u4e2d\u570b\u79fb\u52d5\u9999\u6e2f", "job_title": "Assistant Marketing Manager, Marketing planning (prepaid)", "description": "CHINA MOBILE HONG KONG COMPANY LIMITED (\"CMHK\") is the wholly-owned subsidiary of China Mobile Limited (HKEx: 941) (NYSE: CHL), which ranks\u00a065th on the Fortune Global 500.\n\nOur company strives to offer superior service experience and to become the preferable digital partner for customers. We are preserving an environment with trust, responsibility and caring. At CMHK, we commit to maximizing people\u2019s potential and paving the way toward success for every striver. We are now inviting high caliber professional to join us.\n\nDivision: Marketing\n\nIn this position, you will:\n\nTo explore the opportunities and provide recommendations/ insight of prepaid business.\nParticipate in the formulation of marketing strategy which is in line with company objectives\nSupport and provide report on customers\u2019 portfolio evaluation, behavior analysis, sales performance to develop appropriate marketing programs.\nWork with internal departments to formulate new products/ service/ offers roll-out campaigns.\nMonitor competitors; keep track on the market trend\nAssist in preparation of presentation materials, written reports and proposals\nOther ad hoc duties assigned by management\n\nTo be successful in this position, you should meet the following requirements:\n\nBachelor\u2019s degree in Business Administration, Marketing or equivalent disciplines\nMinimum 6 years of working experience\u00a0in consumer marketing / technology / Telecom industry\nExperience in implement end to end acquisition program, developing marketing plans and campaigns\nGood understanding in business operations\nGood coordination, project management, multitasking and presentation skills\nKnowledge in IT system is a plus\nSelf-motivated, attention to details, multi-tasking and able to work under pressure\nFluency in written and spoken English, Cantonese and Mandarin\nCandidate with less experience may consider as Senior Marketing Executive\n\nWhen you work:\n\n5 days work\n8 hours/day\n\nWhat you enjoy:\n\nDouble pay\nDiscretionary Performance bonus\nLife insurance\nMedical insurance\nEducation subsidies\nBirthday gift\nMarriage leave\nBirthday leave\nStaff discount\n\nCMHK is committed to be an equal opportunity employer. We offer exceptional benefits package and the opportunity to work in a challenging environment. Personal data provided by applicants will be treated strictly in accordance with our personal data policy and for recruitment purposes only.\n\nPlease submit your application to us by clicking the APPLY NOW button and send your full resume with your availability, current and expected salary to us.", "employment_types": ["Full Time", "Permanent"], "selling_points": ["16 AL, 5 days work week", "double pay, dis. performance bonus", "Staff SIM, Staff Offer"], "locations": ["Kwai Hing"], "categories": ["Marketing / Public Relations", "Management", "Marketing - Brand / Product Management", "Marketing - Direct Marketing"], "post_time": "2022-01-12T01:09:47Z", "salary": {"currency": null, "max": null, "min": null, "period": null, "term": null}, "salary_visible": false, "title_keywords": ["assistant marketing manager"], "responsibilities": ["marketing plans", "operations", "evaluation", "administration", "ad hoc duties", "work under pressure", "sales performance", "monitor", "developing", "develop", "reports", "report", "management", "provide recommendations", "analysis", "preparation of presentation materials", "project management", "coordination", "insurance"], "requirements": {"degrees": ["degree", "bachelor"], "majors": ["marketing", "business administration"], "languages": ["cantonese", "english", "mandarin"], "language_level": ["fluency"], "hard_skills": ["mobile", "analysis", "project management", "plus"], "soft_skills": ["self-motivated", "work under pressure", "project management", "presentation skills", "multi-tasking", "committed", "coordination", "attention to details", "presentation", "superior"], "languages_combined": [{"language": "cantonese", "language_level": ["fluency"]}, {"language": "english", "language_level": ["fluency"]}, {"language": "mandarin", "language_level": ["fluency"]}]}, "experience_required": {"duration": ["minimum 6 years"], "field": ["digital", "marketing", "developing"]}}, {"job_id": "100003009046073", "location_code": "hk", "company": "Talent Blue Search Limited", "job_title": "Assistant Product Manager \u2013 US Consumer Health Brand", "description": "Our client, a US Consumer Health brand is seeking an Assistant Product Manager to drive marketing initiatives and to develop and lead the functions of branding, marketing ATL, BTL, digital marketing, product development, etc.\n\nResponsibilities:\n\nListen and develop a deep understanding of Hong Kong consumers and generate new insights. Ensure local resonance and global consistency of the brand.\nDefine the brand action plan to drive awareness & growth and build vision / expansion model\nTake ownership and responsibility for the brands and activate the right launches / campaigns to achieve the objectives.\nCollaborate strongly with Digital / E-comm and E-retail teams to accelerate online visibility & engagement.\n\nRequirements:\n\nExperience preferably within a consumer driven and FMCG environment (OTC, beauty, skin care, personal care, home care, infant formula, food & beverage, etc).\u00a0 Minimum of 3 years.\nDegree holder in any discipline\nExperience in branding / marketing campaign, conventional (ATL/BTL), digital, CRM, trade marketing, etc.\nThis brand is known to have a stable and excellent people culture.\u00a0\n\n\n400K - 455K per annual", "employment_types": ["Full Time", "Permanent"], "selling_points": ["Drive Branding/Marketing/Digital US Health Product", "Excellent People Culture Team Work", "400K - 455K per annual"], "locations": ["Not Specified"], "categories": ["Marketing / Public Relations", "Marketing - Brand / Product Management", "Marketing - Direct Marketing", "Digital Marketing"], "post_time": "2022-01-13T09:32:22Z", "salary": {"currency": null, "max": null, "min": null, "period": "monthly", "term": null}, "salary_visible": false, "title_keywords": ["assistant product manager"], "responsibilities": ["collaborate", "teams", "plan", "develop"], "requirements": {"degrees": ["degree holder"], "majors": [], "languages": [], "language_level": [], "hard_skills": [], "soft_skills": ["stable", "driven"], "languages_combined": []}, "experience_required": {"duration": [], "field": ["fmcg", "digital", "food", "marketing", "beauty", "personal care"]}}, {"job_id": "100003009044095", "location_code": "hk", "company": "Sportshouse Limited", "job_title": "Senior Sales Executive (Wholesale)", "description": "Responsibilities:\n\nFollow up orders, planning and coordinating\nResponsible for developing and expanding a strong wholesale network to achieve sales target and maintain customer base\nMonitoring customer feedback and maintain good working relationship with key accounts of wholesale business\nPresent regular sales report with updated information and detailed market analysis for management review\nMonitor sales performance and inventory level\u00a0 \u00a0 \u00a0 \u00a0 \u00a0\u00a0\u00a0\n\nRequirements:\n\nHigher Diploma or above\nMinimum 4 years\u2019 sales experience, with retail sales experience would be an advantage\n\nGood interpersonal and communication skills\nInitiative, responsible, hard-working and willing to work under pressure\nRelevant experience in marketing (digital and traditional) is preferred\n\nGood command of written and spoken English / Cantonese\nProficient in using MS Word, Excel, PowerPoint\n\nInterested parties please\u00a0send your resume with current and expected salary\u00a0by email or clicking\u00a0\"Apply Now\".\n\nData collected will be used for recruitment purpose only.\n\nFor company information, please visit our website www.sportshouse.com.hk", "employment_types": ["Full Time", "Permanent"], "selling_points": ["Follow up orders, planning and coordinating", "Develop and expand a strong wholesale network", "Maintain good working relationship with customers"], "locations": ["Tsuen Wan Area"], "categories": ["Marketing / Public Relations", "Marketing - Direct Marketing", "Sales, CS & Business Devpt", "Wholesale", "Digital Marketing"], "post_time": "2022-01-13T03:03:03Z", "salary": {"currency": null, "max": null, "min": null, "period": "monthly", "term": null}, "salary_visible": false, "title_keywords": ["senior sales executive"], "responsibilities": ["follow up orders", "sales report", "sales performance", "sales target", "monitoring", "monitor", "developing", "inventory", "maintain", "market analysis", "management review", "planning"], "requirements": {"degrees": ["higher diploma or above"], "majors": [], "languages": ["cantonese", "english"], "language_level": ["good command"], "hard_skills": ["excel", "powerpoint", "ms word"], "soft_skills": ["communication skills", "responsible", "hard-working", "interpersonal", "initiative", "work under pressure"], "languages_combined": [{"language": "cantonese", "language_level": ["good command"]}, {"language": "english", "language_level": ["good command"]}]}, "experience_required": {"duration": ["minimum 4 years"], "field": ["digital", "retail", "relevant experience", "marketing"]}}, {"job_id": "100003009040271", "location_code": "hk", "company": "Job-Box Personnel", "job_title": "Graduate Trainee Program (Welcome Fresh grad. / IANG Student)", "description": "The Role and Responsibilities:\n\nOn-the-job training to established related asset management expertise.\nPreparing investment portfolio and global market analysis.\nTo develop investment strategies to achieve client\u2019s short-term and long-term financial objectives.\nOn going manage client\u2019s portfolios according to client\u2019s financial goals.\nPreparing different scheme of investment proposal and portfolio review report.\nIdentify client objectives and offer appropriate financial consultancy.\n\nRequirements:\n\nBachelor degree holder or above in all disciplines\nInnovative and a good team player\nFluency in Cantonese, English and Mandarin\nGood communication and interpersonal skills\nArticulate and detail oriented, ability to multitask in a fast paced environment.\u00a0\n\nJob Offer:\n\nPersonal development and growth opportunities.\nContinuous Learning Sponsorship, medical benefits.\n5 day work week.\n\nWe offer a competitive salary and benefits package and the professional advantages of a dynamic environment that supports your development and recognizes your achievements.\n\nInterested individuals please send your detailed resume and expected salary by clicking\u00a0\"Apply Now\". Only candidates who are authorized to work in Hong Kong will be considered.\n\nAll personal data provided will only be used for recruitment purpose only. Information of candidates not selected will be destroyed in 3 months.", "employment_types": ["Full Time", "Permanent", "Internship"], "selling_points": ["5 day work,17-20 annual leave, Performance bonus", "Continuous Learning Sponsorship, medical benefits", "Personal development and growth opportunities"], "locations": ["Eastern Area"], "categories": ["Banking / Finance", "Private Banking", "Marketing / Public Relations", "Marketing - Direct Marketing", "Others", "Student / Fresh Graduate / No Experience"], "post_time": "2022-01-12T02:04:20Z", "salary": {"currency": "HKD", "max": 19999, "min": 17000, "period": "monthly", "term": null}, "salary_visible": true, "title_keywords": ["graduate trainee"], "responsibilities": ["investment strategies", "preparing investment portfolio", "global market analysis", "develop", "investment proposal", "portfolio review report", "manage client\u2019s portfolios", "asset management"], "requirements": {"degrees": ["bachelor degree holder"], "majors": [], "languages": ["cantonese", "english", "mandarin"], "language_level": ["fluency"], "hard_skills": [], "soft_skills": ["good team player", "detail oriented", "communication and interpersonal skills", "articulate", "ability to multitask", "innovative"], "languages_combined": [{"language": "cantonese", "language_level": ["fluency"]}, {"language": "english", "language_level": ["fluency"]}, {"language": "mandarin", "language_level": ["fluency"]}]}, "experience_required": {"duration": [], "field": []}}, {"job_id": "100003009040671", "location_code": "hk", "company": "Gemini Personnel Limited", "job_title": "Marketing Executive - retail industry (21 K, bonus) SK-J078119", "description": "A sizable Hong Kong retail chain is now looking for the above position urgently.\n\nRequirements :\n\nDegree qualification\u00a0\nRelevant experience in Retail Industry\u00a0\nExperience in digital marketing\u00a0\nGood language skills\n\nPackage :\u00a0\n\n21 K\u00a0\nyear end bonus (1 month)\nmedical\u00a0\nannual leave\npublic holidays", "employment_types": ["Full Time", "Permanent"], "selling_points": ["Degree", "Exp in Retail Industry, Digital Marketing", "21 K, 1 month bonus, medical, urgent"], "locations": ["Southern Area"], "categories": ["Marketing / Public Relations", "Marketing - Brand / Product Management", "Marketing - Direct Marketing", "Digital Marketing"], "post_time": "2022-01-12T02:55:56Z", "salary": {"currency": "HKD", "max": 24999, "min": 17000, "period": "monthly", "term": null}, "salary_visible": true, "title_keywords": ["marketing executive"], "responsibilities": ["digital marketing"], "requirements": {"degrees": ["degree"], "majors": [], "languages": [], "language_level": [], "hard_skills": [], "soft_skills": [], "languages_combined": []}, "experience_required": {"duration": [], "field": ["retail industry", "relevant experience", "digital marketing"]}}, {"job_id": "100003009036407", "location_code": "hk", "company": "Wah Fong Tea Co Ltd", "job_title": "Accounts Sales Manager", "description": "Job Duties & Requirement:\n\u00a0\u00a0\u00a0\u00a0\u00a0\u00a0\u00a0\u00a0\u00a0\u00a0 Implement Company\u2019s marketing and sales penetration strategies\n\u00a0\u00a0\u00a0\u00a0\u00a0\u00a0\u00a0\u00a0\u00a0\u00a0 Expand & develop\u00a0existing and new hotel, restaurant, club houses accounts\u2019 orders\n\u00a0\u00a0\u00a0\u00a0\u00a0\u00a0\u00a0\u00a0\u00a0\u00a0 Handle new customer accounts from initial approach to closing the sales\n\u00a0\u00a0\u00a0\u00a0\u00a0\u00a0\u00a0\u00a0\u00a0\u00a0 Manage customer demands and issues with appropriate solutions\n\u00a0\u00a0\u00a0\u00a0\u00a0\u00a0\u00a0\u00a0\u00a0\u00a0 Monitor sales orders traffic and customer satisfaction\n\u00a0\u00a0\u00a0\u00a0\u00a0\u00a0\u00a0\u00a0\u00a0\u00a0 Work with marketing staff on promotional materials and products updates\n\u00a0\u00a0\u00a0\u00a0\u00a0\u00a0\u00a0\u00a0\u00a0\u00a0 Assess market developments and capture market opportunities\n\u00a0\u00a0\u00a0\u00a0\u00a0\u00a0\u00a0\u00a0\u00a0\u00a0 Interface with various staffs to facilitate satisfying service to customers\n\u00a0\u00a0\u00a0\u00a0\u00a0\u00a0\u00a0\u00a0\u00a0\u00a0 Maintain and update necessary sales plan, records, documents, and reports as \u00a0required\n\nIncumbent Requirement:\n\n\u00a0\u00a0\u00a0\u00a0\u00a0\u00a0\u00a0\u00a0\u00a0\u00a0\u00a0\u00a0\u00a0\u00a0\u00a0\u00a0\u00a0 3 to 5 years\u2019 sales experience in F&B, Hotel, and Restaurants products sales experience is a plus\n\u00a0\u00a0\u00a0\u00a0\u00a0\u00a0\u00a0\u00a0\u00a0\u00a0\u00a0\u00a0\u00a0\u00a0\u00a0\u00a0\u00a0 Sales result oriented, self-motivated, self-initiating,and responsibility\n\u00a0\u00a0\u00a0\u00a0\u00a0\u00a0\u00a0\u00a0\u00a0\u00a0\u00a0\u00a0\u00a0\u00a0\u00a0\u00a0\u00a0 Have good hotels and F&B catering & beverages knowledge is a plus\n\u00a0\u00a0\u00a0\u00a0\u00a0\u00a0\u00a0\u00a0\u00a0\u00a0\u00a0\u00a0\u00a0\u00a0\u00a0\u00a0\u00a0 Friendly with good personal and communication skills to promote team work in external & internal work environment\u00a0\u00a0\u00a0\u00a0\u00a0\u00a0\u00a0\u00a0\u00a0\u00a0\u00a0\u00a0\u00a0\u00a0\u00a0\u00a0\u00a0\u00a0\u00a0\u00a0\u00a0\u00a0\u00a0\u00a0\u00a0\u00a0\n\u00a0\u00a0\u00a0\u00a0\u00a0\u00a0\u00a0\u00a0\u00a0\u00a0\u00a0\u00a0\u00a0\u00a0\u00a0\u00a0\u00a0 Fluent in English & Chinese written and oral communication\n\u00a0\u00a0\u00a0\u00a0\u00a0\u00a0\u00a0\u00a0\u00a0\u00a0\u00a0\u00a0\u00a0\u00a0\u00a0\u00a0\u00a0 Associate Marketing degree graduate is advantageous\n\nSales with needs selling skill, Marketing, and Product training will be provided.\n\nPersons interested this post, may send resume, expected salary via email,\n\nto Wah Fong Tea Co. Ltd.\u00a0\u00a0\n\nPersonal data received will be used strictly for recruitment purpose.", "employment_types": ["Full Time", "Permanent"], "selling_points": [], "locations": ["Sai Ying Pun"], "categories": ["Marketing / Public Relations", "Marketing - Direct Marketing", "Marketing - General / Support", "Marketing - Marketing Communication"], "post_time": "2022-01-12T23:26:06Z", "salary": {"currency": null, "max": null, "min": null, "period": "monthly", "term": null}, "salary_visible": false, "title_keywords": ["sales manager"], "responsibilities": [], "requirements": {"degrees": ["degree"], "majors": ["marketing"], "languages": ["english", "chinese"], "language_level": ["fluent"], "hard_skills": ["plus", "tea"], "soft_skills": ["communication skills", "oral", "self-motivated", "communication", "result oriented", "friendly"], "languages_combined": [{"language": "english", "language_level": ["fluent"]}, {"language": "chinese", "language_level": ["fluent"]}]}, "experience_required": {"duration": ["3 to 5 years"], "field": ["f&b"]}}, {"job_id": "100003009042049", "location_code": "hk", "company": "Future Leader Recruitment Agency", "job_title": "Graduate Trainee Program (5 days work, 18-22K)", "description": "Comprehensive Trainee Program for graduates\nPromising career path\nCompetitive compensation and benefit package\n\n\nJob Description\n\nOur client is one of the major financial institution in Asia. They are young, energetic and innovative, that nurture many youngsters to be part of their management team. Now they offer highly professional trainee program to\u00a0caliber candidates:\n\nTraining program:\n\nStructured and comprehensive training to build the professional base on finance and investment market knowledge and strategies\nExtensive initial training covering\u00a0professional and comprehensive\u00a0soft skills consulting, negotiation, presentation and communication\u00a0 \u00a0\nWeekly mentor-ship training sessions hold\u00a0by experienced Managers of firm\u00a0\nRotation of job duties in order to acquire experience in management and leadership\n\nJob responsibilities:\n\nTrained to be able to provide investment advice for clients, especially high net worth asset clients, manage their account and improve their investment return\n\nAssist senior managers in presenting investment portfolio and market outlook to clients\n\nWork as a team to organize business development events, such as, investment seminars, marketing events and road shows regarding investment\n\nDevelop your own client servicing skills, and make use of your professional knowledge to maintain a good relationship with clients\n\nDevelop your interpersonal skills and management skills to be a part of the management team in the later stage of your career\n\nRequirements:\n\nUniversity graduate\u00a0in any discipline\nMainland China\u00a0Fresh graduates with IANG visa are welcome\nProficiency in Chinese and English\nProactive to learn\nExcellent interpersonal, communications and presentation skills\nAggressive, self-motivated, customer orientation\u00a0\u00a0\n\nInterested parties please\u00a0click\u00a0Apply Now\n\nPlease note: Short listed candidates will be notified within eight (8) weeks of the date of this advertisement. All personal data collected will be kept confidential and used for recruitment purposes only.\n\n\n\n", "employment_types": ["Full Time", "Permanent"], "selling_points": ["Comprehensive Trainee Program for graduates", "Promising career path to management in 2 years", "harmonious, energetic and professional environment"], "locations": ["Causeway Bay"], "categories": ["Banking / Finance", "Fund Management", "Marketing / Public Relations", "Marketing - Direct Marketing", "Management", "Management Trainee"], "post_time": "2022-01-12T05:42:05Z", "salary": {"currency": null, "max": null, "min": null, "period": "monthly", "term": null}, "salary_visible": false, "title_keywords": ["graduate trainee"], "responsibilities": ["management team", "management", "marketing events", "consulting", "develop", "communication", "good relationship", "maintain"], "requirements": {"degrees": ["university graduate"], "majors": [], "languages": ["english", "chinese"], "language_level": ["proficiency"], "hard_skills": [], "soft_skills": ["presentation skills", "proactive", "interpersonal", "self-motivated"], "languages_combined": [{"language": "english", "language_level": ["proficiency"]}, {"language": "chinese", "language_level": ["proficiency"]}]}, "experience_required": {"duration": [], "field": []}}, {"job_id": "100003009037205", "location_code": "hk", "company": "Top Level Corporation Limited", "job_title": "Marketing Manager - BD & Channel Development (IT Industry)", "description": "Job Description:\n\nDesign and implement marketing strategies to enhance business opportunity and brand awareness\nExplore and study new IT / Data Protection product positioning, value prepositions and key messages to reach the targeted audience\nAccountable for marketing KPI and provide advise on channel partner incentive programs\nProactively conduct market research to analyze competitor's direction and market trend\nCollaborate across teams to promote whole selling cycle including lead generation, proposal preparation, presentation and contract negotiations\nMeasure program effectiveness and provide insights for future business development planning\nEstablish and maintain good relationship with internal teams, vendors and channel partners to ensure business success\n\nRequirements:\n\nDegree holder in Marketing, IT or related disciplines\n5 years relevant B2B Marketing or Business Development experience in security solutions, preferably with IT product, channel marketing or technology product distributor experience\nAble to turn data into actionable insights\nPassionate in IT industry and enthusiastic to serve as pioneer in learning data protection or security solutions technology\nSelf-starter with good communication, negotiation, collaboration and analytical skills\nGood command in spoken and written in Cantonese, Mandarin and English\nCandidate with less experience will be considered as Assistant Manager role\nBenefits we offer:\n\n5-day work week\nBank Holiday\nMedical Coverage\nBirthday, Wedding, Maternity and Paternity Leaves\nDiscretionary Bonus\nYoung and Fun Working Environment\nInterested parties, please click \"apply now\" to submit your resume, including your\u00a0 expected salary and availability.\n\n* All information will be treated as confidential and used solely for recruitment purposes.", "employment_types": ["Full Time", "Permanent"], "selling_points": ["Channel Marketing & IT product distribution field", "Rebuild MKT team & channel mkt strategies", "On-line & off-line marketing promotion"], "locations": ["Kowloon Bay"], "categories": ["Sales, CS & Business Devpt", "Business Development", "Marketing / Public Relations", "Marketing - Brand / Product Management", "Marketing - Direct Marketing"], "post_time": "2022-01-11T02:03:49Z", "salary": {"currency": null, "max": null, "min": null, "period": "monthly", "term": null}, "salary_visible": false, "title_keywords": ["marketing manager"], "responsibilities": ["collaborate", "provide insights", "marketing strategies", "data", "conduct market research", "teams", "design", "maintain good relationship", "planning"], "requirements": {"degrees": ["degree holder"], "majors": ["related disciplines", "marketing", "it"], "languages": ["cantonese", "english", "mandarin"], "language_level": ["good command"], "hard_skills": ["analytical skills"], "soft_skills": ["passionate", "negotiation", "analytical skills", "communication", "learning", "enthusiastic"], "languages_combined": [{"language": "cantonese", "language_level": ["good command"]}, {"language": "english", "language_level": ["good command"]}, {"language": "mandarin", "language_level": ["good command"]}]}, "experience_required": {"duration": ["5 years"], "field": ["marketing", "it", "security", "business development"]}}, {"job_id": "100003009033395", "location_code": "hk", "company": "Bannershop Hong Kong Limited", "job_title": "Digital Marketing Executive/ Senior Digital Marketing Executive", "description": "Job duties\n\nMonitor and manage daily eCommerce operations\nPlan and execute digital marketing campaign, including advertising, eDM, SEO, website content, social media etc.\nCreating a wide range of different marketing materials\nWorking closely with sales and production team and assisting with new product launches\nMonitor, research and identify market trends and competitor activities, provide monthly analysis report\nAssist in executing\u00a0loyalty programs\u00a0to achieve company goal\nExplore new business opportunity, including brand cooperation\n\nRequirements\n\nAt least 1yr working experience in e-commerce or digital agency\nExperience in content marketing and digital marketing\nKnowledge in search engine marketing, social ad, Google Analytic, etc\nGood tracking and data analytic skill\nGood command of written and spoken English and Chinese\nKnowledge of AI is a plus\nExperience in CRM campaign is a plus\nMore experience will be considered as Senior Marketing Executive", "employment_types": ["Full Time"], "selling_points": ["At least 1 yr exp in e-commerce or digital agency", "Exp in content marketing and digital market", "5 days work"], "locations": ["Kwun Tong"], "categories": ["Marketing / Public Relations", "Marketing - Direct Marketing", "Marketing - General / Support", "E-commerce", "Marketing - Brand / Product Management"], "post_time": "2022-01-09T16:25:53Z", "salary": {"currency": null, "max": null, "min": null, "period": "monthly", "term": null}, "salary_visible": false, "title_keywords": ["senior digital marketing executive", "digital marketing executive"], "responsibilities": ["social media", "advertising", "seo", "edm", "analysis report", "operations", "monitor", "website", "digital marketing", "executing", "plan", "marketing materials"], "requirements": {"degrees": [], "majors": [], "languages": ["english", "chinese"], "language_level": ["good command"], "hard_skills": ["ai", "plus", "e-commerce"], "soft_skills": [], "languages_combined": [{"language": "english", "language_level": ["good command"]}, {"language": "chinese", "language_level": ["good command"]}]}, "experience_required": {"duration": [], "field": ["e-commerce", "agency", "marketing", "digital marketing", "digital"]}}, {"job_id": "100003009035159", "location_code": "hk", "company": "Learning Habitat Families (Hampton Loft) Limited", "job_title": "Marketing Manager", "description": "Responsibilities\n\n\nDevelop strategic marketing plans and product promotion campaigns to enhance brand awareness and drive business growth\nCreate and manage the marketing budget\nAchieve business targets set by the direct supervisor\nCreate a targeted and cost-effective multi-channel marketing strategy for generating high quality leads\nManage campaign tracking and improvement, measuring and optimizing the messaging, budget spend, and channel mix.\nBuild brand awareness; plan and implement marketing plans by using different tactics; evaluate the effectiveness of marketing strategies/activities\nOversee digital media marketing strategies, social media and content marketing\nDevelop innovative digital media marketing strategies including search engine optimisation, video and social media, and email marketing campaigns.\nMonitor education industry trends, competitor activities, demographics, pricing schedule\nPrepare online or printed marketing materials for distribution via multi-channels\nDevelop social media content and manage social media platforms for targeted parents\nMonitor and optimize company brand presence across traditional media, social media, and influencers\nManage the website ensuring content are up-to-date by coordinating with in-house and out-sourced IT vendors\nMaintain effective communications with internal and external parties to ensure marketing objectives are aligned\nImplement marketing plans, projects and tasks assigned by the Management\u00a0\n\nRequirement\n\n\nDegree or above in marketing, business or related field\n\nMin. 5-8 years\u2019 working experience in marketing, preferably in Education sector\nExcellent command of written / spoken English and Chinese\nProven understanding of marketing best practices with a track record for developing growth marketing strategies that deliver tangible business results\nStrong business acumen and up to date with the latest trends in marketing technologies\nFamiliarity with traditional and emerging marketing channels\nStrong people skills and team-oriented approach\nProactive, positive, flexible, creative and open-minded\nGood understanding of the Hong Kong education system\nWilling to meet challenges and adaptative to change\n\nWe offer competitive salaries and benefits commensurate with experiences and qualifications.\n\nInterested party please apply with your full resume and expected salary.\n\nAll information received will be kept in strict confidential and only for employment-related purposes within our Bluetop Group of Companies. You may consider your application unsuccessful if you do not hear from us within 12 weeks.", "employment_types": ["Full Time", "Permanent"], "selling_points": ["Minimum 5 years relevant experience", "Strong business acumen", "5 days work week"], "locations": ["Ngau Tau Kok"], "categories": ["Education", "Others", "Marketing / Public Relations", "Management", "Marketing - Direct Marketing"], "post_time": "2022-01-10T06:13:20Z", "salary": {"currency": null, "max": null, "min": null, "period": "monthly", "term": null}, "salary_visible": false, "title_keywords": ["marketing manager"], "responsibilities": ["marketing plans", "budget", "quality", "social media platforms", "website", "internal and external parties", "promotion campaigns", "social media content", "maintain", "plan", "communications with", "monitor", "develop", "schedule", "marketing campaigns", "social media", "cost", "management", "marketing strategies", "tracking", "evaluate", "marketing materials"], "requirements": {"degrees": ["degree or above"], "majors": ["business", "marketing"], "languages": ["english", "chinese"], "language_level": ["excellent"], "hard_skills": ["acumen"], "soft_skills": ["flexible", "creative", "open-minded", "business acumen", "proactive", "positive"], "languages_combined": [{"language": "english", "language_level": ["excellent"]}, {"language": "chinese", "language_level": ["excellent"]}]}, "experience_required": {"duration": ["5-8 years"], "field": ["marketing", "education"]}}, {"job_id": "100003009048468", "location_code": "hk", "company": "WHARF CHINA ESTATES LIMITED \u4e5d\u9f8d\u5009\u4e2d\u570b\u7f6e\u696d\u6709\u9650\u516c\u53f8", "job_title": "SENIOR LEASING OFFICER (RETAIL)", "description": "The successful candidate will handle the leasing matters for prestigious retail properties in PRC, including liaison with international brands, local estate agents, formulating leasing strategy and conducting marketing research etc. Basically stationed in HK but travel to various PRC cities is necessary.\n\n\nApplicants should be a Degree holder in Business, Marketing, Real Estates or related disciplines with at least 6 years\u2019 solid experience in handling property leasing, legal documents as well as dealing with reputable brands and property management people independently. Experience in retail / property management projects in PRC an advantage while experience in marketing / business development will also be considered. Fluent Putonghua and English as well as good negotiation and interpersonal skills are required. Candidate with\u00a0less experience will be considered as Leasing Officer.\n\nWe offer competitive remuneration package that commensurate with experience and qualifications. \u00a0Interested parties are invited to send full resume stating contact telephone number, date available, present and expected salary to our recruitment email address.\u00a0\n\n(Personal data provided will be used strictly in accordance with the Company\u2019s personal data policy which is available upon request.)", "employment_types": ["Full Time", "Permanent"], "selling_points": ["Handle leasing of prestigious retail properties", "6 years' experience in retail leasing", "Degree holder in Business, Marketing, Real Estates"], "locations": ["Not Specified"], "categories": ["Sales, CS & Business Devpt", "Business Development", "Marketing / Public Relations", "Marketing - Direct Marketing", "Property / Real Estate", "Property Consultancy"], "post_time": "2022-01-15T03:49:59Z", "salary": {"currency": null, "max": null, "min": null, "period": null, "term": null}, "salary_visible": false, "title_keywords": ["senior leasing officer"], "responsibilities": ["marketing research", "management"], "requirements": {"degrees": ["degree holder"], "majors": ["related disciplines", "business", "marketing"], "languages": ["putonghua", "english"], "language_level": ["good", "fluent"], "hard_skills": [], "soft_skills": ["independently", "interpersonal skills", "negotiation"], "languages_combined": [{"language": "putonghua", "language_level": ["fluent", "good"]}, {"language": "english", "language_level": ["fluent", "good"]}]}, "experience_required": {"duration": ["at least 6 years"], "field": ["management", "legal", "related", "business development", "business", "marketing", "retail"]}}]