[{"job_id": "100003009053443", "location_code": "hk", "company": "Sunpower Production Limited", "job_title": "Senior Sales Executive, Sales & Marketing", "description": "\nJob Description\nResponsibilities:\n\u2022 Make outbound calls/ cold call to exploit business opportunities and increase market share.\n\u2022 Explore potential customers and maintain good relationships with key customers.\n\u2022 Sales-oriented with strong commitment towards sales target achievement.\n\u2022 Work closely with sales manager/ management to provide regular feedback for sales and services improvement.\n\u2022 Prepare sales reports, analysis and sales forecast.\n\u2022 Setting up meetings with potential clients.\n\u2022 Liaise with internal teams such as project management and design team.\nRequirements:\n\u2022 Work experience with technical background in Printing products/ Packaging Printing / Paper Products/ Telecommunications field is preferred.\n\u2022 Good command of writing and spoken English & Cantonese.\nFamiliar with MS Office (i.e. Excel, Word).\n\u2022 Good leaner, stable, good communication & negotiation skills.\n\u2022 Aggressive, proactive and hard working.\n\u2022 Applicants with more experience will be considered as Assistant Manager.\n\u2022 Newly graduated is welcome.\nWe offer basic salary plus commission based on sales accomplished.\nInterested parties, please send full resume with expected salary to Apply Now and Apply Now .\n*Personal data will be used for recruitment purpose only.\n\n", "employment_types": ["Full Time"], "selling_points": [], "locations": ["Not Specified"], "categories": ["Admin & HR", "Others", "Marketing / Public Relations", "Marketing - General / Support", "Others"], "post_time": "2022-01-17T06:59:52Z", "salary": {"currency": null, "max": null, "min": null, "period": "monthly", "term": null}, "salary_visible": false, "title_keywords": ["senior sales executive", "sales"], "responsibilities": ["management", "sales target", "business opportunities", "prepare sales", "analysis", "teams", "design", "project management", "maintain", "reports", "forecast", "liaise with"], "requirements": {"degrees": [], "majors": [], "languages": ["cantonese", "english"], "language_level": ["good command"], "hard_skills": ["excel", "word", "ms office"], "soft_skills": ["hard working", "communication", "negotiation skills", "stable", "proactive"], "languages_combined": [{"language": "cantonese", "language_level": ["good command"]}, {"language": "english", "language_level": ["good command"]}]}, "experience_required": {"duration": [], "field": ["telecommunications"]}}, {"job_id": "100003009055112", "location_code": "hk", "company": "Autotoll Limited", "job_title": "Marketing and Communications Officer (PR/ Promotion focus)", "description": "About The Role:\n\nAssist the team in planning, monitoring and implementing all marketing-related campaigns for a newly granted Government contract, including but not limited to brand building campaign, publicity and public relations activities.\nPrepare marketing reports, analysis, proposals & presentations for internal & external parties.\nWrite, edit and disseminate a variety of communications including press releases, App & website content, newsletter, social media and online feeds.\nHandle the public enquiries and complaints from stakeholders.\nWork with PR agencies in the planning and execution of public engagement activities, including but not limited to press conferences, seminars, roadshows etc. or\nWork with creative or digital agencies/ designers in the production of marketing materials and social content, including but not limited to video, copywriting, sound bite, print/ digital ads, poster, flyer etc. AND Development of digital campaign for the new acquisition\n\nAbout You:\n\nBachelor\u00a0Degree in Marketing, Communication, Public Relations or related disciplines.\nAt least 2 years\u2019 relevant work experience preferably in the fields of marketing communications / public relations / advertising/ digital marketing.\nProactive, independent with excellent time management skills and ability to work under pressure.\nGood proficiency both in written and spoken English and Chinese.\nKnowledge/ experience in automotive industry is a plus.\u00a0\n\nWhat you can get from us:\n\nOn-the-job training, learning and development provided\nExecutive workshops, interest class, corporate purchase discount offered by SHKP\nCompetitive salary and annual leaves\nFlexible working opportunities\n\nInterested parties, please send full resume with\u00a0expected salary\u00a0and\u00a0available date\u00a0to Human Resources and Administration Department by e-mail or by fax 2111 9459.\n\n(Data collected will be used for recruitment purpose only.)", "employment_types": ["Full Time", "Permanent"], "selling_points": ["Degree holder with 2 year + exp.", "Knowledge/ experience in automotive industry", "5-day work, bank holiday, AL & medical plan"], "locations": ["Kowloon Bay"], "categories": ["Marketing / Public Relations", "Marketing - General / Support", "Public Relations - General / Support", "Others"], "post_time": "2022-01-18T01:15:16Z", "salary": {"currency": null, "max": null, "min": null, "period": "monthly", "term": null}, "salary_visible": false, "title_keywords": ["communications officer"], "responsibilities": ["social media", "management", "advertising", "work under pressure", "analysis", "monitoring", "external parties", "website", "presentations", "communication", "conferences", "purchase", "reports", "digital marketing", "marketing materials", "planning"], "requirements": {"degrees": ["degree", "bachelor"], "majors": ["related disciplines", "marketing"], "languages": ["english", "chinese"], "language_level": ["proficiency", "good"], "hard_skills": ["workshops", "analysis", "presentations", "plus"], "soft_skills": ["flexible", "proactive", "independent", "time management skills", "communication", "learning", "creative", "work under pressure"], "languages_combined": [{"language": "english", "language_level": ["proficiency", "good"]}, {"language": "chinese", "language_level": ["proficiency", "good"]}]}, "experience_required": {"duration": ["at least 2 years"], "field": ["automotive industry", "public relations", "advertising", "marketing communications", "digital marketing"]}}, {"job_id": "100003009053589", "location_code": "hk", "company": "Guidepoint Global Hong Kong Limited", "job_title": "Regional Marketing Coordinator", "description": "\nThis position can be based in Hong Kong or Singapore.\nOverview:\nGuidepoint\u2019s growing Marketing team is responsible for building and expanding the Guidepoint brand. As the storytellers of Guidepoint, the Marketing team executes marketing plans that generate leads, nurture existing clients, and raise overall brand awareness within our 3 main audiences; clients, advisors and employees.\nThe Regional Marketing Coordinator works as part of a regional and global Marketing team to execute marketing and communications initiatives for our offices across the APAC Region, including Hong Kong, Shanghai, Singapore, Mumbai, Sydney, Tokyo and Seoul.\nWhat You\u2019ll Do:\n\u2022 Work closely with the Regional Marketing Manager to plan and execute a marketing, communications and PR strategy to grow brand awareness and boost our business in offices across the APAC region.\n\u2022 Coordinate with the global Marketing and Design teams to run integrated programs including content marketing, thought leadership, lead generation, and digital and social media\n\u2022 Create and market press releases to key social and traditional media outlets relevant to our client base\n\u2022 Support the organization of engaging client events\n\u2022 Develop targeted email campaigns in coordination with the Sales and Client Service teams\n\u2022 Further develop existing sales collateral, marketing materials and client presentations\nWhat You Have:\nBachelor's degree required (Marketing, Communications, English, and/or Business major a plus)\n\u2022 1-3 years\u2019 experience in global B2B marketing, PR and/or communications with experience in digital marketing\n\u2022 A desire to work in a fast-paced, entrepreneurial environment\u2014willing to build up this broad-ranged function and to contribute to the continued success of Guidepoint\n\u2022 A consultative approach with a strategic vision and sense for innovative marketing solutions\n\u2022 Demonstrated skills, knowledge and experience in the execution of creative marketing, including direct mail, email marketing, and full-scale campaigns\n\u2022 Must have both solid writing & interpersonal skills; aptitude for numbers\n\u2022 Working knowledge of Adobe Creative Cloud, Salesforce, and Pardot recommended\n\u2022 Fluency in English and Chinese is essential; knowledge of an additional Asian language such as Japanese or Korean is a plus\nWhat We Have:\n\u2022 Competitive compensation\n\u2022 Entrepreneurial environment, autonomy and fast decisions\n\u2022 Casual work environment and compelling people\n\u2022 Flexible work arrangement\n\u2022 Centrally located office\nInterested parties please click Apply Now to apply job.\n\n", "employment_types": ["Full Time"], "selling_points": [], "locations": ["Not Specified"], "categories": ["Admin & HR", "Others", "Marketing / Public Relations", "Marketing - General / Support", "Others"], "post_time": "2022-01-17T07:12:46Z", "salary": {"currency": null, "max": null, "min": null, "period": "monthly", "term": null}, "salary_visible": false, "title_keywords": ["marketing coordinator"], "responsibilities": ["social media", "communications with", "marketing plans", "coordination with", "teams", "coordinate with", "design", "develop", "presentations", "client base", "digital marketing", "plan", "marketing materials"], "requirements": {"degrees": ["degree", "bachelor"], "majors": ["business", "marketing", "communications"], "languages": ["japanese", "english", "chinese", "korean"], "language_level": ["fluency"], "hard_skills": ["plus", "adobe", "salesforce", "presentations"], "soft_skills": ["flexible", "creative", "responsible", "interpersonal skills", "coordination", "innovative", "leadership"], "languages_combined": [{"language": "japanese", "language_level": []}, {"language": "english", "language_level": ["fluency"]}, {"language": "chinese", "language_level": ["fluency"]}, {"language": "korean", "language_level": []}]}, "experience_required": {"duration": ["1-3 years"], "field": ["pr", "marketing", "digital marketing"]}}, {"job_id": "100003009055053", "location_code": "hk", "company": "The Hong Kong Jockey Club", "job_title": "Public Affairs Support Manager (Social Media)", "description": "The Job\nYou will:\n\nAssist in the development of the Club\u2019s Corporate and Charities social media strategy to raise the Club\u2019s online presence on social media platforms\nassist to manage and monitor designated Club social media accounts, including the development of social media content (e.g. copy-writing, graphic and video production), and coordination with various Club divisions on shared content posting; maintenance of a content calendar\norganise regular social media campaigns to support corporate and charities communications' publicity effort, and drive engagement, reach and viewership\nassist to manage issues, handle enquiries, develop line-to-take\ngenerate regular performance analysis reports\nprovide support in developing corporate and charities communications material for internal & external stakeholders\n\nAbout You\nYou should have:\n\nuniversity degree in a related discipline or relevant qualification, with a minimum of 8 years' experience\nGood knowledge about HK's social-political and media scenes, especially social media\nproven experience in social media management\nexperience and knowledge in managing and developing content for corporate social media accounts\nself-motivated, strong critical and analytical mind\nhigh level of proficiency in written and spoken English and Chinese\nhands-on experience of using MS office, Word, Excel and Power Point.\n\nTerms of employment\nThe level of appointment will be commensurate with qualifications and experience.\n\nHow to Apply\nPlease send your resume, complete with expected salary and job reference by clicking the Apply Now button.", "employment_types": ["Full Time", "Permanent"], "selling_points": ["Proven experience in social media management", "Experience in corporate social media accounts", "Organise regular social media campaigns"], "locations": ["Causeway Bay"], "categories": ["Media & Advertising", "Others", "Marketing / Public Relations", "Others"], "post_time": "2022-01-18T00:58:07Z", "salary": {"currency": null, "max": null, "min": null, "period": null, "term": null}, "salary_visible": false, "title_keywords": ["public affairs support manager"], "responsibilities": ["social media", "provide support", "management", "maintenance", "social media campaigns", "video production", "analysis reports", "social media platforms", "monitor", "coordination with", "developing", "develop", "handle enquiries", "social media content"], "requirements": {"degrees": ["university degree"], "majors": [], "languages": ["english", "chinese"], "language_level": ["proficiency"], "hard_skills": ["excel", "maintenance", "analysis", "word", "power point", "ms office"], "soft_skills": ["hands-on", "self-motivated", "analytical mind", "coordination"], "languages_combined": [{"language": "english", "language_level": ["proficiency"]}, {"language": "chinese", "language_level": ["proficiency"]}]}, "experience_required": {"duration": ["minimum of 8 years"], "field": ["related", "social media", "management", "developing"]}}, {"job_id": "100003009053644", "location_code": "hk", "company": "United Asia Finance Limited", "job_title": "Senior Officer, Digital Marketing", "description": "Job Responsibilities:\n\nFormulate and implement content marketing strategy and campaigns to drive online awareness, lead generation and engagement for the various corporate events and public mission initiatives\nDevelop engaging content and assure content excellence for marketing channels including website, blogs and social media platforms\nDevelop and implement social media plans and explore tactics to penetrate brand image to young segment\nDraw traffic to various social media accounts and drive engagement rate and number of fans\nKeep abreast of the latest development, tactics, and policy of various social media channels\nMake use of social media analytics and social listening tools to timely optimize the effectiveness of digital campaigns and engagement effort\nCreate high quality video contents including ideation and script writing to maximize engagement on digital platforms\nWork with designers to produce impactful and attractive visual and design for various public mission initiatives and campaigns\nManage quality assurance for creative and video production output\n\nJob Requirements:\n\nBachelor\u2019s degree or above in Business, Marketing, Communications, Digital Marketing or equivalent\nMinimum five years or above relevant experience in social media marketing, brand management, digital marketing\nTrack records in developing and implementing impactful social media marketing campaigns and promotions (Instagram, Facebook, YouTube)\nExperienced in managing internal/external social media and video production team/KOL/Youtubers\nHighly flexible work style to respond to the dynamic and rapidly changing environment\nWell versed in social media analytics tools, deployment of SEO and website CMS platforms\nCreative, Pro-active, open-minded, and result-oriented\nExcellent interpersonal and communications skills with a strong command in both written and spoken English and Chinese\n\nWe offer attractive remuneration package which includes double pay and discretionary bonus. Interested parties please send your CV indicating your current salary, expected salary and availability to HR Department, by email via \"Apply Now\"\n\n(Personal data collected will be treated in the strictest confidence and will be handled by authorized personnel for recruitment-related purposes only. Applicants who do not hear from us within 3 months may consider their application unsuccessful and their data will be destroyed within 24 months of receipt.)", "employment_types": ["Full Time", "Permanent"], "selling_points": ["Bachelor\u2019s degree or above in Business", "5 years or above relevant experience", "Double pay and Discretionary bonus"], "locations": ["Wan Chai"], "categories": ["Marketing / Public Relations", "Public Relations - General / Support", "Others", "Digital Marketing"], "post_time": "2022-01-17T07:16:57Z", "salary": {"currency": null, "max": null, "min": null, "period": "monthly", "term": null}, "salary_visible": false, "title_keywords": ["senior officer", "digital marketing"], "responsibilities": ["social media", "video production", "social media platforms", "quality", "website", "design", "develop", "visual", "digital campaigns", "contents", "plans"], "requirements": {"degrees": ["degree or above", "bachelor"], "majors": ["business", "digital marketing", "communications", "marketing"], "languages": ["english", "chinese"], "language_level": ["excellent"], "hard_skills": ["analytics tools", "seo", "dynamic", "deployment", "facebook"], "soft_skills": ["flexible", "interpersonal", "open-minded", "dynamic", "pro-active", "creative", "result-oriented"], "languages_combined": [{"language": "english", "language_level": ["excellent"]}, {"language": "chinese", "language_level": ["excellent"]}]}, "experience_required": {"duration": ["minimum five years"], "field": ["social media", "management", "brand", "marketing", "relevant experience", "digital marketing"]}}, {"job_id": "100003009055902", "location_code": "hk", "company": "The University of Hong Kong", "job_title": "Senior Manager / Manager (at the rank of Administrative I/II)", "description": "Senior Manager (Communications and News / Digital Specialist / Marketing and Events) (at the rank of Administrative Assistant I) and Manager (Marketing and Events) (at the rank of Administrative Assistant II) in the Communications and Public Affairs Office of the Registry (Ref.: 511288)\u00a0\n\nThe Communications and Public Affairs Office (CPAO) of the Registry of the University of Hong Kong (HKU) strengthens the reputation of University through a range of strategies including media relations and digital communications. \u00a0The Office is also responsible for University events and ceremonies, publications, both external and internal communications, crisis management and community engagement. \u00a0CPAO is currently elevating and expanding its scope of services. We are looking for talented candidates to join the team.\n\nThe key responsibilities of the Senior Manager (Communications and News / Digital Specialist) of CPAO are to:\n\nsupport the Director and the Assistant Director in engaging and building rapport with both local and international media; create multimedia content, conduct interviews and write-ups;\nhandle media enquiries, draft and edit media releases, organise media events, press conferences and media interviews;\nhelp develop a digital portal and take up the role as the Editor; and\ncoordinate the University\u2019s websites revamp and liaise with users and stakeholders on the sitemap, navigation and design etc.\n\nThe key responsibilities of the Senior Manager / Manager (Marketing and Events) are to:\n\nsupport the Director and the Assistant Director in the development and execution of effective corporate marketing, branding and community engagement plans;\ncoordinate the University branding exercise;\norganise University ceremonies, including Congregation, inaugural lectures, awards presentations, visits, and others;\nmanage the official online and print publications of the University; and\nimplement marketing and community engagement programmes.\n\nFor the above posts, we expect the applicants to have:\n\na good bachelor\u2019s degree in a relevant discipline;\nat least eight years\u2019 relevant experience, with at least three years in a managerial position for consideration of appointment as Senior Manager; or at least five years\u2019 relevant experience, with at least two years in a supervisory position for consideration of appointment as Manager;\nthe ability to manage fast-moving projects and collaborate with internal and external cross-functional teams in a complicated environment;\nexperience in Higher Education as a plus;\na good command of English and Chinese;\nan excellent command of web technologies, social media platform trends, data analytics for marketing; and\na willingness to work outside regular work hours and on duty roster.\n\nThe appointment will be made from as soon as possible, on a three-year fixed-term basis for the Senior Manager post and on a two-year fixed-term basis for the Manager post, with a possibility of renewal.\n\nA highly competitive salary commensurate with qualifications and experience will be offered. The appointments carry leave and medical/dental benefits. \u00a0The appointment will attract a contract-end gratuity and University contribution to a retirement benefits scheme, totalling up to 15% of basic salary for Senior Manager post and up to 10% of basic salary for Manager post.\n\nThe University only accepts online application for the above posts. \u00a0Applicants should apply online at the University\u2019s careers site (https://jobs.hku.hk) and upload an up-to-date C.V. \u00a0Review of application will commence as soon as possible and continue until February 16, 2022.\u00a0\n\nThe University is an equal opportunities employer\nand is committed to equality, ethics, inclusivity, diversity and transparency", "employment_types": ["Full Time"], "selling_points": ["Bachelor's degree", "at least 8 years' work experience", "annual leave and medical benefits"], "locations": ["Pok Fu Lam"], "categories": ["Marketing / Public Relations", "Others"], "post_time": "2022-01-18T03:04:03Z", "salary": {"currency": null, "max": null, "min": null, "period": "monthly", "term": null}, "salary_visible": false, "title_keywords": ["senior manager", "manager"], "responsibilities": ["collaborate with", "social media", "revamp", "data", "design", "develop", "coordinate", "presentations", "conferences", "cross-functional teams", "liaise with", "plans", "crisis management"], "requirements": {"degrees": ["degree", "bachelor"], "majors": [], "languages": ["english", "chinese"], "language_level": ["good command"], "hard_skills": ["plus", "data analytics", "presentations", "multimedia", "web technologies"], "soft_skills": ["responsible", "willingness to work"], "languages_combined": [{"language": "english", "language_level": ["good command"]}, {"language": "chinese", "language_level": ["good command"]}]}, "experience_required": {"duration": ["at least five years", "at least two years", "at least three years", "at least eight years"], "field": ["managerial", "supervisory", "relevant experience", "education"]}}, {"job_id": "100003009055501", "location_code": "hk", "company": "The University of Hong Kong", "job_title": "Project Associate (2 posts)", "description": "Ref: SMD014/22,\u00a05125/JDB/100122\nJob Description\nWho we are looking for:\nCreativity in new ideas and future focus vision.\u00a0\nCollaboration with colleagues and the community at large.\nWork Smart, Play Smart!\nWhat you'll do:\nConduct design, development and evaluation of High Entropy Alloys\u00a0fabrication process, equipment, tooling, mechanism\nConduct R&D works on metals processing, machining, stamping and other forming technology\nAssist to provide consultancy service on metals processing\u00a0\nAssist to compile technological guide books and articles\nSupport commercialization and promotion of new technologies and service solutions\nOrganize and market new technology local and overseas training, seminars, conference, study missions, exhibitions and other technology dissemination events\nTravel to Mainland China and overseas occasionally for project implementation and new technology study\nSupport ad hoc projects and assignments when required\nYou'll be a good fit if you have/are:\nBachelor/Master degree in mechanical engineering, manufacturing engineering, or related discipline from a local university\nKnowledge and skill in metal processing, sintering, casting and/or other related experience.\nWorking experience in technology research and development preferred\nGood presentation, communication and interpersonal skills\nMature, self-motivated, confident and able to work under pressure\nGood command of English, Cantonese and Putonghua.\u00a0\nNote:\n1. Applicant may be considered for other positions if not matching the requirements of the subject position.\n2. This is a position funded by the Research Talent Hub Programme under the Innovation and Technology Fund (ITF) to conduct R&D project from January 2022 to April 2023.\nWhat we offer and What you\u2019ll like here:\nInnovative and energetic culture with smart outfits and sport shoes\nProfessional lab and latest technology to actualize your creative ideas\n5-day work week\u00a0\nPrime location with good public transport network\nDental benefit\nMedical benefits from Day-1 with extended coverage to dependent(s)\nProfessional training and career advancement opportunities\nApply now if you\u2019re ready to take the challenge! \u00a0Do not miss this opportunity to join us to Create Value and \u201cMAKE SMART SMARTER\u201d!\u00a0\u00a0\nHKPC will take into consideration both the quantitative and qualitative requirements of the position when selecting the suitable candidates.\u00a0 A competitive salary package commensurate with academic qualifications and experience will be offered.\u00a0The successful candidates will be employed on a fixed-term contract basis, which is renewable subject to appointee\u2019s performance and the Council\u2019s development needs.\nApplicants are welcome to\u00a0submit application\u00a0at the HKPC e-Recruitment System (careers.hkpc.org) in 1\u00a0week\u00a0from the posting date.\u00a0 Recruitment will continue until the position is filled.\u00a0\u00a0\nPersonal data collected will be used for recruitment purpose only. Candidates not invited for interviews within 6 weeks may consider their applications unsuccessful and the applications will be disposed by HKPC within 12 months.", "employment_types": ["Full Time"], "selling_points": ["Will assist in organizing events", "Perform any other duties as assigned", "Recognized Bachelor\u2019s degree in any discipline"], "locations": ["Pok Fu Lam"], "categories": ["Education", "Others", "Marketing / Public Relations", "Public Relations - Event Management", "Others"], "post_time": "2022-01-18T02:39:47Z", "salary": {"currency": null, "max": null, "min": null, "period": "monthly", "term": null}, "salary_visible": false, "title_keywords": ["associate"], "responsibilities": ["ideas", "implementation", "design", "communication", "commercialization", "ad hoc projects", "evaluation", "work under pressure"], "requirements": {"degrees": ["bachelor", "master degree"], "majors": ["manufacturing", "engineering", "mechanical engineering"], "languages": ["cantonese", "putonghua", "english"], "language_level": ["good command"], "hard_skills": ["r&d", "focus", "processing"], "soft_skills": ["confident", "self-motivated", "mature", "communication and interpersonal skills", "work smart", "focus", "presentation", "work under pressure"], "languages_combined": [{"language": "cantonese", "language_level": ["good command"]}, {"language": "putonghua", "language_level": ["good command"]}, {"language": "english", "language_level": ["good command"]}]}, "experience_required": {"duration": [], "field": ["related", "development", "research"]}}, {"job_id": "100003009053968", "location_code": "hk", "company": "Gain Miles Assurance Consultants Limited", "job_title": "Assistant Manager \u2013 Content Marketing", "description": "Job Duties:\n\nAssist in assessment of the funding applications and perform initial check of final reports from the grantees and prepare relevant documents required for funding disbursement\nSupport project work and on-site checking of funded projects, liaise with applicants and arrange meetings\n\nJob Requirements:\n\nDegree holder in Business, Engineering, Science subject or related discipline\n2 years\u2019 full time administrative / customer service experience is preferred\nGood command of English and Cantonese\n\n\nApplicants are welcome to submit application quoting the Ref. No. with your availability and expected salary by clicking \"Apply Now\". Recruitment will continue until the openings are filled.\n\nPersonal data collected will be used for recruitment purpose only. Candidates not invited for interviews within 6 weeks may consider their applications unsuccessful and the applications will be disposed by HKPC within 12 months.", "employment_types": ["Full Time", "Permanent"], "selling_points": ["Content marketing", "financial service", "marketing channels"], "locations": ["Not Specified"], "categories": ["Marketing / Public Relations", "Marketing - Direct Marketing", "Public Relations - Event Management", "Others"], "post_time": "2022-01-17T07:51:55Z", "salary": {"currency": null, "max": null, "min": null, "period": "monthly", "term": null}, "salary_visible": false, "title_keywords": ["assistant manager"], "responsibilities": ["liaise with", "arrange meetings", "reports", "checking"], "requirements": {"degrees": ["degree holder"], "majors": ["science", "business", "engineering"], "languages": ["cantonese", "english"], "language_level": ["good command"], "hard_skills": ["no"], "soft_skills": ["customer service"], "languages_combined": [{"language": "cantonese", "language_level": ["good command"]}, {"language": "english", "language_level": ["good command"]}]}, "experience_required": {"duration": ["2 years"], "field": ["administrative", "customer service"]}}, {"job_id": "100003009047694", "location_code": "hk", "company": "Luk Fook Holdings Company Limited", "job_title": "Assistant Marketing Officer", "description": "If you are a driver of innovation with energetic and outgoing personality; hungry to learn about hospitality with positive and proactive mindset; and looking for an environment where you can further develop yourself, then DON\u2019T miss this opportunity to join us!\u00a0\n\nThe Job\n\nTake ownership of developing sales pipeline, building and marketing all size deals\nLead generation and prospecting, including but not limited to cold calling, business partners/ customers pitching and networking\nTour and demonstrate our locations and business solutions with potential business partners/ customers\nProvide professional advice on marketing positioning and translate strategies into business results\nPerform ad-hoc projects as and when needed\nMore experiences will be considered as Sales Accounting Manager\nWork location: Causeway Bay / Kowloon City\n\nThe Person\n\nDegree holder in Business, Sales & Marketing or related disciplines\nAt least 3 years of B2B sales & business development experiences\nAbility to identify new markets and establish cohesive relationships with potential business partners/customers\nProactive, presentable with excellent organization and communication skills\nProficiency in both written/spoken English and Chinese, including Mandarin\n\nWhat We Offer\n\nOpportunity to take on responsibility from day one and have a direct impact on our business growth\nExposure to every area of startup building from business operations and marketing to management\nA great collaborative working atmosphere\nCareer advancement\n\nWhat You Need To Do\nIf you have the drive to succeed and have a passion for exploring and working with us, please send your cover letter and full resume with current and expected salary by clicking \"Apply Now\".\u00a0 \u00a0\u00a0\n", "employment_types": ["Full Time"], "selling_points": ["At least 3-year solid experience in marketing", "Excellent interpersonal and communications skills", "Candidates with PR background is highly desirable"], "locations": ["Shatin Area"], "categories": ["Marketing / Public Relations", "Management", "Marketing - Direct Marketing", "Others"], "post_time": "2022-01-14T03:46:24Z", "salary": {"currency": null, "max": null, "min": null, "period": "monthly", "term": null}, "salary_visible": false, "title_keywords": ["assistant marketing officer"], "responsibilities": ["ad-hoc projects", "developing"], "requirements": {"degrees": [], "majors": [], "languages": [], "language_level": [], "hard_skills": [], "soft_skills": [], "languages_combined": []}, "experience_required": {"duration": [], "field": []}}, {"job_id": "100003009053518", "location_code": "hk", "company": "Chinese Bible International Limited", "job_title": "Marketing & Sales Manager", "description": "Job Responsibilities\n\nDevelop brand and marketing strategy for the core medical brand(s) and drive the implementation to enhance brand equity and increase market penetration;\nBuild relationship with medical professionals for brand growth opportunities, including awareness building, lead generation and partnership liaison;\nEstablish partnerships with local and global patient peer groups for brand growth opportunities, including patient community engagement;\nPlan and manage B2B and B2C events, including participating or, if necessary, organizing conference, seminars, webinars;\nDevelop master sales & marketing communication assets and ensure proper adaptation and usage of the materials;\nWork closely with media (esp. news outlets) and agencies for media plan development and execution, including social media, SEM, display ad, PR (including interviews and advertorials);\nLead content development for website and social platforms;\nDevelop CRM plan and enhance the existing membership loyalty program;\nPartner with sales team to gain market insights and sharpen sales conversion tactics;\nLiaise with universities for both regular marketing activities and long-term strategic partnership.\n\nRequirements\n\nBachelor\u2019s Degree in Science or Business; Pharmacy or Medical related discipline is a plus;\n3 years of marketing experience in pharmaceutical industry; particularly in ethical channel is a plus;\nFluent in spoken and written English and Chinese;\nOpen-minded attitude and creativity to bring in new initiatives;\nStrong branding mindset and strategic thinking for long-term brand development;\nStrong desire to learn and ability to multi-task;\nGood communication and interpersonal skills;\nProficient in Microsoft Office (Excel, PowerPoint, Outlook).\n\nWorking Location: Hong Kong Science Park, Tai Po, N.T.\n\nWe offer 5-day working week and an attractive remuneration package. Interested party please submit your resume with current and expected salary by clicking \u201cAPPLY NOW\u201d. For company details, please visit\u00a0www.purapharm.com.\n\nOur company is an equal opportunity employer. All personal data collected will be used for recruitment purpose only, while the personal data of the unsuccessful applicants will be destroyed within 6 months after the recruitment process.", "employment_types": ["Full Time"], "selling_points": [], "locations": ["Not Specified"], "categories": ["Admin & HR", "Others", "Marketing / Public Relations", "Marketing - General / Support", "Others"], "post_time": "2022-01-17T07:05:15Z", "salary": {"currency": null, "max": null, "min": null, "period": "monthly", "term": null}, "salary_visible": false, "title_keywords": ["sales manager"], "responsibilities": ["social media", "implementation", "website", "develop", "communication", "sales team", "plan", "sem", "liaise with"], "requirements": {"degrees": ["degree", "bachelor"], "majors": ["science", "business"], "languages": ["english", "chinese"], "language_level": ["fluent"], "hard_skills": ["excel", "plus", "microsoft office", "powerpoint", "outlook"], "soft_skills": ["multi-task", "strategic thinking", "open-minded", "communication and interpersonal skills", "ethical"], "languages_combined": [{"language": "english", "language_level": ["fluent"]}, {"language": "chinese", "language_level": ["fluent"]}]}, "experience_required": {"duration": ["3 years"], "field": ["pharmaceutical", "marketing"]}}, {"job_id": "100003009047841", "location_code": "hk", "company": "Ecolab Limited", "job_title": "Assistant Marketing Manager", "description": "Smart Manufacturing Division\nRef:\u00a0SMD409/21,\u00a04866/JDB/040122\nJob Description\nWho we are looking for:\nCreativity in new ideas and future focus vision.\u00a0\nCollaboration with colleagues and the community at large.\nWork Smart, Play Smart!\nWhat you'll do:\nTo provide industrial consultancy services and implement government-funded and consultancy projects on Industry 4.0 (i4.0), intelligent manufacturing and reindustrialization related smart enabling solutions adoption, such as Digital Lean, Machine Connectivity via IIoT, Human Machine interface (HMI), Smart Data Analytics, Cyber Physical Production System (CPPS), etc.\nTo formulate government project proposals on i4.0 enabling technology development, reindustrialization, manufacturing upgrading and industrial applications.\nTo conduct R&D work in development of i4.0 enabling technology solution such as Blockchain, Industrial Drone, Smart Logistics, Sensor applications\nOrganize and deliver training and marketing activities such as overseas study missions, international conferences, technical seminars, workshops, etc.\nTo travel over GBA on a regular basis for consultancy projects\nYou'll be a good fit if you have/are:\nBachelor Degree from engineering disciplines such as Industrial and System Engineering, Manufacturing Engineering, Data/Computer Science, or equivalent. Candidate with top up master degree on Information and Communication Technology preferred\nAt least two years\u2019 or more relevant experience in manufacturing operations, particularly in the technical area of digital manufacturing knowledge/solutions\nSounds knowledge on i4.0, intelligent manufacturing, reindustrialization, advanced digital tools and enabling technologies for digital manufacturing a definitely advantage\nStrong commitment to task outcome, mature, independent, self-initiated, proactive and good team player\nExcellent analytical, presentation, communication and interpersonal skills\nExcellent command of English, Cantonese and Putonghua\nNote:\nApplicant may be considered for other positions if not matching the requirements of the subject position.\nWhat we offer and What you\u2019ll like here:\nInnovative and energetic culture with smart outfits and sport shoes\nProfessional lab and latest technology to actualize your creative ideas\n5-day work week\u00a0\nPrime location with good public transport network\nMPF Top-up and dental benefit\nMedical benefits from Day-1 with extended coverage to dependent(s)\nProfessional training and career advancement opportunities\nApply now if you\u2019re ready to take the challenge! \u00a0Do not miss this opportunity to join us to Create Value and \u201cMAKE SMART SMARTER\u201d!\u00a0\u00a0\nHKPC will take into consideration both the quantitative and qualitative requirements of the position when selecting the suitable candidates.\u00a0 A competitive salary package commensurate with academic qualifications and experience will be offered.\u00a0\nApplicants are welcome to\u00a0submit application\u00a0at the HKPC e-Recruitment System (careers.hkpc.org) in 1\u00a0week\u00a0from the posting date.\u00a0 Recruitment will continue until the position is filled.\u00a0\u00a0\nPersonal data collected will be used for recruitment purpose only. Candidates not invited for interviews within 6 weeks may consider their applications unsuccessful and the applications will be disposed by HKPC within 12 months.", "employment_types": ["Full Time", "Permanent"], "selling_points": ["MNC and Fortune Global 500", "Excellent Career Opportunity", "Market Leader in Food Safety and Water Treatment"], "locations": ["Kwun Tong"], "categories": ["Marketing / Public Relations", "Marketing - Brand / Product Management", "Marketing - General / Support", "Others"], "post_time": "2022-01-14T04:01:14Z", "salary": {"currency": null, "max": null, "min": null, "period": "monthly", "term": null}, "salary_visible": false, "title_keywords": ["assistant marketing manager"], "responsibilities": ["ideas", "data", "operations", "communication", "conferences", "logistics"], "requirements": {"degrees": ["degree", "bachelor", "master degree"], "majors": ["system engineering", "manufacturing", "engineering", "computer science"], "languages": ["cantonese", "putonghua", "english"], "language_level": ["excellent"], "hard_skills": ["r&d", "blockchain", "lean", "data analytics", "workshops", "focus"], "soft_skills": ["good team player", "independent", "advanced", "mature", "communication", "communication and interpersonal skills", "work smart", "focus", "proactive", "presentation"], "languages_combined": [{"language": "cantonese", "language_level": ["excellent"]}, {"language": "putonghua", "language_level": ["excellent"]}, {"language": "english", "language_level": ["excellent"]}]}, "experience_required": {"duration": ["at least two years"], "field": ["digital", "manufacturing", "relevant experience"]}}, {"job_id": "100003009050977", "location_code": "hk", "company": "Hong Kong Science & Technology Parks Corporation", "job_title": "Assistant Manager, Intelligence Research [JDB/AMIR/220114]", "description": "We are looking for a seasoned senior leader who is passionate to join the largest Innovation and Technology eco-system in Hong Kong.\u00a0 The successful incumbent shall possess strong leadership to lead and drive the team to ideate, plan and implement high level flagship events, conferences, exhibitions, community engagement programme and new business initiatives to support the continuous growth of the Corporation and to elevate the vibrancy and diversity of the Science Park community.\u00a0 He / she has to be a strategic thinker and planner, a great problem solver, and is goal getting, result driven, innovative, co-creative, energetic, collaborative, enthusiastic; and bold to tackle and overcome challenges to deliver remarkable results.\nResponsibilities:\nIdeating, content curating, brand positioning, budgeting, planning, promoting and managing high-quality and influential B2B & B2C events to achieve the Corporate objectives\nLead and drive the team to meet and even exceed targeted goals, accomplish high quality and remarkable outcomes and manage to propose and make strategical, timely and decisive directions and changes in the dynamic environment\nMaster impactful marketing and promotional assets; research, analyse, interpret and present latest marketing trend and data in a world perspective\nStrategically plan and deliver engagement initiatives to build a vibrant and actively engaging community among the partner companies in the Science Park eco-system\nContent curate and manage digital platforms including websites and social media for specified events and programmes\nPerform any other duties as assigned by supervisors\nRequirements:\nBachelor degree in Business Administration, Marketing, Communication or other related disciplines\n10 years relevant experience in event marketing and management, preferably gained in sizable / MNC corporations with at least 3 years of solid team leadership\nProven track record in ideating, content curating and managing high level, large-scale & impactful events, and mastering professional, trendy and effective marketing promotional assets\nStrong business sense, thorough understanding of the latest world marketing trend and rich experience in digital and content marketing\nStrong leadership demonstration of tackling challenges, accomplishing remarkable results and growing the team\nInnovative, idea-driven, goal-getting, dynamic, self-motivated, detailed-oriented and is able to work under tight schedule\nProficient in both verbal and written English and Chinese, including Cantonese and Putonghua\nStrong industry network with excellent interpersonal and communications skills\nWe offer market competitive compensation, 5-day work week, and generous benefits including medical and life insurance; and voluntary contribution in addition to the legal minimum MPF.\u00a0 To apply, please send your full resume with current and expected salary to the Human Resources & Office Administration Department, Hong Kong Science and Technology Parks Corporation, 5/F, Building 5E, 5 Science Park East Avenue, Hong Kong Science Park, Hong Kong or, by email via \"Apply Now\"\u00a0on or before 27 January 2022.\u00a0 \u00a0Please quote the reference number on the email subject/envelope and the application letter.\u00a0\nPersonal data provided will be treated in strict confidence and used for recruitment purpose only.\u00a0 All personal data collected will be used strictly in accordance with employer\u2019s personal data policies, you can access to HKSTP\u2019s Personal Information Collection Statement at https://www.hkstp.org/hkstp_web/en/hkstp/personal-information-collection-statement-recruitment\nApplicants not invited for interview within four weeks after application deadline may consider their applications unsuccessful.\u00a0 Personal data of unsuccessful applicants will be retained for a maximum of two years.\u00a0\nwww.hkstp.org", "employment_types": ["Full Time"], "selling_points": [], "locations": ["Shatin Area"], "categories": ["Marketing / Public Relations", "Management", "Marketing - Market Research", "Others"], "post_time": "2022-01-14T12:24:06Z", "salary": {"currency": null, "max": null, "min": null, "period": "monthly", "term": null}, "salary_visible": false, "title_keywords": ["assistant manager,"], "responsibilities": ["social media", "any other duties", "data", "budgeting", "quality", "planning", "marketing trend", "plan", "analyse"], "requirements": {"degrees": ["degree", "bachelor"], "majors": ["related disciplines", "marketing", "business administration"], "languages": ["cantonese", "putonghua", "english", "chinese"], "language_level": ["proficient"], "hard_skills": ["goal", "dynamic"], "soft_skills": ["self-motivated", "business sense", "interpersonal", "communication", "dynamic", "thorough", "innovative", "leadership", "driven", "detailed"], "languages_combined": [{"language": "cantonese", "language_level": []}, {"language": "putonghua", "language_level": []}, {"language": "english", "language_level": ["proficient"]}, {"language": "chinese", "language_level": ["proficient"]}]}, "experience_required": {"duration": ["at least 3 years", "10 years"], "field": ["management", "business", "marketing", "relevant experience", "digital", "team"]}}, {"job_id": "100003009051949", "location_code": "hk", "company": "OSIM (HK) Co. Limited", "job_title": "Digital Marketing Executive ( 5 Days Work)", "description": "Responsibilities:\n\u00a0In view of the rapid expansion and continuous growth of the Corporation, we are looking for a high-calibre to support the Business Development team bringing the top-notch global Innovation and Technology (I&T)\u00a0companies to set up research and development operation in HKSTP.\nMajor responsibilities are listed below:\nSource and identify potential start-ups & scales-ups to business development team for engagement through research in the key market intelligence platform.\nLead research to understand emerging innovations and technologies across Biotech, Property Technology AI & Robotic, Smart Mobility, Fintech, Microelectronics, Industry 4.0 sectors.\nDelivers reports and makes insights/recommendations of key findings to improve business outcomes and support growth strategy initiatives.\nSummarize and consolidate the information into actionable items.\nKeep abreast of the latest technology trend across the global.\nDevelop strong partnerships with cross-functional teams.\nPerforms other related duties as assigned.\nRequirements:\u00a0\nBachelor\u2019s degree in business, Marketing, Data Science, Statistics, or related field required.\nMinimum 5+ years experience in market research or related field, engineering background is preferred.\nExcellent organizational skills and attention to detail.\nSuperior research and analytical skills.\nAbility to translate complex concepts and methodologies into easily understood language.\nExcellent project management and business writing skills.\nExcellent interpersonal, presentation and communication skills.\nCreative, self-driven and customer-oriented.\nProficient in both written and spoken English and Chinese (including Putonghua)\nCandidates with more experience may be considered as manager.\n[This position is open for referral by Recruitment agencies. The profile should be sent to our HR email address\u00a0a g e n c y c v @ h k s t p . o r g]\nWe offer market competitive compensation, 5-day work week, and generous benefits including medical and life insurance; and voluntary contribution in addition to the legal minimum MPF.\u00a0 To apply, please send your full resume with current and expected salary to the Human Resources & Office Administration Department, Hong Kong Science and Technology Parks Corporation, 5/F, Building 5E, 5 Science Park East Avenue, Hong Kong Science Park, Hong Kong or, by email via \"Apply Now\"\u00a0on or before 27 January 2022.\u00a0 \u00a0Please quote the reference number on the email subject/envelope and the application letter.\u00a0\u00a0\nPersonal data provided will be treated in strict confidence and used for recruitment purpose only.\u00a0 All personal data collected will be used strictly in accordance with employer\u2019s personal data policies, you can access to HKSTP\u2019s Personal Information Collection Statement at https://www.hkstp.org/hkstp_web/en/hkstp/personal-information-collection-statement-recruitment\nApplicants not invited for interview within four weeks after application deadline may consider their applications unsuccessful.\u00a0 Personal data of unsuccessful applicants will be retained for a maximum of two years.\u00a0\nwww.hkstp.org", "employment_types": ["Full Time", "Permanent"], "selling_points": [], "locations": ["Shatin Area"], "categories": ["Marketing / Public Relations", "Marketing - Direct Marketing", "Others", "E-commerce", "Marketing - Brand / Product Management"], "post_time": "2022-01-17T01:36:24Z", "salary": {"currency": null, "max": null, "min": null, "period": "monthly", "term": null}, "salary_visible": false, "title_keywords": ["digital marketing executive"], "responsibilities": ["reports", "cross-functional teams", "develop"], "requirements": {"degrees": ["degree", "bachelor"], "majors": ["data science", "business", "statistics", "marketing"], "languages": ["putonghua", "english", "chinese"], "language_level": ["proficient"], "hard_skills": ["writing skills", "analytical skills", "project management", "c", "r"], "soft_skills": ["organizational skills", "communication skills", "presentation", "driven", "writing skills", "analytical skills", "project management", "customer-oriented", "attention to detail", "creative", "interpersonal", "superior"], "languages_combined": [{"language": "putonghua", "language_level": []}, {"language": "english", "language_level": ["proficient"]}, {"language": "chinese", "language_level": ["proficient"]}]}, "experience_required": {"duration": ["minimum 5+ years"], "field": ["related", "engineering", "market research"]}}, {"job_id": "100003009050246", "location_code": "hk", "company": "Maxim's Caterers Ltd", "job_title": "Senior Trade Marketing Officer", "description": "Responsibilities:\n\nResponsible for content management of the brand website and other e-commerce channels\nAssist the team to plan and execute online promotion campaigns\n\nManage social media channels in order to meet the targeted KPI\nPlan and monitor company\u2019s SEO and SEM management\n\nParticipate and communicate with headquarters in website enhancement\nAssist in performance analysis in all digital channels\nAssist in any ad hoc duties as requested\n\nRequirements:\n\nDegree holder in Marketing / Communications e-commerce or related disciplines\nWith 1 - 2 years of solid experience in online marketing\n\nExperience in Google analytics is an advantage\nProactive, results-oriented with a strong sense of responsibility\nFast-paced with excellent communication and interpersonal skills\nCreative and attention to details\nGood command of spoken and written English, Cantonese, and Mandarin\n\n\nInterested parties, please send your full resume with\u00a0current salary,\u00a0expected salary,\u00a0and\u00a0available date\u00a0either by direct application from JobsDB (Please quote the job title on the subject ) or by WhatsApp:69298297 or by post to Human Resources Department, Unit 8-14 & 22-28, 11/F, Topsail Plaza, 11 On Sum Street, Shek Mun.\n\"Personal data collected will be used for recruitment purposes only.\"", "employment_types": ["Full Time", "Permanent"], "selling_points": ["Pricing, trade marketing, promotion analysis", "Organization of trade fairs, promotions and events", "Implementation of Below The Line strategies"], "locations": ["Not Specified"], "categories": ["Marketing / Public Relations", "Marketing - Brand / Product Management", "Marketing - General / Support", "Others"], "post_time": "2022-01-14T10:00:29Z", "salary": {"currency": null, "max": null, "min": null, "period": "monthly", "term": null}, "salary_visible": false, "title_keywords": ["marketing officer"], "responsibilities": ["communicate with", "social media", "management", "ad hoc duties", "seo", "analysis", "monitor", "website", "plan", "sem", "online promotion"], "requirements": {"degrees": ["degree holder"], "majors": ["related disciplines", "marketing", "communications", "e-commerce"], "languages": ["cantonese", "english", "mandarin"], "language_level": ["good command"], "hard_skills": ["google analytics", "e-commerce"], "soft_skills": ["creative", "sense of responsibility", "communication and interpersonal skills", "attention to details", "proactive"], "languages_combined": [{"language": "cantonese", "language_level": ["good command"]}, {"language": "english", "language_level": ["good command"]}, {"language": "mandarin", "language_level": ["good command"]}]}, "experience_required": {"duration": ["1 - 2 years"], "field": ["marketing"]}}, {"job_id": "100003009050861", "location_code": "hk", "company": "Estee Lauder (Hong Kong) Ltd", "job_title": "Assistant Online Manager", "description": "Responsibilities\n\nDevelop & implement Below-The-Line (BTL) strategies within brands guidelines as well as customers' & shoppers' expectations\nFacilitate smooth and effective implementation of brand plans (pricing, trade marketing, promotion analysis).\u00a0Coordinate closely with Sales team and Marketing Team\nAssist, support and organize trade fairs, promotions, events and road shows\nFully responsible for the implementation of all trade activities\nWork with supplier and promoter agency independently\nMonitor and evaluate ROI of trade activities and provide recommendations for improvement\nRequirements\n\nUniversity graduate in Marketing, Business Administration or related discipline\nAt least 3 years relevant experience in FMCG Trade Marketing or Marketing field\nIndependent, self-motivated, strong sense of responsibility, organized, detailed minded, good communication skills and can cope with pressure on tight timeline\nGood command in spoken and written English, Chinese and Mandarin\nOversea travel required\nInterested parties please apply with full resume, state current and expected salaries by clicking \"Apply Now\". All applications and data collected will be treated in strict confidence and used exclusively for recruitment purposes.\u00a0 Only short listed candidates will be invited for interview. The company will retain the applications for a maximum period of 24 months and may refer suitable candidates to other vacancies within the Group.\n\nOversea travel required", "employment_types": ["Full Time"], "selling_points": ["minimum of 5 years' working experience", "Proactive, self-motivated and independent", "Manage & prepare regular and ad-hoc reports"], "locations": ["Not Specified"], "categories": ["Marketing / Public Relations", "Others", "Sales, CS & Business Devpt", "Others", "Others", "Others"], "post_time": "2022-01-14T11:35:30Z", "salary": {"currency": null, "max": null, "min": null, "period": "monthly", "term": null}, "salary_visible": false, "title_keywords": ["manager", "assistant"], "responsibilities": ["trade marketing", "guidelines", "analysis", "monitor", "implementation", "develop", "coordinate", "evaluate", "sales team", "provide recommendations", "plans"], "requirements": {"degrees": ["university graduate"], "majors": ["marketing", "business administration"], "languages": ["english", "chinese", "mandarin"], "language_level": ["good command"], "hard_skills": [], "soft_skills": ["organized", "self-motivated", "communication skills", "independent", "sense of responsibility", "detailed"], "languages_combined": [{"language": "english", "language_level": ["good command"]}, {"language": "chinese", "language_level": ["good command"]}, {"language": "mandarin", "language_level": ["good command"]}]}, "experience_required": {"duration": ["at least 3 years"], "field": ["fmcg", "relevant experience", "marketing"]}}, {"job_id": "100003009043684", "location_code": "hk", "company": "Joinmax Display & Productions Limited", "job_title": "Sales & Marketing Assistant", "description": "What You Will Achieve\n\nAs part of our dynamic team, you will:\u00a0\n\nFormulate plans and strategies of online marketing to drive sales and revenue\u00a0\nDevelop e-Commerce marketing calendar in line with brand marketing and online strategies\nAssist to develop and implement the digital marketing strategy, e-Commerce brand sites, third party platforms, Retailer.com and Omni Channels for business growth for the company including website and social media\nOversee the daily operations of the on-line business to ensure smooth running of the online platforms\nEnhance the website content and flow to grow the customer usage, traffic and conversion rate\nWork closely with external and internal stakeholders on marketing, products, creative and system development\nManage & prepare regular and ad-hoc reports\nAssist to conduct market research and campaign result analysis\n\nWhat You Will Need\n\nUniversity degree, preferably in marketing, communication, e-commerce or related disciplines\nA minimum of 5 years' working experience in online business environment\u00a0\nGeneral knowledge of web performance analytic & web development cycle\nGood understanding of the latest Internet, mobile, search and social media development trends\nGood command of written and spoken English and Chinese, including Putonghua\nA good team player with strong communication and interpersonal skills\nProactive, self-motivated and independent\nHighly analytical and well-structured in problem solving and presentation\nWell organized and meticulous with the ability to multi-task and work under pressure\nCandidate with less experience will be considered for Senior Online Executive\n\n\n\nInterested candidates, please click Apply Now.", "employment_types": ["Full Time"], "selling_points": [], "locations": ["Hung Hom"], "categories": ["Marketing / Public Relations", "Others"], "post_time": "2022-01-13T01:35:46Z", "salary": {"currency": null, "max": null, "min": null, "period": "monthly", "term": null}, "salary_visible": false, "title_keywords": ["marketing assistant", "sales"], "responsibilities": ["ad-hoc", "social media", "oversee the daily operations", "conduct market research", "website", "develop", "communication", "campaign result analysis", "digital marketing", "reports", "plans", "brand sites", "drive sales", "third party", "work under pressure"], "requirements": {"degrees": ["university degree"], "majors": ["related disciplines", "marketing", "e-commerce"], "languages": ["putonghua", "english", "chinese"], "language_level": ["good command"], "hard_skills": ["web development", "e-commerce", "analysis", "problem solving", "mobile", "dynamic", "web performance"], "soft_skills": ["meticulous", "good team player", "proactive", "self-motivated", "independent", "multi-task", "well organized", "communication", "problem solving", "dynamic", "communication and interpersonal skills", "smooth", "business environment", "creative", "presentation", "structured", "work under pressure"], "languages_combined": [{"language": "putonghua", "language_level": ["good command"]}, {"language": "english", "language_level": ["good command"]}, {"language": "chinese", "language_level": ["good command"]}]}, "experience_required": {"duration": ["minimum of 5 years"], "field": ["business"]}}, {"job_id": "100003009047180", "location_code": "hk", "company": "Christian Family Service Centre", "job_title": "Marketing Officer (PO3b-ESP)", "description": "Job responsibilities:\n\nHandle sales and marketing activities\nSupport internal parties to fulfill challenging duties\nFollow up orders and after sales services\nExplore new clients\nOrganize and participate in promotion events\nSupport business development activities of the sales team\nAssist in corporate website and social media platform management\nAble to execute ad hoc assignment\n\nRequirements:\n\nSales & Marketing experience preferred\nDetail-minded, organized, highly self-motivated and initiative\nSelf-learner and self-starter, can work with minimal supervision\nOutgoing, cheerful, aggressive, energetic and team-oriented\nGood command of spoken and written English and Chinese (Mandarin);\nProficiency in MS Office application and Chinese Word Processing", "employment_types": ["Full Time"], "selling_points": [], "locations": ["Kwun Tong"], "categories": ["Marketing / Public Relations", "Marketing - General / Support", "Others", "Public / Civil", "Social Services - Community / Non-profit Organization"], "post_time": "2022-01-14T02:31:45Z", "salary": {"currency": null, "max": null, "min": null, "period": "monthly", "term": null}, "salary_visible": false, "title_keywords": ["marketing officer"], "responsibilities": ["follow up orders", "social media", "management", "ad hoc assignment", "website", "sales team", "internal parties"], "requirements": {"degrees": [], "majors": [], "languages": ["english", "chinese", "mandarin"], "language_level": ["proficiency", "good command"], "hard_skills": ["chinese word processing", "ms office"], "soft_skills": ["detail-minded", "organized", "self-motivated", "outgoing", "cheerful", "energetic", "initiative"], "languages_combined": [{"language": "english", "language_level": ["good command"]}, {"language": "chinese", "language_level": ["proficiency", "good command"]}, {"language": "mandarin", "language_level": ["good command"]}]}, "experience_required": {"duration": [], "field": ["marketing"]}}, {"job_id": "100003009048114", "location_code": "hk", "company": "Continental Conair Ltd", "job_title": "Assistant New Product Manager", "description": "Requirements:\n\n\nDiploma or above in Marketing, Communications or Business-related discipline, with at least 3 years of experience in marketing or public relations;\nUniversity Degree in relevant discipline is preferable;\nExcellent verbal and written communication skills;\nGood command of written and spoken English, Cantonese and Mandarin;\nProactive, independent and able to develop new initiatives.\n\nJob Duties:\n\n\nSupport all marketing activities and materials preparation including press release, newsletter, public seminar, service brochure, etc.;\nCoordinate with stakeholders to ensure excellent execution of marketing initiatives;\nAttend business meetings to introduce or follow-up service projects;\nPrepare business proposals and handle service accounts;\nProvide administrative or technical support to training and wellness programs;\nOther ad hoc duties as assigned by seniors.\n\nWorking Hours: 44 hours per week\nWorking Location:\u00a0Vital Employee Service Consultancy, Kwun Tong District\n\nPlease send your application letter quoting our job reference code together with a full resume, available date, last and expected salary by post to the Human Resources Department at 10/F, 3 Tsui Ping Road, Kwun Tong, Kowloon or by clicking \"Apply Now\".\n\nProspective employees who will undertake child or mentally incapacitated persons related work will be requested to undergo the Sexual Conviction Record Check (SCRC).\nApplicants not hearing from us within two months from the date of advertisement may consider their applications fail.\nAll personal data of unsuccessful candidates would be destroyed after 6 months of interview and after 3 months of receiving applications for those without interview.\nPersonal data provided by job applicants will be used for recruitment purpose for different posts in the Agency only.", "employment_types": ["Full Time", "Permanent"], "selling_points": [], "locations": ["Not Specified"], "categories": ["Marketing / Public Relations", "Others", "Merchandising & Purchasing", "Home Appliances"], "post_time": "2022-01-15T03:49:52Z", "salary": {"currency": null, "max": null, "min": null, "period": "monthly", "term": null}, "salary_visible": false, "title_keywords": ["product manager", "assistant"], "responsibilities": ["ad hoc duties", "technical support", "recruitment", "coordinate with stakeholders", "personal data"], "requirements": {"degrees": ["university degree", "diploma or above"], "majors": ["business", "marketing", "communications"], "languages": ["cantonese", "english", "mandarin"], "language_level": ["good command"], "hard_skills": [], "soft_skills": ["communication skills", "proactive", "independent"], "languages_combined": [{"language": "cantonese", "language_level": ["good command"]}, {"language": "english", "language_level": ["good command"]}, {"language": "mandarin", "language_level": ["good command"]}]}, "experience_required": {"duration": ["at least 3 years"], "field": ["business", "public relations", "marketing", "related"]}}, {"job_id": "100003009050956", "location_code": "hk", "company": "Hong Kong Science & Technology Parks Corporation", "job_title": "Manager, Talent Engagement, HKSTP InnoAcademy [JDB/MTEHKSTPI/220114]", "description": "Responsibilities:\nManage and drive New Products project from concept/design stage to production stage\nContribute to sourcing decisions for identifying required supplier capability and quality level\nHandle project development, follow up and work closely with internal departments e.g. R&D, Mechanical Engineering, Merchandising & Quality Department\nLiaise and negotiation with marketing and suppliers\nUpdate and report on management projects on time\nPerform ad-hoc tasks and project as assigned\nRequired Qualifications:\nBachelor Degree in Mechanical Engineering, Industrial Engineering or relevant business- related discipline\nMinimum 8 years working experience, with preferably more than 5 years experiences in an industrial environment. Professional in relevant manufacturing technology and preferably in home small appliance industry. Consumer electronics background is an absolute advantage\nIn-depth knowledge of process improvements and cost optimization\nStrong communication skills with external and internal stakeholders\nIndependent, proactive, driving for result\nFrequent traveling in China is required\n\nWe offer an attractive remuneration package and comprehensive fringe benefits to suitable candidate.\u00a0 Interested parties, please send your application together with a detail resume including availability, present and expected salary,by e-mail via \"Apply Now\". Your interest will be treated in strict confidence and only shortlisted candidates will be notified. All personal data will be treated in strict confidence and collected for recruitment purposes only.", "employment_types": ["Full Time"], "selling_points": [], "locations": ["Shatin Area"], "categories": ["Marketing / Public Relations", "Marketing - Marketing Communication", "Public Relations - Event Management", "Others"], "post_time": "2022-01-14T12:01:14Z", "salary": {"currency": null, "max": null, "min": null, "period": "monthly", "term": null}, "salary_visible": false, "title_keywords": ["manager"], "responsibilities": ["liaise", "management", "cost optimization", "ad-hoc tasks", "merchandising", "quality", "design", "communication", "report"], "requirements": {"degrees": ["degree", "bachelor"], "majors": ["engineering", "mechanical engineering"], "languages": [], "language_level": [], "hard_skills": ["r&d", "small"], "soft_skills": ["communication skills", "proactive", "independent", "negotiation"], "languages_combined": []}, "experience_required": {"duration": ["5 years", "minimum 8 years"], "field": []}}, {"job_id": "100003009048828", "location_code": "hk", "company": "Dah Chong Hong, Limited", "job_title": "Marketing Executive", "description": "HKSTP InnoAcademy (innoacademy.hkstp.org) is HKSTP\u2019s initiative to nurture, inspire and engage talent for innovation and technology (I&T) careers in Hong Kong. Our vision is to develop Hong Kong into a global I&T talent hub that draws Hong Kong, Mainland and overseas I&T talent.\nWe are looking for a seasoned professional who is passionate about talent development for Hong Kong\u2019s I&T sector to join our growing and committed team. As a key member of the team, you will grow and manage the community of talent who have participated in HKSTP\u2019s talent initiatives, as well as the broader I&T talent pool in Hong Kong and the Guangdong-Hong Kong-Macau Greater Bay Area (GBA).\nThe overarching goals are to engage and retain the talent who are already in our ecosystem so as to turn them into advocates / ambassadors for Hong Kong and HKSTP, as well as draw more local and non-local talent to join Hong Kong\u2019s I&T sector and build a vibrant I&T talent community in Hong Kong and the GBA.\nYou\u2019re a people person who is extroverted and always happy to learn more about communities and what motivates them. You know communities and their members so well that not only do you connect with them, but also connect them with each other when you see synergy. You also have a nose for success stories in the community, and a passion for making the community and its culture stronger and better. You should have previous experience engaging with and managing communities in your career, whether they are professional associations, customer groups, alumni, etc.\nResponsibilities:\nWork with Senior Manager to grow Hong Kong\u2019s I&T talent community, as well as ideate, plan, promote and manage high-impact online and offline branding campaigns to drive perception of Hong Kong\u2019s I&T sector as the \u201cEmployer of Choice\u201d among local and non-local talent.\nDeliver engagement initiatives and activities to build a vibrant I&T talent community and culture in the HKSTP ecosystem in Hong Kong and the GBA\nEngage and grow community via events, social channels, e-newsletters, and various promotion channels\nGather feedback from members, talents and partners for the team to constantly improve/optimize InnoAcademy\u2019s community features, activities and benefits\nMeasure engagement initiatives / activities\u2019 effectiveness, community member activity and impact\nPerform any other duties as assigned by supervisors\nRequirements:\nBachelor\u2019s degree in Marketing, Human Resource Management, Communication, Social Science, Business or other related disciplines\nAt least 5 years of relevant experience in marketing, branding or community building, preferably in the I&T sector or an employer branding capacity. Candidates with less experience will be considered for lower position.\nStrong in project management and execution in a fast-paced, dynamic environment\nExperienced in working with a wide range of internal and external stakeholders to drive impactful results\nFamiliar with social channels (LinkedIn, Facebook, Instagram) and their related metrics\nA self-starter who is innovative, entrepreneurial, goal-getting, detail-oriented, and able to work under tight schedule\nExcellent interpersonal and communication skills in verbal and written English and Chinese, including Cantonese and Putonghua\nExtensive network within the I&T and/or tertiary education sectors in Hong Kong and the GBA will be a definite advantage\nGBA, Mainland and international working experience will be a plus\nWe offer market competitive compensation, 5-day work week, and generous benefits including medical and life insurance; and voluntary contribution in addition to the legal minimum MPF.\u00a0 To apply, please send your full resume with current and expected salary to the Human Resources & Office Administration Department, Hong Kong Science and Technology Parks Corporation, 5/F, Building 5E, 5 Science Park East Avenue, Hong Kong Science Park, Hong Kong or, by email via \"Apply Now\"\u00a0on or before 27 January 2022.\u00a0 \u00a0Please quote the reference number on the email subject/envelope and the application letter.\u00a0\nPersonal data provided will be treated in strict confidence and used for recruitment purpose only.\u00a0 All personal data collected will be used strictly in accordance with employer\u2019s personal data policies, you can access to HKSTP\u2019s Personal Information Collection Statement at https://www.hkstp.org/hkstp_web/en/hkstp/personal-information-collection-statement-recruitment\nApplicants not invited for interview within four weeks after application deadline may consider their applications unsuccessful.\u00a0 Personal data of unsuccessful applicants will be retained for a maximum of two years.\u00a0\nwww.hkstp.org", "employment_types": ["Full Time", "Permanent"], "selling_points": [], "locations": ["Kowloon Bay"], "categories": ["Marketing / Public Relations", "Marketing - Brand / Product Management", "Marketing - General / Support", "Others"], "post_time": "2022-01-14T07:22:04Z", "salary": {"currency": null, "max": null, "min": null, "period": "monthly", "term": null}, "salary_visible": false, "title_keywords": ["marketing executive"], "responsibilities": ["any other duties", "plan"], "requirements": {"degrees": ["degree", "bachelor"], "majors": ["business", "science", "related disciplines", "marketing"], "languages": ["cantonese", "putonghua", "english", "chinese"], "language_level": ["excellent"], "hard_skills": ["plus", "project management", "goal", "dynamic", "facebook"], "soft_skills": ["communication skills", "dynamic environment", "detail-oriented", "communication", "project management", "innovative", "extensive", "interpersonal"], "languages_combined": [{"language": "cantonese", "language_level": ["excellent"]}, {"language": "putonghua", "language_level": ["excellent"]}, {"language": "english", "language_level": ["excellent"]}, {"language": "chinese", "language_level": ["excellent"]}]}, "experience_required": {"duration": ["at least 5 years"], "field": ["marketing", "relevant experience"]}}, {"job_id": "100003009045989", "location_code": "hk", "company": "EY", "job_title": "Cryptography and Blockchain Researcher, Assistant Director", "description": "The incumbent will be responsible for a series of marketing initiatives for the assigned brands or product portfolio as below.\n\nResponsibilities :\n\nFormulate and implement of marketing programs\nControl and monitor of all marketing activities and promotions\nEvaluate the effectiveness of marketing and promotion programs\nLiaison and communicate with Principals\nWork closely with the internal parties such as Key Account team\nPerform inventory control and order planning\nConduct price analysis and sales analysis\n\nThe ideal candidate should be :\n\nUniversity graduate in Marketing or related disciplines\nAt least 1-2 years relevant experience in marketing. Exposure in food/beverage product is an advantage\nResponsible, analytical, independent, self-motivated with excellent communication skills and able to work under pressure\nGood command of spoken and written English and Chinese\nProficiency in MS Office\n\nPlease send your application with resume and expected salary to The HR Manager, Sims Trading Co. Ltd, 8/F, DCH Building, 20 Kai Cheung Road, Kowloon Bay\u00a0or submit your application online by clicking\u00a0\"Apply Now\"\n\nInformation provided will be kept for the purpose of selection within the company and only shortlisted candidates will be contacted. All applications will be retained for a maximum period of 6 months.", "employment_types": ["Full Time"], "selling_points": ["drive the creation of advanced mathematics", "Develop advanced Zero Knowledge Proof protocols", "Help us to develop practical applications"], "locations": ["Not Specified"], "categories": ["Marketing / Public Relations", "Marketing - Market Research", "Others"], "post_time": "2022-01-13T09:21:53Z", "salary": {"currency": null, "max": null, "min": null, "period": "monthly", "term": null}, "salary_visible": false, "title_keywords": ["researcher", "assistant director"], "responsibilities": ["communicate with", "control", "work under pressure", "analysis", "hr", "monitor", "evaluate", "communication", "inventory control", "internal parties", "planning"], "requirements": {"degrees": ["university graduate"], "majors": ["related disciplines", "marketing"], "languages": ["english", "chinese"], "language_level": ["good command"], "hard_skills": ["analysis", "ms office"], "soft_skills": ["communication skills", "self-motivated", "independent", "responsible", "work under pressure", "ideal"], "languages_combined": [{"language": "english", "language_level": ["good command"]}, {"language": "chinese", "language_level": ["good command"]}]}, "experience_required": {"duration": ["at least 1-2 years"], "field": ["marketing", "relevant experience"]}}, {"job_id": "100003009050654", "location_code": "hk", "company": "Links International", "job_title": "Marketing Admin / Coordinator (One year contract)", "description": "Our future success depends on the diverse talent and performance of dedicated employees. We now call for applications to fill this position which is financially supported by the Home Affairs Bureau\u2019s Arts and Sports Development Fund. The position is under the Marketing and Communications Department in the organization structure of HKFA. Reporting to the Public Relations and Communications Manager, the appointee is responsible for the following:\nJob Descriptions\nTo assist with the management of media relations and the delivery of the HKFA\u2019s communications strategy\nTo assist the PR and Communications Manager in the planning, development, implementation and evaluation of PR campaigns to meet the Association\u2019s mission, increase public awareness and enhance the image of the HKFA\nUnder the direction of the PR and Communications Manager, to respond to public and media enquiries\nTo proactively promote the HKFA brand and create a positive corporate image\nTo work with agency / stakeholders, to conduct market research, develop appropriate strategies, to collect and report information, and use feedback to guide current and future PR and media efforts\nTo prepare press statements and regular communication materials with stakeholders to be approved by the PR and Communications Manager\nTo ensure that all PR and Media dealings are coordinated with other marketing and management initiatives\nTo be responsible for the production of events from conception through to completion, e.g. press conference, event launch, most valuable player award and etc.\nTo perform on-site event management including venue logistics co-ordinations, rehearsals, rundown handling and stage management\nTo contribute on the post event evaluation reports to inform future event planning\nTo assist in more general HKFA marketing and promotional activities, events and programmes as instructed by the PR and Communications Manager\nTo perform such other duties and responsibilities as instructed by the Chief Executive Officer and PR and Communications Manager\nQualifications and Experience\nUniversity degree in Communications/Business Administration/Public Relations or related discipline\nMinimum of 5 years and preferably 10 years of relevant experience in media relations\nGood command of written and spoken English, Cantonese and (preferably) Mandarin\nStrong communication & interpersonal skills, confident in facing public and media\nKnowledge and interest in football / sports will be advantageous\nWilling to learn, detail minded and a good team player\nProficient in PC skills (MS Word, Excel, PowerPoint, Chinese character input)\nExpected to work overtime, irregular hours and some weekends and public holidays when required\nApplicants with less experience may be considered for the post of Assistant Public Relations and Communications Officer\nThe successful candidate will be offered on a contract term employment. Starting salary will be commensurate with qualifications and experience. Our employee benefits include Group Medical and Life Insurance to the right candidate.\u00a0\nDeadline: 19 January 2022\nPlease ensure that you have explored the following official link which lists the relevant instructions before making an application:\nwww.hkfa.com/en/load_page/82\n\nThe information provided by the applicants will be treated in strict confidence and will only be used for the purpose of considering your employment application.\nPLEASE DO NOT USE \u201cAPPLY NOW\u201d FUNCTION.", "employment_types": ["Full Time", "Permanent"], "selling_points": ["Fortune Global 500 Companies", "Under Marketing CRM Department", "Immediate / Short notice preferred"], "locations": ["Not Specified"], "categories": ["Marketing / Public Relations", "Marketing - General / Support", "Marketing - Marketing Communication", "Others"], "post_time": "2022-01-14T11:07:15Z", "salary": {"currency": "HKD", "max": 16999, "min": 14000, "period": "monthly", "term": null}, "salary_visible": true, "title_keywords": ["coordinator", "admin"], "responsibilities": ["administration", "reporting", "management", "other duties", "conduct market research", "implementation", "develop", "communication", "logistics", "reports", "promotional activities", "evaluation", "report", "planning"], "requirements": {"degrees": ["university degree"], "majors": ["business administration", "communications"], "languages": ["cantonese", "english", "chinese", "mandarin"], "language_level": ["good command", "proficient"], "hard_skills": ["excel", "inform", "powerpoint", "pc skills", "ms word"], "soft_skills": ["confident", "good team player", "work overtime", "responsible", "willing to learn", "communication", "diverse", "interpersonal skills", "positive"], "languages_combined": [{"language": "cantonese", "language_level": ["good command"]}, {"language": "english", "language_level": ["good command"]}, {"language": "chinese", "language_level": ["proficient"]}, {"language": "mandarin", "language_level": ["good command"]}]}, "experience_required": {"duration": ["10 years", "minimum of 5 years"], "field": ["public relations", "relevant experience", "media"]}}, {"job_id": "100003009044613", "location_code": "hk", "company": "The Clearwater Bay Golf & Country Club", "job_title": "Membership Executive", "description": "Our client is one of the Fortune 500 members and they are currently looking for a Marketing Assistant to join their team. This employment is under one year contract, subject to renewal.\n\n\nResponsibilities\n\nProduce regular reports on redemption, fraud, third party loyalty program and so on\nCoordinate among different stakeholders, including team members, vendors, partners to assist loyalty operation\nCollaborate with Customer Service team to deal with customer complaints\nSupport online project UAT\nExamine payment reports from retailers and payment vendors\nDeal with payment disputes cases\n\nRequirements\n\nBachelor in Marketing, Business Administration or related disciplines\n1-2 years related experience\nProficient in Microsoft Word, Excel, PowerPoint and Teams\nGood command in both written and spoken English and Chinese\nCandidate with short notice or immediate availability is highly preferred", "employment_types": ["Full Time", "Permanent"], "selling_points": [], "locations": ["Sai Kung"], "categories": ["Admin & HR", "Clerical / Admin Staff", "Hospitality / F & B", "Hospitality / Hotel Services", "Marketing / Public Relations", "Others"], "post_time": "2022-01-13T04:50:47Z", "salary": {"currency": null, "max": null, "min": null, "period": "monthly", "term": null}, "salary_visible": false, "title_keywords": ["executive"], "responsibilities": ["collaborate with", "uat", "customer complaints", "coordinate", "payment", "customer service", "reports", "third party"], "requirements": {"degrees": ["bachelor"], "majors": ["related disciplines", "marketing", "business administration"], "languages": ["english", "chinese"], "language_level": ["good command"], "hard_skills": ["excel", "microsoft word", "powerpoint"], "soft_skills": [], "languages_combined": [{"language": "english", "language_level": ["good command"]}, {"language": "chinese", "language_level": ["good command"]}]}, "experience_required": {"duration": ["1-2 years"], "field": ["related"]}}, {"job_id": "100003009048934", "location_code": "hk", "company": "Pok Oi Hospital", "job_title": "Temporary Senior Corporate Communications and Fundraising Officer (Ref: BOD/SCCFO/Temp)", "description": "Diploma or above in Communications, Public Relations, Journalism or related disciplines\nMinimum 5 years\u2019 relevant experience in the field of corporate communications, fundraising, event management, publishing and editing\nGood communication skills in both written and spoken English, Chinese and Mandarin\nProficient in MS Office applications\nCandidates with less experience will be considered as Corporate Communications and Fundraising Officer\nContract period : 2022/2/4 to 2022/5/31\nThe appointment will be made on a fixed-term contract basis. Interested candidates are invited to apply by sending full resume with current salary, expected salary and date available to Human Resources Department, Pok Oi Hospital Board, UG/F., Pok Oi Hospital Jockey Club Care & Attention Home Building, Au Tau, Yuen Long or by email via \"Apply Now\"\u00a0on or before 26 January 2022.\u00a0 For more details of Pok Oi Hospital, please visit our website http://www.pokoi.org.hk.\n\u00a0(All personal data collected from applicants will be kept confidential and used for employment-related purpose only. \u00a0The Board is an equal opportunity employer.)", "employment_types": ["Contract"], "selling_points": ["Good communication skills", "Diploma or above in Communications", "Minimum 5 years\u2019 relevant experience"], "locations": ["Not Specified"], "categories": ["Media & Advertising", "Editorial / Journalism", "Marketing / Public Relations", "Marketing - Marketing Communication", "Others"], "post_time": "2022-01-14T07:47:09Z", "salary": {"currency": null, "max": null, "min": null, "period": "monthly", "term": null}, "salary_visible": false, "title_keywords": ["fundraising officer"], "responsibilities": ["communication", "management", "editing"], "requirements": {"degrees": ["diploma or above"], "majors": ["journalism", "related disciplines", "communications"], "languages": ["english", "chinese", "mandarin"], "language_level": ["good"], "hard_skills": ["ms office"], "soft_skills": ["communication skills"], "languages_combined": [{"language": "english", "language_level": ["good"]}, {"language": "chinese", "language_level": ["good"]}, {"language": "mandarin", "language_level": ["good"]}]}, "experience_required": {"duration": ["minimum 5 years"], "field": ["management", "publishing", "relevant experience", "editing"]}}, {"job_id": "100003009049126", "location_code": "hk", "company": "Centaline Property Agency Ltd", "job_title": "Executive", "description": "Responsibilities:\n\nPrepare reports for primary sector including consumption table, analytical reports of property transaction etc.\nHandle and coordinate with the promotions of projects, such as preparing proposal for Tendering as Sole Agent\nLiaise with Developer for updates of leasing properties\nAc hoc tasks as assigned by Administrative Team\n\nRequirements:\n\nFor 5 or above\n1-2 years' relevant work experience\nGood\u00a0command of written Chinese\nProficient in MS Excel and Powerpoint\nImmediate available is preferred\n\nWe provide its members\u00a0with professional training, attractive remuneration package and excellent career prospects.\u00a0 For application, please send full resume with present and expected salary to Human Resources Department, 5/F., Tower 1, New World Tower, 18 Queen' s Road Central, Hong Kong\n\nFor more information about us, please visit our website at: www.centanet.com\n\nData collected will be used for recruitment purpose only", "employment_types": ["Full Time", "Permanent"], "selling_points": ["Data searching and analysis", "Responsible for reports preparation", "Form 5 or above with 1-2 years work experience"], "locations": ["Central"], "categories": ["Marketing / Public Relations", "Marketing - Market Research", "Others"], "post_time": "2022-01-14T08:09:06Z", "salary": {"currency": null, "max": null, "min": null, "period": "monthly", "term": null}, "salary_visible": false, "title_keywords": ["executive"], "responsibilities": ["coordinate with", "tendering", "liaise with", "reports", "prepare reports"], "requirements": {"degrees": [], "majors": [], "languages": ["chinese"], "language_level": ["good command"], "hard_skills": ["ms excel", "powerpoint"], "soft_skills": [], "languages_combined": [{"language": "chinese", "language_level": ["good command"]}]}, "experience_required": {"duration": ["1-2 years"], "field": []}}, {"job_id": "100003009046141", "location_code": "hk", "company": "Eddid Securities & Futures Limited", "job_title": "Marketing Intern (App Store Focus)", "description": "Eddid Securities and Futures Ltd. (Eddid Securities and Futures) is a core member of the Eddid Holdings Group. It was incorporated in Hong Kong in 2015. It relies on professional investment and research capabilities, excellent business capabilities, and comprehensive competition with abundant capital strength.\n\nPossessing the profession, we successively obtained the 1, 2, 3, 4, 5 & 9 regulated activity licenses issued by Hong Kong SFC (Central Code: BHT550), and also a HKSE Participant (02047) (OTP-C broker code: 0974 and 0977). As a leading new first-line Internet licensed brokerage firm, EDDID Securities & Futures is committed to providing investors with an intelligent, one-stop global trading service platform. Currently, our businesses cover Hong Kong stocks, US stocks, Hong Kong futures, global futures and asset management, etc.\n\nEDDID Securities & Futures attaches great importance to the improvement of overall investment and research strength, actively attracts and trains outstanding investment and research talents, integrates information, reporting, investment education and financial technology intelligence, empowers investment decisions, and helps investors strive for over-predicted return on investment.\n\n\u00a0To cope with our rapid expansion in the Great China region, we are recruiting capable talent to join us.\n\n\n\nKey elements of the job will involve:\n\nResponsible for ASO work of APP in App store, including on-shelf, maintenance, iterative product versions, and increase the right of the APP in App Store;\nFormulate the application department promotion strategy, implement the program, etc;\nOptimize App Store screenshots and app descriptions and metadata;\nManage the App Store's ratings and positive reviews;\nResponsible for the paid promotion and payment optimization of the App Store;\nResponsible for daily paid promotion account data statistics, analysis;\nPay attention to the App Store's competition ASO situation;\nTrack the key word algorithm adjustment of App Store, and make countermeasures in time\n\nThe ideal candidate should be a :\n\n\nUniversity graduate in Marketing or Business Administration or equivalent, undergraduate will also be considered\nPreferably with hands-on knowledge in App Store operations\nWilling to learn\nWell-organized, self-motivated, detail-minded, able to work independently\nGood communication and interpersonal skills\nGood command of written and spoken English and Chinese, proficiency in Putonghua is preferred\n\nWe offer an exciting career opportunity to the successful candidate. Please email your detailed resume and availability for work by clicking \u201cApply Now\u201d.\n\nAll information provided will be treated in strict confidence and used solely for recruitment purposes.", "employment_types": ["Part Time", "Internship"], "selling_points": ["ASO work of APP in App store", "Optimize App Store screenshots and app description", "Bachelor in Marketing or related discipline"], "locations": ["Wan Chai"], "categories": ["Information Technology (IT)", "Others", "Marketing / Public Relations", "Marketing - General / Support", "Others"], "post_time": "2022-01-13T09:44:04Z", "salary": {"currency": null, "max": null, "min": null, "period": "hourly", "term": null}, "salary_visible": false, "title_keywords": ["intern"], "responsibilities": ["administration", "reporting", "maintenance", "data", "brokerage", "analysis", "operations", "us stocks", "communication", "payment", "asset management"], "requirements": {"degrees": ["university graduate"], "majors": ["marketing", "business administration"], "languages": ["putonghua", "english", "chinese"], "language_level": ["proficiency", "good command"], "hard_skills": ["maintenance", "analysis", "word", "make", "c", "rapid", "code"], "soft_skills": ["detail-minded", "self-motivated", "work independently", "capable", "responsible", "willing to learn", "well-organized", "committed", "hands-on", "comprehensive", "communication and interpersonal skills", "positive", "ideal"], "languages_combined": [{"language": "putonghua", "language_level": ["proficiency", "good command"]}, {"language": "english", "language_level": ["proficiency", "good command"]}, {"language": "chinese", "language_level": ["proficiency", "good command"]}]}, "experience_required": {"duration": [], "field": []}}, {"job_id": "100003009051292", "location_code": "hk", "company": "C2 Recruitment Limited", "job_title": "\u5ba2\u6236\u670d\u52d9\u4e3b\u4efb - \u65b0\u754c\u5340\u63a5\u807d\u71b1\u7dda\u90e8", "description": "\u65bc\u5ba2\u6236\u670d\u52d9\u71b1\u7dda\u5167,\u5c31\u5ba2\u6236\u7684\u67e5\u8a62,\u5feb\u901f\u5c0b\u627e\u89e3\u6c7a\u554f\u984c\u7684\u65b9\u6cd5\u4ee5\u53ca\u89e3\u7b54\u6709\u95dc\u90e8\u9580\u7684\u67e5\u8a62\u8207\u53ca\u8f49\u4ecb\u610f\u898b\u6216\u6295\u8a34\n\n\u5168\u76e4\u8ca0\u8cac\u63a5\u807d\u5ba2\u6236\u71b1\u7dda, \u7121\u9700\u92b7\u552e!\n\n\u4e2d\u4e94/\u4e2d\u5b78\u6587\u6191 (DSE)\u6216\u4ee5\u4e0a\u7a0b\u5ea6,\u6b61\u8fce\u6709\u8208\u8da3\u65bc\u5ba2\u6236\u670d\u52d9\u884c\u696d\u767c\u5c55\u53ca \u61c9\u5c46\u7562\u696d\u751f\n\n\u5177\u5099\u57fa\u672c\u5ba2\u6236\u670d\u52d9\u7d93\u9a57, \u7d93\u9a57\u8c50\u5bcc\u8005\u53ef\u53d7\u8058\u70ba\u9ad8\u7d1a\u5ba2\u6236\u670d\u52d9\u4e3b\u4efb\n\n\u6708\u85aa\u6708\u5165\u7d04$16,000 - $20,000 \u8996\u4e4e\u7d93\u9a57\n\n\u826f\u597d\u6649\u5347\u6a5f\u6703 \u53ca \u5b8c\u5584\u5728\u8077\u57f9\u8a13\n\n\u65b0\u754c\u5340\u5de5\u4f5c\n\n\u9700\u8f2a\u73ed\n\n15\u5929\u5e74\u5047\n\n\u91ab\u7642\u6d25\u8cbc\n\n\u8c50\u5bcc\u54e1\u5de5\u6d3b\u52d5\u53ca\u798f\u5229\n\nPersonal data provided by job applicants will be used strictly in accordance with the employer's personal data policies and for recruitment purposes only.", "employment_types": ["Full Time", "Permanent"], "selling_points": ["\u7121\u9700\u92b7\u552e\uff0c\u63a5\u807d\u5ba2\u6236\u670d\u52d9\u71b1\u7dda", "\u6708\u85aa\u6708\u5165\u7d04$16,000 - $20,000 \u8996\u4e4e\u7d93\u9a57", "\u8c50\u5bcc\u54e1\u5de5\u6d3b\u52d5\u53ca\u798f\u5229"], "locations": ["Not Specified"], "categories": ["Sales, CS & Business Devpt", "Call Centre", "Customer Service - Supervisor / Officer", "Marketing / Public Relations", "Others"], "post_time": "2022-01-16T21:50:26Z", "salary": {"currency": null, "max": null, "min": null, "period": "monthly", "term": null}, "salary_visible": false, "title_keywords": ["\u5ba2\u6236\u670d\u52d9\u4e3b\u4efb"], "responsibilities": ["policies", "personal data", "recruitment"], "requirements": {"degrees": [], "majors": [], "languages": [], "language_level": [], "hard_skills": [], "soft_skills": [], "languages_combined": []}, "experience_required": {"duration": [], "field": []}}, {"job_id": "100003009048248", "location_code": "hk", "company": "Elite Asia Development Group Limited", "job_title": "Marketing manager", "description": "\n\u2022 brand strategy for new product line- planning & project management.\n\u2022 execution and implementation of integrated communication plan including collection of customer needs, translation into creative briefs, management of creative process, and global launch communication planning.\n\u2022 Lead product commercialization activities for products to include revenue forecasts, demand planning, coordination of promotional material, creation/update of marketing materials, sales field support, convention planning duties, implementation of sales training.\n\u2022 Manage product portfolio plans and execute the plan including customer needs analysis and gap identification, new product development and launches, product obsolescence, competitive landscape and activity, value creation and messaging, and ongoing pricing/cost management to ensure sustained profitability.\n\u2022 Manage marketing launch plans to include brand strategies, market research, competitive assessments, product positioning, media plans, public relations and marketing programs,\n\u2022 Manage sales tools, promotional literature and other product-related tools geared towards internal and external customers.\n\u2022 Create strategic plan for revenue growth for Global Product line and manage execution of tactics within budget guidelines.\n\u5de5\u4f5c\u985e\u578b: \u5168\u8077, \u9577\u5de5\n\u85aa\u916c: $20,000.00\u81f3$30,000.00(\u6bcf\u6708)\n\u798f\u5229:\n\u2022 \u5728\u5bb6\u5de5\u4f5c\n\u2022 \u80b2\u5b30\u5047\n\u2022 \u54e1\u5de5\u8cfc\u7269\u512a\u60e0\n\u2022 \u6649\u5347\u6a5f\u6703\n\u2022 \u7522\u5047\n\u2022 \u5f48\u6027\u4e0a\u73ed\u6642\u9593\n\u88dc\u5145\u85aa\u916c:\n\u2022 \u4f63\u91d1\n\u2022 \u7e3e\u6548\u734e\u91d1\nCOVID-19 \u75ab\u60c5\u8003\u91cf:\nYes and WFH would be an option, Compiling with highest standard of precautions\n\u9060\u7a0b\u5de5\u4f5c:\n\u2022 \u56e0 COVID-19 \u66ab\u6642\u53ef\u4ee5\n\n", "employment_types": ["Full Time"], "selling_points": [], "locations": ["Not Specified"], "categories": ["Admin & HR", "Others", "Marketing / Public Relations", "Marketing - General / Support", "Others"], "post_time": "2022-01-14T06:03:16Z", "salary": {"currency": null, "max": null, "min": null, "period": "monthly", "term": null}, "salary_visible": false, "title_keywords": ["marketing manager"], "responsibilities": ["demand planning", "brand strategies", "budget", "communication", "commercialization", "plan", "plans", "integrated communication", "implementation", "management", "cost", "revenue growth", "internal and external customers", "guidelines", "analysis", "market research", "project management", "coordination", "marketing materials", "planning"], "requirements": {"degrees": [], "majors": [], "languages": [], "language_level": [], "hard_skills": ["demand planning", "analysis", "gap", "project management", "translation"], "soft_skills": ["communication", "project management", "creative", "coordination"], "languages_combined": []}, "experience_required": {"duration": [], "field": []}}, {"job_id": "100003009051468", "location_code": "hk", "company": "Zext intelligence Limited", "job_title": "Graduate Trainee Program (20K+, Finance)", "description": "The Employer:\n\nOur client is one of the major financial institution in Hong Kong. They are aggressive and innovative, and fast growing.\u00a0 They would like to expand the market share by investing their resources on the right talents.\n\nThe Role and Responsibilities:\n\nComprehensive on-the-job training regarding professional investment and asset management expertise.\nPreparing investment portfolio and global market analysis.\nTo develop investment strategies to achieve client\u2019s short-term and long-term financial objectives.\nOn going manage client\u2019s portfolios according to client\u2019s financial goals.\nPreparing different scheme of investment proposal and portfolio review report.\nIdentify client objectives and offer appropriate financial consultancy.\n\nRequirements:\n\nBachelor degree holder or above in all disciplines\nInitiative, sincere and a good team player\nProficiency in Chinese and English\nGood communication and interpersonal skills\nArticulate and detail oriented, ability to multitask in a fast paced environment.\u00a0\n\n\n\nWe offer a competitive salary and benefits package and the professional advantages of a dynamic environment that supports your development and recognizes your achievements.\n\nInterested individuals please send your detailed resume and expected salary by clicking\u00a0\"Apply Now\". Only candidates who are authorized to work in Hong Kong will be considered.\n\nAll personal data provided will only be used for recruitment purpose only.\nInformation of candidates not selected will be destroyed in 3 months.", "employment_types": ["Full Time", "Permanent"], "selling_points": ["on the job training, continuous studying subsidy", "portfolio/ asset management experience is a plus", "To be a future leader"], "locations": ["Quarry Bay"], "categories": ["Marketing / Public Relations", "Others", "Management", "Management Trainee", "Banking / Finance", "Asset Management"], "post_time": "2022-01-16T03:20:07Z", "salary": {"currency": null, "max": null, "min": null, "period": "monthly", "term": null}, "salary_visible": false, "title_keywords": ["graduate trainee"], "responsibilities": ["investment strategies", "preparing investment portfolio", "global market analysis", "develop", "investment proposal", "portfolio review report", "manage client\u2019s portfolios", "asset management"], "requirements": {"degrees": ["bachelor degree holder"], "majors": [], "languages": ["english", "chinese"], "language_level": ["proficiency"], "hard_skills": ["dynamic"], "soft_skills": ["good team player", "dynamic environment", "sincere", "detail oriented", "communication and interpersonal skills", "articulate", "ability to multitask", "initiative", "detailed"], "languages_combined": [{"language": "english", "language_level": ["proficiency"]}, {"language": "chinese", "language_level": ["proficiency"]}]}, "experience_required": {"duration": [], "field": []}}, {"job_id": "100003009049484", "location_code": "hk", "company": "The Hong Kong Institute Of Bankers", "job_title": "Assistant Product Marketing Manager", "description": "Job Responsibilities\n\nDesign and implement short-term and long-term marketing plans to drive business growth, market position and penetration of Institute\u2019s products covering Certified Banker (CB), Enhanced Competency Framework (ECF) and Continuing Professional Development (CPD) programmes as well as awards & industry events.\nCarry out regular market research and benchmarking to analyse market needs for growth, new product launch and stakeholders\u2019 engagement.\u00a0\nWork closely with relevant teams to ensure the smooth execution of marketing plans, product portfolio and channel communications.\nWork closely with all teams to cater sales needs and leverage operation costs and marketing tools to maximise impact.\nProvide insights to management and respective teams to create suitable programmes and to maximise the Institute\u2019s competitive edge.\nCarry out any ad hoc project as assigned by management.\n\nJob Requirements\n\nUniversity degree holder or above, preferably in marketing or business discipline.\nMinimum 5 years of marketing experience, preferably in\u00a0banking and finance industry, or private education sector.\nEquipped with effective management skills, analytical abilities, sharp business acumen and high sense of self ownership, together with good communication and project management skills, and ability to handle multiple tasks.\nFluent in spoken English, Cantonese and Putonghua.\nMore experience candidates can be considered as Product Marketing Manager.\n\nInterested parties may send in your application together with a detailed resume stating your\u00a0academic results, present & expected salaries, date of availability\u00a0and contact phone number by clicking\u00a0\"Apply Now\"\n\nApplicants are welcomed to visit our website:\u00a0www.hkib.org\u00a0for further information about the institute.\n\n(All information provided will be treated in strict confidence and used solely for recruitment purposes)", "employment_types": ["Full Time", "Permanent"], "selling_points": ["Product Marketing", "Marketing plans to drive business growth", "Market research and benchmarking"], "locations": ["Sheung Wan"], "categories": ["Banking / Finance", "Others", "Marketing / Public Relations", "Marketing - Brand / Product Management", "Others"], "post_time": "2022-01-14T08:44:26Z", "salary": {"currency": null, "max": null, "min": null, "period": "monthly", "term": null}, "salary_visible": false, "title_keywords": ["product marketing manager", "assistant"], "responsibilities": ["provide insights", "management", "ad hoc", "marketing plans", "teams", "market research", "design", "costs", "analyse"], "requirements": {"degrees": ["university degree"], "majors": ["business", "marketing"], "languages": ["cantonese", "putonghua", "english"], "language_level": ["fluent"], "hard_skills": ["project management", "acumen"], "soft_skills": ["business acumen", "project management skills", "handle multiple tasks", "communication"], "languages_combined": [{"language": "cantonese", "language_level": ["fluent"]}, {"language": "putonghua", "language_level": ["fluent"]}, {"language": "english", "language_level": ["fluent"]}]}, "experience_required": {"duration": ["minimum 5 years"], "field": ["marketing", "education", "finance industry", "banking"]}}, {"job_id": "100003009049231", "location_code": "hk", "company": "Arrow Asia Pac Ltd", "job_title": "Head of Digital Platform - Asia Pacific", "description": "What You'll Be Doing\n\nResponsible for managing the sales efforts of their team and providing leadership towards the achievement of maximum profitability and growth in line with the company's vision. Represents the team internally and externally; ensures their department is exceeding expectations from both a vendor ad customer perspective. Manages the workforce by making decisions on workload and setting priorities for the team. Consistently recommends operational improvements, contributes to the strategic objectives and manages team effectiveness. Accurately forecasts and drives teams to manage opportunities and sales.\u00a0\nManagement: Manage the strategic and sales objectives for the sales teams and creates tactical solutions to meet/exceed objectives. Go on field sales account calls and supplier reviews to provide leadership towards the achievement of maximum profitability and growth. Manage manager and employee development, recruiting, hiring and training, performance reviews, salary administration, daily coaching and feedback, goal setting, development planning and performance management. Progressively and proactively manage development and performance issues. Deliver a high performing team.\nSales: Direct strategy that motivates sales teams to reach sales goals and deliver results. Maintain senior level relationships at customers, suppliers and Arrow corporate. Take on assigned projects and drives corporate initiatives. Through data analysis and past experience make solid decisions on strategy and direction. Direct value added sales opportunities by implementing supply chain, engineering, supplier, or service excellence strategies. Identifies and helps obtain branch goals.\nDevelop customer, supplier and vendor relationships: Strengthens Arrow's reputation by delivering service excellence and process efficiencies. Attend reviews and meetings. Increase management presence at customer accounts in order to achieve access to all levels of decision makers. Implement effective and practiced techniques for solving problems. Effectively communicate with all levels senior level contacts at customers, suppliers and Arrow corporate.\n\nWhat We Are Looking For\n\nRequires a minimum of 12 years of related experience with a 4 year degree\nProvides leadership to managers, supervisors and/or professional staff\nIs accountable for the performance and results of multiple related units\nDevelops departmental plans, including business, production and/or organizational priorities\nControls resources and policy formation in area of responsibility\nDecisions are guided by resource availability and functional objectives\nIdentifies applications of functional knowledge and existing methodologies to complex problems\u00a0\nManages large teams of professionals and/or junior managers", "employment_types": ["Full Time"], "selling_points": ["Regional sales position on eCommerce", "Minimum of 12 years of related exp.", "Develop customer, supplier and vendor relationship"], "locations": ["Not Specified"], "categories": ["Marketing / Public Relations", "Management", "Others"], "post_time": "2022-01-14T08:17:52Z", "salary": {"currency": null, "max": null, "min": null, "period": "monthly", "term": null}, "salary_visible": false, "title_keywords": ["head of digital platform"], "responsibilities": ["administration", "communicate with", "management", "teams", "develop", "data analysis", "providing leadership", "maintain", "plans", "planning"], "requirements": {"degrees": ["degree"], "majors": [], "languages": [], "language_level": [], "hard_skills": ["analysis", "vendor", "goal", "make", "go"], "soft_skills": ["organizational", "leadership", "accountable", "responsible"], "languages_combined": []}, "experience_required": {"duration": ["4 year", "minimum of 12 years"], "field": ["data analysis", "related"]}}, {"job_id": "100003009044677", "location_code": "hk", "company": "China State Construction International Holdings Limited", "job_title": "Investor Relations Manager", "description": "Assistant Investor Relations Manager / Investor Relations Manager\n\nResponsibilities:\nFormulate and implement ongoing investor relations plan to align with the Group\u2019s vision, mission and development strategies;\nPrepare corporate collaterals including Annual/Interim Report, management reports, press releases, etc.;\nHandle enquiries from investors, financial analysts and reporters promptly;\nArrange different kinds of investor relations and public relations activities, such as press conference and roadshow, and prepare related corporate materials;\nAnalyze and present financial trends, competitor behaviors, shareholder issues and anything else that could impact and expand the business.\nMonitors analyst reports, represents the views of the investor community to the management in the development of corporate strategy;\nHandle ad-hoc assignments as required.\nRequirements:\nDegree Holder preferably in finance, economics, public relations, communications, or related business-related discipline, with both HK and overseas education background would be an advantage;\nMinimum 3 years of years\u2019 solid IR experience in listed companies,\nProven excellent verbal and written communication skills in Cantonese, Putonghua and English;\nGood communication and interpersonal skills, positive attitude and team player;\nExcellent skills in communication and crisis management.\nCandidates with more experience will be considered as \"Investor Relations Manager\"", "employment_types": ["Full Time", "Permanent"], "selling_points": ["(Assistant) Investor Relations Manager", "Degree Holder preferably in finance", "Minimum 3 years of years\u2019 solid IR experience"], "locations": ["Not Specified"], "categories": ["Banking / Finance", "Others", "Marketing / Public Relations", "Marketing - Marketing Communication", "Others"], "post_time": "2022-01-13T10:30:16Z", "salary": {"currency": null, "max": null, "min": null, "period": "monthly", "term": null}, "salary_visible": false, "title_keywords": ["manager"], "responsibilities": ["management", "ad-hoc assignments", "handle enquiries", "management reports", "reports", "plan", "report"], "requirements": {"degrees": ["degree holder"], "majors": ["business", "finance", "economics", "communications"], "languages": ["cantonese", "putonghua", "english"], "language_level": ["excellent"], "hard_skills": [], "soft_skills": ["communication skills", "positive attitude", "communication", "communication and interpersonal skills", "team player"], "languages_combined": [{"language": "cantonese", "language_level": ["excellent"]}, {"language": "putonghua", "language_level": ["excellent"]}, {"language": "english", "language_level": ["excellent"]}]}, "experience_required": {"duration": ["minimum 3 years"], "field": []}}, {"job_id": "100003009047145", "location_code": "hk", "company": "JPMorgan Chase Bank, N.A.", "job_title": "AWM APAC Regional Social Media & Advertising Team Lead", "description": "Description\n\nJ.P. Morgan Asset Management and Private Bank is seeking a talented\u00a0AWM\u00a0APAC Head of Social Media & Advertising\u00a0to join the Integrated Media and Performance Analytics team. The role's focus will be to build out the regional social media and advertising capabilities and strategy for 2 different lines of business - Asset Management and Private Bank.\n\nThe role will be tasked to oversee the design and implementation of our regional social media and advertising strategy, while providing the necessary local oversight for our agency partners and stakeholders. This person will oversee development of our end-to-end social media and advertising experience to build our brand and maximize client engagement throughout the purchase funnel. They will work closely with their global peers to develop and institute processes and drive best-practices adoption.\n\nThis individual will be responsible for working with local marketing managers and agency teams to design cohesive multi-touch, multi-channel programs aligned and delivering against the objectives of each marketing group. The successful individual will possess a strong understanding of the APAC social media landscape and working knowledgeof the mechanics of social media within larger multichannel campaigns. This person will also work with digital and design specialists, senior management, as well as analytics teams in the optimization of these campaigns.\n\nThe individual should be performance driven and analytically inclined. Experience building direct and indirect (agency) teams is important, as are project management and interpersonal skills. With a successful model in place in the other parts of the globe, this individual will be key in establishing the Integrated Media Team's presence in the APAC region.\n\nResponsibilities Include\n\nPartner with stakeholders, subject matter experts (SMEs) and the relevant digital teams to deliver engaging digital experiences for various audiences and client segments\nDesign and execute social media campaigns working with cross-functional teams to deliver exceptional client engagement across a suite of owned-media properties\nCollaborate with marketing partners to ensure a seamless and coordinated social media and advertising support\nDefine campaign KPIs and leverage campaign analytics to determine success criteria, efficacy and ongoing optimization opportunities\nDeliver measurable improvements against agreed upon KPIs and define best practices by ongoing measurement and documentation\nManage the sourcing and creation of content required to deliver engaging social media experiences\nPartner with other specialist digital teams for development, design/UX, content, analytics to support social media efforts\nDirect a team of social media specialists to create, build, and publish across our digital channels\nSupport strategy definition, supervise the planning and ongoing activities including maintaining the quality and consistency across all digital externally facing properties and communications\nQualifications\n\nAt least 7 years of social media and/or advertising experience, including the development of strategy, media buying, and tactical optimization of channels\nExperience in the development and management of internal and agency teams\nMedia agency side experience is a big plus, preferably on brands with a performance marketing mindset\nKnowledge of local social media platforms (WeChat, Snowball, WhatsApp, Instagram, etc.)\nStrong time management and organization skills; able to maintain a high quality of work in a deadline driven environment\nProactive with a high level of attention to detail; quick learner who can adapt to changing priorities\nA strong understanding of social media best practices and related digital user experience\nTeam player, with a very strong work ethic and high energy level\nMust demonstrate initiative and ownership of assigned responsibilities\nAbility to translate technical or SME specific information to communicate business impact / benefit effectively to non-technical stakeholders\nMust be able to establish strong relationship with the business and project stakeholders to ensure that business goals are met\nExcellent communication skills and the ability to interact confidently with all levels of management\nJPMorgan Chase & Co., one of the oldest financial institutions, offers innovative financial solutions to millions of consumers, small businesses and many of the world's most prominent corporate, institutional and government clients under the J.P. Morgan and Chase brands. Our history spans over 200 years and today we are a leader in investment banking, consumer and small business banking, commercial banking, financial transaction processing and asset management.\n\nWe recognize that our people are our strength and the diverse talents they bring to our global workforce are directly linked to our success. We are an equal opportunity employer and place a high value on diversity and inclusion at our company. We do not discriminate on the basis of any protected attribute, including race, religion, color, national origin, gender, sexual orientation, gender identity, gender expression, age, marital or veteran status, pregnancy or disability, or any other basis protected under applicable law. In accordance with applicable law, we make reasonable accommodations for applicants' and employees' religious practices and beliefs, as well as any mental health or physical disability needs.\n\nThe health and safety of our colleagues, candidates, clients and communities has been a top priority in light of the COVID-19 pandemic. JPMorgan Chase was awarded the \"WELL Health-Safety Rating\" for all of our 6,200 locations globally based on our operational policies, maintenance protocols, stakeholder engagement and emergency plans to address a post-COVID-19 environment.\n\nAs a part of our commitment to health and safety, we have implemented various COVID-related health and safety requirements for our workforce. These requirements may include sharing information in the firm's vaccine record tool, vaccination or regular testing, mask wearing, social distancing and daily health checks. Requirements may change in the future with the evolving public health landscape. JPMorgan Chase will consider accommodation requests.\n\nEqual Opportunity Employer/Disability/Veterans\n\nInterested parties please click \u201cApply Now\u201d to apply job.\n\nAll applications applied through our system will be delivered directly to the advertiser and privacy of personal data of the applicant will be ensured with security.", "employment_types": ["Full Time"], "selling_points": [], "locations": ["Not Specified"], "categories": ["Marketing / Public Relations", "Marketing - Market Research", "Marketing - Marketing Communication", "Others"], "post_time": "2022-01-14T02:27:15Z", "salary": {"currency": null, "max": null, "min": null, "period": "monthly", "term": null}, "salary_visible": false, "title_keywords": ["lead"], "responsibilities": ["collaborate with", "business goals", "social media platforms", "quality", "design", "communication", "purchase", "maintain", "sme", "plans", "senior management", "advertising", "social media campaigns", "maintaining", "teams", "implementation", "measurement", "develop", "user experience", "testing", "banking", "kpis", "social media", "management", "transaction processing", "documentation", "cross-functional teams", "maintenance", "policies", "project management", "asset management", "planning"], "requirements": {"degrees": [], "majors": [], "languages": [], "language_level": [], "hard_skills": ["small", "plus", "maintenance", "wechat", "project management", "whatsapp", "make", "snowball", "documentation", "focus", "processing"], "soft_skills": ["initiative", "communication skills", "proactive", "responsible", "cohesive", "quick learner", "innovative", "project management", "diverse", "team player", "interpersonal skills", "attention to detail", "work ethic", "organization skills", "focus", "time management", "driven"], "languages_combined": []}, "experience_required": {"duration": ["at least 7 years"], "field": ["social media", "management", "advertising", "brand", "agency", "development", "related", "project management", "marketing", "media buying", "digital", "media"]}}, {"job_id": "100003009048215", "location_code": "hk", "company": "Good Food Technologies Limited", "job_title": "Marketing Manager", "description": "\nRare opportunity to join a fast growing, well-funded startup in a blue ocean market!\n\nIf you are passionate about transforming the F&B industry, and have proven experience in marketing - then look no further!\n\nAbout the job\n\u2022 Define and execute the marketing and comms activities according to our marketing plan\n\u2022 Generate innovative ideas to increase consumer awareness and following across key platforms\nLead key partners (marketing, creative, restaurant etc.) to ensure successful execution of marketing campaigns\n\u2022 Prepare and manage Marketing budgets\n\u2022 Track performance of all marketing campaigns\n\nAbout the talent\n\u2022 Prior experience in similar role\n\u2022 Experience in FMCG or F&B is preferred but not required\n\u2022 Strong understanding of consumer behavior and preferences in Asia\n\u2022 Experience running successful campaigns\n\u2022 Good knowledge on plant-based foods\n\u2022 High attention to detail\n\u2022 Excellent written & verbal communication skills\n\u2022 Fluent in English and Chinese\n\u2022 BSc or MSc in relevant field\n\nThe opportunity\n\u2022 Competitive compensation package for the right candidate\n\u2022 Influence direction of an up and coming brand / oversee strategy and execution across B2B and retail\nYou'll be one of our first 10 hires. Significant career growth opportunities - Upon proving yourself, you will lead our scale up and go-to-market into other geographies. (Greater Bay Area, Taiwan and South East Asia)\n\u2022 Dynamic working culture with great team spirit\n\u2022 Results oriented\n\n", "employment_types": ["Full Time"], "selling_points": [], "locations": ["Not Specified"], "categories": ["Admin & HR", "Others", "Marketing / Public Relations", "Marketing - General / Support", "Others"], "post_time": "2022-01-14T05:55:45Z", "salary": {"currency": null, "max": null, "min": null, "period": "monthly", "term": null}, "salary_visible": false, "title_keywords": ["marketing manager"], "responsibilities": ["budgets", "ideas", "communication", "marketing plan", "marketing campaigns"], "requirements": {"degrees": ["bsc"], "majors": [], "languages": ["english", "chinese"], "language_level": ["fluent"], "hard_skills": ["no", "go", "dynamic"], "soft_skills": ["communication skills", "team spirit", "creative", "dynamic", "attention to detail", "innovative", "passionate about"], "languages_combined": [{"language": "english", "language_level": ["fluent"]}, {"language": "chinese", "language_level": ["fluent"]}]}, "experience_required": {"duration": [], "field": ["f&b", "marketing", "fmcg"]}}, {"job_id": "100003009050349", "location_code": "hk", "company": "Abbott Laboratories Ltd.", "job_title": "Brand Manager \u2013 Nutritional Products", "description": "This position supports the team in driving the major product line business and market share growth. Key responsibilities include the followings:\n\n\nWork together with Marketing Manager to analyze customer and market data, develop marketing strategies to meet business objectives\nPlan, execute, monitor and evaluate various marketing programs including materials development, vendor management and merchandising activities to drive brand growth with control budget\nIndependently manage routine brand management responsibilities including A&P management, forecasting, product training, handling customer inquiries, etc\nMonitor sales performance, competitor moves and market trend on a regular basis with on time report for management review\nCollaborate cross-functionally across departments to drive brand growth\nWork closely with trade marketing & CRM team to deliver credible presentation / education to business partner and customer whenever necessary\nWork with ethical marketing/ affairs to identify the most compelling products claims of the brand based on research and technical materials\n\nRequirements:\n\nUniversity\u2019s Degree in Marketing or Business Management preferred\nAt least 5 years of brand management/ consumer marketing experience, preferably FMCG or Healthcare industry\nA team player with passion, good interpersonal, project management, analytical and presentation skills\nDemonstrate ability of working with and managing people in a complex changing environment to deliver value-added results to the organization\nFluent in spoken and written English and Chinese (Cantonese and Mandarin)\n\nInterested parties, please send your profile with present and\u00a0expected salary in Word to us by clicking the Apply Now button.\n\nPersonal data collected will be used for recruitment purposes only.", "employment_types": ["Full Time", "Permanent"], "selling_points": [], "locations": ["North Point"], "categories": ["Marketing / Public Relations", "Marketing - Brand / Product Management", "Marketing - General / Support", "Others"], "post_time": "2022-01-15T03:51:01Z", "salary": {"currency": null, "max": null, "min": null, "period": "monthly", "term": null}, "salary_visible": false, "title_keywords": ["manager"], "responsibilities": ["collaborate", "forecasting", "management", "control", "marketing strategies", "trade marketing", "customer inquiries", "sales performance", "budget", "monitor", "merchandising", "develop", "evaluate", "plan", "market data", "management review", "report"], "requirements": {"degrees": ["degree"], "majors": ["business", "marketing"], "languages": ["cantonese", "english", "chinese", "mandarin"], "language_level": ["fluent"], "hard_skills": ["business management", "project management"], "soft_skills": ["project management", "team player", "interpersonal", "presentation skills"], "languages_combined": [{"language": "cantonese", "language_level": ["fluent"]}, {"language": "english", "language_level": ["fluent"]}, {"language": "chinese", "language_level": ["fluent"]}, {"language": "mandarin", "language_level": ["fluent"]}]}, "experience_required": {"duration": ["at least 5 years"], "field": ["management", "fmcg", "brand", "marketing", "healthcare industry"]}}, {"job_id": "100003009044169", "location_code": "hk", "company": "AIA International Limited", "job_title": "Wealth Management Student Internship \u2013 \u5927\u5b78\u751f\u8ca1\u5bcc\u7ba1\u7406\u71df\u5546\u5be6\u7fd2 [ \u91cd\u9ede\u57f9\u8a13 2022 \u5e74\u5927\u5b78\u7562\u696d\u751f ( \u6b63\u5728\u672c\u5730\u5927\u5b78\u5c31\u8b80\u512a\u5148 ) ]", "description": "\u5be6\u7fd2\u76ee\u7684\uff1a\n\n\u70ba\u7562\u696d\u5f8c\u6b63\u5f0f\u6295\u5165\u5de5\u4f5c\u5148\u7a4d\u6975\u88dd\u5099\u81ea\u5df1\uff0c\u5feb\u901f\u638c\u63e1\u5de5\u4f5c\u898f\u5f8b\u53ca\u6280\u80fd\uff0c\u5960\u5b9a\u7a69\u56fa\u7684\u57fa\u790e\u53ca\u8cfa\u53d6\u984d\u5916\u6536\u5165\uff0c\u52a0\u5feb\u4e0a\u4f4d\u901f\u5ea6\u9020\u5c31\u51fa\u672a\u4f86\u7684\u6210\u529f\u4f01\u696d\u9818\u8896\u3002\n\n\u5be6\u7fd2\u5167\u5bb9\u7c21\u4ecb\uff1a\n\n\u9999\u6e2f\u5c45\u6c11\uff0c\u63a5\u53d7\u6b63\u5728\u9999\u6e2f\u5c31\u8b80\u7684 Final Year \u5927\u5b78\u751f ( 2022 \u5e74\u5927\u5b78\u7562\u696d\u751f ) \u7533\u8acb\n\u70ba\u5408\u8cc7\u683c\u5be6\u7fd2\u751f\u5b89\u6392\u53ca\u8cc7\u52a9\u53c3\u52a0 VTC IIQE \u724c\u7167\u8003\u8a66\u7372\u53d6\u57f7\u696d\u8cc7\u683c\n\u5927\u5b78\u751f\u71df\u5546\u5de5\u4f5c\u9ad4\u9a57 ( \u63d0\u4f9b\u4ee5\u6bcf\u55ae\u8a08\u5177\u5438\u5f15\u529b\u7684\u4f63\u91d1\uff0c\u591a\u9805\u7af6\u8cfd\u73fe\u91d1\u734e\u8cde ) \u53ca\u9818\u8896\u8a13\u7df4\n\u4e86\u89e3\u9999\u6e2f\u91d1\u878d\u5e02\u5834\u5be6\u6cc1\u53ca\u767c\u5c55\u524d\u666f\uff0c\u57f9\u990a\u5546\u696d\u7684\u654f\u611f\u5ea6\n\u5b78\u7fd2\u81e8\u5834\u61c9\u8b8a\u53ca\u8655\u7406\u62d2\u7d55\u7684\u8edf\u6280\u5de7\u3001\u91d1\u878d\u53ca\u91ab\u5b78\u76f8\u95dc\u77e5\u8b58\n\u63a1\u7528\u5718\u968a\u7cfb\u7d71\u5316\u57f9\u8a13\u6a5f\u5236\uff0c\u8b93\u5be6\u7fd2\u751f\u80fd\u5920\u9810\u5148\u5236\u5b9a\u53ef\u9810\u898b\u7684\u4e8b\u696d\u9577\u9060\u767c\u5c55\u76ee\u6a19\n\u5c07\u6703\u4ee5\u66ab\u53d6\u8cc7\u683c\u5b89\u6392\u65bc\u5927\u5b78\u7562\u696d\u5f8c\u8f49\u6b63\u4e26\u8c41\u514d\u9996\u8f2a\u9762\u8a66\n\n\u5e74\u8f15\u7684\u60a8\u4e5f\u53ef\u4ee5\u5728\u5927\u5b78\u7562\u696d\u524d\u7a81\u7834\u6536\u5165\u754c\u9650\uff0c\u800c\u60a8\u7684\u6536\u5165\u4ea6\u6703\u8ddf\u60a8\u7684\u4e8b\u696d\u6210\u5c31\u300c\u570b\u969b\u734e\u9805 MDRT \u767e\u842c\u5713\u684c\u6703\u300d\u76f4\u63a5\u639b\u920e\uff1a\n\n\u9054\u6210 MDRT \u8cc7\u683c\uff1a\u60a8\u7684\u5be6\u969b\u5e74\u5ea6\u4f63\u91d1\u6536\u5165 = HKD 419,800.00\n\u9054\u6210 COT \u8cc7\u683c\uff1a\u60a8\u7684\u5be6\u969b\u5e74\u5ea6\u4f63\u91d1\u6536\u5165\u00a0= HKD 1,259,400.00\n\u9054\u6210 TOT \u8cc7\u683c\uff1a\u60a8\u7684\u5be6\u969b\u5e74\u5ea6\u4f63\u91d1\u6536\u5165\u00a0= HKD 2,518,800.00\n\n\n\n-------------------------\n\n\u8fa6\u516c\u5ba4\u4f4d\u65bc\u9285\u947c\u7063\u4ea4\u901a\u65b9\u4fbf\u7684\u4e2d\u5fc3\u5730\u6bb5\u3002\n\nPersonal data will be collected for recruitment and business license related purpose only.\n\n", "employment_types": ["Internship"], "selling_points": [], "locations": ["Causeway Bay"], "categories": ["Marketing / Public Relations", "Others", "Sales, CS & Business Devpt", "Account Servicing", "Banking / Finance", "Wealth Management"], "post_time": "2022-01-15T19:11:32Z", "salary": {"currency": null, "max": null, "min": null, "period": "monthly", "term": null}, "salary_visible": false, "title_keywords": ["wealth management", "internship"], "responsibilities": ["personal data", "recruitment"], "requirements": {"degrees": [], "majors": [], "languages": [], "language_level": [], "hard_skills": ["iiqe"], "soft_skills": [], "languages_combined": []}, "experience_required": {"duration": [], "field": []}}, {"job_id": "100003009047342", "location_code": "hk", "company": "Aerosim (HK) Limited, HKSTP Acceleration Programme", "job_title": "Sales Executive", "description": "Responsibilities:\nPromote company products and services to the schools\nDevelop business\u00a0plans to grow business, optimize sales volume, sales revenue and profitability\nExplore resources to develop channel strategy and expand new market opportunities\nCultivate a strong and positive relationship with both potential and current customers\nHandle customers enquires and liaise with customers\nRequirements:\nDiploma or above in marketing or related discipline (Fresh graduate is welcome)\n1-2 years of relevant working experience is a plus\nHardworking team player and able to work under pressure\nGood analytical skills, communication and negotiation skills\nBasic knowledge and understanding of financial numbers and attention-to-details\nProblem solving capabilities to come up with strategic and effective solutions whenever appropriate\nStrong verbal and written communication skills in English and Chinese", "employment_types": ["Full Time"], "selling_points": ["Promote company products & services to the schools", "Diploma or above in marketing", "1-2 years of relevant working experience"], "locations": ["Shatin Area"], "categories": ["Sales, CS & Business Devpt", "Business Development", "Customer Service - Supervisor / Officer", "Marketing / Public Relations", "Others"], "post_time": "2022-01-14T02:54:44Z", "salary": {"currency": null, "max": null, "min": null, "period": "monthly", "term": null}, "salary_visible": false, "title_keywords": ["sales executive"], "responsibilities": ["liaise with", "business plans", "develop"], "requirements": {"degrees": ["fresh graduate", "diploma or above"], "majors": ["marketing"], "languages": ["english", "chinese"], "language_level": [], "hard_skills": ["problem solving capabilities", "plus", "basic", "analytical skills"], "soft_skills": ["communication skills", "analytical skills", "communication", "problem solving", "negotiation skills", "team player", "hardworking", "work under pressure"], "languages_combined": [{"language": "english", "language_level": []}, {"language": "chinese", "language_level": []}]}, "experience_required": {"duration": ["1-2 years"], "field": ["relevant working experience"]}}, {"job_id": "100003009042888", "location_code": "hk", "company": "Perfect Shape (Holdings) Limited", "job_title": "Digital Marketing Executive", "description": "Pursue a Career with Impact\n\nAt Perfect Medical, we dare to envision, and we strive for perfection.\n\nPerfect Medical is a leading Medical Beauty Group with over 100 treatment centers worldwide. With our passion for innovation and breakthroughs, our business\u2019 global footprint has been extending from Hong Kong Headquarter to China, Macau, Australia and Singapore with over 2,000 employees across regions.\n\nTo cope with the Company\u2019s rapid expansion, we are currently looking for high caliber and visionary candidates to join our team as\u00a0Digital Marketing Executive.\n\n\n\nResponsibilities:\n\nResponsible for the planning, implementation and management of the company\u2019s contents marketing plan for Facebook\u00a0\nDevelop creative ideas and copy-writing for brand promotions on social media platforms\nAnalyse online opinion to identify insights and to develop social media report\nAssist to prepare and\u00a0execute proposals on full range of digital deliverable for branded campaigns\n\nRequirements:\n\nBachelor Degree in Marketing or related disciplines\nDigital marketing with Media Buy experience\u00a0\n1-2 years experiences in Facebook/ Youtube paid promotion\u00a0\nGood communication skills, presentable, result-oriented and able to work under pressure\nGood command of both written and spoken English and Chinese\n\nWe offer competitive remuneration package and good prospects to the right candidates.\u00a0Interested parties please send your full resume with expected salary to apply.\u00a0Data collected will be kept confidential and used for recruitment purposes only.", "employment_types": ["Permanent"], "selling_points": ["Digital Marketing, Facebook", "Social Media, Media Buy, Media Advertisement", "Young and Energetic Environment, 5-Day Work"], "locations": ["Mong Kok"], "categories": ["Marketing / Public Relations", "Others", "Digital Marketing"], "post_time": "2022-01-12T09:09:00Z", "salary": {"currency": null, "max": null, "min": null, "period": "monthly", "term": null}, "salary_visible": false, "title_keywords": ["digital marketing executive"], "responsibilities": ["social media", "management", "social media platforms", "implementation", "develop", "marketing plan", "contents", "facebook", "report", "analyse", "develop creative ideas", "planning"], "requirements": {"degrees": ["degree", "bachelor"], "majors": ["related disciplines", "marketing"], "languages": ["english", "chinese"], "language_level": ["good command"], "hard_skills": ["facebook"], "soft_skills": ["work under pressure", "communication skills", "result-oriented", "presentable"], "languages_combined": [{"language": "english", "language_level": ["good command"]}, {"language": "chinese", "language_level": ["good command"]}]}, "experience_required": {"duration": ["1-2 years"], "field": ["digital marketing", "media"]}}, {"job_id": "100003009047156", "location_code": "hk", "company": "The Hong Kong Jockey Club", "job_title": "Marketing Officer (Wagering Product)", "description": "The Job\nYou will:\nassist in the execution of marketing campaigns to promote our horse racing products\nco-ordinate and work independently with multi internal and external stakeholders for product campaigns\nliaise and ensure quality deliverables in timely manner from advertising agencies, design house and printers, etc\ncompile and co-ordinate product information and racing content for each racing cycle\nprovide support to the team\u2019s operation and ad-hoc projects\nmonitor media effectiveness and customer response\nAbout You\nYou should have:\na degree with a minimum of 4 years marketing experience\ngood project management skills with attention to details and deadline\ngood communication and interpersonal skills\ngood command of both written and spoken English and Chinese\nproficiency in Microsoft Office Applications (e.g. Powerpoint, Excel, Word)\nknowledge of horse racing is an advantage\nTerms of employment\nThe level of appointment will be commensurate with qualifications and experience.\nHow to Apply\nPlease send your resume, complete with expected salary and job reference by clicking the Apply Now button\nWe are an equal opportunity employer. Personal data provided by job applicants will be used strictly in accordance with the Club's notice to employees and prospective employees relating to the Personal Data (Privacy) Ordinance. A copy of which will be provided immediately upon request.", "employment_types": ["Full Time"], "selling_points": ["Assist in the execution of marketing campaigns", "Knowledge of horse racing is an advantage", "Degree with a minimum of 4 years marketing exp."], "locations": ["Causeway Bay"], "categories": ["Marketing / Public Relations", "Marketing - Brand / Product Management", "Marketing - General / Support", "Others"], "post_time": "2022-01-14T07:14:09Z", "salary": {"currency": null, "max": null, "min": null, "period": null, "term": null}, "salary_visible": false, "title_keywords": ["marketing officer"], "responsibilities": ["liaise", "provide support", "advertising", "quality", "monitor", "design", "communication", "project management", "marketing campaigns", "personal data", "ad-hoc projects"], "requirements": {"degrees": ["degree"], "majors": ["marketing"], "languages": ["english", "chinese"], "language_level": ["good command"], "hard_skills": ["printers", "excel", "microsoft office", "word", "powerpoint", "project management"], "soft_skills": ["work independently", "project management skills", "timely", "communication and interpersonal skills", "attention to details"], "languages_combined": [{"language": "english", "language_level": ["good command"]}, {"language": "chinese", "language_level": ["good command"]}]}, "experience_required": {"duration": ["minimum of 4 years"], "field": ["marketing"]}}, {"job_id": "100003009046189", "location_code": "hk", "company": "Hong Kong Tourism Board", "job_title": "Assistant Manager, Trade Development", "description": "Responsibilities\n\nAssist the Manager to plan, co-ordinate and execute new cross-industry collaborative approaches and programmes that create and generate new business opportunities for travel trade partners in promoting Hong Kong.\nCo-ordinate with different teams in Head Office/overseas offices in formulating effective consumer and trade development programs in Hong Kong/overseas, such as travel missions, trade shows, familiarisation programs, in order to increase the awareness of Hong Kong and boost conversion of visitor\u2019s interests into business in accordance with the agreed strategic directions.\nMaintain close communication with Hong Kong travel trade stakeholders particularly the hotel sector so as to obtain their supports on HKTB\u2019s initiatives/local tactical activities and to facilitate their promotional efforts.\nMonitor progress on trade development programs as to ensure the most effective promotions are conducted.\nCoach and develop team members in the execution of their duties.\u00a0 Assist in their career development and ensure a succession plan is in place.\nAssist the Manager to manage the financial responsibility within the team for effective budgetary plan and control.\nProvide execution supports on ad-hoc marketing activities as assigned by the Manager.\n\nRequirements\n\nUniversity degree holder with at least 8 years of marketing/sales experience in travel industry, of which 2 years is at managerial level\nGood knowledge of travel industry and tourism products in Hong Kong, preferably with solid network of business contacts\nAnalytical, strong problem solving and project management skills\nGood report writing and verbal presentation skills; fluency in Chinese and English\nMature, multi-tasked, able to work independently and under pressure\nWilling to travel occasionally\n\nInterested parties please send resume with present and expected salary by clicking \u201cApply Now\u201d.\n\nPersonal data provided by job applicants will be used strictly in accordance with our personal data policies, a copy of which will be provided upon request.\u00a0 Applicants may send a request for a copy of the Personal Information Collection Statement pertaining to Job\u00a0Application.\u00a0 Only shortlisted applicants will be contacted. \u00a0All Information received will be kept in strict confidence and\u00a0used\u00a0only for employment-related purpose.\n\nWe are an equal opportunities employer.", "employment_types": ["Full Time", "Permanent"], "selling_points": ["Plan new cross-industry collaborative programmes", "Formulate effective trade development programs", "Trade missions and trade shows"], "locations": ["Tin Hau"], "categories": ["Hospitality / F & B", "Hospitality / Hotel Services", "Marketing / Public Relations", "Others", "Tourism / Travel Agency"], "post_time": "2022-01-13T09:53:42Z", "salary": {"currency": null, "max": null, "min": null, "period": "monthly", "term": null}, "salary_visible": false, "title_keywords": ["assistant manager,"], "responsibilities": ["ad-hoc", "control", "development programs", "monitor progress", "co-ordinate with", "business opportunities", "teams", "develop", "communication", "maintain", "plan", "career development"], "requirements": {"degrees": ["university degree"], "majors": ["marketing"], "languages": ["english", "chinese"], "language_level": ["fluency"], "hard_skills": ["problem solving", "project management"], "soft_skills": ["work independently", "under pressure", "project management skills", "mature", "problem solving", "presentation skills", "multi-tasked"], "languages_combined": [{"language": "english", "language_level": ["fluency"]}, {"language": "chinese", "language_level": ["fluency"]}]}, "experience_required": {"duration": ["at least 8 years", "2 years"], "field": ["managerial", "marketing"]}}, {"job_id": "100003009043585", "location_code": "hk", "company": "Agile Sources Limited", "job_title": "Graduate Trainee", "description": "District:Kwun Tong\n\nIndustry: Import and Export Trades\n\nResponsibilities:\n\nResponsible for various daily operation tasks as assigned by different departments\nGain valuable work experience and exposure via full mentorship and coaching\nExplore individual's potential and career aspiration through participating in cross-functional assignment\n\nRequirements:\n\nBachelor Degree in any discipline\nFluent Cantonese ; Fluent Putonghua ; Fluent English\nAble to read & write Chinese ; Able to read & write English\nAble to handle multi-tasks and meet tight deadlines\nProficient in MS office application\n\nEmployment Terms:\n\n$12,000 - $13,000 per month, with Medical Insurance and On-the-job Training\nMon to Fri: 9:00AM-6:00PM, 5 working days per week\n\nPlease send your resume and job reference to email\u00a0or Fax: 34878408.", "employment_types": ["Full Time"], "selling_points": ["Bachelor Degree in any discipline", "Responsible for various daily operation tasks", "Based on skill sets"], "locations": ["Kwun Tong"], "categories": ["Admin & HR", "Others", "Marketing / Public Relations", "Others", "Others", "Student / Fresh Graduate / No Experience"], "post_time": "2022-01-12T23:19:11Z", "salary": {"currency": null, "max": null, "min": null, "period": "monthly", "term": null}, "salary_visible": false, "title_keywords": ["graduate trainee"], "responsibilities": ["daily operation"], "requirements": {"degrees": ["degree", "bachelor"], "majors": [], "languages": ["cantonese", "putonghua", "english", "chinese"], "language_level": ["fluent"], "hard_skills": ["ms office"], "soft_skills": ["meet tight deadlines", "multi-tasks"], "languages_combined": [{"language": "cantonese", "language_level": ["fluent"]}, {"language": "putonghua", "language_level": ["fluent"]}, {"language": "english", "language_level": ["fluent"]}, {"language": "chinese", "language_level": []}]}, "experience_required": {"duration": [], "field": []}}, {"job_id": "100003009048889", "location_code": "hk", "company": "Livi Bank Limited", "job_title": "Assistant Product Marketing Manager", "description": "Responsibilities:\n\nMonitor financial product P&L delivery, evaluate the effectiveness of the campaign, and conduct continuous optimization to improve product performance\nGrowth Marketing on B2C financial products for both in-base and external\nDevelop marketing communication plan for B2C financial products\nCollaborate with other teams to ensure alignment of activation plans with overall growth strategies\nManage creative content output, including but not limited to app content, website, brand video, social media, and digital banners\nCollaborate with technology scrum team on product features enhancement and user journey optimization\nMonitor market trends and conduct insightful business analysis\nRequirements:\n\nDegree or above in any discipline\n\nAt least 4 years experience; experience in digital / e-commerce platform, start-up or financial technology industry an advantage\nHands-on experiences in business operations and integrated marketing programme\nBasic knowledge regarding financial products (i.e. Deposits & Payment, Investment & Insurance, Lending, etc.)\nAbility in designing customer journeys via diagrams (e.g. draw.io, lucidchart, etc.)\nKnowledge in campaign performance and customer profile analysis (e.g. Tableau, Power BI)\nExcellent command of both spoken and written English and Chinese, including Putonghua\n\nWe offer competitive salary package to the successful candidate.\u202f If you are interested in joining this exciting team, please send your full resume including your\u202fCURRENT\u202fand\u202fEXPECTED\u202fsalary for our consideration.", "employment_types": ["Full Time", "Permanent"], "selling_points": ["Virtual Banking/ FinTech.", "Dynamic & Innovative Working Culture", "Great Career Prospects"], "locations": ["Quarry Bay"], "categories": ["Banking / Finance", "Retail Banking", "Marketing / Public Relations", "Marketing - Brand / Product Management", "Others"], "post_time": "2022-01-14T07:36:24Z", "salary": {"currency": null, "max": null, "min": null, "period": "monthly", "term": null}, "salary_visible": false, "title_keywords": ["product marketing manager", "assistant"], "responsibilities": ["collaborate with", "social media", "creative content", "monitor", "teams", "p&l", "develop", "evaluate", "communication", "website", "banners", "plan", "business analysis", "plans"], "requirements": {"degrees": ["degree or above"], "majors": [], "languages": ["putonghua", "english", "chinese"], "language_level": ["excellent"], "hard_skills": ["bi", "basic", "io", "e-commerce", "customer journeys", "analysis", "tableau"], "soft_skills": ["hands-on"], "languages_combined": [{"language": "putonghua", "language_level": ["excellent"]}, {"language": "english", "language_level": ["excellent"]}, {"language": "chinese", "language_level": ["excellent"]}]}, "experience_required": {"duration": ["at least 4 years"], "field": ["e-commerce", "business", "marketing", "digital", "financial"]}}, {"job_id": "100003009045356", "location_code": "hk", "company": "MakerBay Foundation Limited", "job_title": "Marketing And Public Relations Manager", "description": "\nMakerBay Foundation is a fast growing NGO. We are seeking a Marketing & PR Manager to play an integral role in public/media relations, communication, and content creation for our organisation.\u00a0\n\nIn this role, you will drive the promotion of our programs, such as our newly launched \u2018AI Community Innovation program\u2019. The work requires a high level of creativity, attention to detail along with good communication skills .\n\nYou will report directly to the Executive Director of MakerBay. The working environment is collaborative. As a rapidly growing organisation, there are many opportunities to learn new professional skills and grow as an individual.\n\nKey Responsibilities:\n\u2022 Drive media engagement strategies\u00a0\n\u2022 Create and publish content for upcoming programs and program highlights\u00a0\n\u2022 Develop storytelling to highlight our impact and our beneficiaries testimonials\u00a0\n\u2022 Create partnerships with other organisations and NGOs to promote our programs\u00a0\n\u2022 Manage social media\u00a0\n\u2022 Organise PR events\u00a0\n\u2022 Grow our community of makers\u00a0\nBasic Requirements:\n3+ years of marketing & PR experience\n\u2022 Ability to guide team members and external partners to create content\n\u2022 Strong written and verbal communication skills\nFluency in Cantonese and English (spoken/written)\n\nSoft skills required for the role:\n\u2022 Team player\u00a0\n\u2022 Adaptive and flexible\u00a0\n\u2022 Excellent communicator - as you will be interacting with different stakeholders\n\u2022 Pro-active - you will have a lot of room to express your potential\u00a0\n\u2022 Creative - we want to hear about all your crazy ideas!\nInterested parties please click Apply Now to apply job.\n\n", "employment_types": ["Part Time"], "selling_points": [], "locations": ["Not Specified"], "categories": ["Admin & HR", "Others", "Marketing / Public Relations", "Marketing - General / Support", "Others"], "post_time": "2022-01-13T07:40:50Z", "salary": {"currency": null, "max": null, "min": null, "period": "hourly", "term": null}, "salary_visible": false, "title_keywords": ["manager"], "responsibilities": ["social media", "develop"], "requirements": {"degrees": [], "majors": [], "languages": ["cantonese", "english"], "language_level": ["fluency"], "hard_skills": ["basic"], "soft_skills": ["flexible", "communication skills", "pro-active", "team player", "creative", "communicator"], "languages_combined": [{"language": "cantonese", "language_level": ["fluency"]}, {"language": "english", "language_level": ["fluency"]}]}, "experience_required": {"duration": ["3+ years"], "field": ["pr", "marketing"]}}, {"job_id": "100003009046840", "location_code": "hk", "company": "LIEBHERR-SINGAPORE PTE LTD.", "job_title": "SALES EXECUTIVE (Tower Crane)", "description": "Responsible for the sales and rental of our extensive range of top slewing & bottom slewing cranes in Hong Kong & Macau.\n\nRequirements:\n\n\nMinimum Higher Diploma in Engineering & Marketing\nMinimum 2 years in marketing and sales in construction machinery, preferably in regional markets\nExperience in working with client at multiple levels\nHighly organised and motivated team player with good interpersonal skills\nAble to prepare technical & commercial tenders\nGood computer literacy\nGood command of spoken/writing English\nAble to commence work at short notice\nWith Driving License (1) are preferably\nResponsibilities:\n\n\nIdentify sales leads and potential markets to achieve sales target\nAcquire new clients & maintain existing customers\nLiaise and build close rapport with customers at all levels\nIdentify the needs of customers & extend professional advice/solutions\nPrepare quotations, sales presentations, sales forecast and marketing plan\nReport on the trends in the industry\nLiaison with respective project/engineering departments and factories on project, technical and engineering matters\nWe operate on a 5-day workweek and offer attractive salary with comprehensive benefits package to the right candidate. Location in Ping Che, Fanling, New Territories. Interested parties please fax resume expected salary and enclose supporting testimonials and certificates to 2830 6999 or email Apply Now\u00a0.", "employment_types": ["Full Time"], "selling_points": [], "locations": ["Shatin Area"], "categories": ["Sales, CS & Business Devpt", "Business Development", "Marketing / Public Relations", "Others", "Others"], "post_time": "2022-01-14T01:30:53Z", "salary": {"currency": null, "max": null, "min": null, "period": "monthly", "term": null}, "salary_visible": false, "title_keywords": ["sales executive"], "responsibilities": ["liaise", "sales target", "presentations", "marketing plan", "maintain", "forecast", "report"], "requirements": {"degrees": ["diploma"], "majors": ["marketing", "engineering"], "languages": ["english"], "language_level": ["good command"], "hard_skills": [], "soft_skills": ["computer literacy", "motivated", "interpersonal skills", "organised", "team player"], "languages_combined": [{"language": "english", "language_level": ["good command"]}]}, "experience_required": {"duration": [], "field": []}}, {"job_id": "100003009044354", "location_code": "hk", "company": "Hong Kong Disneyland", "job_title": "Senior Event Services Manager", "description": "Job Summary:\nWorking closely with event sales teams in each market, the job holder will be responsible for overall management of Event Services team and deliver the highest quality service at Disney standard to various kinds of Business Solutions & Events (BS&E) events, including corporate events, wedding events, and social catering events.\nResponsibilities:\nLead a team of Event Services professionals to manage and deliver various types of BS&E events that take place in the resort hotels and in Hong Kong Disneyland Park, and ensure the team consistently offer world-class level of service to drive client and guest satisfaction for each event;\nDrive creation and capturing of upselling/ cross-selling opportunities during the course of event management and delivery with each client, and contribute to revenue generation under overall BS&E team;\nLead and support the team on problem solving and solution formulation during the event delivery process, when there are conflicts/ inconsistency among clients\u2019 requests, standards/ requirement from internal stakeholders, available resources, government regulations, etc.;\nLead the team to maintain high standard of storage and upkeep for key reusable amenities and props for BS&E event formats, and/ or to request replenishment of consumable items when necessary, in close collaboration with different vendors and internal partners;\nDrive knowledge management efforts among the team, to ensure all team members have the training and resources to carry out their current responsibilities and get ready for more, as well as continuous product, process, systems and operational knowledge refresh;\nContinuously explore ways to streamline and improve event management and delivery processes, to improve work efficiency and quality;\nAct as a primary internal point of contact for the team in terms of different operational issues, or cross-department projects/initiatives.\nBasic Qualifications:\nBachelor degree or above;\nAt least 7 years of event management experience with a luxury hotel/ resort/ venue, with extensive knowledge in hospitality management, food & beverage and banquet catering operations.\nExperience with operational teams within HKDL and/ or experience in handling sizable groups and events would be an advantage;\nDemonstrated track-record and ability to lead a team;\nBe able to work independently and under pressure, in an ever-changing business environment;\nExcellent presentation, problem solving, negotiations and coaching skills;\nExcellent written (English and Chinese) and verbal (English, Cantonese, Mandarin) communication skills.\nAdditional Information:\nSUBMITTING YOUR APPLICATION\nAfter clicking \u201cApply for this job\u201d below, the employment application will open in a new window. Please complete ALL pages of the application in ENGLISH by clicking \u201cNext\u201d on each page, then \u201cSubmit\u201d on the final page.\n#LI-GN1 HKProfessional", "employment_types": ["Full Time"], "selling_points": ["Lead and support the team on problem solving", "Bachelor degree or above", "7 years of event management experience"], "locations": ["Lantau Island"], "categories": ["Marketing / Public Relations", "Management", "Public Relations - Event Management", "Others"], "post_time": "2022-01-13T03:49:23Z", "salary": {"currency": null, "max": null, "min": null, "period": "monthly", "term": null}, "salary_visible": false, "title_keywords": ["manager"], "responsibilities": ["regulations", "management", "operations", "systems", "quality", "teams", "replenishment", "communication", "lead a team", "maintain", "contact", "support the team", "catering"], "requirements": {"degrees": ["degree or above", "bachelor"], "majors": [], "languages": ["cantonese", "english", "chinese", "mandarin"], "language_level": ["excellent"], "hard_skills": ["problem solving", "basic"], "soft_skills": ["communication skills", "work independently", "under pressure", "responsible", "changing business environment", "problem solving", "extensive", "presentation", "world-class"], "languages_combined": [{"language": "cantonese", "language_level": ["excellent"]}, {"language": "english", "language_level": ["excellent"]}, {"language": "chinese", "language_level": ["excellent"]}, {"language": "mandarin", "language_level": ["excellent"]}]}, "experience_required": {"duration": ["at least 7 years"], "field": ["food", "management"]}}, {"job_id": "100003009038932", "location_code": "hk", "company": "The Independent Schools Foundation Academy Ltd", "job_title": "Senior Officer, Communications and Community (Ref: SO/C&C_20220111_jdb)", "description": "Candidate with less experience will be considered as\u00a0Assistant\u00a0Membership Executive\n\nResponsibilities\n\nHandle membership enquires\nProcess new member applications\nManage membership data\nAssist in Club\u2019s events and activities if assigned\n\nRequirements\n\nUniversity degree holder in hospitality management or related discipline\nGood interpersonal skills and strong administration skills\nProficiency in computer software application\nProficiency in written & spoken English and Chinese\nA mature self-starter who is customer orientated, reliable and pays attention to detail at all times\nWe offer career progression, attractive remuneration and associated benefits.\u00a0Free shuttle bus service will be provided and only 15 minutes ride from MTR station. Please apply with\u00a0full resume\u00a0and\u00a0expected salary, in the strictest of confidence to\u00a0Ms Sanda Chan, Director of Human Resources, 139 Tai Au Mun Road, Clearwater Bay, New Territories, Hong Kong\u00a0or\u00a0click \"Apply Now\"\u00a0to submit your application or\u00a0fax to 2264 0436.\nFor other vacancies, please visit our Club website: www.cwbgolf.org\u00a0\n(Personal data collected from applicants is for recruitment purposes)", "employment_types": ["Full Time", "Permanent"], "selling_points": ["Manage all school portals and platforms", "Bachelor Degree in Communications, Journalism", "Minimum 4 years of experience"], "locations": ["Pok Fu Lam"], "categories": ["Media & Advertising", "Editorial / Journalism", "Marketing / Public Relations", "Marketing - Marketing Communication", "Others"], "post_time": "2022-01-11T08:12:36Z", "salary": {"currency": null, "max": null, "min": null, "period": "monthly", "term": null}, "salary_visible": false, "title_keywords": ["senior officer"], "responsibilities": ["data"], "requirements": {"degrees": ["university degree"], "majors": ["hospitality management"], "languages": ["english", "chinese"], "language_level": ["proficiency"], "hard_skills": [], "soft_skills": ["administration skills", "mature", "interpersonal skills", "attention to detail", "reliable"], "languages_combined": [{"language": "english", "language_level": ["proficiency"]}, {"language": "chinese", "language_level": ["proficiency"]}]}, "experience_required": {"duration": [], "field": []}}, {"job_id": "100003009044862", "location_code": "hk", "company": "Big Big Channel Limited", "job_title": "DIGITAL MARKETING EXECUTIVE", "description": "Job Responsibilities:\nAssist in all editorial responsibilities relating to school publications, annual calendars, circulars, marketing and media material, digital content and any other material as required to support various departments and stakeholders of the school;\nManage all school portals and platforms;\nMultimedia content creation or editing; \u00a0\nAssist with school, media and public events;\nInternal and external coordination and relations with stakeholders and vendors; \u00a0\nNews monitoring and alert;\nHandling of general enquiries;\nAny other duties as assigned by the Senior Manager and Head of Communications; and\nAlign with and contribute to the overall strategy goals of the Communications and Communities office.\nRequirements:\nBachelor Degree in Communications, Journalism, Translation or related disciplines;\nMinimum 4 years of experience in marketing communications is preferable;\nDigital content and marketing skills a plus;\nExcellent written and verbal communication skills in English and Chinese (Cantonese and Putonghua);\nWilling to work overtime or weekends if required; and\nWell organized, self-motivated and a good team player.\nThe ISF Foundation, Academy & Pre-School are committed to ensuring safety and well-being of our students. We hold high standards of recruitment practices with specific attention to child protection. All applicants must be willing to undergo relevant background checks and screenings.\u00a0\u00a0\nFree Shuttle Bus travelling to and from The ISF Academy will be provided:\nRoute: North Point > Admiralty Centre > Causeway Bay > Aberdeen > The ISF Academy\nApplication Deadline: 28 January 2022\nRemuneration will commensurate with qualifications and experience. We will offer an attractive benefits package including medical, life insurance, and opportunities for professional development and continuing education to the right candidate. Please submit your application by completing the Application Form, Reference Check Statement which could be downloaded from our website: www.isf.edu.hk together with full Curriculum Vitae and Covering Letter. Please quote with our \u201cRef: no.\u201d by email via \"Apply Now\". \u00a0\u00a0\nPersonal data is collected for employment purposes only.", "employment_types": ["Full Time", "Permanent"], "selling_points": [], "locations": ["Not Specified"], "categories": ["Marketing / Public Relations", "Others", "Digital Marketing", "E-commerce", "Business Development"], "post_time": "2022-01-13T06:28:31Z", "salary": {"currency": null, "max": null, "min": null, "period": "monthly", "term": null}, "salary_visible": false, "title_keywords": ["digital marketing executive"], "responsibilities": ["any other duties", "editing", "monitoring", "coordination"], "requirements": {"degrees": ["degree", "bachelor"], "majors": ["journalism", "related disciplines", "communications"], "languages": ["cantonese", "putonghua", "english", "chinese"], "language_level": ["excellent"], "hard_skills": ["no", "translation", "marketing skills", "plus"], "soft_skills": ["communication skills", "work overtime", "self-motivated", "good team player", "well organized", "committed"], "languages_combined": [{"language": "cantonese", "language_level": ["excellent"]}, {"language": "putonghua", "language_level": ["excellent"]}, {"language": "english", "language_level": ["excellent"]}, {"language": "chinese", "language_level": ["excellent"]}]}, "experience_required": {"duration": ["minimum 4 years"], "field": ["marketing communications"]}}, {"job_id": "100003009046536", "location_code": "hk", "company": "MoneyHero Global Limited", "job_title": "Account Executive (Full-time internship; Part-time also welcome; Hybrid work style)", "description": "Job Duties\n\nResponsible for planning & executing product development and marketing campaigns (ATL/BTL) of various product lines\nAssist in managing all aspects of marketing activities to support brand initiatives and business needs\nHandle the development of marketing collaterals to ensure consistency of campaign message across multi-platforms\nResponsible for social media marketing via different platforms (e.g. Facebook, Instagram) and content creation for online marketing materials (e.g. edm, website content, e-commerce platform content)\nWork closely with various internal departments for program implementation\nParticipate in ad-hoc assignments as required\n\nJob Requirements\n\nDegree holder in Marketing or related discipline\nMinimum 5 years or above solid experience in food and beverage marketing field\nExperience with operating social media would be an advantage\nGood communication, planning and interpersonal skills\nProactive, accountable, detailed-oriented and willing and able to apapt to a fast-paced environment\nProficiency in MS Office (Excel, Powerpoint) and Chinese Word Processing\nExcellent command of both written and verbal communication skills in English and Chinese\nCandidates with less experience will be considered as Marketing Executive\n\nInterested persons are invited to send in an application letter with a full resume, stating expected salary and date available for commencement to\u00a0Human Resources Manager, Cuisine Continental Group (HK) Ltd, 27/F Casey Aberdeen House, 38 Heung Yip Road, Wong Chuk Hang, Hong Kong or e-mail it to us\n\n(Personal data collected will be treated in strict confidence and for recruitment purpose only)", "employment_types": ["Full Time", "Internship"], "selling_points": ["full time internship, account executive", "Proficient in Web Analytics technologies e.g. GA", "Capable of managing multiple deliverables"], "locations": ["Tin Hau"], "categories": ["Marketing / Public Relations", "Others", "Sales, CS & Business Devpt", "Account Servicing"], "post_time": "2022-01-13T13:31:55Z", "salary": {"currency": null, "max": null, "min": null, "period": "monthly", "term": null}, "salary_visible": false, "title_keywords": ["account executive", "internship"], "responsibilities": ["social media", "edm", "ad-hoc assignments", "marketing collaterals", "website", "implementation", "executing", "marketing campaigns", "marketing materials", "facebook", "e-commerce platform", "planning"], "requirements": {"degrees": ["degree holder"], "majors": ["marketing"], "languages": ["english", "chinese"], "language_level": ["proficiency", "excellent"], "hard_skills": ["excel", "chinese word processing", "powerpoint", "ms office"], "soft_skills": ["communication skills", "confidence", "fast-paced environment", "accountable", "communication", "interpersonal skills", "proactive", "detailed"], "languages_combined": [{"language": "english", "language_level": ["excellent"]}, {"language": "chinese", "language_level": ["proficiency", "excellent"]}]}, "experience_required": {"duration": ["minimum 5 years"], "field": ["food", "marketing", "social media"]}}, {"job_id": "100003009046998", "location_code": "hk", "company": "IBM China / Hong Kong Ltd", "job_title": "Workforce Management Lead", "description": "eKos_connect is a SaaS provider connecting financial institutions with their digital partners and affiliates. Aiming to accelerate and expand the digital financial ecosystem across Asia, eKos_connect is the largest independent Tech-Fin platform in Asia with over 200 integrations and 4 million consumers connected through our partnership network. eKos_connect was launched in 2019 and is part of Hyphen Group, Asia\u2019s leading financial management platform.\n\nWe are a group of professionals in technology and finance, passionate about growing Asia's digital financial ecosystem so as to accelerate the region's digital maturity and growth, and improve the financial health of people across Asia.\n\nTHE ROLE\n\nCampaign Management:\n\nAids in the creation of affiliate plan objectives and strategies\nAble to create, maintain and execute affiliate plan based on various campaign initiatives\nCoordinate with internal stakeholders across different functions to ensure campaign details are up to date\nMaintain timely delivery updates of marketing campaigns to external stakeholders, designated for promotional and recurring campaigns\nOptimise campaign execution procedures in current various environment platforms - content stack and affiliate connect\nWork closely with internal stakeholders in building, implementing, tracking and improving acquisition campaigns\nCapable of managing multiple deliverables and ability to seamlessly transition among them\n\nReporting and analytics:\n\nSupport local teams on business development initiatives, campaigns and data requests\nConduct deep-dive analysis at a partner or market level to explain latest trends and changes\nMange the MIS/data reporting, metrics tracking and reporting for Ops function\nFacilitate coordination and production of monthly financial, and other reporting related deliverables\nAnalyse and monitor conversion rates and conversion drivers\nMeasure key results, including revenue, competitive and supply metrics\nEvaluate revenue risk for new strategies and initiatives and develop strategies to mitigate risks\nProvide recommendations on how to improve revenue to partners and leadership team\n\nSKILLS & REQUIREMENTS\n\nStrong communication skills, particularly in presenting complex quantitative analysis in targeted, easily understandable messaging\nAbility to interface & communicate with different internal and external stakeholders\nKnowledge in Digital Marketing and experience with reporting and insights creation is preferable\nExcellent planning, analytical and organisational skills alongside high attention to detail\nuch as Google Analytics and Adobe Analytics to deliver actionable insights\nStrong understanding of revenue drivers and commercial environment\nDemonstrated skills in understanding conversion drivers in an online environment\nKnowledge of statistics, and applying to commercial problem solving\nA proven track record of working on own initiative and an instinctive \"can-do\" attitude, with strong focus on delivering results\nExcellent ability to communicate and a structured approach to capture new leads and projects as well as assignments and to solve challenges\nAttention to detail to ensure nothing is overlooked and every little detail is thought about and executed perfectly\nStrong entrepreneurial spirit and passion\nFluent English and Cantonese\nCurrently pursuing or have completed a Bachelor\u2019s in Business or quantitative discipline", "employment_types": ["Full Time"], "selling_points": [], "locations": ["Not Specified"], "categories": ["Marketing / Public Relations", "Management", "Public Relations - Event Management", "Others"], "post_time": "2022-01-14T01:59:12Z", "salary": {"currency": null, "max": null, "min": null, "period": "monthly", "term": null}, "salary_visible": false, "title_keywords": ["lead"], "responsibilities": ["data", "communication", "maintain", "planning", "plan", "teams", "monitor", "marketing campaigns", "reporting", "management", "coordinate with", "procedures", "provide recommendations", "digital marketing", "campaign management", "tracking", "communicate with", "develop strategies", "analysis", "evaluate", "coordination", "analyse"], "requirements": {"degrees": ["bachelor"], "majors": ["business"], "languages": ["cantonese", "english"], "language_level": ["fluent"], "hard_skills": ["google analytics", "analysis", "problem solving", "adobe", "focus"], "soft_skills": ["communication skills", "independent", "capable", "timely", "deep", "problem solving", "organisational skills", "coordination", "attention to detail", "can-do", "focus", "structured", "leadership", "initiative", "passionate about"], "languages_combined": [{"language": "cantonese", "language_level": ["fluent"]}, {"language": "english", "language_level": ["fluent"]}]}, "experience_required": {"duration": [], "field": ["digital marketing"]}}, {"job_id": "100003009037320", "location_code": "hk", "company": "METRO Sourcing International Limited", "job_title": "Packaging Specialist / Packaging Coordinator", "description": "Introduction\n\nAt IBM, work is more than a job - it's a calling: To build. To design. To code. To consult. To think along with clients and sell. To make markets. To invent. To collaborate. Not just to do something better, but to attempt things you've never thought possible. Are you ready to lead in this new era of technology and solve some of the world's most challenging problems? If so, lets talk.\n\nYour Role and Responsibilities\n\nPrimary Responsibilities\n\n\nOptimizing performance in support of WFM KPIs and driving actions to close gaps to target.\nSupporting HK senior leadership team in all WFM activities\nBuilding effective collaboration with service line and practice leaders, solutioning, HR/TA, Procurement, and Finance/Enterprise Operation.\nEnsuring compliance with Global WFM processes and tolls\nEnsuring compliance to local labor regulations\nProactively identifying and driving capacity actions to manage shortages and excesses\nDriving quarterly demand interlock, fall plan and spring plan resource planning for HK Market\nEnsuring data integrity across supply and demand dynamics\nSupporting internal and external audits in respect of WFM scope\nSupporting special projects e.g. that enable WFM strategy\n\n\nRequirements\n\n\nStrong understanding of consulting skill portfolio\nStrong understanding of consulting business and financial metrics\nknowledgeable in WFM processes and tools\ncreative thinker who thrives in a dynamic environment\nStrong analytical skills and problem-solving abilities\nAbility to change and embrace new challenges and drive new ways of working\nEffective decision making, strong adaptability and ability to make important changes quickly\n\n\nRequired Technical and Professional Expertise\n\nSee Job Description\n\nPreferred Technical and Professional Expertise\n\nAbout Business Unit\n\nIBM Consulting is IBM\u2019s consulting and global professional services business, with market leading capabilities in business and technology transformation. With deep expertise in many industries, we offer strategy, experience, technology, and operations services to many of the most innovative and valuable companies in the world. Our people are focused on accelerating our clients\u2019 businesses through the power of collaboration. We believe in the power of technology responsibly used to help people, partners and the planet.\n\nYour Life @ IBM\n\nAre you craving to learn more? Prepared to solve some of the world's most unique challenges? And ready to shape the future for millions of people? If so, then it's time to join us, express your individuality, unleash your curiosity and discover new possibilities.\n\nEvery IBMer, and potential ones like yourself, has a voice, carves their own path, and uses their expertise to help co-create and add to our story. Together, we have the power to make meaningful change \u2013 to alter the fabric of our clients, of society and IBM itself, to create a truly positive impact and make the world work better for everyone.\n\nIt's time to define your career.\n\nAbout IBM\n\nIBM\u2019s greatest invention is the IBMer. We believe that through the application of intelligence, reason and science, we can improve business, society and the human condition, bringing the power of an open hybrid cloud and AI strategy to life for our clients and partners around the world.\n\nRestlessly reinventing since 1911, we are not only one of the largest corporate organizations in the world, we\u2019re also one of the biggest technology and consulting employers, with many of the Fortune 50 companies relying on the IBM Cloud to run their business.\n\nAt IBM, we pride ourselves on being an early adopter of artificial intelligence, quantum computing and blockchain. Now it\u2019s time for you to join us on our journey to being a responsible technology innovator and a force for good in the world.\n\nLocation Statement\n\nFor additional information about location requirements, please discuss with the recruiter following submission of your application.\n\nBeing You @ IBM\n\nIBM is committed to creating a diverse environment and is proud to be an equal opportunity employer. All qualified applicants will receive consideration for employment without regard to race, color, religion, gender, gender identity or expression, sexual orientation, national origin, genetics, pregnancy, disability, age, veteran status, or other characteristics. IBM is also committed to compliance with all fair employment practices regarding citizenship and immigration status.", "employment_types": ["Full Time", "Permanent"], "selling_points": ["Exp in packaging development / packaging solution", "Take charge of the entire artwork process", "MNC, 5-day work, insurance, double pay, bonus"], "locations": ["Kowloon Bay"], "categories": ["Marketing / Public Relations", "Others", "Merchandising & Purchasing", "Others", "Manufacturing", "Printing"], "post_time": "2022-01-11T16:01:40Z", "salary": {"currency": null, "max": null, "min": null, "period": "monthly", "term": null}, "salary_visible": false, "title_keywords": ["specialist", "coordinator"], "responsibilities": ["regulations", "data", "hr", "compliance", "internal and external audits", "plan", "kpis", "planning"], "requirements": {"degrees": [], "majors": [], "languages": [], "language_level": [], "hard_skills": ["blockchain", "ai", "problem-solving", "reason", "analytical skills", "make", "dynamic"], "soft_skills": ["dynamic environment", "focused", "responsible", "problem-solving", "deep", "unique", "analytical skills", "innovative", "committed", "diverse", "adaptability", "creative", "positive", "decision making"], "languages_combined": []}, "experience_required": {"duration": [], "field": []}}, {"job_id": "100003009046077", "location_code": "hk", "company": "Ocean Park Corporation", "job_title": "Communication Manager", "description": "Role Purpose:\nOur Packaging Specialist is a project manager, taking charge of the entire artwork process from packaging brief to final on-time delivery of product.\n\n\nWhat you will be handling:\nEnsure execution of quality artwork - both content & layout \u2013 for boosting sales of our products\nLiaise with internal & external parties to plan and release artworks as per shipment schedule\nMaintain & update accurate data/record in network/system\nBrief and guide artwork agencies on design concepts, marketing elements & instruction manuals in 19 languages\nMonitor the performance of artwork service providers and printers\nPropose and develop innovative and sustainable packaging solutions\nTalent that we are looking for:\nAble to prioritize multiple projects and cope with the pressure of tight deadlines\nPossess strong sense of ownership and high degree of independence\nDrive for customer success and excellent service\nAttention to details, solution-oriented mindset\nPassionate in connecting with people\nExperience, knowledge and skills required:\nDegree holder in Business Administration / Supply Chain Management / Packaging Science or equivalent discipline\nAt least 5 years\u2019 experience in packaging development / project management / packaging solution / printing\nGood command of both written & spoken English & Chinese (including Mandarin)\nProficient in MS Office (Excel / Word / PowerPoint / Outlook) applications\nKnowledge of Adobe Illustrator/InDesign/Photoshop is advantageous\nCandidate with lesser experience will be considered as\u00a0Packaging Coordinator\nYou can enjoy:\nDiverse and Inclusive work environment\nFlexi Office Space with flexible working hours and home office option\n5-day work week, 13th month salary & performance bonus\nProfessional training and career advancement opportunities\nTraining Sponsorship for personal professional development\nJoin us and apply now!\n\n\nPlease send your full resume with available date, present and expected salary to us.\u00a0\nResume and personal data collected will be kept strictly confidential and used for recruitment purpose only.", "employment_types": ["Full Time", "Contract"], "selling_points": ["Communication Manager", "conservation", "marketing"], "locations": ["Aberdeen"], "categories": ["Marketing / Public Relations", "Marketing - General / Support", "Marketing - Marketing Communication", "Others"], "post_time": "2022-01-13T09:32:59Z", "salary": {"currency": null, "max": null, "min": null, "period": "monthly", "term": null}, "salary_visible": false, "title_keywords": ["manager"], "responsibilities": ["design concepts", "management", "data", "external parties", "quality", "develop", "project management", "maintain", "recruitment", "schedule", "plan", "monitor the performance", "liaise with", "multiple projects", "personal data", "administration"], "requirements": {"degrees": ["degree", "degree holder"], "majors": ["science", "business administration"], "languages": ["english", "chinese", "mandarin"], "language_level": ["good command"], "hard_skills": ["printers", "excel", "indesign", "word", "powerpoint", "adobe illustrator", "project management", "outlook", "photoshop", "ms office"], "soft_skills": ["passionate", "flexible", "able to prioritize", "innovative", "project management", "diverse", "attention to details", "accurate"], "languages_combined": [{"language": "english", "language_level": ["good command"]}, {"language": "chinese", "language_level": ["good command"]}, {"language": "mandarin", "language_level": ["good command"]}]}, "experience_required": {"duration": ["at least 5 years"], "field": ["development", "project management"]}}, {"job_id": "100003009045139", "location_code": "hk", "company": "OSIM (HK) Co. Limited", "job_title": "Marketing Executive (5 Days Work)", "description": "Responsibilities\n(Long \u2013Term contract)\n\nThe incumbent will be responsible to build up OPCF\u2019s conservation brand to facilitate fundraising and the Park\u2019s positioning of Conservation and Education, Communication Manager to increase exposure, his position is vital to lead the Foundation\u2019s branding strategy and increase Foundation\u2019s exposure both in social media and traditional media. He/she needs to develop and maintain OPCFHK\u2019s publication and website as well as manage Facebook and other social media as effective communication tools to engage general public.\n\nRequirements\n-\u00a0Degree in Communication Studies/ Public Relations or Marketing Management\n-\u00a0At least 7 years relevant experience in Marketing/ Communication or Non-profit organization\n-\u00a0Passionate and knowledge in conservation, and familiar with digital marketing or press will be advantage\n-\u00a0Excellent written skills in English and Chinese\n-\u00a0Fluent in English, Chinese and Putonghua\n-\u00a0Ability to work independently and multi-tasking\n\nApplications including details of qualifications, working experience, expected salary, contact telephone number and address should be applied via:\u00a0http://careers.oceanpark.com.hk\u00a0--> Job opening --> Full time/ Long-term.\n\nApplicants not contacted within six weeks may consider their application unsuccessful. Personal data collected will be used for recruitment-related purpose only.", "employment_types": ["Full Time", "Permanent"], "selling_points": [], "locations": ["Shatin Area"], "categories": ["Marketing / Public Relations", "Marketing - Brand / Product Management", "Marketing - Direct Marketing", "Others"], "post_time": "2022-01-13T07:16:45Z", "salary": {"currency": null, "max": null, "min": null, "period": "monthly", "term": null}, "salary_visible": false, "title_keywords": ["marketing executive"], "responsibilities": ["social media", "website", "develop", "communication", "maintain", "facebook", "communication tools", "publication"], "requirements": {"degrees": ["degree"], "majors": ["marketing"], "languages": ["putonghua", "english", "chinese"], "language_level": ["excellent", "fluent"], "hard_skills": [], "soft_skills": ["communication", "work independently", "passionate", "multi-tasking"], "languages_combined": [{"language": "putonghua", "language_level": ["fluent"]}, {"language": "english", "language_level": ["excellent", "fluent"]}, {"language": "chinese", "language_level": ["excellent", "fluent"]}]}, "experience_required": {"duration": ["at least 7 years"], "field": ["marketing", "relevant experience"]}}, {"job_id": "100003009045714", "location_code": "hk", "company": "Engel & Voelkers", "job_title": "Property Agent & Consultant (EAA license holder)", "description": "Responsibilities:\n\nTo assist the team in planning and executing marketing campaigns, including ATL, BTL, PR, and Online promotion\nOrganize events to maximize product launch awareness and enhance customer relationship\nResponsible for planning and execution of CRM Program for customer acquisition and retention\nPrepare regular reports and insights for business performance review\nTo participate in training programme and presentation\nAssist in any ad hoc duties as requested\n\nRequirements:\n\nDegree holder in Marketing / Communications or related disciplines\nWith 1 - 2 years of working experience in marketing\nProactive, result oriented with a strong sense of responsibility\nWith good presentation skills\nFast-paced with excellent communication and interpersonal skills\nCreative and attention to details\nGood command of spoken and written English, Cantonese and Mandarin\n\nInterested parties, please send your full resume with\u00a0current salary,\u00a0expected salary,\u00a0and\u00a0available date\u00a0either by direct application from JobsDB (Please quote the job title on the subject ) or by WhatsApp:69298297 or by post to Human Resources Department, Unit 8-14 & 22-28, 11/F, Topsail Plaza, 11 On Sum Street, Shek Mun.\n\n\"Personal data collected will be used for recruitment purposes only.\"", "employment_types": ["Full Time", "Permanent", "Contract", "Freelance"], "selling_points": ["Attractive commissions", "Uncapped Earning Potential", "Flexible Working Hours;Work from Home;Bonus"], "locations": ["Sheung Wan"], "categories": ["Sales, CS & Business Devpt", "Business Development", "Marketing / Public Relations", "Others", "Property / Real Estate", "Property Consultancy"], "post_time": "2022-01-13T08:25:17Z", "salary": {"currency": null, "max": null, "min": null, "period": "monthly", "term": null}, "salary_visible": false, "title_keywords": ["consultant"], "responsibilities": ["ad hoc duties", "review", "planning", "reports", "executing", "marketing campaigns", "online promotion"], "requirements": {"degrees": ["degree holder"], "majors": ["related disciplines", "marketing", "communications"], "languages": ["cantonese", "english", "mandarin"], "language_level": ["good command"], "hard_skills": [], "soft_skills": ["creative", "sense of responsibility", "result oriented", "presentation skills", "communication and interpersonal skills", "attention to details", "proactive"], "languages_combined": [{"language": "cantonese", "language_level": ["good command"]}, {"language": "english", "language_level": ["good command"]}, {"language": "mandarin", "language_level": ["good command"]}]}, "experience_required": {"duration": ["1 - 2 years"], "field": ["marketing"]}}, {"job_id": "100003009037246", "location_code": "hk", "company": "Cathay Pacific Airways Ltd", "job_title": "Engagement & Events Executive", "description": "Engel & V\u00f6lkers is one of the world\u2019s leading service companies specialized in the brokerage of premium residential property, commercial real estate. As part of our expansion, we are looking to recruit:\n\nProperty Agent & Consultant\n\nWe offer\n\n\u00a0\u00a0\u00a0\u00a0\u00a0\u00a0\u00a0\u00a0 Attractive commissions\u00a0\n\n\u00a0\u00a0\u00a0\u00a0\u00a0\u00a0\u00a0\u00a0 The ability to work from anywhere\n\u00a0\u00a0\u00a0\u00a0\u00a0\u00a0\u00a0\u00a0 An extensively large property portfolio\n\u00a0\u00a0\u00a0\u00a0\u00a0\u00a0\u00a0\u00a0 Uncapped earning potential\n\u00a0\u00a0\u00a0\u00a0\u00a0\u00a0\u00a0\u00a0 On-going training and constant support\n\u00a0\u00a0\u00a0\u00a0\u00a0\u00a0\u00a0\u00a0 A worldwide network providing you with access to clients and premium properties\n\u00a0\u00a0\u00a0\u00a0\u00a0\u00a0\u00a0\u00a0 Global Luxury UHNW (Ultra High-Net-Worth) network\n\nOur requirement\n\n\u00a0\u00a0\u00a0\u00a0\u00a0\u00a0\u00a0\u00a0 Sales experience is a\u00a0MUST\n\u00a0\u00a0\u00a0\u00a0\u00a0\u00a0\u00a0\u00a0 EAA license holder is a MUST\n\u00a0\u00a0\u00a0\u00a0\u00a0\u00a0\u00a0\u00a0 Proven Revenue Earner\n\u00a0\u00a0\u00a0\u00a0\u00a0\u00a0\u00a0\u00a0 Self-Discipline\n\u00a0\u00a0\u00a0\u00a0\u00a0\u00a0\u00a0\u00a0 Excellent Communication Skills\n\u00a0\u00a0\u00a0\u00a0\u00a0\u00a0\u00a0\u00a0 Strong Sense of Team Spirit\n\u00a0\u00a0\u00a0\u00a0\u00a0\u00a0\u00a0\u00a0 Professional\n\u00a0\u00a0\u00a0\u00a0\u00a0\u00a0\u00a0\u00a0 Stand Out with a High Degree of Initiative and Flexibility\n\nIf you are interested in working for a service-oriented, prestigious, and international real estate brand, you have an outgoing manner and enjoy working with people, we are offering you the opportunity to become a member of our growing and highly-motivated global team.\n\nAre you interested? Then apply online now.\n\nWe look forward to receiving your application.", "employment_types": ["Full Time", "Permanent"], "selling_points": ["Graduate opportunity", "Project and event management", "Travel Benefits, 5-day work, Medical Benefits"], "locations": ["Lantau Island"], "categories": ["Marketing / Public Relations", "Public Relations - Event Management", "Public Relations - General / Support", "Others"], "post_time": "2022-01-11T02:11:27Z", "salary": {"currency": null, "max": null, "min": null, "period": "monthly", "term": null}, "salary_visible": false, "title_keywords": ["executive"], "responsibilities": ["brokerage"], "requirements": {"degrees": [], "majors": [], "languages": [], "language_level": [], "hard_skills": [], "soft_skills": [], "languages_combined": []}, "experience_required": {"duration": [], "field": []}}, {"job_id": "100003009047300", "location_code": "hk", "company": "JPMorgan Chase Bank, N.A.", "job_title": "CIB - Quantitative Research - Equity Derivatives - Vice President", "description": "Reports to:\u00a0Engagement & Events Manager\nDepartment:\u00a0People (PPL)\n\nRole Introduction\n\nThe job holder is responsible for the delivery and implementation of engagement and events activities for all Cathay employees. This role will work closely with the Engagement and Events Manager and Engagement and Events Assistant Manager to co-ordinate plans and events to improve the employee experience and drive engagement across our varied employee groups globally \u2013 while contributing towards creating a positive work place.\n\nKey Responsibilities\n\nWork with the Engagement and Events team to develop and execute on our annual engagement strategy and calendar of activities\u00a0\nPlan, organise and implement our social and seasonal events\nProvide day-to-day administrative and logistics support for all our engagement activities and events\nSupport with all events on our activity calendar \u2013 with the goal of providing seamless events experiences for Cathay employees\nCoordinate all venue bookings and set up arrangements for in house events\u00a0\nProvide support for Cathy\u2019s global employee recognition programme \u2018Work Well Done\u2019 \u2013 including the management of toolkits, website and reporting\nSupport event production for Cathay\u2019s annual awards programme, the Niki and Betsy Awards\nOversee and support Cathay\u2019s 20+ sports & interest clubs and activities including expenses control, liaise with representatives and external activity organisers for our people and teams to participate in\nWork with our Global Business Service team on employee data \u2013 requests, data handling and records management for various initiatives and projects\nSupport our Long Service Awards programme \u2013 with day-to-day management, list management, administration, prizes and event experience\nRepresent the Company at the Swire Hong Kong Staff Association committee and external forums such as Inter-Hong and relevant associations to organise and promote different activities and events for our employees and enhance Company image\u00a0\nSupport the broader Internal Communications and Engagement team on discrete projects as required\nSupport and collaborate with the Corporate Affairs Department (CAF) on volunteering opportunities and charity activities\u00a0\nMonitor inventory for prizes items and souvenirs for internal campaigns\nManage Cathay Club common mailbox\nManage SAP Purchase Orders and invoicing\nUndertake ad hoc projects as assigned\n\nRequirements\n\nGraduate opportunity/1-2 years\u2019 experience in an events role advantageous\nExcellent communication and presentation skills\nProject and event management experience advantageous\nKnowledge of marketing, event management and/or communications theories, models and trends\nProactive, high drive and strong energy\nSelf-motivator\nOutstanding customer service and team working skills\nExcellent time management and prioritisation skills\nAttention to detail\nAbility to communicate confidently (both verbal and written) in English and Cantonese advantageous\u00a0\n\n\n\nApplication deadline:\u00a025 January 2022\n\nPersonal & Application Information\nCathay Pacific is an Equal Opportunities Employer. Personal data provided by job applicants will be used strictly in accordance with our personal data policy and for recruitment purposes only. Candidates not notified within eight weeks may consider their application unsuccessful. All related information will be kept in our file for up to 24 months. A copy of our Personal Information Collection Statement will be provided upon request by contacting our Data\u00a0Protection Officer.\n\n\nPlease note that with effect from 1 December 2021, all employees must be vaccinated in order to access Cathay City and all other Cathay Group Company premises in Hong Kong. Consideration will be given to those who are unable to get vaccinated for valid medical reasons.", "employment_types": ["Full Time"], "selling_points": [], "locations": ["Not Specified"], "categories": ["Banking / Finance", "Others", "Marketing / Public Relations", "Others"], "post_time": "2022-01-14T02:47:55Z", "salary": {"currency": null, "max": null, "min": null, "period": "monthly", "term": null}, "salary_visible": false, "title_keywords": ["vice president"], "responsibilities": ["collaborate with", "data", "inventory", "website", "purchase", "plan", "liaise with", "administration", "control", "expenses", "teams", "monitor", "develop", "day-to-day management", "logistics", "reporting", "provide support", "management", "coordinate", "invoicing", "ad hoc projects"], "requirements": {"degrees": [], "majors": [], "languages": ["cantonese", "english"], "language_level": [], "hard_skills": [], "soft_skills": ["communication", "time management", "presentation skills", "customer service", "attention to detail", "team working", "proactive"], "languages_combined": [{"language": "cantonese", "language_level": []}, {"language": "english", "language_level": []}]}, "experience_required": {"duration": ["1-2 years"], "field": ["management"]}}, {"job_id": "100003009048953", "location_code": "hk", "company": "Heep Hong Society", "job_title": "Assistant Corporate Development Manager", "description": "J.P. Morgan is a global leader in financial services, providing strategic advice and products to the world's most prominent corporations, governments, wealthy individuals and institutional investors. Our first-class business in a first-class way approach to serving clients drives everything we do. We strive to build trusted, long-term partnerships to help our clients achieve their business objectives.\n\nThe APAC Quantitative Research Equity Derivatives Team\n\nThe main mandate of the team is to support the APAC Equity Derivatives business, with a wide range of responsibilities covering: model and payoff development to support existing and new client demands; trading, risk management and hedging automation and optimization; analyze and develop trading & hedging strategies. The team also acts as a culture carrier for modern data-driven business methods and brings data-driven decision making and automation to the Equity businesses.\n\nJob Summary\n\nThe role consists in providing front-office modelling and risk-management support to equity trading desk (covering both Exotics and Flow). This involves:\n\nDeveloping and enhancing models for pricing and risk management of equity derivatives (variance/volatility payoff, parametric volatility models, risk-decomposition/replication/optimization)\nAnalyzing the risks of complex derivatives portfolios\nImplementing new models / products in our quant library, writing model documentation and working closely with the technology team for model testing and deployment in production\nProviding day-to-day support to the trading desk: discussing new ideas, analyzing complex problems and providing solutions\nQualifications\n\nThe ideal candidate brings quantitative experience in the Equity business (volatility product modeling and hedging strategy), combined with a strong background in Mathematics/Engineering (ideally with knowledge in Stochastic Calculus, Probability theory, Financial Engineering) and a curiosity to expand in this field. Communication skills and drive are critical for the role as we expect the candidate to actively engage with the business and to bring cultural change towards a modern data-driven approach to business.\nKey Qualifications\n\nA PhD or Master's Degree in a quantitative discipline from a top-tier institution\nExcellent knowledge of derivatives pricing and risk management theory, vanilla options and volatility products\nOutstanding problem-solving abilities and communication skills\nA strong coding background with proficiency in Python, C++, and relevant quantitative packages (numpy, pandas)\nGood expertise in statistical modelling including standard techniques, linear, convex & conic optimization\nWe recognize that our people are our strength and the diverse talents they bring to our global workforce are directly linked to our success. We are an equal opportunity employer and place a high value on diversity and inclusion at our company. We do not discriminate on the basis of any protected attribute, including race, religion, color, national origin, gender, sexual orientation, gender identity, gender expression, age, marital or veteran status, pregnancy or disability, or any other basis protected under applicable law. In accordance with applicable law, we make reasonable accommodations for applicants' and employees' religious practices and beliefs, as well as any mental health or physical disability needs.\n\nInterested parties please click \u201cApply Now\u201d to apply job.\n\nAll applications applied through our system will be delivered directly to the advertiser and privacy of personal data of the applicant will be ensured with security.", "employment_types": ["Full Time"], "selling_points": ["Fundraising & corporate partnership", "Degree in Marketing, Communication, PR, Event Mgmt", "Min. 5 years' marketing/communication experience"], "locations": ["Ngau Tau Kok"], "categories": ["Marketing / Public Relations", "Marketing - Brand / Product Management", "Public Relations - Event Management", "Others"], "post_time": "2022-01-14T11:46:57Z", "salary": {"currency": null, "max": null, "min": null, "period": "monthly", "term": null}, "salary_visible": false, "title_keywords": ["manager", "assistant"], "responsibilities": ["management", "ideas", "data", "developing", "coding", "develop", "testing", "communication", "documentation"], "requirements": {"degrees": ["degree", "master"], "majors": [], "languages": [], "language_level": [], "hard_skills": ["c++", "problem-solving", "python", "make", "deployment", "documentation"], "soft_skills": ["communication skills", "first-class", "decision making", "problem-solving", "diverse", "driven", "ideal"], "languages_combined": []}, "experience_required": {"duration": [], "field": ["business", "engineering", "financial"]}}, {"job_id": "100003009046200", "location_code": "hk", "company": "OCBC Wing Hang Bank Limited", "job_title": "Assistant Vice President, Marketing", "description": "Responsibilities:\n\nTo assist the Head of Corporate Development to coordinate the work of fundraising and corporate partnership\nTo liaise and maintain relationship with existing sponsors and corporate partners\nTo devise and implement outreach strategies to attract new corporate partners; and generate new business opportunities\nTo assist in the planning and execution of various fundraising events to meet the Society's fundraising objectives\nTo undertake any other duties as required\n\nRequirements:\n\nDegree in Marketing, Communication, Public Relations, Event Management or related discipline\nAt least 5 years' marketing and/or communication experience; experience in NGO fundraising preferable\nProven record of event management and fundraising\nExperience of networking with a broad contact base, including business and funding bodies\nA good team player, well organized and attentive to details\nProactive, positive with strong interest in charity\nExcellent command of written and spoken English and Chinese\n\nWe provide equal employment opportunities to all employees and applicants. For interested parties, please click\u00a0\u201cApply Now\u201d.\n\n(Personal data collected will be used for recruitment purpose only)", "employment_types": ["Full Time", "Permanent"], "selling_points": ["Design and implement marketing campaigns", "Monitor and manage social media", "Solid experience from banking industry"], "locations": ["Shau Kei Wan"], "categories": ["Banking / Finance", "Retail Banking", "Marketing / Public Relations", "Others"], "post_time": "2022-01-13T09:54:48Z", "salary": {"currency": null, "max": null, "min": null, "period": "monthly", "term": null}, "salary_visible": false, "title_keywords": ["assistant vice president"], "responsibilities": ["liaise", "any other duties", "business opportunities", "coordinate", "maintain", "planning"], "requirements": {"degrees": ["degree"], "majors": ["marketing"], "languages": ["english", "chinese"], "language_level": ["excellent"], "hard_skills": ["charity"], "soft_skills": ["good team player", "attentive to details", "well organized", "communication", "proactive", "positive"], "languages_combined": [{"language": "english", "language_level": ["excellent"]}, {"language": "chinese", "language_level": ["excellent"]}]}, "experience_required": {"duration": ["at least 5 years"], "field": ["business", "marketing"]}}, {"job_id": "100003009043714", "location_code": "hk", "company": "Swire Resources Ltd", "job_title": "CRM Data Analyst", "description": "Job Responsibilities:\n\nThis Officer / Assistant Officer will support Senior Manager and the team in launching advertising campaigns:\n\nAssist in developing and implementing effective integrated advertising campaigns\n\nWork closely with advertising and media agencies to ensure successful execution of marketing strategies\n\nLiaise with internal parties for materials approval\n\nAssist the team on the launch communication\n\nStay alert on competitive activities and keep the team updated\n\nAct as a brand custodian to ensure the communications are in line and consistent across the entire company\n\nPerform daily administrative works and assist in maintaining and process invoices\n\nJob Requirements:\n\nUniversity graduate, in Marketing, Public Relations, Communications, Business Admin or related disciplines\n\n1-2 years' experience in marketing/ advertising/ branding preferred. Fresh graduates are also welcomed.\n\nProficiency in MS Office (Excel, Word and especially Powerpoint), basic Adobe Illustration and Photoshop skills will be a bonus\n\nStrong presentation, analytical, communication and interpersonal skills, with attention to details and high sensitivity\n\nSelf-motivated, good team player with entrepreneurial spirit\n\nStrong writing skills in both English and Chinese\n\nExcellent command spoken English and Chinese\n\n(Candidates with less experience will be considered as Assistant Officer)\n", "employment_types": ["Full Time", "Permanent"], "selling_points": ["CRM Data extraction, dashboard visualization", "Basic knowledge in Tableau, PowerBI", "Experience in F&B/retail environment"], "locations": ["Kowloon Bay"], "categories": ["Professional Services", "Business Analysis / Data Analysis", "Information Technology (IT)", "DBA", "Marketing / Public Relations", "Others"], "post_time": "2022-01-13T01:38:06Z", "salary": {"currency": null, "max": null, "min": null, "period": "monthly", "term": null}, "salary_visible": false, "title_keywords": ["data analyst"], "responsibilities": ["advertising", "marketing strategies", "maintaining", "invoices", "developing", "communication", "liaise with", "advertising campaigns", "internal parties"], "requirements": {"degrees": ["university graduate"], "majors": ["business", "related disciplines", "marketing", "communications"], "languages": ["english", "chinese"], "language_level": ["excellent"], "hard_skills": ["excel", "basic", "word", "powerpoint", "writing skills", "adobe", "photoshop", "illustration", "ms office"], "soft_skills": ["self-motivated", "good team player", "sensitivity", "writing skills", "communication and interpersonal skills", "attention to details", "presentation"], "languages_combined": [{"language": "english", "language_level": ["excellent"]}, {"language": "chinese", "language_level": ["excellent"]}]}, "experience_required": {"duration": ["1-2 years"], "field": ["marketing", "advertising"]}}, {"job_id": "100003009050907", "location_code": "hk", "company": "Links International", "job_title": "Senior CRM Manager (Financial Trading)", "description": "Job Summary\n\nThe Data analyst will support the Retail Division for company\u2019s growing needs on CRM analytics and big data analysis. Candidate\u2019s analytical and technical skills will be leveraged to support various CRM programs and manage CRM analytical projects.\n\nJob Duties and Responsibilities\n\n1. Drive data driven marketing program\u00a0\n\n\nUnderstand business requirement to extract data from CRM system, conduct analysis to identify customer needs and sales opportunities for sales-driven marketing program design\n\n2.\u00a0Create data visualization\u00a0\n\n\nBuild dashboard that helps CRM team to gain understanding on business results & trend, monitor KPI and alert for action plan (e.g.\u00a0CRM KPI/ Mobile App performance/ Customer life cycle analytics)\n\n3.\u00a0Derive customer segmentation\n\n\nReveal and uncover insights by exploring and mining structured and unstructured data to build different customer segmentation\nModel includes\u00a0Customer life cycle/RFM (Frequency/Monetary Value/Recency/ Digital footprint behavior/ Response to communications etc.)\n4.\u00a0Execute marketing program\n\nPerform data extraction to fulfill marketing program requirement\nDevelop campaign evaluation framework, set control to review campaign effectiveness & conduct reports\n5.\u00a0Develop customer data set\n\nCo-work with IT team to ensure data accuracy and develop comprehensive customer data set (customer 360) &\u00a0manual for data field definition\n6. Develop control reports\n\nDesign data reports to facilitate control on potential risk & loss of CRM program execution i.e. VIP Bonus scheme, Bulk & abnormal VIP purchase identification\u00a0\n\n\u00a0Requirements\n\nDegree holder, preferably in Information Technology, Computer Science, Data Analytics, Statistics, BIS/MIS or\u00a0related disciplines\n1-2 year experience in\u00a0 data analysis and ideally with experience in F&B/retail environments\nFamiliar with visualization tools (e.g. Tableau, PowerBI) is an advantage\nExperience in handling large sets of data is a plus\nInterested in customer behavior and CRM\nStrong sense in data processing, good business acumen and communication skills\nFresh graduate with internship experience will be considered\u00a0\nWe offer competitive remuneration package with\u00a0a wide range of fringe benefits including\n5-day work week\nDiscretionary Bonus\nComprehensive Medical Coverage\nStaff Shopping Discount\nNon-contributory Retirement Benefits Scheme\nBirthday Leave\nPlease send resume with present and expected salary to Human Resources Department, Swire Resources Limited, 12/F Kingston International Centre 19 Wang Chiu Road Kowloon Bay Hong Kong or by clicking the \"Apply Now\" button below.\n\nSwire Resources Limited is Equal Opportunity Employer", "employment_types": ["Full Time", "Permanent"], "selling_points": ["Leading financial trading platform", "Customer Lifecycle / CRM", "Exp in China Market is a big plus"], "locations": ["Not Specified"], "categories": ["Marketing / Public Relations", "Management", "Others", "Digital Marketing"], "post_time": "2022-01-14T11:44:03Z", "salary": {"currency": "HKD", "max": 54999, "min": 45000, "period": "monthly", "term": null}, "salary_visible": true, "title_keywords": ["manager"], "responsibilities": ["control", "mobile app", "visualization", "data", "analysis", "review", "monitor", "customer data", "design", "develop", "ensure data accuracy", "purchase", "reports", "plan", "evaluation"], "requirements": {"degrees": ["fresh graduate", "degree holder"], "majors": ["related disciplines", "statistics", "computer science", "information technology"], "languages": [], "language_level": [], "hard_skills": ["plus", "data analytics", "analysis", "tableau", "processing", "acumen"], "soft_skills": ["business acumen", "communication skills", "interested in"], "languages_combined": []}, "experience_required": {"duration": ["1-2 year"], "field": ["data analysis", "f&b", "retail"]}}, {"job_id": "100003009041893", "location_code": "hk", "company": "Think China", "job_title": "[HK] Account Director - Digital Marketing & Ecommerce", "description": "Our client is a leading financial trading platform. They are looking for Senior Marketing Manager, CRM / Customer Lifecycle to join their marketing team.\n\nJob Description\n\n\nLead the team to develop and manage Customer Value Management (CVM) strategy for both retail clients and partnership across targeted market\nDevelop key strategies on customer experience and brand proposition throughout customer lifecycle\nCollaborate closely with central supporting team to drive development and implementation of journeys throughout customer lifecycle\nWork with marketing teams of social media, UXUI, acquisition and client facing team for optimizing loyalty and rewards programs\nPlan and conduct regular reports of acquisition, conversion and retention activities, and share insights and ideas on optimizing customer journey\n\nJob Requirement\n\n\n5-8 years of work experience in marketing strategy planning or customer lifecycle / experience\nSolid CRM and social CRM experience across multiple channels such as WeChat, Email, Loyalty\nExperience in designing and implementing automated journeys\nExperience about CRM / customer experience in Greater China market is a definite advantage\nData driven and analytical", "employment_types": ["Full Time"], "selling_points": [], "locations": ["Not Specified"], "categories": ["Admin & HR", "Others", "Marketing / Public Relations", "Marketing - General / Support", "Others"], "post_time": "2022-01-12T04:35:46Z", "salary": {"currency": null, "max": null, "min": null, "period": "monthly", "term": null}, "salary_visible": false, "title_keywords": ["account director", "digital marketing"], "responsibilities": ["collaborate", "social media", "management", "ideas", "teams", "implementation", "develop", "reports", "plan"], "requirements": {"degrees": [], "majors": [], "languages": [], "language_level": [], "hard_skills": ["wechat"], "soft_skills": ["driven"], "languages_combined": []}, "experience_required": {"duration": ["5-8 years"], "field": ["marketing", "planning"]}}, {"job_id": "100003009041621", "location_code": "hk", "company": "Agoda International (Hong Kong) Limited", "job_title": "Global Lead Marketing Innovation and Analytics (Bangkok-based, relocation provided)", "description": "\nAbout Agoda\n\nAgoda is an online travel booking platform for accommodations, flights, and more. We build and deploy cutting-edge technology that connects travelers with more than 2.5 million accommodations globally. Based in Asia and part of Booking Holdings, our 4,000+ employees representing 90+ nationalities foster a work environment rich in diversity, creativity, and collaboration. We innovate through a culture of experimentation and ownership,\u202fenhancing the ability for our customers to experience the world.\n\nGet to Know our Team:\n\nThe Performance Marketing Team of Agoda is a world leader in online marketing. This department is highly data-driven and focused on developing at-scale marketing programs that improve the lifetime value of Agoda customers through measurable marketing programs and channels. The team is a blend of the best analysts, marketing strategists, and data scientists in the world. The marketing leadership at Agoda have deep experience in data science, product, strategy, and other marketing fields and have built an organization that thrives on data, creative ideas, and technology. The Performance Marketing Team also fosters a great learning environment. You will be able to learn and grow by working closely with experts from a variety of backgrounds from all over the world.\n\nIn this role, you\u2019ll get to:\n\u2022 Take ownership of analytical projects end to end from extracting and exploring data, generating hypothesis, building a structured analysis, and rigorously evaluating methods and results\n\u2022 Provide analytical and valuable insights for decision-making support for key projects and management\n\u2022 Work closely with various business functions to identify opportunities, analyze, and interpret trends or patterns in complex data sets using different techniques and tools such as R studio or Tableau\n\u2022 Communicate findings and propose actionable recommendations to address the problems\nWhat you\u2019ll need to succeed:\n\u2022 Bachelor Degree in Computer Science/Statistics/Math or Engineering or Economics and Finance\n5+ years in Data Analyst position or otherwise in projects involving big data\n\u2022 People management and strong commercial acumen\n\u2022 Proficient in business intelligence tools and data warehouse i.e. SQL, Tableau and MS Excel\n\u2022 Must be data savvy and love crunching numbers\n\u2022 Strong analytical and statistical analysis skills in order to extract insights and recommendations\nFluent in English with strong communication skills (both written and verbal)\nIt\u2019s great if you have:\n\u2022 Experience in R studio, data modeling, hypothesis testing is a plus\n#STRA #ANLS #MRKT #3 #hongkong #kualalumpur #mumbai #newdelhi #delhi #bangalore #hochiminh #jakarta #manila #hongkong #beijing #toronto #vancouver #berlin #paris #barcelona #london #madrid #bangkok data representation data analysis SQL data analytics analytics python (programming language) data mining data science r (programming language) tableau analytical skills data visualization databases business analysis business intelligence (bi) microsoft sql server machine learning statistics microsoft power bi java finance shopee traveloka google facebook ctrip trip.com makemytrip grab amazon pandas (software) artificial intelligence (ai) information technology capital one accenture upwork deloitte mckinsey bain microsoft uber lyft gojek lazada alibaba shopify expedia skyscanner\n\nEqual Opportunity Employer\n\nAt Agoda, we pride ourselves on being a company represented by people of all different backgrounds and orientations. We prioritize attracting diverse talent and cultivating an inclusive environment that encourages collaboration and innovation. Employment at Agoda is based solely on a person\u2019s merit and qualifications. We are committed to providing equal employment opportunity regardless of sex, age, race, color, national origin, religion, marital status, pregnancy, sexual orientation, gender identity, disability, citizenship, veteran or military status, and other legally protected characteristics.\n\nWe will keep your application on file so that we can consider you for future vacancies and you can always ask to have your details removed from the file. For more details please read our privacy policy .\n\nTo all recruitment agencies: Agoda does not accept third party resumes. Please do not send resumes to our jobs alias, Agoda employees or any other organization location. Agoda is not responsible for any fees related to unsolicited resumes.\n\n", "employment_types": ["Full Time"], "selling_points": [], "locations": ["Not Specified"], "categories": ["Admin & HR", "Others", "Marketing / Public Relations", "Marketing - General / Support", "Others"], "post_time": "2022-01-12T04:07:36Z", "salary": {"currency": null, "max": null, "min": null, "period": "monthly", "term": null}, "salary_visible": false, "title_keywords": ["lead"], "responsibilities": ["visualization", "software", "data", "big data", "communication", "deploy", "data mining", "facebook", "developing", "testing", "management", "data analysis", "booking", "third party", "creative ideas", "power bi", "analysis", "recruitment", "databases", "business analysis"], "requirements": {"degrees": ["degree", "bachelor"], "majors": ["engineering", "finance", "economics", "statistics", "computer science", "math"], "languages": ["english"], "language_level": ["fluent"], "hard_skills": ["plus", "bi", "statistical analysis", "ai", "shopify", "data mining", "facebook", "java", "tableau", "microsoft sql server", "data warehouse", "data analytics", "analytical skills", "sql", "python", "r", "acumen", "amazon", "analysis", "ms excel", "programming", "data visualization", "databases", "math", "business intelligence"], "soft_skills": ["communication skills", "focused", "cutting-edge", "responsible", "deep", "prioritize", "analytical skills", "diverse", "committed", "learning", "structured", "creative", "leadership", "driven"], "languages_combined": [{"language": "english", "language_level": ["fluent"]}]}, "experience_required": {"duration": [], "field": ["marketing", "testing"]}}, {"job_id": "100003009041583", "location_code": "hk", "company": "Agoda International (Hong Kong) Limited", "job_title": "Associate Director, Marketing Analytics (Bangkok-based, relocation provided)", "description": "\nAbout Agoda\n\nAgoda is an online travel booking platform for accommodations, flights, and more. We build and deploy cutting-edge technology that connects travelers with more than 2.5 million accommodations globally. Based in Asia and part of Booking Holdings, our 4,000+ employees representing 90+ nationalities foster a work environment rich in diversity, creativity, and collaboration. We innovate through a culture of experimentation and ownership,\u202fenhancing the ability for our customers to experience the world.\n\nGet to Know our Team:\n\nThe Performance Marketing Team of Agoda is a world leader in online marketing. This department is highly data-driven and focused on developing at-scale marketing programs that improve the lifetime value of Agoda customers through measurable marketing programs and channels. The team is a blend of the best analysts, marketing strategists, and data scientists in the world. The marketing leadership at Agoda have deep experience in data science, product, strategy, and other marketing fields and have built an organization that thrives on data, creative ideas, and technology. The Performance Marketing Team also fosters a great learning environment. You will be able to learn and grow by working closely with experts from a variety of backgrounds from all over the world.\n\nIn this role, you\u2019ll get to:\n\u2022 Take ownership of analytical projects end to end from extracting and exploring data, generating hypothesis, building a structured analysis, and rigorously evaluating methods and results\n\u2022 Provide analytical and valuable insights for decision-making support for key projects and management\n\u2022 Work closely with various business functions to identify opportunities, analyze, and interpret trends or patterns in complex data sets using different techniques and tools such as R studio or Tableau\n\u2022 Communicate findings and propose actionable recommendations to address the problems\nWhat you\u2019ll need to succeed:\n\u2022 Bachelor Degree in Computer Science/Statistics/Math or Engineering or Economics and Finance\n9+ years in Data Analyst position or otherwise in projects involving big data\n\u2022 People management and strong commercial acumen\n\u2022 Proficient in business intelligence tools and data warehouse i.e. SQL, Tableau and MS Excel\n\u2022 Must be data savvy and love crunching numbers\n\u2022 Strong analytical and statistical analysis skills in order to extract insights and recommendations\nFluent in English with strong communication skills (both written and verbal)\nIt\u2019s great if you have:\n\u2022 Experience in R studio, data modeling, hypothesis testing is a plus\n#STRA #ANLS #MRKT #3 #hongkong #kualalumpur #mumbai #newdelhi #delhi #bangalore #hochiminh #jakarta #manila #hongkong #beijing #toronto #vancouver #berlin #paris #barcelona #london #madrid #bangkok #datarepresentation #dataanalysis #SQL #dataanalytics #python #datamining #datascience #r (programming language) #tableau analytical skills data visualization databases business analysis business intelligence (bi) microsoft sql server machine learning statistics microsoft power bi java finance shopee traveloka google facebook ctrip trip.com makemytrip grab amazon pandas (software) artificial intelligence (ai) information technology capital one accenture upwork deloitte mckinsey bain microsoft uber lyft gojek lazada alibaba shopify expedia skyscanner\n\nEqual Opportunity Employer\n\nAt Agoda, we pride ourselves on being a company represented by people of all different backgrounds and orientations. We prioritize attracting diverse talent and cultivating an inclusive environment that encourages collaboration and innovation. Employment at Agoda is based solely on a person\u2019s merit and qualifications. We are committed to providing equal employment opportunity regardless of sex, age, race, color, national origin, religion, marital status, pregnancy, sexual orientation, gender identity, disability, citizenship, veteran or military status, and other legally protected characteristics.\n\nWe will keep your application on file so that we can consider you for future vacancies and you can always ask to have your details removed from the file. For more details please read our privacy policy .\n\nTo all recruitment agencies: Agoda does not accept third party resumes. Please do not send resumes to our jobs alias, Agoda employees or any other organization location. Agoda is not responsible for any fees related to unsolicited resumes.\n\n", "employment_types": ["Full Time"], "selling_points": [], "locations": ["Not Specified"], "categories": ["Admin & HR", "Others", "Marketing / Public Relations", "Marketing - General / Support", "Others"], "post_time": "2022-01-12T04:04:13Z", "salary": {"currency": null, "max": null, "min": null, "period": "monthly", "term": null}, "salary_visible": false, "title_keywords": ["associate director"], "responsibilities": ["creative ideas", "management", "visualization", "power bi", "data", "software", "analysis", "big data", "developing", "testing", "communication", "recruitment", "booking", "databases", "deploy", "business analysis", "facebook", "third party"], "requirements": {"degrees": ["degree", "bachelor"], "majors": ["engineering", "finance", "economics", "statistics", "computer science", "math"], "languages": ["english"], "language_level": ["fluent"], "hard_skills": ["plus", "bi", "statistical analysis", "ai", "shopify", "facebook", "java", "tableau", "microsoft sql server", "data warehouse", "analytical skills", "sql", "python", "r", "acumen", "amazon", "analysis", "ms excel", "programming", "data visualization", "databases", "math", "business intelligence"], "soft_skills": ["communication skills", "focused", "cutting-edge", "responsible", "deep", "prioritize", "analytical skills", "diverse", "committed", "learning", "structured", "creative", "leadership", "driven"], "languages_combined": [{"language": "english", "language_level": ["fluent"]}]}, "experience_required": {"duration": [], "field": ["marketing", "testing"]}}, {"job_id": "100003009042105", "location_code": "hk", "company": "Ocean Park Corporation", "job_title": "Project Officer (Retail Operations Department)", "description": "(Long-term contract)\n\nResponsibilities\n\nThe incumbent will be responsible for collaborate with contractors and internal parties for various Retail projects, monitor projects\u2019 progress as schedule, attend field work for quality control and compliance, and other ad hoc duties as assigned by supervisor.\n\nRequirements\n\n-Diploma or above\n-2 years or above working experience, preferably in retail industry\n-Knowledge in Electronics / Electrical Applications will be an advantage\n-Be creative, self-motivated, responsible, good team player and able to work under tight schedule\n-Strong planning and organization skill\n-Capable in solving on-site problems with rationales\n-Good communication and management skills\n-Good command of both spoken and written Chinese and English\n-Work on shift / night work is required at interval\n\nApplications including details of qualifications, working experience, expected salary, contact telephone number and address should be applied via:\u00a0http://careers.oceanpark.com.hk\u00a0--> Job opening --> Full time/ Long-term.\n\nApplicants not contacted within six weeks may consider their application unsuccessful. Personal data collected will be used for recruitment-related purpose only.", "employment_types": ["Full Time", "Contract"], "selling_points": ["retail projects", "Diploma or above", "2 years or above working experience"], "locations": ["Aberdeen"], "categories": ["Engineering", "Electrical / Electronics", "Marketing / Public Relations", "Public Relations - Event Management", "Others"], "post_time": "2022-01-12T06:10:22Z", "salary": {"currency": null, "max": null, "min": null, "period": "monthly", "term": null}, "salary_visible": false, "title_keywords": ["operations", "project officer"], "responsibilities": ["collaborate with", "ad hoc duties", "compliance", "monitor", "schedule", "quality control", "internal parties"], "requirements": {"degrees": [], "majors": [], "languages": ["english", "chinese"], "language_level": [], "hard_skills": [], "soft_skills": ["good team player", "self-motivated", "responsible", "organization skill", "communication", "creative"], "languages_combined": [{"language": "english", "language_level": []}, {"language": "chinese", "language_level": []}]}, "experience_required": {"duration": [], "field": ["retail industry"]}}, {"job_id": "100003009050920", "location_code": "hk", "company": "Links International", "job_title": "Marketing Campaign Manager (Financial Trading)", "description": "(Long-term contract)\n\nResponsibilities\n\nThe incumbent will be responsible for collaborate with contractors and internal parties for various Retail projects, monitor projects\u2019 progress as schedule, attend field work for quality control and compliance, and other ad hoc duties as assigned by supervisor.\n\nRequirements\n\n-Diploma or above\n-2 years or above working experience, preferably in retail industry\n-Knowledge in Electronics / Electrical Applications will be an advantage\n-Be creative, self-motivated, responsible, good team player and able to work under tight schedule\n-Strong planning and organization skill\n-Capable in solving on-site problems with rationales\n-Good communication and management skills\n-Good command of both spoken and written Chinese and English\n-Work on shift / night work is required at interval\n\nApplications including details of qualifications, working experience, expected salary, contact telephone number and address should be applied via:\u00a0http://careers.oceanpark.com.hk\u00a0--> Job opening --> Full time/ Long-term.\n\nApplicants not contacted within six weeks may consider their application unsuccessful. Personal data collected will be used for recruitment-related purpose only.", "employment_types": ["Full Time", "Permanent"], "selling_points": ["Global financial trading platform", "Marketing project management", "All round digital marketing"], "locations": ["Not Specified"], "categories": ["Marketing / Public Relations", "Marketing - Brand / Product Management", "Others", "Digital Marketing"], "post_time": "2022-01-14T11:47:03Z", "salary": {"currency": "HKD", "max": 29999, "min": 20000, "period": "monthly", "term": null}, "salary_visible": true, "title_keywords": ["manager"], "responsibilities": ["collaborate with", "ad hoc duties", "compliance", "monitor", "schedule", "quality control", "internal parties"], "requirements": {"degrees": [], "majors": [], "languages": ["english", "chinese"], "language_level": [], "hard_skills": [], "soft_skills": ["good team player", "self-motivated", "responsible", "organization skill", "communication", "creative"], "languages_combined": [{"language": "english", "language_level": []}, {"language": "chinese", "language_level": []}]}, "experience_required": {"duration": [], "field": ["retail industry"]}}, {"job_id": "100003009038464", "location_code": "hk", "company": "Caritas - Hong Kong", "job_title": "Assistant Communications Officer \u52a9\u7406\u50b3\u8a0a\u7d71\u7c4c\u4e3b\u4efb", "description": "Our client is a leading global financial trading platform. They are now looking for Marketing Campaign Manager to join their expanding marketing team.\n\nJob Description\n\n\nLead and develop branding campaign plans, manage the delivery roadmap and timeline\nManage brand campaigns of digital acquisition, retention and events to drive higher conversion, deposits and revenue in strategic markets\nCoordinate with different internal and external stakeholders to create, execute campaigns and provide all resources required\nConduct data analysis to review the effectiveness and performance of brand campaigns, thereby providing insights and optimization\nPerform quality assurance checks on published marketing materials and prepare insight reports\n\nJob Requirements\n\n\nBachelor degree holder in Marketing, Communications or other related disciplines\n2-5 years of related job experience\nGood project management skills across internal and external partners\nStrong ownership and problem solving skills\nOutstanding written and spoken communication in both Chinese and English", "employment_types": ["Full Time", "Contract"], "selling_points": [], "locations": ["Central"], "categories": ["Marketing / Public Relations", "Others"], "post_time": "2022-01-11T06:59:43Z", "salary": {"currency": null, "max": null, "min": null, "period": "monthly", "term": null}, "salary_visible": false, "title_keywords": ["communications officer", "assistant"], "responsibilities": ["review", "coordinate with", "quality", "develop", "data analysis", "reports", "marketing materials", "plans"], "requirements": {"degrees": ["bachelor degree holder"], "majors": ["related disciplines", "marketing", "communications"], "languages": ["english", "chinese"], "language_level": [], "hard_skills": ["project management", "problem solving skills"], "soft_skills": ["communication", "project management skills", "problem solving skills"], "languages_combined": [{"language": "english", "language_level": []}, {"language": "chinese", "language_level": []}]}, "experience_required": {"duration": ["2-5 years"], "field": ["related"]}}, {"job_id": "100003009041447", "location_code": "hk", "company": "GS1 Hong Kong Limited", "job_title": "Training Development Manager", "description": "Communications Office\n\n\n\nJob Requirements:\n\n\u00a0\u00a0\u00a0\u00a0\u00a0 A recognized university degree or equivalent with at least 2 years\u2019 experience in Event Management, Fund Raising, Public Relations, Corporate Communications or related fields\n\u00a0\u00a0\u00a0\u00a0\u00a0 Good command of written and spoken English and Chinese, fluent in Putonghua is preferred\n\u00a0\u00a0\u00a0\u00a0\u00a0 Proficient in MS Office (including Word, Excel and PowerPoint) and Chinese word processing is a must\n\u00a0\u00a0\u00a0\u00a0\u00a0 Knowledge in digital marketing, video production, web analytics and content management is an advantage\n\u00a0\u00a0\u00a0\u00a0\u00a0 Cooperative team player with excellent interpersonal and communication skills\n\u00a0\u00a0\u00a0\u00a0\u00a0 Self-motivated, responsible, detail-minded with creative mindset\n\u00a0\u00a0\u00a0\u00a0\u00a0 Capable to handle multi-tasks, meet tight deadlines and work under pressure\n\u00a0\u00a0\u00a0\u00a0\u00a0 Experience working in public organization or NGO is preferred\nJob Responsibilities\n\n\u00a0\u00a0\u00a0\u00a0 Assist the Assistant Manager in the organization of fund raising activities (e.g. Charity TV Show, Raffle Tickets Sale, Charity Walk, etc.) and other agency/Friends of Caritas functions\n\u00a0\u00a0\u00a0\u00a0 Liaise and co-ordinate with contractors and different stakeholders in daily work\n\u00a0\u00a0\u00a0\u00a0 Prepare publicity materials, draft speeches, press releases, promotional articles, etc.\n\u00a0\u00a0\u00a0\u00a0 Provide logistics support for event organization\n\u00a0\u00a0\u00a0\u00a0 Provide clerical support to the Communications Office (e.g. maintain proper donation records and filing system)\n\u00a0\u00a0\u00a0\u00a0 Perform any other duties as assigned by the Head of Communications\nWorking Location: Caine Road, Central\n\nWorking Hour: 39 net hours per week; shift duty is not required\n\nSalary: Subject to work experience and qualifications\n\nAppointment will be on full-time contract basis. Application with resume, expected salary and contact telephone number should be sent to Head of Communications, Room 603, Caritas House, 2 Caine Road, Hong Kong or via \"Apply Now\" on or before 25 January 2022.\nApplicants not invited for interview before 25 March 2022 may assume their applications unsuccessful.\n\n(The personal data of applicants will be used strictly and exclusively for recruitment-related purpose)\n\n", "employment_types": ["Full Time", "Permanent"], "selling_points": ["Design & maintain training programmes for members", "Knowledge of learning theories & design modules", "8+ yrs of working exp. in training & development"], "locations": ["Wan Chai"], "categories": ["Sales, CS & Business Devpt", "Business Development", "Admin & HR", "Training & Development", "Marketing / Public Relations", "Others"], "post_time": "2022-01-12T03:53:26Z", "salary": {"currency": null, "max": null, "min": null, "period": "monthly", "term": null}, "salary_visible": false, "title_keywords": ["manager"], "responsibilities": ["liaise", "provide clerical support", "any other duties", "co-ordinate with", "provide logistics support", "maintain", "recruitment", "contact", "personal data"], "requirements": {"degrees": ["university degree"], "majors": ["communications"], "languages": ["putonghua", "english", "chinese"], "language_level": ["proficient", "good command", "fluent"], "hard_skills": ["excel", "chinese word processing", "word", "powerpoint", "web analytics", "ms office"], "soft_skills": ["detail-minded", "communication skills", "self-motivated", "meet tight deadlines", "capable", "responsible", "multi-tasks", "cooperative", "creative mindset", "web analytics", "team player", "interpersonal", "work under pressure"], "languages_combined": [{"language": "putonghua", "language_level": ["fluent", "good command"]}, {"language": "english", "language_level": ["fluent", "good command"]}, {"language": "chinese", "language_level": ["fluent", "proficient", "good command"]}]}, "experience_required": {"duration": ["at least 2 years"], "field": ["related", "management", "public relations"]}}, {"job_id": "100003009042352", "location_code": "hk", "company": "Crocodile Garments Limited", "job_title": "Assistant Marketing Manager", "description": "Position Objectives\nThe primary objective of this position is to design and maintain training programmes to help members and industry practioners build knowledge, skills and capabilities leveraging GS1 global standards, services and solutions.\nBased on the training needs, the person in this role also leads and develops training content by working with subject matter experts, external training partners and trade associations.\n\nThe role also needs to be responsible for driving the business development, training and learning to enable digital transformation.\nResponsibilities\nTake the lead to identify business opportunities in current and future training and development needs, develop new initiatives for corporate and professional trainings\nCreate engaging training programmes and compelling course content leveraging GS1 standards, services and solutions\nExecute training needs analysis and develop training strategies\nDrive and lead the implementation of training courses and workshops, utilising a variety ofmethods, (classroom training, private onsite trainingandvirtualcourses)\nDevelop training materials and content as eLearning courses, educational videos, infographics, Power Point presentations and any relevant\nCollaborate efficiently with third parties and training partners for training development\nCollaborate effectively with the GS1HK stakeholders (Global Office, training associates, delivery partners, and the industries that GS1HK serves) for all training related activities\nDrive the promotion and marketing of training and learning programs\nAchieve annual target and prepare budget\nMonitor, evaluate and report on training effectiveness\nRequirements\nBachelor\u2019s or above\n8+ years of working experience in training and development\nExtensive experience in design, development and implementation of professional training programmes (in-person and virtual) and course marketing\nExcellent knowledge of learning theories and instructional design models\nLesson and curriculum planning skills\nIn-depth understanding of traditional and modern training methods and latest trends in education landscape, including e-learning, workshops and coaching, etc\nExperience in working with third parties and external training agencies\nGood command of written and spoken English and Chinese\nComputer literate (PowerPoint and other Microsoft Office, Zoom, Teams, \u2026)\nProject Management\nAbility to effectively communicate with both highly technical and non-technical persons seamlessly\nExcellent presentation and engagement skills\nPlease click \"Apply Now\" to submit your application.\nPersonal data collected will be used for recruitment purpose only.", "employment_types": ["Full Time", "Permanent"], "selling_points": ["All-rounded marketing", "PR campaigns / CRM", "Marketing planning"], "locations": ["Kwun Tong"], "categories": ["Marketing / Public Relations", "Marketing - Direct Marketing", "Others", "Digital Marketing"], "post_time": "2022-01-12T07:09:11Z", "salary": {"currency": null, "max": null, "min": null, "period": "monthly", "term": null}, "salary_visible": false, "title_keywords": ["assistant marketing manager"], "responsibilities": ["collaborate", "identify business opportunities", "analysis", "budget", "monitor", "implementation", "presentations", "develop", "evaluate", "report"], "requirements": {"degrees": ["bachelor"], "majors": [], "languages": ["english", "chinese"], "language_level": ["good command"], "hard_skills": ["workshops", "project management", "powerpoint", "microsoft office"], "soft_skills": ["planning skills", "project management", "learning", "extensive", "presentation"], "languages_combined": [{"language": "english", "language_level": ["good command"]}, {"language": "chinese", "language_level": ["good command"]}]}, "experience_required": {"duration": ["8+ years"], "field": ["development", "marketing", "training", "design"]}}, {"job_id": "100003009050958", "location_code": "hk", "company": "Links International", "job_title": "Senior Manager, Web & Mobile Marketing", "description": "Responsibilities:\n\nDevelop and manage execution all-rounded marketing and promotion campaign covering (both online and offline promotions, e-marketing, social media campaign and joint promotions with third parties)\n\nAnalyze customer insights, consumer trends, market analysis, and marketing best practices to build successful strategies\nDrive and implement strategic PR campaigns for brand positioning and enhancing brand image and awareness\nAlign with the company strategy and objectives, initiate and implement relevant online and social media platforms\nDevelop content strategy and social media plan to maximize the brand exposure\nTo initiate and implement CRM strategy and programs\n\nRequirements:\n\nDegree holder in Business, Marketing, eCommerce or a related field\nMinimum 5 years' experience in Marketing with retail exposure\nExcellent marketing planning and writing skills\nGood network with the media, press and KOL is preferred\nSense of urgency and good project management skills\nA good team player, proactive, creative, independent, detail-minded\nExcellent interpersonal and communication skills with very positive attitude\n\nInterested parties, please apply with full resume, stating date available, present and expected salary to\u00a0Human Resources & Administration Department by clicking 'Apply Now'.\n\nPersonal Data provided in the employment applications will be treated as strictly confidential and used only for recruitment purpose.\u00a0 All unsuccessful applications will be destroyed upon completion of the selection process.", "employment_types": ["Full Time", "Permanent"], "selling_points": ["Global financial trading platform", "Web marketing strategy planning", "In-depth knowledge in SEO / search engines"], "locations": ["Not Specified"], "categories": ["Information Technology (IT)", "IT - Webmaster / SEO", "Marketing / Public Relations", "Management", "Others"], "post_time": "2022-01-14T12:02:05Z", "salary": {"currency": null, "max": null, "min": null, "period": "monthly", "term": null}, "salary_visible": false, "title_keywords": ["senior manager"], "responsibilities": ["consumer trends", "social media", "social media platforms", "customer insights", "develop", "market analysis", "plan"], "requirements": {"degrees": ["degree holder"], "majors": ["ecommerce", "business", "marketing"], "languages": [], "language_level": [], "hard_skills": ["project management", "writing skills"], "soft_skills": ["detail-minded", "communication skills", "good team player", "independent", "creative", "urgency", "project management skills", "writing skills", "positive attitude", "proactive", "interpersonal"], "languages_combined": []}, "experience_required": {"duration": ["minimum 5 years"], "field": ["marketing", "retail"]}}, {"job_id": "100003009038181", "location_code": "hk", "company": "Medicare Health Clinic Limited", "job_title": "Marketing Executive & Accounts Clerk", "description": "Our client is a leading Financial Trading company. They are expanding the team and looking for Senior Manager, Web & Mobile Marketing to join their team.\n\nJob Description\n\nDevelop website and mobile marketing strategies for all markets including Greater China, India, Korea, etc.\nLead the team in monitoring, maintaining and optimizing the performance of digital platforms\nDrive website re-built project to deliver new websites for targeted markets\nCollaborate closely with product team and technology team for website optimization, covering structure, performance, UX, content perspectives through data analysis\nMaintain strong online presence for the brands across desktop and mobile environments\n\nJob Requirements\n\nDegree holder, with minimum 6 years of related web or mobile marketing\nIn-depth knowledge and experience in website technology, SEO & PPC\nHands-on experience in SEO optimization, preferably gained from financial industry\nKnowledgeable in search engines (google insight, metadata, WeChat integration), data analytic tools (Google Adwords), organic & paid traffics\nExperience in online community growth & maintenance is a plus\nData driven, good problem-solving and tech savvy\nExperiece Highly fluent in both English and Mandarin", "employment_types": ["Full Time"], "selling_points": ["5-day work", "Experience in medical field is an advantage", "Immediate available preferred"], "locations": ["Tsim Sha Tsui"], "categories": ["Marketing / Public Relations", "Others"], "post_time": "2022-01-11T05:56:55Z", "salary": {"currency": null, "max": null, "min": null, "period": "monthly", "term": null}, "salary_visible": false, "title_keywords": ["accounts clerk", "marketing executive"], "responsibilities": ["collaborate", "marketing strategies", "maintaining", "monitoring", "website", "develop", "data analysis", "maintain"], "requirements": {"degrees": ["degree holder"], "majors": ["marketing"], "languages": ["english", "mandarin"], "language_level": ["fluent"], "hard_skills": ["plus", "seo", "web", "maintenance", "adwords", "problem-solving", "wechat", "mobile", "integration"], "soft_skills": ["problem-solving", "hands-on", "driven"], "languages_combined": [{"language": "english", "language_level": ["fluent"]}, {"language": "mandarin", "language_level": ["fluent"]}]}, "experience_required": {"duration": [], "field": ["financial industry", "maintenance"]}}, {"job_id": "100003009038733", "location_code": "hk", "company": "Wang On Group", "job_title": "Assistant Officer - Corporate Affairs & Investor Relations", "description": "Marketing Executive\nJob Highlights:\n\n\nExperience in medical field is an advantage\n5-day work\nStable working environment & job prospects\n\n\u00a0Duties:\u00a0\n\nDevelop and explore new market segment for the business\nPrepare marketing materials, implement, assist & improve marketing activities/ promotions\nWork closely with internal and external parties on marketing projects\nSupport department\u2019s daily operation & marketing events / promotions\nPrepare different marketing reports as required\nAd hoc assignments as required\n\nRequirements:\n\nUniversity graduate / Higher Diploma in marketing or business-related discipline\nMinimum 1-year relevant experience in communications, advertising, PR or marketing (fresh graduates are also welcome)\nProactive, detail-minded, hard-working, multi-tasking and good team player\nGood communication, organization, presentation & interpersonal skills\nGood command of written and spoken English & Chinese (Cantonese & Mandarin)\nProficient in MS applications and Chinese Word Processing\nKnowledge of social media and/ or digital marketing is an advantage\nImmediate available is highly preferred\n\nAccounts Clerk\nJob Highlights:\n\nAccounting experience\n5-day work\nImmediately available\n\nDuties:\u00a0\n\nbank reconciliation\ndata entry\nHandle AR/AP\nHandle ad hoc tasks as assigned by supervisor\n\n\u00a0Requirements:\n\nF 5/ DSE or above\nLCCI level\n1 year or above accounting experience\ndetailed-oriented and good communication skills\nGood command in English, Chinese & Mandarin\nFamiliar with MS Words & Excel\nSolid experience in MYOB or Clinic Solution is an advantage\nImmediately available is an advantage\n\nFor Company detail, please visit our website https://medicaregroup.hk/\n\nWe offer\u00a0competitive salary,\u00a0comprehensive on-the-job training, bank holiday and basic medical benefits and attractive remuneration package to the right candidates. Interested parties please apply with your detailed resume, availability, current and expected salary.\n\n(ALL APPLICATIONS WITHOUT AVAILABILITY, CURRENT AND EXPECTED SALARY ON THEIR RESUME WILL NOT BE CONSIDERED).\n\n\u00a0All information received will be treated strictly confidential and for employment purpose only.", "employment_types": ["Full Time", "Permanent"], "selling_points": [], "locations": ["Kowloon Bay"], "categories": ["Marketing / Public Relations", "Public Relations - Event Management", "Public Relations - General / Support", "Others"], "post_time": "2022-01-11T07:42:17Z", "salary": {"currency": null, "max": null, "min": null, "period": "monthly", "term": null}, "salary_visible": false, "title_keywords": ["assistant officer"], "responsibilities": ["marketing events", "internal and external parties", "daily operation", "marketing projects", "develop", "reports", "ad hoc assignments", "prepare marketing materials"], "requirements": {"degrees": ["university graduate", "diploma", "dse"], "majors": ["business", "marketing"], "languages": ["cantonese", "english", "chinese", "mandarin"], "language_level": ["good command", "proficient"], "hard_skills": ["ap", "excel", "chinese word processing", "ms applications", "ar", "ms words", "basic", "myob"], "soft_skills": ["detail-minded", "communication skills", "good team player", "communication", "multi-tasking", "comprehensive", "hard-working", "interpersonal skills", "proactive", "presentation", "detailed"], "languages_combined": [{"language": "cantonese", "language_level": ["good command"]}, {"language": "english", "language_level": ["good command", "good command"]}, {"language": "chinese", "language_level": ["good command", "good command", "proficient"]}, {"language": "mandarin", "language_level": ["good command", "good command"]}]}, "experience_required": {"duration": ["minimum 1-year", "1 year"], "field": ["pr", "clinic", "advertising", "accounting experience", "marketing", "relevant experience"]}}, {"job_id": "100003009039931", "location_code": "hk", "company": "csl.", "job_title": "Marketing Executive, csl Mobile", "description": "Responsibilities:\n\n\nSupport corporate communications plan to facilitate effective internal and external communications\nPrepare various multimedia communications materials, including corporate publications, audio visual materials, press release, newsletter and corporate video etc.\nAssist in execution of brand management, advertising sales & marketing communication campaign on different online & printed channels\nExplore new opportunities for media coverage, collaboration and networking for promoting corporate image\nCoordinate with agencies & suppliers to ensure the quality of deliverable\nOther ad-hoc tasks as assigned by the management\n\nRequirements:\n\nDegree holder in Communications / Journalism / Public Relations / Marketing /\u00a0\u00a0Languages or related disciplines\nMinimum 2 years\u2019 experience in corporate affairs / marketing\nExcellent command of spoken and written English and Chinese including Putonghua\nIndependent, strong communication skills, and able to multi-task and work under pressure\nProficient in MS Word & Excel, and Chinese Word Processing\nKnowledge in Photoshop or other graphic design and video editing software is preferable\nExtensive network of different types of media , thorough understanding of the PR cycle\nImmediate\u00a0available\u00a0is highly preferred\n\nWe offer competitive remuneration package, our benefits include\n\nPerformance Bonus\nEducation Subsidy\nProfessional Membership Fee Sponsorship\nLife & Medical Insurance\nMarriage Leave, Compassionate Leave, Examination Leave etc.\nPublic Holidays\nStaff Purchase Discount\n\nInterested parties please send\u00a0full resume with present and\u00a0expected salary\u00a0to Human Resources Department by clicking\u00a0\"Apply Now\".\n\n(Information provided will be treated in strict confidence and will only be used for recruitment-related purposes.)", "employment_types": ["Permanent"], "selling_points": ["Grow customer value", "Support UI/UX enhancement of online shop", "Drive the loyalty programs"], "locations": ["Quarry Bay"], "categories": ["Marketing / Public Relations", "Marketing - Brand / Product Management", "Marketing - General / Support", "Others"], "post_time": "2022-01-11T15:34:19Z", "salary": {"currency": null, "max": null, "min": null, "period": "monthly", "term": null}, "salary_visible": false, "title_keywords": ["marketing executive"], "responsibilities": ["management", "advertising", "ad-hoc tasks", "coordinate with", "quality", "communication", "plan", "visual", "audio"], "requirements": {"degrees": ["degree holder"], "majors": ["journalism", "related disciplines", "marketing", "communications"], "languages": ["putonghua", "english", "chinese"], "language_level": ["excellent", "proficient"], "hard_skills": ["excel", "chinese word processing", "ms word", "video editing", "photoshop"], "soft_skills": ["communication skills", "independent", "multi-task", "thorough", "extensive", "work under pressure"], "languages_combined": [{"language": "putonghua", "language_level": ["excellent"]}, {"language": "english", "language_level": ["excellent"]}, {"language": "chinese", "language_level": ["proficient", "excellent"]}]}, "experience_required": {"duration": ["minimum 2 years"], "field": ["marketing"]}}, {"job_id": "100003009042735", "location_code": "hk", "company": "John Swire & Sons (HK) Limited", "job_title": "Communications Manager, IT & Digital (1-year contract)", "description": "Your role\n\n\nGrow customer value through innovative marketing programs\nSupport UI/UX enhancement of online shop\nDrive the loyalty programs such as customer community engagement\nProviding all-rounded supports on marketing campaigns within the team\nPerform market analysis and research\nParticipate in the daily team operation to understanding the team and business nature\nHandling assigned Ad-hoc projects\n\nTo succeed in this role\n\nUniversity graduate in Marketing, Business Administration or related disciplines\n2 years working experience in consumer marketing, preferably gained in telecommunication / banking / insurance industry or digital marketing agencies\nCreative, self-motivated, attentive to details, enjoy team work\nGood command of written and spoken English and Cantonese\nFamiliar with Google Analytics is an advantage\n\n\nHKT is an equal opportunity employer and welcomes applications from all qualified candidates. Information provided will be treated in strict confidence and will only be used for recruitment-related purposes.\nPersonal data provided by job applicants will be used strictly in accordance with the employer's privacy statement (www.hkt.com/privacy-statement), a copy of which will be provided immediately upon request.", "employment_types": ["Full Time", "Part Time", "Contract"], "selling_points": ["8 years\u2019 experience in content management", "Excellent writing and storytelling skills", "Part-time availability will also be considered"], "locations": ["Quarry Bay"], "categories": ["Media & Advertising", "Editorial / Journalism", "Marketing / Public Relations", "Others", "Professional Services", "Translation"], "post_time": "2022-01-12T08:36:33Z", "salary": {"currency": null, "max": null, "min": null, "period": null, "term": null}, "salary_visible": false, "title_keywords": ["manager"], "responsibilities": ["personal data", "market analysis", "digital marketing", "recruitment", "marketing campaigns", "banking", "ad-hoc projects", "insurance", "ui", "administration"], "requirements": {"degrees": ["university graduate"], "majors": ["related disciplines", "marketing", "business administration"], "languages": ["cantonese", "english"], "language_level": ["good command"], "hard_skills": ["google analytics", "analysis"], "soft_skills": ["self-motivated", "confidence", "creative", "attentive to details", "innovative"], "languages_combined": [{"language": "cantonese", "language_level": ["good command"]}, {"language": "english", "language_level": ["good command"]}]}, "experience_required": {"duration": ["2 years"], "field": ["marketing", "digital marketing", "insurance industry", "banking"]}}, {"job_id": "100003009045262", "location_code": "hk", "company": "PR Asia Consultants Limited", "job_title": "Assistant Associates /Associates / Senior Associates", "description": "John Swire & Sons (H.K.) Limited is the holding company of the publicly-listed conglomerate, Swire Pacific Ltd. Our IT & Digital section is inviting candidates to apply for the following position, which may be a good fit for someone looking to re-enter the workforce after an extended break.\n\nCommunications Manager, IT & Digital (1-year contract)\n\n\nThis role develops all internal and external communication from IT & Digital team to ensure message is consistent and engaging to end users. He or she facilitates a culture of self-service and self-solve, as well as shares impact and benefits of advanced technologies. The job holder also applies data and analytic insights to evolve communications strategy and tactics.\n\n\nResponsibilities:\n\nPrepare and review operational notices and processes to ensure it is easy to understand and executable\nDesign and create user guides about different IT components for end users\nCollect feedback and data analytics, and proactively revise communications for different channels and formats\nGather updates and stories to prepare regular internal newsletters\nPartner with Communication & Engagement Business Partner, for development of internal communication strategy and planning, and communication to colleagues\nDeliver training and briefings as required\n\nRequirements:\n\nBachelor\u2019s degree or above in Information Management, Business, or related discipline\n8 years\u2019 relevant experience in creating written and video content in different media\nProven record of utilizing content management systems such as Wordpress and Unily\nSound knowledge of technologies and effective applications in commercial sector\nExcellent writing and storytelling skills\nAttention to details, adaptive and a drive for continuous improvement\nGood communication skills in both spoken and written English and Chinese. Putonghua is desirable\nPart-time availability (at least 3 days a week) will also be considered\n\nApplication:\nAt Swire, we are committed to creating an inclusive and supportive working environment for all our people regardless of their age, gender, gender identity, sexual orientation, relationship, family status, disability, race, ethnicity, nationality, religious or political beliefs. We believe in creating an environment where people feel comfortable at work and are able to realise their full potential.\n\nWe offer a competitive package to the right candidate. If you meet the qualifications and are interested in this position, you can send your application by clicking \u2018Apply Now\u2019. We will contact all shortlisted candidates.\n\nThe Swire group is an equal opportunity employer. All applications will be used exclusively for selection purposes and handled confidentially by authorised personnel only. Your application may also be considered for other suitable positions within the Swire group (please indicate clearly on your application if you would not like to be considered for other positions within the group.) Following the data privacy ordinance, all unsuccessful applications will be destroyed after an appropriate time.", "employment_types": ["Full Time"], "selling_points": [], "locations": ["Sheung Wan"], "categories": ["Banking / Finance", "Financial Services", "Marketing / Public Relations", "Public Relations - General / Support", "Others"], "post_time": "2022-01-13T07:30:55Z", "salary": {"currency": null, "max": null, "min": null, "period": null, "term": null}, "salary_visible": false, "title_keywords": ["assistant"], "responsibilities": [], "requirements": {"degrees": [], "majors": [], "languages": [], "language_level": [], "hard_skills": [], "soft_skills": [], "languages_combined": []}, "experience_required": {"duration": [], "field": []}}, {"job_id": "100003009038693", "location_code": "hk", "company": "Cloudflare", "job_title": "Partner Marketing Specialist, APJC (Based in Singapore)", "description": "Assistant Associates /Associates / Senior Associates\n\nRequirements\n\nl\u00a0\u00a0 University degree holder or equivalent\n\nl\u00a0\u00a0 1 to 3 years of experience in public relations / investor relations / market research / financial media field, depending on position applied for\n\nl\u00a0\u00a0 Fresh graduates will also be considered for the post of Assistant Associate\n\nl\u00a0\u00a0 Experience in account servicing / IPO arrangement\n\nl\u00a0\u00a0 Good interpersonal communication skills and a team player\n\nl\u00a0\u00a0 Strong writing and presentation skills in both English and Chinese (fluency in spoken Mandarin)\n\nl\u00a0\u00a0 Proficiency in Chinese typing (30 wpm or above)\n\nCompetitive remuneration package including basic salary, fringe benefits and semi-annual bonus will be offered to the right candidate.\u00a0\n\nPlease note that only short-listed candidates will be notified. \u00a0Data collected will be used for recruitment purposes only and personal data of unsuccessful applicants will be destroyed after 12 months.", "employment_types": ["Full Time"], "selling_points": [], "locations": ["Not Specified"], "categories": ["Admin & HR", "Others", "Marketing / Public Relations", "Marketing - General / Support", "Others"], "post_time": "2022-01-11T07:39:13Z", "salary": {"currency": null, "max": null, "min": null, "period": "monthly", "term": null}, "salary_visible": false, "title_keywords": ["marketing specialist"], "responsibilities": ["communication", "market research"], "requirements": {"degrees": ["university degree"], "majors": [], "languages": ["english", "chinese", "mandarin"], "language_level": ["fluency", "proficiency"], "hard_skills": ["typing"], "soft_skills": ["communication skills", "team player", "interpersonal", "presentation skills"], "languages_combined": [{"language": "english", "language_level": ["fluency"]}, {"language": "chinese", "language_level": ["fluency", "proficiency"]}, {"language": "mandarin", "language_level": ["fluency"]}]}, "experience_required": {"duration": ["1 to 3 years"], "field": ["public relations", "market research", "account servicing", "media", "financial"]}}, {"job_id": "100003009043870", "location_code": "hk", "company": "Office Systems Ltd", "job_title": "Marketing Assistant", "description": "\nAbout Us\nAt Cloudflare, we have our eyes set on an ambitious goal: to help build a better Internet. Today the company runs one of the world\u2019s largest networks that powers approximately 25 million Internet properties, for customers ranging from individual bloggers to SMBs to Fortune 500 companies. Cloudflare protects and accelerates any Internet application online without adding hardware, installing software, or changing a line of code. Internet properties powered by Cloudflare all have web traffic routed through its intelligent global network, which gets smarter with every request. As a result, they see significant improvement in performance and a decrease in spam and other attacks. Cloudflare was named to Entrepreneur Magazine\u2019s Top Company Cultures list and ranked among the World\u2019s Most Innovative Companies by Fast Company.\nWe realize people do not fit into neat boxes. We are looking for curious and empathetic individuals who are committed to developing themselves and learning new skills, and we are ready to help you do that. We cannot complete our mission without building a diverse and inclusive team. We hire the best people based on an evaluation of their potential and support them throughout their time at Cloudflare. Come join us!\n\nAbout the role:\nThe Partner Marketing Team is looking for an experienced, enthusiastic & highly-motivated Partner Marketing Specialist to lead Cloudflare\u2019s partner events and campaigns in Asia Pacific, Japan and China regions. You will work hand-in-hand with partners on executing event and digital campaign initiatives to grow partner pipeline and revenue with Cloudflare . You can multitask, efficiently communicate & work cross-functionally within a partner\u2019s organization and also with Cloudflare sales, regional marketing, operations, communications & other functions. You have a passion for working with partners, are detail oriented and have a knack for juggling multiple projects at once in a (really) fast-paced environment. The programs you oversee will contribute to further accelerating Cloudflare\u2019s quickly expanding go-to-market with channel and alliance partners.\n\nWhat You'll Do\n\u2022 Collaborate with Cloudflare partners and Channel Account Managers in to develop marketing plans that help drive pipeline and revenue goals\nExecute end-to-end physical and in-person event logistics (webinars, executive roundtables, tradeshows, conferences)\nTailor global digital campaigns to partner requirements and assist partners with implementation (email, social, inbound, PPC)\n\u2022 Measure campaign impact through SFDC reporting, evaluate event/campaign ROI, and present on recommendations for improvement\n\u2022 Manage Cloudflare\u2019s MDF program in APJC, ensuring timely reviews and completed partner submissions and compiling internal and partner-facing reports\n\u2022 Provide onsite event staff/support when needed\n\nExamples Of Desirable Skills, Knowledge And Qualifications\n\u2022 Mandarin written and verbal business language competency is a must\n\u2022 Minimum of 3 years partner field marketing experience\n\u2022 Track record delivering strong event experiences that accelerate partner revenue growth\n\u2022 Familiar with different types of partners and routes to market\n\u2022 Self-motivated, able to work autonomously and communicate effectively.\n\u2022 Project management/organizational skills and the ability to successfully manage multiple initiatives at once\n\u2022 Strong interpersonal skills and the ability to coordinate across multiple departments\n\u2022 Results oriented with experience using qualitative and quantitative metrics with a focus on revenue, conversion, sales and other marketing goals\n\u2022 Experience with an enterprise software, SaaS or security company\n\u2022 Salesforce & Marketo experience\n\u2022 Ability to travel\n\u2022 Familiarity with digital campaigns is a plus\n\nWhat Makes Cloudflare Special?\nWe\u2019re not just a highly ambitious, large-scale technology company. We\u2019re a highly ambitious, large-scale technology company with a soul. Fundamental to our mission to help build a better Internet is protecting the free and open Internet.\nProject Galileo : We equip politically and artistically important organizations and journalists with powerful tools to defend themselves against attacks that would otherwise censor their work, technology already used by Cloudflare\u2019s enterprise customers--at no cost.\nAthenian Project : We created Athenian Project to ensure that state and local governments have the highest level of protection and reliability for free, so that their constituents have access to election information and voter registration.\nPath Forward Partnership : Since 2016, we have partnered with Path Forward, a nonprofit organization, to create 16-week positions for mid-career professionals who want to get back to the workplace after taking time off to care for a child, parent, or loved one.\n1.1.1.1 : We released 1.1.1.1 to help fix the foundation of the Internet by building a faster, more secure and privacy-centric public DNS resolver. This is available publicly for everyone to use - it is the first consumer-focused service Cloudflare has ever released. Here\u2019s the deal - we don\u2019t store client IP addresses never, ever. We will continue to abide by our privacy commitment and ensure that no user data is sold to advertisers or used to target consumers.\nSound like something you\u2019d like to be a part of? We\u2019d love to hear from you!\nThis position may require access to information protected under U.S. export control laws, including the U.S. Export Administration Regulations. Please note that any offer of employment may be conditioned on your authorization to receive software or technology controlled under these U.S. export laws without sponsorship for an export license.\nCloudflare is proud to be an equal opportunity employer. We are committed to providing equal employment opportunity for all people and place great value in both diversity and inclusiveness. All qualified applicants will be considered for employment without regard to their, or any other person's, perceived or actual race, color, religion, sex, gender, gender identity, gender expression, sexual orientation, national origin, ancestry, citizenship, age, physical or mental disability, medical condition, family care status, or any other basis protected by law. We are an AA/Veterans/Disabled Employer.\nCloudflare provides reasonable accommodations to qualified individuals with disabilities. Please tell us if you require a reasonable accommodation to apply for a job. Examples of reasonable accommodations include, but are not limited to, changing the application process, providing documents in an alternate format, using a sign language interpreter, or using specialized equipment. If you require a reasonable accommodation to apply for a job, please contact us via e-mail at Apply Now or via mail at 101 Townsend St. San Francisco, CA 94107.\n\n", "employment_types": ["Full Time", "Permanent"], "selling_points": ["Degree in Marketing", "3 years' experience in marketing", "Assist in social media marketing"], "locations": ["Shau Kei Wan"], "categories": ["Marketing / Public Relations", "Marketing - General / Support", "Marketing - Market Research", "Others"], "post_time": "2022-01-13T03:43:53Z", "salary": {"currency": null, "max": null, "min": null, "period": "monthly", "term": null}, "salary_visible": false, "title_keywords": ["marketing assistant"], "responsibilities": ["software", "developing", "hardware", "installing", "evaluation"], "requirements": {"degrees": [], "majors": [], "languages": [], "language_level": [], "hard_skills": ["code", "goal", "hardware", "web traffic"], "soft_skills": ["committed", "innovative", "diverse", "learning"], "languages_combined": []}, "experience_required": {"duration": [], "field": []}}, {"job_id": "100003009038753", "location_code": "hk", "company": "Circle Home Limited", "job_title": "Event & Roadshow Marketing Trainee", "description": "Degree in Marketing\n3 years' experience in marketing\nAssist in social media marketing\nInterested parties please email by clicking \"Apply Now\" for interview.\nAll information collected for recruitment purpose only.", "employment_types": ["Full Time"], "selling_points": [], "locations": ["Wan Chai"], "categories": ["Admin & HR", "Others", "Marketing / Public Relations", "Marketing - General / Support", "Others"], "post_time": "2022-01-11T07:44:48Z", "salary": {"currency": null, "max": null, "min": null, "period": "monthly", "term": null}, "salary_visible": false, "title_keywords": ["trainee"], "responsibilities": ["social media"], "requirements": {"degrees": ["degree"], "majors": ["marketing"], "languages": [], "language_level": [], "hard_skills": [], "soft_skills": [], "languages_combined": []}, "experience_required": {"duration": ["3 years"], "field": ["marketing"]}}, {"job_id": "100003009042743", "location_code": "hk", "company": "Hong Kong Productivity Council", "job_title": "Manager, Digital Consulting  (Digital Transformation Division) (Ref: DTD021/22, 5410/JDB/120122)", "description": "\nJob Highlights\n*\nEvent & Roadshow Marketing\n*\nGraduate Trainee\n*\nFriendly and joyful working environment\nJob Description\nJob Duties:\n\u2022 To assist clients in increasing brand awareness and boosting sales performance through events, exhibitions and roadshows\n\u2022 To ensure the smooth operation of the events and roadshows by providing logistics and transportation arrangement, location planning, product testing and on-site support\n\u2022 To take part in team development and management by recruiting new people, as well as providing support and coaching to the new people\nWhat We Offer:\nOverseas exchange opportunities (e.g. Malaysia, Korea, Singapore, Bali, Thailand and Taiwan, etc)\n\u2022 Friendly and joyful working environment with strong team culture\n\u2022 Diversified workshops and team activities\n\u2022 Support in career development and career growth\n\u2022 Hierarchical training from sales to leadership and management\nJob Requirements:\n\u2022 Fluent Cantonese is a must\n\u2022 Outgoing, presentable, talkative and self-motivated\n\u2022 Excellent communication and collaboration skills\n\u2022 Diploma or above in any disciplines\n\u2022 Fresh graduates are welcome\nPart-time hours: 45 per week\nApplication Deadline: 14/1/2022\n\u5de5\u4f5c\u985e\u578b: \u5168\u8077, \u517c\u8077, \u9577\u5de5, \u81ea\u7531\u5de5\u4f5c\n\u85aa\u916c: $17,000.00\u81f3$23,000.00(\u6bcf\u6708)\n\u6642\u9593:\n\u2022 \u65e5\u73ed\n\u2022 \u5f48\u6027\u6642\u9593\n\u798f\u5229:\n\u2022 \u5728\u8077\u5c08\u696d\u57f9\u8a13\n\u2022 \u80b2\u5b30\u5047\n\u2022 \u4f9b\u81b3\u98df\n\u2022 \u54e1\u5de5\u8cfc\u7269\u512a\u60e0\n\u2022 \u5f48\u6027\u4e0a\u73ed\u6642\u9593\n\u2022 \u984d\u5916\u4f11\u606f\u65e5\n\u88dc\u5145\u85aa\u916c:\n\u2022 \u4f63\u91d1\n\u2022 \u52e4\u5de5\u734e\u91d1\n\u2022 \u7e3e\u6548\u734e\u91d1\n\u6559\u80b2\u7a0b\u5ea6:\n\u526f\u5b78\u58eb / \u9ad8\u7d1a\u6587\u6191 (\u5fc5\u8981\u689d\u4ef6)\n\u8a9e\u8a00:\nCantonese (\u5fc5\u8981\u689d\u4ef6)\n\u9060\u7a0b\u5de5\u4f5c:\n\u2022 \u5426\n\n", "employment_types": ["Permanent"], "selling_points": ["5-day work week, dental benefit, Medical benefit", "Bachelor degree in Statistics, Psychology", "At least 6 years experience in quantitative"], "locations": ["Not Specified"], "categories": ["Professional Services", "Business Analysis / Data Analysis", "Marketing / Public Relations", "Others", "Sciences, Lab, R&D", "Research & Development (R&D)"], "post_time": "2022-01-12T09:54:04Z", "salary": {"currency": null, "max": null, "min": null, "period": "monthly", "term": null}, "salary_visible": false, "title_keywords": ["manager"], "responsibilities": ["management", "sales performance", "testing", "logistics", "providing support", "planning"], "requirements": {"degrees": [], "majors": [], "languages": [], "language_level": [], "hard_skills": [], "soft_skills": [], "languages_combined": []}, "experience_required": {"duration": [], "field": []}}, {"job_id": "100003009038400", "location_code": "hk", "company": "GDC Technology Limited", "job_title": "Marketing Assistant", "description": "Responsibilities:\u00a0\n\nPrepare reports with key findings and provide value-added deliverables to senior management review\nWork closely with sales team to identify revenue and profit growth opportunities and evaluate the revenue impact of business changes\nIdentify opportunities to improve customer profitability\nMonitor customer contract compliance to ensure revenue management policy and procedure adherence by field operations\nAnalyze UPS offerings and develop a summary of UPS\u2019s position relative to competitors\nAssist ad-hoc projects as required\nRequirements:\n\nDegree holder or above in Business Administration, Marketing, Economics, Mathematics, Statistics or a quantitative related discipline\nAt least 2 years of relevant working experience\nStrong analytical skills, business acumen and value focused\nExcellent interpersonal and communication skills with different stakeholders\nExcellent time management and be able to work under pressure\nKnowledge of air cargo or express industry and revenue management is a plus\nProficient in MS Office Suite of products including Access, Excel and PowerPoint\nWhat we can offer:\nAttractive Salary Package\nGuaranteed Double Pay\nPerformance Bonus\n5-day work week\nPaid Annual Leave\nMedical Insurance\nLife Insurance\nTraining Opportunities\nCareer Development Opportunities\nStable, Open and Friendly Working Environment", "employment_types": ["Full Time"], "selling_points": [], "locations": ["North Point"], "categories": ["Marketing / Public Relations", "Marketing - General / Support", "Others", "Digital Marketing"], "post_time": "2022-01-11T06:47:40Z", "salary": {"currency": null, "max": null, "min": null, "period": "monthly", "term": null}, "salary_visible": false, "title_keywords": ["marketing assistant"], "responsibilities": ["management", "ad-hoc projects", "operations", "review", "monitor", "compliance", "develop", "evaluate", "sales team", "prepare reports", "senior management"], "requirements": {"degrees": ["degree holder"], "majors": ["mathematics", "business administration", "economics", "statistics", "marketing"], "languages": [], "language_level": [], "hard_skills": ["excel", "plus", "acumen", "analytical skills", "powerpoint", "ms office"], "soft_skills": ["communication skills", "focused", "analytical skills", "business acumen", "time management", "interpersonal", "work under pressure"], "languages_combined": []}, "experience_required": {"duration": ["at least 2 years"], "field": ["relevant working experience"]}}, {"job_id": "100003009039932", "location_code": "hk", "company": "csl.", "job_title": "Senior Marketing Executive (retail visual merchandising)", "description": "Senior Marketing Executive, 1O1O Marketing (retention focus)\n\nYour role\n\nPlan and execute a vast of marketing campaigns to retain customers and to grow in-base revenue in order to achieving business target\nDevelop and implement the customer retention strategy by making use of up-to-date marketing tool, such as digital marketing tools, segmentation by data\nWork closely with channel anchors, frontend and backend departments to ensure end-to-end smoothly delivery of mobile marketing programs\nExplore collaboration with external business partner to create extra value to our customers and partners\nEvaluate the effectiveness of campaigns and prepare related reports and post-campaign analysis\nMonitor mobile marketing policy and support other ad hoc projects\n\nTo succeed in this role\n\nUniversity graduate in Marketing, Business Administration or related discipline\n3 years working experience in marketing of telecommunications / banking / consumer goods or services\nStrong business sense, detailed oriented and a team player\nExcellent project management and presentation skills\nPreferably with marketing experience in customer retention programs launch\nExcellent command of written and spoken English and Cantonese\n\n\nHKT is an equal opportunity employer and welcomes applications from all qualified candidates. Information provided will be treated in strict confidence and will only be used for recruitment-related purposes.\nPersonal data provided by job applicants will be used strictly in accordance with the employer's privacy statement (www.hkt.com/privacy-statement), a copy of which will be provided immediately upon request.", "employment_types": ["Full Time"], "selling_points": ["Support retail branding", "Prepare and manage retail stores planograms", "Safeguard the brand essence in retail environment"], "locations": ["Quarry Bay"], "categories": ["Media & Advertising", "Others", "Marketing / Public Relations", "Marketing - Marketing Communication", "Others"], "post_time": "2022-01-11T15:36:29Z", "salary": {"currency": null, "max": null, "min": null, "period": "monthly", "term": null}, "salary_visible": false, "title_keywords": ["merchandising", "senior marketing executive"], "responsibilities": ["data", "analysis", "monitor", "banking", "develop", "evaluate", "project management", "digital marketing", "reports", "marketing campaigns", "plan", "ad hoc projects", "recruitment", "personal data", "administration"], "requirements": {"degrees": ["university graduate"], "majors": ["marketing", "business administration"], "languages": ["cantonese", "english"], "language_level": ["excellent"], "hard_skills": ["mobile", "focus", "analysis", "project management"], "soft_skills": ["confidence", "detailed oriented", "business sense", "project management", "presentation skills", "team player", "focus", "vast"], "languages_combined": [{"language": "cantonese", "language_level": ["excellent"]}, {"language": "english", "language_level": ["excellent"]}]}, "experience_required": {"duration": ["3 years"], "field": ["telecommunications", "marketing", "banking"]}}, {"job_id": "100003009038679", "location_code": "hk", "company": "Redpath Partners Limited", "job_title": "Senior Property Officer/Property Officer \u2013 Residential (Kowloon/HK Island area)", "description": "Responsibilities:\n\n\nResponsible for coordinating well-rounded projects including digital and offline projects \u00a0\nCoordinate with regional offices and other departments to support overseas events\nInterested in developing website design and content\u00a0with Shopify/ Wordpress/ WIX backend\nManage social media platforms including YouTube, LinkedIn, Instagram\nHands-on experience to create layouts with stock photos, canva, mail chimp for Facebook posts, IG posts and email marketing\nCollect market intelligence, benchmark and understand trends to provide recommendations and evaluation on new technologies\u00a0for digital marketing\nTrack and analyze the website and campaign traffic flow and provide regular internal reports\nDefine SEO / SEM strategy and implement at reasonable price\nResponsible for the production of marketing materials including artworks development,\u00a0script writing for\u00a0brochures, presentations, etc.\nSupport marketing team in PR tasks such as editing and proof-reading releases and distributing press releases\nSource vendors and manage inventory and distribution of marketing materials and premiums\nResponsible for maintaining daily marketing expenses records\nHandling ad hoc duties assigned by superiors\nOpportunity to work in GDC regional offices including USA and Singapore\n\nRequirements:\n\nRecent graduates with exceptional profile or Chinese citizens with outstanding international or Hong Kong work experience are welcome to apply\nPassionate about digital online tools and technology. Up to date with the latest trends and best practices in online marketing and measurement\nKnowledge in website management, eDM formulation and distribution, social media and digital marketing is preferred\nKnowledge in e-commerce platforms e.g. Amazon, Google Shopping, Facebook Shops and eBay is preferred\nHands-on campaign management experience for key paid marketing platforms (Google Ads, Facebook Ads Manager, etc.) is preferred\nA highly motivated self-starter with good planning and time management skills to meet tight deadlines and able to maintain a \u201ccan-do\u201d mind-set\nProficient in proofreading, translation and editing in both English and Chinese\nStrong organizational, prioritization and communication skills; must be a \u201cpeople-person\u201d and well-versed in communicating with international parties\n\nAttractive remuneration package will be offered.\n\nAll information provided by applicants will be treated in strict confidence and used only for processing application.", "employment_types": ["Full Time", "Permanent"], "selling_points": ["Top Property Management Firm", "Hong Kong Based", "Attractive salary renumeration package"], "locations": ["Central & Western Area"], "categories": ["Marketing / Public Relations", "Others", "Property / Real Estate", "Property Management", "Sales, CS & Business Devpt", "Sales - Real Estate"], "post_time": "2022-01-11T16:01:46Z", "salary": {"currency": null, "max": null, "min": null, "period": "monthly", "term": null}, "salary_visible": false, "title_keywords": ["property officer", "senior property officer"], "responsibilities": ["inventory", "social media platforms", "website", "design", "evaluation", "facebook", "editing", "ad hoc duties", "maintaining", "expenses", "developing", "presentations", "reports", "seo", "coordinate with", "provide recommendations", "digital marketing", "create layouts", "sem", "marketing materials"], "requirements": {"degrees": [], "majors": [], "languages": ["english", "chinese"], "language_level": ["proficient"], "hard_skills": ["amazon", "e-commerce", "facebook", "processing", "translation"], "soft_skills": ["communication skills", "meet tight deadlines", "confidence", "time management skills", "organizational", "hands-on", "motivated", "can-do", "passionate about"], "languages_combined": [{"language": "english", "language_level": ["proficient"]}, {"language": "chinese", "language_level": ["proficient"]}]}, "experience_required": {"duration": [], "field": ["management", "marketing"]}}, {"job_id": "100003009041392", "location_code": "hk", "company": "GS1 Hong Kong Limited", "job_title": "Senior Product Marketing Officer", "description": "Your role\n\nSupport retail branding and merchandizing strategy implementation\nCoordinate and liaise with internal teams, including sales and marketing teams, to deliver effective marketing communications materials for different marketing programs at our retail shops\nBrief, manage and evaluate external agencies in delivering quality and effective communications materials in a timely and cost efficient manner\nPrepare and manage retail stores planograms to maximize products and services exposure\nBe the brand champion to safeguard the brand essence in retail environment\nPerform quality checks and shop visits to ensure smooth and complete implementation of visual merchandising materials according to the guideline and standard\nHandle and follow up retail\u2019s enquiries on visual merchandizing and replenishment request\nUndertake any other activities as assigned by supervisors\n\nTo succeed in this role\n\nDegree holder preferably in marketing, communications or business disciplines\n2-3 years of working experience in marketing communications, advertising agency background is an advantage\nSelf-motivated, able to work independently and handle multi-tasks\nDetailed oriented, creative, strong organizational skills\nAble to work under high pressure and long hours and meet tight deadline\nExcellent English and Chinese in both written and verbal communications\nProficiency in MS window application including Excel, Word and Chinese word processing\n\u00a0\n\nHKT is an equal opportunity employer and welcomes applications from all qualified candidates. Information provided will be treated in strict confidence and will only be used for recruitment-related purposes.\nPersonal data provided by job applicants will be used strictly in accordance with the employer's privacy statement (www.hkt.com/privacy-statement), a copy of which will be provided immediately upon request.", "employment_types": ["Full Time", "Permanent"], "selling_points": ["Execute go-to-market strategies,marketing campaign", "3yrs+ B2B product marketing experience", "Exp. in IT/Retail/Food industry would be advantage"], "locations": ["Wan Chai"], "categories": ["Marketing / Public Relations", "Marketing - General / Support", "Public Relations - General / Support", "Others"], "post_time": "2022-01-12T03:50:04Z", "salary": {"currency": null, "max": null, "min": null, "period": "monthly", "term": null}, "salary_visible": false, "title_keywords": ["marketing officer"], "responsibilities": ["cost", "advertising", "teams", "implementation", "quality", "merchandising", "coordinate", "evaluate", "replenishment", "recruitment", "visual", "liaise with", "personal data"], "requirements": {"degrees": ["degree holder"], "majors": ["business", "marketing", "communications"], "languages": ["english", "chinese"], "language_level": ["excellent", "proficiency"], "hard_skills": ["merchandizing", "excel", "chinese word processing", "visual merchandising", "word"], "soft_skills": ["efficient", "organizational skills", "work independently", "self-motivated", "detailed oriented", "confidence", "multi-tasks", "timely", "work under high pressure", "meet tight deadline", "smooth", "creative"], "languages_combined": [{"language": "english", "language_level": ["excellent"]}, {"language": "chinese", "language_level": ["excellent", "proficiency"]}]}, "experience_required": {"duration": ["2-3 years"], "field": ["marketing communications", "advertising agency"]}}, {"job_id": "100003009040397", "location_code": "hk", "company": "Michael Page", "job_title": "Vice President, Public Relations Practice (US Agency)", "description": "A well-known entity in Hong Kong is currently seeking a Senior Property Officer/Property Officer to assist with their current property management portfolio in Hong Kong.\n\nTo be a successful candidate you should possess the following key skills:\u00a0\n\nDegree or Diploma in Property Management or related industries\n2+ years\u2019 experience or above in property management\nYou will be responsible with overseeing tenancy issues, compliance checks and maintaining good relations with tenants and owners\nIdentify areas requiring preventive or remedial actions in respect of cleaning, repairs, and security\nLiaise with internal and external parties on necessary changes in the property estate\nStrong communication and interpersonal skills are required \u00a0\nThose holding a valid Property Management Licence will be highly preferred\n\nTo apply, please contact Jacky at 3796 3121 in our Hong Kong office at jacky(at)redpathpartners.com\n\nPlease email your CV\u2019s in Word format, all applications will be dealt with in confidence.\n\nFor more live vacancies please visit www.redpathpartners.com", "employment_types": ["Full Time", "Permanent"], "selling_points": ["US-based Agency", "Strong client base in Asia", "Strategic role - developing SEA markets"], "locations": ["Not Specified"], "categories": ["Media & Advertising", "Strategic Planning", "Editorial / Journalism", "Marketing / Public Relations", "Others"], "post_time": "2022-01-12T02:31:39Z", "salary": {"currency": null, "max": null, "min": null, "period": "monthly", "term": null}, "salary_visible": false, "title_keywords": ["vice president"], "responsibilities": ["management", "maintaining", "compliance", "internal and external parties", "communication", "contact", "cleaning", "liaise with"], "requirements": {"degrees": ["diploma", "degree"], "majors": [], "languages": [], "language_level": [], "hard_skills": ["word"], "soft_skills": ["communication and interpersonal skills", "confidence", "responsible"], "languages_combined": []}, "experience_required": {"duration": ["2+ years"], "field": ["management"]}}, {"job_id": "100003009041391", "location_code": "hk", "company": "GS1 Hong Kong Limited", "job_title": "Senior Officer (SEM), Digital Marketing", "description": "Key Responsibilities:\nAssist supervisor to drive the development of product value prepositions, vision, strategy and go-to-market plan for GS1HK solutions and services.\nResearch markets, competitors and trends, analyze target and potential sectors, formulate effective messaging strategies and marketing channels to reach the respective target segments.\nExecute go-to-market strategies, marketing campaigns, online/offline marketing programs to achieve business targets, drive lead generation and enhance product awareness & positioning.\nDevelop product collaterals, eDMs, social media content, use cases, videos, etc. to correctly communicate the values to the target segments\u00a0\u00a0\nCoordinate and organize lead-generation events such as webinars, seminars, workshops, round tables, trade fair booths, etc.\nAnalyze campaign statistics to measure effectiveness and prepare reports\nSupport ad hoc projects when required.\nRequirements:\nDegree holder in Marketing, Communications, Business or related field\n3-5+ years of B2B product marketing experience, preferably for IT solutions\nHighly motivated self-starter who can work in a dynamic fast-paced environment, full of drive and able to work under pressure\nExcellent communication, presentation and interpersonal skills\nGood command of written and spoken Chinese and English\nExperience in IT, Retail, or Food industry would be an advantage\nInterested parties please send your application letter and resume with salary expected to HR Department, GS1 Hong Kong, 22/F OTB Building, No.160 Gloucester Road, Wanchai or by clicking \"Apply Now\"\n\n(Personal data collected will be used for recruitment purpose only)", "employment_types": ["Full Time", "Permanent"], "selling_points": ["Develop bilingual content & image for SEM", "Must have hands on experience on SEM", "Experience in digital agency is an advantage"], "locations": ["Wan Chai"], "categories": ["Marketing / Public Relations", "Marketing - Marketing Communication", "Others", "Digital Marketing"], "post_time": "2022-01-12T03:50:04Z", "salary": {"currency": null, "max": null, "min": null, "period": "monthly", "term": null}, "salary_visible": false, "title_keywords": ["senior officer", "digital marketing"], "responsibilities": ["edms", "develop", "coordinate", "social media content", "ad hoc projects", "marketing campaigns", "plan", "prepare reports"], "requirements": {"degrees": ["degree holder"], "majors": ["business", "marketing", "communications"], "languages": ["english", "chinese"], "language_level": ["good command"], "hard_skills": ["dynamic"], "soft_skills": ["fast-paced environment", "communication", "dynamic", "motivated", "interpersonal skills", "presentation", "work under pressure"], "languages_combined": [{"language": "english", "language_level": ["good command"]}, {"language": "chinese", "language_level": ["good command"]}]}, "experience_required": {"duration": ["5+ years"], "field": ["marketing", "it", "food industry", "retail"]}}, {"job_id": "100003009034918", "location_code": "hk", "company": "The Garage Limited", "job_title": "Digital Strategist", "description": "A leading public relations agency is seeking a Vice President to expand its businesses in Asia. With a strong client portfolio in North Asia and Greater China, the company is seeking to develop the South-east Asia market through strategic hires in Hong Kong.\n\nClient Details\n\nThis company is a renowned US-based agency with strong performances in public relations, investor relations and corporate communications. It provides a unique solution to multinational corporations (MNCs) - uplifting Asia-based companies' profiles in western markets (North America and Europe) in order to engage potential customers and investors.\n\nDescription\n\nThe VP for the Public Relations practice will be a strategic leader in the company's public relations businesses. Working with teammates across APAC (the company has presence in Mainland China, Hong Kong, Singapore, and India currently), you will deepen existing client relationships while developing new ones. The company is particularly strong in some geographical markets and industries. Hence, you can leverage on these strengths and increase penetration through cross-selling. There is also a large untapped market potential in new geographical markets and industries. The role of the VP is to identify potential growth areas and develop plans to expand the reach of the business. The VP will make use of the company's global consulting network to deliver client solutions. Gradually, the VP will also hire new staff based in Hong Kong to serve South-east Asia clients more effectively.\n\nProfile\n\nThe successful candidate should come with at least 10 years of experience in corporate communications, public relations (financial PR is preferred). Experiences working in an agency environment would make it easier for the candidate to adapt to the fast-paced and entrepreneurial environment. As a competent leader, the candidate should be able to deliver excellent products to clients, develop new businesses, manage stakeholders who are often in very senior positions in listed companies, and collaborate with teammates from across cultures and locations.\n\nStrong written and verbal communications skills in English are non-negotiable. Spoken Chinese competency is an advantage.\n\nJob Offer\n\nThis position offers an entrepreneurial candidate with an opportunity to take ownership of a business venture, while enjoying the backing of a well-established company. It also offers flexibility of remote work. Operating with established offices, staff are enabled to work in locations of their own preferences. Some travels may be required once Covid-related travel restrictions are lifted. Until then, the role is mainly based in Hong Kong.\n\nTo apply online please click the 'Apply' button below. For a confidential discussion about this role please contact Anthony Lau on +852 3412 4851.", "employment_types": ["Full Time"], "selling_points": ["Plan and implement marketing campaigns", "Manage digital campaign projects", "Prepare proposals and reports"], "locations": ["Kowloon Bay"], "categories": ["Media & Advertising", "Account Servicing", "Marketing / Public Relations", "Others", "Digital Marketing"], "post_time": "2022-01-10T04:38:54Z", "salary": {"currency": null, "max": null, "min": null, "period": "monthly", "term": null}, "salary_visible": false, "title_keywords": [], "responsibilities": ["collaborate with", "consulting", "market potential", "developing", "develop", "contact", "develop plans"], "requirements": {"degrees": [], "majors": [], "languages": ["english", "chinese"], "language_level": ["advantage"], "hard_skills": ["make"], "soft_skills": ["unique", "competent"], "languages_combined": [{"language": "english", "language_level": []}, {"language": "chinese", "language_level": ["advantage"]}]}, "experience_required": {"duration": ["at least 10 years"], "field": ["pr", "public relations", "agency", "it", "financial"]}}, {"job_id": "100003009039090", "location_code": "hk", "company": "Auberge Hospitality Limited", "job_title": "And we are hiring \u2013 Assistant Manager \u2013 Marketing & Membership, Auberge Hospitality", "description": "Job Duties\nAttentive to details, execute and monitor Google and social media (FB, LinkedIn, WeChat) paid campaigns, set & monitor conversion tracking, and updating corporate website\nCreating online ads campaign including SEM, GDN, Facebook boost post and LinkedIn Ads\nDevelop bilingual content & image for SEM and other marketing materials on digital media platforms (e.g. Google, Facebook, website and blog, etc.)\nEvaluate effectiveness of digital marketing campaigns with analysis report, maximize ROI of Search Engine Marketing (SEM), Display Advertising, Social Media Marketing, etc.\nIdentify, evaluate, and take actions to improve campaigns' effectiveness\nAssist in managing social media channels and preparing monthly report\nRequirements\nDegree holder in Marketing/Communications/ Multi-media or related disciplines\n3-5 years of experience in digital marketing, must have hands on experience on SEM\nKnowledge in using Photoshop or ai in designing artworks\nExperience in digital agency is an advantage\nKnowledge in Google Tag Manager will be an advantage\nGood command of written Chinese and English\nInterested parties please send your application letter and resume with salary expected to HR Department, GS1 Hong Kong, 22/F OTB Building, No.160 Gloucester Road, Wanchai or by clicking \"Apply Now\"\n(Personal data collected will be used for recruitment purpose only)", "employment_types": ["Full Time", "Permanent"], "selling_points": ["Plan and execute marketing activities, events", "Degree holder or above, graduated in Marketing", "5 - 6 years relevant work experience"], "locations": ["Lantau Island"], "categories": ["Marketing / Public Relations", "Marketing - Marketing Communication", "Public Relations - Event Management", "Others"], "post_time": "2022-01-11T08:44:46Z", "salary": {"currency": null, "max": null, "min": null, "period": "monthly", "term": null}, "salary_visible": false, "title_keywords": ["assistant manager"], "responsibilities": ["social media", "advertising", "analysis report", "digital marketing campaigns", "monitor", "website", "develop", "evaluate", "sem", "maximize roi", "marketing materials", "facebook", "monthly report", "tracking"], "requirements": {"degrees": ["degree holder"], "majors": ["related disciplines", "marketing", "communications"], "languages": ["english", "chinese"], "language_level": ["good command"], "hard_skills": ["ai", "sem", "photoshop"], "soft_skills": ["hands on"], "languages_combined": [{"language": "english", "language_level": ["good command"]}, {"language": "chinese", "language_level": ["good command"]}]}, "experience_required": {"duration": ["3-5 years"], "field": ["agency", "digital", "digital marketing"]}}, {"job_id": "100003009033585", "location_code": "hk", "company": "CLP Power Hong Kong Limited", "job_title": "Account Manager (2-Year Contract) [Ref.: CLPP_CBD_CCE_CCA_AM]", "description": "Responsibilities:\nAssist the Director of Hospitality Marketing and Membership in promoting Auberge Hospitality portfolios, including its hotel, clubs and other leisure properties in Discovery Bay\nInitiate brand development strategy and marketing plan for promoting our DB Ice Rink's services and facilities\nPlan and execute marketing activities, events & PR promotions\nAssist in membership recruitment and membership related matters and services\nAnalyze data and provide insights to relevant departments, identify new marketing opportunities to achieve business objectives\nDevelop all marketing materials, such as e-newsletters, leaflets, press release, display and promotional materials, and digital marketing programs (CRM, Social, Content, SEM, SEO etc)\nPerform any other ad-hoc tasks as assigned\nRequirements:\nDegree holder or above, graduated in Marketing or Communications will be an advantage\n5 - 6 years relevant work experience, preferably with experience in shopping mall marketing\nFamiliar with CMS, design software, social media, web analytics and production of marketing materials\nIndependent, attention to detail, resourceful and proactive in solving problems\nProficiency in Microsoft Office (Word / Excel / PowerPoint)\nExcellent command of spoken and written English, Cantonese and Mandarin\nWe offer an attractive remuneration package and excellent career opportunities to the right candidate. Interested applicants please send your CV by email via \"Apply Now\"\u00a0or by WhatsApp at 63173527.\nPersonal data provided by job applicants will be used strictly for recruitment purposes only.", "employment_types": ["Full Time", "Contract"], "selling_points": [], "locations": ["Sham Shui Po"], "categories": ["Engineering", "Engineering Project Management", "Marketing / Public Relations", "Others"], "post_time": "2022-01-10T16:52:51Z", "salary": {"currency": null, "max": null, "min": null, "period": "monthly", "term": null}, "salary_visible": false, "title_keywords": ["account manager"], "responsibilities": ["marketing materials", "provide insights", "seo", "digital marketing programs", "leaflets", "ad-hoc tasks", "develop", "marketing plan", "promotional materials", "recruitment", "plan", "sem", "analyze data"], "requirements": {"degrees": ["degree holder"], "majors": ["marketing", "communications"], "languages": ["cantonese", "english", "mandarin"], "language_level": ["excellent"], "hard_skills": ["excel", "microsoft office", "word", "powerpoint", "web analytics"], "soft_skills": ["independent", "resourceful", "attention to detail", "web analytics", "proactive"], "languages_combined": [{"language": "cantonese", "language_level": ["excellent"]}, {"language": "english", "language_level": ["excellent"]}, {"language": "mandarin", "language_level": ["excellent"]}]}, "experience_required": {"duration": ["5 - 6 years"], "field": ["marketing"]}}, {"job_id": "100003009035623", "location_code": "hk", "company": "AMERICAN EAGLE OUTFITTERS HONG KONG LTD", "job_title": "Director Program Management - International Omni-channel Retail", "description": "Reporting to the Corporate Customer Experience Manager - Corporate and Commercial Accounts, the appointee will have the following key responsibilities:\n\nMajor Duties:\n\nGenerate targeted business outcomes including retaining existing electricity sales and generating additional sales through fuel switching projects and achieving energy reduction targets via sale of energy management products and services\u00a0\nSeek to build relationships with potential customers outside the assigned portfolio and establish new business opportunities with new customers\u00a0\nAnalyse\u00a0and evaluate customer energy consumption characteristics, develop innovative energy concepts &\u00a0solutions\u00a0and take appropriate actions to meet customer needs\u00a0\u00a0\nCommunicate CLP\u2019s position on issues concerning the environment, tariff, community, etc. and seek customer endorsement of these activities\u00a0\nAssist in organizing events,\u00a0seminars\u00a0and meetings for customers\u00a0\u00a0\nCoordinate with relevant internal stakeholders to provide timely technical consultancy and energy management advice to customers\u00a0\nDevelop a set of challenging targets and related strategy to achieve energy sustainability goals for management endorsement\u00a0\nRequirements:\u00a0\n\nA recognized university degree in Engineering/ Environmental Management or\u00a0related disciplines, with a minimum of\u00a07\u00a0years\u2019 working experience\u00a0\nExperience in marketing, e-marketing,\u00a0sales\u00a0and account management in a fast-moving business environment.\u00a0 Hand-on experience in developing energy management solutions for corporate clients is a plus\u00a0\nFamiliarity with power supply systems and demand side energy management practices\u00a0\nStrong presentation skills including ability to put together persuasive sales presentations and establish strong business partnerships\u00a0\nWell versed in project management and application of commercial tools for business and market analysis\u00a0\u00a0\nPrevious experience in leading a team for innovation projects and digital transformation is highly desirable\u00a0\nGood communication skills, including both spoken and written English and Chinese\u00a0\nCandidates with less experience may be considered as Account Management Specialist\u00a0\nWe look for professional and experienced candidate who will manage a portfolio of accounts, including Government Departments, Institutional Organizations,\u00a0NGOs\u00a0and large commercial customers. Competitive remuneration package will be offered to the right candidate.\u00a0\n\nPlease apply by\u00a0clicking the button \"Apply Now\"\u00a0\u00a0giving a detailed C.V., including career history, major achievements and personal attributes on or before 18 January\u00a02022.\n\nImportant:\u00a0 To facilitate our easy tracking please use a unique file name for all attachments and your email subject box in this format:\u00a0CCE_CCA_AM_Last Name_First Name_Other Names (if applicable)\n\nApplicants not invited for interview within 6 weeks from the closing date may assume their applications unsuccessful.\u00a0\n\nInformation provided will be for recruitment purpose within the CLP Group and only short-listed candidates will be contacted. We comply with all applicable laws and regulations of HKSAR in handling applications.\n\nFor details of the Personal Information Collection Statement, please visit our website: https://clp.to/engPICS\u00a0\n\n\nFor further information on our company, please visit our website:\u00a0\u00a0\nhttps://www.clpgroup.com/\u00a0\n\n\n\n\u00a0 \u00a0Date Exhibited: 11.01.2022\u00a0\nDate Withdrawn: 18.01.2022\n\n\nInformation Classification: PROPRIETARY\n(\u672c\u9805\u8077\u4f4d\u7a7a\u7f3a\u53ea\u5099\u82f1\u6587\u7248\u672c)\n", "employment_types": ["Full Time"], "selling_points": [], "locations": ["Overseas"], "categories": ["Marketing / Public Relations", "Marketing - Brand / Product Management", "Marketing - General / Support", "Others"], "post_time": "2022-01-10T07:54:53Z", "salary": {"currency": null, "max": null, "min": null, "period": "monthly", "term": null}, "salary_visible": false, "title_keywords": ["director"], "responsibilities": ["management", "business opportunities", "coordinate with", "develop", "evaluate", "analyse"], "requirements": {"degrees": ["university degree"], "majors": ["related disciplines", "engineering"], "languages": ["english", "chinese"], "language_level": ["good"], "hard_skills": ["plus", "analysis", "presentations", "project management", "c"], "soft_skills": ["communication skills", "persuasive", "unique", "project management", "presentation skills", "business environment", "detailed"], "languages_combined": [{"language": "english", "language_level": ["good"]}, {"language": "chinese", "language_level": ["good"]}]}, "experience_required": {"duration": ["minimum of 7 years"], "field": ["management", "engineering", "related", "developing", "marketing", "environmental", "business", "digital", "account management", "team"]}}, {"job_id": "100003009038709", "location_code": "hk", "company": "Philips Electronics Hong Kong Limited", "job_title": "2022 Graduate Trainee (Personal Health Business)", "description": "Position Summary\n\nAs a Director of Program Management, this role is responsible for driving the development and management of the features and functionality of our Omni-channel experiences in order to provide a seamless, world-class customer experience across a diverse, multichannel environment for International stores and e-commerce. This role will partner with cross-functional teams to drive the development of product features and capabilities across all channels for international business while optimizing ROI and driving business strategies.\n\nResponsibilities\n\nProvide a single point of coordination and communication at the highest level to gain executive sponsorship, streamline communication, ensure common understanding of development plans, facilitate portfolio change management, and implement tracking and status reporting for the total project portfolio.\nDrives the adoption and implementation of project and program management methodology and oversees project and program management coaching. Establishes methodologies and governance for the organization ensuring total compliance\nDevelop metrics to measure success of program features, analyze results, and partner across the organization to develop action plans and enhancement recommendations.\nDrive teams to execute and deliver: development roadmaps, project plans, project and iteration estimates, technical documentation, deliverable lists, burn down and burn up charts, project budgets and forecasting, and the overall deployment of projects and releases for all individual projects.\nSupport teams in the synthesizing business requirements, identifying areas of uncertainty, recommending solutions, gathering buy-in from relevant stakeholders, rolling solutions out to team, shepherding features through development and reviewing code before rollout.\nEnsure project management team creates and drives detailed communication plans, champions the needs of business.\nLead the prioritization of product features and understand the art of sequencing their delivery in an agile framework.\nLead the product-discovery process, collaborating with key stakeholders to identify and analyze new product opportunities and enhancements\nWork to consistently understand all cross-functional requirements around product design to ensure critical business issues are surfaced, addressed, and resolved.\nEnsure all business and technology teams have clarification around product specifications and respond to any considerations raised by these teams\nEnsure our partner relationships and third-party dependencies run as smoothly as possible by identifying desirable features, negotiating contracts, handling implementation, etc.\nPartner with all consumer insight teams to define metrics and report on business results\nProviding guidance on detailed project right sizing, timeline adjustments, resource adjustments, detailed functional and technical requirement gathering and project needs\nIdentify, assess, and communicate project risks and partner with delivery teams, cross-functional partners, and business stakeholders to understand options and execute solves.\nExecutive Stakeholder Management\n\nDeliver consistent communication to key stakeholders and relevant business partners from product lifecycle though launch\nCommunicate all relevant business decisions and key metrics to Head of Product and executive leadership team\nDevelop strong relationships with business owners, senior leadership, and executive team\nQualifications\n\nBachelor\u2019s Degree in a Business Administration, Finance, Marketing, or related discipline\nAdvanced degree (MBA, Master\u2019s) or equivalent experience preferred\n10+ years relevant experience, including 5+ years\u2019 experience in the area of Retail Technology with demonstrated proficiency in the global retail industry a plus\nBi-Lingual fluency strongly preferred\nHigh degree of proficiency MS Office Suite, Outlook & Internet applications\nStrong analytical, prioritizing, interpersonal, problem-solving, presentation (one-on-one, small and large groups, with peers and management), b udgeting, & planning skills\nDemonstrates a high level of competence and passion for technology and a comprehensive understanding of usability. Innovative and forward-thinking. Needs to understand the global retail best practices as well as practical solutions to problems.\nStrong business acumen particularly in the areas of retail marketing and sales, including strategic planning, business case development, forecasting, budgeting and prioritizing.\nStrong verbal and written communication skills\nDemonstrated collaborative skills and ability to work well within a team\nAbility to work with and influence peers and senior management\nAbility to work in a fast-paced and deadline-oriented environment\nSelf-motivated with critical attention to detail, deadlines and reporting\nAEO is an Equal Opportunity Employer and is committed to complying with all federal, state and local equal employment opportunity (\"EEO\") laws. AEO prohibits discrimination against associates and applicants for employment because of the individual's race or color, religion or creed, alienage or citizenship status, sex (including pregnancy), national origin, age, sexual orientation, disability, gender identity or expression, marital or partnership status, domestic violence or stalking victim status, genetic information or predisposing genetic characteristics, military or veteran status, or any other characteristic protected by law. This applies to all AEO activities, including, but not limited to, recruitment, hiring, compensation, assignment, training, promotion, performance evaluation, discipline and discharge. AEO also provides reasonable accommodation of religion and disability in accordance with applicable law.\n\nPrimary Location\n\nUnited States-New York-NEW YORK\n\nWork Locations\n\nNew York Design Office\n\nJob\n\nTechnology\n\nShift\n\nStandard\n\nJob Type\n\nFull-time\n\nJob Level\n\nDay Job\n\nJob Posting\n\nOct 6, 2021, 9:12:29 AM\n\n\n\nInterested candidates, please click APPLY NOW \u00a0to apply.", "employment_types": ["Full Time"], "selling_points": ["Management Trainee", "Fresh Graduate", "Healthcare Industry"], "locations": ["Shatin Area"], "categories": ["Marketing / Public Relations", "Others", "Sales, CS & Business Devpt", "Others", "Management", "Management Trainee"], "post_time": "2022-01-11T07:39:42Z", "salary": {"currency": null, "max": null, "min": null, "period": "monthly", "term": null}, "salary_visible": false, "title_keywords": ["personal", "graduate trainee"], "responsibilities": ["budgeting", "clarification", "communication", "evaluation", "plans", "senior management", "administration", "contracts", "compliance", "teams", "implementation", "develop", "forecasting", "report", "reporting", "management", "guidance", "change management", "strategic planning", "product design", "specifications", "documentation", "cross-functional teams", "tracking", "budgets", "project management", "recruitment", "coordination", "planning"], "requirements": {"degrees": ["degree", "bachelor", "master"], "majors": ["finance", "marketing", "business administration"], "languages": [], "language_level": [], "hard_skills": ["small", "plus", "bi", "agile", "e-commerce", "problem-solving", "acumen", "project management", "outlook", "deployment", "documentation", "code", "ms office"], "soft_skills": ["agile", "collaborative", "communication", "comprehensive", "leadership", "problem-solving", "diverse", "committed", "presentation", "interpersonal", "world-class", "communication skills", "attention to detail", "prioritizing", "detailed", "planning skills", "self-motivated", "advanced", "responsible", "passion for", "project management", "coordination", "business acumen", "innovative"], "languages_combined": []}, "experience_required": {"duration": ["5+ years", "10+ years"], "field": ["retail industry", "management", "e-commerce", "development", "relevant experience", "retail"]}}, {"job_id": "100003009043173", "location_code": "hk", "company": "OSIM (HK) Co. Limited", "job_title": "Digital Marketing Executive ( 5 Days Work)", "description": "Are you a recent graduate ready to start an amazing career? Are you looking for a role where you\u2019ll be able to make a difference and improve people\u2019s lives?\n\nPhilips Hong Kong 2-year Graduate Trainee Program while give you an insight to what it\u2019s like to work for a global health technology company and experiencing 1st career life. We are now hiring:\n\nPersonal Health Graduate Trainee (Consumer Product Sales & Marketing focus)\nYou have an opportunity to\n\n\nJoin a global leading healthtech company and be part of a dynamic team. Philips Graduate Program not only providing on-the-job training, but a 2-year immersive journey. Our program will accompany young talents to have mutual growth, to be innovative and write the future of Healthtech together.\n\n2-year job rotation program within Personal Health business unit\nVarious job attachment across business & functions including sales & marketing, operations, services delivery and project management\nAssignments via hands-on training, day-to-day business, with mentors coaching and buddies support\nCareer development path to be progressed into a future leader throughout the program\n\nTo succeed in this role, you should have the following skills, attributes and experience:\n\nHave graduated in 2021/2022 (Degree or Master) from any of the following faculties \u2013 Business Administration, Sciences, Life Sciences, Health & Social Science and Health Technology\nIdeally bring work experience through internships, held leadership roles or involvement in extracurricular activities\nExcellent communication, presentation and analytical skills\nHave a genuine interest in business and are intellectually curious\nAbility to adapt in an ever-changing environment\nGood command of written and spoken English and Chinese/Cantonese\n\nIn return, we offer you\n\nA path towards your most rewarding career. Philips is growing its marketing capability enterprise wide. Succeeding in this market-based role in a complex environment will open many doors for your long term career, in other areas in Philips or otherwise. We also believe that we are at our best as a company when you are at yours as a person. Thus, we offer competitive health benefits, a flexible work schedule and access to local well-being focused activities.\n\nWhy should you join Philips?\n\nWorking at Philips is more than a job. It\u2019s a calling to create a healthier society through meaningful work, focused on improving 3 billion lives a year by delivering innovative solutions across the\u00a0health continuum. Our people experience a variety of unexpected moments when their lives and careers come together in meaningful ways.\n\n\n", "employment_types": ["Full Time", "Permanent"], "selling_points": [], "locations": ["Shatin Area"], "categories": ["Marketing / Public Relations", "Marketing - Direct Marketing", "Others", "E-commerce", "Marketing - Brand / Product Management"], "post_time": "2022-01-12T10:00:42Z", "salary": {"currency": null, "max": null, "min": null, "period": "monthly", "term": null}, "salary_visible": false, "title_keywords": ["digital marketing executive"], "responsibilities": ["operations", "communication", "project management", "career development", "administration"], "requirements": {"degrees": ["degree", "master"], "majors": ["science", "business administration"], "languages": ["cantonese", "english", "chinese"], "language_level": ["good command"], "hard_skills": ["analytical skills", "make", "project management", "dynamic", "focus"], "soft_skills": ["genuine", "analytical skills", "communication", "project management", "hands-on", "dynamic", "focus", "innovative", "leadership", "presentation"], "languages_combined": [{"language": "cantonese", "language_level": ["good command"]}, {"language": "english", "language_level": ["good command"]}, {"language": "chinese", "language_level": ["good command"]}]}, "experience_required": {"duration": [], "field": []}}, {"job_id": "100003009039383", "location_code": "hk", "company": "MOL Hong Kong Limited", "job_title": "Accounts Receivable Administrator / Assistant Manager (MCS)", "description": "Responsibilities:\n\nResponsible for content management of the brand website and other e-commerce channels\nAssist the team to plan and execute online promotion campaigns\n\nManage social media channels in order to meet the targeted KPI\nPlan and monitor company\u2019s SEO and SEM management\n\nParticipate and communicate with headquarters in website enhancement\nAssist in performance analysis in all digital channels\nAssist in any ad hoc duties as requested\n\nRequirements:\n\nDegree holder in Marketing / Communications e-commerce or related disciplines\nWith 1 - 2 years of solid experience in online marketing\n\nExperience in Google analytics is an advantage\nProactive, results-oriented with a strong sense of responsibility\nFast-paced with excellent communication and interpersonal skills\nCreative and attention to details\nGood command of spoken and written English, Cantonese, and Mandarin\n\n\nInterested parties, please send your full resume with\u00a0current salary,\u00a0expected salary,\u00a0and\u00a0available date\u00a0either by direct application from JobsDB (Please quote the job title on the subject ) or by WhatsApp:69298297 or by post to Human Resources Department, Unit 8-14 & 22-28, 11/F, Topsail Plaza, 11 On Sum Street, Shek Mun.\n\"Personal data collected will be used for recruitment purposes only.\"", "employment_types": ["Full Time", "Permanent"], "selling_points": [], "locations": ["Kwai Hing"], "categories": ["Accounting", "Others", "Marketing / Public Relations", "Others"], "post_time": "2022-01-11T09:36:16Z", "salary": {"currency": null, "max": null, "min": null, "period": "monthly", "term": null}, "salary_visible": false, "title_keywords": ["administrator", "assistant manager"], "responsibilities": ["communicate with", "social media", "management", "ad hoc duties", "seo", "analysis", "monitor", "website", "plan", "sem", "online promotion"], "requirements": {"degrees": ["degree holder"], "majors": ["related disciplines", "marketing", "communications", "e-commerce"], "languages": ["cantonese", "english", "mandarin"], "language_level": ["good command"], "hard_skills": ["google analytics", "e-commerce"], "soft_skills": ["creative", "sense of responsibility", "communication and interpersonal skills", "attention to details", "proactive"], "languages_combined": [{"language": "cantonese", "language_level": ["good command"]}, {"language": "english", "language_level": ["good command"]}, {"language": "mandarin", "language_level": ["good command"]}]}, "experience_required": {"duration": ["1 - 2 years"], "field": ["marketing"]}}, {"job_id": "100003009043845", "location_code": "hk", "company": "Office Systems Ltd", "job_title": "Marketing Manager", "description": "Responsibilities:\n\nManage and handle overall accounts receivable administration process;\nProvide aging reports and invoice statements to management, internal and external customers;\nHandle ad-hoc accounts receivables and billing matters, e.g. cancelled invoices and overpayments;\nHandle cost invoices from group companies;\nPerform other ad hoc reports, support functions and projects upon request.\n\nRequirements:\n\nDiploma in Business Administration or equivalent; with accounting knowledge is an advantage;\n3-5 years\u2019 relevant working experience; fresh graduates will also be considered;\nDetail-minded, good analytical and interpersonal skills;\nProficiency in MS Excel Functions (Pivot Table, V-Lookup, Sumif, etc.);\nWith knowledge of FlexSystem will be an advantage;\nGood command of both spoken and written English and Chinese;\nImmediately available is preferred;\nCandidates with less experience will be considered as Accounts Receivable Administrator.\nInterested parties, please click \"Apply Now\" to submit your application.\n\nAll information provided by applicants will be used for recruitment related purpose only and will be handled in strict confidence by authorized personnel.", "employment_types": ["Full Time", "Permanent"], "selling_points": ["Degree in Marketing", "5 years' experience in marketing", "Experience in manage a sales team"], "locations": ["Shau Kei Wan"], "categories": ["Marketing / Public Relations", "Management", "Marketing - Brand / Product Management", "Others"], "post_time": "2022-01-13T03:46:28Z", "salary": {"currency": null, "max": null, "min": null, "period": "monthly", "term": null}, "salary_visible": false, "title_keywords": ["marketing manager"], "responsibilities": ["ad-hoc", "internal and external customers", "management", "cost", "ad hoc", "invoices", "accounts receivable", "invoice", "reports", "administration"], "requirements": {"degrees": ["diploma"], "majors": ["business administration"], "languages": ["english", "chinese"], "language_level": ["good command"], "hard_skills": ["pivot table", "ms excel", "flexsystem"], "soft_skills": ["detail-minded", "interpersonal skills"], "languages_combined": [{"language": "english", "language_level": ["good command"]}, {"language": "chinese", "language_level": ["good command"]}]}, "experience_required": {"duration": ["3-5 years"], "field": ["relevant working experience"]}}, {"job_id": "100003009038771", "location_code": "hk", "company": "Recruitment Intelligence Consultants Ltd", "job_title": "MARKETING COMMUNICATIONS EXECUTIVE", "description": "Degree in Marketing\n5 years' experience in marketing\nExperience in manage a sales team\nCommission + Bonus\n\n\nInterested parties please email by clicking \"Apply Now\" for interview.\nAll information collected for recruitment purpose only.", "employment_types": ["Full Time", "Permanent"], "selling_points": [], "locations": ["Not Specified"], "categories": ["Marketing / Public Relations", "Marketing - General / Support", "Marketing - Marketing Communication", "Others"], "post_time": "2022-01-11T08:15:24Z", "salary": {"currency": null, "max": null, "min": null, "period": "monthly", "term": null}, "salary_visible": false, "title_keywords": ["marketing communications executive"], "responsibilities": ["sales team"], "requirements": {"degrees": ["degree"], "majors": ["marketing"], "languages": [], "language_level": [], "hard_skills": [], "soft_skills": [], "languages_combined": []}, "experience_required": {"duration": ["5 years"], "field": ["marketing", "team"]}}, {"job_id": "100003009035679", "location_code": "hk", "company": "Champion Land Properties Limited", "job_title": "Senior Manager (Corporate Digital Marketing)", "description": "Expanding Technology Company\nExcellent Career Opportunity\nOur client is an IT Managed Services and Support company with a strong focus on VDI, Virtualization and Cloud. The company provides customized IT Consulting Solutions, Project Management, IT Resourcing and on/off-shore Application Development Services across the Asia Pacific region. With offices strategically located in key business Hubs including Hong Kong, Japan and Singapore with satellite operations in Australia, China, India and the Unites States, the company is looking for an outstanding individual to join the company due to expansion.\u00a0\u00a0\n\nAssist the line manager in planning and implementing lead-generation campaigns, event, promotion. Develop compelling marketing collateral for different lines of business, with cross functional teams. Work with graphic designer to develop effective lead-generation activities and drip email campaigns. Promote our products and services in online and offline channels. Support and coordinate for brand building initiatives with internal stakeholders. Track ROI for all marketing campaigns and deliver reporting and metrics on result and campaign effectiveness. Stay up to date on competitive landscape and market trends while continuing to innovate marketing tactics. Assist ad hoc duties as assigned.\u00a0\u00a0\n\nTo be considered, you will be a university graduate with a minimum of 3 relevant experience in B2B marketing for enterprise IT products and solutions. Familiar with eDM systems is a must. Flexible and dynamic, ability to work under pressure and navigate and lead under uncertainty. Attention to details, quality control & execution efficiency. Excellent command of English & Chinese.\u00a0\n\nInterested applicants should send a detailed resume to Kelly Kam quoting reference jdb-4573\u00a0via email.\u00a0 Please click \u201cAPPLY NOW\u201d button below.\u00a0\n\n(Applicants not contacted within 4 weeks should consider their application unsuccessful.)", "employment_types": ["Full Time"], "selling_points": [], "locations": ["Not Specified"], "categories": ["Marketing / Public Relations", "Marketing - Marketing Communication", "Others", "Digital Marketing"], "post_time": "2022-01-10T08:08:10Z", "salary": {"currency": null, "max": null, "min": null, "period": "monthly", "term": null}, "salary_visible": false, "title_keywords": ["senior manager", "digital marketing"], "responsibilities": ["ad hoc duties", "reporting", "consulting", "edm", "work under pressure", "operations", "systems", "teams", "develop", "coordinate", "project management", "marketing campaigns", "quality control", "application development", "planning"], "requirements": {"degrees": ["university graduate"], "majors": ["marketing", "it"], "languages": ["english", "chinese"], "language_level": ["excellent"], "hard_skills": ["project management", "focus", "dynamic"], "soft_skills": ["flexible", "detailed", "project management", "dynamic", "attention to details", "focus", "work under pressure"], "languages_combined": [{"language": "english", "language_level": ["excellent"]}, {"language": "chinese", "language_level": ["excellent"]}]}, "experience_required": {"duration": [], "field": ["marketing", "relevant experience", "it"]}}, {"job_id": "100003009034316", "location_code": "hk", "company": "Niya K HK Limited", "job_title": "Sales & Marketing Coordinator", "description": "This position revolves around formulating and implementing of integrated marketing projects at the corporate level. Projects include but not limited to website development, social media management (content & strategies) and through the line campaign management. The incumbent will also liaise and coordinate with internal and external parties to ensure cost efficiency and timely delivery. Other duties include developing integrated marketing strategies to achieve KPI, keeping track on the regular media performance, conducting industrial and competitor analysis as well as translating findings into workable strategies.\nRequirements:\nDegree in Marketing, MIS, Journalism or related disciplines\nA minimum of 10 years working experience in digital & integrated marketing, preferably in real estate industry/ corporate environment\nStrong in MS Excel, database/CMS platform and analytics tools\nKnowledge in SEO and website structure\nCreative and highly resourceful with strategic mind and people skills\nAbility to work independently under pressure and meet challenging deadlines\nExcellent spoken and written communication in English and Chinese\nCandidates with less experience will be considered as Manager\n\n\nWe offer attractive remuneration packages commensurate with experience and qualifications. If you aspire to an exciting and rewarding career, send your resume immediately, quoting your present and expected salaries by clicking the button\u00a0\u201cApply Now\u201d.\nIf the applicant does not receive a response by 9 February 2022, the application will be considered unsuccessful.\u00a0 Please read our Personal Information Collection Statement at\u00a0https://www.sino.com/en-US/Careers/Personal-Information-Collection-Statement\u00a0before submitting your application. Information provided by applicants will be treated in strict confidence and used for recruitment purposes only.", "employment_types": ["Full Time"], "selling_points": [], "locations": ["Not Specified"], "categories": ["Admin & HR", "Others", "Marketing / Public Relations", "Marketing - General / Support", "Others"], "post_time": "2022-01-10T03:09:21Z", "salary": {"currency": null, "max": null, "min": null, "period": "monthly", "term": null}, "salary_visible": false, "title_keywords": ["marketing coordinator", "sales"], "responsibilities": ["liaise", "social media", "management", "cost", "marketing strategies", "analytics tools", "other duties", "seo", "analysis", "internal and external parties", "coordinate with", "marketing projects", "website", "developing", "communication", "database", "campaign management"], "requirements": {"degrees": ["degree"], "majors": ["journalism", "related disciplines", "marketing"], "languages": ["english", "chinese"], "language_level": ["excellent"], "hard_skills": ["analytics tools", "analysis", "ms excel", "seo"], "soft_skills": ["work independently", "under pressure", "resourceful", "timely", "communication", "creative"], "languages_combined": [{"language": "english", "language_level": ["excellent"]}, {"language": "chinese", "language_level": ["excellent"]}]}, "experience_required": {"duration": ["minimum of 10 years"], "field": ["digital", "marketing"]}}, {"job_id": "100003009039402", "location_code": "hk", "company": "Christian Dior Far East Limited", "job_title": "Regional Private Clients Analyst (1-year contract)", "description": "\nWe are a growing jewellery retail brand with a wide customer base in Hong Kong specialising in bespoke designs. We are looking for someone to work closely with the Owners and help them to follow up on all sales and marketing related matters.\nThis includes the following responsibilities:\n- Follow up on all actions after sales meeting including quotations, order issuing, procurement of materials and follow up with factory\n- Manage website and e-commerce activities for ready products\n- Assist Owners in marketing activities, including social media posts and other advertising\nThe candidate should have at least 2 years of experience in the jewellery industry with a passion for design. At the same time, they should be familiar with photo taking and social media marketing.\nWe are willing to consider candidates with less experience but with a drive to learn, willing to work hard and showing a sense of responsibility towards their work\nFluency in english is a must as well as good communication skills\nCandidate should be able to work under pressure and multi-task\nFluency in excel is important, knowledge of photo editing is an advantage\nThis is a great opportunity for candidates interested in jewellery and marketing and want to be involved throughout the process\nJob Types: Full-time, Permanent\nSalary: $18,000.00 - $23,000.00 per month\nSchedule:\n\u2022 Monday to Friday\nSupplemental Pay:\n\u2022 Performance bonus\nExperience:\njewellery: 2 years (Preferred)\nLanguage:\nEnglish (Required)\nCantonese (Preferred)\nMandarin (Preferred)\nWork Remotely:\n\u2022 No\n\n", "employment_types": ["Full Time", "Temporary", "Contract"], "selling_points": ["Coordination of Clienteling Projects in APAC & HQ", "Reporting and data analysis", "Uber Luxury Business Facilitation"], "locations": ["Causeway Bay"], "categories": ["Marketing / Public Relations", "Others", "Sales, CS & Business Devpt", "Others"], "post_time": "2022-01-11T09:40:16Z", "salary": {"currency": null, "max": null, "min": null, "period": "monthly", "term": null}, "salary_visible": false, "title_keywords": ["analyst"], "responsibilities": ["social media", "advertising", "manage website", "design", "communication", "schedule", "editing", "work under pressure"], "requirements": {"degrees": [], "majors": [], "languages": ["cantonese", "english", "mandarin"], "language_level": ["fluency", "good"], "hard_skills": ["excel", "no", "e-commerce"], "soft_skills": ["communication skills", "multi-task", "sense of responsibility", "passion for", "interested in", "work under pressure"], "languages_combined": [{"language": "cantonese", "language_level": []}, {"language": "english", "language_level": ["fluency", "good"]}, {"language": "mandarin", "language_level": []}]}, "experience_required": {"duration": ["at least 2 years"], "field": ["design"]}}, {"job_id": "100003009039666", "location_code": "hk", "company": "Sun Hung Kai Properties Ltd", "job_title": "RESEARCH OFFICER \u2013 MARKET RESEARCH", "description": "Responsibilities\n\nCoordination of Clienteling Projects with 13 markets and with Paris HQ\nCoordinate with Paris HQ and 13 markets with Private Client requests\nAllocation and consolidation of Show gifting, Welcome Packages, and Thank you Initiatives\nBuild Client itineraries for traveling clients (local, regional, and international)\nReporting and data analysis\nExtract relevant data from Dior Client Database\nRun Pivot table and create charts based on client data\nExecute strategies set by Senior Manager based on yearly client calendar\nWeekly Best Practice reporting (based on Big Purchases or Special Dior initiatives)\nUber Luxury Business Facilitation\nAnalyze\u00a0Uber Luxury Business with market KPIs\nConsolidate Uber Luxury\u00a0Product orders and follow up with Paris HQ\nCalculate ROI, Client RSVP for each\u00a0Uber Luxury Events\nMonitor Uber Luxury\u00a0database and provide monthly feedback to Paris HQ\nOther ad hoc duties as assigned\nRequirement\n\nUniversity or College Degree in relevant field\u00a0 \u00a0\u00a0\nMinimum 4 years relevant working experience in the high-end niche market\nRetail product knowledge is an advantage\nProficiency in Microsoft computer applications (Excel, Word, PowerPoint) and email skills required\nFluent in English, both written and spoken is essential\nAbility to speak Mandarin and a second language would be an advantage\nStrong comprehension of how data and information flow through client data systems\nDisciplined approach to managing metrics and reporting\nSolid comprehension of luxury industry and specific markets in APAC region\nPositive, bold, resilient, can-do attitude and thrive in a fast-paced environment\nStrong project execution skills and meet deadlines/deliverables\nImmediate availability preferred\nInterested parties please send your full resume and salary expectation to:\u00a0recruit@ hk.christiandior.com.\n*All applications will be treated in strict confidence and used only for recruitment purpose. Applicants who are not invited for an interview within 4 weeks may be considered for other suitable positions within the Group over a one year period, after which their personal data will be destroyed.*", "employment_types": ["Full Time", "Permanent"], "selling_points": ["Degree with 5 years' market research experience", "Conduct quantitative surveys on properties markets", "Willing to work overtime and on public holidays"], "locations": ["Wan Chai"], "categories": ["Marketing / Public Relations", "Marketing - Market Research", "Others", "Property / Real Estate", "Others"], "post_time": "2022-01-11T10:25:27Z", "salary": {"currency": null, "max": null, "min": null, "period": null, "term": null}, "salary_visible": false, "title_keywords": ["research officer"], "responsibilities": ["ad hoc duties", "reporting", "data", "coordinate with", "monitor", "data analysis", "coordination", "database", "kpis"], "requirements": {"degrees": ["degree"], "majors": [], "languages": ["english", "mandarin"], "language_level": ["advantage", "fluent"], "hard_skills": ["excel", "luxury industry", "word", "powerpoint"], "soft_skills": ["can-do attitude", "fast-paced environment", "bold", "meet deadlines", "positive"], "languages_combined": [{"language": "english", "language_level": ["fluent"]}, {"language": "mandarin", "language_level": ["advantage"]}]}, "experience_required": {"duration": ["minimum 4 years"], "field": ["relevant working experience"]}}, {"job_id": "100003009033611", "location_code": "hk", "company": "CaSO (HK) Engineering Co., Limited", "job_title": "Sales Administrator", "description": "Requirements:\n\n\nBachelor\u2019s degree in statistics, mathematics, marketing or a related discipline\nMinimum 5 years\u2019 experience in market research in Hong Kong & China with qualitative research experience preferred\nKnowledge on residential property and retail market in HK & Mainland China preferred\nProficiency with SPSS, Excel & Powerpoint. Knowledge on SQL and VBA an advantage\nProven English proficiency and fluent Putonghua\nGood communication, analytical and time management skills\nProactive, independent and detail-minded\nWilling to work overtime and on public holidays, as well as under pressure\n\nResponsibilities:\n\n\nDesign and conduct quantitative surveys on residential properties markets, shopping malls in HK and Mainland and other Group's business so as to understand market sentiment and customer behaviors & needs\nLiaise with internal departments and external research agencies on research requirement\nAssist in leveraging large amount of data by using SQL, VBA or some big data tools\nCompile timely research & analytical reports\n\nGood remuneration and attractive fringe benefits will be offered to the successful applicant.\u00a0 Interested parties please apply with full resume, present and expected salary, available date by clicking \" Apply Now\".\n\nFor further information, please visit our company website:\u00a0www.shkp.com.\n\nWe are an equal opportunity employer and welcome applications from all qualified candidates. All personal data collected will be used for recruitment purpose only.\u00a0 Applicants not hearing from us within 3 months may consider their applications unsuccessful.\u00a0 All personal data collected will be destroyed within 24 months.", "employment_types": ["Full Time"], "selling_points": ["Sales", "marketing", "Sales & marketing"], "locations": ["Tsim Sha Tsui"], "categories": ["Marketing / Public Relations", "Others", "Sales, CS & Business Devpt", "Others", "Sales Administration"], "post_time": "2022-01-10T01:19:47Z", "salary": {"currency": null, "max": null, "min": null, "period": "monthly", "term": null}, "salary_visible": false, "title_keywords": ["sales administrator"], "responsibilities": ["data", "big data", "design", "reports", "liaise with"], "requirements": {"degrees": ["degree", "bachelor"], "majors": ["mathematics", "marketing", "statistics"], "languages": ["putonghua", "english"], "language_level": ["proficiency", "fluent"], "hard_skills": ["sql", "excel", "vba", "powerpoint"], "soft_skills": ["detail-minded", "work overtime", "independent", "under pressure", "time management skills", "communication", "proactive"], "languages_combined": [{"language": "putonghua", "language_level": ["fluent", "proficiency"]}, {"language": "english", "language_level": ["proficiency"]}]}, "experience_required": {"duration": ["minimum 5 years"], "field": ["research", "market research"]}}, {"job_id": "100003009036481", "location_code": "hk", "company": "IKEA", "job_title": "Marketing Leader, North Asia", "description": "CaSO (HK) Engineering Company Limited\n\nCaSO (HK) Engineering Company Limited which is wholly-owned subsidiary of CaSO Environmental Group Limited was incorporated in 2003 and aims to provide green products backed by premium service. In Hong Kong and Macau, construction industry is very hot market now, and our business is extending fast recently as well, so that we are looking for a high caliber professional to join our group.\n\nWe treat our staff the most treasurable asset of the group and have been providing the best nurture and career prospect to any talents. We now invite capable & passionate person to join us.\n\n\n\nResponsibilities:\n\uff0eTo provide full spectrum of clerical and administration support to marketing and sales team\n\uff0e\u00a0To support sales team including prepare quotations, purchase order, generate reports\n\uff0eTo support marketing activities\n\uff0eTo perform system entries and master update\n\uff0eTo organize and maintain the filing system\n\uff0eTo assist in ad hoc assignments\n\nRequirements:\n\uff0eDiploma or above, Fresh Graduate preferred\n\uff0eLanguage skills in English, Cantonese and Mandarin\n\uff0eTeam player, able to work with tight deadline\n\uff0eProficiency in computer skills including Microsoft Word, Excel and PowerPoint, Knowledge of Chinese Word Processing is ideal\n\uff0eDetail-minded, good communication and interpersonal skills\n\uff0eImmediate available is preferable\n\nSatisfactory remuneration package will be offered to the successful applicants.\u00a0Interested parties please send your application with date of availability, present & expected salary to our email\u00a0or\u00a0clicking \u201cAPPLY NOW\u201d.\u00a0\u00a0\n\nPersonal data collected would be used for recruitment purpose only. If candidates are not hearing from us within 6 weeks, their applications will be filed for future reference and will be destroyed after three months. Please visit http://www.caso.com.hk for company information.\n\nOur Benefits:\n\nPublic Holiday, Annual Leave, Marriage Leave, Maternity Leave & Paternity Leave\nAnnual\u00a0Bonus\nBirthday Gift\nMedical Insurance Benefits\nMandatory Provident Fund Contribution\nTraining Subsidies\nExcellent Training & Career Advancement Opportunitie\n\nPersonal data collected will be used for recruitment purposes only.", "employment_types": ["Full Time", "Permanent"], "selling_points": ["Drive innovative ideas with marketing campaigns", "Support Manager to develop communication plan", "Work independently and lead big-scaled projects"], "locations": ["Shatin Area"], "categories": ["Marketing / Public Relations", "Marketing - General / Support", "Marketing - Marketing Communication", "Others"], "post_time": "2022-01-10T10:38:49Z", "salary": {"currency": null, "max": null, "min": null, "period": "monthly", "term": null}, "salary_visible": false, "title_keywords": [], "responsibilities": ["purchase", "maintain", "sales team", "reports", "ad hoc assignments", "administration"], "requirements": {"degrees": ["fresh graduate"], "majors": [], "languages": ["cantonese", "english", "chinese", "mandarin"], "language_level": [], "hard_skills": ["excel", "microsoft word", "chinese word processing", "powerpoint", "computer skills"], "soft_skills": ["communication and interpersonal skills", "ideal"], "languages_combined": [{"language": "cantonese", "language_level": []}, {"language": "english", "language_level": []}, {"language": "chinese", "language_level": []}, {"language": "mandarin", "language_level": []}]}, "experience_required": {"duration": [], "field": []}}, {"job_id": "100003009034696", "location_code": "hk", "company": "The English Schools Foundation", "job_title": "Communications Officer with Graphic Design - Sha Tin College", "description": "\nWHY YOU WILL LOVE US\n\nWe\u2019re a diverse group of down-to-earth, straightforward people with a passion for home furnishing. We come from all over the world, but we share an inspiring vision: \u201cto create a better everyday life for the many people\u201d. How we realize this vision is based on our shared humanistic values. These values guide our work and build our inclusive, open and honest culture. It\u2019s all based on a spirit of togetherness and enthusiasm. We work hard, but we have fun doing it. We\u2019re always looking for people who share our positive attitude and values.\n\n\nWHY WE WILL LOVE YOU\n\n\nMinimum 6 years of working experience in Marketing Communication\nExperience with handling multiple projects at the same time with good schedule control\nAbility to work with tight time schedules and used to high working pace\nExperience of effective and efficient use and measurement of all media\nExperience of successfully coordinating and leading processes creating marketing communication\nCompelling communicator both verbally and in writing\nAbility to communicate confidently and clearly both in Chinese and English\nSelf-reliant and motivated with a proven ability to work as part of a team as well as independently\n\nWHAT YOU WILL BE DOING DAY TO DAY\n\nStrategically plan conceptualized idea and key message of national campaigns and activities based on commercial priority and consumer insight, which are feasible for both North Asia market\nIn close co-operation with SO commercial activity team and store local marketing team, and lead marketing campaign owner of all functions to develop campaign communications, and integrate the communication execution in all marketing functions are aligned in content, message, key visual and copy elements under the same direction\nSupport External Communication Manager to develop communication plan from strategic perspective to synergy and integrate various media tools to support commercial activities and achieve business objectives\nManage the creative communication done in all external media including offline and online contents are aligned with IKEA Brand Values and contribute to Business objectives\nDrive innovative ideas, coordinate and influence internal and external stakeholders to create more synergy to maximize communication impact\nSupervise media agency to optimize the most efficient and effective media buying to achieve campaign goal\nFollow up the execution, results, return on investment and investment related to all external marketing communication activities (GRP, web analytics, SOV, etc.) and provide learning and solution to continually optimize effectiveness\nLead advertising and media agency service review to enhance better quality to meet our expectation. To establish agreed SOP with agencies to enhance time management and working efficiency\nWork independently and lead big-scaled projects with cross function team to drive action and maximize communication synergy that improves brand preference and supports achieving sales goals\nControl budget and costs by working in lean, simple, and cost-conscious way, and have a good sense of ROI\n\nTOGETHER AS A TEAM\n\nLead marketing campaign project team on project basis to develop and execute impactful communication ideas and plans and be a key contributor to commercial campaign activity team to achieve communication campaign KPIs and visitation goals that improves brand preference and supports achieving sales goals.\u00a0\n\nSTAFF BENEFITS\n\n\nAnnual Fixed Bonus, 5-Day Work Week, 17 days Public Holiday, Paid Leave (Paid Annual Leave, 14 weeks Maternity Leave, 5 days Paternity Leave, 1 week Marriage Leave), Employee Medical Coverage, Non-Contributory Retirement Plan, Staff Purchase Discount, Birthday Coupon, Referral Bonus, Excellent Career Path\n\nKindly WhatsApp 9438 6523 for any Queries.\n\nPersonal data collected will be kept and handled confidentially by authorized personnel for recruitment purposes only. It might also be disclosed to our subsidiaries, associates and agencies authorized to process the information for appointment. The Company will retain the applications of candidates not selected for a maximum period of 24 months after the selection process is finalized. Our Personal Information Collection Statement (PICS) is available at our career site and can be provided upon request by contacting our Human Resources Department.\u00a0Applicants not heard from us within six weeks may consider their applications filed for future reference.\n\nIssued by The Dairy Farm Company, Limited", "employment_types": ["Full Time", "Permanent"], "selling_points": ["Role is a key role in managing the public image", "The role is varied and the post-holder is expected", "Work under pressure, within tight deadlines"], "locations": ["Not Specified"], "categories": ["Design", "Graphics", "Marketing / Public Relations", "Marketing - Marketing Communication", "Others"], "post_time": "2022-01-10T03:58:30Z", "salary": {"currency": null, "max": null, "min": null, "period": "monthly", "term": null}, "salary_visible": false, "title_keywords": ["communications officer"], "responsibilities": ["ideas", "schedules", "budget", "quality", "communication", "plan", "plans", "costs", "control", "advertising", "measurement", "develop", "schedule", "visual", "kpis", "management", "cost", "review", "contents", "coordinate", "multiple projects"], "requirements": {"degrees": [], "majors": [], "languages": ["english", "chinese"], "language_level": [], "hard_skills": ["simple", "lean", "fun", "goal", "web analytics"], "soft_skills": ["efficient", "work independently", "independently", "passion for", "innovative", "positive attitude", "diverse", "communication", "motivated", "learning", "inspiring", "honest", "time management", "web analytics", "communicator", "creative"], "languages_combined": [{"language": "english", "language_level": []}, {"language": "chinese", "language_level": []}]}, "experience_required": {"duration": ["minimum 6 years"], "field": ["marketing", "media"]}}, {"job_id": "100003009033473", "location_code": "hk", "company": "STMicroelectronics Ltd", "job_title": "Industrial Customer Sr Manager/ Director", "description": "Diploma or\u00a0Degree holder, major in Marketing or in relevant areas\nTo assist a Sales team to prepare a PowerPoint, design brochure, sales materials, organize event and marketing activities, etc\nAs a fast growing market in Security / Home Automation with such knowledge and experience is an advantage\nGood communication skill & presentation skills\nOutgoing Personality, aggressive and well organize.\nIndependent, hard-working and can work under pressure\nWill provide training for the candidates with less experience\nGood Video and Photo editing skills\nCandidate with basic filming technique will be highly considered\n\nWe offer attractive salaries, fringe benefits and training with excellent opportunities for promotion and career development for the right candidates.\n\u00a0\nInterested parties please send your FULL\u00a0RESUME\u00a0(in MS Word Format) with availability, current and expected salary.\n\u00a0\n(Personal data collected will be used for recruitment purpose only; all the information shall be kept confidential)", "employment_types": ["Full Time", "Permanent"], "selling_points": ["10+ years experience in Marketing in Semi-con", "Analytical skills", "Stable working environment, 5 days work"], "locations": ["Tsim Sha Tsui"], "categories": ["Marketing / Public Relations", "Others"], "post_time": "2022-01-09T16:25:23Z", "salary": {"currency": null, "max": null, "min": null, "period": "monthly", "term": null}, "salary_visible": false, "title_keywords": ["manager", "director"], "responsibilities": ["provide training", "design", "communication", "sales team", "editing", "work under pressure"], "requirements": {"degrees": ["diploma", "degree holder"], "majors": ["marketing"], "languages": [], "language_level": [], "hard_skills": ["basic", "powerpoint"], "soft_skills": ["outgoing personality", "independent", "communication skill", "presentation skills", "hard-working", "work under pressure"], "languages_combined": []}, "experience_required": {"duration": [], "field": ["training", "security"]}}]