[{"job_id": "100003009053682", "location_code": "hk", "company": "Adsale Exhibition Services Ltd", "job_title": "Assistant Project Executive - Marketing Communications", "description": "(Ref : EXH-MCAPE-005-2022)\n\nResponsibilities:\n\nAssist in different kinds of projects from planning to execution, e.g. events, video/animation, live stream, design.\nProvide support to marketing campaigns through ATL & BTL channels.\nPrepare promotion materials, eDMs, printed & online advertisements as well as reports.\nWork closely with internal cross-functional teams and external parties to generate different marketing assets and ensure execution.\nAssist ad hoc project when required.\n\n\u00a0Requirements:\n\nDegree\u00a0holder with at least 2\u00a0years solid experience in Marketing, preferably in advertising agency/ exhibition industry, with digital marketing experience is an advantage.\nExcellent in written and spoken English and Chinese ( incl. Putonghua).\nMature, pro-active, self-motivated, well organized and detail-oriented.\nA team player with good communication skills\u00a0 and able to work under multitasking environment.\nBasic knowledge of producing eDM, artwork editing and promotion via Social Media are preferable.\nOccasional mainland China trips are required.\n\nWe offer attractive remuneration package including 5-day work, double pay, medical insurance, medical check-up, birthday leave, training and excellent development prospect to the right candidate.\u00a0Interested parties please send full resume with expected salary, availability and contact no. to\u00a0The Human Resources & Administration Manager\u00a0by fax :\u00a03586-0196\u00a0or click\u00a0APPLY NOW.\u00a0 \u201cPlease quote our job reference\u201d\u00a0\n\nCorporate Website : www.adsale.com.hk\n\n(All personal data will be used for recruitment purpose only)", "employment_types": ["Full Time"], "selling_points": ["5-day work week; double pay with bonus", "Assist different projects, planning to execution", "2 years solid experience in Marketing"], "locations": ["North Point"], "categories": ["Marketing / Public Relations", "Marketing - General / Support", "Marketing - Marketing Communication", "Public Relations - Event Management"], "post_time": "2022-01-17T07:20:30Z", "salary": {"currency": null, "max": null, "min": null, "period": "monthly", "term": null}, "salary_visible": false, "title_keywords": ["project executive", "assistant"], "responsibilities": ["provide support", "edms", "internal cross-functional teams", "ad hoc", "advertisements", "external parties", "design", "reports", "marketing campaigns", "animation", "planning"], "requirements": {"degrees": ["degree holder"], "majors": ["marketing", "digital marketing"], "languages": ["putonghua", "english", "chinese"], "language_level": ["excellent"], "hard_skills": ["basic"], "soft_skills": ["communication skills", "self-motivated", "well organized", "mature", "detail-oriented", "pro-active", "team player"], "languages_combined": [{"language": "putonghua", "language_level": []}, {"language": "english", "language_level": ["excellent"]}, {"language": "chinese", "language_level": ["excellent"]}]}, "experience_required": {"duration": ["at least 2 years"], "field": ["marketing", "digital marketing", "advertising agency"]}}, {"job_id": "100003009054073", "location_code": "hk", "company": "Rooftop Republic Co. Limited", "job_title": "Marketing & Events Executive", "description": "We\u2019re seeking a Marketing & Events Executive to join us! This role will give you the opportunity to be involved in urban farming,\u00a0grow the urban farming movement in the city, get first-hand experience at urban farm projects in Hong Kong, and also be part\u00a0of our journey of social entrepreneurship towards transforming our city into a greener and more edible space!\n\nResponsibilities:\n\nCreate awareness and promote our mission, vision and impact to clients, partners, stakeholders, interested parties and the general public through our digital platforms and social media channels\nDesign and implement engaging content, events and programs to drive buzz around urban farming, and attract and involve city dwellers to get started in growing their own food.\nWork with the Business Development team to develop and implement marketing strategies to drive the company\u2019s business growth.\u00a0\nLiaise with press & media on a regular basis to amplify the brand and our projects.\nClient relationship management for marketing and promotion related matters.\n\nRequirements For The Role:\n\nMin Bachelor\u2019s Degree in Marketing, Communication, Business or other relevant disciplines.\nProficient in MS Office Applications.\nProficiency in communications and design related software - Mailchimp and Canva.\nDigital native, and interest in latest trends, innovations and developments in the sector.\nHas an interest and concern for agriculture, environment, social issues, and growing your own veggies and herbs.\nHas strong verbal and communication skills.\nHas a creative spirit, and is willing to experiment with new ideas.\nStrong organisational skills and high attention to detail.\nIs a self-starter who has the ability to work independently.\nAble to work under tight deadlines and manage multiple projects at the same time - willing to get his/her hands dirty as necessary to move fast and get things done.\nHas a good command in Chinese (Cantonese) and English (speaking & writing).\nRight to work in Hong Kong. Rooftop Republic cannot provide a visa.\nCandidates with 1-2 years of working experience Marketing/PR/Communications will be preferred.\nYou may be required to work on weekends where necessary (off-days to be given in-lieu)\n\n\n\nApply now!\n\nInterested parties, please write to us with your resume, and please add a few sentences about why you are interested and how you feel you are a great fit!\n\nWe\u2019re an equal opportunity employer. All applicants will be considered for employment without attention to race, color, religion, sex, sexual orientation, gender identity, national origin, or disability status.\n\n(All information provided will be used for recruitment purposes only. Applicants who do not hear from us within 4 weeks may consider their applications unsuccessful.)\n\nFor more information, please click: www.rooftoprepublic.com\u00a0", "employment_types": ["Full Time", "Permanent"], "selling_points": [], "locations": ["Lai Chi Kok"], "categories": ["Marketing / Public Relations", "Marketing - Marketing Communication", "Public Relations - Event Management", "Digital Marketing"], "post_time": "2022-01-17T08:19:20Z", "salary": {"currency": null, "max": null, "min": null, "period": "monthly", "term": null}, "salary_visible": false, "title_keywords": ["executive"], "responsibilities": [], "requirements": {"degrees": [], "majors": [], "languages": [], "language_level": [], "hard_skills": [], "soft_skills": [], "languages_combined": []}, "experience_required": {"duration": [], "field": []}}, {"job_id": "100003009053278", "location_code": "hk", "company": "Seeds Financial Group", "job_title": "Assistant Sales and Event Manager/ HK$25,000-35,000 plus bonus", "description": "Qualification:\n\nUndergraduate/graduate\nExperience in managing events\nStrong communication skills - English, Cantonese and Mandarin\nProficient MS Office Skills - Excel, Powerpoint\n\nResponsibilitie\n\n\u00a0 \u00a0 \u00a0 \u00a0 \u00a0- Minimum 2 years solid experience in event coordination & production\n\u00a0 \u00a0 \u00a0 \u00a0 \u00a0- Project Management, project budgeting & coordinate the works of the designer & contractors, etc\n\u00a0 \u00a0 \u00a0 \u00a0 -\u00a0 Familiar with the usage of lighting, sound & AV systems is a must\n\u00a0 \u00a0 \u00a0 \u00a0 -\u00a0 Must be self-motivated, mature & able to work under pressure\n\u00a0 \u00a0 \u00a0 \u00a0 -\u00a0 Proactive, pleasant & able to work as part of a team\n\u00a0 \u00a0 \u00a0 \u00a0-\u00a0 Storong interpersonal & customer relations\n\u00a0 \u00a0 \u00a0 \u00a0-\u00a0 Coordinate the production of all events including prioritizing & scheduling work adhering to event\n\u00a0 \u00a0 \u00a0 \u00a0 \u00a0 budgets, organizing work flow, critical paths, event day logistics, load-in schedules & trouble-\u00a0 \u00a0 \u00a0 \u00a0 \u00a0 \u00a0 \u00a0 \u00a0 \u00a0 \u00a0shooting\n\u00a0 \u00a0 \u00a0 -\u00a0 assist the team in managing client's protfolio\n\u00a0 \u00a0 \u00a0 -\u00a0 attend production meetings, meet the requirements of our clients, & do on-site execution on\u00a0\n\u00a0 \u00a0 \u00a0 \u00a0 \u00a0the event date\n\u00a0 \u00a0 \u00a0-\u00a0 co-ordinat with in-house designers & technicians for arrangement of the event\n\u00a0 \u00a0 \u00a0-\u00a0 responsible for providing support services on general administration & other ad hoc tasks\u00a0\n\u00a0 \u00a0 \u00a0-\u00a0 team work player / travelling to china will be needed\n\nWe offer attractive package to the right candidate.\n\nInterested parties please send full resume with salary expected, to Fax No. 3426 9709\u00a0\u00a0for an interview.", "employment_types": ["Full Time"], "selling_points": ["Monthly Income up to HK$50,000 (including bonus)", "Fresh-graduates are welcomed", "Good team culture"], "locations": ["Causeway Bay"], "categories": ["Sales, CS & Business Devpt", "Customer Service - Supervisor / Officer", "Marketing / Public Relations", "Public Relations - Event Management", "Merchandising & Purchasing", "Procurement / Purchasing / Sourcing"], "post_time": "2022-01-17T06:39:09Z", "salary": {"currency": "HKD", "max": 34999, "min": 25000, "period": "monthly", "term": null}, "salary_visible": true, "title_keywords": ["sales", "assistant", "event manager"], "responsibilities": ["administration", "budgets", "schedules", "budgeting", "systems", "ad hoc tasks", "communication", "project management", "coordinate", "scheduling", "logistics", "coordination", "providing support", "work under pressure"], "requirements": {"degrees": [], "majors": [], "languages": ["cantonese", "english", "mandarin"], "language_level": [], "hard_skills": ["excel", "project management", "powerpoint", "ms office"], "soft_skills": ["communication skills", "self-motivated", "responsible", "mature", "pleasant", "project management", "coordination", "proactive", "interpersonal", "prioritizing", "work under pressure"], "languages_combined": [{"language": "cantonese", "language_level": []}, {"language": "english", "language_level": []}, {"language": "mandarin", "language_level": []}]}, "experience_required": {"duration": ["minimum 2 years"], "field": []}}, {"job_id": "100003009053246", "location_code": "hk", "company": "Tulipland Group Limited", "job_title": "Marketing event Assistant \u5e02\u5834\u6d3b\u52d5\u52a9\u7406", "description": "Job Duties:\n\nTo assist clients in increasing brand awareness and boosting sales performance through events, exhibitions and roadshows\nTo ensure the smooth operation of the events and roadshows by providing on-site support and engaging in sales activities\nTo take part in team development and management by recruiting new people, as well as providing support and coaching to the new people\n\n\nWhat We Offer:\n\nOverseas exchange opportunities (e.g. Malaysia, Korea, Singapore, Bali, Thailand and Taiwan, etc)\nFriendly and joyful working environment with strong team culture\nDiversified workshops and team activities\nSupport in career development and career growth\nHierarchical training from sales to leadership and management\n\nJob Requirements:\n\nFluent Cantonese is a must\nOutgoing, presentable, talkative and self-motivated\nExcellent communication and collaboration skills\nDiploma or above in any disciplines\nFresh graduates are welcome\n\nJoin Us NOW !!!", "employment_types": ["Full Time"], "selling_points": [], "locations": ["Tsim Sha Tsui"], "categories": ["Marketing / Public Relations", "Public Relations - Event Management"], "post_time": "2022-01-17T06:31:25Z", "salary": {"currency": "HKD", "max": 24999, "min": 17000, "period": "monthly", "term": null}, "salary_visible": true, "title_keywords": ["event assistant"], "responsibilities": ["sales performance", "management", "sales activities", "providing support"], "requirements": {"degrees": [], "majors": [], "languages": [], "language_level": [], "hard_skills": [], "soft_skills": [], "languages_combined": []}, "experience_required": {"duration": [], "field": []}}, {"job_id": "100003009054642", "location_code": "hk", "company": "Crowne Plaza Hong Kong Causeway Bay", "job_title": "Events Executive", "description": "Job Summary:\nAssistant Sales and Event Manager\u00a0 - \u00a0is responsible for providing administrative and coordination to support sales projects and event services team. It also involves day to day tasks of preparing departmental correspondence for sales activities and events servicing.\n\nTo enhance the financial services that our team provides to our clients, this role requires good customer service knowledge, exhibit a professional attitude and be a team player to achieve \u00a0sales and services goals.\n\nResponsibilities:\n\nDelivery quality customer services by providing accurate and sufficient information to clients as well as drafting concise and informative replies when necessary.\nProvide sales activities support, in organizing sales materials, preparing prospect proposal review, merchandise give-away items, \u00a0turnover preparation, answering sales or client enquiries, etc.\nMaintain extensive accounts and client\u2019s data for customer relationship management\nOffice administration and clerical support, including the arrangement of meetings, taking meeting minutes, office supply ordering / pickup and maintenance, management of team roster and leave records, courier deliveries, team cast related preparation and arrangement, organize filing systems and other related tasks.\nKeep up-to-date spending records, trace clients' billings, and prepare financial reports to clients.\nAssist in handling small scale corporate groups, social and internal event\nGenerate related reports for management and operation partners\nBasic Qualifications:\nBachelor degree is required, fresh-graduates are welcomed\nKnowledgeable in customer service industry\nAble to work independently\nLiterate in PC applications including MS Word, Excel, PowerPoint and Chinese typing\nGood communication skills with spoken and written English, Cantonese, and Putonghua", "employment_types": ["Full Time"], "selling_points": ["Handle customer requirements", "Bachelor\u2019s degree or Higher Diploma", "Minimum 2 years\u2019 relevant experience"], "locations": ["Causeway Bay"], "categories": ["Hospitality / F & B", "Hospitality / Hotel Services", "Marketing / Public Relations", "Public Relations - Event Management"], "post_time": "2022-01-17T10:23:21Z", "salary": {"currency": null, "max": null, "min": null, "period": "monthly", "term": null}, "salary_visible": false, "title_keywords": ["executive"], "responsibilities": ["sales activities", "management", "financial reports", "maintenance", "data", "office administration", "billings", "review", "quality", "clerical support", "systems", "customer services", "communication", "customer service", "maintain", "reports", "coordination"], "requirements": {"degrees": ["degree", "bachelor"], "majors": [], "languages": ["cantonese", "putonghua", "english", "chinese"], "language_level": ["good"], "hard_skills": ["small", "excel", "basic", "maintenance", "typing", "powerpoint", "pc applications", "ms word"], "soft_skills": ["communication skills", "work independently", "responsible", "customer service", "coordination", "team player", "accurate", "extensive"], "languages_combined": [{"language": "cantonese", "language_level": ["good"]}, {"language": "putonghua", "language_level": ["good"]}, {"language": "english", "language_level": ["good"]}, {"language": "chinese", "language_level": []}]}, "experience_required": {"duration": [], "field": []}}, {"job_id": "100003009055130", "location_code": "hk", "company": "Hong Kong Productivity Council", "job_title": "Officer, Website & Event Support (Digital Transformation Division)(Ref: DTD027/22, 5419/JDB/170122)", "description": "Job responsibilities:\n-Assist in the planning and management of different business activities\n-Evaluate and monitor the performance of business activities\n-Conduct goal-oriented market research under the guidance of the head of the marketing team\n-Production of promotions and materials (posters, leaflets, brochures)\n-Handling temporary projects as needed\n\nQualifications\n-University degree or are currently studying.\n-Active, proactive, independent and careful, full of enthusiasm for work\n-Good interpersonal communication skills and ability to work independently\n-Fluent in Mandarin and Cantonese", "employment_types": ["Permanent"], "selling_points": ["Provide support on digital solutions", "Bachelor Degree or above", "2 years' relevant experience in website management"], "locations": ["Not Specified"], "categories": ["Information Technology (IT)", "Support", "Marketing / Public Relations", "Public Relations - Event Management", "Others"], "post_time": "2022-01-18T01:53:17Z", "salary": {"currency": null, "max": null, "min": null, "period": "monthly", "term": null}, "salary_visible": false, "title_keywords": ["officer"], "responsibilities": ["guidance", "management", "leaflets", "market research", "communication", "monitor the performance", "business activities", "planning"], "requirements": {"degrees": ["degree"], "majors": [], "languages": ["cantonese", "mandarin"], "language_level": [], "hard_skills": ["goal"], "soft_skills": ["communication skills", "work independently", "careful", "independent", "proactive", "interpersonal"], "languages_combined": [{"language": "cantonese", "language_level": []}, {"language": "mandarin", "language_level": []}]}, "experience_required": {"duration": [], "field": []}}, {"job_id": "100003009046087", "location_code": "hk", "company": "The Hong Kong Institute Of Bankers", "job_title": "Officer - Projects and Events", "description": "Responsibilities:\n\nHandle customer requirements from event planning, during meetings to post-event follow-up;\nPrepare event documentation and thoroughly communicate to the hotel operations in a timely manner to ensure consistent and high level of service;\nConduct Sales activities and interact with guests to drive sales and solicit new business;\nReport and provide support to supervisor on any ad hoc issues.\n\nRequirements:\n\nBachelor\u2019s degree or Higher Diploma in Hotel or Catering Management or related field;\nMinimum 2 years\u2019 relevant experience preferably in hotels or catering;\nProficient in PC application;\nGood communication skills and negotiation skills;\nGood command of English and Chinese.\n\n\n\nIn return for your hard work, you can look forward to a highly competitive salary and benefits package \u2013 including healthcare support, pension scheme, hotel discounts worldwide and the chance to work with a great team of people. What\u2019s more, because your career will be as unique as you are, we\u2019ll give you all the tailored support you need to make a great start, be involved and grow.\n\nAnd because the Crowne Plaza Hotels & Resorts brand belongs to the IHG\u00ae family of brands, you\u2019ll also benefit from all of the opportunities that come from being part of a successful, global hospitality company with over 5,000 hotels in over 100 countries around the world.\n\nSo why not work somewhere that gives you the freedom to be yourself? Find out more about joining us today by visiting\u00a0www.ihgjobs.hk.\n\n\n\nWe are equal opportunity employer.\n\n\n\nAll applications will be treated in strict confidence and only be used for recruitment related purpose.\n\nFacebook: @\u6d32\u969b\u9152\u5e97\u96c6\u5718\u5de5\u4f5c\u6a5f\u6703\uff08\u9999\u6e2f\u53ca\u6fb3\u9580\u5340\uff09\nLinkedIn: @InterContinental Hotels Group\nWechat: @IHG\u6d32\u969b\u9152\u5e97\u96c6\u5718\u83c1\u82f1\u6703\nWeibo: @IHG\u6d32\u969b\u9152\u5e97\u96c6\u5718\u83c1\u82f1\u6703", "employment_types": ["Full Time", "Permanent"], "selling_points": ["Great development opportunity", "Membership Benefit and Events", "Banking & Finance Institution"], "locations": ["Sheung Wan"], "categories": ["Marketing / Public Relations", "Marketing - General / Support", "Public Relations - Event Management", "Public Relations - General / Support"], "post_time": "2022-01-16T21:50:15Z", "salary": {"currency": null, "max": null, "min": null, "period": "monthly", "term": null}, "salary_visible": false, "title_keywords": ["officer"], "responsibilities": ["sales activities", "provide support", "ad hoc", "operations", "a timely manner", "documentation", "drive sales", "report", "planning"], "requirements": {"degrees": ["diploma", "degree", "bachelor"], "majors": ["hotel"], "languages": ["english", "chinese"], "language_level": ["good command"], "hard_skills": ["scheme", "wechat", "make", "pc", "facebook"], "soft_skills": ["communication skills", "negotiation skills", "confidence", "unique"], "languages_combined": [{"language": "english", "language_level": ["good command"]}, {"language": "chinese", "language_level": ["good command"]}]}, "experience_required": {"duration": ["minimum 2 years"], "field": ["hotels", "relevant experience"]}}, {"job_id": "100003009052051", "location_code": "hk", "company": "Whampoa Garden Management Limited", "job_title": "PR & PROMOTIONS OFFICER / ASSISTANT PR & PROMOTIONS OFFICER [Ref: WGML-PRO/APRO]", "description": "Job Duties:\n\nAssist in assessment of the funding applications and perform initial check of final reports from the grantees and prepare relevant documents required for funding disbursement\nSupport project work and on-site checking of funded projects, liaise with applicants and arrange meetings\n\nJob Requirements:\n\nDegree holder in Business, Engineering, Science subject or related discipline\n2 years\u2019 full time administrative / customer service experience is preferred\nGood command of English and Cantonese\n\n\nApplicants are welcome to submit application quoting the Ref. No. with your availability and expected salary by clicking \"Apply Now\". Recruitment will continue until the openings are filled.\n\nPersonal data collected will be used for recruitment purpose only. Candidates not invited for interviews within 6 weeks may consider their applications unsuccessful and the applications will be disposed by HKPC within 12 months.", "employment_types": ["Full Time", "Permanent"], "selling_points": ["Degree holder", "Minimum 4 years' experience", "To plan and implement advertising strategy"], "locations": ["Hung Hom"], "categories": ["Marketing / Public Relations", "Marketing - Marketing Communication", "Public Relations - Event Management", "Property / Real Estate", "Others"], "post_time": "2022-01-17T07:22:21Z", "salary": {"currency": null, "max": null, "min": null, "period": null, "term": null}, "salary_visible": false, "title_keywords": ["assistant", "pr & promotions officer"], "responsibilities": ["liaise with", "arrange meetings", "reports", "checking"], "requirements": {"degrees": ["degree holder"], "majors": ["science", "business", "engineering"], "languages": ["cantonese", "english"], "language_level": ["good command"], "hard_skills": ["no"], "soft_skills": ["customer service"], "languages_combined": [{"language": "cantonese", "language_level": ["good command"]}, {"language": "english", "language_level": ["good command"]}]}, "experience_required": {"duration": ["2 years"], "field": ["administrative", "customer service"]}}, {"job_id": "100003009056193", "location_code": "hk", "company": "Code International Limited", "job_title": "Event & Roadshow Marketing Trainee", "description": "Job Duties:\n\nTo assist clients in increasing brand awareness and boosting sales performance through events, exhibitions and roadshows\nTo ensure the smooth operation of the events and roadshows by providing on-site support and engaging in sales activities\nTo take part in team development and management by recruiting new people, as well as providing support and coaching to the new people\n\n\nWhat We Offer:\n\nOverseas exchange opportunities (e.g. Malaysia, Korea, Singapore, Bali, Thailand and Taiwan, etc)\nFriendly and joyful working environment with strong team culture\nDiversified workshops and team activities\nSupport in career development and career growth\nHierarchical training from sales to leadership and management\n\nJob Requirements:\n\nFluent Cantonese is a must\nOutgoing, presentable, talkative and self-motivated\nExcellent communication and collaboration skills\nDiploma or above in any disciplines\nFresh graduates are welcome\n\nJoin Us NOW !!!", "employment_types": ["Full Time"], "selling_points": ["Event & Roadshow Marketing", "Indoor & Outdoor Events", "Friendly and joyful working environment"], "locations": ["Wan Chai Area"], "categories": ["Marketing / Public Relations", "Marketing - Direct Marketing", "Public Relations - Event Management", "Sales, CS & Business Devpt", "Direct Sales"], "post_time": "2022-01-18T03:31:08Z", "salary": {"currency": null, "max": null, "min": null, "period": "monthly", "term": null}, "salary_visible": false, "title_keywords": ["trainee"], "responsibilities": ["sales performance", "management", "sales activities", "providing support"], "requirements": {"degrees": [], "majors": [], "languages": [], "language_level": [], "hard_skills": [], "soft_skills": [], "languages_combined": []}, "experience_required": {"duration": [], "field": []}}, {"job_id": "100003009049778", "location_code": "hk", "company": "Bethel Bible Seminary", "job_title": "\u884c\u653f\u53ca\u6d3b\u52d5\u52a9\u7406 Administration and Event Assistant", "description": "Responsibilities:\n\nResponsible for all online activities including user acquisition, conversion and retention to deliver continuous optimization and growth\nCreate, manage, and analyze Search Engine Marketing and social media across multiple platforms to achieve user acquisition and conversion goals\nCreation & delivery of all paid acquisition campaigns on social media platforms\nTake a data-driven approach to optimism marketing performance\nAnalyze market landscape and consumer insights to identify business opportunity\nHandle and present the performance and ROI of the above digital campaigns\nLiaise with internal and external parties to provide marketing administrative supports\nAny ad-hoc duties as assigned\n\nRequirements:\n\nDegree holder or above in Marketing, Digital Marketing, New Media Communication, Journalism or related disciplines\nMinimum 3 years marketing experience (less experience will be considered for Executive role)\nHands-on experience in Facebook Ad Manager, SEO, SEM, Google Analytics, Adwords planning and content development is a must\nFamiliar with automated email marketing tools preferable\nPossess Google Ads Search Certification, and Ads Display Certification preferable\nProficiency in design software such as Photoshop, AI is a must, video editing is a plus\nAble to handle multi-tasks with strong problem-solving skills with a can-do attitude\nSee themselves as project lead with strong ability of execution\nExcellent communication and interpersonal skills\nExcellent command of Chinese and English writing\n\nInterested parties are invited to send their applications with full resume stating availability date, present and expected salary to us.\n\nPersonal data provided by job applicants will be used strictly in accordance with our personal data policy and for recruitment purposes only.", "employment_types": ["Full Time", "Permanent", "Contract"], "selling_points": [], "locations": ["Kowloon City"], "categories": ["Admin & HR", "Clerical / Admin Staff", "Marketing / Public Relations", "Public Relations - Event Management", "Media & Advertising", "Print Media"], "post_time": "2022-01-14T09:14:33Z", "salary": {"currency": null, "max": null, "min": null, "period": "monthly", "term": null}, "salary_visible": false, "title_keywords": ["event assistant"], "responsibilities": ["social media", "consumer insights", "data", "social media platforms", "internal and external parties", "digital campaigns", "ad-hoc duties", "liaise with"], "requirements": {"degrees": ["degree holder"], "majors": ["journalism", "related disciplines", "marketing", "digital marketing"], "languages": ["english", "chinese"], "language_level": ["excellent"], "hard_skills": ["google analytics", "plus", "seo", "ai", "problem-solving skills", "adwords", "video editing", "sem", "facebook", "photoshop"], "soft_skills": ["multi-tasks", "can-do attitude", "communication", "hands-on", "communication and interpersonal skills", "problem-solving skills"], "languages_combined": [{"language": "english", "language_level": ["excellent"]}, {"language": "chinese", "language_level": ["excellent"]}]}, "experience_required": {"duration": ["minimum 3 years"], "field": ["marketing", "content development", "planning"]}}, {"job_id": "100003009050916", "location_code": "hk", "company": "World Vision Hong Kong", "job_title": "Temporary Event Officer (9 months)", "description": "Responsibilities:\n\nDirect report to Marketing Manager\nAssist to achieve brand targets and present the channel strategies to the Sales Team\nReview depletion for replenishment when needed\nAssist the team in A&P budget and review on regular basis\nAssist to prepare and execute promotion plans for specific channels\nExecute marketing programs including wine tastings, wine dinners, fairs, and exhibitions.\nCoordinate event management including logistic, and production of marketing collaterals\nExecute and follow up the agreed A&P activities including print, magazine, online, electronic media and direct mail\nExplore distribution development programs related to trade and corporate customers\n\n\u00a0Requirements:\n\nUniversity graduate, preferably in marketing or communications field\nA minimum of 3 years\u2019 experience in brand marketing or marketing communications of related industry\nAble to work in a fast-paced, multi-cultural environment\nDetail-minded, presentable with good judgment\nAble to work in a team but also independently\nStrong interest and passion in wine is a must. Certificate holder of WSET or related is an advantage\nPro-active, self-motivated, and positive with creative thinking\nGood command of spoken and written English, Cantonese, and Mandarin\nImmediately available preferred\nNext by Wong Chuk Hang MTR station", "employment_types": ["Full Time", "Temporary"], "selling_points": [], "locations": ["Mong Kok"], "categories": ["Marketing / Public Relations", "Marketing - Brand / Product Management", "Public Relations - Event Management", "Public Relations - General / Support"], "post_time": "2022-01-14T11:46:25Z", "salary": {"currency": null, "max": null, "min": null, "period": "monthly", "term": null}, "salary_visible": false, "title_keywords": ["officer"], "responsibilities": ["management", "development programs", "review", "budget", "replenishment", "marketing collaterals", "coordinate", "sales team", "plans", "report"], "requirements": {"degrees": ["certificate", "university graduate"], "majors": ["marketing", "communications"], "languages": ["cantonese", "english", "mandarin"], "language_level": ["good command"], "hard_skills": [], "soft_skills": ["detail-minded", "self-motivated", "independently", "passion in", "presentable", "pro-active", "creative", "positive"], "languages_combined": [{"language": "cantonese", "language_level": ["good command"]}, {"language": "english", "language_level": ["good command"]}, {"language": "mandarin", "language_level": ["good command"]}]}, "experience_required": {"duration": ["minimum of 3 years"], "field": ["marketing communications", "marketing", "brand", "related"]}}, {"job_id": "100003009051167", "location_code": "hk", "company": "International Conference Consultants Limited", "job_title": "Event Assistant / Project Assistant", "description": "Are you tired of working overtime?\n\nAre you seeking for\u00a0new opportunities and excitement in workplace?\n\nIf you pursue work-life balance, apply our job now !!!\n\n\n\nOur work covers:\u00a0\n\n- Indoor and Outdoor Events\n\n- Sales Management\n\n- Strategic Planning\n\n- Team Management\u00a0\n\nWhat's special in our workplace:\n\n- Treat our office as your playground\n\n- A group of young and energetic colleagues\n\n- Different workshops, company activities and gamified working atmosphere\n\n- On-the-job training, from sales to management\n\nYou must be:\n\n- Fluent in Cantonese\u00a0\n\n- A good team player\n\n- Outgoing, talkative and creative\n\n-\u00a0Fresh graduates are welcome\n\n\nBring your energy and passion to our workplace NOW !!!", "employment_types": ["Full Time", "Permanent"], "selling_points": [], "locations": ["North Point"], "categories": ["Marketing / Public Relations", "Marketing - General / Support", "Marketing - Marketing Communication", "Public Relations - Event Management"], "post_time": "2022-01-15T03:48:56Z", "salary": {"currency": null, "max": null, "min": null, "period": "monthly", "term": null}, "salary_visible": false, "title_keywords": ["event assistant", "project assistant"], "responsibilities": ["sales management", "strategic planning", "management"], "requirements": {"degrees": [], "majors": [], "languages": ["cantonese"], "language_level": ["fluent"], "hard_skills": ["workshops"], "soft_skills": ["outgoing", "good team player", "energetic", "creative"], "languages_combined": [{"language": "cantonese", "language_level": ["fluent"]}]}, "experience_required": {"duration": [], "field": []}}, {"job_id": "100003009054361", "location_code": "hk", "company": "eCargo Enterprise Limited", "job_title": "E-commerce Operations Assistant Manager / Manager", "description": "\u9999\u6e2f\u4e2d\u5b78\u6587\u6191\u8003\u8a66\u6216\u9999\u6e2f\u4e2d\u5b78\u6703\u8003\u4e94\u79d1\u8003\u7372\u7b2c2\u7d1a\uff0f\u9054\u6a19\u6216\u4ee5\u4e0a\uff08\u5305\u62ec\u4e2d\u3001\u82f1\u6587\u79d1(\u8ab2\u7a0b\u4e59)\uff09\n\u8ca0\u8cac\u7c4c\u8fa6\u53ca\u63a8\u884c\u9577\u8005\u4e2d\u5fc3\u6d3b\u52d5\u53ca\u5e36\u9818\u5c0f\u7d44\n\u9700\u5916\u52e4\u5de5\u4f5c\uff0c\u4f8b\u5982\u8857\u7ad9\u3001\u63a2\u8a2a\u9577\u8005\n\u5177\u9577\u8005\u670d\u52d9\u7d93\u9a57\u6216\u7fa9\u5de5\u7d93\u9a57\u8005\u512a\u5148\u8003\u616e\n\n\u6709\u610f\u8005\u8acb\u65bc\u4e8c\u96f6\u4e8c\u4e8c\u5e74\u4e8c\u6708\u4e94\u65e5\u524d\u89aa\u7e55\u5c65\u6b77\u53ca\u671f\u671b\u5f85\u9047\uff08\u8acb\u65bc\u4fe1\u5c01\u9762\u53ca\u4fe1\u5167\u8a3b\u660e\u7533\u8acb\u8077\u4f4d\u7de8\u865f\uff09\u5bc4\u65b0\u754c\u5c07\u8ecd\u6fb3\u9748\u5be6\u8def\u4e03\u865f\u57fa\u7763\u6559\u9748\u5be6\u5354\u6703\u4eba\u529b\u8cc7\u6e90\u90e8\u6536\uff0c\u6216\u96fb\u90f5\u81f3Apply Now\uff0c\u6216\u767c\u9001\u81f3Whatsapp\u865f\u78bc6507 8148\uff08\u6a19\u984c\u8acb\u8a3b\u660e\u8077\u4f4d\u7de8\u865f\uff09\u3002\u5982\u4e00\u500b\u6708\u5167\u672a\u7372\u901a\u77e5\u7d04\u898b\uff0c\u5247\u4f5c\u843d\u9078\u8ad6\u3002\n\u67e5\u8a62\u71b1\u7dda\uff1a2703 3227 (\u96fb\u8a71)\uff1b6507 8148 (Whatsapp)\u3002\n\u6709\u95dc\u672c\u6703\u8a73\u60c5\uff0c\u8acb\u700f\u89bd\u7db2\u9801http://www.hohcs.org.hk\n\n(\u53ef\u80fd\u7372\u8058\u4eba\u58eb\uff08\u5982\u5f9e\u4e8b\u8207\u5152\u7ae5\u6216\u7cbe\u795e\u4e0a\u7121\u884c\u70ba\u80fd\u529b\u4eba\u58eb\u6709\u95dc\u5de5\u4f5c\u8077\u4f4d\uff09\u9808\u65bc\u5165\u8077\u524d\u9032\u884c\uff0f\u63d0\u4ea4\u6027\u7f6a\u884c\u5b9a\u7f6a\u7d00\u9304\u67e5\u6838\u3002\u7533\u8acb\u4eba\u6240\u63d0\u4f9b\u7684\u8cc7\u6599\u5c07\u4e88\u4fdd\u5bc6\u53ca\u4f5c\u62db\u8058\u6709\u95dc\u8077\u4f4d\u7528\u9014)\n\n\u672a\u7d93\u672c\u5354\u6703\u66f8\u9762\u540c\u610f\uff0c\u4ee5\u4e0a\u62db\u8058\u5ee3\u544a\u5168\u90e8\u6216\u90e8\u5206\u5167\u5bb9\u5747\u4e0d\u5f97\u8907\u88fd\u81f3\u5176\u4ed6\u62db\u8058\u7db2\u7ad9\u3002", "employment_types": ["Full Time", "Permanent"], "selling_points": ["Support sales and marketing when necessary", "With wine knowledge will be a plus", "Five-day Work Week, Double Pay, Birthday Leave"], "locations": ["Kwai Tsing Area"], "categories": ["Marketing / Public Relations", "Public Relations - Event Management", "Digital Marketing", "E-commerce", "Marketing - Brand / Product Management"], "post_time": "2022-01-17T09:16:31Z", "salary": {"currency": null, "max": null, "min": null, "period": "monthly", "term": null}, "salary_visible": false, "title_keywords": ["manager", "operations assistant"], "responsibilities": [], "requirements": {"degrees": [], "majors": [], "languages": [], "language_level": [], "hard_skills": ["whatsapp"], "soft_skills": [], "languages_combined": []}, "experience_required": {"duration": [], "field": []}}, {"job_id": "100003009051689", "location_code": "hk", "company": "The University of Manchester Worldwide Limited", "job_title": "Operations Administrative Assistant", "description": "Responsibilities:\n\nAssist to strengthen and maintain tenant relationship by providing quality tenant services and support on sales action plan, service standards and operation efficiency\nAssist the Manager to organize tour activities, marketing campaign, digital marketing and PR events\nLiaise with both stakeholders and agencies to create all-rounded marketing collaterals\nImplement year-round retailing marketing campaign\nSolicit supports from potential partners and stakeholders for joint promotion\nHandle telephone enquiries and requests from tenants in a professional manner and take appropriate / necessary actions\nPrepare related reports and conduct relevant analysis\nCoordinate with different business units, tenants and external parties for smooth execution and high level of quality on all marketing activities\n\nRequirements:\n\nDegree holder in Marketing, Journalism, Business Administration or related disciplines\nMinimum 4 years' solid experience in event management / property leasing and marketing, preferably with property developers or event agencies\nCreative, responsible, dynamic, multi-tasking and good marketing sense\nAble to work independently to meet multiple project deadlines\nGood interpersonal, communication and presentation skills\nFluent in spoken and written English and Chinese\nWilling to work on weekends and public holidays when necessary\nInterested parties please send full resume stating current and expected salary, date available to:\u00a0Human Resources Manager, Chinachem Group, 35-38 Floor, Tower 2, Nina Tower, 8 Yeung Uk Road, Tsuen Wan, N.T.\u00a0or click \"Apply Now\" to submit your application.\n\nApplicants who fail to hear from the Chinachem Group within 8 weeks from the date of submitting applications should consider their applications unsuccessful. The personal data of unsuccessful candidates collected for this recruitment exercise will be kept for 2 years from its completion and thereafter destroyed.\n\nAll applications will be treated in the strictest confidence. Personal data provided will be used for recruitment purpose only and in accordance with the Code of Practice on Human Resource Management.", "employment_types": ["Full Time", "Contract"], "selling_points": ["H Dip or above, 3-5 yrs wk exp, Gd Eng, IT skills", "Mature, can-do, multi-task, creative, outgoing", "Int'l exposure, training, immediate, salary expect"], "locations": ["Causeway Bay"], "categories": ["Admin & HR", "Clerical / Admin Staff", "Education", "Others", "Marketing / Public Relations", "Public Relations - Event Management"], "post_time": "2022-01-16T21:50:48Z", "salary": {"currency": null, "max": null, "min": null, "period": "monthly", "term": null}, "salary_visible": false, "title_keywords": ["administrative assistant", "operations"], "responsibilities": ["analysis", "marketing collaterals", "quality", "professional manner", "coordinate with", "external parties", "service standards", "maintain", "digital marketing", "reports", "plan", "liaise with"], "requirements": {"degrees": ["degree holder"], "majors": ["journalism", "related disciplines", "marketing", "business administration"], "languages": ["english", "chinese"], "language_level": ["fluent"], "hard_skills": ["dynamic"], "soft_skills": ["work independently", "marketing sense", "responsible", "communication", "multi-tasking", "dynamic", "presentation skills", "creative", "interpersonal"], "languages_combined": [{"language": "english", "language_level": ["fluent"]}, {"language": "chinese", "language_level": ["fluent"]}]}, "experience_required": {"duration": ["minimum 4 years"], "field": ["property developers", "management", "marketing"]}}, {"job_id": "100003009054751", "location_code": "hk", "company": "Starlite Holdings Limited", "job_title": "PR and Marketing Manager", "description": "[REF: SHRM(P)1/SAFRM(CMS)/JOBS]\n\nLocation: Sheung Wan\n\nRoles and responsibilities:\n\nProvide executive support in formulation of strategy to strengthen/uplift corporate donations and data mining analysis to identify prospective donors as well as competitive edge, better options and market trends in fund-raising activities;\nenhance data warehouse with collection and collation of updated data for planning and development purposes as well as carry out segmentation of donor groups to identify the best tactics for expansion of opportunity and facilitate collaboration with key stakeholders and setting of business priorities;\ndeliver fund-raising promotion activities and strengthen donor communication platform;\nstrategically manage corporate relationship with donors to achieve high satisfaction and retention results;\nidentify prospective donors and opportunities to bring in new source of donation;\nmonitor and initiate system enhancement of the relevant database and draw up users\u2019 specifications based on business needs as required; and\nplan and execute fund-raising activities, and review the related process to meet the corporate objectives.\n\nThe ideal candidate should possess:\n\na recognized degree in business administration, marketing or related subjects, OR other qualifications with substantial exposure to marketing and customer analytics;\nat least Grade D in English Language (Syllabus B) and Chinese Language in the HKCEE or equivalent;\nat least 4 years of execution experience preferably having performed marketing roles in sizable business operations and possession of strong business acumen;\npreferably managerial experience in marketing gained in B2B businesses or fast-moving consumer goods industry. Connection with corporate of expatriate community is an advantage;\nclear understanding of corporate needs/orientation in the charity field with excellent analytical, problem solving and project management skills;\nproficiency in PC applications and sound knowledge in Microsoft Office, particular in Excel;\nproficiency in written and oral English and Chinese, preferably including Putonghua; and\ngood interpersonal and communication skills, flexible mind, independent with strong drive and initiative well organized, details oriented and result driven with strong sense of responsibility.\n\n(Please specify in the application form the HKCEE results and relevant qualifications/working experience you have attained in detail.)\n\nCompensation & employment terms:\n\nThe successful candidate will be appointed on contract terms with a remuneration package which will be commensurate with his/her background and experience.\u00a0 Apart from contributions to the MPF Scheme, other benefits include paid annual leave, medical services, a dental scheme and training sponsorships.\u00a0 The incumbent will normally work under a 5-day week schedule subject to operational needs and exigencies of the service.\n\nApplication:\n\nPlease send your resume and a completed application form <F601(n)> with indication of your current and expected salaries to the Head of Human Resources Division, Tung Wah Group of Hospitals at 4/F., Wong Fung Ling Memorial Building, 12 Po Yan Street, Hong Kong by\u00a024 January\u00a02022.\u00a0\u00a0Application forms are obtainable in person or can be downloaded from http://www.tungwah.org.hk.\u00a0\u00a0The reference code should be marked both in the letter and on the envelope.\u00a0 Underpaid mail items will not be accepted by Tung Wah.\u00a0 For proper delivery of your mail items, please ensure your mail items bear sufficient postage with return address before posting.\u00a0\u00a0Personal data provided by applicants will be used strictly for recruitment purpose only and in accordance with the Tung Wah's personal data policy.\u00a0 Applicants not invited to attend an interview by\u00a030 April 2022 may assume that their applications are unsuccessful.\n\nWE ARE AN EQUAL OPPORTUNITIES EMPLOYER", "employment_types": ["Full Time", "Permanent"], "selling_points": ["Five-day work week", "Medical insurance", "Immediately available is highly preferred"], "locations": ["Wong Tai Sin Area"], "categories": ["Marketing / Public Relations", "Marketing - General / Support", "Public Relations - Event Management", "Public Relations - General / Support"], "post_time": "2022-01-17T10:53:35Z", "salary": {"currency": null, "max": null, "min": null, "period": "monthly", "term": null}, "salary_visible": false, "title_keywords": ["marketing manager"], "responsibilities": ["administration", "data", "operations", "analysis", "review", "monitor", "executive support", "communication", "project management", "specifications", "database", "plan", "data mining", "planning"], "requirements": {"degrees": ["degree"], "majors": ["marketing", "business administration"], "languages": ["putonghua", "english", "chinese"], "language_level": ["proficiency"], "hard_skills": ["excel", "microsoft office", "data warehouse", "analysis", "charity", "pc applications", "problem solving", "project management", "data mining", "wan", "acumen"], "soft_skills": ["flexible", "communication skills", "oral", "independent", "sense of responsibility", "project management skills", "well organized", "driven", "communication", "problem solving", "clear", "business acumen", "initiative", "interpersonal", "ideal"], "languages_combined": [{"language": "putonghua", "language_level": []}, {"language": "english", "language_level": ["proficiency"]}, {"language": "chinese", "language_level": ["proficiency"]}]}, "experience_required": {"duration": ["at least 4 years"], "field": ["business", "managerial", "fast-moving consumer goods", "marketing"]}}, {"job_id": "100003009050775", "location_code": "hk", "company": "The College of Surgeons of Hong Kong Limited", "job_title": "Executive Assistant (Event Management)", "description": "Responsibilities:\n\nResponsible for planning, organizing and implementing promotional & marketing campaigns, art and cultural exhibitions, for the mall as well as the tenants\nHandle the preparation works and provide event logistics support for the whole marketing and promotion planning process\nPerform other duties as assigned\n\nRequirements:\n\nDegree holder in Marketing or related disciplines\nAt least 1-2 years\u2019 relevant working experience, preferably in event management\n\nExcellent interpersonal and communication skills in both written and spoken English & Chinese\nGood organizational skills, independent with minimum supervision, ability to work under pressure and working on festive holidays are required\nShopping mall promotion, O2O marketing and good knowledge in computer are essential\n\nWe offer competitive salary package that will be commensurate with experience and qualifications. Interested parties are invited to send full resume stating contact telephone number, date available, present and expected salary to our recruitment email address.\n\n(Personal data provided will be used strictly in accordance with the Company\u2019s personal data policy which is available upon request.)", "employment_types": ["Full Time", "Contract"], "selling_points": [], "locations": ["Aberdeen"], "categories": ["Admin & HR", "Others", "Marketing / Public Relations", "Public Relations - Event Management"], "post_time": "2022-01-14T11:21:29Z", "salary": {"currency": null, "max": null, "min": null, "period": "monthly", "term": null}, "salary_visible": false, "title_keywords": ["executive assistant"], "responsibilities": ["perform other duties", "planning process", "logistics", "marketing campaigns", "planning"], "requirements": {"degrees": ["degree holder"], "majors": ["related disciplines", "marketing"], "languages": ["english", "chinese"], "language_level": ["excellent"], "hard_skills": [], "soft_skills": ["communication skills", "organizational skills", "independent", "interpersonal", "work under pressure"], "languages_combined": [{"language": "english", "language_level": ["excellent"]}, {"language": "chinese", "language_level": ["excellent"]}]}, "experience_required": {"duration": ["at least 1-2 years"], "field": ["management", "relevant working experience"]}}, {"job_id": "100003009054437", "location_code": "hk", "company": "Hong Kong Cyberport Management Co Ltd", "job_title": "Manager - Ecosystem Programme (Ref# MEP220117J)", "description": "Responsibilities:\nAssist Manager to drive change in the role of business partner who serves as a consultant on human resources issues and align business objectives with employees and management in the business units\nInvolve in different system enhancement to enhance staff experience and provide better environment for daily operations\nPlan, develop and coordinate different company campaigns and events to engage employees including but not limited to CSR programme, employee relation activities, town hall meeting, annual dinner and etc.\nCoordinate and participate in different recruitment activities as well as to engage new joiners via on-boarding process including pre-employment day, staff orientation programme, terminal tour, networking and etc. to build up cohesive & collaborating working culture\nFacilitate various HR related projects in the areas of employee relation, talent acquisition, that support and meet business strategy\nHandle ad hoc project as assigned by immediate supervisor\nCandidates with less experience will be considered as People Officer\nRequirements:\nDegree holder in Human Resources Management or Business Administration or\u00a0 other business related discipline\nMinimum 5 years working experience in all-rounded personnel experience at sizable companies\nPassion to work in a fast pacing and dynamic environment\nBe positive, proactive, energetic, creative and have cheerful manner\nExcellent communication and interpersonal skills and with good influencing skills\nChange agent, customer focused, detail minded, execute with excellence and result-oriented\nWell-conversant in Employment Ordinance and other related legislation\nExcellent in written and spoken English and Chinese\nProficient in MS Office applications, knowledge in video editing and social media tools is an advantage\n\nTo apply, you may simply click the \"Apply Online\" or\u00a0email your confidential resume with date of availability, current and expected salary to recruitment @cpsl.com.hk.\u00a0Applicants not contacted within 6 weeks may consider their applications unsuccessful.\n\nCathay Pacific Services Limited is an Equal Opportunities Employer. Personal data provided by job applicants will be used strictly in accordance with our personal data policy and for recruitment purposes only. Candidates not notified within six weeks may consider their application unsuccessful. All related information will be kept in our file for up to 24 months.\n\n", "employment_types": ["Full Time", "Permanent", "Contract"], "selling_points": ["Collaboration with ecosystem partners", "Manage partner events from ideation to execution", "Wide spectrum of event management"], "locations": ["Pok Fu Lam"], "categories": ["Marketing / Public Relations", "Public Relations - Event Management", "Public Relations - General / Support", "Others"], "post_time": "2022-01-17T09:33:33Z", "salary": {"currency": null, "max": null, "min": null, "period": "monthly", "term": null}, "salary_visible": false, "title_keywords": ["manager"], "responsibilities": ["management", "ad hoc", "pre-employment", "hr", "develop", "coordinate", "daily operations", "recruitment", "plan"], "requirements": {"degrees": ["degree holder"], "majors": ["business", "business administration"], "languages": ["english", "chinese"], "language_level": ["excellent"], "hard_skills": ["video editing", "sizable companies", "dynamic", "ms office"], "soft_skills": ["dynamic environment", "proactive", "cheerful", "creative", "focused", "communication and interpersonal skills", "energetic", "result-oriented", "positive"], "languages_combined": [{"language": "english", "language_level": ["excellent"]}, {"language": "chinese", "language_level": ["excellent"]}]}, "experience_required": {"duration": ["minimum 5 years"], "field": []}}, {"job_id": "100003009049485", "location_code": "hk", "company": "The Hong Kong Institute Of Bankers", "job_title": "Project Manager \u2013 Event Marketing & Anniversary Celebration", "description": "\u8077\u4f4d\u540d\u7a31\uff1a\u884c\u653f\u53ca\u6d3b\u52d5\u52a9\u7406\n\n\n\u4f2f\u7279\u5229\u795e\u5b78\u9662\u8aa0\u8058\u300c\u884c\u653f\u53ca\u6d3b\u52d5\u52a9\u7406\u300d\u4e00\u540d\n\n\u8077\u8cac\uff1a\n1. \u8ddf\u9032\u5b78\u9662\u8ab2\u7a0b\u53ca\u6d3b\u52d5\u7684\u5ba3\u50b3\u3001\u5831\u540d\u5de5\u4f5c\uff0c\u5305\u62ec\u8655\u7406\u8ab2\u7a0b\u53ca\u6d3b\u52d5\u8cec\u76ee\u53ca\u8cc7\u6599\u8f38\u5165\n2. \u8ab2\u5802\u5f71\u97f3\u652f\u63f4\u3001\u7db2\u9801\u66f4\u65b0\u3001\u6587\u66f8\u5de5\u4f5c\u3001\u6d3b\u52d5\u6703\u8b70\u8a18\u9304\u3001\u8ddf\u9032\u5370\u5237\u5de5\u4f5c\n3. \u5b78\u9662\u6d3b\u52d5\u806f\u7d61\u53ca\u7269\u6d41\u5b89\u6392\uff1a\u5982\u7562\u696d\u5178\u79ae\u3001\u53ec\u547d\u65e5\u3001\u958b\u653e\u65e5\u3001\u8056\u8a95\u6d3b\u52d5\u3001\u6176\u5178\u7b49\u7b49(\u6709\u6a5f\u6703\u5728\u661f\u671f\u5929\u6216\u516c\u773e\u5047\u671f\u8209\u884c)\n4. \u5354\u52a9\u5927\u5c0f\u578b\u805a\u6703 5. \u6216\u5176\u4ed6\u4e00\u5207\u4e0a\u7d1a\u6307\u6d3e\u4e4b\u5b78\u9662\u5de5\u4f5c\uff0c\u5305\u62ec\u652f\u63f4\u5176\u4ed6\u90e8\u9580\u3002\n\n\u8981\u6c42\uff1a\n1. \u4e2d\u5b78\u7562\u696d\u6216\u4ee5\u4e0a\u5b78\u6b77\uff0c\u5982\u6301\u6709\u8207\u5927\u5c08\u5b78\u6b77\u5c07\u7372\u512a\u5148\u8003\u616e\n2. \u64cd\u6d41\u5229\u5ee3\u6771\u8a71\u3001\u4e2d\u82f1\u6587\u80fd\u529b\u826f\u597d\n3. \u5177\u826f\u597d\u61c9\u7528\u8cc7\u8a0a\u79d1\u6280\u80fd\u529b\uff0c\u719f\u8b58\u96fb\u8166\u6587\u66f8\u8655\u7406\u3001\u53ca\u5404\u8fa6\u516c\u5ba4\u8edf\u4ef6\u61c9\u7528\uff0c\u4e2d\u82f1\u6587\u6253\u5b57\uff0c\u61c2Windows, MS Office (Excel, Word), Google Suite, Internet \u7b49\n4. \u9858\u610f\u76e1\u5fc3\u4e8b\u5949\uff0c\u5728\u5718\u968a\u4e2d\u8207\u4eba\u5408\u4f5c\n5. \u4e3b\u52d5\u53ca\u6709\u71b1\u8aa0\u7684\u5de5\u4f5c\u614b\u5ea6\uff0c\u826f\u597d\u54c1\u884c\uff0c\u52e4\u596e\u76e1\u8cac\uff0c\u80fd\u61c9\u4ed8\u9650\u671f\u5de5\u4f5c\u3001\u6709\u4e8b\u5949\u5fc3\u5fd7\u3002\n\n\u5de5\u4f5c\u6642\u9593\uff1a \u6bcf\u661f\u671f5\u5929\u5de5\u4f5c\uff0c\u661f\u671f\u4e00\u81f3\u4e948:30AM-5:30PM\u621612:30-9:30PM, \u6309\u8ab2\u7a0b\u6216\u6d3b\u52d5\u9700\u8981\u8f2a\u73ed\u5de5\u4f5c(\u6bcf\u661f\u671f\u5927\u7d04\u9700\u8f2a\u503c2\u5929\u591c\u73ed)\n\n\u85aa\u916c\uff1a\u8996\u4e4e\u76f8\u95dc\u7d93\u9a57\n\u798f\u5229\uff1a\u91ab\u7642\u4f4f\u9662\u4fdd\u96aa\u300112-14\u5929\u6709\u85aa\u5e74\u5047\u3001\u9280\u884c\u5047\u671f\u3001\u4f4f\u9662\u91ab\u7642\u3001\u5831\u8b80\u672c\u9662\u8ab2\u7a0b\u512a\u60e0\u7b49", "employment_types": ["Full Time", "Contract"], "selling_points": ["priority-setting for key celebration activities", "gala dinner and a banking history archive", "Promotes and executes integrated programmes"], "locations": ["Sheung Wan"], "categories": ["Banking / Finance", "Others", "Marketing / Public Relations", "Marketing - Brand / Product Management", "Public Relations - Event Management"], "post_time": "2022-01-14T08:44:27Z", "salary": {"currency": null, "max": null, "min": null, "period": "monthly", "term": null}, "salary_visible": false, "title_keywords": ["project manager"], "responsibilities": [], "requirements": {"degrees": [], "majors": [], "languages": [], "language_level": [], "hard_skills": ["excel", "word", "ms office"], "soft_skills": [], "languages_combined": []}, "experience_required": {"duration": [], "field": []}}, {"job_id": "100003009050241", "location_code": "hk", "company": "Hong Kong Trade Development Council", "job_title": "Project Executive", "description": "Job Responsibilities\u00a0\n\nDevelop and organize branding and fundraising events and promotional projects, from quotation & cost preparation, online registration, designing, factory production, on-site operation to post-event evaluation e.g. fundraising campaigns, ceremonies, exhibitions, performances, etc. \u00a0\u00a0 \u00a0\u00a0\nLiaise and collaborate with relevant internal and external parties to ensure smooth execution of events and projects promotion and operation\nPerform ad hoc duties as assigned\u00a0\nJob Requirements\u00a0 \u00a0 \u00a0 \u00a0 \u00a0 \u00a0 \u00a0 \u00a0 \u00a0 \u00a0 \u00a0 \u00a0 \u00a0 \u00a0 \u00a0 \u00a0 \u00a0 \u00a0 \u00a0 \u00a0 \u00a0 \u00a0 \u00a0 \u00a0 \u00a0 \u00a0 \u00a0 \u00a0 \u00a0 \u00a0 \u00a0 \u00a0 \u00a0 \u00a0\u00a0\n\nDegree holder / Higher Diploma in Event Management, Marketing, Digital Marketing, Communications or equivalent\u00a0\nMinimum 3 years of relevant working experience in event marketing & management (both online and offline events) and promotions.\nGood communication skills, responsible, well-organized, independent, creative, multi-tasking, able to anticipate needs and prioritize work\u00a0\u00a0\nGood command of written and spoken English and Chinese\u00a0\nProficiency in MS Word, PowerPoint, Excel and other Microsoft Applications\nWork outdoor and work on weekends & public holidays occasionally\nImmediate available is highly preferred\nThe temporary contract is subjected to renewal\u00a0\n\nPlease apply online with your full resume, listing church affiliations (if any), current and expected salary.\u00a0\n\nYou may also send your\u00a0application\u00a0to\u00a0Head of HR & Administration,\u00a0World Vision Hong Kong,\u00a02/F Mayfair Centre,\u00a04 Anchor Street, Tai Kok Tsui,\u00a0Kowloon\u00a0\n\nTo find out more about our job opportunities, please visit our website\nhttps://www.worldvision.org.hk/get-involved/vacancies\n\nWorld Vision Hong Kong is committed to safeguarding our children and adult beneficiaries from any risk of abuse, exploitation and harm. Candidates selected for interviews will be requested a self-declaration of previous records for any crimes against children or sexual offences, and may be requested to undergo Sexual Conviction Record Check by the HK Police.\n\nPersonal Data provided by job applicants will be used for recruitment purposes only and will be treated in accordance with the organization's personal data privacy policy. Applicants who are not invited for interviews within six weeks may consider their applications unsuccessful and the personal data collected will be destroyed within 12 months.", "employment_types": ["Full Time", "Permanent"], "selling_points": ["Promote HK Service to the world", "Customer Service and Event Management", "Coordinate trade events"], "locations": ["Wan Chai"], "categories": ["Marketing / Public Relations", "Marketing - General / Support", "Marketing - Market Research", "Public Relations - Event Management"], "post_time": "2022-01-14T10:00:14Z", "salary": {"currency": null, "max": null, "min": null, "period": "monthly", "term": null}, "salary_visible": false, "title_keywords": ["project executive"], "responsibilities": ["liaise", "collaborate with", "cost", "ad hoc duties", "management", "hr", "quotation", "designing", "internal and external parties", "website", "develop", "communication", "digital marketing", "recruitment", "evaluation", "personal data", "listing", "administration"], "requirements": {"degrees": ["diploma", "degree holder"], "majors": ["marketing", "digital marketing", "communications"], "languages": ["english", "chinese"], "language_level": ["good command"], "hard_skills": ["excel", "microsoft applications", "powerpoint", "ms word"], "soft_skills": ["communication skills", "independent", "responsible", "well-organized", "prioritize", "committed", "multi-tasking", "smooth", "creative"], "languages_combined": [{"language": "english", "language_level": ["good command"]}, {"language": "chinese", "language_level": ["good command"]}]}, "experience_required": {"duration": ["minimum 3 years"], "field": ["management", "marketing", "relevant working experience"]}}, {"job_id": "100003009048073", "location_code": "hk", "company": "The Hong Kong Exporters' Association", "job_title": "Senior Officer (Event Management-focus)", "description": "(Reference number: S_ATO_95_JB)\n\nJob duties:\n\nCoordinate with the Admissions and Advancement team in executing of all the marketing and fundraising campaign events and reporting preparation, including but not limited to the following: sourcing, drafting publication material, promotion, photo shooting, budgeting and administration\u00a0\nAssist Admissions and Advancement team in cultivating relations within and outside the school community, including but not limited to staff, parents, students and alumni\nMarket the school\u2019s brand and shape the way we connect with our targeted audience via phone, email, in person and other means\nAttend key school functions; prepare, write and post any news copy and social media coverage of the event\nSupport the school in preparing presentations for different marketing events as needed\nUpdate and maintain the school\u2019s website and other publications\nCollect data and maintain a systemic database for analysis\nCoordinate with outside agencies to produce marketing material\nProviding general administrative support as required\nPerform any other duties as assigned by supervisors or management\nBe able to manage ad-hoc projects\n\nJob Requirements:\n\nA recognized degree, preferred in event management, marketing, communications and public relations or related discipline preferably with 3 years\u2019 relevant work experience\nExperience in planning projects from ground work to results delivery in the educational institution, non-profit organization, charitable organization would be an advantage\nHigh proficiency in English. Strong written and verbal communication skills are necessary. Fluency in Mandarin would be an advantage\nArticulate, presentable and possess strong interpersonal skills in order to represent the school\u2019s mission and vision\nSelf-motivated with good analytical skill and be able to work under pressure\nAbility to work effectively independently and as a team member\nDesire to work in a fast-paced environment with the ability to multi task and manage time effectively\nProficient computer skills with experience in MS Word, Excel, Power Point, Adobe Illustrator, Photoshop and InDesign\n\nApplication Details\n\nInterested parties please apply with full resume stating current and expected salary by clicking \u201cApply Now\u201d or email to the Human Resources Department via our employment webpage at\u00a0www.caisbv.edu.hk.\n\nPlease quote the reference number of the post in your application.\n\nAll personal data submitted will be used for recruitment purposes only and all related information will be kept for up to 24 months.", "employment_types": ["Full Time", "Contract"], "selling_points": [], "locations": ["Tsim Sha Tsui"], "categories": ["Marketing / Public Relations", "Public Relations - Event Management"], "post_time": "2022-01-14T04:41:03Z", "salary": {"currency": null, "max": null, "min": null, "period": "monthly", "term": null}, "salary_visible": false, "title_keywords": ["senior officer"], "responsibilities": ["any other duties", "data", "budgeting", "website", "maintain", "database", "ad-hoc projects", "administration", "presentations", "marketing material", "publication", "reporting", "social media", "management", "general administrative support", "coordinate with", "executing", "marketing events", "analysis"], "requirements": {"degrees": ["degree"], "majors": ["marketing", "communications"], "languages": ["english", "mandarin"], "language_level": ["fluency", "advantage", "proficiency"], "hard_skills": ["excel", "analytical skill", "indesign", "adobe illustrator", "computer skills", "photoshop", "power point", "ms word"], "soft_skills": ["work effectively", "communication skills", "self-motivated", "analytical skill", "independently", "fast-paced environment", "presentable", "interpersonal skills", "articulate", "team member", "work under pressure"], "languages_combined": [{"language": "english", "language_level": ["proficiency"]}, {"language": "mandarin", "language_level": ["fluency", "advantage"]}]}, "experience_required": {"duration": ["3 years"], "field": ["management", "public relations", "related", "marketing", "planning"]}}, {"job_id": "100003009049488", "location_code": "hk", "company": "The Hong Kong Institute Of Bankers", "job_title": "Officer - Marketing, Membership & Events", "description": "Job Function\nTo assist in organization and implementation of conferences, exhibition, events and association activities.\u00a0\u00a0\n\n\nRequirements\n\n\nUniversity graduate\nGood command of English and Chinese.\nSkilled in MS Office\u00a0(Word, Excel,\u00a0Outlook) and webinar operation\nPleasant disposition, strong interpersonal and organizing skills\nEnthusiastic, mature, self-motivated and able to take on responsibilities\n5-day work with medical benefits will be provided.\u00a0 Interested parties, please send your resume with expected salary by clicking \"Apply Now\".\n\n\nPersonal data collected will be used for recruitment purpose only.", "employment_types": ["Full Time", "Permanent"], "selling_points": ["Great development opportunity", "Membership Benefit and Events", "Banking & Finance Institution"], "locations": ["Sheung Wan"], "categories": ["Marketing / Public Relations", "Marketing - General / Support", "Public Relations - Event Management", "Public Relations - General / Support"], "post_time": "2022-01-14T08:44:27Z", "salary": {"currency": null, "max": null, "min": null, "period": "monthly", "term": null}, "salary_visible": false, "title_keywords": ["officer"], "responsibilities": ["conferences", "implementation"], "requirements": {"degrees": ["university graduate"], "majors": [], "languages": ["english", "chinese"], "language_level": ["good command"], "hard_skills": ["excel", "outlook", "word", "ms office"], "soft_skills": ["self-motivated", "mature", "pleasant", "enthusiastic", "interpersonal"], "languages_combined": [{"language": "english", "language_level": ["good command"]}, {"language": "chinese", "language_level": ["good command"]}]}, "experience_required": {"duration": [], "field": []}}, {"job_id": "100003009055571", "location_code": "hk", "company": "Page Personnel", "job_title": "Assistant Corporate Communication Manager - I&T industry", "description": "This is a dynamic and demanding role and will involve considerable flexibility and the ability to prioritise tasks in order to deliver administrative support for the academic community within the Centre and wider community.\u00a0 The post holder\u2019s role will be to ensure effective and professional liaison and communication with academic, administrative and external customers at all levels, to facilitate the smooth running of day-to-day activities.\n\n\nKey Responsibilities\n\n\nTo provide efficient and professional services to stakeholders\nTo provide effective support in programme, event and office administration\nTo implement the admission and registration process\nTo support teaching and learning services\nTo maintain student records and its systems\nTo support and implement event plans and concepts\n20 days annual leave, 5 days work, fringe benefits and working with global teams.", "employment_types": ["Full Time", "Permanent"], "selling_points": ["Knowledge in Innovation & Technology industry", "Experienced in bilingual PR materials development", "Stable environment"], "locations": ["Not Specified"], "categories": ["Marketing / Public Relations", "Marketing - Marketing Communication", "Public Relations - Copy-writing", "Public Relations - Event Management"], "post_time": "2022-01-18T02:44:36Z", "salary": {"currency": null, "max": null, "min": null, "period": "monthly", "term": null}, "salary_visible": false, "title_keywords": ["manager", "assistant"], "responsibilities": ["administrative support", "office administration", "systems", "communication", "maintain student records", "plans"], "requirements": {"degrees": [], "majors": [], "languages": [], "language_level": [], "hard_skills": ["dynamic"], "soft_skills": ["efficient", "prioritise", "communication", "dynamic", "learning", "smooth"], "languages_combined": []}, "experience_required": {"duration": [], "field": []}}, {"job_id": "100003009054808", "location_code": "hk", "company": "Billion Joy Media HK Limited", "job_title": "Senior Digital and Campaign Marketing Executive", "description": "Responsibilities:\n\nDevelop PR and branding, marketing strategies for the Center from scratch;\nDesign, execute and perform tracking of PR, branding and marketing programs;\nPromote the Center through different channels including website, e-newsletter, social media, printed and electronic media, etc;\nHandle PR and media relations such as interviews and media activities; maintain good relations with the media;\nCollaborate and communicate with the University partners, local and overseas research collaborators, and the industry to promote our company.\nOrganize various kinds of events and workshops e.g. conferences, award ceremonies, seminars, public events, planning, budget control, execution and event logistics\n\nRequirements:\n\nA bachelor or higher degree preferably in business, communication, marketing, public relations, or science;\n\u00a0At least 5 years\u2019\u00a0experience in PR or marketing fields and experience in social media and writing would be an advantage;\nSmart,\u00a0mature, organized with pleasant personality and\u00a0strong interpersonal skills;\nAttentive to details, creative, independent, proactive and flexible to meet tight schedule;\nPossess excellent communication skills, media relations experience and network;\nProficiency in the design and production of marketing materials; Basic knowledge of graphic design and proficient in Adobe Photoshop, Illustrator and PowerPoint;\nGood command of spoken & written English and Chinese.\n\nWe offer a competitive package & career prospect to the right candidate. Qualified and interested parties, please send application quoting the above reference number and detailing contact information, education and employment background, and salary expectation via : \u201cAPPLY NOW\u201d\n\nOnly shortlisted candidates will be contacted. For more information, please be welcome to visit our \uff1awebsite: www.hkstarlite.com /\u00a0\u00a0https://teamgreenworld.net/\n\nPersonal data provided will be used for consideration of your application for the applied position and other suitable vacancies in the Starlite Group.", "employment_types": ["Full Time", "Permanent"], "selling_points": [], "locations": ["Quarry Bay"], "categories": ["Marketing / Public Relations", "Public Relations - Event Management", "Digital Marketing"], "post_time": "2022-01-17T11:12:35Z", "salary": {"currency": null, "max": null, "min": null, "period": "monthly", "term": null}, "salary_visible": false, "title_keywords": ["marketing executive"], "responsibilities": ["collaborate", "social media", "communicate with", "marketing strategies", "website", "design", "develop", "conferences", "maintain", "planning", "logistics", "budget control", "tracking"], "requirements": {"degrees": ["degree", "bachelor"], "majors": ["science", "business", "marketing"], "languages": ["english", "chinese"], "language_level": ["good command"], "hard_skills": ["adobe photoshop", "basic", "illustrator", "powerpoint"], "soft_skills": ["flexible", "organized", "communication skills", "proactive", "independent", "attentive to details", "mature", "pleasant", "communication", "interpersonal skills", "creative"], "languages_combined": [{"language": "english", "language_level": ["good command"]}, {"language": "chinese", "language_level": ["good command"]}]}, "experience_required": {"duration": ["at least 5 years"], "field": ["social media", "pr", "marketing", "writing", "media"]}}, {"job_id": "100003009053311", "location_code": "hk", "company": "Altaya Wines Limited", "job_title": "Marketing Executive", "description": "Job Responsibilities\n\nPromotes and executes integrated programmes for celebrating HKIB\u2019s anniversary with a view to strengthen industry\u2019s collaboration and partnership, promoting the joint effort of the banking industry and stakeholders\u2019 engagement.\nProvides strategic planning and priority-setting for key celebration activities \u2013 gala dinner and a banking history archive.\nWorks independently to produce promotion plan and content with full utilisation of the engaged vendors.\nRepresents HKIB in communications with key stakeholders for lining up content and support to the celebration activities.\nContributes market knowledge on driving effective branding and marketing campaigns for anniversary celebration.\n\nJob Requirements\n\nUniversity degree holder or above, preferably in journalism, marketing or communications discipline.\nMinimum 5 years of event marketing, event management and editorial experience with 2 years at a supervisory role.\nStrong project management & communications skills and attention to details.\nProactive and a good team player.\nOutgoing, responsible, independent and resourceful.\nExcellent English and Chinese writing skills with the ability to create quality promotion materials.\n\nInterested parties may send in your application together with a detailed resume stating your\u00a0academic results, present & expected salaries, date of availability\u00a0and contact phone number by clicking\u00a0\"Apply Now\"\n\nApplicants are welcomed to visit our website:\u00a0www.hkib.org\u00a0for further information about the institute.\n\n(All information provided will be treated in strict confidence and used solely for recruitment purposes)", "employment_types": ["Full Time"], "selling_points": ["All round marketing functions", "5 day work per week with Medical & Dental Scheme", "Career Development"], "locations": ["Aberdeen"], "categories": ["Marketing / Public Relations", "Marketing - Brand / Product Management", "Marketing - Marketing Communication", "Public Relations - Event Management"], "post_time": "2022-01-17T06:44:19Z", "salary": {"currency": null, "max": null, "min": null, "period": "monthly", "term": null}, "salary_visible": false, "title_keywords": ["marketing executive"], "responsibilities": ["communications with", "strategic planning", "banking", "marketing campaigns", "plan"], "requirements": {"degrees": ["university degree"], "majors": ["journalism", "marketing", "communications"], "languages": ["english", "chinese"], "language_level": ["excellent"], "hard_skills": ["project management", "writing skills"], "soft_skills": ["outgoing", "good team player", "independent", "responsible", "resourceful", "writing skills", "project management", "attention to details", "proactive"], "languages_combined": [{"language": "english", "language_level": ["excellent"]}, {"language": "chinese", "language_level": ["excellent"]}]}, "experience_required": {"duration": ["2 years", "minimum 5 years"], "field": ["editorial", "management", "marketing", "supervisory"]}}, {"job_id": "100003009048706", "location_code": "hk", "company": "Hong Kong Trade Development Council", "job_title": "Project Assistant (3 - 12 months)", "description": "Position Summary:\n\nThe\u00a0Senior Manager (Institutional Advancement) will be an important member of the Institutional Advancement and Marketing Office (IAMO).\n\nThe Key Responsibilities include:\n\nWork with the senior team members to establish annual financial goals, strategies and work plans;\nBuild relationships with prospects and donors to confirm major-gift giving and referrals. Cultivate and conduct prospect research to identify prospects to build a healthy pipeline and meet annual targets;\nWork with the marketing & communications team to develop supporting materials and proposals;\nWork with the stewardship team to establish donor stewardship plan and ensure the deliverables are met and communicated in a timely manner;\nBuild relationships with associations, corporate networks and other platforms to expand the reach and build prospect pipelines; and\nAny other duties as assigned by the College as appropriate.\n\nRequirements:\n\nApplicants should meet the following requirements:\n\nA Bachelor\u2019s degree in Business/Communications/Marketing or related discipline;\nAt least 8-10 years\u2019 relevant work experience. Experience in the post-secondary education sector will be an asset;\nDeep knowledge of the Hong Kong philanthropic landscape and fundraising principles;\nAccreditation in fundraising will be an advantage;\nStrong track record of the previous fundraising and industry connections are a must;\nExcellent communications and writing skills in English and Chinese (Spoken Cantonese & Putonghua, ability to read & write traditional and simplified Chinese)\nAbility to engage with senior executives\nOrganised and task-oriented to meet deadlines\nMust be self-motivated and proactive; and\nStrong interpersonal skills, able to resolve issues and maintain strong relationships.\nRemarks: Candidates with more experience may be appointed as Head (Institutional Advancement).\n\n\nSalary and Fringe Benefits:\n\nThe appointment will be made on a contract basis, renewable subject to mutual consent.\nRemuneration is competitive and will be based on qualifications and relevant experience.\nThe College offers group medical insurance, staff development support, annual leave and sick leave, and mandatory Provident Fund to the eligible appointee.\n\nApplication Procedure:\n\nApplicants are invited to:\n\nSubmit an application letter with a full Curriculum Vitae, and copies of all graduate transcripts, and the names and contact details of three references.\nSpecify in the application letter the current/latest salary and expected salary.\nSend applications to HR Office, Yew Chung College of Early Childhood Education by clicking \"Apply Now\".\nThe College will review applications immediately and applications will be accepted until the posts are filled.\u00a0 Only shortlisted candidates will be contacted.\n\nImportant notes to Applicants:\n\nAppointees will have to undergo a medical examination.\u00a0 Reimbursement of costs subject to a ceiling is applicable.\nLocal applicants will have to undergo a Sexual Conviction Record Check. Overseas applicants will have to present a police report before the appointment can be confirmed.\nA satisfactory employment reference is required before the appointment can be confirmed.\nThe College also reserves the right to make an appointment by invitation.\n\n\n\nPersonal data collected will be used for recruitment-related purposes only.", "employment_types": ["Full Time", "Temporary"], "selling_points": ["Experience in Events / Exhibitions", "Fluent in English and Putonghua", "Fresh graduate"], "locations": ["Wan Chai"], "categories": ["Marketing / Public Relations", "Marketing - General / Support", "Marketing - Marketing Communication", "Public Relations - Event Management"], "post_time": "2022-01-14T07:05:54Z", "salary": {"currency": null, "max": null, "min": null, "period": "monthly", "term": null}, "salary_visible": false, "title_keywords": ["project assistant"], "responsibilities": ["any other duties", "a timely manner", "develop", "plan", "plans"], "requirements": {"degrees": ["degree", "bachelor", "secondary education"], "majors": ["business", "communications", "marketing"], "languages": ["cantonese", "putonghua", "english", "chinese"], "language_level": ["excellent"], "hard_skills": ["writing skills"], "soft_skills": ["self-motivated", "deep", "writing skills", "interpersonal skills", "organised", "meet deadlines", "proactive"], "languages_combined": [{"language": "cantonese", "language_level": ["excellent"]}, {"language": "putonghua", "language_level": ["excellent"]}, {"language": "english", "language_level": ["excellent"]}, {"language": "chinese", "language_level": ["excellent"]}]}, "experience_required": {"duration": ["at least 8-10 years"], "field": ["education"]}}, {"job_id": "100003009054217", "location_code": "hk", "company": "Brink's Hong Kong Limited", "job_title": "Jewellery Show Coordinator", "description": "Responsibilities:\n\n\nTo assist Project Managers in the overall planning and execution of local and overseas trade promotional events related to financial service industries\nTo coordinate logistical arrangements and to provide onsite support for events including but not limited to conferences, seminars, webinars, ceremonies, gala evenings, networking cocktails, etc.; and to liaise with the event venue, service vendors and internal departments on the required technical setup for different events\nTo liaise with speakers / VIPs / travel agency on travel arrangement and collection of marketing materials\nTo liaise and maintain good relations with relevant business contact, industry and trade associations\nTo handle enquiries from event participants and undertake any ad-hoc on-site duties\nTo closely update the database of business leaders and to keep track of any major management movement of top conglomerates\n\nRequirements:\u00a0\n\nProactive, self-initiated and detail-minded\nMature, creative, with team spirits\nMeticulous and detail-minded\nWillingness to work long hours to meet tight deadlines\nStrong command of spoken and written English and Chinese. Fluent in Putonghua\nProficiency in MS applications and Chinese word-processing\nCustomer-oriented with good communication and interpersonal skills in dealing with people from all levels\nSolid prior experience in event management will be an advantage\n\nRemuneration and Benefits:\nSalary will be commensurate with qualifications and experience. A competitive remuneration and benefits package, including annual leave, medical and dental benefits will be offered.\n\nApplication Procedure:\nInterested candidates are invited to complete the application form on our\u00a0website\u00a0http://www.hktdc.com/careers.html\u00a0.\u00a0Those who do not hear from us within EIGHT WEEKS after the closing date may assume their applications were unsuccessful.\n\n\n\nAll information provided by applicants will be treated in strict confidence and used only for recruitment purposes. Applicants may be considered for other suitable positions within the Council. Their personal data will be destroyed\u00a0six months after the selection is finalized.", "employment_types": ["Full Time", "Permanent"], "selling_points": ["Exciting Opportunity to work in a unique business", "Friendly working environment", "Fresh graduates are also welcome"], "locations": ["Hung Hom"], "categories": ["Transportation & Logistics", "Freight Forwarding", "Marketing / Public Relations", "Public Relations - Event Management", "Others", "Student / Fresh Graduate / No Experience"], "post_time": "2022-01-17T08:50:16Z", "salary": {"currency": null, "max": null, "min": null, "period": "monthly", "term": null}, "salary_visible": false, "title_keywords": ["coordinator"], "responsibilities": ["marketing materials", "liaise", "ad-hoc", "management", "coordinate", "logistical arrangements", "conferences", "maintain", "handle enquiries", "contact", "travel arrangement", "database", "liaise with", "setup", "planning"], "requirements": {"degrees": [], "majors": [], "languages": ["putonghua", "english", "chinese"], "language_level": ["proficiency", "fluent"], "hard_skills": ["ms applications", "chinese word-processing"], "soft_skills": ["detail-minded", "meticulous", "meet tight deadlines", "creative", "mature", "customer-oriented", "communication and interpersonal skills", "willingness to work", "proactive"], "languages_combined": [{"language": "putonghua", "language_level": ["fluent"]}, {"language": "english", "language_level": []}, {"language": "chinese", "language_level": ["proficiency"]}]}, "experience_required": {"duration": [], "field": ["management"]}}, {"job_id": "100003009046517", "location_code": "hk", "company": "Seeds Financial Group", "job_title": "Event and Project Manager (Sales)/ HK$25,000-35,000 plus bonus", "description": "A rare opportunity to join a reputable I&T organization! They are looking for Assistant Corporate Communication Manager to join their dedicated team. If you are passionate about Innovation and Technology with 5+ years of experience in Corporate Communication, please do not hesitate to apply!\n\nClient Details\n\nOur client is a I&T company based in HK with 15 years of history. They have the most up-to-date industry insight and devoted to developing a strong digital, technology and FinTech community in Hong Kong.\n\nDescription\n\nPlan and execute publicity campaigns through all communication channels\nBilingual content development for PR materials, including speeches, press release, presentations, advertorials, annual reports, award submission, ESG report and more\nInvolve in event management, both physical and virtual\nMedia relation: handle media enquiries, maximize PR coverage and maintain good relationships\nHandle internal and external communications and publications production\nConduct market search to obtain the most up-to-date industry information and trends\nEngage with digital tech companies to enhance the brand awareness of company\nAd hoc tasks as assigned\n\nProfile\n\nDegree holder in Communications, Journalism, Language or other related disciplines\n5+ years of experience in all-rounded Corporate Communication, PR duties or other relevant experience\nStrong in bilingual copywriting, especially for press release, CEO speeches, publications etc.\nCreative, self-motivated, fast-paced, tech-savvy team player with can-do attitude\nKnowledge in Innovation & Technology, Fintech, digital etc.\nExcellent command in written and verbal Chinese and English is a must\n\nJob Offer\n\n5-day work week\nStable environment\nOn-the-job training\n\nTo apply online please click the 'Apply' button below. For a confidential discussion about this role please contact Josephine Loong on +852 3602 2436.", "employment_types": ["Full Time"], "selling_points": ["Monthly Income up to HK$50,000 (including bonus)", "Fresh-graduates are welcomed", "Excellent training opportunities"], "locations": ["Causeway Bay"], "categories": ["Sales, CS & Business Devpt", "Customer Service - Manager", "Marketing / Public Relations", "Public Relations - Event Management", "Hospitality / F & B", "Tourism / Travel Agency"], "post_time": "2022-01-13T12:53:31Z", "salary": {"currency": "HKD", "max": 34999, "min": 25000, "period": "monthly", "term": null}, "salary_visible": true, "title_keywords": ["project manager", "sales"], "responsibilities": ["management", "ad hoc tasks", "developing", "presentations", "communication", "maintain", "reports", "contact", "plan", "report"], "requirements": {"degrees": ["degree holder"], "majors": ["journalism", "related disciplines", "communications"], "languages": ["english", "chinese"], "language_level": ["excellent"], "hard_skills": ["presentations"], "soft_skills": ["self-motivated", "can-do attitude", "communication", "devoted", "team player", "creative", "stable", "passionate about"], "languages_combined": [{"language": "english", "language_level": ["excellent"]}, {"language": "chinese", "language_level": ["excellent"]}]}, "experience_required": {"duration": ["5+ years"], "field": ["corporate communication", "pr", "relevant experience"]}}, {"job_id": "100003009052841", "location_code": "hk", "company": "Hong Kong Cyberport Management Co Ltd", "job_title": "Manager - Corporate Marketing (Ref# MCM220117J)", "description": "Job Summary:\nEvent and Project Manager (Sales)\u00a0 - \u00a0is responsible for providing administrative and coordination to support sales projects and event services team. It also involves day to day tasks of preparing departmental correspondence for sales activities and events servicing.\n\nTo enhance the financial services that our team provides to our clients, this role requires good customer service knowledge, exhibit a professional attitude and be a team player to achieve \u00a0sales and services goals.\n\nResponsibilities:\n\nDelivery quality customer services by providing accurate and sufficient information to clients as well as drafting concise and informative replies when necessary.\nProvide sales activities support, in organizing sales materials, preparing prospect proposal review, merchandise give-away items, \u00a0turnover preparation, answering sales or client enquiries, etc.\nMaintain extensive accounts and client\u2019s data for customer relationship management\nOffice administration and clerical support, including the arrangement of meetings, taking meeting minutes, office supply ordering / pickup and maintenance, management of team roster and leave records, courier deliveries, team cast related preparation and arrangement, organize filing systems and other related tasks.\nKeep up-to-date spending records, trace clients' billings, and prepare financial reports to clients.\nAssist in handling small scale corporate groups, social and internal event\nGenerate related reports for management and operation partners\nBasic Qualifications:\nBachelor degree is required, fresh-graduates are welcomed\nKnowledgeable in customer service industry\nAble to work independently\nLiterate in PC applications including MS Word, Excel, PowerPoint and Chinese typing\nGood communication skills with spoken and written English, Cantonese, and Putonghua", "employment_types": ["Full Time", "Permanent", "Contract"], "selling_points": ["Manage major company events", "strategic planning to create an event experience", "Build collaborations, partnerships and sponsorship"], "locations": ["Pok Fu Lam"], "categories": ["Marketing / Public Relations", "Marketing - General / Support", "Marketing - Marketing Communication", "Public Relations - Event Management"], "post_time": "2022-01-17T04:14:05Z", "salary": {"currency": null, "max": null, "min": null, "period": "monthly", "term": null}, "salary_visible": false, "title_keywords": ["manager"], "responsibilities": ["sales activities", "management", "financial reports", "maintenance", "data", "office administration", "billings", "review", "quality", "clerical support", "systems", "customer services", "communication", "customer service", "maintain", "reports", "coordination"], "requirements": {"degrees": ["degree", "bachelor"], "majors": [], "languages": ["cantonese", "putonghua", "english", "chinese"], "language_level": ["good"], "hard_skills": ["small", "excel", "basic", "maintenance", "typing", "powerpoint", "pc applications", "ms word"], "soft_skills": ["communication skills", "work independently", "responsible", "customer service", "coordination", "team player", "accurate", "extensive"], "languages_combined": [{"language": "cantonese", "language_level": ["good"]}, {"language": "putonghua", "language_level": ["good"]}, {"language": "english", "language_level": ["good"]}, {"language": "chinese", "language_level": []}]}, "experience_required": {"duration": [], "field": []}}, {"job_id": "100003009050960", "location_code": "hk", "company": "Hong Kong Science & Technology Parks Corporation", "job_title": "Senior Manager, Event Marketing & Community Engagement  [JDB/SMEMCE/220114]", "description": "Job Responsibilities\n\n\n\nAct as the key liaison of key stakeholders including Hong Kong Monetary Authority, and other government, regulatory bodies and our members.\nPlan and execute a wide range of events including regulatory initiatives, industry awards, annual conferences, sponsored luncheons and webinars, secondary school events, etc.\nResponsible for all pre and post events activities including promotion, invitation, enrolment, payment, evaluation, report, etc. and work closely with other internal teams to ensure these activities are executed properly.\nWork with Marketing Team to ensure consistency in Institute\u2019s branding in all promotional materials.\nSource and manage external vendors related to event management.\nAny ad-hoc projects or tasks assigned by supervisor.\n\nJob Requirements\n\n\nUniversity degree holder or above, preferably in business or marketing discipline.\nMinimum 5 years of marketing or event management experience.\nKnowledge and exposure in the banking & finance industry, as well as experience in work on government funded projects would be advantageous.\nStrong project management, analytical and problem-solving skills.\nStrong event execution skills and proven ability to manage multiple responsibilities in a fast-paced environment with critical deadlines.\nExcellent interpersonal skills to work with people at all levels.\nEnergetic, self-motivated, resourceful, and result oriented.\nExcellent command in both written and spoken English and Chinese.\n\nInterested parties may send in your application together with a detailed resume stating your\u00a0academic results, present & expected salaries, date of availability\u00a0and contact phone number by clicking\u00a0\"Apply Now\"\n\nApplicants are welcomed to visit our website:\u00a0www.hkib.org\u00a0for further information about the institute.\n\n(All information provided will be treated in strict confidence and used solely for recruitment purposes)", "employment_types": ["Full Time"], "selling_points": [], "locations": ["Shatin Area"], "categories": ["Marketing / Public Relations", "Marketing - Marketing Communication", "Public Relations - Event Management", "Others"], "post_time": "2022-01-14T12:04:56Z", "salary": {"currency": null, "max": null, "min": null, "period": "monthly", "term": null}, "salary_visible": false, "title_keywords": ["senior manager"], "responsibilities": ["management", "teams", "school events", "conferences", "payment", "promotional materials", "plan", "evaluation", "ad-hoc projects", "report"], "requirements": {"degrees": ["university degree"], "majors": ["business", "marketing"], "languages": ["english", "chinese"], "language_level": ["excellent"], "hard_skills": ["problem-solving skills", "project management"], "soft_skills": ["self-motivated", "resourceful", "fast-paced environment", "project management", "result oriented", "interpersonal skills", "problem-solving skills", "energetic"], "languages_combined": [{"language": "english", "language_level": ["excellent"]}, {"language": "chinese", "language_level": ["excellent"]}]}, "experience_required": {"duration": ["minimum 5 years"], "field": ["management", "marketing", "finance industry", "banking"]}}, {"job_id": "100003009052171", "location_code": "hk", "company": "A-World Consulting Limited", "job_title": "Account Executive", "description": "Key Responsibilities\n\nPlan, organise and manage major company events in physical, hybrid or virtual formats. Devise strategic implementation plan\nDevelop and implement strategic planning to create an integrated event experience. Curate programmes and activities to align Cyberport\u2019s public missions and to enhance its position and brand as thought leadership and industry voice in the region\nProvide full support on wide spectrum of event management including but not limited to project scheduling, speaker co-ordination, programme development, stage management, promotion and advertising, marketing collaterals, stage production, manpower management, onsite logistics, as well as market research and procurement\nPlan, source and incorporate innovative event elements to enhance traction and attendee experience, including digital/stage gimmicks, interactive games, incentives, event platforms/solutions etc.\nDrive attendance and positive publicity through integrated marketing & communications in conjunction with Branding & Corporate Communications teams to achieve best synergies, incl. event content marketing and distribution via effective channels for maximum audience engagement & impact\nExplore, solicit and follow up potential collaborations, partnerships and sponsorships opportunities for better event synergy\nLiaise and work closely with different business units, agencies/vendors, Government or public bodies and industry organisations\nManage marketing budget and monitor event P/L\n\nRequirements\n\nDegree in marketing, journalism, mass communications, public relations or related discipline\nMinimum 10 years relevant working experience in corporate/event management, event production & marketing, corporate communications, marketing communication and / or public relations with hands-on experience in physical, hybrid and virtual events ideally from sizable organization/public bodies and preferably from technology sector\nAll-round experience & proven track record in planning and managing large scale industry conference and events a must\nKnowledge and experience in hybrid/ virtual events, event platforms/technologies, creative digital elements, stage management, cross-platform marketing and user experience is essential\nConnection with industry associations, chambers of commerce, industry organisations and speakers bureau for potential collaborations, sponsorship solicitation, and/or speakers invitations a plus\nStrong event and project management skills, especially hybrid events\nGood understanding of technicality & acumen on integrated event platforms, registration and EDM systems and virtual event setup\nA fast mover and strategic thinker with who possess new normal agility with excellent efficiency and strategic focus\nA relationship-builder and team player with excellent interpersonal and negotiation skills\nExcellent command of written and spoken English and Chinese (Cantonese and Putonghua)\nOutstanding project management and organisational skills\nAble to work effectively under pressure and deliver high quality work under tight deadlines/ schedules\nDetail-oriented with exceptional strengths in multi-tasking\nA self-motivated team player with strong can-do attitude\nCreative, analytical and well-organised\n\nThe position is on a renewable 2-year fixed-term contract, subject to performance and operational needs, the position will convert into open contract after 2 years.\n\nWe offer competitive package to the right candidate. Interested party please click\u00a0Apply Now\u00a0to apply on or before 11 February 2022\u00a0in confidence with full resume in Word document, stating present and expected salary, and available date\u00a0and quote the reference.\u00a0\n\nApplicants who do not hear from us by 25 February 2022\u00a0may assume that their applications are unsuccessful.\n\nFurther information about the Cyberport is available at\u00a0http://www.cyberport.hk", "employment_types": ["Full Time", "Permanent"], "selling_points": ["5 days work per week", "performance bonus", "Fresh Graduate also welcome"], "locations": ["Sheung Wan"], "categories": ["Media & Advertising", "Editorial / Journalism", "Marketing / Public Relations", "Public Relations - Copy-writing", "Public Relations - Event Management"], "post_time": "2022-01-17T02:20:07Z", "salary": {"currency": null, "max": null, "min": null, "period": "monthly", "term": null}, "salary_visible": false, "title_keywords": ["account executive"], "responsibilities": ["liaise", "attendance", "management", "advertising", "strategic planning", "marketing collaterals", "teams", "implementation", "market research", "develop", "budget", "monitor", "logistics", "project scheduling", "plan"], "requirements": {"degrees": ["degree"], "majors": ["journalism", "marketing", "communications"], "languages": ["cantonese", "putonghua", "english", "chinese"], "language_level": ["excellent"], "hard_skills": ["project management", "plus", "focus", "acumen"], "soft_skills": ["work effectively", "self-motivated", "under pressure", "can-do attitude", "project management skills", "detail-oriented", "communication", "project management", "hands-on", "team player", "negotiation skills", "organisational skills", "multi-tasking", "well-organised", "focus", "creative", "interpersonal"], "languages_combined": [{"language": "cantonese", "language_level": ["excellent"]}, {"language": "putonghua", "language_level": ["excellent"]}, {"language": "english", "language_level": ["excellent"]}, {"language": "chinese", "language_level": ["excellent"]}]}, "experience_required": {"duration": ["minimum 10 years"], "field": ["management", "public relations", "sizable organization", "relevant working experience", "marketing", "digital", "planning"]}}, {"job_id": "100003009055227", "location_code": "hk", "company": "Rue Madame Retail Limited", "job_title": "PR & Marketing Manager", "description": "We are looking for a seasoned senior leader who is passionate to join the largest Innovation and Technology eco-system in Hong Kong.\u00a0 The successful incumbent shall possess strong leadership to lead and drive the team to ideate, plan and implement high level flagship events, conferences, exhibitions, community engagement programme and new business initiatives to support the continuous growth of the Corporation and to elevate the vibrancy and diversity of the Science Park community.\u00a0 He / she has to be a strategic thinker and planner, a great problem solver, and is goal getting, result driven, innovative, co-creative, energetic, collaborative, enthusiastic; and bold to tackle and overcome challenges to deliver remarkable results.\nResponsibilities:\nIdeating, content curating, brand positioning, budgeting, planning, promoting and managing high-quality and influential B2B & B2C events to achieve the Corporate objectives\nLead and drive the team to meet and even exceed targeted goals, accomplish high quality and remarkable outcomes and manage to propose and make strategical, timely and decisive directions and changes in the dynamic environment\nMaster impactful marketing and promotional assets; research, analyse, interpret and present latest marketing trend and data in a world perspective\nStrategically plan and deliver engagement initiatives to build a vibrant and actively engaging community among the partner companies in the Science Park eco-system\nContent curate and manage digital platforms including websites and social media for specified events and programmes\nPerform any other duties as assigned by supervisors\nRequirements:\nBachelor degree in Business Administration, Marketing, Communication or other related disciplines\n10 years relevant experience in event marketing and management, preferably gained in sizable / MNC corporations with at least 3 years of solid team leadership\nProven track record in ideating, content curating and managing high level, large-scale & impactful events, and mastering professional, trendy and effective marketing promotional assets\nStrong business sense, thorough understanding of the latest world marketing trend and rich experience in digital and content marketing\nStrong leadership demonstration of tackling challenges, accomplishing remarkable results and growing the team\nInnovative, idea-driven, goal-getting, dynamic, self-motivated, detailed-oriented and is able to work under tight schedule\nProficient in both verbal and written English and Chinese, including Cantonese and Putonghua\nStrong industry network with excellent interpersonal and communications skills\nWe offer market competitive compensation, 5-day work week, and generous benefits including medical and life insurance; and voluntary contribution in addition to the legal minimum MPF.\u00a0 To apply, please send your full resume with current and expected salary to the Human Resources & Office Administration Department, Hong Kong Science and Technology Parks Corporation, 5/F, Building 5E, 5 Science Park East Avenue, Hong Kong Science Park, Hong Kong or, by email via \"Apply Now\"\u00a0on or before 27 January 2022.\u00a0 \u00a0Please quote the reference number on the email subject/envelope and the application letter.\u00a0\nPersonal data provided will be treated in strict confidence and used for recruitment purpose only.\u00a0 All personal data collected will be used strictly in accordance with employer\u2019s personal data policies, you can access to HKSTP\u2019s Personal Information Collection Statement at https://www.hkstp.org/hkstp_web/en/hkstp/personal-information-collection-statement-recruitment\nApplicants not invited for interview within four weeks after application deadline may consider their applications unsuccessful.\u00a0 Personal data of unsuccessful applicants will be retained for a maximum of two years.\u00a0\nwww.hkstp.org", "employment_types": ["Full Time", "Permanent"], "selling_points": ["Challenging job opportunity", "Dynamic, creative and flexible working team", "Attractive remuneration package"], "locations": ["Sheung Wan"], "categories": ["Marketing / Public Relations", "Management", "Marketing - Brand / Product Management", "Public Relations - Event Management"], "post_time": "2022-01-18T01:52:30Z", "salary": {"currency": null, "max": null, "min": null, "period": "monthly", "term": null}, "salary_visible": false, "title_keywords": ["marketing manager"], "responsibilities": ["social media", "any other duties", "data", "budgeting", "quality", "planning", "marketing trend", "plan", "analyse"], "requirements": {"degrees": ["degree", "bachelor"], "majors": ["related disciplines", "marketing", "business administration"], "languages": ["cantonese", "putonghua", "english", "chinese"], "language_level": ["proficient"], "hard_skills": ["goal", "dynamic"], "soft_skills": ["self-motivated", "business sense", "interpersonal", "communication", "dynamic", "thorough", "innovative", "leadership", "driven", "detailed"], "languages_combined": [{"language": "cantonese", "language_level": []}, {"language": "putonghua", "language_level": []}, {"language": "english", "language_level": ["proficient"]}, {"language": "chinese", "language_level": ["proficient"]}]}, "experience_required": {"duration": ["at least 3 years", "10 years"], "field": ["management", "business", "marketing", "relevant experience", "digital", "team"]}}, {"job_id": "100003009054561", "location_code": "hk", "company": "Chinachem Group", "job_title": "Senior Officer - Leasing (Tenant Management & Marketing)", "description": "Who we are:\n\nA-World Consulting (www.a-world.com.hk) is a Hong Kong-based, full-service communication and management consultancy covering Greater China.\u00a0 With affiliates/offices in various cities in Mainland China, we seek to provide creative solutions to clients through the combined networks and resources of a tight team of professionals with creative minds.\n\n\n\nJob Description:\n\n\nBusiness development and/or client servicing\n\nResearch, development and implementation of effective communication strategies and work plans for clients\n\nMonitor the larger environment and industry developments etc. to pre-empt clients of potential issues and opportunities, and provide corresponding solutions and recommendations\n\nAccount management in terms of finances, schedules and deliverables\n\nSupervision of junior staff as appropriate\u00a0\n\nRequirements:\n\nTertiary degree or equivalent in communication/public affairs/journalism\n\nAt least 2 years of experience in PR or related industries for Senior Account Executive and 1 years for Account Executive, preferably with agency background\n\nProven English and Chinese proficiency; fluency in Putonghua preferred\n\nPublic affairs/media/corporate communication experience and good network/relations\n\nExcellent business acumen, leadership and interpersonal skills, if applicable\n\nDetail-minded, proactive and able to work under tight schedule and pressure\n\nA good team player with a can-do spirit\n\nExperience in account management and mentoring junior executives, if applicable\n\n5-day work per week, but work outside normal working hours and days should be expected.\u00a0 Excellent compensation and attractive fringe benefits will be offered to the successful candidate.\u00a0 Interested parties please send full resume with availability and present and expected salary by clicking \"Apply Now\".\n\n\nAll personal data collected will be used for recruitment purpose only.\u00a0 Applicants not hearing from us within 6 months may consider their applications unsuccessful.\u00a0 All personal data supplied will be destroyed after 6 months.", "employment_types": ["Full Time", "Permanent"], "selling_points": ["Tenant Management & Marketing", "Marketing campaign, digital marketing and PR event", "Event management / property leasing and marketing"], "locations": ["Central"], "categories": ["Marketing / Public Relations", "Public Relations - Event Management", "Property / Real Estate", "Others", "Digital Marketing"], "post_time": "2022-01-17T09:59:34Z", "salary": {"currency": null, "max": null, "min": null, "period": "monthly", "term": null}, "salary_visible": false, "title_keywords": ["senior officer"], "responsibilities": [], "requirements": {"degrees": [], "majors": [], "languages": [], "language_level": [], "hard_skills": [], "soft_skills": [], "languages_combined": []}, "experience_required": {"duration": [], "field": []}}, {"job_id": "100003009049514", "location_code": "hk", "company": "Tokyo Chuo Auction Hongkong Company Limited", "job_title": "Marketing and Communication Officer", "description": "Responsibilities:\n\nDefine and articulate a clear branding strategy for our brands;\nIdentify, drive and implement marketing strategic plan, PR events and marketing promotions for strengthening the brand positioning and enhancing brand images;\nAnalyze results from conducted marketing activities and ensure the marketing campaigns are hosted with satisfied business efficiency;\nDevelop strategic partnerships to increase our brands\u2019 exposures;\nBuild on existing, and establish new relationships with media in order to maximize media lineage opportunities and marketing partnership opportunities;\nManage and monitor PR and marketing strategies budget;\nLiaise with principals\n\nQualifications:\n\nIndependent, creative and result-oriented with team management skills;\nEager to try new concept and\nStrong network and connection with press, media, celebrity and agencies;\nExcellent understanding of HK branding and PR and the affordable luxury market;\nProficiency in spoken and written English;\nProven track record in designing and executing successful public relations campaigns at both a local and national (especially PRC, Macau and Singapore) level;\nGood writing and editing skills, as well as event planning experience\n\nBenefits:\n\n5-day work week\nFlex working hours\nMedical insurance & dental care\nPublic Holiday\n12-17 days paid Annual Leave\n5 days Marriage Leave\nBirthday Leave\nStaff purchase discount\n\nInterested parties, please send resume with current and expected salary to \"APPLY NOW\"\u00a0for interview arrangement. (Data collected will be used as recruitment related purpose only.)", "employment_types": ["Full Time", "Permanent"], "selling_points": ["Assist in planning and implementing PR promotions", "Prepare marketing and PR collaterals", "Coordinate advertising campaign"], "locations": ["Central & Western Area"], "categories": ["Marketing / Public Relations", "Marketing - General / Support", "Marketing - Marketing Communication", "Public Relations - Event Management"], "post_time": "2022-01-14T08:47:08Z", "salary": {"currency": null, "max": null, "min": null, "period": "monthly", "term": null}, "salary_visible": false, "title_keywords": ["communication officer"], "responsibilities": ["management", "marketing strategies", "budget", "monitor", "designing", "develop", "executing", "marketing promotions", "marketing campaigns", "plan", "liaise with", "editing", "planning"], "requirements": {"degrees": [], "majors": [], "languages": ["english"], "language_level": ["proficiency"], "hard_skills": [], "soft_skills": ["independent", "clear", "articulate", "creative", "result-oriented"], "languages_combined": [{"language": "english", "language_level": ["proficiency"]}]}, "experience_required": {"duration": [], "field": ["editing", "writing", "planning"]}}, {"job_id": "100003009054068", "location_code": "hk", "company": "MLC", "job_title": "Investor Relations Assistant  -  Innovative Fashion Design/Manufacturing Leader  (happy culture)", "description": "Responsibilities:\n\nSupport and assist \u00a0in the planning and execution of the marketing and advertising campaigns\nRender quality works in copywriting and translation\u00a0 for marketing materials including press releases, invitations and catalogues\nFoster close working relationship with journalists and editors of international and local media\nCreate and develop contents for social media channels and ensure they are updated accordingly and timely\nConduct market researches and evaluate the effectiveness of all marketing activities\nLogistic support fordifferent events and campaigns\nAssist in ad-hoc projects as assigned\nHandle general clients\u2019 enquiries when necessary during the auction seasons\n\n\nRequirements:\n\n3\u00a0years\u00a0or above\u00a0of\u00a0work experience in press and marketing field\nExperience in translation, copyediting or copywriting will be an advantage, preferably from the field of art\nGood command of both written and spoken Cantonese, Putonghua and English\nExperience in handling different social media accounts\nMulti-tasking skills, attentive to details\u00a0and able to work under pressure\nStrong proficiency with MS Word, Excel,\u00a0PowerPoint\u00a0and Chinese Word Processing\nExcellent time management skills, ability to meet deadlines;\nTravel required when necessary\n\nPersonal data collected will be used for recruitment purpose only\n\nOnly shortlisted candidates will be notified.", "employment_types": ["Full Time", "Permanent"], "selling_points": ["PR events, Business Research & Administration", "Website Update, Executive Speech, Announcement", "Happy Work Place, Multi-Cultural Environment"], "locations": ["Others"], "categories": ["Banking / Finance", "Analyst", "Media & Advertising", "Editorial / Journalism", "Marketing / Public Relations", "Public Relations - Event Management"], "post_time": "2022-01-17T08:17:26Z", "salary": {"currency": null, "max": null, "min": null, "period": "monthly", "term": null}, "salary_visible": false, "title_keywords": ["assistant"], "responsibilities": ["social media", "quality", "logistic support", "develop", "evaluate", "contents", "marketing materials", "ad-hoc projects", "advertising campaigns", "planning"], "requirements": {"degrees": [], "majors": [], "languages": ["cantonese", "putonghua", "english", "chinese"], "language_level": ["proficiency", "good command"], "hard_skills": ["excel", "chinese word processing", "powerpoint", "translation", "ms word"], "soft_skills": ["attentive to details", "time management skills", "multi-tasking skills", "meet deadlines", "work under pressure"], "languages_combined": [{"language": "cantonese", "language_level": ["good command"]}, {"language": "putonghua", "language_level": ["good command"]}, {"language": "english", "language_level": ["good command"]}, {"language": "chinese", "language_level": ["proficiency"]}]}, "experience_required": {"duration": ["3 years"], "field": ["copywriting", "social media", "marketing"]}}, {"job_id": "100003009050091", "location_code": "hk", "company": "Hays", "job_title": "Head of Event", "description": "Working in a design driven, innovation & dynamic, and fast growing environment, you will support the Investor Relations Director on the full spectrum of investor relations functions for the organization, a top Innovative Design Manufacturer,\u00a0 relying on core technologies, innovative, research & development, and production capabilities to develop and\u00a0 produce top quality and creative fashion collections including seamless sports wear, yoga wear, functional body wear and bras, for global fashion brands.\n\nYou will partner with the Investor Relations Director and PR Agencies to organize all\u00a0Investor Relations corporate events including conference calls, meeting requests, and roadshows etc.\u00a0 You will assist in gathering company development information, market research, and industry trend research to develop IR materials, presentations, and communication strategies.\n\nYou will take lead on updating and maintaining company's website, industry news, and investors' database etc.\u00a0\n\nIf you have 1 years of relevant experience in investor relations, have a bachelor's degree in business administration, journalism, or related discipline,\u00a0and have strong communication ability in English and Chinese,\u00a0 then we would like to hear from you.\n\nPlease forward you resume to Ms. Lau of MLC by clicking the \"APPLY NOW\".\u00a0 Alternatively, you are welcome to call Ms. Lau at 27805232 to discuss your interest.\n\nAll data collected will be treated in strictest confidence and used only for recruitment purpose only.", "employment_types": ["Full Time", "Permanent"], "selling_points": ["Listed MNC in medical / pharmaceutical", "Flexible working hours", "Dynamic & Energetic Culture"], "locations": ["Not Specified"], "categories": ["Marketing / Public Relations", "Marketing - Marketing Communication", "Public Relations - Event Management", "Medical Services", "Pharmaceutical"], "post_time": "2022-01-14T09:46:07Z", "salary": {"currency": null, "max": null, "min": null, "period": "monthly", "term": null}, "salary_visible": false, "title_keywords": [], "responsibilities": ["maintaining", "data", "quality", "market research", "presentations", "design", "develop", "communication", "website", "recruitment", "database", "administration"], "requirements": {"degrees": ["degree", "bachelor"], "majors": ["journalism", "business administration"], "languages": ["english", "chinese"], "language_level": [], "hard_skills": ["dynamic", "presentations"], "soft_skills": ["confidence", "innovative", "communication", "dynamic", "creative", "driven"], "languages_combined": [{"language": "english", "language_level": []}, {"language": "chinese", "language_level": []}]}, "experience_required": {"duration": ["1 years"], "field": ["related", "relevant experience", "business administration"]}}, {"job_id": "100003009052541", "location_code": "hk", "company": "NWS Holdings Limited", "job_title": "Officer \u2013 Sustainability", "description": "Managing a team of event managers at various levels on their daily projects' execution and deliveries\n\nYour new company\nYour new company is a leading MNC which specialized in medical conference and education. They are now looking for a Head of Event to manage a team of conference managers. You will be responsible for professional event management services.\n\nYour new role\n\nExecution of Regional/local physical virtual events\nMeet with client to obtain a detailed brief and understanding of requirements\nVenue-searching to meet client expectations\nProvision of proposed venue report, with detailed comparison chart Liaison with hotel regarding contract & arrangements\nPreparation of action plan, including detailed timelines and budget planning\nCommunication with regional & local offices of client company re delegate attendance\nProvision of regular status report to client, including delegate registration Liaison with invited speakers & VIP guests (travel, accommodation, special requirements)\nLiaison with internal editorial, design and production teams to produce event materials (invitations, backdrop, quick-stands, abstract books)\nLiaison with contractors for physical events/technical contractors for virtual events\nOn-site leadership of team, including internal and external briefings\nProvision of budget report upon completion of event\n\n\n\nWhat you'll need to succeed\n\n\nUniversity degree or above\n7 years+ working experience in event management\n5 years' experience in organizing regional and international meetings/conferences\nPreferably with pharmaceutical event background\nExcellent communication and negotiation skills\nExperience in preparation of budget reports\nFlexibility in working hours\nAbility and willingness to travel\n\n\nWhat you need to do now\nIf you're interested in this role, click 'apply now' to forward an up-to-date copy of your CV, or email to Melanie Fung at melanie.fung@hays.com.hk.\nIf this job isn't quite right for you but you are looking for a new position, please contact us for a confidential discussion on your career.", "employment_types": ["Full Time", "Permanent"], "selling_points": ["Bachelor degree in Environmental Science", "2-3 years\u2019 relevant experience", "Strong business acumen"], "locations": ["Central"], "categories": ["Sciences, Lab, R&D", "Environmental Science / Waste Management", "Marketing / Public Relations", "Public Relations - Event Management"], "post_time": "2022-01-17T03:20:52Z", "salary": {"currency": null, "max": null, "min": null, "period": "monthly", "term": null}, "salary_visible": false, "title_keywords": ["officer"], "responsibilities": ["attendance", "budget planning", "management", "budget reports", "budget", "teams", "design", "communication", "conferences", "contact", "plan", "managing a team", "report"], "requirements": {"degrees": ["degree or above"], "majors": [], "languages": [], "language_level": [], "hard_skills": ["briefings"], "soft_skills": ["responsible", "interested in", "communication", "negotiation skills", "leadership", "detailed"], "languages_combined": []}, "experience_required": {"duration": ["5 years"], "field": ["management"]}}, {"job_id": "100003009048034", "location_code": "hk", "company": "Lexis Group Consultancy Limited", "job_title": "Events / Conference Assistant", "description": "The candidate will be a team player to drive various corporate sustainability initiatives across the Group. In this regard, the incumbent is required to:\n\nSupport and drive sustainability development and performance across the Group;\nCollaborate with external parties and subsidiaries to develop and prepare sustainability reports;\nCoordinate group-wide Environmental Management Committee;\nWork with various benchmarking organisations to report and raise awareness of the Group\u2019s sustainability performance;\nPromote and build awareness over sustainability among stakeholders through events and programmes; and\n\nPerform other duties as assigned by the supervisor.\n\nRequirements\n\nBachelor degree holder in Environmental Science/Management or related discipline;\n2 - 3 years\u2019 relevant experience in corporate sustainability, including but not limited to reporting, data management etc;\nSolid understanding of HKEX ESG disclosure requirements and GRI reporting standards;\nExperience in organizing sustainability awareness programs and campaigns\u00a0will be an added advantage;\n\nStrong business acumen to drive sustainability in commercial setting;\nExcellent command of both spoken and written English and Chinese, including Putonghua; and\nResults-driven, mature, organized and meticulous.\nWe offer competitive salary and package for the right candidate. Interested parties please click \"Apply Now\" below to submit your application expected salary and availability.\n\n\nVisit our website at www.nws.com.hk.\n(All information collected will be treated in strict confidence and only be used for recruitment purposes.)", "employment_types": ["Full Time"], "selling_points": ["A famous financial publisher", "Content Research and conference assistant", "1-2 years of work experience"], "locations": ["Others"], "categories": ["Marketing / Public Relations", "Marketing - Brand / Product Management", "Public Relations - Event Management", "Banking / Finance", "Risk Management"], "post_time": "2022-01-14T04:34:02Z", "salary": {"currency": null, "max": null, "min": null, "period": "monthly", "term": null}, "salary_visible": false, "title_keywords": ["assistant"], "responsibilities": ["collaborate with", "reporting", "management", "perform other duties", "data", "external parties", "develop", "coordinate", "reports", "report"], "requirements": {"degrees": ["bachelor degree holder"], "majors": ["environmental science"], "languages": ["putonghua", "english", "chinese"], "language_level": ["excellent"], "hard_skills": ["data management", "acumen"], "soft_skills": ["organized", "meticulous", "mature", "business acumen", "team player", "driven"], "languages_combined": [{"language": "putonghua", "language_level": ["excellent"]}, {"language": "english", "language_level": ["excellent"]}, {"language": "chinese", "language_level": ["excellent"]}]}, "experience_required": {"duration": ["2 - 3 years"], "field": ["management", "relevant experience", "sustainability"]}}, {"job_id": "100003009056117", "location_code": "hk", "company": "Champion Land Properties Limited", "job_title": "Manager (Customer Relations) (Ref: M-CR)", "description": "Who we are:\n\nA-World Consulting (www.a-world.com.hk) is a Hong Kong-based, full-service communication and management consultancy covering Greater China.\u00a0 With affiliates/offices in various cities in Mainland China, we seek to provide creative solutions to clients through the combined networks and resources of a tight team of professionals with creative minds.\n\n\n\nJob Description:\n\n\nBusiness development and/or client servicing\n\nResearch, development and implementation of effective communication strategies and work plans for clients\n\nMonitor the larger environment and industry developments etc. to pre-empt clients of potential issues and opportunities, and provide corresponding solutions and recommendations\n\nAccount management in terms of finances, schedules and deliverables\n\nSupervision of junior staff as appropriate\u00a0\n\nRequirements:\n\nTertiary degree or equivalent in communication/public affairs/journalism\n\nAt least 2 years of experience in PR or related industries for Senior Account Executive and 1 years for Account Executive, preferably with agency background\n\nProven English and Chinese proficiency; fluency in Putonghua preferred\n\nPublic affairs/media/corporate communication experience and good network/relations\n\nExcellent business acumen, leadership and interpersonal skills, if applicable\n\nDetail-minded, proactive and able to work under tight schedule and pressure\n\nA good team player with a can-do spirit\n\nExperience in account management and mentoring junior executives, if applicable\n\n5-day work per week, but work outside normal working hours and days should be expected.\u00a0 Excellent compensation and attractive fringe benefits will be offered to the successful candidate.\u00a0 Interested parties please send full resume with availability and present and expected salary by clicking \"Apply Now\".\n\n\nAll personal data collected will be used for recruitment purpose only.\u00a0 Applicants not hearing from us within 6 months may consider their applications unsuccessful.\u00a0 All personal data supplied will be destroyed after 6 months.", "employment_types": ["Full Time", "Permanent"], "selling_points": [], "locations": ["Not Specified"], "categories": ["Marketing / Public Relations", "Marketing - Marketing Communication", "Public Relations - Event Management", "Others"], "post_time": "2022-01-18T03:21:15Z", "salary": {"currency": null, "max": null, "min": null, "period": "monthly", "term": null}, "salary_visible": false, "title_keywords": ["manager"], "responsibilities": [], "requirements": {"degrees": [], "majors": [], "languages": [], "language_level": [], "hard_skills": [], "soft_skills": [], "languages_combined": []}, "experience_required": {"duration": [], "field": []}}, {"job_id": "100003009052168", "location_code": "hk", "company": "A-World Consulting Limited", "job_title": "Account Executive/ Senior Account Executive", "description": "Responsibilities:\n\nDevise and manage promotional campaigns and projects on Community development\nWork closely with community and welfare NGOs, local shops, volunteers, and schools for a community empowerment project, which aim to enhance the commitment on community work and provide support to the grass-roots families and elderly, as well as to build up the connections between people and community\nAssist in contacting and communicating local NGOs, welfare partners, commercial companies for activities and programs implementation\nAble to develop and complete projects through timely monitoring progress according to priorities and objectives, problem solving, and constantly making appropriate adjustments to plans to reach goals\nPrepare periodic reports, presentation materials, conducting research and drafting correspondence\nMaintain liaison with all levels of administration to coordinate and resolve problems and issues related to administrative matters of internal and external institutions/organizations\nAssist in any ad hoc tasks or projects\n\nRequirements:\n\nHigher Diploma / Associate Degree Holder or above\nWorking experience in event or program management, or related experience in handling funding programs\nRelevant experience preferably in community development would be an advantage\nInterested in serving the local community, including the grass-roots families and elderly\nGood command of written and spoken English and Chinese to meet the demands of project implementation and coordination\nProficient in computer application including MS Word, MS Excel, MS PowerPoint and Chinese word processing; knowledge of Adobe Illustrator would be an advantage\nPossess positive work ethics, strong result orientation, good time management, maturity, resilience and attention to detail and accuracy\nEffective interpersonal skills, and able to work productively with multiple parties\nWilling to work overtime with tight schedule, and occasionally working on Public Holiday is required\n\nInterested parties may apply with resume, stating source of recruitment information, current & expected salary (application without expected salary will not be considered) and availability to:\n\nHuman Resources Department\n\nWofoo Social Enterprises Limited\n\n25/F Wofoo Commercial Building\n\n574-576 Nathan Road\n\nMongkok, Kowloon, Hong Kong\n\nOur website: www.wse.hk\n\n\n\nPersonal data collected will be kept in strict confidence and used for employment-related purpose only.", "employment_types": ["Full Time", "Permanent"], "selling_points": ["5 days work per week", "performance bonus", "Fresh Graduate also welcome"], "locations": ["Sheung Wan"], "categories": ["Media & Advertising", "Editorial / Journalism", "Marketing / Public Relations", "Public Relations - Copy-writing", "Public Relations - Event Management"], "post_time": "2022-01-17T02:19:09Z", "salary": {"currency": null, "max": null, "min": null, "period": "monthly", "term": null}, "salary_visible": false, "title_keywords": ["account executive", "senior account executive"], "responsibilities": ["provide support", "monitoring", "ad hoc tasks", "implementation", "develop", "coordinate", "maintain", "reports", "plans", "administration"], "requirements": {"degrees": ["associate degree", "diploma"], "majors": [], "languages": ["english", "chinese"], "language_level": ["good command", "proficient"], "hard_skills": ["chinese word processing", "grass", "adobe illustrator", "ms excel", "ms powerpoint", "ms word"], "soft_skills": ["work overtime", "interested in", "interpersonal skills", "coordination", "attention to detail", "time management", "positive"], "languages_combined": [{"language": "english", "language_level": ["good command"]}, {"language": "chinese", "language_level": ["good command", "proficient"]}]}, "experience_required": {"duration": [], "field": ["related", "development", "management", "relevant experience"]}}, {"job_id": "100003009045611", "location_code": "hk", "company": "Wofoo Social Enterprises Limited", "job_title": "Project Executive / Assistant Project Executive", "description": "Requirements:\n\n\nBachelor\u2019s degree preferably in communications / marketing or related disciplines\nMinimum 10 years' solid experience in mall promotions / marketing in property developers\nProven English and Chinese proficiency\nGood in digital marketing and media relations with strong market sense\nExcellent interpersonal and leadership skills\nAble to meet tight deadlines and work in a fast-paced and pressurized environment\nWilling to work long hours and during holidays occasionally\n\nResponsibilities:\n\n\nPlan and oversee promotion and advertising activities of shopping malls\nDevelop overall marketing strategy of shopping malls\nPlan and implement digital marketing campaigns\nLiaise and maintain good relationship with tenants and agencies in promoting shopping malls\nWork with internal stakeholders to support group loyalty program\n\nGood remuneration and attractive fringe benefits will be offered to the successful applicant. Interested parties please apply with full resume, present and expected salary, available date by clicking \"Apply Now\".\n\nWe are an equal opportunity employer and welcome applications from all qualified candidates. All personal data collected will be used for recruitment purpose only.\u00a0 Applicants not hearing from us within 3 months may consider their applications unsuccessful.\u00a0 All personal data collected will be destroyed within 24 months.", "employment_types": ["Full Time", "Permanent"], "selling_points": [], "locations": ["Mong Kok"], "categories": ["Marketing / Public Relations", "Marketing - General / Support", "Public Relations - Event Management", "Public / Civil", "Social Services - Community / Non-profit Organization"], "post_time": "2022-01-13T08:11:58Z", "salary": {"currency": null, "max": null, "min": null, "period": "monthly", "term": null}, "salary_visible": false, "title_keywords": ["project executive", "assistant"], "responsibilities": ["liaise", "advertising", "digital marketing campaigns", "develop", "maintain good relationship", "plan"], "requirements": {"degrees": ["degree", "bachelor"], "majors": ["related disciplines", "marketing", "communications"], "languages": ["english", "chinese"], "language_level": ["proficiency"], "hard_skills": [], "soft_skills": ["strong market sense", "leadership skills", "interpersonal", "meet tight deadlines"], "languages_combined": [{"language": "english", "language_level": ["proficiency"]}, {"language": "chinese", "language_level": ["proficiency"]}]}, "experience_required": {"duration": ["minimum 10 years"], "field": ["property developers", "marketing"]}}, {"job_id": "100003009054939", "location_code": "hk", "company": "Sun Hung Kai Properties Ltd", "job_title": "SENIOR PROMOTIONS MANAGER \u2013 SHOPPING MALL", "description": "Responsible for corporate affairs and corporate communication matters, including:\n\nPlan and organise FHKI's flagship events, such as large-scale dinners, award recognition schemes or high-level forums etc.;\nPlan and implement corporate initiatives, such as, large-scale publicity campaigns and collaboration programmes;\nPrepare promotional materials, manage websites and social media platforms;\nHandle media enquiries;\nAssist in preparing speeches, consultation papers and responses;\nProvide secretariat support to designated functional committees, including, preparation of meeting documents and presentation materials etc.;\nProvide support to other duties as assigned.\n\nJob Requirement\n\nDegree holder in related disciplines, preferably in journalism, communication, public relations, language or social sciences;\nMinimum 6 years of relevant work experience in communications and public affairs, preferably gained from sizable or public organisations; established local media network is a definite advantage;\nExcellent command of written English and Chinese; Experience in digital content development and multimedia production is a plus;\nStrong sense in local and global economic policy and industrial development;\nA mature, self-motivated team player with excellent organisational skills and is able to perform under pressure and tight timeline;\nWilling to work outside office hours as and when necessary;\nImmediate availability is preferred;\nCandidates with less experience may be considered for Senior Officer, Corporate Communication;\nCandidates who can provide a recent English write-up or publication for reference will be considered favourably.\n\nApplication Methods\n\nInterested parties, please send your resume\u00a0(present/last and expected salary)\u00a0with\u00a0applied position\u00a0through the \"APPLY NOW\" button or by post to Human Resources Division, Federation of Hong Kong Industries, 31/F Billion Plaza, 8 Cheung Yue Street, Cheung Sha Wan, Kowloon;\n\nWe are equal opportunity employer. Personal data collected will be treated in strictest confidence and handled confidentially by authorized personnel for recruitment-related purposes only. Candidates not notified within 8 weeks may consider their application unsuccessful.", "employment_types": ["Full Time", "Permanent"], "selling_points": ["Plan & oversee promotion activities of malls", "Develop marketing strategy of malls", "Implement digital marketing campaigns"], "locations": ["Wan Chai"], "categories": ["Marketing / Public Relations", "Marketing - Marketing Communication", "Public Relations - Event Management", "Digital Marketing"], "post_time": "2022-01-17T14:29:22Z", "salary": {"currency": null, "max": null, "min": null, "period": null, "term": null}, "salary_visible": false, "title_keywords": ["manager"], "responsibilities": ["provide support", "other duties", "social media platforms", "communication", "promotional materials", "plan", "publication"], "requirements": {"degrees": ["degree holder"], "majors": ["related disciplines", "journalism", "social sciences"], "languages": ["english", "chinese"], "language_level": ["excellent"], "hard_skills": ["plus", "multimedia"], "soft_skills": ["self-motivated", "under pressure", "responsible", "mature", "communication", "organisational skills", "team player", "presentation"], "languages_combined": [{"language": "english", "language_level": ["excellent"]}, {"language": "chinese", "language_level": ["excellent"]}]}, "experience_required": {"duration": ["minimum 6 years"], "field": ["digital content", "development", "corporate communication"]}}, {"job_id": "100003009052144", "location_code": "hk", "company": "Federation of Hong Kong Industries", "job_title": "Assistant Manager / Senior Officer, Corporate Communication (Ref: PRCD/AM/CC)", "description": "Who we are:\n\nA-World Consulting (www.a-world.com.hk) is a Hong Kong-based, full-service communication and management consultancy covering Greater China.\u00a0 With affiliates/offices in various cities in Mainland China, we seek to provide creative solutions to clients through the combined networks and resources of a tight team of professionals with creative minds.\n\n\n\nJob Description:\n\n\nBusiness development and/or client servicing\n\nResearch, development and implementation of effective communication strategies and work plans for clients\n\nMonitor the larger environment and industry developments etc. to pre-empt clients of potential issues and opportunities, and provide corresponding solutions and recommendations\n\nAccount management in terms of finances, schedules and deliverables\n\nSupervision of junior staff as appropriate\u00a0\n\nRequirements:\n\nTertiary degree or equivalent in communication/public affairs/journalism\n\nAt least 2 years of experience in PR or related industries for Senior Account Executive and 1 years for Account Executive, preferably with agency background\n\nProven English and Chinese proficiency; fluency in Putonghua preferred\n\nPublic affairs/media/corporate communication experience and good network/relations\n\nExcellent business acumen, leadership and interpersonal skills, if applicable\n\nDetail-minded, proactive and able to work under tight schedule and pressure\n\nA good team player with a can-do spirit\n\nExperience in account management and mentoring junior executives, if applicable\n\n5-day work per week, but work outside normal working hours and days should be expected.\u00a0 Excellent compensation and attractive fringe benefits will be offered to the successful candidate.\u00a0 Interested parties please send full resume with availability and present and expected salary by clicking \"Apply Now\".\n\n\nAll personal data collected will be used for recruitment purpose only.\u00a0 Applicants not hearing from us within 6 months may consider their applications unsuccessful.\u00a0 All personal data supplied will be destroyed after 6 months.", "employment_types": ["Full Time"], "selling_points": ["Corporate Communication", "Corporate Affairs", "5 day work week"], "locations": ["Cheung Sha Wan"], "categories": ["Marketing / Public Relations", "Marketing - General / Support", "Public Relations - Event Management"], "post_time": "2022-01-17T03:33:49Z", "salary": {"currency": null, "max": null, "min": null, "period": "monthly", "term": null}, "salary_visible": false, "title_keywords": ["assistant manager", "senior officer"], "responsibilities": [], "requirements": {"degrees": [], "majors": [], "languages": [], "language_level": [], "hard_skills": [], "soft_skills": [], "languages_combined": []}, "experience_required": {"duration": [], "field": []}}, {"job_id": "100003009052169", "location_code": "hk", "company": "A-World Consulting Limited", "job_title": "Senior Account Executive", "description": "\u8077\u8cac\uff1a\n\n\u7b56\u5283\u53ca\u63a8\u884c\u9752\u5c11\u5e74\u53ca\u89aa\u5b50\u6d3b\u52d5\uff1b\n\u63a8\u5ee3\u5347\u639b\u570b\u65d7\u6587\u5316\u7b49\u570b\u6c11\u6559\u80b2\u6d3b\u52d5\uff1b\n\u57f7\u884c\u57f9\u80b2\u9752\u5c11\u5e74\u6b63\u5411\u50f9\u503c\u7684\u6d3b\u52d5\uff1b\n\u5076\u7136\u8981\u5ba4\u5916\u5de5\u4f5c\uff0c\u80fd\u517c\u4efb\u5347\u65d7\u79ae\u5c0e\u5e2b\u512a\u5148\u8003\u616e\uff1b\n\n\u8cc7\u6b77\uff1a\n\n\n\u8a8d\u540c\u672c\u6703\u5b97\u65e8\uff1b\n\u6a02\u65bc\u63a5\u89f8\u9752\u5c11\u5e74\uff1b\n\u5927\u5c08\u6216\u5927\u5b78\u7a0b\u5ea6\uff1b\n\u80fd\u807d\u8b1b\u8b80\u5beb\u7cb5\u8a9e\u3001\u666e\u901a\u8a71\u53ca\u82f1\u8a9e\uff1b\n\n\u6709\u610f\u61c9\u5fb5\u8077\u4f4d\u8005\uff0c\u8acb\u6309\"Apply Now\"\u63d0\u4ea4\u5c65\u6b77\u8868\u53ca\u671f\u671b\u85aa\u916c\u3002\n\n\u5982\u6709\u67e5\u8a62\uff0c\u53ef\u96fb\u90f5\u81f3\u672c\u6703\u3002", "employment_types": ["Full Time", "Permanent"], "selling_points": ["5 days work per week", "performance bonus", "Fresh Graduate also welcome"], "locations": ["Sheung Wan"], "categories": ["Media & Advertising", "Editorial / Journalism", "Marketing / Public Relations", "Public Relations - Copy-writing", "Public Relations - Event Management"], "post_time": "2022-01-17T02:19:40Z", "salary": {"currency": null, "max": null, "min": null, "period": "monthly", "term": null}, "salary_visible": false, "title_keywords": ["senior account executive"], "responsibilities": [], "requirements": {"degrees": [], "majors": [], "languages": [], "language_level": [], "hard_skills": [], "soft_skills": [], "languages_combined": []}, "experience_required": {"duration": [], "field": []}}, {"job_id": "100003009048589", "location_code": "hk", "company": "Association of Hong Kong Flag-Guards Limited", "job_title": "\u6d3b\u52d5\u7d71\u7c4c\u54e1(Project Coordinator)", "description": "Main Purpose of The Job\n\nThe job holder should be able to translate concepts into easily understandable and appealing marketing materials, whilst managing multiple projects with.\n\nJob Descriptions:\u00a0 \u00a0 \u00a0 \u00a0 \u00a0 \u00a0\nSupport content marketing initiatives through the creation of bespoke and audience-driven content across a variety of channels, including the corporate website, social media, email, events, videos and webinars\nDevelop and coordinate day-to-day content marketing deliverables\u00a0\nDevelop new and curating existing content for use across multiple marketing channels, with a particular focus on digital content creation and amplification.\nAct as a content marketing subject matter expert, consulting with fellow marketers and internal stakeholders\nRequirements:\n\nBachelor's degree in marketing, communications, journalism or a similar field\nAt least 2-3 years of experience in content marketing within financial services or other B2B industries, though aptitude & quality of written content is valued more than years of experience.\nExcellent writing, communication and editorial skills\nDigital savvy, with proven experience in prior content and research marketing role\nSolid experience with digital marketing, including digital advertising, SEO and social media\nSignificant experience with content project management including planning, organizing, and executing content-focused initiatives, publications, and multi-platform editorial calendars\nExperience with video development and website content management will be a PLUS\nFluency in English and Chinese (both spoken and written)\nWe Offer:\n5-day work\nAttractive monthly basic salary and annual performance bonus\nComprehensive fringe benefits including but not limited to\n16 working days annual leave up to 24 days depending on years of services\nFamily care leave, maternity and paternity leave, birthday leave, etc.\nFree life and health insurance including both in and out-patient benefits\nPension benefits on top of MPF mandatory contribution\nAdequate training and good allowance\nJoin the GM Winning Team today!\nReady to fly high in your career? Interested parties please submit your full resume with availability, current and expected salary by e-mail via clicking \u201cApply Now\u201d.\u00a0 Written test as well as aptitude test will be conducted with shortlisted candidates.\nAll personal data provided by job applicants are used only for recruitment purpose and will be treated in strict confidential. Unsuccessful applications will be properly disposed within 3 months.", "employment_types": ["Full Time"], "selling_points": ["\u6d3b\u52d5\u7d71\u7c4c\u54e1(Project Coordinator)", "\u8ca0\u8cac\u7d71\u7c4c\u76f8\u95dc\u8ab2\u7a0b\u53ca\u6d3b\u52d5", "\u5982\u6709\u67e5\u8a62\uff0c\u53ef\u96fb\u90f5\u81f3\u672c\u6703\u3002"], "locations": ["Not Specified"], "categories": ["Marketing / Public Relations", "Public Relations - Event Management", "Public / Civil", "Social Services - Community / Non-profit Organization"], "post_time": "2022-01-14T06:51:44Z", "salary": {"currency": null, "max": null, "min": null, "period": "monthly", "term": null}, "salary_visible": false, "title_keywords": ["coordinator"], "responsibilities": ["social media", "consulting", "website", "subject matter expert", "develop", "coordinate", "marketing materials", "multiple projects"], "requirements": {"degrees": ["degree", "bachelor"], "majors": ["journalism", "marketing", "communications"], "languages": ["english", "chinese"], "language_level": ["fluency"], "hard_skills": ["project management", "plus", "seo"], "soft_skills": ["communication", "project management", "focused"], "languages_combined": [{"language": "english", "language_level": ["fluency"]}, {"language": "chinese", "language_level": ["fluency"]}]}, "experience_required": {"duration": ["at least 2-3 years"], "field": ["social media", "management", "research", "advertising", "video", "development", "project management", "editorial", "marketing", "digital marketing", "financial services", "digital", "planning"]}}, {"job_id": "100003009053968", "location_code": "hk", "company": "Gain Miles Assurance Consultants Limited", "job_title": "Assistant Manager \u2013 Content Marketing", "description": "\u00a0Ref. No.: JDB/HLD11/CCO\n\nDegree in\u00a0Public Relations, Journalism, Marketing / Digital Marketing, English / Chinese Language or related disciplines\nMinimum 2 years'experience in Public Relations, media, or digital / marketing communications in a sizable organization or consultancy\nRelevant working experience in corporate communications includingmedia / stakeholder relations,CSR,events management, copy writing and translation, collateral / video production\nProficiency in MS office including Word, Excel, PowerPoint, and Photoshop\nInternet and social media savvy\nRelevant experience in marketing / digital marketing, website and social media management will be considered a merit\nVery strong English and Chinese language skills and fluency in Putonghua\nAttractive salary and fringe benefits will be offered to the successful candidates. Please apply with full resume by mail to\u00a0Human Resources Department, Henderson Land Development Co. Ltd., 71/F, Two International Finance Centre, 8 Finance Street, Central, Hong Kong\u00a0or by fax at\u00a02905 1855\u00a0or visit our homepage at\u00a0http://www.hld.com\u00a0or\u00a0by clicking \"Apply Now\".\n(Please quote the ref. no. on letter)\u00a0\n\nPersonal data provided by job applicants will be used for recruitment purpose only.", "employment_types": ["Full Time", "Permanent"], "selling_points": ["Content marketing", "financial service", "marketing channels"], "locations": ["Not Specified"], "categories": ["Marketing / Public Relations", "Marketing - Direct Marketing", "Public Relations - Event Management", "Others"], "post_time": "2022-01-17T07:51:55Z", "salary": {"currency": null, "max": null, "min": null, "period": "monthly", "term": null}, "salary_visible": false, "title_keywords": ["assistant manager"], "responsibilities": ["social media", "management", "video production", "website", "digital marketing"], "requirements": {"degrees": ["degree"], "majors": ["journalism", "related disciplines", "marketing", "digital marketing"], "languages": ["putonghua", "english", "chinese"], "language_level": ["fluency"], "hard_skills": ["excel", "no", "word", "powerpoint", "photoshop", "translation", "ms office"], "soft_skills": [], "languages_combined": [{"language": "putonghua", "language_level": ["fluency"]}, {"language": "english", "language_level": ["fluency"]}, {"language": "chinese", "language_level": []}]}, "experience_required": {"duration": [], "field": ["social media", "management", "video production", "relevant working experience", "marketing", "relevant experience", "writing", "digital marketing"]}}, {"job_id": "100003009050256", "location_code": "hk", "company": "Henderson Land Development Company Limited", "job_title": "CORPORATE COMMUNICATIONS OFFICER", "description": "Established in 2009, Hong Kong Green Building Council (\u201cthe Council\u201d) is the leading body, co-founded by four major construction industry and environmental organisations, driving the market transformation towards green and sustainable buildings in Hong Kong through engagement with the industry, the government and broader community.\nHKGBC is expanding its secretariat team in line with its positioning as Hong Kong's leading member-based body dedicated to green building development, with opening for the post of Project Executive:\nKey Roles:\nReport to the Head of Marketing, Project Manager and Senior Project Executive;\nCoordinate with internal departments, external parties and schools for organising and executing various public education events, trainings, tours and workshops;\nSupport the preparation of promotional materials including videos, training kits, presentation materials, advertorials and proposals for school engagement activities;\nAssist the planning and implementation of online and offline promotional campaigns;\nLiaise with vendors including consultants, PR agencies, production houses, etc. to ensure quality and timeliness of deliverables for events and campaigns;\nSupport all reporting, invoicing and logistics works;\nPerform any other duties as assigned.\n\u00a0Requirements:\nBachelor\u2019s degree holder in Communications, Marketing, Public Relations or related disciplines with minimum 2 years relevant working experience.\nExcellent command of both written and spoken English and Cantonese. Fluency in Mandarin would be an advantage;\nGrade C or above in Use of English in HKALE and Grade C (Syl. B) / Level 4 or above in English in HKCEE or Grade 5 or above in English in DSE would be an asset\nDetailed-mined, versatile and naturally outgoing with strong communication skills\nAbility to work both independently and collaboratively with the team;\nSelf-motivated with a strong sense of responsibility and able to work under pressure;\nProficient in PC applications including MS Office, Chinese word processing and database management;\nKnowledge of Adobe Photoshop, Illustrator and Dreamweaver would be an advantage.\u00a0\u00a0\n\u00a0How to Apply\nThe Council is an equal opportunity employer and offers attractive career prospects and remuneration to our staff. Recruitment will be initially under contract terms from commencement date to 30 June 2023. Interested applicants please apply by sending\u00a0full resume with date of availability, present and expected salary, contact telephone number, as well as results of public examinations\u00a0to the\u00a0Executive Director, Hong Kong Green Building Council\u00a0via e-mail\u00a0careers@ hkgbc.org.hk, or by post to\u00a01/F, Jockey Club Environmental Building, 77 Tat Chee Avenue, Kowloon Tong, Hong Kong. Please state the position you want to apply for on the envelope.\n(N.B. Application with incomplete information as requested above may not be considered.)\nApplicants who do not receive a response within six weeks from the date of this advertisement may consider their applications filed for future reference. Personal data will be used strictly for recruitment related purposes only and retained for no more than six months.", "employment_types": ["Full Time", "Permanent"], "selling_points": ["Medical Allowance", "Education Allowance", "Free Lunch"], "locations": ["Central"], "categories": ["Marketing / Public Relations", "Marketing - Marketing Communication", "Public Relations - Event Management", "Public Relations - General / Support"], "post_time": "2022-01-14T10:02:41Z", "salary": {"currency": null, "max": null, "min": null, "period": "monthly", "term": null}, "salary_visible": false, "title_keywords": ["corporate communications officer"], "responsibilities": ["any other duties", "external parties", "quality", "communication", "promotional materials", "database", "liaise with", "personal data", "work under pressure", "implementation", "logistics", "report", "reporting", "management", "coordinate with", "executing", "contact", "invoicing", "recruitment", "planning"], "requirements": {"degrees": ["bachelor", "dse", "degree holder"], "majors": ["related disciplines", "marketing", "communications"], "languages": ["cantonese", "english", "chinese", "mandarin"], "language_level": ["fluency", "advantage", "excellent", "proficient"], "hard_skills": ["no", "chinese word processing", "adobe photoshop", "illustrator", "pc applications", "c", "dreamweaver", "workshops", "ms office"], "soft_skills": ["outgoing", "communication skills", "self-motivated", "independently", "sense of responsibility", "work under pressure", "versatile", "presentation", "detailed"], "languages_combined": [{"language": "cantonese", "language_level": ["excellent"]}, {"language": "english", "language_level": ["excellent"]}, {"language": "chinese", "language_level": ["proficient"]}, {"language": "mandarin", "language_level": ["fluency", "advantage"]}]}, "experience_required": {"duration": ["minimum 2 years"], "field": ["related", "public relations", "marketing", "relevant working experience"]}}, {"job_id": "100003009050550", "location_code": "hk", "company": "Hong Kong Green Building Council Limited", "job_title": "Project Executive", "description": "Responsibilities:\n\n\nCopy-write and edit marketing brochures, executive speeches, statements to media and press releases;\nPrint & produce of all event-related materials such as brochures, flyers, preview, posters, catalogue and post-show reports, e-newsflash, e-flyer, e-card;\nDevelop and execute advertising planning, media buying and advertisement production;\nResponsible for media relations and organization of press conferences;\nProvide onsite media support such as exhibitor and visitor interview, media tour, photography and videography, executive interview;\nArrange incentive trips for foreign journalists to Hong Kong and China.\n\nRequirements:\n\nDegree holder in any disciplines, preferably in Public Relations or Communications;\nAt least 3 years' relevant experience in Public Relations or Marketing Communications, preferably with strong contacts to media in Hong Kong;\nEnglish native speaker is an advantage;\nAble to interact positively and effectively with employees at all levels within the organization, as well as customers, prospects, and vendors;\nA good team player with strong organizational skill and capable of working under pressure;\nDetail-minded and results oriented;\nExcellent media relations and copy-writing skills are preferable;\nGood command of both written and spoken English and Mandarin and Cantonese;\nKnowledgeable in Microsoft Office, Chinese Word Processing;\nWilling to travel overseas;\nCandidates with lesser experience will be considered as a position of Assistant Public Relations Officer.\n\n\u00a0We work 5 days per week\nWe offer long-term career development opportunities, attractive remuneration package and fringe benefits including 5-day work, group life and medical insurance to right candidates. Interested parties please send full resume stating our reference number, present and expected salary to\u00a0HR @hongkong.messefrankfurt.com or fax to 2511-5112. \u00a0\n\nMesse Frankfurt (HK) Ltd. is an equal opportunity employer and is awarded the Good MPF Employer Award. Information provided will be treated in strict confidence and only be used for recruitment purpose. Candidates not invited for interview within 4 weeks may consider their application unsuccessful. However, we will retain the applications for a maximum period of 6 months and may refer them to suitable openings.", "employment_types": ["Full Time", "Contract"], "selling_points": [], "locations": ["Kowloon City Area"], "categories": ["Marketing / Public Relations", "Marketing - Marketing Communication", "Public Relations - Event Management", "Public Relations - General / Support"], "post_time": "2022-01-14T10:41:32Z", "salary": {"currency": null, "max": null, "min": null, "period": "monthly", "term": null}, "salary_visible": false, "title_keywords": ["project executive"], "responsibilities": ["advertising", "develop", "conferences", "reports", "catalogue", "planning"], "requirements": {"degrees": ["degree holder"], "majors": ["any disciplines", "communications"], "languages": ["cantonese", "english", "chinese", "mandarin"], "language_level": ["native", "good command", "advantage"], "hard_skills": ["chinese word processing", "writing skills", "microsoft office"], "soft_skills": ["detail-minded", "good team player", "under pressure", "organizational skill", "capable", "writing skills"], "languages_combined": [{"language": "cantonese", "language_level": ["good command"]}, {"language": "english", "language_level": ["native", "good command", "advantage"]}, {"language": "chinese", "language_level": []}, {"language": "mandarin", "language_level": ["good command"]}]}, "experience_required": {"duration": ["at least 3 years"], "field": ["marketing communications", "public relations", "relevant experience", "media"]}}, {"job_id": "100003009054077", "location_code": "hk", "company": "Messe Frankfurt (HK) Ltd", "job_title": "Public Relations Officer", "description": "\u8077\u8cac\uff1a\n\n\u4e3b\u8981\u8ca0\u8cac\u958b\u5c55\u3001\u7c4c\u5283\u53ca\u63a8\u52d5\u8207\u4fc3\u9032\u52de\u5de5\u653f\u7b56\u767c\u5c55\u76f8\u95dc\u7684\u6d3b\u52d5\u5de5\u4f5c\n\u7814\u7a76\u53ca\u5021\u8b70\u8207\u52de\u5de5\u6b0a\u76ca\u4e8b\u52d9\u76f8\u95dc\u7684\u653f\u7b56\n\u652f\u63f4\u59d4\u54e1\u6703\u7684\u65e5\u5e38\u4e8b\u52d9\uff0c\u4ee5\u53ca\u884c\u653f\u7d71\u7c4c\u548c\u806f\u7d61\u5354\u8abf\u5de5\u4f5c\n\n\u8981\u6c42\uff1a\n\n\u5927\u5b78\u7562\u696d\u6216\u4ee5\u4e0a\u7a0b\u5ea6\n\u51772\u5e74\u6216\u4ee5\u4e0a\u76f8\u95dc\u5de5\u4f5c\u7d93\u9a57\uff0c\u719f\u6089\u96fb\u8166\u6587\u66f8\u64cd\u4f5c\n\u826f\u597d\u7684\u4e2d\u82f1\u6587\u66f8\u5beb\u548c\u8868\u9054\u80fd\u529b\n\u5177\u793e\u4ea4\u5a92\u9ad4\u61c9\u7528\u548c\u7ba1\u7406\u7d93\u9a57\uff0c\u53ca\u7565\u61c2\u7c21\u55ae\u8a2d\u8a08\u8edf\u4ef6\u512a\u5148\n\u6210\u719f\u4e3b\u52d5\uff0c\u8f03\u5f37\u7684\u7d44\u7e54\u548c\u7b56\u5283\u6d3b\u52d5\u7684\u80fd\u529b\uff0c\u5584\u65bc\u6e9d\u901a\u548c\u5354\u8abf\uff0c\u8655\u4e8b\u7368\u7acb\uff0c\u65b0\u805e\u89f8\u89ba\u654f\u92b3\uff0c\u6709\u8cac\u4efb\u611f\u8207\u5de5\u4f5c\u9b44\u529b\n\n\u6709\u610f\u8005\u8acb\u628a\u6c42\u8077\u4fe1\u3001\u500b\u4eba\u5c65\u6b77\u3001\u8981\u6c42\u5f85\u9047\u5bc4\u300c\u4e5d\u9f8d\u571f\u74dc\u7063\u99ac\u5751\u6d8c\u905312\u865f3\u6a13\u300d\u5de5\u806f\u6703\u79d8\u66f8\u8655\u4eba\u529b\u8cc7\u6e90\u90e8\u6536\uff0c\u6216\u96fb\u90f5\u81f3\"Apply Now\"\u3002\u8acb\u65bc\u4fe1\u5c01\u9762\u6216\u96fb\u90f5\u4e3b\u65e8\u8a3b\u660e\u61c9\u5fb5\u7684\u8077\u4f4d\u548c\u7de8\u865f\u3002\n\n(\u7533\u8acb\u4eba\u6240\u63d0\u4f9b\u7684\u8cc7\u6599\u5c07\u4e88\u4ee5\u4fdd\u5bc6\uff0c\u4e26\u53ea\u4f5c\u62db\u8058\u7528\u9014\u3002)", "employment_types": ["Full Time", "Permanent"], "selling_points": ["Copy-write and edit marketing brochures", "Print & produce of all event-related materials", "Develop and execute advertising planning"], "locations": ["Wan Chai"], "categories": ["Marketing / Public Relations", "Public Relations - Copy-writing", "Public Relations - Event Management", "Public Relations - General / Support"], "post_time": "2022-01-17T08:19:30Z", "salary": {"currency": null, "max": null, "min": null, "period": "monthly", "term": null}, "salary_visible": false, "title_keywords": ["officer"], "responsibilities": [], "requirements": {"degrees": [], "majors": [], "languages": [], "language_level": [], "hard_skills": [], "soft_skills": [], "languages_combined": []}, "experience_required": {"duration": [], "field": []}}, {"job_id": "100003009045456", "location_code": "hk", "company": "The Hong Kong Federation of Trade Unions", "job_title": "\u59d4\u54e1\u6703\u5e79\u4e8b (Committee Event / Policy Officer) (Ref: PAC/210901)", "description": "Our client is an innovative company in organizing exhibitions, they are looking for a Project Executive to join their team to support their business expansion\n\nJob Responsibilities:\n\nInvite new associations / visitors to engage the online and offline activities\nExplore and maintain relation with major associations and visitors\nUpdate changing purchasing needs and market trends\nOrganize online and offline events, including webinar and business matching\nCoordinate with associations and other third parties\nOrganize and implement the promotion campaigns and events\nProvide onsite services to the visitors with other departments and vendors\n\nJob Requirements:\n\nDegree in Marketing / Event Management or related disciplines\nMinimum 1 year event management experience\nFluent in spoken and written English, Cantonese and Mandarin\nA good team player with excellent communication and interpersonal skills\n\n\nIf you're interested in this role, please CLICK HERE or click 'Apply Now' to apply the position via Adecco website with your CV, or if you would like to have a further discussion about this role, please contact Mr. Mok on +852 2899 6180.\nPlease note that only short-listed candidates will be notified. All information gathered will be treated in strict confidence and solely used for recruitment purposes", "employment_types": ["Full Time"], "selling_points": [], "locations": ["To Kwa Wan"], "categories": ["Media & Advertising", "Strategic Planning", "Marketing / Public Relations", "Public Relations - Event Management", "Public / Civil", "Social Services - Community / Non-profit Organization"], "post_time": "2022-01-13T07:53:33Z", "salary": {"currency": null, "max": null, "min": null, "period": "monthly", "term": null}, "salary_visible": false, "title_keywords": ["\u59d4\u54e1\u6703\u5e79\u4e8b", "officer"], "responsibilities": ["promotion campaigns", "maintain", "coordinate with"], "requirements": {"degrees": ["degree"], "majors": ["related disciplines", "marketing"], "languages": ["cantonese", "english", "mandarin"], "language_level": ["fluent"], "hard_skills": [], "soft_skills": ["interested in", "good team player", "communication and interpersonal skills", "confidence"], "languages_combined": [{"language": "cantonese", "language_level": ["fluent"]}, {"language": "english", "language_level": ["fluent"]}, {"language": "mandarin", "language_level": ["fluent"]}]}, "experience_required": {"duration": ["minimum 1 year"], "field": ["management"]}}, {"job_id": "100003009050954", "location_code": "hk", "company": "ADECCO", "job_title": "Project Executive \u2013 Marketing Communication", "description": "Responsibilities:\n\nResponsible for project management to present positive and professional parenting knowledge to the public, as well as delivering charitable programs in early childhood development and care, healthcare and environment\nPlan, execute, supervise and evaluate charitable programs\nOrganise education programs, symposium and publicity events\nDevelop internal & external communication collaterals to promote positive parenting\nInitiate and assess funding applications\nHandle ad hoc duties assignment by management\n\nRequirements:\n\nDegree holder in Social Work, Education, Public Health, Public Administration or other related disciplines\nAt least 8 years of work experience in NGO sector, preferably for children / healthcare / environment related services\nExperience with NGO is preferred\nUnderstanding the latest trends and global best practices of philanthropy\nExperience in negotiating partnerships with multiple stakeholders with diverse interests is preferred\nOutgoing, proactive, analytical, independent, multi-tasking, attentive to detail and well-organized.\nExcellent command of written and spoken English, Cantonese and Putonghua\n\nSalary and benefits will be commensurate with qualifications and experience. \u00a0Interested parties, please send a full resume with present and expected salary, and date available to The Human Resources Department, 3/F., Great Eagle Centre, 23 Harbour Road, Wanchai, Hong Kong or e-mail to us.\u00a0\u00a0(Please quote the reference no. on the envelope and the covering letter.)\n\nTo know more about us, please visit our website at http://babyparent.org.\n\nWe are an equal opportunity employer and welcome applications from all qualified candidates.Personal data collected will be treated in strict confidence and used only for recruitment-related purpose. Applicants who have not heard from us within four weeks may consider their applications unsuccessful. All personal data will be destroyed after 12 months.", "employment_types": ["Full Time", "Permanent"], "selling_points": [], "locations": ["North Point"], "categories": ["Marketing / Public Relations", "Management", "Marketing - Brand / Product Management", "Public Relations - Event Management"], "post_time": "2022-01-14T12:00:48Z", "salary": {"currency": null, "max": null, "min": null, "period": "monthly", "term": null}, "salary_visible": false, "title_keywords": ["project executive"], "responsibilities": ["ad hoc duties", "management", "develop", "evaluate", "project management", "communication", "plan"], "requirements": {"degrees": ["degree holder"], "majors": ["social work", "related disciplines", "public health", "public administration"], "languages": ["cantonese", "putonghua", "english"], "language_level": ["excellent"], "hard_skills": [], "soft_skills": ["outgoing", "independent", "attentive to detail", "well-organized", "diverse", "multi-tasking", "proactive"], "languages_combined": [{"language": "cantonese", "language_level": ["excellent"]}, {"language": "putonghua", "language_level": ["excellent"]}, {"language": "english", "language_level": ["excellent"]}]}, "experience_required": {"duration": ["at least 8 years"], "field": ["related", "healthcare"]}}, {"job_id": "100003009051941", "location_code": "hk", "company": "Healthy Seed", "job_title": "Senior Program Manager / Program Manager", "description": "The Job\n\nAdminister revenue driven marketing campaigns with effective advertising/communications strategies to monitor relative results\nManage all the marketing collaterals content and production with relevant departments\nDevelop press release and media pitching, handle media enquiries and relations\nIdentify, explore and work with potential business partners for joint promotion/barter opportunities\nUpdate website and all information portals in timely manner\nHandle administrative works (e.g. issue PR, handle invoice, weekly clipping report etc.) and marketing budget monitoring\nThe Requirement\n\nDegree in Communications, Journalism, Languages, Hospitality or related disciplines\nAt least 4 years' relevant working experience in PR/communications field, experience in hospitality industry is an advantage\nProficient with MS office application\nExcellent command of both written and spoken Chinese and English, proficiency in Putonghua is an advantage\nGood presentation, excellent organizing and planning skills\nFlexible, independent and a good\u00a0team player\nAttractive remuneration would be offered to the right candidates.\n\nPlease send your application with expected salary to Human Resources Manager:\n\nBy WhatsApp: 6388-3034 or\nBy Fax: 2722-5555\n\nPersonal data collected will be used for recruitment purpose only. We are an equal opportunity employer.", "employment_types": ["Full Time", "Permanent"], "selling_points": ["Manage charitable programs and projects", "Promote positive parenting", "NGO sector / fundraising"], "locations": ["Wan Chai"], "categories": ["Marketing / Public Relations", "Public Relations - Event Management", "Public Relations - General / Support"], "post_time": "2022-01-17T01:35:20Z", "salary": {"currency": null, "max": null, "min": null, "period": "monthly", "term": null}, "salary_visible": false, "title_keywords": ["manager"], "responsibilities": ["advertising", "invoice", "marketing collaterals", "monitor", "website", "budget", "develop", "monitoring", "marketing campaigns", "report"], "requirements": {"degrees": ["degree"], "majors": ["journalism", "related disciplines", "hospitality", "communications"], "languages": ["putonghua", "english", "chinese"], "language_level": ["advantage", "excellent", "proficiency"], "hard_skills": ["whatsapp", "ms office"], "soft_skills": ["flexible", "planning skills", "good team player", "independent", "presentation"], "languages_combined": [{"language": "putonghua", "language_level": ["proficiency", "advantage", "excellent"]}, {"language": "english", "language_level": ["advantage", "excellent"]}, {"language": "chinese", "language_level": ["advantage", "excellent"]}]}, "experience_required": {"duration": ["at least 4 years"], "field": ["hospitality industry", "pr", "relevant working experience"]}}, {"job_id": "100003009051309", "location_code": "hk", "company": "Miramar Hotel and Investment Company, Limited", "job_title": "Assistant Marketing Manager \u2013 Hotels and Serviced Apartments", "description": "RESEARCH OFFICE\n\nExecutive Officer (PR0256/21-22)\n\nThe Office is looking for a number of meticulous teamplayers. The candidate will perform the following duties:\n\nSupport the University\u2019s research initiatives and enhance its research culture and engagement;\nSupport the development of the interdisciplinary research labs and the hiring of labs\u2019 members;\nDevelop and enhance the existing websites and contribute in various social media platforms and external liaison;\nPromote research-related events/activities, including but not limited to talks, programmes, conferences, tour visits, interviews, symposiums and exhibitions, etc.;\nProvide support in forging industrial/academic partnerships;\nPromote research communication and publicity;\nProvide support in committee work; and\nCarry out ad hoc tasks as assigned.\nApplicants should possess:\n\nA recognised degree in Public Relations & Communications, Language Studies or related disciplines preferred;\nAt least four years of relevant experience;\nAn excellent command of written and spoken English and Chinese (including Putonghua), and relevant editing and multimedia production skills;\nProactivity, maturity, meticulousness, readiness to accept challenges, capability in multitasking and independence at work;\nStrong communication and interpersonal skills, good analytical ability and a strong sense of responsibility;\nAbility to work under tight timelines; and\nProficiency in a wide range of computing applications.\nInitial appointment will be offered on a fixed-term contract of 2 years. Re-appointment thereafter will be subject to mutual agreement.\n\nSalary will be commensurate with qualifications and experience.\n\nApplication Procedure:\n\nApplicants are invited to submit their applications at the HKBU e-Recruitment System (jobs.hkbu.edu.hk). Those not invited for interview 8 weeks after the closing date may consider their applications unsuccessful. Details of the University\u2019s Personal Information Collection Statement can be found at http://hro.hkbu.edu.hk/pics.\n\nThe University reserves the right not to make an appointment for the post advertised, and the appointment will be made according to the terms and conditions then applicable at the time of offer.\n\nClosing date: 27 January 2022", "employment_types": ["Full Time", "Permanent"], "selling_points": [], "locations": ["Tsim Sha Tsui"], "categories": ["Hospitality / F & B", "Hospitality / Hotel Services", "Marketing / Public Relations", "Marketing - Brand / Product Management", "Public Relations - Event Management"], "post_time": "2022-01-15T07:56:09Z", "salary": {"currency": null, "max": null, "min": null, "period": "monthly", "term": null}, "salary_visible": false, "title_keywords": ["assistant marketing manager"], "responsibilities": ["provide support", "social media platforms", "ad hoc tasks", "develop", "communication", "conferences", "recruitment", "committee work", "editing"], "requirements": {"degrees": ["degree"], "majors": ["related disciplines", "communications"], "languages": ["putonghua", "english", "chinese"], "language_level": ["excellent"], "hard_skills": ["make", "multimedia"], "soft_skills": ["communication", "meticulous", "communication and interpersonal skills", "sense of responsibility"], "languages_combined": [{"language": "putonghua", "language_level": ["excellent"]}, {"language": "english", "language_level": ["excellent"]}, {"language": "chinese", "language_level": ["excellent"]}]}, "experience_required": {"duration": ["at least four years"], "field": ["relevant experience"]}}, {"job_id": "100003009048482", "location_code": "hk", "company": "Hong Kong Baptist University", "job_title": "Executive Officer (PR0256/21-22)", "description": "The applicant must possess\na recognised degree in marketing, communication, business administration or other construction related disciplines;\na minimum of 5 years\u2019 post-qualification relevant work experience, preferably in sizeable organisations / education institutions / government departments;\nproficiency in Microsoft application software (including Word, Excel, PowerPoint, etc.) and website management; Chinese word processing is a must;\nexcellent project management and interpersonal skills;\ngood time management skill and ability to work independently under pressure; and\ngood command of both written and spoken English and Chinese.\n(Applicants who do not possess the required qualifications and / or experience may be considered for other positions within the organisation.)\nDuties include\nto devise strategies, implement and promote various collaboration schemes and Approved Technical Talents Training Programmes;\nto liaise with industry stakeholders on participation in various collaboration schemes / programmes;\nto provide a full range of support and execution of various events and activities such as Graduation Ceremony, Awards and Presentation Ceremony, Lo Pan Dinner, Recruitment Day, Sharing sessions, etc.;\nto monitor Mentorship Programme, Site Practice Scheme, Alumni Affairs, etc.;\nto conduct surveys, research, studies, analyses and compile report for management; and\nto carry out any other duties as assigned from time to time by the Executive Director.\nApplications\nThe position is on a renewable fixed-term contract (subject to performance and operational needs) for a period of 2 years.\nPlease click the below \u201cApply Online\u201d to complete the application form and upload the updated curriculum vitae, the results of English and Chinese Language obtained in public examinations, current and expected salary together with a covering letter stating one\u2019s suitability for the job on or before\u00a028\u00a0January 2022.\nFor further details on HKIC please refer to website: http://www.hkic.edu.hk.", "employment_types": ["Full Time"], "selling_points": ["Support the University\u2019s research initiatives", "Contribute in various social media platforms", "Relevant editing and multimedia production skills"], "locations": ["Kowloon City"], "categories": ["Education", "Others", "Marketing / Public Relations", "Marketing - Marketing Communication", "Public Relations - Event Management"], "post_time": "2022-01-14T06:39:02Z", "salary": {"currency": null, "max": null, "min": null, "period": "monthly", "term": null}, "salary_visible": false, "title_keywords": ["executive officer"], "responsibilities": ["any other duties", "management", "software", "monitor", "website", "communication", "project management", "recruitment", "liaise with", "report", "administration"], "requirements": {"degrees": ["degree"], "majors": ["related disciplines", "marketing", "business administration"], "languages": ["english", "chinese"], "language_level": ["good command"], "hard_skills": ["excel", "chinese word processing", "word", "powerpoint", "scheme", "project management"], "soft_skills": ["work independently", "under pressure", "communication", "project management", "interpersonal skills", "time management skill", "organisation", "presentation"], "languages_combined": [{"language": "english", "language_level": ["good command"]}, {"language": "chinese", "language_level": ["good command"]}]}, "experience_required": {"duration": ["minimum of 5 years"], "field": ["post-qualification", "education"]}}, {"job_id": "100003009050510", "location_code": "hk", "company": "Hong Kong Institute of Construction", "job_title": "Senior Officer \u2013 Collaboration Scheme", "description": "Our client is a global corporate with energy and petrochemicals companies, they are now seeking to hire an experienced Corporate Communication Manager to join their team.\nJob Responsibilities:\nDevelop and implement integrated corporate communication strategy and effective media communications programmes at corporate level\nFormulate corporate communication plans to enhance the organization reputation to sustain the business as a market leader in the industry\nDevelop corporate communications materials including but not limited to press release, newsletter, brochure, digital & social media materials, executives' speeches and presentations, ensure align with business imperatives\nDevise publicity and media plan for various business projects, establish solid media and stakeholder relationship\nAct as project leader to lead major corporate events and prepare press related and corporate materials\nJob Requirements:\n8-10 years experience in corporate communication and media management from sizable organization\nSolid experience in crisis and key stakeholder management is an advantage\nDynamic and strong ability to deal with challenges and changing priorities\nPresentable with excellent communication and interpersonal skills\nFluent spoken and written English, Cantonese & Mandarin\nInterested parties, please\u00a0CLICK HERE\u00a0to apply the position via Adecco website with your CV, or if you would like to have a further discussion about this role, please contact Cathy Yeung at 852-28996182.", "employment_types": ["Full Time", "Contract"], "selling_points": ["a recognised degree in related disciplines", "a minimum of 5 years\u2019 post-qualification work exp.", "implement and promote various collaboration scheme"], "locations": ["Not Specified"], "categories": ["Admin & HR", "Clerical / Admin Staff", "Marketing / Public Relations", "Public Relations - Event Management", "Building & Construction", "Others"], "post_time": "2022-01-14T10:35:31Z", "salary": {"currency": null, "max": null, "min": null, "period": null, "term": null}, "salary_visible": false, "title_keywords": ["senior officer"], "responsibilities": ["social media", "business projects", "presentations", "develop", "communication", "plan", "plans"], "requirements": {"degrees": [], "majors": [], "languages": ["cantonese", "english", "mandarin"], "language_level": ["fluent"], "hard_skills": ["dynamic"], "soft_skills": ["communication", "dynamic", "communication and interpersonal skills", "presentable"], "languages_combined": [{"language": "cantonese", "language_level": ["fluent"]}, {"language": "english", "language_level": ["fluent"]}, {"language": "mandarin", "language_level": ["fluent"]}]}, "experience_required": {"duration": ["8-10 years"], "field": ["sizable organization", "corporate communication", "management", "media"]}}, {"job_id": "100003009053666", "location_code": "hk", "company": "ADECCO", "job_title": "Corporate Communication Manager", "description": "Assist to plan and execute the whole program and to liaise with related organizations and associations related to trade fairs\nAssist to solicit for quotations /tenders and shortlist suitable vendors, and oversee their engagements and deliverables.\nOrganize and execute trade fairs in Mainland, etc. with the fair organizer/related parties/vendors\n\nResponsible for market research, roving exhibitions, visual promotion and public relation, etc\nExecute seminar, trade visits, etc. with the agencies/related parties\n\nTravel to Mainland for event and exhibition operation\nRequirements:\n\nUniversity degree holder or above with a minimum of 4 years related experience in marketing/event management/exhibition/advertising. Project management of government funding project is preferred.\nExcellent project execution skills to enhance procedures and controls under tight timeline and pressure.\nKnowledge in design aesthetic and in handling technical issues of exhibition e.g. space requirements of exhibits and their set-ups at shows will be an advantage.\n\nMature, strong communication and problem solving skills. Patient and able to handle multi-tasks accurately\nAll round marketing skills including but not limited to conferences, forums, exhibitions, large-scale festivals / sports events, familiarization tours etc.\nSelf-initiated, well-organized, attention to details and willing to travel occasionally\nWell-versed of spoken and written English, Chinese and Putonghua.\n\nimmediately available is highly preferred\nInterested parties may send in your application together with a detailed resume stating your academic results, present & expected salaries, date of availability and the post title by email via clicking \"Apply Now\".\u00a0 (All information provided will be treated in strict confidence and used solely for recruitment purposes)", "employment_types": ["Full Time", "Permanent"], "selling_points": [], "locations": ["North Point"], "categories": ["Marketing / Public Relations", "Marketing - Marketing Communication", "Public Relations - Event Management", "Digital Marketing"], "post_time": "2022-01-17T07:18:47Z", "salary": {"currency": null, "max": null, "min": null, "period": "monthly", "term": null}, "salary_visible": false, "title_keywords": ["manager"], "responsibilities": ["management", "advertising", "procedures", "market research", "design", "communication", "project management", "conferences", "plan", "visual", "liaise with"], "requirements": {"degrees": ["university degree"], "majors": ["marketing"], "languages": ["putonghua", "english", "chinese"], "language_level": [], "hard_skills": ["project management", "problem solving skills", "marketing skills"], "soft_skills": ["responsible", "multi-tasks", "well-organized", "mature", "communication", "project management", "attention to details", "patient", "problem solving skills"], "languages_combined": [{"language": "putonghua", "language_level": []}, {"language": "english", "language_level": []}, {"language": "chinese", "language_level": []}]}, "experience_required": {"duration": ["minimum of 4 years"], "field": ["related", "management", "marketing", "advertising"]}}, {"job_id": "100003009047195", "location_code": "hk", "company": "JPMorgan Chase Bank, N.A.", "job_title": "Corporate & Investment Banking Events - Vice President", "description": "J.P. Morgan is a global leader in financial services, providing strategic advice and products to the world's most prominent corporations, governments, wealthy individuals and institutional investors. Our first-class business in a first-class way approach to serving clients drives everything we do. We strive to build trusted, long-term partnerships to help our clients achieve their business objectives.\n\nThe Corporate Meetings & Events Marketing teams work in partnership with all lines of business and firm-wide to plan, execute and support client and internal conferences and events.\n\nEvent teams are located in key markets in APAC, EMEA, North Asia, and Latin America and are comprised of experienced event professionals with specialized expertise and supplier relationships to execute events to a high standard while closely managing costs.\n\nThis role will be based in Hong Kong as a key contributor for the Corporate Meetings & Events (CME) team. The successful candidate will work with their manager and colleagues on all work related to any event responsibilities, such as onsite visits and support, budget tracking and monitoring, and event related reporting.\n\nThe successful candidate will have significant exposure and interactions with senior management and would be required to have a thorough understanding of business strategy and goals, equipped with strategic, financial and project coordination skills. The successful candidate will also be expected to partner effectively with colleagues across other functions including Lines of Businesses, Legal, Compliance, Marketing & Communications teams, sales and bankers, product partners, and senior management.\n\nResponsibilities\n\nLead event project initiatives in the region, partnering with the business and other functional partners to develop impactful programs in alignment with business strategy\nEffective planning and execution of client conferences and events across APAC\nManage the end-to-end process of event planning & execution and logistics, ranging from event briefs, research, approvals, invitations, speakers management, venue set-up, designs, onsite support, production / audio / video / virtual event management, financial management and post-event analysis\nManage effectively external vendors and venues on all event related matters\nProvide support across J.P. Morgan franchise sponsorships as well as industry conferences and events, ensuring benefits are delivered, effectively leveraged and executed flawlessly\nManage and keep track of event budget with a view to cost efficiency\nAdhere to internal policy and procedures with regards to reporting activities and spend, compliance regulations, approval processes and ensuring appropriate documentation is in place\nMaintain Corporate Meetings & Events database which include (but is not limited to) event metrics, budgets, and event collateral\nDevelop partnerships amongst the team for coverage on complex conferences and events and build relationships for new projects with other Lines of Businesses\nThe ideal candidate would have\n\nA Degree in Business Administration, Marketing, Communications, Hotel Management or a related degree is preferred\nMinimum 6 years of experience in event planning and management/execution, preferably in financial industry with experience in managing investor conference\nStrong problem-solving, analytical, and project management skills and ability/flexibility to confidently lead and manage an event on an end-to-end basis\nIndependent to take initiative and ownership of assigned projects\nExcellent organizational and time management skills with the ability to multi-task under tight deadlines\nClient focused, highly organized, and process oriented with the ability to manage multiple and competing deadlines\nAbility to manage budget, and to stay within strict budget parameters\nConfidence to be an ambassador to internal client management. Ability to forge strong relationships, interact, influence and communicate effectively with all levels of the organization and across Lines of Businesses\nTeam player with proven ability to communicate in clear, concise and accurate manner, and able to collaborate with team members, vendors and all levels of internal and external stakeholders\nA highly motivated and proactive individual with strong prioritization skills\nStrong accuracy, attention to details and consistent follow through\nExcellent English oral and written communication skills; Mandarin proficiency would be an advantage\nExcellent Microsoft skills including Word, Excel and PowerPoint, and savvy with technology\nPeriodic travel within the region may be required\nWe recognize that our people are our strength and the diverse talents they bring to our global workforce are directly linked to our success. We are an equal opportunity employer and place a high value on diversity and inclusion at our company. We do not discriminate on the basis of any protected attribute, including race, religion, color, national origin, gender, sexual orientation, gender identity, gender expression, age, marital or veteran status, pregnancy or disability, or any other basis protected under applicable law. In accordance with applicable law, we make reasonable accommodations for applicants' and employees' religious practices and beliefs, as well as any mental health or physical disability needs.\n\nInterested parties please click \u201cApply Now\u201d to apply job.\n\nAll applications applied through our system will be delivered directly to the advertiser and privacy of personal data of the applicant will be ensured with security.", "employment_types": ["Full Time"], "selling_points": [], "locations": ["Not Specified"], "categories": ["Banking / Finance", "Others", "Management", "General Management", "Marketing / Public Relations", "Public Relations - Event Management"], "post_time": "2022-01-14T02:33:38Z", "salary": {"currency": null, "max": null, "min": null, "period": "monthly", "term": null}, "salary_visible": false, "title_keywords": ["vice president"], "responsibilities": ["regulations", "collaborate with", "budget", "communication", "maintain", "plan", "database", "senior management", "costs", "administration", "compliance", "teams", "develop", "conferences", "logistics", "audio", "reporting", "management", "provide support", "cost", "monitoring", "procedures", "documentation", "tracking", "budgets", "project coordination", "analysis", "project management", "planning"], "requirements": {"degrees": ["degree"], "majors": ["hotel", "marketing", "business administration", "communications"], "languages": ["english", "mandarin"], "language_level": ["advantage", "excellent", "proficiency"], "hard_skills": ["excel", "analysis", "problem-solving", "word", "powerpoint", "project management", "make", "documentation"], "soft_skills": ["oral", "first-class", "coordination skills", "focused", "team player", "confidence", "independent", "problem-solving", "clear", "diverse", "initiative", "ideal", "organized", "communication skills", "attention to details", "accurate", "multi-task", "time management skills", "project management skills", "organizational", "motivated", "thorough", "proactive"], "languages_combined": [{"language": "english", "language_level": ["excellent"]}, {"language": "mandarin", "language_level": ["proficiency", "advantage"]}]}, "experience_required": {"duration": ["minimum 6 years"], "field": ["management", "financial industry", "planning"]}}, {"job_id": "100003009053899", "location_code": "hk", "company": "NWS Holdings Limited", "job_title": "Manager \u2013 Sustainability", "description": "The candidate will be responsible to drive various corporate sustainability initiatives across the Group.\u00a0In this regard, the incumbent is required to:\n\nSupport and drive sustainability development and performance across the Group;\nCollaborate with external parties and subsidiaries to develop and prepare sustainability reports;\nCoordinate group-wide Environmental Management Committee;\nWork with various benchmarking organisations to report and raise awareness of the Group\u2019s sustainability performance;\nPromote and engage stakeholders on sustainability through events and programmes, including sustainability marketing / promotional campaigns; and\n\nPerform other duties as assigned by the supervisor.\n\nRequirements\n\n\nBachelor and above degree holder in Environmental Science/ Management or related discipline;\nAt least 8 years\u2019 relevant hands-on experience in corporate sustainability, including but not limited to reporting, data management etc;\nSolid understanding of HKEX ESG disclosure requirements and GRI reporting standards;\nExperience in organizing sustainability awareness programs and campaigns;\nStrong business acumen to drive sustainability in commercial setting;\nExcellent communication and interpersonal skills, including command of written and spoken English, Cantonese and Mandarin; and\nEntrepreneurial mindset, results-driven, mature, organized and meticulous.\nWe offer competitive salary and package for the right candidate. Interested parties please click \"Apply Now\" below to submit your application expected salary and availability.\n\n\nVisit our website at www.nws.com.hk.\n(All information collected will be treated in strict confidence and only be used for recruitment purposes.)", "employment_types": ["Full Time", "Permanent"], "selling_points": ["Bachelor & above degree in Environmental Science", "At least 8 years\u2019 relevant experience", "Strong business acumen"], "locations": ["Central"], "categories": ["Sciences, Lab, R&D", "Environmental Science / Waste Management", "Marketing / Public Relations", "Public Relations - Event Management"], "post_time": "2022-01-17T07:43:07Z", "salary": {"currency": null, "max": null, "min": null, "period": "monthly", "term": null}, "salary_visible": false, "title_keywords": ["manager"], "responsibilities": ["collaborate with", "reporting", "management", "perform other duties", "data", "external parties", "develop", "coordinate", "communication", "reports", "report"], "requirements": {"degrees": ["bachelor", "degree holder"], "majors": ["environmental science"], "languages": ["cantonese", "english", "mandarin"], "language_level": ["excellent"], "hard_skills": ["data management", "acumen"], "soft_skills": ["organized", "meticulous", "responsible", "mature", "hands-on", "communication and interpersonal skills", "business acumen", "driven"], "languages_combined": [{"language": "cantonese", "language_level": ["excellent"]}, {"language": "english", "language_level": ["excellent"]}, {"language": "mandarin", "language_level": ["excellent"]}]}, "experience_required": {"duration": ["at least 8 years"], "field": ["management", "sustainability"]}}, {"job_id": "100003009048974", "location_code": "hk", "company": "Across Asia Communications Limited", "job_title": "Senior Account Executive / Account Executive", "description": "Responsibilities:\nResponsible for execution and follow up of media relations and integrated marketing campaigns\nCopywriting and translation of press release, newsletter and other forms of corporate collateral\nHandle print and multimedia production projects\u00a0\nRequirements:\nDegree holder in Journalism, Language, Business Administration, Finance or Accounting preferred\n1-2 years relevant experience, preferably with media\u00a0\nExcellent command of written and oral English and Mandarin\nFamiliar with Social media,\u00a0MS Powerpoint, Excel and proficiency in Chinese word processing\nMust be detail-minded, meticulous and proactive\nProven communication and organizational skill\nSelf-motivated and able to meet deadline\nGood team player. Able to work independently & catch tight deadline\nImmediate availability is preferable", "employment_types": ["Full Time"], "selling_points": [], "locations": ["Sheung Wan"], "categories": ["Marketing / Public Relations", "Public Relations - Copy-writing", "Public Relations - Event Management", "Public Relations - General / Support"], "post_time": "2022-01-14T07:49:41Z", "salary": {"currency": null, "max": null, "min": null, "period": "monthly", "term": null}, "salary_visible": false, "title_keywords": ["account executive", "senior account executive"], "responsibilities": ["marketing campaigns"], "requirements": {"degrees": ["degree holder"], "majors": ["journalism", "finance", "accounting", "business administration"], "languages": ["english", "chinese", "mandarin"], "language_level": ["excellent", "proficiency"], "hard_skills": ["excel", "ms powerpoint", "chinese word processing"], "soft_skills": ["detail-minded", "meticulous", "oral", "self-motivated", "organizational skill", "good team player", "work independently", "communication", "proactive"], "languages_combined": [{"language": "english", "language_level": ["excellent"]}, {"language": "chinese", "language_level": ["proficiency"]}, {"language": "mandarin", "language_level": ["excellent"]}]}, "experience_required": {"duration": ["1-2 years"], "field": ["relevant experience", "media"]}}, {"job_id": "100003009046555", "location_code": "hk", "company": "Sun Hung Kai Properties Ltd", "job_title": "ASSISTANT PROMOTIONS OFFICER / PROMOTIONS ASSISTANT - SHOPPING MALL", "description": "Requirements:\n\n\nBachelor\u2019s degree, preferably major in Marketing / Business Administration / Event Management\nSome marketing or administration experience preferred, fresh graduates will also be considered\nFamiliar with PC software e.g. MS Word, Excel & Chinese Word Processing\nKnowledge in using Photoshop, Illustrator and HTML would be an advantage\nWilling to work overtime, irregular hours and during weekends / public holidays\nProven English proficiency\n\nResponsibilities:\n\n\nProvide administrative support to mall promotions team\nPrepare and organize marketing materials\nManage warehouse, inventory and procurement logistics\nLiaise with vendors and contractors\nWork closely with agencies and tenants in promoting the shopping mall\n\n(Candidates with more experience will be considered for Assistant Promotions Officer.)\n\nGood remuneration and attractive fringe benefits will be offered to the successful applicant. Interested parties please apply with full resume, present and expected salary, available date by clicking \"Apply Now\".\n\nFor further information, please visit our company website: www.shkp.com.\n\nWe are an equal opportunity employer and welcome applications from all qualified candidates. All personal data collected will be used for recruitment purpose only.\u00a0 Applicants not hearing from us within 3 months may consider their applications unsuccessful.\u00a0 All personal data collected will be destroyed within 24 months.", "employment_types": ["Full Time", "Permanent"], "selling_points": ["Prepare and organize marketing activities", "Handle public relations work of the activities", "Work closely with agencies and tenants"], "locations": ["Not Specified"], "categories": ["Marketing / Public Relations", "Marketing - Marketing Communication", "Public Relations - Event Management", "Others", "Student / Fresh Graduate / No Experience"], "post_time": "2022-01-13T13:54:45Z", "salary": {"currency": null, "max": null, "min": null, "period": null, "term": null}, "salary_visible": false, "title_keywords": ["officer", "assistant"], "responsibilities": ["marketing materials", "inventory", "liaise with", "logistics", "provide administrative support"], "requirements": {"degrees": ["degree", "bachelor"], "majors": ["marketing", "business administration"], "languages": ["english", "chinese"], "language_level": ["proficiency"], "hard_skills": ["excel", "chinese word processing", "ms word", "illustrator", "html", "pc", "photoshop"], "soft_skills": ["work overtime"], "languages_combined": [{"language": "english", "language_level": ["proficiency"]}, {"language": "chinese", "language_level": []}]}, "experience_required": {"duration": [], "field": ["marketing", "administration"]}}, {"job_id": "100003009048113", "location_code": "hk", "company": "Hong Kong Education City Limited", "job_title": "Senior Project Officer", "description": "Responsibilities:\n\nAssist the Manager to develop strategies and detailed plans for executing projects and services to EdCity users to achieve company goals and KPIs.\nOversee, develop, kick off and sustain projects and related online services for EdCity users, particular schools, teachers and students.\nPlan and execute user engagement strategies to drive their cohesiveness of EdCity\u2019s services.\nCollaborate closely with government bodies, educational institutes and organisations, schools and community groups for partnership establishment and cooperation opportunities.\nDesign, manage and conduct a range of learning and teaching programmes for promoting ICT in Education and Innovative education for the education sector.\nDevelop thematic content, and manage web contents, social media and community platforms and budget.\nTake up ad-hoc duties as required.\n\nRequirements:\n\nDegree or above in Education, Linguistics, Translation, Psychology, or other related disciplines.\nMinimum 6 years of solid experience in project management and content development, preferably in the fields of ICT in Education.\nHaving knowledge of developing resources and services for Reading.\nExposure in Gamified Learning and Educational Technology, and understanding of HK school curriculum will be an advantage.\nDemonstrated ability to develop, deliver and evaluate communications and engagement strategies.\nWide network with local and overseas educational business segment, publishers, schools, teachers or/and education bodies.\nExcellent command of written and spoken Chinese and English.\nExcellent interpersonal and communication skills with outgoing personality.\nProven skills in facilitation, design and implementation of educational projects, stakeholder events, workshops, briefings, information sessions and presentations.\nStrong knowledge in social networking, web authoring and editing.\nProficient in Microsoft applications.\nAble to work independently, meet tight deadlines and be a good team player.\nPassion for education and innovation.\nProactive, creative; detailed-minded, result-oriented, and skilful at multi-tasking.\nCandidates with less experience will also be considered as Project Officer.\n\nWe provide attractive remuneration and fringe benefits to the right candidate:\n\n5-day workweek\n14 Days Annual Leave + 7 days seniority annual leave\nPerformance Incentive\nMedical and Dental Insurance (Including dependents)\nAnnual Health Check-up Benefit\nLife Insurance\nEmployer MPF Voluntary Contribution (No cap)\nTraining Subsidies\n\nInterested parties looking for a promising career, please send your application letter and resume stating your\u00a0English and Chinese result in public examination(s), current and expected salary\u00a0by clicking \"Apply Now\"\u00a0on or before 27 January 2022.\n\nPersonal data provided will be used strictly for recruitment and other employment-related purposes.\u00a0 Details of the Personal Information Collection Statement - Recruitment of the Company can be found at\u00a0https://www.hkedcity.net/hq/recruit/statement\n\nApplicants please submit one application for each post.\u00a0 Applicants not invited for interview after 8 weeks from the closing date may consider their applications unsuccessful.\u00a0 The Company reserves the right not to fill the post(s).", "employment_types": ["Full Time"], "selling_points": ["Education services/events for teachers & students", "Promotion of ICT in education", "Collaboration with education sectors & community"], "locations": ["Shatin Area"], "categories": ["Media & Advertising", "Editorial / Journalism", "Marketing / Public Relations", "Marketing - Brand / Product Management", "Public Relations - Event Management"], "post_time": "2022-01-14T04:57:38Z", "salary": {"currency": null, "max": null, "min": null, "period": "monthly", "term": null}, "salary_visible": false, "title_keywords": ["senior project officer"], "responsibilities": ["collaborate", "social media", "develop strategies", "detailed plans", "partnership establishment", "learning and teaching programmes", "budget", "manage web contents", "design", "develop", "executing", "cooperation opportunities", "plan", "ad-hoc duties", "kpis", "user engagement strategies", "community platforms"], "requirements": {"degrees": ["degree or above"], "majors": ["related disciplines", "psychology"], "languages": ["english", "chinese"], "language_level": ["excellent"], "hard_skills": ["briefings", "information sessions", "educational projects", "microsoft applications", "web authoring", "presentations", "project management", "workshops", "translation", "stakeholder events"], "soft_skills": ["outgoing personality", "communication skills", "work independently", "meet tight deadlines", "good team player", "creative", "result-oriented", "passion for", "project management", "multi-tasking", "learning", "proactive", "interpersonal", "detailed"], "languages_combined": [{"language": "english", "language_level": ["excellent"]}, {"language": "chinese", "language_level": ["excellent"]}]}, "experience_required": {"duration": ["minimum 6 years"], "field": ["project management", "content development", "education"]}}, {"job_id": "100003009046522", "location_code": "hk", "company": "Skyera International (HK) Limited", "job_title": "Marketing Coordinator  / Project Coordinator (Full time / Partime)", "description": "Responsibilities:\n\nSourcing & data\u00a0collection\nPrepare marketing materials and execution for company projects\u00a0\nCooperate with design team, productions and all vendors to ensure the delivery of quality services in a timely manner\nCollaborate with sales lead for preparing proposal\nDigital marketing , content for social media platform\nExplore market trend & new business\u00a0opportunities\nHandling ad hoc\u00a0projects.\n\n\u00a0Requirements:\n\nTertiary education, Diploma or above,\u00a0 preferably\u00a0in Marketing, Multi Media or related discipline.\n1-2 years solid experience preferably in event marketing, exhibition, design production or related industry.\nFluent in Cantonese & English\nGoode command of PC skills and MS office, such as PowerPoint, Excel, MS Words\u00a0\nKnowledge in video production, graphic software, webpage is\u00a0 a plus.\nStrong communication skills, initiative, and flexible\nPositive work manner\u00a0and willing to learn.\n\nAn attractive salary package and year bonus will be offered to successful candidate.\n\n\nFor interested candidate, please send us your full resume by clicking \"APPLY NOW\".\n\nCompany website:\u00a0www.skyera-hk.com", "employment_types": ["Full Time", "Part Time"], "selling_points": ["Prepare and execute marketing materials & programe", "Tertiary Education or above, 1 year solid work exp", "Polite, positive work attitude, willing to learn"], "locations": ["Tin Hau"], "categories": ["Media & Advertising", "Production", "Marketing / Public Relations", "Marketing - General / Support", "Public Relations - Event Management"], "post_time": "2022-01-13T13:05:58Z", "salary": {"currency": null, "max": null, "min": null, "period": "monthly", "term": null}, "salary_visible": false, "title_keywords": ["marketing coordinator", "project coordinator"], "responsibilities": ["collaborate with", "social media", "business opportunities", "quality", "a timely manner", "design", "digital marketing", "ad hoc projects", "data collection", "cooperate with", "prepare marketing materials"], "requirements": {"degrees": ["diploma or above"], "majors": ["marketing"], "languages": ["cantonese", "english"], "language_level": ["fluent"], "hard_skills": ["excel", "plus", "ms words", "powerpoint", "pc skills", "ms office"], "soft_skills": ["flexible", "communication skills", "willing to learn", "initiative", "positive"], "languages_combined": [{"language": "cantonese", "language_level": ["fluent"]}, {"language": "english", "language_level": ["fluent"]}]}, "experience_required": {"duration": ["1-2 years"], "field": ["related", "marketing", "design"]}}, {"job_id": "100003009045348", "location_code": "hk", "company": "Genting Hong Kong Limited", "job_title": "Senior Executive - Events & Promotion Planning (Event Marketing)", "description": "Working location:\u00a0Elite Centre in Kwun Tong\n\nResponsibilities:\n\nGather, understand and consolidate business & user requirement from various sources\nConduct regular analysis reports, including budgeting, pre and post campaign analysis.\nLiaise and connect closely with internal stakeholders, external parties and business partners on marketing activities and projects\nAssist in product strategies, included but not limited to implementation flow, segmentation and performance evaluation\nAssist in developing analysis model such as business intelligence, competitor analysis, customer survey and market trend report\nPerform other ad hoc projects and assignments as required\n\nRequirements:\n\nBachelor degree in business, marketing or related filed\n4 years of relevant working experiences\nProficient in PC skills (MS Word, Excel and PowerPoint)\nExperience in CRM or data analytics is a plus\nSelf-motivated, good communication, interpersonal skills and well-organized\nFluent in spoken and written English, Cantonese and Mandarin\n\nGenting Hong Kong is an Equal Opportunity Employer. All applications received will be treated in strict confidence and be used exclusively for recruitment purpose only. If you are not contacted within four weeks, your application will be retained for a period of 1 year and may be presented for other appropriate positions within this period.", "employment_types": ["Full Time", "Permanent"], "selling_points": ["VIP program & event planning, promotion analysis", "Experience in CRM & data analytics is a plus", "Self-motivated with good communication skills"], "locations": ["Kwun Tong"], "categories": ["Professional Services", "Business Analysis / Data Analysis", "Marketing / Public Relations", "Marketing - Direct Marketing", "Public Relations - Event Management"], "post_time": "2022-01-13T07:39:53Z", "salary": {"currency": null, "max": null, "min": null, "period": "monthly", "term": null}, "salary_visible": false, "title_keywords": ["senior executive"], "responsibilities": ["liaise", "user requirement", "analysis reports", "budgeting", "analysis", "external parties", "implementation", "developing", "ad hoc projects", "evaluation", "report"], "requirements": {"degrees": ["degree", "bachelor"], "majors": ["business", "marketing"], "languages": ["cantonese", "english", "mandarin"], "language_level": ["fluent"], "hard_skills": ["excel", "plus", "data analytics", "powerpoint", "pc skills", "ms word"], "soft_skills": ["self-motivated", "confidence", "well-organized", "communication", "interpersonal skills"], "languages_combined": [{"language": "cantonese", "language_level": ["fluent"]}, {"language": "english", "language_level": ["fluent"]}, {"language": "mandarin", "language_level": ["fluent"]}]}, "experience_required": {"duration": ["4 years"], "field": []}}, {"job_id": "100003009051876", "location_code": "hk", "company": "LAWSGROUP", "job_title": "Corporate Communication Manager", "description": "Job Responsibilities:\n\nAssist in formulating communication strategies, budget and media events\nPromote the Corporate image and maintaining good relationship with the media, guests and business partners\nBuild, maintain, and manage the company reputation via a full range of corporate communications activities, CSR, sponsorship, media relations, issue/crisis management, to internal communications\nDevelop corporate communications materials such as newsletter, brochure, press releases, website, digital marketing materials, executives\u2019 speeches and presentations in alignment with the company\u2019s business imperatives\nEstablish efficient communications workflow and best practices; contribute to the development and adoption of best-in-class PR principles and practices across organization\nWork with external vendor and internal team in media monitoring\nAssist ad-hoc duties as assigned\nJob Requirements:\n\nDegree holder or above in Public Relations, Corporate Communications, Journalism, Marketing or related disciplines\nA minimum of 5 years' solid PR experience in media relations / public affairs / corporate communications and event management\nExcellent detail-minded and with good communication, translation and interpersonal skills\nExcellent command of spoken and written English, Chinese and Mandarin\nProficient in MS office applications (e.g. Word, PowerPoint, Excel)\nAble to work under pressure and meet tight deadlines\nWe\u00a0offer\u00a0attractive remuneration package to the right candidate. Interested parties please click the \"APPLY NOW\" button below and send your application together with a detailed resume including current & expected salary and availability to Human Resources Department.\nCompany website:\u00a0https://www.lawsgroup.com\n(Data collected will be treated in strict confidence and used for recruitment purpose only)", "employment_types": ["Full Time", "Permanent"], "selling_points": ["Degree in Public Relations or related disciplines", "Min. 5 yrs PR experience in media relations", "Promote the Corporate image"], "locations": ["Lai Chi Kok"], "categories": ["Media & Advertising", "Strategic Planning", "Marketing / Public Relations", "Marketing - Marketing Communication", "Public Relations - Event Management"], "post_time": "2022-01-17T01:25:51Z", "salary": {"currency": null, "max": null, "min": null, "period": "monthly", "term": null}, "salary_visible": false, "title_keywords": ["manager"], "responsibilities": ["maintaining", "budget", "monitoring", "website", "presentations", "develop", "communication", "good relationship", "maintain", "digital marketing", "ad-hoc duties", "crisis management"], "requirements": {"degrees": ["degree holder"], "majors": ["journalism", "related disciplines", "marketing", "communications"], "languages": ["english", "chinese", "mandarin"], "language_level": ["excellent"], "hard_skills": ["excel", "word", "powerpoint", "translation", "ms office"], "soft_skills": ["detail-minded", "meet tight deadlines", "communication", "interpersonal skills", "work under pressure"], "languages_combined": [{"language": "english", "language_level": ["excellent"]}, {"language": "chinese", "language_level": ["excellent"]}, {"language": "mandarin", "language_level": ["excellent"]}]}, "experience_required": {"duration": ["minimum of 5 years"], "field": ["pr", "media", "management"]}}, {"job_id": "100003009045954", "location_code": "hk", "company": "ADECCO", "job_title": "Marketing Communication Executive (Project) (Event) (PR) (16K-25K)", "description": "Our client, a pioneer in organizing exhibitions,\u00a0is now looking for Marketing Communication Executive (Project) (Event) (PR)\n\nMarketing Communication Executive (Project) (Event) (1)\n\nJob Responsibilities\n\nResearch vendors\nNegotiate with vendors to achieve the most favorable terms\nManage all event operations (preparing venue, invitations etc.)\nDo final checks at the day of the event (e.g. tables, technology) to ensure everything meets standards\nOversee event happenings and act quickly to resolve problems\nEvaluate event\u2019s success and submit reports\n\nJob Requirements\n\nHigher diploma in Marketing, Communications, Public Relations, Journalism or relevant field\nProficiency in MS Office\nExcellent verbal and written communication skills\nGood presentation skills\n\nMarketing Communication Executive (Project) (Event) (2)\n\nJob Responsibilities\n\nCoordinate the design of promotional material and distribute in online and offline channels\nAdvertise company and products/services on various media\nCraft and send regular newsletters with company updates\nMonitor corporate website and social media pages and address clients\u2019 queries\nGather customer feedback to inform sales and product teams\n\nJob Requirements\n\nHigher diploma in Marketing, Communications, Public Relations, Journalism or relevant field\nProficiency in MS Office\nExcellent verbal and written communication skills\nGood presentation skills\n\nMarketing Communication Executive (PR)\n\nJob Responsibilities\n\nWriting and producing presentations and press releases\nDealing with enquiries from the public, the press, and related organisations\nOrganising and attending promotional events such as press conferences, open days, exhibitions, tours and visits\nLiaising with clients, managerial and journalistic staff about budgets, timescales and objectives\n\nJob Requirements\n\nHigher diploma in Marketing, Communications, Public Relations, Journalism or relevant field\nProficiency in MS Office\nExcellent verbal and written communication skills\nGood presentation skills\n\nInterested parties, please CLICK HERE to apply online.\n\nOr if you would like to have a further discussion about this role, please Whatsapp Hoyin Siu at 9862 0297.\n\nPlease note that only short-listed candidates will be notified. All information gathered will be treated in strict confidence and solely used for recruitment purposes.", "employment_types": ["Full Time"], "selling_points": [], "locations": ["North Point"], "categories": ["Marketing / Public Relations", "Marketing - General / Support", "Marketing - Marketing Communication", "Public Relations - Event Management"], "post_time": "2022-01-13T09:14:12Z", "salary": {"currency": "HKD", "max": 19999, "min": 14000, "period": "monthly", "term": null}, "salary_visible": true, "title_keywords": ["executive"], "responsibilities": ["evaluate", "operations", "reports"], "requirements": {"degrees": ["diploma"], "majors": ["journalism", "marketing", "communications"], "languages": [], "language_level": [], "hard_skills": ["inform", "presentations", "ms office"], "soft_skills": ["communication", "communication skills", "presentation skills"], "languages_combined": []}, "experience_required": {"duration": [], "field": []}}, {"job_id": "100003009048340", "location_code": "hk", "company": "NHT Global Hong Kong Ltd", "job_title": "Marketing Assistant (5-day work)", "description": "Our client is well known European based financial publisher. They are now looking for a researcher to join their regional office in Hong Kong. This position offers on job training from top notch financial and event management professionals in the regional, and with exposure to work with high profile clients around the global.\n\nYour core duties including but not limited to research on recent and hot topics in the financial capital market, prepare conference materials, collaborate with training course marketer on marketing campaigns and lead generation exercises, assist in online and on-site conference.\u00a0\n\nIdeal candidates should possess a Bachelor Degree from reputable university.\u00a0 With 1-2 years of work experience in MNCs is preferred. With good international exposure and vision. Enjoy working in a multinational team. Good research and drafting skills in English is highly essential. Good business sense. Open minded, with can-do attitude, willing to learn and willing go extra miles. No prior experience is needed. Fresh graduate is welcome to apply.", "employment_types": ["Full Time", "Permanent"], "selling_points": [], "locations": ["Tsim Sha Tsui"], "categories": ["Marketing / Public Relations", "Marketing - General / Support", "Public Relations - Event Management"], "post_time": "2022-01-14T06:21:12Z", "salary": {"currency": null, "max": null, "min": null, "period": "monthly", "term": null}, "salary_visible": false, "title_keywords": ["marketing assistant"], "responsibilities": ["collaborate with", "management", "marketing campaigns"], "requirements": {"degrees": ["degree", "bachelor", "fresh graduate"], "majors": [], "languages": ["english"], "language_level": ["good"], "hard_skills": ["publisher", "no", "go"], "soft_skills": ["can-do attitude", "business sense", "enjoy working", "willing to learn", "open minded", "ideal"], "languages_combined": [{"language": "english", "language_level": ["good"]}]}, "experience_required": {"duration": ["1-2 years"], "field": []}}, {"job_id": "100003009050199", "location_code": "hk", "company": "Hong Kong Quality Assurance Agency", "job_title": "Senior Marketing Communications Officer/ Marketing Communications Officer", "description": "Responsibilities\n\nMarketing Assistant is responsible for working with the marketing team on budgeting, executing marketing promotions, programs, campaigns. Event management is a strong focus for this position; Work closely with internal and external parties to ensure excellent execution of marketing campaign;Preparing marketing materials and handle ad hoc projects.\n\nJob Requirements\u00a0\n\nDegree / Associate Degree holder in Marketing / Business Administration / Public Relations / Communications or related fields\nLess experienced candidates who have strong ambition in the event management field will also be considered\nGood command of spoken and written English, Mandarin and Cantonese\nWilling to learn & good communication skills\nExcellent organizational, problem solving, communication and teamwork spirit, and ability to work under pressure and tight deadlines\nCreative, proactive, mature, positive thinker & self-starter\nProficient in PC application such as Word, Excel, PowerPoint and Chinese word processing\u00a0\n\nRemuneration\n\nSalary will be commensurate with experience and qualification. A wide range of benefits including 5-days work, MPF, Medical Scheme, Annual Leave, Double Pay and Education Allowance will be offered to successful candidates.\u00a0\n\nWe offer an attractive remuneration package to the right candidate. Interested parties please e-mail with full resume with availability, present and expected salary to us.\n\nAll information provided will be treated in strict confidence and be used solely for consideration of your application. Personal data of unsuccessful applicants will be destroyed after the recruitment exercise.", "employment_types": ["Full Time", "Contract"], "selling_points": ["Tertiary education with 3 years experience", "Marketing or Public Relations related experience", "5-day work, Medical & Life Insurance is provided"], "locations": ["North Point"], "categories": ["Marketing / Public Relations", "Marketing - General / Support", "Public Relations - Event Management", "Public / Civil", "Social Services - Community / Non-profit Organization"], "post_time": "2022-01-14T09:55:39Z", "salary": {"currency": null, "max": null, "min": null, "period": "monthly", "term": null}, "salary_visible": false, "title_keywords": ["communications officer", "senior marketing communications officer"], "responsibilities": ["management", "budgeting", "internal and external parties", "executing", "marketing promotions", "ad hoc projects", "marketing materials"], "requirements": {"degrees": ["associate degree", "degree"], "majors": ["marketing", "business administration", "communications"], "languages": ["cantonese", "english", "chinese", "mandarin"], "language_level": ["good command", "proficient"], "hard_skills": ["excel", "chinese word processing", "word", "powerpoint", "scheme", "problem solving", "pc"], "soft_skills": ["communication skills", "proactive", "organizational", "willing to learn", "mature", "problem solving", "communication", "teamwork spirit", "creative", "positive", "work under pressure"], "languages_combined": [{"language": "cantonese", "language_level": ["good command"]}, {"language": "english", "language_level": ["good command"]}, {"language": "chinese", "language_level": ["proficient"]}, {"language": "mandarin", "language_level": ["good command"]}]}, "experience_required": {"duration": [], "field": []}}, {"job_id": "100003009039147", "location_code": "hk", "company": "Hong Kong China Dragon Boat Association", "job_title": "Assistant Manager", "description": "Responsibilities:\n\nManage the editorial agenda and content development for online and offline publicity materials, such as newsletters, booklet, eDM, leaflets; preparation and production of CSR report\nPrepare speeches, press releases and MC scripts\nFormulate and implement marketing communication strategies\nOrganize PR and marketing communications events and campaigns\nPremium sourcing, production of corporate video and revamp of website\n\nRequirements:\n\nTertiary education or above in Marketing, Communication, Translation, English or related disciplines\nMinimum 3\u00a0years working experience in Marketing or Public Relations\nPractical experience in copy-writing, \u00a0translation, publishing, event management and digital marketing is highly preferred\u00a0\nProactive, organized, detail-minded, able to work under pressure and meet\u00a0tight deadline\nStrong team player with excellent interpersonal and communication skills\nFluent in spoken and written English and Chinese\nProficient in Microsoft Office and Chinese Word Processing\n\nCandidate with more experience will be considered as Senior Marketing Communications Officer\n\n*2-year Contract will be offered to suitable candidate, and is subject to renewal.\u00a0\u00a0\n\nRemuneration will be commensurate with qualification and working experience.\u00a0 Interested parties please forward your resume with photo, expected remuneration and personal particulars to the\u00a0Human Resource Office, Hong Kong Quality Assurance Agency, 19th Floor, K Wah Centre, 191 Java Road, North Point, Hong Kong\u00a0OR\u00a0by fax to\u00a0 2202 9190\u00a0OR\u00a0 \u00a0click\u00a0\u201cApply Now\u201d to apply job.\u00a0 Duplicate applications will not be considered.\u00a0\u00a0\n\n\nInformation supplied will be kept in strict confidence and only be used for recruitment related purpose. Applicants not invited for interview within 6 weeks may consider their applications unsuccessful. Application forms and curriculum vitae will be kept for a period of 3 months after completion of the selection process.", "employment_types": ["Full Time", "Permanent"], "selling_points": [], "locations": ["Wong Tai Sin Area"], "categories": ["Admin & HR", "Clerical / Admin Staff", "Marketing / Public Relations", "Public Relations - Event Management", "Public / Civil", "Social Services - Community / Non-profit Organization"], "post_time": "2022-01-14T07:26:37Z", "salary": {"currency": null, "max": null, "min": null, "period": "monthly", "term": null}, "salary_visible": false, "title_keywords": ["assistant manager"], "responsibilities": ["revamp", "edm", "leaflets", "website", "communication", "report"], "requirements": {"degrees": [], "majors": [], "languages": ["english", "chinese"], "language_level": ["proficient", "fluent"], "hard_skills": ["translation", "chinese word processing", "microsoft office"], "soft_skills": ["detail-minded", "organized", "communication skills", "communication", "meet tight deadline", "team player", "proactive", "interpersonal", "work under pressure"], "languages_combined": [{"language": "english", "language_level": ["fluent"]}, {"language": "chinese", "language_level": ["proficient", "fluent"]}]}, "experience_required": {"duration": ["minimum 3 years"], "field": ["management", "public relations", "publishing", "marketing communications", "marketing", "digital marketing", "writing"]}}, {"job_id": "100003009045876", "location_code": "hk", "company": "The Chinese Manufacturers' Association of Hong Kong", "job_title": "Marketing Executive (EOA2)", "description": "Job Responsibilities\n\nPlan and organize membership programs including Seminars, Dinner Reception and Trade Matching programs, etc;\n\nTo conduct project management, and event coordination / supervision;\nManage FB and IG accounts;\nTo provide administrative support to the department;\n\nJob Requirements\n\nUniversity graduate with at least 2 years working experience;\u00a0\nA good team player with strong communication skills and service-oriented minds;\nInitiative and detail-minded with good sense of responsibility;\nGood writing skills in both English and Chinese;\nAble to speak fluent English, Cantonese and Putonghua;\nProficient with MS Office, knowing of Chinese typing is a must;\nBasic photo and video editing skill;\nCandidates with less experience will be considered as Senior Marketing Assistant.\nImmediate available is preferred.\n\nWe offer competitive remuneration and all applications will be treated in strict confidence. If your profile matches the above requirements, please send your full resume including your last and expected salary to us.\n\nData collected will be used for recruitment purpose only.", "employment_types": ["Full Time", "Permanent"], "selling_points": [], "locations": ["Central"], "categories": ["Marketing / Public Relations", "Marketing - Brand / Product Management", "Marketing - General / Support", "Public Relations - Event Management"], "post_time": "2022-01-14T06:11:31Z", "salary": {"currency": null, "max": null, "min": null, "period": "monthly", "term": null}, "salary_visible": false, "title_keywords": ["marketing executive"], "responsibilities": ["provide administrative support", "project management", "coordination", "plan"], "requirements": {"degrees": ["university graduate"], "majors": [], "languages": ["cantonese", "putonghua", "english", "chinese"], "language_level": ["fluent", "proficient", "good"], "hard_skills": ["basic", "typing", "writing skills", "video editing", "ms office"], "soft_skills": ["detail-minded", "communication skills", "good team player", "sense of responsibility", "service-oriented", "writing skills", "initiative"], "languages_combined": [{"language": "cantonese", "language_level": ["fluent"]}, {"language": "putonghua", "language_level": ["fluent"]}, {"language": "english", "language_level": ["fluent", "good"]}, {"language": "chinese", "language_level": ["proficient", "good"]}]}, "experience_required": {"duration": ["at least 2 years"], "field": ["marketing"]}}, {"job_id": "100003009050962", "location_code": "hk", "company": "The Hong Kong Polytechnic University", "job_title": "Community Engagement Officer", "description": "JOCKEY CLUB DESIGN INSTITUTE FOR SOCIAL INNOVATION\nCommunity Engagement Officer (Ref. 22011406-E)\nJockey Club Design Institute for Social Innovation is a unit aims at providing an innovative and human-centred platform to envision a better life in the society, connecting people with passion and nurturing doers of all ages to innovate with collective wisdom to enable impactful action.\u00a0\n\nDuties\nThe appointee will be required to:\n(a) formulate and execute effective marketing programmes;\n(b) organize events including preparation of promotion and event materials, pre-event logistic arrangements, on-site event management, etc.;\n(c) work closely with internal and external parties to facilitate the smooth implementation of marketing activities;\n(d) manage the digital communication channels, including website, social media, etc.;\n(e) assist in the development of the Institute\u2019s publicity, corporate branding and image-building;\n(f)\u00a0 engage a spectrum of community groups including senior citizens and non-governmental organizations; and\n(g) perform any other duties as assigned by the Director of the Jockey Club Design Institute for Social Innovation and the Project Managers.\nQualifications\nApplicant should:\n(a)\u00a0 have a recognised degree, preferably in Marketing, Communications, Advertising, Journalism or related disciplines;\n(b)\u00a0 have at least five years of marketing and communications experience;\n(c) have an excellent command of both written and spoken English and Chinese, including Putonghua;\n(d) have good communication, liaison and organizational skills;\n(e) be a good team player with a strong sense of responsibility and capable of handling multi tasks;\n(f) be highly motivated with strong initiatives, innovative and attentive to details;\n(g) demonstrate the ability to work under pressure;\n(h) have proficiency in MS Office applications, contemporary design applications (e.g. Adobe Photoshop and Illustrator, etc.) and Chinese word processing; and\n(i) have strong media network in local news or feature pages being an advantage.\nShortlisted candidates will be invited to sit for a written test.\nApplication\nPlease send a completed application form by post to Human Resources Office, 13/F, Li Ka Shing Tower, The Hong Kong Polytechnic University, Hung Hom, Kowloon, Hong Kong or via email by clicking \"Apply Now\"\u00a0 Application forms can be downloaded from https://www.polyu.edu.hk/hro/careers/guidelines_and_forms/forms.\u00a0 If a separate curriculum vitae is to be provided, please still complete the application form which will help speed up the recruitment process.\u00a0 Consideration of applications will commence on 21 January 2022 until the position is filled.\u00a0 The University\u2019s Personal Information Collection Statement for recruitment can be found at https://www.polyu.edu.hk/hro/careers/guidelines_and_forms/pics_for_recruitment.\nPolyU is an equal opportunity employer committed to diversity and inclusivity.\u00a0 All qualified applicants will receive consideration for employment without regard to gender, ethnicity, nationality, family status or physical or mental disabilities.", "employment_types": ["Full Time"], "selling_points": [], "locations": ["Not Specified"], "categories": ["Media & Advertising", "Editorial / Journalism", "Marketing / Public Relations", "Marketing - Marketing Communication", "Public Relations - Event Management"], "post_time": "2022-01-14T12:05:23Z", "salary": {"currency": null, "max": null, "min": null, "period": "monthly", "term": null}, "salary_visible": false, "title_keywords": ["officer"], "responsibilities": ["social media", "management", "any other duties", "advertising", "internal and external parties", "implementation", "design", "website", "communication", "recruitment", "recruitment process", "work under pressure"], "requirements": {"degrees": ["degree"], "majors": ["journalism", "related disciplines", "marketing", "communications"], "languages": ["putonghua", "english", "chinese"], "language_level": ["excellent"], "hard_skills": ["chinese word processing", "adobe photoshop", "illustrator", "c", "ms office"], "soft_skills": ["organizational skills", "good team player", "capable", "attentive to details", "sense of responsibility", "communication", "committed", "motivated", "smooth", "innovative", "work under pressure"], "languages_combined": [{"language": "putonghua", "language_level": ["excellent"]}, {"language": "english", "language_level": ["excellent"]}, {"language": "chinese", "language_level": ["excellent"]}]}, "experience_required": {"duration": ["at least five years"], "field": ["marketing"]}}, {"job_id": "100003009050027", "location_code": "hk", "company": "Urban Group", "job_title": "Marketing Officer", "description": "Responsibilities:\n\nProvide administrative support to ensure alignment and achievement of the overall objectives of events and campaigns\nPerform event management duties including but not limited to event registration and onsite assistance with crowd control; community liaison with internal and external parties; mass email drafting and blasting; event logistics coordination for physical, virtual and hybrid workshops and webinars; and all rounded administrative support\nManage membership & communication with members for various programmes and activities; arrange and maintain in-app and social media promotion for specific programmes\nCoordinate projects, tour and visits; conduct various research, consolidate and compile reports and analyses as required\nHandle general enquiries from internal and external parties and members\nPerform any other duties as assigned by supervisors\n\nRequirements:\n\nBachelor degree in Business Administration, Marketing or other related disciplines\nPreferably 1-2 years\u2019 relevant experience gained in sizable organizations. Fresh graduates are also welcomed\nMature, proactive, approachable and a good team player\nStrong computer skills in MS Office including Word, PowerPoint, Excel and Chinese word processing\nEffective communication, customer service and interpersonal skills\nExcellent command of written and spoken, English, Cantonese and Mandarin\nWorking location in Hong Kong Science Park\nInterested parties please\u00a0send\u00a0application letter with detailed resume, current and expected salary\u00a0to\u00a0Group Manager \u2013 Human Capital & Training\u00a0through one of the following means:\nMail:\u00a0Unit 213-215, Core Building 1, No.1 Science Park East Avenue,\u00a0Hong Kong Science Park, Pak Shek Kok, Shatin, N. T.\u00a0\u00a0\nEmail:\u00a0Clicking 'Apply Now'\n\n\nAll personal data collected will be used for employment-related purposes only.", "employment_types": ["Full Time", "Permanent"], "selling_points": [], "locations": ["Shatin Area"], "categories": ["Sales, CS & Business Devpt", "Customer Service - Supervisor / Officer", "Marketing / Public Relations", "Public Relations - Event Management", "Public Relations - General / Support"], "post_time": "2022-01-14T09:39:17Z", "salary": {"currency": null, "max": null, "min": null, "period": "monthly", "term": null}, "salary_visible": false, "title_keywords": ["marketing officer"], "responsibilities": ["crowd control", "social media", "management", "any other duties", "administrative support", "compile reports", "internal and external parties", "communication", "coordinate", "maintain", "provide administrative support", "logistics coordination"], "requirements": {"degrees": ["degree", "bachelor"], "majors": ["related disciplines", "marketing", "business administration"], "languages": ["cantonese", "english", "chinese", "mandarin"], "language_level": ["excellent"], "hard_skills": ["excel", "chinese word processing", "word", "powerpoint", "computer skills", "ms office"], "soft_skills": ["good team player", "approachable", "mature", "communication", "customer service", "interpersonal skills", "proactive"], "languages_combined": [{"language": "cantonese", "language_level": ["excellent"]}, {"language": "english", "language_level": ["excellent"]}, {"language": "chinese", "language_level": []}, {"language": "mandarin", "language_level": ["excellent"]}]}, "experience_required": {"duration": ["1-2 years"], "field": ["relevant experience"]}}, {"job_id": "100003009050862", "location_code": "hk", "company": "Williams Lea (Hong Kong) Ltd", "job_title": "Administration Associate (Public Relations)", "description": "Responsibilities:\n\nOrganise and participate in events, such as\u00a0press conferences, seminars, luncheons, client visits.\nWork closely with media, agencies, vendors and internal units to ensure the smooth implementation of PR activities with good media coverage\nPrepare, review material intended for public release to ensure that it represents the best interests of the group and is consistent with established brand messages\n\n\u00a0Requirements:\n\nDegree holder in Communications / Marketing or any related disciplines with 3 to 4 years of relevant experience\nProficiency in Microsoft Office, and collaboration tools (Zoom, Microsoft Teams, Cisco Webex)\nDetailed-oriented with ability to work effectively in a cross-functional team\nExcellent command of both written and spoken English, Mandarin and Cantonese\nAble to work under pressure and meet tight deadlines\n\nWe offer attractive remuneration package to the successful candidate.\u00a0 In addition, you will have an opportunity to work in a reputable company with excellent career exposure.\u00a0 Interested parties, please click \"APPLY NOW\" to submit your application.\n\nAll information provided will be treated confidentially and used solely for recruitment purpose.\u00a0", "employment_types": ["Full Time", "Permanent"], "selling_points": ["Banking Environment, Work Location: Central", "Monday to Friday 0900 - 1800", "AL 15 Days, Medical & Dental Coverage"], "locations": ["Central"], "categories": ["Marketing / Public Relations", "Marketing - Marketing Communication", "Public Relations - Event Management", "Public Relations - General / Support"], "post_time": "2022-01-14T11:35:36Z", "salary": {"currency": null, "max": null, "min": null, "period": "monthly", "term": null}, "salary_visible": false, "title_keywords": ["associate"], "responsibilities": ["conferences", "review", "implementation"], "requirements": {"degrees": ["degree holder"], "majors": ["related disciplines", "marketing", "communications"], "languages": ["cantonese", "english", "mandarin"], "language_level": ["excellent"], "hard_skills": ["microsoft office"], "soft_skills": ["work effectively", "work under pressure", "meet tight deadlines", "detailed"], "languages_combined": [{"language": "cantonese", "language_level": ["excellent"]}, {"language": "english", "language_level": ["excellent"]}, {"language": "mandarin", "language_level": ["excellent"]}]}, "experience_required": {"duration": ["3 to 4 years"], "field": ["related", "marketing", "relevant experience"]}}, {"job_id": "100003009047572", "location_code": "hk", "company": "The University of Hong Kong", "job_title": "Senior Research Assistant (holding the functional title of Project Manager) (Ref.: 511355)", "description": "Work type:\u00a0Full-time\nDepartment:\u00a0Faculty of Education (10000)\nCategories:\u00a0Research Support Staff\n\nSenior Research Assistant (holding the functional title of Project Manager) in the Faculty of Education\u00a0(Ref.: 511355) (to commence as soon as possible for 1 year, with the possibility of renewal)\u00a0\u00a0\n\nApplicants should possess a MPhil degree or above, with at least 1 year\u2019s post-qualification working experience.\u00a0 They should have a good command of written and spoken English and Chinese (including Cantonese), excellent research skills in qualitative research, experience in teaching biology, good time management skills, and the ability to work independently and as a team.\u00a0\u00a0\n\nThe appointee will work for a Quality Education Fund (QEF) project on biology teaching.\u00a0 He/She will be responsible for coordinating school visits, liaising with teachers on matters related to producing lesson videos, on-site directing and filming of the lessons, supporting the development and write-up of educative curriculum materials, organizing professional development workshops, plenary workshops and dissemination seminars, overseeing the production of educative curriculum materials and delivery to schools, collecting, analyzing and evaluating data on various components of the projects, and performing other duties as assigned.\u00a0\u00a0\n\nEnquiries about the post should be sent to Dr. Kennedy Chan at [via APPLY NOW].\u00a0\n\nA highly competitive salary commensurate with qualifications and experience will be offered, in addition to annual leave and medical benefits.\u00a0\n\nThe University only accepts online application for the above post. Applicants should apply online and upload an up-to-date C.V[via APPLY NOW].\u00a0 Review of applications will start as soon as possible and continue until\u00a0January 23, 2022, or until the post is filled, whichever is earlier.\n\nAdvertised:Dec 23, 2021 (HK Time)\nApplications close:Jan 23, 2022 (HK Time)", "employment_types": ["Full Time"], "selling_points": ["possess a MPhil degree or above", "1 year\u2019s post-qualification working experience", "coordinating school visits, liaising with teachers"], "locations": ["Not Specified"], "categories": ["Admin & HR", "Others", "Education", "Others", "Marketing / Public Relations", "Public Relations - Event Management"], "post_time": "2022-01-14T03:28:43Z", "salary": {"currency": null, "max": null, "min": null, "period": "monthly", "term": null}, "salary_visible": false, "title_keywords": ["project manager", "senior research assistant"], "responsibilities": ["management", "other duties", "data", "quality", "liaising with", "research support"], "requirements": {"degrees": ["degree or above"], "majors": [], "languages": ["cantonese", "english", "chinese"], "language_level": ["excellent", "good command", "good"], "hard_skills": ["workshops"], "soft_skills": ["time management skills", "work independently", "research skills", "responsible"], "languages_combined": [{"language": "cantonese", "language_level": ["good command", "good"]}, {"language": "english", "language_level": ["excellent", "good command", "good"]}, {"language": "chinese", "language_level": ["excellent", "good command", "good"]}]}, "experience_required": {"duration": ["at least 1 year"], "field": ["management", "research", "post-qualification", "teaching", "team"]}}, {"job_id": "100003009045521", "location_code": "hk", "company": "Swire Properties Limited", "job_title": "Marketing and Promotion Officer (Ref: OS00091)", "description": "About our role\nWe are now looking for a talented Marketing & Promotions Officer to be part of our dynamic team. \u00a0Reporting to the Assistant Marketing & Promotions Manager, the incumbent will assist in running a wide range of marketing and promotions activities for Citygate Outlets in Tung Chung. \u00a0He / She will also be highly involved in assisting in the pre-opening marketing initiatives for the mall\u2019s new development. \u00a0Duties include but not limited to supporting the re-branding exercises, coordinating launch activations, handling PR initiatives, preparing marketing communication materials, organizing sales-driven customer promotions and liaising with tenants / third parties for potential collaboration opportunities.\u00a0\n\nTogether with creativity, integrity and passion, our ideal staff should be:\nDegree in Marketing, Business Administration or related discipline\nMinimum 4 years\u2019 experience in branding, PR, advertising, communication, events, sales promotion, partnership and digital marketing\nExperienced in working with agencies of different scopes such as brand agency, PR agency, creative agency, advertising agency and event production house\nGood project management, interpersonal, time management and presentation skills, with sound marketing sense\nCreative, independent, well-organized and self-motivated\nExcellent communication skills in spoken and written English & Chinese\nCandidates with all-round marketing experience in shopping mall or retail industry would be highly preferred\nJoin us\n\nYou are invited to submit your application via the Apply button.\n\nAs an equal opportunity employer, Swire Properties strives to foster a diverse workforce and inclusive workplace, where People can thrive. If you require special assistance, due to disability, during any part of the recruitment process \u2013 including the online application and/or the selection process \u2013 please reach out to us via email (as specified on the job application website) at any time.\n\nIf we haven\u2019t contacted you six weeks after your submission, then please consider your application unsuccessful this time. All personal data collected during the application process will be kept for 12 months after its completion, and then\u00a0destroyed. All information will be used for recruitment and appointment purposes only. The Company will handle all personal data confidentially in accordance with the Hong Kong Special Administrative Region\u2019s Personal Data (Privacy) Ordinance.\n\nTo find out more about Swire Properties\u2019 Sustainable Development (SD) 2030 Strategy, especially in the area of People, visit www.swireproperties.com/en/sustainable-development/people.aspx.\n\n\u00a9 Swire Properties Limited \u592a\u53e4\u5730\u7522\u6709\u9650\u516c\u53f8", "employment_types": ["Full Time", "Permanent"], "selling_points": ["To run marketing and promotions activities", "To organize events and prepare marketing materials", "4-year experience in brand marketing"], "locations": ["Tung Chung"], "categories": ["Marketing / Public Relations", "Marketing - Brand / Product Management", "Public Relations - Event Management"], "post_time": "2022-01-13T08:00:22Z", "salary": {"currency": null, "max": null, "min": null, "period": null, "term": null}, "salary_visible": false, "title_keywords": ["officer"], "responsibilities": ["reporting", "management", "advertising", "liaising with", "website", "communication", "project management", "digital marketing", "recruitment", "recruitment process", "personal data", "administration"], "requirements": {"degrees": ["degree"], "majors": ["marketing", "business administration"], "languages": ["english", "chinese"], "language_level": ["excellent"], "hard_skills": ["project management", "dynamic"], "soft_skills": ["communication skills", "self-motivated", "marketing sense", "independent", "interpersonal", "integrity", "well-organized", "communication", "project management", "time management", "dynamic", "presentation skills", "diverse", "creative", "driven", "ideal"], "languages_combined": [{"language": "english", "language_level": ["excellent"]}, {"language": "chinese", "language_level": ["excellent"]}]}, "experience_required": {"duration": ["minimum 4 years"], "field": ["retail industry", "pr", "advertising", "marketing", "digital marketing"]}}, {"job_id": "100003009039496", "location_code": "hk", "company": "", "job_title": "Event Assistant", "description": "Responsibilities:\n\nPlanning and organizing of a diverse range of events (e.g. Birthday Party, Artist\u2019s Events, VIP dinners etc.)\nAssist for family support\nHandle personal matters and ad hoc assignment\nResponsible for property and facilities management and maintenance, renovation, worker recruitment if necessary\n\nRequirement:\n\nDegree Holder, Oversea graduates are welcomed\nMinimum 3 years of working experience\nOutgoing, detail-oriented, independent and pleasant personality\nExcellent command of both written and spoken English and Chinese (Cantonese & Mandarin)\nExcellent interpersonal and communication skills\nA good team player with proactive working attitude and positive thinking\n\nAttractive remuneration package will be offered to the suitable candidates. All personal data collected will be used for recruitment purpose only. Should you have any queries,please contact Ms Au at 2895 9936 for further information.", "employment_types": ["Full Time", "Permanent"], "selling_points": [], "locations": ["Wan Chai"], "categories": ["Admin & HR", "Personal / Executive Assistant", "Secretary", "Marketing / Public Relations", "Public Relations - Event Management"], "post_time": "2022-01-11T09:55:53Z", "salary": {"currency": null, "max": null, "min": null, "period": "monthly", "term": null}, "salary_visible": false, "title_keywords": ["event assistant"], "responsibilities": ["management", "maintenance", "ad hoc assignment", "renovation", "recruitment", "planning"], "requirements": {"degrees": ["degree holder"], "majors": [], "languages": ["cantonese", "english", "chinese", "mandarin"], "language_level": ["excellent"], "hard_skills": [], "soft_skills": ["outgoing", "communication skills", "good team player", "independent", "positive thinking", "pleasant", "detail-oriented", "proactive", "interpersonal"], "languages_combined": [{"language": "cantonese", "language_level": ["excellent"]}, {"language": "english", "language_level": ["excellent"]}, {"language": "chinese", "language_level": ["excellent"]}, {"language": "mandarin", "language_level": ["excellent"]}]}, "experience_required": {"duration": ["minimum 3 years"], "field": []}}, {"job_id": "100003009047391", "location_code": "hk", "company": "Christian Family Service Centre", "job_title": "Project Officer (M3-SCGS/SKGS)", "description": "Requirements:\u00a0 \u00a0\n\nA Diploma or above holder in Environmental Science / Education / Communication / Social Science / Marketing or any relevant discipline, preferably with a University Degree and 3 years working experience;\nEnglish Language (Syllabus B) and Chinese Language at Grade E or above in HKCEE/Level 2 in HKDSE;\nSound knowledge of local environmental issues, especially in waste reduction, is preferred;\nExperience in developing and organising public educational programmes, events, demonstrations and/or workshops is preferred;\nFamiliar with photo and graphic editing software, such as Adobe Photoshop and Illustrator, will be an advantage;\nCandidates with lower academic qualification or less experience will be considered for a post at a lower rank.\nJob\u00a0Duties:\n\nTo coordinate the planning, content development, liaison, promotion and implementation of educational mass programmes, events and activities related to environmental protection and waste management;\nTo coordinate the design and production of the publicity and education materials, and the management of social media platforms;\nTo engage and liaise with stakeholders in the communities to facilitate the promotion and implementation of the programmes / events / activities;\nTo supervise junior and part-time staff;\nTo perform other tasks pertaining to the work as assigned.\n\nWorking Hours:\u00a045 hours per week and work on weekend when necessary\u00a0 \u00a0\nWorking Location:\u00a0\u00a0Shatin District and Sai Kung District\u00a0\u00a0\n\nPlease send your application letter quoting our job reference code together with a full resume, available date, last and expected salary by post to the Human Resources Department at 10/F, 3 Tsui Ping Road, Kwun Tong, Kowloon or by email via \"Apply Now\".\nProspective employees who will undertake child or mentally incapacitated persons related work will be requested to undergo the Sexual Conviction Record Check (SCRC).\nApplicants not hearing from us within two months from the date of advertisement may consider their applications fail.\nAll personal data of unsuccessful candidates would be destroyed after 6 months of interview and after 3 months of receiving applications for those without interview.\nPersonal data provided by job applicants will be used for recruitment purpose for different posts in the Agency only.", "employment_types": ["Full Time"], "selling_points": [], "locations": ["Not Specified"], "categories": ["Sciences, Lab, R&D", "Environmental Science / Waste Management", "Marketing / Public Relations", "Public Relations - Event Management", "Public / Civil", "Social Services - Community / Non-profit Organization"], "post_time": "2022-01-14T02:58:22Z", "salary": {"currency": null, "max": null, "min": null, "period": "monthly", "term": null}, "salary_visible": false, "title_keywords": ["project officer"], "responsibilities": ["management", "social media platforms", "implementation", "design", "coordinate", "other tasks", "recruitment", "liaise with", "personal data", "planning"], "requirements": {"degrees": ["university degree", "hkdse", "diploma or above"], "majors": ["science", "environmental science", "marketing"], "languages": ["english", "chinese"], "language_level": [], "hard_skills": ["workshops", "adobe photoshop", "illustrator"], "soft_skills": ["communication"], "languages_combined": [{"language": "english", "language_level": []}, {"language": "chinese", "language_level": []}]}, "experience_required": {"duration": ["3 years"], "field": ["marketing", "environmental", "developing", "education"]}}, {"job_id": "100003009048953", "location_code": "hk", "company": "Heep Hong Society", "job_title": "Assistant Corporate Development Manager", "description": "Responsibilities:\n\nTo assist the Head of Corporate Development to coordinate the work of fundraising and corporate partnership\nTo liaise and maintain relationship with existing sponsors and corporate partners\nTo devise and implement outreach strategies to attract new corporate partners; and generate new business opportunities\nTo assist in the planning and execution of various fundraising events to meet the Society's fundraising objectives\nTo undertake any other duties as required\n\nRequirements:\n\nDegree in Marketing, Communication, Public Relations, Event Management or related discipline\nAt least 5 years' marketing and/or communication experience; experience in NGO fundraising preferable\nProven record of event management and fundraising\nExperience of networking with a broad contact base, including business and funding bodies\nA good team player, well organized and attentive to details\nProactive, positive with strong interest in charity\nExcellent command of written and spoken English and Chinese\n\nWe provide equal employment opportunities to all employees and applicants. For interested parties, please click\u00a0\u201cApply Now\u201d.\n\n(Personal data collected will be used for recruitment purpose only)", "employment_types": ["Full Time"], "selling_points": ["Fundraising & corporate partnership", "Degree in Marketing, Communication, PR, Event Mgmt", "Min. 5 years' marketing/communication experience"], "locations": ["Ngau Tau Kok"], "categories": ["Marketing / Public Relations", "Marketing - Brand / Product Management", "Public Relations - Event Management", "Others"], "post_time": "2022-01-14T11:46:57Z", "salary": {"currency": null, "max": null, "min": null, "period": "monthly", "term": null}, "salary_visible": false, "title_keywords": ["manager", "assistant"], "responsibilities": ["liaise", "any other duties", "business opportunities", "coordinate", "maintain", "planning"], "requirements": {"degrees": ["degree"], "majors": ["marketing"], "languages": ["english", "chinese"], "language_level": ["excellent"], "hard_skills": ["charity"], "soft_skills": ["good team player", "attentive to details", "well organized", "communication", "proactive", "positive"], "languages_combined": [{"language": "english", "language_level": ["excellent"]}, {"language": "chinese", "language_level": ["excellent"]}]}, "experience_required": {"duration": ["at least 5 years"], "field": ["business", "marketing"]}}, {"job_id": "100003009050074", "location_code": "hk", "company": "Royalty HK Limited", "job_title": "Field Marketing Management Trainee", "description": "Job Description\nJoin us and you\u2019ll shape more than just your career\n\nLet\u2019s talk about the job\n\nIf you enjoy working on a far-reaching dimension of projects that will help flourish business, you\u2019ll fit right in. Here are some things you can expect from Royalty marketing team.\n\n\nJob Overview:\n\n-\u00a0\u00a0\u00a0\u00a0\u00a0\u00a0 Identify market opportunities to boost up consumer sales on a face-to-face level\n\n-\u00a0\u00a0\u00a0\u00a0\u00a0\u00a0 Participate in direct marketing and sales strategy by interacting face to face with customers including indoor and outdoor events\n\n-\u00a0\u00a0\u00a0\u00a0\u00a0\u00a0 Evaluate effectiveness of marketing efforts, and make adjustments\n\n-\u00a0\u00a0\u00a0\u00a0\u00a0\u00a0 Ensure that multiple field market tactics all provide a consistent message\n\n-\u00a0\u00a0\u00a0\u00a0\u00a0\u00a0 Train teams in effective communication and presentation skills\n\n\n\nJob Highlights:\n\n-\u00a0\u00a0\u00a0\u00a0\u00a0\u00a0 Extensive, multifaceted training\n\n-\u00a0\u00a0\u00a0\u00a0\u00a0\u00a0 Weekly bonus (competitive compensation, bonuses, recognition and rewards)\n\n-\u00a0\u00a0\u00a0\u00a0\u00a0\u00a0 Leaders training course\n\n-\u00a0\u00a0\u00a0\u00a0\u00a0\u00a0 Advance career driven environment\n\nRequirements:\n\n-\u00a0\u00a0\u00a0\u00a0\u00a0\u00a0 Diploma holder or equivalent;\n\n-\u00a0\u00a0\u00a0\u00a0\u00a0\u00a0 With working experience in sales or marketing in an advantage;\n\n-\u00a0\u00a0\u00a0\u00a0\u00a0\u00a0 Creative, analytical, well-organized and excellent communication skills;\n\n-\u00a0\u00a0\u00a0\u00a0\u00a0\u00a0 Self-motivated and hardworking\n\n-\u00a0\u00a0\u00a0\u00a0\u00a0\u00a0 Fluent in Cantonese", "employment_types": ["Full Time"], "selling_points": ["Caring, Fun, Lively Work Environment", "5-day Work Week", "Immediate availability Preferred"], "locations": ["Wan Chai"], "categories": ["Marketing / Public Relations", "Marketing - Brand / Product Management", "Marketing - Direct Marketing", "Public Relations - Event Management"], "post_time": "2022-01-14T09:44:02Z", "salary": {"currency": "HKD", "max": 19999, "min": 17000, "period": "monthly", "term": null}, "salary_visible": true, "title_keywords": ["marketing management trainee"], "responsibilities": ["evaluate", "teams", "communication"], "requirements": {"degrees": ["diploma holder"], "majors": [], "languages": ["cantonese"], "language_level": ["fluent"], "hard_skills": [], "soft_skills": ["communication skills", "self-motivated", "well-organized", "creative", "hardworking"], "languages_combined": [{"language": "cantonese", "language_level": ["fluent"]}]}, "experience_required": {"duration": [], "field": ["marketing"]}}, {"job_id": "100003009047866", "location_code": "hk", "company": "The Hong Kong Polytechnic University", "job_title": "Project Officer (two posts)", "description": "KNOWLEDGE TRANSFER AND ENTREPRENEURSHIP OFFICE\n\nProject Officer (two posts) (Ref. 22011403-JCS)\n\nDuties\n\nThe appointees will work under the Branding and Marketing Division and be required to:\n\n(a) implement and organize marketing events and activities, such as banquets, ceremonies, seminars, conferences, competitions, exhibitions, press conferences, delegation visits, etc.;\n\n(b) liaise and coordinate with relevant parties to ensure successful delivery of projects;\n\n(c) provide administrative support to the University\u2019s societies, committees, trade associations and meetings;\n\n(d) maintain website and social media channels;\n\n(e) prepare reports and project documentations including proposals and budget; and\n\n(f) perform any other duties as may be assigned by the Director of the Office or his delegates.\n\nWorking on irregular hours including evenings, Saturdays and Sundays, and occasional travel outside Hong Kong may be required.\n\nQualifications\n\nApplicants should:\n\n(a) have a recognized degree preferably in Communication, Marketing or Event Management, plus at least three years\u2019 relevant post-qualification working experience; or a recognized certificate or diploma or an equivalent qualification preferably in the said disciplines plus at least five years\u2019 relevant post-qualification working experience;\n\n(b) have sound knowledge of computer software applications, preferably with knowledge of and experience in MS Office applications;\n\n(c) have a good command of both written and spoken English and Chinese, with fluency in Putonghua being an advantage;\n\n(d) have good planning, organizational and problem-solving skills;\n\n(e) be attentive to details and a good team player;\n\n(f) be able to work independently and meet tight deadlines; and\n\n(g) have good interpersonal and communication skills.\n\nShortlisted candidates will be invited to sit for a written test.\n\nApplicants who have responded to the previous advertisement need not re-apply.\n\nRemuneration and Conditions of Service\n\nA highly competitive remuneration package will be offered.\u00a0 Appointment will be on a one-year gratuity-bearing contract.\u00a0\u00a0 Applicants should state their current and expected salary in the application.\u00a0\n\nApplication\n\nPlease send a completed application form by post to Human Resources Office, 13/F, Li Ka Shing Tower, The Hong Kong Polytechnic University, Hung Hom, Kowloon, Hong Kong or via email by clicking \"Apply Now\". Application forms can be downloaded from https://www.polyu.edu.hk/hro/careers/guidelines_and_forms/forms. If a separate curriculum vitae is to be provided, please still complete the application form which will help speed up the recruitment process. Consideration of applications will commence on 21 January 2022 until the positions are filled. The University\u2019s Personal Information Collection Statement for recruitment can be found at https://www.polyu.edu.hk/hro/careers/guidelines_and_forms/pics_for_recruitment.\n\nPolyU is an equal opportunity employer committed to diversity and inclusivity.\u00a0 All qualified applicants will receive consideration for employment without regard to gender, ethnicity, nationality, family status or physical or mental disabilities.", "employment_types": ["Full Time"], "selling_points": [], "locations": ["Not Specified"], "categories": ["Marketing / Public Relations", "Marketing - Marketing Communication", "Public Relations - Event Management", "Others"], "post_time": "2022-01-14T04:07:07Z", "salary": {"currency": null, "max": null, "min": null, "period": null, "term": null}, "salary_visible": false, "title_keywords": ["project officer"], "responsibilities": ["liaise", "marketing events", "social media", "any other duties", "prepare reports", "management", "software", "budget", "coordinate with", "website", "communication", "conferences", "maintain", "recruitment", "provide administrative support", "recruitment process", "planning"], "requirements": {"degrees": ["certificate", "diploma", "degree"], "majors": ["marketing"], "languages": ["putonghua", "english", "chinese"], "language_level": ["fluency", "advantage", "good command"], "hard_skills": ["plus", "c", "problem-solving skills", "documentations", "ms office"], "soft_skills": ["communication skills", "good team player", "work independently", "meet tight deadlines", "attentive to details", "organizational", "communication", "committed", "problem-solving skills", "interpersonal"], "languages_combined": [{"language": "putonghua", "language_level": ["fluency", "advantage", "good command"]}, {"language": "english", "language_level": ["advantage", "good command"]}, {"language": "chinese", "language_level": ["advantage", "good command"]}]}, "experience_required": {"duration": ["at least five years", "at least three years"], "field": ["management", "marketing", "post-qualification"]}}, {"job_id": "100003009050503", "location_code": "hk", "company": "Uniplan Hong Kong Ltd", "job_title": "Assistant Procurement Manager", "description": "What awaits you \u2026\n\nResponsible for direct and indirect procurement of products and services to support company\u2019s business\nEnsure that the products or services are of high quality and cost effective aligned with the procurement policies and guidelines in the approval of each purchase including RFQ, PO issue, invoice tracking, filing and log in record in internal system\nBuild and maintain good relationships with key vendors and various stakeholders and explore great opportunities to obtain the best deals from them and ensure products and services are in high quality and delivered on time\nCompare and evaluate offers from vendors and review annual contract with vendors and negotiate contract terms of agreement and pricing\nWork closely with Operations Teams to understand their requirements for potential suppliers\nUpdate vendors/suppliers\u2019 data on regularly base and maintain the up-to-dated list for record and analysis\nMaintain accurate records of purchases, delivery information, benchmarking prices in internal databases\nPrepare reports on purchases including cost analyses\nConduct research on potential new vendors or sub-contractors from local and overseas market\nFactory visit on new potential vendors within or outside Hong Kong\nOnsite visit before and after client events to ensure quality of vendor service is up to standard\nWhat you should bring with you \u2026\n\n\nDiploma or degree in related discipline\nHold relevant certification such as MCIPS or CPSM will be a bonus\nMinimum 3+ years of purchasing management experience in fast paced working environment\nWorking knowledge in Events and Exhibition industry is preferred but not a must\nStrong existing network of high-quality suppliers to Event and Exhibition industry is a bonus\nProven knowledge of vendor sourcing practices (researching, evaluating and liaising with vendors)\nSolid analytical skills, with the ability to create financial reports and conduct cost analyses\nAttention to details with strong commercial awareness and compliance with deadlines\nExcellent interpersonal and negotiation skills\nEffective verbal and written English and Chinese communication skills, ability to speak Mandarin is a bonus\nProficient in MS Word, Excel and PowerPoint\u00a0\nPlease submit your resume together\u00a0with your current and expected salary\u00a0by clicking \"Apply Now\".\u00a0\n\nAll\u00a0applications will be treated in strict confidence and used exclusively for recruitment purposes.\n\nApplicants who are not being contacted within 6-8 weeks may consider their application unsuccessful.", "employment_types": ["Full Time", "Permanent"], "selling_points": ["Min. 3+ years of purchasing management experience", "Direct and indirect procurement", "Event and Exhibition"], "locations": ["Wan Chai"], "categories": ["Marketing / Public Relations", "Public Relations - Event Management", "Merchandising & Purchasing", "Procurement / Purchasing / Sourcing", "Others", "Others"], "post_time": "2022-01-14T10:34:01Z", "salary": {"currency": null, "max": null, "min": null, "period": "monthly", "term": null}, "salary_visible": false, "title_keywords": ["manager", "assistant"], "responsibilities": ["data", "operations", "quality", "communication", "purchase", "procurement policies", "maintain", "conduct research", "compliance", "teams", "liaising with", "cost", "management", "invoice", "review", "tracking", "financial reports", "guidelines", "analysis", "evaluate", "recruitment", "databases", "prepare reports"], "requirements": {"degrees": ["diploma", "degree"], "majors": [], "languages": ["english", "chinese", "mandarin"], "language_level": [], "hard_skills": ["excel", "analysis", "vendor", "powerpoint", "analytical skills", "databases", "ms word"], "soft_skills": ["communication skills", "confidence", "responsible", "analytical skills", "negotiation skills", "attention to details", "accurate", "interpersonal"], "languages_combined": [{"language": "english", "language_level": []}, {"language": "chinese", "language_level": []}, {"language": "mandarin", "language_level": []}]}, "experience_required": {"duration": ["minimum 3+ years"], "field": ["purchasing", "management"]}}, {"job_id": "100003009050328", "location_code": "hk", "company": "Asia Beauty Concepts Limited", "job_title": "Senior Marketing Executive/Assistant Marketing Manager", "description": "Responsibilities:\n\n\nPR & Media Focus\nPrepare member communications including eDM, personalization messages, SMS, WhatsApp etc.\nKeep the consistency of the Brand image and viral in the market\u00a0\nWork together with the sales team to deliver the brand position across multiple aspects of the consumer in-store experience such as direct-to-consumer activities, instore support such as promotional programs, media plans, POS and GWP\u2019s development and redemption programs\nExplore new business opportunities / partners with distinctive and innovative ideas for long term development of business sources and lead generation to grow the sales\nCommunicate and extent good relationships with online media & KOL\nTo assist in sales and marketing activities including fee quotation, CRM implementation, etc.\nMonitor Brand performance and sales trend, conduct business analysis reports\nOther ad-hoc projects as assigned by management\n\u00a0\u00a0Requirements:\nDegree holder in Marketing, Communications or related disciplines\nAt least 3 years relevant experience in marketing for retail industry\nPrior experience in a FMCG /cosmetic and beauty industry / agency preferred\nStrong understanding in marketing trends\nStrong communication and interpersonal skill\nProficient with technology\nCreative thinking and attention to details\nProficient in Cantonese and English is a MUST, Mandarin is an advantage\nAble to work under pressure and meet deadlines\n\nInterested parties please send your application letter, resume, expected salary and availability to the \"Apply Now\" button.\n\n\u00a0* Data collected will be used for recruitment purpose only. It may be transferred to other companies of the Group to see if suitable vacancies arise. Applicants not contacted within 6 weeks may consider their application unsuccessful. The information will be destroyed.", "employment_types": ["Full Time", "Permanent"], "selling_points": ["Experience in Beauty Industry Preferred", "5 days work week, Birthday Leave, Free Goods", "Marketing, PR, Media"], "locations": ["Causeway Bay"], "categories": ["Marketing / Public Relations", "Marketing - Brand / Product Management", "Public Relations - Event Management", "Public Relations - General / Support"], "post_time": "2022-01-14T10:07:21Z", "salary": {"currency": null, "max": null, "min": null, "period": "monthly", "term": null}, "salary_visible": false, "title_keywords": ["assistant marketing manager", "senior marketing executive"], "responsibilities": ["management", "ideas", "explore new business opportunities", "edm", "quotation", "monitor", "implementation", "business analysis reports", "sales team", "plans", "ad-hoc projects"], "requirements": {"degrees": ["degree holder"], "majors": ["related disciplines", "marketing", "communications"], "languages": ["cantonese", "english", "mandarin"], "language_level": ["advantage", "proficient"], "hard_skills": [], "soft_skills": ["interpersonal skill", "communication", "attention to details", "meet deadlines", "creative", "work under pressure"], "languages_combined": [{"language": "cantonese", "language_level": ["proficient"]}, {"language": "english", "language_level": ["proficient"]}, {"language": "mandarin", "language_level": ["advantage"]}]}, "experience_required": {"duration": ["at least 3 years"], "field": ["retail industry", "fmcg", "agency", "beauty industry", "marketing", "relevant experience"]}}, {"job_id": "100003008825424", "location_code": "hk", "company": "", "job_title": "Event assistant/Promotion Manager", "description": "We are looking for\u00a0\n\n\nenergetic\u00a0candidates\nYoung and dynamic work environment\nTeam in Top Financial group in industry\n\nJob Description\n\nWork at exhibition on site job\u00a0\nDesign contingency solutions to personal and corporate clients\nWorking on follow up services to existing accounts\n\nThe Successful Applicant\n\nFresh graduates are welcomed\nDegree/Diploma or above\n1 year of related experience is preferable\nEquipped with outstanding interpersonal and communication skills\nProficiency in Cantonese and English (both in reading and writing)\nMandarin would be a bonus\n\nWhat's on Offer\n\nYou will be offered an exciting role where you can lead a highly motivated team. You can expect the working environment to be young, dynamic and energetic.\n\nYou will be entering an expanding team with a positive and winning mindset.\n\nOther benefits: group medical, year-end bonus, training, further study subsidies,\u00a0 etc.\n\nInterested candidates, please contact us at 60905847 for company details before applying.", "employment_types": ["Full Time", "Part Time", "Permanent"], "selling_points": ["Promotion & Event exhibition", "Outstanding Team in industry", "Fresh graduates are welcomed"], "locations": ["Tsim Sha Tsui"], "categories": ["Banking / Finance", "Financial Services", "Marketing / Public Relations", "Public Relations - Event Management"], "post_time": "2022-01-11T16:01:37Z", "salary": {"currency": "HKD", "max": 29999, "min": 20000, "period": "monthly", "term": null}, "salary_visible": true, "title_keywords": ["event assistant", "manager"], "responsibilities": [], "requirements": {"degrees": [], "majors": [], "languages": [], "language_level": [], "hard_skills": [], "soft_skills": [], "languages_combined": []}, "experience_required": {"duration": [], "field": []}}, {"job_id": "100003009047635", "location_code": "hk", "company": "Best Come Limited (Eaton Club)", "job_title": "Events Sales Executive", "description": "Responsibilities:\n\nIdentify new business opportunities and enhance sales on events and catering to achieve company\u2019s goals\nDevelop strategic planning on event, project management and budget control\nMaintain good relationship with guests and ensure professional interactions with local communities and business network\nDrive and lead events from initial concept to final delivery to meet clients\u2019 objectives\nPrepare proposal and presentation to clients\nLiaise with operation & F&B teams to ensure events are delivered professionally\nConduct market research on competitors\u2019 analysis and market trend\n\nRequirements:\n\nDegree holder\u00a0in\u00a0Event Management, Marketing, Hospitality Management\u00a0or\u00a0other\u00a0related disciplines\nAt least 1 years\u2019 experience in corporate event sales or account servicing\nGood relationship with major corporate clients like banks, financial firms, marketing events and conferences organizations is a definite advantage\nSales hunter personality, self-motivated, business results-oriented, passionate with success, and strong negotiation skill\nOutgoing, initiative and energetic personality with good customer services skill\nEnjoy interacting with people and being exposed to multi-cultural work environment\nGood command of both spoken and written English and Chinese (including Putonghua)\nCandidates with more experience will be considered as Assistant Event Sales Manager\n\nSalary and benefits will be commensurate with qualifications and experience.\u00a0 Interested parties, please send a full resume with present and expected salary, and date available to The Human Resources Department, 32/F., Great Eagle Centre, 23 Harbour Road, Wanchai, Hong Kong or e-mail to us.\u00a0\u00a0(Please quote the reference no. on the envelope and the covering letter.)\n\nTo know more about us, please visit our website at https://www.eatonclub.com.hk/\n\nWe are an equal opportunity employer and welcome applications from all qualified candidates.\n\nPersonal data collected will be treated in strict confidence and used only for recruitment-related purpose. Applicants who have not heard from us within four weeks may consider their applications unsuccessful. All personal data will be destroyed after 12 months.", "employment_types": ["Full Time", "Permanent"], "selling_points": ["Enhance sales on events & projects", "Drive and lead events for clients", "Co-working space & Business centre"], "locations": ["Central"], "categories": ["Hospitality / F & B", "Hospitality / Hotel Services", "Marketing / Public Relations", "Public Relations - Event Management", "Sales, CS & Business Devpt", "Account Servicing"], "post_time": "2022-01-14T03:37:44Z", "salary": {"currency": null, "max": null, "min": null, "period": "monthly", "term": null}, "salary_visible": false, "title_keywords": ["sales executive"], "responsibilities": ["strategic planning", "business opportunities", "conduct market research", "teams", "analysis", "develop", "maintain good relationship", "project management", "liaise with", "budget control", "catering"], "requirements": {"degrees": ["degree holder"], "majors": ["hospitality management", "related disciplines", "marketing"], "languages": ["putonghua", "english", "chinese"], "language_level": ["good command"], "hard_skills": [], "soft_skills": ["passionate", "outgoing", "self-motivated", "customer services skill", "negotiation skill", "energetic", "initiative"], "languages_combined": [{"language": "putonghua", "language_level": ["good command"]}, {"language": "english", "language_level": ["good command"]}, {"language": "chinese", "language_level": ["good command"]}]}, "experience_required": {"duration": ["at least 1 years"], "field": ["account servicing"]}}, {"job_id": "100003009042686", "location_code": "hk", "company": "CK Asset Holdings Limited", "job_title": "Promotion Officer", "description": "Degree\u00a0in Marketing /\u00a0PR / Communications or related disciplines\nAt\u00a0least 3 years\u2019 relevant experience in promotion, marketing or PR and with proven record in shopping malls / retail\nSelf-motivated, independent and detailed minded\nCreative, outgoing with good interpersonal and communication skills\nFamiliar with CRM, digital promotion and social media promotion\nBasic knowledge in Photoshop / graphic\u00a0design would be an advantage\nProficiency in MS Office & Chinese word processing\nExcellent command of written and spoken English\n\nWe will offer attractive compensation package to the right candidate. Please send application enclosing resume stating career and salary history, expected salary and date of availability\u00a0to The\u00a0Senior Manager, Human Resources\u00a0Department, CK Asset\u00a0Holdings Limited, 7/F Cheung Kong Center, 2 Queen's Road Central, Hong Kong or by clicking\u00a0\"Apply Now\" (in Word format). Please quote the reference of the position you apply for in all correspondences.\n\nWe are an equal opportunity employer and welcome applications from all qualified candidates. Personal data collected will be treated in strictest confidence and handled confidentially by authorized personnel for recruitment-related purposes within the Group. Applicants not hearing from us within six weeks from the date of advertisement may consider their applications unsuccessful.", "employment_types": ["Full Time", "Permanent"], "selling_points": ["Marketing in shopping mall", "Basic knowledge in Photoshop / graphic design", "Familiar with CRM"], "locations": ["Central"], "categories": ["Marketing / Public Relations", "Marketing - General / Support", "Marketing - Marketing Communication", "Public Relations - Event Management"], "post_time": "2022-01-13T18:54:50Z", "salary": {"currency": null, "max": null, "min": null, "period": null, "term": null}, "salary_visible": false, "title_keywords": ["officer"], "responsibilities": ["social media", "graphic design", "communication", "recruitment", "personal data"], "requirements": {"degrees": ["degree"], "majors": ["related disciplines", "marketing", "communications"], "languages": ["english", "chinese"], "language_level": ["proficiency", "excellent"], "hard_skills": ["chinese word processing", "basic", "word", "photoshop", "ms office"], "soft_skills": ["outgoing", "communication skills", "self-motivated", "confidence", "independent", "creative", "interpersonal", "detailed"], "languages_combined": [{"language": "english", "language_level": ["excellent"]}, {"language": "chinese", "language_level": ["proficiency"]}]}, "experience_required": {"duration": ["at least 3 years"], "field": ["pr", "marketing", "relevant experience", "retail"]}}, {"job_id": "100003009047642", "location_code": "hk", "company": "School of Continuing Education, HKBU", "job_title": "Programme Assistant (Ref. No.: PRSCE0031/21-22)", "description": "The appointee will be required to a) provide administrative and clerical support to academic programmes and daily office operation; b) liaise with part-time tutors, prepare contract requests and payroll related matters; c) answer student and public enquiries; and d) assist in event co-ordination and ad hoc projects. Shift duties may be required.\nMinimum Requirements:\nlHolders of Associate Degree / Higher Diploma with at least one year of relevant work experience ;\nlGood command of written and spoken English and Chinese;\nlEffective interpersonal skills, self-motivated and attention to details; and\nlProficiency in Chinese and English Word processing and MS Office applications, such as Word / Excel / Powerpoint.\nSalary will be commensurate with qualifications and experience.\nThose who have responded to the advertisement posted in December 2021 need not re-apply.\nApplication Procedure:\nApplicants are invited to submit their applications at the HKBU e-Recruitment System (jobs.hkbu.edu.hk). Shortlisted candidates will be invited to sit for computer and written tests. Applicants not invited for interview 8 weeks after the closing date may consider their applications unsuccessful. Details of the University's Personal Information Collection Statement can be found at http://hro.hkbu.edu.hk/pics.\nThe School reserves the right not to make an appointment for the post advertised, and the appointment will be made according to the terms & conditions then applicable at the time of offer.\nClosing date: 26 January 2022", "employment_types": ["Full Time"], "selling_points": [], "locations": ["Kowloon City"], "categories": ["Admin & HR", "Clerical / Admin Staff", "Marketing / Public Relations", "Public Relations - Event Management", "Public Relations - General / Support"], "post_time": "2022-01-14T03:38:54Z", "salary": {"currency": null, "max": null, "min": null, "period": "monthly", "term": null}, "salary_visible": false, "title_keywords": ["assistant"], "responsibilities": ["ad hoc projects", "recruitment", "administrative and clerical support", "liaise with", "payroll"], "requirements": {"degrees": ["associate degree", "diploma"], "majors": [], "languages": ["english", "chinese"], "language_level": [], "hard_skills": ["excel", "chinese and english word processing", "word", "powerpoint", "make", "c", "ms office"], "soft_skills": ["self-motivated", "interpersonal skills", "attention to details"], "languages_combined": [{"language": "english", "language_level": []}, {"language": "chinese", "language_level": []}]}, "experience_required": {"duration": ["at least one year"], "field": []}}, {"job_id": "100003009043599", "location_code": "hk", "company": "", "job_title": "Project Executive", "description": "Job Description :\n\nProvide products services, advice to corporate client and Handle cost control\nEvent management, Presentation and Maintain high standard of client services\nContact clients and Conduct digital marketing activity via social media including email, Zoom, WhatApp, Facebook, LinkedIn etc.\nJob Requirements:\n\nBachelor degree qualification or above, Fresh Graduates\nStrong communication skills\nProblem-solving abilities, Teamwork spirit and self-motivator\nPositive and driven attitude\nInterested candidates, please contact us at 28732733 for company details before applying.", "employment_types": ["Full Time", "Permanent", "Contract", "Internship"], "selling_points": [], "locations": ["Kwun Tong"], "categories": ["Sales, CS & Business Devpt", "Business Development", "Marketing / Public Relations", "Public Relations - Event Management", "Digital Marketing"], "post_time": "2022-01-12T23:19:20Z", "salary": {"currency": null, "max": null, "min": null, "period": "monthly", "term": null}, "salary_visible": false, "title_keywords": ["project executive"], "responsibilities": ["social media", "management", "maintain", "digital marketing", "contact", "cost control", "facebook"], "requirements": {"degrees": ["degree", "bachelor"], "majors": [], "languages": [], "language_level": [], "hard_skills": ["problem-solving"], "soft_skills": ["communication skills", "problem-solving", "teamwork spirit", "driven", "positive"], "languages_combined": []}, "experience_required": {"duration": [], "field": []}}, {"job_id": "100003009044354", "location_code": "hk", "company": "Hong Kong Disneyland", "job_title": "Senior Event Services Manager", "description": "Job Summary:\nWorking closely with event sales teams in each market, the job holder will be responsible for overall management of Event Services team and deliver the highest quality service at Disney standard to various kinds of Business Solutions & Events (BS&E) events, including corporate events, wedding events, and social catering events.\nResponsibilities:\nLead a team of Event Services professionals to manage and deliver various types of BS&E events that take place in the resort hotels and in Hong Kong Disneyland Park, and ensure the team consistently offer world-class level of service to drive client and guest satisfaction for each event;\nDrive creation and capturing of upselling/ cross-selling opportunities during the course of event management and delivery with each client, and contribute to revenue generation under overall BS&E team;\nLead and support the team on problem solving and solution formulation during the event delivery process, when there are conflicts/ inconsistency among clients\u2019 requests, standards/ requirement from internal stakeholders, available resources, government regulations, etc.;\nLead the team to maintain high standard of storage and upkeep for key reusable amenities and props for BS&E event formats, and/ or to request replenishment of consumable items when necessary, in close collaboration with different vendors and internal partners;\nDrive knowledge management efforts among the team, to ensure all team members have the training and resources to carry out their current responsibilities and get ready for more, as well as continuous product, process, systems and operational knowledge refresh;\nContinuously explore ways to streamline and improve event management and delivery processes, to improve work efficiency and quality;\nAct as a primary internal point of contact for the team in terms of different operational issues, or cross-department projects/initiatives.\nBasic Qualifications:\nBachelor degree or above;\nAt least 7 years of event management experience with a luxury hotel/ resort/ venue, with extensive knowledge in hospitality management, food & beverage and banquet catering operations.\nExperience with operational teams within HKDL and/ or experience in handling sizable groups and events would be an advantage;\nDemonstrated track-record and ability to lead a team;\nBe able to work independently and under pressure, in an ever-changing business environment;\nExcellent presentation, problem solving, negotiations and coaching skills;\nExcellent written (English and Chinese) and verbal (English, Cantonese, Mandarin) communication skills.\nAdditional Information:\nSUBMITTING YOUR APPLICATION\nAfter clicking \u201cApply for this job\u201d below, the employment application will open in a new window. Please complete ALL pages of the application in ENGLISH by clicking \u201cNext\u201d on each page, then \u201cSubmit\u201d on the final page.\n#LI-GN1 HKProfessional", "employment_types": ["Full Time"], "selling_points": ["Lead and support the team on problem solving", "Bachelor degree or above", "7 years of event management experience"], "locations": ["Lantau Island"], "categories": ["Marketing / Public Relations", "Management", "Public Relations - Event Management", "Others"], "post_time": "2022-01-13T03:49:23Z", "salary": {"currency": null, "max": null, "min": null, "period": "monthly", "term": null}, "salary_visible": false, "title_keywords": ["manager"], "responsibilities": ["regulations", "management", "operations", "systems", "quality", "teams", "replenishment", "communication", "lead a team", "maintain", "contact", "support the team", "catering"], "requirements": {"degrees": ["degree or above", "bachelor"], "majors": [], "languages": ["cantonese", "english", "chinese", "mandarin"], "language_level": ["excellent"], "hard_skills": ["problem solving", "basic"], "soft_skills": ["communication skills", "work independently", "under pressure", "responsible", "changing business environment", "problem solving", "extensive", "presentation", "world-class"], "languages_combined": [{"language": "cantonese", "language_level": ["excellent"]}, {"language": "english", "language_level": ["excellent"]}, {"language": "chinese", "language_level": ["excellent"]}, {"language": "mandarin", "language_level": ["excellent"]}]}, "experience_required": {"duration": ["at least 7 years"], "field": ["food", "management"]}}, {"job_id": "100003009043317", "location_code": "hk", "company": "Peoplus Recruitment", "job_title": "Event Producer / Audio-Visual System Administrator (US based investment firm)", "description": "Our client is\u00a0one of the leading video conference solution provider, they are currently looking for\u00a0a high caliber to fill up above positions for their business expansion.\n\nEvent Producer / Audio-Visual System Administrator (US based investment firm)\n\nResponsibilities\n\nLiaise with Event and Roadshow support areas to determine business requirements and deliver timely and cost-effective technical solutions for events\nPlanning and execution of technical requirements for conferences and roadshow events at hotels and other similar venues\nAttend site inspections and pre-con meetings, develop room drawings and budget estimates, coordinate and execute pre/post production plans, oversee internal and outsourced technicians, complete post-event invoice and budget reconciliation\nOperation of portable LCD projectors, video record and playback equipment, audio recorders, P/A systems, microphones, audio mixers and amplifiers and associated screens, speakers and sets\nCoordinate the creation of digital messaging and content with internal and external content teams\n\nRequirements\n\nKnowledge of virtual meeting rooms is essential\nMinimum of 3-5 years' experience in audio, video, staging or related field\nFamiliarity with audio conference and video conference systems (especially Webex and Zoom)\nFamiliarity with auditorium systems including recording and playback equipment, camera and related controls, video switchers, routing equipment and audio mixing equipment\nFamiliarity with PC, LAN, streaming audio/video and telecommunications operations and terminology\nHigh energy level; ability to work in a fast-paced environment\nFlexible, adaptable team-player\nDisplay a professional and courteous manner to all clients, technical and support staff\nProficient in Microsoft Office applications, primarily PowerPoint\nFluent English is a must\n\nAttractive remuneration package and excellent career prospects will be provided to the right candidate.\n\nInterested parties please send full resume with followings to cv2@ peoplus.com.hk\n1. Current & Expected Salary\n2. Availability\n3. Date of Achievement : Academic Result\n4. Quoting the Emp. Ref. No. : EK220112-01\n\nAll personal data provided by job applicants will be used for recruitment purpose only", "employment_types": ["Full Time", "Permanent"], "selling_points": ["As Event & Roadshow support in a US investment Co.", "Fluent English is a must", "Knowledge of virtual meeting rooms"], "locations": ["Not Specified"], "categories": ["Banking / Finance", "Others", "Marketing / Public Relations", "Public Relations - Event Management", "Others"], "post_time": "2022-01-12T10:42:02Z", "salary": {"currency": null, "max": null, "min": null, "period": "monthly", "term": null}, "salary_visible": false, "title_keywords": ["producer", "system administrator"], "responsibilities": ["cost", "invoice", "budget", "systems", "teams", "develop", "drawings", "coordinate", "conferences", "site inspections", "liaise with", "plans", "audio", "planning"], "requirements": {"degrees": [], "majors": [], "languages": ["english"], "language_level": ["fluent"], "hard_skills": ["pc", "powerpoint", "microsoft office"], "soft_skills": ["flexible", "courteous", "fast-paced environment", "team-player", "adaptable"], "languages_combined": [{"language": "english", "language_level": ["fluent"]}]}, "experience_required": {"duration": ["minimum of 3-5 years"], "field": ["related", "video"]}}, {"job_id": "100003009044751", "location_code": "hk", "company": "The Hong Kong Polytechnic University", "job_title": "Administrative Assistant", "description": "SPRG is a leading, award winning and caring public relations group with headquarters in Hong Kong and operation overseas. The right candidate will be working for our clients that are listed or ready-to-list on the stock exchanges, to plan and implement their ongoing investor relations and media relations campaigns\u00a0and IPO communications programs.\n\nResponsibilities:\n\nFormulate comprehensive financial communication strategies and proposals for clients\nHands-on approach to ensure perfect implementation\nDevelop new clients\n\nGeneral Requirements:\n\nUniversity graduate\n5+ years' solid experience as a financial PR veteran\nGood writing skill and in-depth knowledge of media relations and financial markets\nExcellent command in both written and spoken English & Chinese\nMandarin proficiency is preferred\nPleasant and mature personality, good mastery of analytical, presentation and problem solving skills, strong leadership and detail-minded\nSophisticated in PowerPoint and\u00a0other computer softwares\n\nInterested parties please complete the standard application form by clicking the\u00a0Apply now\u00a0button. You can also attach your tailored CV and Cover letter with your current and expected salary which we will use to review applications.\u00a0\n\nIt is Our Company policy to comply with the requirements of the Personal Data (Privacy) Ordinance (Cap. 486) of the Laws of the Hong Kong Special Administrative Region. Any personal data which is collected shall be handled in accordance with this Personal Information Collection Statement (\u201cPICS\u201d).\n\n\nThe personal data collected from you will be used for purposes relating to your application for employment with the Company. You must ensure that all personal data provided to the Company are accurate, complete and up-to-date. For correction of or access to personal data after submission of the job application or enquiries on recruitment matters, please contact the HR or subject officer as specified in the recruitment advertisement.\n\nWebsite:\u00a0\u00a0www.sprg.com.hk\u00a0/\u00a0www.sprg.asia\n\nFacebook:\u00a0\u00a0https://www.facebook.com/SPRGAsia\u00a0/\u00a0https://www.facebook.com/CSR.SPRG\u00a0", "employment_types": ["Full Time"], "selling_points": [], "locations": ["Not Specified"], "categories": ["Admin & HR", "Clerical / Admin Staff", "Others", "Marketing / Public Relations", "Public Relations - Event Management"], "post_time": "2022-01-13T06:08:51Z", "salary": {"currency": null, "max": null, "min": null, "period": "monthly", "term": null}, "salary_visible": false, "title_keywords": ["administrative assistant"], "responsibilities": ["communication", "implementation", "develop"], "requirements": {"degrees": ["university graduate"], "majors": [], "languages": ["english", "chinese", "mandarin"], "language_level": ["excellent", "proficiency"], "hard_skills": ["problem solving skills", "powerpoint", "writing skill"], "soft_skills": ["detail-minded", "sophisticated", "mature", "pleasant", "writing skill", "problem solving skills", "leadership", "presentation"], "languages_combined": [{"language": "english", "language_level": ["excellent"]}, {"language": "chinese", "language_level": ["excellent"]}, {"language": "mandarin", "language_level": ["proficiency"]}]}, "experience_required": {"duration": ["5+ years"], "field": ["pr", "financial"]}}, {"job_id": "100003009049646", "location_code": "hk", "company": "Strategic Financial Relations (China) Ltd.", "job_title": "Consultant / Senior Consultant", "description": "Responsibility:\n\n- Execution and follow up of events and marketing programs\n\n- Day-to-day liaison with clients and vendors on job progress\n\n- Provide support and coordinate with internal project team and external parties\n\nRequirement:\n\n- Minimum 1 year experience in event management and/or exhibition industry\n\n- Excellent interpersonal, presentation and communication skills\n\n- Good team spirit and ability to work under pressure\n\n- Requested to work on holidays occasionally\n\n- Candidate with less experience will be considered as Project Assistant.\n\n- Immediate availability is an advantage\n\n\n\n\u00a0 Please send the CV and expected salary to our email.\n\n\n\u00a0(Personal data collected will be used for recruitment purpose only.)", "employment_types": ["Full Time", "Permanent"], "selling_points": ["Public Relations - Financial", "5 Days Work/ Bank Holiday", "12 -15 Days AL/B-day Leave/Medical&Life Insurance"], "locations": ["Admiralty"], "categories": ["Marketing / Public Relations", "Public Relations - Copy-writing", "Public Relations - Event Management", "Public Relations - General / Support"], "post_time": "2022-01-14T09:01:01Z", "salary": {"currency": null, "max": null, "min": null, "period": "monthly", "term": null}, "salary_visible": false, "title_keywords": ["senior consultant", "consultant"], "responsibilities": ["provide support", "external parties", "coordinate with"], "requirements": {"degrees": [], "majors": [], "languages": [], "language_level": [], "hard_skills": [], "soft_skills": ["communication skills", "team spirit", "interpersonal", "presentation", "work under pressure"], "languages_combined": []}, "experience_required": {"duration": ["minimum 1 year"], "field": ["management"]}}, {"job_id": "100003009048083", "location_code": "hk", "company": "iPR Ogilvy Limited", "job_title": "Associate (Financial PR)", "description": "(Long-term contract)\n\nResponsibilities\n\nThe incumbent will be responsible for collaborate with contractors and internal parties for various Retail projects, monitor projects\u2019 progress as schedule, attend field work for quality control and compliance, and other ad hoc duties as assigned by supervisor.\n\nRequirements\n\n-Diploma or above\n-2 years or above working experience, preferably in retail industry\n-Knowledge in Electronics / Electrical Applications will be an advantage\n-Be creative, self-motivated, responsible, good team player and able to work under tight schedule\n-Strong planning and organization skill\n-Capable in solving on-site problems with rationales\n-Good communication and management skills\n-Good command of both spoken and written Chinese and English\n-Work on shift / night work is required at interval\n\nApplications including details of qualifications, working experience, expected salary, contact telephone number and address should be applied via:\u00a0http://careers.oceanpark.com.hk\u00a0--> Job opening --> Full time/ Long-term.\n\nApplicants not contacted within six weeks may consider their application unsuccessful. Personal data collected will be used for recruitment-related purpose only.", "employment_types": ["Full Time", "Permanent"], "selling_points": ["Proactive, creative, good team spirit", "Degree holder with 1 year of relevant experience", "Excellent communication skills"], "locations": ["Wan Chai"], "categories": ["Marketing / Public Relations", "Marketing - Marketing Communication", "Public Relations - Event Management", "Public Relations - General / Support"], "post_time": "2022-01-14T04:44:14Z", "salary": {"currency": null, "max": null, "min": null, "period": "monthly", "term": null}, "salary_visible": false, "title_keywords": ["associate"], "responsibilities": ["collaborate with", "ad hoc duties", "compliance", "monitor", "schedule", "quality control", "internal parties"], "requirements": {"degrees": [], "majors": [], "languages": ["english", "chinese"], "language_level": [], "hard_skills": [], "soft_skills": ["good team player", "self-motivated", "responsible", "organization skill", "communication", "creative"], "languages_combined": [{"language": "english", "language_level": []}, {"language": "chinese", "language_level": []}]}, "experience_required": {"duration": [], "field": ["retail industry"]}}, {"job_id": "100003009042105", "location_code": "hk", "company": "Ocean Park Corporation", "job_title": "Project Officer (Retail Operations Department)", "description": "Are you looking for a role where you can learn, grow, excel and get experience and exposure to a startup environment? If you\u2019re someone who loves being in the mix of teamwork and gets excited about developing and executing PR and media plans, then we have a role for you!\n\nDuties and Responsibilities\n\nTo generate local & international PR and media coverage on prints and online platforms.\nProvide copywriting for corporate communications materials such as website, newsletters, video script, corporate pamphlets, annual reports, and other promotional publicity\nHandling PR crisis\nTo develop and implement PR plans\nTo drive impact, develop a media plan to maximize the exposure and media coverage\nPlan and implement the press event, public engagement, and health events\nInitiate and implement CSR communication programs\nAdvise internal departments on preparation and research on communications projects\nExcellent content management, copywriting, presentation, and communication skills\n\nRequirement\n\nDegree holder preferably major in Communications, Journalism, Public Relations, or relevant disciplines\n5 years + solid experience in public relations, event management, and communications, preferably in a PR agency or able organization\nFamiliar with the media environment and strong in media relations, with well-established relationships and network with local and international media is highly preferred\nExcellent written and verbal communication skills in English and Chinese.\nSelf-motivated, dedicated with strong problem solving and communications skills, good team player, and can work independently.\nExcellent command in both spoken and written English, Cantonese, and Putonghua", "employment_types": ["Full Time", "Contract"], "selling_points": ["retail projects", "Diploma or above", "2 years or above working experience"], "locations": ["Aberdeen"], "categories": ["Engineering", "Electrical / Electronics", "Marketing / Public Relations", "Public Relations - Event Management", "Others"], "post_time": "2022-01-12T06:10:22Z", "salary": {"currency": null, "max": null, "min": null, "period": "monthly", "term": null}, "salary_visible": false, "title_keywords": ["operations", "project officer"], "responsibilities": ["management", "website", "develop", "communication", "reports", "plan", "plans"], "requirements": {"degrees": ["degree holder"], "majors": ["journalism", "communications"], "languages": ["cantonese", "putonghua", "english", "chinese"], "language_level": ["excellent"], "hard_skills": ["problem solving"], "soft_skills": ["communication skills", "self-motivated", "work independently", "good team player", "problem solving"], "languages_combined": [{"language": "cantonese", "language_level": ["excellent"]}, {"language": "putonghua", "language_level": ["excellent"]}, {"language": "english", "language_level": ["excellent", "excellent"]}, {"language": "chinese", "language_level": ["excellent"]}]}, "experience_required": {"duration": ["5 years +"], "field": ["agency", "management", "public relations", "pr"]}}, {"job_id": "100003009043610", "location_code": "hk", "company": "GOFA", "job_title": "Assistant Public Relations Manager (NGO/Education/Event) - freelance", "description": "Our future success depends on the diverse talent and performance of dedicated employees. We now call for applications to fill this position which is financially supported by the Home Affairs Bureau\u2019s Arts and Sports Development Fund. The position is under the Marketing and Communications Department in the organization structure of HKFA. Reporting to the Public Relations and Communications Manager, the appointee is responsible for the following:\nJob Descriptions\nTo assist with the management of media relations and the delivery of the HKFA\u2019s communications strategy\nTo assist the PR and Communications Manager in the planning, development, implementation and evaluation of PR campaigns to meet the Association\u2019s mission, increase public awareness and enhance the image of the HKFA\nUnder the direction of the PR and Communications Manager, to respond to public and media enquiries\nTo proactively promote the HKFA brand and create a positive corporate image\nTo work with agency / stakeholders, to conduct market research, develop appropriate strategies, to collect and report information, and use feedback to guide current and future PR and media efforts\nTo prepare press statements and regular communication materials with stakeholders to be approved by the PR and Communications Manager\nTo ensure that all PR and Media dealings are coordinated with other marketing and management initiatives\nTo be responsible for the production of events from conception through to completion, e.g. press conference, event launch, most valuable player award and etc.\nTo perform on-site event management including venue logistics co-ordinations, rehearsals, rundown handling and stage management\nTo contribute on the post event evaluation reports to inform future event planning\nTo assist in more general HKFA marketing and promotional activities, events and programmes as instructed by the PR and Communications Manager\nTo perform such other duties and responsibilities as instructed by the Chief Executive Officer and PR and Communications Manager\nQualifications and Experience\nUniversity degree in Communications/Business Administration/Public Relations or related discipline\nMinimum of 5 years and preferably 10 years of relevant experience in media relations\nGood command of written and spoken English, Cantonese and (preferably) Mandarin\nStrong communication & interpersonal skills, confident in facing public and media\nKnowledge and interest in football / sports will be advantageous\nWilling to learn, detail minded and a good team player\nProficient in PC skills (MS Word, Excel, PowerPoint, Chinese character input)\nExpected to work overtime, irregular hours and some weekends and public holidays when required\nApplicants with less experience may be considered for the post of Assistant Public Relations and Communications Officer\nThe successful candidate will be offered on a contract term employment. Starting salary will be commensurate with qualifications and experience. Our employee benefits include Group Medical and Life Insurance to the right candidate.\u00a0\nDeadline: 19 January 2022\nPlease ensure that you have explored the following official link which lists the relevant instructions before making an application:\nwww.hkfa.com/en/load_page/82\n\nThe information provided by the applicants will be treated in strict confidence and will only be used for the purpose of considering your employment application.\nPLEASE DO NOT USE \u201cAPPLY NOW\u201d FUNCTION.", "employment_types": ["Freelance"], "selling_points": ["5 years + solid experience in public relation", "NGO/ Education/ Event", "freelance"], "locations": ["Central"], "categories": ["Marketing / Public Relations", "Public Relations - Event Management", "Public Relations - General / Support"], "post_time": "2022-01-13T00:40:40Z", "salary": {"currency": null, "max": null, "min": null, "period": "monthly", "term": null}, "salary_visible": false, "title_keywords": ["manager", "assistant"], "responsibilities": ["administration", "reporting", "management", "other duties", "conduct market research", "implementation", "develop", "communication", "logistics", "reports", "promotional activities", "evaluation", "report", "planning"], "requirements": {"degrees": ["university degree"], "majors": ["business administration", "communications"], "languages": ["cantonese", "english", "chinese", "mandarin"], "language_level": ["good command", "proficient"], "hard_skills": ["excel", "inform", "powerpoint", "pc skills", "ms word"], "soft_skills": ["confident", "good team player", "work overtime", "responsible", "willing to learn", "communication", "diverse", "interpersonal skills", "positive"], "languages_combined": [{"language": "cantonese", "language_level": ["good command"]}, {"language": "english", "language_level": ["good command"]}, {"language": "chinese", "language_level": ["proficient"]}, {"language": "mandarin", "language_level": ["good command"]}]}, "experience_required": {"duration": ["10 years", "minimum of 5 years"], "field": ["public relations", "relevant experience", "media"]}}, {"job_id": "100003009045965", "location_code": "hk", "company": "The Hong Kong Football Association Ltd", "job_title": "Public Relations and Communications Officer", "description": "Manager/ Assistant Manager (at the rank of\u00a0Administrative Assistant II/Executive Officer) (several posts) in the LKS Faculty of Medicine (Ref.: 511518)\u00a0(to commence as soon as possible, on a two- to three-year fixed-term basis with contract-end gratuity and University contribution to a retirement benefits scheme, totalling up to 10% of basic salary, with the possibility of renewal subject to satisfactory performance)\n\nApplicants should possess a good university degree with at least 5 years' experience in events, communications, journalism and/or public relations, at a public/quasi-public organization. They should have exceptional communications, interpersonal, organizational and problem-solving skills; and the ability to produce high-quality outputs in a fast-paced environment.\u00a0 The ability to handle several projects simultaneously, manage and meet multiple deadlines is a must. Applicants with less experience may be considered for appointment as Executive Officer.\n\nThe appointees will play a versatile role in one or more of the following areas: (i) knowledge exchange and faculty advancement; (ii) digital communications and social media; (iii) branding and marketing; (iv) event management and production; (v) media relations; (vi) publications; (vii) alumni affairs; and (viii) admissions & outreach. They may also be tasked to perform other job-related duties and projects as assigned in support of the Faculty's mission, core values and goals.\n\nThe appointments will be made under the Faculty, and the appointees may be posted to school/department/faculty office in a rotational manner and provide support to one or more of the said functional areas. Work outside office hours and on weekends may be required occasionally. Shortlisted candidates will be invited to attend an interview and/or written test.\n\nA highly competitive salary commensurate with qualifications and experience will be offered, in addition to annual leave and medical benefits.\n\nThe University only accepts online application for the above posts. Applicants should apply online at the University\u2019s careers site (https://jobs.hku.hk) and upload an up-to-date C.V.\u00a0Review of applications will start from January 27, 2022 and continue until\u00a0February 23, 2022, or until the posts are filled, whichever is earlier.\n\nThe University is an equal opportunities employer and\nis committed to equality, ethics, inclusivity, diversity and transparency", "employment_types": ["Full Time", "Contract"], "selling_points": [], "locations": ["Mong Kok"], "categories": ["Marketing / Public Relations", "Public Relations - Event Management", "Public Relations - General / Support", "Others"], "post_time": "2022-01-13T09:15:03Z", "salary": {"currency": null, "max": null, "min": null, "period": "monthly", "term": null}, "salary_visible": false, "title_keywords": ["communications officer"], "responsibilities": ["social media", "management", "quality", "provide support"], "requirements": {"degrees": ["university degree"], "majors": ["journalism", "communications"], "languages": [], "language_level": [], "hard_skills": ["problem-solving skills", "basic", "scheme", "exchange"], "soft_skills": ["fast-paced environment", "organizational", "versatile", "exceptional communications", "problem-solving skills", "interpersonal"], "languages_combined": []}, "experience_required": {"duration": ["at least 5 years"], "field": ["public relations"]}}, {"job_id": "100003009046421", "location_code": "hk", "company": "The University of Hong Kong", "job_title": "Manager/ Assistant Manager (at the rank of Administrative Assistant II/Executive Officer)", "description": "HKSTP InnoAcademy (innoacademy.hkstp.org) is HKSTP\u2019s initiative to nurture, inspire and engage talent for innovation and technology (I&T) careers in Hong Kong. Our vision is to develop Hong Kong into a global I&T talent hub that draws Hong Kong, Mainland and overseas I&T talent.\nWe are looking for a seasoned professional who is passionate about talent development for Hong Kong\u2019s I&T sector to join our growing and committed team. As a key member of the team, you will grow and manage the community of talent who have participated in HKSTP\u2019s talent initiatives, as well as the broader I&T talent pool in Hong Kong and the Guangdong-Hong Kong-Macau Greater Bay Area (GBA).\nThe overarching goals are to engage and retain the talent who are already in our ecosystem so as to turn them into advocates / ambassadors for Hong Kong and HKSTP, as well as draw more local and non-local talent to join Hong Kong\u2019s I&T sector and build a vibrant I&T talent community in Hong Kong and the GBA.\nYou\u2019re a people person who is extroverted and always happy to learn more about communities and what motivates them. You know communities and their members so well that not only do you connect with them, but also connect them with each other when you see synergy. You also have a nose for success stories in the community, and a passion for making the community and its culture stronger and better. You should have previous experience engaging with and managing communities in your career, whether they are professional associations, customer groups, alumni, etc.\nResponsibilities:\nWork with Senior Manager to grow Hong Kong\u2019s I&T talent community, as well as ideate, plan, promote and manage high-impact online and offline branding campaigns to drive perception of Hong Kong\u2019s I&T sector as the \u201cEmployer of Choice\u201d among local and non-local talent.\nDeliver engagement initiatives and activities to build a vibrant I&T talent community and culture in the HKSTP ecosystem in Hong Kong and the GBA\nEngage and grow community via events, social channels, e-newsletters, and various promotion channels\nGather feedback from members, talents and partners for the team to constantly improve/optimize InnoAcademy\u2019s community features, activities and benefits\nMeasure engagement initiatives / activities\u2019 effectiveness, community member activity and impact\nPerform any other duties as assigned by supervisors\nRequirements:\nBachelor\u2019s degree in Marketing, Human Resource Management, Communication, Social Science, Business or other related disciplines\nAt least 5 years of relevant experience in marketing, branding or community building, preferably in the I&T sector or an employer branding capacity. Candidates with less experience will be considered for lower position.\nStrong in project management and execution in a fast-paced, dynamic environment\nExperienced in working with a wide range of internal and external stakeholders to drive impactful results\nFamiliar with social channels (LinkedIn, Facebook, Instagram) and their related metrics\nA self-starter who is innovative, entrepreneurial, goal-getting, detail-oriented, and able to work under tight schedule\nExcellent interpersonal and communication skills in verbal and written English and Chinese, including Cantonese and Putonghua\nExtensive network within the I&T and/or tertiary education sectors in Hong Kong and the GBA will be a definite advantage\nGBA, Mainland and international working experience will be a plus\nWe offer market competitive compensation, 5-day work week, and generous benefits including medical and life insurance; and voluntary contribution in addition to the legal minimum MPF.\u00a0 To apply, please send your full resume with current and expected salary to the Human Resources & Office Administration Department, Hong Kong Science and Technology Parks Corporation, 5/F, Building 5E, 5 Science Park East Avenue, Hong Kong Science Park, Hong Kong or, by email via \"Apply Now\"\u00a0on or before 27 January 2022.\u00a0 \u00a0Please quote the reference number on the email subject/envelope and the application letter.\u00a0\nPersonal data provided will be treated in strict confidence and used for recruitment purpose only.\u00a0 All personal data collected will be used strictly in accordance with employer\u2019s personal data policies, you can access to HKSTP\u2019s Personal Information Collection Statement at https://www.hkstp.org/hkstp_web/en/hkstp/personal-information-collection-statement-recruitment\nApplicants not invited for interview within four weeks after application deadline may consider their applications unsuccessful.\u00a0 Personal data of unsuccessful applicants will be retained for a maximum of two years.\u00a0\nwww.hkstp.org", "employment_types": ["Contract"], "selling_points": ["possess a good university degree", "5 years' experience in events/communications", "annual leave and medical benefits"], "locations": ["Pok Fu Lam"], "categories": ["Marketing / Public Relations", "Public Relations - Event Management"], "post_time": "2022-01-13T10:58:02Z", "salary": {"currency": null, "max": null, "min": null, "period": "monthly", "term": null}, "salary_visible": false, "title_keywords": ["administrative assistant", "assistant manager", "executive officer", "manager"], "responsibilities": ["any other duties", "plan"], "requirements": {"degrees": ["degree", "bachelor"], "majors": ["business", "science", "related disciplines", "marketing"], "languages": ["cantonese", "putonghua", "english", "chinese"], "language_level": ["excellent"], "hard_skills": ["plus", "project management", "goal", "dynamic", "facebook"], "soft_skills": ["communication skills", "dynamic environment", "detail-oriented", "communication", "project management", "innovative", "extensive", "interpersonal"], "languages_combined": [{"language": "cantonese", "language_level": ["excellent"]}, {"language": "putonghua", "language_level": ["excellent"]}, {"language": "english", "language_level": ["excellent"]}, {"language": "chinese", "language_level": ["excellent"]}]}, "experience_required": {"duration": ["at least 5 years"], "field": ["marketing", "relevant experience"]}}, {"job_id": "100003009050956", "location_code": "hk", "company": "Hong Kong Science & Technology Parks Corporation", "job_title": "Manager, Talent Engagement, HKSTP InnoAcademy [JDB/MTEHKSTPI/220114]", "description": "Established in 2009, Hong Kong Green Building Council (\u201cthe Council\u201d) is the leading body, co-founded by four major construction industry and environmental organisations, driving the market transformation towards green and sustainable buildings in Hong Kong through engagement with the industry, the government and broader community.\n\nHKGBC is expanding its secretariat team in line with its positioning as Hong Kong's leading member-based body dedicated to green building development, with opening for the post of Senior Marketing & PR Executive:\n\nJob Description\n\nAssist the Marketing & PR Manager to plan, organise and execute all marketing and communications related duties including:\n\nKey Roles:\n\nTo develop various online and offline marketing collaterals from conception, content development, layout design to production\nTo manage online and offline marketing channels including but not limited to corporate publications, reports, official website, social media (Facebook, LinkedIn and Instagram) or other related applications\nTo prepare editorial contents such as council announcements, press releases, speeches, presentations, monthly e-newsletter, etc.\nTo conduct translation and copywriting duties\nTo organise and follow through the planning, budget control, execution and logistic arrangements of various types of events, including large scale international and regional conferences, award presentations, press conferences, exhibitions, public campaigns, seminars and site visits, etc.\nTo liaise with media and respond to media enquiries\nTo assist in corporate marketing and project marketing initiatives\nTo assist in corporate website development and content management\nTo coordinate with event and PR agencies or other vendors and monitor the service delivery\nTo build good rapport among the NGO community, media and relevant stakeholders\nTo support the team in other activities as required and necessary.\u00a0 \u00a0 \u00a0 \u00a0 \u00a0\n\n\u00a0Requirements:\n\nDegree holder in Marketing, Communications, Language, Sustainability, Business or related disciplines\nOver 4 years of working experience, preferably in corporate communications, Journalism, marketing, PR, social media or translation; less experience will be considered as Marketing & PR Executive\nStrong translation and writing skills\nProficiency in Adobe Photoshop, Illustrator and InDesign would be an asset\nExperience in video production would be an advantage\nCan work independently with minimal supervision\nAn enthusiastic team player with a mature, pleasant and sociable personality\nGood project management skills, multi-tasking, detail-minded and able to meet tight deadlines\nMeticulous, self-motivated with a strong sense of responsibility\nAble to work under pressure and irregular hours\nPassion towards building a sustainable city and endorsing a green lifestyle\n\n\u00a0How to Apply\n\nThe Council is an equal opportunity employer and offers attractive career prospects and remuneration to our staff. Recruitment will be initially under contract terms of two years with the possibility of converting to a permanent post. Interested applicants please apply by sending\u00a0full resume with date of availability, present and expected salary, contact telephone number, as well as results of public examinations\u00a0to the\u00a0Executive Director, Hong Kong Green Building Council\u00a0via e-mail\u00a0careers@ hkgbc.org.hk, or by post to\u00a01/F, Jockey Club Environmental Building, 77 Tat Chee Avenue, Kowloon Tong, Hong Kong. Please state the position you want to apply for on the envelope.\n\n(N.B. Application with incomplete information as requested above may not be considered.)\n\nApplicants who do not receive a response within six weeks from the date of this advertisement may consider their applications filed for future reference. Personal data will be used strictly for recruitment related purposes only and retained for no more than six months.", "employment_types": ["Full Time"], "selling_points": [], "locations": ["Shatin Area"], "categories": ["Marketing / Public Relations", "Marketing - Marketing Communication", "Public Relations - Event Management", "Others"], "post_time": "2022-01-14T12:01:14Z", "salary": {"currency": null, "max": null, "min": null, "period": "monthly", "term": null}, "salary_visible": false, "title_keywords": ["manager"], "responsibilities": ["layout design", "marketing collaterals", "website", "plan", "liaise with", "facebook", "budget control", "service delivery", "monitor", "presentations", "develop", "conferences", "reports", "social media", "management", "coordinate with", "contents", "support the team", "planning"], "requirements": {"degrees": ["degree holder"], "majors": ["business", "related disciplines", "marketing", "communications"], "languages": [], "language_level": [], "hard_skills": ["no", "indesign", "adobe photoshop", "illustrator", "writing skills", "project management", "translation"], "soft_skills": ["detail-minded", "meticulous", "work independently", "meet tight deadlines", "self-motivated", "sense of responsibility", "project management skills", "sociable", "mature", "writing skills", "pleasant", "multi-tasking", "enthusiastic", "team player", "work under pressure"], "languages_combined": []}, "experience_required": {"duration": ["4 years"], "field": ["video production", "social media", "pr", "marketing"]}}, {"job_id": "100003009046284", "location_code": "hk", "company": "Hong Kong Green Building Council Limited", "job_title": "Senior Marketing & PR Executive", "description": "Job Title:\u00a0\u00a0Marketing Executive\n\nCompany Name:\u00a0Geospatial Lab\n\nLocation:\u00a0Kwun Tong\n\nQualification and Experience Requirements\n\n(1) Bachelor degree holder or equivalent;\n\n(2) Minimum 3 years of working experience;\n\u00a0 \u00a0 \u00a0 Experiences in event management, public relations,\n\u00a0 \u00a0 \u00a0 online or real-time news\u00a0 environment will be an advantage;\n\n(3) Proficiency in written Chinese and competency in English;\n\n(4) Good computer literacy;\n\n(5) Good understanding of Hong Kong public affairs.\n\n\u00a0Responsibilities\n\n1. Develop content of marketing materials (DMs, presentation materials) and ensure articles that have appropriate visual elements;\n\n2. Post message on website and social media;\n\n3. Develop strategies to drive traffic to the Geolab\u2019s website and social media platform;\n\n4. Provide regular digital marketing data analysis and report;\n\n5. Assist Business Officer in Geolab engagement activities (liaise with working partners, collaborating organisations and stakeholders, onsite support, etc);\n\n6. Any other duties assigned by the GeoLab Manager.\n\nTo apply\n\nIf you are interested in the post, please send your resume together with your present and expected salaries by email to Smart City Consortium.\n\n\n\u00a0Enquiries\n\nPlease contact us at 3480 4230 or by email.", "employment_types": ["Full Time", "Contract"], "selling_points": [], "locations": ["Kowloon City Area"], "categories": ["Media & Advertising", "Editorial / Journalism", "Marketing / Public Relations", "Marketing - Marketing Communication", "Public Relations - Event Management"], "post_time": "2022-01-13T10:16:39Z", "salary": {"currency": null, "max": null, "min": null, "period": "monthly", "term": null}, "salary_visible": false, "title_keywords": ["executive"], "responsibilities": ["social media", "any other duties", "develop strategies", "website", "develop", "data analysis", "liaise with", "digital marketing", "contact", "visual", "marketing materials", "report"], "requirements": {"degrees": ["bachelor degree holder"], "majors": [], "languages": ["english", "chinese"], "language_level": ["proficiency"], "hard_skills": [], "soft_skills": ["computer literacy"], "languages_combined": [{"language": "english", "language_level": ["proficiency"]}, {"language": "chinese", "language_level": ["proficiency"]}]}, "experience_required": {"duration": ["minimum 3 years"], "field": ["management", "public relations"]}}, {"job_id": "100003009047621", "location_code": "hk", "company": "Smart City Consortium Limited", "job_title": "Be part of SCC team \u2013 Marketing Executive", "description": "What will be your involvement:\n\nAs part of the core team with direct influence on the business\nDevelop and execute our business strategies\nPlan, develop and implement customer focus marketing and community campaigns and activities\nEngage external partners and explore collaboration opportunities regarding the building and growth of the community across our properties\u00a0\u00a0\nConduct social media analysis, competitive research, conversation management & web\u00a0behavioural\u00a0analysis and steering the company to achieve business objectives\nEnsure\u00a0marketing investment is tracked and measured appropriately to demonstrate effectiveness and return on investment.\n\n\u00a0What we look for:\n\nField of Studies - Business Management, Marketing, Hotel Management\nWork Experience - 2 years or more\nMust-have Quality - Good with numbers, Logical\nDesirable Attributes - Keen learner, Team player, Go-getter, Quick thinker, Highly adaptive\nLanguage Skills -\u00a0\u00a0Fluent in English, Cantonese and Putonghua\nTech Skills - MS Office, Social Media, PowerPoint/Keynote\nFlexibility - do not mind working on weekends occasionally", "employment_types": ["Full Time"], "selling_points": [], "locations": ["Kwun Tong"], "categories": ["Marketing / Public Relations", "Public Relations - Event Management"], "post_time": "2022-01-14T03:35:43Z", "salary": {"currency": null, "max": null, "min": null, "period": "monthly", "term": null}, "salary_visible": false, "title_keywords": ["marketing executive"], "responsibilities": ["social media", "management", "analysis", "quality", "develop", "plan"], "requirements": {"degrees": [], "majors": [], "languages": ["cantonese", "putonghua", "english"], "language_level": ["fluent"], "hard_skills": ["business management", "web", "analysis", "powerpoint", "focus", "go", "ms office"], "soft_skills": ["customer focus", "keen", "team player"], "languages_combined": [{"language": "cantonese", "language_level": ["fluent"]}, {"language": "putonghua", "language_level": ["fluent"]}, {"language": "english", "language_level": ["fluent"]}]}, "experience_required": {"duration": ["2 years"], "field": []}}, {"job_id": "100003009050095", "location_code": "hk", "company": "Crystal Investment Limited", "job_title": "Marketing and Community Building - Manager / Assistant Manager", "description": "Responsibilities:\n\nFormulate strategies and implement donor recruitment and retention programmes and initiatives to achieve the Society\u2019s fundraising goals\nLead and motivate a team of staff to manage fundraising programmes and activities, especially the face-to-face programme\nAssist to recruit fundraising staffs and to provide relevant training programmes to increase productivity and improve sales performance\nAssist to develop and manage public and donor database; and provide strategic and analytic insights, reports and recommendations\nManage teammates to handle and execute exhibitions / fundraising events including planning, liaising and solicitation with exhibitors, suppliers and venues etc.\nDevise and implement outreach strategies, initiatives, activities and events to attract and engage public partners; and enhance brand awareness and engagement\nAssist to copy write fundraising and donor communications including newsletters, invitations, direct and online appeals, solicitations, acknowledgements, proposals, etc.\n\nRequirements:\n\nTertiary qualification in business administration, sales, marketing or related discipline\nMinimum 4 years\u2019 experience in fundraising, sales, coaching and marketing, with at least 2 years\u2019 in supervisory role gained from NGO or fundraising agencies\nSolid experience in managing a sales team or face-to-face monthly giving programme would be an asset\u00a0\nGood knowledge of fundraising in NGO is desirable\u00a0\nStrong leadership with excellent interpersonal and motivational skills\nHighly analytical with solid exposure in database management would be highly desirable\nGood organizational and planning skills, ability to work under pressure\nExcellent communications and presentation skills, including the ability to communicate fluently and professionally in English and Chinese\u00a0\nInterested to contribute to help others in need\n\nWe provide equal employment opportunities to all employees and applicants. For interested parties, please click\u00a0\u201cApply Now\u201d.\n\n(Personal data collected will be used for recruitment purpose only)", "employment_types": ["Full Time", "Permanent"], "selling_points": ["Marketing Experience in Hospitality sector", "Keen to build and grow customer focus community", "Proficiency in digital marketing initiatives"], "locations": ["Causeway Bay"], "categories": ["Marketing / Public Relations", "Public Relations - Event Management", "Digital Marketing"], "post_time": "2022-01-14T09:46:28Z", "salary": {"currency": null, "max": null, "min": null, "period": "monthly", "term": null}, "salary_visible": false, "title_keywords": ["assistant manager", "manager"], "responsibilities": ["improve sales performance", "develop", "manage teammates", "reports", "recruitment", "database", "planning"], "requirements": {"degrees": [], "majors": [], "languages": ["english", "chinese"], "language_level": ["excellent"], "hard_skills": [], "soft_skills": ["organizational and planning skills", "presentation skills", "leadership", "interpersonal", "work under pressure"], "languages_combined": [{"language": "english", "language_level": ["excellent"]}, {"language": "chinese", "language_level": ["excellent"]}]}, "experience_required": {"duration": ["minimum 4 years", "at least 2 years"], "field": ["supervisory", "marketing", "team"]}}, {"job_id": "100003009047801", "location_code": "hk", "company": "Go In Marketing", "job_title": "Senior PR & Marketing Executive / PR & Marketing Executive (PR Focus)", "description": "Responsibilities:\n\nAssist the project manager in managing partnership projects and accelerators;\nPlan and execute a wide range of programme events and activities including but not limited to media launch, information session, solutions day, demo day, etc.;\nManage and maintain the content for programme website and other promotion channels and platforms;\nClosely monitor programme progress and its key results to improve the quality of deliverables;\nLiaise and coordinate with internal and external stakeholders to ensure a smooth project delivery;\nProvide general administrative support and handle enquiries from different programme stakeholders; and\nPerform any other duties as assigned by supervisor.\n\nRequirements:\n\nA bachelor\u2019s degree in Business Administration, Communications or related disciplines;\nMinimum 3 years\u2019 experience in project management, event management or client servicing, preferably in the I&T industry;\nExperience in content creation in social media platforms;\nCreative, innovative and agile thinking person with good interpersonal and communication skill;\nSelf-motivated, detail-oriented and able to work independently under tight schedule; and\nProficient in both verbal and written English and Chinese, including Cantonese and Putonghua.\n\nCandidate with less experience will be considered for lower position as Officer.\n\nWe offer market competitive compensation, 5-day work week, and generous benefits including medical and life insurance; and voluntary contribution in addition to the legal minimum MPF. To apply, please send your full resume with current and expected salary to the Human Resources & Office Administration Department, Hong Kong Science and Technology Parks Corporation, 5/F, Building 5E, 5 Science Park East Avenue, Hong Kong Science Park, Hong Kong or, by email via \"Apply Now\"\u00a0on or before 24 January 2022. Please quote the reference number on the email subject/envelope and the application letter.\u00a0\n\nPersonal data provided will be treated in strict confidence and used for recruitment purpose only.\u00a0 All personal data collected will be used strictly in accordance with employer\u2019s personal data policies, you can access to HKSTP\u2019s Personal Information Collection Statement at https://www.hkstp.org/hkstp_web/en/hkstp/personal-information-collection-statement-recruitment\n\nApplicants not invited for interview within four weeks after application deadline may consider their applications unsuccessful.\u00a0 Personal data of unsuccessful applicants will be retained for a maximum of two years.\u00a0\n\nwww.hkstp.org", "employment_types": ["Full Time"], "selling_points": ["5 days\u2019 work", "Incentive Bonus", "Performance Bonus"], "locations": ["Lai Chi Kok"], "categories": ["Marketing / Public Relations", "Marketing - Marketing Communication", "Public Relations - Event Management", "Public Relations - General / Support"], "post_time": "2022-01-14T03:56:02Z", "salary": {"currency": null, "max": null, "min": null, "period": "monthly", "term": null}, "salary_visible": false, "title_keywords": ["pr & marketing executive"], "responsibilities": ["liaise", "any other duties", "general administrative support", "quality", "monitor", "website", "coordinate with", "handle enquiries", "maintain", "plan"], "requirements": {"degrees": ["degree", "bachelor"], "majors": ["related disciplines", "business administration", "communications"], "languages": ["cantonese", "putonghua", "english", "chinese"], "language_level": ["proficient"], "hard_skills": ["project management", "agile"], "soft_skills": ["self-motivated", "work independently", "agile", "communication skill", "innovative", "detail-oriented", "project management", "creative", "interpersonal"], "languages_combined": [{"language": "cantonese", "language_level": []}, {"language": "putonghua", "language_level": []}, {"language": "english", "language_level": ["proficient"]}, {"language": "chinese", "language_level": ["proficient"]}]}, "experience_required": {"duration": ["minimum 3 years"], "field": ["project management", "management", "social media", "content creation"]}}, {"job_id": "100003009039273", "location_code": "hk", "company": "Hong Kong Science & Technology Parks Corporation", "job_title": "Senior Officer, Partnerships (focus on event coordination & programme support) [JDB/SOPECPS/220111]", "description": "Responsibilities:\nProvide assistance on coordinating different scales of events / roadshows / exhibitions\nDevelop strategic marketing plans from idealization, content curation to execution\nLiaise with multiple internal & external stakeholders to ensure smooth delivery of the events\nWork closely with the PR agency to maximize exposure and drive conversions\nManage the development of digital marketing channels, such as social media platforms, SEO & SEM\nCoordinate event logistics arrangements\nAssist in other marketing activities\nRequirements:\nDegree holder or above in Marketing, Event Management, Public Relations, or other related disciplines\n2-3 years of relevant experience in event management or marketing, experience in the aviation industry is not necessary but an added advantage\nProficient in verbal and written communication skills in English and Chinese\nExcellent interpersonal and teamwork skills\nDetail-oriented, good organizational skills, and able to multi-task\nCandidates with more experience will be considered for senior position", "employment_types": ["Full Time"], "selling_points": [], "locations": ["Shatin Area"], "categories": ["Sales, CS & Business Devpt", "Business Development", "Marketing / Public Relations", "Public Relations - Event Management", "Others"], "post_time": "2022-01-11T09:15:28Z", "salary": {"currency": null, "max": null, "min": null, "period": "monthly", "term": null}, "salary_visible": false, "title_keywords": ["senior officer"], "responsibilities": ["seo", "marketing plans", "social media platforms", "logistics arrangements", "develop", "coordinate", "digital marketing", "sem", "liaise with", "provide assistance"], "requirements": {"degrees": ["degree holder"], "majors": ["related disciplines", "marketing"], "languages": ["english", "chinese"], "language_level": ["proficient"], "hard_skills": [], "soft_skills": ["communication skills", "organizational skills", "multi-task", "teamwork", "detail-oriented", "interpersonal"], "languages_combined": [{"language": "english", "language_level": ["proficient"]}, {"language": "chinese", "language_level": ["proficient"]}]}, "experience_required": {"duration": ["2-3 years"], "field": ["management", "marketing", "relevant experience"]}}]