[{"job_id": "100003009055562", "location_code": "hk", "company": "Chandler Macleod Group (HK) Limited", "job_title": "Copywriter (Professional Service/ Beauty/ Retail)", "description": "Responsibilities:\n\n\n\nTo provide English and Chinese copy writing for a full range of editing, proofreading and translating various marketing collaterals including user manual, brochure, press release, print advertisement, corporate, etc.\nCoordinating, implementing and managing various marketing campaigns including Advertising, PR, Event, Print and Joint Promotion.\nLiaising closely with internal teams including Design, Sales, Promotion and Purchasing, to ensure effective communication and to progress all marketing campaigns at each stage, from information gathering to concepts, from copy writing to production\n\nRequirements:\n\n\n\nDegree Holder in Languages, Communications, Journalism, Marketing or Public Relations\nAt least 2 years' solid experience in writing position Strong interest in social media industry\nPassionate, detailed mind, proactive/ outgoing, self & team motivated and willing to take responsibilities\nCreative, willing to take up challenge", "employment_types": ["Full Time", "Permanent"], "selling_points": ["Multinational Working Environment", "Genuine Development Opportunity", "A Growing Business"], "locations": ["Not Specified"], "categories": ["Marketing / Public Relations", "Marketing - Marketing Communication", "Public Relations - Copy-writing", "Digital Marketing"], "post_time": "2022-01-18T02:43:26Z", "salary": {"currency": null, "max": null, "min": null, "period": "monthly", "term": null}, "salary_visible": false, "title_keywords": ["copywriter"], "responsibilities": ["advertising", "marketing collaterals", "teams", "design", "communication", "proofreading", "marketing campaigns", "editing"], "requirements": {"degrees": ["degree holder"], "majors": ["journalism", "marketing", "communications"], "languages": [], "language_level": [], "hard_skills": [], "soft_skills": ["passionate", "outgoing", "proactive", "creative", "motivated", "detailed mind"], "languages_combined": []}, "experience_required": {"duration": ["at least 2 years"], "field": ["social media", "writing"]}}, {"job_id": "100003009055640", "location_code": "hk", "company": "Page Personnel", "job_title": "Digital Copywriter - Financial Services (Chinese/English)", "description": "Excellent opportunity for candidates who have experience in English / Chinese copywriting and strong user experience mindset to support the launch of new digital features and products.\n\nClient Details\n\nOur client is a leading bank providing personal & corporate financial management service. With their experiences and sophisticated business, our client has strong client base and great reputation in the industry. To corporate with their growth for their digital product, our client is looking for a high-calibre candidate to join them and support their newly launched digital features and products.\n\nDescription\n\nDevelop clear and customer-centric copy that promote digital products and new features including both long and short form\nUnderstand the digital journeys in order to produce an effective user experience\nEnsure all content presents an accurate overview of brand and is aligned to brand guidelines/tone\nWork closely with internal team to identify opportunities and create human-centred copy-writing experience\n\nProfile\n\nDegree in Marketing / Communication/ Journalism / Language / Related discipline\n3+ years working experience in copy-writing\nStrong communication and written skills in English or Chinese (both Traditional and Simplified)\nExperience in financial services industry is a plus\nPositive attitude, hands-on and can-do mentality\n\nJob Offer\n\nLarge audience based\nGreat career prospect\nReputable brand", "employment_types": ["Full Time", "Contract"], "selling_points": ["Support new launch digital features", "Immediately available", "Competitive salary range"], "locations": ["Not Specified"], "categories": ["Marketing / Public Relations", "Public Relations - Copy-writing", "Others", "Digital Marketing"], "post_time": "2022-01-18T02:49:22Z", "salary": {"currency": null, "max": null, "min": null, "period": "monthly", "term": null}, "salary_visible": false, "title_keywords": ["copywriter"], "responsibilities": ["management", "user experience", "develop", "communication", "client base", "brand guidelines"], "requirements": {"degrees": ["degree"], "majors": ["journalism", "marketing"], "languages": ["english", "chinese"], "language_level": ["excellent"], "hard_skills": ["plus"], "soft_skills": ["sophisticated", "positive attitude", "communication", "clear", "hands-on", "can-do", "accurate"], "languages_combined": [{"language": "english", "language_level": ["excellent"]}, {"language": "chinese", "language_level": ["excellent"]}]}, "experience_required": {"duration": ["3+ years"], "field": ["business", "writing", "copywriting", "digital", "financial services industry", "team"]}}, {"job_id": "100003009052705", "location_code": "hk", "company": "Poly Treasure Investment Limited", "job_title": "\u653f\u6cbb\u52a9\u7406", "description": "Responsibilities:\n\n\nCopy-write and edit marketing brochures, executive speeches, statements to media and press releases;\nPrint & produce of all event-related materials such as brochures, flyers, preview, posters, catalogue and post-show reports, e-newsflash, e-flyer, e-card;\nDevelop and execute advertising planning, media buying and advertisement production;\nResponsible for media relations and organization of press conferences;\nProvide onsite media support such as exhibitor and visitor interview, media tour, photography and videography, executive interview;\nArrange incentive trips for foreign journalists to Hong Kong and China.\n\nRequirements:\n\nDegree holder in any disciplines, preferably in Public Relations or Communications;\nAt least 3 years' relevant experience in Public Relations or Marketing Communications, preferably with strong contacts to media in Hong Kong;\nEnglish native speaker is an advantage;\nAble to interact positively and effectively with employees at all levels within the organization, as well as customers, prospects, and vendors;\nA good team player with strong organizational skill and capable of working under pressure;\nDetail-minded and results oriented;\nExcellent media relations and copy-writing skills are preferable;\nGood command of both written and spoken English and Mandarin and Cantonese;\nKnowledgeable in Microsoft Office, Chinese Word Processing;\nWilling to travel overseas;\nCandidates with lesser experience will be considered as a position of Assistant Public Relations Officer.\n\n\u00a0We work 5 days per week\nWe offer long-term career development opportunities, attractive remuneration package and fringe benefits including 5-day work, group life and medical insurance to right candidates. Interested parties please send full resume stating our reference number, present and expected salary to\u00a0HR @hongkong.messefrankfurt.com or fax to 2511-5112. \u00a0\n\nMesse Frankfurt (HK) Ltd. is an equal opportunity employer and is awarded the Good MPF Employer Award. Information provided will be treated in strict confidence and only be used for recruitment purpose. Candidates not invited for interview within 4 weeks may consider their application unsuccessful. However, we will retain the applications for a maximum period of 6 months and may refer them to suitable openings.", "employment_types": ["Full Time", "Permanent"], "selling_points": ["\u5177\u653f\u6cbb\u89f8\u89d2,\u5c0d\u9999\u6e2f\u3001\u4e2d\u570b\u548c\u570b\u969b\u653f\u6cbb\u4e8b\u52d9\u6709\u8a8d\u8b58\u548c\u8208\u8da3", "\u719f\u6089\u4e2d\u6e2f\u5169\u5730\u653f\u5e9c\u7d44\u7e54\u67b6\u69cb\u548c\u6b0a\u8cac\u5206\u5de5", "\u512a\u539a\u7684\u5f85\u9047\u53ca\u85aa\u916c\u798f\u5229"], "locations": ["North Point"], "categories": ["Media & Advertising", "Editorial / Journalism", "Marketing / Public Relations", "Public Relations - Copy-writing", "Public Relations - Event Management"], "post_time": "2022-01-17T04:32:09Z", "salary": {"currency": null, "max": null, "min": null, "period": "monthly", "term": null}, "salary_visible": false, "title_keywords": [], "responsibilities": ["advertising", "develop", "conferences", "reports", "catalogue", "planning"], "requirements": {"degrees": ["degree holder"], "majors": ["any disciplines", "communications"], "languages": ["cantonese", "english", "chinese", "mandarin"], "language_level": ["native", "good command", "advantage"], "hard_skills": ["chinese word processing", "writing skills", "microsoft office"], "soft_skills": ["detail-minded", "good team player", "under pressure", "organizational skill", "capable", "writing skills"], "languages_combined": [{"language": "cantonese", "language_level": ["good command"]}, {"language": "english", "language_level": ["native", "good command", "advantage"]}, {"language": "chinese", "language_level": []}, {"language": "mandarin", "language_level": ["good command"]}]}, "experience_required": {"duration": ["at least 3 years"], "field": ["marketing communications", "public relations", "relevant experience", "media"]}}, {"job_id": "100003009054077", "location_code": "hk", "company": "Messe Frankfurt (HK) Ltd", "job_title": "Public Relations Officer", "description": "Responsibilities\n\nAssist in planning of PR publicity programmes for Hong Kong Tourism Board events/ campaigns in Hong Kong\nTake charge of implementation of PR publicity programmes\nPrepare press materials and pitch media to generate positive media coverage\nCultivate close working relationship with local media and stakeholders\nHandle media enquiries\nAssist in issue preparedness and crisis management\n\nRequirements\n\nUniversity degree holder, prefer major in Communications, Public Relations, Journalism or related discipline\nAt least 6 years of solid experience in the field of public relations, media relations and event promotion\nPrior journalistic experience is an added advantage\nStrong communications and interpersonal skills\nGood command of spoken and written English & Chinese\nWilling to work under pressure and handle multi-tasks\nDetail-oriented and able to work independently\n\nInterested parties please send resume with present and expected salary by clicking \u201cApply Now\u201d.\n\nPersonal data provided by job applicants will be used strictly in accordance with our personal data policies, a copy of which will be provided upon request.\u00a0 Applicants may send a request for a copy of the Personal Information Collection Statement pertaining to Job\u00a0Application.\u00a0 Only shortlisted applicants will be contacted. \u00a0All Information received will be kept in strict confidence and\u00a0used\u00a0only for employment-related purpose.\n\nWe are an equal opportunities employer.", "employment_types": ["Full Time", "Permanent"], "selling_points": ["Copy-write and edit marketing brochures", "Print & produce of all event-related materials", "Develop and execute advertising planning"], "locations": ["Wan Chai"], "categories": ["Marketing / Public Relations", "Public Relations - Copy-writing", "Public Relations - Event Management", "Public Relations - General / Support"], "post_time": "2022-01-17T08:19:30Z", "salary": {"currency": null, "max": null, "min": null, "period": "monthly", "term": null}, "salary_visible": false, "title_keywords": ["officer"], "responsibilities": ["implementation", "crisis management", "planning"], "requirements": {"degrees": ["university degree"], "majors": ["journalism", "communications"], "languages": ["english", "chinese"], "language_level": ["good command"], "hard_skills": [], "soft_skills": ["work independently", "multi-tasks", "detail-oriented", "interpersonal skills", "work under pressure"], "languages_combined": [{"language": "english", "language_level": ["good command"]}, {"language": "chinese", "language_level": ["good command"]}]}, "experience_required": {"duration": ["at least 6 years"], "field": ["public relations", "media", "journalistic"]}}, {"job_id": "100003009056358", "location_code": "hk", "company": "Hong Kong Tourism Board", "job_title": "Senior Executive, Communications (HK Focused)", "description": "Generate and manage unique, engaging and creative content and day-to-day handling of all social media channels such as LinkedIn, Facebook, Twitter, Discord, Instagram, etc, and EDM, adapting content to suit different channels using social media marketing tools to create and maintain the company\u2019s brand\nBuild and maintain relationships with our stakeholders, group companies, partners, customers and other industry professionals\nAssist with the design and execution of social media campaigns\nResearching social media trends and informing management of changes that are relevant to the company\u2019s marketing activities\nAttend networking events or relevant industry\nCoordinate with HR, Marketing, Art, Business Development and Management teams\nImplement strategies to improve employee experience and to build community within our organization\n\nRequirements:\n\nBachelor's degree in business, marketing, journalism, public relations or related field\n2+ year of experience in community marketing / community engagement / community management\nHands on experience in content management and excellent copywriting skills\nYou are responsible and organized\nExperience in online social platforms such as Telegram, Facebook, Twitter, Discord, etc.\nExperience in MailChimp.\nKnowledge in Photoshop or illustrator with basic understanding of graphic design principles.\nProficiency in spoken and written English\nExcellent in communication and interpersonal skills\nAnalytical and multitasking skills\nImmediately available is highly preferred\n\n\u00a0Nice to have:\n\nKnowledge of Cryptocurrency and Blockchain\u00a0\nKnowledge of games, especially blockchain games\u00a0\n\n\u00a0What We Offer:\n\nAttractive remuneration package that includes 5-day work\nPrivilege insurance plan for group medical (covers clinical, hospitalization with supplementary major medical) & dental\nConvenient office location in TsimShaTsui\nWork with the young and energetic team\nOpportunities to participate in blockchain projects\nFree snacks, coffee, and tea\nFestival cash and gifts\nRegular staff activities\n\nPlease send your full resume in English, stating present and expected salary by clicking APPLY NOW.\n\nWe are an equal opportunity employer and welcome applications from all qualified candidates.\u00a0 Personal data collected will be treated in strictest confidence and handled confidentially by authorized personnel for recruitment-related purposes within the Group.", "employment_types": ["Full Time", "Permanent"], "selling_points": ["Assist in PR events/ campaigns in Hong Kong", "Prepare press materials, pitch and handle media", "Issue preparedness and crisis management"], "locations": ["Tin Hau"], "categories": ["Marketing / Public Relations", "Public Relations - Copy-writing", "Public Relations - Event Management", "Public Relations - General / Support"], "post_time": "2022-01-18T04:04:43Z", "salary": {"currency": null, "max": null, "min": null, "period": "monthly", "term": null}, "salary_visible": false, "title_keywords": ["senior executive"], "responsibilities": ["maintain relationships", "social media", "management", "management teams", "creative content", "social media campaigns", "edm", "graphic design", "hr", "coordinate with", "design", "communication", "maintain", "facebook"], "requirements": {"degrees": ["degree", "bachelor"], "majors": ["journalism", "business", "marketing"], "languages": ["english"], "language_level": ["proficiency"], "hard_skills": ["blockchain", "basic", "nice", "illustrator", "cryptocurrency", "facebook", "photoshop"], "soft_skills": ["organized", "responsible", "unique", "hands on", "communication and interpersonal skills", "creative"], "languages_combined": [{"language": "english", "language_level": ["proficiency"]}]}, "experience_required": {"duration": ["2+ year"], "field": ["copywriting", "management", "marketing"]}}, {"job_id": "100003009054757", "location_code": "hk", "company": "LABS Group Limited", "job_title": "Social Media and Community Executive/Manager", "description": "Responsibilities:\n\nManage and create content for various social media platforms (Facebook, Instagram, YouTube), including copywriting, image and video editing;\nMonitor, analyze, and provide insight on social media platform activities;\nHandle various ad hoc duties such as online marketing, develop and maintain social network, etc.\nWork closely with marketing team to develop and execute image visual for advertising materials.\nCooperate with\u00a0team\u00a0members and assisting to keep the office operation.\nKeep up with trends that can be adapted to our online platforms\n\nRequirements :\n\nHigher Diploma or Degree\u00a0holder, preferably in multimedia production, design, multi-media, communication\u00a0or related disciplines.\nA minimum of 1-2 years\u2019 hands-on experience in multimedia and video production, or relevant working experience.\nProficient in photo and video editing software (Photoshop, Premiere Pro) is highly preferred, coupled with basic Illustrator and After Effect skills would be a plus\nOutgoing, creative, well-organized, detail-minded with a strong sense of responsibility, independent and able to work under pressure.\nExperience in web-based and mobile learning courseware development is an advantage.\nDesire to learn new multimedia technology.\nAble to work efficiently and effectively, both independently and as a team member.\nGood command of Chinese, English and Putonghua.", "employment_types": ["Full Time", "Permanent"], "selling_points": ["Knowledge of Cryptocurrency and Blockchain", "Immediately available is highly preferred", "2+ year of experience in community marketing"], "locations": ["Tsim Sha Tsui"], "categories": ["Marketing / Public Relations", "Marketing - Marketing Communication", "Public Relations - Copy-writing", "Digital Marketing"], "post_time": "2022-01-17T10:55:58Z", "salary": {"currency": null, "max": null, "min": null, "period": "monthly", "term": null}, "salary_visible": false, "title_keywords": ["executive", "manager"], "responsibilities": ["ad hoc duties", "social media", "advertising", "social media platforms", "monitor", "develop", "video editing", "maintain", "visual", "facebook", "cooperate with"], "requirements": {"degrees": ["diploma", "degree holder"], "majors": ["related disciplines", "design"], "languages": ["putonghua", "english", "chinese"], "language_level": ["good command"], "hard_skills": ["plus", "basic", "web", "illustrator", "video editing", "mobile", "premiere pro", "multimedia", "after effect", "photoshop"], "soft_skills": ["outgoing", "detail-minded", "independently", "independent", "sense of responsibility", "well-organized", "team member", "communication", "hands-on", "learning", "creative", "work under pressure"], "languages_combined": [{"language": "putonghua", "language_level": ["good command"]}, {"language": "english", "language_level": ["good command"]}, {"language": "chinese", "language_level": ["good command"]}]}, "experience_required": {"duration": ["minimum of 1-2 years"], "field": ["video production", "development", "relevant working experience"]}}, {"job_id": "100003009056393", "location_code": "hk", "company": "Hong Kong Live Feed Limited", "job_title": "Digital Content Creator", "description": "Scope of Assignment\n\nYour role will be an important member of content team to work with OMG Hong Kong\u2019s clients on how to strategize, create, assess, disseminate, evaluate, and monitor content engagement; not just as an executioner but also a thinker able to take the creative ideas and turn them into something tangible to bring them to life, by using knowledge of platforms and audiences and deliver ideas to completion and engage brands for our clients.\n\nPreferably, you will have experience in managing content planning and execution with great project coordination skill and you are a people person as part of your role will be client management.\u00a0 At least 2 years working experience in advertising, social, creative or media agency will be vital, especially in FMCG brand.\n\nJob Responsibilities:\n\nAssist the Content Specialist in managing all aspects of clients\u2019 content platforms and implementing content strategy across all platforms, including content creation, posting and monitoring social community\nServe as liaison between the client and creative team to track the progression of campaigns\nProvide creative and engaging text, image and video content\nProject Manage and respond to comments and customer queries in a timely manner\nLiaise with various parties including clients and vendors for execution of ideas and quality control of deliverable.\nIdentify and communicate with key bloggers and influencers; experience with KOL management will be a big plus\nMock up preview of social post and copywriting for social post will be an added advantage\nCosting and budgeting campaign and deliverable.\n\nWorking Together\n\nEncourage creativity and inspirational team spirit to build and strengthen agency\u2019s creative culture within the agency.\nDemonstrate an infectious enthusiasm and good team spirit within agency\nand with clients\u2019 working team.\n\nOutward Facing\n\nEngaged with existing and potential clients through day to day interaction.\nTreat client business as you would your own, focusing on results\nTo gain trust and respect from the clients.\nLeads all influencer projects, executing partnerships from outreach\nTo creative deliverables, with in-person support as well\n\nRequirements:\n\nUniversity degree in business, marketing, advertising, communications, or a related field\nUp to date with Social Media Trend and Popular culture in Hong Kong and around the world\nExcellent common sense and strategic thinking.\nQuick thinker and doer with great sense of humor and attitude; pleasant and positive with a \u201cCAN DO\u201d mindset.\nA self-starter, a passion for learning and problem solving.\nKeen learner with great sense of ownership and being able to complete the work independently as well as with the team members.\nAble to work under pressure and tight turnaround.\nSuper detail oriented to ensure output quality of work.\nMust be well organized with timeline and deliverable and have strong communication skills\nProficiency in MS Office. Ability to use Social media mock-up tools such as canva will be added value.\nGood command of spoken and written Cantonese, Mandarin and English\nAble to build a good rapport with clients and vendors in respective and reasonable communications way.\nAble to articulate ideas and thoughts to stakeholders in effective manners.\nCandidate with more experience will be considered as Social Content Planner\nImmediate availability is an advantage\n\nWorking Location: Cyberport (\u6578\u78bc\u6e2f) , Hong Kong\n\nWe offer a 5-day week of work, group medical & life insurance coverage, free shuttle bus to the right candidate. Interested parties please send your application letter and resume by clicking the \u201cApply Now\u201d button.\n\nAll information collected will be used for recruitment only and treated in strict confidence. We will retain the personal data of unsuccessful applicants for future recruitment purpose for a maximum period of 2 years.", "employment_types": ["Full Time"], "selling_points": [], "locations": ["Shatin Area"], "categories": ["Marketing / Public Relations", "Public Relations - Copy-writing", "Media & Advertising", "Photography / Video", "Digital Marketing"], "post_time": "2022-01-18T04:08:46Z", "salary": {"currency": null, "max": null, "min": null, "period": "monthly", "term": null}, "salary_visible": false, "title_keywords": [], "responsibilities": ["communicate with", "management", "ideas", "budgeting", "comments", "monitoring", "a timely manner", "executing", "quality control", "liaise with", "customer queries"], "requirements": {"degrees": ["university degree"], "majors": ["business", "communications", "marketing"], "languages": ["cantonese", "english", "mandarin"], "language_level": ["good command"], "hard_skills": ["problem solving", "planner", "ms office"], "soft_skills": ["communication skills", "work independently", "strategic thinking", "passion for", "keen", "detail oriented", "well organized", "pleasant", "problem solving", "learning", "articulate", "positive", "work under pressure"], "languages_combined": [{"language": "cantonese", "language_level": ["good command"]}, {"language": "english", "language_level": ["good command"]}, {"language": "mandarin", "language_level": ["good command"]}]}, "experience_required": {"duration": [], "field": []}}, {"job_id": "100003009053346", "location_code": "hk", "company": "Omnicom Media Group", "job_title": "Social Content Executive / Social Content Planner (Media & Advertising Field)", "description": "\u8a72\u8077\u4f4d\u4e3b\u8981\u8ca0\u8cac\u5404\u65b9\u9762\u7684\u652f\u63f4,\u5305\u62ec\u9032\u884c\u5404\u65b9\u9762\u7684\u7814\u7a76\u53ca\u9810\u5099\u6ed9\u5831\u6216\u6f14\u8b1b\u6750\u6599\u4ee5\u53ca\u548c\u5354\u52a9\u7ba1\u7406\u5c64\u53c3\u4e88\u53ca\u7d44\u7e54\u5404\u7a2e\u793e\u6703\u8cac\u4efb\u3001\u653f\u6cbb\u548c\u5546\u696d\u6d3b\u52d5\u3002\n\n\u4e3b\u8981\u8077\u8cac:\n\n\u5c31\u4efb\u4f55\u53d7\u9080\u7684\u5546\u696d\u6216\u653f\u6cbb\u6216\u793e\u6703\u4e8b\u52d9\u548c\u6d3b\u52d5\u5411\u7ba1\u7406\u5c64\u63d0\u4f9b\u653f\u6cbb\u8003\u616e\u5efa\u8b70\n\u5354\u52a9\u7ba1\u7406\u5c64\u5728\u9999\u6e2f\u548c\u4e2d\u570b\u7b56\u5283\u548c\u7d44\u7e54\u793e\u6703\u8cac\u4efb\u6d3b\u52d5\u6216\u6703\u8b70\n\u70ba\u7ba1\u7406\u5c64\u6e96\u5099\u6f14\u8b1b\u3001\u5a92\u9ad4\u6f14\u793a\u548c\u5176\u4ed6\u6587\u7ae0\n\u5c31\u4efb\u4f55\u65b0\u7684\u653f\u5e9c\u653f\u7b56\u9032\u884c\u7814\u7a76\uff0c\u4e26\u786e\u5b9a\u5c0d\u9999\u6e2f\u548c\u4e2d\u570b\u696d\u52d9\u7684\u6f5c\u5728\u5f71\u97ff/\u5f8c\u679c\n\u7ba1\u7406\u53ca\u5354\u8abf\u5404\u7a2e\u6d3b\u52d5\u7d30\u7bc0\u4f8b\u5982\u88dd\u98fe\u3001\u9910\u98f2\u3001\u5a1b\u6a02\u3001\u4ea4\u901a\u3001\u5730\u9ede\u3001\u53d7\u9080\u540d\u55ae\u3001\u7279\u9080\u5609\u8cd3\u3001\u8a2d\u5099\u8a2d\u65bd\u3001\u5ba3\u50b3\u8cc7\u6599\u7b49\n\n\u5165\u8077\u8981\u6c42:\n\n\n\u64c1\u6709\u5de5\u5546\u7ba1\u7406\u3001\u516c\u5171\u95dc\u4fc2\u3001\u653f\u6cbb\u5b78\u3001\u65b0\u805e\u8207\u50b3\u64ad\u6216\u76f8\u95dc\u5b78\u79d1\u7684\u5b78\u4f4d\n\u5177\u653f\u6cbb\u89f8\u89d2,\u5c0d\u9999\u6e2f\u3001\u4e2d\u570b\u548c\u570b\u969b\u653f\u6cbb\u4e8b\u52d9\u6709\u8a8d\u8b58\u548c\u8208\u8da3\n\u81f3\u5c11 5 \u5e74\u5927\u578b\u516c\u5171\u6d3b\u52d5\u7d44\u7e54\u548c\u653f\u6cbb\u65b0\u805e\u5beb\u4f5c\u6216\u7de8\u8f2f\u7d93\u9a57\n\u77ad\u89e3\u4e2d\u570b\u7684\u653f\u6cbb\u548c\u793e\u6703\u554f\u984c\u4ee5\u53ca\u7d93\u6fdf\u767c\u5c55\uff0c\u5c24\u5176\u662f\u5927\u7063\u5340\n\u719f\u6089\u4e2d\u6e2f\u5169\u5730\u653f\u5e9c\u7d44\u7e54\u67b6\u69cb\u548c\u6b0a\u8cac\u5206\u5de5\n\u8207\u653f\u6cbb\u6216\u793e\u6703\u9818\u8896\u4fdd\u6301\u826f\u597d\u95dc\u7cfb\u66f4\u4f73\n\u5916\u5411\u7684\u500b\u6027\u548c\u5177\u7368\u7acb\u5de5\u4f5c\u7684\u80fd\u529b\n\u512a\u79c0\u7684\u4e2d\u6587\u5beb\u4f5c\u548c\u5206\u6790\u80fd\u529b\n\u826f\u597d\u7684\u6e9d\u901a\u548c\u4eba\u969b\u4ea4\u5f80\u80fd\u529b\uff0c\u80fd\u5920\u8207\u653f\u6cbb\u6216\u793e\u6703\u9818\u8896\u6253\u4ea4\u9053\u66f4\u4f73\n\u5177\u5099\u7684\u7d44\u7e54\u548c\u57f7\u884c\u80fd\u529b\n\u6c42\u8077\u8005\u8acb\u8a73\u9644\u500b\u4eba\u5c65\u6b77\u53ca\u8981\u6c42\u5f85\u9047\u6309\u201cApply Now\u201d\u63d0\u4ea4\u7533\u8acb\u3002\n\n\n\u672c\u516c\u53f8\u70ba\u516c\u5e73\u6a5f\u6703\u50f1\u4e3b\uff0c\u6b61\u8fce\u6240\u6709\u5408\u8cc7\u683c\u7684\u5019\u9078\u4eba\u7533\u8acb\u3002\u6240\u63d0\u4f9b\u7684\u4fe1\u606f\u5c07\u56b4\u683c\u4fdd\u5bc6\uff0c\u50c5\u7528\u65bc\u62db\u8058\u76f8\u95dc\u7528\u9014\u3002\u82e5\u672a\u80fd\u65bc 8 \u9031\u5167\u7372\u9080\u51fa\u5e2d\u9762\u8a66\u7684\u7533\u8acb\u8005\u6703\u81ea\u52d5\u843d\u9078\uff0c\u53e6\u6240\u6709\u843d\u9078\u7684\u7533\u8acb\u8005\u7684\u6240\u6709\u500b\u4eba\u8cc7\u6599\u5c07\u57282\u5e74\u5167\u92b7\u6bc0\u3002", "employment_types": ["Full Time", "Permanent"], "selling_points": ["Free Shuttle Bus & Free Breakfast", "Birthday, Family Day & Self-Love Day Leave", "5-Day Work Week"], "locations": ["Pok Fu Lam"], "categories": ["Media & Advertising", "Account Servicing", "Marketing / Public Relations", "Marketing - Brand / Product Management", "Public Relations - Copy-writing"], "post_time": "2022-01-17T06:48:53Z", "salary": {"currency": null, "max": null, "min": null, "period": "monthly", "term": null}, "salary_visible": false, "title_keywords": ["executive"], "responsibilities": [], "requirements": {"degrees": [], "majors": [], "languages": [], "language_level": [], "hard_skills": [], "soft_skills": [], "languages_combined": []}, "experience_required": {"duration": [], "field": []}}, {"job_id": "100003009054784", "location_code": "hk", "company": "MANNING SELVAGE & LEE", "job_title": "Associate, PR & Social Media", "description": "Responsibilities\n\nPrepare annual report and other presentation material.\nProvide support to senior level for corporate governance.\nResponsible in communicate with the Group Company.\nOrganize important meetings or events.\nOther ad-hoc job.\n\nRequirements\n\nUndergraduate or above, with minimum 10 years of working experience.\nRelated Experience on serving in Government or Large state-owned enterprise is highly preferred.\nGood Chinese writing skills, graduate of Arts is highly preferred.\nStrong sense of responsibility, able to work well under pressure.\nFamiliarize with Administrative related knowledge.\nProficient in Microsoft Office.\nProficient in Mandarin, Cantonese and English.\n\n\u5de5\u4f5c\u8077\u8cac\n\n\u64b0\u5beb\u516c\u53f8\u5de5\u4f5c\u7e3d\u7d50\u53ca\u5176\u4ed6\u6ed9\u5831\u6750\u6599\n\u5354\u52a9\u4e0a\u7d1a\u8655\u7406\u516c\u53f8\u6cbb\u7406\u76f8\u95dc\u5de5\u4f5c\n\u8ca0\u8cac\u8207\u96c6\u5718\u7e3d\u90e8\u6e9d\u901a\u7b49\u5de5\u4f5c\n\u5b8c\u6210\u91cd\u8981\u6703\u8b70\u3001\u6d3b\u52d5\u7684\u7d44\u7e54\u3001\u5be6\u65bd\n\u5b8c\u6210\u4e0a\u7d1a\u4ea4\u8fa6\u7684\u5176\u4ed6\u5404\u9805\u5de5\u4f5c\n\n\u00a0\u4efb\u8077\u8981\u6c42\n\n\u5927\u5b78\u672c\u79d1\u53ca\u4ee5\u4e0a\u5b78\u6b77\uff0c\u81f3\u5c11\u5341\u5e74\u4ee5\u4e0a\u5de5\u4f5c\u7d93\u9a57\n\u5177\u6709\u653f\u5e9c\u6216\u5927\u578b\u570b\u4f01\u76f8\u95dc\u5de5\u4f5c\u7d93\u9a57\u8005\u512a\u5148\n\u5177\u6709\u624e\u5be6\u7684\u4e2d\u6587\u5beb\u4f5c\u529f\u5e95\uff0c\u6587\u79d1\u985e\u5c08\u696d\u512a\u5148\n\u8cac\u4efb\u5fc3\u5f37\uff0c\u5177\u6709\u4e00\u5b9a\u7684\u6297\u58d3\u80fd\u529b\n\u719f\u6089\u8fa6\u516c\u5ba4\u884c\u653f\u7ba1\u7406\u77e5\u8b58\u53ca\u5de5\u4f5c\u6d41\u7a0b\uff0c\u719f\u6089\u76f8\u95dc\u4fe1\u51fd\u3001\u6a94\u8655\u7406\u8981\u6c42\uff0c\u719f\u7df4\u904b\u7528OFFICE\u7b49\u8fa6\u516c\u8edf\u9ad4\uff0c\u5177\u5099\u8f03\u5f37\u7684\u66f8\u9762\u548c\u53e3\u982d\u8868\u9054\u80fd\u529b\n\u826f\u597d\u666e\u901a\u8a71\u3001\u5ee3\u6771\u8a71\u3001\u82f1\u8a9e", "employment_types": ["Full Time", "Permanent"], "selling_points": ["Part of fully integrated Publicis Groupe", "Diverse clientele, market leading brands", "Spacious, stylish office with an outdoor terrace"], "locations": ["Kwun Tong"], "categories": ["Marketing / Public Relations", "Marketing - Marketing Communication", "Public Relations - Copy-writing", "Digital Marketing"], "post_time": "2022-01-17T11:04:17Z", "salary": {"currency": null, "max": null, "min": null, "period": "monthly", "term": null}, "salary_visible": false, "title_keywords": ["associate"], "responsibilities": ["communicate with", "ad-hoc", "provide support", "report"], "requirements": {"degrees": [], "majors": [], "languages": ["cantonese", "english", "chinese", "mandarin"], "language_level": ["proficient", "good"], "hard_skills": ["writing skills", "microsoft office"], "soft_skills": ["under pressure", "writing skills", "sense of responsibility"], "languages_combined": [{"language": "cantonese", "language_level": ["proficient"]}, {"language": "english", "language_level": ["proficient"]}, {"language": "chinese", "language_level": ["good"]}, {"language": "mandarin", "language_level": ["proficient"]}]}, "experience_required": {"duration": ["minimum 10 years"], "field": ["related"]}}, {"job_id": "100003009052169", "location_code": "hk", "company": "A-World Consulting Limited", "job_title": "Senior Account Executive", "description": "Responsibilities:\nSocial media management including content development & consumer engagement\nCommunicate and extent good relationships with on-line media, KOL, vendors & platform partners\nAnalyze market trends and explore new marketing techniques & business opportunities\nParticipate and support internal teams for different marketing campaign and operation needs\nPrepare marketing proposal for client\nPrepare regular reports for management review\nParticipate & support in all new business initiatives and all ad hoc projects\nGood content writer\nStrong Creative Designer is much preferred\n\nRequirements:\n\nDegree holder in Marketing / Communication / Multi-media Design preferred\nMin. 2 years\u2019 experienced in marketing\nExcellent interpersonal, presentation and communication skills\nProficient in MS Word, Excel, PowerPoint and Chinese Word Processing\nFluency in written and spoken Chinese and English\nExperience in CMS (Wordpress) ,graphic design tools (Adobe Photoshop and Adobe Illustrator)\nDetail-minded, tech-savvy, outgoing, and flexible to work\nHard-working, willing to learn and able to handle multi-task, work under pressure and meet deadlines\nCandidate with more experienced will be considered as Senior Marketing Executive", "employment_types": ["Full Time", "Permanent"], "selling_points": ["5 days work per week", "performance bonus", "Fresh Graduate also welcome"], "locations": ["Sheung Wan"], "categories": ["Media & Advertising", "Editorial / Journalism", "Marketing / Public Relations", "Public Relations - Copy-writing", "Public Relations - Event Management"], "post_time": "2022-01-17T02:19:40Z", "salary": {"currency": null, "max": null, "min": null, "period": "monthly", "term": null}, "salary_visible": false, "title_keywords": ["senior account executive"], "responsibilities": ["social media", "management", "business initiatives", "business opportunities", "review", "teams", "regular reports for management", "ad hoc projects"], "requirements": {"degrees": ["degree holder"], "majors": ["marketing", "design"], "languages": ["english", "chinese"], "language_level": ["fluency", "proficient"], "hard_skills": ["excel", "chinese word processing", "adobe photoshop", "powerpoint", "adobe illustrator", "wordpress", "ms word"], "soft_skills": ["detail-minded", "communication skills", "outgoing", "flexible", "multi-task", "willing to learn", "communication", "hard-working", "meet deadlines", "interpersonal", "presentation", "work under pressure"], "languages_combined": [{"language": "english", "language_level": ["fluency"]}, {"language": "chinese", "language_level": ["fluency", "proficient"]}]}, "experience_required": {"duration": [], "field": ["graphic design"]}}, {"job_id": "100003009052171", "location_code": "hk", "company": "A-World Consulting Limited", "job_title": "Account Executive", "description": "Who we are:\n\nA-World Consulting (www.a-world.com.hk) is a Hong Kong-based, full-service communication and management consultancy covering Greater China.\u00a0 With affiliates/offices in various cities in Mainland China, we seek to provide creative solutions to clients through the combined networks and resources of a tight team of professionals with creative minds.\n\n\n\nJob Description:\n\n\nBusiness development and/or client servicing\n\nResearch, development and implementation of effective communication strategies and work plans for clients\n\nMonitor the larger environment and industry developments etc. to pre-empt clients of potential issues and opportunities, and provide corresponding solutions and recommendations\n\nAccount management in terms of finances, schedules and deliverables\n\nSupervision of junior staff as appropriate\u00a0\n\nRequirements:\n\nTertiary degree or equivalent in communication/public affairs/journalism\n\nAt least 2 years of experience in PR or related industries for Senior Account Executive and 1 years for Account Executive, preferably with agency background\n\nProven English and Chinese proficiency; fluency in Putonghua preferred\n\nPublic affairs/media/corporate communication experience and good network/relations\n\nExcellent business acumen, leadership and interpersonal skills, if applicable\n\nDetail-minded, proactive and able to work under tight schedule and pressure\n\nA good team player with a can-do spirit\n\nExperience in account management and mentoring junior executives, if applicable\n\n5-day work per week, but work outside normal working hours and days should be expected.\u00a0 Excellent compensation and attractive fringe benefits will be offered to the successful candidate.\u00a0 Interested parties please send full resume with availability and present and expected salary by clicking \"Apply Now\".\n\n\nAll personal data collected will be used for recruitment purpose only.\u00a0 Applicants not hearing from us within 6 months may consider their applications unsuccessful.\u00a0 All personal data supplied will be destroyed after 6 months.", "employment_types": ["Full Time", "Permanent"], "selling_points": ["5 days work per week", "performance bonus", "Fresh Graduate also welcome"], "locations": ["Sheung Wan"], "categories": ["Media & Advertising", "Editorial / Journalism", "Marketing / Public Relations", "Public Relations - Copy-writing", "Public Relations - Event Management"], "post_time": "2022-01-17T02:20:07Z", "salary": {"currency": null, "max": null, "min": null, "period": "monthly", "term": null}, "salary_visible": false, "title_keywords": ["account executive"], "responsibilities": [], "requirements": {"degrees": [], "majors": [], "languages": [], "language_level": [], "hard_skills": [], "soft_skills": [], "languages_combined": []}, "experience_required": {"duration": [], "field": []}}, {"job_id": "100003009056376", "location_code": "hk", "company": "Modern Dental Laboratory Company Limited", "job_title": "Project Executive", "description": "Who we are:\n\nA-World Consulting (www.a-world.com.hk) is a Hong Kong-based, full-service communication and management consultancy covering Greater China.\u00a0 With affiliates/offices in various cities in Mainland China, we seek to provide creative solutions to clients through the combined networks and resources of a tight team of professionals with creative minds.\n\n\n\nJob Description:\n\n\nBusiness development and/or client servicing\n\nResearch, development and implementation of effective communication strategies and work plans for clients\n\nMonitor the larger environment and industry developments etc. to pre-empt clients of potential issues and opportunities, and provide corresponding solutions and recommendations\n\nAccount management in terms of finances, schedules and deliverables\n\nSupervision of junior staff as appropriate\u00a0\n\nRequirements:\n\nTertiary degree or equivalent in communication/public affairs/journalism\n\nAt least 2 years of experience in PR or related industries for Senior Account Executive and 1 years for Account Executive, preferably with agency background\n\nProven English and Chinese proficiency; fluency in Putonghua preferred\n\nPublic affairs/media/corporate communication experience and good network/relations\n\nExcellent business acumen, leadership and interpersonal skills, if applicable\n\nDetail-minded, proactive and able to work under tight schedule and pressure\n\nA good team player with a can-do spirit\n\nExperience in account management and mentoring junior executives, if applicable\n\n5-day work per week, but work outside normal working hours and days should be expected.\u00a0 Excellent compensation and attractive fringe benefits will be offered to the successful candidate.\u00a0 Interested parties please send full resume with availability and present and expected salary by clicking \"Apply Now\".\n\n\nAll personal data collected will be used for recruitment purpose only.\u00a0 Applicants not hearing from us within 6 months may consider their applications unsuccessful.\u00a0 All personal data supplied will be destroyed after 6 months.", "employment_types": ["Full Time", "Permanent"], "selling_points": ["Optimization of overseas advertisement channels", "Enjoy Social Media & English copywriting", "Genuine interest in SEO / Digital Marketing"], "locations": ["Lai Chi Kok"], "categories": ["Marketing / Public Relations", "Marketing - General / Support", "Public Relations - Copy-writing", "Digital Marketing"], "post_time": "2022-01-18T04:06:25Z", "salary": {"currency": null, "max": null, "min": null, "period": "monthly", "term": null}, "salary_visible": false, "title_keywords": ["project executive"], "responsibilities": [], "requirements": {"degrees": [], "majors": [], "languages": [], "language_level": [], "hard_skills": [], "soft_skills": [], "languages_combined": []}, "experience_required": {"duration": [], "field": []}}, {"job_id": "100003009052779", "location_code": "hk", "company": "Blockchain Solutions Limited", "job_title": "Script Writer", "description": "Responsibilities:\u00a0\u00a0\nResponsible and optimization of overseas advertisement channels such as Google, Facebook and Instagram\nSolid experience with social media including blogs, Instagram, Facebook, etc.\nProvide and execute marketing plans including strategy, budget, goals of the project launches\nManager all-rounded marketing and promotion campaigns covering (both online & offline promotions, e-marketing, social media campaign, website updates and consumer experience enhancement)\nOrganize product seeding among celebrities, KOL, media, influencers\nResearch and monitor the strategies of competitors and adjust project plan\nManage brand positioning and product design, online activities planning and promotion for the platforms\n\nRequirements:\n\nDegree or above in Business, Advertising, Marketing, Communications, E-commerce, Project Management, PR or related discipline;\n3 years or above solid experience in marketing / project management\nGood knowledge or experience in HTML, Search Engine Marketing and SEO is an advantage\nKnowledge in\u00a0Google Analytics/ Google Ads/ Facebook Ads Manager tools is a must - Proficient in spoken and written English and Chinese\nEnergetic, self-motivated, detail-oriented, passionate,\u00a0results-oriented and able to work under pressure\nGreat communication and management skills\n\nInterested Candidates,\u00a0please send your\u00a0full resume with your recent photo,\u00a0current & expected salary\u00a0by e-mail to\u00a0hr @moderndentallab.com.\nAll personal data collected will be used for recruitment and employment related purpose only.", "employment_types": ["Full Time", "Permanent"], "selling_points": ["5 days work", "Medical Insurance\uff1b Annual Leave", "Flexible working hours"], "locations": ["Shatin Area"], "categories": ["Marketing / Public Relations", "Public Relations - Copy-writing"], "post_time": "2022-01-17T04:01:58Z", "salary": {"currency": null, "max": null, "min": null, "period": "monthly", "term": null}, "salary_visible": false, "title_keywords": [], "responsibilities": ["social media", "marketing plans", "budget", "monitor", "website", "project plan", "promotion campaigns", "product design", "facebook", "planning"], "requirements": {"degrees": ["degree or above"], "majors": ["e-commerce", "project management", "business", "marketing", "communications"], "languages": ["english", "chinese"], "language_level": ["proficient"], "hard_skills": ["google analytics", "seo", "e-commerce", "html", "project management", "facebook"], "soft_skills": ["passionate", "self-motivated", "detail-oriented", "communication", "project management", "energetic", "work under pressure"], "languages_combined": [{"language": "english", "language_level": ["proficient"]}, {"language": "chinese", "language_level": ["proficient"]}]}, "experience_required": {"duration": ["3 years"], "field": ["project management", "marketing"]}}, {"job_id": "100003009052168", "location_code": "hk", "company": "A-World Consulting Limited", "job_title": "Account Executive/ Senior Account Executive", "description": "Job Description\n\n\n\nDevelop engaging content, edit, translate and proofread the promotional materials for marketing channels (i.e. brochures, press releases, professional bulletins, newsletters, website articles) in line with the brand guidelines and marketing campaigns.\nBe able to create brand story script, tagline and advertising slogan write-up\nEnsure consistency both within and across documents, brands, sub brands and partner\nEnsure projects are completed with high quality and on schedule.\nExcellent English and Chinese writing skills.\nA team player, positive and flexible\nOther ad hoc projects\n\nRequirements:\n\nDegree holder in Business, Marketing Communications, Advertising, Journalism, writing-related major or related disciplines is preferred\n1-2 years of experience in B2B copywriting.\nKnowledge on Finance/ Blockchain or cryptocurrency fields related is a plus\nSharp creative writing skills, conceptual minded and sound editorial judgment\nExperiences in social media, user experience design, and content development is a plus\nExcellent\u00a0command of Chinese and English\nAbility to work collaboratively as well as autonomously\nStrong communication skills\nAble to write in varies style\n\nBenefits\uff1a\n\nPublic Holiday\nMedical Insurance\nAnnual Leave\nDiscretionary Bonus\nMandatory Provident Fund Contribution\nExcellent Training & Career Advancement Opportunities", "employment_types": ["Full Time", "Permanent"], "selling_points": ["5 days work per week", "performance bonus", "Fresh Graduate also welcome"], "locations": ["Sheung Wan"], "categories": ["Media & Advertising", "Editorial / Journalism", "Marketing / Public Relations", "Public Relations - Copy-writing", "Public Relations - Event Management"], "post_time": "2022-01-17T02:19:09Z", "salary": {"currency": null, "max": null, "min": null, "period": "monthly", "term": null}, "salary_visible": false, "title_keywords": ["account executive", "senior account executive"], "responsibilities": ["advertising", "quality", "website", "develop", "promotional materials", "brand guidelines", "schedule", "marketing campaigns", "ad hoc projects"], "requirements": {"degrees": ["degree holder"], "majors": ["marketing communications", "related disciplines", "business", "journalism"], "languages": ["english", "chinese"], "language_level": ["excellent"], "hard_skills": ["blockchain", "plus", "writing skills", "cryptocurrency"], "soft_skills": ["communication skills", "creative", "writing skills"], "languages_combined": [{"language": "english", "language_level": ["excellent"]}, {"language": "chinese", "language_level": ["excellent"]}]}, "experience_required": {"duration": ["1-2 years"], "field": ["copywriting", "social media", "content development", "design"]}}, {"job_id": "100003009054157", "location_code": "hk", "company": "China Life Insurance (Overseas) Company Limited", "job_title": "Manager (\u516c\u6587\u5d17)", "description": "What You Do:\n\nTo develop and edit content for the Group\u2019s promotion channels\nResponsible in the areas of draft copywriting, project documentation for branding projects\nEnsure all branding projects / events / collaterals production are delivered on time, within scope, budget and technical feasibility\nMeasure project performance by using appropriate systems, tools and techniques\nPerform risk management to minimize the project risks\nLiaise with both internal and external parties to ensure all branding initiatives are conducted effectively\nEstablish and maintain the relationships with the client and all stakeholders (vendors / third parties)\nHandle ad-hoc project as assigned by supervisor\n\nWho Will Thrive:\n\nDegree holders in Marketing or Business related disciplines with at least 3 years\u2019 of solid experience\nGood knowledge in branding, marketing or project management are highly preferred\nOrganized and possess good project management skills\nStrategic and creative mindset with business insights\nGood interpersonal & communication skills\nGood command of written and spoken English, Cantonese and Mandarin\nOccasionally business travels are necessary\nImmediately available is highly preferred\nBenefits:\n5-day work\nCompetitive salary, staff meal,\u00a0medical and dental insurance, life insurance\nVarious types of leave, e.g. Family-friendly leave, self-development leave,\u00a0Examination leave, marriage leave, birthday leave, volunteer service leave, etc\nWe offer excellent career opportunities, attractive remuneration package & benefits to the right candidate. Interested parties please click \"Apply Now\" below or apply with full resume with portfolio by stating latest and expected salaries to 22/F, Chow Tai Fook Centre, 580A-580F Nathan Road, Mongkok, Kowloon, Hong Kong.\nAll information collected for recruitment purpose only.", "employment_types": ["Full Time", "Permanent"], "selling_points": ["Corporate governance", "Communicate with Group Company", "Prepare presentation material."], "locations": ["Hung Hom"], "categories": ["Marketing / Public Relations", "Public Relations - Copy-writing", "Public Relations - General / Support", "Media & Advertising", "Print Media"], "post_time": "2022-01-17T08:36:22Z", "salary": {"currency": null, "max": null, "min": null, "period": "monthly", "term": null}, "salary_visible": false, "title_keywords": ["manager"], "responsibilities": ["ad-hoc", "management", "budget", "systems", "internal and external parties", "develop", "communication", "project management", "maintain", "liaise with", "project documentation"], "requirements": {"degrees": ["degree"], "majors": ["business", "related disciplines", "marketing"], "languages": ["cantonese", "english", "mandarin"], "language_level": ["good command"], "hard_skills": ["documentation", "project management"], "soft_skills": ["organized", "communication skills", "responsible", "project management skills", "creative mindset", "project management", "interpersonal"], "languages_combined": [{"language": "cantonese", "language_level": ["good command"]}, {"language": "english", "language_level": ["good command"]}, {"language": "mandarin", "language_level": ["good command"]}]}, "experience_required": {"duration": ["at least 3 years"], "field": ["business", "marketing", "related"]}}, {"job_id": "100003009051771", "location_code": "hk", "company": "The Great Eagle Group of Companies", "job_title": "Assistant Officer - Digital Marketing", "description": "Responsibilities:\n\nAssist in supporting and managing the day to day operations of a website / e-commerce business, include CMS, content, SEO, online shop, and customer engagement / support\nSupport marketing cloud operation including customer journey building, automation, email and sms preparation and customer engagement / support\nAssist in planning and implementation of marketing campaigns and promotion activities including but not limited to social media, blogs, KOLs, PR, media\nSupport in data and analytical tasks to run reports, create insights, and optimize marketing campaigns\nSupport in preparing, updating marketing materials (content/visuals), maintain, and drive brand awareness via online and offline marketing\nSupport event planning and operations, including but not limited to material sourcing, vendor coordination, logistics, rsvp\nWork closely with internal and external parties to facilitate smooth implementation and operation of marketing strategies on digital, traditional marketing and event coordination\nHandle other ad hoc projects assigned\n\nRequirements:\n\nDegree holder or above in Communication, Language, Literature, Marketing, Business or related disciplines\n1 - 3 years\u2019 experience in marketing or digital technology, preferable gained in managing external agencies / vendors / recent grads with solid intern experience are welcome\nHands-on experience in online and offline marketing and e-commerce\nWell-organized with ability to prioritize and multi-task\nSelf-motivated, result-oriented and attentive to details\nGood project management, interpersonal skills and communication skills\nGood command of both written and spoken English and Chinese\n\nSalary and benefits will be commensurate with qualifications and experience.\u00a0 Interested parties, please send a full resume with present and expected salary, and date available to The Human Resources Department, 32/F., Great Eagle Centre, 23 Harbour Road, Wan chai, Hong Kong or e-mail to us.\u00a0(Please quote the reference no. on the envelope and the covering letter.)\n\nTo know more about us, please visit our website at http://www.greateagle.com.hk.\n\nWe are an equal opportunity employer and welcome applications from all qualified candidates.\n\nPersonal data collected will be treated in strict confidence and used only for recruitment-related purpose. Applicants who have not heard from us within four weeks may consider their applications unsuccessful. All personal data will be destroyed after 12 months.", "employment_types": ["Full Time", "Permanent"], "selling_points": ["Content marketing", "Social media management", "Marketing campaigns and promotion"], "locations": ["Wan Chai"], "categories": ["Marketing / Public Relations", "Marketing - Marketing Communication", "Public Relations - Copy-writing", "Digital Marketing"], "post_time": "2022-01-17T01:01:39Z", "salary": {"currency": null, "max": null, "min": null, "period": "monthly", "term": null}, "salary_visible": false, "title_keywords": ["assistant officer", "digital marketing"], "responsibilities": ["social media", "seo", "day to day operations", "marketing strategies", "data", "operations", "internal and external parties", "implementation", "website", "maintain", "reports", "logistics", "marketing campaigns", "coordination", "marketing materials", "ad hoc projects", "planning"], "requirements": {"degrees": ["recent grads", "degree holder"], "majors": ["business", "related disciplines", "marketing"], "languages": ["english", "chinese"], "language_level": ["good command"], "hard_skills": ["project management", "e-commerce"], "soft_skills": ["communication skills", "self-motivated", "multi-task", "attentive to details", "well-organized", "prioritize", "communication", "project management", "hands-on", "interpersonal skills", "result-oriented"], "languages_combined": [{"language": "english", "language_level": ["good command"]}, {"language": "chinese", "language_level": ["good command"]}]}, "experience_required": {"duration": ["1 - 3 years"], "field": ["digital", "marketing", "e-commerce"]}}, {"job_id": "100003009051488", "location_code": "hk", "company": "Imbee Limited", "job_title": "Creative Writer (English, Saas)", "description": "Please apply via:\u00a0https://jobs.lever.co/imbeelimited/93a6e4b9-05c5-417b-99fb-a7bb944bebd9\nHyper-growth tech startup. VC-backed. Competitive package. Remote work. Friendly team. : )\nAbout imBee\nimBee.io\u00a0is the #1 Customer Chat Management Platform - it provides one inbox for all communication channels with best-in-class business tools and workflow automation for brands to scale their business and communicate better externally with customers and internally with teams.\nAs one of the venture-backed, fastest-growing startups in Asia, we serve clients across industries and sizes. Some of our happy clients are insurance giants, telecom enterprises, and SMEs in the e-commerce, retail, education, and medical industry.\nOur Mission\nThe world is becoming more conversational - we\u2019re on a mission to empower businesses to scale on all communications channels effectively.\nWe\u2019re reinventing the way businesses communicate with their customers and teams, from the ground up, so businesses can sell more, accomplish more collaboratively, save more, and build better relationships with customers.\nOur Culture\nWe\u2019re ambitious, collaborative, and fun. We work smart and play hard, and pursue excellence in everything we do. It\u2019s a learning culture that we embrace.\u00a0\nAnd we care about each and everyone in our team - we want to help you achieve your personal goals and be part of this exciting and unforgettable journey.\nYou can enjoy a flexible work environment (remote work), free snacks and beers, game room, and more!\nRole\nWe are seeking an experienced writer to help improve the communication of our website, product messaging, and marketing materials. The ideal candidate will have a passion for writing and possess strong written communication skills.\n\nResponsibilities:\n\nTranslate customer needs and market demand into sharp and compelling messaging, content, sales tools, and campaigns to help us meet our business goals\nResearch and understand the client's needs and target audiences, through research, and interviews with subject matter experts\nWriting clear and engaging content for our website including blogs, and sales and marketing materials that reflects our brand\nDefine key messages and brand voice for external communications\nCollaborate with growth team and designers on marketing projects (e.g. email campaigns and landing pages)\nRequirements\n\nStrong editorial, proofreading, and writing skills (English)\nAbility to translate what customers want into compelling messages\nExperience with content marketing and cross-functional responsibilities\nExcellent interpersonal, verbal, and written communication skills\nAbility to manage multiple projects and meet deadlines under pressure\nPassion for writing with an excellent portfolio of work", "employment_types": ["Full Time", "Part Time", "Permanent", "Contract", "Freelance"], "selling_points": [], "locations": ["Kowloon City Area"], "categories": ["Media & Advertising", "Editorial / Journalism", "Marketing / Public Relations", "Public Relations - Copy-writing"], "post_time": "2022-01-16T04:16:56Z", "salary": {"currency": "HKD", "max": 24999, "min": 17000, "period": "monthly", "term": null}, "salary_visible": true, "title_keywords": ["creative"], "responsibilities": ["collaborate with", "business goals", "marketing projects", "website", "marketing materials"], "requirements": {"degrees": [], "majors": [], "languages": ["english"], "language_level": [], "hard_skills": ["writing skills"], "soft_skills": ["communication skills", "under pressure", "passion for", "writing skills", "meet deadlines", "interpersonal"], "languages_combined": [{"language": "english", "language_level": []}]}, "experience_required": {"duration": [], "field": ["marketing"]}}, {"job_id": "100003009051529", "location_code": "hk", "company": "Ma Belle Jewellery Co Ltd", "job_title": "Senior Officer/ Officer - Branding/ Communications/ Marketing", "description": "Senior Officer/ Officer - Banding/ Communications/ Marketing\nBased at our Hong Kong headquarters, you will be a team member to interact and work closely with a professional team delegated for the assigned distinguished jewellery brands.\nIf you have the right attitudes and aspirations of develop yourself in luxury retail will receive our investment in your career.\nThe Job\nDevelop and execute all-rounded marketing campaigns and promotions (both conventional and digital), ensure the timely, accurate deployment of all promotion campaigns;\nTo plan and execute all websites and social media platforms\nAnalyze marketing data and preparing regular reports to keep track of the campaign performance\nWork closely with internal departments, external partners and vendors to deliver marketing and event activities\nProvide support to frontline's event/ enquiries and follow up\nThe Person\nDegree in Marketing or business related disciplines\n2 years marketing/ communications experience, preferably gained in retail industry\nIndependent, Creative, multi-tasked and able to work under pressure in a fast paced environment\nGood interpersonal skills and ability to communicate effectively\nCandidates with less experience will be considered as Officer\nAttractive remuneration package will be offered to the right candidate. Please email full resume with current and expected salary to us\nPersonal data collected will be used for recruitment purposes only and will be treated in strict confidence.\u00a0 Applicants not invited for interview within 16 weeks may consider their applications unsuccessful and all information submitted will be destroyed.", "employment_types": ["Full Time"], "selling_points": ["Senior Branding Officer/ Officer", "execute conventional & digital marketing campaign", "plan & execute  websites and social media platform"], "locations": ["Tin Hau"], "categories": ["Marketing / Public Relations", "Marketing - Brand / Product Management", "Marketing - Marketing Communication", "Public Relations - Copy-writing"], "post_time": "2022-01-16T08:08:08Z", "salary": {"currency": null, "max": null, "min": null, "period": null, "term": null}, "salary_visible": false, "title_keywords": ["senior officer", "officer"], "responsibilities": ["provide support", "data", "social media platforms", "develop", "promotion campaigns", "reports", "plan", "marketing campaigns"], "requirements": {"degrees": ["degree"], "majors": ["business", "related disciplines", "marketing"], "languages": [], "language_level": [], "hard_skills": [], "soft_skills": ["confidence", "independent", "multi-tasked", "interpersonal skills", "creative", "work under pressure"], "languages_combined": []}, "experience_required": {"duration": ["2 years"], "field": ["retail industry", "marketing"]}}, {"job_id": "100003009050285", "location_code": "hk", "company": "Clarity Medical Group Holding Limited", "job_title": "Content Specialist", "description": "Responsibilities:\u00a0\n\nPlan and manage all Social Media platforms strategy including content creation and posting\nResponsible for writing marketing promotional articles and create scripts for video production\nPerform ad hoc projects as required\n\nRequirements:\n\nHigh Diploma or above, preferably in Communications, Marketing, Journalism, PR or related disciplines\nExcellent writing, editing, presentation and communication skills\nStrong sense of responsibility, mature, detail-minded and self-motivated\nImmediate availability preferred\n\nInterested parties, please send\u00a0detailed resume in WORD FORMAT with current and EXPECTED SALARY to the HR Department by clicking \"APPLY NOW\".\n\nData collected will be used for recruitment purposes only and personal data of unsuccessful applicants will be destroyed after 12 months.", "employment_types": ["Full Time"], "selling_points": [], "locations": ["Central"], "categories": ["Media & Advertising", "Editorial / Journalism", "Marketing / Public Relations", "Public Relations - Copy-writing", "Digital Marketing"], "post_time": "2022-01-14T10:03:37Z", "salary": {"currency": null, "max": null, "min": null, "period": "monthly", "term": null}, "salary_visible": false, "title_keywords": ["specialist"], "responsibilities": ["video production", "social media platforms", "ad hoc projects", "plan"], "requirements": {"degrees": ["high diploma or above"], "majors": ["journalism", "related disciplines", "marketing", "communications"], "languages": [], "language_level": [], "hard_skills": [], "soft_skills": ["detail-minded", "communication skills", "self-motivated", "sense of responsibility", "mature", "presentation"], "languages_combined": []}, "experience_required": {"duration": [], "field": []}}, {"job_id": "100003009054765", "location_code": "hk", "company": "Tam Jai International Co. Limited", "job_title": "Corporate Communications Officer", "description": "Responsibilities\n\nAssist in launching corporate activities and ESG programs\nSupport project execution, event organization, logistics arrangement, data management, etc.\nDevelop, edit and translate external communications materials (online and offline) including but not limited to, press release, newsletter, speeches, website content and presentation materials\nMonitor and update Company website and external communications platforms\nLiaise and coordinate with both internal and external stakeholders, including but not limited to overseas offices of the Group\nProvide administrative support and coordination work for the department\nOther ad hoc projects as required\n\nRequirements\n\nDegree holder in communications, language and linguistics, translation, journalism or related disciplines\nAt least 3 years of working experience in corporate communications in listed companies and / or financial PR agency\nExperience in results announcement and ESG reporting at a listed company would be an advantage\nStrong in creative writing and content generation\nExcellent command of written and spoken English and Chinese (including Mandarin); High proficiency in Japanese would be an advantage\nSelf-starter, detail-minded, well-organized and committed to excellence\n\nWe offer 5-day work week, on-the-job development program and rewarding career opportunities for ambitious individuals who are looking for challenges. If you aspire to an exciting and rewarding career, send your resume immediately with your present and expected salary.\n\n(All personal data collected will be used for recruitment purpose only.)", "employment_types": ["Full Time", "Permanent"], "selling_points": ["Strong in creative writing and content generation", "Excellent command of written and spoken English", "Exp. in listed companies or financial PR agencies"], "locations": ["Lai Chi Kok"], "categories": ["Media & Advertising", "Editorial / Journalism", "Marketing / Public Relations", "Marketing - Marketing Communication", "Public Relations - Copy-writing"], "post_time": "2022-01-17T10:58:55Z", "salary": {"currency": null, "max": null, "min": null, "period": "monthly", "term": null}, "salary_visible": false, "title_keywords": ["corporate communications officer"], "responsibilities": ["liaise", "management", "data", "logistics arrangement", "monitor", "website", "coordinate with", "develop", "ad hoc projects", "coordination", "provide administrative support", "company website"], "requirements": {"degrees": ["degree holder"], "majors": ["journalism", "related disciplines", "communications"], "languages": ["japanese", "english", "chinese", "mandarin"], "language_level": ["advantage", "excellent", "proficiency"], "hard_skills": ["translation"], "soft_skills": ["detail-minded", "committed", "creative", "well-organized"], "languages_combined": [{"language": "japanese", "language_level": ["proficiency", "advantage"]}, {"language": "english", "language_level": ["excellent"]}, {"language": "chinese", "language_level": ["excellent"]}, {"language": "mandarin", "language_level": ["excellent"]}]}, "experience_required": {"duration": ["at least 3 years"], "field": ["agency", "pr", "financial"]}}, {"job_id": "100003009055999", "location_code": "hk", "company": "ConnectedGroup Limited", "job_title": "English Writing Specialist (12-month)", "description": "Our Client is one of the leading financial services institutions in the market. We are currently hiring a Specialist to join its Communications team.\n\nYou will be reporting directly to the Head of Communications focusing on English writing at corporate level.\n\nResponsibilities:\n\nDesign, prepare and publish contents for a range of marketing and campaign materials, i.e. senior executive speeches, brochures, newsletters, annual report sections, digital channels, etc.\nWrite, edit and proof-read of a variety of internal communications for strategic targets\nWork closely with other internal parties and provide support to internal messages, such as press releases, Q&A documents, etc.\nCreate and maintain specific writing guidelines to ensure brand consistency and accuracy\nPerform other ad-hoc projects\n\nRequirements:\n\nBachelor's Degree in English, Communications or Journalism is preferred\nAt least 8 years of experience as a professional writer (English) and/or editor (English) within large organizations, journalists are also welcomed\nStrong communication and interpersonal skills, with good storytelling skills\nExcellent writing/editorial skills with proven portfolio\nExperience working in finance related content a plus\n\nFor those who are interested, please submit your latest profile (in WORD Format) to raman.hong@connectedgroup.com. Only qualified candidates will be contacted.", "employment_types": ["Full Time", "Contract"], "selling_points": ["Leading Financial Services", "International Culture", "English Content Writer"], "locations": ["Not Specified"], "categories": ["Insurance", "Others", "Marketing / Public Relations", "Marketing - Marketing Communication", "Public Relations - Copy-writing"], "post_time": "2022-01-18T03:10:39Z", "salary": {"currency": null, "max": null, "min": null, "period": "monthly", "term": null}, "salary_visible": false, "title_keywords": ["specialist"], "responsibilities": ["provide support", "guidelines", "design", "maintain", "contents", "brand consistency", "ad-hoc projects", "internal parties", "report"], "requirements": {"degrees": ["degree", "bachelor"], "majors": ["journalism", "communications"], "languages": ["english"], "language_level": [], "hard_skills": ["plus", "word"], "soft_skills": ["communication and interpersonal skills"], "languages_combined": [{"language": "english", "language_level": []}]}, "experience_required": {"duration": ["at least 8 years"], "field": ["editor", "finance", "related"]}}, {"job_id": "100003009049003", "location_code": "hk", "company": "Shun Tak Holdings Ltd", "job_title": "Corporate Communications Executive (Ref. STHL1713)", "description": "Job Duties:\n\nSupport the department in English and Chinese editorial needs;\nMonitor media coverage to provide analysis and insights;\nConduct research on public affairs to provide market intelligence;\nParticipate in organizing corporate and media events;\nAssist in building and maintaining good relationships with key stakeholders;\nProvide administrative support to the department;\nSupport any ad-hoc duties as and when required.\n\nRequirements:\n\nDegree holder in Translations, English Studies, Mass Communications or related disciplines;\nPreferably has 1 year of relevant working experience but fresh graduate with a strong desire to learn will also be considered;\nExcellent command of written and spoken English and Chinese, conversant in Mandarin is preferred;\nStrong PC skills, familiar with creative software is preferable;\nTeam player, good interpersonal and communications skills.\n\nWe offer long-term career prospect and competitive remuneration package to the appointed candidate. Please apply in confidence with your detailed resume stating your current and expected salary to\u00a0Group Human Resources Department\n\nby email to\u00a0recruit(at)shuntakgroup.com\n\nor mail to\u00a0Penthouse 39/F, West Tower, Shun Tak Centre, 200 Connaught Road Central, Hong Kong\n\n(Please quote reference number and applied position)\n\nThe information supplied by the applicants will be used in accordance with the Personal Data (Privacy) Policy of Shun Tak Group (a copy of which will be provided upon request). Only shortlisted candidates will be notified.\n\n\nwww.shuntakgroup.com", "employment_types": ["Full Time"], "selling_points": ["Support the department in editorial needs", "Monitor media coverage to provide analysis", "Conduct research on public affairs"], "locations": ["Sheung Wan"], "categories": ["Marketing / Public Relations", "Marketing - Marketing Communication", "Public Relations - Copy-writing", "Public Relations - General / Support"], "post_time": "2022-01-14T07:54:01Z", "salary": {"currency": null, "max": null, "min": null, "period": "monthly", "term": null}, "salary_visible": false, "title_keywords": ["executive"], "responsibilities": ["maintaining", "analysis", "monitor", "ad-hoc duties", "provide administrative support", "conduct research"], "requirements": {"degrees": ["fresh graduate", "degree holder"], "majors": ["related disciplines", "communications"], "languages": ["english", "chinese", "mandarin"], "language_level": ["excellent"], "hard_skills": ["pc skills"], "soft_skills": ["team player", "creative", "interpersonal"], "languages_combined": [{"language": "english", "language_level": ["excellent"]}, {"language": "chinese", "language_level": ["excellent"]}, {"language": "mandarin", "language_level": ["excellent"]}]}, "experience_required": {"duration": ["1 year"], "field": ["relevant working experience"]}}, {"job_id": "100003009045968", "location_code": "hk", "company": "Smart Will Engineering Limited", "job_title": "\u5ee3\u544a\u52a9\u7406\u53ca\u64b0\u7a3f\u54e1 PR and Copywriter HK$17,000 - 25,000 /month", "description": "\n\u2022 \u8ca0\u8cac\u64b0\u5beb\u7e55\u7a3f , \u7ba1\u7406\u516c\u53f8FACEBOOK\u53ca\u5404\u5927\u793e\u4ea4\u5a92\u9ad4\n\u2022 \u5c0d\u5916\u5a92\u9ad4\u95dc\u4fc2\u53ca\u806f\u7d61\n\u2022 \u5167\u90e8\u884c\u653f\u6587\u66f8\u5de5\u4f5c\n\u2022 \u516c\u53f8\u7db2\u9801 : www.dic.hk\n\u2022 \u61c9\u5fb5\u8005\u9808\u6709\u826f\u597d\u6e9d\u901a\u80fd\u529b\u3001\u500b\u6027\u7d30\u5fc3\u3001\u6709\u8cac\u4efb\u5fc3\u3001\u52e4\u596e\u53ca\u4e0d\u8a08\u8f03\n\u2022 \u80fd\u5373\u6642\u4e0a\u73ed\u8005\u7372\u512a\u5148\u8003\u616e\n\u2022 \u4e0a\u73ed\u5730\u5740 : \u706b\u70ad\n\u2022 \u4e0a\u73ed\u6642\u9593 : \u4e0a\u534810\u664230\u5206\u81f3\u4e0b\u53488\u6642, \u6bcf\u9031\u5de5\u4f5c5.5\u5929,\u8f2a\u4f11, \u6bcf\u5929\u5de5\u4f5c 8 .5\u5c0f\u6642\n\u672c\u516c\u53f8\u63d0\u4f9b\u512a\u79c0\u6649\u5347\u524d\u666f\u53ca\u5f85\u9047\uff0c\u8acb\u5c07\u500b\u4eba\u5c65\u6b77\u3001\u8981\u6c42\u5f85\u9047\u53ca\u806f\u7d61\u65b9\u6cd5\uff0cApply Now\u3002\n\n", "employment_types": ["Full Time"], "selling_points": [], "locations": ["Shatin Area"], "categories": ["Media & Advertising", "Editorial / Journalism", "Marketing / Public Relations", "Public Relations - Copy-writing"], "post_time": "2022-01-13T09:15:13Z", "salary": {"currency": "HKD", "max": 24999, "min": 17000, "period": "monthly", "term": null}, "salary_visible": true, "title_keywords": ["copywriter"], "responsibilities": [], "requirements": {"degrees": [], "majors": [], "languages": [], "language_level": [], "hard_skills": [], "soft_skills": [], "languages_combined": []}, "experience_required": {"duration": [], "field": []}}, {"job_id": "100003009051103", "location_code": "hk", "company": "Hong Kong Design Centre Limited", "job_title": "Senior Project Executive \u2013 Marketing Communications", "description": "The Roles\n\nCoordinate, execute and support a variety of corporate and marketing communications activities, public relations and promotion initiatives;\nDrive and deliver a range of marketing communication materials, including but not limited to speeches, press release and media kit, corporate collaterals and enewsletter, editorial and publishing projects, marketing and social media content, surveys and research, etc.;\nMonitor and uphold branding and corporate identity of HKDC and its affiliated programmes;\nManage corporate assets including printed collaterals, digital, visual and video content and online platforms e.g. website, social media channels and email database;\nWork with internal and external parties for the production of HKDC Annual Report, publications and marketing collaterals;\nEffectively handle the logistics and coordination of corporate visits and and provide onsite support to corporate events / activities;\nWork with internal stakeholders and external parties and vendors on a variety of HKDC initiatives;\nManage the overall communication plan and logistics of the corporate membership and partnership programmes; and\nCarry out other ad hoc projects and duties as assigned.\n\n\u00a0\u00a0Requirements\n\nUniversity graduate in Marketing, Communications, Journalism or Translation;\nMinimum 5 years of relevant work experience in marketing, corporate communications or public relations;\nExcellent copywriting and translation skills in both English and Chinese, with fluent spoken English, Cantonese and Putonghua;\nDigital savvy, creative and passionate about communications, with sound knowledge of different social media and communications platforms and trends;\nA self-motivated team-player with strong attention to detail; and\nMature, outgoing multi-tasker with good organisational and project management skills.\n\n\nInterested parties are invited to apply by sending your resume with full details of education, work experience, current & expected salary, contact telephone number and earliest available date to the Human Resources Office, Hong Kong Design Centre, Unit 602, 6/F, Mill 5, The Mills, 45 Pak Tin Par Street, Tsuen Wan or by clicking \u201cApply Now\u201d or email to:\u00a0hr[@]hkdesigncentre.org\u00a0on or before 28 January 2022. HKDC reserves the right not to make appointment for the post(s) advertised. Only short-listed candidates will be notified. All information received will be kept in strict confidence for six months and data will only be used for recruitment purpose.", "employment_types": ["Full Time"], "selling_points": [], "locations": ["Tsuen Wan Area"], "categories": ["Media & Advertising", "Editorial / Journalism", "Marketing / Public Relations", "Marketing - Marketing Communication", "Public Relations - Copy-writing"], "post_time": "2022-01-15T02:17:27Z", "salary": {"currency": null, "max": null, "min": null, "period": "monthly", "term": null}, "salary_visible": false, "title_keywords": ["senior project executive"], "responsibilities": ["data", "internal and external parties", "marketing collaterals", "website", "external parties", "design", "communication", "social media content", "database", "plan", "monitor", "logistics", "visual", "report", "social media", "contact", "coordinate", "project management", "ad hoc projects", "recruitment", "coordination"], "requirements": {"degrees": ["university graduate"], "majors": ["journalism", "marketing", "communications"], "languages": ["cantonese", "putonghua", "english", "chinese"], "language_level": ["excellent", "fluent"], "hard_skills": ["translation", "project management", "wan", "make"], "soft_skills": ["outgoing", "self-motivated", "confidence", "team-player", "project management skills", "mature", "communication", "coordination", "attention to detail", "creative", "passionate about"], "languages_combined": [{"language": "cantonese", "language_level": ["excellent", "fluent"]}, {"language": "putonghua", "language_level": ["excellent", "fluent"]}, {"language": "english", "language_level": ["excellent", "fluent"]}, {"language": "chinese", "language_level": ["excellent", "fluent"]}]}, "experience_required": {"duration": ["minimum 5 years"], "field": ["public relations", "design", "education", "marketing", "human resources"]}}, {"job_id": "100003009044564", "location_code": "hk", "company": "Manpower Services (Hong Kong) Limited", "job_title": "Content Reviewer/Proofreader/Editor/Copywriter - English speaking(Double Pay,Up to 30K)", "description": "\nYou\u00a0will create impact via\u2026\n\nGenerate assets for print and digital mediums with deliverables including client testimonials, social media content, email marketing, pitch decks, advertisement copywriting and other branding communication materials\nSupport interactive content creation - photos/video shooting, production and edition for contents needed for the posting on websites, SEO, Ads copies, and different social media like Facebook and LinkedIn\nEnsure brand consistency across all materials\nSupport the content strategy across different channels\nCoordinate and support other projects as required\nCommunicate with internal stakeholders, partners or agencies as occasion arise\nThe follow attributes will be valued\u2026\n\nMinimum 4 years related working experience. Candidate with\u00a0tech, agency or FMCG background is an added advantage\nHighly fluent in written and spoken English and excellent attention to details\nA passion for story-telling and delivering great copy\nFlexible and organised under pressure. Able to multi-task and meet tight deadlines\nAble to work independently as well as in a team\nLess experience will be considered as Officer - Marketing Communications\u00a0\n\n\nWhat you get in return\u2026\n\nApart from competitive salary package and benefits, in HKBN, you will work flexibly under our\u00a0Talent-first culture\u00a0and we uphold\u00a0Life-Work Priority. Examples of our flexible initiatives:\n\nFive-day work week\u00a0\nHalf Day Off Friday once a month\u00a0\nHalf Day Off on Festival Eve\u00a0\nUnique leaves arrangement: Family-care leave, Anniversary leave, Bonus leave, Volunteer leave, Sabbatical leave, etc.\nComprehensive medical and life insurance coverage\nUpgraded maternity leave and paternity leave\nDiscounted Talent plan offers including broadband and mobile plans and other promoted products\nEducation subsidies and Examination leave\nYear-end discretionary bonus\nInterested parties, please click \"Apply Now\" to submit your application.\n\n\n\nJoin Us Today!\n\nAll information provided by applicants will be treated in strict confidence and used for consideration in relation to the relevant post within the company.\n\nAll personal data of unsuccessful applicants will be destroyed within\u00a0one year. Applicants who are not invited for an interview within 3 weeks may consider their application unsuccessful.", "employment_types": ["Contract"], "selling_points": ["1 year working experience", "Native English Speaker", "5 days work"], "locations": ["Others"], "categories": ["Media & Advertising", "Editorial / Journalism", "Marketing / Public Relations", "Public Relations - Copy-writing", "Professional Services", "Translation"], "post_time": "2022-01-13T04:36:02Z", "salary": {"currency": null, "max": null, "min": null, "period": "monthly", "term": null}, "salary_visible": false, "title_keywords": ["editor", "copywriter"], "responsibilities": ["communicate with", "social media", "seo", "communication", "coordinate", "video shooting", "social media content", "contents", "facebook", "brand consistency"], "requirements": {"degrees": [], "majors": [], "languages": ["english"], "language_level": ["excellent", "fluent"], "hard_skills": ["facebook", "seo"], "soft_skills": ["flexible", "meet tight deadlines", "work independently", "under pressure", "multi-task", "passion for", "communication", "attention to details", "organised"], "languages_combined": [{"language": "english", "language_level": ["excellent", "fluent"]}]}, "experience_required": {"duration": ["minimum 4 years"], "field": ["related", "marketing communications"]}}, {"job_id": "100003009052064", "location_code": "hk", "company": "Eagle Sky Media Limited", "job_title": "Digital Marketing Officer (Advertising Agency , Digital Marketing, Social media)", "description": "Responsibilities:\nSocial media management including content development & consumer engagement\nCommunicate and extent good relationships with on-line media, KOL, vendors & platform partners\nAnalyze market trends and explore new marketing techniques & business opportunities\nParticipate and support internal teams for different marketing campaign and operation needs\nPrepare marketing proposal for client\nPrepare regular reports for management review\nParticipate & support in all new business initiatives and all ad hoc projects\nGood content writer\nStrong Creative Designer is much preferred\n\nRequirements:\n\nDegree holder in Marketing / Communication / Multi-media Design preferred\nMin. 2 years\u2019 experienced in marketing\nExcellent interpersonal, presentation and communication skills\nProficient in MS Word, Excel, PowerPoint and Chinese Word Processing\nFluency in written and spoken Chinese and English\nExperience in CMS (Wordpress) ,graphic design tools (Adobe Photoshop and Adobe Illustrator)\nDetail-minded, tech-savvy, outgoing, and flexible to work\nHard-working, willing to learn and able to handle multi-task, work under pressure and meet deadlines\nCandidate with more experienced will be considered as Senior Marketing Executive", "employment_types": ["Full Time", "Permanent"], "selling_points": ["CONTENT Marketing", "Advertising Agency", "designer"], "locations": ["Tsuen Wan Area"], "categories": ["Media & Advertising", "Creative / Design", "Design", "Graphics", "Marketing / Public Relations", "Public Relations - Copy-writing"], "post_time": "2022-01-17T08:45:18Z", "salary": {"currency": null, "max": null, "min": null, "period": "monthly", "term": null}, "salary_visible": false, "title_keywords": ["digital marketing officer", "digital marketing"], "responsibilities": ["social media", "management", "business initiatives", "business opportunities", "review", "teams", "regular reports for management", "ad hoc projects"], "requirements": {"degrees": ["degree holder"], "majors": ["marketing", "design"], "languages": ["english", "chinese"], "language_level": ["fluency", "proficient"], "hard_skills": ["excel", "chinese word processing", "adobe photoshop", "powerpoint", "adobe illustrator", "wordpress", "ms word"], "soft_skills": ["detail-minded", "communication skills", "outgoing", "flexible", "multi-task", "willing to learn", "communication", "hard-working", "meet deadlines", "interpersonal", "presentation", "work under pressure"], "languages_combined": [{"language": "english", "language_level": ["fluency"]}, {"language": "chinese", "language_level": ["fluency", "proficient"]}]}, "experience_required": {"duration": [], "field": ["graphic design"]}}, {"job_id": "100003009054295", "location_code": "hk", "company": "CHOW TAI FOOK JEWELLERY CO LTD", "job_title": "Associate, Branding Projects", "description": "What You Do:\n\nTo develop and edit content for the Group\u2019s promotion channels\nResponsible in the areas of draft copywriting, project documentation for branding projects\nEnsure all branding projects / events / collaterals production are delivered on time, within scope, budget and technical feasibility\nMeasure project performance by using appropriate systems, tools and techniques\nPerform risk management to minimize the project risks\nLiaise with both internal and external parties to ensure all branding initiatives are conducted effectively\nEstablish and maintain the relationships with the client and all stakeholders (vendors / third parties)\nHandle ad-hoc project as assigned by supervisor\n\nWho Will Thrive:\n\nDegree holders in Marketing or Business related disciplines with at least 3 years\u2019 of solid experience\nGood knowledge in branding, marketing or project management are highly preferred\nOrganized and possess good project management skills\nStrategic and creative mindset with business insights\nGood interpersonal & communication skills\nGood command of written and spoken English, Cantonese and Mandarin\nOccasionally business travels are necessary\nImmediately available is highly preferred\nBenefits:\n5-day work\nCompetitive salary, staff meal,\u00a0medical and dental insurance, life insurance\nVarious types of leave, e.g. Family-friendly leave, self-development leave,\u00a0Examination leave, marriage leave, birthday leave, volunteer service leave, etc\nWe offer excellent career opportunities, attractive remuneration package & benefits to the right candidate. Interested parties please click \"Apply Now\" below or apply with full resume with portfolio by stating latest and expected salaries to 22/F, Chow Tai Fook Centre, 580A-580F Nathan Road, Mongkok, Kowloon, Hong Kong.\nAll information collected for recruitment purpose only.", "employment_types": ["Full Time"], "selling_points": ["Branding Projects / Group\u2019s promotion channels", "Branding, marketing, project management", "5-day work"], "locations": ["Kwai Hing"], "categories": ["Marketing / Public Relations", "Marketing - Brand / Product Management", "Public Relations - Copy-writing", "Public Relations - General / Support"], "post_time": "2022-01-17T09:05:12Z", "salary": {"currency": null, "max": null, "min": null, "period": "monthly", "term": null}, "salary_visible": false, "title_keywords": ["associate"], "responsibilities": ["ad-hoc", "management", "budget", "systems", "internal and external parties", "develop", "communication", "project management", "maintain", "liaise with", "project documentation"], "requirements": {"degrees": ["degree"], "majors": ["business", "related disciplines", "marketing"], "languages": ["cantonese", "english", "mandarin"], "language_level": ["good command"], "hard_skills": ["documentation", "project management"], "soft_skills": ["organized", "communication skills", "responsible", "project management skills", "creative mindset", "project management", "interpersonal"], "languages_combined": [{"language": "cantonese", "language_level": ["good command"]}, {"language": "english", "language_level": ["good command"]}, {"language": "mandarin", "language_level": ["good command"]}]}, "experience_required": {"duration": ["at least 3 years"], "field": ["business", "marketing", "related"]}}, {"job_id": "100003009046303", "location_code": "hk", "company": "H&W Technology Service Limited", "job_title": "Digital Copywriter (Fintech Industry)", "description": "About The Role:\n\n\nUnderstand and implement the company brand standard and ensure all copy and information are aligned with brand standard\nResponsible for writing and developing content, translating, editing and proofreading all copy for marketing materials online and offline (e.g. posters, website, brochures, press releases, professional bulletins, newsletters, etc.)\nAssist in business marketing communication, proofreading and copy editing to ensure consistency of tone, style and language used\nCopyedit all Company\u2019s product descriptions, brand-specific webpages and direct-to-consumer marketing communications in compliance with the highest standard for grammar, punctuation, spelling, style and tone under the direction of Marketing Manager\n\nWhat you\u2019ll need to have:\n\n\nDegree Holder in\u00a0English / Translation / Journalism / Communications / Public Relations preferred\nAt least 1 year of experience in copywriting/translation\nExperience in FX/ CFD products is an advantage\nDifferent techniques and styles of writing / editing / Translation/ copywriting\u00a0is an advantageous\nStrong sense of responsibility, detail-minded, self-motivated\nExcellent interpersonal, communication and presentation skills\nAble to work under pressure and tight deadline\nExcellent command of written & spoken English & Chinese, Fluent Mandarin\nKnowing Vietnamese, Indonesian, or Thai will definitely be an advantage\nImmediate available is highly preferred\nInternational candidates are also welcome\nWhy you should join us?\n\n\nWorking in a growth driven, collaborative open space where we encourage creativity and ideas flow freely.\nWorking within a small multi-cultural team where your ideas are welcome.\nFlat structure environment, you will be able to work independently and make your own choices\n\nDoes it sound like you?\n\nWe would love to talk to you!\n\nPlease send full resume with\u00a0current and expected salary\u00a0by clicking the Apply link and telling us why you want to work with us. If your skills and experience are a match, we will be in touch soon. Meanwhile, please visit our website at\u00a0https://www.hwtech.hk/\u00a0and social media channels to learn more about our innovative business.\n\nWe are an equal opportunity employer and welcome applications from all qualified candidates. All personal data collected will be treated in strict confidence and be used solely for recruitment purpose.", "employment_types": ["Full Time", "Permanent"], "selling_points": ["Implement the company brand standard", "Experience in FX/ CFD products is an advantage", "Different techniques and styles of writing/editing"], "locations": ["Hung Hom"], "categories": ["Media & Advertising", "Editorial / Journalism", "Marketing / Public Relations", "Marketing - Marketing Communication", "Public Relations - Copy-writing"], "post_time": "2022-01-13T10:24:33Z", "salary": {"currency": null, "max": null, "min": null, "period": "monthly", "term": null}, "salary_visible": false, "title_keywords": ["copywriter"], "responsibilities": ["social media", "product descriptions", "ideas", "compliance", "developing", "website", "communication", "proofreading", "recruitment", "personal data", "marketing materials", "editing", "work under pressure"], "requirements": {"degrees": ["degree holder"], "majors": ["journalism", "communications"], "languages": ["english", "mandarin", "thai", "vietnamese", "indonesian", "chinese"], "language_level": ["advantage", "excellent", "fluent"], "hard_skills": ["small", "translation", "make"], "soft_skills": ["detail-minded", "self-motivated", "work independently", "confidence", "responsible", "sense of responsibility", "driven", "collaborative", "communication", "presentation skills", "innovative", "interpersonal", "work under pressure"], "languages_combined": [{"language": "english", "language_level": ["fluent", "excellent"]}, {"language": "mandarin", "language_level": ["excellent"]}, {"language": "thai", "language_level": ["advantage"]}, {"language": "vietnamese", "language_level": ["advantage"]}, {"language": "indonesian", "language_level": ["advantage"]}, {"language": "chinese", "language_level": ["fluent", "excellent"]}]}, "experience_required": {"duration": ["at least 1 year"], "field": ["copywriting"]}}, {"job_id": "100003009047519", "location_code": "hk", "company": "HKBN Enterprise Solutions HK Limited", "job_title": "Senior Officer - Marketing Communications (Copywriting)", "description": "\nYou\u00a0will create impact via\u2026\n\nGenerate assets for print and digital mediums with deliverables including client testimonials, social media content, email marketing, pitch decks, advertisement copywriting and other branding communication materials\nSupport interactive content creation - photos/video shooting, production and edition for contents needed for the posting on websites, SEO, Ads copies, and different social media like Facebook and LinkedIn\nEnsure brand consistency across all materials\nSupport the content strategy across different channels\nCoordinate and support other projects as required\nCommunicate with internal stakeholders, partners or agencies as occasion arise\nThe follow attributes will be valued\u2026\n\nMinimum 4 years related working experience. Candidate with\u00a0tech, agency or FMCG background is an added advantage\nHighly fluent in written and spoken English and excellent attention to details\nA passion for story-telling and delivering great copy\nFlexible and organised under pressure. Able to multi-task and meet tight deadlines\nAble to work independently as well as in a team\nLess experience will be considered as Officer - Marketing Communications\u00a0\n\n\nWhat you get in return\u2026\n\nApart from competitive salary package and benefits, in HKBN, you will work flexibly under our\u00a0Talent-first culture\u00a0and we uphold\u00a0Life-Work Priority. Examples of our flexible initiatives:\n\nFive-day work week\u00a0\nHalf Day Off Friday once a month\u00a0\nHalf Day Off on Festival Eve\u00a0\nUnique leaves arrangement: Family-care leave, Anniversary leave, Bonus leave, Volunteer leave, Sabbatical leave, etc.\nComprehensive medical and life insurance coverage\nUpgraded maternity leave and paternity leave\nDiscounted Talent plan offers including broadband and mobile plans and other promoted products\nEducation subsidies and Examination leave\nYear-end discretionary bonus\nInterested parties, please click \"Apply Now\" to submit your application.\n\n\n\nJoin Us Today!\n\nAll information provided by applicants will be treated in strict confidence and used for consideration in relation to the relevant post within the company.\n\nAll personal data of unsuccessful applicants will be destroyed within\u00a0one year. Applicants who are not invited for an interview within 3 weeks may consider their application unsuccessful.", "employment_types": ["Full Time", "Permanent"], "selling_points": ["Experienced in creating content for various media", "Excellent in Chinese & English content writing", "Talent-first culture & Life-Work Priority"], "locations": ["Kowloon Bay"], "categories": ["Media & Advertising", "Creative / Design", "Marketing / Public Relations", "Marketing - Marketing Communication", "Public Relations - Copy-writing"], "post_time": "2022-01-14T03:22:04Z", "salary": {"currency": null, "max": null, "min": null, "period": "monthly", "term": null}, "salary_visible": false, "title_keywords": ["senior officer"], "responsibilities": ["communicate with", "social media", "seo", "communication", "coordinate", "video shooting", "social media content", "contents", "facebook", "brand consistency"], "requirements": {"degrees": [], "majors": [], "languages": ["english"], "language_level": ["excellent", "fluent"], "hard_skills": ["facebook", "seo"], "soft_skills": ["flexible", "meet tight deadlines", "work independently", "under pressure", "multi-task", "passion for", "communication", "attention to details", "organised"], "languages_combined": [{"language": "english", "language_level": ["excellent", "fluent"]}]}, "experience_required": {"duration": ["minimum 4 years"], "field": ["related", "marketing communications"]}}, {"job_id": "100003009055571", "location_code": "hk", "company": "Page Personnel", "job_title": "Assistant Corporate Communication Manager - I&T industry", "description": "Responsibilities:\n\nDevelop 2D motion and static graphic creatives for social/digital platforms\nSupport generation of social/digital marketing content & campaign ideas\nShoot and edit basic videos for internal communications video channel and social media platforms\u00a0\nResearch market information for creative brainstorming and maintain high level of social media awareness\nPrepare reports and support admin duties as needed\u00a0\nCoordinate with internal teams to co-produce digital marketing/branding materials\u00a0\nAssist in ad hoc tasks and projects as assigned by supervisor\n\nRequirements:\n\nCertificate/Diploma/Degree holder in Creative Arts, Graphic/Motion Graphic Design, or related disciplines\nKeen eye for aesthetics and details\nFresh graduates are welcome!\nPortfolio of proven expertise in motion graphic/graphic design and basic video editing\nProficient in Adobe Creative Suite (Illustrator, Photoshop, Premiere, After Effects, InDesign)\nFamiliar with MS Office, also knowledge in iOS preferred\nKnowledge in D animation, Spark AR would be a bonus\u00a0\nGood written and verbal in both English and Chinese\nSelf-motivated quick learner with good communication skills\n\nApart from competitive remuneration package and exciting opportunity for career development within the Group, we provide attractive employee benefits such as free company shuttle, free company SIM card and preferential SIM plan offers, comprehensive medical & insurance schemes, as well as full range of other employee well-being provisions.\n\nInterested parties, please apply with full resume, present and expected salary, by clicking \u201cAPPLY NOW\u201d. Please quote the reference number on the e-mail subject.\n\nWe are an equal opportunity employer and welcome applications from all qualified candidates. Personal data collected will be treated in the strictest confidence and handled confidentially by authorised personnel for recruitment-related purposes only within the CK Hutchison Group of companies. The personal data of unsuccessful applicants will be destroyed after the recruitment exercise pursuant to the requirements of the Personal Data (Privacy) Ordinance in Hong Kong.", "employment_types": ["Full Time", "Permanent"], "selling_points": ["Knowledge in Innovation & Technology industry", "Experienced in bilingual PR materials development", "Stable environment"], "locations": ["Not Specified"], "categories": ["Marketing / Public Relations", "Marketing - Marketing Communication", "Public Relations - Copy-writing", "Public Relations - Event Management"], "post_time": "2022-01-18T02:44:36Z", "salary": {"currency": null, "max": null, "min": null, "period": "monthly", "term": null}, "salary_visible": false, "title_keywords": ["manager", "assistant"], "responsibilities": ["social media", "market information", "ideas", "social media platforms", "coordinate with", "teams", "ad hoc tasks", "develop", "maintain", "digital marketing", "prepare reports"], "requirements": {"degrees": ["certificate", "diploma", "degree holder"], "majors": ["related disciplines", "graphic design"], "languages": ["english", "chinese"], "language_level": ["good"], "hard_skills": ["basic", "ar", "indesign", "illustrator", "premiere", "video editing", "after effects", "spark", "ms office", "adobe creative suite", "photoshop"], "soft_skills": ["communication skills", "self-motivated", "keen", "quick learner", "comprehensive", "creative"], "languages_combined": [{"language": "english", "language_level": ["good"]}, {"language": "chinese", "language_level": ["good"]}]}, "experience_required": {"duration": [], "field": []}}, {"job_id": "100003009044242", "location_code": "hk", "company": "Eternity Consultants (HK) Ltd", "job_title": "Copywriter / Editor / Translator", "description": "What are your key responsibilities?\u00a0\n\n\nConducting research to understand the market needs and targeted audience.\u00a0\nInterpreting briefs to develop and produce creative concepts through execution on assigned brands.\u00a0\nGenerating original copy,\u00a0editing content, and proofreading\u00a0a range of corporate marketing and communications materials across different platforms including social media platforms.\u00a0\nCollaborating with regional teams from concept development to delivery of final product.\u00a0\u00a0\nTranslating\u00a0contents from\u00a0English to Mandarin.\u00a0\nHandling ad-hoc tasks as and when needed.\u00a0\n\n\nWho are we looking for?\u00a0\n\n\nYou must possess a\u00a0Bachelor\u00a0degree,\u00a0i.e.\u00a0in the area of Linguistics/Languages, Mass Communications, Finance, Economy,\u00a0or equivalent.\u00a0\nMin. 3\u00a0years of experience is required.\u00a0\nKnowledge in finance and trading is a nice-to-have.\u00a0\nKnowledge in SEO, HTML, CSS, and WordPress\u00a0is a nice-to-have.\u00a0\nBe a\u00a0clear communicator and writer by translating financial terms into everyday language.\u00a0\nYou must have excellent command of written\u00a0and spoken Mandarin.\u00a0\n\nFresh graduates are welcome to apply.\n\nWe are hiring for 4 headcounts. The position level will be determined by your skills and experience.", "employment_types": ["Full Time", "Permanent"], "selling_points": ["Generate ideas and creative concept", "Draft English & Chinese press & publication copies", "Familiar with various social media platforms"], "locations": ["Not Specified"], "categories": ["Media & Advertising", "Editorial / Journalism", "Marketing / Public Relations", "Public Relations - Copy-writing", "Professional Services", "Translation"], "post_time": "2022-01-13T03:30:48Z", "salary": {"currency": null, "max": null, "min": null, "period": "monthly", "term": null}, "salary_visible": false, "title_keywords": ["editor", "translator", "copywriter"], "responsibilities": ["seo", "ad-hoc tasks", "social media platforms", "teams", "develop", "proofreading", "contents", "editing"], "requirements": {"degrees": ["degree", "bachelor"], "majors": [], "languages": ["english", "mandarin"], "language_level": ["excellent"], "hard_skills": ["seo", "nice", "html", "wordpress", "css"], "soft_skills": ["clear", "communicator", "creative", "determined"], "languages_combined": [{"language": "english", "language_level": []}, {"language": "mandarin", "language_level": ["excellent"]}]}, "experience_required": {"duration": ["3 years"], "field": []}}, {"job_id": "100003009041379", "location_code": "hk", "company": "Doo Technology Limited", "job_title": "Content Writer / Copywriter - Senior / Junior (Content Marketing)", "description": "Key Responsibilities\n\nProvide editorial and event management support in all publicity related assignments;\nSupport the department in English and Chinese editorial needs, including corporate materials and marketing write-ups;\nAct as key liaison between external stakeholders and internal departments to ensure communication objective are met;\nSupervise the team in day-to-day assignments and manage departmental calendar effectively;\nSupport building digital capability across the enterprise and act as custodian of all online assets;\nResearch and collect information on industry and public affairs to keep the company abreast of market developments;\nAssist in ad-hoc projects as assigned.\n\nRequirement\n\nBachelor Degree holder, preferably in Translations, English Studies, Mass Communications or related disciplines;\nMinimum 10 years of solid experience in media, corporate communications, public affairs, or research and analysis, preferably in sizable company or news outlet;\nAt least 2 years\u2019 experience in supervisory role in reputable organization is preferred;\nExcellent command of written and spoken English and Chinese, conversant in Mandarin is preferred;\nStrong PC skills, familiar with creative software is preferable;\nMust have solid media experience and proven track record in handling large scale events;\nGood interpersonal and communications skills; team player and meticulous;\nCandidate with lesser experience will be considered for an Assistant Manager position.\n\nWe offer long-term career prospect and competitive remuneration package to the appointed candidate. Please apply in confidence with your detailed resume stating your current and expected salary to\u00a0Group Human Resources Department\n\nby email to\u00a0recruit(at)shuntakgroup.com\n\nor mail to\u00a0Penthouse 39/F, West Tower, Shun Tak Centre, 200 Connaught Road Central, Hong Kong\n\n(Please quote reference number and applied position)\n\nThe information supplied by the applicants will be used in accordance with the Personal Data (Privacy) Policy of Shun Tak Group (a copy of which will be provided upon request). Only shortlisted candidates will be notified.\n\n\nwww.shuntakgroup.com", "employment_types": ["Full Time", "Permanent"], "selling_points": [], "locations": ["Kowloon Bay"], "categories": ["Media & Advertising", "Editorial / Journalism", "Marketing / Public Relations", "Public Relations - Copy-writing", "Public Relations - General / Support"], "post_time": "2022-01-12T03:51:41Z", "salary": {"currency": null, "max": null, "min": null, "period": "monthly", "term": null}, "salary_visible": false, "title_keywords": ["copywriter", "content writer", "junior"], "responsibilities": ["communication", "management", "ad-hoc projects"], "requirements": {"degrees": ["bachelor degree holder"], "majors": ["related disciplines", "communications"], "languages": ["english", "chinese", "mandarin"], "language_level": ["excellent"], "hard_skills": ["analysis", "pc skills"], "soft_skills": ["meticulous", "team player", "creative", "interpersonal"], "languages_combined": [{"language": "english", "language_level": ["excellent"]}, {"language": "chinese", "language_level": ["excellent"]}, {"language": "mandarin", "language_level": ["excellent"]}]}, "experience_required": {"duration": ["at least 2 years", "minimum 10 years"], "field": ["supervisory", "research", "media"]}}, {"job_id": "100003009049058", "location_code": "hk", "company": "Shun Tak Holdings Ltd", "job_title": "Manager, Corporate Communications (Ref. STHL1714)", "description": "My client is\u00a0a young and fast-growing startup well-funded by strategic investors and the HKSAR government. They are looking for a Social Media Editor/Digital Content Editor\n\nResponsibilities\n\n\nManage and create content for various social media platforms (Facebook, Instagram, YouTube), including copywriting, image and basic video editing;\nClosely monitor social media channels for timely response to comments and inquiries from audiences;\nManage budget spent on social media promotion and pay-per-click (PPC) advertising;\nMonitor, analyze, and provide insight on social media platform activities;\nContribute visual and copywriting ideas for editorial, marketing and advertising projects;\nAssist in maintaining and updating website content and other marketing duties as assigned.\n\nRequirements\n\n\nFun and creative;\nDegree holder in any related disciplines (i.e. Creative Design / Marketing / e-Commerce / Communications);\n2-5 year experience in social media marketing or content creative field;\nKnowledge or experience in properties, home renovation or interior design is a plus;\nFamiliar with digital media solutions (Social media, Facebook advertising, Google Analytics, SEO and SEM) is a plus;\nProficiency in AI and Photoshop;\nStrong interest in social trends.", "employment_types": ["Full Time"], "selling_points": ["Provide editorial and event management support", "Corporate materials and marketing write-ups", "Supervise the team in day-to-day assignments"], "locations": ["Sheung Wan"], "categories": ["Marketing / Public Relations", "Marketing - Market Research", "Marketing - Marketing Communication", "Public Relations - Copy-writing"], "post_time": "2022-01-14T08:00:11Z", "salary": {"currency": null, "max": null, "min": null, "period": "monthly", "term": null}, "salary_visible": false, "title_keywords": ["manager"], "responsibilities": ["social media", "advertising", "ideas", "maintaining", "social media platforms", "monitor", "comments", "budget", "website", "video editing", "visual", "facebook"], "requirements": {"degrees": ["degree holder"], "majors": ["related disciplines"], "languages": [], "language_level": [], "hard_skills": ["creative design", "google analytics", "plus", "seo", "fun", "e-commerce", "ai", "sem", "facebook", "photoshop"], "soft_skills": ["creative"], "languages_combined": []}, "experience_required": {"duration": ["2-5 year"], "field": ["social media", "marketing", "design"]}}, {"job_id": "100003009041948", "location_code": "hk", "company": "Eagle Sky Media Limited", "job_title": "Digital Marketing Copywriter / Content Editor (Online advertising agency )", "description": "Job Responsibilities\n\nDevelop creative content strategy to meet client's marketing needs;\nCreate contents on digital platforms, including Facebook, Instagram, Weibo etc.;\nTo ensure all copy and information is accurate and meets commercial standard;\nResearch online behaviours and trends of the target audience\nMonitor and report SEO performance and metrics, using web analytics tools and dashboards\nKeeping updated with industry trends\nSupport the Business Manager on strategic projects as assigned\n\nJob Requirements:\n\nMinimum 1 years copywriting experience in writing;\nAble to write excellent and stylish Cantonese;\nCreative, willing to learn, self-initiative & motivated, responsible, supportive and able to work under pressure, independently and over time;\nGood team player with excellent interpersonal and communication skills\nStay updated on creative trends *Immediate availability is preferred", "employment_types": ["Full Time"], "selling_points": ["Copywriter", "Content Editor", "content marketing"], "locations": ["Tsuen Wan Area"], "categories": ["Media & Advertising", "Creative / Design", "Marketing / Public Relations", "Public Relations - Copy-writing", "Digital Marketing"], "post_time": "2022-01-12T04:47:02Z", "salary": {"currency": null, "max": null, "min": null, "period": "monthly", "term": null}, "salary_visible": false, "title_keywords": ["copywriter", "content editor", "digital marketing"], "responsibilities": ["analytics tools", "seo", "creative content", "monitor", "develop", "contents", "facebook", "report"], "requirements": {"degrees": [], "majors": [], "languages": ["cantonese"], "language_level": ["excellent"], "hard_skills": [], "soft_skills": ["communication skills", "supportive", "independently", "good team player", "responsible", "willing to learn", "motivated", "self-initiative", "creative", "interpersonal", "work under pressure"], "languages_combined": [{"language": "cantonese", "language_level": ["excellent"]}]}, "experience_required": {"duration": ["minimum 1 years"], "field": ["copywriting", "writing"]}}, {"job_id": "100003009048426", "location_code": "hk", "company": "Impact Partner Consulting Co., Limited", "job_title": "Social Media Editor / Digital Content Editor", "description": "Responsibilities:\nSocial media management including content development & consumer engagement\nCommunicate and extent good relationships with on-line media, KOL, vendors & platform partners\nAnalyze market trends and explore new marketing techniques & business opportunities\nParticipate and support internal teams for different marketing campaign and operation needs\nPrepare marketing proposal for client\nPrepare regular reports for management review\nParticipate & support in all new business initiatives and all ad hoc projects\nGood content writer\nStrong Creative Designer is much preferred\n\nRequirements:\n\nDegree holder in Marketing / Communication / Multi-media Design preferred\nMin. 2 years\u2019 experienced in marketing\nExcellent interpersonal, presentation and communication skills\nProficient in MS Word, Excel, PowerPoint and Chinese Word Processing\nFluency in written and spoken Chinese and English\nExperience in CMS (Wordpress) ,graphic design tools (Adobe Photoshop and Adobe Illustrator)\nDetail-minded, tech-savvy, outgoing, and flexible to work\nHard-working, willing to learn and able to handle multi-task, work under pressure and meet deadlines\nCandidate with more experienced will be considered as Senior Marketing Executive", "employment_types": ["Full Time", "Permanent"], "selling_points": [], "locations": ["Hung Hom"], "categories": ["Marketing / Public Relations", "Public Relations - Copy-writing", "Digital Marketing"], "post_time": "2022-01-14T06:32:05Z", "salary": {"currency": null, "max": null, "min": null, "period": "monthly", "term": null}, "salary_visible": false, "title_keywords": ["content editor", "social media editor"], "responsibilities": ["social media", "management", "business initiatives", "business opportunities", "review", "teams", "regular reports for management", "ad hoc projects"], "requirements": {"degrees": ["degree holder"], "majors": ["marketing", "design"], "languages": ["english", "chinese"], "language_level": ["fluency", "proficient"], "hard_skills": ["excel", "chinese word processing", "adobe photoshop", "powerpoint", "adobe illustrator", "wordpress", "ms word"], "soft_skills": ["detail-minded", "communication skills", "outgoing", "flexible", "multi-task", "willing to learn", "communication", "hard-working", "meet deadlines", "interpersonal", "presentation", "work under pressure"], "languages_combined": [{"language": "english", "language_level": ["fluency"]}, {"language": "chinese", "language_level": ["fluency", "proficient"]}]}, "experience_required": {"duration": [], "field": ["graphic design"]}}, {"job_id": "100003009044056", "location_code": "hk", "company": "Goodbye Dear Company Limited", "job_title": "Creative Content Writer / Copywriter", "description": "Join us to create new values to the online offline commerce communities\n\nPrice.com.hk, being one of the most popular online platforms* in Hong Kong, strives to bring extra values to merchants and consumers by not only connecting them seamlessly with our state-of-the-art technology but co-creating a community that encourages a more user centric shopping experience combined with the application of big data analytics.\n\nWe start with a goal to minimize market information costs incurred upon consumers allowing them to find their favorite products easier and faster and at the same time enable merchants to successfully run their brick and click strategies to reach their targeted consumers at the lowest cost possible. Today, we are serving 2M+ monthly unique visitors. We cannot accomplish that without working together with individuals who are passionate about what they do.\u00a0\n\n*According to Alexa, Price.com.hk is one of the top 25 most frequently visited sites in Hong Kong. https://www.alexa.com/siteinfo/price.com.hk\n\n\nWebsite:\u00a0http://www.price.com.hk/\nFacebook Page:\u00a0http://bit.ly/1VkYTJx\nYoutube channel:\u00a0https://bit.ly/3z7jB7d\n\nYour role with us involves:\nHost for Youtube channel:\nhttps://www.youtube.com/channel/UCUEJok-GiWaGlv5nIPwk-GQ\nAble to face the camera professionally and confidently\nProduce comprehensive and reliable content on product comparisons and reviews in both article and/or script formats\nDiscover the hottest and newest topics and products, write about them in fresh and engaging ways\nObserve and analyze the interests of our readers and cater to their tastes\nCreate advertorial content\nCollaborate with other departments and business partners\n\nAs an employer, our role is to empower you by bringing your true talents and best self to this dynamic digital world and the people we serve. We welcome individuals from all backgrounds, ideally with skills and traits as below:\n\nDiploma or above\nMinimum 1 year experience in copywriting, social media or related fields\nFamiliar with consumer electronics and gadgets\nSelf-motivated and able to work independently\nAttention to details\nProficient in MS Office and Chinese Word Processing\n\n\u00a0\u00a0Be part of us, you will enjoy:\n\nDiscretionary Bonus\n5-day Work Week\nFlexible Working Hour\nBirthday, Marriage, Maternity and Paternity Leave\nBirthday Gift\nMedical Insurance\nMonthly Birthday Party\nTeam Event and Team Building Activities\nHappy and Dynamic Environment\nCasual Dress Code\nWorking Location: Kwun Tong (5 minutes from Kwun Tong MTR station)\n\n\nInterested parties, please click \"Apply now\" to submit your resume with the availability and expected salary to us.\n\nPersonal data collected will be kept strictly confidential and only be used for recruitment related purpose.\n", "employment_types": ["Full Time"], "selling_points": [], "locations": ["Kwun Tong"], "categories": ["Media & Advertising", "Creative / Design", "Marketing / Public Relations", "Marketing - Brand / Product Management", "Public Relations - Copy-writing"], "post_time": "2022-01-13T02:55:48Z", "salary": {"currency": null, "max": null, "min": null, "period": "monthly", "term": null}, "salary_visible": false, "title_keywords": ["copywriter", "content writer", "creative"], "responsibilities": ["collaborate with", "social media", "cost", "market information", "big data", "website", "facebook", "insurance", "costs"], "requirements": {"degrees": ["diploma or above"], "majors": [], "languages": ["chinese"], "language_level": ["proficient"], "hard_skills": ["chinese word processing", "data analytics", "code", "goal", "dynamic", "facebook", "ms office"], "soft_skills": ["flexible", "self-motivated", "work independently", "dynamic environment", "unique", "comprehensive", "dynamic", "attention to details", "reliable", "passionate about"], "languages_combined": [{"language": "chinese", "language_level": ["proficient"]}]}, "experience_required": {"duration": ["minimum 1 year"], "field": ["copywriting", "social media", "related"]}}, {"job_id": "100003009048927", "location_code": "hk", "company": "Eagle Sky Media Limited", "job_title": "Digital Marketing Officer (Advertising Agency , Digital Marketing, Social media)", "description": "Responsibilities:\n\nYou will be responsible for managing and engaging with the organization\u2019s online community (Discord, Telegram, Twitter, Instagram, Facebook, Youtube, etc.) in a way that builds brand awareness and a sense of community\nYou will work cross-functionally with partners while focusing on engagement, enjoyment, and growth\nEngage with DeFi, Crypto and NFT communities daily through various online channels: Discord, Telegram, Twitter, etc\nIncrease brand awareness and community engagement\u00a0\nListen, gather and share the community\u2019s feedback and opinions with the team\nTrack community sentiment and provide actionable reports and recommendations\nRespond to user questions, comments, and concerns in a timely manner\nEnforce strict community rules, identify and remove bots\nHelp build and scale data pipelines for a rapidly growing global organization\nHelp build social/community measurement, attribution, and modeling\nBuild and maintain BI/dashboards and reports and also respond to ad-hoc requests\n\nRequirements:\n\n1-3 years of community management experience in managing online communities on Telegram and Discord\nThis person MUST have actual experience in the blockchain, crypto, and NFT space\nProven record of community engagement and management in the crypto, DeFi space\nStrong experience with Telegram and Discord is a must\nExcellent written and verbal communication skills\nExperience identifying and delivering helpful community content\nA creative, strategic approach to community growth and engagement", "employment_types": ["Full Time", "Permanent"], "selling_points": ["Socail media management", "Advertising Agency", "designer"], "locations": ["Tsuen Wan Area"], "categories": ["Media & Advertising", "Creative / Design", "Design", "Graphics", "Marketing / Public Relations", "Public Relations - Copy-writing"], "post_time": "2022-01-14T07:43:38Z", "salary": {"currency": null, "max": null, "min": null, "period": "monthly", "term": null}, "salary_visible": false, "title_keywords": ["digital marketing officer", "digital marketing"], "responsibilities": ["online channels", "data", "comments", "a timely manner", "measurement", "maintain", "reports", "ad-hoc requests", "facebook"], "requirements": {"degrees": [], "majors": [], "languages": [], "language_level": [], "hard_skills": ["blockchain", "crypto"], "soft_skills": ["communication skills", "creative"], "languages_combined": []}, "experience_required": {"duration": ["1-3 years"], "field": ["management"]}}, {"job_id": "100003009039537", "location_code": "hk", "company": "Price.com.hk Limited", "job_title": "Anchor / Editor", "description": "Responsibilities:\n\nWork for marketing team to initiate creative concepts and maintain brand consistency across all channels\nExecute full spectrum of multimedia design, including but not limited to photo shooting and retouching, video editing and production, as well as graphic design for website, social media (FB, IG, LinkedIn, WeChat etc.), e-mail marketing and printed materials\nLayout design and artwork production of marketing materials to support brand/promotion campaigns\nContent development and post design for social media platform\nPerform ad-hoc tasks as assigned\n\n\u00a0Requirements:\n\nDegree or diploma in Multimedia / Graphic Design / Creative Media or related disciplines\nMinimum of 6-8 years\u2019 relevant working experience in creative agency / digital marketing/ in-house marketing team\nProficient in Adobe Creative Suite, including Premiere Pro, After Effects, Animate, Illustrator, InDesign and Photoshop\nSkilled in various social media platforms (e.g. Facebook, Instagram, LinkedIn, WeChat)\nExperienced in video production, motion graphic and photography\nAn excellent team player with good communication skills and the ability to multitask\nCreative and pro-active, responsible, well-organized, detail-oriented with a strong sense of responsibility and team work\nKnowledge in HTML5, CSS, Action script is a plus\nExperience in copywriting/editing in English & Chinese is a plus\nWe offer an attractive remuneration package and excellent career prospects to the right candidate. Please send full resume including the current, expected salary, the portfolio with video works, photography, design layouts and finished marketing materials\u00a0and the contact information by clicking \"Apply Now\"\n\n\n\n(The personal data provided will be used for recruitment purpose only. \u00a0All data of unsuccessful applications will be destroyed.)", "employment_types": ["Full Time", "Permanent"], "selling_points": ["Fast Growing Industry", "An Expanding E-Commerce Company", "Offer Training & Development"], "locations": ["Kwun Tong"], "categories": ["Media & Advertising", "Others", "Editorial / Journalism", "Marketing / Public Relations", "Public Relations - Copy-writing"], "post_time": "2022-01-11T10:01:21Z", "salary": {"currency": null, "max": null, "min": null, "period": "monthly", "term": null}, "salary_visible": false, "title_keywords": ["editor", "anchor"], "responsibilities": ["multimedia design", "retouching", "social media", "graphic design", "artwork production", "layout design", "ad-hoc tasks", "website", "design", "video editing", "maintain", "promotion campaigns", "marketing materials", "brand consistency"], "requirements": {"degrees": ["diploma", "degree"], "majors": ["related disciplines", "graphic design", "creative media"], "languages": ["english", "chinese"], "language_level": [], "hard_skills": ["plus", "animate", "css", "indesign", "illustrator", "wechat", "after effects", "premiere pro", "multimedia", "facebook", "adobe creative suite", "photoshop"], "soft_skills": ["communication skills", "responsible", "sense of responsibility", "well-organized", "detail-oriented", "team player", "pro-active", "ability to multitask", "creative"], "languages_combined": [{"language": "english", "language_level": []}, {"language": "chinese", "language_level": []}]}, "experience_required": {"duration": ["minimum of 6-8 years"], "field": ["agency", "relevant working experience", "marketing", "digital marketing", "copywriting", "editing", "team"]}}, {"job_id": "100003009051221", "location_code": "hk", "company": "Match Talent Limited", "job_title": "Community Manager (NFT)", "description": "Responsibilities:\n\n\nAccount Servicing and new business pitching\nPropose and implement PR campaigns, including brand promotion, product launches, media luncheons, social media campaigns, KOL campaigns, product promotion, advertising activities, sponsorship line ups, etc\u2026\nAssist the Team Head on preparing all PR materials, including pitching proposals, press material write ups, KOL management, social media copy writing, content editing, proofreading etc\u2026\nCoach and supervise junior staff in execution of all PR campaigns and retainer projects\nMedia Pitching to enhance media exposure for various client projects\nBuild and maintain a good relationship with media (both online and offline), KOLs and Artist Management\nCo-ordinate with external and internal parties to ensure the smooth execution of PR and marketing campaigns\nSupport on reports, admin works, and maintaining filing systems, and any other ad-hoc tasks assigned by senior management\n\n\u00a0Requirements:\n\n\nDegree holder preferably in Communications, Journalism or related discipline\n5 years\u2019 agency experience in PR agency is a must; candidate with less experience would also considered as Manager\nSolid hands on experience in Media Pitching, KOL pitching, social media content development and/or digital media buying\nGood communication, presentation and interpersonal skills\nProficiency in written and spoken English and Chinese\nExcellent project management skills and enthusiastic multi-tasker with a can do attitude and passion for PR industry\u00a0\n\nWe offer excellent career opportunity, benefits and generous compensations.\u00a0 Please apply in strict confidence with expected salary by email.", "employment_types": ["Part Time", "Contract", "Freelance"], "selling_points": ["Increase brand awareness and community engagement", "Creative, strategic approach to community growth", "Flexibility working hours"], "locations": ["Central"], "categories": ["Marketing / Public Relations", "Marketing - Marketing Communication", "Public Relations - Copy-writing", "Digital Marketing"], "post_time": "2022-01-15T05:15:11Z", "salary": {"currency": null, "max": null, "min": null, "period": "monthly", "term": null}, "salary_visible": false, "title_keywords": ["manager"], "responsibilities": ["social media", "management", "advertising", "social media campaigns", "maintaining", "co-ordinate with", "ad-hoc tasks", "systems", "good relationship", "proofreading", "maintain", "reports", "marketing campaigns", "editing", "internal parties", "senior management"], "requirements": {"degrees": ["degree holder"], "majors": ["journalism", "communications"], "languages": ["english", "chinese"], "language_level": ["proficiency"], "hard_skills": ["project management"], "soft_skills": ["passion for", "project management skills", "communication", "hands on", "interpersonal skills", "enthusiastic", "presentation"], "languages_combined": [{"language": "english", "language_level": ["proficiency"]}, {"language": "chinese", "language_level": ["proficiency"]}]}, "experience_required": {"duration": ["5 years"], "field": ["social media", "pr", "content development", "agency", "digital media", "media"]}}, {"job_id": "100003009045705", "location_code": "hk", "company": "Humansa", "job_title": "Multimedia Designer", "description": "Responsibilities:\n\nProofreading and manage the quality process of mobile apps project.\nConduct compliance awareness for the content review process and normalization.\nManage the accuracy and timely delivery of production and projects.\n\nRequirements:\n\nUniversity graduate in any discipline.\n1 year or above relevant experience.\nNative Chinese & English Speaker\nHong Kong PR; No remote working is allowed. It is a full-time job in Hong Kong", "employment_types": ["Full Time", "Permanent"], "selling_points": ["Solid 6-8 years of experience in multimedia", "Creative with good art sense", "Experience in copywriting/editing is a plus"], "locations": ["Lai Chi Kok"], "categories": ["Design", "Graphics", "Multi-media", "Marketing / Public Relations", "Public Relations - Copy-writing"], "post_time": "2022-01-13T08:24:22Z", "salary": {"currency": null, "max": null, "min": null, "period": "monthly", "term": null}, "salary_visible": false, "title_keywords": ["multimedia designer"], "responsibilities": ["compliance", "review", "proofreading", "quality"], "requirements": {"degrees": ["university graduate"], "majors": [], "languages": ["english", "chinese"], "language_level": ["native"], "hard_skills": ["no"], "soft_skills": [], "languages_combined": [{"language": "english", "language_level": ["native"]}, {"language": "chinese", "language_level": ["native"]}]}, "experience_required": {"duration": ["1 year"], "field": ["relevant experience"]}}, {"job_id": "100003009048990", "location_code": "hk", "company": "Zenith Integrated Communications Limited", "job_title": "Senior Manager/Manager", "description": "Our company is looking for a Digital Marketing Candidate to join our team,\u00a0\n\nWho you are\n\nHigh passionate and enthusiastic in Music\nAlready or ready to be a talented marketer\nLooking for career exposure in Music Industry\nLove the digital world", "employment_types": ["Full Time"], "selling_points": [], "locations": ["Kwun Tong"], "categories": ["Media & Advertising", "Account Servicing", "Marketing / Public Relations", "Marketing - Brand / Product Management", "Public Relations - Copy-writing"], "post_time": "2022-01-14T07:50:50Z", "salary": {"currency": null, "max": null, "min": null, "period": "monthly", "term": null}, "salary_visible": false, "title_keywords": ["senior manager", "manager"], "responsibilities": [], "requirements": {"degrees": [], "majors": [], "languages": [], "language_level": [], "hard_skills": [], "soft_skills": ["passionate", "enthusiastic"], "languages_combined": []}, "experience_required": {"duration": [], "field": []}}, {"job_id": "100003009046373", "location_code": "hk", "company": "Tom Lee Music Co Ltd", "job_title": "Digital Marketing", "description": "We are looking for a Chinese Translator to assist in interpret written and audio pieces, making sure to maintain their original meaning, format and tone.\n\nResponsibilities:\n\nRead given material and research industry-specific terminology\nConvert text and audio recordings from one language to one or more others\nEnsure translated content conveys original meaning and tone\nPrepare subtitles for videos and online presentations\nCross-reference specialised\u00a0dictionaries and translation tools to check quality of translation\nProofread translated texts for grammar, spelling and punctuation accuracy\nFollow up with internal team members and clients to ensure translation meets their needs\nAssist with a variety of projects and processes, prepare presentation materials, research and reports etc.\nOther responsibilities and duties as assigned by the superior.\u00a0\nRequirements:\n\n\nDegree holder or above with major in\u00a0related discipline from reputable university and at least 1 year experience.\nFluency in both spoken and written Chinese and English is a must.\nMeticulous planning and organizational skills.\nHave great time management skills and be able to act without guidance.\nProduce clear and concise verbal and written communications.\nSelf-motivated, creative, independent and able to work under pressure and meet tight deadlines.\nHave a positive and passionate approach with a can-do attitude.\nInterested candidates please submit your CV and expected salary by clicking Apply Now!", "employment_types": ["Full Time"], "selling_points": [], "locations": ["Tsim Sha Tsui"], "categories": ["Marketing / Public Relations", "Marketing - Marketing Communication", "Public Relations - Copy-writing", "Digital Marketing"], "post_time": "2022-01-13T10:46:54Z", "salary": {"currency": null, "max": null, "min": null, "period": "monthly", "term": null}, "salary_visible": false, "title_keywords": ["digital marketing"], "responsibilities": ["audio", "quality", "presentations", "reports"], "requirements": {"degrees": ["degree holder"], "majors": [], "languages": ["english", "chinese"], "language_level": ["fluency"], "hard_skills": [], "soft_skills": ["passionate", "meticulous", "self-motivated", "organizational skills", "independent", "meet tight deadlines", "can-do attitude", "time management skills", "clear", "creative", "positive", "work under pressure"], "languages_combined": [{"language": "english", "language_level": ["fluency"]}, {"language": "chinese", "language_level": ["fluency"]}]}, "experience_required": {"duration": ["at least 1 year"], "field": ["related"]}}, {"job_id": "100003009044381", "location_code": "hk", "company": "Ignition HK Limited", "job_title": "Chinese Translator", "description": "Key Responsibilities:\nInitiate and implement publicity campaigns to promote the Company's mission and achievements through multiple communication channels\nDevelop, edit and translate a full range of Chinese and English PR materials, such as speeches, press releases, presentations, advertorials, annual reports, success stories of Cyberport companies etc.\nBe the gate keeper of corporate PR messages\u00a0\nHandle media enquiries; maintain good relationship with the media to maximise positive coverage for the Company\nWork with different teams to formulate story angles, develop key messages and talking points for corporate events, industry activities and visits to ensure effective delivery of corporate positioning and messages\u00a0\nSupport senior executives for media activities and public speaking opportunities\nCoordinate with internal and external parties for the production of corporate publications\nConduct research with regards to updates of industry trends and government policies\nEngage the digital tech companies in Cyberport; support the promotion of their innovation and leverage on their work to raise the brand awareness of Cyberport\nPerform other duties as assigned\n\u00a0Requirements:\nBachelor's degree in Languages, Translation, Communications, Journalism or related discipline\nGood qualification in language subjects preferred\nMinimum 8 years of relevant experience across different communications functions, such as media relations, stakeholder\u2019s engagement, copywriting, production of annual report and corporate literature etc.\nStrong connection with local and regional media with proven track record in formulating story angles and conducting media pitching\nSolid experience in planning and implementing integrated communication campaigns across different channels, both the traditional and new media platforms\nGood understanding of the Innovation & Technology industry as well as related government policies an advantage\nExceptional command of written and spoken Chinese and English \u00a0\nSelf-motivated and detail-minded with good project management ability\nDetail-minded and independent with strong analytical mind\nAble to demonstrate problem-solving skills\nTeam player and self-motivated with can-do spirit\nCandidate with less experience will be considered for assistant manager role.\u00a0\n\u00a0\nThe position is on a 2-year fixed-term renewable contract.\n\n\nWe offer competitive package to the right candidate. Interested party please click\u00a0Apply Now\u00a0to apply on or before 11 Feb 2022 in confidence with full resume in Word document, stating present and expected salary, and available date\u00a0and quote the reference.\u00a0\n\nApplicants who do not hear from us by 25 Feb 2022 may assume that their applications are unsuccessful.\n\nFurther information about the Cyberport is available at\u00a0http://www.cyberport.hk\n\n\n", "employment_types": ["Full Time"], "selling_points": ["Provide Chinese translation support", "5 days work week", "Degree holder or above"], "locations": ["Sheung Wan"], "categories": ["Media & Advertising", "Editorial / Journalism", "Marketing / Public Relations", "Public Relations - Copy-writing", "Professional Services", "Translation"], "post_time": "2022-01-13T03:55:13Z", "salary": {"currency": null, "max": null, "min": null, "period": "monthly", "term": null}, "salary_visible": false, "title_keywords": ["translator"], "responsibilities": ["perform other duties", "policies", "internal and external parties", "teams", "coordinate with", "presentations", "maintain good relationship", "communication", "develop", "reports", "conduct research"], "requirements": {"degrees": ["degree", "bachelor"], "majors": ["journalism", "communications"], "languages": ["english", "chinese"], "language_level": [], "hard_skills": ["problem-solving skills", "translation", "project management"], "soft_skills": ["detail-minded", "self-motivated", "independent", "communication", "project management", "analytical mind", "can-do", "problem-solving skills", "team player"], "languages_combined": [{"language": "english", "language_level": []}, {"language": "chinese", "language_level": []}]}, "experience_required": {"duration": ["minimum 8 years"], "field": ["copywriting", "relevant experience", "media", "planning"]}}, {"job_id": "100003009049882", "location_code": "hk", "company": "Hong Kong Cyberport Management Co Ltd", "job_title": "Manager - Corporate Communications (Ref# M-CC220114J)", "description": "About DrGo\n\nThe DrGo app connects you with Hong Kong registered doctors, so you can benefit from a telemedicine video consultation. Our on-demand mobile platform enables you to book an appointment and consult a doctor of your choice via a video call. Any medicine and any medical certificate and/or referral letter which the doctor may prescribe or issue to you after the consultation will be delivered directly to your door.\n\nYour role\n\nAs Digital Marketing Executive of our DrGo team, your major job responsibilities include:\n\nDevelop content strategy across all platforms including app, web, emails and social media that supports the business objective\nMonitor, measure, and analyze the performance metrics of websites, ecommerce, online marketing activities across paid, owned and earned media channels, and provide insights and interpretations\nPerform copy writing, editing and proofreading for digital and print materials\nLiaise and work with internal parties to execute marketing campaigns \u00a0\nCollaborate with UX and Design teams to deliver new initiatives to continuously improve user experience\n\nTo succeed in this role\n\nUniversity graduate in marketing, business management \u00a0or related disciplines;\nProven 1-2 years\u2019 working experience in marketing, business development or operational management; preferable in telecom, FMCG, eCommerce and retail industries;\nGood analytical and problem solving skills, able to work under tight timeline;\nSelf-motivated and able to accomplish multiple tasks with minimal supervision;\nGood\u00a0interpersonal and communication skills and\u00a0able to work with people at all levels;\nGood command in both spoken and written English.\nStrong sense of\u00a0ownership\u00a0for the channels and campaigns that you\u2019re in charge of with a natural sense of responsibility towards campaign performance\nFlexible\u00a0- \u00a0able to multitask across multiple channels. This role would involve testing as well as filling the gaps wherever needed to explore new paid media channels\nKnowledge and experience in using Google Analytics, data studio or magento is preferred", "employment_types": ["Full Time", "Permanent", "Contract"], "selling_points": ["Implement publicity campaigns and promote", "Engage the community companies", "To raise the brand awareness"], "locations": ["Pok Fu Lam"], "categories": ["Marketing / Public Relations", "Marketing - Marketing Communication", "Public Relations - Copy-writing", "Public Relations - Event Management"], "post_time": "2022-01-14T09:23:20Z", "salary": {"currency": null, "max": null, "min": null, "period": "monthly", "term": null}, "salary_visible": false, "title_keywords": ["manager"], "responsibilities": ["liaise", "provide insights", "collaborate with", "data", "design", "communication", "media channels", "editing", "monitor", "teams", "user experience", "develop", "testing", "marketing campaigns", "social media", "management", "proofreading", "digital marketing", "performance metrics", "internal parties"], "requirements": {"degrees": ["certificate", "university graduate"], "majors": ["business", "related disciplines", "marketing"], "languages": ["english"], "language_level": ["good command"], "hard_skills": ["business management", "google analytics", "web", "mobile", "problem solving skills"], "soft_skills": ["flexible", "communication skills", "self-motivated", "multiple tasks", "sense of responsibility", "multitask", "analytical and problem solving skills", "interpersonal"], "languages_combined": [{"language": "english", "language_level": ["good command"]}]}, "experience_required": {"duration": ["1-2 years"], "field": ["management", "marketing", "design", "business development"]}}, {"job_id": "100003009044646", "location_code": "hk", "company": "HKT Consumer Group", "job_title": "Senior Marketing Executive, DrGo Marketing, DrGo Marketing (Digital Marketing)", "description": "Perfect Medical is a leading Medical Beauty group with over 50 treatment centers around the world. We strive for perfection with passion. Our team are filled with young, ambitious and driven professionals. We are now seeking for a Copywriter to join our Digital Marketing Team.\n\nResponsibilities:\n\n\nCraft creative copy writing across digital platforms (e.g. Social Media, Blog, Forum etc.);\nTo develop and edit content / copy for online customer communications;\nPerform quality control on all advertisements and content distribution\nWork with internal teams to ensure content for internal and external communication are published in the right channels\nAssist online marketing execution team to plan and implement of digital marketing communication/programs to build brand awareness;\nTrack monthly performance data\u00a0\nRequirements:\n\nPassionate in digital is a MUST\nDiploma holder majoring in Journalism, Marketing, communications or PR related discipline or above\nExperienced in Beauty industry would be advantaged\nMinimum 2 years relevant work experience in publishing, editing or copy writing;\nExperience in creative writing, blogging or publications is highly preferable;\nExcellent in Chinese and English written skill;\nTo be responsible, organized, proactive and self-motivated\n\nWe offer attractive remuneration package to the right candidate. Interested parties please send your full resume with present and expected salary by clicking \u201cApply Now\u201d .\n\nPersonal information collected will be used for recruitment purpose only\u00a0", "employment_types": ["Full Time"], "selling_points": [], "locations": ["Quarry Bay"], "categories": ["Marketing / Public Relations", "Marketing - Brand / Product Management", "Marketing - Marketing Communication", "Public Relations - Copy-writing"], "post_time": "2022-01-13T04:58:35Z", "salary": {"currency": null, "max": null, "min": null, "period": "monthly", "term": null}, "salary_visible": false, "title_keywords": ["digital marketing", "senior marketing executive"], "responsibilities": ["social media", "advertisements", "data", "teams", "develop", "communication", "digital marketing", "quality control", "plan"], "requirements": {"degrees": ["diploma holder"], "majors": ["journalism", "marketing", "communications"], "languages": ["english", "chinese"], "language_level": ["excellent"], "hard_skills": [], "soft_skills": ["passionate", "organized", "self-motivated", "proactive", "responsible", "creative"], "languages_combined": [{"language": "english", "language_level": ["excellent"]}, {"language": "chinese", "language_level": ["excellent"]}]}, "experience_required": {"duration": ["minimum 2 years"], "field": ["editing", "publishing", "writing"]}}, {"job_id": "100003009042764", "location_code": "hk", "company": "Perfect Shape (Holdings) Limited", "job_title": "Copywriter (Digital Marketing) Listed Company", "description": "YesStyle is looking for passionate talents, who love and appreciate the fascination of Asian fashion and beauty. Our team is active, energetic, and culturally diverse.\n\nTo embrace the idea of work-life balance, we also endeavor to create a fun and enjoyable environment for our team members.\n\nWhat You'll Do:\u00a0\n\n\nWriting English content for YesStyle to engage and inform customers, and reaffirm the company\u2019s position as a leading online beauty and fashion retailer.\nProviding blog content, product descriptions, social media content and marketing copy for YesStyle websites and related businesses through writing, and editing work from content providers and staff.\nAid quality control of YesStyle English content.\nAssist in content development for YesStyle websites and related businesses.\n\nWhat You Have:\u00a0\n\nEnglish editing skills (1-2 years of editorial experience preferred)\nExcellent English writing and communication skills\nPresentation skills, including public speaking or video presentations, are a plus\nStrong visual sense (e.g., photos or images)\nKnowledge of and interest in fashion and beauty\nFamiliar with Windows, Internet and online shopping. Knowledge of a second language (Chinese, Japanese, Korean, German, Spanish) is a plus\nAble to work quickly and independently\nMature, cooperative and dynamic\nInternational sensibility\nDetail oriented\nForward thinking\nCandidates with less experience will be considered as Assistant Content Editor\n\nWhat You'll Enjoy:\n\n5 Days Work\nDynamic, International Cultural & Friendly Working Environment\nPerformance Bonus\u00a0\u00a0\nMedical / Dental Insurance\nStaff Purchase Discount Program\nTraining Programs\nTeam Member's Wellness Program, such as Stretching Class, Thai Boxing\nAnnual Leave, Full Pay Sick Leave, Birthday Leave, Examination Leave\nManagerial Stock Options\n\nThe more you put into your career at YesStyle, the more opportunities you\u2019ll receive. Throughout your time in the Company, you\u2019ll be assessed on the core competencies of your position and prepared for the next level of your development.\u00a0 Your role at YesStyle should progress naturally as you move from assistant grade to management, taking on challenges and responsibilities suited to your unique skills and talents.\n\nPlease send your full resume stating our reference code, your current and expected salary to Human Resource Department for application.\u00a0\n\nTo know more about us, please visit www.yesstyle.com.\n\nAll information provided by applicants will be treated in strict confidence and used only for the recruitment purpose in accordance with employer's data policies.", "employment_types": ["Full Time", "Permanent"], "selling_points": ["Diploma or above in Journalism or Marketing", "2 years relevant working experience", "Experience in creative writing/ blogging"], "locations": ["Mong Kok"], "categories": ["Marketing / Public Relations", "Marketing - Brand / Product Management", "Public Relations - Copy-writing", "Digital Marketing"], "post_time": "2022-01-12T08:44:45Z", "salary": {"currency": null, "max": null, "min": null, "period": "monthly", "term": null}, "salary_visible": false, "title_keywords": ["copywriter", "digital marketing"], "responsibilities": ["management", "product descriptions", "data", "policies", "presentations", "communication", "purchase", "social media content", "recruitment", "quality control", "visual", "editing", "insurance"], "requirements": {"degrees": [], "majors": [], "languages": ["german", "english", "spanish", "japanese", "thai", "korean", "chinese"], "language_level": ["excellent"], "hard_skills": ["inform", "plus", "fun", "presentations", "dynamic", "code"], "soft_skills": ["passionate", "communication skills", "active", "independently", "confidence", "cooperative", "detail oriented", "mature", "team member", "unique", "diverse", "presentation skills", "dynamic", "friendly", "energetic"], "languages_combined": [{"language": "german", "language_level": []}, {"language": "english", "language_level": ["excellent"]}, {"language": "spanish", "language_level": []}, {"language": "japanese", "language_level": []}, {"language": "thai", "language_level": []}, {"language": "korean", "language_level": []}, {"language": "chinese", "language_level": []}]}, "experience_required": {"duration": ["1-2 years"], "field": ["editorial", "editing", "editor"]}}, {"job_id": "100003009047800", "location_code": "hk", "company": "YesStyle.com Limited", "job_title": "Content Editor/ Assistant Content Editor", "description": "You can enjoy:\n\nYoung and energetic, happy\u00a0working environment\nCompetitive compensation and benefits!\nContemporary workplace, free drinks and chill out areas!\nProfessional training and career advancement opportunities!\nConvenient office location, around 10-15min. walk from Tsuen Wan MTR!\nFaster IT equipped workflow and passionate culture!\nCasual wear every Friday, TGIF!\nMarriage, Maternity and Birthday Leave!\nYear around staff events - hiking, BBQ, annual dinner, incentive etc.\nExclusive shopping discount! Red Wine / sparkling Sales for our people only!\n\nResponsibilities:\n\n-\u00a0Write Website Content, SEO, Blogs, and Ad Copy\n\n- Digital online marketing planning and execution for Internal Projects\n\n-\u00a0Develop content strategy across different channels\n\n- Manage major B2C e-commerce online platforms, e.g. list and update product listings, update price\n\n- Update the information of sales platform, social media platforms\n\nRequirements:\n\n- Academic qualification: diploma or above preferably in Marketing, Business Study / Business Administrative, English Language Studies or other related disciplines\n\n- Excellent reading and writing in Chinese & English\u00a0(DSE at least B or above),\u00a0Must be comfortable writing long-form content\n\n- Fresh Graduate with good academic background OR 2-3 year experience in eCommerce/IT/Marketing would be preferable\n\n- Proficient with MS Excel, Word & PowerPoint\n\n- Immediately available is preferred", "employment_types": ["Full Time"], "selling_points": ["Excellent English writing and communication skills", "Strong visual sense", "Knowledge of and interest in beauty and fashion"], "locations": ["Kwai Hing"], "categories": ["Media & Advertising", "Editorial / Journalism", "Marketing / Public Relations", "Public Relations - Copy-writing", "Professional Services", "Translation"], "post_time": "2022-01-14T03:55:57Z", "salary": {"currency": null, "max": null, "min": null, "period": "monthly", "term": null}, "salary_visible": false, "title_keywords": ["content editor", "assistant"], "responsibilities": [], "requirements": {"degrees": [], "majors": [], "languages": [], "language_level": [], "hard_skills": [], "soft_skills": [], "languages_combined": []}, "experience_required": {"duration": [], "field": []}}, {"job_id": "100003009039825", "location_code": "hk", "company": "Brand Story Asia Limited", "job_title": "Marketing Project Executive (Digital Online Media, Content Copywriter)", "description": "Job Description:\n\nMedia relations - Handle media interview pitching, press materials writing, line-to-take preparation, media research, news angle development, news monitoring, media contact list sourcing\nCopywriting - writing for publications, PR, video\u00a0 & promotional materials\nEvent management - Handle event management duties including event materials writing, co-ordination for event publications, photos\u00a0 & video\u00a0\nClient servicing - Co-ordinate between clients and media for media relations projects\n\nRequirements:\n\n- Diploma or above in / Journalism / Translation /\u00a0\u00a0Language / Marketing / PR / Communications /Social Work preferred;\n\n- 0.5-1 year working experience in PR /\u00a0 media relations / copywriting field\n\n- love writing and love talking\n\n- Good bilingual writing skills, esp Chinese\n\n- detailed-minded\n\n- cheerful, talkative and persuasive with good telephone skills\n\n- Past working experience as a reporter/editor in media would be an advantage\n\n- Immediate availability is preferred\n\n- Candidate with less relevant experience will be considered for PR and Event Assistant\n\n- Proficient in PC skill, such as MS Office. Chinese typing experience is a MUST.\n\n- Able to work flexible / long working hours.\n\nHOW TO APPLY:\n\nA competitive remuneration package with generous benefits will be offered to the right candidates. Please apply with a covering letter,\u00a0\u00a0resume, Chinese writing sample (MUST HAVE), expected salary and availability to\u00a0us.\u00a0", "employment_types": ["Full Time", "Permanent"], "selling_points": ["Young and Energetic Working Environment", "Passionate and Visionary in Digital Marketing", "Attractive Package | Career Development"], "locations": ["Tsuen Wan Area"], "categories": ["Marketing / Public Relations", "Public Relations - Copy-writing", "E-commerce", "Marketing - Brand / Product Management", "Management", "Management Trainee"], "post_time": "2022-01-11T11:41:24Z", "salary": {"currency": null, "max": null, "min": null, "period": "monthly", "term": null}, "salary_visible": false, "title_keywords": ["copywriter", "project executive"], "responsibilities": ["management", "monitoring", "promotional materials", "contact"], "requirements": {"degrees": ["diploma or above"], "majors": ["journalism", "marketing", "communications", "social work"], "languages": ["chinese"], "language_level": ["good"], "hard_skills": ["typing", "writing skills", "pc skill", "translation", "ms office"], "soft_skills": ["flexible", "cheerful", "persuasive", "writing skills", "detailed"], "languages_combined": [{"language": "chinese", "language_level": ["good"]}]}, "experience_required": {"duration": ["5-1 year"], "field": ["pr", "editor", "reporter", "relevant experience", "copywriting", "media"]}}, {"job_id": "100003009036897", "location_code": "hk", "company": "Red Asia Communications Limited", "job_title": "PR and Event Assistant", "description": "One of our clients, a insurance company is currently seeking a suitable candidate to join their elite team.\n\n\n\nCommunications Manager, IT & Digital team (1 year contract)\n\nJob Highlights\n\n3-8 years\u2019 experience in creating written content in different media\nExcellent writing and storytelling skills in English and Chinese\n\nJob Description\n\nThis role develops all internal and external communication from the IT & Digital team,\u00a0including CTO, to ensure the message is consistent and engaging to end users. The role\u00a0facilitates a culture of agile, as well as shares impact and benefits of\u00a0advanced technologies in leading insurance company. The job holder is also responsible to face off external Partners (e.g.\u00a0FinTech companies, organizations) on communication and event management.)\u00a0\u00a0\n\nResponsibilities:\n\nGather updates and stories to prepare regular internal newsletters in IT organization and regular update from CTO\nCollect feedback and data analytics (e.g. internal surveys), and proactively revise communications and content management for different channels and formats\nHost internal events for IT & Digital Teams\nCoordinate with external parties on communication and event managements\nManage content of CTO official Social Media accounts\nDrive TDA\u00a0\n\nRequirements:\n\nBachelor\u2019s degree or above in Information Management, Communication, Public Relations, Business, Journalism or related discipline\n3-8 years\u2019 relevant experience in creating written and video content in different media\nPreferably with technologies, insurance, branding or marketing exposures\nExcellent writing and storytelling skills, preferably with experience in creating script, video brief and storyboard\nProficiency in Chinese word processing, Microsoft Word, Excel, PowerPoint\nGood communication skills in both spoken and written English and Cantonese. Putonghua is desirable\nTeam player with good interpersonal and problem-solving skills\n\nInterested parties, please forward your resume in WORD FORMAT to us by clicking here Computer Recruitment Consultants Ltd or fax to 2528-9091.\u00a0\u00a0 The information provided by candidates will be treated in strict CONFIDENTIAL and will only be used for recruitment purpose\u00a0", "employment_types": ["Full Time"], "selling_points": [], "locations": ["Kwai Fong"], "categories": ["Media & Advertising", "Editorial / Journalism", "Marketing / Public Relations", "Public Relations - Copy-writing", "Public Relations - Event Management"], "post_time": "2022-01-10T19:36:11Z", "salary": {"currency": null, "max": null, "min": null, "period": "monthly", "term": null}, "salary_visible": false, "title_keywords": ["event assistant"], "responsibilities": ["communication"], "requirements": {"degrees": [], "majors": [], "languages": [], "language_level": [], "hard_skills": [], "soft_skills": [], "languages_combined": []}, "experience_required": {"duration": [], "field": []}}, {"job_id": "100003009050245", "location_code": "hk", "company": "Computer Recruitment Consultants Ltd", "job_title": "Communications Manager, IT & Digital team", "description": "Job Highlights\n\nDegree holder with 2 years\u2019 experience\nAdvertising / Digital Media Writing\n5 days work with Medical insurance cover\n\nJob Description\n\nGenerate content in Social Media for our Clients (English and Chinese);\nPlan and execute marketing content, social media creatives and any marketing materials;\nWriting, reviewing, editing and updating content for website, Mainly social media platforms like FB and IG: content marketing\u00a0 Development.\nCreate and produce content for promotional campaigns.\nConduct research to learn about current trends and implement them in the content created;\nWork closely with teammates to establish campaign objectives, identify and solve problems;\nPerform ad-hoc tasks as required\nJob Requirements\n\nDegree / higher Diploma in Marketing, Journalism, Multimedia or related discipline;\nAt least 2 years\u2019 experience;\nGood command of both written and spoken English and Chinese is a MUST;\nDigital Marketing Agency Background is a huge Plus;\nFamiliar with different marketing tools;\nGoal oriented personality and be able to work independently as well as part of a team\nInterested candidates, please click the apply now button to submit your", "employment_types": ["Full Time"], "selling_points": ["Degree in Information Management, Communication", "3-8 years exp. in creating written & video content", "Proficiency in English and Chinese word processing"], "locations": ["Not Specified"], "categories": ["Marketing / Public Relations", "Marketing - Marketing Communication", "Public Relations - Copy-writing"], "post_time": "2022-01-14T10:00:29Z", "salary": {"currency": null, "max": null, "min": null, "period": "monthly", "term": null}, "salary_visible": false, "title_keywords": ["manager"], "responsibilities": ["social media", "ad-hoc tasks", "social media platforms", "website", "plan", "marketing materials", "editing", "conduct research"], "requirements": {"degrees": ["diploma", "degree"], "majors": ["journalism", "marketing"], "languages": ["english", "chinese"], "language_level": ["good command"], "hard_skills": ["goal", "plus", "multimedia"], "soft_skills": ["work independently", "goal oriented"], "languages_combined": [{"language": "english", "language_level": ["good command"]}, {"language": "chinese", "language_level": ["good command"]}]}, "experience_required": {"duration": ["at least 2 years"], "field": []}}, {"job_id": "100003009048936", "location_code": "hk", "company": "Heep Hong Society", "job_title": "Service Coordination Officer", "description": "Responsibilities:\n\nTo assist Chief Executive Officer/Deputy Chief Executive Officer on enhancing, editing, and proof reading the write-up of the proposals, reports and minutes prepared by different Departments\nTo liaise with different departments to collect necessary information related to the proposal, reports and minutes and ensure high level of accuracy and fluency on paper writing\nTo assist in the planning, implementation, co-ordination and evaluation of special projects and research\nTo prepare statistical and project reports, correspondence with the centres and external parties\nTo assist in preparing proposals for the further development of services\nTo provide administrative support to centres / project team(s) in relation to service operations and implementation of projects\nTo be responsible for liaising with centre heads, government departments and relevant organizations on issues related to service operation\n\nRequirements:\n\nDegree holder with major in Translations, English, Communications or related discipline\nAt least 2 years\u2019 relevant experience\nExcellent in both written and spoken English and Chinese\nIndependent, proactive, and good team player\nDetail-oriented and organized\nExcellent communication and interpersonal skills\nProficient in computer applications, e.g. Microsoft Word, Excel & PowerPoint and Chinese word processing\nFresh graduate will be considered\nCandidates with less experience will be considered as Assistant Service Coordination Officer\n\nPlease click\u00a0\u201cApply Now\u201d\u00a0to apply for this position or\u00a0send full resume with expected salary and earliest available date to\u00a0WhatsApp: 6875 0346.\n\n(Personal data collected will be used for recruitment purpose only)", "employment_types": ["Full Time"], "selling_points": ["Edit & proof read proposals, reports, minutes", "Plan, implement, coordinate evaluation of research", "Translation, Eng., Comm. Degree, min. 2 yrs' exp"], "locations": ["Ngau Tau Kok"], "categories": ["Media & Advertising", "Editorial / Journalism", "Marketing / Public Relations", "Public Relations - Copy-writing", "Professional Services", "Translation"], "post_time": "2022-01-14T11:33:54Z", "salary": {"currency": null, "max": null, "min": null, "period": "monthly", "term": null}, "salary_visible": false, "title_keywords": ["service coordination officer"], "responsibilities": ["operations", "external parties", "implementation", "liaising with", "project reports", "implementation of projects", "reports", "evaluation", "liaise with", "editing", "provide administrative support", "planning"], "requirements": {"degrees": ["fresh graduate", "degree holder"], "majors": ["communications"], "languages": ["english", "chinese"], "language_level": ["excellent"], "hard_skills": ["excel", "microsoft word", "chinese word processing", "powerpoint", "whatsapp"], "soft_skills": ["organized", "good team player", "independent", "detail-oriented", "communication and interpersonal skills", "coordination", "proactive"], "languages_combined": [{"language": "english", "language_level": ["excellent"]}, {"language": "chinese", "language_level": ["excellent"]}]}, "experience_required": {"duration": ["at least 2 years"], "field": ["relevant experience"]}}, {"job_id": "100003009043688", "location_code": "hk", "company": "Healthy Matters", "job_title": "Social Media Specialist (English/Chinese)", "description": "Do you have an interest in health, digital and want to make a big impact?\u00a0\u00a0\n\nHealthy Matters is looking for a self-motivated and creative Social Media Specialist!\n\n\nOur mission\n\nHealth & wellbeing have never been so important.\n\nWe are the fastest growing health & wellness website in HK.\u00a0Millions of people already trust us, and we're just getting started!\n\nThis is a\u00a0unique opportunity\u00a0to join and collaborate with our team (SEO, content, tech..) and build something positive and amazing for Hong Kong.\n\n\n\nYour key responsibilities\u00a0\n\nWe\u2019re looking for a hands-on,\u00a0passionate marketer to take on a hybrid role: to grow our social media presence, and for a third of your time write lifestyle health content.\n\n- Grow our social media presence. You\u2019ll be responsible for planning and executing. Your KPIs will be social media followers, engagement and traffic to the website.\u00a0\n\n- Create your own social media creatives - beautiful graphics and videos. You will have to create your own visuals to share and grow on social media platforms.\n\n- Write timely, relevant lifestyle articles to reach hundreds of thousands of online users. You will be part of the content team as the one responsible for lifestyle content.\n\n- Have a finger on the pulse on what\u2019s happening around health in HK, be creative and able to quickly execute based on events or news.\n\n\nSkills and experiences\u00a0\n\n-\u00a0Bachelor degree in Journalism / Creative Media / Marketing or equivalent.\n-\u00a0Ideally 1-2 years of work experience (open to fresh grads with the right attitude).\n-\u00a0Excellent written & spoken English & Traditional Chinese.\n- Proven social media experience: you've built thousands of followers on Instagram / Facebook / YouTube / LinkedIn.\n- Experience in Illustrator, Photoshop, or other graphic design tools.\n- Passionate about digital marketing, interest in health is a big plus.\n- Positive and self-motivated. You must be very hands-on.\n- Proven track record of commitment and reliability.\n\n\nWhat we offer\u00a0\n\n- Purpose-driven, fun, collaborative work culture.\n- High impact: you will make a difference in people's lives.\n- Beautiful, modern office space (with great views!)\n- Competitive salary and benefits (incl. medical insurance).\n- Full time position (5 days/week).\n\n\n\nHigh impact job. Top fresh grads welcome. Great opportunity.\u00a0\n\nSend us your CV, work samples (English/Chinese), current/expected salary & availability.\n", "employment_types": ["Full Time", "Contract", "Internship", "Freelance"], "selling_points": ["Social Media Expert", "Exciting Opportunity", "Fun & Collaborative Team"], "locations": ["Sheung Wan"], "categories": ["Media & Advertising", "Creative / Design", "Marketing / Public Relations", "Public Relations - Copy-writing", "Digital Marketing"], "post_time": "2022-01-13T01:30:51Z", "salary": {"currency": null, "max": null, "min": null, "period": "monthly", "term": null}, "salary_visible": false, "title_keywords": ["social media specialist"], "responsibilities": ["collaborate with", "social media", "graphics", "seo", "graphic design", "social media platforms", "website", "executing", "digital marketing", "kpis", "facebook", "planning"], "requirements": {"degrees": ["degree", "bachelor"], "majors": ["journalism", "creative media", "marketing"], "languages": ["english", "chinese"], "language_level": ["excellent"], "hard_skills": ["graphics", "plus", "seo", "illustrator", "make", "facebook", "photoshop"], "soft_skills": ["passionate", "self-motivated", "passionate about", "responsible", "timely", "unique", "hands-on", "creative", "positive"], "languages_combined": [{"language": "english", "language_level": ["excellent"]}, {"language": "chinese", "language_level": ["excellent"]}]}, "experience_required": {"duration": ["1-2 years"], "field": ["social media", "graphic design"]}}, {"job_id": "100003009045316", "location_code": "hk", "company": "Esquel Enterprises Limited", "job_title": "Assistant Officer / Officer, Corporate Communications", "description": "We are inviting high caliber to join us for an exciting career opportunity and be part of a company that believes in innovation and sustainability.\n\nResponsibilities:\n\n\n\nMultimedia production\u00a0\u2013 Develop and execute visual display such as\u00a0video, photos, graphic designs, presentation slides, webpage layouts etc.; assist in setting design directions and storyboards\nSocial media \u2013\u00a0Manage Group-level corporate social media accounts including but not limited to Facebook, Instagram, LinkedIn and YouTube; monitor channel performance; assist in content planning to drive engagement\nPR support\u00a0\u2013 Support routine media monitoring; maintain newsroom content\nKnowledge management \u2013\u00a0Maintain libraries of corporate materials and information to uphold good housekeeping and promote productivity\n\nRequirements:\n\n\nDegree or higher diploma preferably in design, creative media, communications, Fine arts, language or related disciplines\nAt least 1 year of related working experience, candidates with more experiences will be considered as Officer, Corporate Communications\nExperience preferred in Adobe suite (Premiere Pro, Photoshop, Illustrator) or other visual editing software\nFluent in spoken English, Mandarin and Cantonese\nGood command on written English and Chinese (Simplified and Traditional)\nAble to travel for business occasionally to mainland China and southeast Asia\nKeen eyes for aesthetics and attentive to details\nStrong sense of time management and priority\n\nLearn about Esquel and its eCulture values at\u00a0www.esquel.com\n\nData collected will be used for recruitment purpose only and will be kept for 24 months.\n\nAll applications will be treated in strict confidence.", "employment_types": ["Full Time", "Permanent"], "selling_points": ["Multimedia production", "Social media & PR support", "Premiere Pro, PS, Illustrator"], "locations": ["Wan Chai"], "categories": ["Design", "Multi-media", "Marketing / Public Relations", "Marketing - Marketing Communication", "Public Relations - Copy-writing"], "post_time": "2022-01-13T07:36:25Z", "salary": {"currency": null, "max": null, "min": null, "period": "monthly", "term": null}, "salary_visible": false, "title_keywords": ["assistant officer", "officer"], "responsibilities": ["social media", "management", "housekeeping", "monitoring", "graphic designs", "monitor", "design", "develop", "planning", "maintain", "visual", "facebook", "storyboards"], "requirements": {"degrees": ["diploma", "degree"], "majors": ["creative media", "fine arts", "design", "related disciplines", "communications"], "languages": ["cantonese", "english", "chinese", "mandarin"], "language_level": ["good command", "fluent"], "hard_skills": ["illustrator", "visual editing", "adobe", "premiere pro", "photoshop"], "soft_skills": ["confidence", "creative", "attentive to details", "keen", "time management"], "languages_combined": [{"language": "cantonese", "language_level": ["fluent"]}, {"language": "english", "language_level": ["good command", "fluent"]}, {"language": "chinese", "language_level": ["good command"]}, {"language": "mandarin", "language_level": ["fluent"]}]}, "experience_required": {"duration": ["at least 1 year"], "field": ["related", "editing"]}}, {"job_id": "100003009044595", "location_code": "hk", "company": "Iotena Technology Limited \u611b\u5929\u7acb\u79d1\u6280\u6709\u9650\u516c\u53f8", "job_title": "Digital Marketing Executive", "description": "Responsibilities\n\nInitiate and implement corporate communications strategies to build brand awareness\nPrepare materials for globalized campaigns\nPrepare press releases, and corporate materials, including presentations, brochures,\u00a0web content, newsletters, etc\nCopywriting for both print and digital\u00a0marketing collaterals\nOrganize and coordinate press conferences\nEstablish and maintain good relationship with media\nCoordinate and liaise with KOL and influencers\u00a0to promote all brands for the group\nFollow up shooting or video-taking\nConduct research and collect\u00a0materials for joining external company awards\nUndertake ad hoc projects as assigned\n\nRequirements:\n\nDegree in Language / Translation / Journalism / PR / Communications Marketing or relevant disciplines\n3+ years of relevant experience\nExperience in media relations and editor/reporter is preferred\nGood team player, energetic and passionate\nExcellent command of written English and Chinese is essential\nGood communication and interpersonal skills\nCandidates with less experience will be considered as Assistant Corporate Communications Officer\u00a0\nFresh graduates are also welcome\u00a0 \u00a0 \u00a0\nImmediate availability is highly preferred\n\n\u00a0We Offer:\n\n\u00a0 \u00a05-day work week\n\u00a0 \u00a0Competitive Salary Package\n\u00a0 \u00a013 months' Guaranteed Salary\n\u00a0 \u00a0Performance Incentives\n\u00a0 \u00a0Group Medical Scheme\n\u00a0 \u00a0Birthday Leave\n\u00a0 \u00a0Free Lunch\n\u00a0 \u00a0Energetic & Dynamic Culture\n\n\nInterested parties, please send your detailed resume, availability, present and expected salary to Human Resources Department by clicking \u201cApply Now\u201d.\n\nPersonal data collected will be used for recruitment purpose only.", "employment_types": ["Full Time"], "selling_points": ["Diploma/Degree holder prefer in Marketing/Business", "Min 4-5 yr exp in digital marketing Self-motivated", "Creative. Immediate availability preferred"], "locations": ["Shatin Area"], "categories": ["Marketing / Public Relations", "Marketing - General / Support", "Public Relations - Copy-writing", "E-commerce", "Business Development"], "post_time": "2022-01-13T04:44:51Z", "salary": {"currency": null, "max": null, "min": null, "period": "monthly", "term": null}, "salary_visible": false, "title_keywords": ["digital marketing executive"], "responsibilities": ["presentations", "maintain good relationship", "coordinate", "conferences", "digital marketing", "ad hoc projects", "liaise with", "conduct research"], "requirements": {"degrees": ["degree"], "majors": ["journalism", "marketing", "communications"], "languages": ["english", "chinese"], "language_level": ["excellent"], "hard_skills": ["translation"], "soft_skills": ["passionate", "good team player", "energetic", "communication and interpersonal skills"], "languages_combined": [{"language": "english", "language_level": ["excellent"]}, {"language": "chinese", "language_level": ["excellent"]}]}, "experience_required": {"duration": ["3+ years"], "field": ["editor", "reporter", "relevant experience", "media"]}}, {"job_id": "100003009046106", "location_code": "hk", "company": "Uni-China (Business) Management Limited", "job_title": "Corporate Communications Officer/ Assistant Corporate Communications Officer", "description": "Maintain a strong media network to ensure maximum exposure for clients\nAssist in planning and organizing PR & marketing events\nHandle media interviews with medical professionals, advocacy groups and patients\nDevelop multi-media medical content, which includes write-up of articles, advertorials,\nPress materials, newsletters, social media posts and other communication materials\nAssist in preparing copy-writing and proposals\nCreate news angles and execute media pitching\nCreate and develop content flow and scripts for video shooting, monitor the post-production\nMonitor and analyze the results of initiatives, including media coverage report etc.\nAssist in stakeholder engagement\nAssist in any ad-hoc projects as assigned\n\n\u00a0Requirements:\n\nDegree holder in Journalism / Communications / PR / Marketing / Translation / Language is preferred\nPast working experience in Newspaper, Television, PR agencies would be an advantage\nExcellent command of English and Chinese (written and spoken), with ability to write clear and compelling materials; Capability in Mandarin is a plus\nProficient in MS Word, Excel, PowerPoint and Chinese Word Processing\nCreative, outgoing, cheerful, talkative and persuasive with good interpersonal skills\nHave a good eye for details, passion to learn, and an ability to prioritize work\nSelf-motivated, with the ability to work independently and in a team environment\nImmediate availability is preferred\nCandidates with more experience may be considered as Senior PR Executive", "employment_types": ["Full Time", "Permanent"], "selling_points": ["Corporate Communications / PR", "English and Chinese Copywriting", "13 months' Guaranteed Salary + Bonus"], "locations": ["Lai Chi Kok"], "categories": ["Marketing / Public Relations", "Marketing - Brand / Product Management", "Marketing - Marketing Communication", "Public Relations - Copy-writing"], "post_time": "2022-01-13T09:38:35Z", "salary": {"currency": null, "max": null, "min": null, "period": "monthly", "term": null}, "salary_visible": false, "title_keywords": ["corporate communications officer", "assistant corporate communications officer"], "responsibilities": ["marketing events", "social media", "monitor", "develop", "communication", "maintain", "video shooting", "report", "ad-hoc projects", "planning"], "requirements": {"degrees": ["degree holder"], "majors": ["journalism", "marketing", "communications"], "languages": ["english", "chinese", "mandarin"], "language_level": ["excellent", "proficient"], "hard_skills": ["excel", "plus", "chinese word processing", "powerpoint", "translation", "ms word"], "soft_skills": ["outgoing", "self-motivated", "cheerful", "persuasive", "work independently", "prioritize", "communication", "clear", "interpersonal skills", "creative"], "languages_combined": [{"language": "english", "language_level": ["excellent"]}, {"language": "chinese", "language_level": ["excellent", "proficient"]}, {"language": "mandarin", "language_level": []}]}, "experience_required": {"duration": [], "field": ["pr", "newspaper"]}}, {"job_id": "100003009036410", "location_code": "hk", "company": "PURE International (Hong Kong) Ltd", "job_title": "Freelance English Copywriter", "description": "Responsibilities:\u00a0\n\nPlan and manage all Social Media platforms (Youtube, Facebook and Instagram, Telegram) strategy including content creation and posting\nDrive organic traffic and conversions rate\u00a0\nWork with\u00a0Blogger and KOL to continuously achieve social media success for client\nHandle multiple projects simultaneously and manage various accounts in a\u00a0 timely and professional manner\nManage budget and compile reports on campaign effectiveness in social media sites and collect marketing intelligence by using Google Analytics\nRequirements:\u00a0\n\n\nUniversity degree holder in Communications, Marketing, Business Administration or related disciplines\nAt least 3-5 years experiences in content writing, social media marketing and SEO\nExperiences in copywriting, blogging and publications is an advantage\nUnderstanding on social media trends and best practices across the digital and new media sectors\nSelf-motivated, independent, good team player, good analytic and problem solving skills\nGood communication and project management skills\nPassion in digital and technology, eager to learn new skills\nFluent in Cantonese and English, Mandarin is a plus\n\n\n", "employment_types": ["Freelance"], "selling_points": ["Develop/Translate marketing promotional materials", "Develop creative copy concept with design team", "Min. 4 years' experience in English copywriting"], "locations": ["Central"], "categories": ["Marketing / Public Relations", "Public Relations - Copy-writing"], "post_time": "2022-01-10T10:19:20Z", "salary": {"currency": null, "max": null, "min": null, "period": "monthly", "term": null}, "salary_visible": false, "title_keywords": ["copywriter"], "responsibilities": ["social media", "compile reports", "social media platforms", "professional manner", "budget", "plan", "facebook", "multiple projects"], "requirements": {"degrees": ["university degree"], "majors": ["related disciplines", "marketing", "business administration", "communications"], "languages": ["cantonese", "english", "mandarin"], "language_level": ["fluent"], "hard_skills": ["project management", "problem solving skills", "seo", "plus"], "soft_skills": ["good team player", "self-motivated", "independent", "passion in", "project management skills", "communication", "eager to learn", "problem solving skills"], "languages_combined": [{"language": "cantonese", "language_level": ["fluent"]}, {"language": "english", "language_level": ["fluent"]}, {"language": "mandarin", "language_level": []}]}, "experience_required": {"duration": ["at least 3-5 years"], "field": ["content writing", "social media", "copywriting", "marketing"]}}, {"job_id": "100003009050200", "location_code": "hk", "company": "Grey Anderson Limited", "job_title": "Social Media Specialist", "description": "Responsibilities:\n\nResponsible to do the copywriting in various social media platforms\nAssist in preparing analytic reports and proposal\nResponsible to follow up on integrated marketing events\nHighly involve in customer servicing, social media marketing and account servicing management\nCreation and development of presentation materials for marketing and communications\nCreative, self-motivated, responsible, polite, able to work independently and under pressure\n\n\n\nRequirements:\n\nUniversity degree in Journalism / Public Relations / Marketing\u00a0etc.\nGood command of written and spoken English and Chinese\nStrong Media Connections preferably in lifestyle\nActive on social media platforms\nHard-working, able to multi-task, work under pressure and meet deadlines\u00a0\nAble to handle projects independently\nDetail-minded, mature, outgoing, good interpersonal skills and flexible to work\u00a0\n\n\n\nSalaries are subjected to working performance and skills possessed.\n\nTips: Have a look at our website first!\n\nhttp://www.firebean.net\n\nIf you are the perfect fit for Firebean, please email your resume, profile and expect salary by clicking \"Apply Now\" We look forward to meeting you.\n\nAll applications received will be used strictly for selection purposes only.", "employment_types": ["Full Time", "Permanent"], "selling_points": ["Experiences in copywriting and blogging", "Knowledge in SEO and social media", "Passion with Youtube, Facebook and Instagram"], "locations": ["Eastern Area"], "categories": ["Marketing / Public Relations", "Marketing - Brand / Product Management", "Public Relations - Copy-writing", "Digital Marketing"], "post_time": "2022-01-14T09:55:55Z", "salary": {"currency": null, "max": null, "min": null, "period": "monthly", "term": null}, "salary_visible": false, "title_keywords": ["social media specialist"], "responsibilities": ["marketing events", "management", "social media", "social media platforms", "reports"], "requirements": {"degrees": ["university degree"], "majors": ["journalism", "marketing"], "languages": ["english", "chinese"], "language_level": ["good command"], "hard_skills": [], "soft_skills": ["detail-minded", "outgoing", "flexible", "independently", "multi-task", "mature", "hard-working", "interpersonal skills", "meet deadlines", "active", "work under pressure"], "languages_combined": [{"language": "english", "language_level": ["good command"]}, {"language": "chinese", "language_level": ["good command"]}]}, "experience_required": {"duration": [], "field": []}}, {"job_id": "100003009046647", "location_code": "hk", "company": "Firebean Limited", "job_title": "PR & Social Media Executive (5 days work)", "description": "Responsibilities:\n- Lead social campaign strategy and planning, from idea to execution\n- Ensure optimal media performance through KPI development and assessment\n- Measure, optimize and reporting on paid campaigns to achieve traffic and sales boost and increase ROI\n- Create, edit and promote social media content in various formats, eg. feeds, videos, photos, etc\u00a0\n- Assist operation of all social media platforms including Facebook, Instagram, WeChat, Weibo, YouTube, etc\n- Keep track of all trending topics and create instant content with creatives across different platforms\n- Stay alert to ad-hoc happenings during off-office hours and react with quick response\n- Take action to all changes in trends and drive engagement to online platforms\n\nRequirements:\n- Degree holder preferably in Journalism, Communication or related, experience in online environment would be a distinct advantage\n- At least 2 years relevant experience in related field is preferred\n- Social media savvy who can act quick with ad-hoc happenings\n- Creative and has a good sense in beauty, fashion, entertainment and lifestyle trends\n- Proficient in photo and video editing software (Photoshop, Premiere Pro, Final Cut Pro) is highly preferred\n- Excellent written communication skills in Chinese, good experience in Chinese and English copywriting is a plus\u00a0\n- Candidates who have experience in ecommerce is an advantage\n- Highly responsive and self-motivated, capable to work under pressure and tight deadlines\n- A team player with excellent interpersonal skills and communications skills\n\nInterested parties please send full C.V. and expected salary to Ms\u00a0Lo via email", "employment_types": ["Full Time"], "selling_points": ["Copywriting in various social media", "Follow up on integrated marketing events", "1 year relevant working experience"], "locations": ["Wan Chai"], "categories": ["Media & Advertising", "Account Servicing", "Editorial / Journalism", "Marketing / Public Relations", "Public Relations - Copy-writing"], "post_time": "2022-01-13T18:54:01Z", "salary": {"currency": null, "max": null, "min": null, "period": "monthly", "term": null}, "salary_visible": false, "title_keywords": ["social media executive"], "responsibilities": ["ad-hoc", "reporting", "social media platforms", "social media content", "facebook", "planning"], "requirements": {"degrees": ["degree holder"], "majors": ["journalism"], "languages": ["english", "chinese"], "language_level": ["excellent", "good"], "hard_skills": ["final cut pro", "plus", "video editing", "premiere pro", "photoshop"], "soft_skills": ["communication skills", "self-motivated", "capable", "communication", "interpersonal skills", "team player", "creative", "responsive", "work under pressure"], "languages_combined": [{"language": "english", "language_level": ["excellent", "good"]}, {"language": "chinese", "language_level": ["excellent", "good"]}]}, "experience_required": {"duration": ["at least 2 years"], "field": ["related", "copywriting", "relevant experience", "ecommerce"]}}, {"job_id": "100003009042725", "location_code": "hk", "company": "She Communications Ltd", "job_title": "Executive  / Senior Executive, Digital & Social Media", "description": "RESPONSIBILITIES:\n\nAct as a project team member to execute clients\u2019 projects and provide professional advice to clients\nImplement PR and communications plan to meet clients\u2019 objectives and achieve target results\nIdentify unique media angles for Clients\u2019 projects to maximize online/off-line publicity,\nDevelop and strengthen relationships with key clients, media & Influencers\nDrafting of press releases and other corporate materials\nAssisting in the development and execution of PR programs\nPrepare media clippings monitoring, quotations, reports, proposals and social media analytic reports\n\nREQUIREMENTS:\n\nA minimum of 1-2 years\u2019 working experience within a PR or integrated communications agency, candidates with more experience will be considered for the position of Senior Public Relations Executive\nDegree holder, preferably in Journalism, Communications, Marketing, Language, or related disciplines\nKnowledge in PR, Journalism or Corporate Communications. Journalistic background is an advantage\nDigital knowledge through personal/professional use of social media channels\nExcellent written and spoken English and Chinese. Mandarin proficiency is a plus\nGood project management skills and multi-tasking abilities\nOpen-minded, agile with change and practical\n\nWe offer a competitive remuneration package including 5-day work and medical insurance to the right candidate with excellent career advancement.\u00a0Interested parties please send your application letter and detailed CV including date of availability and current and expected salary to lierence @popsible.com, quoting the Job title in the email subject, we only offer short-listed candidates for an interview.\n", "employment_types": ["Full Time", "Permanent"], "selling_points": ["Social media savvy", "Creative & passionate", "Energetic & has a good sense in trending topics"], "locations": ["Sheung Wan"], "categories": ["Media & Advertising", "Account Servicing", "Marketing / Public Relations", "Public Relations - Copy-writing", "Digital Marketing"], "post_time": "2022-01-12T08:32:31Z", "salary": {"currency": null, "max": null, "min": null, "period": "monthly", "term": null}, "salary_visible": false, "title_keywords": ["senior executive", "executive"], "responsibilities": ["social media", "monitoring", "develop", "reports", "plan"], "requirements": {"degrees": ["degree holder"], "majors": ["journalism", "related disciplines", "marketing", "communications"], "languages": ["english", "chinese", "mandarin"], "language_level": ["excellent", "proficiency"], "hard_skills": ["project management", "plus", "agile"], "soft_skills": ["open-minded", "project management skills", "multi-tasking", "agile"], "languages_combined": [{"language": "english", "language_level": ["excellent"]}, {"language": "chinese", "language_level": ["excellent"]}, {"language": "mandarin", "language_level": ["proficiency"]}]}, "experience_required": {"duration": ["minimum of 1-2 years"], "field": ["agency", "pr", "public relations"]}}, {"job_id": "100003009043458", "location_code": "hk", "company": "Besuto PR", "job_title": "PR & Marketing Executive", "description": "Benefits:\n\n5 days Work + Bank Holidays\nFull Medical Coverage\nPerformance Bonus\nBirthday Leave, Wedding Leave\nTraining Subsidy\nProfessional Training + Good Career Prospect in the Growing Digital Marketing Industry\n\nResponsibilities include:\n\nCraft creative copy writing across social media platform;\nSupport creative project pitching;\nAssist online marketing execution team to plan and implement of digital marketing communication/programs to build brand awareness;\nWork with internal teams to ensure content for internal and external communication are published in the right channels;\nDevelop and edit content / copy for online customer communications;\nPerform quality control on all advertisements and content distribution; track monthly performance data.\n\nRequirements :\n\nPassionate in digital is a MUST;\nDiploma holder majoring in Journalism, Marketing, communications or PR related discipline or above;\n1 year of relevant work experience in publishing, editing or copywriting; experience in digital marketing agencies is a plus.\nExperience in creative project pitching is an advantage;\nExcellent in Chinese and English written skill;\nTo be responsible, organized, proactive and self-motivated.\nCandidates with more experience will be considered as Senior Copywriter.\n\nTo Apply:\n\nFor more information about You Find Ltd., please visit\u00a0www.youfind.hk\nWe offer attractive package to the right candidate. Interested parties please send your application by clicking \"Apply Now\".\nAll information received will be used for recruitment purpose only and will be kept in strict confidential.\n\nYouFind is an Equal Opportunity Employer and prohibits discrimination and harassment of any kind. All employment decisions at YouFind are based on business needs, job requirements and individual qualifications, without regard to race; family status; gender; disability status or any other status protected by the laws or regulations in Hong Kong.", "employment_types": ["Full Time", "Permanent"], "selling_points": [], "locations": ["Wan Chai"], "categories": ["Marketing / Public Relations", "Marketing - General / Support", "Public Relations - Copy-writing"], "post_time": "2022-01-12T12:40:01Z", "salary": {"currency": null, "max": null, "min": null, "period": "monthly", "term": null}, "salary_visible": false, "title_keywords": ["pr & marketing executive"], "responsibilities": [], "requirements": {"degrees": [], "majors": [], "languages": [], "language_level": [], "hard_skills": [], "soft_skills": [], "languages_combined": []}, "experience_required": {"duration": [], "field": []}}, {"job_id": "100003009036233", "location_code": "hk", "company": "You Find Limited", "job_title": "Creative Copywriter", "description": "About The Role:\n\nWrite original copy and edit content for a range of marketing and communications materials, translate certain material between English and Chinese.\nDevelop digital marketing and social media content calendar, integrate social media strategies with digital and event campaigns align with company objectives\nFormulate and execute the global marketing campaign across all platforms (e.g. Social Media, Blog, Forum etc.)\nCreate and edit the content for various digital platforms including but not limited to social media, website, eDM and marketing collateral\nCollaborate with in-house designer to develop effective digital marketing campaigns\nAssist the content marketing team in preparing and posting various types of website content, including short videos, blog posts and articles.\nAssist in implementation of different type of online marketing campaign, like KOL, Social media ads in different formats, etc.,\nPerform ad-hoc duties as assigned\nWhat you\u2019ll need to have:\n\nMinimum 2 years of solid experience in digital marketing/ content marketing\nBachelor holder in Marketing, Communications, Journalism or related discipline\nExcellent understanding of digital marketing concepts\nBasic knowledge about UI/UX and how they affect customers.\nCreative writing skill in English and Chinese is a must\nExperience with Financial industry in Global or Asian markets is an advantage\nBackground social media agency/ copywriter is a plus\nPassionate about the Social Media and latest online advertising technologies\nCan-do attitude, proactive, independent and good team player\nWhy you should join us?\nWorking in a growth driven, collaborative open space where we encourage creativity and ideas flow freely.\nWorking within a small multi-cultural team where your ideas are welcome.\nFlat structure environment, you will be able to work independently and make your own choices\n\nWhat We Offer:\u00a0\n\n\n5-day work week, work-life balance and a relaxed yet ambitious environment\nMulti-cultural working environment\nOpportunities for you to upskill yourself continuously\nOpportunities to participate in fun and exciting company events year-round\nMedical scheme & dental benefit\nFitness allowance\nPerformance bonus\nComplimentary food and drinks in the workplace\nDoes it sound like you?\n\n\nWe would love to talk to you!\n\nPlease send full resume with\u00a0current and expected salary by clicking the Apply link and telling us why you want to work with us. If your skills and experience are a match, we will be in touch soon. Meanwhile, please visit our website at https://www.hwtech.hk/ and social media channels to learn more about our innovative business.\n\nWe are an equal opportunity employer and welcome applications from all qualified candidates. All personal data collected will be treated in strict confidence and be used solely for recruitment purpose.", "employment_types": ["Full Time", "Permanent"], "selling_points": ["Fast growing digital marketing industry", "Good career prospect; strong team spirit", "5 days work; fun & energetic working environment"], "locations": ["Ngau Tau Kok"], "categories": ["Media & Advertising", "Editorial / Journalism", "Marketing / Public Relations", "Marketing - Marketing Communication", "Public Relations - Copy-writing"], "post_time": "2022-01-10T09:45:27Z", "salary": {"currency": null, "max": null, "min": null, "period": "monthly", "term": null}, "salary_visible": false, "title_keywords": ["creative copywriter"], "responsibilities": ["collaborate with", "social media", "ideas", "edm", "digital marketing campaigns", "website", "implementation", "develop", "social media content", "digital marketing", "ad-hoc duties", "social media strategies", "online advertising", "ui"], "requirements": {"degrees": ["bachelor"], "majors": ["journalism", "marketing", "communications"], "languages": ["english", "chinese"], "language_level": [], "hard_skills": ["small", "plus", "basic", "writing skill", "make"], "soft_skills": ["good team player", "proactive", "independent", "work independently", "can-do attitude", "collaborative", "writing skill", "ad-hoc duties", "creative", "driven", "passionate about"], "languages_combined": [{"language": "english", "language_level": []}, {"language": "chinese", "language_level": []}]}, "experience_required": {"duration": ["minimum 2 years"], "field": ["marketing", "digital marketing", "financial industry"]}}, {"job_id": "100003009048081", "location_code": "hk", "company": "iPR Ogilvy Limited", "job_title": "Senior Associate/ Consultant (Financial PR)", "description": "Provide support to Marketing team in designing, developing and executing promotional materials to achieve designated business goals\nAssist management in executing marketing strategies and marketing plan to achieve business objectives\nMaintain close relationship with bloggers/ KOLs/ influencers\nContent planning and copywriting for a range of materials including product information on eShop and website, press release and communications on social media\nResponsible for eCommerce business including product update, campaign performance review and customers\u2019 inquiry handling\nLiaise with internal departments and external agencies to ensure the smooth execution of marketing programs\nParticipate in other ad-hoc marketing activities\n\nRequirements:\n\nDegree holder in Communications, Marketing or related disciplines\nMinimum 2 years of working experience in Marketing, eCommerce or related fields, preferably in F&B / FMCG industry\nProficiency in photoshop or illustrator is a plus\nGood marketing sense, multi-tasking, can-do attitude, independent, detail-minded and able to work under pressure\nGood command of both written and spoken English and Chinese\nProficiency in MS Office and Chinese Word Processing\nInterested parties please send your CV,\u00a0expected salary & availability by clicking \"APPLY NOW\" button or contact Human Resources Department at\u00a03656 1388\u00a0for enquiries. Personal data collected will be used for recruitment related purpose only.", "employment_types": ["Full Time", "Permanent"], "selling_points": ["Experienced Financial Public Relations Executives", "Handle key account management", "Organic growth and management exposure"], "locations": ["Wan Chai"], "categories": ["Marketing / Public Relations", "Marketing - Marketing Communication", "Public Relations - Copy-writing", "Public Relations - Event Management"], "post_time": "2022-01-14T04:43:59Z", "salary": {"currency": null, "max": null, "min": null, "period": "monthly", "term": null}, "salary_visible": false, "title_keywords": ["senior associate", "consultant"], "responsibilities": ["ad-hoc", "social media", "provide support", "business goals", "management", "marketing strategies", "work under pressure", "review", "developing", "website", "marketing plan", "promotional materials", "executing", "maintain", "designing", "liaise with", "planning"], "requirements": {"degrees": ["degree holder"], "majors": ["related disciplines", "marketing", "communications"], "languages": ["english", "chinese"], "language_level": ["proficiency", "good command"], "hard_skills": ["plus", "chinese word processing", "fmcg industry", "illustrator", "photoshop", "ms office"], "soft_skills": ["detail-minded", "marketing sense", "independent", "responsible", "can-do attitude", "multi-tasking", "smooth", "work under pressure"], "languages_combined": [{"language": "english", "language_level": ["good command"]}, {"language": "chinese", "language_level": ["proficiency", "good command"]}]}, "experience_required": {"duration": ["minimum 2 years"], "field": ["ecommerce", "fmcg", "related", "f&b", "marketing"]}}, {"job_id": "100003009046347", "location_code": "hk", "company": "H&W Technology Service Limited", "job_title": "Digital Marketing Specialist (Social Media/ FSI/ Fintech)", "description": "Job duties:\n\n\n\nAs a member of Fashion Programme and work with the Fashion Team in executing various fashion promotional initiatives, including Fashion Asia Hong Kong;\nDevelop and implement marketing & communication, and partnership strategies of fashion related programmes;\nImplement digital & social media strategy, PR & advertising for FA to maximize exposure in the regional campaigns;\nAssist and support the team to organize events from start to finish according to the requirements, target audience and objectives;\nEffectively handle logistics, work progresses, result and evaluation and reporting, make sure the process and documentations are in compliance with governance and administrative requirements;\nWork closely with professional service providers and liaise with internal and external parties within and outside HK; and\nPerform ad hoc assignments as required.\n\n\n\nRequirements:\n\n\n\nBachelor degree holder who is a highly motivated and versatile individual;\n2 years\u2019 experience in event management, digital marketing and project management;\nStrong verbal and written communication skills in both English and Chinese are essential (Mandarin will be an advantage);\nProactive, detailed-minded, responsible and resourceful self-starter;\nGood problem solving and interpersonal skills;\nPossesses good knowledge in the fashion industry;\nStrictly adhere to project timeline and deadlines; and\nProficient in MS Office Application and Chinese Word Processing.\n\nMore information about Fashion Asia:\nhttps://www.fashionasiahk.com/\n\nWork Location: Kowloon Bay / Tsuen Wan\n\nInterested parties are invited to apply by sending your resume with full details of education, work experience, current & expected salary, contact telephone number and earliest available date to the Human Resources Office, Hong Kong Design Centre, Unit 602, 6/F, Mill 5, The Mills, 45 Pak Tin Par Street, Tsuen Wan or by clicking \u201cApply Now\u201d or email to:\u00a0hr[@]hkdesigncentre.org\u00a0on or before 26\u00a0January 2022. HKDC reserves the right not to make appointment for the post(s) advertised. Only short-listed candidates will be notified. All information received will be kept in strict confidence for six months and data will only be used for recruitment purpose.", "employment_types": ["Full Time", "Permanent"], "selling_points": ["2yrs+ exp. in digital / content marketing", "Exp. in Financial field &/ global market preferred", "Knowledge in social media & website content"], "locations": ["Hung Hom"], "categories": ["Media & Advertising", "Creative / Design", "Marketing / Public Relations", "Public Relations - Copy-writing", "Digital Marketing"], "post_time": "2022-01-13T10:37:58Z", "salary": {"currency": null, "max": null, "min": null, "period": "monthly", "term": null}, "salary_visible": false, "title_keywords": ["digital marketing specialist"], "responsibilities": ["social media", "reporting", "advertising", "compliance", "internal and external parties", "develop", "communication", "executing", "logistics", "ad hoc assignments", "evaluation", "liaise with", "support the team"], "requirements": {"degrees": ["bachelor degree holder"], "majors": [], "languages": ["english", "chinese", "mandarin"], "language_level": ["advantage", "proficient"], "hard_skills": ["problem solving", "project management", "chinese word processing", "ms office"], "soft_skills": ["communication skills", "responsible", "resourceful", "versatile", "problem solving", "project management", "motivated", "interpersonal skills", "proactive", "detailed"], "languages_combined": [{"language": "english", "language_level": []}, {"language": "chinese", "language_level": ["proficient"]}, {"language": "mandarin", "language_level": ["advantage"]}]}, "experience_required": {"duration": ["2 years"], "field": ["project management", "management", "digital marketing"]}}, {"job_id": "100003009042287", "location_code": "hk", "company": "Leader Marine Products Trading Limited", "job_title": "Marketing Officer (Graphic Design)", "description": "CK Hutchison, head office of a diversified group of companies with over 18,000 employees in Hong Kong and an\u00a0addition 279,300 employees worldwide, invites high calibre and self-motivated individuals to join our organisation.\n\nResponsibilities:\nAssists in development and execution of communications strategies to support the Group\u2019s various corporate activities\nHelps organise corporate and media activities\nWrites and translates Chinese and English communications materials including press releases, speeches, newsletters and feature articles\nCoordinates production work for annual and interim reports and other corporate publications\nMaintains corporate information and compiles various public relations reports\nOffers public relations counsel to subsidiaries and provides assistance in issue management\nRequirements:\nUniversity degree in communications, languages or business related disciplines\nMinimum 10 years\u2019 experience in corporate communications, preferably with in-house public relations and / or agency background\nThorough knowledge of Hong Kong\u2019s media scene and the local political and social environment\nHigh competence in written and spoken English and Chinese, including Putonghua\nProficiency in Microsoft Word, Excel and PowerPoint with Chinese word processing\nGood inter-personal communication skills\nWell organised and prepared to work under pressure and outside regular office hours\nAmiable personality and able to work with others as a team\nCommunications agency experience an added advantage\n\nSalary and benefits will commensurate with experience and competence. Please click the \u201cAPPLY NOW\u201d button and include a detailed resume with indication of expected salary.\u00a0\u00a0\n\n\nWe are an equal opportunity employer and welcome applications from all qualified candidates. Personal data collected will be treated in\u00a0the strictest confidence and handled confidentially by authorised personnel for recruitment-related purposes\u00a0only within the CK Hutchison Group of companies.\n\nApplicants not having heard\u00a0from us within six weeks of the date of application may consider their application unsuccessful.\u00a0The personal data of\u00a0unsuccessful applicants will be destroyed after the recruitment exercise\u00a0pursuant to the requirements of the Personal Data (Privacy) Ordinance in Hong Kong.", "employment_types": ["Full Time", "Permanent"], "selling_points": [], "locations": ["Aberdeen"], "categories": ["Design", "Graphics", "Marketing / Public Relations", "Marketing - Marketing Communication", "Public Relations - Copy-writing"], "post_time": "2022-01-12T06:52:11Z", "salary": {"currency": null, "max": null, "min": null, "period": "monthly", "term": null}, "salary_visible": false, "title_keywords": ["marketing officer"], "responsibilities": ["management", "reports"], "requirements": {"degrees": ["university degree"], "majors": ["related disciplines", "business", "communications"], "languages": ["putonghua", "english", "chinese"], "language_level": ["proficiency"], "hard_skills": ["excel", "microsoft word", "chinese word processing", "powerpoint"], "soft_skills": ["communication skills", "amiable", "inter-personal", "thorough", "organised", "work under pressure"], "languages_combined": [{"language": "putonghua", "language_level": []}, {"language": "english", "language_level": []}, {"language": "chinese", "language_level": ["proficiency"]}]}, "experience_required": {"duration": ["minimum 10 years"], "field": ["agency", "public relations"]}}, {"job_id": "100003009044260", "location_code": "hk", "company": "Hong Kong Design Centre Limited", "job_title": "Project Coordinator - Partnerships & Digital Engagements (Contract ends on 31/3/2022)", "description": "\u4e3b\u8981\u8077\u8cac\uff1a\n\n\u81ea\u7136\u7bc7\n\n\u81ea\u7136\u7bc7\u5de5\u4f5c\uff0c\u65e8\u5728\u4ecb\u7d39\u9999\u6e2f\u7684\u5730\u7406\u7279\u9ede\uff0c\u5c55\u793a\u5730\u7406\u5927\u821e\u53f0\uff0c\u5982\u4f55\u5f71\u97ff\u9999\u6e2f\u653f\u6cbb\u3001\u7d93\u6fdf\u3001\u793e\u6703\u548c\u6587\u5316\u7684\u767c\u5c55\n\u4e3b\u984c\u5305\u62ec\u81ea\u7136\u74b0\u5883\u3001\u81ea\u7136\u8cc7\u6e90\u3001\u751f\u614b\u3001\u74b0\u4fdd\u3001\u6f01\u8fb2\u696d\u3001\u74b0\u5883\u5de5\u7a0b\u3001\u653f\u6cbb\u5730\u7406\u3001\u4eba\u53e3\u7b49\n\n\u4eba\u7269\u7bc7\n\n\n\u7d71\u7c4c\u53e3\u8ff0\u6b77\u53f2\u6d3b\u52d5\uff0c\u5c07\u5176\u878d\u5408\u672c\u4e2d\u5fc3\u7684\u7de8\u7e82\u548c\u63a8\u5ee3\u5de5\u4f5c\n\u50b3\u6388\u53e3\u8ff0\u6b77\u53f2\u7d93\u9a57\uff0c\u63d0\u5347\u672c\u4e2d\u5fc3\u8a2a\u8ac7\u8cea\u91cf\uff0c\u57f7\u884c\u91cd\u8981\u8a2a\u8ac7\n\u898f\u5283\u548c\u843d\u5be6\u300a\u9999\u6e2f\u5fd7\u300b\u4eba\u7269\u7bc7\u7684\u7de8\u4fee\u5de5\u4f5c\n\n\u5176\u4ed6\u8077\u8cac\uff1a\n\n\u66f8\u7c4d\u51fa\u7248\u9805\u76ee\u7ba1\u7406\uff0c\u5f9e\u898f\u5283\u81f3\u4ed8\u5370\uff0c\u5305\u62ec\u5167\u90e8\u81ea\u64b0\u548c\u5916\u5224\u7684\u5377\u76ee\n\u65e5\u5e38\u5de5\u4f5c: \u7814\u7a76\u652f\u63f4\u3001\u8cc7\u6599\u641c\u96c6\u3001\u64b0\u7a3f\u3001\u5be9\u7a3f\u3001\u6f64\u98fe\u7a3f\u4ef6\u3001\u8a2a\u8ac7\u3001\u806f\u7d61\u4f5c\u8005\u3001\u884c\u653f\u652f\u63f4\u7b49\n\u6309\u7167\u4e2d\u5fc3\u6574\u9ad4\u7de8\u64b0\u5de5\u4f5c\u7684\u9700\u8981\u3001\u61c9\u8058\u4eba\u58eb\u7684\u5c08\u9577\u548c\u8208\u8da3\uff0c\u6709\u53ef\u80fd\u7372\u5b89\u6392\u8de8\u90e8\u985e\u5de5\u4f5c\n\n\u8077\u4f4d\u8981\u6c42\uff1a\n\n\u4e3b\u4fee\u74b0\u5883 (\u5730\u7406\u3001\u751f\u7269\u3001\u751f\u7269\u5316\u5b78\u3001\u751f\u614b\u3001\u74b0\u5883\u79d1\u5b78\u7b49)\u3001\u4eba\u6587\u6216\u793e\u6703\u5b78\u79d1\u8005\u512a\u5148\u8003\u616e\n\u7a4d\u7d2f\u4e94\u5e74(\u7f16\u8f2f); \u5341\u5e74 (\u9ad8\u7d1a\u7de8\u8f2f)\u4ee5\u4e0a\u7814\u7a76\u3001\u5beb\u4f5c\u3001\u65b0\u805e\u5831\u9053\u6216\u7de8\u8f2f\u7684\u5de5\u4f5c\u7d93\u9a57\n\u5177\u5099\u7ba1\u7406\u53e3\u8ff0\u6b77\u53f2\u9805\u76ee\u548c\u9999\u6e2f\u4eba\u7269\u7814\u7a76\u7d93\u9a57\uff0c\u66fe\u51fa\u7248\u53e3\u8ff0\u6b77\u53f2\u8457\u4f5c\n\u5177\u5099\u512a\u826f\u7684\u4e2d\u6587\u5beb\u4f5c\u548c\u7de8\u8f2f\u80fd\u529b\uff0c\u53ca\u826f\u597d\u7684\u82f1\u6587\u8b80\u5beb\u80fd\u529b\n\u5177\u5099\u826f\u597d\u7684\u6e9d\u901a\u548c\u9818\u5c0e\u80fd\u529b\uff0c\u80fd\u7ba1\u7406\u53ca\u53c3\u8207\u7814\u7a76\u5718\u968a\u548c\u51fa\u7248\u5718\u968a\n\u719f\u6089\u51fa\u7248\u3001\u77e5\u8b58\u7522\u6b0a\u7b49\u76f8\u95dc\u6cd5\u5f8b\u548c\u653f\u7b56\n\u80fd\u719f\u7df4\u4f7f\u7528\u5e38\u7528\u7de8\u8f2f\u8edf\u4ef6\n\u7d93\u9a57\u8f03\u8c50\u5bcc\u8005\u5c07\u88ab\u8003\u616e\u70ba\u9ad8\u7d1a\u7de8\u8f2f\n\n\u00a0\u6709\u610f\u61c9\u5fb5\u8005\u8acb\u63d0\u4ea4\u4ee5\u4e0b\u8cc7\u6599\uff1a\n\n\u5b8c\u6574\u5c65\u6b77\n\u6c42\u8077\u4fe1\n\u5b78\u6b77\u8b49\u660e\u526f\u672c\uff08\u5305\u62ec\u516c\u958b\u8a66\u6210\u7e3e\uff0c\u5982\u9069\u7528\uff09\n\u73fe\u6709\u53ca\u8981\u6c42\u85aa\u91d1\n\u5c65\u65b0\u65e5\u671f\n\n\n\n\u63d0\u4ea4\u7533\u8acb\u65e5\u671f\u8d77\u8a08\u5169\u500b\u6708\u5167\uff0c\u7533\u8acb\u4eba\u5982\u672a\u7372\u9080\u8acb\u9762\u8a66\uff0c\u53ef\u8996\u7533\u8acb\u672a\u80fd\u6210\u529f\u3002\n\n\u7533\u8acb\u4eba\u63d0\u4f9b\u7684\u6240\u6709\u8cc7\u6599\u7d55\u5c0d\u4fdd\u5bc6\uff0c\u4e26\u50c5\u7528\u65bc\u62db\u8058\u3002", "employment_types": ["Full Time", "Contract"], "selling_points": [], "locations": ["Kowloon Bay"], "categories": ["Media & Advertising", "Editorial / Journalism", "Marketing / Public Relations", "Public Relations - Copy-writing", "Digital Marketing"], "post_time": "2022-01-13T03:35:33Z", "salary": {"currency": null, "max": null, "min": null, "period": "monthly", "term": null}, "salary_visible": false, "title_keywords": ["project coordinator"], "responsibilities": [], "requirements": {"degrees": [], "majors": [], "languages": [], "language_level": [], "hard_skills": [], "soft_skills": [], "languages_combined": []}, "experience_required": {"duration": [], "field": []}}, {"job_id": "100003009045903", "location_code": "hk", "company": "CK Hutchison Holdings Limited", "job_title": "Manager - Corporate Communications", "description": "Getting into 2022, lots of my clients have kicked off their recruitment.\n\nCOVID19 does not slow down the business plan.\n\nCurrently, 2 of my clients from banking field and Electronics & Engineering field are hiring for inhouse Copywriter (Chinese & English content).\n\nMain responsibilities:\n\nPlanning and develop company brand and event related marketing promotion content; Proof read, upload and maintain\nContent development on company website, eDM, Instagram, Facebook, WeChat etc.\nPrepare for press release, product description or new product launch\n\nMain requirements:\n\nMin. 2 years working experience\nBachelor's Degree in Media, Advertising, Translate, Language or Marketing related discipline\nContent development, copywriting (Chinese and English) related experience\nBasic PS, AI is a big plus\nWilling to work under pressure\nFSI, Banking or Engineering background is a huge PLUS", "employment_types": ["Full Time"], "selling_points": [], "locations": ["Central"], "categories": ["Marketing / Public Relations", "Public Relations - Copy-writing", "Public Relations - Event Management", "Public Relations - General / Support"], "post_time": "2022-01-13T10:32:43Z", "salary": {"currency": null, "max": null, "min": null, "period": "monthly", "term": null}, "salary_visible": false, "title_keywords": ["manager"], "responsibilities": ["edm", "develop", "maintain", "facebook", "company website", "planning"], "requirements": {"degrees": ["degree", "bachelor"], "majors": ["marketing"], "languages": ["english", "chinese"], "language_level": [], "hard_skills": ["plus", "basic", "ai"], "soft_skills": ["work under pressure"], "languages_combined": [{"language": "english", "language_level": []}, {"language": "chinese", "language_level": []}]}, "experience_required": {"duration": ["2 years"], "field": ["copywriting", "content development", "related"]}}, {"job_id": "100003009042753", "location_code": "hk", "company": "Hong Kong Chronicles Institute Limited", "job_title": "\u9ad8\u7d1a\u7de8\u8f2f/ \u7de8\u8f2f (\u81ea\u7136/ \u4eba\u7269\u7bc7) Senior Editor/ Editor (Nature/ People Section)", "description": "Responsibilities:\n\nDrive strategic content plans and formulate content pillars for clients (Copy based)\nManage the content calendar as creative gatekeeper\nDevelop creative concepts, suggest innovative ways of delivering content and keep up with the latest marketing trends\nDevelop creative marketing content, including video, graphic, posts to support company campaigns\nCraft creative copywriting for key accounts\nSupport creative project pitching with Creative Director (Art Based)\nFormulate and manage engaging bilingual content for social media and digital platforms.\nBe proactive and creative in contributing content development and social media insights and research.\n\nRequirements:\n\n\nDegree holder in Marketing, Digital Marketing, Communication or related disciplines\n3 - 5 years of solid experience in content marketing, digital marketing or related experience\nCandidates with less experience will be considered as Copywriter\nExcellent in both spoken and written English and Chinese with bilingual copywriting skill.\nBe able to work under pressure with tight timeline and multi-tasking capability.\nWell-presented with excellent interpersonal and communication skills\nGood Knowledge in SEO, SEM and Google Analytics with trackable performance is a plus.", "employment_types": ["Full Time", "Permanent"], "selling_points": ["\u7ba1\u7406\u53e3\u8ff0\u6b77\u53f2\u9805\u76ee\u7d93\u9a57", "\u64b0\u7a3f\u3001\u5be9\u7a3f\u3001\u6f64\u98fe\u7a3f\u4ef6\uff0c\u53c3\u8207\u8abf\u7814\u5de5\u4f5c", "\u5177\u5099\u826f\u597d\u7684\u6e9d\u901a\u548c\u9818\u5c0e\u80fd\u529b\uff0c\u64c5\u9577\u5718\u968a\u5408\u4f5c"], "locations": ["Wan Chai"], "categories": ["Media & Advertising", "Editorial / Journalism", "Marketing / Public Relations", "Public Relations - Copy-writing", "Public / Civil", "Social Services - Community / Non-profit Organization"], "post_time": "2022-01-12T08:42:03Z", "salary": {"currency": null, "max": null, "min": null, "period": "monthly", "term": null}, "salary_visible": false, "title_keywords": ["editor", "senior editor", "\u7de8\u8f2f", "\u9ad8\u7d1a\u7de8\u8f2f"], "responsibilities": ["plans", "develop creative concepts", "social media", "develop"], "requirements": {"degrees": ["degree holder"], "majors": ["related disciplines", "marketing", "digital marketing"], "languages": ["english", "chinese"], "language_level": ["excellent"], "hard_skills": ["google analytics", "plus", "seo", "sem"], "soft_skills": ["communication skills", "communication", "multi-tasking", "interpersonal", "work under pressure"], "languages_combined": [{"language": "english", "language_level": ["excellent"]}, {"language": "chinese", "language_level": ["excellent"]}]}, "experience_required": {"duration": ["3 - 5 years"], "field": ["related", "marketing", "digital marketing"]}}, {"job_id": "100003009039162", "location_code": "hk", "company": "Walters People (HK)", "job_title": "2022 new hiring <Copywriter & Content Executive>", "description": "Looking for candidate with distinguished academic & scholarly achievements to join a leading think tank as policy researcher.\n\nClient Details\n\nA leading think tank with a mission to foster Hong Kong's long-term competitiveness and quality of life through public policy advocacy\n\nDescription\n\nPerform research on assigned policy areas such as economic development, land supply, education, youth policy, healthcare, and innovation.\nAct as project manager and provide leadership to interns, graduates, and junior staff\n\nProfile\n\nThe candidate should have an excellent academic record and intellectually curious. Three to four (3-4) years of relevant experience in policy analysis or policy research is required. Excellent quantitative and qualitative analysis skills, as well as strong written communication in English and Chinese, are essential in this role.\n\nJob Offer\n\nExcellent platform to perform duties as an influencer of public policy that impact Hong Kong's long-term future\n\nTo apply online please click the 'Apply' button below. For a confidential discussion about this role please contact Anthony Lau on +852 3412 4851.", "employment_types": ["Full Time", "Permanent"], "selling_points": ["Several openings from Tech and FS industry", "Welcome agency background candidate", "HKD20~30k with performance bonus"], "locations": ["Not Specified"], "categories": ["Marketing / Public Relations", "Marketing - Marketing Communication", "Public Relations - Copy-writing", "Digital Marketing"], "post_time": "2022-01-11T08:53:28Z", "salary": {"currency": "HKD", "max": 29999, "min": 20000, "period": "monthly", "term": null}, "salary_visible": true, "title_keywords": ["copywriter", "executive"], "responsibilities": ["communication", "analysis", "quality", "contact"], "requirements": {"degrees": [], "majors": [], "languages": ["english", "chinese"], "language_level": ["excellent"], "hard_skills": ["analysis"], "soft_skills": ["communication", "perform duties", "leadership"], "languages_combined": [{"language": "english", "language_level": ["excellent"]}, {"language": "chinese", "language_level": ["excellent"]}]}, "experience_required": {"duration": [], "field": ["research", "relevant experience"]}}, {"job_id": "100003009037581", "location_code": "hk", "company": "Go In Marketing", "job_title": "Senior Copywriter / Digital Creative Specialist (Copy Based)", "description": "Job Highlights\n\nDigital and e-commerce marketing\nCopywriting of social media marketing materials\nImmediate availability is preferred\n\nResponsibilities\n\n-\u00a0\u00a0\u00a0\u00a0\u00a0 Assist in planning, developing and implementing marketing campaign\n\n-\u00a0\u00a0\u00a0\u00a0\u00a0 Manage and monitor the day-to-day performance of social and online marketing platforms\n\n-\u00a0\u00a0\u00a0\u00a0\u00a0 Tracking effectiveness of marketing campaigns and reporting findings to the executive team\n\n-\u00a0\u00a0\u00a0\u00a0\u00a0 PC knowledge in Photoshop or AI is preferable\n\n-\u00a0\u00a0\u00a0\u00a0\u00a0 Knowledge in video or photo editing is a plus\n\nRequirements\n\n-\u00a0\u00a0\u00a0\u00a0\u00a0 Diploma or Degree holder, preferably in Marketing/ Business or related discipline\n\n-\u00a0\u00a0\u00a0\u00a0\u00a0 Minimum 4 \u2013 5 years experience in digital marketing\n\n-\u00a0\u00a0\u00a0\u00a0\u00a0 Self-motivated, independent and well-organized with attention to details\n\n-\u00a0\u00a0\u00a0\u00a0\u00a0 Creative and conceptual, with interest in the latest digital trends\n\n-\u00a0\u00a0\u00a0\u00a0\u00a0 Excellent knowledge of MS Office and graphic design software\n\n-\u00a0\u00a0\u00a0\u00a0\u00a0 Immediate availability is preferred", "employment_types": ["Full Time"], "selling_points": ["Fun working environment", "Five-day work week", "Performance bonus"], "locations": ["Lai Chi Kok"], "categories": ["Marketing / Public Relations", "Marketing - Brand / Product Management", "Public Relations - Copy-writing", "Digital Marketing"], "post_time": "2022-01-11T03:11:32Z", "salary": {"currency": null, "max": null, "min": null, "period": "monthly", "term": null}, "salary_visible": false, "title_keywords": ["specialist", "copywriter", "creative"], "responsibilities": ["reporting", "monitor", "developing", "planning", "marketing campaigns", "editing", "tracking"], "requirements": {"degrees": ["diploma", "degree holder"], "majors": ["business", "marketing"], "languages": [], "language_level": [], "hard_skills": ["ms office"], "soft_skills": ["self-motivated", "independent", "well-organized", "attention to details", "creative"], "languages_combined": []}, "experience_required": {"duration": ["5 years"], "field": ["digital marketing"]}}, {"job_id": "100003009048126", "location_code": "hk", "company": "Page Personnel", "job_title": "Business Development Coordinator - US based law firm", "description": "SPRG is a leading, award winning and caring public relations group with headquarters in Hong Kong and operation overseas. The right candidate will be working for our clients that are listed or ready-to-list on the stock exchanges, to plan and implement their ongoing investor relations and media relations campaigns\u00a0and IPO communications programs.\n\nResponsibilities:\n\nFormulate comprehensive financial communication strategies and proposals for clients\nHands-on approach to ensure perfect implementation\nDevelop new clients\n\nGeneral Requirements:\n\nUniversity graduate\n5+ years' solid experience as a financial PR veteran\nGood writing skill and in-depth knowledge of media relations and financial markets\nExcellent command in both written and spoken English & Chinese\nMandarin proficiency is preferred\nPleasant and mature personality, good mastery of analytical, presentation and problem solving skills, strong leadership and detail-minded\nSophisticated in PowerPoint and\u00a0other computer softwares\n\nInterested parties please complete the standard application form by clicking the\u00a0Apply now\u00a0button. You can also attach your tailored CV and Cover letter with your current and expected salary which we will use to review applications.\u00a0\n\nIt is Our Company policy to comply with the requirements of the Personal Data (Privacy) Ordinance (Cap. 486) of the Laws of the Hong Kong Special Administrative Region. Any personal data which is collected shall be handled in accordance with this Personal Information Collection Statement (\u201cPICS\u201d).\n\n\nThe personal data collected from you will be used for purposes relating to your application for employment with the Company. You must ensure that all personal data provided to the Company are accurate, complete and up-to-date. For correction of or access to personal data after submission of the job application or enquiries on recruitment matters, please contact the HR or subject officer as specified in the recruitment advertisement.\n\nWebsite:\u00a0\u00a0www.sprg.com.hk\u00a0/\u00a0www.sprg.asia\n\nFacebook:\u00a0\u00a0https://www.facebook.com/SPRGAsia\u00a0/\u00a0https://www.facebook.com/CSR.SPRG\u00a0", "employment_types": ["Full Time", "Permanent"], "selling_points": ["Reputable law firm with all rounded training", "Excellent career progression", "Attract salary package"], "locations": ["Not Specified"], "categories": ["Marketing / Public Relations", "Marketing - Market Research", "Marketing - Marketing Communication", "Public Relations - Copy-writing"], "post_time": "2022-01-14T05:06:02Z", "salary": {"currency": "HKD", "max": 29999, "min": 20000, "period": "monthly", "term": null}, "salary_visible": true, "title_keywords": ["coordinator"], "responsibilities": ["communication", "implementation", "develop"], "requirements": {"degrees": ["university graduate"], "majors": [], "languages": ["english", "chinese", "mandarin"], "language_level": ["excellent", "proficiency"], "hard_skills": ["problem solving skills", "powerpoint", "writing skill"], "soft_skills": ["detail-minded", "sophisticated", "mature", "pleasant", "writing skill", "problem solving skills", "leadership", "presentation"], "languages_combined": [{"language": "english", "language_level": ["excellent"]}, {"language": "chinese", "language_level": ["excellent"]}, {"language": "mandarin", "language_level": ["proficiency"]}]}, "experience_required": {"duration": ["5+ years"], "field": ["pr", "financial"]}}, {"job_id": "100003009049646", "location_code": "hk", "company": "Strategic Financial Relations (China) Ltd.", "job_title": "Consultant / Senior Consultant", "description": "Our client is one of the fastest growing technology companies in Hong Kong. Poised at an exciting stage in their growth the need has arisen to hire a Public Relations Manager to join their team.\n\nLeading the PR activities for the company, you will be responsible to engage with the full suite of external and internal stakeholders, as well as develop meaningful media relations that support and drive the organization strategies across the globe.\n\nJob Responsibilities\n\nEstablish the global PR strategies according to the company mission and goals\nSupport the development and implementation on corporate communications strategies to enhance the company's image among international media outlets\nDevelop and maintain lines of communication with media and external stakeholders across government, community, public, NGOs e.t.c\nOverseas the production of PR materials including collaterals, press releases, and other communications documents\nAssist in crisis management communications as need arise\n\nJob Requirements\n\nBachelor degree holder in journalism/ public relations / communications or related discipline\nWith a minimum of 4 years public relations experience in large corporate\nCandidates with experience in internet, technology, Fintech is preferable\nExcellent interpersonal, communications and presentation skills are required\nExcellent spoken and written English, Mandarin and Cantonese is mandatory\nAble to work under pressure in a dynamic environment\n\nInterested individuals can click apply now and send through updated resume in WORD format. For a more comprehensive list of current opportunities, please visit www.connectedgroup.com\n\n#StayConnected", "employment_types": ["Full Time", "Permanent"], "selling_points": ["Public Relations - Financial", "5 Days Work/ Bank Holiday", "12 -15 Days AL/B-day Leave/Medical&Life Insurance"], "locations": ["Admiralty"], "categories": ["Marketing / Public Relations", "Public Relations - Copy-writing", "Public Relations - Event Management", "Public Relations - General / Support"], "post_time": "2022-01-14T09:01:01Z", "salary": {"currency": null, "max": null, "min": null, "period": "monthly", "term": null}, "salary_visible": false, "title_keywords": ["senior consultant", "consultant"], "responsibilities": ["implementation", "develop", "communication", "maintain", "crisis management"], "requirements": {"degrees": ["bachelor degree holder"], "majors": ["journalism", "communications"], "languages": ["cantonese", "english", "mandarin"], "language_level": ["excellent"], "hard_skills": ["dynamic", "word"], "soft_skills": ["dynamic environment", "presentation skills", "comprehensive", "interpersonal", "work under pressure"], "languages_combined": [{"language": "cantonese", "language_level": ["excellent"]}, {"language": "english", "language_level": ["excellent"]}, {"language": "mandarin", "language_level": ["excellent"]}]}, "experience_required": {"duration": ["minimum of 4 years"], "field": ["public relations"]}}, {"job_id": "100003009046872", "location_code": "hk", "company": "ConnectedGroup Limited", "job_title": "Public Relations Manager, Tech (Global)", "description": "Curiosity. Vision. Drive. Integrity. At BCW (Burson Cohn & Wolfe), we\u2019re an integrated communications agency of thinkers, futurists, technologists and makers who come together to create powerful connections spanning every industry, discipline and culture on the planet. Here in APAC, BCW follows a people-first strategy where we focus on recruiting and retaining the best talent, upskilling our team, and instilling a culture of learning, collaboration, winning and having fun.\n\nAs an Account Manager, you are expected to support day-to-day client activities and provide guidance to junior team members through ongoing counsel and effective delegation. You will contribute to BCW\u2019s performance by managing client relationships and integrated communication (IC) programs, satisfying and delighting clients, helping, generate new business and growing existing accounts.\u00a0 You are required to support our corporate strategy and your practice or office to help ensure superior client service, a winning culture and profitability.\n\nCORE JOB RESPONSIBILITIES\n\nStay current on your clients\u2019 businesses, industries and competitors and use your knowledge to develop comprehensive, strategic and integrated communications programs that complement the client\u2019s business objectives and deliver results\nAct as a day-to-day client leader and maintain a clear and consistent communication channel between the client and the account team\nBe actively involved and oversee quality implementation for one or a group of accounts within time and budget constraints\nHave strong verbal and written communication skills including development of various types of materials such as Q&A, key messages, holding statements, press releases etc.\nBe able to support the senior managers and leaders in resolving client issues\nMaintain a strong rapport with journalists/bloggers/media members who cover your clients\u2019 industries and businesses to optimize channels.\u00a0\nHelp develop media strategies, write pitch letters and respond to media queries\nStay updated on social media channels, trends and analytical tools and make recommendations to strengthen our capabilities\nSupport the Directors and other senior leaders to identify new business opportunities within existing and potential clients\nBe proactive during new business brainstorms and take ownership of portions of new business proposals under the guidance of Directors and senior leaders\nManage client relationships and be the client\u2019s key contact, counselor and strategic thinker\n\nJOB REQUIREMENTS\n\nWith 4-6 years of experience in working in an international agency environment\nExperienced in MNC and China global company is an advantage\nExperienced in handling regional/global technology and media\nProficiency in English and Mandarin is a must", "employment_types": ["Full Time", "Permanent"], "selling_points": ["Fast-growing technology company", "Full Suite PR", "Fast paced, dynamic"], "locations": ["Not Specified"], "categories": ["Marketing / Public Relations", "Public Relations - Copy-writing", "Public Relations - Event Management", "Public Relations - General / Support"], "post_time": "2022-01-14T01:32:59Z", "salary": {"currency": null, "max": null, "min": null, "period": "monthly", "term": null}, "salary_visible": false, "title_keywords": ["manager"], "responsibilities": ["make recommendations", "social media", "guidance", "business opportunities", "budget", "quality", "implementation", "letters", "develop", "communication", "maintain", "contact"], "requirements": {"degrees": [], "majors": [], "languages": ["english", "mandarin"], "language_level": ["proficiency"], "hard_skills": [], "soft_skills": [], "languages_combined": [{"language": "english", "language_level": ["proficiency"]}, {"language": "mandarin", "language_level": ["proficiency"]}]}, "experience_required": {"duration": ["4-6 years"], "field": ["agency"]}}, {"job_id": "100003009043622", "location_code": "hk", "company": "Burson-Marsteller (Hong Kong) Limited", "job_title": "PR Account Manager", "description": "At Neat, we\u2019re building a solution that\u2019s friendlier, faster, more modern than a bank. We have users in over 100 countries around the globe, relying on our solutions to manage their business finances.\n\nWant to help us achieve this vision? We\u2019ve built a place where you\u2019ll love doing it!\n\nOur culture of transparency and openness means you\u2019ll have lots of impacts, our test-driven development approach means we move quickly while maintaining super high standards for quality of code and design, and our commitment to your professional growth means you\u2019ll always be learning.\n\nWe are currently looking for a creative\u00a0Senior Digital Content Specialist\u00a0who is dedicated to crafting excellent original content, reviewing and translating existing copy inline with brand guidelines. You will work with the design and product teams others to better understand our customers and their needs expectations, produce content with the needs of us in mind, participate in the brainstorming process, and conduct research to develop or support writing for blog posts, marketing campaigns, and any social media channels. You should also be prepared to assist with other creative processes, such as the visual element selection process.\n\nWhat You\u2019ll Be Doing:\n\nAccountable for content marketing initiatives to drive traffic and engagement that leads to sales and customer retention.\nCollaborates across functions to deliver effective content marketing campaigns and to meet business objectives\nCreate the content our audience is looking for and optimise the path to conversion\nDevelop content with our brand voice to improve SEO.\nKey distribution channels management, including email/newsletter and core social media (Linkedin, Facebook, Instagram), which content and approaches work on each.\nMaking sure our content styles are aligned across different platforms/departments.\nAssisting in other aspects of the creative or research processes to create cohesive, accurate content.\nHelping with bilingual translation when necessary.\nWe\u2019re Looking For:\u00a0\n\nBachelor\u2019s degree in English, Communications, Translations or related field.\nPrior digital content marketing / copywriter experience gained in eCommerce, technology, or start-up environments.\nExperience creating content for the web and growing a social audience\nBasic understanding or experience with SEO, WordPress, Google Analytics, MailChimp and social media channels (Linkedin, Facebook, Instagram).\nProject management experience with collaborating with a wide range of stakeholders from many teams and functions in a fast-paced environment.\nExcellent communication skills (both written and verbal) in Traditional Chinese and English.\nCandidates with less experience shall be considered as Digital Content Specialist.\nWhat Happens Next?\n\nIf your application is successful, you'll be contacted by our Talent & Culture Team to take part in a video screening and psychometric assessment. If you are a good fit, you will be invited to a video / in person interview with the hiring manager, department head and even some of your colleagues. Lastly, ending the interview process with a culture fit chat with our senior management.\n\nCandidates not contacted within 4 weeks may consider their application unsuccessful. Information provided will be treated in strict confidence and will only be used for recruitment-related purposes. Personal data provided by job applicants will be used strictly in accordance with the employer's personal data policies, a copy of which will be provided immediately upon request.\n\nInterested In Joining Us?\n\nClick here to apply now.", "employment_types": ["Full Time"], "selling_points": ["4-6 years of experience in an international agency", "Experienced in MNC and China global company", "Strong in APAC media relations"], "locations": ["Quarry Bay"], "categories": ["Media & Advertising", "Account Servicing", "Marketing / Public Relations", "Public Relations - Copy-writing", "Public Relations - General / Support"], "post_time": "2022-01-13T00:53:55Z", "salary": {"currency": null, "max": null, "min": null, "period": "monthly", "term": null}, "salary_visible": false, "title_keywords": ["account manager"], "responsibilities": ["quality", "design", "communication", "brand guidelines", "facebook", "personal data", "senior management", "conduct research", "maintaining", "teams", "develop", "marketing campaigns", "visual", "social media", "management", "seo", "policies", "project management", "recruitment"], "requirements": {"degrees": ["degree", "bachelor"], "majors": ["communications"], "languages": ["english", "chinese"], "language_level": ["excellent"], "hard_skills": ["google analytics", "seo", "basic", "web", "project management", "wordpress", "code", "facebook", "translation"], "soft_skills": ["communication skills", "confidence", "accurate", "fast-paced environment", "interested in", "accountable", "cohesive", "project management", "learning", "creative", "driven"], "languages_combined": [{"language": "english", "language_level": ["excellent"]}, {"language": "chinese", "language_level": ["excellent"]}]}, "experience_required": {"duration": [], "field": ["ecommerce", "social media", "digital content", "project management", "marketing"]}}, {"job_id": "100003009038462", "location_code": "hk", "company": "Neat Limited", "job_title": "Senior Digital Content Specialist", "description": "The Role:\nCurrently, we are hiring an Assistant Manager \u2013 Influencer Marketing for our most prestigious skincare brand. This role will develop the overall influential marketing strategy and work closely with internal and external stakeholders, especially leading multi-agencies to develop prestige brand image and translate into business results.\n\nReports to: Associate Director - Marketing\n\nJob Responsibilities:\n\nDevelop brand core communication message strategy that elevates the brand equity both for internal and external communication\nDevelop influential marketing strategy & plan that roll-out year-round including roll-out localize global initiative; long term influencer engagement plan; media pitching plan both offline & online\nDevelop SEO strategy & plan that translate engagement plan into direct business results. Including content marketing plan; identify bloggers/ vloggers engagement plan and design digital customer journey that build customer consideration and closure result\nEstablish and maintain good relationships with both print and digital media, digital influencers, bloggers and identify engagement strategies that enable long term brand equity building\nPlan and implement engagement plan including PR events; campaigns launch engagement; year-round pitching, product seeding, press-kit preparation; content development with bloggers/ vloggers.\nAccountable & monitor SEO and assisted conversion result\nPrepare regular PR reports and general PR administrative duties\nLiaise with external parties, such as production house, press and PR agencies on media pitching to generate substantial coverage on both print and digital platforms\n\nJob Requirements:\n\nDegree holder in Journalism/ Public Relations/ Communications or relevant disciplines\nMinimum 5 years experience in media/ public relations agency with experience in cosmetics field/ luxury industry\nGood command of both written and spoken Chinese and English\nProficient in MS Office applications and Chinese word processing\nStrong media and KOL network\nContent marketing and SEO management experience is preferred\nPR savvy, with a strong passion for the beauty industry\nExcellent communication and interpersonal skills\nOutgoing, proactive, self-motivated and good team player\n\nWhat's on offer:\n\nBe part of a growing global organization with a portfolio of around 16 brands, competitive discretionary bonus, quarterly free goods across brands, medical benefits, birthday leave, flexible working hours, wellness program, learning sponsorship, and more.\u00a0\n\nInterested?\n\nPlease apply with your latest resume stating your notice period, current and expected remuneration package.\u00a0\n\nWe regret that only shortlisted candidates will be contacted.\u00a0\n\nShiseido Hong Kong is an Equal Opportunities Employer. All applications received will be treated in strict confidentiality and be used exclusively for employment purposes only.\u00a0", "employment_types": ["Full Time"], "selling_points": ["Fast-Growing Multicultural Fintech Startup", "Prior Digital Content Marketing / Copywriter Exp", "Flat Structure, Empowerment and Work-Life Balance"], "locations": ["Admiralty"], "categories": ["Marketing / Public Relations", "Marketing - Marketing Communication", "Public Relations - Copy-writing", "Digital Marketing"], "post_time": "2022-01-11T06:58:49Z", "salary": {"currency": null, "max": null, "min": null, "period": "monthly", "term": null}, "salary_visible": false, "title_keywords": ["specialist"], "responsibilities": ["seo", "external parties", "monitor", "design", "develop", "communication", "marketing plan", "maintain", "reports", "administrative duties", "plan", "liaise with"], "requirements": {"degrees": ["degree holder"], "majors": ["journalism", "communications"], "languages": ["english", "chinese"], "language_level": ["good command", "proficient"], "hard_skills": ["seo", "luxury industry", "chinese word processing", "ms office"], "soft_skills": ["outgoing", "flexible", "self-motivated", "good team player", "passion for", "communication and interpersonal skills", "learning", "proactive"], "languages_combined": [{"language": "english", "language_level": ["good command"]}, {"language": "chinese", "language_level": ["good command", "proficient"]}]}, "experience_required": {"duration": ["minimum 5 years"], "field": ["management", "public relations", "agency", "marketing", "media"]}}, {"job_id": "100003009033347", "location_code": "hk", "company": "Chandler Macleod Group (HK) Limited", "job_title": "Copywriter (Professional Service/ Beauty/ Retail)", "description": "SPRG is a leading, award winning and caring public relations group with headquarters in Hong Kong and operation overseas. The right candidate will be working for our clients that are listed or ready-to-list on the stock exchanges, to implement their ongoing investor relations and media relations campaigns\u00a0and IPO communications programs.\n\n\u00a0General Requirements:\n\nUniversity graduate, preferably in business, finance, translation or journalism disciplines\nAssociate: Fresh graduate is considered.\nSenior Associate: 2+\u00a0years of experience in the financial PR industry\nAlso preferable with financial media background\nExcellent command in both written and spoken English\u00a0and Chinese\nMandarin proficiency is preferred\nGood writing skill and sophisticated in PowerPoint and\u00a0other computer softwares\nPleasant and mature personality, strong interpersonal and problem solving skills, logical thinking and detail-minded\nInterested parties please complete the standard application form by clicking the\u00a0Apply now\u00a0button. You can also attach your tailored CV and Cover letter with your current and expected salary which we will use to review applications.\n\n\n\u00a0It is Our Company policy to comply with the requirements of the Personal Data (Privacy) Ordinance (Cap. 486) of the Laws of the Hong Kong Special Administrative Region. Any personal data which is collected shall be handled in accordance with this Personal Information Collection Statement (\u201cPICS\u201d).\n\nThe personal data collected from you will be used for purposes relating to your application for employment with the Company. You must ensure that all personal data provided to the Company are accurate, complete and up-to-date. For correction of or access to personal data after submission of the job application or enquiries on recruitment matters, please contact the HR or subject officer as specified in the recruitment advertisement.\n\nWebsite:\u00a0\u00a0www.sprg.com.hk\u00a0/\u00a0www.sprg.asia\n\nFacebook:\u00a0\u00a0https://www.facebook.com/SPRGAsia /\u00a0https://www.facebook.com/CSR.SPRG", "employment_types": ["Full Time", "Permanent"], "selling_points": ["Multinational Working Environment", "Genuine Development Opportunity", "A Growing Business"], "locations": ["Not Specified"], "categories": ["Marketing / Public Relations", "Marketing - Marketing Communication", "Public Relations - Copy-writing", "Digital Marketing"], "post_time": "2022-01-09T10:33:06Z", "salary": {"currency": null, "max": null, "min": null, "period": "monthly", "term": null}, "salary_visible": false, "title_keywords": ["copywriter"], "responsibilities": [], "requirements": {"degrees": ["university graduate", "fresh graduate"], "majors": ["journalism", "finance", "business"], "languages": ["english", "chinese", "mandarin"], "language_level": ["excellent", "proficiency"], "hard_skills": ["translation", "problem solving skills", "powerpoint", "writing skill"], "soft_skills": ["sophisticated", "detail-minded", "mature", "pleasant", "writing skill", "problem solving skills", "interpersonal"], "languages_combined": [{"language": "english", "language_level": ["excellent"]}, {"language": "chinese", "language_level": ["excellent"]}, {"language": "mandarin", "language_level": ["proficiency"]}]}, "experience_required": {"duration": ["2+ years"], "field": ["pr", "financial"]}}, {"job_id": "100003009049645", "location_code": "hk", "company": "Strategic Financial Relations (China) Ltd.", "job_title": "Associate / Senior Associate (Financial PR - Fresh Graduate Welcomed)", "description": "Responsibilities:\u00a0\n\n\nAchieve account servicing and person in charge of handling enquires, routine and ad hoc projects\nConduct comprehensive industry research and market news for both IPO and Retainers clients\nManage various financial communications/investor relations events and ensure a smooth run of events/projects from venue sourcing, negotiation, logistics, and on-site support\nAssist in the development of various corporate presentations and marketing materials including press release, results announcement, interim report, newsletters, and other online materials\nSustain strong relations with media, investors and other third parties\n\nRequirements:\n\nUniversity degree holder in Journalism, Communications, Finance, Economics, and other business-related disciplines\n3 years or above relevant experience in financial communications/media/ investor-relations/ event management, solid experience from a PR agency will be an added advantage\nStrong analysis skills in financial markets and familiar with IPO flow\nProficiency in using MS Excel and PowerPoint is a must\nEssential to have good speaking and writing skills both in Chinese and English\nIndependent, team spirit, proactive and strong interpersonal skills\nTeamwork, integrity and a strong sense of responsibility\nCandidate with less experience will be considered as a junior position\n\nWe offer\n\nPromote internal growth and structured career prospects\nDynamic and team-based working environment\n5-day work\nRemuneration and benefits package for the right candidates\nMPF and medical insurance\n\nInterested candidates, please send your full resume and expected salary to HR Department, 40/F, China Online Centre,\u00a0333 Lockhart Road, Wan Chai, Hong Kong, or by\u00a0clicking \"Apply Now\".", "employment_types": ["Full Time", "Permanent"], "selling_points": ["Public Relations - Financial", "5 Days Work / Bank Holiday", "12 Days AL/B-day Leave/Medical&Life Insurance"], "locations": ["Admiralty"], "categories": ["Marketing / Public Relations", "Public Relations - Copy-writing", "Public Relations - General / Support", "Others"], "post_time": "2022-01-14T09:01:00Z", "salary": {"currency": null, "max": null, "min": null, "period": "monthly", "term": null}, "salary_visible": false, "title_keywords": ["senior associate", "associate"], "responsibilities": ["presentations", "logistics", "ad hoc projects", "marketing materials", "report"], "requirements": {"degrees": ["university degree"], "majors": ["finance", "economics", "journalism", "related disciplines", "business", "communications"], "languages": ["english", "chinese"], "language_level": ["good"], "hard_skills": ["analysis", "ms excel", "powerpoint", "writing skills"], "soft_skills": ["team spirit", "independent", "sense of responsibility", "teamwork", "integrity", "writing skills", "interpersonal skills", "proactive"], "languages_combined": [{"language": "english", "language_level": ["good"]}, {"language": "chinese", "language_level": ["good"]}]}, "experience_required": {"duration": ["3 years"], "field": ["management", "pr", "agency", "relevant experience", "media", "financial"]}}, {"job_id": "100003009036219", "location_code": "hk", "company": "Seven Senses Game Company Limited", "job_title": "Social Media Manager", "description": "Responsibilities:\n\nManage Social Media\u00a0\nCreative Engaging Contents for Different Social Media Platforms and Marketing Campaigns\nHelp Grow Social Media Account Followers\nInvolve in Various Marketing Campaign\nHandle ad-hoc Tasks When Necessary\n\nRequirements:\n\nHigher Diploma or Above in\u00a0Social Media Content Writing or Digital Marketing\nAt Least 2+ year Experience in\u00a0Copywriting Experience in Writing\nGood Command of English and Chinese Copywriting\nGood Team Player and Responsible \u00a0\nDetail-Oriented, Fast Learner and Willing to Face Challenges\nImmediate\u00a0Availability is Preferred\nKnowledge in NFT and Crypto Currency is a Must", "employment_types": ["Full Time", "Permanent"], "selling_points": ["Crypto Industry", "Metaverse / NFT Project", "Min 2+ years\u2019 Experience in Digital Marketing"], "locations": ["Kwun Tong Area"], "categories": ["Marketing / Public Relations", "Marketing - Market Research", "Public Relations - Copy-writing", "Digital Marketing"], "post_time": "2022-01-11T09:57:46Z", "salary": {"currency": null, "max": null, "min": null, "period": "monthly", "term": null}, "salary_visible": false, "title_keywords": ["manager"], "responsibilities": ["social media", "ad-hoc tasks", "social media platforms", "marketing campaigns", "contents"], "requirements": {"degrees": ["higher diploma or above"], "majors": ["digital marketing"], "languages": ["english", "chinese"], "language_level": ["good command"], "hard_skills": ["crypto currency"], "soft_skills": ["good team player", "fast learner", "responsible", "detail-oriented"], "languages_combined": [{"language": "english", "language_level": ["good command"]}, {"language": "chinese", "language_level": ["good command"]}]}, "experience_required": {"duration": ["at least 2+ year"], "field": ["copywriting", "writing"]}}, {"job_id": "100003009033397", "location_code": "hk", "company": "Apegen Limited", "job_title": "Public Relations / Investor Relations Associate - IPO (Sheung Wan)", "description": "Our Client is one of the leading financial services institutions in the market. We are currently hiring a Specialist to join its Communications team.\n\nYou will be reporting directly to the Head of Communications focusing on English writing at corporate level.\n\nResponsibilities:\n\nDesign, prepare and publish contents for a range of marketing and campaign materials, i.e. senior executive speeches, brochures, newsletters, annual report sections, digital channels, etc.\nWrite, edit and proof-read of a variety of internal communications for strategic targets\nWork closely with other internal parties and provide support to internal messages, such as press releases, Q&A documents, etc.\nCreate and maintain specific writing guidelines to ensure brand consistency and accuracy\nPerform other ad-hoc projects\n\nRequirements:\n\nBachelor's Degree in English, Communications or Journalism is preferred\nAt least 8 years of experience as a professional writer (English) and/or editor (English) within large organizations, journalists are also welcomed\nStrong communication and interpersonal skills, with good storytelling skills\nExcellent writing/editorial skills with proven portfolio\nExperience working in finance related content a plus\n\nFor those who are interested, please submit your latest profile (in WORD Format) to raman.hong@connectedgroup.com. Only qualified candidates will be contacted.\n\nFor more job opportunities, please visit our web-site: www.connectedgroup.com.", "employment_types": ["Full Time", "Permanent"], "selling_points": ["Sheung Wan working location with 5 day work", "Extremely busy & Dynamic Work every day", "To meet interesting every day"], "locations": ["Sheung Wan"], "categories": ["Banking / Finance", "Investment", "Professional Services", "Business Analysis / Data Analysis", "Marketing / Public Relations", "Public Relations - Copy-writing"], "post_time": "2022-01-09T16:25:54Z", "salary": {"currency": null, "max": null, "min": null, "period": "monthly", "term": null}, "salary_visible": false, "title_keywords": ["associate"], "responsibilities": ["provide support", "guidelines", "design", "maintain", "contents", "brand consistency", "ad-hoc projects", "internal parties", "report"], "requirements": {"degrees": ["degree", "bachelor"], "majors": ["journalism", "communications"], "languages": ["english"], "language_level": [], "hard_skills": ["plus", "word", "web"], "soft_skills": ["communication and interpersonal skills"], "languages_combined": [{"language": "english", "language_level": []}]}, "experience_required": {"duration": ["at least 8 years"], "field": ["editor", "finance", "related"]}}, {"job_id": "100003009046947", "location_code": "hk", "company": "ConnectedGroup Limited", "job_title": "Japanese Content Writer (12-month Contract)", "description": "Responsibilities:\n\nResponsible for copywriting, editing, proofreading, and translating materials for branding through various channels, e.g. website, blog, newsletters, reports, social media, etc.\nCollaborate closely with the director and existing Japanese team to produce high-class and engaging content\nAssist in writing website content and marketing materials for new and existing foreign exchange broker partners for business purpose\nImplement SEO best practices in relation to content creation and website maintenance\nPerform other ad-hoc duties for business promotion\n\nRequirements:\n\nBachelor's Degree in marketing, media, journalism or related discipline\nMinimum 2 years of experience in content management and performance marketing\nHigh proficiency in Japanese and English\nProficiency in CMS, i.e. WordPress\nPrevious experience as a Japanese content writer is a PLUS\nPrevious experience in foreign exchange or financial services is a PLUS\n\nFor those who are interested, please submit your latest profile (in WORD Format) to raman.hong@connectedgroup.com. Only qualified candidates will be contacted.\n\nFor more job opportunities, please visit our web-site: www.connectedgroup.com.", "employment_types": ["Full Time", "Contract"], "selling_points": ["Expanding Global Consultancy", "Flexible Working Hours", "Fully Remote"], "locations": ["Not Specified"], "categories": ["Marketing / Public Relations", "Marketing - Brand / Product Management", "Marketing - Marketing Communication", "Public Relations - Copy-writing"], "post_time": "2022-01-14T01:50:00Z", "salary": {"currency": null, "max": null, "min": null, "period": "monthly", "term": null}, "salary_visible": false, "title_keywords": ["content writer"], "responsibilities": ["collaborate", "social media", "seo", "website", "website maintenance", "proofreading", "reports", "ad-hoc duties", "marketing materials", "editing"], "requirements": {"degrees": ["degree", "bachelor"], "majors": ["journalism", "marketing"], "languages": ["japanese", "english"], "language_level": ["proficiency"], "hard_skills": ["plus", "web", "word", "wordpress", "exchange"], "soft_skills": [], "languages_combined": [{"language": "japanese", "language_level": ["proficiency"]}, {"language": "english", "language_level": ["proficiency"]}]}, "experience_required": {"duration": ["minimum 2 years"], "field": ["management", "marketing", "financial services"]}}, {"job_id": "100003009035104", "location_code": "hk", "company": "Ocean Park Corporation", "job_title": "Public Affairs Officer", "description": "Responsibilities\n\n(Long Term Contract)\n\nThe incumbent will assist in the implementation of a broad array of public relations activities, which range from media pitches, interviews, editorial shoots, KOL experience sessions, familiarisation tours, launch events to CSR programmes, and more. Key tasks include translation, writing, media tracking, report compilation, coordination of press photography and filming, and liaison with internal and external parties for information gathering, invitations, logistic arrangements and production items. He/she will also provide administrative support to the team.\n\nRequirements\n\n\nUniversity degree\nAt least\u00a02 years of experience in public relations, journalism or marketing communications\nExcellent command of English and Chinese, both written and spoken\nExperience in media relations, social media outreach and KOL coordination\nExperience in event, photography, video and design coordination\nAbility to produce news-friendly copy, media analysis and accurate reports\nAbility to create social media videos would be an advantage\nExcellent attention to detail\nAvailable to work on weekends or public holidays for ad hoc assignments\n\nApplications including details of qualifications, working experience, expected salary, contact telephone number and address should be applied via:\u00a0http://careers.oceanpark.com.hk\u00a0--> Job opening --> Full time/ Long-term.\n\nApplicants not contacted within six weeks may consider their application unsuccessful. Personal data collected will be used for recruitment-related purpose only.", "employment_types": ["Full Time", "Contract"], "selling_points": ["Assist in the implementation of public relations", "2 years of experience in public relations", "Experience in media relations"], "locations": ["Aberdeen"], "categories": ["Marketing / Public Relations", "Public Relations - Copy-writing", "Public Relations - Event Management", "Public Relations - General / Support"], "post_time": "2022-01-10T05:59:55Z", "salary": {"currency": null, "max": null, "min": null, "period": "monthly", "term": null}, "salary_visible": false, "title_keywords": ["officer"], "responsibilities": ["tracking", "internal and external parties", "implementation", "coordination", "provide administrative support", "report"], "requirements": {"degrees": ["university degree"], "majors": [], "languages": ["english", "chinese"], "language_level": ["excellent"], "hard_skills": ["analysis"], "soft_skills": ["accurate", "friendly", "attention to detail", "coordination"], "languages_combined": [{"language": "english", "language_level": ["excellent"]}, {"language": "chinese", "language_level": ["excellent"]}]}, "experience_required": {"duration": ["at least 2 years"], "field": ["social media", "public relations", "video", "design", "marketing communications", "media"]}}, {"job_id": "100003009035665", "location_code": "hk", "company": "The Hong Kong Children's Choir", "job_title": "Executive (English Editor)", "description": "The Job:\n\nProvide full secretarial and administrative support\nResponsible for drafting of notices, press release, minutes and website articles in English and Chinese\nProduction of house programmes and posters\nAssist to organize and promote different performances and events\nPerform miscellaneous assignments and handle ad hoc duties as required\n5-day Work from Mondays to Sundays\n\nThe Person:\n\nDegree, major in English, English Literature or Translation preferred\nAt least 2 years of relevant working experience in editorial or copywriting\nExcellent command of written and spoken English, Chinese and Mandarin\nGood team player, independent, meticulous and attentive to details\nSelf-motivated, possess excellent interpersonal and communication skills\nExperience in graphic design, print production or related field preferred\nExperience in arts administration would be an advantage\nInterested parties please\u00a0send us\u00a0full resume stating current and expected salary and available date\u00a0by\u00a0clicking \"Apply Now\".\n\nPersonal data collected will be used for recruitment purpose only.", "employment_types": ["Full Time", "Permanent"], "selling_points": [], "locations": ["Mong Kok"], "categories": ["Media & Advertising", "Editorial / Journalism", "Marketing / Public Relations", "Public Relations - Copy-writing", "Professional Services", "Translation"], "post_time": "2022-01-10T08:04:38Z", "salary": {"currency": null, "max": null, "min": null, "period": "monthly", "term": null}, "salary_visible": false, "title_keywords": ["editor", "executive"], "responsibilities": ["ad hoc duties", "website", "administrative support"], "requirements": {"degrees": ["degree"], "majors": [], "languages": ["english", "chinese", "mandarin"], "language_level": ["excellent"], "hard_skills": ["translation"], "soft_skills": ["meticulous", "good team player", "self-motivated", "independent", "communication skills", "attentive to details", "interpersonal"], "languages_combined": [{"language": "english", "language_level": ["excellent"]}, {"language": "chinese", "language_level": ["excellent"]}, {"language": "mandarin", "language_level": ["excellent"]}]}, "experience_required": {"duration": ["at least 2 years"], "field": ["related", "graphic design", "print", "relevant working experience", "editorial", "copywriting", "administration"]}}, {"job_id": "100003009042631", "location_code": "hk", "company": "ePropulsion Technology Limited", "job_title": "Digital Marketing and Planning Manager", "description": "Role Purpose:\n\nThis role work is highly collaborative. You are able to bring together the different functions (such as product marketing, digital specialists, content, and creative teams), aligning all the groups whose work contributes to a successful program or campaign. Aims to ensure the ePropulsion is communicating the right messaging to attract prospective customers and retain existing ones.\n\nWhat you\u2019ll get from working at ePropulsion:\n\nCompetitive compensation and benefits, 13-months' salary!\nComprehensive Medical insurance coverage, including specialist and Chinese Medicine Practitioner, Bonesetter, and Acupuncture Consultation!\nFive-day work, bank holiday!\nBirthday surprise!\nFlexible working locations!\nFree afternoon tea, drinks, and snacks sharing!\nInternational exposure in your career and build a global interpersonal network!\nA typical day in this Role:\u00a0\n\nDevelop overall digital marketing and content strategies aligned with the company\u2019s business goals.\nPlan, execute and track digital marketing projects including SEO, SEM, content marketing, email marketing, social media marketing, and influencer marketing.\nManage the internal team and external agencies/vendors to drive website traffic, lead acquisition and improve conversion.\nLiaise with external stakeholders to gather content and high-quality assets that can be relayed online (including our global distributors and media partners).\nClose co-operation with in-house designers, content specialists, and external producers. To create and deliver high-standard content, such as visuals, copy, videos, webpages, and other necessary marketing collaterals within budgets and deadlines.\nMonitor and listen actively on Social Community to analyze engagement, reach, comments, and sentiment.\nDevelop tracking and monitoring system to ensure KPIs are achieving targets, conduct analysis, and learn from data and reports.\nReview new technologies, platforms, and approaches and be at the forefront of trends in digital marketing.\nDesign service details and negotiate contracts with varied vendors, media partners, agencies, and influencers and monitor their deliverables and effectiveness throughout.\nPerform as an HK marketing team leader and report to Marketing Director.\nWhat we look for:\u00a0\u00a0\n\nBachelor\u2019s Degree or above in Marketing, Communications, Journalism, Translation, PR, or other relevant discipline(s).\n5 years or above of solid experience in the digital marketing field preferably in digital planning/ content marketing, with a minimum of 2 years at the managerial level.\nCapability to proofread the content produced by the specialist and all the content to be published in the Company's social media accounts.\nExperience managing external digital media agencies, content contributors, and IT vendors is preferred.\nTrack record in managing social media community and curating engagement campaigns, particularly Facebook groups engaging a worldwide audience.\nExperience in partnering with external influencers/ KOLs remotely (such as in the US and Europe).\nExcellent communication, coaching, and leadership skills.\nAbility to manage multiple projects and present ideas to executives and manage expectations of stakeholders.\nCreative, self-motivated, and strong team spirit with a customer-center mindset.\nProficient in written and spoken English, Cantonese, and Mandarin.\nWilling to have PRC business trips occasionally.\nPotential talent with less experience would be considered as Digital Marketing and Planning Specialist.\nIdeally, you\u2019ll also have:\n\nKnowledge of media tracking implementation, such as Hootsuite.\nInterest in technological development and sustainable energy.\nPassionate boating/ sailing/ marine industry.\nWe are an equal opportunity employer and welcome applications from all qualified candidates. The information provided will be treated in strict confidence and be used only for consideration of your application for relevant/similar posts within the ePropulsion.\n\n\nApplicants not hearing from us within 6 weeks from the date of advertisement may consider their applications unsuccessful. All personal data of unsuccessful applicants will be destroyed within 12 months from the date of application.\n\nhttp://www.epropulsion.com", "employment_types": ["Full Time", "Permanent"], "selling_points": ["5 years in digital planning/ content marketing", "Manage social media community & curating campaigns", "Capability to proofread the English content"], "locations": ["Not Specified"], "categories": ["Marketing / Public Relations", "Marketing - Marketing Communication", "Public Relations - Copy-writing", "Digital Marketing"], "post_time": "2022-01-12T08:14:35Z", "salary": {"currency": null, "max": null, "min": null, "period": "monthly", "term": null}, "salary_visible": false, "title_keywords": ["manager", "digital marketing"], "responsibilities": ["teams"], "requirements": {"degrees": [], "majors": [], "languages": [], "language_level": [], "hard_skills": [], "soft_skills": ["creative", "collaborative"], "languages_combined": []}, "experience_required": {"duration": [], "field": []}}, {"job_id": "100003009037726", "location_code": "hk", "company": "OVO Limited", "job_title": "Marketing Executive", "description": "we are looking for high calibre candidates to\u2026\n\ndevelop digital marketing strategies and campaigns to achieve traffic\u00a0and business goals, monitor GA, SEO etc performance.\nmaintain website content up-tp-date.\nmanage and create content for online platforms (e.g. Website, Social Media, display advertising and digital campaigns) to achieve marketing objectives and to enable smooth collaborations.\ncoordinate with internal departments for campaigns & promotions.\nsupport various tasks in marketing department, including but not limited to POPs preparation etc.\n\n\n\nwelcome to our team if you are\u2026\n\ndiploma\u00a0in Business, or related disciplines\naround 1-2 years of relevant experience, knowledge in GA, SEO is definitely an advantage\nstrong communication and presentation skills\ndesign skills for Illustrator and Photoshop would be an advantage\nexcellent in handling and follow up on details, take initiative, independent & responsible\nfluent in both written and spoken English, Cantonese and Mandarin\n\nwe offer...\u00a0\n\ncompetitive\u00a0pay\ndouble pay\n5 days work\nat least 12 days of annual leave\nmedical benefit\nbirthday leave\nMPF\non-the-job training\nbank holiday\nstaff purchase discount\n\nInterested candidates please email FULL RESUME with SALARY EXPECTATION and AVAILABILITY to us.\u00a0Let's know more about us at www.ovo.com.hk\u00a0\n\nPersonal data collected will be used for recruitment purpose only.", "employment_types": ["Full Time", "Permanent"], "selling_points": ["5 days work with double pay", "dynamic working environment", "Location: Ngau Tau Kok (5 mins from MTR)"], "locations": ["Ngau Tau Kok"], "categories": ["Marketing / Public Relations", "Marketing - Brand / Product Management", "Public Relations - Copy-writing", "Digital Marketing"], "post_time": "2022-01-11T03:38:39Z", "salary": {"currency": null, "max": null, "min": null, "period": "monthly", "term": null}, "salary_visible": false, "title_keywords": ["marketing executive"], "responsibilities": ["social media", "business goals", "seo", "digital marketing strategies", "advertising", "monitor", "website", "coordinate with", "develop", "communication", "design", "maintain", "digital campaigns"], "requirements": {"degrees": ["diploma"], "majors": ["related disciplines", "business"], "languages": ["cantonese", "english", "mandarin"], "language_level": ["fluent"], "hard_skills": ["seo", "illustrator", "photoshop"], "soft_skills": ["independent", "responsible", "communication", "presentation skills", "smooth", "initiative"], "languages_combined": [{"language": "cantonese", "language_level": ["fluent"]}, {"language": "english", "language_level": ["fluent"]}, {"language": "mandarin", "language_level": ["fluent"]}]}, "experience_required": {"duration": ["1-2 years"], "field": ["relevant experience"]}}, {"job_id": "100003009044094", "location_code": "hk", "company": "Hong Kong Internet Registration Corporation Limited", "job_title": "Assistant Marketing & Communications Manager / Senior Marketing & Communications Officer", "description": "Responsibilities:\n\nDeveloping corporate and executive communications content, e.g. group speech, PR article in English and Chinese\nCopywriting in English: producing clear, compelling copy for various mediums across all communications channels (e.g. newsletters, interview), with the aim to bring company\u2019s overall vision, strategy and business objectives to life\nCoordinate and execute the sales and marketing strategies for the Company;\nAssist in writing and managing content across all social media platforms: youtube, Facebook and company website and marketing collaterals\nManage company Facebook page, Google Analytic and Adwords, Yahoo and online campaigns;\nHandle and support marketing/PR activities;\nGood interpersonal skills, self-motivated, hardworking & well-organized;\nGood knowledge in Photoshop / Illustrator / Acrobat\n\nRequirement:\n\nDegree holder in Communications, Public Relations, Marketing, Business Studies or related disciplines with minimum 4 years of experience in Communications, PR or marketing.\nSolid experience in Marketing Communication is essential.\nGood written communication skills in English and Chinese, experience in copywriting is a plus;\nAble to meet tight deadline and handle project independently\nSelf-motivated, well-organized and detail-minded;\nGood team player with strong sense of responsibility", "employment_types": ["Full Time", "Permanent"], "selling_points": [], "locations": ["Pok Fu Lam"], "categories": ["Marketing / Public Relations", "Marketing - Brand / Product Management", "Marketing - Marketing Communication", "Public Relations - Copy-writing"], "post_time": "2022-01-13T03:02:56Z", "salary": {"currency": null, "max": null, "min": null, "period": "monthly", "term": null}, "salary_visible": false, "title_keywords": ["manager", "communications officer", "assistant"], "responsibilities": ["marketing strategies", "social media platforms", "marketing collaterals", "developing", "coordinate", "facebook", "company website"], "requirements": {"degrees": ["degree holder"], "majors": ["business", "related disciplines", "marketing", "communications"], "languages": ["english", "chinese"], "language_level": ["good"], "hard_skills": ["plus"], "soft_skills": ["detail-minded", "communication skills", "self-motivated", "independently", "good team player", "sense of responsibility", "well-organized", "communication", "meet tight deadline"], "languages_combined": [{"language": "english", "language_level": ["good"]}, {"language": "chinese", "language_level": ["good"]}]}, "experience_required": {"duration": ["minimum 4 years"], "field": ["pr", "public relations", "related", "business", "marketing", "copywriting"]}}, {"job_id": "100003009035122", "location_code": "hk", "company": "Ocean Park Corporation", "job_title": "Public Affairs Manager (Water World)", "description": "Responsibilities\n\n(Long Term Contract)\n\nThe incumbent will be responsible for developing and implementing public relations and public affairs initiatives to create positive perception and word of mouth for Water World. He/she will handle projects, briefings, events and press materials in relation to promotions, corporate communications, stakeholder and influencer engagement, issue management and the Park\u2019s new developments. He/she will craft compelling content, build strong narratives, and formulate effective outreach strategies to maximise results and influence. He/she will work closely with subject experts and specialists at the Park on a variety of topics and media/social media opportunities to achieve communications goals through cross-functional collaboration.\n\nRequirements\n\nUniversity degree\nAt least 10 years\u2019 experience in public affairs or public relations, with 6 years and above as a team manager\nExcellent command of both written and spoken English and Chinese\nExcellent copywriting and content creation skills\nProven track record in issue management\nAdept at event management\nHands on, agile and able to manage multiple projects effectively in a fast-paced environment\nEnjoys outdoor activities and water sports\nAvailable to work on weekends or public holidays for ad hoc assignments\n\nApplications including details of qualifications, working experience, expected salary, contact telephone number and address should be applied via:\u00a0http://careers.oceanpark.com.hk\u00a0--> Job opening --> Full time/ Long-term.\n\nApplicants not contacted within six weeks may consider their application unsuccessful. Personal data collected will be used for recruitment-related purpose only.", "employment_types": ["Full Time", "Contract"], "selling_points": ["Develop and implement public relations", "10 years\u2019 experience in public affairs", "Enjoys outdoor activities and water sports"], "locations": ["Aberdeen"], "categories": ["Marketing / Public Relations", "Public Relations - Copy-writing", "Public Relations - Event Management", "Public Relations - General / Support"], "post_time": "2022-01-10T06:03:51Z", "salary": {"currency": null, "max": null, "min": null, "period": "monthly", "term": null}, "salary_visible": false, "title_keywords": ["manager"], "responsibilities": ["social media", "management", "developing"], "requirements": {"degrees": ["university degree"], "majors": [], "languages": ["english", "chinese"], "language_level": ["excellent"], "hard_skills": ["agile"], "soft_skills": ["adept", "fast-paced environment", "hands on", "agile"], "languages_combined": [{"language": "english", "language_level": ["excellent"]}, {"language": "chinese", "language_level": ["excellent"]}]}, "experience_required": {"duration": ["at least 10 years", "6 years"], "field": ["public relations", "team"]}}, {"job_id": "100003009035318", "location_code": "hk", "company": "Blockchain Solutions Limited", "job_title": "Script Writer", "description": "Job Description\n\n\n\nDevelop engaging content, edit, translate and proofread the promotional materials for marketing channels (i.e. brochures, press releases, professional bulletins, newsletters, website articles) in line with the brand guidelines and marketing campaigns.\nBe able to create brand story script, tagline and advertising slogan write-up\nEnsure consistency both within and across documents, brands, sub brands and partner\nEnsure projects are completed with high quality and on schedule.\nExcellent English and Chinese writing skills.\nA team player, positive and flexible\nOther ad hoc projects\n\nRequirements:\n\nDegree holder in Business, Marketing Communications, Advertising, Journalism, writing-related major or related disciplines is preferred\n1-2 years of experience in B2B copywriting.\nKnowledge on Finance/ Blockchain or cryptocurrency fields related is a plus\nSharp creative writing skills, conceptual minded and sound editorial judgment\nExperiences in social media, user experience design, and content development is a plus\nExcellent\u00a0command of Chinese and English\nAbility to work collaboratively as well as autonomously\nStrong communication skills\nAble to write in varies style\n\nBenefits\uff1a\n\nPublic Holiday\nMedical Insurance\nAnnual Leave\nDiscretionary Bonus\nMandatory Provident Fund Contribution\nExcellent Training & Career Advancement Opportunities", "employment_types": ["Full Time", "Permanent"], "selling_points": ["5 days work", "Medical Insurance\uff1b Annual Leave", "Flexible working hours"], "locations": ["Shatin Area"], "categories": ["Marketing / Public Relations", "Public Relations - Copy-writing"], "post_time": "2022-01-10T06:48:44Z", "salary": {"currency": null, "max": null, "min": null, "period": "monthly", "term": null}, "salary_visible": false, "title_keywords": [], "responsibilities": ["advertising", "quality", "website", "develop", "promotional materials", "brand guidelines", "schedule", "marketing campaigns", "ad hoc projects"], "requirements": {"degrees": ["degree holder"], "majors": ["marketing communications", "related disciplines", "business", "journalism"], "languages": ["english", "chinese"], "language_level": ["excellent"], "hard_skills": ["blockchain", "plus", "writing skills", "cryptocurrency"], "soft_skills": ["communication skills", "creative", "writing skills"], "languages_combined": [{"language": "english", "language_level": ["excellent"]}, {"language": "chinese", "language_level": ["excellent"]}]}, "experience_required": {"duration": ["1-2 years"], "field": ["copywriting", "social media", "content development", "design"]}}, {"job_id": "100003009037780", "location_code": "hk", "company": "Ray White (Hong Kong) Limited", "job_title": "Marketing Executive (Content)", "description": "Responsibilities:\n\n\n\nResponsible for Strategic planning, implementing and evaluation of marketing programs\nInitiate creative writing for investment events, in-house video contents and social media posts\nImplement and maintain both online and print marketing activities\nSupport sales & marketing activities to generate sales leads\nCollaborate with internal and external parties such as sales, designers, digital specialists, media agencies, etc.\nConduct research to gain access to up-to-date market trends and bring in new ideas to enhance the performance\nHandle ad hoc tasks as per assigned by the Management\n\u00a0\n\nRequirements:\n\nDegree or above in Advertising, Marketing, E-commerce, PR or related discipline\nMore than 3 years' experience in marketing\nStrong marketing sense and attentive to details\nExperience in copy writing in both Chinese and English\nAbility to work in a tight timeline and work well as a team\nIndependent, creative and result oriented\nGood command of both spoken and written English and Chinese\nProficient in MS Office applications including Excel, Word, PowerPoint etc. (Proficient in Adobe software is a bonus)\nExperience in owning personal blog or social media channel for company is a plus\nWorking, education and living experience in Australia or UK is a plus\n\u00a0", "employment_types": ["Full Time"], "selling_points": ["Competitive salary and benefits", "Open and relaxing working environment", "Career development"], "locations": ["Tsim Sha Tsui"], "categories": ["Marketing / Public Relations", "Public Relations - Copy-writing"], "post_time": "2022-01-11T03:51:36Z", "salary": {"currency": null, "max": null, "min": null, "period": "monthly", "term": null}, "salary_visible": false, "title_keywords": ["marketing executive"], "responsibilities": ["collaborate with", "social media", "management", "evaluation", "strategic planning", "support sales & marketing activities", "ideas", "internal and external parties", "ad hoc tasks", "maintain", "generate sales leads", "contents", "conduct research"], "requirements": {"degrees": ["degree or above"], "majors": ["marketing", "e-commerce"], "languages": ["english", "chinese"], "language_level": ["good command"], "hard_skills": ["excel", "plus", "e-commerce", "word", "powerpoint", "adobe software", "ms office"], "soft_skills": ["independent", "marketing sense", "attentive to details", "result oriented", "creative"], "languages_combined": [{"language": "english", "language_level": ["good command"]}, {"language": "chinese", "language_level": ["good command"]}]}, "experience_required": {"duration": ["3 years"], "field": ["social media", "marketing", "writing", "education"]}}, {"job_id": "100003009040300", "location_code": "hk", "company": "The Wing On Department Stores (Hong Kong) Limited", "job_title": "Marketing Officer (Advertising)", "description": "Responsibilities:\n\nDrive, develop and manage marketing strategy\u00a0and media planning\u00a0to increase the brand awareness\u00a0and achieve business targets; responsible for copywriting the promotional materials in line with marketing campaigns\nMonitor and evaluate the performance of marketing initiatives by conducting analysis; increase ROI by optimize media channel\nKeep tracking marketing trends and updates\n\nRequirements:\n\nDegree holders\u00a0in\u00a0Journalism, Communication, Marketing,\u00a0Business Administration or related discipline\nAt least 2-3\u00a0years solid marketing experience in in advertising, digital marketing, digital agency\u00a0or other related fields, background in retail\u00a0industry would be an advantage\n\u00a0Good communication skills,\u00a0creative with strong market sense,\u00a0self-motivated and\u00a0attentive to details\nAble to meet tight deadlines and work\u00a0independently\u00a0under pressure\u00a0in fast paced environment\nGood command of both written and spoken English and Chinese\nImmediate available is preferable\n\nCommensurate remuneration and other fringe benefits will be offered to the right candidate.\u00a0 Interested parties please send your\u00a0full\u00a0resume\u00a0including\u00a0expected salary\u00a0to Human Resources Division, 3/F, Wing On Godown Building, 1 Wang Kee Street, Kowloon Bay, Kowloon, or by click \"APPLY NOW\" button below.\n\n(Candidates not invited for interview within one month may consider their applications filed for future reference.\u00a0 All information collected will be used for recruitment purpose only and will be destroyed after 6 months.)", "employment_types": ["Full Time", "Permanent"], "selling_points": [], "locations": ["Kowloon Bay"], "categories": ["Media & Advertising", "Media Buying", "Marketing / Public Relations", "Public Relations - Copy-writing"], "post_time": "2022-01-12T02:12:27Z", "salary": {"currency": null, "max": null, "min": null, "period": "monthly", "term": null}, "salary_visible": false, "title_keywords": ["marketing officer"], "responsibilities": ["tracking", "analysis", "monitor", "develop", "evaluate", "promotional materials", "marketing campaigns", "planning"], "requirements": {"degrees": ["degree"], "majors": ["journalism", "marketing", "business administration"], "languages": ["english", "chinese"], "language_level": ["good command"], "hard_skills": [], "soft_skills": ["communication skills", "self-motivated", "meet tight deadlines", "work independently", "under pressure", "attentive to details", "communication", "strong market sense", "creative"], "languages_combined": [{"language": "english", "language_level": ["good command"]}, {"language": "chinese", "language_level": ["good command"]}]}, "experience_required": {"duration": ["at least 2-3 years"], "field": ["retail industry", "advertising", "agency", "related", "marketing", "digital marketing", "digital"]}}, {"job_id": "100003009037480", "location_code": "hk", "company": "Poem Communications Limited", "job_title": "Associate Consultant/Associate, Public Relations", "description": "Responsibilities: \u00a0\n\nCoordinate and aid in the preparation of press materials\nStrategize and implement media plan\nMedia pitching and coverage negotiation\nMedia liaison and coordination\nCelebrity sourcing and management\nEvent management\nClient liaison and management\n\nRequirements:\n\nUniversity graduate with major in Public Relations / Marketing / Journalism / Communications\nMinimum 4-5 years relevant experience in Public Relation / Event Management / Media is preferable\nNative English and excellent English writing skills\nFluent spoken in English and Cantonese\nWell-versed in computer applications software\nPresentable, mature, able to make decisions independently\nLess experience will be considered as Associate\n\nInterested candidates, please send your CV with CURRENT &\u00a0EXPECTED SALARY to us.\n\nApplicants not invited for interview within 4 weeks should consider their applications unsuccessful.\u00a0 Applicants\u2019 personal data collected will only be used for the sole purpose of recruitment.\u00a0 The data of unsuccessful applicants will be destroyed within 6 months.\n\nWebsite: www.poemcommunications.com", "employment_types": ["Full Time", "Permanent"], "selling_points": [], "locations": ["Wan Chai"], "categories": ["Marketing / Public Relations", "Marketing - Marketing Communication", "Public Relations - Copy-writing", "Public Relations - Event Management"], "post_time": "2022-01-11T02:55:42Z", "salary": {"currency": null, "max": null, "min": null, "period": "monthly", "term": null}, "salary_visible": false, "title_keywords": ["associate", "consultant"], "responsibilities": ["coordinate", "coordination", "management", "plan"], "requirements": {"degrees": ["university graduate"], "majors": ["journalism", "marketing", "communications"], "languages": ["cantonese", "english"], "language_level": ["native", "excellent", "fluent"], "hard_skills": ["make", "writing skills"], "soft_skills": ["mature", "independently", "writing skills", "presentable"], "languages_combined": [{"language": "cantonese", "language_level": ["fluent"]}, {"language": "english", "language_level": ["native", "excellent", "fluent"]}]}, "experience_required": {"duration": ["minimum 4-5 years"], "field": ["public relation", "management", "relevant experience", "media"]}}, {"job_id": "100003009048974", "location_code": "hk", "company": "Across Asia Communications Limited", "job_title": "Senior Account Executive / Account Executive", "description": "Responsibilities:\nResponsible for execution and follow up of media relations and integrated marketing campaigns\nCopywriting and translation of press release, newsletter and other forms of corporate collateral\nHandle print and multimedia production projects\u00a0\nRequirements:\nDegree holder in Journalism, Language, Business Administration, Finance or Accounting preferred\n1-2 years relevant experience, preferably with media\u00a0\nExcellent command of written and oral English and Mandarin\nFamiliar with Social media,\u00a0MS Powerpoint, Excel and proficiency in Chinese word processing\nMust be detail-minded, meticulous and proactive\nProven communication and organizational skill\nSelf-motivated and able to meet deadline\nGood team player. Able to work independently & catch tight deadline\nImmediate availability is preferable", "employment_types": ["Full Time"], "selling_points": [], "locations": ["Sheung Wan"], "categories": ["Marketing / Public Relations", "Public Relations - Copy-writing", "Public Relations - Event Management", "Public Relations - General / Support"], "post_time": "2022-01-14T07:49:41Z", "salary": {"currency": null, "max": null, "min": null, "period": "monthly", "term": null}, "salary_visible": false, "title_keywords": ["account executive", "senior account executive"], "responsibilities": ["marketing campaigns"], "requirements": {"degrees": ["degree holder"], "majors": ["journalism", "finance", "accounting", "business administration"], "languages": ["english", "chinese", "mandarin"], "language_level": ["excellent", "proficiency"], "hard_skills": ["excel", "ms powerpoint", "chinese word processing"], "soft_skills": ["detail-minded", "meticulous", "oral", "self-motivated", "organizational skill", "good team player", "work independently", "communication", "proactive"], "languages_combined": [{"language": "english", "language_level": ["excellent"]}, {"language": "chinese", "language_level": ["proficiency"]}, {"language": "mandarin", "language_level": ["excellent"]}]}, "experience_required": {"duration": ["1-2 years"], "field": ["relevant experience", "media"]}}, {"job_id": "100003009038441", "location_code": "hk", "company": "MoneyHero Global Limited", "job_title": "Senior Content Specialist", "description": "YOUR TASKS\n\nOwn the content performance for assigned domains from creation to execution and performance reporting of content strategy\nResearch, create and edit bilingual multi-media content related to personal finance management content (Credit Score, Financial Health, Credit Cards, Personal Loans, Investment, Insurance)\nUpdate, rewrite or edit blogs as needed and support the broader content team in content distribution\nMaintain accuracy of content on a daily basis through CMS to ensure content updates and user engagement\nWork collaboratively to conduct customer and market research at various stages of product development to ensure a focus on the integrated solution and differentiation from competitors\nTrack data, analyse and report on the blog performance and content initiatives\nSupport marketing campaigns to drive improvement of full funnel performance\nEnsure high quality output that upholds editorial standards and protect our brand\n\nSKILLS AND REQUIREMENTS\n\nBachelor\u2019s degree in Journalism, Public Relations or related Communications field.\n3+ years of experience as a digital content creator, writer, journalist or editor producing ZH & EN digital content for the local Hong Kong audience.\u00a0\nExcellent bilingual writing skills in Chinese and English\nThe ability to adapt quickly to the fast-paced start-up environment, to process new information on the go and translate that into customer-friendly language\nData-centric, understand digital landscape of content marketing\nWorking experience of wordpress or other CMS\nPositive attitude and ability to work with suggestions and feedback from multiple parties\nIncredible people skills\nFinancial industry experience in HK is preferential, but not mandatory", "employment_types": ["Full Time", "Permanent"], "selling_points": ["3+ years of experience on content creation", "Working experience of wordpress or other CMS", "Excellent bilingual writing skills"], "locations": ["Tin Hau"], "categories": ["Marketing / Public Relations", "Public Relations - Copy-writing", "Digital Marketing"], "post_time": "2022-01-11T06:53:42Z", "salary": {"currency": null, "max": null, "min": null, "period": "monthly", "term": null}, "salary_visible": false, "title_keywords": ["specialist"], "responsibilities": ["reporting", "management", "data", "maintain accuracy", "quality", "market research", "marketing campaigns", "report", "insurance", "analyse"], "requirements": {"degrees": ["degree", "bachelor"], "majors": ["journalism", "communications"], "languages": ["english", "chinese"], "language_level": ["excellent"], "hard_skills": ["focus", "go", "wordpress", "writing skills"], "soft_skills": ["positive attitude", "focus", "friendly", "writing skills"], "languages_combined": [{"language": "english", "language_level": ["excellent"]}, {"language": "chinese", "language_level": ["excellent"]}]}, "experience_required": {"duration": ["3+ years"], "field": ["editor", "digital content", "financial industry"]}}, {"job_id": "100003009039784", "location_code": "hk", "company": "Linkers International Limited", "job_title": "Assistant Officer / Officer \u2013 Corporate and Marketing Communications", "description": "Our client:\nOur client is a leading insurance company.\n\n\n\nBenefits:\n\nPerformance Bonus (Around 2 months bonus)\nLife Insurance\nMedical Insurance\nDental Insurance\n14AL + 1AL\nWFH under COVID\u00a0\n\nResponsibilities:\n\n\n\nSupport the team in developing and implementing corporate communications strategy\nAssist in PR materials preparation, including press release, letters, advertorial and other communication materials as assigned by supervisors\nAssist in organizing CSR events and campaigns to achieve the objectives set under the company's brand strategies\nAssist in managing PR agency to maintain media relationship for effective delivery and measurable results\nProvide other administrative support as assigned by supervisors\n\nRequirements:\n\nUniversity degree preferably in Marketing, Communications or Journalism, with 3 years\u2019 solid working experience\nExperience and knowledge of marketing materials development and printing production\nDetail minded and able to work under pressure and meet tight deadlines\nProficiency in spoken and written Chinese and English, and with strong communication skills\nStrong PC skills in Word, Chinese Word Processing, Excel, PowerPoint\n\nTo apply online, \u00a0please click the Apply button below. For a confidential discussion about this role please contact us on +852 55939228.\n\nPersonal data collected will be used for recruitment purposes only.", "employment_types": ["Full Time", "Permanent"], "selling_points": ["WFH under COVID", "Sizeable Marketing team", "On the job training"], "locations": ["Not Specified"], "categories": ["Marketing / Public Relations", "Marketing - Marketing Communication", "Public Relations - Copy-writing", "Public Relations - General / Support"], "post_time": "2022-01-11T11:19:30Z", "salary": {"currency": null, "max": null, "min": null, "period": "monthly", "term": null}, "salary_visible": false, "title_keywords": ["assistant officer", "officer"], "responsibilities": [], "requirements": {"degrees": [], "majors": [], "languages": [], "language_level": [], "hard_skills": [], "soft_skills": [], "languages_combined": []}, "experience_required": {"duration": [], "field": []}}, {"job_id": "100003009037143", "location_code": "hk", "company": "Pan Lloyds Publishers Limited", "job_title": "Marketing Executive \u5e02\u5834\u4e3b\u4efb", "description": "Responsibilities\n\nConceive and develop efficient and intuitive marketing strategies;\nOrganize and oversee advertising / communication campaigns (search engine marketing and social media etc.), exhibitions and promotional events;\nPlan and manage the production of marketing materials, including leaflets, posters, newsletters, eDM and video for on-line and off-line channels;\nCoordinate and liaise with internal teams, including sales teams to deliver effective marketing communications materials for different marketing programs;\nManage and liaise with agencies to produce creative and develop strategic marketing plan to support all marketing campaigns rollout;\nDevelop and manage the organization\u2019s website(s) and write and optimize content for the website and social networking accounts such as Facebook;\nTrack and analyze website traffic flow and provide regular internal reports\nConduct market research and analysis to evaluate trends, brand awareness and competition ventures;\nUndertake any other activities as assigned by supervisors\n\nRequirements\n\nDegree holder in Marketing, Communication or related discipline with min. 3 years of solid experience in (digital) marketing and event management;\nEnergetic and creative team player with excellent interpersonal and presentable skills;\nSelf-motivated and flexible to take new challenges in a fast-paced working environment;\nExcellent communication and interpersonal skills, fluency in both English and Cantonese;\nCandidate with more experience will be considered as Senior Marketing Executive\nImmediate available is highly preferred\n\nInterested parties please click\u00a0\"Apply Now\"\u00a0to submit your full resume stating present and expected salary.\n\nPersonal data provided by job applicants will be kept strictly confidential and will be used solely for employment related purposes. Only short-listed candidates will be contacted.\n\nYou are welcome to visit our website to know more about us:\u00a0\nhttp://www.popular.com.hk\u00a0/\nhttp://pl.popularworldhk.com/\nhttp://jp.popularworldhk.com\n\n\n\n", "employment_types": ["Full Time", "Permanent"], "selling_points": ["High initiative, passionate in marketing", "5-day work week, Medical & Dental, Bonus", "Development in marketing projects"], "locations": ["Tsuen Wan Area"], "categories": ["Marketing / Public Relations", "Marketing - General / Support", "Public Relations - Copy-writing", "Public Relations - Event Management"], "post_time": "2022-01-11T01:53:09Z", "salary": {"currency": null, "max": null, "min": null, "period": "monthly", "term": null}, "salary_visible": false, "title_keywords": ["marketing executive"], "responsibilities": ["conduct market research", "website", "communication", "plan", "liaise with", "facebook", "advertising", "teams", "develop", "marketing plan", "reports", "marketing campaigns", "social media", "marketing strategies", "edm", "leaflets", "analysis", "coordinate", "evaluate", "marketing materials"], "requirements": {"degrees": ["degree holder"], "majors": ["marketing"], "languages": ["cantonese", "english"], "language_level": ["fluency", "excellent"], "hard_skills": [], "soft_skills": ["flexible", "self-motivated", "creative", "presentable", "communication", "communication and interpersonal skills", "team player", "energetic", "interpersonal"], "languages_combined": [{"language": "cantonese", "language_level": ["fluency", "excellent"]}, {"language": "english", "language_level": ["fluency", "excellent"]}]}, "experience_required": {"duration": ["3 years"], "field": ["digital", "management", "marketing"]}}, {"job_id": "100003009042957", "location_code": "hk", "company": "ConnectedGroup Limited", "job_title": "Head of Communications - Technology", "description": "This leading organization is consistently expanding their business in HK, the unique organization is now recruiting this communications position to join one of their business functions.\n\nWith over a century presence in HK, the organization continues to grow and expand their team by hiring a communications professional who helps to drive their communication strategies.\n\nResponsibilities:\n\nDevelop and manage corporate communications plans to enhance the company's image\nLead a team to drive media communications in order to achieve business goals of the company\nPartner with senior management as a corporate advisor on communications strategy\nTake charge of critical enterprise communications to assure information released on time to all stakeholders\nKeep abreast of important development related to the industry and public affairs\n\nRequirements:\n\nDegree in communications, marketing or related disciplines\nAt least 15 years of working experience in public relations & communications\nCandidates with large corporate experience within technology sector is preferred\nExtensive knowledge in media landscape\nExcellent communications skills in both conversational and written English, Mandarin and Cantonese\n\nInterested individuals can click apply now and send through updated resume in WORD format. For a more comprehensive list of current opportunities, please visit www.connectedgroup.com\n\n#StayConnected", "employment_types": ["Full Time", "Permanent"], "selling_points": ["Team management", "Consumer & Corporate Communications", "Fast paced, dynamic"], "locations": ["Not Specified"], "categories": ["Marketing / Public Relations", "Management", "Public Relations - Copy-writing", "Public Relations - General / Support"], "post_time": "2022-01-12T09:18:40Z", "salary": {"currency": null, "max": null, "min": null, "period": "monthly", "term": null}, "salary_visible": false, "title_keywords": [], "responsibilities": ["business goals", "develop", "lead a team", "plans", "senior management"], "requirements": {"degrees": ["degree"], "majors": ["related disciplines", "marketing", "communications"], "languages": ["cantonese", "english", "mandarin"], "language_level": ["conversational", "excellent"], "hard_skills": ["word"], "soft_skills": ["comprehensive", "extensive"], "languages_combined": [{"language": "cantonese", "language_level": ["conversational", "excellent"]}, {"language": "english", "language_level": ["conversational", "excellent"]}, {"language": "mandarin", "language_level": ["conversational", "excellent"]}]}, "experience_required": {"duration": ["at least 15 years"], "field": ["public relations"]}}, {"job_id": "100003009041720", "location_code": "hk", "company": "iFAST ePension Services Limited", "job_title": "Editorial/Translation Trainee - Part-time or Full-time Intern/Contract (Financial sector)", "description": "Responsibilities:\n\nTranslate\u00a0pension-related content, mainly from English to Chinese;\nPerform\u00a0proofreading for peer and/or own work;\nSuggest improvement on\u00a0original content from language perspectives, including written style, grammar, structure\u00a0and etc., when necessary.\n\nRequirements:\n\nUndergraduate year-2 or above major in Translation, Language, Journalism or other related disciplines;\nExcellent written English and Chinese;\nAble to work independently under minimum supervision;\nStrong sense of responsibility to complete assigned tasks;\nAble to report at least 4 half-days\u00a0(8:30am to 12:30pm or 1:45pm to 5:45pm)\u00a0 per week.", "employment_types": ["Full Time", "Part Time", "Contract", "Internship"], "selling_points": ["Translation and content editing", "Responsible and detail-oriented", "Work independently"], "locations": ["Tsim Sha Tsui"], "categories": ["Marketing / Public Relations", "Public Relations - Copy-writing", "Professional Services", "Translation"], "post_time": "2022-01-12T04:16:30Z", "salary": {"currency": null, "max": null, "min": null, "period": "hourly", "term": null}, "salary_visible": false, "title_keywords": ["trainee", "intern"], "responsibilities": ["proofreading"], "requirements": {"degrees": [], "majors": [], "languages": ["english", "chinese"], "language_level": ["excellent"], "hard_skills": ["translation"], "soft_skills": ["work independently", "sense of responsibility"], "languages_combined": [{"language": "english", "language_level": ["excellent"]}, {"language": "chinese", "language_level": ["excellent"]}]}, "experience_required": {"duration": [], "field": []}}, {"job_id": "100003009039730", "location_code": "hk", "company": "David James Recruitment Limited", "job_title": "Translator \u2013 International Law Firm ($40K \u2013 45K)", "description": "We work on behalf of an International Law Firm located in Central. They are now looking for an experienced Translator (Chinese and English) to join their operation.\n\nResponsibilities:\n\nTranslate legal documents including but not limited to announcements, legal opinions, statement of claim, cour orders, C&D letters, and financial documents, etc.\nTranslate marketing and commercial materials\nMaintain an efficient and clear database\nPerform ad hoc duties\n\nRequirements:\n\nBachelor\u2019s Degree in Translation, Journalism, or relevant disciplines\n3+ years of experience in writing, translating, or editing, experience from the Legal or Professional industry is a plus\nExcellent proficiency in written English and Chinese\n\nTo Apply\n\nInterested parties please send us your updated resume with your latest and expected salaries or please call +852 3611 7881 or email at legal@ djrecruit.com for a confidential discussion.", "employment_types": ["Full Time", "Permanent"], "selling_points": ["Sizeable and reputable Int' law firm", "Translate and edit legal and commercial document", "Business Writing in Chinese and English"], "locations": ["Eastern Area"], "categories": ["Professional Services", "Legal & Compliance", "Marketing / Public Relations", "Public Relations - Copy-writing", "Translation"], "post_time": "2022-01-11T10:43:24Z", "salary": {"currency": null, "max": null, "min": null, "period": "monthly", "term": null}, "salary_visible": false, "title_keywords": ["translator"], "responsibilities": ["ad hoc duties", "maintain", "letters", "database"], "requirements": {"degrees": ["degree", "bachelor"], "majors": ["journalism"], "languages": ["english", "chinese"], "language_level": ["excellent", "proficiency"], "hard_skills": ["translation", "plus"], "soft_skills": [], "languages_combined": [{"language": "english", "language_level": ["excellent", "proficiency"]}, {"language": "chinese", "language_level": ["excellent", "proficiency"]}]}, "experience_required": {"duration": ["3+ years"], "field": ["editing", "writing", "legal"]}}, {"job_id": "100003009032944", "location_code": "hk", "company": "Brian Cha Motivation", "job_title": "Senior Copywriter", "description": "Role\n\nThis person shall be ambitious and results-driven to cope with the fast growth of our company. This person will be intellectually curious, resourceful and enthusiastic and hungry for a new challenge in a fast-paced and forward-thinking environment.\n\nThe role will be responsible for developing and implementing marketing strategies to meet the company\u2019s customer acquisition and revenue growth targets by keeping our company competitive and innovative through their World class copy.\n\nResponsibilities\n\n\nCultivate strong team culture by injecting company's vision, mission and core values into team discussions and decision making processes and behavioural standards\nCreate promotion messages, editorial articles for campaign launches, site and app update and external communication channel\nDevelop strategic creative communication concepts/ideas\nPlan and write headlines and text in such a way to appeal to target audiences\nResearch on market trends and new ideas, then convert such ideas into opportunities\nAssisting CMO in creating, reviewing and providing feedback for all copy on all marketing platforms/campaigns, social, articles, websites, etc to ensure it is on-brand and hitting KPI goals\nIdentify new market opportunities to derive appropriate marketing collaborations and joint partnerships\nClosely monitor online campaigns and formulate new e-marketing initiatives to generate sales and brand awareness\nOther ad-hoc projects as assigned by management\n\nResults\n\n\nEffective conversion from copy to business opportunities\nDeliver compelling copy to achieve campaign objectives\nAchieve consistent broadcast email open rates 20%\n\nRequirements\n\nDegree holder in Marketing Communications, Advertising, Journalism, Chinese Language or related disciplines is preferred\n3-5 years solid experience in Advertising / Social Media Agency\nHigh literacy on latest digital marketing tools\nHigh Cantonese fluency is a must and English proficiency is preferred\nExcellent communicator and values teamwork\nSelf-starter, hunger for success, eager to learn and open to new ideas\nStrong passion for the internet environment, result-oriented, proactive and independent\nStrong sense of responsibility, well organised with exceptional problem-solving\u00a0skill with a can-do attitude\n\n\nDevelop your life-long career by joining the BCM team where we impact thousands of businesses from around the World everyday\n\nInvesting in our team is our priority so we can grow and shine together, so IF YOU ARE JUST LOOKING FOR A JOB, THIS IS NOT FOR YOU\n", "employment_types": ["Full Time", "Permanent"], "selling_points": ["World Class Platform to Show Off Your Talents", "Infinite career advancement opportunity", "Social Media Copywriter"], "locations": ["Wong Tai Sin Area"], "categories": ["Media & Advertising", "Creative / Design", "Marketing / Public Relations", "Marketing - Marketing Communication", "Public Relations - Copy-writing"], "post_time": "2022-01-08T03:36:26Z", "salary": {"currency": "HKD", "max": 29999, "min": 20000, "period": "monthly", "term": null}, "salary_visible": true, "title_keywords": ["copywriter"], "responsibilities": ["management", "ideas", "business opportunities", "monitor", "develop", "communication", "plan", "ad-hoc projects"], "requirements": {"degrees": ["degree holder"], "majors": ["marketing communications", "related disciplines", "journalism"], "languages": ["cantonese", "english", "chinese"], "language_level": ["fluency", "proficiency"], "hard_skills": ["problem-solving"], "soft_skills": ["independent", "passion for", "sense of responsibility", "can-do attitude", "problem-solving", "teamwork", "eager to learn", "organised", "communicator", "proactive", "result-oriented"], "languages_combined": [{"language": "cantonese", "language_level": ["fluency", "proficiency"]}, {"language": "english", "language_level": ["proficiency"]}, {"language": "chinese", "language_level": []}]}, "experience_required": {"duration": ["3-5 years"], "field": ["social media agency", "advertising"]}}, {"job_id": "100003009039033", "location_code": "hk", "company": "Recolo Limited", "job_title": "Content & Digital Marketing Manager (16613)", "description": "Our client is a well-established European Wealth Investment company, with a rapid growth across the APAC region.\u00a0 To cope with their growth and expansion, they are currently looking for a Content Marketing Manager to drive content creation and distribution to improve engagements across multichannel\n\n\n\nResponsibilities\n\nCollaborates across functions and silos to deliver an effective content marketing strategy and editorial plan to meet the business objectives. Own editorial calendar from strategy through execution\nTranslate/massage go-to-market messaging and brand story across internal and external communication channels\nPartner with owners to develop a comprehensive multichannel content marketing strategy to drive traffic, engagement, leads and retention\nHelp to structure/maintain affiliate marketing relationships\nChampion content governance which to be consistent with brand voice, style and tone\nDevelop a framework for tracking and analyzing results of all channels to demonstrate the overall business value of content efforts\nDevelop and manage eDMs, newsletters and client-facing presentation content\nAssist with PR and communications\n\nRequirements\n\nBachelor\u2019s degree in Marketing Communication or related\nMinimum 5 years experiences in Content Marketing in financial services or HNW industries\nExperience in managing CMS and CRM (HubSpot, WordPress), web and digital analytics, and social platforms\nA portfolio of produced content pieces for brands, sales and marketing campaigns\nSelf-motivated, energetic, creative, resourceful, detail-oriented, and collaborative\nAbility to meet deadlines and handle multiple projects\nFluency in English and Chinese is required\n\n\n\n\nThank you for your interest with Recolo Careers. For your application to reach directly to our consultant responsible for this job openings please apply via our careers portal below for a quick reply.\u00a0 \u00a0\u00a0\n\nPlease\u00a0Apply Here >\u00a0Confidential & Secure\u00a0<\nProblems?\u00a0+852 2971 2971\u00a0\u00a0\n\nApplication Disclaimer.\u00a0\u00a0\nWe recommend that application is made via our careers portal above. This application process does not sit in an email box but directly notifies the specialist consultant on our in-house systems for processing. Furthermore, our business intelligence systems will try to match other suitable jobs with other consultants that are not advertised externally. This accounts for between 50% \u2013 70% of our job openings in HK alone.\u00a0 \u00a0 \u00a0\n\nYou could apply using other methods but this will end up in our central email inbox. Which means our researchers will need to go through hundreds or even thousands of emails before they can finally match you to the consultant. If you want a rapid response, we suggest Recolo Careers Portal above. Furthermore, Recolo complies with the Personal Data (Privacy) Ordinance and regulated by the Labour Department.\u00a0 \u00a0 \u00a0 \u00a0\u00a0\n\nIf you are interested in other job opportunities, please visit\u00a0-\u00a0http://recolo.consulting/", "employment_types": ["Full Time", "Permanent"], "selling_points": ["European Wealth Investment company", "Marketing exp in financial services or HNW ind", "rapid growth across the APAC and Middle East"], "locations": ["Not Specified"], "categories": ["Marketing / Public Relations", "Marketing - Marketing Communication", "Public Relations - Copy-writing", "Digital Marketing"], "post_time": "2022-01-11T08:27:29Z", "salary": {"currency": null, "max": null, "min": null, "period": "monthly", "term": null}, "salary_visible": false, "title_keywords": ["digital marketing manager"], "responsibilities": ["edms", "develop", "communication", "maintain", "plan", "tracking"], "requirements": {"degrees": ["degree", "bachelor"], "majors": ["marketing"], "languages": ["english", "chinese"], "language_level": ["fluency"], "hard_skills": ["web", "processing", "wordpress", "rapid", "go", "business intelligence"], "soft_skills": ["self-motivated", "creative", "resourceful", "responsible", "interested in", "collaborative", "detail-oriented", "communication", "meet deadlines", "energetic"], "languages_combined": [{"language": "english", "language_level": ["fluency"]}, {"language": "chinese", "language_level": ["fluency"]}]}, "experience_required": {"duration": ["minimum 5 years"], "field": ["digital", "marketing", "financial services"]}}, {"job_id": "100003009035637", "location_code": "hk", "company": "Creative Art (HK) Culture Communication Co., Limited", "job_title": "\u6587\u6848\u7b56\u5283", "description": "\u5de5\u4f5c\u8077\u8cac\uff1a\n\n-\u00a0 \u00a0\u64b0\u5beb\u5404\u985e\u6587\u7ae0\uff0c\u80fd\u5920\u7368\u7acb\u64b0\u5beb\u6d3b\u52d5\u65b9\u6848\u3001\u9805\u76ee\u7b56\u5283\u66f8\u7b49\uff1b\n\n-\u00a0\u50b3\u9054\u6e05\u6670\u53ca\u6e96\u78ba\u7684\u76f8\u95dc\u8cc7\u6599\u641c\u96c6\uff0c\u80fd\u5920\u7368\u7acb\u64b0\u5beb\u65b0\u805e\u7a3f\u3001\u8a55\u8ad6\u7a3f\u3001\u6703\u8b70\u8a18\u9304\u7b49\u5404\u985e\u5be6\u7528\u6587\u7a3f\uff1b\n\n-\u00a0\u00a0\u5354\u52a9\u8ddf\u9032\u4e0d\u540c\u7684\u9805\u76ee\u57f7\u884c\uff0c\u6536\u96c6\u4e26\u6574\u7406\u76f8\u95dc\u8cc7\u6599\uff1b\n\n-\u00a0\u00a0\u00a0\u914d\u5408\u4e0a\u7d1a\u5b8c\u6210\u76f8\u95dc\u9805\u76ee\u7b56\u5283\u7684\u6587\u5b57\u8868\u73fe\u5de5\u4f5c\u3002\n\n\n\n\u4efb\u8077\u8981\u6c42\uff1a\n-\u00a0 \u5c08\u4e0a\u6559\u80b2\u6216\u5177\u5099\u5b78\u58eb\u5b78\u4f4d\uff1b\n\n-\u00a0\u00a0\u8f03\u5f37\u7684\u6587\u6848\u5beb\u4f5c\u80fd\u529b\uff0c\u51fa\u8272\u7684\u6587\u5b57\u7d44\u7e54\u80fd\u529b\uff0c\u7b56\u5283\u5beb\u4f5c\u7d93\u9a57\u8c50\u5bcc\uff1b\n\n-\u00a0\u00a0\u7b56\u5283\u3001\u5ee3\u544a\u3001\u65b0\u805e\u3001\u4e2d\u6587\u3001\u5e02\u5834\u71df\u92b7\u76f8\u95dc\u5c08\u696d\u512a\u5148\u8003\u616e\uff1b\n\n-\u00a0\u00a0\u00a0\u7a4d\u6975\u4e3b\u52d5\uff0c\u8cac\u4efb\u5fc3\u5f37\uff0c\u5177\u5099\u826f\u597d\u7684\u81ea\u5b78\u80fd\u529b\u548c\u5718\u968a\u5408\u4f5c\u7cbe\u795e\u3002", "employment_types": ["Full Time"], "selling_points": [], "locations": ["Mong Kok"], "categories": ["Media & Advertising", "Editorial / Journalism", "Marketing / Public Relations", "Marketing - Market Research", "Public Relations - Copy-writing"], "post_time": "2022-01-10T07:58:42Z", "salary": {"currency": null, "max": null, "min": null, "period": "monthly", "term": null}, "salary_visible": false, "title_keywords": [], "responsibilities": [], "requirements": {"degrees": [], "majors": [], "languages": [], "language_level": [], "hard_skills": [], "soft_skills": [], "languages_combined": []}, "experience_required": {"duration": [], "field": []}}, {"job_id": "100003009032461", "location_code": "hk", "company": "The Great Eagle Group of Companies", "job_title": "Assistant Officer - Digital Marketing", "description": "Responsibilities:\n\nAssist in supporting and managing the day to day operations of a website / e-commerce business, include CMS, content, SEO, online shop, and customer engagement / support\nSupport marketing cloud operation including customer journey building, automation, email and sms preparation and customer engagement / support\nAssist in planning and implementation of marketing campaigns and promotion activities including but not limited to social media, blogs, KOLs, PR, media\nSupport in data and analytical tasks to run reports, create insights, and optimize marketing campaigns\nSupport in preparing, updating marketing materials (content/visuals), maintain, and drive brand awareness via online and offline marketing\nSupport event planning and operations, including but not limited to material sourcing, vendor coordination, logistics, rsvp\nWork closely with internal and external parties to facilitate smooth implementation and operation of marketing strategies on digital, traditional marketing and event coordination\nHandle other ad hoc projects assigned\n\nRequirements:\n\nDegree holder or above in Communication, Language, Literature, Marketing, Business or related disciplines\n1 - 3 years\u2019 experience in marketing or digital technology, preferable gained in managing external agencies / vendors / recent grads with solid intern experience are welcome\nHands-on experience in online and offline marketing and e-commerce\nWell-organized with ability to prioritize and multi-task\nSelf-motivated, result-oriented and attentive to details\nGood project management, interpersonal skills and communication skills\nGood command of both written and spoken English and Chinese\n\nSalary and benefits will be commensurate with qualifications and experience.\u00a0 Interested parties, please send a full resume with present and expected salary, and date available to The Human Resources Department, 32/F., Great Eagle Centre, 23 Harbour Road, Wan chai, Hong Kong or e-mail to us.\u00a0(Please quote the reference no. on the envelope and the covering letter.)\n\nTo know more about us, please visit our website at http://www.greateagle.com.hk.\n\nWe are an equal opportunity employer and welcome applications from all qualified candidates.\n\nPersonal data collected will be treated in strict confidence and used only for recruitment-related purpose. Applicants who have not heard from us within four weeks may consider their applications unsuccessful. All personal data will be destroyed after 12 months.", "employment_types": ["Full Time", "Permanent"], "selling_points": ["Content marketing", "Social media management", "Marketing campaigns and promotion"], "locations": ["Wan Chai"], "categories": ["Marketing / Public Relations", "Marketing - Marketing Communication", "Public Relations - Copy-writing", "Digital Marketing"], "post_time": "2022-01-10T03:42:44Z", "salary": {"currency": null, "max": null, "min": null, "period": "monthly", "term": null}, "salary_visible": false, "title_keywords": ["assistant officer", "digital marketing"], "responsibilities": ["social media", "seo", "day to day operations", "marketing strategies", "data", "operations", "internal and external parties", "implementation", "website", "maintain", "reports", "logistics", "marketing campaigns", "coordination", "marketing materials", "ad hoc projects", "planning"], "requirements": {"degrees": ["recent grads", "degree holder"], "majors": ["business", "related disciplines", "marketing"], "languages": ["english", "chinese"], "language_level": ["good command"], "hard_skills": ["project management", "e-commerce"], "soft_skills": ["communication skills", "self-motivated", "multi-task", "attentive to details", "well-organized", "prioritize", "communication", "project management", "hands-on", "interpersonal skills", "result-oriented"], "languages_combined": [{"language": "english", "language_level": ["good command"]}, {"language": "chinese", "language_level": ["good command"]}]}, "experience_required": {"duration": ["1 - 3 years"], "field": ["digital", "marketing", "e-commerce"]}}]