[{"job_id": "100003009053585", "location_code": "hk", "company": "OSMA Consulting Limited", "job_title": "Analyst \u5206\u6790\u5e08", "description": "Our client is an innovation and technology focus venture capital fund partnership with reputable universities in Hong Kong, the founder belongs a reputable local family office. They are currently looking for qualified individual to join the team assisting deal execution and fund operation.\u00a0\n\n\n\nResponsibilities:\nPerform fundamental, in-depth industry research analysis (TMT, Fin-tech);\n\nResearch involves spreadsheet modeling, interviewing management teams and extensive research with potential target companies;\nAssist senior members to perform DD and execution on potential deals;\nAssist in maintaining relations with existing LPs and pitching for new LPs;\nLiaise with councils and fund admin to monitor the fund operation.\n\n\u00a0Requirements:\n\nDegree or above;\nWork with passion, critical thinking and creativity;\nCFA/CPA is a plus\nCommand of Bloomberg or Wind is a plus\nHigh integrity, good communication skill", "employment_types": ["Full Time"], "selling_points": ["Venture capital", "Excellent deal exposure", "Attractive package"], "locations": ["Central"], "categories": ["Banking / Finance", "Analyst", "Financial Services", "Professional Services", "Business Analysis / Data Analysis"], "post_time": "2022-01-17T07:14:55Z", "salary": {"currency": null, "max": null, "min": null, "period": "monthly", "term": null}, "salary_visible": false, "title_keywords": ["analyst"], "responsibilities": ["management teams", "maintaining", "monitor", "liaise with", "research analysis"], "requirements": {"degrees": ["degree or above"], "majors": [], "languages": [], "language_level": [], "hard_skills": ["cfa", "plus", "bloomberg", "cpa"], "soft_skills": ["communication skill", "integrity"], "languages_combined": []}, "experience_required": {"duration": [], "field": []}}, {"job_id": "100003009054989", "location_code": "hk", "company": "Asia Airfreight Terminal Co. Ltd.", "job_title": "Operations Analyst", "description": "About Geek+\nGeek+ leads the technology revolution, by applying advanced robotics and AI technologies to realize high-flexibility and intelligent logistics automation solution. We are always looking for people who can bring new perspectives and life experiences to our company. We understand the value of our people and we strive to constantly satisfy their needs.\n\nWe are looking for a\u00a0Sales Operations Officer\u00a0to join our team. Are you someone who is driven by curiosity, craves a good challenge? Join us and be part of this exciting adventure!\n\nResponsibilities:\n\n\nConduct sales analysis, review client types and follow-up sales activities\nPrepare sales-related documents, monthly reports, or sales proposal as assigned\nHandle CRM for Asia-Pacific regions\nFollow-up inquiries from Channels as well as direct clients\nPerform ad-hoc duties assigned by supervisor\nRequirements:\nHigher diploma or above with relevant experience in sales operations\nOrganized with good communication skills, detail-minded and independent\nNative in Cantonese, good spoken and written English and Mandarin\nProficient in Microsoft Office (Word, Excel and PowerPoint) and Chinese word-processing\nWhat we Offer:\n\nFive-day work week\nYoung and energetic work culture with regional exposure\nCozy office with light refreshments\nDouble pay plus performance bonus\nMedical, dental benefits and insurance\n14 to 21 days annual leave entitlement\nConvenient work location: KCC\n\nIf your qualifications, experience, and aspirations match our requirements, please send your resume with your current and expected salary to us.\n\nAll information and materials submitted to Geek+ will remain strictly confidential and be treated for recruitment purposes only. Only short-listed candidates will be notified.", "employment_types": ["Full Time", "Permanent"], "selling_points": ["13 days annual leave, 5-day week, double pay", "Prepare and coordinate new system development", "Able to work independently and efficiently"], "locations": ["Airport Area"], "categories": ["Transportation & Logistics", "Others", "Professional Services", "Business Analysis / Data Analysis", "Others", "Student / Fresh Graduate / No Experience"], "post_time": "2022-01-17T16:22:48Z", "salary": {"currency": null, "max": null, "min": null, "period": "monthly", "term": null}, "salary_visible": false, "title_keywords": ["operations analyst"], "responsibilities": ["sales activities", "monthly reports", "related documents", "analysis", "review", "prepare sales", "ad-hoc duties"], "requirements": {"degrees": ["higher diploma or above"], "majors": [], "languages": ["cantonese", "english", "chinese", "mandarin"], "language_level": ["native", "proficient", "good"], "hard_skills": ["excel", "chinese word-processing", "microsoft office", "word", "powerpoint"], "soft_skills": ["communication skills", "organized", "detail-minded", "independent"], "languages_combined": [{"language": "cantonese", "language_level": ["native", "good"]}, {"language": "english", "language_level": ["good"]}, {"language": "chinese", "language_level": ["proficient"]}, {"language": "mandarin", "language_level": ["good"]}]}, "experience_required": {"duration": [], "field": ["relevant experience"]}}, {"job_id": "100003009056634", "location_code": "hk", "company": "Cognizant Technology Solutions Hong Kong Limited", "job_title": "Business Analyst (API)", "description": "About Geek+\nGeek+ leads the technology\u00a0revolution, by applying advanced\u00a0robotics and AI technologies to realize high-flexibility and intelligent logistics automation solution.\u00a0We are always looking for people who can bring new perspectives and life experiences to our company.\u00a0We understand the value of our people and we strive to constantly satisfy their needs.\n\nWe are now seeking for a\u00a0Project Manager\u00a0to join our team. Are you someone who is driven by curiosity, craves a good challenge? Join us and be part of this exciting adventure!\n\nAbout the role:\n\n\nResponsible for project/ project team operation and management\nDevelop the project process plan and negotiate with both clients and internal stakeholders\nMonitor and communicate project progress and issues to project teams and stakeholders to ensure project deliverables\nConduct meetings with functional parties to gather business requirements and provide consultation to stakeholders\nPrepare detailed critical paths, milestones, schedules, estimates, resource plans and status updates\nAssist in the integration testing, system testing, user acceptance test & implementation activities\nSupervise and support junior colleagues on project risks measures and ensure projects delivery according to the project milestones\nRequirements:\n\nDegree in Computer Engineering, Information Technology, Computer Sciences or related disciplines\n6 years of project management experience. Familiar in warehouse operation/ solution design in logistics, automation or relevant industries is preferred\nStrong interpersonal skills and able to facilitate and drive cross-department communication\nKnowledge in project management methodologies and tools. Proficient in AutoCAD, WMS or IT infrastructure is a plus\nPossess problem-solving and analytical skills both in quantitative and qualitative\nStrong spoken and written English and Chinese, including Mandarin\nWhat We Offer:\n\nFive-day work week\nYoung and energetic work culture with regional exposure\nCozy office environment with\u00a0light refreshments\nDouble pay & attractive performance bonus\nMedical and dental benefits and insurance\n14 to 21 days Annual Leave\nConvenient work location: KCC\nIf your qualifications, experience, and aspirations match our requirements, please send your resume with your current and expected salary to us.\n\nAll information and materials submitted to Geek+ will remain strictly confidential and be treated for recruitment purposes only. Only short-listed candidates will be notified.", "employment_types": ["Full Time", "Permanent"], "selling_points": [], "locations": ["Quarry Bay"], "categories": ["Professional Services", "Business Analysis / Data Analysis"], "post_time": "2022-01-18T05:17:40Z", "salary": {"currency": null, "max": null, "min": null, "period": "monthly", "term": null}, "salary_visible": false, "title_keywords": ["business analyst"], "responsibilities": ["management", "robotics", "it infrastructure", "project deliverables", "schedules", "monitor", "project progress", "teams", "develop", "testing", "implementation", "project management", "design", "logistics", "communication", "plan", "wms", "plans"], "requirements": {"degrees": ["degree"], "majors": ["related disciplines", "computer engineering", "information technology"], "languages": ["english", "chinese", "mandarin"], "language_level": [], "hard_skills": ["plus", "ai", "problem-solving", "analytical skills", "project management", "integration", "autocad"], "soft_skills": ["advanced", "responsible", "problem-solving", "analytical skills", "communication", "project management", "interpersonal skills", "driven", "detailed"], "languages_combined": [{"language": "english", "language_level": []}, {"language": "chinese", "language_level": []}, {"language": "mandarin", "language_level": []}]}, "experience_required": {"duration": ["6 years"], "field": ["project management"]}}, {"job_id": "100003009054365", "location_code": "hk", "company": "Ricoh Hong Kong Limited", "job_title": "Data Analyst", "description": "About Geek+\nGeek+ leads the technology\u00a0revolution, by applying advanced\u00a0robotics and AI technologies to realize high-flexibility and intelligent logistics automation solution.\u00a0We are always looking for people who can bring new perspectives and life experiences to our company.\u00a0We understand the value of our people and we strive to constantly satisfy their needs.\u00a0\n\nWe are now seeking for a Site Engineer\u00a0to join our team. Are you someone who is driven by curiosity, craves a good challenge? Join us and be part of this exciting adventure!\n\nAbout the role:\n\nConduct implementation and supervision of site works and monitor the site progress, including\u00a0site testing and commissioning\u00a0\nCoordinate with project managers, sub-contractors and manage overall site performance\nPrepare daily on-site record for clients and internal team\nConduct robot preventive maintenance and ad-hoc malfunction analysis and maintenance\nResponsible for root cause analysis of production issue by applying diagnosing tools\nProvide training and support to external partners for project implementation and maintenance\nRequirements:\n\nHigher Diploma or above in Computer Science, Mechanical Engineering, Industrial Engineering, or related disciplines\nExperience in equipment installation, maintenance and site supervision will be an advantage\nFamiliar\u00a0with\u00a0Auto\u00a0CAD and Microsoft Office\nGood spoken\u00a0and\u00a0written\u00a0English,\u00a0Cantonese and\u00a0Mandarin\nGood\u00a0IT\u00a0literate\u00a0such\u00a0as\u00a0network\u00a0infrastructure\u00a0is\u00a0a\u00a0plus\nKnowledge of Warehouse Management System, ERP or other releated logistics systems is a plus\nWilling to learn and detail-oriented\u00a0\nSelf-motivated,\u00a0hard-working\u00a0and\u00a0independent\nWhat we offer:\n\nFive-day work week\nYoung and energetic work culture with regional exposure\nCozy office environment with a fully-stocked beverage fridge, self-served beer and snack\nDouble pay & attractive performance bonus\nMedical and dental benefits and insurance\n14 to 21 days Annual Leave\nConvenient work location: KCC\nIf your qualifications, experience, and aspirations match our requirements, please send your resume with your current and expected salary to us.\n\nAll information and materials submitted to Geek+ will remain strictly confidential and be treated for recruitment purposes only. Only short-listed candidates will be notified.", "employment_types": ["Full Time", "Permanent"], "selling_points": ["Data analytic and business intelligence", "Reports and process improvement", "Exp in data analysis and development of data model"], "locations": ["Kowloon Bay"], "categories": ["Professional Services", "Business Analysis / Data Analysis", "Information Technology (IT)", "Product Management / Business Analyst", "Data Scientist"], "post_time": "2022-01-17T09:17:42Z", "salary": {"currency": null, "max": null, "min": null, "period": "monthly", "term": null}, "salary_visible": false, "title_keywords": ["data analyst"], "responsibilities": ["ad-hoc", "provide training", "installation", "robotics", "commissioning", "site supervision", "maintenance", "network infrastructure", "analysis", "systems", "monitor", "implementation", "coordinate with", "testing", "warehouse management system", "logistics"], "requirements": {"degrees": ["higher diploma or above"], "majors": ["related disciplines", "engineering", "computer science", "mechanical engineering"], "languages": ["cantonese", "english", "mandarin"], "language_level": ["good"], "hard_skills": ["plus", "maintenance", "microsoft office", "ai", "analysis", "auto cad", "erp"], "soft_skills": ["self-motivated", "independent", "advanced", "responsible", "willing to learn", "detail-oriented", "hard-working", "driven"], "languages_combined": [{"language": "cantonese", "language_level": ["good"]}, {"language": "english", "language_level": ["good"]}, {"language": "mandarin", "language_level": ["good"]}]}, "experience_required": {"duration": [], "field": ["installation", "maintenance"]}}, {"job_id": "100003009054155", "location_code": "hk", "company": "Hong Kong Baptist University", "job_title": "Systems Analyst (Data Analytics) (PR0465/21-22)", "description": "About Geek+\nGeek+ leads the technology\u00a0revolution, by applying advanced\u00a0robotics and AI technologies to realize high-flexibility and intelligent logistics automation solution.\u00a0We are always looking for people who can bring new perspectives and life experiences to our company.\u00a0We understand the value of our people and we strive to constantly satisfy their needs.\n\nWe are now seeking for an\u00a0Assistant Manager, Account Management\u00a0to join our team. Are you someone who is driven by curiosity, craves a good challenge? Join us and be part of this exciting adventure!\n\nAbout the role:\nPlan, execute and follow-up after-sales activities directly with key clients\nBuild, sustain and manage relationship with clients at all levels\nLead regular meeting and coordinate with internal teams to fulfill client needs in a timely manner\nHandle complaint cases and queries, divert cases to related functional teams, preapre service reports to clients accordingly\nReview and enhance the current operations to ensure operation runs smoothly\nEnsure constant clear communication with distributors, service partners as well as clients\nRequirements:\n\nDegree holder with 4 years of experience in corporate account management\nExperience in logistics, 3PL, robotic automation is an advantage\nGood spoken and written English and Mandarin, native in Cantonese\nAttention to details, strong planning and organizational skills\nFlexible and open-minded, capable to work with stakeholders independently\nHigh flexibility to suit overseas customers operation hours\nWhat we offer:\n\nFive-day work week\nYoung and energetic work culture with regional exposure\nCozy office environment with\u00a0light refreshments\nDouble pay & attractive performance bonus\nMedical and dental benefits and insurance\n14 to 21 days Annual Leave\nConvenient work location: KCC\nApply immediately if your qualifications, experience, and aspirations match our requirements. Please share your full resume including date of availability, current and expected salary for application.\n\nAll information and materials submitted to Geek+ will remain strictly confidential and be treated for recruitment purpose only. Only shortlisted candidates will be notified.", "employment_types": ["Full Time"], "selling_points": ["Design and analyse data", "Implement data warehouse system", "Perform analysis on large/diverse datasets"], "locations": ["Kowloon City"], "categories": ["Professional Services", "Business Analysis / Data Analysis", "Information Technology (IT)", "Data Scientist"], "post_time": "2022-01-17T08:35:49Z", "salary": {"currency": null, "max": null, "min": null, "period": "monthly", "term": null}, "salary_visible": false, "title_keywords": ["analyst"], "responsibilities": ["sales activities", "management", "robotics", "operations", "review", "coordinate with", "teams", "a timely manner", "communication", "logistics", "reports", "plan", "planning"], "requirements": {"degrees": ["degree holder"], "majors": [], "languages": ["cantonese", "english", "mandarin"], "language_level": ["native", "good"], "hard_skills": ["ai"], "soft_skills": ["flexible", "organizational skills", "independently", "advanced", "capable", "open-minded", "timely", "clear", "communication", "attention to details", "driven"], "languages_combined": [{"language": "cantonese", "language_level": ["native", "good"]}, {"language": "english", "language_level": ["native", "good"]}, {"language": "mandarin", "language_level": ["native", "good"]}]}, "experience_required": {"duration": ["4 years"], "field": ["logistics", "account management"]}}, {"job_id": "100003009052578", "location_code": "hk", "company": "Ricoh Hong Kong Limited", "job_title": "Business Analyst", "description": "About Geek+\nGeek+ leads the technology\u00a0revolution, by applying advanced\u00a0robotics and AI technologies to realize high-flexibility and intelligent logistics automation solution.\u00a0We are always looking for people who can bring new perspectives and life experiences to our company.\u00a0We understand the value of our people and we strive to constantly satisfy their needs.\u00a0\n\nWe are now seeking for an Solution Engineer to join our team. Are you someone who is driven by curiosity, craves a good challenge? Join us and be part of this exciting adventure!\n\nAbout the role:\n\nCollect required informaiton from clients and conduct data analysis\nSupport Sales Manager as pre-sales support and to provide Geek+ standardize solutions\nPrepare proposal and bidding documents in the solution proposal process\nCreate layouts and material flow diagrams based on Geek+ tools and specific requirements\nClosely work with internal teams including product team, R&D team, solution team and project team\nRequirements:\n\nDegree in Industrial Engineering, Logistics, Mechnical Engineering, or related disciplines\n2 years of experience in supporting sales activities in logistics, 3PL, warehouse, automation, or relevant industies\nKnowledge in AutoCAD and Macrosoft Office is a must\nFamiliar in logistics and automation system will be an advantage\nAttention to details, flexible and creative, able to work under fast-paced environment\nStrong in spoken and written English and Chinese, including Mandarin\nWhat we offer:\n\nFive-day work week\nYoung and energetic work culture with regional exposure\nCozy office environment with\u00a0light refreshments\nDouble pay & attractive performance bonus\nMedical and dental benefits and insurance\n14 to 21 days Annual Leave\nConvenient work location: KCC\nIf your qualifications, experience, and aspirations match our requirements, please send your resume with your current and expected salary to us.\n\nAll information and materials submitted to Geek+ will remain strictly confidential and be treated for recruitment purposes only. Only short-listed candidates will be notified.", "employment_types": ["Full Time", "Permanent"], "selling_points": ["Business analysis and process improvement", "Drive innovation and technology integration", "Exp in process engineering and system development"], "locations": ["Kowloon Bay"], "categories": ["Professional Services", "Business Analysis / Data Analysis", "Information Technology (IT)", "Product Management / Business Analyst", "Others"], "post_time": "2022-01-17T03:36:22Z", "salary": {"currency": null, "max": null, "min": null, "period": "monthly", "term": null}, "salary_visible": false, "title_keywords": ["business analyst"], "responsibilities": ["sales activities", "robotics", "solution proposal", "teams", "data analysis", "create layouts", "logistics"], "requirements": {"degrees": ["degree"], "majors": ["related disciplines", "engineering"], "languages": ["english", "chinese", "mandarin"], "language_level": [], "hard_skills": ["r&d", "sales support", "ai", "analysis", "autocad"], "soft_skills": ["flexible", "work under fast-paced environment", "advanced", "attention to details", "creative", "driven"], "languages_combined": [{"language": "english", "language_level": []}, {"language": "chinese", "language_level": []}, {"language": "mandarin", "language_level": []}]}, "experience_required": {"duration": ["2 years"], "field": ["logistics"]}}, {"job_id": "100003009054556", "location_code": "hk", "company": "Sky Wise Hong Kong Limited", "job_title": "Investment Analyst", "description": "About Geek+\nGeek+ leads the technology revolution, by applying advanced robotics and AI technologies to realize high-flexibility and intelligent logistics automation solution. We are always looking for people who can bring new perspectives and life experiences to our company. We understand the value of our people and we strive to constantly satisfy their needs.\n\nWe are looking for a\u00a0Sales Operations Officer\u00a0to join our team. Are you someone who is driven by curiosity, craves a good challenge? Join us and be part of this exciting adventure!\n\nResponsibilities:\n\n\nConduct sales analysis, review client types and follow-up sales activities\nPrepare sales-related documents, monthly reports, or sales proposal as assigned\nHandle CRM for Asia-Pacific regions\nFollow-up inquiries from Channels as well as direct clients\nPerform ad-hoc duties assigned by supervisor\nRequirements:\nHigher diploma or above with relevant experience in sales operations\nOrganized with good communication skills, detail-minded and independent\nNative in Cantonese, good spoken and written English and Mandarin\nProficient in Microsoft Office (Word, Excel and PowerPoint) and Chinese word-processing\nWhat we Offer:\n\nFive-day work week\nYoung and energetic work culture with regional exposure\nCozy office with light refreshments\nDouble pay plus performance bonus\nMedical, dental benefits and insurance\n14 to 21 days annual leave entitlement\nConvenient work location: KCC\n\nIf your qualifications, experience, and aspirations match our requirements, please send your resume with your current and expected salary to us.\n\nAll information and materials submitted to Geek+ will remain strictly confidential and be treated for recruitment purposes only. Only short-listed candidates will be notified.", "employment_types": ["Full Time", "Permanent"], "selling_points": ["Buy-side investment analyst", "Full lifecycle of investment projects", "Strong analytical and presentation skills"], "locations": ["Kowloon Bay"], "categories": ["Banking / Finance", "Investment", "Professional Services", "Business Analysis / Data Analysis", "Risk Management"], "post_time": "2022-01-17T09:58:48Z", "salary": {"currency": null, "max": null, "min": null, "period": "monthly", "term": null}, "salary_visible": false, "title_keywords": ["analyst"], "responsibilities": ["sales activities", "monthly reports", "related documents", "analysis", "review", "prepare sales", "ad-hoc duties"], "requirements": {"degrees": ["higher diploma or above"], "majors": [], "languages": ["cantonese", "english", "chinese", "mandarin"], "language_level": ["native", "proficient", "good"], "hard_skills": ["excel", "chinese word-processing", "microsoft office", "word", "powerpoint"], "soft_skills": ["communication skills", "organized", "detail-minded", "independent"], "languages_combined": [{"language": "cantonese", "language_level": ["native", "good"]}, {"language": "english", "language_level": ["good"]}, {"language": "chinese", "language_level": ["proficient"]}, {"language": "mandarin", "language_level": ["good"]}]}, "experience_required": {"duration": [], "field": ["relevant experience"]}}, {"job_id": "100003009056176", "location_code": "hk", "company": "Modern Terminals Ltd", "job_title": "Assistant Business Process Analyst  \u52a9\u7406\u696d\u52d9\u6d41\u7a0b\u5206\u6790\u4e3b\u4efb", "description": "About Geek+\nGeek+ leads the technology\u00a0revolution, by applying advanced\u00a0robotics and AI technologies to realize high-flexibility and intelligent logistics automation solution.\u00a0We are always looking for people who can bring new perspectives and life experiences to our company.\u00a0We understand the value of our people and we strive to constantly satisfy their needs.\n\nWe are now seeking for an\u00a0Assistant Manager, Account Management\u00a0to join our team. Are you someone who is driven by curiosity, craves a good challenge? Join us and be part of this exciting adventure!\n\nAbout the role:\nPlan, execute and follow-up after-sales activities directly with key clients\nBuild, sustain and manage relationship with clients at all levels\nLead regular meeting and coordinate with internal teams to fulfill client needs in a timely manner\nHandle complaint cases and queries, divert cases to related functional teams, preapre service reports to clients accordingly\nReview and enhance the current operations to ensure operation runs smoothly\nEnsure constant clear communication with distributors, service partners as well as clients\nRequirements:\n\nDegree holder with 4 years of experience in corporate account management\nExperience in logistics, 3PL, robotic automation is an advantage\nGood spoken and written English and Mandarin, native in Cantonese\nAttention to details, strong planning and organizational skills\nFlexible and open-minded, capable to work with stakeholders independently\nHigh flexibility to suit overseas customers operation hours\nWhat we offer:\n\nFive-day work week\nYoung and energetic work culture with regional exposure\nCozy office environment with\u00a0light refreshments\nDouble pay & attractive performance bonus\nMedical and dental benefits and insurance\n14 to 21 days Annual Leave\nConvenient work location: KCC\nApply immediately if your qualifications, experience, and aspirations match our requirements. Please share your full resume including date of availability, current and expected salary for application.\n\nAll information and materials submitted to Geek+ will remain strictly confidential and be treated for recruitment purpose only. Only shortlisted candidates will be notified.", "employment_types": ["Full Time", "Permanent"], "selling_points": [], "locations": ["Kwai Tsing Area"], "categories": ["Admin & HR", "Clerical / Admin Staff", "Professional Services", "Business Analysis / Data Analysis", "Transportation & Logistics", "Maritime - General"], "post_time": "2022-01-18T03:34:27Z", "salary": {"currency": null, "max": null, "min": null, "period": "monthly", "term": null}, "salary_visible": false, "title_keywords": ["analyst", "assistant"], "responsibilities": ["sales activities", "management", "robotics", "operations", "review", "coordinate with", "teams", "a timely manner", "communication", "logistics", "reports", "plan", "planning"], "requirements": {"degrees": ["degree holder"], "majors": [], "languages": ["cantonese", "english", "mandarin"], "language_level": ["native", "good"], "hard_skills": ["ai"], "soft_skills": ["flexible", "organizational skills", "independently", "advanced", "capable", "open-minded", "timely", "clear", "communication", "attention to details", "driven"], "languages_combined": [{"language": "cantonese", "language_level": ["native", "good"]}, {"language": "english", "language_level": ["native", "good"]}, {"language": "mandarin", "language_level": ["native", "good"]}]}, "experience_required": {"duration": ["4 years"], "field": ["logistics", "account management"]}}, {"job_id": "100003009055432", "location_code": "hk", "company": "Eidea Professional Services Company Limited", "job_title": "Business Valuer / Analyst (Business Valuation Department)", "description": "Roles & Responsibilities\u00a0\u00a0\n\nFacilitate the implementation and support of SAP\u00a0FMS\u00a0Deployment in Asia Pacific Region\u00a0\nWork closely with Point of Sale (POS),\u00a0external\u00a0logistics\u00a0system,\u00a0e-commerce system,\u00a0other retail applications\u00a0and\u00a0different\u00a0teams during design and implementation of SAP Retail functionalities to support Retail Business\u00a0\nWork with 3rd\u00a0party\u00a0external\u00a0vendor, monitor,\u00a0coordinate different project activities\u00a0and align with master project plan\u00a0\u00a0\nFacilitate workshops to collect business requirements\u00a0and mapping global template as well as identify issues and work around solutions\u00a0\nDriving\u00a0and support\u00a0the functional and technical gap analysis\u00a0\nPerform detailed analysis of complex business process requirements and provide appropriate system solutions; identify, interpret, validate and document\u00a0user\u00a0requirements\u00a0\u00a0\nProactively identify and propose business process and/or system enhancements\u00a0\nDrive and support\u00a0data conversion from legacy system to SAP\u00a0and\u00a0coordinate\u00a0with\u00a0user on different data conversion activities\u00a0\nSupport different testing activities including\u00a0functional\u00a0unit test,\u00a0system integration testing\u00a0and end-to-end\u00a0scenarios testing\u00a0\u00a0\nProvide\u00a0key\u00a0user\u00a0training and\u00a0end\u00a0user support as required\u00a0\u00a0\n\nDesired Skills & Experience\u00a0\u00a0\n\nDegree holder or above in Computer Science/ Information Systems/ Software Engineering or others related\u00a0\nAt least\u00a010\u00a0years of work experience\u00a0in relevant\u00a0retail business environments, implementing or using\u00a0retail business processes and applications\u00a0\u00a0\nExperience with SAP\u00a0IS-Retail/FMS\u00a0(in following areas: Planning, Retail Financial,\u00a0Pricing, Value Added Service\u00a0and Promotions or Supply Chain)\u00a0\u00a0\nA consistent track record of successfully delivering projects on time, working with various internal and external teams\u00a0\nDeployment of\u00a0SAP\u00a0retail\u00a0projects\u00a0in different APAC region is desirable\u00a0\nExperience in\u00a0working\u00a0with\u00a0global and diverse team\u00a0\nAbility to support all stages of SAP Retail implementation project\u00a0\u00a0\nProfound understanding of Retail business processes\u00a0\u00a0\nUnderstanding of integration points with the SD, MM, and FI/CO modules\u00a0\u00a0\nProficiency in spoken and written English\u00a0and Mandarin\u00a0\nAbility to multitask and manage multiple deliverables and projects concurrently.\u00a0\u00a0\nAbility to work in a team environment, effectively interacting with others\u00a0\u00a0\nMust be result-oriented and demonstrate a\u00a0can-do\u00a0attitude \u2013 adaptability, flexibility and resourcefulness\u00a0\u00a0\nAbility to provide recommendations with regards to future business and solution opportunities\u00a0\u00a0", "employment_types": ["Full Time", "Part Time", "Permanent"], "selling_points": ["Handle valuation projects", "5-day work, working hour: 10am-6pm, Wan Chai", "Self-motivated, well-organized"], "locations": ["Wan Chai"], "categories": ["Professional Services", "Business Analysis / Data Analysis", "Business Consultancy"], "post_time": "2022-01-18T02:34:37Z", "salary": {"currency": null, "max": null, "min": null, "period": "monthly", "term": null}, "salary_visible": false, "title_keywords": ["valuer", "analyst"], "responsibilities": ["software", "data", "analysis", "systems", "monitor", "teams", "implementation", "design", "coordinate", "project plan", "coordinate with", "business process", "logistics", "testing activities", "testing", "provide recommendations", "collect business requirements", "planning"], "requirements": {"degrees": ["degree holder", "master"], "majors": ["software engineering", "computer science"], "languages": ["english", "mandarin"], "language_level": ["proficiency"], "hard_skills": ["sap", "e-commerce", "pos", "integration", "fms", "analysis", "gap", "vendor", "deployment", "workshops"], "soft_skills": ["can-do attitude", "diverse", "adaptability", "ability to multitask", "result-oriented", "detailed"], "languages_combined": [{"language": "english", "language_level": ["proficiency"]}, {"language": "mandarin", "language_level": ["proficiency"]}]}, "experience_required": {"duration": ["at least 10 years"], "field": ["supply chain", "business", "planning", "team", "retail", "financial"]}}, {"job_id": "100003009055700", "location_code": "hk", "company": "Tata Consultancy Services Limited", "job_title": "SAP Retail Consultant", "description": "Responsibilities:\nCollect business requirement, analyze, formulate and document business flows and process\nConduct business and in-house user requirement analysis\nPerform feasibility study, solution design, system support and develop user manual\nCreate functional specifications for enhancement and new development\nDevelop test plan and conduct system UAT\nData analysis\nRequirements:\nDiploma or above in Computer Science, Information Systems, Statistics or related discipline\nFresh graduates are welcome\nExperience in project management, project lifecycle and direct interaction with end user\nProficiency in SQL, Power BI, SharePoint, Excel and Google Analytics\nKnowledge of data analysis\nCustomer-oriented, good analytical, presentation, communication, problem solving and project management skills\nProficiency in both written and spoken English and Chinese\nPlease send full resume with expected salary and reference no. quoted to Haven of Hope Christian Service, Staff Engagement Department, 7 Haven of Hope Road, Tseung Kwan O, New Territories or via email by clicking \"Apply Now\", or via Whatsapp no. 6507 8148 (with reference no. quoted at the caption) on or before 5 February 2022. Only short-listed candidates will be notified.\nEnquiry: 2703 3227 (Phone); 6507 8148 (Whatsapp).\nFor details about our organization, please visit www.hohcs.org.hk.\nProspective employees are requested to undergo/submit Sexual Conviction Record Check for work relating to children or mentally incapacitated persons before employment. Data collected will be used for recruitment purpose only.\nThis advertisement should not be reproduced, in whole or in part, to other recruitment websites without our prior written permission.", "employment_types": ["Full Time", "Permanent"], "selling_points": ["Deployment of SAP retail projects.", "Experience with SAP IS-Retail/FMS.", "At least 10 years of work experience."], "locations": ["Others"], "categories": ["Professional Services", "Business Analysis / Data Analysis"], "post_time": "2022-01-18T02:52:01Z", "salary": {"currency": null, "max": null, "min": null, "period": "monthly", "term": null}, "salary_visible": false, "title_keywords": ["consultant"], "responsibilities": ["user requirement", "uat", "analysis", "design", "develop", "data analysis", "specifications", "plan"], "requirements": {"degrees": ["diploma or above"], "majors": ["statistics", "computer science"], "languages": ["english", "chinese"], "language_level": ["proficiency"], "hard_skills": ["hope", "google analytics", "excel", "bi", "no", "analysis", "sql", "project management", "problem solving", "whatsapp"], "soft_skills": ["project management skills", "communication", "project management", "customer-oriented", "problem solving", "presentation"], "languages_combined": [{"language": "english", "language_level": ["proficiency"]}, {"language": "chinese", "language_level": ["proficiency"]}]}, "experience_required": {"duration": [], "field": ["project management"]}}, {"job_id": "100003009049773", "location_code": "hk", "company": "Chow Sang Sang Holdings International Limited", "job_title": "Business and Data Analyst", "description": "Responsibilities:\n\nParticipate in business intelligence projects, including designing and creating dashboards, reports or other data delivery solutions\nTransform business users\u2019 requirements into the constructive ideas for data visualization, including the design of data structure and dashboard layouts\nCoordinate internally the BI\u2019s system development, maintenance and enhancements with users and technical departments\nPrepare reports and analysis, provide partners with business insights to support the strategic decisions\nManage BI-related documentation, administrative works & other tool maintenance tasks\nPerform other ad-hoc analyses as assigned\n\nRequirements:\n\nDegree holder, preferably in Statistics, Quantitative Analysis, MIS, Business Administration or other equivalent\n2-3 years relevant experience in BI development, data/business analysis or related fields\nExperience in Qilkview/Nprinting is definitely an advantage\nExcellent in Excel or other analytical tools.\nExperience in retail industry preferred\nGood interpersonal and communication skills, able to work collaboratively with business partners at different levels\nSelf-motivated, enthusiastic, able to work independently with a can-do attitude under a fast-changing environment\nStrong data analytical skill and able to communicate findings effectively with business partners\nInterest in continuously learning by actively seeking opportunities to enrich knowledge and new skills\nGood command of Cantonese, Mandarin and English\nWe offer 5-day-work week with competitive remuneration packages to the right candidate. Interested parties please send your CV with EXPECTED SALARY through the below application procedure.\n\n(Personal data will be used by Chow Sang Sang (CSS) for recruitment only. CSS may refer suitable applications to other vacancies within CSS and its associated companies. We will retain unsuccessful applications for a maximum period of 24 months.)", "employment_types": ["Full Time", "Permanent"], "selling_points": ["Participate in business intelligence projects", "Design of data structure and dashboard layouts", "2-3 years relevant experience in BI development"], "locations": ["Cheung Sha Wan"], "categories": ["Professional Services", "Business Analysis / Data Analysis", "Information Technology (IT)", "Product Management / Business Analyst", "Marketing / Public Relations", "Marketing - Market Research"], "post_time": "2022-01-14T09:13:01Z", "salary": {"currency": null, "max": null, "min": null, "period": "monthly", "term": null}, "salary_visible": false, "title_keywords": ["data analyst"], "responsibilities": ["ad-hoc", "ideas", "visualization", "maintenance", "data", "related documentation", "analysis", "design", "maintenance tasks", "coordinate", "reports", "designing", "prepare reports"], "requirements": {"degrees": ["degree holder"], "majors": ["statistics", "business administration"], "languages": ["cantonese", "english", "mandarin"], "language_level": ["good command"], "hard_skills": ["excel", "analysis", "bi", "analytical skill"], "soft_skills": ["communication skills", "self-motivated", "work independently", "analytical skill", "can-do attitude", "learning", "enthusiastic", "interpersonal"], "languages_combined": [{"language": "cantonese", "language_level": ["good command"]}, {"language": "english", "language_level": ["good command"]}, {"language": "mandarin", "language_level": ["good command"]}]}, "experience_required": {"duration": ["2-3 years"], "field": ["retail industry", "related", "development", "relevant experience", "business analysis"]}}, {"job_id": "100003009052198", "location_code": "hk", "company": "IPSOS Asia Limited", "job_title": "Sr./Research Manager (Quantitative)", "description": "Are you looking for a career at one of the world\u2019s largest research organizations?\u00a0\nTo cope with the transformation of the research industry and also support our rapidly growing business, we are looking for talents to work with us, who will be provided valuable exposure to a wide spectrum of industries, innovative tools & platforms and insightful analytical frameworks in Hong Kong as well as the APAC region.\nWe are currently looking for a Research Manager to work collaboratively to assist with uncovering and communicating key insights, contexts, and actionable strategies. \u00a0This opportunity to join a globally renowned market research organization can provide valuable experience to anyone with a passion for research.\nDepending on experience, candidates may be considered for the role of Senior Research Manager.\nKey Responsibilities:\nManage and coordinate all aspects of the research process - questionnaire writing, research design, analysis and presentation, and preparation of reports based on client objectives\nProvide strategic advice to help the client understand the research questions or methodologies to address key business challenges\nMaintain project budget and work with the team to ensure smooth operation of studies\nMaintain/ strengthen client relationships and leverage solutions to provide advice on research design, insights, and implications\nContent creation for pitches, proposal preparation, and delivery by using Ipsos solutions and tools\nLiaise regularly with all key internal parties and counterparts to ensure that reliable results are delivered to the client in a timely, cost-efficient manner\nCoach juniors to build their research skills and knowledge to ensure the quality of service\n\u00a0Qualifications:\nUniversity degree holder in any discipline\nAt least 3 years of market research experience at a research agency\nAbility to manage complex, multi-faceted project budgets and to create, manage, and commit to a project\nStrong leadership skills in interactions with junior members and clients\nHighly motivated, self-directed and capable of working within tight deadlines\nExcellent written & verbal communication skills with well-developed interpersonal and presentation skills\nWe are committed to equality, treating people fairly, promoting a positive and inclusive working environment, and ensuring diversity of people and views. We recognize that this is important for our business success - a more diverse workforce will enable us to reflect better and understand the world we research and ultimately deliver better research and insight to our clients. We understand the importance of choice and offer a blended work environment - office and work from home.\n\nCome to join us if you consider yourself\u00a0agile, bold, collaborative, determined, and entrepreneurial!\n\nSend us your application to us\u00a0and we will reach back to you for a chat!", "employment_types": ["Full Time", "Permanent"], "selling_points": ["Quantitative Research", "Report Writing", "Proposal Writing"], "locations": ["Hung Hom"], "categories": ["Professional Services", "Business Analysis / Data Analysis", "Marketing / Public Relations", "Marketing - General / Support", "Marketing - Market Research"], "post_time": "2022-01-17T02:26:12Z", "salary": {"currency": null, "max": null, "min": null, "period": "monthly", "term": null}, "salary_visible": false, "title_keywords": ["manager"], "responsibilities": ["liaise", "budgets", "cost", "analysis", "budget", "quality", "market research", "design", "coordinate", "communication", "maintain", "reports", "provide advice", "questionnaire", "internal parties"], "requirements": {"degrees": ["university degree"], "majors": [], "languages": [], "language_level": [], "hard_skills": ["analysis", "agile"], "soft_skills": ["capable", "agile", "leadership skills", "collaborative", "bold", "efficient", "determined", "committed", "diverse", "smooth", "reliable", "interpersonal", "presentation", "communication skills", "positive", "research skills", "passion for", "timely", "presentation skills", "motivated", "innovative"], "languages_combined": []}, "experience_required": {"duration": ["at least 3 years"], "field": ["agency", "research", "market research"]}}, {"job_id": "100003009042482", "location_code": "hk", "company": "Knight Frank Petty Ltd", "job_title": "Analyst, Research & Consultancy", "description": "We are offering you:\n\nAn experience of advanced technologies and working modules\u00a0\nGlobal exposure to work on innovative projects\u00a0\nCoaching and training to solidify your skill set throughout the trainee program\u00a0\nClear career road map & career advancement\nYoung, energetic & friendly work environment\nWork-life balance, fringe benefits with medical/dental insurance coverage, double pay, discretionary bonus, free meal & shuttle bus service\n\nData Science Trainee Program\n\nBe curious and passionate in developing or enhancing machine learning and artificial intelligence algorithms\u00a0\nBring up your insights to dedicated projects with strong analytical and logical thinking\u00a0\nTransform your knowledge and ideas into enterprise solutions\u00a0\n\nTechnical Analyst Trainee Program\n\nLearn and apply the new technologies in building enterprise software systems\nBy offering job rotation, you will experience different IT areas such as Cloud Engineering, Data Analytics, Software Development, Infrastructure & Networking, Cyber Security, Development Operations (DevOps), etc\nExperience the latest working models - Agile development and pair programming\n\nBusiness Analyst Trainee Program\n\nProvide analysis to create requirement specifications for in-house enterprise application systems and recommend solutions for future business processes\u00a0\nPerform business/functional analysis, recommend solutions and create product requirement specifications for in-house enterprise application systems to drive business improvement changes\u00a0\nParticipate in system roll out planning, coordinate with global IT teams, and conduct training to world-wide end users\u00a0\nCollaborate with world-wide business users and global IT teams in system development, implementation planning, acceptance testing, user training and post-implementation review\u00a0\n\nOperations Analyst Trainee Program\n\nIdentify and interpret trends and patterns in datasets to locate influences through simulations, algorithms, and machine learning\u00a0\nGet involved in various data analytics tools, methodologies, reports, and dashboard design and implementation processes\u00a0\n\nWho\u00a0we are\u00a0looking for\n\nBachelor\u2019s degree or above in Computer Science, Information Engineering, Information Systems, Business Analytics, Data Science, Operations Research, Statistics, Mathematics, International Shipping, Operations Management, Global Supply Chain Management or related disciplines\u00a0\nNumerically sensitive, creative aptitude and highly adaptable in a multicultural environment\u00a0\nGood team player with excellent analytical, communication and presentation skills\u00a0\nEmbrace challenge, enjoy team collaboration and an open organization\u00a0\nEager to learn in a fast-paced and dynamic environment\u00a0\nPassionate in pursuing IT professionalism\n\nInterested parties, please submit your application letter together with detailed resume and copies of your latest transcript\u00a0by clicking \u201cApply Now\u201d.\n\n(Data collected will be used for recruitment purpose only.)", "employment_types": ["Full Time", "Permanent"], "selling_points": ["Produce research and analysis reports", "Provide analysis on the Real Estate Market", "1 - 2 years' research experience in property field"], "locations": ["Wan Chai"], "categories": ["Professional Services", "Business Analysis / Data Analysis", "Marketing / Public Relations", "Marketing - Market Research", "Property / Real Estate", "Property Consultancy"], "post_time": "2022-01-12T07:41:04Z", "salary": {"currency": null, "max": null, "min": null, "period": "monthly", "term": null}, "salary_visible": false, "title_keywords": ["analyst"], "responsibilities": [], "requirements": {"degrees": [], "majors": [], "languages": [], "language_level": [], "hard_skills": [], "soft_skills": ["advanced", "innovative", "clear", "friendly", "energetic"], "languages_combined": []}, "experience_required": {"duration": [], "field": []}}, {"job_id": "100003009056261", "location_code": "hk", "company": "Conners Consulting Limited", "job_title": "Assistant Vice President - Consultation & Planning", "description": "\nOur client, a well-known local financial institution in Hong Kong, is looking for a high calibre to join the group.\n\n\nResponsibilities\n\nPlan ahead strategically to support the company growth objectives and enhancing the exising service level\nGather insightful information including market trends, competitor offerings and performance, operational data and tech aspects for analytics purpose\nUse the information gathered to analyze and work out insightful and meaning reports and presentation in order to formulate strategic direction\nWork closely with Business Planning Team to transform high level objectives into detailed action plans which is measurable so as to ensure a smooth execution\nWork closely with other teams (including BD team and IT team) to implement the new initiative smoothly\nInvolve in Sales and Marketing projects from time to time\nRequirements\n\nUniversity graduate in Business or related field\nCandidates from BIG4 business consultation stream will be highly preferable\u00a0\n5 - 7 years\u2019 working experience in business planning, preferably within the financial industry, for example MPF companies, banks, insurance companies and financial institutions\nExperience in data analytics to formulate strategic planning is a MUST\nExperience in involving or taking charge of projects related to sales and marketing will be highly preferred\nGood understanding of investment and insurance products\nStrong sense of responsibility and commitment to excellence\nGood organizational, analytical and multitasking skills\nOpen-minded with a creative mindset\nCandidates with less experience will be considered as Manager\nTo apply, please send your detailed resume to travis[at]connersconsulting[dot]com or contact Travis Poon at 3460 2011 for a confidential discussion.\n\n\nOnly shortlisted candidates will be notified.\n\nApplicants who are not contacted within two weeks may consider their applications unsuccessful.\n\nAll data collected will be used for recruitment purpose only & will be used strictly confidential.\n\nConners Consulting Limited\n2005 Kai Tak Commercial Building 317 Des Voeux Road Central Hong Kong\nTel: (852) 3996 8090\nWebsite:\u00a0www.connersconsulting.com", "employment_types": ["Full Time", "Permanent"], "selling_points": ["Strategic Buisness Planning to Drive Performance", "BIG4 Candidates passionate in in-house consulting", "Experienced in Analyzing Data for useful insights"], "locations": ["Sheung Wan"], "categories": ["Banking / Finance", "Financial Services", "Professional Services", "Business Analysis / Data Analysis", "Business Consultancy"], "post_time": "2022-01-18T03:44:22Z", "salary": {"currency": null, "max": null, "min": null, "period": "monthly", "term": null}, "salary_visible": false, "title_keywords": ["assistant vice president"], "responsibilities": ["data", "teams", "marketing projects", "reports", "plan", "plans", "planning"], "requirements": {"degrees": ["university graduate"], "majors": ["business"], "languages": [], "language_level": [], "hard_skills": ["data analytics"], "soft_skills": ["sense of responsibility", "open-minded", "organizational", "creative mindset", "detailed"], "languages_combined": []}, "experience_required": {"duration": ["5 - 7 years"], "field": ["mpf", "related", "financial industry", "business", "marketing", "financial institutions", "insurance", "planning"]}}, {"job_id": "100003009049825", "location_code": "hk", "company": "Sun Hung Kai Properties Ltd", "job_title": "BUSINESS ANALYST / ASSISTANT BUSINESS ANALYST", "description": "Job Summary\n\nThis role is responsible for conducting research on real estate sectors in the Greater China region and supporting other service lines.\n\n\u00a0Responsibilities\n\n\nProvide analysis on the Hong Kong and Chinese Mainland property markets\nProduce market reports for external and internal distribution\nDevelop and maintain property market and related databases\nPrepare project and pitching presentation materials\nUndertake daily tasks in the Research & Consultancy Dept\u00a0\n\nRequirements\n\n\n\nDegree in real estate, finance, economics, statistics or a related discipline\nAt least 1-2 years\u2019 relevant experience in property / economic research or consultancy\nA team player who can also work independently\nStrong research & analytical skills and strategic thinking\nSelf-motivated\nGood knowledge of the Hong Kong property market preferred\nExcellent spoken and written English and Cantonese, Mandarin is an advantage\nProficient in MS Word, Excel, PowerPoint and Chinese word processing\n\nCandidates with more experience will be considered for the position of Senior Analyst.\n\n\n\nWe will offer an attractive remuneration package to the right candidate. Interested parties please click \"Apply Now\" below to submit your full r\u00e9sum\u00e9 with available date, and current and expected salaries to the Human Resources Department.\n\nTo learn more about working at Knight Frank, please click here to view our corporate video.\n\nYou are encouraged to read our digital brochure \u201cWhy Knight Frank\u201d to understand how we attract and inspire people to join our exceptional firm.\n\nKnight Frank is an equal opportunity employer. All information submitted will be treated in the strictest confidence and used only for recruitment purposes in accordance with our personal data policy.", "employment_types": ["Full Time", "Permanent"], "selling_points": ["5 yrs' exp in business analysis (non-property)", "Financial analysis for business opportunities", "Operational analysis to investigate ongoing issue"], "locations": ["Wan Chai"], "categories": ["Accounting", "Financial Analyst", "Banking / Finance", "Analyst", "Professional Services", "Business Analysis / Data Analysis"], "post_time": "2022-01-14T09:17:27Z", "salary": {"currency": null, "max": null, "min": null, "period": null, "term": null}, "salary_visible": false, "title_keywords": ["business analyst", "assistant"], "responsibilities": ["analysis", "develop", "maintain", "reports", "databases"], "requirements": {"degrees": ["degree"], "majors": ["finance", "economics", "statistics"], "languages": ["cantonese", "english", "chinese", "mandarin"], "language_level": ["advantage", "excellent", "proficient"], "hard_skills": ["excel", "chinese word processing", "powerpoint", "analytical skills", "ms word"], "soft_skills": ["self-motivated", "work independently", "strategic thinking", "analytical skills", "team player"], "languages_combined": [{"language": "cantonese", "language_level": ["excellent"]}, {"language": "english", "language_level": ["excellent"]}, {"language": "chinese", "language_level": ["proficient"]}, {"language": "mandarin", "language_level": ["advantage", "excellent"]}]}, "experience_required": {"duration": ["at least 1-2 years"], "field": ["research", "relevant experience"]}}, {"job_id": "100003009052098", "location_code": "hk", "company": "AVISTA Valuation Advisory Limited", "job_title": "Senior Valuer/ Assistant Manager, Valuation and Advisory Services", "description": "Requirements:\n\nBachelor\u2019s degree in Finance, Business, Accounting or related disciplines. An MBA degree is an added advantage\nMinimum 5 years\u2019 relevant experience in business analysis\nStrong business acumen and numerical sense\nGood analytical and communication skills\nGood command of spoken and written English and Chinese\nFamiliar with PC software e.g. MS Word, Excel, PowerPoint\nResponsibilities:\n\nPerform financial analysis for business opportunities, including financial modelling, valuation analysis and scenario simulations\nConduct insightful operational analysis to investigate ongoing issue\nAssist the team with research to provide business insight and context for business recommendations\nSupport with putting together presentations for senior management\nSource and develop market intelligence available to the team, including monitoring of news and other sources of public information\nExecute relevant industry analysis against competitors\nParticipate in ad hoc projects to understand market development and identify opportunities for business units\nSupport the monitoring and reporting of business units and financial performance of business units\n(Candidates with less experience will be considered as Assistant Business Analyst.)\n\nGood remuneration and attractive fringe benefits will be offered to the successful applicant. Interested parties please apply with full resume, present and expected salary, available date by clicking \"Apply Now\".\n\nFor further information, please visit our company website: www.shkp.com.\n\nWe are an equal opportunity employer and welcome applications from all qualified candidates. All personal data collected will be used for recruitment purpose only.\u00a0 Applicants not hearing from us within 3 months may consider their applications unsuccessful.\u00a0 All personal data collected will be destroyed within 24 months.", "employment_types": ["Full Time", "Permanent"], "selling_points": ["Handle HK, PRC & overseas valuation works", "2-4 yrs relevant experience in international firms", "More experience will be considered as AM"], "locations": ["Wan Chai"], "categories": ["Professional Services", "Business Analysis / Data Analysis", "Business Consultancy", "Property / Real Estate", "Others"], "post_time": "2022-01-17T02:05:32Z", "salary": {"currency": null, "max": null, "min": null, "period": "monthly", "term": null}, "salary_visible": false, "title_keywords": ["senior valuer", "assistant manager,"], "responsibilities": ["valuation", "reporting", "business opportunities", "analysis", "monitoring", "presentations", "develop", "financial analysis", "ad hoc projects", "senior management"], "requirements": {"degrees": ["degree", "bachelor"], "majors": ["related disciplines", "finance", "business", "accounting"], "languages": ["english", "chinese"], "language_level": ["good command"], "hard_skills": ["excel", "analysis", "acumen", "powerpoint", "pc", "ms word"], "soft_skills": ["business acumen", "communication skills"], "languages_combined": [{"language": "english", "language_level": ["good command"]}, {"language": "chinese", "language_level": ["good command"]}]}, "experience_required": {"duration": ["minimum 5 years"], "field": ["business analysis", "relevant experience"]}}, {"job_id": "100003009051235", "location_code": "hk", "company": "RecruitFirst Limited", "job_title": "Finance Analyst -American FMCG Company (up to $32K)", "description": "Job Nature: Valuation Advisory\n\nJob Description and Responsibilities:\n\n\nAssist manager to perform valuation works for investment property, land & building, equipment and business in HK, the PRC & overseas\u00a0\nConduct market research, data analysis, modelling and report preparation\nPerform valuation assignments for various purposes, such as IPO, M&A and financial reporting purposes\nInvolve in ad hoc advisory projects such as market research analysis, investment project analysis and feasibility study.\n\nJob Requirements:\n\n\nDegree holder in Real Estate, Surveying, Property Management, Mathematic, Statistics or related disciplines\n2-4 years relevant working experience in international firms would be a plus\nProficiency in both written and spoken English, Cantonese and Mandarin\nFluent in Mandarin will be a plus\nGood team player and logical mind\nStrong communication skills and problem-solving skills\nProficient in MS Excel\nAmbition to grow fast personally and with the firm\nBusiness trip to PRC and overseas may be required\nCandidate with more experience can be considered as Assistant Manager\nBenefits: We offer attractive remuneration package including a 5-day work week, medical insurance and good career prospect to the suitable candidate.\n\nApplication Procedure: Please send your CV with expected salary by clicking \"Apply Now\".\n\nPersonal data will be used for recruitment purpose only.", "employment_types": ["Full Time"], "selling_points": [], "locations": ["Kowloon Bay"], "categories": ["Professional Services", "Business Analysis / Data Analysis", "Business Consultancy", "Sales, CS & Business Devpt", "Business Development"], "post_time": "2022-01-15T05:31:16Z", "salary": {"currency": null, "max": null, "min": null, "period": "monthly", "term": null}, "salary_visible": false, "title_keywords": ["analyst"], "responsibilities": ["valuation", "ad hoc", "conduct market research", "analysis", "market research", "data analysis", "financial reporting", "report"], "requirements": {"degrees": ["degree holder"], "majors": ["related disciplines", "statistics", "surveying"], "languages": ["cantonese", "english", "mandarin"], "language_level": ["proficiency", "fluent"], "hard_skills": ["problem-solving skills", "plus", "ms excel"], "soft_skills": ["problem-solving skills", "communication skills", "good team player"], "languages_combined": [{"language": "cantonese", "language_level": ["proficiency"]}, {"language": "english", "language_level": ["proficiency"]}, {"language": "mandarin", "language_level": ["fluent", "proficiency"]}]}, "experience_required": {"duration": ["2-4 years"], "field": ["relevant working experience"]}}, {"job_id": "100003009055673", "location_code": "hk", "company": "Hutchmed Group (HK) Limited", "job_title": "Senior Manager / Manager of Sustainability", "description": "Responsibilities\nSupport the development of corporate sustainability strategies that reflect the environmental, social, and governance issues important to HUTCHMED;\nCo-ordinate sustainability activities across Hong Kong, Shanghai, Suzhou and New Jersey operations;\nOversee implementation of sustainability goals and targ\u00adets across the R&D, manufacturing, China comm\u00adercial joint ventures and U.S. R&D / comm\u00adercial businesses;\nImprove implementation methodologies, set annual milestones, and establish reporting mechanisms to inform employees and executive leadership on progress;\nSupport communication with investors and investment analysts regarding HUTCHMED\u2019s sustainability position and progress (e.g. large mutual funds).\nCommunicate with ESG research firms and indices (e.g. MSCI, ISS Oekom, Sustainalytics);\nSupport the Board of Directors\u2019 Sustainability Committee in strategic discussions and the exec\u00adution of sustain\u00adability focus areas;\nProduce an annual corporate sustain\u00adability report, including data collection, measure\u00adment & analysis, stakeholder engagement and content devel\u00adopment;\nLiaise with the corporate public relations, investor rela\u00adtions, commercial, marketing, Human Resources technical teams (mainly China & U.S.) to coordinate and drive sustain\u00adability positioning and actions;\nOrganise internal sustainability events and other enga\u00adgements to promote and inspire staff.\nRequirements\n\n8 years minimum experience in a corporate environment in sustainability, compli\u00adance or finance, with some track record of delivering sustain\u00adability programmes;\nAbility to influence change with internal business part\u00adners without direct reporting relationships;\nComfortable working with all levels of employees, from senior executives to front-line individual contributors;\nStrong analytic, written and oral communication skills in English and preferably Mandarin Chinese;\nAbility to manage and work collaboratively with cross-functional and cross-geographical working groups;\nAbility to clearly articulate business value of sustain\u00adability investment.\nAbility to multi-task, set priorities, and meet tight deadlines;\nEntrepreneurial spirit to identify and act on new opportunities or improvements;\nEducated to degree level in a sustainability, or business-related subject, or relevant work experience;\nInterest or expertise in healthcare industry.\n\n\nSalary and benefits will be commensurate with experience.\u00a0Please send detailed resume with\u00a0current and\u00a0expected salary\u00a0by clicking \u201cAPPLY NOW\u201d in the below.\nWe are an equal opportunity employer and welcome applications from all qualified candidates. The information provided will be treated in strict confidence and used only for consideration of application for relevant/similar post(s) within the CK Hutchison Group of Companies. Applicants not having heard from us within four weeks from the date of this advertisement may consider their application unsuccessful. All personal data of unsuccessful applicants will be destroyed after the recruitment exercise when no longer required.", "employment_types": ["Full Time", "Permanent"], "selling_points": [], "locations": ["Hung Hom"], "categories": ["Professional Services", "Business Analysis / Data Analysis", "Business Consultancy", "Medical Services", "Pharmaceutical"], "post_time": "2022-01-18T02:50:40Z", "salary": {"currency": null, "max": null, "min": null, "period": "monthly", "term": null}, "salary_visible": false, "title_keywords": ["senior manager", "manager"], "responsibilities": ["communicate with", "reporting", "operations", "analysis", "teams", "implementation", "communication", "coordinate", "data collection", "liaise with", "report"], "requirements": {"degrees": ["degree"], "majors": ["business"], "languages": ["mandarin chinese", "english"], "language_level": [], "hard_skills": [], "soft_skills": ["communication skills", "oral", "meet tight deadlines", "multi-task", "articulate"], "languages_combined": [{"language": "mandarin chinese", "language_level": []}, {"language": "english", "language_level": []}]}, "experience_required": {"duration": ["8 years"], "field": ["related", "finance", "business", "sustainability"]}}, {"job_id": "100003009054810", "location_code": "hk", "company": "China Everbright Securities International Company Limited", "job_title": "Associate / Senior Associate, Business Management (Business control & transaction surveillance)", "description": "\u00a0Ref: ASSO/BM/170122DB/78\n\nResponsibilities\n\n\nSupport ongoing transaction surveillance tasks to detect potential regulatory and internal policy violations, ensure the update of transactional surveillance workflow policy and procedure in accordance with regulatory and internal requirements\nCollaborate with Product team on annual due diligence for over-the-counter (OTC) products, contribute to process automation, improvement projects to strengthen process control and efficiency\nCoordinate with IT and relevant business units to review and execute regular Business Continuity Planning (BCP)/drill\nParticipate in project development and user acceptance testing of new business initiatives e.g. Operational Risk Management, Business Intelligence, Customer Experience\nRequirements\n\nDegree holder in Business Administration, Business Management, Risk Management, Finance or related discipline\nMinimum 2 years\u2019 of relevant experience in financial services industry, with exposure to risk control, business analysis, compliance or project management a definite advantage\nGood exposure to wealth management & brokerage business is a plus\nStrong business sense, analytical mindset and problem solving skills\nGood interpersonal and communication skills, able to work independently\nProficiency in MS Office applications\nGood command of both written and spoken English and Chinese. Fluency in Putonghua an advantage\nWe offer a competitive remuneration package to the right candidate. If you are interested in the post, please send your resume together with your present and expected salaries by clicking \u201cApply Now\u201d.\u00a0\n\n\nFor more information about China Everbright Securities International Company Limited, please visit www.ebshk.com.\n\nWe are an equal opportunity employer and welcome applications from all qualified candidates. All applications will be treated in the strictest confidence. Personal data provided will be used for recruitment purposes only. The job applicant will assume all or any risks arising out of or in connection with the job application transmission process prior to our actual receipt of the same including but not limited to accidental or unauthorized loss or disclosure of personal information, to which we will not be responsible in any way.\n\nUnder the Personal Data (Privacy) Ordinance, you may request access to, and / or correction of your personal data in relation to your application. If you wish to do so, please email to us.", "employment_types": ["Full Time", "Permanent"], "selling_points": [], "locations": ["Causeway Bay"], "categories": ["Banking / Finance", "Financial Services", "Professional Services", "Business Analysis / Data Analysis", "Risk Management"], "post_time": "2022-01-17T11:15:53Z", "salary": {"currency": null, "max": null, "min": null, "period": "monthly", "term": null}, "salary_visible": false, "title_keywords": ["senior associate", "associate"], "responsibilities": ["collaborate with", "due diligence", "control", "business continuity", "business initiatives", "management", "review", "coordinate with", "testing", "planning"], "requirements": {"degrees": ["degree holder"], "majors": ["finance", "risk management", "business", "business administration"], "languages": ["putonghua", "english", "chinese"], "language_level": ["fluency", "advantage", "good command"], "hard_skills": ["business management", "plus", "analysis", "project management", "problem solving skills", "ms office"], "soft_skills": ["communication skills", "work independently", "business sense", "project management", "problem solving skills", "interpersonal"], "languages_combined": [{"language": "putonghua", "language_level": ["fluency", "advantage"]}, {"language": "english", "language_level": ["good command"]}, {"language": "chinese", "language_level": ["good command"]}]}, "experience_required": {"duration": ["minimum 2 years"], "field": ["compliance", "project management", "relevant experience", "business analysis", "financial services industry"]}}, {"job_id": "100003009053970", "location_code": "hk", "company": "Hang Seng Bank Ltd", "job_title": "Business Transformation Manager", "description": "HANG SENG INDEXES COMPANY LTD\n\nHang Seng Indexes Company Limited (\u2018Hang Seng Indexes Company\u2019) manages and compiles the Hang Seng Family of Indexes, which cover stocks listed in Hong Kong and Mainland China. Our index series includes the Hang Seng Index, the Hang Seng China Enterprises Index and the Hang Seng TECH Index, as well as Stock Connect, Greater Bay Area and sector-related indexes. As at the end of 2019, assets under management in products passively tracking indexes in the Hang Seng Family of Indexes had reached a total of about US$38\u00a0billion.\n\nHang Seng Indexes Company is a wholly owned subsidiary of Hang Seng Bank. Our company is a team of professionals who strives for delivering quality, efficient and world-class index complier services to customers and financial institutions around the world.\n\nWe are currently seeking a high caliber professional to join our department as\u00a0Business Transformation\u00a0Manager.\n\nPrincipal responsibilities\n\nProvide project management and consultancy services on project/ system implementation, workflow design, and process re-engineering to various stakeholders in the Company;\nActively monitor the project scope and resources to meet the project schedule and budget;\nCoordinate between users and internal IT team or external vendors to ensure an effective project implementation;\nProactively manage all the potential risks on projects and recommend mitigating measures if required;\nAssist in collection of user requirements, conduct user acceptance tests, prepare training materials and conduct user training to support system/ project roll out\n\n\nRequirements\n\nUniversity degree in Information System, Business Administration or a related discipline;\nMinimum eight years of working experience, preferably with system project management or business analyst background in financial institutions;\nPrevious experience as a project manager in medium-to-large scale projects will be a plus;\nStrong managerial, project management, communications, analytical, problem-solving, planning and organizing skills;\nAbility to work independently, cope with pressure and meet tight deadlines;\nProficiency in both spoken and written English and Chinese;\nKnowledge of index industry and HK and China stock market is an advantage;\nExperience in Agile project management is preferable;\nPMP/ Lean Six Sigma certification is an advantage;\nFamiliar with HSBC Change Framework, Data Platform and Analytics would be an advantage;\nGreat sense of ownership and servicing mindset to ensure efficient and effective customer service processes\nCandidates with less experience will be considered for the position of\u00a0Assistant\u00a0Business Transformation Manager.\n\nIf you would like to explore other opportunities at Hang Seng Hong Kong, please visit\u00a0www.hangseng.com/careers/\u00a0for details.\n\nThe health and safety of our employees and candidates is very important to us. Due to the current situation related to the Novel Coronavirus (2019-nCoV), we\u2019re leveraging our digital capabilities to ensure we can continue to recruit top talent at the HSBC Group. \u00a0As your application progresses, you may be asked to use one of our digital tools to help you through your recruitment journey.\u00a0 If so, one of our Resourcing colleagues will explain how our video-interviewing technology will be used throughout the recruitment process and will be on hand to answer any questions you might have.\n\nAll information provided by applicants will be used only for recruitment purposes and will be used strictly in accordance with the Bank's personal data policies, a copy of which may be obtained by the applicant upon request. Unless otherwise instructed in writing by the applicant concerned, applicants may be considered for other suitable positions within the Bank and its related companies. The personal data of unsuccessful job applicants may be retained for a maximum of two years from the date when the job application is rejected and such data may be retained for a longer period if there is a subsisting reason that obliges the Bank to do so, after which the personal data will be destroyed.", "employment_types": ["Full Time", "Permanent"], "selling_points": [], "locations": ["Not Specified"], "categories": ["Banking / Finance", "Others", "Professional Services", "Business Analysis / Data Analysis", "Others", "Others"], "post_time": "2022-01-17T07:52:41Z", "salary": {"currency": null, "max": null, "min": null, "period": "monthly", "term": null}, "salary_visible": false, "title_keywords": ["manager"], "responsibilities": ["budget", "monitor", "implementation", "design", "coordinate", "project management", "schedule", "re-engineering"], "requirements": {"degrees": ["university degree"], "majors": ["business administration"], "languages": ["english", "chinese"], "language_level": ["proficiency"], "hard_skills": ["plus", "lean", "agile", "problem-solving", "information system", "reason", "project management", "six sigma", "pmp"], "soft_skills": ["efficient", "work independently", "meet tight deadlines", "agile", "problem-solving", "project management", "customer service", "novel"], "languages_combined": [{"language": "english", "language_level": ["proficiency"]}, {"language": "chinese", "language_level": ["proficiency"]}]}, "experience_required": {"duration": ["minimum eight years"], "field": ["project management", "financial institutions", "business"]}}, {"job_id": "100003009053701", "location_code": "hk", "company": "Hong Kong Aircraft Engineering Co Ltd", "job_title": "Coordinator (Inventory Management)", "description": "HAECO ITM Limited is a joint venture between HAECO (Hong Kong Aircraft Engineering Co. Ltd) and Cathay Pacific, providing inventory technical management services to different airline customers in Hong Kong and around the world. Customers anticipate to benefit saving from the ITM services through synergy of component pooling, sound technical know-how of component engineering, repair and supplier management.\n\nHXITM is now looking for candidates who are interested in this business for the position of\u00a0Coordinator (Inventory Management).\n\nScope of Duties:\u00a0\n\nAnalyze provisioning parameter, customer fleet data, part reliability and repair time performance to determine the optimum stock level and provisioning policy\nManaging Float module template and incorporating changes as approved\nRecommend changes in inventory level and support model where appropriate based on analysis and simulation on part shortage promptly, by gathering information, interfacing with functional teams, and monitoring shortage recovery continuously\nProduce and deliver regular inventory reports and maintain relevant database to support inventory operations planning and control in an effective and efficient manner\nInteract, communicate, and influence functional teams for appropriate action based on stock level alert and failed pick analysis\n\nRequirements:\u00a0\n\nA minimum of 1 year of relevant experience, preferably in Inventory Management, Operations, Planning field or Material control.\nFresh graduates are welcome\nA recognized Degree in Supply Chain, Business Analysis, or related disciplines\nKnowledge or experience in aviation industry would be an advantage\nGood analytical and problem-solving skills, able to think systematically and holistically\nSkillful in preparing analytical report and presentations with MS Excel, MS Access, MS PowerPoint\nGood command of English, both spoken and written\n\nHow to Apply:\n\nPlease send your resume with expected salary, quoting the employer's reference no., to: Human Resources Department - Talent & Partnership Team, Hong Kong Aircraft Engineering Company Limited, 80 South Perimeter Road, Hong Kong International Airport, Lantau, Hong Kong OR submit your application via\u00a0https://careers.haeco.com/hkg/job-opening-itm/\n\nCandidates not contacted 4-6 weeks after submission of applications and/or interviews may consider their application unsuccessful.\n\nAll information provided by candidates will be treated in strict confidence and will be used for employment purpose only.", "employment_types": ["Full Time", "Permanent"], "selling_points": ["A minimum of 1 year of relevant experience", "Fresh graduates are welcome", "Good analytical and problem-solving skills"], "locations": ["Airport Area"], "categories": ["Professional Services", "Business Analysis / Data Analysis", "Transportation & Logistics", "Inventory / Warehousing", "Supply Chain"], "post_time": "2022-01-17T07:23:08Z", "salary": {"currency": null, "max": null, "min": null, "period": "monthly", "term": null}, "salary_visible": false, "title_keywords": ["inventory management", "coordinator"], "responsibilities": ["control", "data", "operations", "analysis", "inventory", "teams", "monitoring", "repair", "maintain", "reports", "database", "planning"], "requirements": {"degrees": ["degree"], "majors": ["related disciplines", "business"], "languages": ["english"], "language_level": ["good command"], "hard_skills": ["no", "aircraft", "analysis", "presentations", "ms excel", "problem-solving skills", "ms powerpoint"], "soft_skills": ["problem-solving skills", "confidence"], "languages_combined": [{"language": "english", "language_level": ["good command"]}]}, "experience_required": {"duration": ["minimum of 1 year"], "field": ["inventory management", "relevant experience", "planning"]}}, {"job_id": "100003009052197", "location_code": "hk", "company": "IPSOS Asia Limited", "job_title": "Temporary Research Assistant (Temp to Perm)", "description": "Are you looking for a career at one of the world\u2019s largest research organizations?\u00a0\n\nTo cope with the transformation of the research industry and also support our rapidly growing business, we are looking for talents to work with us, who will be provided valuable exposure to a wide spectrum of industries, innovative tools & platforms and insightful analytical frameworks in Hong Kong as well as the APAC region.\n\nWe are looking for a Temporary Research Assistant to support projects throughout the entire process.\n\n\n\nKey Responsibility:\n\nLiaise with internal teams and counterparts to ensure projects run smoothly, on time, and within budget\nCommunicate with project management and operations teams to positively impact project outcome\nCoordinate and manage data entry of project costs into internal costing program based on research target specifications\nAssist in analyzing research data and secondary sources to deliver stories and narratives to focus on data insights\nSupport content creation for pitches, proposal preparation and delivery by using Ipsos solutions and tools\n\nQualifications:\n\nUniversity degree holder in any discipline\nAnalytical skills and data literacy required\nStrong team player with a positive attitude\nAbility to work in a fast-paced environment\nGood organization and communication skills essential\n\nWe are committed to equality, treating people fairly, promoting a positive and inclusive working environment, and ensuring diversity of people and views. We recognize that this is important for our business success - a more diverse workforce will enable us to reflect better and understand the world we research and ultimately deliver better research and insight to our clients. We understand the importance of choice and offer a blended work environment - office and work from home.\n\nCome to join us if you consider yourself\u00a0agile, bold, collaborative, determined, and entrepreneurial!\n\nSend us your application\u00a0and we will reach back to you for a chat!", "employment_types": ["Full Time", "Part Time", "Permanent", "Temporary", "Contract", "Internship", "Freelance"], "selling_points": ["Data analysis", "Quantitative research", "Project Management"], "locations": ["Hung Hom"], "categories": ["Professional Services", "Business Analysis / Data Analysis", "Marketing / Public Relations", "Marketing - General / Support", "Marketing - Market Research"], "post_time": "2022-01-17T02:26:11Z", "salary": {"currency": null, "max": null, "min": null, "period": "monthly", "term": null}, "salary_visible": false, "title_keywords": ["research assistant"], "responsibilities": ["communicate with", "support projects", "data entry", "data", "operations", "budget", "teams", "coordinate", "project management", "communication", "specifications", "liaise with", "costs"], "requirements": {"degrees": ["university degree"], "majors": [], "languages": [], "language_level": [], "hard_skills": ["project management", "focus", "agile", "analytical skills"], "soft_skills": ["communication skills", "agile", "determined", "fast-paced environment", "collaborative", "bold", "analytical skills", "positive attitude", "project management", "committed", "team player", "diverse", "focus", "innovative", "positive"], "languages_combined": []}, "experience_required": {"duration": [], "field": []}}, {"job_id": "100003009046452", "location_code": "hk", "company": "Pioneer Dynamic Limited", "job_title": "Data Analyst", "description": "Job Highlights\n\nStable company, energetic working environment\n\nmulti-task, meet deadline\n\nJob Description\n\n\u2022 Responsible for preparing product and production data analysis required by business - including quality, production and merchandising teams\n\n\u2022 Communicate closely with senior level management and leadership team to come up with executive summaries and salient points\n\n\u2022 Manage and organize data from various systems\n\n\u2022 Understand the key performance indicators with different teams and provide support to teams to run the business effectively.\n\n\u2022 Cooperate with IT peers on system enhancement/ data collection from vendor partners.\n\n\u2022 Conduct UAT and support training related activities on reporting and data analytics.\n\nSkills & experiences required\n\n\u2022 At least 3+ years of relevant working experience\n\n\u2022 Degree holder in Business Administrations, IT or related discipline\n\n\u2022 Technically proficient in Excel formula and report building Office 365\n\n\u2022 Experience in building data and analytics solutions and data visualization\n\n\u2022 Experience in collaborating with vendor for creating tracking or reporting tools\n\n\u2022 Knowledge in Cisco, Java would be an advantage\n\n\u2022 Fluent in both written & verbal English\n\nEducation\nAssociate Degree/Diploma or above", "employment_types": ["Full Time"], "selling_points": ["5 days work", "grade a working complex", "annual leave"], "locations": ["Ngau Tau Kok"], "categories": ["Professional Services", "Business Analysis / Data Analysis"], "post_time": "2022-01-13T11:18:10Z", "salary": {"currency": "HKD", "max": 24999, "min": 20000, "period": "monthly", "term": null}, "salary_visible": true, "title_keywords": ["data analyst"], "responsibilities": ["reporting", "management", "provide support", "tracking", "uat", "visualization", "data", "systems", "merchandising", "teams", "quality", "data analysis", "data collection", "cooperate with", "report"], "requirements": {"degrees": ["associate degree", "diploma or above", "degree holder"], "majors": ["business", "it"], "languages": ["english"], "language_level": ["fluent"], "hard_skills": ["excel", "office 365", "java", "data analytics", "analysis", "vendor", "data visualization"], "soft_skills": ["multi-task", "responsible", "stable", "energetic", "leadership"], "languages_combined": [{"language": "english", "language_level": ["fluent"]}]}, "experience_required": {"duration": ["at least 3+ years"], "field": ["relevant working experience"]}}, {"job_id": "100003009047118", "location_code": "hk", "company": "Zero Finance Hong Kong Limited", "job_title": "IT Business Analyst", "description": "In this role, you will perform:\n\nManage business requirements gathering, analysis and documentation. Act as a bridge between business users, technical team and vendors to ensure the business requirements well address business needs\nDevelop, review, and edit requirements, specifications, business processes and recommendations related to a proposed solution\nWork closely with development team and external vendors to ensure the requirements can be completed timely.\nPrepare test plans, conduct testing, coordinate UAT and provide user training.\nProvide technical support to Sales / Business Unit team on product development, pre- and post-sales process\n\nTo be successful in this role, you should meet the following requirements:\u00a0\n\nDiploma holder or above in Computer Science / Information Technology or other related disciplines\nPreferably 1 to 3 years relevant experience\nKnowledge in banking / finance operations and mobile technology is a plus\nProficiency in design and prototyping tools, ideally MS Office, Axrue RP, MS Visio\nPractical experience in analyzing and verifying user requirements versus business processes to develop programmable documents\nGood command of written and spoken English and Chinese (including Putonghua)\nSelf-motivated, positive, able to work under pressure with emphasis on deliverables\nGood communication and interpersonal skills\n\n\n\nCompany Website:\u00a0https://www.zerofinance.hk/zh/\u00a0\n\nAttractive remuneration package will be offered to the right candidate. Please apply with full resume stating present and expected salary to us by\u00a0clicking\u00a0\u201cAPPLY NOW\u201d.\n\n(Personal data collected will be used for recruitment purpose only.)", "employment_types": ["Full Time", "Permanent"], "selling_points": ["IT Business Analyst", "Design and prototyping tools", "Knowledge in banking / finance operations"], "locations": ["Sheung Wan"], "categories": ["Professional Services", "Business Analysis / Data Analysis", "Information Technology (IT)", "Product Management / Business Analyst", "Mobile / Wireless Communications"], "post_time": "2022-01-14T02:22:43Z", "salary": {"currency": null, "max": null, "min": null, "period": "monthly", "term": null}, "salary_visible": false, "title_keywords": ["business analyst"], "responsibilities": ["uat", "technical support", "analysis", "review", "design", "develop", "testing", "coordinate", "finance operations", "specifications", "communication", "recruitment", "banking", "documentation", "plans", "personal data", "company website", "work under pressure"], "requirements": {"degrees": ["diploma holder"], "majors": ["related disciplines", "computer science", "information technology"], "languages": ["putonghua", "english", "chinese"], "language_level": ["good command"], "hard_skills": ["plus", "analysis", "mobile", "documentation", "ms office"], "soft_skills": ["self-motivated", "timely", "communication and interpersonal skills", "positive", "work under pressure"], "languages_combined": [{"language": "putonghua", "language_level": ["good command"]}, {"language": "english", "language_level": ["good command"]}, {"language": "chinese", "language_level": ["good command"]}]}, "experience_required": {"duration": ["1 to 3 years"], "field": ["business", "relevant experience"]}}, {"job_id": "100003009050197", "location_code": "hk", "company": "Henderson Land Development Company Limited", "job_title": "SENIOR ORGANIZATION AND METHODS OFFICER / BUSINESS ANALYST", "description": "Ref. No.: JDB/HLD21/SOMO\n\n\nDegree in Business Administration / Information Technology or related disciplines\n4 - 6 years\u2019 relevant experience in Organization and Methods (O&M) / business analysis with solid experience in performing business process analysis & developing business requirements\nPerform UAT, prepare user manuals and conduct user training\nEnhance internal operational procedures, including workflow and procedures reviews\nProficiency in PC applications and MS Office (including Visio)\nStrong analytical mindsetwith good interpersonal and communication skills\nExcellent report writing skills in both English and Chinese\nGood command of spoken English and Chinese (including Putonghua)\nKnowledge and experience in SQL will be an advantage\nCandidates with less experience will be considered for junior posts\nAttractive salary and fringe benefits will be offered to the successful candidates. Please apply with full resume by mail to\u00a0Human Resources Department, Henderson Land Development Co. Ltd., 71/F, Two International Finance Centre, 8 Finance Street, Central, Hong Kong\u00a0or by fax at\u00a02905 1855\u00a0or visit our homepage at\u00a0http://www.hld.com\u00a0or\u00a0by clicking \"Apply Now\".\n\n\n\n(Please quote the ref. no. on letter)\n\nPersonal data provided by job applicants will be used for recruitment purpose only.\u00a0", "employment_types": ["Full Time", "Permanent"], "selling_points": ["Medical Allowance", "Education Allowance", "Free Lunch"], "locations": ["Central"], "categories": ["Professional Services", "Business Analysis / Data Analysis", "Information Technology (IT)", "Support", "Property / Real Estate", "Others"], "post_time": "2022-01-14T09:55:38Z", "salary": {"currency": null, "max": null, "min": null, "period": "monthly", "term": null}, "salary_visible": false, "title_keywords": ["officer", "business analyst"], "responsibilities": ["uat", "analysis", "procedures", "developing", "communication", "business process", "operational procedures", "business analysis", "report", "administration"], "requirements": {"degrees": ["degree"], "majors": ["related disciplines", "business administration", "information technology"], "languages": ["putonghua", "english", "chinese"], "language_level": ["excellent", "good command"], "hard_skills": ["no", "analysis", "writing skills", "pc applications", "sql", "ms office"], "soft_skills": ["communication skills", "interpersonal", "writing skills"], "languages_combined": [{"language": "putonghua", "language_level": ["good command"]}, {"language": "english", "language_level": ["excellent", "good command"]}, {"language": "chinese", "language_level": ["excellent", "good command"]}]}, "experience_required": {"duration": ["4 - 6 years"], "field": ["developing", "sql", "business process analysis", "business", "relevant experience", "business analysis"]}}, {"job_id": "100003009054672", "location_code": "hk", "company": "A.S. Watson Retail (HK) Limited", "job_title": "Accountant (Financial Reporting & Internal Control) - Group Finance", "description": "Come and join a Winning Team\n\nWe are Awesome!\n\nWhy Should You Join Us?\n\nAt ASW, we believe in our people, in teamwork and the importance of your personal growth.\u00a0If you are looking for the opportunity to join our award-winning international family with 15,000+ stores across 25 markets in Asia and Europe, the ASW family welcomes you\u2026\u00a0 #BePartofMORE\n\nYou can enjoy:\n\nComprehensive Medical and Life insurance coverage, including your spouse and children!Professional training and career advancement opportunities!\nAttractive ACCA and CPA Australia Recognized Employer Partnership for F&A talents!\nExclusive company pension schemes!\u00a0 Marriage, Maternity and Paternity Leave!\nConvenient office location, less than 5 min. walk from MTR!\nContemporary workplace with Onside Clinic, Lactation Rooms, free drinks and chill out areas!\nWell-equipped Gym inside our office building, plus fitness and interest class packages!\nFree round-trip lunchtime shuttle bus services to Shatin!\nExclusive shopping discount, Bazaar Sales for our people only!\n\nRole Purpose:\n\nThe role suits individuals with inquisitive who can take complex issues, pull together data from multiple sources, simplify the issue and then present clear and concise conclusions.\n\nThe role handles routine accounting work and requires you to work with experts from different areas of the business. \u00a0You will be working with diverse teams and in sharing opinions and be able to engage and influence others.\n\nA typical day in this Role:\u00a0\n\nWork with Finance Shared Service Centre and other departments in month-end closing, financial reporting, and other management reporting\nDevelop value added reports for facilitating management decision or business performance\nPerform internal control assignment\nCoordinate with other departments to compile financial information\nUndertake and participate other duties and ad-hoc projects as assigned\n\nThis job is a good fit for You if:\u00a0\n\nYou are keen to\u00a0join retail industry\nYou are commercially minded, with strong analytical and problem solving skills\nYou are\u00a0equipped with influencing skills are key \u2013 proven ability to influence others using logic and structured arguments\n\nWhat we look for:\n\nBachelor\u2019s Degree in Accounting, Business or related discipline with professional accounting qualification and good understanding of\u00a0IFRS.\nMinimum 3 years experience in accounting and audit experience for accounting firms and/ or MNCs. With commercial experience in internal control is an advantage\u00a0\nDetail-oriented, independent and strong analytical and problem solving skills\nProficiency in Excel, Word, PowerPoint,\u00a0and knowledge of Oracle or similar systems.\nFluent in spoken and written Chinese and proficient in English\n\nWhat is holding you back?\u00a0\n\nDon\u2019t miss out on this great chance to shape your life!\u00a0\n\nApply now!\n\nInterested parties please e-mail your full resume in WORD FORMAT with expected salary to our company email (shown in our Company Profile).\n\n\nWe are an equal opportunity employer and welcome applications from all qualified candidates. The information provided will be treated in strict confidence and be used only for consideration of your application for relevant / similar posts within the A.S. Watson Group.\n\n\nApplicants not hearing from us within 6 weeks from the date of advertisement may consider their applications unsuccessful. All personal data of unsuccessful applicants will be destroyed within 12 months from the date of application.\u00a0", "employment_types": ["Full Time", "Permanent"], "selling_points": ["Financial Reporting", "Annual Budget, Forecast review and analysis", "Perform internal control assignment"], "locations": ["Shatin Area"], "categories": ["Accounting", "Accountant", "Audit", "Professional Services", "Business Analysis / Data Analysis"], "post_time": "2022-01-17T10:29:25Z", "salary": {"currency": null, "max": null, "min": null, "period": "monthly", "term": null}, "salary_visible": false, "title_keywords": ["accountant"], "responsibilities": ["management", "other duties", "data", "systems", "teams", "coordinate with", "audit", "develop", "month-end closing", "reports", "financial reporting", "management reporting", "ad-hoc projects", "insurance", "internal control"], "requirements": {"degrees": ["degree", "bachelor"], "majors": ["business", "accounting"], "languages": ["english", "chinese"], "language_level": ["proficient", "fluent"], "hard_skills": ["excel", "acca", "plus", "ifrs", "oracle", "word", "powerpoint", "chill", "cpa", "problem solving skills", "internal control"], "soft_skills": ["independent", "keen", "teamwork", "detail-oriented", "clear", "diverse", "analytical and problem solving skills", "comprehensive", "structured"], "languages_combined": [{"language": "english", "language_level": []}, {"language": "chinese", "language_level": ["fluent", "proficient"]}]}, "experience_required": {"duration": ["minimum 3 years"], "field": ["commercial", "audit experience", "accounting"]}}, {"job_id": "100003009050154", "location_code": "hk", "company": "Magic Search Limited", "job_title": "CRM Analyst (Premium Lifestyle Brand)", "description": "Our client, a premium lifestyle brand, is currently looking for a CRM Analyst to support their business expansion in local markets.\n\nThe Job:\n\nConduct comprehensive customer and business insights based on track history and sales data and identify strengths and weaknesses of existing CRM programmes; analyse customers' purchasing\u00a0behaviour\nDevelop short-, mid- and long-term strategies for clienteling campaigns and customer sales maintenance and growth\u00a0\nTo analyze the client data and make recommendations / insights on sales and CRM programs with data support\nTo ensure the client data's accuracy and privacy\nDevelop internal programmes for front-line staff to improve clienteling skillsets and mindsets\nProvide support in CRM events\nInvolves in small part of marketing activities, manage eDMs, support brand programme, optimizing member experience across the various tiers whenever required.\u00a0\nThe Candidate\n\nDegree in Business, Marketing, Mathematics, Statistics, Sciences and related disciplines\n5+ years of experience gained in data analysis\nSensitivity to numbers with good logic and analytic skills is a must\nKnowledge in SPSS, SQL, SAS is a MUST\n\nAll information provided will be treated in strict confidence and used solely for recruitment purposes. To apply, please quote current and expected salary and Click \"Apply Now\"", "employment_types": ["Full Time"], "selling_points": ["CRM Analysis", "SQL", "EDM"], "locations": ["Not Specified"], "categories": ["Professional Services", "Business Analysis / Data Analysis", "Marketing / Public Relations", "Marketing - Market Research", "Marketing - Marketing Communication"], "post_time": "2022-01-14T09:53:05Z", "salary": {"currency": null, "max": null, "min": null, "period": "monthly", "term": null}, "salary_visible": false, "title_keywords": ["crm analyst"], "responsibilities": ["make recommendations", "provide support", "edms", "maintenance", "data", "develop", "data analysis", "recruitment", "analyse"], "requirements": {"degrees": ["degree"], "majors": ["mathematics", "statistics", "related disciplines", "business", "marketing"], "languages": [], "language_level": [], "hard_skills": ["small", "maintenance", "sas", "analysis", "sql", "make", "analytic skills"], "soft_skills": ["make recommendations", "sensitivity", "comprehensive", "confidence"], "languages_combined": []}, "experience_required": {"duration": ["5+ years"], "field": ["data analysis", "marketing", "brand"]}}, {"job_id": "100003009043999", "location_code": "hk", "company": "Amorepacific Hong Kong Co Ltd", "job_title": "Senior Business Analyst", "description": "Job Responsibilities:\n\nAssist in establishing a centralized database for Archives and Records Management\nInvolve in formulating and implementing Archives and Records Management programmes\nLiaise logistics with other department for records transfer, Undertake the acquisition, appraisal, accessioning, description and filing of historical material\nNegotiate and liaise with service providers and maintain and operate the archives collection management system\nHandle audio-visual editing and digitization tasks as well as Design, co-ordinate and participate in outreach programmes to promote the archives services\nAssist in handling the process of copyright clearance and compliance\nCollaborate across internal teams to use the archival materials\nAd hoc duties as required\n\nJob Requirements:\n\nDegree holders in Business studies with qualification in Archives management\n6+ years working experience in archives, less experience will consider as Archives Officer\nExcellent written and spoken in both English and Chinese, and Chinese typing\nA team player with self-motivation, detail orientated and work independently\nProficient in operating computerized systems\nWilling to develop new skills to fit with the job requirement\nRequire lifting and moving boxes up to 10KG", "employment_types": ["Full Time", "Permanent"], "selling_points": ["Work closely with Brand to design customer journey", "Execute business performance analytics", "4-5 years working experience in business analysis"], "locations": ["Wan Chai"], "categories": ["Accounting", "Financial Analyst", "Professional Services", "Business Analysis / Data Analysis", "Marketing / Public Relations", "Marketing - Market Research"], "post_time": "2022-01-13T02:44:45Z", "salary": {"currency": null, "max": null, "min": null, "period": "monthly", "term": null}, "salary_visible": false, "title_keywords": ["senior business analyst"], "responsibilities": ["liaise", "collaborate", "management", "ad hoc duties", "editing", "compliance", "teams", "design", "maintain", "logistics", "database", "visual", "liaise with", "audio"], "requirements": {"degrees": ["degree"], "majors": ["business"], "languages": ["english", "chinese"], "language_level": ["excellent"], "hard_skills": ["typing"], "soft_skills": ["team player", "self-motivation", "detail orientated", "work independently"], "languages_combined": [{"language": "english", "language_level": ["excellent"]}, {"language": "chinese", "language_level": ["excellent"]}]}, "experience_required": {"duration": ["6+ years"], "field": []}}, {"job_id": "100003009044831", "location_code": "hk", "company": "HSBC Group", "job_title": "Senior Business Analyst - Digital Business Services", "description": "Key Responsibilities\n\nWork as business partners to support Brand Function to deliver their business goal; Ensure effective strategy implementation and monitoring performance\nExecute business performance analytics including implement modeling development and refinement to maximize customer retention and value, gather customer insights through data mining and analysis, identify up-sell & cross-sell opportunities to increase customer value\nWork closely with Brand Function to design customer journeys, conduct customer segmentation and best targeting tactics as well as effectiveness evaluation.\nProduce reporting analytics to enable identification of key trends or issues in the Business / Operating Unit that necessitate further analysis and discussion\nConnect with Headquarter Strategy Team on different aspect of the business e.g. analysis of internal financial information and external economic condition and its impact on business operations, future market outlook etc.\nSupport in Dashboards development including data modelling and design\nAny ad hoc activities arising\u00a0 \u00a0\n\nKey Stakeholders\n\nThis position\u2019s primary interfaces are (engagement, interaction, etc)\n\n\nLocal: Brand GM, Brand Marketing & Operation Team, Finance Operation Team, HR Team\nHQ: Strategy Team\n\nRequirements:\n\nDegree in Business, Statistics or Mathematics related field\n4-5 years working experience in business/data analysis or business intelligence preferably gained from Retail Industry\nStrong business acumen and analytical skillset\nEnjoy challenges and willing to push back & confront status quo when necessary\nExcellent communication, interpersonal & influencing skills\nAbility to work independently & effectively with all levels within an organization\nHigh proficient in SQL, MS Excel.\nExperience in statistical tool e.g. SPSS and BI tools e.g. Tableau is highly preferred.\u00a0 Knowledge in Salesforce Marketing Cloud will be a plus.\n\nCandidate with less experience will be considered as Business Analyst.\n\n\n\n\nWe offer opportunities for development in addition to a competitive remuneration and benefit package to the right candidate. Interested parties please click \"Apply Now\" for application.\n\nPersonal data provided by job applicants will be used strictly for recruitment purpose only.", "employment_types": ["Full Time"], "selling_points": ["One of the world\u2019s leading international banks", "Excellent Career Progression", "Senior Management Opportunity"], "locations": ["Central"], "categories": ["Banking / Finance", "Professional Services", "Business Analysis / Data Analysis"], "post_time": "2022-01-13T06:26:28Z", "salary": {"currency": null, "max": null, "min": null, "period": "monthly", "term": null}, "salary_visible": false, "title_keywords": ["senior business analyst"], "responsibilities": ["reporting", "ad hoc", "data", "operations", "analysis", "monitoring", "customer insights", "implementation", "design", "hr", "evaluation", "data mining"], "requirements": {"degrees": ["degree"], "majors": ["mathematics", "business", "statistics"], "languages": [], "language_level": [], "hard_skills": ["plus", "bi", "salesforce", "analysis", "tableau", "sql", "ms excel", "business intelligence", "acumen"], "soft_skills": ["business acumen", "work independently", "interpersonal", "communication"], "languages_combined": []}, "experience_required": {"duration": ["4-5 years"], "field": ["data analysis", "business", "retail industry"]}}, {"job_id": "100003009042306", "location_code": "hk", "company": "HKT Consumer Group", "job_title": "Customer Data Analyst", "description": "The health and safety of our employees and candidates is very important to us. Due to the current situation related to the Novel Coronavirus (2019-nCoV), we\u2019re leveraging our digital capabilities to ensure we can continue to recruit top talent at HSBC. \u00a0As your application progresses, you may be asked to use one of our digital tools to help you through your recruitment journey. \u00a0If so, one of our Resourcing colleagues will explain how our video-interviewing technology will be used throughout the recruitment process and will be on hand to answer any questions you might have.\n\nSome careers have more impact than others.\n\nIf you\u2019re looking for a career where you can make a real impression, join HSBC and discover how valued you\u2019ll be. Whether you want a career that could take you to the top, or simply take you in an exciting new direction, HSBC offers opportunities, support and rewards that will take you further.\n\nIT Operations manages the IT infrastructure and supporting services that are critical for HSBC employees and customers, such as cost-efficient hardware, system software, middleware and databases, data centres, voice and data networks, ATMs, desktops and other devices.\n\nThe area comprises five functions: Client Services, Enterprise Services and Architecture, Data Centre and Service Management, Relationship Management, Project Management and Risk and Administration. Collectively, these areas define and deliver HSBC\u2019s technology strategy to support the Group\u2019s goals.\n\nWe are currently seeking a high calibre professional to join our team as a Senior Business Analyst.\n\nPrincipal Responsibilities\n\nCollaborate with the business to conduct feasibility analysis on the initiatives with deliverables like Business cases, where proposals are signed-off by the client\nWork with domain architects to propose and drive appropriate IT solutions to fulfil client and business requirements\nConduct comprehensive analysis of the existing system (if any) and creates analysis of customer journeys and product functionalities\nIdentifies and recommends process improvements that significantly reduce workloads or improve quality\nEnsure that the functional information is appropriately conveyed to the technical teams as per project needs\nProduce relevant project documentation as and when required with the Agile TOM\nAbility to manage conflicting business requirements and project scope\nCoordinate with testing team for review of test cases and defect management\nAccountable for making and keeping the product a success\u2014by ensuring that it offers a strong value proposition to the customers and users and that it creates the desired business benefits\nUnderstands risk exposure to the bank and help senior colleagues manage it\n\nRequirements\n\nExperience\n\nDegree Holder of Computer Science or Business Administration discipline preferred, with 5-7 years of relevant experience\nExperience in banking industry and especially in Banking products / applications related to commercial banking\nFull life cycle Business Analysis experience from requirements definition, testing, through to implementation\nProven experience of working in large, complex programmes across multiple streams and geographies is preferred\n\nSkills & Competencies\n\nStrong analytical ability with a high degree of attention to details and problem analysis techniques\nStrong interpersonal, communication and presentation skills with good command of written and spoken English\nSelf-motivated, enthusiastic and fast learner\nAppetite and desire to initiate change and execute strategy\nAbility to work independently and as part of a team\nFlexible and able to adapt in a fast-paced, changing environment\nFluent communication in Mandarin is a plus\n\nYou\u2019ll achieve more when you join HSBC.\nwww.hsbc.com/careers\n\nHSBC is committed to building a culture where all employees are valued, respected and opinions count. We take pride in providing a workplace that fosters continuous professional development, flexible working and opportunities to grow within an inclusive and diverse environment. Personal data held by the Bank relating to employment applications will be used in accordance with our Privacy Statement, which is available on our website.\n\nIssued by The Hongkong and Shanghai Banking Corporation Limited.", "employment_types": ["Full Time"], "selling_points": [], "locations": ["Quarry Bay"], "categories": ["Professional Services", "Business Analysis / Data Analysis", "Marketing / Public Relations", "Marketing - Direct Marketing"], "post_time": "2022-01-12T06:56:58Z", "salary": {"currency": null, "max": null, "min": null, "period": "monthly", "term": null}, "salary_visible": false, "title_keywords": ["data analyst"], "responsibilities": ["collaborate with", "management", "analysis", "review", "quality", "teams", "coordinate with", "testing", "project documentation"], "requirements": {"degrees": ["degree", "degree holder"], "majors": ["business administration", "computer science"], "languages": ["english", "mandarin"], "language_level": ["good command", "fluent"], "hard_skills": ["analysis", "plus"], "soft_skills": ["flexible", "self-motivated", "work independently", "communication", "committed", "presentation skills", "diverse", "attention to details", "enthusiastic", "fast learner", "interpersonal"], "languages_combined": [{"language": "english", "language_level": ["good command"]}, {"language": "mandarin", "language_level": ["fluent"]}]}, "experience_required": {"duration": ["5-7 years"], "field": ["banking industry", "business administration", "related", "testing", "commercial", "relevant experience", "banking", "business analysis"]}}, {"job_id": "100003009055575", "location_code": "hk", "company": "GreySpark Partners (HK) Limited", "job_title": "Business Development Trainee/Executive", "description": "Your role:\n\nResponsible for lead generation and prepare tracking reports to support various marketing campaigns;\nDevelop Dashboards to facilitate efficient data analysis for product performance, customer profiles and campaign effectiveness;\nConduct quantitative analysis and data mining to support management decisions and provide data-driven recommendations;\nOrganize and prepare regular\u00a0reports relating to business performance and service usage;\nConduct user acceptance test of in-house-developed applications.\n\nTo succeed in this role\n\nUniversity graduate in Computer Science, Information Technology, Data Science, Statistics or relevant discipline;\n3 \u2013 4 years\u2019 relevant experience, preferably in data analysis, database programming or database management\nProficient in SAS, SQL, Python or other data mining tools;\nPractical experience in data visualization tools (e.g. Qlik View/Sense, Power BI or Tableau);\nGood analytical and problem solving skills, able to work under tight timeline;\nSelf-motivated and able to accomplish multiple tasks with minimal supervision;\nGood\u00a0interpersonal and communication skills and\u00a0able to work with people at all levels;\nGood command in both spoken and written English;\nCandidate with less experience will be considered for the position of Senior Customer Data Analyst.\n\nHKT is an equal opportunity employer and welcomes applications from all qualified candidates. Information provided will be treated in strict confidence and will only be used for recruitment-related purposes. Personal data provided by job applicants will be used strictly in accordance with the employer's privacy statement (http://www.hkt.com/privacy-statement), a copy of which will be provided immediately upon request.", "employment_types": ["Full Time", "Permanent"], "selling_points": ["Immediate exposure within Capital Markets", "Fresh Grad welcomed", "Attractive remuneration package"], "locations": ["Central & Western Area"], "categories": ["Professional Services", "Business Analysis / Data Analysis"], "post_time": "2022-01-18T02:45:03Z", "salary": {"currency": null, "max": null, "min": null, "period": "monthly", "term": null}, "salary_visible": false, "title_keywords": ["executive", "trainee"], "responsibilities": ["management", "visualization", "power bi", "data", "analysis", "customer data", "develop", "data analysis", "communication", "reports", "recruitment", "marketing campaigns", "database", "data mining", "personal data", "tracking"], "requirements": {"degrees": ["university graduate"], "majors": ["data science", "statistics", "computer science", "information technology"], "languages": ["english"], "language_level": ["good command"], "hard_skills": ["bi", "sas", "analysis", "tableau", "python", "sql", "database programming", "data visualization", "data mining", "problem solving skills"], "soft_skills": ["efficient", "communication skills", "self-motivated", "confidence", "responsible", "multiple tasks", "analytical and problem solving skills", "interpersonal", "driven"], "languages_combined": [{"language": "english", "language_level": ["good command"]}]}, "experience_required": {"duration": ["4 years"], "field": ["data analysis", "database management", "relevant experience", "programming", "database"]}}, {"job_id": "100003009049750", "location_code": "hk", "company": "China Construction Bank (Asia) Corporation Limited", "job_title": "AM/Mgr/AVP, Business Analytics & Campaign Management", "description": "GreySpark Partners\u00a0are a Business & Technology Consultancy, specialising in mission- critical areas of the Capital Markets industry.\n\nWe provide the expert advice necessary to deliver change to investment banks, hedge funds and asset management firms. The deep understanding of the financial services sector we have gained through our collective experience, creativity and tenacity enable us to consistently deliver the best results for our clients.\n\nAt GreySpark, you will join a working environment that fosters entrepreneurship, leadership and knowledge building. GreySpark is committed to providing each employee with the resources and support necessary to develop professional growth. That is why our organisation is fundamentally built on merit, respect, team effort and loyalty.\n\nWe are now looking for a Business Development Trainee/Business Development Executive (dependent on experience) to join our fast- paced, fast- growing organisation.\n\nWhat we offer:\n\nA challenging, dynamic role in a Capital Markets consultancy\nThe ability to carve out your own niche and attain levels of seniority within a growing company\nCompetitive salary and generous package\nThe chance to join a creative, energetic and dynamic team\n\nJob Specification\n\nThis position will suit those who enjoy generating new business as well as maintaining long-term relationships with clients. As an ambitious, highly motivated and enthusiastic individual, you will be excited by the challenge of helping to drive GreySpark\u2019s profitability, within a supportive and \u2018all-for-one\u2019 environment. You will be responsible for managing the entire sales cycle, including initiating contact, meeting with potential clients, formulating and presenting proposals, agreeing on commercial terms, closing business, overseeing ongoing account management and building long-term relationships with clients.\n\nAdditionally, you will participate in interviewing Consultants who will work on client engagements.\n\nThis is a great opportunity to work in an exciting, fast-paced and challenging role that will suit target- driven, results-orientated individuals.\n\n\u00a0Skills/Experience required:\n\nSales experience: 0-2 years, preferably in a service-led organisation\nA naturally confident communicator with excellent presentation and inter- personal skills\nStrong prospecting skills with an energetic phone presence\nSelf-starter with a track record of exceeding targets\nExperience of appointment making for field sales and key account management will be a plus\nThe ability to build relationships with senior level executives will be another plus\nEntrepreneurial approach/ mind- set\nUniversity Degree educated\nFluent in written & spoken English\nFresh Grad is welcomed, extensive training will be provided to those with less experience\n\nThe following would be advantageous:\n\nKnowledge of Capital Markets, Payments, FinTech and broader financial services", "employment_types": ["Full Time", "Permanent"], "selling_points": ["Business analytics", "Campaign Management", "data analytics in credit card, loan and deposit"], "locations": ["Kowloon Bay"], "categories": ["Banking / Finance", "Analyst", "Professional Services", "Business Analysis / Data Analysis"], "post_time": "2022-01-14T09:11:30Z", "salary": {"currency": null, "max": null, "min": null, "period": "monthly", "term": null}, "salary_visible": false, "title_keywords": [], "responsibilities": [], "requirements": {"degrees": [], "majors": [], "languages": [], "language_level": [], "hard_skills": [], "soft_skills": [], "languages_combined": []}, "experience_required": {"duration": [], "field": []}}, {"job_id": "100003009046175", "location_code": "hk", "company": "Target Sourcing Services Hong Kong Limited", "job_title": "Business Analyst (Raw Materials team)", "description": "Job Description:\n\nFocus on supporting analytics in credit card, unsecured personal loan and deposit products\u00a0\nCarry out marketing campaign execution which involves list extraction, campaign result tracking and post-campaign analysis and provide recommendations for subsequent campaigns\nPerform statistical analysis to identify business opportunities, and present key findings to senior management and/or other stakeholders with actionable recommendation\nDesign, develop and automate regular business reports to monitor business performance\nManage the implementation of the Business Intelligence and Data Warehouse project / enhancement\n\nRequirements:\u00a0\u00a0\n\n\nUniversity Degree or above in Statistics, Data Science, Computer Science, Information Management or related discipline\nMinimum 3 years\u2019 experience in quantitative analysis, and consumer finance /insurance/banking related business\nStrong analytical with basic understanding of different statistical methodologies and knowledge of scorecard development\nDetail-oriented, strong business sense, influencing skill, communication and interpersonal skills\nAble to work independently and under pressure\nSolid experience in SAS, Python, SQL, OLAP, Microsoft Excel VBA, PowerPoint\nProficiency in spoken & written English & Chinese\n\n\u00a0* Please state your current and expected salary in the application as a reference.\u00a0\n\nApplicants who are not contacted within 8 weeks may consider their applications unsuccessful and their personal data will be retained by the bank for a period up to two years.\n\nAll information provided by applicants will be used for recruitment purposes only and will be used strictly in accordance with the bank\u2019s personal data policies, a copy of which will be provided upon request.", "employment_types": ["Full Time"], "selling_points": [], "locations": ["Hung Hom"], "categories": ["Professional Services", "Business Analysis / Data Analysis", "Information Technology (IT)", "Data Scientist"], "post_time": "2022-01-13T09:50:31Z", "salary": {"currency": null, "max": null, "min": null, "period": "monthly", "term": null}, "salary_visible": false, "title_keywords": ["business analyst"], "responsibilities": ["identify business opportunities", "data", "analysis", "monitor", "implementation", "design", "develop", "provide recommendations", "reports", "senior management", "tracking"], "requirements": {"degrees": ["degree or above"], "majors": ["data science", "statistics", "computer science"], "languages": ["english", "chinese"], "language_level": ["proficiency"], "hard_skills": ["vba", "basic", "sas", "analysis", "powerpoint", "microsoft excel", "sql", "python"], "soft_skills": ["work independently", "under pressure", "business sense", "detail-oriented", "communication and interpersonal skills"], "languages_combined": [{"language": "english", "language_level": ["proficiency"]}, {"language": "chinese", "language_level": ["proficiency"]}]}, "experience_required": {"duration": ["minimum 3 years"], "field": ["related", "finance", "sql", "business", "banking", "insurance"]}}, {"job_id": "100003009048475", "location_code": "hk", "company": "WHARF CHINA ESTATES LIMITED \u4e5d\u9f8d\u5009\u4e2d\u570b\u7f6e\u696d\u6709\u9650\u516c\u53f8", "job_title": "BUSINESS MANAGER", "description": "Client Details:\n\nOur client\u00a0is an American multinational manufacturer and marketer of branded consumer foods sold through retail stores, it offers attractive salary and great career progress for potential candidate.\n\nResponsibilities\nAssist in forecasting, annual budgeting\nEnsure effective strategy implementation and monitoring performance\nPerform financial analysis,\u00a0variance analysis, commentary reports, trade specific promotion evaluation on sales performance\u00a0\nConduct feasibility studies to explore more potential business opportunities\nRequirements\n\nDegree in business or finance related fields\n2-3 years working experience in business/financial analysis (FMCG industry is preferable)\nExperience with SAP is an advantage\nStrong critical thinking, excellent analytical skills with good communication skill\nInterested parties, please click \u2018Apply Now\u2019. Feel free to contact Hailey Chan at 3702 3826 for further details.", "employment_types": ["Full Time", "Permanent"], "selling_points": ["Preparation of budget and business planning", "Perform financial analysis and business modelling", "Experience in retail / FMCG / shopping mall"], "locations": ["Not Specified"], "categories": ["Professional Services", "Business Analysis / Data Analysis", "Sales, CS & Business Devpt", "Business Development", "Marketing / Public Relations", "Marketing - Market Research"], "post_time": "2022-01-15T03:49:59Z", "salary": {"currency": null, "max": null, "min": null, "period": "monthly", "term": null}, "salary_visible": false, "title_keywords": ["manager"], "responsibilities": ["annual budgeting", "sales performance", "business opportunities", "monitoring", "implementation", "financial analysis", "variance analysis", "reports", "evaluation", "forecasting"], "requirements": {"degrees": ["degree"], "majors": ["finance", "business"], "languages": [], "language_level": [], "hard_skills": ["financial analysis", "fmcg industry", "sap", "analytical skills"], "soft_skills": ["communication skill", "analytical skills"], "languages_combined": []}, "experience_required": {"duration": ["2-3 years"], "field": ["fmcg", "business", "financial"]}}, {"job_id": "100003009049675", "location_code": "hk", "company": "P & A Consultant Limited", "job_title": "Sr. Data Analyst / Data Analyst/ Data Engineer  X2 - (Top Urgent )", "description": "WeLab is a leading fintech company in Asia, \u00a0which operates one of first licensed digital banks in Asia \u2013 WeLab Bank, as well as multiple leading online financial services businesses including WeLend and WeLab Bank in Hong Kong, WeLab Digital (\u6211\u6765\u6570\u79d1), Taoxinji (\u6dd8\u65b0\u673a), Wallet Gugu (\u94b1\u5939\u8c37\u8c37) and Tianmian Tech (\u5929\u5195\u79d1\u6280)\u00a0in Mainland China and Maucash in Indonesia. WeLab aims to bring joy to everyone\u2019s financial journey. We strive to improve people\u2019s lives by reinventing financial services through game-changing technology. We put our people first, whether it\u2019s our customers or our employees.\n\nAs the only homegrown Hong Kong fintech to receive a virtual banking license, we aim to reinvent and redefine the banking experience by building a bank we love.\n\nWe are an energetic and passionate team that can deliver and execute. We are looking for other intellectually curious, open-minded and smart-working individuals who are just as passionate as we are about making financial services enjoyable. Now you have the opportunity to join us on our journey to achieve our vision and be part of building a better financial future for everyone.\n\nAbout you:\n\nYou're a go-getter with mad juggling skills (or multiple hats) who can thrive in a fast-paced, agile environment\nYou have a strong thirst for knowledge and are driven to find solutions that don't exist yet\nYou are comfortable with ambiguity and extremely resourceful (in your past life you could've been a detective)\nYou always find a way to get things done without sacrificing the quality of your work, integrity and values. No task is off limits for you.\nYou are humble and prioritize the success of the team over your own with an eagerness to help those around you\nYou don't shy away from challenges and have the ability to bounce back from setbacks\n\nWhat you\u2019ll do and what success looks like in this role\u00a0\n\nIdentify, articulate and quantify any potential risk exposure in the Bank\u2019s daily workflows and procedures\nDevelop effective risk control measures with business unit owners\nMonitor the progress of risk control measure implementation\nPerform periodic thematic review to ensure the Bank\u2019s routine operations are executed in a strict adherence of specifications stated in procedure manuals\nFormulate, drive and implement process enhancement initiatives to improve operational efficiency, risk effectiveness and to deliver quality customer service\nTrack the Bank\u2019s risk exposure in its daily operations and escalate to the management for any material breach of risk controls\n\nWhat is required and what we\u2019re looking for\u00a0\n\nDegree or above in Business Administration, Economics, Finance, Operation Management, Risk Management or related discipline\nAt least 3 - 5 years relevant experience, preferably in retail banking and fintech industry\nPassionate in shaping a brand-new banking experience to the market\nSolid knowledge of internal control principles and ability to assess risk in various dimensions\nStrong understanding of digital/online/ virtual retail banking operations\nGood communication skills and able to articulate complex information for audiences of different backgrounds\nExcellent command of spoken and written Cantonese and English\nLess experience candidate will be considered as Officer\n\nWeLab perks:\n\nCompetitive salary\nLearning and development stipend, because we value lifelong learning and believe the best way to invest in our employees is to encourage them to continue to learn\nWork hard and laugh lots (chicken wings and french toast, etc.) with a high-performing, fun and diverse team\nHappiness Dollars for spending on anything that makes you happy\nCoffee stipend\nConveniently located office surrounded by diverse and delicious lunch options\nLively office with gaming consoles and a ping pong table\nFun extracurricular activities with your colleagues like hiking, yoga, badminton, wine tasting, dragon boat racing, rock climbing, etc.\nEmployee referral bonuses\n\nAwards & recognition:\n\nFinancial Times (FT) 2020 Asia-Pacific High-Growth Companies \u2013 #2 ranked company\n2020 CNBC Disruptor 50 List \u2013 #11, only company included from Hong Kong and just one of five from Asia\n\nWe offer competitive salary package to the successful candidate.\u00a0 If you are interested in joining this exciting team, please apply with resume via the \"Apply\" button.\n\nAll information provided by applicants will be used for recruitment purposes only. Information of unsuccessful applicants will be destroyed within 24 months of receipt.", "employment_types": ["Full Time"], "selling_points": [], "locations": ["Tsuen Wan Area"], "categories": ["Professional Services", "Business Analysis / Data Analysis", "Information Technology (IT)", "Product Management / Business Analyst", "Data Scientist"], "post_time": "2022-01-15T03:50:34Z", "salary": {"currency": null, "max": null, "min": null, "period": "monthly", "term": null}, "salary_visible": false, "title_keywords": ["data analyst", "data engineer"], "responsibilities": ["control", "management", "operations", "review", "quality", "procedures", "monitor", "develop", "implementation", "communication", "daily operations", "specifications", "customer service", "banking", "internal control", "assess risk", "administration"], "requirements": {"degrees": ["degree or above"], "majors": ["finance", "economics", "business administration", "risk management"], "languages": ["cantonese", "english", "french"], "language_level": ["excellent"], "hard_skills": ["no", "joy", "agile", "fun", "go", "internal control", "mad"], "soft_skills": ["passionate", "communication skills", "agile", "resourceful", "open-minded", "integrity", "prioritize", "diverse", "customer service", "learning", "articulate", "energetic", "driven"], "languages_combined": [{"language": "cantonese", "language_level": ["excellent"]}, {"language": "english", "language_level": ["excellent"]}, {"language": "french", "language_level": []}]}, "experience_required": {"duration": ["at least 3 - 5 years"], "field": ["brand", "banking experience", "retail banking", "relevant experience", "banking"]}}, {"job_id": "100003009048671", "location_code": "hk", "company": "Hong Kong Examinations and Assessment Authority", "job_title": "Manager \u2013 Assessment Technology and Research (Ref: ATR/01/810)", "description": "Responsibilities:\n\n\n\nDrive company business by conducting market analysis, business forecast, category and brand specific review to identify business opportunities and support fact-based decisions\nManage routine sales performance tracking and trend analysis by key channels, packs, category & brands\nProvide commercial operation support including budget preparation, forecasting, and pricing\nSupport Revenue Growth Management (RGM) and Pricing strategies and execution\nPrepare and report on Company\u2019s result against budget and forecast. \u00a0Work with relevant business units to identify and mitigate potential risks\nCollaborate with key stakeholders to design and deliver core commercial strategies, practices and innovative solutions, to grow SCCHK profitability, and deliver value to our customers\nSupport Commercial Leadership team to manage relevant analysis on various commercial projects\n\nRequirements:\n\n\nDegree in Business / Marketing or equivalent\nMinimum 2 years of working experience, preferably in FMCG but not a must\nSolid data analysis experience with good numeric sense, and able to work with data in different format from various sources\nGood business acumen and strategic mindset, attention to details with agile delivery\nComfortable in communicating with different parties and liaise for better results\nStrong presentation skills and able to articulate analysis insights to audience from different backgrounds\nExperience in FMCG Sales and Marketing functions, with a focus on Category Management/ Shopper Insights/ Business Intelligence is highly preferred\nExperience in Project Management is preferred\nStrong sense of responsibility, self-motivated and result oriented\nKnowledge in PowerBI or other data visualization tool is a plus\nProficient in Nielsen NAD and other statistical software is preferred but not a must\nExcellent MS Excel and PowerPoint skills\nExcellent command of spoken and written English and Chinese\n\nPlease apply with full resume, current and expected salary and availability to:\u00a0The Human Resources Manager, Swire Coca-Cola HK, 17-19 Yuen Shun Circuit, Siu Lek Yuen, Shatin, or by clicking \"Apply Now\".\u00a0\n\n*Personal data provided are treated in strictest confidence and for recruitment purposes only. All information will be destroyed after the process completed.*\u00a0", "employment_types": ["Full Time", "Contract"], "selling_points": [], "locations": ["Not Specified"], "categories": ["Professional Services", "Business Analysis / Data Analysis", "Education", "Others", "Sciences, Lab, R&D", "Research & Development (R&D)"], "post_time": "2022-01-14T07:04:22Z", "salary": {"currency": null, "max": null, "min": null, "period": null, "term": null}, "salary_visible": false, "title_keywords": ["manager"], "responsibilities": ["collaborate with", "management", "identify business opportunities", "sales performance", "analysis", "review", "budget", "design", "market analysis", "revenue growth", "forecast", "report", "forecasting", "tracking"], "requirements": {"degrees": ["degree"], "majors": ["business", "marketing"], "languages": ["english", "chinese"], "language_level": ["excellent"], "hard_skills": ["plus", "agile", "analysis", "powerpoint", "project management", "ms excel", "data visualization", "focus", "business intelligence", "acumen"], "soft_skills": ["self-motivated", "confidence", "agile", "sense of responsibility", "project management", "presentation skills", "result oriented", "attention to details", "business acumen", "articulate", "focus"], "languages_combined": [{"language": "english", "language_level": ["excellent"]}, {"language": "chinese", "language_level": ["excellent"]}]}, "experience_required": {"duration": ["minimum 2 years"], "field": ["management", "fmcg", "data analysis", "project management", "business", "marketing"]}}, {"job_id": "100003009043714", "location_code": "hk", "company": "Swire Resources Ltd", "job_title": "CRM Data Analyst", "description": "As a Analyst of Raw Materials, you will be responsible for executing and improving critical functions through developing, building and maintaining data management model. You will also be responsible for enhancing current workflow by process automation and providing details on business metrics by creating reports and dashboards for the raw materials team.\n\nPrinciple Duties and Responsibilities\n\n\nCollect structured and unstructured data, build and maintain data pipelines, conduct data exploration and visualization, develop and maintain the dashboard to interpret the analysis results\nLeverage data science tools/techniques to analysis large data sets through custom models and algorithms to uncover insights, pattern and trends in the data\nIdentify and support improvements in daily work efficiency through automated and streamlined processes\nManage routine data processes e.g. inventory data collection, reconciliation, etc.\nCore responsibilities of this job are described within this job description. Job duties may change at any time due to business needs.\n\nRequirements\n\nCollege degree or equivalent work experience in data analysis\n\n1-2 years of experience in workflow enhancement, workflow digitalization, data analysis and data visualization via dashboards\nExpertise in Microsoft Excel - \u00a0VBA, Power Query\nExperience in MS forms, MS flow, One drive, SharePoint\nDemonstrated ability to work across multiple teams as well as independently\nStrong verbal and written communication skills addressing a variety of levels, internal and external\nHigh attention to detail and accuracy\nFlexible, resilient and nimble, comfortable working in grey areas with constant change\nAccountable with a high degree of initiative\nStrong organization and collaboration skills\nDesired Requirements\n\nExperience in Vendor Management and Product Lifecycle Management systems, Smartsheet, DOMO, and other analytics software\nBenefits\n\n\nEligible team members will receive one of the best earnings packages anywhere, including competitive pay, all-around insurance coverage, training and development and many other perks and benefits. Target is an Equal Employment Opportunity Employer.\u00a0\n\nInterested parties please apply in writing with detailed resume, last salary and\u00a0expected salary.\n\nFor more company information, please feel free to visit:\u00a0www.target.com\n\n(Data collected will be used for recruitment purpose only)", "employment_types": ["Full Time", "Permanent"], "selling_points": ["CRM Data extraction, dashboard visualization", "Basic knowledge in Tableau, PowerBI", "Experience in F&B/retail environment"], "locations": ["Kowloon Bay"], "categories": ["Professional Services", "Business Analysis / Data Analysis", "Information Technology (IT)", "DBA", "Marketing / Public Relations", "Others"], "post_time": "2022-01-13T01:38:06Z", "salary": {"currency": null, "max": null, "min": null, "period": "monthly", "term": null}, "salary_visible": false, "title_keywords": ["data analyst"], "responsibilities": ["visualization", "data", "analysis", "inventory", "develop", "maintain", "maintain data", "data collection"], "requirements": {"degrees": ["degree"], "majors": [], "languages": [], "language_level": [], "hard_skills": ["vba", "analysis", "vendor", "microsoft excel", "data visualization"], "soft_skills": ["flexible", "communication skills", "independently", "accountable", "attention to detail", "initiative"], "languages_combined": []}, "experience_required": {"duration": ["1-2 years"], "field": ["data analysis", "management"]}}, {"job_id": "100003009043195", "location_code": "hk", "company": "Arup", "job_title": "Data Analyst", "description": "Responsibilities:\n\nSupport management for the preparation of budget & business planning, financial analysis and management reporting of the Mainland investment property, with a focus in Chongqing\nPerform financial analysis and business modelling to facilitate business reviews, management decision making on business, financial trends and new opportunities\nIdentify issues, discuss and work closely with relevant departments and cross functional teams to analyze and review the financial and operational performance\nWork on quantitative and qualitative study to understand customers and mall performance\nProvide support on the regular update of business performance reports\nAssist in ad hoc projects as assigned\n\nRequirements:\n\nUniversity graduates in Business Administration/ Accounting/ Finance/ Economics/ Statistics or related disciplines\nAt least 5 years of experience with track record in conducting business analysis for management reporting, marketing research, business consulting, data analytics/ intelligence\nExperience in retail/ FMCG/ shopping mall is highly preferred, research agency background an added advantage\nStrong business acumen with excellent interpersonal and presentation skills\nProactive, detail-oriented, sensitive to numbers, and able to work under tight deadlines in a dynamic business environment\nExcellent command in written and spoken\u00a0English and Chinese\nProficient in MS Excel and PowerPoint\n\nWe offer competitive remuneration package that commensurate with experience and qualifications.\u00a0 Interested parties are invited to send full resume stating contact telephone number, date available, present and expected salary to our recruitment email address.", "employment_types": ["Full Time", "Permanent"], "selling_points": [], "locations": ["Kowloon City Area"], "categories": ["Professional Services", "Business Analysis / Data Analysis", "Information Technology (IT)", "Data Scientist"], "post_time": "2022-01-12T10:11:27Z", "salary": {"currency": null, "max": null, "min": null, "period": null, "term": null}, "salary_visible": false, "title_keywords": ["data analyst"], "responsibilities": ["management", "provide support", "performance reports", "budget", "teams", "review", "financial analysis", "ad hoc projects", "management reporting", "planning"], "requirements": {"degrees": [], "majors": [], "languages": ["english", "chinese"], "language_level": ["excellent"], "hard_skills": ["data analytics", "analysis", "powerpoint", "ms excel", "dynamic", "acumen"], "soft_skills": ["business environment", "detail-oriented", "presentation skills", "dynamic", "business acumen", "sensitive to numbers", "proactive", "interpersonal"], "languages_combined": [{"language": "english", "language_level": ["excellent"]}, {"language": "chinese", "language_level": ["excellent"]}]}, "experience_required": {"duration": ["at least 5 years"], "field": ["management", "research", "fmcg", "consulting", "agency", "marketing", "business", "business analysis", "retail"]}}, {"job_id": "100003009050716", "location_code": "hk", "company": "Hutchison Telecommunications (Hong Kong) Limited", "job_title": "BI Developer", "description": "Sr. Data Analyst/ Data Analyst/ Data Engineer X2\u00a0\nLocation : Tsuen Wan ( 5 Days ) Salary : 23-38K ( Negotiable)\u00a0\n\nResponsibilities :\u00a0\n\n\nResponsible for the structuring & execution of the company\u2019s in-house data management & business intelligence planning\nGathering & understanding of business & user requirement, then plan out the execution of the business intelligence projects\nStructure & execute company\u2019s data-collection tasks, ETL process, and manage data warehouse\nBuild up front-end Business Intelligence dashboards / platforms for varies in-house units\nProvide maintenance and support for existing applications\u00a0\n\nRequirements:\n\n\n2-8 years of experience in Data Analyst position\n\nRequired knowledge in: SQL, Tableau, database structure\nAdditional knowledge in: Python, MS Dynamic (ERP), ETL tools, preferred\nStrong sense of responsibility and a good team player;\nGood communication skills including spoken, written English and Chinese\nCandidates have less exp also will be consider\n*** Personal data will be treated with strict confidential and used for recruitment purpose only\n*** P & A consultant Ltd will not charge any fees from the above-stated job-seeker, your job apply to our company means your acceptance of our terms and conditions.", "employment_types": ["Full Time", "Permanent"], "selling_points": [], "locations": ["Tsing Yi"], "categories": ["Professional Services", "Business Analysis / Data Analysis", "Information Technology (IT)", "Others", "Data Scientist"], "post_time": "2022-01-14T11:13:31Z", "salary": {"currency": null, "max": null, "min": null, "period": "monthly", "term": null}, "salary_visible": false, "title_keywords": ["developer"], "responsibilities": ["user requirement", "management", "maintenance", "data", "plan", "planning"], "requirements": {"degrees": [], "majors": [], "languages": ["english", "chinese"], "language_level": ["good"], "hard_skills": ["erp", "tableau", "sql", "dynamic", "python"], "soft_skills": ["communication skills", "good team player", "dynamic", "sense of responsibility"], "languages_combined": [{"language": "english", "language_level": ["good"]}, {"language": "chinese", "language_level": ["good"]}]}, "experience_required": {"duration": ["2-8 years"], "field": []}}, {"job_id": "100003009051817", "location_code": "hk", "company": "RGF HR Agent Hong Kong Limited", "job_title": "Japanese Speaking Strategic Planning Officer (Up to 35K/ Good package/ Multinational corporation)", "description": "Duties:\u00a0The appointee will be responsible for performing high-quality analyses, conducting research and overseeing the timely delivery of quality outcomes for internal and external projects, developing value propositions and presenting to relevant committees, sharing on best international practices related to examinations, assessments and research, giving expert advice to Secretariat staff and other parties, and helping the Division Head oversee the smooth running of the Division with the objective of enhancing organizational practices and processes within the human and financial resources given.\n\nRequirements:\n\nA doctoral degree in Education, Statistics, Measurement and Assessment or related disciplines;\nAt least 6 years of managerial experience, preferably in management of research work;\nAbundant knowledge of research concepts and methods;\nSubstantial knowledge of statistical tools and assessment technology;\nFamiliarity with multidimensional item response theory and/or cognitive diagnostic modeling is preferred;\nExcellent analytical skills and professional report writing skills;\nOutstanding presentation and communication skills in Cantonese, English, and Putonghua;\nExperience in working with primary and/or secondary schools in Hong Kong is an advantage;\nGood interpersonal skills and teamwork spirit; and\nCandidates with less working experience will also be considered.\n\nEmployment Terms:\u00a0 The remuneration package will be commensurate with qualifications and experience.\u00a0 Appointment will be on a fixed-term contract with contract-end-gratuity, MPF benefits, medical and dental care.\u00a0 Future employment may be offered on renewable contracts subject to performance and staffing needs.\n\nDate for Application Review: 28 January 2022\n\nApplications would be considered until the post is filled.\n\nApplication forms can be obtained from the HKEAA office on 13/F., Southorn Centre, 130 Hennessy Road, Wan Chai, Hong Kong or downloaded from the HKEAA website (www.hkeaa.edu.hk/tc/Career/general.html).\u00a0 Completed application forms should be returned to the Manager \u2013 Human Resources at the above address. Due to the secrecy nature of HKEAA's job duties, applicants invited for interview may be required to make a declaration of any conflict of interests. Applicants not notified within 10 weeks from the application review date should consider their applications unsuccessful.\n\nThe HKEAA is an equal opportunities employer and welcomes applications from all qualified candidates. Information provided relating to employment will be kept confidential and used only for processing applications. For details, please refer to the Policy Statement on Equal Opportunities and the Personal Information Collection Statement on the HKEAA website (www.hkeaa.edu.hk).", "employment_types": ["Full Time", "Permanent"], "selling_points": ["Multinational corporation/ Strategic planning", "Strong analytical skills/ presentable/ JLPT N2", "Up to 35K / Good package / Kowloon"], "locations": ["Not Specified"], "categories": ["Professional Services", "Business Analysis / Data Analysis", "Business Consultancy"], "post_time": "2022-01-17T01:16:29Z", "salary": {"currency": null, "max": null, "min": null, "period": "monthly", "term": null}, "salary_visible": false, "title_keywords": ["officer"], "responsibilities": ["management", "measurement", "quality", "developing", "expert advice", "communication", "report"], "requirements": {"degrees": ["degree"], "majors": ["related disciplines", "statistics"], "languages": ["cantonese", "putonghua", "english"], "language_level": [], "hard_skills": ["writing skills", "analytical skills"], "soft_skills": ["communication skills", "responsible", "organizational", "timely", "writing skills", "analytical skills", "interpersonal skills", "teamwork spirit", "smooth", "presentation"], "languages_combined": [{"language": "cantonese", "language_level": []}, {"language": "putonghua", "language_level": []}, {"language": "english", "language_level": []}]}, "experience_required": {"duration": ["at least 6 years"], "field": ["managerial", "management", "research"]}}, {"job_id": "100003009052735", "location_code": "hk", "company": "The Hongkong Electric Co., Ltd.", "job_title": "Engineer I (System Planning) (Ref: CDD-P-EI-JD)", "description": "Job Summary\n\nThe Data analyst will support the Retail Division for company\u2019s growing needs on CRM analytics and big data analysis. Candidate\u2019s analytical and technical skills will be leveraged to support various CRM programs and manage CRM analytical projects.\n\nJob Duties and Responsibilities\n\n1. Drive data driven marketing program\u00a0\n\n\nUnderstand business requirement to extract data from CRM system, conduct analysis to identify customer needs and sales opportunities for sales-driven marketing program design\n\n2.\u00a0Create data visualization\u00a0\n\n\nBuild dashboard that helps CRM team to gain understanding on business results & trend, monitor KPI and alert for action plan (e.g.\u00a0CRM KPI/ Mobile App performance/ Customer life cycle analytics)\n\n3.\u00a0Derive customer segmentation\n\n\nReveal and uncover insights by exploring and mining structured and unstructured data to build different customer segmentation\nModel includes\u00a0Customer life cycle/RFM (Frequency/Monetary Value/Recency/ Digital footprint behavior/ Response to communications etc.)\n4.\u00a0Execute marketing program\n\nPerform data extraction to fulfill marketing program requirement\nDevelop campaign evaluation framework, set control to review campaign effectiveness & conduct reports\n5.\u00a0Develop customer data set\n\nCo-work with IT team to ensure data accuracy and develop comprehensive customer data set (customer 360) &\u00a0manual for data field definition\n6. Develop control reports\n\nDesign data reports to facilitate control on potential risk & loss of CRM program execution i.e. VIP Bonus scheme, Bulk & abnormal VIP purchase identification\u00a0\n\n\u00a0Requirements\n\nDegree holder, preferably in Information Technology, Computer Science, Data Analytics, Statistics, BIS/MIS or\u00a0related disciplines\n1-2 year experience in\u00a0 data analysis and ideally with experience in F&B/retail environments\nFamiliar with visualization tools (e.g. Tableau, PowerBI) is an advantage\nExperience in handling large sets of data is a plus\nInterested in customer behavior and CRM\nStrong sense in data processing, good business acumen and communication skills\nFresh graduate with internship experience will be considered\u00a0\nWe offer competitive remuneration package with\u00a0a wide range of fringe benefits including\n5-day work week\nDiscretionary Bonus\nComprehensive Medical Coverage\nStaff Shopping Discount\nNon-contributory Retirement Benefits Scheme\nBirthday Leave\nPlease send resume with present and expected salary to Human Resources Department, Swire Resources Limited, 12/F Kingston International Centre 19 Wang Chiu Road Kowloon Bay Hong Kong or by clicking the \"Apply Now\" button below.\n\nSwire Resources Limited is Equal Opportunity Employer", "employment_types": ["Full Time", "Permanent"], "selling_points": ["Perform power system studies and transformer", "Bachelor in Electrical Engineering, Power System", "A minimum of 5 years\u2019 relevant work experience"], "locations": ["Admiralty"], "categories": ["Professional Services", "Business Analysis / Data Analysis", "Engineering", "Electrical / Electronics", "Sciences, Lab, R&D", "Research & Development (R&D)"], "post_time": "2022-01-17T03:52:09Z", "salary": {"currency": null, "max": null, "min": null, "period": "monthly", "term": null}, "salary_visible": false, "title_keywords": ["engineer"], "responsibilities": ["control", "mobile app", "visualization", "data", "analysis", "review", "monitor", "customer data", "design", "develop", "ensure data accuracy", "purchase", "reports", "plan", "evaluation"], "requirements": {"degrees": ["fresh graduate", "degree holder"], "majors": ["related disciplines", "statistics", "computer science", "information technology"], "languages": [], "language_level": [], "hard_skills": ["plus", "data analytics", "analysis", "tableau", "processing", "acumen"], "soft_skills": ["business acumen", "communication skills", "interested in"], "languages_combined": []}, "experience_required": {"duration": ["1-2 year"], "field": ["data analysis", "f&b", "retail"]}}, {"job_id": "100003009049451", "location_code": "hk", "company": "Sun Hung Kai Properties Ltd", "job_title": "ANALYST / ASSISTANT ANALYST - TECHNOLOGY & INNOVATION", "description": "WeLab is a leading fintech company in Asia, \u00a0which operates one of first licensed digital banks in Asia \u2013 WeLab Bank, as well as multiple leading online financial services businesses including WeLend and WeLab Bank in Hong Kong, WeLab Digital (\u6211\u6765\u6570\u79d1), Taoxinji (\u6dd8\u65b0\u673a), Wallet Gugu (\u94b1\u5939\u8c37\u8c37) and Tianmian Tech (\u5929\u5195\u79d1\u6280)\u00a0in Mainland China and Maucash in Indonesia. WeLab aims to bring joy to everyone\u2019s financial journey. We strive to improve people\u2019s lives by reinventing financial services through game-changing technology. We put our people first, whether it\u2019s our customers or our employees.\n\nAs the only homegrown Hong Kong fintech to receive a virtual banking license, we aim to reinvent and redefine the banking experience by building a bank we love.\n\nWe are an energetic and passionate team that can deliver and execute. We are looking for other intellectually curious, open-minded and smart-working individuals who are just as passionate as we are about making financial services enjoyable. Now you have the opportunity to join us on our journey to achieve our vision and be part of building a better financial future for everyone.\n\nAbout you:\n\nYou're a go-getter with mad juggling skills (or multiple hats) who can thrive in a fast-paced, agile environment\nYou have a strong thirst for knowledge and are driven to find solutions that don't exist yet\nYou are comfortable with ambiguity and extremely resourceful (in your past life you could've been a detective)\nYou always find a way to get things done without sacrificing the quality of your work, integrity and values. No task is off limits for you.\nYou are humble and prioritize the success of the team over your own with an eagerness to help those around you\nYou don't shy away from challenges and have the ability to bounce back from setbacks\n\nWhat you\u2019ll do and what success looks like in this role\n\nProvide user requirement and drive the card enhancement projects\nWork closely with Digital and stakeholder teams to drive card innovations and develop new card features\nEnsure the card product and end-to-end journey is in compliance with internal and external governance and regulatory standards\nWork with cross-functional teams to optimize for card business and operation efficiency\nConduct analyses on market landscape developments, trends and innovations for cards growth opportunities\n\nWhat is required and what we\u2019re looking for\n\nDegree holder in relevant disciplines\n5+ years of experience on card business / product management\nGood understanding of the risk and compliance framework in card industry\nStrong project management, analytical and problem-solving skills\nSelf-driven and able to work in a fast-pacing environment\nExperience in start-ups and passion for fintech is an advantage\nFluent in English & Cantonese with good presentation skills\n\nWeLab perks:\n\nCompetitive salary\nLearning and development stipend, because we value lifelong learning and believe the best way to invest in our employees is to encourage them to continue to learn\nWork hard and laugh lots (chicken wings and french toast, etc.) with a high-performing, fun and diverse team\nHappiness Dollars for spending on anything that makes you happy\nCoffee stipend\nConveniently located office surrounded by diverse and delicious lunch options\nLively office with gaming consoles and a ping pong table\nFun extracurricular activities with your colleagues like hiking, yoga, badminton, wine tasting, dragon boat racing, rock climbing, etc.\nEmployee referral bonuses\n\nAwards & recognition:\n\nFinancial Times (FT) 2020 Asia-Pacific High-Growth Companies \u2013 #2 ranked company\n2020 CNBC Disruptor 50 List \u2013 #11, only company included from Hong Kong and just one of five from Asia\n\nWe offer competitive salary package to the successful candidate.\u00a0 If you are interested in joining this exciting team, please apply with resume via the \"Apply\" button.\n\nAll information provided by applicants will be used for recruitment purposes only. Information of unsuccessful applicants will be destroyed within 24 months of receipt.", "employment_types": ["Full Time", "Permanent"], "selling_points": ["Exp in consulting or digital-related roles", "Research and distill insights on digital trends", "Identify & drive digital & innovation initiatives"], "locations": ["Wan Chai"], "categories": ["Professional Services", "Business Analysis / Data Analysis", "Sales, CS & Business Devpt", "Business Development", "Information Technology (IT)", "Others"], "post_time": "2022-01-14T08:40:53Z", "salary": {"currency": null, "max": null, "min": null, "period": null, "term": null}, "salary_visible": false, "title_keywords": ["analyst", "assistant"], "responsibilities": ["user requirement", "management", "compliance", "quality", "teams", "develop", "project management", "banking", "enhancement projects", "cross-functional teams"], "requirements": {"degrees": ["degree holder"], "majors": [], "languages": ["cantonese", "english", "french"], "language_level": ["good", "fluent"], "hard_skills": ["no", "joy", "agile", "fun", "project management", "problem-solving skills", "go", "mad"], "soft_skills": ["passionate", "agile", "resourceful", "passion for", "open-minded", "integrity", "prioritize", "project management", "presentation skills", "learning", "diverse", "problem-solving skills", "energetic", "driven"], "languages_combined": [{"language": "cantonese", "language_level": ["good", "fluent"]}, {"language": "english", "language_level": ["good", "fluent"]}, {"language": "french", "language_level": []}]}, "experience_required": {"duration": ["5+ years"], "field": ["product management", "business", "banking experience", "banking"]}}, {"job_id": "100003009055638", "location_code": "hk", "company": "Links International", "job_title": "Archives Officer / Senior Officer", "description": "Responsibilities:\n\nCreate, develop and maintain architecture of data and business intelligence system\nGet involved in data mining, management and develop analytics models\nDevelop analytics algorithm and data roadmap\nIdentify and solve business-related problems by using data-driven techniques\nResearch latest technologies and techniques of big data sources / deep learning and Machine Learning techniques\nCommunicate findings with internal users and prepare reports to present workable solutions to both technical and non-technical stakeholders\nWork with developers and application analysts within the team to deliver results to the clients in easy-to-understand format\n\nQualifications & Experience required:\n\nFresh PhD with research experience or Master Degree in Mathematics, Data Science or related discipline with around 3 years of relevant experience\nExperience in applying data analytics, data mining and machine learning within business environment\nExperience in a consulting firm environment will be an advantage\nHave an interest in engineering and building industry\nHands-on experience in TensorFlow, Keras and Python\nStrong analytical and organization skills\nAble to work independently coupled with strong interpersonal skills\nProficiency in both written and spoken English and Chinese\n\n\nWe offer a competitive remuneration package commensurate with qualifications and experience to the right candidate including Global Profit Share scheme, additional fringe benefits of maternity/paternity leave and long-term career development opportunities.\u00a0\nFor interested applicants, please click \u201cApply Now\" to submit your online application.\n\nTo explore more job opportunities in Arup, please visit our website at http://www.arup.com/Careers/Experienced_Hires/ApplyForAJob\n\nPersonal data collected will be used for recruitment purpose only. Applicants not contacted within 8 weeks may consider their applications unsuccessful.\n\u00a0", "employment_types": ["Full Time", "Permanent"], "selling_points": ["6+ Years' experience in archives management", "Chinese typing is required", "Immediate available is preferred"], "locations": ["Central"], "categories": ["Professional Services", "Business Analysis / Data Analysis", "Sciences, Lab, R&D", "Research & Development (R&D)"], "post_time": "2022-01-18T02:49:12Z", "salary": {"currency": null, "max": null, "min": null, "period": "monthly", "term": null}, "salary_visible": false, "title_keywords": ["officer", "senior officer"], "responsibilities": ["management", "prepare reports", "consulting", "data", "big data", "website", "develop", "maintain", "recruitment", "career development", "data mining", "personal data", "architecture"], "requirements": {"degrees": ["master degree"], "majors": ["mathematics", "data science"], "languages": ["english", "chinese"], "language_level": ["proficiency"], "hard_skills": ["data analytics", "scheme", "python", "data mining", "business intelligence"], "soft_skills": ["work independently", "deep", "organization skills", "hands-on", "learning", "interpersonal skills", "business environment", "driven"], "languages_combined": [{"language": "english", "language_level": ["proficiency"]}, {"language": "chinese", "language_level": ["proficiency"]}]}, "experience_required": {"duration": ["3 years"], "field": ["research", "consulting", "related", "development", "business", "relevant experience"]}}, {"job_id": "100003009056199", "location_code": "hk", "company": "ME Job Personnel Limited", "job_title": "Legal Office / Intellectual Property Officer", "description": "Job Responsibilities:\n\nIdentify data sources, transform, correlate and aggregate information, load useful records to Data Warehouses, and formulate Data Marts for users to access\nData integrity assurance, monitor job alerts, rescue/ restore problem data records/ jobs\nAnalyze the information and produce useful summarized figures/ reports to management\nJobs/ scripting/ SQL statements tuning\nAutomation of users reports\nSystem maintenance support\n\nJob Requirements:\n\nDegree or Higher Diploma holder in Computer Science or related disciplines\nFamiliar with Database applications\nExperience in statistics analysis and presentation\nUnderstanding of structural and unstructured data manipulation\nGood command of written and spoken English and Cantonese included Mandarin\n\nComputer Skills:\n\nComputer Software (e.g. MS Office): Talend ETL, Tableau, Oracle OBIEE, Adobe AEM, Google Cloud\nOperating System: Unix/ Linux, Windows Server\nDatabase/ Network: Oracle, MongoDB, MYSQL, MS-SQL\nProgramming Language: PL-SQL, Python, C++, Java, Unix shell scripting, Google Big Query\nOther skills: REST API, JSON, XML, NoSQL, K-SQL\n\nApart from competitive remuneration package and exciting opportunity for career development within the Group, we provide attractive employee benefits such as free company shuttle, free company SIM card and preferential SIM plan offers, comprehensive medical & insurance schemes, as well as full range of other employee well-being provisions.\n\nInterested parties, please apply with full resume, present and expected salary, by clicking \u201cAPPLY NOW\u201d. Please quote the reference number on the e-mail subject.\n\nWe are an equal opportunity employer and welcome applications from all qualified candidates. Personal data collected will be treated in the strictest confidence and handled confidentially by authorised personnel for recruitment-related purposes only within the CK Hutchison Group of companies. The personal data of unsuccessful applicants will be destroyed after the recruitment exercise pursuant to the requirements of the Personal Data (Privacy) Ordinance in Hong Kong.", "employment_types": ["Full Time"], "selling_points": [], "locations": ["Central"], "categories": ["Professional Services", "Business Analysis / Data Analysis", "Legal & Compliance", "Marketing / Public Relations", "Marketing - Brand / Product Management"], "post_time": "2022-01-18T03:32:00Z", "salary": {"currency": null, "max": null, "min": null, "period": "monthly", "term": null}, "salary_visible": false, "title_keywords": ["property officer"], "responsibilities": ["management", "data", "maintenance support", "monitor", "reports"], "requirements": {"degrees": ["degree", "higher diploma holder"], "majors": ["related disciplines", "computer science"], "languages": ["cantonese", "english", "mandarin"], "language_level": ["good command"], "hard_skills": ["linux", "oracle", "java", "c++", "analysis", "unix shell", "tableau", "pl", "sql", "adobe", "computer skills", "ms-sql", "programming", "python", "data manipulation", "windows server", "ms office"], "soft_skills": ["comprehensive", "presentation"], "languages_combined": [{"language": "cantonese", "language_level": ["good command"]}, {"language": "english", "language_level": ["good command"]}, {"language": "mandarin", "language_level": ["good command"]}]}, "experience_required": {"duration": [], "field": ["statistics"]}}, {"job_id": "100003009056310", "location_code": "hk", "company": "HKIC Human Resources Services", "job_title": "Executive Secretary (Global Sourcing & Operations Dept) 6-month contract / Permanent", "description": "Our client, a \u00a0Japanese Machine Parts Company, is looking for a suitable candidate for a\u00a0System Support as below\n\nJob Duties\n\nFollow up existing clients\nOccasionally, Business Development\nCommunicate with Japan HQ,other overseas bases\nBusiness trip (Mainland/ Japan/Vietnam/ Taiwan etc..)\nPerform ad hoc duties\nRequirement\n\n\n2-3 years experience of Electronic parts or Solid light source is prefer\nGood command of Japanese(JLPT N2 or above), English and Mandarin\n\nAble to Business Travel to Asia countries (Included\u00a0Mainland)\nGuangdong Japan Vietnam Taiwan, etc (Communicate with China factory)\nImmediately available is highly prefer\nPackage\n\nDouble Pay\nMedical Allowance\nAnnual Leave\nSick Leave\nPerformance Bonus\nInterested parties please send us your resume in MS Word/PDF format in English.\nAll information received will be kept in strict confidential and only for recruitment purpose", "employment_types": ["Full Time"], "selling_points": ["Global event arrangement with Senior Executives", "Office moving, renovation, administration", "Provide secretarial support to Executive"], "locations": ["Not Specified"], "categories": ["Admin & HR", "Personal / Executive Assistant", "Secretary", "Professional Services", "Business Analysis / Data Analysis"], "post_time": "2022-01-18T03:55:59Z", "salary": {"currency": null, "max": null, "min": null, "period": "monthly", "term": null}, "salary_visible": false, "title_keywords": ["executive secretary", "operations"], "responsibilities": ["communicate with", "business trip", "ad hoc duties"], "requirements": {"degrees": [], "majors": [], "languages": ["english", "mandarin"], "language_level": ["good command"], "hard_skills": [], "soft_skills": [], "languages_combined": [{"language": "english", "language_level": ["good command"]}, {"language": "mandarin", "language_level": ["good command"]}]}, "experience_required": {"duration": ["2-3 years"], "field": []}}, {"job_id": "100003009043306", "location_code": "hk", "company": "Swire Coca-Cola HK Ltd", "job_title": "Commercial Manager (Business Analytics/ Analyst)", "description": "Our client, an electronic parts trading company, is seeking for Sales Coordinator to join their team.\n\nJob Responsibility\u00a0\n\n\u30fbFollow up customer orders\n\u30fbContact oversea customers and suppliers for delivery control\n\u30fbHandle shipping documents and logistics arrangements\n\u30fbCoordinate with internal and external parties for delivery schedule\n\u30fbCommunicate with customers, sales and shippers to resolve any problems\n\u30fbProcess issuance of invoices, packing list and PO\n\u30fbKeep and file records of invoices and shipment information\n\u30fbPrepare sales reports for management\n\u30fbOther ad-hoc duties assigned by management\n\nRequirement\u00a0\n\n\u30fb5 years\u2019 experience in sales / shipping coordinating (Electronic components)\n\u30fbCustomer-oriented, responsible and well-organized\n\u30fbGood in spoken and written English and Cantonese\n\u30fbJapanese speaking is advantage\n\u30fbImmediate available is great advantage\n\n<Preferable Skill / Experience>\n\u30fbJapanese speaking is advantage\n\n\nPackage\u00a0\n\n-\u00a0Up to 25K\n-\u00a0Discretionary Bonus\u00a0\n-\u00a0Double Pay\n- Medical\n-\u00a0Sick leave\n\n\n\nInterested parties please send us your resume in MS Word/PDF format in English.\n\nAll information received will be kept in strict confidential and only for recruitment purpose.", "employment_types": ["Full Time", "Permanent"], "selling_points": ["Market analysis, business forecast, pricing mgt", "FMCG background, strong analytical skills", "Nielsen data handling, Power BI report"], "locations": ["Shatin Area"], "categories": ["Banking / Finance", "Analyst", "Professional Services", "Business Analysis / Data Analysis", "Sales, CS & Business Devpt", "Others"], "post_time": "2022-01-12T10:40:55Z", "salary": {"currency": null, "max": null, "min": null, "period": null, "term": null}, "salary_visible": false, "title_keywords": ["analyst", "manager"], "responsibilities": ["shipping documents", "control", "management", "invoices", "sales reports", "logistics arrangements", "internal and external parties", "packing list", "delivery schedule", "ad-hoc duties"], "requirements": {"degrees": [], "majors": [], "languages": ["cantonese", "english"], "language_level": [], "hard_skills": [], "soft_skills": ["well-organized", "responsible"], "languages_combined": [{"language": "cantonese", "language_level": []}, {"language": "english", "language_level": []}]}, "experience_required": {"duration": [], "field": []}}, {"job_id": "100003008402403", "location_code": "hk", "company": "HH Partners", "job_title": "Auditor - short or long-term / flexible working hours - video call interview", "description": "Our client, a Japanese\u00a0Electronic Company is looking for IT and Administration Coordinator\u00a0to join their team.\n\nJob duties\n\n\nIT (90%):\n1) Provides end-user support and problem-solving support on hardware, software & package installation and maintenance for servers & PCs\n2) Performs IT audit & complete group IT checklists & surveys\n3) Liaisons with internal & external vendors on network, email, application system (SBO), IT contracts and other related issues\n4) Set up presentation and conference equipment\n5) Studies and supports on IT security control software\n6) Provides IT training on MS office, IT security, etc. for employees\n7) Performs periodic review on the IT infrastructure and to make suggestions and budget on possible enhancement measures\n8) Maintains IT security policies and procedures to ensure data security, accuracy and compliance with corporate standards\n9) Conducts servers backup & restore\n10) Maintains company Intranet website\n11) Conducts fixed asset stock take with A/C Dept.\n12) Ad Hoc projects\n\nAdmin (10%):\n1) Updates attendance & leave records and generates attendance reports\n2) Liaisons with internal & external vendors on admin. related issues\n3) Organizes company activities\n4) Orders office supplies\n5) Conducts budget estimation for next Fiscal year\n6) Manages the stock of postal stamp\n7) Ad Hoc projects\n\nRequirement\u00a0\n\n\n1) Bachelor's degree/diploma in information technology, computer technology, or a similar field.\n2) At least two years' experience as an IT coordinator or related role.\n3) Experience working with Microsoft Office 2016, 2019, or Office 365.\n4) Strong troubleshooting, analytical, and problem-solving skills.\n5) Good interpersonal skills and the ability to work with technical and non-technical personnel.\n6) Can speak Mandarin and English\n\nPackage\n\n\n- Double pay\n-\u00a0Discretionary Bonus\n- Medical check\n- Life insurance\n- Transportation allowance\n-\u00a0Motivation allowance\n- OT allowance\n- Annual Leave\n-\u00a0Sick leave\n\n\nInterested parties please send your English CV to us in MS Word/ PDF format.\n\nAll information received will be kept in strict confidential and only for recruitment purpose.", "employment_types": ["Full Time", "Part Time", "Permanent", "Temporary", "Contract", "Internship", "Freelance"], "selling_points": ["International work experience", "Flexible hours - work from home", "Transparent bonus system"], "locations": ["Wan Chai"], "categories": ["Accounting", "Accountant", "Audit", "Professional Services", "Business Analysis / Data Analysis"], "post_time": "2022-01-18T02:39:59Z", "salary": {"currency": null, "max": null, "min": null, "period": "monthly", "term": null}, "salary_visible": false, "title_keywords": [], "responsibilities": ["software", "data", "budget", "audit", "website", "control", "it infrastructure", "contracts", "pcs", "compliance", "application system", "stock take", "reports", "installation", "attendance", "office supplies", "review", "procedures", "maintenance", "policies", "hardware", "ad hoc projects"], "requirements": {"degrees": ["diploma", "degree", "bachelor"], "majors": ["information technology"], "languages": ["english", "mandarin"], "language_level": [], "hard_skills": ["problem-solving skills", "office 365", "microsoft office"], "soft_skills": ["problem-solving skills", "interpersonal skills", "troubleshooting"], "languages_combined": [{"language": "english", "language_level": []}, {"language": "mandarin", "language_level": []}]}, "experience_required": {"duration": ["at least two years"], "field": ["related", "it"]}}, {"job_id": "100003009046206", "location_code": "hk", "company": "Shiseido Hong Kong Limited", "job_title": "Assistant Manager - Demand Planning, Shiseido Fragrance Division and DG Beauty", "description": "Our client , is seeking for a Japanese Speaking HR Officer to join their team as below:\n\nDuties:\n\u2022 Handle full spectrum of HR and C&B functions including payroll calculation, taxation filing, and MPF contribution\n\u2022 Maintain accurate and up-to-date staff data, including personal, contract, attendance, and leave records\n\u2022 Implement and maintain the HRIS(human resource information system) to ensure the accuracy of employee data and payroll information\n\u2022 Assist in general administration duties\n\u2022 Translate and interpret from Japanese to Cantonese/ English and vice versa if necessary\n\u2022 Other ad-hoc duties as assigned\n\nRequirement:\n\u2022 Bachelor\u2019s degree or above\n\u2022 Fluent in Japanese(JLPT N2), English, and Chinese\n\u2022 At least 3 years of HR experience\n\u2022 Experience in the F&B industry is highly preferred\n\u2022 Experience in the HRIS implementation is highly preferred\n\u2022 Can-do spirit, cheerful and adaptive\n\nPackage:\n\n5 working days\nMedical insurance\nSick Leave\nDiscretionary Bonus\nAnnual leave\n\nInterested parties please send your English CV to us in MS Word/ PDF format.\u00a0All information collected will be kept strictly confidential and only for recruitment purpose.\nPackage:", "employment_types": ["Full Time"], "selling_points": ["Maximize sales and inventory management", "Sales analysis and strategy development", "Demand planning and product ordering"], "locations": ["Kowloon Bay"], "categories": ["Professional Services", "Business Analysis / Data Analysis", "Sales, CS & Business Devpt", "Business Development", "Merchandising & Purchasing", "Others"], "post_time": "2022-01-13T09:56:56Z", "salary": {"currency": null, "max": null, "min": null, "period": "monthly", "term": null}, "salary_visible": false, "title_keywords": ["assistant manager"], "responsibilities": ["taxation", "attendance", "mpf", "data", "hr", "maintain", "ad-hoc duties", "payroll", "administration"], "requirements": {"degrees": ["degree or above", "bachelor"], "majors": [], "languages": ["english", "chinese"], "language_level": ["fluent"], "hard_skills": [], "soft_skills": ["cheerful", "can-do"], "languages_combined": [{"language": "english", "language_level": ["fluent"]}, {"language": "chinese", "language_level": ["fluent"]}]}, "experience_required": {"duration": ["at least 3 years"], "field": ["hr", "f&b"]}}, {"job_id": "100003009052870", "location_code": "hk", "company": "Manulife (International) Limited", "job_title": "MPF Customer Service Officer (20k up)", "description": "Our client, a Japanese Automobile Company is looking for a suitable candidate for Japanese Speaking sales coordinator.\n\nJob Duties:\n\u2022 Assist in daily operations in Procurement & Supply Department\n\u2022 Prepare and follow-up POs with overseas suppliers\n\u2022 Issue trading/shipping-related documents. Mainly by SAP\n\u2022 Coordinate with Suppliers, Forwarders, Warehouse, and Internal Departments on delivery arrangements to ensure smooth operations\n\u2022 Oversee Suppliers & Forwarders\u2019 performance in delivery and pricings\n\u2022 Preparing reports and conducting inventory control\n\u2022 Visit factories in Shenzhen and Vietnam(2-3 times/year)\n\u2022 Ad-hoc duties as assigned\n\nResponsibilities:\n\u2022 Diploma or above\n\u2022 1 year of relevant experience preferred\n\u2022 Fresh graduate welcome\n\u2022 Fluent in Japanese (JLPT N2 or above), English, and Chinese\n\u2022 Knowledge in SAP is preferred\n\n\nPackage:\n- Double pay\n- Discretionary bonus\n- Medical insurance\n- Dental insurance\n- Sick leave\n- Transportation allowance\n- OT allowance\n- Travel allowance\n\nInterested parties please send us your resume in MS Word/PDF format in English.\u00a0\nAll information collected will keep strictly confidential and only for recruitment purpose\n", "employment_types": ["Full Time", "Permanent"], "selling_points": ["20k up Income", "Customer Service Experience will be an advantage", "Coach junior team member"], "locations": ["Ngau Tau Kok"], "categories": ["Professional Services", "Business Analysis / Data Analysis", "Sales, CS & Business Devpt", "Business Development", "Hospitality / F & B", "Hospitality / Hotel Services"], "post_time": "2022-01-17T04:22:11Z", "salary": {"currency": null, "max": null, "min": null, "period": "monthly", "term": null}, "salary_visible": false, "title_keywords": ["customer service officer"], "responsibilities": ["shipping", "related documents", "coordinate with", "daily operations", "inventory control", "ensure smooth operations", "preparing reports", "ad-hoc duties", "insurance"], "requirements": {"degrees": ["fresh graduate", "diploma or above"], "majors": [], "languages": ["japanese", "english", "chinese"], "language_level": ["fluent"], "hard_skills": ["sap", "pos"], "soft_skills": ["ad-hoc duties", "smooth"], "languages_combined": [{"language": "japanese", "language_level": ["fluent"]}, {"language": "english", "language_level": ["fluent"]}, {"language": "chinese", "language_level": ["fluent"]}]}, "experience_required": {"duration": ["1 year"], "field": ["relevant experience"]}}, {"job_id": "100003009052606", "location_code": "hk", "company": "Sun Life Hong Kong Ltd", "job_title": "Specialist, L&H Strategic Operational Initiatives", "description": "Our client, a Japanese property company, is looking for\u00a0Japanese Speaking Sales Executive to join their team\n\nJob duties:\n- Negotiations related to housing and office leasing\n- Responding to enquiries from customers (consultations and inquiries regarding leasing, etc.)\n- Accompanying the property preview\n- Negotiation of conditions before contract, preparation of provisional contract\n- Preparation of furniture and home appliances before moving in, follow-up after moving in\n- Managing good relationships with real estate owners\n- Ad hoc duties\n\nRequirement:\n- Sales experience or more than 2 years of experience in the hospitality industry\n- Good command of Japanese(JLPT N1 Holder), English and mandarin\n- Proficient in MS office\n- Candidate with great communication skills and positive attitude\n\nPackage:\n- Basic Salary + Commission\n- Double pay\n- Discretionary bonus\n- Medical insurance\n- Sick leave\n\nInterested parties please send us your resume in MS Word/PDF format in English.\nAll information collected will be kept strictly confidential and only for recruitment purpose.\n\n", "employment_types": ["Full Time", "Permanent"], "selling_points": ["5-8 years working experience in Life Insurance", "Strong knowledge in Life insurance products & ops", "Exp in business analysis"], "locations": ["Hung Hom"], "categories": ["Professional Services", "Business Analysis / Data Analysis", "Information Technology (IT)", "IT Project Management / Team Lead", "Product Management / Business Analyst"], "post_time": "2022-01-17T03:31:29Z", "salary": {"currency": null, "max": null, "min": null, "period": "monthly", "term": null}, "salary_visible": false, "title_keywords": ["specialist"], "responsibilities": ["ad hoc duties"], "requirements": {"degrees": [], "majors": [], "languages": ["english", "mandarin"], "language_level": ["good command"], "hard_skills": ["basic", "ms office"], "soft_skills": ["positive attitude", "communication skills"], "languages_combined": [{"language": "english", "language_level": ["good command"]}, {"language": "mandarin", "language_level": ["good command"]}]}, "experience_required": {"duration": ["2 years"], "field": ["hospitality industry"]}}, {"job_id": "100003009044063", "location_code": "hk", "company": "Bravo Transport Services Limited", "job_title": "Senior Planning Analyst (Ref: JD/SPA/03/2022)", "description": "Our client, a Japanese Electronic Company is looking for a suitable candidate for a\u00a0Japanese Speaking Sales Coordinator\u00a0 to join their team.\n\nJob Duties:\n\u2022 Prepare and follow-up POs\n\u2022 Prepare shipping documents\n\u2022 Coordinate with internal clients in Japan\n\u2022 Coordinate with suppliers, forwarders, and warehouse on delivery arrangements to ensure smooth operations\n\u2022 Prepare reports and conduct inventory control\n\u2022 Ad-hoc duties as assigned\n\nRequirement:\n\u2022 High school or above\n\u2022 Fresh graduate welcome\n\u2022 Experience in a Japanese electronics company is an advantage\n\u2022 Fluent in Japanese(JLPT N2 or above), English and Chinese\n\nPackage:\n- Double pay\n- Discretionary bonus\n-Annual Leaves\n- Medical insurance\n- OT allowance\n- Transportation allowance\n\nInterested parties please send us your resume in MS Word/PDF format in English.\u00a0\nAll information received will be kept in strict confidential and only for recruitment purpose\u00a0 \u00a0 \u00a0 \u00a0 \u00a0 \u00a0 \u00a0 \u00a0 \u00a0 \u00a0 \u00a0 \u00a0\u00a0", "employment_types": ["Full Time", "Permanent"], "selling_points": ["Business Administration", "Business Analyst", "BI and programming tools"], "locations": ["Chai Wan"], "categories": ["Professional Services", "Business Analysis / Data Analysis", "Sales, CS & Business Devpt", "Business Development", "Transportation & Logistics", "Public Transportation"], "post_time": "2022-01-13T02:59:35Z", "salary": {"currency": null, "max": null, "min": null, "period": "monthly", "term": null}, "salary_visible": false, "title_keywords": ["analyst"], "responsibilities": ["shipping documents", "coordinate with", "inventory control", "ensure smooth operations", "ad-hoc duties", "prepare reports"], "requirements": {"degrees": ["fresh graduate", "high school"], "majors": [], "languages": ["japanese", "english", "chinese"], "language_level": ["advantage", "fluent"], "hard_skills": [], "soft_skills": [], "languages_combined": [{"language": "japanese", "language_level": ["advantage", "fluent"]}, {"language": "english", "language_level": ["fluent"]}, {"language": "chinese", "language_level": ["fluent"]}]}, "experience_required": {"duration": [], "field": []}}, {"job_id": "100003009052295", "location_code": "hk", "company": "Tianda Institute", "job_title": "\u7814\u7a76\u90e8\u4e3b\u4efb Director of Research Department", "description": "Our client, a Japanese Company is looking for a suitable candidate for Senior Accounting officer / Accounting officer\u00a0.\n\nJob Duties:\n\u30fbHandle Accounting duty (data entry, bank reconciliation, tasks related to monthly closing)\n\u30fbHandle Account receivable and Accounts payable\n\u30fbInventory level monitoring\n\u30fbCashflow forecast\n\u30fbAssist in annual audit and liaise with the external auditor\n\u30fbAssist in small part of Admin duty\n\u30fbAd-hoc duty\n\nRequirement:\n\u30fbMinimum 5 years\u2019 relevant working experience\n\u30fbBusiness level of English\n\u30fbStudied Finance or Accounting\n\u30fbMature and independent\n\n<Preferable Skill / Experience>\n\u30fbJapanese speaker is an advantage\n\u30fbImmediately available is great advantage\n\nPackage:\n- Double pay\n-\u00a0Discretionary Bonus\n- Medical insurance\n- Sick Leave\n- Transportation allowance\n- OT allowance\n- Long Service leave\n\nInterested parties please send us your resume in MS Word/PDF format in English.\u00a0\nAll information received will be kept in strict confidential and only for recruitment purpose", "employment_types": ["Full Time"], "selling_points": [], "locations": ["Central"], "categories": ["Media & Advertising", "Others", "Professional Services", "Business Analysis / Data Analysis", "Editorial / Journalism"], "post_time": "2022-01-17T02:39:44Z", "salary": {"currency": null, "max": null, "min": null, "period": "monthly", "term": null}, "salary_visible": false, "title_keywords": ["director"], "responsibilities": ["data entry", "annual audit", "monitoring", "bank reconciliation", "forecast", "liaise with", "accounts payable"], "requirements": {"degrees": [], "majors": [], "languages": ["english"], "language_level": [], "hard_skills": [], "soft_skills": ["independent"], "languages_combined": [{"language": "english", "language_level": []}]}, "experience_required": {"duration": ["5 years"], "field": ["relevant working experience"]}}, {"job_id": "100003009039924", "location_code": "hk", "company": "csl.", "job_title": "Data Analyst", "description": "Our client, a Japanese Electronic Company, is looking for a suitable candidate for a Sales Coordinator as below:\n\nJob Duties:\n\u30fbData entry\n\u30fbCommunicate with clients by E-mail\n\u30fbOrdering support\n\u30fbSales Support\n\u30fbAd hoc duties\n\nRequirement:\n\u30fb2 years Experience of Sales Coordinator\uff08 Electronic components \uff09\n\u30fbAble to speak Japanese is preferred\n\u30fbEnglish: Business level (Communicate with clients)\n\u30fbProficient in MS office\n\u30fbSincere & polite\n\u30fbImmediately is highly preferable\n\nPackage:\n- Double pay\n- Discretionary bonus\n- Medical insurance\n- Sick leave\n- OT allowance\n- Education allowance\n\n", "employment_types": ["Full Time"], "selling_points": ["Perform data extraction", "Fulfill marketing programs\u2019 requirements", "Reveal and uncover insights"], "locations": ["Quarry Bay"], "categories": ["Professional Services", "Business Analysis / Data Analysis", "Marketing / Public Relations", "Marketing - Market Research"], "post_time": "2022-01-11T15:29:28Z", "salary": {"currency": null, "max": null, "min": null, "period": "monthly", "term": null}, "salary_visible": false, "title_keywords": ["data analyst"], "responsibilities": [], "requirements": {"degrees": [], "majors": [], "languages": ["japanese"], "language_level": [], "hard_skills": ["ms office"], "soft_skills": ["polite"], "languages_combined": [{"language": "japanese", "language_level": []}]}, "experience_required": {"duration": [], "field": []}}, {"job_id": "100003009052294", "location_code": "hk", "company": "Tianda Institute", "job_title": "\u7814\u7a76\u54e1 Researcher (Full time or Part time)", "description": "Our client, a Japanese financial company is looking for a Japanese Speaking Customer Support to join their team.\n\nJob Duties:\n\u30fbPerform remittance support, trading support, live chat support\n\u30fbSupport Japanese clients account opening\n\u30fbPerform standard checks to the Japanese clients\n\u30fbUse the internal system to carry out the deposit process\n\nRequirement:\n\u30fbBachelor's degree or above\n\u30fbAt least 1 year of work experience in using Business japanese at work\n\u30fbFluent in Japanese(JPLT N1), English, and Chinese\n\u30fbProficient in Keigo (Writing & Speaking)\n\u30fbProficient in MS Office\n\nPackage:\n- Discretionary bonus\n- Medical insurance\n- Sick leave\n\nInterested parties please send us your resume in MS Word/PDF format in English.\nAll information received will be kept in strict confidential and only for recruitment purpose.\n", "employment_types": ["Full Time", "Permanent"], "selling_points": [], "locations": ["Central"], "categories": ["Media & Advertising", "Others", "Professional Services", "Business Analysis / Data Analysis", "Education", "Others"], "post_time": "2022-01-17T02:39:43Z", "salary": {"currency": null, "max": null, "min": null, "period": "monthly", "term": null}, "salary_visible": false, "title_keywords": ["researcher"], "responsibilities": ["account opening"], "requirements": {"degrees": ["degree or above"], "majors": [], "languages": ["japanese", "english", "chinese"], "language_level": [], "hard_skills": ["ms office"], "soft_skills": [], "languages_combined": [{"language": "japanese", "language_level": []}, {"language": "english", "language_level": []}, {"language": "chinese", "language_level": []}]}, "experience_required": {"duration": ["least 1 year"], "field": ["business"]}}, {"job_id": "100003009045780", "location_code": "hk", "company": "Kepro Solutions Limited", "job_title": "Consultant/Associate Consultant \u2013 Business Intelligence", "description": "Our client, a Japanese company, is looking for Senior Manager\n\n<Job Responsibilities>\n\u30fb\u304a\u5ba2\u69d8\u304b\u3089\u306e\u554f\u3044\u5408\u308f\u305b\u306b\u30e1\u30fc\u30eb\u8fd4\u7b54\u3000\u3000\u3000\u3000\n\u30fb\u30e9\u30a4\u30d6\u30c1\u30e3\u30c3\u30c8\u5bfe\u5fdc\n\u30fb\u30b7\u30b9\u30c6\u30e0\u64cd\u4f5c\u78ba\u8a8d\n\u30fb\u30c1\u30fc\u30e0\u30df\u30fc\u30c6\u30a3\u30f3\u30b0\u306b\u53c2\u52a0\n\u30fb\u5165\u793e\u5f8c\u7814\u4fee\u6709\u3000\n\n<Necessary Skill / Experience >\n\u30fb\u30d1\u30bd\u30b3\u30f3\u306e\u57fa\u672c\u7684\uff08\u30a8\u30af\u30bb\u30eb\u3001\u30ef\u30fc\u30c9\u3001\u30d1\u30ef\u30fc\u30dd\u30a4\u30f3\u30c8\u7b49\uff09\u30b9\u30ad\u30eb\u3092\u304a\u6301\u3061\u306e\u65b9\u3000\u3000\u3000\u3000\u3000\n\u30fb\u82f1\u8a9e\u65e5\u5e38\u4f1a\u8a71\u30ec\u30d9\u30eb\n\u30fbCS\u7d4c\u9a13\u8005\u512a\u9047\n\n<Package>\nDouble pay\nMedical\n\nInterested parties please send us your resume in MS Word/PDF format in English&Japanese. All information received will be kept in strict confidential and only for recruitment purpose.", "employment_types": ["Full Time", "Permanent"], "selling_points": ["Fresh graduates are welcome; 5-day work", "BI and Data Analytics", "Big data projects exposure and Steady career path"], "locations": ["Kwun Tong"], "categories": ["Professional Services", "Business Analysis / Data Analysis", "Information Technology (IT)", "Product Management / Business Analyst", "Data Scientist"], "post_time": "2022-01-15T03:49:32Z", "salary": {"currency": null, "max": null, "min": null, "period": "monthly", "term": null}, "salary_visible": false, "title_keywords": ["associate", "consultant"], "responsibilities": [], "requirements": {"degrees": [], "majors": [], "languages": ["japanese"], "language_level": [], "hard_skills": [], "soft_skills": [], "languages_combined": [{"language": "japanese", "language_level": []}]}, "experience_required": {"duration": [], "field": []}}, {"job_id": "100003009042756", "location_code": "hk", "company": "Avnet Technology Hong Kong Limited", "job_title": "Business Analyst/ Solutions Analyst (RPA Robotic Process Automation)", "description": "Our client, a Japanese Financial Company is looking for an Japanese Speaking Operation Assistant to join their team.\n\nJob Duties:\n\u30fbPerform general bookkeeping\n\u30fbHandle data entry and maintain a good filing system\n\u30fbLiaise with the tax advisors and accounting firm in Japan\n\u30fbTranslate website content from Japanese to English and Chinese\n\u30fbOther ad-hoc duties as assigned\n\nRequirement:\n\u30fb Bachelor's degree or above\n\u30fb At least 1 year of work experience in any industries\n\u30fb Exchange experience in Japan would be advantage\n\u30fb Good command of English, Japanese (JLPT N1 holder) and Mandarin\n\u30fb Sensitive in numbers, polite and acceptable to routine work\n\u30fb Proficient in MS office\n\nPackage:\n- Discretionary bonus\n- Medical insurance\n- Annual leave (Around 10 days)\n- Sick leave\n\nInterested parties please send us your resume in MS Word/PDF format in English.\u00a0\nAll information collected will be kept strictly confidential and only for recruitment purpose", "employment_types": ["Full Time", "Permanent"], "selling_points": ["5 days work", "Double Pay, Discretionary incentive", "Fresh Graduate will also be considered"], "locations": ["Kowloon Bay"], "categories": ["Professional Services", "Business Analysis / Data Analysis", "Information Technology (IT)", "DBA", "Data Scientist"], "post_time": "2022-01-12T08:42:26Z", "salary": {"currency": null, "max": null, "min": null, "period": "monthly", "term": null}, "salary_visible": false, "title_keywords": ["analyst", "business analyst"], "responsibilities": ["tax", "data entry", "website", "maintain", "ad-hoc duties"], "requirements": {"degrees": ["degree or above", "bachelor"], "majors": [], "languages": ["japanese", "english", "mandarin"], "language_level": ["good command"], "hard_skills": ["ms office", "exchange"], "soft_skills": ["polite", "sensitive"], "languages_combined": [{"language": "japanese", "language_level": ["good command"]}, {"language": "english", "language_level": ["good command"]}, {"language": "mandarin", "language_level": ["good command"]}]}, "experience_required": {"duration": ["at least 1 year"], "field": []}}, {"job_id": "100003009049744", "location_code": "hk", "company": "China Mobile Hong Kong \u4e2d\u570b\u79fb\u52d5\u9999\u6e2f", "job_title": "Assistant Customer Data Analytics Manager", "description": "Our client, a Japanese Electronic Company, is looking for a\u00a0Japanese speaking Purchasing Executive to join the team:\n\nJob Duties\n\nSearch new suppliers(Electrical and Electronics products)\nNegotiate the price and T&C with suppliers\nNegotiate the price with overseas branches\nPrepare purchase plan and purchase order\nArrange delivery schedule\nPrepare cost reduction plan\nOther ad hoc duties as assigned\nResponsibilities\n\nDiploma Holder or above\nFluent in Japanese(JLPT N2 or above), English, and Chinese\nAt least 3 years of purchasing experience in a Japanese electronics company\nProficient in MS Office, especially EXCEL\nPackage:\n\n5-days-work\nMedical Allowance\u00a0\nTransportation allowance\nAnnual leave (Over 10 days)\nSick leave\nDouble pay\nDiscretionary bonus\nInterested parties please send us your resume in MS Word/PDF format in English.\nAll information collected will be kept strictly confidential and only for recruitment purpose.", "employment_types": ["Full Time", "Permanent"], "selling_points": ["CS System Development", "Customer analytics", "Supervisory experience"], "locations": ["Kwai Hing"], "categories": ["Professional Services", "Business Analysis / Data Analysis", "Information Technology (IT)", "Product Management / Business Analyst", "Data Scientist"], "post_time": "2022-01-14T09:11:24Z", "salary": {"currency": null, "max": null, "min": null, "period": null, "term": null}, "salary_visible": false, "title_keywords": ["manager", "assistant"], "responsibilities": ["ad hoc duties", "cost", "delivery schedule", "purchase", "plan"], "requirements": {"degrees": ["diploma holder"], "majors": [], "languages": ["japanese", "english", "chinese"], "language_level": ["fluent"], "hard_skills": ["excel", "ms office"], "soft_skills": [], "languages_combined": [{"language": "japanese", "language_level": ["fluent"]}, {"language": "english", "language_level": ["fluent"]}, {"language": "chinese", "language_level": ["fluent"]}]}, "experience_required": {"duration": ["at least 3 years"], "field": ["purchasing"]}}, {"job_id": "100003009051026", "location_code": "hk", "company": "The Wharf Group", "job_title": "Assistant Investment Research Officer", "description": "Our client, a Japanese pharmaceutical company, is now looking for a good candidate to join their team as follows:\n\n\u00a0Job Description\n\n\nAttendance management\nPayroll calculation\nManagement of consumables, stationery, etc.\nArrangement of year-end party, employee trip, etc.\nResearch(Hong Kong Ordinance etc..)\nPerforma any ad-hoc duties\nCompany System: SONTECH\n\nRequirements\n\n\nAt least 3 years of working experience in general affairs\u00a0\nGood Knowledge of HK labor law ordinance\nGood command of Japanese (N2 level or above) is required\nStable & responsible candidate\n\nPackage\n\n5 days' work\nMedical insurance\nSick leave\nOT Allowance\nAnnual Leave\nDouble Pay\nDiscretionary Bonus\nTransportation Allowance\n\nInterested parties please send English CV in MS Word/ PDF format.\u00a0All information received will be kept in strict confidential and only for recruitment purpose.", "employment_types": ["Full Time", "Permanent"], "selling_points": [], "locations": ["Central"], "categories": ["Banking / Finance", "Analyst", "Investment", "Professional Services", "Business Analysis / Data Analysis"], "post_time": "2022-01-15T01:17:12Z", "salary": {"currency": null, "max": null, "min": null, "period": null, "term": null}, "salary_visible": false, "title_keywords": ["research officer", "assistant"], "responsibilities": ["attendance", "management", "year-end", "stationery", "ad-hoc duties", "payroll"], "requirements": {"degrees": [], "majors": [], "languages": ["japanese"], "language_level": ["good command"], "hard_skills": [], "soft_skills": ["stable", "responsible"], "languages_combined": [{"language": "japanese", "language_level": ["good command"]}]}, "experience_required": {"duration": ["at least 3 years"], "field": []}}, {"job_id": "100003009049130", "location_code": "hk", "company": "Beyondsoft Information Technology Corporation Limited", "job_title": "Sales Excellence [work with Microsoft]", "description": "Our client, a Fining Dining Company, is looking for a suitable candidate as below:\n\nJobs Duties\n\u30fbProvide excellent standard of sushi in a professional manner\n\u30fbProvide high quality customer service to Japanese\u00a0(Only has counter seat, under 10 seats)\n\nRequirement\n\n\u30fbAt least 5 years Experience as a Sushi chef in Japanese restaurant\u00a0\n\u30fbAble to support the Japanese head chef for providing sushi dishes\n\u30fbSense of responsibility for your role\n\u30fbFluent level Japanese\n\u30fbConversational level English\n\nPackage\n\n6 Working days\u00a0\nWorking hour (10:30 am to 3pm, and 5pm to 10pm)\nShift working\nIncentive benefit\nMedical\nMeal allowance\nSick leave\nAnnual leave (Over 10 days)\nInterested parties please send us your resume in MS Word/PDF format in English. All information collected will be kept strictly confidential and only for recruitment purpose.", "employment_types": ["Full Time"], "selling_points": [], "locations": ["Pok Fu Lam"], "categories": ["Professional Services", "Business Analysis / Data Analysis", "Business Consultancy", "Sales, CS & Business Devpt", "Sales Administration"], "post_time": "2022-01-14T08:09:20Z", "salary": {"currency": null, "max": null, "min": null, "period": "monthly", "term": null}, "salary_visible": false, "title_keywords": ["sales"], "responsibilities": ["quality", "customer service", "professional manner"], "requirements": {"degrees": [], "majors": [], "languages": ["japanese", "english"], "language_level": [], "hard_skills": [], "soft_skills": [], "languages_combined": [{"language": "japanese", "language_level": []}, {"language": "english", "language_level": []}]}, "experience_required": {"duration": ["least 5 years"], "field": ["restaurant"]}}, {"job_id": "100003009037949", "location_code": "hk", "company": "JFE Consulting Limited", "job_title": "Data Analyst", "description": "Our client, a multinational corporation\u00a0is looking for a high-caliber candidate to join their company.\n\nJob Responsibilities:\n\u2022 Assist to plan & implement marketing strategies on target markets, channels, Macau account development.\n\u2022 Handle full spectrum of marketing programs, campaigns, events, etc to achieve business objectives.\n\u2022 Assist to achieve the business plan of dedicated products.\n\u2022 Responsible to develop products and solutions for target customers, market & channel partners. \u2022 Liaise and cooperate with headquarter for product planning.\n\u2022 Provide suggestions to the Company to achieve the company goal.\n\u2022 Perform ad-hoc projects as assigned\n\nRequirement:\n\u2022 Degree holder or above in Marketing, Business Administration, or related disciplines.\n\u2022 Minimum 5 years of relevant experience in product marketing or product management.\n\u2022 Passionate, creative with good marketing and business sense.\n\u2022 Able to work independently, proactive team player with good interpersonal and presentation skills.\n\u2022 Proficient in PC skills including MS Word, Excel, and PowerPoint.\n\u2022 Fluent in English and Chinese\n\nPackage:\n- Discretionary Bonus\n- Medical insurance\n- Sick leave\n- Annual leave (over 10 days)\n- OT Allowance\n\nInterested parties please send us your resume in MS Word/PDF format in English.\nAll information collected will kept strictly confidential and only for recruitment purpose.", "employment_types": ["Full Time"], "selling_points": ["2 years related experience", "SQL, Python, Tableau", "Passionate about data"], "locations": ["Central & Western Area"], "categories": ["Professional Services", "Business Analysis / Data Analysis", "Information Technology (IT)", "Product Management / Business Analyst", "Data Scientist"], "post_time": "2022-01-11T04:24:04Z", "salary": {"currency": null, "max": null, "min": null, "period": "monthly", "term": null}, "salary_visible": false, "title_keywords": ["data analyst"], "responsibilities": ["liaise", "marketing strategies", "develop", "plan", "business plan", "ad-hoc projects", "cooperate with", "planning"], "requirements": {"degrees": ["degree holder"], "majors": ["related disciplines", "marketing", "business administration"], "languages": ["english", "chinese"], "language_level": ["fluent"], "hard_skills": ["excel", "pc skills", "powerpoint", "ms word"], "soft_skills": ["passionate", "work independently", "proactive", "business sense", "presentation skills", "team player", "creative", "interpersonal"], "languages_combined": [{"language": "english", "language_level": ["fluent"]}, {"language": "chinese", "language_level": ["fluent"]}]}, "experience_required": {"duration": ["minimum 5 years"], "field": ["product management", "marketing", "relevant experience"]}}, {"job_id": "100003009043928", "location_code": "hk", "company": "American & Efird (HK) Ltd", "job_title": "Business Analyst", "description": "Our client, a Japanese automobile company is looking for an Accounting, HR & Admin Manager to join their team as follows:\n\nJob Duties:\n\u2022 Handle the full set of accounting\n\u2022 Prepare month-end consolidation\n\u2022 Manage statutory audit, J-SOX, and tax filing\n\u2022 Prepare reports according to the templates provided by the HQ in Japan\n\u2022 Oversee the HR and Admin department\n\u2022 Liaise with the HQ in Japan\n\u2022 Other ad-hoc duties as assigned\n\nRequirement:\n\u2022 Bachelor's degree or higher\n\u2022 At least 10 years of relevant experience\n\u2022 Fluent in Japanese(JLT N2 or higher), English, and Chinese\n\u2022 ACCA/ HKIAAT student member or equivalent\n\u2022 Work experience in a Japanese company is a must\n\nPackage:\n- Discretionary bonus\n- Medical insurance\n\nInterested parties please send us your resume in MS Word/PDF format in English. All information received will be kept in strict confidential and only for recruitment purpose.\n\n", "employment_types": ["Full Time"], "selling_points": ["University graduate in IT, min. 3 yrs' solid exp.", "Travel occasionally, medical & dental insurance", "5-day work week, flexible working hours"], "locations": ["Kwun Tong"], "categories": ["Professional Services", "Business Analysis / Data Analysis", "Information Technology (IT)", "IT Project Management / Team Lead", "Network & System"], "post_time": "2022-01-13T02:29:43Z", "salary": {"currency": null, "max": null, "min": null, "period": "monthly", "term": null}, "salary_visible": false, "title_keywords": ["business analyst"], "responsibilities": ["hr", "tax filing", "month-end", "audit", "full set of accounting", "liaise with", "ad-hoc duties", "prepare reports"], "requirements": {"degrees": ["degree", "bachelor"], "majors": [], "languages": ["japanese", "english", "chinese"], "language_level": ["fluent"], "hard_skills": ["acca"], "soft_skills": [], "languages_combined": [{"language": "japanese", "language_level": ["fluent"]}, {"language": "english", "language_level": ["fluent"]}, {"language": "chinese", "language_level": ["fluent"]}]}, "experience_required": {"duration": ["at least 10 years"], "field": ["relevant experience"]}}, {"job_id": "100003009047301", "location_code": "hk", "company": "Global Executive Consultants Ltd.", "job_title": "Data Analyst (HK$30K - $45K) (Ref. No.: 25093)", "description": "Our client, a Japanese\u00a0Logistics company, is looking for a suitable candidate for\u00a0Shipping Assistant Manager as below:\nJob Duties\n\nControl and manage Import & Export team operation\nSupervising the team to reach the KPI\nPrepare quotations\nNegotiate shipment routine, freight schedules, and price, with carriers and forwarders\u00a0\nLiaise with group companies, agents, existing key customers, and new customers for shipping arrangements\u00a0\nPrepare budget, monthly and annual forecast\nResponsible for cost control\nAnalyze and prepare data and reports to the top management in HK & JP\nAssist the management in improving the team's efficiency\nOther ad-hoc duties as assigned\nRequirement\n\nDiploma or above\nAt least 5 years of experience in the logistic industry\nImport, export & forwarding experience is a MUST\nManagement experience is a MUST\nFluent in English and Chinese\nJapanese ability is an advantage\nPackage\nAlternate Weekends\nMedical Insurance\nSick Leave\nTransportation allowance\nFull attendance allowance\nTitle Allowance\nAnnual Leave\nDouble Pay\nDiscretionary Bonus\n\nInterested parties please send us your resume in MS Word/PDF format in English.\nAll information received will be kept in strict confidential and only for recruitment purpose", "employment_types": ["Full Time", "Permanent"], "selling_points": ["Data Modeling, Data Management", "Machine Learning", "Python"], "locations": ["Not Specified"], "categories": ["Professional Services", "Business Analysis / Data Analysis", "Information Technology (IT)", "Application Specialist - Software", "Software Development"], "post_time": "2022-01-14T09:20:51Z", "salary": {"currency": null, "max": null, "min": null, "period": "monthly", "term": null}, "salary_visible": false, "title_keywords": ["data analyst"], "responsibilities": ["control", "supervising", "shipping", "management", "ad-hoc duties", "data", "schedules", "budget", "reports", "forecast", "cost control", "liaise with"], "requirements": {"degrees": ["diploma or above"], "majors": [], "languages": ["japanese", "english", "chinese"], "language_level": ["advantage", "fluent"], "hard_skills": [], "soft_skills": [], "languages_combined": [{"language": "japanese", "language_level": ["advantage"]}, {"language": "english", "language_level": ["fluent"]}, {"language": "chinese", "language_level": ["fluent"]}]}, "experience_required": {"duration": ["at least 5 years"], "field": ["management"]}}, {"job_id": "100003009048861", "location_code": "hk", "company": "Luxmed Medical Group Limited", "job_title": "Operation Officer", "description": "Our client , a Japanese Banking company is seeking for\u00a0Analyst/Transaction to join their team as below:\n\nDuties:\n\u2022 To work closely with clients, relationship managers, and Operations Departments to ensure client transactions are completed efficiently and accurately\n\u2022 To handle instructions and inquiries about client transactions in a timely and orderly manner to ensure quality service is delivered.\n\u2022 To follow up pending items by contacting clients regularly to avoid overdue tasks\n\u2022 To prepare control sheet for unprocessed documents and follow up the settlement in a timely manner\n\u2022 To act as the 1st line of defense and ensure all transactions are in compliance with internal policies, AML, sanctions, and other regulatory requirements\n\u2022 To prepare AML related reports and relevant documents to facilitate KYC and transaction monitoring processes\n\u2022 To support the implementation and delivery of enhancement initiatives of the Business Unit according to the predetermined schedule\n\u2022 To maintain a good working knowledge of procedural changes, products, relevant rules, and regulations\n\nRequirement:\n\u2022 Degree holder\n\u2022 Fluent in Japanese and English\n\u2022 At least 3 years of relevant experience in administration and operational support\n\u2022 Candidates with NO banking and finance background will also be considered\n\u2022 Good numerical sense and analytical skills\n\u2022 Team player with excellent interpersonal and communication skills\n\nPackage:\n\n5 working days\nMedical\nDiscretionary Bonus\nAnnual leave\nSick leave\nInterested parties please send your English CV to us in MS Word/ PDF format.\u00a0All information received will be kept in strict confidential and only for recruitment purpose.", "employment_types": ["Full Time", "Permanent"], "selling_points": ["Support and enhance operation process", "5-day work", "Proficient in MS Excel"], "locations": ["Tsim Sha Tsui"], "categories": ["Professional Services", "Business Analysis / Data Analysis", "Sales, CS & Business Devpt", "Business Development"], "post_time": "2022-01-14T07:47:25Z", "salary": {"currency": null, "max": null, "min": null, "period": "monthly", "term": null}, "salary_visible": false, "title_keywords": ["operation officer"], "responsibilities": ["regulations", "control", "aml", "operations", "policies", "compliance", "a timely manner", "quality", "transactions", "regulatory requirements", "monitoring", "implementation", "maintain", "reports", "schedule", "kyc"], "requirements": {"degrees": ["degree holder"], "majors": [], "languages": ["japanese", "english"], "language_level": ["fluent"], "hard_skills": ["no", "analytical skills"], "soft_skills": ["communication skills", "team player", "interpersonal", "analytical skills"], "languages_combined": [{"language": "japanese", "language_level": ["fluent"]}, {"language": "english", "language_level": ["fluent"]}]}, "experience_required": {"duration": ["at least 3 years"], "field": ["relevant experience", "administration"]}}, {"job_id": "100003009044642", "location_code": "hk", "company": "HKT Consumer Group", "job_title": "Business Analysis Officer / Executive", "description": "\nJob Description\n\n\nIdentify data opportunities and transfer data to meaningful business insights\nCollect data, build and maintain data warehouse,\u00a0data analysis with SQL, OracleDB, Python, Tableau and maintain the dashboard to interpret the analysis results\nIdentify and support improvements in daily reporting and data consolidation through automated and streamlined processes\nWork with other business units on some ad-hoc analytical projects/tasks and handle some regular reports\nCollect data, build and maintain data pipelines, conduct data exploration and visualization, develop and maintain the dashboard to interpret the analysis results\nSupport and align efforts to drive business process analysis meeting to support the Business Unit\nEnsure a valid data analyzing process\u00a0including data extraction, manipulation, processing, storage, archival and more\nRequirements\n\u00a0\nUniversity graduate in Statistics, Data Science, Computer Science/Information System & Mathematics or relevant discipline\n2 years of analytical\u00a0experience including proficiency in SAS (including EM/EG/VIYA) & SQL and superior knowledge of Excel..\nSelf-motivated and able to accomplish multiple tasks\nIntermediate python skills - you are able to write modular, well documented, and scalable code\u00a0\nIntermediate knowledge of standard Data Science and Machine Learning techniques\nStrong communication and conceptual problem-solving skills\nRelentless business focus and drive for impact\n\n\n", "employment_types": ["Full Time"], "selling_points": [], "locations": ["Quarry Bay"], "categories": ["Accounting", "Audit", "Banking / Finance", "Analyst", "Professional Services", "Business Analysis / Data Analysis"], "post_time": "2022-01-13T04:58:15Z", "salary": {"currency": null, "max": null, "min": null, "period": "monthly", "term": null}, "salary_visible": false, "title_keywords": ["officer", "executive"], "responsibilities": ["ad-hoc", "reporting", "manipulation", "visualization", "data", "analysis", "develop", "data analysis", "maintain", "reports", "business process", "maintain data"], "requirements": {"degrees": ["university graduate"], "majors": ["data science", "statistics", "computer science", "mathematics"], "languages": [], "language_level": [], "hard_skills": ["excel", "sas", "problem-solving skills", "information system", "sql", "python", "code", "focus"], "soft_skills": ["self-motivated", "multiple tasks", "communication", "relentless", "learning", "problem-solving skills", "focus", "superior"], "languages_combined": []}, "experience_required": {"duration": ["2 years"], "field": ["sql", "analytical"]}}, {"job_id": "100003009044042", "location_code": "hk", "company": "Swire Resources Ltd", "job_title": "Data Management Specialist", "description": "Our client, a Public Listed Company, is looking for high-caliber person to fill the position.\n\nResponsibilities:-\n\nDevelop and maintain spatial data platforms\nDesign and analyze the development of large scale spatial data dissemination platform riding on cloud environment\nValidate data modeling, design data processing workflows, verify data conversion integrity and examine spatial data dissemination via API\nIdentify and rectify data issues during functional testing, system integration testing, and support useracceptance test\nReview, comment and revise technical project documents to enhance the quality of project deliverables\nPrepare documentation, project reports and specifications\n\nRequirements:-\n\nAt least 2 years' working experience in data modelling and management\nSolid knowledge and experience in data architecture design and modelling, implementing and development of data dissemination platform\nHands-on experience in working with spatial data modelling spatial data conversion is a plus\nExperience in Python, web programming or Java programming is an advantage\nPossess strong sense of analytical and problem solving skills\nGood command of both spoken and written Chinese and English", "employment_types": ["Full Time", "Permanent"], "selling_points": ["Data Analyst, Knowledge in Python, R", "Experience in Google Cloud, Googloe BigQuery", "AI, machine learning techniques/algorithms"], "locations": ["Kowloon Bay"], "categories": ["Professional Services", "Business Analysis / Data Analysis", "Information Technology (IT)", "Data Scientist"], "post_time": "2022-01-13T02:54:02Z", "salary": {"currency": null, "max": null, "min": null, "period": "monthly", "term": null}, "salary_visible": false, "title_keywords": ["specialist"], "responsibilities": ["data", "project deliverables", "review", "quality", "design", "data processing", "develop", "testing", "project documents", "maintain", "project reports", "specifications", "documentation"], "requirements": {"degrees": [], "majors": [], "languages": ["english", "chinese"], "language_level": ["good command"], "hard_skills": ["plus", "java", "web", "programming", "python", "problem solving skills"], "soft_skills": ["analytical and problem solving skills", "hands-on"], "languages_combined": [{"language": "english", "language_level": ["good command"]}, {"language": "chinese", "language_level": ["good command"]}]}, "experience_required": {"duration": ["at least 2 years"], "field": ["programming", "development", "management", "design"]}}, {"job_id": "100003009049579", "location_code": "hk", "company": "China Construction Bank (Asia) Corporation Limited", "job_title": "AVP / VP, Big Data Analytics & Machine Learning", "description": "Responsibility\n\nWork closely with the operation manager and liaise with different parties to ensure a smooth operation process under the company guidelines, strategy plans and procedures\nProvide effective solutions and recommendations on business operation\nIntegrate data from various sources and compile analytic reports for the management\nMonitor business data integrity\nAssist in ad-hoc duties as and when assigned\n\nRequirements:\n\nDiploma or above graduates\nProficient\u00a0in MS Excel (formula\u00a0setting, Lookup, Pivot Table, etc.)\nTeam player with a mature working attitude\nStrong sense in data, detail-minded, organized, meticulous and responsible\nImmediately available is highly prefered\n\nInterested candidates please click\u00a0APPLY NOW\u00a0to send your CV with current and expected salaries to us; Only shortlisted candidate will be notified.\u00a0 Personal data collected by job applicants will be kept in strict confidence and used for recruitment purpose only.", "employment_types": ["Full Time", "Permanent"], "selling_points": ["Data Management", "Big Data", "Machine Learning"], "locations": ["Not Specified"], "categories": ["Banking / Finance", "Corporate Banking", "Retail Banking", "Professional Services", "Business Analysis / Data Analysis"], "post_time": "2022-01-14T08:54:13Z", "salary": {"currency": null, "max": null, "min": null, "period": "monthly", "term": null}, "salary_visible": false, "title_keywords": [], "responsibilities": ["business operation", "management", "data", "procedures", "monitor", "company guidelines", "reports", "ad-hoc duties", "liaise with", "plans"], "requirements": {"degrees": ["diploma or above"], "majors": [], "languages": [], "language_level": [], "hard_skills": ["pivot table", "ms excel"], "soft_skills": ["detail-minded", "organized", "meticulous", "responsible", "mature", "team player"], "languages_combined": []}, "experience_required": {"duration": [], "field": []}}, {"job_id": "100003009042986", "location_code": "hk", "company": "DBS Bank Ltd", "job_title": "Associate/Analyst, Business Planning and Analytics, Corporate Banking", "description": "We are looking for:\n\nDegree holder\u00a0in all discipline\nEnergetic and outgoing\nMature, self\u00ad-motivated, hardworking and willing to learn\n1-2 years working experience is an advantage\nExperience\u00a0in banking industry or background in mainland will be an advantage\nOverseas Hong Kong Students are also welcome\nFluent in Cantonese, English and Mandarin is an advantage\u00a0\n\nResponsibilities:\n\nIdentifying needs of clients and providing\u00a0professional financial advice\nManagement of wealth assets of clients through investment vehicles\nUpdating financial news to your clients\nProviding\u00a0financial analyst, investment, saving, retirement, MPF\u00a0and\u00a0risk management\u00a0services\u00a0(Capital Investment Immigration Consultancy, Asset Management, Bonds & Mutual Funds Investment, Securities & Futures Dealing, Risk Management, Premium Financing)\nHigh End and Wealth Management for\u00a0HNW\u00a0and\u00a0PRC\u00a0Clients\nCorporate Solution Planning\u00a0for Corporate Clients\nProvide quality\u00a0after-sales services\u00a0to maintain good customer relationship\n\n\u00a0We\u00a0offer:\n\nOver 200 hours\u00a0well-structured and comprehensive mentoring program\nMonthly income from\u00a0HK$60,000 +\u00a0remuneration & fringe benefits\nOne year fast track program to managerial level\nSpecial holiday package\u00a0(2 company trips per year)\nOverseas learning experience\n\u201cWork Hard, Play Hard\u201dworking environment & lots of fun\nOpportunity to explore PRC and CIES business\n\nJob Description:\n\n1 \u00a0Professional Investment plannings for clients or companies\n\nWealth Management & Portfolio Advices\nInvestment Planning\nRetirement Planning\nPRC Business & CIES (Capital Investment Entrant Scheme) Planning\nCorporate Solutions Provision\n\n2 \u00a0Management level\n\nPlanning Strategies for Constructing Team\nLearn Leading, Recruiting & Managing Skills\nProvide marketing strategies skills\n\n3 \u00a0Self Continuous Improvement\n\nAchieve Professional Destinations (MDRT, COT, TOT, CFPCM,ChFC, RFP,RFC,etc.)\nAcquire Up-to-Date Financial Knowledge and News\nDevelop Better Interpersonal and Communication Skills\n\n4 \u00a0Development Path and Work Benefit\n\nA structured career path and solid training in all aspects of management\nYou will work very closely with a senior manager who will guide, train and mentor you\nManagement trainee programme offers excellent training and a fast track career into management\nSponsored overseas travelling for achieving yearly targets\n\nPlease click \"\u00a0APPLY NOW\u00a0'' if you are interested in our program.\u00a0\nWe always welcome talent.\u00a0", "employment_types": ["Full Time"], "selling_points": ["See job description.", "See job description.", "See job description."], "locations": ["Central"], "categories": ["Banking / Finance", "Corporate Banking", "Professional Services", "Business Analysis / Data Analysis"], "post_time": "2022-01-12T09:25:46Z", "salary": {"currency": null, "max": null, "min": null, "period": "monthly", "term": null}, "salary_visible": false, "title_keywords": ["analyst", "associate"], "responsibilities": ["management", "mpf", "quality", "planning", "maintain", "banking", "asset management"], "requirements": {"degrees": ["degree holder"], "majors": [], "languages": ["cantonese", "english", "mandarin"], "language_level": ["advantage", "fluent"], "hard_skills": [], "soft_skills": ["outgoing", "willing to learn", "mature", "energetic", "hardworking"], "languages_combined": [{"language": "cantonese", "language_level": ["fluent", "advantage"]}, {"language": "english", "language_level": ["fluent", "advantage"]}, {"language": "mandarin", "language_level": ["fluent", "advantage"]}]}, "experience_required": {"duration": ["1-2 years"], "field": ["banking industry"]}}, {"job_id": "100003009045665", "location_code": "hk", "company": "Huafa Properities (HK) Limited", "job_title": "Officer / Manager, BUSINESS MANAGEMENT(\u4f01\u696d\u7d93\u71df\u7ba1\u7406)", "description": "REPORTS TO\n\nHead of Private Markets Research\n\nRELATES TO\n\nDirector of Research & Analytics, Research Managers, Research Associates (London, HK and NYC)\n\nRESPONSIBLE FOR\n\nCreating and maintaining high-quality information and intelligence on the activities of fund managers in private markets.\n\nRole\nThe research associate forms part of a global team responsible for the research and maintenance of several online intelligence services that track the flow of capital between investors (LPs) and fund managers (GPs) active in the alternative asset classes.\n\nWe strive to ensure that opportunities to work and develop at PEI Media are fair, inclusive, and open to all. We welcome applications from all qualified candidates, regardless of age, disability, gender identity, or gender expression, race, ethnicity, religion or belief, sex, sexual orientation, or any other equality characteristic.\n\nPEI Media supports flexible working arrangements, and we welcome career returners.\n\nRequirements\n\nResearch\nBuilding and maintaining written and data-driven profiles of managers in private markets for publication in our online products\n\n\nUsing online sources, including company websites, regulatory filings and news sources to maintain up-to-date and accurate intelligence\n\n\nTelephone interviews with senior executives at fund management firms to determine their current and future fundraising plans\n\n\nTranslation of phone conversations with senior executives into the accurate input of data and intelligence\nAiding the execution of plans to improve the quality of research conducted on private market funds and managers by PEI\u2019s research team globally\nAiding the execution of plans to expand the numbers of private market funds and managers tracked by PEI\u2019s research team globally\nWriting\nWriting high quality factual copy to summarize the latest fundraising market updates\nWriting high quality data-led analysis pieces relating to managers of alternative asset funds and the fundraising environment\nData & Analysis\nBecoming expert in how best to interpret and present data in chart and graph form\nWorking as part of a team to rank the largest institutions in private markets\nWorking as a team to survey market participants and analyzing the results for publication across PEI\u2019s editorial titles\nKnowledge\nMaintaining an excellent knowledge of alternative assets through reading multiple intelligence sources to spot trends and contribute ideas for analysis\nUsing the above knowledge, the candidate will be expected to become a specialist in the following fields: private equity, private debt and the secondaries market\nThe balance of the above tasks, along with other duties, will vary.\nThe role demands first-rate organizational skills, excellent verbal and written communication and an analytical mind. The ability to focus and a keen eye for detail are essential to ensure that we maintain accuracy and a high quality of output. The research associate also needs to be comfortable with processes and must be thorough in his/her work.\nKey relationships\nThe research associate will work with a team of research associates within the local office and will be expected to build relationships with colleagues in other offices.\u00a0 The research associate will also need to build relationships with editorial, sales, event and marketing staff members where necessary.\nThe research associate is responsible for building relationships with senior contacts in the industry through telephone and e-mail correspondence and occasional face-to-face meetings.\nExperience/knowledge required\nThe role would suit individuals with highly developed written and research skills, high levels of self-motivation, excellent verbal communication skills and the ability to understand the dynamics of the industry so as to have informed conversations with its players. Past experience within a research role is useful, but not necessary.\nThe role also demands attention to detail and patience so that work is completed on time and to the required standard. Multitasking and strong time management skills are also essential.\nThe successful candidate must have excellent spoken and written English skills and be degree educated. Proficiency in Japanese, Korean, or Chinese is advantageous.\nThe role demands excellent research skills. The post holder should be inquisitive and have a proactive, methodological and enthusiastic approach to work.\nA working knowledge of and interest in financial services would be a distinct advantage. The potential to grasp the dynamics of the private markets industry is also required. The ability to work on one\u2019s own initiative whilst\u00a0maintaining close and effective relationships within a\u00a0team is needed.\n\nFresh graduates are welcome.\n\nKey success measures\nMeeting agreed deadlines\nBuilding strong relationships with key players within the candidate\u2019s specialization fields\nMeeting agreed targets of numbers of institutions researched and updated\nAccuracy of data researched, both from an individual and team level\nMaintenance of an enthusiastic and positive attitude towards work\n\nBenefits\n\n\n20 days\u2019 annual leave, employee will receive an extra one day of holiday after two full calendar years of service\nMedical insurance coverage after passing probation\nEmployee Assistance Programme to enhance employee\u2019s wellbeing\nDental plan provided to employee at a discounted price\nVolunteer leave in service to an approved charitable or community organisation\nFlexible working hours, including options to work from home", "employment_types": ["Full Time"], "selling_points": ["5-day working week", "attractive remuneration package", "state-owned-enterprise"], "locations": ["Central"], "categories": ["Professional Services", "Business Analysis / Data Analysis", "Management", "General Management", "Property / Real Estate", "Others"], "post_time": "2022-01-13T08:18:21Z", "salary": {"currency": null, "max": null, "min": null, "period": "monthly", "term": null}, "salary_visible": false, "title_keywords": ["officer", "manager"], "responsibilities": ["company websites", "management", "ideas", "maintenance", "maintaining", "data", "other duties", "analysis", "maintain accuracy", "quality", "develop", "communication", "maintain", "reports", "plans", "publication"], "requirements": {"degrees": ["degree"], "majors": [], "languages": ["japanese", "english", "chinese", "korean"], "language_level": ["excellent", "proficiency"], "hard_skills": ["maintenance", "analysis", "translation", "focus", "private equity"], "soft_skills": ["organizational skills", "communication", "self-motivation", "patience", "focus", "keen", "analytical mind", "initiative", "communication skills", "eye for detail", "attention to detail", "enthusiastic", "accurate", "active", "driven", "flexible", "research skills", "responsible", "time management skills", "positive attitude", "thorough", "proactive"], "languages_combined": [{"language": "japanese", "language_level": ["proficiency"]}, {"language": "english", "language_level": ["excellent"]}, {"language": "chinese", "language_level": ["proficiency"]}, {"language": "korean", "language_level": ["proficiency"]}]}, "experience_required": {"duration": [], "field": ["research"]}}, {"job_id": "100003009049578", "location_code": "hk", "company": "China Construction Bank (Asia) Corporation Limited", "job_title": "Manager /Assistant Vice President, Data Management", "description": "Job Duties and Responsibilities\n\nDevelop customer analytics data foundation and deliver behavioral analytics deliverables to business units with business insights and recommendation\nEnable the dialogue about the value and meaning of the analytic insights, and make it easy for business stakeholders to apply data-driving decisions across the business\nExplore the availability, access and transformation/use of sales performance and browsing data for analytics purpose\nDevelop advanced analytics/machine Learning-based solutions to uplift effectiveness of analytics and modelling riding on (i) supervised/ unsupervised Machine Learning techniques (ii) unstructured data e.g. digital footprint\nWork with business users in setting the data strategy and vision\nWork with the business users in collaboration around value-driven data analytics and focus effort on what is best to deliver to business\n\n\u00a0Requirements\n\n\n\nBachelor\u2019s / Master's degree in Mathematics, Computer Science, Data and Information Management or a related discipline\nMinimum 3 years of hands-on experience in developing and executing large scale analytics deliverables/ projects in Retail Industry\nProficiency with one or more programming/scripting languages (e.g. Python, R) as well as SQL\nHands on experience in Google Cloud and Google BigQuery platforms.\nExperience in applying artificial intelligence and machine learning techniques/algorithms infused with industry knowledge to enhance business strategies\nStrong in transforming analytical concepts and developments into business strategies and applications for the uplift of business value\nAbility to build strong stakeholders\u2019 relationships through thorough understanding of business requirements and the ability to analyse issues to find effective solutions\nEffective presentation, communication and interpersonal skills\n\nWe offer competitive remuneration package with\u00a0a wide range of fringe benefits including\n\n5-day work week\nDiscretionary Bonus\nComprehensive Medical Coverage\nStaff Shopping Discount\nNon-contributory Retirement Benefits Scheme\nBirthday Leave\nPlease send resume with present and expected salary to Human Resources Department, Swire Resources Limited, 12/F Kingston International Centre 19 Wang Chiu Road Kowloon Bay Hong Kong or by clicking the \"Apply Now\" button below.\n\nSwire Resources Limited is Equal Opportunity Employer", "employment_types": ["Full Time", "Permanent"], "selling_points": ["Data Management", "Data Governance model", "Envision & shape the governance"], "locations": ["Not Specified"], "categories": ["Banking / Finance", "Corporate Banking", "Retail Banking", "Professional Services", "Business Analysis / Data Analysis"], "post_time": "2022-01-14T08:54:13Z", "salary": {"currency": null, "max": null, "min": null, "period": "monthly", "term": null}, "salary_visible": false, "title_keywords": ["manager", "assistant vice president"], "responsibilities": ["sales performance", "data", "develop"], "requirements": {"degrees": ["degree", "bachelor", "master"], "majors": ["mathematics", "computer science"], "languages": [], "language_level": [], "hard_skills": ["python", "r", "sql", "programming"], "soft_skills": ["ability to analyse", "hands-on", "hands on", "learning", "thorough", "communication and interpersonal skills", "presentation"], "languages_combined": []}, "experience_required": {"duration": ["minimum 3 years"], "field": ["retail industry", "business", "developing"]}}, {"job_id": "100003009050526", "location_code": "hk", "company": "Wharf Real Estate Investment Company Limited", "job_title": "BUSINESS EXECUTIVE", "description": "Responsibilities:\n\n\nExplore the availability, access and transformation/ use of unstructured data (browsing data, voice, email, picture, videos) for analytics and customer contact purpose\nHands-on develop advanced analytics/ Machine Learning-based solutions to uplift effectiveness of analytics, modelling and customer contact riding on (i) supervised/ unsupervised Machine Learning techniques (ii) unstructured data e.g. digital footprint\nStudy and develop the business implementation of speech and text analytics\nIntegrate customer external and internal data, structured and unstructured\nDevelop close-loop learning path and ensure insights and learnings are carried out for continuous customer interactions\nAs the Subject Matter Expert, trainer and advocate to uplift the machine learning skillset and culture of existing analysts pool\n\nRequirements:\n\nBachelor\u2019s / Master's degree in Computer Science, Data and Information Management or a related discipline\nA data scientist with minimum 8 years of hands-on experience in developing and executing large scale analytics deliverables/ projects in the Financial Services Industry\nDeep experience in applying artificial intelligence and machine learning techniques/algorithms, infused with industry knowledge, to enhance business strategies\nStrong in transforming analytical concepts and developments into business strategies and applications for the uplift of business value\nAbility to build strong stakeholders\u2019 relationships through thorough understanding of business requirements and the ability to analyse issues to find effective solutions\nSolid experience in training analysts on machine learning techniques\nEffective presentation, communication and interpersonal skills\nGreat sense of ownership and servicing mindset to ensure efficient and effective customer service processes\nProficiency in English and Chinese (both Cantonese and Mandarin)\nCandidate with less experience will be considered for the AVP position\n\nPlease specify your current and expected package in your application for reference.\u00a0\n\nApplicants who are not contacted within 8 weeks may consider their applications unsuccessful and their personal data will be retained by the bank for a period up to two years.\n\nAll information provided by applicants will be used for recruitment purposes only and will be used strictly in accordance with the bank\u2019s personal data policies, a copy of which will be provided upon request.", "employment_types": ["Full Time", "Permanent"], "selling_points": ["Fast-track career development", "Degree holder or above in related disciplines", "3-5 years\u2019 relevant working experience"], "locations": ["Tsim Sha Tsui"], "categories": ["Professional Services", "Business Analysis / Data Analysis", "Property / Real Estate", "Property Management", "Management", "Management Trainee"], "post_time": "2022-01-15T03:51:10Z", "salary": {"currency": null, "max": null, "min": null, "period": null, "term": null}, "salary_visible": false, "title_keywords": ["business executive"], "responsibilities": ["data", "implementation", "subject matter expert", "develop", "contact"], "requirements": {"degrees": ["degree", "bachelor", "master"], "majors": ["computer science"], "languages": ["cantonese", "english", "chinese", "mandarin"], "language_level": ["proficiency"], "hard_skills": [], "soft_skills": ["efficient", "ability to analyse", "deep", "hands-on", "learning", "communication and interpersonal skills", "thorough", "customer service", "presentation"], "languages_combined": [{"language": "cantonese", "language_level": []}, {"language": "english", "language_level": ["proficiency"]}, {"language": "chinese", "language_level": ["proficiency"]}, {"language": "mandarin", "language_level": []}]}, "experience_required": {"duration": ["minimum 8 years"], "field": ["financial services industry", "business", "training", "developing"]}}, {"job_id": "100003009046526", "location_code": "hk", "company": "Sun Hung Kai Properties Ltd", "job_title": "ASSOCIATE DATA SCIENTIST / DATA SCIENTIST", "description": "Business Function\nCorporate and Investment Banking provides corporate customers with a full range of commercial banking products and services, including cash management services, current accounts, time deposits, trade finance, working capital finance, term loans and foreign exchange. Through our continued commitment, DBS has cultivated long-standing relationships with its customers in the region that are based on account relationship management, service differentiation, product development and rigorous credit standards.\n\nObjectives\n\nProvide financial and business performance reports, dashboards and analytics to facilitate strategic planning, budget, forecast, performance management pertaining to Institutional Banking Group\n\nResponsibilities\n\nSupport the Head of Business Planning & Analytics to formulate business strategies, financial budget/forecast and action plans for the Institutional Banking Group\nCompile accurate and comprehensive intelligent management dashboards, presentation, performance reports and data analytics to track business performance, measure sales effectiveness / productivity and identify insights on business opportunities or performance gaps for possible areas for improvement.\nProvide result tracking of the performance scorecard to ensure business objectives and KPIs are well observed and met\nWork with Business Finance, Corporate Treasury and TLM to review funding/FTP/ capital management and support special funding program to acquire high yield loans and deposits to drive capital efficiencies and improve our competitive edge and ROE\nConduct accounting entries and perform financial reconciliation for the business\n\nRequirements\n\nBachelor\u2019s degree, preferably in Financial Management, Accounting, Economic, Mathematics, Statistics or related disciplines\nAt least 5 years of relevant experience in banking industry with strong understanding of corporate banking products and services.\nSuitable candidates with less experience may be considered as Analyst instead\nStrong business acumen, with solid knowledge of accounting and financial analysis.\nConversant with PC skills, in particular Excel, Access and PowerPoint. Knowledge of Qlikview and Python is preferred \u00a0\nStrong analytical and problem-solving skills, with the ability to come up with effective business strategies to drive business growth based on quantitative analysis\nWork well in a collaborative environment. Good interpersonal, communication and presentation skills\nAble to work with financial and operation teams and business users, handling multiple tasks, attention to details and meeting tight deadlines under pressure", "employment_types": ["Full Time", "Permanent"], "selling_points": ["Leveraging large amount of data", "Must be proficient in Python", "Amazon AWS, Big data tools, query lang for SQL"], "locations": ["Wan Chai"], "categories": ["Professional Services", "Business Analysis / Data Analysis", "Information Technology (IT)", "Product Management / Business Analyst", "Data Scientist"], "post_time": "2022-01-13T13:10:50Z", "salary": {"currency": null, "max": null, "min": null, "period": null, "term": null}, "salary_visible": false, "title_keywords": ["associate", "data scientist"], "responsibilities": ["management", "tracking", "kpis", "performance reports", "data", "business opportunities", "budget", "review", "forecast", "banking", "plans", "planning"], "requirements": {"degrees": ["degree", "bachelor"], "majors": ["related disciplines", "mathematics", "accounting", "statistics"], "languages": [], "language_level": [], "hard_skills": ["excel", "qlikview", "analysis", "powerpoint", "financial analysis", "python", "problem-solving skills", "pc skills", "acumen"], "soft_skills": ["meeting tight deadlines", "under pressure", "multiple tasks", "collaborative", "communication", "presentation skills", "attention to details", "business acumen", "problem-solving skills", "interpersonal"], "languages_combined": []}, "experience_required": {"duration": ["at least 5 years"], "field": ["banking industry", "relevant experience", "banking"]}}, {"job_id": "100003009046614", "location_code": "hk", "company": "MTR Corporation Limited", "job_title": "System Support Officer (Ref: 2200002X)", "description": "KEY RESPONSIBILITIES:\n\n1. Work closely with Zhuhai headquarters to organize, direct, coordinate and control the business activities so as to ensure the realization of the business plan and guard against all kinds of risks;\n\n2. Assist the senior Management to develop business strategies, business plans, organizational structure, risk management policies etc. for the company;\n\n3.\u00a0Coordinate with all departments to streamline and strengthen existing business operations and controlling procedures;\n\n4. Generate regular reports/statistics to monitor the business operations performance, propose corrective & improvement actions, and develop the performance evaluation for internal departments;\n\n5. Keep abreast of market information, government policies and business trends, give advices to the senior Management for the new business opportunities;\n\n6. Preform any ad hoc duties assigned by the Company\n\n\nREQUIREMENTS:\n\n1. Degree in Economics, Finance, or Business Administration related disciplines;\n\n2. Experienced in state-owned enterprise of China/ Chinese enterprise is a plus;\n\n3. 3-5 years solid experiences in business management;\n\n4. Be self-motivated and a good team player with excellent communication, interpersonal and influencing skills;\n\n5. Mature, detailed-oriented, meticulous with strong time management and organizing skills;\n\n6. Proficient in Cantonese, Putonghua and English, good Chinese writing skill;\n\n7. Immediately available is highly preferred.", "employment_types": ["Full Time"], "selling_points": ["Support the development, implementation", "Higher Diploma / Higher Certificate", "A minimum of 8 years' relevant experience"], "locations": ["Others"], "categories": ["Professional Services", "Business Analysis / Data Analysis", "Engineering", "Building & Construction", "Civil / Structural"], "post_time": "2022-01-13T16:26:46Z", "salary": {"currency": null, "max": null, "min": null, "period": "monthly", "term": null}, "salary_visible": false, "title_keywords": ["officer", "system support"], "responsibilities": ["ad hoc duties", "control", "management", "market information", "policies", "operations", "business opportunities", "coordinate with", "procedures", "business plans", "develop", "coordinate", "monitor", "reports", "evaluation", "business plan", "senior management", "business activities"], "requirements": {"degrees": ["degree"], "majors": ["related disciplines", "finance", "economics", "business administration"], "languages": ["cantonese", "putonghua", "english", "chinese"], "language_level": ["good", "proficient"], "hard_skills": ["business management", "plus", "writing skill"], "soft_skills": ["meticulous", "good team player", "self-motivated", "mature", "writing skill", "communication", "time management", "interpersonal", "detailed"], "languages_combined": [{"language": "cantonese", "language_level": ["proficient", "good"]}, {"language": "putonghua", "language_level": ["proficient", "good"]}, {"language": "english", "language_level": ["proficient", "good"]}, {"language": "chinese", "language_level": ["good"]}]}, "experience_required": {"duration": ["3-5 years"], "field": ["management", "business"]}}, {"job_id": "100003009044875", "location_code": "hk", "company": "Hongkong International Terminals Limited", "job_title": "Assistant Operations Process Analyst", "description": "Responsibilities:\n\n\nFollow the guidelines of Data Governance model from Head Office to setup the Bank's own Data Governance framework, and act abide by it\nEnvision & shape the governance, scope, framework and implementation plan in relationship to data quality management\nCollaborate effectively with technology, operations/ process, business and other stakeholders to formulate and lead project team on data quality to define data quality governance structure, identify critical data elements, and define data quality dashboards/ KPIs for ongoing monitor and review\nPerform data quality profiling and analysis, identify issues where applicable\nFormulate remediation strategy/ approach; drive, coordinate and collaborate with stakeholders on remediation activities; orchestrate between different data quality initiatives\nDevelop MI reports to provide business insight or review business performance\nAutomate the generation of regular reports to minimize human intervention\nSetup an effective mechanism to do ETL for external data, ensure the readiness and accuracy of data\nFacilitate the usage of OLAP tools and coordinate its related enhancements\u00a0\n\nRequirements:\n\n\nBachelor / Master degree in Computer Science, Data and Information Management or a related discipline\nMinimum 3 years' banking experience in information and data management, leads and campaign management, MI reporting with respect to programming and database architecture\nProven experience in leading and driving data quality management initiatives with measurable achievements\nTrack record of experience in data governance projects in banking industry\nKnowledge of data structures, data systems and tools and related software and data management policies and practices in a complex organizational environment an added advantage\nHands on experience in programming language : SAS, VBA, SQL etc.\nExcellence command of MS Excel (e.g. advanced formulas)\nBusiness process analysis skills, including the ability to analyze and document the current processes and organizations that create and manage the client data\nExcellent project management skill is a must with the ability to get things done through others not directly under his or her supervision\nGood command of written and spoken English, Chinese and Putonghua\nCandidates with less experience will be considered for the Manager position while candidates with more experience will be considered for the Vice President position\n\nPlease specify your current and expected package in your application for reference.\u00a0\n\nApplicants who are not contacted within 8 weeks may consider their applications unsuccessful and their personal data will be retained by the bank for a period up to two years.\n\nAll information provided by applicants will be used for recruitment purposes only and will be used strictly in accordance with the bank\u2019s personal data policies, a copy of which will be provided upon request.", "employment_types": ["Full Time", "Permanent"], "selling_points": ["Degree Holder with relevant experiences", "5-day week, double pay, bonus, free shuttle bus", "Fresh graduates are also welcome"], "locations": ["Kwai Fong"], "categories": ["Professional Services", "Business Analysis / Data Analysis", "Engineering", "Engineering Project Management", "Manufacturing & Production"], "post_time": "2022-01-13T06:32:26Z", "salary": {"currency": null, "max": null, "min": null, "period": "monthly", "term": null}, "salary_visible": false, "title_keywords": ["analyst", "operations", "assistant"], "responsibilities": ["collaborate", "collaborate with", "management", "data", "guidelines", "operations", "analysis", "review", "quality", "implementation", "monitor", "develop", "coordinate", "reports", "plan", "kpis", "setup"], "requirements": {"degrees": ["bachelor", "master degree"], "majors": ["computer science"], "languages": ["putonghua", "english", "chinese"], "language_level": ["good command"], "hard_skills": ["vba", "data management", "sas", "analysis", "sql", "project management", "ms excel", "programming"], "soft_skills": ["advanced", "organizational", "ability to analyze", "hands on", "project management skill"], "languages_combined": [{"language": "putonghua", "language_level": ["good command"]}, {"language": "english", "language_level": ["good command"]}, {"language": "chinese", "language_level": ["good command"]}]}, "experience_required": {"duration": ["minimum 3 years"], "field": ["banking industry", "management", "banking experience", "sql", "programming", "quality management", "database"]}}, {"job_id": "100003009051478", "location_code": "hk", "company": "BDO", "job_title": "Manager / Senior Associate / Associate (IT Audit / Audit Analytics) - Assurance", "description": "The Company is committed to building and developing quality human capital, not only for operational excellence that leads to organizational growth but also for career growth for aspiring talents.\u00a0 In support of our quest for operational excellence and value creation, we aim at developing mid-career talents to be our future leaders at different levels to meet the business growth and embrace the challenges ahead.\n\nDepending on the career aspiration, exposure and qualification, the successful candidates will undergo placements in the investment properties in HK and Mainland covering retail and office\u00a0leasing/ marketing/ centre operations/ tenant services.\u00a0 We also seek candidates with competence and interest in functions of asset management, business development and finance, investment and treasury, accounting and company secretary.\u00a0 For having a more holistic perspective of the Company's business, rotation opportunities would form part of the career development and the incumbents will be nurtured for taking up management positions upon completion of the programme.\nBachelor degree holder or above in related disciplines.\nNo less than 3-5 years' relevant working experience gained in sizable/ reputable organizations.\nMembership of professional body in related disciplines will be given priority consideration.\nResourceful, positive thinking, self-motivated, versatile, innovative, highly analytical, organized and a good team player with strong interpersonal and communication skills.\nDemonstrated strong leadership skills with sound business acumen.\nHigh proficiency in both spoken and written English, Chinese and Putonghua.\nPast recruits for post-university graduates have attained company directorship\nAttractive financial packages will be offered to successful applicants, commensurate with professional status and past experience. If you are ready to take the challenge, please send your application letter and full resume with date available, present and expected salary to the recruitment e-mail address.\n(Personal data provided will be used strictly in accordance with the Company\u2019s personal data policy which is available upon request.)", "employment_types": ["Full Time", "Permanent"], "selling_points": ["Data Modelling, analytics and visualization", "Conduct IT audit / assessment", "Excellent Career Prospects"], "locations": ["Sheung Wan"], "categories": ["Accounting", "Audit", "Professional Services", "Business Analysis / Data Analysis", "Information Technology (IT)", "IT Auditing"], "post_time": "2022-01-16T03:50:00Z", "salary": {"currency": null, "max": null, "min": null, "period": "monthly", "term": null}, "salary_visible": false, "title_keywords": ["senior associate", "associate", "manager"], "responsibilities": ["management", "operations", "quality", "developing", "communication", "recruitment", "career development", "personal data", "asset management"], "requirements": {"degrees": ["bachelor degree holder"], "majors": ["related disciplines"], "languages": ["putonghua", "english", "chinese"], "language_level": ["proficiency"], "hard_skills": ["no", "acumen"], "soft_skills": ["organized", "self-motivated", "good team player", "communication skills", "resourceful", "organizational", "versatile", "leadership skills", "positive thinking", "committed", "business acumen", "innovative", "interpersonal"], "languages_combined": [{"language": "putonghua", "language_level": ["proficiency"]}, {"language": "english", "language_level": ["proficiency"]}, {"language": "chinese", "language_level": ["proficiency"]}]}, "experience_required": {"duration": ["3-5 years"], "field": ["relevant working experience", "financial"]}}, {"job_id": "100003009047778", "location_code": "hk", "company": "iTalent Company", "job_title": "Data Analytics Manager - HK Listed Company", "description": "Requirements:\n\n\nBachelor\u2019s degree in Computer Science, Econometrics, Mathematics, Operation Research, Statistics or related disciplines\nMinimum 2 years\u2019 work experience in data science with proven track record of leveraging large amount of data to drive significant business impact\nAdvanced analytical skills, experience in recommending appropriate algorithm and methodology for problem-solving and decision making, leveraging both logic and creativity\nExposure to Amazon AWS core services such as S3, EC2, API Gateway, and Lambda is advantageous\nExperience in prototyping and productionalizing advance analytics solutions in business\nMust be proficient in Python. Knowledge of Java, Scala and C++ is a plus\nExperience in IT big data tools (e.g Hadoop, Spark), as well as query languages for SQL and NoSQL\nFamiliar with machine learning algorithm and libraries (e.g. scikit-learn, XGBoost, LGBM, TensorFlow etc.)\nProficiency in data visualization tools, ideally Tableau\nExperience with MLOps and DevOps solution architecture design is a plus\nUnderstands common software engineering best practices such as is a code versioning, test-driven development, and code modularization\n\nResponsibilities:\n\n\nTranslate unstructured business questions into quantitative problems\nPrototyping advance analytics and machine learning solutions for business partners\nProvide advanced analytics support and advise on appropriate analytical models based on available data, technology and platform\nMake intelligent approximations to the model if required to make it scalable and operatable\nAnticipate needs and lead implementation of capabilities such as data modelling, algorithms, new technology & partners\nRecommend and implement the development path of capabilities and skillsets to foster a culture of applying data & insight driven culture in decision making\n\n(Candidates with more experience will be considered as Data Scientist.)\n\nGood remuneration and attractive fringe benefits will be offered to the successful applicant. Interested parties please apply with full resume, present and expected salary, available date by clicking \u201cApply Now\u201d.\n\nFor further information, please visit our company website:\u00a0http://www.shkp.com/.\n\nWe are an equal opportunity employer and welcome applications from all qualified candidates. All personal data collected will be used for recruitment purpose only.\u00a0 Applicants not hearing from us within 3 months may consider their applications unsuccessful.\u00a0 All personal data collected will be destroyed within 24 months.", "employment_types": ["Full Time", "Permanent"], "selling_points": ["Strategic planning for data management", "Subject Matter Expert and adovate data culture", "7 yrs+ data management exp, vendor exp is a plus"], "locations": ["Not Specified"], "categories": ["Professional Services", "Business Analysis / Data Analysis", "Information Technology (IT)", "DBA", "Data Scientist"], "post_time": "2022-01-14T03:53:07Z", "salary": {"currency": null, "max": null, "min": null, "period": "monthly", "term": null}, "salary_visible": false, "title_keywords": ["manager"], "responsibilities": ["implementation", "data"], "requirements": {"degrees": ["degree", "bachelor"], "majors": ["related disciplines", "mathematics", "statistics", "computer science"], "languages": [], "language_level": [], "hard_skills": ["java", "amazon", "plus", "c++", "problem-solving", "devops", "code", "tableau", "aws", "analytical skills", "scala", "sql", "data visualization", "python", "spark", "s3"], "soft_skills": ["advanced", "problem-solving", "analytical skills", "learning", "driven", "decision making"], "languages_combined": []}, "experience_required": {"duration": ["minimum 2 years"], "field": ["analytical", "devops", "design", "business", "it"]}}, {"job_id": "100003009050889", "location_code": "hk", "company": "KOS International Limited", "job_title": "Senior Manager, Business Analytics & Data Warehouse (Bank)", "description": "Responsibilities\n\nSupport the development, implementation and review of Integrated Management System (IMS) and Asset Management System (AMS) for various asset disciplines in the department\nAssist in the governance of maintenance activities in accordance with AMS and IMS\u00a0\nImplement and monitor safety, quality and asset management\u00a0related initiatives to improve performance\nPerform data analytics and reporting on key performance indicators\u00a0\nSupport the preparation, monitoring and control of maintenance and costing and coordinate budget variance analysis\nReview and compile documentation including departmental procedure and work instruction in accordance with statutory and corporate requirements and monitoring the review progress\nDevelop and monitor inspection plan and prepare summary/analysis of findings from inspection/audit\nSupport the development, implementation and maintenance of eProcess for various departmental governance mechanisms\nSupport departmental recruitment plan, competency management assessment and staff development program\nConduct departmental event, develop and implement large-scale promotion campaign and develop staff communication initiatives\u00a0\n\nRequirements\n\nHigher Diploma / Higher Certificate in Engineering / Business Administration or a related discipline\nA minimum of 8 years' relevant experience, of which 3 years should be at supervisory level\nGood command of both written and spoken English and Chinese\nAble to work independently and under pressure with strong analytical and interpersonal skills\nKnowledge of railway safety rules and related statutory requirements is an advantage\nWell-versed with various software applications and IT system and Access, preferably with versatility in various Management Information System\n\nRemarks\n\nCandidates with less experience or lower qualification will be considered for the Assistant System Support Officer position\n\nApplications\n\nYou are invited to apply online via Careers at MTR or send in your CV stating the position (with reference number) you are applying for by mail to Human Resource Management Department, MTR Corporation, G.P.O. Box 9916, Hong Kong on or before 27 January 2022.\n\nFor other job openings, please visit MTR Corporation's website for more details.\n\nAll information provided by applicants will be treated in strict confidence and used for recruitment purpose only. All personal data of unsuccessful applicants will be retained for 12 months for future recruitment purpose and will then be destroyed.\n\u00a0", "employment_types": ["Full Time", "Permanent"], "selling_points": ["Strong business analytics skills", "Data warehouse and modeling projects", "SAS / SQL required"], "locations": ["Not Specified"], "categories": ["Banking / Finance", "Retail Banking", "Professional Services", "Business Analysis / Data Analysis", "Information Technology (IT)", "Data Scientist"], "post_time": "2022-01-14T11:40:02Z", "salary": {"currency": null, "max": null, "min": null, "period": "monthly", "term": null}, "salary_visible": false, "title_keywords": ["senior manager"], "responsibilities": ["data", "budget", "quality", "audit", "communication", "plan", "control", "monitor", "implementation", "develop", "reporting", "management", "review", "monitoring", "inspection", "variance analysis", "documentation", "maintenance", "analysis", "coordinate", "recruitment", "asset management"], "requirements": {"degrees": ["diploma", "higher certificate"], "majors": ["business administration", "engineering"], "languages": ["english", "chinese"], "language_level": ["good command"], "hard_skills": ["information system"], "soft_skills": ["work independently", "confidence", "under pressure", "interpersonal skills"], "languages_combined": [{"language": "english", "language_level": ["good command"]}, {"language": "chinese", "language_level": ["good command"]}]}, "experience_required": {"duration": ["3 years", "minimum of 8 years"], "field": ["supervisory level", "system support", "relevant experience"]}}, {"job_id": "100003009039209", "location_code": "hk", "company": "DHL EXPRESS (HONG KONG) LIMITED", "job_title": "Facilities Management Analyst", "description": "Main Duties:\nPrepare feasibility studies and provide solution design on various terminal operational technology projects such as equipment automation, process digitalization and so on\nWork closely with technical teams and vendors on resources allocation and project scheduling\nCarry out testing and provide user training to ensure smooth delivery\nFacilitate on-site implementation, conduct post-implementation reviews and on-going enhancements\nRequirements:\n\nDegree holder in Engineering, Operations Management or other related disciplines with 2-year relevant working experiences\nProficient in MS Office with knowledge of MS Project is a plus\nCustomer-focused and self-motivated with excellent analytical, presentation and communication skills\nAble to work independently under pressure and tight schedule\nFluent in written and spoken English and Chinese (Cantonese and Putonghua)\nCandidate with more experiences will be considered as Operations Process Analyst\nFresh graduates are also welcome\nPlease apply through our Career Centre at\u00a0Assistant Operations Process Analyst | HIT.\u00a0You may also apply the job by sending your full resume with current and expected salary to Human Resources Manager, Terminal 4, Container Port Road South, Kwai Chung.\n\nFor further information, please visit our website at\u00a0HIT:: Hongkong International Terminals\n\nPlease read the Personal Information Collection Statement before submitting your application.\n\nWe are an equal opportunity employer and welcome applications from all qualified candidates. The information provided will be treated in strict confidence and used only for consideration of application for relevant/similar positions within the Hutchison Group of Companies. Applicants not invited for interview in 6 weeks after job posting may consider their application unsuccessful and your personal data will be destroyed after a period of 6 months.", "employment_types": ["Full Time", "Permanent"], "selling_points": ["Conduct market research and analysis", "Maintain updated building certificates and service", "3 years\u2019 relevant experience in facilities mgmt."], "locations": ["Ngau Tau Kok"], "categories": ["Admin & HR", "Clerical / Admin Staff", "Professional Services", "Business Analysis / Data Analysis", "Marketing / Public Relations", "Marketing - Market Research"], "post_time": "2022-01-11T09:01:30Z", "salary": {"currency": null, "max": null, "min": null, "period": "monthly", "term": null}, "salary_visible": false, "title_keywords": ["analyst"], "responsibilities": ["teams", "implementation", "design", "testing", "project scheduling"], "requirements": {"degrees": ["degree holder"], "majors": ["related disciplines", "engineering"], "languages": ["cantonese", "putonghua", "english", "chinese"], "language_level": ["fluent"], "hard_skills": ["plus", "container", "ms office"], "soft_skills": ["communication skills", "self-motivated", "work independently", "customer-focused", "under pressure", "confidence", "presentation"], "languages_combined": [{"language": "cantonese", "language_level": ["fluent"]}, {"language": "putonghua", "language_level": ["fluent"]}, {"language": "english", "language_level": ["fluent"]}, {"language": "chinese", "language_level": ["fluent"]}]}, "experience_required": {"duration": ["2-year"], "field": ["related", "operations management", "engineering"]}}, {"job_id": "100003009044647", "location_code": "hk", "company": "Hong Kong Express Airways Limited", "job_title": "Manager, Digital Experience (Digital Analytics)", "description": "Responsibilities:\n\nAssist in planning and scoping of client engagements\nConduct IT audit or independent assessment to evaluate system security and control effectiveness\nDesign and apply appropriate data modelling, analytics and visualization techniques in audit engagements\nCommunicate and report findings to senior management and clients\nSupport and act towards the BDO Global Vision\nBe committed to act with the firm\u2019s core values and competency expectations\n\nRequirements:\n\nBachelor degree or above in Information Technology Management, Computer Science, Mathematics, Accounting or other relevant fields\nExperience in auditing, data analytics or programming is a plus but not a must\nAbility to work independently within a team environment\nExcellent command of written and spoken English and Chinese, including Putonghua\nPosition offered will commensurate with the experience of the right candidate\n\nWe are an equal opportunity employer, and offer excellent prospects and career development for the right candidate.\u00a0 Interested parties please send your application\u00a0with full career history, current and expected salary by clicking the\u00a0Apply Now\u00a0button below.\n\nApplications will be treated in strict confidence. Personal data collected will be used for recruitment purposes only.", "employment_types": ["Full Time"], "selling_points": ["Digital analytics, data", "ecommerce analytics", "digital experience"], "locations": ["Airport Area"], "categories": ["Professional Services", "Business Analysis / Data Analysis"], "post_time": "2022-01-13T04:58:40Z", "salary": {"currency": null, "max": null, "min": null, "period": "monthly", "term": null}, "salary_visible": false, "title_keywords": ["manager"], "responsibilities": ["control", "visualization", "data", "audit", "design", "evaluate", "system security", "report", "senior management", "planning"], "requirements": {"degrees": ["degree or above", "bachelor"], "majors": ["mathematics", "accounting", "computer science", "information technology"], "languages": ["putonghua", "english", "chinese"], "language_level": ["excellent"], "hard_skills": ["data analytics", "plus", "programming"], "soft_skills": ["work independently"], "languages_combined": [{"language": "putonghua", "language_level": ["excellent"]}, {"language": "english", "language_level": ["excellent"]}, {"language": "chinese", "language_level": ["excellent"]}]}, "experience_required": {"duration": [], "field": ["programming"]}}, {"job_id": "100003009044961", "location_code": "hk", "company": "ELEVATE Hong Kong Holdings Limited", "job_title": "Senior ESG Data Scientist", "description": "Our client\n\nA HK listed company. They are looking for Data Analytics Manager to join their team.\n\nYour role\n\nStrategic Planning in data collection, processing and providing insight to support business growth\nExplore and apply latest Big Data technologies and applications\nWork with the internal and external stakeholders to enhance the awareness of data insight\nAs the Subject Matter Expert, trainer and advocate to uplift the data analytics skillset and culture of the team\n\nRequirement\n\nMinimum of 7 years' experience with proven record in data analysis/statistics and big data projects\nExperience in both in-house and vendor is a plus\nGood understanding of advanced data analysis tools and methodology, in particulars, big data analytics and Al modelling\nPassionate, creative and organized problem solver with a strong market-centric mindset and data driven capabilities\n\nClick \"Apply Now\" to apply for this position or\u00a0call\u00a0us\u00a0at\u00a0+852 2762 4829\u00a0for a confidential discussion. All information collected will be kept in strict confidence and will be used for recruitment purpose only.", "employment_types": ["Full Time"], "selling_points": ["with an amazing team of like-minded creative think", "in a fast-paced dynamic environment", "deep interest in sustainability and supply chains"], "locations": ["Quarry Bay"], "categories": ["Professional Services", "Business Analysis / Data Analysis", "Transportation & Logistics", "Supply Chain", "Sciences, Lab, R&D", "Research & Development (R&D)"], "post_time": "2022-01-13T06:45:18Z", "salary": {"currency": null, "max": null, "min": null, "period": "monthly", "term": null}, "salary_visible": false, "title_keywords": ["data scientist"], "responsibilities": ["strategic planning", "data", "big data", "subject matter expert", "data analysis", "recruitment", "data collection"], "requirements": {"degrees": [], "majors": [], "languages": [], "language_level": [], "hard_skills": ["plus", "data analytics", "analysis", "vendor", "processing"], "soft_skills": ["passionate", "organized", "confidence", "problem solver", "advanced", "creative", "driven"], "languages_combined": []}, "experience_required": {"duration": ["minimum of 7 years"], "field": ["data analysis", "statistics"]}}, {"job_id": "100003009022593", "location_code": "hk", "company": "Peak Vision Appraisals Limited", "job_title": "Financial Analyst - Valuation", "description": "Senior Manager, Business Analytics and Data Warehouse (Bank)\n\nBusiness and campaign analysis\nData warehouse and platform enhancement\nData modeling projects\n\nAbout the company\n\nOur client is a fast growing and well-established banking group with extensive branch network in Hong Kong. Due to the recent expansion, they are now looking for a Senior Manager for their Business Analytics and Data Warehouse team.\n\nAbout the role\n\nReporting to Team Head, you will be responsible for preparing various business analysis based on statistical modeling and data mining to provide business insight to management. You have to propose, build and execute predictive modeling and data projects independently. You are required to manage overall performance and security control of data platform. In addition, you will participate in policy and regulatory updates as well as maintenance of data framework to ensure effective operations of data team.\n\nThe Successful Applicant\n\nTo qualify, the successful individual must possess:\n\nUniversity Graduate, preferably in Statistics, Quantitative Analysis, Data Science or related disciplines.\nMinimum 5-7 years of relevant experience in managing data analytics, statistical modeling and data warehouse projects independently.\nStrong business sense, good analytical mind and presentation skills.\nSolid knowledge in SAS, Python, Tableau and other data analytics tools is a must.\nGood command of spoken and written English, Chinese and Mandarin.\nCandidate with less experience will be considered as Manager position.\n\nClick \"Apply Now\" to apply for this position or call Emily Leung at +852 3180 4913 for a confidential discussion. All information collected will be kept in strict confidence and will be used for recruitment purpose only.", "employment_types": ["Full Time"], "selling_points": ["Good career prospect", "Degree holder in Accounting, Finance, Surveying", "Friendly working environment"], "locations": ["Wan Chai Area"], "categories": ["Accounting", "Financial Analyst", "Banking / Finance", "Analyst", "Professional Services", "Business Analysis / Data Analysis"], "post_time": "2022-01-12T23:26:05Z", "salary": {"currency": null, "max": null, "min": null, "period": "monthly", "term": null}, "salary_visible": false, "title_keywords": ["financial analyst"], "responsibilities": ["reporting", "data mining", "management", "control", "analytics tools", "maintenance", "data", "operations", "analysis", "recruitment", "banking", "business analysis"], "requirements": {"degrees": ["university graduate"], "majors": ["related disciplines", "data science", "statistics"], "languages": ["english", "chinese", "mandarin"], "language_level": ["good command"], "hard_skills": ["maintenance", "sas", "data warehouse", "data analytics", "analysis", "tableau", "python", "data mining"], "soft_skills": ["independently", "confidence", "responsible", "business sense", "presentation skills", "analytical mind", "extensive"], "languages_combined": [{"language": "english", "language_level": ["good command"]}, {"language": "chinese", "language_level": ["good command"]}, {"language": "mandarin", "language_level": ["good command"]}]}, "experience_required": {"duration": ["minimum 5-7 years"], "field": ["relevant experience"]}}, {"job_id": "100003009050500", "location_code": "hk", "company": "Peoplus Recruitment", "job_title": "Actuarial / Reinsurance Assistant or Analyst", "description": "Work Location: Ngau Tau Kok\nReporting to Operations Manager, Facilities Management, the jobholder will provide administrative and clerical support on facilities management\u00a0tasks.\nResponsibilities\nSupport in developing and maintaining facilities service records, databases and documentation\nMaintain updated building certificates and service contracts\nWork with internal colleagues and external vendors on preparation of reports, budgets, tenders, contracts, assessments, etc.\nProcess invoices and prepare payments\nUse company systems and tools and gate keep internal policies and Corporate governance to ensure necessary procedures and documentation are fulfilled\nMaintain inventory and process purchase of\u00a0facilities management materials\nConduct market research and analysis\nInvolve in global/ regional initiatives on continuous improvement\nInvolve in internal and external audits\nProvide other administrative support to the team\nRequirements\n3 years\u2019 relevant experience in facilities management field\nRelevant professional qualification is preferred\nKnowledge of logistics or real estate industries will be an advantage\nDetail-minded and analytical\nA good team player\nGood communication skills with good command of spoken and written English and Chinese\nProficient PC skills, especially in MS Word, Excel, PowerPoint and Project\nWilling to work at different company facilities and locations if needed\nApplication:\nClick \"Apply Now\"\nPersonal Information Collection Statement pertaining to Recruitment\nDHL Express (Hong Kong) Limited / DHL Aviation (Hong Kong) Limited (\u201cDHL\u201d) is committed to protecting and respecting your privacy in accordance with the Personal Data (Privacy) Ordinance of Hong Kong (the \u201cOrdinance\u201d) and DHL\u2019s Personal Data Protection Policy (the \u201cPolicy\u201d) at\u00a0https://www.dhl.com/hk-en/home/footer/local-privacy-notice.html\nBy proceeding to respond to this recruitment advertisement, you consent that we may use, retain, process, transfer or otherwise handle the personal data that we collect from you for recruitment,\u00a0 application processing, assessment and communication purposes (including any other purposes directly related thereto) in accordance with the Policy.\nAll personal data of unsuccessful applicants will be retained for future recruitment purposes for a period of not more than two (2) years after which such data will be destroyed.\nYou have the right at any time to make a data access or correction request concerning your personal data held by us. In addition, you may request us to delete your personal data that is no longer required for the relevant purposes which you have given consent. Should you wish to exercise such rights or have any question in relation to your personal data or the Policy, please contact our Human Resources Division in writing", "employment_types": ["Full Time", "Permanent"], "selling_points": ["One of the leading global insurance group", "Strong analytic and numeric skill", "Fresh graduate are welcomed"], "locations": ["Not Specified"], "categories": ["Professional Services", "Business Analysis / Data Analysis", "Insurance", "Actuarial", "Others"], "post_time": "2022-01-15T03:51:08Z", "salary": {"currency": null, "max": null, "min": null, "period": "monthly", "term": null}, "salary_visible": false, "title_keywords": ["analyst", "assistant"], "responsibilities": [], "requirements": {"degrees": [], "majors": [], "languages": [], "language_level": [], "hard_skills": [], "soft_skills": [], "languages_combined": []}, "experience_required": {"duration": [], "field": []}}, {"job_id": "100003009042486", "location_code": "hk", "company": "Divine Consultancy", "job_title": "Analyst/Associate,  Assistant Relationship Manager (ref: AT)", "description": "Role\n\nSenior ESG Data Scientist\n\nLocation\n\nHong Kong or London\n\nWho we are\n\nAnalytics\n\nAt ELEVATE, we offer a unique and impactful career journey designed to empower our teams to influence change.\u00a0 Join our team for a truly international experience.\u00a0 With 24+ offices globally (and still growing), you will have exposure to real issues that span the globe.\u00a0 Fasten your seatbelt for an energetic and dynamic experience where you will become immersed in ELEVATE intelligence, or EiQ.\u00a0 EiQ is a unique and comprehensive suite of supply chain analytics designed to engage investors, brands, suppliers, factories, and workers.\u00a0 It harnesses one of the best audit datasets in the industry and couples it with risk analytics by country, region and sector leveraging bottom-up worker insight.\u00a0 Our associates reach across 100 countries and can thus support immediate decisions and enable program effectiveness improvements to increase impact and allow for lasting transformation.\n\nJob overview at a glance\n\nWe are looking for a senior and experienced data scientist with a deep interest in sustainability and supply chains. This position will play a pivotal role in applying big data and machine learning algorithms to provide innovative and transformative solutions to ESG related challenges. This is exceptional opportunity for a creative and entrepreneurial individual, who is passionate about data, analytics, creative products, sustainability and is looking for a role that will have positive impact.\n\nWho you are\n\nAre you thrilled by the idea of working in a business that aims tackle the world\u2019s biggest challenges? Do you want to work:\n\non environmental, social and governance issues\nwith an amazing team of like-minded creative thinkers\nin a fast-paced dynamic environment\nfor some of the biggest and most forward-looking brands in the world\n\nResponsibilities\n\nAnalyze structured and unstructured data and visualize findings to support the discovery of unique/actionable ESG insights\nData visualization using different reporting software i.e. Tableau, Power BI\nResearch and test machine-learning and theoretical data models related to major risk areas in key industries, supply chains, markets and geographies\nDevelop machine learning / AI pipeline that is applicable to supply chain ESG sector\nContribute to the ideation, design and evolution of existing and new analytical ESG products or services leveraging access to internal or external data\nLead project delivery and account management, and demonstrate leadership skills\nContribute to company data-driven culture by supporting business strategies with data and communicating results to business units\nWork closely with other team leaders across consulting and assessment businesses to achieve end-to-end data driven solutions\nDeliver outputs and presentations to clients\n\nQualifications\n\nBSc degree in Computer Science, Business and Economics, Statistics or Engineering\n5+ years of work experience in a relevant discipline\nStrong skills in Python\nExcellent understanding and experience of statistical models and machine learning algorithms such as Forecasting, Classification, Clustering, and Optimization algorithms.\nStrong understanding of statistic al concepts e.g. sampling, power calculation, causality\nExperience with data visualization tools such as Tableau and PowerBI are preferred\nStrong knowledge of GCP or AWS platforms\nCritical thinker, proactive and positive attitude, team player and solutions driven.\nExcellent written, verbal, and cross communication skills (English)\nExceptional attention to detail and a passion for quality\nAbility to monitor, analyze, and manage data to meet client expectations and goals\nInterest in sustainability and working on impactful data-driven solutions\nPrevious experience in supply chain / sustainability / social compliance preferred\nAbility to work in a time critical environment and to meet deadlines.\n\nEqual Opportunity Employer\n\nELEVATE is committed to creating a diverse and inclusive workplace and is proud to be an Equal Opportunity Employer. All qualified applicants will be considered without regard to race, color, religion, gender, gender identity, sexual orientation, national origin, genetics, disability, age, veteran status, or any other status protected by local law. Personal data provided by applicants will be treated as confidential information and will be used exclusively for employment purposes only.\u00a0 Only short-listed candidates will be notified.\u00a0 Applicants who are not invited for an interview may consider their applications filed for future reference.\n\nTo learn more about career opportunities at ELEVATE, please visit our Careers Page here: https://www.elevatelimited.com/careers/", "employment_types": ["Full Time", "Permanent"], "selling_points": [], "locations": ["Wan Chai"], "categories": ["Accounting", "Finance / Accounting Manager", "Professional Services", "Business Analysis / Data Analysis", "Sales, CS & Business Devpt", "Business Development"], "post_time": "2022-01-12T07:42:43Z", "salary": {"currency": "HKD", "max": 34999, "min": 25000, "period": "monthly", "term": null}, "salary_visible": true, "title_keywords": ["analyst", "associate", "assistant relationship manager"], "responsibilities": [], "requirements": {"degrees": [], "majors": [], "languages": [], "language_level": [], "hard_skills": [], "soft_skills": [], "languages_combined": []}, "experience_required": {"duration": [], "field": []}}, {"job_id": "100003009042469", "location_code": "hk", "company": "Bank of Communications Trustee Limited", "job_title": "Contract Business Analyst", "description": "Financial Analyst - Valuation\u00a0\n\nLocation: Wanchai, Hong Kong\n\nJob Description and Responsibilities:\n\n\u00a0- Conduct company and industry research and analysis\n\u00a0- Assist in performing financial analysis and valuation including business and property valuations\n\u00a0- Draft valuation report\n\u00a0- Assist in organizing and monitoring project progress, liaise with internal and external parties\n\nRequirements:\n\n- Degree holder in Accounting, Finance, Surveying or related disciplines preferred\n- 1 to 2 years relevant experience in valuation or audit would be an advantage\n- Responsible, committed, details oriented, and willing to learn\n- Good computer skills (MS Office, Excel, PowerPoint)\n- Good command of both written and spoken English, Mandarin and Cantonese\n- Good team player with the ability to work independently\n- Able to work under pressure and meet deadline\n- Fresh graduates are welcome\n\nWhat we offer:\n\n- 5 working days per week\n- Attractive remuneration package\n- Good career prospect\n- Medical benefits\n- Friendly working environment\u00a0\n\nInterest parties, please send detailed resume with expected salary to us or by clicking \"Apply Now\"\n\nOur website : https://www.peakval.com\u00a0\n\n(Personal data collected would be used for recruitment purpose only)\n\nPeak Vision Appraisals Limited\n\nWe are a professional appraisal and advisory firm. We offer professional valuation services for M&A, IPO and accounting reference purposes, as well as advise on Environmental, Social and Governance (ESG) reporting. Our clients are mainly listed companies in Hong Kong.", "employment_types": ["Contract"], "selling_points": ["Analyze user requirement document and review", "Degree holder or above in Business Administration", "Minimum 2 years\u2019 experience in financial industry"], "locations": ["Not Specified"], "categories": ["Banking / Finance", "Analyst", "Financial Services", "Professional Services", "Business Analysis / Data Analysis"], "post_time": "2022-01-12T07:37:35Z", "salary": {"currency": null, "max": null, "min": null, "period": "monthly", "term": null}, "salary_visible": false, "title_keywords": ["business analyst"], "responsibilities": ["valuation", "analysis", "monitoring", "internal and external parties", "project progress", "financial analysis", "liaise with", "report"], "requirements": {"degrees": ["degree holder"], "majors": ["related disciplines", "finance", "accounting", "surveying"], "languages": ["cantonese", "english", "mandarin"], "language_level": ["good command"], "hard_skills": ["excel", "computer skills", "powerpoint", "ms office"], "soft_skills": ["good team player", "work independently", "responsible", "willing to learn", "committed", "work under pressure"], "languages_combined": [{"language": "cantonese", "language_level": ["good command"]}, {"language": "english", "language_level": ["good command"]}, {"language": "mandarin", "language_level": ["good command"]}]}, "experience_required": {"duration": ["1 to 2 years"], "field": ["relevant experience", "audit"]}}, {"job_id": "100003009039627", "location_code": "hk", "company": "BDO Financial Services Limited", "job_title": "Data Analyst  \u2013 Banking", "description": "Our client, a leading global insurance group, is now looking for a high caliber to fill up above position for their company.\n\nActuarial / Reinsurance Assistant or Analyst\u00a0\n\n\nResponsibilities\n- To provide support and assist in updating risk profiles, catastrophe data, major loss status summary and other underwriting information package, etc. for treaty renewal.\n- To provide accurate fire accumulation calculation to underwriters and ensure no overexposure risk/location for new, renewal and endorsement cases in the fire accumulation register.\n- To assist in monitoring the underwriting limit of all lines of business and ensure the sufficient coverage of the portfolio.\n- To assist in preparing the regular reinsurance treaty related bordereaux.\n- To assist in handling enquiries raised by internal and external stakeholders\n- To assist in identifying system needs, prepare user requirement, perform any UAT, health check, follow up with IT and ensure all R/I transactions report generated in system are correct and meet time line.\n- To resolve deficiencies in the system with IT project team.\n\n\nRequirements\n- 0-5 years experience\n- Preferable to have reinsurance knowledge\n- Diploma holder in insurance and any related discipline\n- Recognized insurance qualification ANZII / ACII or equivalent preferred\n- Good in spoken and written English and Chinese\n- Knowledge of PC (i.e. Excel, Word, PowerPoint, Access)\n- Experience in reinsurance field with solid background\n- Data Programming (SAS, VBA, R) is a plus\n- Fresh graduate will be considered as Assistant, more experience will be considered as Analyst\n\n\nAttractive remuneration package and excellent career prospects will be provided to the right candidate.\n\nInterested parties please send full resume with followings to cv2@ peoplus.com.hk\n1. Current & Expected Salary\n2. Availability\n3. Date of Achievement : Academic Result\n4. Quoting the Emp. Ref. No. : EK220115-01\n\nAll personal data provided by job applicants will be used for recruitment purpose only", "employment_types": ["Full Time", "Permanent"], "selling_points": ["Attractive Remuneration", "Banking Experience preferred", "Data Analysis"], "locations": ["Not Specified"], "categories": ["Banking / Finance", "Financial Services", "Professional Services", "Business Analysis / Data Analysis", "Information Technology (IT)", "Data Scientist"], "post_time": "2022-01-11T10:15:39Z", "salary": {"currency": null, "max": null, "min": null, "period": "monthly", "term": null}, "salary_visible": false, "title_keywords": ["data analyst"], "responsibilities": ["user requirement", "provide support", "uat", "data", "monitoring", "transactions", "report"], "requirements": {"degrees": ["diploma holder", "fresh graduate"], "majors": ["insurance"], "languages": ["english", "chinese"], "language_level": ["good"], "hard_skills": ["excel", "vba", "plus", "r", "sas", "word", "powerpoint", "programming", "pc"], "soft_skills": [], "languages_combined": [{"language": "english", "language_level": ["good"]}, {"language": "chinese", "language_level": ["good"]}]}, "experience_required": {"duration": ["0-5 years"], "field": []}}, {"job_id": "100003009035713", "location_code": "hk", "company": "Konica Minolta Business Solutions (HK) Limited", "job_title": "Data Analyst", "description": "Responsibilities:\n\n\n\nSupport Relationship Managers to provide excellent service to high net-worth clients so as to achieve client retention\nUnderstand client requirements and assist\u00a0 in daily maintenance of account relationships\nAssist director on analyzing HK and China market growth.\nActively explore the new business leads by offering services in order to meet the customers' satisfaction\u00a0\nLiaise with committee to plan and execute various types of marketing events, in HK or in China.\nBuild systematic training and marketing programs and systems.\nPrepare proposal and presentation materials\u00a0to best fit the client's needs\n\n\u00a0Requirements:\n\nBachelor\u2019s degree holder with 3 years or above of working experience will be considered firstly.\nGood interpersonal skills, detail-oriented and customer-oriented\nGood interpersonal and communication skills, good in both Cantonese and English; fluent in Mandarin is an advantage.\nBusiness mindset, self-motivated, confident and a team player will be preferred.\nDetailed-oriented with good analytical and problem solving skills.\n\nStrong PRC connection and exposure is a definite advantage\nFresh graduates and IANG holders will also consider for trainee post.\nProactive, patient and responsible.", "employment_types": ["Full Time", "Permanent"], "selling_points": ["1-2 years experience in data analytics", "PowerBI, Tableau", "Sensitive to numbers"], "locations": ["Quarry Bay"], "categories": ["Professional Services", "Business Analysis / Data Analysis", "Sciences, Lab, R&D", "Research & Development (R&D)", "Information Technology (IT)", "Data Scientist"], "post_time": "2022-01-10T08:14:44Z", "salary": {"currency": null, "max": null, "min": null, "period": "monthly", "term": null}, "salary_visible": false, "title_keywords": ["data analyst"], "responsibilities": ["marketing events", "maintenance", "systems", "plan", "liaise with"], "requirements": {"degrees": ["bachelor", "degree holder"], "majors": [], "languages": ["cantonese", "english", "mandarin"], "language_level": ["advantage", "fluent", "good"], "hard_skills": ["problem solving skills"], "soft_skills": ["confident", "communication skills", "self-motivated", "responsible", "detail-oriented", "analytical and problem solving skills", "customer-oriented", "interpersonal skills", "patient", "team player", "proactive", "interpersonal", "detailed"], "languages_combined": [{"language": "cantonese", "language_level": ["good"]}, {"language": "english", "language_level": ["good"]}, {"language": "mandarin", "language_level": ["fluent", "advantage"]}]}, "experience_required": {"duration": ["3 years"], "field": []}}, {"job_id": "100003009038322", "location_code": "hk", "company": "Central Business Information Limited", "job_title": "Researcher/ Research Analyst", "description": "Responsibilities:\nAnalyze user requirement document and review system design documentations to ensure that the functionalities meet the user requirement document\nLead testers to execute UAT including planning, prepare or review test plan and results\nCo-ordinate and monitor UAT progress to ensure development team\u2019s deliverables meet user requirements.\nIdentify key issues and risks throughout the project cycle\nBuild and maintain application/ system documentations and procedures\nPrepare training materials and provide training to business users\nPerform ad-hoc assignment as required\nRequirements:\nDegree holder or above in Business Administration, Information Systems or Actuarial\nMinimum 2 years\u2019 experience in financial industry and business analyst role\nGood understanding of MPF & SFC regulated activities with license preferred\nStrong communication, analytical and problem solving skills\nProficient in both spoken and written English and Chinese, Putonghua a plus\nImmediately available is highly preferred\nCandidates with less experience will be considered as lower position\nPlease click \"Apply Now\" to submit your application.\nPersonal data collected will be used for recruitment purpose only.", "employment_types": ["Full Time", "Permanent"], "selling_points": [], "locations": ["Wan Chai"], "categories": ["Banking / Finance", "Corporate Finance", "Professional Services", "Business Analysis / Data Analysis", "Legal & Compliance"], "post_time": "2022-01-11T06:32:41Z", "salary": {"currency": null, "max": null, "min": null, "period": "monthly", "term": null}, "salary_visible": false, "title_keywords": ["researcher", "research analyst"], "responsibilities": ["provide training", "user requirement", "ad-hoc", "uat", "review", "monitor", "procedures", "system design", "maintain", "plan", "planning"], "requirements": {"degrees": ["degree holder"], "majors": ["business administration"], "languages": ["putonghua", "english", "chinese"], "language_level": ["proficient"], "hard_skills": ["problem solving skills", "plus"], "soft_skills": ["communication", "analytical and problem solving skills"], "languages_combined": [{"language": "putonghua", "language_level": ["proficient"]}, {"language": "english", "language_level": ["proficient"]}, {"language": "chinese", "language_level": ["proficient"]}]}, "experience_required": {"duration": ["minimum 2 years"], "field": ["business", "financial industry"]}}, {"job_id": "100003009038577", "location_code": "hk", "company": "Global Sources", "job_title": "(Senior) Digital Marketing Executive", "description": "Our client is a multinational bank with an all-rounded financial operations at its prime within the APAC region.\u00a0 They are looking for a young and energetic individual to support their Group Finance Project initiatives\n\n\u00a0Responsibilities:\u00a0\n\n\nDevelop Dashboards to monitor operations performance\nManaging data quality issues and data design/solutions\nSupport on UAT and users' transition experience\nConsolidate a large amount of market data and apply analytical methods to generate business insights and improve operational efficiency\nDevelop Qlik Sense solutions (or equivalent) as a BI tool to visualize and automate reporting\nFacilitate and coordinate with different functional units to including front office, middle office and supporting departments to ensure the progress of the projects /initiatives\nCultivate the mindset of internal customers on continuous improvement through various improvement initiatives\nKeep abreast of the market, suggest and propose new improvement initiatives\nLiaise with business users and IT on defining project initiatives, requirement documentation and analysis\nDevelop testing schedules and test plans for UAT with close monitoring on implementation progress\nDocument on workflow procedures for business users\nProvide recommendations on operational process workflows reviews and solutions\n\n\u00a0Requirements:\u00a0\n\nTertiary qualification or above preferred\nAt least 3-5 years\u2019 experience in performing data analysis & extraction with the use of SQL\nExperience in data science and modelling is an added advantage (but not a must)\nGood Knowledge with project mechanics and process design techniques preferred\nWell versed in digital business insight\u00a0\nGood business analysis, problem solving and facilitation skills\nAble to manage personal workload with good communication skills\nGood command of both written and spoken English, Cantonese & Mandarin", "employment_types": ["Full Time", "Permanent"], "selling_points": ["execute automated marketing plan", "Deg w/ 2-3 yrs exp", "Proficient in web analytics & reporting tools"], "locations": ["Aberdeen"], "categories": ["Professional Services", "Business Analysis / Data Analysis", "Marketing / Public Relations", "Digital Marketing", "E-commerce", "Product Management / Business Analyst"], "post_time": "2022-01-11T07:25:15Z", "salary": {"currency": null, "max": null, "min": null, "period": "monthly", "term": null}, "salary_visible": false, "title_keywords": ["digital marketing executive"], "responsibilities": ["data", "schedules", "operations", "quality", "design", "liaise with", "plans", "market data", "uat", "monitor", "implementation", "develop", "testing", "reporting", "monitoring", "coordinate with", "procedures", "provide recommendations", "documentation", "analysis"], "requirements": {"degrees": [], "majors": [], "languages": ["cantonese", "english", "mandarin"], "language_level": ["good command"], "hard_skills": ["sql", "analysis", "problem solving"], "soft_skills": ["problem solving", "communication skills"], "languages_combined": [{"language": "cantonese", "language_level": ["good command"]}, {"language": "english", "language_level": ["good command"]}, {"language": "mandarin", "language_level": ["good command"]}]}, "experience_required": {"duration": ["at least 3-5 years"], "field": ["data analysis", "sql"]}}, {"job_id": "100003009046974", "location_code": "hk", "company": "Centaline Property Agency Limited", "job_title": "Assistant Research Officer (Ref: RHDR)", "description": "Job Duties:\n\nGather business and operational requirements from stakeholders to build BI reports and analysis with query tools\nProvide maintenance and modification to existing BI reports\nPerform regular reports, business analysis and statistical work on a timely basis and ensure operation data correctness for business units and management\nProvide input on the design and maintenance of BI reports, standard data dashboards, graphics and visuals that provide meaningful business insight\nSupport ad-hoc management insight to facilitate the business decision making process\n\nRequirements:\n\n\nHigher Diploma in Statistics, Data Science, Information Systems or related disciplines\nMinimum 1-2 years' hands-on experience in data analytics\nFamiliarity with data visualization tool (e.g. PowerBI, Tableau)\nProven experience in process and analysis of data using SQL or Python\nProficient in Microsoft Excel, Word & PowerPoint\nGood analytical and problem-solving skills, attention to detail and sensitive to numbers\nPositive, Proactive and open in mindset to learn and adapt new things\nGood command of written and spoken English & Chinese\n\nBenefits:\n\n\n5-Day Work Week\nDouble Pay and Discretionary Bonus\nPublic Holiday\nMedical Insurance\nBirthday Leave\nStaff Recreational Activity", "employment_types": ["Full Time", "Permanent"], "selling_points": ["Degree in Statistics/Economics/Management Science", "Proficiency with Excel", "Maintain and analyse data and information"], "locations": ["Tsim Sha Tsui"], "categories": ["Professional Services", "Business Analysis / Data Analysis", "Property / Real Estate", "Others", "Others", "Student / Fresh Graduate / No Experience"], "post_time": "2022-01-14T01:55:00Z", "salary": {"currency": null, "max": null, "min": null, "period": "monthly", "term": null}, "salary_visible": false, "title_keywords": ["research officer", "assistant"], "responsibilities": ["graphics", "ad-hoc", "management", "maintenance", "data", "analysis", "design", "reports", "business analysis"], "requirements": {"degrees": ["diploma"], "majors": ["related disciplines", "data science", "statistics"], "languages": ["english", "chinese"], "language_level": ["good command"], "hard_skills": ["data analytics", "analysis", "word", "tableau", "microsoft excel", "sql", "powerpoint", "data visualization", "python", "problem-solving skills"], "soft_skills": ["hands-on", "attention to detail", "problem-solving skills", "sensitive to numbers", "proactive", "positive"], "languages_combined": [{"language": "english", "language_level": ["good command"]}, {"language": "chinese", "language_level": ["good command"]}]}, "experience_required": {"duration": ["minimum 1-2 years"], "field": ["sql"]}}, {"job_id": "100003009046027", "location_code": "hk", "company": "FWD Life Insurance Company (Bermuda) Limited", "job_title": "Senior Business Analyst/ Business Analyst, Life Claims (1-year Contract)", "description": "Responsibilities:\n\nMaintain and analyse data and information\nDevelop the application of data mining on property data\n\nRequirements:\n\nBachelor's degree in Statistics, Economics, Management Science or equivalent\nProficiency with Excel (VBA) and Word\nGood command of Chinese and English\nCandidates with more experience will be considered as Research Officer/ Senior Research Officer\n\nWe provide its staff members with professional training, attractive remuneration package and excellent career prospects. For application, please send full resume with present and expected salary to\u00a0Human Resources Department,\u00a010/F., Wharf T & T Centre, Harbour City, No. 7 Canton Road, Tsimshatsui, Kowloon\u00a0or by email.\n\nFor more information about us, please visit our website at:\u00a0www.centanet.com\n\nData collected will be used for recruitment purpose only.", "employment_types": ["Full Time"], "selling_points": ["3 years experience in insurance firm", "Strong communication and writing skills", "Contract role, 14 ALs, Medical, Dental & Gratuity"], "locations": ["Kwun Tong"], "categories": ["Professional Services", "Business Analysis / Data Analysis", "Insurance", "Claims Officer"], "post_time": "2022-01-13T09:27:14Z", "salary": {"currency": null, "max": null, "min": null, "period": "monthly", "term": null}, "salary_visible": false, "title_keywords": ["senior business analyst", "business analyst"], "responsibilities": ["data", "develop", "maintain", "data mining", "analyse"], "requirements": {"degrees": ["degree", "bachelor"], "majors": ["science", "economics", "statistics"], "languages": ["english", "chinese"], "language_level": ["good command"], "hard_skills": ["excel", "vba", "word"], "soft_skills": [], "languages_combined": [{"language": "english", "language_level": ["good command"]}, {"language": "chinese", "language_level": ["good command"]}]}, "experience_required": {"duration": [], "field": ["research"]}}, {"job_id": "100003009047769", "location_code": "hk", "company": "Public Bank (Hong Kong) Ltd", "job_title": "Officer \u2013 Risk Management (Ref: JD-RMO)", "description": "One of our clients is now looking for a high calibre candidate to fill the following position:\n\n\nDegree holder;\n\n1 year or above relevant experience;\n\nPerform analysis on problems reported by users and give solutions;\n\nExecute business application projects consistent with customer\u2019s requirements;\n\nProvide technological support and training to customers;\n\nWorking with large demanding customers and product team for enhancement discussions/solution planning;\n\nKnowledge in programming is an advantage;\n\nExperience in Network Infrastructure and Computer Hardware Support is an advantage;\n\nTravel between Hong Kong, PRC & Macau may be required after Covid;\n\nProficiency in both spoken and written Cantonese, Mandarin & English.\n\nRemarks:\nMonthly Salary: HK$20-30K + Incentive;\n\n5-day work;\n\nWorking location: Shatin;\n\nGood fringe benefits e.g. medical, banking holiday, will be provided.\n\nIf the above position is not suitable for you, please also feel free to send your CV to us for our job matching.\n\nInterested parties please click \"APPLY NOW\"\u00a0or send to\u00a0OUR EMAIL\u00a0and attach your updated resume with expected salary in \"MS WORD\" format.\n\nPlease quote the\u00a0Job Ref. No.\u00a0and\u00a0Applied Post\u00a0on the subject of your application.\n\nInterest to know our candidates' and clients' comments about our service? Please click\u00a0HERE.\n\nCompany website:\u00a0www.kek.com.hk\n\nThe information provided will only be used for recruitment related purposes.", "employment_types": ["Full Time", "Permanent"], "selling_points": [], "locations": ["Not Specified"], "categories": ["Banking / Finance", "Analyst", "Professional Services", "Business Analysis / Data Analysis", "Risk Management"], "post_time": "2022-01-15T03:49:06Z", "salary": {"currency": null, "max": null, "min": null, "period": null, "term": null}, "salary_visible": false, "title_keywords": ["officer"], "responsibilities": ["network infrastructure", "hardware", "analysis", "planning"], "requirements": {"degrees": ["degree holder"], "majors": [], "languages": ["cantonese", "english", "mandarin"], "language_level": ["proficiency"], "hard_skills": ["hardware", "analysis", "programming"], "soft_skills": [], "languages_combined": [{"language": "cantonese", "language_level": ["proficiency"]}, {"language": "english", "language_level": ["proficiency"]}, {"language": "mandarin", "language_level": ["proficiency"]}]}, "experience_required": {"duration": ["1 year"], "field": ["infrastructure", "relevant experience"]}}, {"job_id": "100003009037429", "location_code": "hk", "company": "DFS Hong Kong Limited", "job_title": "Finance Analyst - DFS91121193", "description": "With the mission to promote Global Sources www.Globalsources.com, as a global e-commerce B2B marketplace, we are currently seeking a passionate candidate to join our dynamic GSOL team. This is an exciting opportunity for those who are keen on exploring and building their career in the digital and eCommerce ecosystem.\n\nWhy should you join us?\n\nYou\u2019ll work in a growth-driven environment, where we encourage creativity and ideas to flow freely.\nYou\u2019ll be able to make a true impact on our business and team growth, big or small, and see the results of your hard work and receive timely feedback.\nFlat structure environment, you will be able to work independently and make your own choices.\nGuidance and mentorship is provided to develop your career skillsets to grow professionally\nYou are exposed to global & international culture, work with people with different nationalities.\nYou\u2019ll build your network locally & and regionally in Asia & worldwide\nWe\u2019re the market lead in B2B sourcing platform in APAC.\n\nResponsibilities:\n\nWork closely with Senior Marketing Manager to plan and execute automated marketing plan in line with sales strategies to maximize conversion or develop buyer community across business segments along their sourcing journey\nPlan and manage marketing campaigns within budget and on schedule to achieve target metrics/KPIs\nCollaborate with internal teams and third-party agencies to create result-driven campaigns and optimize user experience, as well as excellent content production\nAnalyze and report on the performance of campaigns including actionable insights for enhancement and optimization of communication.\nConduct competitive analysis and provide recommendations based on competitive reviews, learnings, and industry best practice\nRequirements:\u00a0\n\nBachelor\u2019s degree in marketing, business, or equivalent\nAt least 2 -3 years hands-on experience in digital marketing and/or CRM campaign management using Oracle, Salesforce, Marketo, etc\nStrong proficiency in web analytics and reporting tools (Google Analytics/Webtrends/Adobe Analytics/Salesforce or equivalent)\nHighly driven and results-oriented work ethic with strong analytical skills\nGood command of English and Chinese (Cantonese and Mandarin)\nCandidates with more experience may be considered for a senior specialist role\nImmediate available is highly preferred", "employment_types": ["Full Time", "Permanent"], "selling_points": ["World's Leading Luxury Travel Retailer", "Work Life Balance, Five-day Work Week", "International & Dynamic Working Environment"], "locations": ["Quarry Bay"], "categories": ["Accounting", "Financial Analyst", "Professional Services", "Business Analysis / Data Analysis"], "post_time": "2022-01-11T02:47:10Z", "salary": {"currency": null, "max": null, "min": null, "period": "monthly", "term": null}, "salary_visible": false, "title_keywords": ["analyst"], "responsibilities": ["collaborate with", "analysis", "budget", "teams", "user experience", "develop", "communication", "marketing plan", "provide recommendations", "schedule", "marketing campaigns", "plan", "kpis", "report"], "requirements": {"degrees": ["degree", "bachelor"], "majors": ["business", "marketing"], "languages": ["cantonese", "english", "chinese", "mandarin"], "language_level": ["good command"], "hard_skills": ["google analytics", "salesforce", "analytical skills", "adobe", "web analytics", "oracle"], "soft_skills": ["analytical skills", "hands-on", "work ethic", "web analytics", "driven"], "languages_combined": [{"language": "cantonese", "language_level": ["good command"]}, {"language": "english", "language_level": ["good command"]}, {"language": "chinese", "language_level": ["good command"]}, {"language": "mandarin", "language_level": ["good command"]}]}, "experience_required": {"duration": ["at least 2 -3 years"], "field": ["management", "digital marketing"]}}, {"job_id": "100003009042393", "location_code": "hk", "company": "Wang On Group", "job_title": "Manager - Business Analysis & Control", "description": "Established in Asia in 2013 with a trailblazer mentality, FWD is the primary insurance business of investment group, Pacific Century Group (PCG), with minority shareholders Swiss Re Group, GIC Ventures, RRJ Capital and Hopu Investments.\n\nFWD spans 10 markets in Asia including Hong Kong SAR & Macau SAR, Thailand, Indonesia, the Philippines, Singapore, Vietnam, Japan, Malaysia and Cambodia. In Hong Kong, FWD offers life and medical insurance, general insurance, employee benefits, and financial planning. We focus on creating fresh customer experiences and making the insurance journey simpler, faster and smoother, with innovative propositions and easy-to-understand products, supported by digital technology. Through this customer-led approach, FWD aims to be a leading pan-Asian insurer by changing the way people feel about insurance.\n\nIf you are looking for a company where can fuel your inspiration and cultivate your expertise, join us on our exciting journey.\n\nThe Job:\n\nResponsible for managing various parts of Life operation project, including claim system development and data migration \u00a0\nWork with team members and other departments to support various initiatives/ projects.\nHandle system issues and coordinate with different IT teams to solve system production issues and provide solution to handle the fix\nPrepare user requirement, UAT plan and manage UAT testing; and\nSupport UAT and troubleshoot software development problems.\nHandle ad-hoc tasks assigned by supervisor.\nAssist in operation guidelines write-ups and updates\nEnsure quality outputs are delivered according to project timeline\n\nThe Person:\n\nMinimum 3 years\u2019 experience of working as a business analyst in Life Insurance\nExperience with claims system, change process and project management\nExperience with policy systems AS400 / Life Asia\nGood knowledge of PC, particularly proficient in MS Office tools\nProficiency in Chinese and English\nStrong communication and writing skills\nStrong analytical anal independent problem solving capability\n\nWe offer 5-day work, excellent learning & development opportunities and an attractive package to the right candidate.\n\nInformation collected will be treated in strict confidence and used solely for recruitment purpose. The company will retain all applications no longer than 24 months of which will be destroyed thereafter. When there are vacancies in any of our subsidiaries, holding companies, associated or affiliated companies of, or companies controlled by, or under common control with the Company during that period, we may transfer your application to them for consideration of employment. We are an equal opportunity employer. We do not discriminate on the basis of race, sex, disability or family status in employment process.", "employment_types": ["Full Time", "Permanent"], "selling_points": [], "locations": ["Kowloon Bay"], "categories": ["Professional Services", "Business Analysis / Data Analysis"], "post_time": "2022-01-12T07:18:24Z", "salary": {"currency": null, "max": null, "min": null, "period": "monthly", "term": null}, "salary_visible": false, "title_keywords": ["manager"], "responsibilities": [], "requirements": {"degrees": [], "majors": [], "languages": [], "language_level": [], "hard_skills": [], "soft_skills": [], "languages_combined": []}, "experience_required": {"duration": [], "field": []}}, {"job_id": "100003009045087", "location_code": "hk", "company": "Michael Page", "job_title": "Assistant Project Manager - Data & Customer Intelligence", "description": "Assist in review of risk management framework, policies and procedures\nConduct risk analysis and assessment to identify and monitor major risks of the Bank\nPerform ad hoc tasks and projects assigned by supervisor\nUniversity Degree in Finance, Economics, Risk Management, Mathematics or other related disciplines with minimum 1 year relevant working experience\nExperience in asset and liability management will be an advantage\nSelf-motivated with good interpersonal and communication skill in both English and Chinese\nProficient in PC applications, including MS Excel\nCFA / FRM Level I or above is preferable\n\nTo apply, interested parties please follow the application methods available in the Bank\u2019s career website\u00a0https://www.publicbank.com.hk/en/aboutus/careeropportunities. You can send us your resume quoting our job reference number together with present &\u00a0expected salary (a must)\u00a0to the Human Resources Department by email or fax at\u00a02815 3157\u00a0or by post to\u00a0Human Resources Department, 12/F, Public Bank Centre, 120 Des Voeux Road Central, Hong Kong. You may also visit our career website for other career opportunities available within our Group.\n\nPersonal data collected will be used for recruitment purpose only and will be treated in accordance with the Bank\u2019s Personal Information Collection Statement, a copy of which has been available in the Bank\u2019s career website.", "employment_types": ["Full Time", "Permanent"], "selling_points": ["Large scale retail MNC", "Strategic role - provide big picture to BUs", "Design and deploy data solutions"], "locations": ["Not Specified"], "categories": ["Professional Services", "Business Analysis / Data Analysis", "Information Technology (IT)", "Application Specialist - Software", "Product Management / Business Analyst"], "post_time": "2022-01-13T07:07:51Z", "salary": {"currency": null, "max": null, "min": null, "period": "monthly", "term": null}, "salary_visible": false, "title_keywords": ["assistant project manager"], "responsibilities": ["management", "policies", "review", "procedures", "monitor", "ad hoc tasks", "communication", "risk analysis"], "requirements": {"degrees": ["university degree"], "majors": ["mathematics", "risk management", "finance", "economics", "related disciplines"], "languages": ["english", "chinese"], "language_level": ["good"], "hard_skills": ["cfa", "analysis", "pc applications", "ms excel", "frm"], "soft_skills": ["self-motivated", "communication skill", "interpersonal"], "languages_combined": [{"language": "english", "language_level": ["good"]}, {"language": "chinese", "language_level": ["good"]}]}, "experience_required": {"duration": ["minimum 1 year"], "field": ["risk management", "management", "related", "finance", "relevant working experience"]}}, {"job_id": "100003009045792", "location_code": "hk", "company": "Computer Recruitment Consultants Ltd", "job_title": "Contract Business Project Manager", "description": "Purpose\u00a0of the Role\n\nReporting into the team Manager or Director, to provide business analysis and decision support for the finance team and be part of a Global Commercial Finance team managing business performance with a focus on PNL reporting, consolidation and analytical review.\u00a0 You will assist the team to manage all financial planning and analysis activities for the business and improve the business insights of those analysis to drive business performance and sound decision making.\n\nResponsibilities\n\nFinancial Analysis\n\nIdentify and recommend efficiencies and cost saving opportunities across all global store locations.\nReview division month end financials and ensure all variances are adequately explained.\nHighlight any anomalies that require follow up actions by Accounting & Reporting team or divisions.\nCollaborate with business partners to evaluate the effectiveness of investments via financial and non-financial KPIs.\n\nBudget/Forecast Planning\n\nAnalyse sales, margin, KPI and profit results to identify business trends and opportunities and quantify the effects of business changes, initiatives and events.\u00a0\nConduct frequent trend analysis and consolidate store locations for management decision making.\nSupport the team in preparing budget, forecast scenario and monthly financial review by working closely with business partners and cross departments.\n\nReporting\n\nWork with related functions to streamline and automate reports where possible and enhance communication.\nDevelop and maintain reporting required to monitor results at global level.\nStandardize division PNL analysis, business case template and reporting tool.\n\nControl\n\nMonitor and control expenditure in actual, budget and forecast in close collaboration with corporate and divisional functional and all finance functional teams.\nDocument and refine SOP (Standard Operating Procedures) for cross departments; ensure the SOP is well communicated to corporate and divisional level, compliance to company policies, accounting treatments, systems and audit standards.\nPerform any other ad hoc duties requested by your manager.\n\nRequirements\n\nDegree holder in Finance, Accounting, Business Management or related field\nStrong Microsoft PC based applications \u2013 Word, Excel and Powerpoint required.\u00a0\nMicrosoft Strategy and Power BI knowledge a plus.\nExcellent command of the English language and excellent communication skills\nStrong quantitative skills and able to analyse a business both statistically and conceptually\nAbility to format analytical works into presentation forms.\u00a0\nHigh degree of integrity and confidentiality with a keen sense of business/financial acumen", "employment_types": ["Full Time"], "selling_points": ["3 years experience in Business Analysis", "Perform business and user requirement analysis", "Liaison between Business and IT Units"], "locations": ["Not Specified"], "categories": ["Professional Services", "Business Analysis / Data Analysis", "Information Technology (IT)", "Product Management / Business Analyst"], "post_time": "2022-01-14T04:28:40Z", "salary": {"currency": null, "max": null, "min": null, "period": "monthly", "term": null}, "salary_visible": false, "title_keywords": ["project manager"], "responsibilities": ["collaborate with", "budget", "audit", "communication", "maintain", "planning", "ad hoc duties", "control", "compliance", "monitor", "teams", "develop", "reports", "forecast", "kpis", "reporting", "cost", "management", "review", "procedures", "support the team", "policies", "analysis", "systems", "financial analysis", "evaluate", "analyse"], "requirements": {"degrees": ["degree", "degree holder"], "majors": ["business", "finance", "accounting"], "languages": ["english"], "language_level": ["excellent"], "hard_skills": ["business management", "excel", "plus", "bi", "word", "powerpoint", "pc", "acumen"], "soft_skills": ["communication skills", "integrity", "presentation", "keen"], "languages_combined": [{"language": "english", "language_level": ["excellent"]}]}, "experience_required": {"duration": [], "field": []}}, {"job_id": "100003009049749", "location_code": "hk", "company": "China Construction Bank (Asia) Corporation Limited", "job_title": "AVP/VP, Big Data Analytics and Machine Learning (Business Implementation)", "description": "Responsibilities\n\nPerform management and financial reports analysis\nMonitor and evaluate the financial and operating performance of the business against budget and forecast\nConduct feasibility studies on potential investment and acquisition, specifically related to real estate, loan finance and securities\nDesign and improve the policies, procedures and systems with different departments to enhance the efficiency and control of the business units\nDevelop financial model to control and forecast the profitability of the existing business and new projects, such as cash flow analysis and IRR calculation\nPropose solutions with business unit heads to enhance business performance\nPerform strategic planning for the business growth\nAssist top management to perform ad-hoc analysis and research\nManage KPIs and analytics to support business growth and identify business risks\nIdentify data anomalies, trends, or deviations, and then develop strategies for improvement Requirements\nJob Requirements:\n\nBachelor\u2019s degree in Business Administration/ Business Analysis/ Accounting/ Finance is preferred but not a must\nCPA /CIMA/ CFA/ RICS/ HKIS candidate is desirable but not a must\nProficiency in Excel is an advantage\nAble to work under pressure and details-oriented\nIndependent, well-organized, self-motivated and strong sense of responsibility; \uf06c Strong interpersonal & communication skills\nStrong analytical skills & research skills\nCandidate with less experience will be considered as Assistant Manager - Business Analysis Control\nImmediate available is highly preferred\n\nWe offer competitive remuneration package, our benefits include:\n\nPerformance bonus\nEducation subsidy\nProfessional membership fee sponsorship\nLife & medical insurance\nMarriage Leave, Compassionate Leave, Examination Leave etc.\nPublic holidays\nStaff purchase discount\n\nInterested parties please send full resume with present and expected salary to Human Resources Department by clicking \"Apply Now\" or by email recruit @wangon.com\n\n(Information provided will be treated in strict confidence and will only be used for recruitment-related purposes.)", "employment_types": ["Full Time"], "selling_points": ["A minimum of 10 years experience", "Degree in BA, Statistic/ other related discipline", "With exp in CRM solution/ campaign management, etc"], "locations": ["Not Specified"], "categories": ["Banking / Finance", "Corporate Banking", "Retail Banking", "Professional Services", "Business Analysis / Data Analysis"], "post_time": "2022-01-14T09:11:30Z", "salary": {"currency": null, "max": null, "min": null, "period": "monthly", "term": null}, "salary_visible": false, "title_keywords": [], "responsibilities": ["ad-hoc", "data", "budget", "design", "control", "monitor", "develop", "forecast", "kpis", "management", "strategic planning", "procedures", "cash flow", "financial reports", "develop strategies", "policies", "analysis", "systems", "evaluate"], "requirements": {"degrees": ["degree", "bachelor"], "majors": ["finance", "business", "business administration", "accounting"], "languages": [], "language_level": [], "hard_skills": ["excel", "hkis", "cfa", "analysis", "rics", "analytical skills", "cpa", "cima"], "soft_skills": ["communication skills", "self-motivated", "independent", "research skills", "sense of responsibility", "well-organized", "analytical skills", "interpersonal", "work under pressure"], "languages_combined": []}, "experience_required": {"duration": [], "field": ["business analysis"]}}, {"job_id": "100003009038761", "location_code": "hk", "company": "Li & Fung (Trading) Limited", "job_title": "IT - Senior Business Analyst", "description": "Large scale retail MNC\nGroup level role\nStrategic role - provide big picture to the BUs\nDevelop and deploy data solutions (e.g. Campaign/ Product Analytics, BI/ Machine Learning)\nLead and provide technical guidance to Dev team (e.g. Data Engineers/ Scientists)\nSolution design and A/B testing\nPerform data analytics to deliver insight and recommendations to BUs\nRegional exposure\n\n\u5ba2\u6237\u7b80\u4ecb\n\nOur client is a large scale conglomerate with business across APAC. To cope with their business growth, they are hiring a Assistant Project Manager - Data & Customer Intelligence to sit at group level in providing a strategic view and big picture to their retail BU. As a project manager to design, develop and deploy data solutions (e.g. Campaign/ Product Analytics, BI/ Machine Learning). Lead and coach development team and assist in A/B testing.\n\n\u5de5\u4f5c\u5185\u5bb9\n\nLead, coordinate and prioritize a large portfolio of customer data projects with complex data demand and multiple stakeholder engagement\nPartner with Business Analysts and Product Owners to fully elaborate the feature stories based on Definition of Done and align them with the technical workstream\nManage the customer data product lifecycle from strategic planning to tactical execution (e.g. campaign, product analytics, BI or machine learning)\nWork closely with developers and requesters to identify data and functional requirements for the application\nDevelop long-term roadmaps and work with key stakeholders to bring alignment\nDrive product development and execution with a team of world-class engineers and analysts\nProject management - manage timelines, estimates, resources, communication, and documentation\nCollaborate with Dev team members to review and design any technical solution\nAct as consultant and single point of contact across BU's data engineers, scientist & business users and responsible to translate business demand to data solution acrpss APAC\nDevelop and deploy models to support data-based decisions across APAC\nSupport the execution of A/B Testing\nLead initiatives to track customer behavior and business performance across various analytics projects by setting KPIs and creating insightful reporting\nIdentify business opportunities and developed projects data analytics to solve business problems\nEstablished procedure for providing consulting services for new technology adoption, system assessment within innovation & analytics sector\n\n\u7406\u60f3\u7684\u6c42\u804c\u8005\n\nDegree holder in Information Technology, Computer Science, Marketing or related discipline\nMinimum of 5 years project/ product management experience, in Customer Data Analytics\nStrong in customer journey review & analysis, product design, identify painpoints and proposing data-driven solutions\nStrong analytical skills and proven ability of data-driven decision-making, ability to define and manage qualitative and quantitative research and measurement plans\nPractical knowledge in A/B testing, data pipeline/ architecture, machine learning etc.\nStrong track record in leading retail/ customer (B2C) analytics projects\nAbility to communicate key goals and consistently create momentum for a project across teams with sometimes competing priorities in a dynamic environment\nDigital-savvy and knowledgeable on the latest digital trends preferred\nRetail/ Property/ B2C industries background is preferred\nAggressive, self-motivated with excellent communication and presentation skills\nExcellent communication skill and presentation skills in Chinese & English\n\n\u798f\u5229\u5f85\u9047\n\nOur client offers attractive compensation package with sustainable career path.\n\nTo apply online please click the 'Apply' button below. For a confidential discussion about this role please contact Eliza Lai on +852 2848 9544.", "employment_types": ["Full Time", "Permanent"], "selling_points": ["Global work team exposure", "Friendly and flexible work culture", "Attractive remuneration package"], "locations": ["Lai Chi Kok"], "categories": ["Professional Services", "Business Analysis / Data Analysis", "Information Technology (IT)", "Application Specialist - Software", "IT Project Management / Team Lead"], "post_time": "2022-01-11T07:45:45Z", "salary": {"currency": null, "max": null, "min": null, "period": "monthly", "term": null}, "salary_visible": false, "title_keywords": ["senior business analyst"], "responsibilities": ["collaborate with", "consulting", "data", "design", "communication", "deploy", "plans", "measurement", "teams", "develop", "testing", "customer data", "kpis", "architecture", "guidance", "reporting", "management", "strategic planning", "review", "product design", "contact", "documentation", "identify business opportunities", "analysis", "coordinate", "project management"], "requirements": {"degrees": ["degree holder"], "majors": ["marketing", "computer science", "information technology"], "languages": ["english", "chinese"], "language_level": ["excellent"], "hard_skills": ["bi", "data analytics", "analysis", "analytical skills", "project management", "dynamic", "documentation"], "soft_skills": ["dynamic environment", "self-motivated", "responsible", "communication skill", "prioritize", "analytical skills", "communication", "project management", "presentation skills", "learning", "driven", "world-class"], "languages_combined": [{"language": "english", "language_level": ["excellent"]}, {"language": "chinese", "language_level": ["excellent"]}]}, "experience_required": {"duration": ["minimum of 5 years"], "field": ["product management"]}}, {"job_id": "100003009042544", "location_code": "hk", "company": "Ravia Global Appraisal Advisory Limited", "job_title": "Senior Analyst / Manager - Valuation & Advisory Services", "description": "One of our clients, a major bank is currently seeking a suitable candidate to join their elite team.\n\nResponsibilities:\n\nPerform business and user requirement analysis\nActing as the primary liaison between business and IT units\nManage IT Project implementation and monitor the project progress and resolving occurred problems\nProvide strong support to business users\nPrepare various management reports\nManage project budget and procurement process\nParticipate in the Risk Analysis for new product launch\n\nRequirements:\n\nDegree holder or above in Business Studies, Information Technology, Computer Science or related disciplines\nAt least 3 years of relevant experience in Business Analysis.\nStrong interpersonal, communication, presentation and problem solving skills\nSelf-motivated, willing to work in competent, challenging and team-work environment\nGood command in both written and spoken Chinese and English, knowledge of the Mandarin is a plus.\n\nInterested parties, please forward your resume in WORD FORMAT to us by clicking here Computer Recruitment Consultants Ltd or fax to 2528-9091.\u00a0\u00a0 The information provided by candidates will be treated in strict CONFIDENTIAL and will only be used for recruitment purpose\u00a0", "employment_types": ["Full Time"], "selling_points": [], "locations": ["Wan Chai"], "categories": ["Banking / Finance", "Financial Services", "Professional Services", "Business Analysis / Data Analysis", "Business Consultancy"], "post_time": "2022-01-12T07:56:40Z", "salary": {"currency": null, "max": null, "min": null, "period": "monthly", "term": null}, "salary_visible": false, "title_keywords": ["manager", "senior analyst"], "responsibilities": ["user requirement", "analysis", "budget", "monitor", "project progress", "management reports", "risk analysis", "it project implementation"], "requirements": {"degrees": ["degree holder"], "majors": ["related disciplines", "business", "computer science", "information technology"], "languages": ["english", "chinese", "mandarin"], "language_level": ["good command"], "hard_skills": ["analysis", "problem solving skills", "plus"], "soft_skills": ["self-motivated", "competent", "communication", "problem solving skills", "interpersonal", "presentation"], "languages_combined": [{"language": "english", "language_level": ["good command"]}, {"language": "chinese", "language_level": ["good command"]}, {"language": "mandarin", "language_level": ["good command"]}]}, "experience_required": {"duration": ["at least 3 years"], "field": ["business analysis", "relevant experience"]}}, {"job_id": "100003008938578", "location_code": "hk", "company": "JFE Consulting Limited", "job_title": "Business Analyst", "description": "Responsibilities:\n\n\nDevelop an analytical and insight-driven customer-centric communication framework based on customer needs to deliver personalized and relevant communications in fulfilling their financial goals\nEstablish an end-to-end implementation process of customer journey via omni-channels\nEvaluate and monitor business results to enable close-loop learning\nLeverage on the integration of internal bank data and external data to drive effective customer targeting\nCollaborate with key internal stakeholders and effectively manage agency/ vendor relationships\nBring in new ideas and suggestions to continually enhance customer experience and improve cost effectiveness through driving innovation, system/ process improvement and refining standardized operating procedure to streamline manual support\nEnsure all communications/ programs/ projects are strictly adhered to banking practices, compliance and regulatory requirements\n\nRequirements:\n\n\n\nUniversity degree in Business Administration, Statistics or other related discipline\nA minimum of 10 years marketing or campaign management experience in financial service industry\nWith hands-on experience in developing and executing large scale CRM solutions / campaign management/ customer lifecycle marketing is an advantage\nStrong in transforming analytical concepts and developments into business strategies and applications for the uplift of business value\nAbility to build strong stakeholders relationships through thorough understanding of business requirements and the ability to analyse issues to find effective solutions\nGreat sense of ownership and servicing mindset to ensure efficient and effective customer service processes\nStrong project management, people and negotiations skills; able to motivate others to strike for excellence; capable of working independently as well as in a team\nSelf-motivated, result oriented, attentive to details and able to work under pressure\nProficiency in English and Chinese (both Cantonese and Putonghua)\nPlease specify your current and expected package in your application for reference.\u00a0\n\n\nApplicants who are not contacted within 8 weeks may consider their applications unsuccessful and their personal data will be retained by the bank for a period up to two years.\n\nAll information provided by applicants will be used for recruitment purposes only and will be used strictly in accordance with the bank\u2019s personal data policies, a copy of which will be provided upon request.", "employment_types": ["Full Time", "Permanent"], "selling_points": ["MNC with with business across globally", "Monitoring projects/programs progress", "1  year relevant work experience,attractive salary"], "locations": ["Not Specified"], "categories": ["Professional Services", "Business Analysis / Data Analysis", "Information Technology (IT)", "Product Management / Business Analyst", "E-commerce", "Product Management / Business Analyst"], "post_time": "2022-01-11T04:25:31Z", "salary": {"currency": null, "max": null, "min": null, "period": "monthly", "term": null}, "salary_visible": false, "title_keywords": ["business analyst"], "responsibilities": ["collaborate with", "cost", "ideas", "data", "regulatory requirements", "compliance", "monitor", "implementation", "develop", "communication", "evaluate", "banking"], "requirements": {"degrees": ["university degree"], "majors": ["statistics", "business administration"], "languages": ["cantonese", "putonghua", "english", "chinese"], "language_level": ["proficiency"], "hard_skills": ["project management"], "soft_skills": ["efficient", "self-motivated", "independently", "ability to analyse", "capable", "attentive to details", "project management", "hands-on", "customer service", "result oriented", "thorough", "work under pressure"], "languages_combined": [{"language": "cantonese", "language_level": []}, {"language": "putonghua", "language_level": []}, {"language": "english", "language_level": ["proficiency"]}, {"language": "chinese", "language_level": ["proficiency"]}]}, "experience_required": {"duration": ["minimum of 10 years"], "field": ["management", "developing", "service industry", "marketing", "financial"]}}, {"job_id": "100003009037177", "location_code": "hk", "company": "Infocast Limited", "job_title": "Business Analyst / Solution Analyst", "description": "Are you a movement maker? Are you seeking new and exciting career opportunities?Here is what you need to know about the job:\n\n\u200b\n\nA Little About Us\u00a0\n\nIt's an amazing time to be working at\u00a0Li & Fung, especially for IT Business Analyst \u2013 Application Support. We are a big enough company to have the ability to execute large-scale deliverables, and small enough that you will play an important role in that\u00a0delivery.\u00a0\u00a0\n\nOur\u00a0Culture\u00a0\n\nWithin our team,\u00a0we are all about getting things done and owning what we do.\u00a0we don\u2019t hide behind fancy job titles or set up bureaucratic processes. Instead we treat our people equally, fairly and give them a ton of freedom and autonomy to create something awesome.\u00a0We make mistakes, we learn from them and we back everything up with data and logic.\n\nAbout this role\n\nTo perform system analysis, design, application or technology development on system enhancements.\nParticipate in projects on implementing ERP application, J.D. Edwards EnterpriseOne and rollouts, new business implementations or technology enhancements of IT system(s) and solution(s)\nConvert user requirements into detailed functional business requirement specifications (FBR), interface specifications or system configuration specifications.\n\u00a0Ensure all functional requirements and objectives are properly documented and maintained throughout the delivery\nAccountable for delivery in order to ensure time, cost and functional contracts are met\n\u00a0Work closely with management to establish, communicate and agree project opportunities to ensure that business goals are achieved\nMaintain a central repository of training materials of relevant business system applications.\n\nYou might be the good fit if you have...\n\nCandidate must possess at least an Advanced/Bachelor's Degree in Computer Science/Information Technology or equivalent.\nAt least 3 years experience with Enterprise Resource Planning systems (ERP) eg. SAP, Oracle, Oracle EnterpriseOne, or other ERP systems.\nUnderstanding of business processes\nExperience in functional / technical architecture design of ERP or\u00a0 applications is an advantages\nGood initiative with \u201ccan do\u201d attitude\nGood command of written and spoken English, Chinese and Mandarin\n\nPerks:\n\nCompetitive salary with 13th month salary plus performance bonus\nHealth, dental, life and personal accident insurances\nPaid days off + festival early leave + volunteer leave\nTraining courses organized and training sponsorship\nNumerous sample sales and staff discount offer\n\n#lifung #lftrading\n\nIf this sounds like you, Apply Now!\n\n\u200b", "employment_types": ["Full Time", "Permanent"], "selling_points": ["Conduct in depth requirement analysis", "Lead medium sized project implementation", "Review business requirements"], "locations": ["Hung Hom"], "categories": ["Banking / Finance", "Analyst", "Professional Services", "Business Analysis / Data Analysis", "Information Technology (IT)", "Product Management / Business Analyst"], "post_time": "2022-01-11T01:59:03Z", "salary": {"currency": null, "max": null, "min": null, "period": "monthly", "term": null}, "salary_visible": false, "title_keywords": ["business analyst", "solution analyst"], "responsibilities": ["cost", "management", "business goals", "data", "configuration", "contracts", "analysis", "systems", "design", "specifications", "maintain", "insurances", "architecture", "planning"], "requirements": {"degrees": ["degree", "bachelor"], "majors": ["computer science", "information technology"], "languages": ["english", "chinese", "mandarin"], "language_level": ["good command"], "hard_skills": ["small", "erp systems", "plus", "sap", "analysis", "erp", "make", "oracle"], "soft_skills": ["organized", "advanced", "accountable", "initiative", "detailed"], "languages_combined": [{"language": "english", "language_level": ["good command"]}, {"language": "chinese", "language_level": ["good command"]}, {"language": "mandarin", "language_level": ["good command"]}]}, "experience_required": {"duration": ["at least 3 years"], "field": ["design", "planning"]}}, {"job_id": "100003009047701", "location_code": "hk", "company": "Moore Associates Limited", "job_title": "Senior Associates/Manager/Senior Manager - Valuation", "description": "Job Duties:\n\nManage engagement progress for pre-engagement work, risk management, financial modelling and report writing\nConduct business valuations, intangible asset valuations, financial asset valuations and purchase price allocations etc.\nParticipate in business development work\nMaintain in-house research database\nCoach junior team members\n\nRequirements:\n\nDegree holder with major in accounting, finance, financial engineering or other financial related disciplines\nPreferably has professional qualifications such as CPA and CFA, etc. is an advantage.\nAt least\u00a03 years relevant working experience (candidates with less experience will also be considered)\nStrong relationship with client is an advantage\nGood command of both spoken and written English and Chinese (both Cantonese and Mandarin)\nImmediate available is highly preferred.\n\n\nWe offer attractive remuneration and excellent prospects for the right candidates. Please apply in writing with full resume and\u00a0expected\u00a0salary to Human Resources Department.\n\nApplications will be treated in strict confidence.\u00a0 Personal data collected will be used for recruitment purposes only.", "employment_types": ["Full Time", "Permanent"], "selling_points": ["Preparing professional valuations", "Handling cross-border M&A advisory projects", "2-year+ hands-on experience in business valuation"], "locations": ["Tsim Sha Tsui"], "categories": ["Accounting", "Consulting", "Banking / Finance", "Financial Services", "Professional Services", "Business Analysis / Data Analysis"], "post_time": "2022-01-15T03:49:49Z", "salary": {"currency": null, "max": null, "min": null, "period": "monthly", "term": null}, "salary_visible": false, "title_keywords": ["senior manager", "manager"], "responsibilities": ["management", "purchase", "maintain", "database", "report"], "requirements": {"degrees": ["degree holder"], "majors": ["related disciplines", "finance", "accounting", "engineering"], "languages": ["cantonese", "english", "chinese", "mandarin"], "language_level": ["good command"], "hard_skills": ["cfa", "cpa", "professional qualifications"], "soft_skills": [], "languages_combined": [{"language": "cantonese", "language_level": ["good command"]}, {"language": "english", "language_level": ["good command"]}, {"language": "chinese", "language_level": ["good command"]}, {"language": "mandarin", "language_level": ["good command"]}]}, "experience_required": {"duration": ["at least 3 years"], "field": ["relevant working experience"]}}]