[{"job_id": "100003009055714", "location_code": "hk", "company": "Tata Consultancy Services Limited", "job_title": "Business Process Consultant \u2013 Planning", "description": "Accountable for defining and capturing the Planning Functional processes, including end to end Merchandise Financial Planning, Product and Assortment planning, Demand Planning and Supply Planning processes. This could cover other processes (e.g. samples management)\u00a0\nApply a structured business architecture approach and methodology for capturing current state of the enterprise, desired future state, and plan to get to the end state through logical, planned tactics. Conduct process workshops, identify process and system enhancements to meet business requirements.\u00a0\nDevelop a business process strategy to help gather the business requirements from subject matter experts in the Asia region and validate that the system functionality will support the business needs.\u00a0\u00a0\nDefine the data shared across the enterprise and the relationships between those data.\u00a0\nConduct Change Impact analysis to business processes. Assist business partners to define their \u201cfrom/to\u201d change impacts and develop adoption action plans. Develop deliverables such as Business Process and Change impact analysis documentation\u00a0\nEffectively collaborate and coordinate among all groups to ensure consistent levels of detail in the business process models.\u00a0\nContribute as a Subject Matter Expert (SME) with strong knowledge in assigned business areas; to both current state and opportunities to improve.\u00a0\nIdentify opportunities for increased efficiency through new tools and techniques. Participate in system process reviews and testing to examine output and alignment to business requirements.\u00a0\nPresent program\u00a0leadership with project status and progress updates, timelines, and challenges\u00a0\nMaintain strong relationships with business partners to achieve a robust and sustainable governance model.\u00a0", "employment_types": ["Full Time"], "selling_points": ["Develop a business process strategy", "Effectively collaborate and coordinate", "Maintain relationships with business partners"], "locations": ["Others"], "categories": ["Professional Services", "Business Consultancy"], "post_time": "2022-01-18T02:52:45Z", "salary": {"currency": null, "max": null, "min": null, "period": "monthly", "term": null}, "salary_visible": false, "title_keywords": ["consultant"], "responsibilities": ["collaborate", "management", "data", "demand planning", "analysis", "subject matter expert", "develop", "coordinate", "testing", "business process", "maintain", "sme", "plan", "meet business requirements", "documentation", "plans", "architecture", "planning"], "requirements": {"degrees": [], "majors": [], "languages": [], "language_level": [], "hard_skills": ["supply planning", "documentation", "demand planning", "analysis", "workshops"], "soft_skills": ["structured", "leadership", "accountable", "robust"], "languages_combined": []}, "experience_required": {"duration": [], "field": []}}, {"job_id": "100003009055254", "location_code": "hk", "company": "Accenture Company Limited", "job_title": "Strategy & Consulting - Insurance Consulting Manager", "description": "Your Role:\nThere will never be a typical day at Accenture, but that\u2019s why people love it here. The opportunities to make a difference within exciting client initiatives are limitless in this ever-changing business landscape.\n\nKey Responsibilities:\n\nLead a project delivery team to solve client\u2019s burning issues and help clients to achieve new performance highs.\nProvide intellectual leadership for the team and ensure that the project is delivered on time and within budget, harnessing the team's diversity to ensure the development of creative solutions to complex problems.\nDemonstrate strong analytical capabilities and apply knowledge of selected tools and techniques, drawing logical conclusions\nDevelop expertise in customer insight & growth experience practice areas to increase the breadth and depth of our knowledge base and capabilities\nManage work-streams/project delivery on time with the appropriate use of resources, working within and lead Accenture and/or Client teams\nManage and develop junior team members on the project by providing coaching, mentoring and regular feedback\nExperience, Attributes and Qualifications:\n\nUniversity Degree from reputable university, MBA preferred.\nMinimum 6 years of working experience with insurance clients or insurance companies, and experience working with workflow / business process management solutions.\nKnowledge in Insurance Products/Process and Insurance Core System\nKnowledge in project management (Waterfall/Agile Scrum)\uff0cLean Six Sigma qualification is a plus\nExperience in end-to-end Insurance or retirement operating model design, business process design initiatives\nExperience in business process re-engineering\n\u00a0Able to lead and drive project delivery independently, willing to mentor junior team members\nStrong stakeholder management with business/IT stakeholders and subject matter experts, able to create and deliver high-impact communication to senior audiences (written and oral in English, Mandarin and Cantonese)", "employment_types": ["Full Time"], "selling_points": ["Management Consulting", "Insurance Core System", "Digital Transformation"], "locations": ["Quarry Bay"], "categories": ["Professional Services", "Business Consultancy", "Information Technology (IT)", "IT Project Management / Team Lead"], "post_time": "2022-01-18T01:55:31Z", "salary": {"currency": null, "max": null, "min": null, "period": "monthly", "term": null}, "salary_visible": false, "title_keywords": ["manager"], "responsibilities": ["management", "budget", "teams", "design", "develop", "business process re-engineering", "project management", "communication", "business process", "insurance"], "requirements": {"degrees": ["university degree"], "majors": [], "languages": ["cantonese", "english", "mandarin"], "language_level": [], "hard_skills": ["plus", "agile", "make", "six sigma", "project management"], "soft_skills": ["oral", "independently", "agile", "communication", "project management", "creative", "leadership"], "languages_combined": [{"language": "cantonese", "language_level": []}, {"language": "english", "language_level": []}, {"language": "mandarin", "language_level": []}]}, "experience_required": {"duration": ["minimum 6 years"], "field": ["management", "engineering", "design", "business", "insurance"]}}, {"job_id": "100003009055673", "location_code": "hk", "company": "Hutchmed Group (HK) Limited", "job_title": "Senior Manager / Manager of Sustainability", "description": "Responsibilities\nSupport the development of corporate sustainability strategies that reflect the environmental, social, and governance issues important to HUTCHMED;\nCo-ordinate sustainability activities across Hong Kong, Shanghai, Suzhou and New Jersey operations;\nOversee implementation of sustainability goals and targ\u00adets across the R&D, manufacturing, China comm\u00adercial joint ventures and U.S. R&D / comm\u00adercial businesses;\nImprove implementation methodologies, set annual milestones, and establish reporting mechanisms to inform employees and executive leadership on progress;\nSupport communication with investors and investment analysts regarding HUTCHMED\u2019s sustainability position and progress (e.g. large mutual funds).\nCommunicate with ESG research firms and indices (e.g. MSCI, ISS Oekom, Sustainalytics);\nSupport the Board of Directors\u2019 Sustainability Committee in strategic discussions and the exec\u00adution of sustain\u00adability focus areas;\nProduce an annual corporate sustain\u00adability report, including data collection, measure\u00adment & analysis, stakeholder engagement and content devel\u00adopment;\nLiaise with the corporate public relations, investor rela\u00adtions, commercial, marketing, Human Resources technical teams (mainly China & U.S.) to coordinate and drive sustain\u00adability positioning and actions;\nOrganise internal sustainability events and other enga\u00adgements to promote and inspire staff.\nRequirements\n\n8 years minimum experience in a corporate environment in sustainability, compli\u00adance or finance, with some track record of delivering sustain\u00adability programmes;\nAbility to influence change with internal business part\u00adners without direct reporting relationships;\nComfortable working with all levels of employees, from senior executives to front-line individual contributors;\nStrong analytic, written and oral communication skills in English and preferably Mandarin Chinese;\nAbility to manage and work collaboratively with cross-functional and cross-geographical working groups;\nAbility to clearly articulate business value of sustain\u00adability investment.\nAbility to multi-task, set priorities, and meet tight deadlines;\nEntrepreneurial spirit to identify and act on new opportunities or improvements;\nEducated to degree level in a sustainability, or business-related subject, or relevant work experience;\nInterest or expertise in healthcare industry.\n\n\nSalary and benefits will be commensurate with experience.\u00a0Please send detailed resume with\u00a0current and\u00a0expected salary\u00a0by clicking \u201cAPPLY NOW\u201d in the below.\nWe are an equal opportunity employer and welcome applications from all qualified candidates. The information provided will be treated in strict confidence and used only for consideration of application for relevant/similar post(s) within the CK Hutchison Group of Companies. Applicants not having heard from us within four weeks from the date of this advertisement may consider their application unsuccessful. All personal data of unsuccessful applicants will be destroyed after the recruitment exercise when no longer required.", "employment_types": ["Full Time", "Permanent"], "selling_points": [], "locations": ["Hung Hom"], "categories": ["Professional Services", "Business Analysis / Data Analysis", "Business Consultancy", "Medical Services", "Pharmaceutical"], "post_time": "2022-01-18T02:50:40Z", "salary": {"currency": null, "max": null, "min": null, "period": "monthly", "term": null}, "salary_visible": false, "title_keywords": ["senior manager", "manager"], "responsibilities": ["communicate with", "reporting", "operations", "analysis", "teams", "implementation", "communication", "coordinate", "data collection", "liaise with", "report"], "requirements": {"degrees": ["degree"], "majors": ["business"], "languages": ["mandarin chinese", "english"], "language_level": [], "hard_skills": [], "soft_skills": ["communication skills", "oral", "meet tight deadlines", "multi-task", "articulate"], "languages_combined": [{"language": "mandarin chinese", "language_level": []}, {"language": "english", "language_level": []}]}, "experience_required": {"duration": ["8 years"], "field": ["related", "finance", "business", "sustainability"]}}, {"job_id": "100003009054441", "location_code": "hk", "company": "SHINEWING Sustainability Advisory Services Limited", "job_title": "Senior Consultant/ Consultant \u2013 Environmental, Social and Governance", "description": "Sustainability and climate change has emerged as top priorities amongst corporations, but many are at different stages of understanding, responding and implementing the necessary sustainability elements into its business development and operations. As part of the strong team of ESG and sustainability professionals in SHINEWING Sustainability Advisory Services Limited, you will help our clients construct a well-rounded ESG and sustainability portfolio, which not only fulfills the requirements from governmental bodies, but also seeks to become industry-leading benchmarks in its ESG and sustainability performance. We leverage our extensive knowledge and experience and methodical work approaches to help clients integrate into a sustainable future.\n\nRESPONSIBILITIES:\n\nConduct ESG and sustainability reporting through applying recognized ESG and sustainability standards and frameworks, such as HKEX requirements, GRI, TCFD, UNSDG, etc.\nPerform ESG and sustainability-related risk assessment and analysis via various stakeholder engagement activities\nDevelop sustainability and carbon management products which include corporate ESG reporting, sustainability and carbon assessments, verification and communication\nConduct extensive research on ESG, sustainable finance and sustainability-related issues and business opportunities\nProvide insights to enhance clients\u2019 ESG performance and quality and assist clients achieve long term sustainability and energy reduction targets\nDevelop guidelines and procedures to refine the ESG and sustainability service systems, including ESG reporting, assurance, analysis and consulting\nUndertake business development including business marketing, client networking and partnership building\nDevelop client proposals, product brochures and deliver presentations to senior management\n\nREQUIREMENTS:\n\nBachelor\u2019s degree or equivalent in Environmental Studies (environmental engineering, science or management), or other relevant disciplines\nA minimum of 2-3 years of solid relevant experience in ESG or sustainability consulting, assurance, carbon auditing, sustainability reporting and/or other relevant project management; candidates with less experience will be considered as Consultant\nDemonstrable knowledge in common ESG and sustainability reporting standards and frameworks, including HKEX requirements, GRI Standards, TCFD framework, IIRC and sustainability raters\u2019 parameters\nLocal or overseas professional qualification(s) (e.g. CAP, CEM) is an advantage\nProficiency in both written and spoken English and Chinese, fluency in Putonghua is a great advantage\nStrong analytical, project management, communication and interpersonal skills\nCalm working under pressure\nWilling to travel\n\n\nPersonal data collected will be used for recruitment purpose only.\u00a0\u00a0\nwww.shinewing.hk", "employment_types": ["Full Time", "Permanent"], "selling_points": ["ESG and sustainability reporting", "Degree equivalent in Environmental Studies", "2-3 years of relevant experience"], "locations": ["Causeway Bay"], "categories": ["Professional Services", "Business Consultancy", "Sciences, Lab, R&D", "Environmental Science / Waste Management", "Others"], "post_time": "2022-01-17T09:34:17Z", "salary": {"currency": null, "max": null, "min": null, "period": "monthly", "term": null}, "salary_visible": false, "title_keywords": ["senior consultant", "consultant"], "responsibilities": ["reporting", "provide insights", "consulting", "guidelines", "analysis", "business opportunities", "quality", "procedures", "systems", "develop", "communication", "presentations", "carbon management", "client proposals", "senior management"], "requirements": {"degrees": ["degree", "bachelor"], "majors": ["science", "environmental engineering"], "languages": ["putonghua", "english", "chinese"], "language_level": ["fluency", "advantage", "proficiency"], "hard_skills": ["project management"], "soft_skills": ["project management", "communication and interpersonal skills", "under pressure", "calm"], "languages_combined": [{"language": "putonghua", "language_level": ["fluency", "advantage", "proficiency"]}, {"language": "english", "language_level": ["advantage", "proficiency"]}, {"language": "chinese", "language_level": ["advantage", "proficiency"]}]}, "experience_required": {"duration": ["minimum of 2-3 years"], "field": ["assurance", "consulting", "sustainability", "project management", "relevant experience"]}}, {"job_id": "100003009054903", "location_code": "hk", "company": "Geek Plus International Company Limited", "job_title": "Business Analyst", "description": "About Geek+\nGeek+ leads the technology\u00a0revolution, by applying advanced\u00a0robotics and AI technologies to realize high-flexibility and intelligent logistics automation solution.\u00a0We are always looking for people who can bring new perspectives and life experiences to our company.\u00a0We understand the value of our people and we strive to constantly satisfy their needs.\n\nWe are now seeking for a\u00a0Business Analyst\u00a0to join our team. Are you someone who is driven by curiosity, craves a good challenge? Join us and be part of this exciting adventure!\n\nAbout the role\n\nGather key requirements from clients and translate items into project blueprint and interface documents\nWork close with product and R&D team to ensure client\u2019s requirement are clearly defined and scoped\nPrepare system integration test (SIT) and user acceptance test (UAT) based on the confirmed blueprint\nPrepare system user manual and relevant training materials\nSupport new product launch and system design with technical teams, identify both business and technical impediments and drive for solutions\nRequirements\n\nBachelor in Computer Science, Information Technology, Supply Chain Management, Industrial Engineering or other related disciplines\nExperience in system integration, business analysis, or project management\nKnowledge in warehouse management system (WMS) or related system integration\nKeen appreciation of new technologies, new project and innovative mindset\nSelf-confident and able to work with clients independently, good communication skills\nComputer literate (AutoCAD, Project, Visio) will be an advantage\nNative in Cantonese, good spoken and written English and Mandarin\nWhat We Offer\n\nFive-day work week\nYoung and energetic work culture with regional exposure\nCozy office environment with\u00a0light refreshments\nDouble pay & attractive performance bonus\nMedical and dental benefits and insurance\n14 to 21 days Annual Leave\nConvenient work location: KCC\nIf your qualifications, experience, and aspirations match our requirements, please send your resume with your current and expected salary to us.\n\nAll information and materials submitted to Geek+ will remain strictly confidential and be treated for recruitment purposes only. Only short-listed candidates will be notified", "employment_types": ["Full Time", "Permanent"], "selling_points": ["Experience in Business Analyst", "Automation projects for warehouse & logistics", "Great career prospect & competitive package"], "locations": ["Kwai Hing"], "categories": ["Professional Services", "Business Analysis / Data Analysis", "Business Consultancy", "Transportation & Logistics", "Inventory / Warehousing"], "post_time": "2022-01-17T13:23:35Z", "salary": {"currency": null, "max": null, "min": null, "period": "monthly", "term": null}, "salary_visible": false, "title_keywords": ["business analyst"], "responsibilities": ["management", "robotics", "uat", "teams", "warehouse management system", "project management", "communication", "system design", "logistics", "wms", "business analysis"], "requirements": {"degrees": ["bachelor"], "majors": ["related disciplines", "engineering", "computer science", "information technology"], "languages": ["cantonese", "english", "mandarin"], "language_level": ["native", "good"], "hard_skills": ["r&d", "ai", "analysis", "project management", "system design", "integration", "autocad"], "soft_skills": ["confident", "communication skills", "independently", "advanced", "keen", "project management", "innovative", "driven"], "languages_combined": [{"language": "cantonese", "language_level": ["native", "good"]}, {"language": "english", "language_level": ["good"]}, {"language": "mandarin", "language_level": ["good"]}]}, "experience_required": {"duration": [], "field": ["business analysis", "project management"]}}, {"job_id": "100003009051518", "location_code": "hk", "company": "EQC Advisory Limited", "job_title": "Fast-Track Management Trainee (Fresh Graduates Welcome) - HK$28,500+, 13 months + bonus", "description": "Reporting to Senior Management, the incumbent will be responsible for the\u00a0Business Development functions include identifying customer markets, monitoring industry trends, conducting competitor analyses and crafting business plans with the aim to determine ideal market opportunities to pursue and introduce new lifestyle and sports brands to Asia under distribution/ joint-venture / franchising / other suitable models.\u00a0\n\nResponsibilities\n\nConduct market research and analysis to identify customer markets, monitor industry trends, conduct competitor analyses to drive business opportunities\nAssist in developing business proposals and participate in new business pitches for targeted brands and future business collaboration\nAssist in Company\u2019s branding and media communication activities e,g, press releases, corporate marketing collaterals and website, etc.\nSupport senior management on preparing business presentation materials and internal / external communications materials such as press materials related to corporate-level etc.\nParticipate in operational analysis and special corporate projects\n\nRequirements\n\nUniversity graduate with 3 years\u2019\u00a0 working experience in business analysis, business development or consultancy\nStrong numeric and business acumen\nGood interpersonal & presentation skills\nProactive, energetic, dynamic and with genuine passion in retail industry\nAttentive to details and with multi-tasking capability\nStrong oral and written communication in English, Mandarin and Cantonese\nExcellent command of\u00a0 Microsoft office application including PowerPoint, Excel and Word\n\nWe offer competitive remuneration package with\u00a0a wide range of fringe benefits including\n\n5-day work week\nDiscretionary Bonus\nComprehensive Medical Coverage\nStaff Shopping Discount\nNon-contributory Retirement Benefits Scheme\nBirthday Leave\n\nInterested parties please send resume with present and expected salary to Human Resources Department, Swire Resources Limited,\u00a012/F Kingston International Centre, 19 Wang Chiu Road Kowloon Bay, Hong Kong or by\u00a0clicking the below \"Apply Now\" button.\n\nSwire Resources Limited is Equal Opportunity Employer\n", "employment_types": ["Full Time", "Permanent", "Internship"], "selling_points": ["Fast-track to Management Position", "Fresh Graduates are Welcome", "Fm HK$28,500 / m (Basic) + Bonus + Double Pay"], "locations": ["Causeway Bay"], "categories": ["Accounting", "Audit", "Professional Services", "Business Consultancy", "Management", "Management Trainee"], "post_time": "2022-01-16T07:36:04Z", "salary": {"currency": "HKD", "max": 44999, "min": 30000, "period": "monthly", "term": null}, "salary_visible": true, "title_keywords": ["management trainee"], "responsibilities": ["conduct market research", "analysis", "monitor", "business opportunities", "developing", "marketing collaterals", "communication", "website", "senior management"], "requirements": {"degrees": ["university graduate"], "majors": ["business"], "languages": ["cantonese", "english", "mandarin"], "language_level": [], "hard_skills": ["excel", "microsoft office", "analysis", "word", "powerpoint", "dynamic", "acumen"], "soft_skills": ["oral", "attentive to details", "passion in", "genuine", "communication", "presentation skills", "energetic", "dynamic", "multi-tasking", "business acumen", "proactive", "interpersonal"], "languages_combined": [{"language": "cantonese", "language_level": []}, {"language": "english", "language_level": []}, {"language": "mandarin", "language_level": []}]}, "experience_required": {"duration": ["3 years"], "field": ["business analysis", "business development"]}}, {"job_id": "100003009053196", "location_code": "hk", "company": "Alpacian Limited", "job_title": "Associate Consultant (Information Security & Audit)", "description": "We are looking for highly proactive and well-rounded individuals to assist with the launch of our new business services,\u00a0including professional firms appraisal services, online training services, and regulatory compliance consultancy services.\u00a0 The opportunity will allow the successful candidate to fast-track into a management position leading a team of professionals in delivering quality professional services that are practical to small and medium sized CPA practices in Hong Kong and overseas.\u00a0 \u00a0\n\nWHAT WE OFFER:\n- Basic Salary from HK$28,500 / month + 13th Month Salary + Performance Bonus\n- Semi-Annual Appraisals and upward salary adjustments & discretionary performance-based bonus\n- 18-month Fast-track to a junior management position\u00a0\u00a0\n- 12+ Annual Leave Days\u00a0\n- Mentoring program by direct supervisor, an industry elite and CPA\n\n\nJOB\u00a0RESPONSIBILITIES:\n\u00b7 Act as project in-charge in providing FRC inspection / compliance consultancy engagements\n\u00b7 Lead the business strategic planning, launch and growth of new service lines\u00a0\n\u00b7 Oversee work progress of subordinates and interns\n\nJOB REQUIREMENTS:\n(FRESH GRADUATES WILL BE CONSIDERED):\n- Interest in developing a career in a startup advisory firm\n- Willing to step out of comfort zone with an entrepreneurial mindset\n\u00b7 1 year of office working experience preferred, but fresh graduates are also welcome\n- Sensitive to numbers with strong business acumen\n- Strong multi-tasking & time management skills\n- Strong communication skills with accountability and follow-through\n- Comfortable with report and research writing\n\u00b7 Comfortable with accounting and financial reporting subjects & quick self-learner\n\u00b7 Fluent in written and spoken English (IELTS 7.5 or above is preferred)\n\u00b7 Degree holder in any discipline, preferably in accounting, finance, or economics\u00a0\n\u00b7 Immediately available is preferred", "employment_types": ["Full Time", "Permanent"], "selling_points": ["Flexible Working Hours", "Dental and Medical Insurance", "Education Allowance"], "locations": ["Quarry Bay"], "categories": ["Professional Services", "Business Consultancy", "Information Technology (IT)", "Security", "Technical / Functional Consulting"], "post_time": "2022-01-17T06:24:12Z", "salary": {"currency": null, "max": null, "min": null, "period": "monthly", "term": null}, "salary_visible": false, "title_keywords": ["associate", "consultant"], "responsibilities": [], "requirements": {"degrees": [], "majors": [], "languages": [], "language_level": [], "hard_skills": [], "soft_skills": [], "languages_combined": []}, "experience_required": {"duration": [], "field": []}}, {"job_id": "100003009055065", "location_code": "hk", "company": "Linkbiz Global Limited", "job_title": "Account Executive", "description": "Responsibilities :\n\nDevelop new market initiatives, assess new markets, and analyze business opportunities\nDevelop a sales contact plan and attending industry events to build relationships with key prospects\nConduct face to face meetings with new business prospects and attend events.\nDeliver sales plans and provide documented reviews of business contracts\nDevelop effective working relationships with clients through regular meetings and identify and obtain further sales and business development opportunities.\nProvide sales reports when requested and to keep an accurate pipeline and CRM\nLiaise will all departments to ensure accurate deliverables of services\nRequirements :\u00a0\n\n\nFluent in English\u00a0\nAble to work in startup culture\nAble to reach target", "employment_types": ["Full Time"], "selling_points": [], "locations": ["Tsim Sha Tsui"], "categories": ["Banking / Finance", "Financial Services", "Professional Services", "Business Consultancy", "Sales, CS & Business Devpt", "Account Servicing"], "post_time": "2022-01-18T01:08:01Z", "salary": {"currency": null, "max": null, "min": null, "period": "monthly", "term": null}, "salary_visible": false, "title_keywords": ["account executive"], "responsibilities": ["liaise", "sales reports", "working relationships", "contracts", "business opportunities", "develop", "sales plans", "contact", "plan"], "requirements": {"degrees": [], "majors": [], "languages": ["english"], "language_level": ["fluent"], "hard_skills": [], "soft_skills": [], "languages_combined": [{"language": "english", "language_level": ["fluent"]}]}, "experience_required": {"duration": [], "field": []}}, {"job_id": "100003009051345", "location_code": "hk", "company": "C2 Recruitment Limited", "job_title": "Assistant Business Manager", "description": "What we do daily\n\n1. Facilitate clients\u2019 concern on cyber security\n2. Design, implement and maintain security policies, procedures and guidelines for our end clients\n3. Perform security assessment such as vulnerability scanning, penetration testing or RED TEAM exercise\n4. Perform cyber security risk assessment or gap analysis for our end clients based on ISO/PCI/HKMA/SFC requirement\n5. Analysis the result of security assessment, risk assessment and generate reports for clients\n6. Participate and assist clients on IT auditing, ISO audit and PCI audit\n7. Co-ordinate with internal teammate for different projects or clients\n\nIf that\u2019s you, come and join us\n\n1. University graduate in Information Technology or related disciplines preferred\n2. IT Security or ISO knowledge or experience is an advantage\n3. Good communication skill with internal teammate and clients\n4. A team plater with excellent interpersonal and communication skills\n5. Responsible, independent, self-motivated, organised, efficient, analytical & detail-minded\n6. Good written and spoken communication skills in Cantonese & English\n7. Fresh graduate with interest in cybersecurity and positive attitude will also be welcome (in-house training will be provided)\n8. Knowledge of Linux and network command\n9. Immediate availability is preferred", "employment_types": ["Full Time", "Permanent"], "selling_points": ["Regional business planning and operations role", "Implementation of business development plans", "Highly organized and logical in thought"], "locations": ["Central & Western Area"], "categories": ["Admin & HR", "Administration / Operation Manager", "Professional Services", "Business Consultancy", "Management", "General Management"], "post_time": "2022-01-16T21:50:27Z", "salary": {"currency": null, "max": null, "min": null, "period": "monthly", "term": null}, "salary_visible": false, "title_keywords": ["manager", "assistant"], "responsibilities": ["scanning", "cyber security", "guidelines", "policies", "analysis", "co-ordinate with", "procedures", "audit", "design", "maintain", "reports", "penetration testing", "auditing"], "requirements": {"degrees": [], "majors": [], "languages": [], "language_level": [], "hard_skills": ["cyber security", "hkma", "analysis", "gap", "red"], "soft_skills": [], "languages_combined": []}, "experience_required": {"duration": [], "field": []}}, {"job_id": "100003009051587", "location_code": "hk", "company": "Trinity Search Limited", "job_title": "Business Analyst - Property Developer", "description": "\nOur client, a well-known local financial institution in Hong Kong, is looking for a high calibre to join the group.\n\n\nResponsibilities\n\nPlan ahead strategically to support the company growth objectives and enhancing the exising service level\nGather insightful information including market trends, competitor offerings and performance, operational data and tech aspects for analytics purpose\nUse the information gathered to analyze and work out insightful and meaning reports and presentation in order to formulate strategic direction\nWork closely with Business Planning Team to transform high level objectives into detailed action plans which is measurable so as to ensure a smooth execution\nWork closely with other teams (including BD team and IT team) to implement the new initiative smoothly\nInvolve in Sales and Marketing projects from time to time\nRequirements\n\nUniversity graduate in Business or related field\nCandidates from BIG4 business consultation stream will be highly preferable\u00a0\n5 - 7 years\u2019 working experience in business planning, preferably within the financial industry, for example MPF companies, banks, insurance companies and financial institutions\nExperience in data analytics to formulate strategic planning is a MUST\nExperience in involving or taking charge of projects related to sales and marketing will be highly preferred\nGood understanding of investment and insurance products\nStrong sense of responsibility and commitment to excellence\nGood organizational, analytical and multitasking skills\nOpen-minded with a creative mindset\nCandidates with less experience will be considered as Manager\nTo apply, please send your detailed resume to travis[at]connersconsulting[dot]com or contact Travis Poon at 3460 2011 for a confidential discussion.\n\n\nOnly shortlisted candidates will be notified.\n\nApplicants who are not contacted within two weeks may consider their applications unsuccessful.\n\nAll data collected will be used for recruitment purpose only & will be used strictly confidential.\n\nConners Consulting Limited\n2005 Kai Tak Commercial Building 317 Des Voeux Road Central Hong Kong\nTel: (852) 3996 8090\nWebsite:\u00a0www.connersconsulting.com", "employment_types": ["Full Time"], "selling_points": ["Business Analyst", "Group Corporate Strategies", "Internal Management Consulting"], "locations": ["Central & Western Area"], "categories": ["Professional Services", "Business Analysis / Data Analysis", "Business Consultancy", "Information Technology (IT)", "Data Scientist"], "post_time": "2022-01-16T13:01:34Z", "salary": {"currency": null, "max": null, "min": null, "period": "monthly", "term": null}, "salary_visible": false, "title_keywords": ["developer", "business analyst"], "responsibilities": ["data", "teams", "marketing projects", "reports", "plan", "plans", "planning"], "requirements": {"degrees": ["university graduate"], "majors": ["business"], "languages": [], "language_level": [], "hard_skills": ["data analytics"], "soft_skills": ["sense of responsibility", "open-minded", "organizational", "creative mindset", "detailed"], "languages_combined": []}, "experience_required": {"duration": ["5 - 7 years"], "field": ["mpf", "related", "financial industry", "business", "marketing", "financial institutions", "insurance", "planning"]}}, {"job_id": "100003009052151", "location_code": "hk", "company": "BDO", "job_title": "Senior Associate / Associate - Corporate Social Responsibility / ESG", "description": "Job Description\n\n\nResponsible for handling assigned accounts and exploring new channels for business development\nEstablish and maintain strong relationships with business partners and clients\nHandle client liaison, budget control and scheduling\nPrepare internal documentation for account opening process\nPerform ad hoc task as assigned\n\nJob Requirements\n\n\nHigh Diploma or above\nGood command of Cantonese, English and Mandarin\nOutgoing, cheerful and team-oriented\nExcellent communication, impersonal and negotiation skills is a must\nImmediately available is preferred\n\nWe offer attractive remuneration package with 5-days work week, medical insurance, double pay, attractive commission scheme and bank holidays to the right candidate.\u00a0 Interested parties, please email full resume with expected and current salary by clicking \u201cApply Now\u201d below.\n\n\u00a0All personal data collected will be kept confidential and used for recruitment purpose only.\n\n\n", "employment_types": ["Full Time", "Permanent"], "selling_points": ["Fresh graduates is welcomed", "Excellent opportunity of career growth", "Birthday Leave, Medical and Life Insurance, etc."], "locations": ["Sheung Wan"], "categories": ["Professional Services", "Business Consultancy", "Sciences, Lab, R&D", "Environmental Science / Waste Management", "Others", "Student / Fresh Graduate / No Experience"], "post_time": "2022-01-17T02:16:30Z", "salary": {"currency": null, "max": null, "min": null, "period": "monthly", "term": null}, "salary_visible": false, "title_keywords": ["senior associate", "associate"], "responsibilities": ["ad hoc", "account opening", "scheduling", "maintain", "documentation", "budget control"], "requirements": {"degrees": ["high diploma or above"], "majors": [], "languages": ["cantonese", "english", "mandarin"], "language_level": ["good command"], "hard_skills": ["scheme"], "soft_skills": ["outgoing", "negotiation skills", "cheerful", "communication"], "languages_combined": [{"language": "cantonese", "language_level": ["good command"]}, {"language": "english", "language_level": ["good command"]}, {"language": "mandarin", "language_level": ["good command"]}]}, "experience_required": {"duration": [], "field": []}}, {"job_id": "100003009055446", "location_code": "hk", "company": "AIA Hong Kong and Macau", "job_title": "Partnership Strategy, Principal (Associate Director)", "description": "We are partnered with a renowned property developer to seek for a Business Analyst who will be working alongside their top management in formulating and executing new business strategies and initiatives.\n\nThe incumbent of this role will be responsible for a series of group data analysis, identify key growth factors, \u00a0macro research, collaboration with multiple business unit leaders in formulation and proposal of growth strategies, business innovation / transformation.\n\nRequirements:\n\nDegree holder in Accounting, Finance, Business Administration or other relevant disciplines\nCandidates with Big 4 Advisory, management consulting practices or Private Equity experience and financial background is preferred\nMinimum 3 years of relevant work experience\nKeen learner, versatile and possess a creative mindset\nExcellent presentation and communication skills\nFluency in English and Chinese", "employment_types": ["Full Time"], "selling_points": ["Solid experience in Strategic Planning", "Open to Consultancy/Big 4 candidates", "Strong stakeholder management skills"], "locations": ["Quarry Bay"], "categories": ["Media & Advertising", "Strategic Planning", "Professional Services", "Business Consultancy"], "post_time": "2022-01-18T02:36:05Z", "salary": {"currency": null, "max": null, "min": null, "period": "monthly", "term": null}, "salary_visible": false, "title_keywords": ["associate director"], "responsibilities": ["management", "consulting", "data analysis", "communication", "executing", "administration"], "requirements": {"degrees": ["degree holder"], "majors": ["finance", "accounting", "business administration"], "languages": ["english", "chinese"], "language_level": ["fluency"], "hard_skills": ["analysis", "private equity", "macro"], "soft_skills": ["communication skills", "responsible", "keen", "versatile", "creative mindset", "presentation"], "languages_combined": [{"language": "english", "language_level": ["fluency"]}, {"language": "chinese", "language_level": ["fluency"]}]}, "experience_required": {"duration": ["minimum 3 years"], "field": ["management", "big 4", "consulting", "financial"]}}, {"job_id": "100003009054024", "location_code": "hk", "company": "CanAsia Consulting Group Hong Kong Co., Limited", "job_title": "Accountant / Senior / Manager (Big-4 audit preferred, match existing salary)", "description": "Strategic & Project Assistant (MNC)\n\nOur client is an international business which has over 70 year's history with global presence. They are looking for a Strategic & Project Assistant to join their global team.\n\nPosition Responsibilities\n\nServes as a trusted partner, maintaining confidentiality and professionalism in all situations.\nPartners and collaborates with peers and direct reports to manage cross-functional initiatives from conception to completion\nEffective calendar management, advanced planning and preparation of leadership team meetings internally and externally, including but not limited to townhall meetings, off- sites, vendor webinars, one-on-one meetings, etc.\nEvent management - organization of quarterly meetings, volunteering events, off-sites, webinars, summits etc.\nCreation and editions of document (Word, PPT, Excel, Power BI, Tableau) to support the direct report across the full spectrum of their work\nWork with cross-functional teams in the definition of project scope and objectives and resourcing, as aligned to company's strategies.\nManage synchronization across all dependencies.\nProvide oversight to project progress, issues/risks and decisions required.\nManage execution of initiatives ensuring that all projects are delivered on-time, within scope and within budget.\nManages all executive correspondence; directing or responding to customer and vendor communication.\nExpense management duties.\nOversee department budget.\nOther administrative duties as requested.\n\nPosition Requirements\n\nMBA and Master Degree holder is strongly preferred\nConsulting background candidates are highly preferred as well\nSolid administrative or project management experience; with experience supporting C-level executives\nLearning agility and a curiosity for understanding the business\nHigh attention to detail, organization and process.\nStrong teamwork skills and a strong ability to offer suggestions and improvements to process and work effectively.\nStrong relationship management skills.\nHigh level of confidentiality, discernment and judgment.\nAbility to be flexible in response to changing priorities and needs.\nProven ability to manage projects, work under pressure and consistently make deadlines.\nDemonstrated ability and willingness to continuously acquire new competencies and accept new challenges.\nStrong communication, oral and written. Ability to communicate clearly and effectively with senior leaders and external business partners.\nFluent in English and Chinese communication.\n\nInterested individuals can apply now and send CV to Vivian Wong, or call +852 3972 5831 for more information. Only relevant candidates will be contacted\n\nFor a more comprehensive list of our vacancies, please visit: www.connectedgroup.com", "employment_types": ["Full Time"], "selling_points": ["Fast learner, room for progress and growth", "Big-4 / Mid-tier audit background preferred", "Fresh grads are welcome"], "locations": ["Shatin Area"], "categories": ["Accounting", "Accountant", "Financial Analyst", "Professional Services", "Business Consultancy"], "post_time": "2022-01-17T08:07:21Z", "salary": {"currency": null, "max": null, "min": null, "period": "monthly", "term": null}, "salary_visible": false, "title_keywords": ["accountant", "manager"], "responsibilities": ["management", "power bi", "maintaining", "budget", "project progress", "from conception to completion", "communication", "reports", "administrative duties", "report", "cross-functional teams", "planning"], "requirements": {"degrees": ["master degree"], "majors": [], "languages": ["english", "chinese"], "language_level": ["fluent"], "hard_skills": ["project management", "make", "c"], "soft_skills": ["work effectively", "flexible", "oral", "teamwork", "communication", "project management", "learning", "comprehensive", "attention to detail", "work under pressure"], "languages_combined": [{"language": "english", "language_level": ["fluent"]}, {"language": "chinese", "language_level": ["fluent"]}]}, "experience_required": {"duration": [], "field": ["project management", "administrative"]}}, {"job_id": "100003009055438", "location_code": "hk", "company": "BOCI", "job_title": "AVP, AML Compliance", "description": "Responsibilities:\n\nParticipate in ESG engagements\nProvide assistance and support on the preparation and production of reports (in compliance with the ESG / GRI G4 / AA1000 / ISO 26000 guidelines)\nMaintain\u00a0relationships with key client personnel to obtain an understanding of business operations, processes and functions\nPrepare work papers\u00a0\nOther duties as required\nSupport\u00a0and act towards the BDO Global Vision\nBe\u00a0committed to act with\u00a0the firm\u2019s core values and competency expectations\n\n\u00a0Requirements:\n\nDegree in CSR Management, Environmental Science, Engineering,\u00a0or related disciplines\n1 year of relevant experience. Experience in Carbon Accounting, GRI reporting and ESG will be a plus (but not a must)\nGood interpersonal and communication skills\u00a0\nExcellent\u00a0command of written and spoken English and Mandarin is essential\nAbility\u00a0to successfully multi-task while working independently or within a group environment\nProven ability\u00a0to work in a deadline-driven environment and willing to travel\nBe passionate for providing exceptional quality service and striving for exceeding clients\u2019 expectations\nFresh graduates will also be considered\nWe are an equal opportunity employer, and offer excellent prospects and career development for the right candidate.\u00a0 Interested parties please send your application\u00a0with full career history, current and expected salary by clicking\u00a0Apply Now\u00a0button below.\n\n\nApplications will be treated in strict confidence. Personal data collected will be used for recruitment purposes only.", "employment_types": ["Full Time"], "selling_points": ["5-8 years of AML compliance experience", "AML / KYC / CDD", "Banking experience a must"], "locations": ["Sheung Wan"], "categories": ["Banking / Finance", "Analyst", "Professional Services", "Business Consultancy", "Legal & Compliance"], "post_time": "2022-01-18T02:35:21Z", "salary": {"currency": null, "max": null, "min": null, "period": "monthly", "term": null}, "salary_visible": false, "title_keywords": ["aml compliance"], "responsibilities": ["maintain relationships", "other duties", "guidelines", "operations", "compliance", "reports", "provide assistance"], "requirements": {"degrees": ["degree"], "majors": ["related disciplines", "environmental science", "engineering"], "languages": ["english", "mandarin"], "language_level": ["excellent"], "hard_skills": ["plus"], "soft_skills": ["passionate", "communication skills", "independently", "multi-task", "interpersonal", "driven"], "languages_combined": [{"language": "english", "language_level": ["excellent"]}, {"language": "mandarin", "language_level": ["excellent"]}]}, "experience_required": {"duration": ["1 year"], "field": ["accounting", "relevant experience"]}}, {"job_id": "100003009051580", "location_code": "hk", "company": "Vistra (Hong Kong) Limited", "job_title": "Manager, Fund Services", "description": "\u00a0Responsibilities\n\nProviding outsourced internal audit services to our clients across various industries locally and internationally;\nDevelop and review risk management frameworks and policies;\nAssist organizations to maintain effective and efficient controls, in order to manage organizational and strategic risks;\nConduct various advisory tasks such as enterprise risk management under ISO31000, COSO Framework etc., compliance reviews and controls related projects, such as PN21/PN2 under the Listing Rules of the Stock Exchange of Hong Kong;\nAssist in operational risk assessment process including collect and verify data for evaluation of operational risk level;\nParticipate and provide risk comments in product development and business projects;\nKeep abreast of market news including customer data protection and fraud prevention;\nAssisting our clients in the risk management process.\n\n\u00a0Requirements\n\nHigher Diploma\u00a0in Accounting/Risk Management/Corporate Governance or related disciplines;\n0-3 year's experience in internal audit and risk services;\nStudent member/ member of HKICPA/ACCA/CPA Australia/IIA or equivalent qualification is preferred;\nPractical experience in internal audit & risk management;\nAttention to detail, able to work independently and as a team member;\nGood communication, interpersonal and analytical skills;\nAbility to interact with all levels of personnel, including senior executives of client management;\nGood command of written English & Chinese, Mandarin is an advantage;\nProficient in MS Office, including Word & Excel\u00a0and Chinese word processing is required;\nAble to travel overseas and the PRC;\nFresh\u00a0graduates are welcome;\nImmediate available is preferred;\nCandidates with more experience will be considered as Senior Associate.\n\nWhat we offered?\n\n5-day work week\nImportant festivals early leave\nOvertime meal allowance\nTraveling allowance\nDiscretionary bonus\nFull-paid sick leave\nStudy & Exam leave\nGraduation leave\nWedding leave\nCompassionate leave\nMedical Insurance Scheme\nTraining reimbursement\n\n\nInterested parties please click \"APPLY NOW\" and send your full resume with your\u00a0working experience, academic and professional qualification, expected salary, and date of availability\u00a0to HR Department.\n\nPersonal data collected will be used for recruitment purpose only.\u00a0", "employment_types": ["Full Time", "Permanent"], "selling_points": ["Fund Services managerial role", "Investran / VPM  / PE fund admin knowledge", "High service quality mindset"], "locations": ["Causeway Bay"], "categories": ["Banking / Finance", "Financial Services", "Fund Management", "Professional Services", "Business Consultancy"], "post_time": "2022-01-16T11:58:18Z", "salary": {"currency": null, "max": null, "min": null, "period": "monthly", "term": null}, "salary_visible": false, "title_keywords": ["manager"], "responsibilities": ["management", "internal audit", "data", "business projects", "policies", "review", "compliance", "comments", "customer data", "develop", "maintain", "evaluation", "listing"], "requirements": {"degrees": ["diploma"], "majors": ["related disciplines", "risk management", "accounting"], "languages": ["english", "chinese", "mandarin"], "language_level": ["advantage", "good command", "proficient"], "hard_skills": ["excel", "acca", "chinese word processing", "word", "analytical skills", "cpa", "hkicpa", "ms office"], "soft_skills": ["work independently", "analytical skills", "communication", "attention to detail", "team member", "interpersonal"], "languages_combined": [{"language": "english", "language_level": ["advantage", "good command"]}, {"language": "chinese", "language_level": ["advantage", "good command", "proficient"]}, {"language": "mandarin", "language_level": ["advantage", "good command"]}]}, "experience_required": {"duration": ["0-3 year"], "field": ["risk management", "audit"]}}, {"job_id": "100003009053894", "location_code": "hk", "company": "Spruson & Ferguson (Hong Kong) Limited", "job_title": "Trademark Specialist / Executive", "description": "Bring your career aspirations to life with AIA!\n\nDrive the development of strategy for Partnership Distribution, special projects and manage business planning, analysis and management & financial reporting\n\nRoles and Responsibilities:\n\nDrive the formulation of overall PD strategy and integrated business plans with sales channels\n\nLead and drive new partnership business development and collaborate with stakeholders to deliver the desired outcome\n\nManage strategic plan development/ budget planning/ forecasting process/ sales target setting\n\nProvide and manage management and performance reporting with insightful analysis and recommendations to various management groups and stakeholders\n\nAnalyze performance across revenue and expenses lines to identify and explore business opportunities\n\nMonitor and keep track of business initiatives and provide timely updates and recommendations to the management.\n\nObserve market trends, changes and developments to identify opportunities and challenges, and provide ideas and assessment to maximize business strength and opportunities\n\nCollect and analyze market needs from various sources (e.g. sales, customers, opinion leaders, market statistics and research) with insights for management team to formulate business plan for PD\n\nDefine, drive and develop sales incentive scheme for sales channels\n\nEnsure compliance with local budget and expense guideline, establish and maintain appropriate internal controls\n\nCommunicate business directions to PD staff via different platforms to align expectations and increase staff engagement.\n\nPerform other responsibilities and duties periodically assigned by direct manager and department heads in order to meet business needs\n\nMinimum Job Requirements:\n\nUniversity degree with over 8 years working experience in insurance/financial services, management consulting or corporate strategy\n\nQualification of CPA, MBA or equivalent preferred\n\nProven experience in financial analysis, management reporting, strategic planning\n\nInnovative, curious and courageous to share insights and propose new ideas in business solution\n\nStrategic and analytical mindset, self-motivated and result-oriented\n\nStrong interpersonal and time management skills\n\nAble to work under pressure and meet tight deadlines\n\nBe a team player\n\nStrong in MS Excel and PowerPoint tools for developing financial models, data analysis and management presentation\n\nGood command of written & spoken Chinese and English\n\nObtain relevant license if job involves in regulated activities\n\nBuild a career with us as we help our customers and the community live healthier, longer, better lives.\n\nYou must provide all requested information, including Personal Data, to be considered for this career opportunity. Failure to provide such information may influence the processing and outcome of your application. You are responsible for ensuring that the information you submit is accurate and up-to-date.", "employment_types": ["Full Time", "Permanent"], "selling_points": ["HK or overseas qualified legal professional", "1-3 years' PQE preferred", "5 days work, up to 3 months bonus"], "locations": ["Wan Chai"], "categories": ["Professional Services", "Business Consultancy", "Legal & Compliance", "Translation"], "post_time": "2022-01-17T07:42:51Z", "salary": {"currency": null, "max": null, "min": null, "period": "monthly", "term": null}, "salary_visible": false, "title_keywords": ["specialist", "executive"], "responsibilities": ["collaborate with", "business initiatives", "ideas", "budget", "business plans", "maintain", "plan", "management team", "budget planning", "sales target", "expenses", "monitor", "develop", "business plan", "forecasting", "reporting", "management", "business opportunities", "analysis", "ensure compliance"], "requirements": {"degrees": ["university degree"], "majors": ["insurance"], "languages": ["english", "chinese"], "language_level": ["good command"], "hard_skills": ["analysis", "powerpoint", "financial analysis", "cpa", "ms excel", "processing"], "soft_skills": ["self-motivated", "meet tight deadlines", "responsible", "interpersonal", "time management skills", "accurate", "presentation", "team player", "innovative", "result-oriented", "work under pressure"], "languages_combined": [{"language": "english", "language_level": ["good command"]}, {"language": "chinese", "language_level": ["good command"]}]}, "experience_required": {"duration": ["8 years"], "field": ["management", "consulting", "financial services", "planning", "insurance", "financial"]}}, {"job_id": "100003009055253", "location_code": "hk", "company": "Accenture Company Limited", "job_title": "Strategy & Consulting - Insurance Consultant", "description": "Perform pre-contract and post-contract quantity surveying duties\nHandle tender documents administration, material taking off and pricing, measurement of works, valuation of variation\nAttend site inspections, site meetings and tender interviews\nLiaise with contractors, specialist, suppliers and related parties\n\n\u00a0Requirements\u00a0\n\nDegree / Associate Degree / Higher Diploma in Quantity Surveying / Building Services or equivalent\nFor AQS: At least 1-year working experience, fresh graduate are also welcomed\nFor QS:\u00a0Minimum 5\u00a0years working experience or 1 year post qualification experience with Membership of HKIS/RICS/AIQS\nFor SQS: Minimum 2 years post qualification experience with Membership of HKIS/RICS/AIQS\nExperience in all aspects of quantity surveying / building services\nE&M Background is highly preferred\nKnowledge in QS related software is highly preferred\nGood command of spoken & written English & Chinese\nGood communication and interpersonal skill, able to work independently and in a team\nSelf-motivated and disciplined\nImmediate available is preferable\n\nWe offer competitive remuneration package with fringe benefits including 5 days\u2019 work, public holidays, medical insurance and study allowance to the right candidate. Interested parties please send us full resume including expected salary and date available to us.", "employment_types": ["Full Time"], "selling_points": ["Management consulting", "Digital transformation", "Insurance core system"], "locations": ["Quarry Bay"], "categories": ["Professional Services", "Business Consultancy", "Information Technology (IT)", "Product Management / Business Analyst", "Insurance", "Others"], "post_time": "2022-01-18T01:55:31Z", "salary": {"currency": null, "max": null, "min": null, "period": "monthly", "term": null}, "salary_visible": false, "title_keywords": ["consultant"], "responsibilities": ["valuation", "software", "site meetings", "tender documents", "measurement", "communication", "tender", "site inspections", "insurance", "liaise with contractors", "administration"], "requirements": {"degrees": ["associate degree", "diploma", "degree", "fresh graduate"], "majors": ["building services", "surveying"], "languages": ["english", "chinese"], "language_level": ["good command"], "hard_skills": ["rics", "hkis"], "soft_skills": ["communication", "work independently", "self-motivated", "interpersonal skill"], "languages_combined": [{"language": "english", "language_level": ["good command"]}, {"language": "chinese", "language_level": ["good command"]}]}, "experience_required": {"duration": ["minimum 2 years", "1 year", "at least 1-year", "minimum 5 years"], "field": ["building services"]}}, {"job_id": "100003009056006", "location_code": "hk", "company": "KPMG", "job_title": "Manager / Senior Consultant, CRM - Technology Enablement", "description": "Job Responsibilities:-\n\n\nPrepare companies for fund raising and/or IPO by analyzing their financial information, preparing financial projections and assisting them in preparing financial and management accounts;\nConduct financial due diligence potential acquisition targets by collecting detailed information and conducting interviews; collate, analyze the information and prepare a detailed due diligence report;\nBe the acting CFO of a client; prepare and review monthly/quarterly consolidated financial information; manage cash position, cashflow projection; analyze and compare company forecasts and budgets;\nWork with a team of professionals, auditors, financial advisors, valuers and lawyers to perform consulting/advisory projects; and\nAssist in compliance including company secretarial matters for private companies in Hong Kong; cross-border company setup and transactions in Hong Kong & China.\n\u00a0\n\nJob Requirements: -\n\nBachelor degree or above in Accounting or Finance, (HKICPA, CIA or ACCA preferred);\nAt least 2-years relevant working experience;\nGood grasp of Microsoft Office applications such as excel and powerpoint;\nGood communication and presentation skills and sense of servicing awareness;\nGood command in English and Mandarin (listening, oral, reading and writing)\u00a0is a must; good communication and presentation skills in English and Mandarin.\nExperience in using Xero, CRM applications (such as ZOHO) is a plus.\nApplicants with international background preferred;\nEntrepreneurial\u00a0mindset, intellectual curiosity, structured thinking, innovative, and\u00a0embraces change and disruption;\nHonest, reliable, responsible, focus on teamwork, open minded, willing to learn;", "employment_types": ["Permanent"], "selling_points": ["Microsoft Dynamics; CRM implementations; UAT", "Agile Scrum methodology; RFP responses; Marketing", "configuration; Project management; CRM platform"], "locations": ["Aberdeen"], "categories": ["Professional Services", "Business Consultancy"], "post_time": "2022-01-18T03:11:04Z", "salary": {"currency": null, "max": null, "min": null, "period": "monthly", "term": null}, "salary_visible": false, "title_keywords": ["manager", "senior consultant"], "responsibilities": ["due diligence", "management", "budgets", "consulting", "review", "compliance", "transactions", "conducting interviews", "setup", "report"], "requirements": {"degrees": ["degree or above", "bachelor"], "majors": ["finance", "accounting"], "languages": ["english", "mandarin"], "language_level": ["good command", "good"], "hard_skills": ["excel", "acca", "plus", "microsoft office", "xero", "powerpoint", "focus", "hkicpa"], "soft_skills": ["oral", "responsible", "teamwork", "willing to learn", "communication", "presentation skills", "reliable", "honest", "structured", "open minded", "focus", "innovative"], "languages_combined": [{"language": "english", "language_level": ["good command", "good", "good"]}, {"language": "mandarin", "language_level": ["good command", "good", "good"]}]}, "experience_required": {"duration": [], "field": ["relevant working experience"]}}, {"job_id": "100003009051817", "location_code": "hk", "company": "RGF HR Agent Hong Kong Limited", "job_title": "Japanese Speaking Strategic Planning Officer (Up to 35K/ Good package/ Multinational corporation)", "description": "The Role\n\nAML Advisory role for all lines of our business - investment banking, equity derivatives, trading and research, etc.\n\nKey Accountabilities\n\nAssist the Money Laundering Reporting Officer (MLRO) in implementing effective AML measures and controls\nProvide advice to business units, including investment banking, equity sales and derivatives, financial products, sales, trading and research, global commodities and overseas offices if necessary, on AML, KYC and CDD matters\nReview the completeness of customers' KYC / CDD information, supporting documentation and risk assessment before granting approvals for new relationship or CCDD reviews whenever necessary\nIdentify, investigate and report suspicious activity and transaction, and escalate any material risk relevant information to MLRO and submit suspicious transaction reports to the JFIU on timely manner\nProduce regular AML reports for internal stakeholders\nPerform supervisory control and quality assurance of the KYC tasks within the compliance function, as second line of defense\nIdentify risk issues and propose recommendations / rectifications to senior management for resolution\nParticipate in the AML compliance projects to ensure the effective enhancements of the compliance control framework\nAct as project manager to advise on FinTech / RegTech AML systems\nAssist to organize and deliver AML training in relation to internal controls and regulatory updates\n\nSkills & Experience\n\nDegree holder of law, accounting, finance or other related disciplines\nMinimum 6 years relevant working experience in KYC or AML compliance\nRelevant industry qualifications in AML (ICA or ACAMS) preferred\nStrong knowledge of Hong Kong regulatory regime, especially KYC requirements and standards, preferably from investment and corporate banking services aspects\nStrong team player who is highly motivated, independent and able to work under pressure and tight timelines\nFluent in written and spoken Cantonese, Mandarin and English\n\nOther Information\n\nNotes to applicants:\n1. Please apply in strict confidence with full resume, academic record, current and expected salaries.\n2. The personal data provided will be used for consideration of recruitment only. All personal data of unsuccessful candidate will be destroyed within 24 months.\n3. Candidates with Enhanced Competency Framework (ECF): please state on the CV.\n\nAbout BOCI\n\nAs a leading investment bank in China and Hong Kong region, the investment banking arm of Bank of China, BOC International Holdings Limited (\u201cBOCI\u201d), is now seeking highly motivated, creative and success-oriented professional who would like to pursue the career in our group.\u00a0", "employment_types": ["Full Time", "Permanent"], "selling_points": ["Multinational corporation/ Strategic planning", "Strong analytical skills/ presentable/ JLPT N2", "Up to 35K / Good package / Kowloon"], "locations": ["Not Specified"], "categories": ["Professional Services", "Business Analysis / Data Analysis", "Business Consultancy"], "post_time": "2022-01-17T01:16:29Z", "salary": {"currency": null, "max": null, "min": null, "period": "monthly", "term": null}, "salary_visible": false, "title_keywords": ["officer"], "responsibilities": ["quality", "personal data", "senior management", "work under pressure", "control", "cdd", "compliance", "resolution", "reports", "banking", "kyc", "report", "reporting", "review", "documentation", "aml", "systems", "provide advice", "recruitment"], "requirements": {"degrees": ["degree holder"], "majors": ["related disciplines", "finance", "accounting", "law"], "languages": ["cantonese", "english", "mandarin"], "language_level": ["fluent"], "hard_skills": ["aml", "cdd", "kyc", "documentation", "acams"], "soft_skills": ["confidence", "independent", "timely", "motivated", "team player", "creative", "work under pressure"], "languages_combined": [{"language": "cantonese", "language_level": ["fluent"]}, {"language": "english", "language_level": ["fluent"]}, {"language": "mandarin", "language_level": ["fluent"]}]}, "experience_required": {"duration": ["minimum 6 years"], "field": ["compliance", "relevant working experience"]}}, {"job_id": "100003009051358", "location_code": "hk", "company": "Changetic Limited", "job_title": "Assistant Project Manager", "description": "Client Engagement\n\nManage and maintain regular communications with the clients\nManage communications with internal and external parties such as other client personnel, investors, attorneys, auditors, bankers and etc.\nService Delivery\n\nEnsure monthly and quarterly client deliverables are met\nOversee and provide guidance to junior staffs\nReview quarterly and annual financial work papers including portfolio schedules, accruals, partner capital allocations and etc\nCoordination of annual audit and tax return preparation with external accounting firms\nService Quality\n\nManage internal workflow to ensure internal processing and client deadlines are met\nTeamwork\n\nDemonstrate good interpersonal skills and the ability to work well with others, individually and within a group\nActing as one of the key resources to provide guidance and/or necessary coaching to junior and/or new team members of the team\nOther Responsibilities\n\nIntegrate new business/client on boarding\nOther ad hoc projects assigned by immediate supervisor\nRequirements\n\nDegree holder in Accounting, Finance, Economics or related discipline\nAt least 4 years of related experience with experience in coaching and mentoring junior staff\nWorking knowledge on Private Equity fund administration is preferred\nQualification in HKICPA/ ACCA or similar qualification preferred\nInvestran and/or VPM software experience is highly advantageous\nHighly motivated self-starter with the ability to deal with ambiguities, able to work within ill-defined boundaries and able to challenge status quo\nExcellent interpersonal and communication skills are essential and can communicate at the senior executive level\nStrong leadership and a team player, able to work under pressure in meeting deadlines\nGood analytical and problem solving skills\nProficiency in MS Office Suite\nFluent in written and oral English with a good command of Chinese and Mandarin proficiency\u00a0\n\nWe are an equal opportunity employer and welcome applications from all qualified candidates. Applications and resume will be kept for a period of 24 months after completion of the recruitment process. (All information will be held in strict confidence and only be used for recruitment purpose).\n\n(We are not accepting any\u00a0unsolicited resumes from search firm recruiters.)", "employment_types": ["Full Time", "Permanent"], "selling_points": ["5-day work week", "Professional working environment", "Strong personal and professional growth"], "locations": ["Sheung Wan"], "categories": ["Professional Services", "Business Consultancy", "Sales, CS & Business Devpt", "Business Development", "Marketing / Public Relations", "Marketing - Market Research"], "post_time": "2022-01-15T10:54:23Z", "salary": {"currency": null, "max": null, "min": null, "period": "monthly", "term": null}, "salary_visible": false, "title_keywords": ["assistant project manager"], "responsibilities": ["ad hoc projects"], "requirements": {"degrees": ["degree holder"], "majors": ["finance", "accounting", "economics"], "languages": ["english", "chinese", "mandarin"], "language_level": ["proficiency", "good command", "fluent"], "hard_skills": ["acca", "hkicpa", "problem solving skills", "private equity", "ms office"], "soft_skills": ["communication skills", "oral", "confidence", "analytical and problem solving skills", "motivated", "team player", "leadership", "interpersonal", "work under pressure"], "languages_combined": [{"language": "english", "language_level": ["fluent", "good command"]}, {"language": "chinese", "language_level": ["proficiency", "good command"]}, {"language": "mandarin", "language_level": ["proficiency", "good command"]}]}, "experience_required": {"duration": ["at least 4 years"], "field": ["related"]}}, {"job_id": "100003009047020", "location_code": "hk", "company": "Don Nelson Recruitment Limited", "job_title": "Assistant Business Manager - Consulting Industry", "description": "Key responsibilities\n\nConducing trademark searches and preparing search reports\nFiling trade mark applications in China, Hong Kong, and other counties\nAdvising on and responding to office actions in China, Hong Kong, and other counties\nAdvising on trademark prosecution matters in general\nMonitoring trademark workflow and deadlines\n\nSkills and experience\n\nHong Kong or overseas qualified legal professional with 1-3 years' PQE preferred\nGood command of both spoken and written English and Putonghua\nAbility to prioritize tasks and multitask effectively\nA proactive, solution-oriented approach to work and team interaction\nWilling to work overtime and flexibility regarding work schedule\nFamiliarity with Patricia or Inprotech docketing software will be an advantage\n\nThe successful candidate will be working with a highly motivated team and a company who is currently expanding globally.\n\nWe offer a competitive benefits package.\n\nOnly shortlisted candidates will be notified.\n\n(Personal data collected will be used for recruitment purposes only)", "employment_types": ["Full Time", "Permanent"], "selling_points": ["Awarded and fast growing recruitment agency", "Planning the development and growth strategies", "Challenging work nature with regional exposure"], "locations": ["Sheung Wan"], "categories": ["Professional Services", "Business Consultancy", "Sales, CS & Business Devpt", "Business Development", "Management", "General Management"], "post_time": "2022-01-15T03:49:34Z", "salary": {"currency": null, "max": null, "min": null, "period": "monthly", "term": null}, "salary_visible": false, "title_keywords": ["manager", "assistant"], "responsibilities": ["monitoring", "reports", "schedule", "software"], "requirements": {"degrees": [], "majors": [], "languages": ["putonghua", "english"], "language_level": ["good command"], "hard_skills": [], "soft_skills": ["work overtime", "prioritize", "multitask", "motivated", "proactive"], "languages_combined": [{"language": "putonghua", "language_level": ["good command"]}, {"language": "english", "language_level": ["good command"]}]}, "experience_required": {"duration": [], "field": []}}, {"job_id": "100003009051499", "location_code": "hk", "company": "", "job_title": "Manager / Asst. Manager  (5 days work)", "description": "Your Role:\nThere will never be a typical day at Accenture, but that\u2019s why people love it here. The opportunities to make a difference within exciting client initiatives are limitless in this ever-changing business landscape.\n\nKey Responsibilities:\n\nAnalyze opportunities and challenges our clients face in the areas of system, processes, operations, and enterprise performance management\nSupport the client in defining and modeling the key drivers of current and future enterprise value\nSupport clients\u2019 transformation in insurance products, process and core system\nDemonstrate strong analytical capabilities and apply knowledge of selected tools and techniques, drawing logical conclusions\nDevelop expertise in customer insight & growth experience practice areas to increase the breadth and depth of our knowledge base and capabilities\nDesign and deploy end-to-end insurance process and operating model\n\n\nExperience, Attributes and Qualifications:\n\nUniversity Degree from reputable university, MBA preferred.\nMinimum 3 years of working experience with insurance clients or insurance companies, experience in large-scale system integration/data migration project will be preferred\nKnowledge in Insurance Products/Process and Insurance Core System\nKnowledge in project management (Waterfall/Agile Scrum)\nExperience in end-to-end insurance or retirement process and operating model design\nStrong stakeholder management with business/IT stakeholders and subject matter experts, able to create and deliver high-impact communication to senior audiences (written and oral in English, Mandarin and Cantonese)", "employment_types": ["Full Time", "Permanent"], "selling_points": ["Coaching & team building, develop new market", "International & friendly working environment", "very attractive remuneration  package"], "locations": ["Not Specified"], "categories": ["Professional Services", "Business Consultancy", "Management", "General Management", "Sales, CS & Business Devpt", "Sales - Sales Management"], "post_time": "2022-01-16T05:28:25Z", "salary": {"currency": "HKD", "max": 69999, "min": 25000, "period": "monthly", "term": null}, "salary_visible": true, "title_keywords": ["asst. manager", "manager"], "responsibilities": ["management", "data", "operations", "design", "develop", "communication", "migration", "project management", "support clients", "deploy", "insurance"], "requirements": {"degrees": ["university degree"], "majors": [], "languages": ["cantonese", "english", "mandarin"], "language_level": [], "hard_skills": ["integration", "make", "project management", "agile"], "soft_skills": ["communication", "project management", "oral", "agile"], "languages_combined": [{"language": "cantonese", "language_level": []}, {"language": "english", "language_level": []}, {"language": "mandarin", "language_level": []}]}, "experience_required": {"duration": ["minimum 3 years"], "field": ["insurance", "design"]}}, {"job_id": "100003009052481", "location_code": "hk", "company": "BSI Pacific Ltd", "job_title": "BIM tutor", "description": "In KPMG's Consulting practice, we don't limit ourselves to either strategy or implementation. Instead, we deliver both.\u00a0 Our team in Hong Kong is the fastest growing division within KPMG China and represents a young and enthusiastic team that always pushes itself to succeed.\u00a0 Since our creation, we've developed in-depth knowledge of an incredibly broad spread of sectors and services.\n\nWe are looking for a Manager or Senior Consultant candidate for our Technology Enablement service team. This role provides technical support in sales and delivery cycle through the evangelizing of technology, conveying the art of the possible and showcasing business value to our clients leveraging CRM platform.\n\nAbout your experience\n\nAny Microsoft Dynamics and Salesforce functional certification\u00a0\nExperience in onsite functional roles on full-lifecycle CRM implementations\nStrong consulting and/or CRM implementation experience.\nExperience designing and implementing technology-enabled business solutions in client-facing and team leadership roles (e.g. functional lead, workstream lead, project manager).\nExperience defining systems strategy, developing systems requirements, planning and executing testing, training, defining support procedures, and implementing practical business solutions under multiple deadlines.\nExperience delivering projects using Agile Scrum methodology.\nExperience contributing to RFP responses and other sales activities.\n\nAbout the role\n\nBuild own understanding of our purpose and values; explore opportunities for impact\nDemonstrate strong commitment to personal learning and development\nUnderstand expectations and demonstrate personal accountability for keeping performance on track\nActively focus on developing effective communication and relationship-building skills\nUnderstand how client's daily work contributes to the priorities of the team and the business\nPerform the configuration and administration work of the application solution\nWork with onshore and offshore technical developers on delivering the solution based on the business requirement\nPlan and execute testing to ensure the application usability, including drafting test plan and test cases, conducting UAT etc.\n\nOther Requirements\n\nBachelor degree in Computer Science, Information Systems, Marketing or a related field, other degree holders will also be considered\nAt least 2 years of related experiences in the IT&T industry\nProject management/Agile/Scrum Master certifications is a plus\nGood oral and written communication skills in English, and Chinese\nStrong business acumen, excellent working attitude, self-motivated and a team player\nGood client management experience, and able to deal with both business users and technical personnel\nStrong business acumen, excellent working attitude, self-motivated and a team player\nGood client management experience, and able to deal with both business users and technical personnel", "employment_types": ["Full Time"], "selling_points": ["BIM training instructor", "Excellent career advancement", "5 days, medical, dental, life, commission, bonus"], "locations": ["Quarry Bay"], "categories": ["Professional Services", "Business Consultancy", "Education", "Tutor / Instructor", "Building & Construction", "Building / Construction / QS"], "post_time": "2022-01-17T03:09:21Z", "salary": {"currency": null, "max": null, "min": null, "period": "monthly", "term": null}, "salary_visible": false, "title_keywords": ["tutor"], "responsibilities": ["consulting", "microsoft dynamics", "communication", "plan", "designing", "administration", "uat", "configuration", "implementation", "developing", "testing", "management", "procedures", "executing", "sales activities", "technical support", "systems", "project management", "planning"], "requirements": {"degrees": ["degree", "bachelor", "master"], "majors": ["project management", "marketing", "computer science"], "languages": ["english", "chinese"], "language_level": ["good"], "hard_skills": ["plus", "salesforce", "agile", "project management", "focus", "acumen"], "soft_skills": ["communication skills", "oral", "self-motivated", "agile", "accountability", "communication", "project management", "learning", "team player", "enthusiastic", "business acumen", "focus", "leadership", "client-facing"], "languages_combined": [{"language": "english", "language_level": ["good"]}, {"language": "chinese", "language_level": ["good"]}]}, "experience_required": {"duration": ["at least 2 years"], "field": ["management", "training", "consulting", "related", "developing", "testing", "business", "planning", "client-facing", "team"]}}, {"job_id": "100003009056220", "location_code": "hk", "company": "Swire Resources Ltd", "job_title": "Business Development Executive", "description": "Reporting to Senior Management, the incumbent will be responsible for the\u00a0Business Development functions include identifying customer markets, monitoring industry trends, conducting competitor analyses and crafting business plans with the aim to determine ideal market opportunities to pursue and introduce new lifestyle and sports brands to Asia under distribution/ joint-venture / franchising / other suitable models.\u00a0\n\nResponsibilities\n\nConduct market research and analysis to identify customer markets, monitor industry trends, conduct competitor analyses to drive business opportunities\nAssist in developing business proposals and participate in new business pitches for targeted brands and future business collaboration\nAssist in Company\u2019s branding and media communication activities e,g, press releases, corporate marketing collaterals and website, etc.\nSupport senior management on preparing business presentation materials and internal / external communications materials such as press materials related to corporate-level etc.\nParticipate in operational analysis and special corporate projects\n\nRequirements\n\nUniversity graduate with 3 years\u2019\u00a0 working experience in business analysis, business development or consultancy\nStrong numeric and business acumen\nGood interpersonal & presentation skills\nProactive, energetic, dynamic and with genuine passion in retail industry\nAttentive to details and with multi-tasking capability\nStrong oral and written communication in English, Mandarin and Cantonese\nExcellent command of\u00a0 Microsoft office application including PowerPoint, Excel and Word\n\nWe offer competitive remuneration package with\u00a0a wide range of fringe benefits including\n\n5-day work week\nDiscretionary Bonus\nComprehensive Medical Coverage\nStaff Shopping Discount\nNon-contributory Retirement Benefits Scheme\nBirthday Leave\n\nInterested parties please send resume with present and expected salary to Human Resources Department, Swire Resources Limited,\u00a012/F Kingston International Centre, 19 Wang Chiu Road Kowloon Bay, Hong Kong or by\u00a0clicking the below \"Apply Now\" button.\n\nSwire Resources Limited is Equal Opportunity Employer\n", "employment_types": ["Full Time", "Permanent"], "selling_points": ["Conduct market research and analysis", "developing business proposals & pitches", "Support senior management in business presentation"], "locations": ["Kowloon Bay"], "categories": ["Professional Services", "Business Consultancy", "Sales, CS & Business Devpt", "Business Development", "Management", "General Management"], "post_time": "2022-01-18T03:37:09Z", "salary": {"currency": null, "max": null, "min": null, "period": null, "term": null}, "salary_visible": false, "title_keywords": ["business development executive"], "responsibilities": ["conduct market research", "analysis", "monitor", "business opportunities", "developing", "marketing collaterals", "communication", "website", "senior management"], "requirements": {"degrees": ["university graduate"], "majors": ["business"], "languages": ["cantonese", "english", "mandarin"], "language_level": [], "hard_skills": ["excel", "microsoft office", "analysis", "word", "powerpoint", "dynamic", "acumen"], "soft_skills": ["oral", "attentive to details", "passion in", "genuine", "communication", "presentation skills", "energetic", "dynamic", "multi-tasking", "business acumen", "proactive", "interpersonal"], "languages_combined": [{"language": "cantonese", "language_level": []}, {"language": "english", "language_level": []}, {"language": "mandarin", "language_level": []}]}, "experience_required": {"duration": ["3 years"], "field": ["business analysis", "business development"]}}, {"job_id": "100003009056430", "location_code": "hk", "company": "Osmium Consulting Group Limited", "job_title": "Business Development Executive ( Commission Driven )", "description": "Responsibilities :\n\nDevelop new market initiatives, assess new markets, and analyze business opportunities\nDevelop a sales contact plan and attending industry events to build relationships with key prospects\nConduct face to face meetings with new business prospects and attend events.\nDeliver sales plans and provide documented reviews of business contracts\nDevelop effective working relationships with clients through regular meetings and identify and obtain further sales and business development opportunities.\nProvide sales reports when requested and to keep an accurate pipeline and CRM\nLiaise will all departments to ensure accurate deliverables of services\nRequirements :\u00a0\n\n\nFluent in English\u00a0\nAble to work in startup culture\nAble to reach target", "employment_types": ["Full Time", "Permanent"], "selling_points": ["Media Intelligence", "Commission Driven", "Sales"], "locations": ["Sheung Wan"], "categories": ["Professional Services", "Business Consultancy", "Sales, CS & Business Devpt", "Business Development", "Account Servicing"], "post_time": "2022-01-18T04:17:24Z", "salary": {"currency": "HKD", "max": 24999, "min": 17000, "period": "monthly", "term": null}, "salary_visible": true, "title_keywords": ["business development executive"], "responsibilities": ["liaise", "sales reports", "working relationships", "contracts", "business opportunities", "develop", "sales plans", "contact", "plan"], "requirements": {"degrees": [], "majors": [], "languages": ["english"], "language_level": ["fluent"], "hard_skills": [], "soft_skills": [], "languages_combined": [{"language": "english", "language_level": ["fluent"]}]}, "experience_required": {"duration": [], "field": []}}, {"job_id": "100003009056340", "location_code": "hk", "company": "ConnectedGroup Limited", "job_title": "Strategic & Project Assistant (MNC)", "description": "Strategic & Project Assistant (MNC)\n\nOur client is an international business which has over 70 year's history with global presence. They are looking for a Strategic & Project Assistant to join their global team.\n\nPosition Responsibilities\n\nServes as a trusted partner, maintaining confidentiality and professionalism in all situations.\nPartners and collaborates with peers and direct reports to manage cross-functional initiatives from conception to completion\nEffective calendar management, advanced planning and preparation of leadership team meetings internally and externally, including but not limited to townhall meetings, off- sites, vendor webinars, one-on-one meetings, etc.\nEvent management - organization of quarterly meetings, volunteering events, off-sites, webinars, summits etc.\nCreation and editions of document (Word, PPT, Excel, Power BI, Tableau) to support the direct report across the full spectrum of their work\nWork with cross-functional teams in the definition of project scope and objectives and resourcing, as aligned to company's strategies.\nManage synchronization across all dependencies.\nProvide oversight to project progress, issues/risks and decisions required.\nManage execution of initiatives ensuring that all projects are delivered on-time, within scope and within budget.\nManages all executive correspondence; directing or responding to customer and vendor communication.\nExpense management duties.\nOversee department budget.\nOther administrative duties as requested.\n\nPosition Requirements\n\nMBA and Master Degree holder is strongly preferred\nConsulting background candidates are highly preferred as well\nSolid administrative or project management experience; with experience supporting C-level executives\nLearning agility and a curiosity for understanding the business\nHigh attention to detail, organization and process.\nStrong teamwork skills and a strong ability to offer suggestions and improvements to process and work effectively.\nStrong relationship management skills.\nHigh level of confidentiality, discernment and judgment.\nAbility to be flexible in response to changing priorities and needs.\nProven ability to manage projects, work under pressure and consistently make deadlines.\nDemonstrated ability and willingness to continuously acquire new competencies and accept new challenges.\nStrong communication, oral and written. Ability to communicate clearly and effectively with senior leaders and external business partners.\nFluent in English and Chinese communication.\n\nInterested individuals can apply now and send CV to Vivian Wong, or call +852 3972 5831 for more information. Only relevant candidates will be contacted\n\nFor a more comprehensive list of our vacancies, please visit: www.connectedgroup.com", "employment_types": ["Full Time", "Permanent"], "selling_points": ["One of the market leading players in the industry", "International working environment", "Attractive package with promising career prospect"], "locations": ["Not Specified"], "categories": ["Accounting", "Others", "Admin & HR", "Personal / Executive Assistant", "Professional Services", "Business Consultancy"], "post_time": "2022-01-18T04:00:28Z", "salary": {"currency": null, "max": null, "min": null, "period": "monthly", "term": null}, "salary_visible": false, "title_keywords": ["project assistant"], "responsibilities": ["management", "power bi", "maintaining", "budget", "project progress", "from conception to completion", "communication", "reports", "administrative duties", "report", "cross-functional teams", "planning"], "requirements": {"degrees": ["master degree"], "majors": [], "languages": ["english", "chinese"], "language_level": ["fluent"], "hard_skills": ["project management", "make", "c"], "soft_skills": ["work effectively", "flexible", "oral", "teamwork", "communication", "project management", "learning", "comprehensive", "attention to detail", "work under pressure"], "languages_combined": [{"language": "english", "language_level": ["fluent"]}, {"language": "chinese", "language_level": ["fluent"]}]}, "experience_required": {"duration": [], "field": ["project management", "administrative"]}}, {"job_id": "100003009053251", "location_code": "hk", "company": "APEC Group International Limited", "job_title": "Associate / Senior Associate \u2013 Risk Management Advisory (Internal Audit)", "description": "\u00a0Responsibilities\n\nProviding outsourced internal audit services to our clients across various industries locally and internationally;\nDevelop and review risk management frameworks and policies;\nAssist organizations to maintain effective and efficient controls, in order to manage organizational and strategic risks;\nConduct various advisory tasks such as enterprise risk management under ISO31000, COSO Framework etc., compliance reviews and controls related projects, such as PN21/PN2 under the Listing Rules of the Stock Exchange of Hong Kong;\nAssist in operational risk assessment process including collect and verify data for evaluation of operational risk level;\nParticipate and provide risk comments in product development and business projects;\nKeep abreast of market news including customer data protection and fraud prevention;\nAssisting our clients in the risk management process.\n\n\u00a0Requirements\n\nHigher Diploma\u00a0in Accounting/Risk Management/Corporate Governance or related disciplines;\n0-3 year's experience in internal audit and risk services;\nStudent member/ member of HKICPA/ACCA/CPA Australia/IIA or equivalent qualification is preferred;\nPractical experience in internal audit & risk management;\nAttention to detail, able to work independently and as a team member;\nGood communication, interpersonal and analytical skills;\nAbility to interact with all levels of personnel, including senior executives of client management;\nGood command of written English & Chinese, Mandarin is an advantage;\nProficient in MS Office, including Word & Excel\u00a0and Chinese word processing is required;\nAble to travel overseas and the PRC;\nFresh\u00a0graduates are welcome;\nImmediate available is preferred;\nCandidates with more experience will be considered as Senior Associate.\n\nWhat we offered?\n\n5-day work week\nImportant festivals early leave\nOvertime meal allowance\nTraveling allowance\nDiscretionary bonus\nFull-paid sick leave\nStudy & Exam leave\nGraduation leave\nWedding leave\nCompassionate leave\nMedical Insurance Scheme\nTraining reimbursement\n\n\nInterested parties please click \"APPLY NOW\" and send your full resume with your\u00a0working experience, academic and professional qualification, expected salary, and date of availability\u00a0to HR Department.\n\nPersonal data collected will be used for recruitment purpose only.\u00a0", "employment_types": ["Full Time", "Permanent"], "selling_points": ["Internal Control, Risk Management, Internal Audit", "5-day work week", "Excellent career promotion prospect"], "locations": ["Sheung Wan"], "categories": ["Accounting", "Accountant", "Consulting", "Professional Services", "Business Consultancy"], "post_time": "2022-01-17T06:32:16Z", "salary": {"currency": null, "max": null, "min": null, "period": "monthly", "term": null}, "salary_visible": false, "title_keywords": ["senior associate", "associate"], "responsibilities": ["management", "internal audit", "data", "business projects", "policies", "review", "compliance", "comments", "customer data", "develop", "maintain", "evaluation", "listing"], "requirements": {"degrees": ["diploma"], "majors": ["related disciplines", "risk management", "accounting"], "languages": ["english", "chinese", "mandarin"], "language_level": ["advantage", "good command", "proficient"], "hard_skills": ["excel", "acca", "chinese word processing", "word", "analytical skills", "cpa", "hkicpa", "ms office"], "soft_skills": ["work independently", "analytical skills", "communication", "attention to detail", "team member", "interpersonal"], "languages_combined": [{"language": "english", "language_level": ["advantage", "good command"]}, {"language": "chinese", "language_level": ["advantage", "good command", "proficient"]}, {"language": "mandarin", "language_level": ["advantage", "good command"]}]}, "experience_required": {"duration": ["0-3 year"], "field": ["risk management", "audit"]}}, {"job_id": "100003009056690", "location_code": "hk", "company": "Beria Consultants Limited", "job_title": "ASSISTANT QUANTITY SURVEYOR / QUANTITY SURVEYOR / SENIOR QUANTITY SURVEYOR", "description": "Perform pre-contract and post-contract quantity surveying duties\nHandle tender documents administration, material taking off and pricing, measurement of works, valuation of variation\nAttend site inspections, site meetings and tender interviews\nLiaise with contractors, specialist, suppliers and related parties\n\n\u00a0Requirements\u00a0\n\nDegree / Associate Degree / Higher Diploma in Quantity Surveying / Building Services or equivalent\nFor AQS: At least 1-year working experience, fresh graduate are also welcomed\nFor QS:\u00a0Minimum 5\u00a0years working experience or 1 year post qualification experience with Membership of HKIS/RICS/AIQS\nFor SQS: Minimum 2 years post qualification experience with Membership of HKIS/RICS/AIQS\nExperience in all aspects of quantity surveying / building services\nE&M Background is highly preferred\nKnowledge in QS related software is highly preferred\nGood command of spoken & written English & Chinese\nGood communication and interpersonal skill, able to work independently and in a team\nSelf-motivated and disciplined\nImmediate available is preferable\n\nWe offer competitive remuneration package with fringe benefits including 5 days\u2019 work, public holidays, medical insurance and study allowance to the right candidate. Interested parties please send us full resume including expected salary and date available to us.", "employment_types": ["Full Time", "Permanent"], "selling_points": [], "locations": ["Kowloon Bay"], "categories": ["Building & Construction", "Architectural Services", "Professional Services", "Business Consultancy", "Building / Construction / QS"], "post_time": "2022-01-18T05:47:50Z", "salary": {"currency": null, "max": null, "min": null, "period": "monthly", "term": null}, "salary_visible": false, "title_keywords": ["assistant quantity surveyor", "quantity surveyor", "senior quantity surveyor"], "responsibilities": ["valuation", "software", "site meetings", "tender documents", "measurement", "communication", "tender", "site inspections", "insurance", "liaise with contractors", "administration"], "requirements": {"degrees": ["associate degree", "diploma", "degree", "fresh graduate"], "majors": ["building services", "surveying"], "languages": ["english", "chinese"], "language_level": ["good command"], "hard_skills": ["rics", "hkis"], "soft_skills": ["communication", "work independently", "self-motivated", "interpersonal skill"], "languages_combined": [{"language": "english", "language_level": ["good command"]}, {"language": "chinese", "language_level": ["good command"]}]}, "experience_required": {"duration": ["minimum 2 years", "1 year", "at least 1-year", "minimum 5 years"], "field": ["building services"]}}, {"job_id": "100003009049491", "location_code": "hk", "company": "Perrett Laver Limited", "job_title": "Consultant / Associate Consultant  (5 days)", "description": "Our client, a Japanese automobile company is looking for an Accounting, HR & Admin Manager to join their team as follows:\n\nJob Duties:\n\u2022 Handle the full set of accounting\n\u2022 Prepare month-end consolidation\n\u2022 Manage statutory audit, J-SOX, and tax filing\n\u2022 Prepare reports according to the templates provided by the HQ in Japan\n\u2022 Oversee the HR and Admin department\n\u2022 Liaise with the HQ in Japan\n\u2022 Other ad-hoc duties as assigned\n\nRequirement:\n\u2022 Bachelor's degree or higher\n\u2022 At least 10 years of relevant experience\n\u2022 Fluent in Japanese(JLT N2 or higher), English, and Chinese\n\u2022 ACCA/ HKIAAT student member or equivalent\n\u2022 Work experience in a Japanese company is a must\n\nPackage:\n- Discretionary bonus\n- Medical insurance\n\nInterested parties please send us your resume in MS Word/PDF format in English. All information received will be kept in strict confidential and only for recruitment purpose.\n\n", "employment_types": ["Full Time"], "selling_points": ["Higher Education and Research Leadership", "Senior Executive Recruitment Consultation", "best support our clients and candidates"], "locations": ["Central"], "categories": ["Professional Services", "Business Consultancy", "Marketing / Public Relations", "Marketing - Marketing Communication", "Public / Civil", "Social Services - Community / Non-profit Organization"], "post_time": "2022-01-14T08:47:50Z", "salary": {"currency": null, "max": null, "min": null, "period": "monthly", "term": null}, "salary_visible": false, "title_keywords": ["associate", "consultant"], "responsibilities": ["hr", "tax filing", "month-end", "audit", "full set of accounting", "liaise with", "ad-hoc duties", "prepare reports"], "requirements": {"degrees": ["degree", "bachelor"], "majors": [], "languages": ["japanese", "english", "chinese"], "language_level": ["fluent"], "hard_skills": ["acca"], "soft_skills": [], "languages_combined": [{"language": "japanese", "language_level": ["fluent"]}, {"language": "english", "language_level": ["fluent"]}, {"language": "chinese", "language_level": ["fluent"]}]}, "experience_required": {"duration": ["at least 10 years"], "field": ["relevant experience"]}}, {"job_id": "100003009052113", "location_code": "hk", "company": "AVISTA PRO-WIS Risk Advisory Limited", "job_title": "Senior Environmental Consultant (ESG Advisory Services)", "description": "Our client, a Japanese\u00a0Logistics company, is looking for a suitable candidate for\u00a0Shipping Assistant Manager as below:\nJob Duties\n\nControl and manage Import & Export team operation\nSupervising the team to reach the KPI\nPrepare quotations\nNegotiate shipment routine, freight schedules, and price, with carriers and forwarders\u00a0\nLiaise with group companies, agents, existing key customers, and new customers for shipping arrangements\u00a0\nPrepare budget, monthly and annual forecast\nResponsible for cost control\nAnalyze and prepare data and reports to the top management in HK & JP\nAssist the management in improving the team's efficiency\nOther ad-hoc duties as assigned\nRequirement\n\nDiploma or above\nAt least 5 years of experience in the logistic industry\nImport, export & forwarding experience is a MUST\nManagement experience is a MUST\nFluent in English and Chinese\nJapanese ability is an advantage\nPackage\nAlternate Weekends\nMedical Insurance\nSick Leave\nTransportation allowance\nFull attendance allowance\nTitle Allowance\nAnnual Leave\nDouble Pay\nDiscretionary Bonus\n\nInterested parties please send us your resume in MS Word/PDF format in English.\nAll information received will be kept in strict confidential and only for recruitment purpose", "employment_types": ["Full Time", "Permanent"], "selling_points": ["ESG consulting, sustainability target setting", "Knowledge in climate/environmental science,TCFD", "More experience will be considered as AM"], "locations": ["Wan Chai"], "categories": ["Accounting", "Consulting", "Banking / Finance", "Financial Services", "Professional Services", "Business Consultancy"], "post_time": "2022-01-17T02:07:37Z", "salary": {"currency": null, "max": null, "min": null, "period": "monthly", "term": null}, "salary_visible": false, "title_keywords": ["senior environmental consultant"], "responsibilities": ["control", "supervising", "shipping", "management", "ad-hoc duties", "data", "schedules", "budget", "reports", "forecast", "cost control", "liaise with"], "requirements": {"degrees": ["diploma or above"], "majors": [], "languages": ["japanese", "english", "chinese"], "language_level": ["advantage", "fluent"], "hard_skills": [], "soft_skills": [], "languages_combined": [{"language": "japanese", "language_level": ["advantage"]}, {"language": "english", "language_level": ["fluent"]}, {"language": "chinese", "language_level": ["fluent"]}]}, "experience_required": {"duration": ["at least 5 years"], "field": ["management"]}}, {"job_id": "100003009052162", "location_code": "hk", "company": "BDO", "job_title": "Associate - Risk Advisory Services (2022 Jan Intake)", "description": "Our client , a Japanese Banking company is seeking for\u00a0Analyst/Transaction to join their team as below:\n\nDuties:\n\u2022 To work closely with clients, relationship managers, and Operations Departments to ensure client transactions are completed efficiently and accurately\n\u2022 To handle instructions and inquiries about client transactions in a timely and orderly manner to ensure quality service is delivered.\n\u2022 To follow up pending items by contacting clients regularly to avoid overdue tasks\n\u2022 To prepare control sheet for unprocessed documents and follow up the settlement in a timely manner\n\u2022 To act as the 1st line of defense and ensure all transactions are in compliance with internal policies, AML, sanctions, and other regulatory requirements\n\u2022 To prepare AML related reports and relevant documents to facilitate KYC and transaction monitoring processes\n\u2022 To support the implementation and delivery of enhancement initiatives of the Business Unit according to the predetermined schedule\n\u2022 To maintain a good working knowledge of procedural changes, products, relevant rules, and regulations\n\nRequirement:\n\u2022 Degree holder\n\u2022 Fluent in Japanese and English\n\u2022 At least 3 years of relevant experience in administration and operational support\n\u2022 Candidates with NO banking and finance background will also be considered\n\u2022 Good numerical sense and analytical skills\n\u2022 Team player with excellent interpersonal and communication skills\n\nPackage:\n\n5 working days\nMedical\nDiscretionary Bonus\nAnnual leave\nSick leave\nInterested parties please send your English CV to us in MS Word/ PDF format.\u00a0All information received will be kept in strict confidential and only for recruitment purpose.", "employment_types": ["Full Time", "Permanent"], "selling_points": ["Excellent opportunity of career growth", "Good exposure in a sizable CPA firm", "Birthday Leave, Medical and Life Insurance, etc."], "locations": ["Sheung Wan"], "categories": ["Accounting", "Audit", "Consulting", "Professional Services", "Business Consultancy"], "post_time": "2022-01-17T02:17:57Z", "salary": {"currency": null, "max": null, "min": null, "period": "monthly", "term": null}, "salary_visible": false, "title_keywords": ["associate"], "responsibilities": ["regulations", "control", "aml", "operations", "policies", "compliance", "a timely manner", "quality", "transactions", "regulatory requirements", "monitoring", "implementation", "maintain", "reports", "schedule", "kyc"], "requirements": {"degrees": ["degree holder"], "majors": [], "languages": ["japanese", "english"], "language_level": ["fluent"], "hard_skills": ["no", "analytical skills"], "soft_skills": ["communication skills", "team player", "interpersonal", "analytical skills"], "languages_combined": [{"language": "japanese", "language_level": ["fluent"]}, {"language": "english", "language_level": ["fluent"]}]}, "experience_required": {"duration": ["at least 3 years"], "field": ["relevant experience", "administration"]}}, {"job_id": "100003009038278", "location_code": "hk", "company": "Links International", "job_title": "Strategy Manager (Consulting Firm background welcome )", "description": "Job Description\n\nOur client a reputable TMT company. They are looking for an experienced candidate join as business strategy manager to lead their Strategy and Operation team. You will act as a business advisory focus on project management, business process improvement and market entry strategy.\n\nJob Duties\n\nAct as a business advisory and lead the Strategy &Operation consulting team\nDesigned Operation mode to improve operational efficiency\nProvide change management advice, develop change management plans and implement change management activities\nDeveloped customer strategy at procedure level\nOrganized and delivered internal consulting training\nSupport cross functional business partners with analytical insights and problem solving\nBuild cross functional partnerships and consensus\nAlign processes, resources-planning and functional goals with overall strategy\nMonitor and analyses industry trends and market changes\n\nRequirements\n\nBachelor's degree holder in business related discipline\n3-5 years strategic planning or business strategy development experience\nExcellent command of English and Chinese\nExcellent leadership and track records in project management , process improvement\nImmediate available is highly preferable", "employment_types": ["Full Time", "Permanent"], "selling_points": ["TMT Industry", "Attractive Package", "Big 4 Strategy Consulting candiate welcome"], "locations": ["Not Specified"], "categories": ["Professional Services", "Business Consultancy"], "post_time": "2022-01-11T06:25:35Z", "salary": {"currency": null, "max": null, "min": null, "period": "monthly", "term": null}, "salary_visible": false, "title_keywords": ["manager"], "responsibilities": ["change management", "consulting", "monitor", "develop", "project management", "business process", "plans", "planning"], "requirements": {"degrees": ["bachelor", "degree holder"], "majors": ["business"], "languages": ["english", "chinese"], "language_level": ["excellent"], "hard_skills": ["project management"], "soft_skills": ["project management", "leadership"], "languages_combined": [{"language": "english", "language_level": ["excellent"]}, {"language": "chinese", "language_level": ["excellent"]}]}, "experience_required": {"duration": ["3-5 years"], "field": ["development", "business", "planning"]}}, {"job_id": "100003009048300", "location_code": "hk", "company": "Perun Consultants Limited", "job_title": "Restructuring and Insolvency Manager / Assistant Manager / Associate", "description": "Perun Consultants is the leading independent advisory firm with offices in Hong Kong and Singapore. We specialise in provision of high quality services in the areas of forensic accounting, corporate advisory, restructuring, turnaround and liquidation appointments. At Perun, we promote a work-life balance, value individualism and embrace the differences.\nWe are currently seeking an ambitious and qualified candidate with the following attributes to join our Hong Kong office as a Restructuring and Insolvency Manager / Assistant Manager / Associate\n\nResponsibilities:\n\nday-to-day administration of different compulsory and voluntary liquidations, bankruptcy receiverships, and/or restructuring engagements\ndrafting reports to the Court and other deliverables to clients;\ncontributing to development of best practice;\nestablishing and developing client network; and\ncoaching and training junior staff.\nRequirements:\n\nBachelor\u2019s degree or higher in Accounting, Finance, Law or other Business-related discipline preferred.\nCA, CPA or equivalent. Consideration will also be given to part qualified candidates, with support given to complete the qualification process;\n5+ years relevant experience including insolvency, restructuring and forensic accounting for the position of Assistant Manager and above and 2+ years relevant experience for the position of Associate.\nGood business sense and commercial acumen;\nStrong problem solving skills;\nStrong financial, business analytical and excellent report writing skills; and\nExcellent written and oral communication skills in both English and Mandarin Chinese.\nThe successful candidate will be able to demonstrate solid experience (commensurate with the applicable employment grade) in:\n\ninsolvency, financial and operational restructuring and/or other advisory engagements. Experience in complex cross-border matters would be advantageous;\nadministration of compulsory and voluntary liquidations, bankruptcy receiverships, and/or restructuring assignments;\ndrafting reports, letters and other deliverables;\nclient management from a professional services background.\nIn addition to the above role, we are always interested in hearing from proactive, commercially minded, individuals at all levels of seniority and experience looking to work in a dynamic and flexible environment.\n\nWe offer a competitive remuneration package where you will be rewarded for your individual and team performance. We are committed to being an inclusive employer and are happy to consider flexible working arrangements.\nTo apply, contact us at Apply Now .", "employment_types": ["Full Time"], "selling_points": [], "locations": ["Central"], "categories": ["Professional Services", "Business Analysis / Data Analysis", "Business Consultancy"], "post_time": "2022-01-14T06:11:03Z", "salary": {"currency": null, "max": null, "min": null, "period": "monthly", "term": null}, "salary_visible": false, "title_keywords": ["assistant manager", "associate", "manager"], "responsibilities": ["reports", "developing", "administration"], "requirements": {"degrees": ["degree", "bachelor"], "majors": ["business", "finance", "accounting", "law"], "languages": ["mandarin chinese", "english"], "language_level": ["excellent"], "hard_skills": ["writing skills", "cpa", "dynamic", "problem solving skills", "acumen"], "soft_skills": ["flexible", "communication skills", "oral", "business sense", "interested in", "writing skills", "dynamic", "problem solving skills", "proactive"], "languages_combined": [{"language": "mandarin chinese", "language_level": ["excellent"]}, {"language": "english", "language_level": ["excellent"]}]}, "experience_required": {"duration": ["5+ years", "2+ years"], "field": ["accounting", "relevant experience"]}}, {"job_id": "100003009051475", "location_code": "hk", "company": "BDO", "job_title": "Manager / Senior Associate - Transfer Pricing (Ref: TAX)", "description": "Applications are invited for appointment as\u00a0Research Assistant Professor (RAP) in Epidemiology and Biostatistics in the School of Public Health\u00a0(Ref.: 508977), to commence as soon as possible, on a two-year fixed-term basis, with the possibility of renewal subject to satisfactory performance.\n\nApplicants should possess a doctoral degree by research (Ph.D., D.Sc., Dr.P.H. or equivalent) in epidemiology, biostatistics, medicine, or related disciplines.\u00a0They should have strong expertise in infectious disease epidemiology demonstrated by a strong track record in influenza and COVID-19 research; excellent written and oral communication skills; and the ability to work independently and in collaboration with a multidisciplinary team. Relevant work experience in infectious disease epidemiology, and an excellent record of publications and grants would be advantages.\n\nThe appointee will conduct epidemiological research with a focus on generating data on COVID-19 epidemiology and control to support evidence-based policies.\u00a0He/She will develop research programs independently; write scientific publications, grant proposals and reports; supervise junior research staff and students; and assist in administrative, operational and other duties as assigned. There will be opportunities for participation in teaching programmes. Information about the School can be obtained at\u00a0http://sph.hku.hk/index.php.\u00a0\n\nA highly competitive salary commensurate with qualifications and experience will be offered, in addition to annual leave and medical benefits. At current rates, salaries tax does not exceed 15% of gross income. The appointment will attract a contract-end gratuity and University contribution to a retirement benefits scheme, totalling up to 15% of basic salary.\n\nThe University only accepts online applications for the above post.\u00a0Applicants should apply online and upload an up-to-date C.V.\u00a0\u00a0Review of applications will start on December 7, 2021 and continue until\u00a0January 31, 2022,\u00a0or until the post is filled, whichever is earlier.\n\nAdvertised:Nov 23, 2021 (HK Time)\nApplications close:Jan 31, 2022 (HK Time)\n\n\u6709\u610f\u7533\u8acb\u8005\u8acb \u6309 APPLY NOW\u7533\u8acb\n\n", "employment_types": ["Full Time", "Permanent"], "selling_points": ["Perform various TP and tax analysis", "2 to 6 years of relevant experience", "Excellent Career Prospect"], "locations": ["Sheung Wan"], "categories": ["Accounting", "Taxation", "Professional Services", "Business Consultancy"], "post_time": "2022-01-16T03:48:30Z", "salary": {"currency": null, "max": null, "min": null, "period": "monthly", "term": null}, "salary_visible": false, "title_keywords": ["senior associate", "manager"], "responsibilities": ["control", "other duties", "data", "policies", "develop", "communication", "reports"], "requirements": {"degrees": ["degree"], "majors": [], "languages": [], "language_level": [], "hard_skills": ["focus", "php"], "soft_skills": ["communication skills", "oral", "work independently", "independently", "focus"], "languages_combined": []}, "experience_required": {"duration": [], "field": []}}, {"job_id": "100003009045799", "location_code": "hk", "company": "The University of Hong Kong", "job_title": "Research Assistant Professor (508977)", "description": "In KPMG's Management Consulting practice, we don't limit ourselves to either strategy or implementation. Instead, we deliver both.\u00a0 Our team in Hong Kong is growing and represents a young and enthusiastic team that always pushes itself to succeed.\u00a0 Since our creation, we've developed in-depth knowledge of an incredibly broad spread of sectors and services.\n\nOur People Change Consulting team is dedicated to helping our clients get the best out of their people. We work on standalone People & Change projects, we also provide subject matter expertise to projects led by other areas of KPMG such as Financial Management, Business Effectiveness, or Operational Strategy.\n\nWe provide a broad range of services to our clients which include:\n\nOrganisation Development - target operating model development, organisation design and workforce shaping\nHR Transformation - creating cost effective, integrated HR functions that contribute to the delivery of business strategy\nTalent development - helping clients identify, retain and develop talent\nBehavioural Change Management - ensuring organisations realise the benefits of large-scale change projects by embedding new behaviours and minimizing underperformance during the change\nCorporate strategy clarification and performance management \u2013 clarify, align and translate the strategy into executable work streams\nFor for details on PCC team, please refer to below link:\nhttps://home.kpmg/cn/en/home/services/advisory/management-consulting/people-change.html\n\nResponsibilities\n\nWe are looking for Manager candidate with specific experience and skills in some of the following categories:\n\nExperience of working for a major advisory business or leading Corporate organization\nExperience helping re-structure HR functions / teams to deliver a more optimized service\nActing as subject matter expert in advising clients to maximize benefits whilst reducing risk\nUsing your knowledge, expertise and experience to support the development People and Change propositions\nResponsibility for standalone deliverables that add significantly to the overall success of the project or workstream\nPassionate about your discipline with a history of continuous learning\nCommercial awareness evidenced by an ability to identify business opportunities\nDrive and resilience to overcome challenges or setbacks\nStrong communicator able to build lasting client relationships\n\nThe responsibilities attributable to this role will include some or all of the following:\n\nManaging a team of KPMG professionals on client engagements and providing leadership and shaping delivery approach\nDevelop appropriate client relationships to enhance the reputation of KPMG as advisor of choice and identify further client opportunities.\nManaging competing agendas/priorities and establish achievable programmes/projects\nTake a significant role in sharing knowledge and supporting the development of other team members.\nAct as a subject matter expert in advising clients to maximise benefits while reducing risks.\nSupport business development initiatives including bid proposal and contract/commercial management.\nBeing passionate about areas of expertise, managing your own development by learning continuously from experience and seeking out development opportunities.\nCoaching team members to ensure excellent client delivery whilst also enabling their career development\n\nThe individual will have:\n\nFull professional proficiency in English, Mandarin and Cantonese\nA good track record of delivering high quality project, or assignment outputs with a focus on delivering measurable business improvements preferably from working for a major advisory business, consultancy or corporate\nPlanning, designing and shaping project work streams, managing progress, resolving issues and limiting risks\nSolid problem solving skills, ability to analyse complex data, identify core issues, investigate, evaluate and reach appropriate conclusions/solutions\nEvidence of managing multiple tasks, priorities, delegating and managing staff\nHigh levels of personal integrity and be a team player with commercial awareness", "employment_types": ["Full Time"], "selling_points": [], "locations": ["Pok Fu Lam"], "categories": ["Professional Services", "Business Consultancy", "Sciences, Lab, R&D", "Research & Development (R&D)", "Others"], "post_time": "2022-01-13T08:45:11Z", "salary": {"currency": null, "max": null, "min": null, "period": "monthly", "term": null}, "salary_visible": false, "title_keywords": ["research assistant"], "responsibilities": ["management", "implementation", "consulting"], "requirements": {"degrees": [], "majors": [], "languages": [], "language_level": [], "hard_skills": [], "soft_skills": ["enthusiastic"], "languages_combined": []}, "experience_required": {"duration": [], "field": []}}, {"job_id": "100003009044858", "location_code": "hk", "company": "KPMG", "job_title": "Manager, People Change Consulting,  Management Consulting", "description": "We are looking for a high calibre professional to join our operation team!\n\nPrimary role purpose:\n\nThe ERP Team is responsible for the Microsoft Dynamics 365 Business Central platform at Fiducia Management Consultants. Business Central is used to run business processes across accounting, corporate and trade services, consulting and recruiting. Our talented team is experienced, collaborative, innovative and lots of fun to work with. Our mission is to enable our clients to get the most out of our applications.\n\nOur ERP-Team is accountable for the strategy, implementation & operation of our ERP technologies and journeys. Working with service managers and clients, they provide customer-centric solutions to evolving processes. Our services are at the heart of how Fiducia Management Consultants run the Finance and Accounting services as well as a critical enabler for the supply chain operations of our clients in Mainland China and APAC.\n\nThis is an exciting time to join our team. We are also about to embark on a major ERP Strategy to further grow our services. This will revolutionise ERP for our clients and internal users. Therefore, we are looking to augment our team of outstanding Functional Consultants who will be pivotal to delivering ambitious solutions within the current platform and contributing to shaping the new-direction ERP. It is a great opportunity to play a major role in this programme and develop the depth & breath of your experience. If you are a proactive and detail-oriented consultant with strong ability to communicate with our clients and have the capability to think both tactically & strategically, we would love to speak to you.\n\nYour focus will be the delivery of End to End Microsoft Dynamics 365 business solutions, that meet the business requirements and add business value. As a Functional Consultant in the ERP-team,\u00a0 you will use your expertise, experience, Dynamics365 skills and business process knowledge to design, develop, integrate, test and deploy solutions to help our business achieve its objectives.\n\nJob Description:\n\nAs a key member of the ERP Team you will ensure the design and realisation of functional solutions are fit for purpose and delivered against stated business requirements. You will collaborate with cross functional teams & business stakeholders to implement and oversee operational excellence in maintaining processes by the service units within Fiducia Management Consultants. Be able to identify & assess available technologies and recommend solution options according to the business requirements & drivers. You are expected to collaborate with clients, team members and service managers to clearly understand business journeys and requirements and how they can be simplified and optimised. You may serve as team member in some projects or Functional Team Lead on others; as such, you will work well in partnership with the team and be equally able to work independently. You will be able to do, teach & evangelise all things in the field of ERP and bring colleagues and stakeholders on the journey to best-of-class solutions.\n\n\n\nYour responsibilities:\n\nAbility to perform the role of Functional Consultant on Microsoft Dynamics365 Business Central, Enhancements and Projects including the facilitation of requirement gathering sessions.\nAbility to drive excellence in the delivery of support in this domain, partnering with our internal team and external partners, including successful knowledge transfer to this team and mentoring of partner colleagues.\nAbility to communicate effectively at all levels within the organisation, our implementation partners and pool of freelancers\nDesign and implement best practice business / Dynamics365 Business Central solutions appropriate to the requirements, business needs and strategic direction of the client and the organization\nManage and own enhancements and incidents through to completion adhering to Fiducia Management Consultants standards.\nTo keep up to date with Microsoft Dynamics 365 Business Central capabilities within the whole solution offering\nDelivery of complex integrated solutions\nPreparation of specifications, estimates and solution documentation to support work completed\nFostering and maintaining good relationships with clients and colleagues to meet expected customer service quality\nMay be required to coach and manage the other members within the team\nManaging third party suppliers and delivery of contracted work\nTaking ownership of continuous improvement within the ERP solution\n\nWho are we looking for:\n\nExperience of multiple, full lifecycle project implementations.\nExcellent experience in Microsoft Dynamics 365 Business Central functional configuration and technical support.\nExtensive experience in designing Dynamics 365 Business Central and integrated solutions.\nDeep knowledge & experience in integrating with other applications.\nA creative and innovative mindset to your work and stakeholders while ensuring the highest quality work delivered on time.\nDesire for self-improvement, results and growth oriented mind together with a strong work ethic.\nCertifications in Microsoft Dynamics 365 Business Central or a related field is a plus\nExcellent communication skills & command of English, preferably also Mandarin\n\nPlease refer to our Company Website:\u00a0http://www.fiducia-china.com. Please submit your full CV with expected salary, plus availability to us. If you do not hear from us within four weeks, you can assume that your application is unsuccessful.", "employment_types": ["Permanent"], "selling_points": ["Organisation Development; HR Transformation;", "Behavioural Change Management; People & Change", "Corporate strategy clarification; HR Consulting"], "locations": ["Aberdeen"], "categories": ["Professional Services", "Business Consultancy"], "post_time": "2022-01-13T06:28:08Z", "salary": {"currency": null, "max": null, "min": null, "period": "monthly", "term": null}, "salary_visible": false, "title_keywords": ["manager"], "responsibilities": ["collaborate with", "consulting", "operations", "microsoft dynamics", "quality", "design", "communication", "business process", "customer service", "deploy", "designing", "maintaining", "configuration", "teams", "implementation", "develop", "company website", "management", "specifications", "documentation", "third party", "communicate with", "technical support"], "requirements": {"degrees": [], "majors": [], "languages": ["english", "mandarin"], "language_level": ["excellent"], "hard_skills": ["plus", "fun", "erp", "documentation", "focus"], "soft_skills": ["communication skills", "work independently", "creative", "responsible", "deep", "accountable", "collaborative", "innovative", "detail-oriented", "team member", "customer service", "organisation", "work ethic", "focus", "proactive", "extensive"], "languages_combined": [{"language": "english", "language_level": ["excellent"]}, {"language": "mandarin", "language_level": ["excellent"]}]}, "experience_required": {"duration": [], "field": ["business", "it", "design", "team"]}}, {"job_id": "100003009048001", "location_code": "hk", "company": "Fiducia Limited", "job_title": "ERP Functional Consultant (China, Hong Kong or Singapore)", "description": "\u5de5\u4f5c\u8077\u8cac\uff1a\u00a0\n\n\u7ba1\u7406\u53ca\u62d3\u5c55\u65b0\u754c\u7269\u696d\uff0c\u5305\u62ec\u7269\u696d\u4f30\u50f9\u3001\u79df\u503c\u5546\u8b70\u3001\u57ce\u5e02\u898f\u5283\u7533\u8acb\u3001\u9805\u76ee\u767c\u5c55\u5206\u6790\u53ca\u53ef\u884c\u6027\u7814\u7a76\u7b49\n\u8655\u7406\u4e00\u822c\u79df\u8cc3\u5305\u62ec\u65b0\u79df/\u7e8c\u79df\u8ac7\u5224\u53ca\u76f8\u95dc\u7ba1\u7406\u3001\u8ddf\u9032\u7269\u696d\u8a34\u8a1f\n\u5206\u6790\u79df\u8cc3\u5e02\u5834\u8da8\u52e2/\u6578\u64da\u7814\u7a76\u4e26\u6e96\u5099\u5b9a\u671f\u79df\u8cc3\u5831\u544a\u3001\u9810\u7b97\u8a08\u5283\u548c\u79df\u91d1\u9810\u6e2c\n\u8655\u7406\u76f8\u95dc\u7684\u7533\u8acb\u6216\u7533\u8a34\u6d41\u7a0b\uff0c\u5305\u62ec\u63db\u5730\u3001\u653f\u5e9c\u8c41\u514d\u7533\u8acb\u3001\u6536\u5730\u88dc\u511f\u7533\u7d22\u7b49\n\n\u9805\u76ee\u7d71\u7c4c\u5b89\u6392\u548c\u5354\u8abf\u6e9d\u901a\uff0c\u8207\u5916\u8058\u7684\u5c08\u696d\u4eba\u58eb\u7dca\u5bc6\u5408\u4f5c\uff0c\u70ba\u516c\u53f8\u5206\u6790\u53ca\u63d0\u4f9b\u6700\u4f73\u7684\u5c08\u696d\u610f\u898b\n\u6839\u64da\u9700\u8981\u57f7\u884c\u5176\u4ed6\u7531\u4e0a\u53f8\u6307\u6d3e\u4e4b\u5de5\u4f5c\n\n\u8077\u4f4d\u8981\u6c42\uff1a\u00a0\n\n\u5927\u5b78\u7a0b\u5ea6\u6216\u4ee5\u4e0a\n\u6b61\u8fce\u5177\u7d93\u9a57\u7684\u5c08\u696d\u6e2c\u91cf\u5e2b\u3001\u898f\u5283\u5e2b\u3001\u4f30\u503c\u5e2b\u61c9\u5fb5\n8\u5e74\u6216\u4ee5\u4e0a\u5de5\u4f5c\u7d93\u9a57\n\u826f\u597d\u4e2d\u82f1\u6587\u6e9d\u901a\u53ca\u66f8\u5beb\u80fd\u529b\uff0c\u61c2\u4e2d\u6587\u96fb\u8166\u8f38\u5165\u6cd5\u8f03\u512a\n\u6301\u6709\u79c1\u5bb6\u8eca\u99d5\u99db\u57f7\u7167\u512a\u5148\n\u719f\u6089\u79df\u8cc3\u6cd5\u4f8b\u3001\u57ce\u5e02\u898f\u5283\uff08\u6cd5\u5b9a\u5716\u5247\uff09\u3001\u571f\u5730\uff08\u5730\u5951\uff09\u53ca\u5efa\u7bc9\uff08\u300a\u5efa\u7bc9\u7269\u689d\u4f8b\u300b\uff09\n\u505a\u4e8b\u9748\u6d3b\u3001\u4e3b\u52d5\u3001\u5b88\u6642\u3001\u6709\u8cac\u4efb\u611f\n\u80fd\u65bc\u5718\u968a\u4e2d\u7368\u7acb\u5de5\u4f5c\uff0c\u5728\u5de5\u4f5c\u4e2d\u5c55\u793a\u5c08\u696d\u6027\u4e26\u56b4\u683c\u4fdd\u5b88\u5de5\u4f5c\u6a5f\u5bc6\n\u826f\u597d\u7684\u7d44\u7e54\u80fd\u529b\n\n\u516c\u53f8\u798f\u5229\uff1a\n\n\u6709\u85aa\u5e74\u5047\n\u9280\u884c\u5047\u671f\n\u4e94\u5929\u5de5\u4f5c\u00a0\n\u751f\u65e5\u5047\n\u91ab\u7642\u9580\u8a3a\u6d25\u8cbc\u798f\u5229\n\u9022\u661f\u671f\u4e94\u8336\u9ede\u4f9b\u61c9\n\u5e74\u7d42\u8868\u73fe\u734e\u91d1\n\n\u00a0*\u6240\u6709\u7533\u8acb\u8005\u8cc7\u6599\u6703\u88ab\u4fdd\u5bc6\u8655\u7406\u4e26\u53ea\u4f5c\u62db\u8058\u7528\u9014*\u00a0\n\n**\u6709\u610f\u8005\u8acb\u63d0\u4f9b\u500b\u4eba\u4e2d\u6587\u5c65\u6b77\u3001\u8981\u6c42\u5f85\u9047\u53ca\u53ef\u4e0a\u73ed\u65e5\u671f\uff0c\u8a3b\u660e\u81f4\u90ed\u5c0f\u59d0**", "employment_types": ["Full Time", "Permanent"], "selling_points": ["ERP strategy, implementation & operation", "Minimum 3 years related experience", "12-mth Salaries +2 Behavioural Goals Bonuses"], "locations": ["Wan Chai"], "categories": ["Accounting", "Consulting", "Professional Services", "Business Consultancy", "Information Technology (IT)", "Product Management / Business Analyst"], "post_time": "2022-01-14T04:28:03Z", "salary": {"currency": null, "max": null, "min": null, "period": "monthly", "term": null}, "salary_visible": false, "title_keywords": ["consultant"], "responsibilities": [], "requirements": {"degrees": [], "majors": [], "languages": [], "language_level": [], "hard_skills": [], "soft_skills": [], "languages_combined": []}, "experience_required": {"duration": [], "field": []}}, {"job_id": "100003009052757", "location_code": "hk", "company": "Yicon Consultants Limited", "job_title": "Deputy General Manager - Property Development (\u526f\u7e3d\u7d93\u7406 - \u7269\u696d\u62d3\u5c55)", "description": "Client Details:\n\nOur client\u00a0is an American multinational manufacturer and marketer of branded consumer foods sold through retail stores, it offers attractive salary and great career progress for potential candidate.\n\nResponsibilities\nAssist in forecasting, annual budgeting\nEnsure effective strategy implementation and monitoring performance\nPerform financial analysis,\u00a0variance analysis, commentary reports, trade specific promotion evaluation on sales performance\u00a0\nConduct feasibility studies to explore more potential business opportunities\nRequirements\n\nDegree in business or finance related fields\n2-3 years working experience in business/financial analysis (FMCG industry is preferable)\nExperience with SAP is an advantage\nStrong critical thinking, excellent analytical skills with good communication skill\nInterested parties, please click \u2018Apply Now\u2019. Feel free to contact Hailey Chan at 3702 3826 for further details.", "employment_types": ["Full Time", "Permanent", "Contract", "Freelance"], "selling_points": [], "locations": ["Not Specified"], "categories": ["Professional Services", "Business Consultancy", "Management", "General Management", "Property / Real Estate", "Property Management"], "post_time": "2022-01-17T03:56:17Z", "salary": {"currency": null, "max": null, "min": null, "period": "monthly", "term": null}, "salary_visible": false, "title_keywords": ["general manager"], "responsibilities": ["annual budgeting", "sales performance", "business opportunities", "monitoring", "implementation", "financial analysis", "variance analysis", "reports", "evaluation", "forecasting"], "requirements": {"degrees": ["degree"], "majors": ["finance", "business"], "languages": [], "language_level": [], "hard_skills": ["financial analysis", "fmcg industry", "sap", "analytical skills"], "soft_skills": ["communication skill", "analytical skills"], "languages_combined": []}, "experience_required": {"duration": ["2-3 years"], "field": ["fmcg", "business", "financial"]}}, {"job_id": "100003009048193", "location_code": "hk", "company": "Vistra (Hong Kong) Limited", "job_title": "Director, Governance and Compliance (Company Formations)", "description": "Our client is a global top tier management consulting firm.They are currently looking for an experienced candidate to join as Director/Partner for their strategy team across APAC.\n\nJob Scope\n\nAct as a business advisory and lead the Strategy consulting team\nDeveloped customer strategy at procedure level\nOrganized and delivered internal consulting training\nSupport cross functional business partners with analytical insights and problem solving\nBuild cross functional partnerships and consensus\nAlign processes, resources-planning and functional goals with overall strategy\nMonitor and analyses industry trends and market changes\n\nRequirements\n\nBachelor degree and above\n10 years management consulting firm or in-house related working experience\nRetail, digital and omni-channel projects equivalent professional experience\nProjects experience in retail company (Beauty, Cosmetics, Sport Ware and Luxury) is preferred\nExcellent command of English and Chinese\nExcellent leadership and track records in project management , process improvement\nImmediate available is highly preferable", "employment_types": ["Full Time", "Permanent"], "selling_points": ["Senior Compliance role for Company Formation team", "Act as MLRO for the CF business", "Exposure in various jurisdictions required"], "locations": ["Causeway Bay"], "categories": ["Professional Services", "Business Consultancy", "Legal & Compliance", "Banking / Finance", "Risk Management"], "post_time": "2022-01-14T05:49:19Z", "salary": {"currency": null, "max": null, "min": null, "period": "monthly", "term": null}, "salary_visible": false, "title_keywords": ["director"], "responsibilities": ["management", "consulting", "monitor", "project management", "team across", "planning"], "requirements": {"degrees": ["degree", "bachelor"], "majors": [], "languages": ["english", "chinese"], "language_level": ["excellent"], "hard_skills": ["problem solving", "project management"], "soft_skills": ["problem solving", "organized", "project management", "leadership"], "languages_combined": [{"language": "english", "language_level": ["excellent"]}, {"language": "chinese", "language_level": ["excellent"]}]}, "experience_required": {"duration": ["10 years"], "field": ["management", "consulting", "related", "beauty", "digital", "retail"]}}, {"job_id": "100003009042332", "location_code": "hk", "company": "Links International", "job_title": "Strategy Director  /Partner (Leading Consulting Firm  )", "description": "Role\n\nAssociate Director, Human Rights, Sustainability Consulting, Asia\n\n\u00a0Location\n\nSingapore or Hong Kong\n\n\u00a0Who we are\n\nAt ELEVATE, we offer a unique and impactful career journey designed to empower our teams to influence change on people, planet, and community. Join our team for a truly international experience. With 24+ offices globally (and still growing), you will have exposure to real issues that span the globe. Fasten your seatbelt for an energetic and dynamic experience where you will partner with world class leaders on solving some of the planet\u2019s most imminent issues (climate change, human rights, sustainability, and more!) in new and innovative ways that achieve our goals together!\n\nJob overview at a glance\n\nELEVATE is looking for a senior and experienced professional to lead its human rights portfolio in the Asia sustainability consulting practice. The Associate Director, Human Rights, Asia will oversee our human rights advisory services in Asia and play a key role in the evolution and scaling of our transformative products by building consistency in quality and delivery across at a regional level.\u00a0This is an exceptional opportunity for a creative and entrepreneurial individual who is passionate about quality, high performing teams and the design / implementation of high-impact solutions.\n\n\u00a0Who you are\n\nAre you a dynamic, innovative and driven individual that wants to work:\n\nOn social / human rights issues and their interface environmental and governance challenges\nWith an amazing team of like-minded creative thinkers\nIn a fast-paced dynamic and high impact environment\nWith some of the biggest and most forward-looking brands in the world\n\n\u00a0Responsibilities\n\nContribute to the development of ELEVATE\u2019s human rights advisory and due diligence services together with the One Consulting process and global Product Working Group including:\nStrategy development, regional market evaluation, conceptualization and planning\nInternal and external engagement with key expert stakeholders and customers\nAlignment with external legal and regulatory drivers both regional as well as in U.S. and Europe\nAlign with internal leaders on products development, training, and scalable roll-out\nPrototyping, testing and refinement in the field to enable delivery efficiencies and enhancements\nAlignment with internal platforms such as EiQ and our supply chain program effectiveness vision\nLeading relevant Knowledge Hubs, learning platforms and internal capacity building\nInform and implement our global advisory strategy in alignment with ELEVATE objectives\nLead ELEVATE\u2019s Human Rights services in Asia and coordinate project teams including:\nOversight of human rights oriented grant-funded development projects in the Asia region\nLead local human rights advisory and in-country Asia investigation and remediation projects\nBuilding an engaged team culture based on collaboration, development and innovation\nEnsure consistent use of tools, templates, ways of working and scalable solutions\nEstablish a working environment that enables quality, learning and personal development\nActively support the business development process and pipeline for human rights services\nDevelop a regional client base\u00a0and relationships with senior industry executives and leaders\nIndustry level thought leadership including blogs, engagement at external events etc.\n\n\u00a0Qualifications\n\n7\u201310 years of experience in a relevant field\nMaster\u2019s Degree in a relevant discipline\nProven consulting, business development, client management, and team leadership experience\nHas and applies emotional intelligence and manages conflict for members in own organization\nProven team player with communication, networking and stakeholder engagement skills\nBudget management (revenue and pipeline), preferred\nBusiness development experience and comfort working to ambitious growth targets\n\n\u00a0Equal Opportunity Employer\n\nELEVATE is committed to creating a diverse and inclusive workplace and is proud to be an Equal Opportunity Employer. All qualified applicants will be considered without regard to race, color, religion, gender, gender identity, sexual orientation, national origin, genetics, disability, age, veteran status, or any other status protected by local law. Personal data provided by applicants will be treated as confidential information and will be used exclusively for employment purposes only. Only short-listed candidates will be notified. Applicants who are not invited for an interview may consider their applications filed for future reference.\n\nTo learn more about career opportunities at ELEVATE, please visit our Careers Page here:\u00a0https://www.elevatelimited.com/careers/", "employment_types": ["Full Time", "Permanent"], "selling_points": ["Experience in Retail /FMCG Industry", "Omni-channel experience", "Big 4 Strategy Consulting candiate welcome"], "locations": ["Not Specified"], "categories": ["Professional Services", "Business Consultancy"], "post_time": "2022-01-12T07:05:38Z", "salary": {"currency": null, "max": null, "min": null, "period": "monthly", "term": null}, "salary_visible": false, "title_keywords": ["director"], "responsibilities": [], "requirements": {"degrees": [], "majors": [], "languages": [], "language_level": [], "hard_skills": [], "soft_skills": [], "languages_combined": []}, "experience_required": {"duration": [], "field": []}}, {"job_id": "100003009044928", "location_code": "hk", "company": "ELEVATE Hong Kong Holdings Limited", "job_title": "Associate Director, Human Rights, Sustainability Consulting, Asia - Hong Kong", "description": "Responsibilities:\n\nTo handle trademark and patent application, renewal, and other related matters\nTo manage IP portfolio for client\nTo communicate with clients and foreign agents\nTo maintain up-to-date records\nTo provide legal support to supervisor\n\n\u00a0Requirements:\n\nHigher Diploma holder in Law\n3 years\u2019 or above working experience in legal field (preferably in intellectual property aspect)\nStrong communication skills with good commercial sense and team-work spirit\nResponsible, self-motivated, detail-oriented and well-organized\nProficient in MS Office including Word, Excel and Chinese WP\nGood command of written and spoken English, Cantonese and Mandarin\nImmediate available is highly preferred\n\n\n\nInterested parties please state your employment history, present and expected salary on your resume.\n\nWe are an equal opportunity employer and welcome applications from all qualified candidates. All personal information provided will be treated in strict confidence and used solely for recruitment purpose. It is possible that information about the applicant or the applicant\u2019s application will be shared within the Conpak Group.\n\nApplicants not hearing from us within 6 weeks from the date of advertisement may consider applications unsuccessful. Personal data of an unsuccessful applicant will normally be kept for a period of 2 years.", "employment_types": ["Full Time"], "selling_points": ["interface environmental and governance challenges", "With an amazing team of like-minded creative think", "In a fast-paced dynamic & high impact environment"], "locations": ["Quarry Bay"], "categories": ["Professional Services", "Business Analysis / Data Analysis", "Business Consultancy", "Sales, CS & Business Devpt", "Business Development"], "post_time": "2022-01-13T06:40:08Z", "salary": {"currency": null, "max": null, "min": null, "period": "monthly", "term": null}, "salary_visible": false, "title_keywords": ["associate director"], "responsibilities": ["communicate with", "maintain"], "requirements": {"degrees": ["higher diploma holder"], "majors": ["law"], "languages": ["cantonese", "english", "chinese", "mandarin"], "language_level": ["good command", "proficient"], "hard_skills": ["excel", "chinese wp", "word", "ms office"], "soft_skills": ["communication skills", "self-motivated", "responsible", "well-organized", "detail-oriented"], "languages_combined": [{"language": "cantonese", "language_level": ["good command"]}, {"language": "english", "language_level": ["good command"]}, {"language": "chinese", "language_level": ["proficient"]}, {"language": "mandarin", "language_level": ["good command"]}]}, "experience_required": {"duration": ["3 years"], "field": ["legal"]}}, {"job_id": "100003009049935", "location_code": "hk", "company": "Conpak CPA Limited", "job_title": "Intellectual Property Senior Associate", "description": "KPMG is one of the most trusted and respected global professional services firms. Through depth of expertise, clarity of insight and strength of purpose we help our clients solve complex challenges, steer change, strengthen, transition and grow. We are looking for talented people who share our purpose of inspiring confidence and empowering change for our clients, our people and our communities.\n\nOur Hong Kong office is looking for a Senior Consultant / Consultant to join our Procurement & Supply Chain Technology Enablement Consulting Practice and help our clients transform their Procurement organization through technology, organization redesign and process re-engineering.\n\nResponsibilities:\n\nProvide industry specific procurement and supply chain transformation, digitization advisory services.\nCommunicate with senior management and client personnel\nEffectively manage multiple tasks independently\nAssist in developing proposals\nWork with/supervise staff on assigned engagements\nMaintain up-to-date knowledge of latest developments and methods in procurement and supply chain management, both locally and internationally\n\nWhat you should bring to the role:\n\nBachelor\u2019s degree (or above), in supply chain management, business management, engineering or business analysis background. Master\u2019s degree in related subjects is preferred\nProcurement, supply chain knowledge and project management experience\nA minimum of 2 years\u2019 experience in supply chain or procurement management, or 2 years\u2019 experience in consulting with demonstrable experience of the following:\nmaturity assessment of supply chain organizations/ departments\ncost optimization for direct and indirect spend across diverse industries\nsetting up international procurement offices\nanalysis and improvement sourcing, procurement and supply chain planning processes\ncost reduction in supply chains\nimplementation of procurement or supply chain planning solutions (e.g. Coupa, Ivalua, Ariba, O9, SAP IBP, Blue Yonder, Llamasoft etc)\nIndustry experience should include manufacturing, FMCG, retail or Life Science\nHave a flexible, creative and innovative approach to problem solving and possess strong communication and writing skill\nQualification such as CPIM, CSCP is a plus\nFluent in both written and oral English, Cantonese and Mandarin", "employment_types": ["Full Time"], "selling_points": ["Higher Diploma holder in Law", "3 years\u2019 or above working experience in legal fi", "Immediate available is highly preferred"], "locations": ["Tsim Sha Tsui"], "categories": ["Professional Services", "Business Consultancy", "Company Secretary", "Legal & Compliance"], "post_time": "2022-01-14T09:27:47Z", "salary": {"currency": null, "max": null, "min": null, "period": "monthly", "term": null}, "salary_visible": false, "title_keywords": ["senior associate"], "responsibilities": ["communicate with", "management", "cost", "cost optimization", "consulting", "analysis", "developing", "implementation", "communication", "project management", "maintain", "business analysis", "senior management", "re-engineering", "planning"], "requirements": {"degrees": ["degree", "bachelor", "master"], "majors": ["business", "engineering"], "languages": ["cantonese", "english", "mandarin"], "language_level": ["fluent"], "hard_skills": ["business management", "plus", "sap", "analysis", "writing skill", "problem solving", "project management"], "soft_skills": ["flexible", "oral", "independently", "confidence", "multiple tasks", "innovative", "problem solving", "project management", "diverse", "communication", "writing skill", "inspiring", "creative"], "languages_combined": [{"language": "cantonese", "language_level": ["fluent"]}, {"language": "english", "language_level": ["fluent"]}, {"language": "mandarin", "language_level": ["fluent"]}]}, "experience_required": {"duration": ["2 years", "minimum of 2 years"], "field": ["management", "manufacturing", "fmcg", "consulting", "supply chain", "project management", "retail", "procurement"]}}, {"job_id": "100003009047878", "location_code": "hk", "company": "KPMG", "job_title": "Senior Consultant / Consultant \u2013 Procurement & Supply Chain, Technology Consulting", "description": "\nPerun Consultants is the leading independent advisory firm with offices in Hong Kong and Singapore. We specialise in provision of high quality services in the areas of forensic accounting, corporate advisory, restructuring, turnaround and liquidation appointments. At Perun, we promote a work-life balance, value individualism and embrace the differences.\n\nWe are currently seeking an ambitious and qualified candidate with the following attributes to join our Hong Kong office as a Forensic Accounting Manager / Assistant Manager / Associate:\n\n\nBatchelor\u2019s degree in Accounting, Finance, Computer Science, Information Technology, Law or other Business-related discipline preferred.\nCA, CPA, ACCA or equivalent. Consideration will also be given to part qualified candidates, with support given to complete the qualification process;\n4+ years relevant experience for the position of Assistant Manager and 2+ years relevant experience for the position of Associate.\n\u2022 Eager to learn and motivated to succeed;\n\u2022 Proficient in detailed financial and commercial analysis and be able to identify potential areas of sensitivity;\n\u2022 Self-motivated, proactive and mature;\n\u2022 Proficient in Microsoft office applications;\n\u2022 Strong financial, business analytical and report writing skills; and\n\u2022 Excellent written and oral communication skills in both English and Mandarin Chinese, including both technical and business writing.\nThe successful candidate will possess technical knowledge of financial accounting practices and be able to demonstrate experience (commensurate with the applicable employment grade) with the following:\n\nAssessment and quantification of losses and potential damage awards;\nValuation and appraisal of assets;\nDesign and evaluation of financial forecast models;\nReport writing;\nProviding litigation support services, working closely with legal counsel, law enforcement officers and regulatory agencies; and\nAssisting with internal and external investigations.\nInsolvency-related experience; and\nAssisting with internal and external investigations.\n\nIn addition to the above role, we are always interested in hearing from proactive, commercially minded, individuals at all levels of seniority and experience looking to work in a dynamic and flexible environment.\n\nWe offer a competitive remuneration package where you will be rewarded for your individual and team performance. We are committed to being an inclusive employer and are happy to consider flexible working arrangements.\nTo apply, contact us at Apply Now .", "employment_types": ["Full Time"], "selling_points": ["Procurement; Supply Chain; Technology Enablement", "process re-engineering; digitization; FMCG; retail", "project management; cost reduction; Life Science"], "locations": ["Aberdeen"], "categories": ["Professional Services", "Business Consultancy"], "post_time": "2022-01-14T04:07:02Z", "salary": {"currency": null, "max": null, "min": null, "period": "monthly", "term": null}, "salary_visible": false, "title_keywords": ["senior consultant", "consultant"], "responsibilities": ["valuation", "analysis", "support services", "quality", "design", "communication", "forecast", "evaluation", "report"], "requirements": {"degrees": ["degree"], "majors": ["law", "finance", "information technology", "business", "computer science", "accounting"], "languages": ["mandarin chinese", "english"], "language_level": ["excellent"], "hard_skills": ["acca", "microsoft office", "analysis", "writing skills", "cpa", "dynamic"], "soft_skills": ["flexible", "communication skills", "self-motivated", "oral", "independent", "sensitivity", "interested in", "mature", "writing skills", "eager to learn", "motivated", "dynamic", "proactive", "detailed"], "languages_combined": [{"language": "mandarin chinese", "language_level": ["excellent"]}, {"language": "english", "language_level": ["excellent"]}]}, "experience_required": {"duration": ["2+ years", "4+ years"], "field": ["related", "accounting", "relevant experience", "financial"]}}, {"job_id": "100003009043466", "location_code": "hk", "company": "CHAN HIU MAN CPA & Co", "job_title": "Audit associate : Associate I / Semi Senior to Senior Post   ( FRESH  graduate )", "description": "There exists an exciting opportunity for a senior Compliance role for our Company Formations business to be based in Hong Kong.\u00a0 The incumbent will be partnering with our high volume CF business globally and would require someone to have process improvement and some aspects of transformation experience within a Compliance setting.\u00a0\n\nResponsibilities\n\nDevelop, implement, monitor and maintain a comprehensive and cost-effective global Company Formations (\u201cCF\u201d) compliance strategy\nEstablish a standardized approach to AML/CFT to encompass the compliance and governance standards of Vistra\u2019s CF jurisdictions\nImplement Group Compliance and other relevant Group functional policies across the CF business as may be relevant\nCollaborate with technology business partners and the business to ensure consistency with CF compliance strategy\nAct as money laundering reporting officer (MLRO) for Vistra\u2019s Hong Kong CF business\nEnsure maintenance by local offices of CF relevant compliance manuals, seeking to harmonize these across regions as far as possible\nResponsible for building compliance procedures into Vistra\u2019s CF operating systems\nLead the review of existing, and development of new, compliance forms and processes that can be applied across regions\u00a0\nCreate and disseminate / present reports to different stakeholders including employees, senior management and board members,\u00a0championing a culture of compliance and ethics across the CF business\nCollaborate with business partners and the business to ensure consistency with CF compliance strategy\nChampioning a culture of compliance and ethics across the CF business\nRequirements\n\nDegree in Business Administration, Law, Risk Management, Compliance or related discipline with proven multi-jurisdictional experience\nWith at least 10 \u2013 15 years of relevant compliance experience for a high-volume business and with broad exposure to various work areas\u00a0 including commercial, compliance strategy, management and legal (regulatory advisory)\nStrong influencing skills with the ability to build persuasive cases based on fact and through the strength of leadership ensure that all relevant stakeholders buy into the CF Compliance strategy\nConsultancy skills in order to be a trusted adviser to the business on regulatory and compliance related issues\nKnowledge of or demonstrated ability to interpret and remain abreast of compliance and governance standards for key offshore company formation jurisdictions in which Vistra operates\nCollaborative, strong team-player with demonstrable experience in working within a dynamic organisation and able to build bridges between the different stakeholders within the organisation, division and locations\nExercise due skill, care and diligence, observe proper standards of compliance conduct and deal with any relevant stakeholders in an open and co-operative way\nExcellent verbal and written communication skills, as well as presentation skills\nAbility to work under minimal supervision and manage multiple tasks/projects simultaneously, while meeting demanding deadlines\nSubstantial experience in a compliance leadership role, assessing and articulating legal and regulatory requirements for regulated business environments.\nExperience implementing, maintaining, and managing regulatory requirements of multiple jurisdictions an advantage\nAll personal information collected will be used for recruitment purpose only.", "employment_types": ["Full Time"], "selling_points": ["Associate  Degree/ Degree /Fresh graduate: junior", "Independent", "13 month salary/ 5 DAYS/ reasonable workload"], "locations": ["Tsim Sha Tsui"], "categories": ["Accounting", "Audit", "Professional Services", "Business Analysis / Data Analysis", "Business Consultancy"], "post_time": "2022-01-12T12:55:08Z", "salary": {"currency": null, "max": null, "min": null, "period": "monthly", "term": null}, "salary_visible": false, "title_keywords": ["associate"], "responsibilities": ["collaborate with", "reporting", "cost", "aml", "maintenance", "policies", "compliance", "monitor", "procedures", "review", "develop", "maintain", "reports", "senior management", "operating systems"], "requirements": {"degrees": ["degree"], "majors": ["risk management", "business administration", "law"], "languages": [], "language_level": [], "hard_skills": ["dynamic"], "soft_skills": ["communication skills", "persuasive", "multiple tasks", "team-player", "collaborative", "presentation skills", "dynamic", "organisation", "leadership"], "languages_combined": []}, "experience_required": {"duration": ["15 years"], "field": ["risk management", "management", "business administration", "legal", "related", "compliance", "commercial", "business", "team"]}}, {"job_id": "100003009046629", "location_code": "hk", "company": "Betterment Asia Limited", "job_title": "HR Executive, Generalist - US Luxury Retail Group (Contract Role)", "description": "In a world of disruption and increasingly complex business challenges, our professionals bring truth into focus with the Kroll Lens. Our sharp analytical skills, paired with the latest technology, allow us to give our clients clarity\u2014not just answers\u2014in all areas of business.\n\nWe embrace diverse backgrounds and global perspectives, and we cultivate diversity by respecting, including, and valuing one another. As part of One team, One Kroll, you\u2019ll contribute to a supportive and collaborative work environment that empowers you to excel.\n\nKroll Restructuring practice aims to provide effective solutions to its clients. Our clients include major banks, asset based lenders, private equity houses, accountants, solicitors, financial sponsors, lenders, creditors, corporates and individuals. We are tasked with assuming direct responsibility for organisations in distressed situations across virtually every industry and every situation.\n\nWe are currently seeking an individual to join our team as a Finance Administrator in Hong Kong. You will be involved in cand ensuring that all finance records are recorded and filed. The individual will also provide reports to the wider team when required.\n\nAt Kroll, your work will help deliver clarity to our clients\u2019 most complex governance, risk, and transparency challenges. Apply now to join One team, One Kroll.\n\nResponsibilities:\n\nPreparing forms and coordinating with banks, appointed liquidators to setup liquidation of bankruptcy bank accounts\nStatutory annual reviews such as KYC updates and US Tax declaration\nApplication and online banking access maintenance and closure of bank accounts upon discharge\nMaintenance of bank account list and ensuring accounts are active and required\nProcess payment requests from the corresponding bank accounts and ensuring proper approval has been received\nMonitoring of receipts in bank accounts\nFollowing up on instructions after payables or receivables\nRecording and filing all payable and receivable transactions and records in Accounting system\nPerforming monthly reconciliation of all accounts\nProvide reporting to the team for receivables, payables for particular client or supplier accounts\n\nRequirements:\n\nMinimum Diploma in Accounting\nMinimum 2 years of working experience in a bookkeeping/accounting role\nFamiliarity with Microsoft Money and IPS an added advantage but not a prerequisite\nProficiency in Microsoft Word, Excel, Powerpoint Outlook.\nStrong analytical skills and attention to detail\nCritical thinking, proactive and problem-solving oriented mind-set\nProficiency in English and Chinese\n\nIn order to be considered for a position, you must formally apply via careers.kroll.com.\n\nKroll is committed to equal opportunity and diversity, and recruits people based on merit.", "employment_types": ["Full Time"], "selling_points": ["US listed Luxury Retail Group", "20-25k", "Chance to renew"], "locations": ["Not Specified"], "categories": ["Professional Services", "Business Consultancy", "Admin & HR", "HR Director / Manager", "Recruitment / Executive Search"], "post_time": "2022-01-13T17:38:15Z", "salary": {"currency": "HKD", "max": 29999, "min": 20000, "period": "monthly", "term": null}, "salary_visible": true, "title_keywords": ["hr", "executive"], "responsibilities": ["tax", "reporting", "receipts", "maintenance", "kyc", "monitoring", "transactions", "payment", "banking", "setup"], "requirements": {"degrees": ["diploma"], "majors": ["accounting"], "languages": ["english", "chinese"], "language_level": ["proficiency"], "hard_skills": ["excel", "microsoft word", "problem-solving", "powerpoint", "analytical skills", "outlook"], "soft_skills": ["problem-solving", "analytical skills", "committed", "attention to detail", "proactive"], "languages_combined": [{"language": "english", "language_level": ["proficiency"]}, {"language": "chinese", "language_level": ["proficiency"]}]}, "experience_required": {"duration": ["minimum 2 years"], "field": ["accounting"]}}, {"job_id": "100003009044013", "location_code": "hk", "company": "D&P China (HK) Limited", "job_title": "Finance Administrator, Hong Kong", "description": "About the Company:\nKPay (kpay-group.com) is a leading digital payment gateway company founded in 2020 by a team of serial entrepreneurs who have successful exited their previous ventures. We currently have a hundred-person team based in Hong Kong. We have aggressive plans to expand across Asia next year and are looking to build out the strategy and investments team, which reports directly to the founders.\n\nOur culture is nimble, entrepreneurial, and fun.\n\nJob Duties:\n\u2022 Conduct company, industry, market, and economic research and monitoring\n\u2022 Financial modelling and analysis\n\u2022 Develop presentation materials in both English and Chinese\n\nJob Requirements :\n\u2022 Relevant work experience (under 5 years) in financial services (PE/VC/hedge funds), investment banking, strategy / management consulting, accounting, digital assets (crypto), or internet start-ups (in particular, fintech involved with payments and/or lending), big data\n\u2022 Excellent communication and interpersonal skills\n\u2022 Excellent written and spoken English and Chinese\n\u2022 Proficiency in MS Word, Excel, PowerPoint, and Chinese word processing\n\u2022 Ability to interact and build relationships with senior management\n\n", "employment_types": ["Full Time", "Permanent"], "selling_points": ["Min. 2 years of exp. in Bookkeeping/Accounting", "Minimum Diploma in Accounting", "Global organisation with development opportunties"], "locations": ["Admiralty"], "categories": ["Accounting", "Accountant", "Accounting Clerk / Supervisor", "Professional Services", "Business Consultancy"], "post_time": "2022-01-13T02:46:35Z", "salary": {"currency": null, "max": null, "min": null, "period": "monthly", "term": null}, "salary_visible": false, "title_keywords": ["administrator"], "responsibilities": ["analysis", "monitoring", "develop"], "requirements": {"degrees": [], "majors": [], "languages": ["english", "chinese"], "language_level": ["excellent", "proficiency"], "hard_skills": ["excel", "crypto", "vc", "chinese word processing", "powerpoint", "pe", "ms word"], "soft_skills": ["communication and interpersonal skills"], "languages_combined": [{"language": "english", "language_level": ["excellent"]}, {"language": "chinese", "language_level": ["excellent", "proficiency"]}]}, "experience_required": {"duration": ["5 years"], "field": ["management", "consulting", "financial services", "investment", "banking", "digital", "accounting"]}}, {"job_id": "100003009044270", "location_code": "hk", "company": "KPay Merchant Service Limited", "job_title": "Business Strategy Manager (Fintech/Digital Payment/SaaS)", "description": "Job responsibilities\nTimely review the external rating of the collateral submitted for financing business application; evaluate its rationality and provide opinions on the collateral valuation\nPrepare relevant statistics and analysis for the collateral valuation\nRegularly consolidate the practice status of the intermediaries and the external regulatory information, and make a reasonable evaluation of the annual cooperation\nReview and compare the transaction prices of similar properties in local market and determine whether the value of the collateral is reasonable, in line with the actual market conditions and acceptable to the Bank\nCommunicate with relationship manager for the collateral loan application issues and provide further clarification if needed\nKeep track on those credit issues that need to be followed up, conduct interim review of accounts that required extra caution\nPerform other duties delegated by Section Head\nRequirements\nBachelor degree or above in real estate, assets valuation or economics related majors\nProfessional qualification of Certified Public Valuer, Chartered Surveyor (General Practice), Chartered Surveyor (Valuation)\nOver 5 years of experience in assets valuation with in-depth knowledge of real estate valuation industry\nExperience in financial industry is preferred\nFamiliar with real estate market conditions in Hong Kong and Mainland, as well as banking law and practical\nPossess in-depth knowledge of assets valuation and real estate market transactions\nGood analytical and report writing skills with logical credit judgment\nSelf-motivated and able to work independently & under pressure with limited time constraints\nGood problem solving ability and tactful inter-personal & communication skills\nGood knowledge in PC operation\nGood command of written & spoken English and Chinese", "employment_types": ["Full Time", "Permanent"], "selling_points": ["Fast growing fintech firm", "Newly establish team", "Great employment package"], "locations": ["Kwun Tong"], "categories": ["Banking / Finance", "Analyst", "Professional Services", "Business Analysis / Data Analysis", "Business Consultancy"], "post_time": "2022-01-13T03:36:42Z", "salary": {"currency": null, "max": null, "min": null, "period": "monthly", "term": null}, "salary_visible": false, "title_keywords": ["manager"], "responsibilities": ["communicate with", "valuation", "perform other duties", "credit issues", "analysis", "review", "clarification", "evaluate", "evaluation"], "requirements": {"degrees": ["degree or above", "bachelor"], "majors": ["economics"], "languages": ["english", "chinese"], "language_level": ["good command"], "hard_skills": ["problem solving", "pc", "writing skills"], "soft_skills": ["communication skills", "self-motivated", "work independently", "under pressure", "inter-personal", "writing skills", "problem solving", "tactful"], "languages_combined": [{"language": "english", "language_level": ["good command"]}, {"language": "chinese", "language_level": ["good command"]}]}, "experience_required": {"duration": ["5 years"], "field": ["financial industry"]}}, {"job_id": "100003009042886", "location_code": "hk", "company": "Industrial and Commercial Bank of China (Asia) Limited", "job_title": "Deputy Manager to Senior Manager, Collateral Valuation (Ref: CAD-BMS-537)", "description": "\nEY Asia-Pacific Tax Center (APTC) serves high-profile, multinational clients, providing a range of domestic and cross border tax services.\n\nThe opportunity\n\nOur Tax Accounting Risk Advisory Services (TARAS) practice operates within APTC, focus on helping clients effectively manage local statutory income tax reporting, bookkeeping and tax compliance obligations proactively and responsibly of our client\u2019s operations. TARAS professionals focus on details of income tax accounting, processes and internal controls over tax accounting and reporting. With engagements involving a few countries or many, you will have the opportunity to provide clients an integrated, consistent, quality service that unlocks the potential of the tax function across the entire record-to-report process.\n\nYour Key Responsibilities\n\nAs a Manager/Senior Manager in the services, you will spend your time transforming EY client\u2019s business. You will work with a variety of teams to understand their income tax processes and identify process and technology improvement opportunities across the record-to-report process. You may utilize a variety of tools and techniques to document current state and identify future state processes. You may design and configure automation tools, such as robotic process automation, data integration and workflow.\n\nFor key clients you will also help manage implementation of centrally managed global outsourcing/sourcing models that provide clients with greater control and visibility over global tax accounting compliance and reporting activities, access to global team members with finance expertise, and development of new operating models to address new markets. You will serve on audits of key clients including those requiring: HKAS 12, IAS 12 and US GAAP ASC 740 tax reporting requirements.\n\nSkills/Experience:\n\nFoundational accounting background including income tax accounting. Individuals from Assurance background in Financial Services strongly preferred.\nExperience in providing assurance services to listed clients including income tax accounts\nIdentify ways to automate manual tasks using existing financial or tax systems and emerging technologies\nExhibit competency in technology by maintaining complex sets of data, reviewing data analytics and analyzing trends including the collection of data as per agreed financial statement close timelines and other requirements\nExhibit critical thinking across EY methodologies/tools to enhance service delivery, challenge current procedures to find new approaches\nStrong spirit of entrepreneurship with colleagues and clients\nOpenness to collaborate with individuals from different backgrounds in an international environment\nFunction as Project Manager, team motivator, and oversee process guidance of workflow development\nTake ownership of tasks and make decisions and resolve issues including the escalation of client and internal partner issues while having a strong ability to work under pressure and strict deadlines\nAbility to think strategically to client centric solutions across: ESG reporting, Transactions, tax accounting process improvement, internal tax controls\nManaging, coaching and developing a team of staff and seniors, expectations to serve as counselors to junior resources\nBuild client relationships and demonstrate knowledge of client businesses\nScoping of new opportunities: develop proposals and participate in oral presentations provide high-quality services/work products build relationships with clients, understanding their unique needs to provide a tailored service\nTo qualify for the role you must have:\n\nA Bachelor's in Accounting or related field and a minimum of 7 years of related work experience\nStrong desire grow within EY as a TARAS specialist, team builder and client relationship management\nCertified Public Accountant or related designation being pursued\nAbility to lead a team, mentor counselees and manage client-serving business\nStrong organizational and time management skills, with exceptional client-serving consulting skills\nDemonstrated ability to capture and synthesize business requirements and entrepreneurship to operate in a new market and operate at a higher level\nWillingness to travel, expectations of 15%+ across APAC post Covid restrictions lifted\nIdeally, you\u2019ll also have\n\nBusiness Analyst background/experience\nExperience implementing robotic process automation\nMicrosoft Excel VBA development\nMicrosoft Power BI suite, including Power Pivot, Power Query, Power View and Power Map\nKnowledge and experience in the design and development of databases (specifically SQL Server)\nAlteryx\nERP experience, including SAP and/or Oracle\nWhat We Look For\n\nWe\u2019re interested in professionals who enjoy promoting the people agenda in organizations and change initiatives, bringing people issues and challenges to the forefront. You\u2019ll need the confidence to keep the people agenda front and centre, and the interpersonal skills and communications savvy to do this in a way that integrates well with executive priorities and objectives.\n\nWhat Working At EY Offers\n\nWe offer a competitive compensation package where you\u2019ll be rewarded based on your performance and recognized for the value you bring to services. In addition, our Total Rewards package includes medical and hospitalization benefits, group life and personal accident insurance, annual leave and Mandatory Provident Fund and a range of programs and benefits designed to support your physical and social well-being. Plus, we offer:\n\nSupport, coaching and feedback from some of the most engaging colleagues around\nOpportunities to develop new skills and progress your career\nThe freedom and flexibility to handle your role in a way that\u2019s right for you\nJoin us in building a better working world.\n\nApply now.", "employment_types": ["Permanent"], "selling_points": [], "locations": ["Central"], "categories": ["Banking / Finance", "Corporate Banking", "Credit Analysis / Approval", "Professional Services", "Business Consultancy"], "post_time": "2022-01-12T09:07:15Z", "salary": {"currency": null, "max": null, "min": null, "period": "monthly", "term": null}, "salary_visible": false, "title_keywords": ["senior manager", "deputy manager"], "responsibilities": ["collaborate with", "consulting", "data", "operations", "quality", "design", "transactions", "financial statement", "work under pressure", "service delivery", "control", "maintaining", "compliance", "teams", "implementation", "developing", "develop", "presentations", "report", "reporting", "guidance", "management", "procedures", "audits", "tax", "power bi", "systems", "lead a team", "databases"], "requirements": {"degrees": ["bachelor"], "majors": ["accounting"], "languages": [], "language_level": [], "hard_skills": ["vba", "server", "bi", "sap", "data analytics", "presentations", "microsoft excel", "sql", "make", "erp", "databases", "alteryx", "integration", "focus", "oracle"], "soft_skills": ["oral", "confidence", "time management skills", "organizational", "interested in", "unique", "interpersonal skills", "think strategically", "focus", "work under pressure"], "languages_combined": []}, "experience_required": {"duration": ["minimum of 7 years"], "field": ["assurance", "related", "development", "design", "sql", "business", "accounting"]}}, {"job_id": "100003008948269", "location_code": "hk", "company": "EY", "job_title": "Asia Pacific Tax Centre - Tax Accounting Risk Advisory Services - Manager/Senior Manager - Hong Kong", "description": "Responsibilities:\n\n\n\nProvide leadership and promote business ties with clients across key businesses and support functions;\nLead execution team for business valuations, intangible asset valuations, financial asset valuations and purchase price allocations etc;\nTake responsibility for delivery and fulfilment of projects;\nWork with management to develop business development plans and follow up with the execution;\nProvide advisory services to businesses and follow up with clients proactively;\nMaintain in-house research database;\u00a0\nWork on ad-hoc reports and presentations.\n\n\u00a0Requirements:\n\nDegree holder with major in Accounting, Finance, Financial Engineering or other related disciplines;\nHolder of professional qualifications such as CPA and CFA, etc;\nAt least 5 years relevant experience;\nStrong analytical, strategic and commercial experience;\nStrong communicator with the presentation skills to build strong and lasting client relationships;\nAble to work independently and under pressure;\nProficiency in Microsoft Word, Excel and PowerPoint;\nFluent in written and spoken English and Chinese (both Cantonese and Mandarin);\nImmediately available is preferred.\n\n------------------------------------------------------------------------------------------------------------------------------\n\nWe offer attractive remuneration and excellent prospects for the right candidates. Please apply in writing with full resume and expected salary to Human Resources Department.\n\nApplications will be treated in strict confidence. Personal data collected will be used for recruitment purposes only.", "employment_types": ["Full Time"], "selling_points": ["Asia Pacific Tax Center", "Income Tax, Bookkeeping & Tax Compliance - USGAAP", "International team and global exposures"], "locations": ["Quarry Bay"], "categories": ["Accounting", "Taxation", "Others", "Professional Services", "Business Consultancy"], "post_time": "2022-01-15T10:20:56Z", "salary": {"currency": null, "max": null, "min": null, "period": "monthly", "term": null}, "salary_visible": false, "title_keywords": ["senior manager", "accounting", "manager"], "responsibilities": ["ad-hoc", "work with management", "presentations", "develop", "purchase", "maintain", "reports", "database", "plans"], "requirements": {"degrees": ["degree holder"], "majors": ["related disciplines", "finance", "accounting", "engineering"], "languages": ["cantonese", "english", "chinese", "mandarin"], "language_level": ["fluent"], "hard_skills": ["excel", "microsoft word", "professional qualifications", "cfa", "powerpoint", "cpa"], "soft_skills": ["communicator", "under pressure", "presentation skills", "work independently"], "languages_combined": [{"language": "cantonese", "language_level": ["fluent"]}, {"language": "english", "language_level": ["fluent"]}, {"language": "chinese", "language_level": ["fluent"]}, {"language": "mandarin", "language_level": ["fluent"]}]}, "experience_required": {"duration": ["at least 5 years"], "field": ["commercial", "relevant experience", "analytical"]}}, {"job_id": "100003009043366", "location_code": "hk", "company": "BDO", "job_title": "Senior Associate / Associate \u2013 Specialist Advisory Services (Insolvency)", "description": "Job Description\n\nDue to our growth in Asia, we are looking for a Senior Consultant to join our team in HK.\u00a0The ideal candidate will come with a background of proven KYC/AML project experience and remediation experience, as well as ideally having\u00a0worked with Financial Services industries and/or clients.\n\nAs a Senior Consultant, you will help to build our expertise and guarantee the quality of delivery to ensure market-leading practices for our Hong Kong office, taking into account the global nature of our organisation and our clients.\n\nResponsibilities:\n\nParticipate in projects with leading banks and Financial Institutions\nConduct compliance reviews, internal control review policies and procedures, risk and compliance advisory and other independent assessments as per the regulatory requirements to ensure compliance and make recommendations where necessary\nBe hands on and contribute to the successful execution of client projects.\nAssist in the development of new intellectual property including leading-edge research on white papers, supporting the development of marketing materials, and assist in publishing articles\nWork closely with our other offices and leverage our global network to take part in cross-selling initiatives and widely share our knowledge\n\nMore experienced candidates will have these additional responsibilities:\n\nIndependently drive the success of a work stream by directing activities, ensuring high quality deliverables, and timely submissions\nManaging a team of consultants by defining meaningful work packages, managing activities, and close mentorship\nParticipate in business development activities including content development, proposal preparation, and sales presentations\nShare consulting best practices with the team.\n\nQualifications\n\nKey Requirements:\n\nUniversity graduate or above in accounting, business, information technology or related disciplines.\n3 to 6 years' relevant experience in risk and regulatory compliance within a reputable consulting firm. Banking candidates are welcome\nFamiliar with HKMA and/or SFC regulations\nHolder of professional qualifications such as CPA, CFA, FRM, CAMS, CISA, CISSP, CIA and/or other related qualification is an advantage.\nGood project management and stakeholder management skills\nStrong interpersonal, logical and analytical skills\nAble to work independently with minimal supervision\nExcellent presentation and communication skills with clients and colleagues\nPossess an entrepreneurial spirit and team leadership skills\nExcellent command of spoken and written English and Chinese. Fluency in Mandarin is an advantage.\n\nIn addition to the strong consulting skills and business knowledge that our clients value, the ideal candidate must possess an entrepreneurial mind-set with both a drive and willingness to be involved in all areas of a growing business.", "employment_types": ["Full Time", "Permanent"], "selling_points": ["Support in insolvency & restructuring assignments", "Conduct investigation, draft reports & documents", "Excellent career prospects"], "locations": ["Sheung Wan"], "categories": ["Accounting", "Consulting", "Others", "Professional Services", "Business Consultancy"], "post_time": "2022-01-12T11:03:00Z", "salary": {"currency": null, "max": null, "min": null, "period": "monthly", "term": null}, "salary_visible": false, "title_keywords": ["specialist", "senior associate", "associate"], "responsibilities": ["make recommendations", "aml", "consulting", "policies", "regulatory requirements", "compliance", "quality", "review", "procedures", "ensure compliance", "presentations", "kyc", "marketing materials", "managing a team", "internal control"], "requirements": {"degrees": ["university graduate or above"], "majors": ["business", "related disciplines", "accounting", "information technology"], "languages": ["english", "chinese", "mandarin"], "language_level": ["fluency", "advantage", "excellent"], "hard_skills": ["professional qualifications", "hkma", "cfa", "analytical skills", "cpa", "project management", "frm"], "soft_skills": ["communication skills", "work independently", "leadership skills", "analytical skills", "project management", "interpersonal", "presentation", "ideal"], "languages_combined": [{"language": "english", "language_level": ["excellent"]}, {"language": "chinese", "language_level": ["excellent"]}, {"language": "mandarin", "language_level": ["fluency", "advantage"]}]}, "experience_required": {"duration": ["3 to 6 years"], "field": ["compliance", "relevant experience", "consulting"]}}, {"job_id": "100003009048192", "location_code": "hk", "company": "Vistra (Hong Kong) Limited", "job_title": "Senior Manager, Compliance (Asia Trust)", "description": "Operations Specialist\nLocated in the Tsim Sha Tsui area of Kowloon, NGC Hong Kong, Ltd. (NGC HK), is the Hong Kong-based subsidiary of Numismatic Guaranty Corporation (NGC) and Paper Money Guaranty (PMG).\u00a0 NGC and PMG are the world's largest and leading third-party authentication and grading services for collectible coins and paper money respectively. As our business in Hong Kong and Asia expands, we looking to add highly motivated self-starters to our team.\nPrimary responsibilities include:\nAnswer customer enquiries from Hong Kong and throughout Asia.\nInput customer submission information into company database.\nAssist with regional sales and marketing efforts.\nCoordinate shipments between customers and our Hong Kong office and between our Hong Kong and US offices.\u00a0\nParticipate in tradeshow and onsite events.\nRequirements:\nFluency in English and Chinese. Fluency in other languages is a significant benefit.\u00a0\nExcellent written and verbal communication skills.\nStrong organizational abilities.\u00a0\nAbility to multitask and be flexible in an often fast-paced environment.\u00a0\nProficiency in Microsoft Office suite.\u00a0\nSalary is commensurate with experience.\nOvertime Pay Offered\nMedical and Life Insurances Offered\nAbout Us:\nNGC HK is the Hong Kong affiliate of the Certified Collectibles Group (CCG) which includes seven of the world\u2019s leading collectible coin, paper money, comic book, and stamp service companies.\u00a0 The CCG companies are: Numismatic Guaranty Corporation (NGC), Numismatic Conservation Services (NCS), Paper Money Guaranty (PMG), Certified Guaranty Company (CGC), Classic Collectible Services (CCS), Authenticated Stamp Guaranty (ASG) and Collectibles Authentication Guaranty (CAG).\u00a0 Headquartered in Sarasota, Florida USA, CCG has additional locations in Shanghai, Munich, and London.", "employment_types": ["Full Time", "Permanent"], "selling_points": ["Trust Compliance senior level role located in HK", "Serving HK, PRC & SG market", "Individual contributor working in a global team"], "locations": ["Causeway Bay"], "categories": ["Banking / Finance", "Private Banking", "Professional Services", "Business Consultancy", "Legal & Compliance"], "post_time": "2022-01-14T05:49:19Z", "salary": {"currency": null, "max": null, "min": null, "period": "monthly", "term": null}, "salary_visible": false, "title_keywords": ["senior manager"], "responsibilities": ["customer enquiries", "coordinate", "database"], "requirements": {"degrees": [], "majors": [], "languages": ["english", "chinese"], "language_level": ["fluency"], "hard_skills": ["microsoft office suite"], "soft_skills": ["flexible", "communication skills", "fast-paced environment", "organizational", "ability to multitask"], "languages_combined": [{"language": "english", "language_level": ["fluency"]}, {"language": "chinese", "language_level": ["fluency"]}]}, "experience_required": {"duration": [], "field": []}}, {"job_id": "100003008515587", "location_code": "hk", "company": "Sia Partners Hong Kong Limited", "job_title": "Senior Consultant - Risk&Compliance (KYC focus)", "description": "Job description\n\nHandle company secretarial works for HK/PRC and offshore corporations;\nMaintain and update statutory and relevant records;\nProvide general support to the team;\nOther duties and ad hoc assignments as required.\n\nRequirements\n\n\n\nDegree in Business Administration, Company Secretarial studies or equivalent;\n2-3 years company secretarial hands-on experience is preferred;\nKnowledge in CSA will be an advantage;\nSelf-motivated, mature and responsible;\nGood command in written English and Chinese, and in spoken English, Cantonese and Mandarin..\n\nInterested parties please send your full resume with availability and expected salary to Ms. Mandy Lau by clicking \"Apply Now\"\n\n*The information collected will be used for recruitment purpose only.", "employment_types": ["Full Time", "Permanent"], "selling_points": [], "locations": ["Wan Chai Area"], "categories": ["Professional Services", "Business Consultancy"], "post_time": "2022-01-12T02:09:33Z", "salary": {"currency": null, "max": null, "min": null, "period": "monthly", "term": null}, "salary_visible": false, "title_keywords": ["senior consultant"], "responsibilities": ["general support", "maintain", "ad hoc assignments", "other duties"], "requirements": {"degrees": ["degree"], "majors": ["business administration"], "languages": ["cantonese", "english", "chinese", "mandarin"], "language_level": ["good command"], "hard_skills": [], "soft_skills": ["mature", "hands-on", "self-motivated", "responsible"], "languages_combined": [{"language": "cantonese", "language_level": ["good command"]}, {"language": "english", "language_level": ["good command"]}, {"language": "chinese", "language_level": ["good command"]}, {"language": "mandarin", "language_level": ["good command"]}]}, "experience_required": {"duration": ["2-3 years"], "field": ["secretarial"]}}, {"job_id": "100003009046355", "location_code": "hk", "company": "NGC Hong Kong Limited", "job_title": "Operations Specialist", "description": "Managing Director (Leading family office )\n\nAttractive remuneration package\nFund Raising\nFocus on deal structuring, bank financing and overall strategy\n\nAbout the Client\n\nOur client is one of Asia billionaire's family office .They have investment across financial services, TMT and healthcare industries with a focus on late stage development. They are currently looking for an experience candidate to join as MD and lead their business across APAC .Ideal candidate will come from a top tier investment bank ,PE or family office with over 15-20 years' leadership experience . This role will play as an advisor to group chairman on providing and developing business strategy and deal structuring across their APAC .\n\nResponsibilities\n\nResponsible for the firms overall strategy across APAC\nFormulate the overall business plan and direction, entry and exit strategies\nPlay an active role in deal souring, deals and funds structuring and closely working with partners on DD\nWorking closely with the head of IR to understand investors risk appetite\nStrategies the firm, define the themes of the investment, sculpt the firm\nOversee the bank financing and manage functional departments\nReview and improve organizational effectiveness by developing processes, overseeing employees, establishing a highly motivated work environment\nMaintain strong relationships with internal and external senior stakeholders\nOrganize and implement the board decisions, establish company annual plans\n\nRequirements:\n\nBachelor degree from reputable university\n10+ years' experience in a leadership role in a sizable Financial Institution\nExcellent leadership skills with strong leadership skills\nProven track record in defining the themes of the investment and excellent presentation skills\nStrong capability of business development & people management", "employment_types": ["Full Time"], "selling_points": [], "locations": ["Kowloon City"], "categories": ["Professional Services", "Business Consultancy"], "post_time": "2022-01-13T10:40:39Z", "salary": {"currency": null, "max": null, "min": null, "period": "monthly", "term": null}, "salary_visible": false, "title_keywords": ["specialist", "operations"], "responsibilities": ["review", "developing", "maintain", "business plan", "plans"], "requirements": {"degrees": ["degree", "bachelor"], "majors": [], "languages": [], "language_level": [], "hard_skills": [], "soft_skills": ["leadership skills", "leadership", "presentation skills"], "languages_combined": []}, "experience_required": {"duration": ["10+ years"], "field": ["financial"]}}, {"job_id": "100003009048230", "location_code": "hk", "company": "CW Secretarial Services Limited", "job_title": "Company Secretarial Assistant", "description": "Job Duties:\n\nManage engagement progress for pre-engagement work, risk management, financial modelling and report writing\nConduct business valuations, intangible asset valuations, financial asset valuations and purchase price allocations etc.\nParticipate in business development work\nMaintain in-house research database\nCoach junior team members\n\nRequirements:\n\nDegree holder with major in accounting, finance, financial engineering or other financial related disciplines\nPreferably has professional qualifications such as CPA and CFA, etc. is an advantage.\nAt least\u00a03 years relevant working experience (candidates with less experience will also be considered)\nStrong relationship with client is an advantage\nGood command of both spoken and written English and Chinese (both Cantonese and Mandarin)\nImmediate available is highly preferred.\n\n\nWe offer attractive remuneration and excellent prospects for the right candidates. Please apply in writing with full resume and\u00a0expected\u00a0salary to Human Resources Department.\n\nApplications will be treated in strict confidence.\u00a0 Personal data collected will be used for recruitment purposes only.", "employment_types": ["Full Time", "Permanent"], "selling_points": ["5-day work", "Medical, Study and Exam Leave", "2-3 years company secretarial experience"], "locations": ["Tsim Sha Tsui"], "categories": ["Professional Services", "Business Consultancy", "Company Secretary"], "post_time": "2022-01-14T08:23:31Z", "salary": {"currency": null, "max": null, "min": null, "period": "monthly", "term": null}, "salary_visible": false, "title_keywords": ["company secretarial assistant"], "responsibilities": ["management", "purchase", "maintain", "database", "report"], "requirements": {"degrees": ["degree holder"], "majors": ["related disciplines", "finance", "accounting", "engineering"], "languages": ["cantonese", "english", "chinese", "mandarin"], "language_level": ["good command"], "hard_skills": ["cfa", "cpa", "professional qualifications"], "soft_skills": [], "languages_combined": [{"language": "cantonese", "language_level": ["good command"]}, {"language": "english", "language_level": ["good command"]}, {"language": "chinese", "language_level": ["good command"]}, {"language": "mandarin", "language_level": ["good command"]}]}, "experience_required": {"duration": ["at least 3 years"], "field": ["relevant working experience"]}}, {"job_id": "100003009042560", "location_code": "hk", "company": "Links International", "job_title": "Managing Director (Leading family office )", "description": "CKP Sustainability Consultants (CKP) is a professional provider of corporate sustainability consulting services in Hong Kong. We specialize in sustainability report writing and we offer a host of complementary services, including stakeholder engagements and environmental data analysis.\u00a0\n\nOur deliverables not only ensure our clients comply with all regulations, but more importantly, provide a complete picture of corporate sustainability standing for corporate leaders to make informed business decisions. This would, in turn, allow us to work with our clients to manage and mitigate economic, environmental, and social risks, and enhance corporate value.\n\n\u00a0Your role:\n\n\u00a0 Assist in areas of sustainability consultancy, including sustainability reporting, stakeholder engagement, materiality assessment, benchmarking and others\n\n\u00a0 Review clients\u2019 operational activities and sustainability initiatives\n\n\u00a0 Cultivate professional relationships through open communications with existing and/or prospective clients\n\n\u00a0 Assist in other relevant projects\n\n\u00a0We are looking for:\n\n\u00a0 Excellent written and spoken English and Mandarin\n\n\u00a0 Passionate for environmental and social, or sustainability, topics\n\n\u00a0 Bachelor Degree from disciplines in Marketing, Journalism, Science, Environmental Management or equivalent with relevant experience\n\n\u00a0 Excellent analytical, interpersonal and communication skills\n\n\u00a0 Fast-learner, self-motivated, flexible and able to work independently\u00a0\n\nCompetitive salary is dependent on qualifications and experience. Part-time positions will not be considered. Interested applicants must send their CV along with expected salary to our corporate email. Short-listed candidates will be contacted individually.", "employment_types": ["Full Time", "Permanent"], "selling_points": ["Attractive remuneration package", "fund raising", "deal structuring, bank financing and strategy"], "locations": ["Not Specified"], "categories": ["Accounting", "Financial Controller", "Banking / Finance", "Financial Services", "Professional Services", "Business Consultancy"], "post_time": "2022-01-12T07:58:38Z", "salary": {"currency": "HKD", "max": null, "min": 160000, "period": "monthly", "term": null}, "salary_visible": true, "title_keywords": ["director"], "responsibilities": ["regulations", "reporting", "communications with", "management", "consulting", "review", "data analysis", "communication", "report"], "requirements": {"degrees": ["degree", "bachelor"], "majors": ["journalism", "science", "marketing"], "languages": ["english", "mandarin"], "language_level": ["excellent"], "hard_skills": ["make", "analysis"], "soft_skills": ["passionate", "communication skills", "self-motivated", "flexible", "work independently", "interpersonal"], "languages_combined": [{"language": "english", "language_level": ["excellent"]}, {"language": "mandarin", "language_level": ["excellent"]}]}, "experience_required": {"duration": [], "field": ["management", "marketing", "environmental", "relevant experience"]}}, {"job_id": "100003009042544", "location_code": "hk", "company": "Ravia Global Appraisal Advisory Limited", "job_title": "Senior Analyst / Manager - Valuation & Advisory Services", "description": "A growing financial institution in Hong Kong is looking for an experienced Company Secretary with exposure to private company and offshore matters to join their team.\n\nClient Details\n\nOur client is a reputable investment firm with a strong presence in Hong Kong and Mainland China. Due to an increase in business activities they are expanding their corporate services department.\n\nDescription\n\nReporting to the Head of Department, this role will be responsible for over-seeing and managing full spectrum of company secretarial work for 4 team members - all at Assistant/Officer level. This team is responsible for managing a portfolio of private companies including offshore and overseas.\n\nProfile\n\nThe successful candidate must have a minimum of 7 years of company secretarial experience and be an Associate Member of HKICS/HKCGI. They must have prior management experience and be familiar with private/offshore company matters. The ideal candidate will come from a large professional firm.\n\nJob Offer\n\nThe chosen candidate will be offered the opportunity to join a stable platform with attractive benefits.\n\nTo apply online please click the 'Apply' button below. For a confidential discussion about this role please contact Soraya Tennent on +852 2848 4795.", "employment_types": ["Full Time"], "selling_points": [], "locations": ["Wan Chai"], "categories": ["Banking / Finance", "Financial Services", "Professional Services", "Business Analysis / Data Analysis", "Business Consultancy"], "post_time": "2022-01-12T07:56:40Z", "salary": {"currency": null, "max": null, "min": null, "period": "monthly", "term": null}, "salary_visible": false, "title_keywords": ["manager", "senior analyst"], "responsibilities": ["reporting", "management", "business activities"], "requirements": {"degrees": [], "majors": [], "languages": [], "language_level": [], "hard_skills": [], "soft_skills": ["responsible", "ideal"], "languages_combined": []}, "experience_required": {"duration": ["minimum of 7 years"], "field": ["secretarial", "management"]}}, {"job_id": "100003009036831", "location_code": "hk", "company": "CKP Sustainability Consultants Limited", "job_title": "Assistant Consultant/ Consultant - Full time", "description": "The position will be responsible to help attracting and hiring fee earners into PageGroup Hong Kong & Taiwan according to business needs.\n\n\u5ba2\u6237\u7b80\u4ecb\n\nEstablished in London in 1976, Page Group is a leading professional recruitment consultancy specializing in the recruitment of permanent, contract and temporary positions for the world's top companies. With over 7,000 employees in 36 countries across the globe, we aim to be the leading specialist recruiter in our chosen markets, specializing in a broad range of professions and industries.\n\nIt's not just about what we do - it's about how we do it. Our success is underpinned by a culture of putting people and teamwork first, and we're immensely proud of our reputation for professionalism and integrity.\n\nOur values are reflected in everything we do, every day, all over the world. They're an integral part of our business and help set us apart from our competitors.\n\n\u5de5\u4f5c\u5185\u5bb9\n\nWorking closely with internal stakeholders to understand their recruitment needs in order to meeting hiring needs on a timely basis.\nManaging the full lifecycle recruitment process of hiring, from marketing mapping, sourcing, screening, interviewing to offering.\nProactively sourcing talents through effective channels, both for open roles as well as building future pipeline.\nAdopting effective and innovative methods of recruitment in order to attract the best talents to PageGroup.\nDriving Employer Branding & talent diversity initiatives and other talent acquisition related projects, e.g. graduate programs, talent mapping or etc.\nActing as a brand ambassador, proactively promoting our employee value proposition and inspiring candidates throughout the recruitment process.\nResponsible for TA KPI and metrics, including time to hire, diversity, sourcing channel efficiency, etc.\nParticipate in ad-hoc projects as assigned.\n\n\u7406\u60f3\u7684\u6c42\u804c\u8005\n\nAs your role within PageGroup includes operating as part of a team, you are expected to work as a team member, showing appropriate behaviors and respect to all employees and work with spirit of co-operation. We seek for a highly motivated individual who is a team player and able to communicate effectively and build solid relationships with your peers and other stakeholders in the company. A bachelor's degree or above and a minimum of one year work experience is a must.\n\n\u798f\u5229\u5f85\u9047\n\nWe believe no-one can match the career opportunities we offer and we all work hard to make sure it stays that way. If you would like to be a part of our team, we would love to hear from you.\n\n20 days annual leave\nComprehensive Medical and Dental insurance provided\nCompetitive salary with a clear career progression path\nLaptop and mobile phone provided\n\nTo apply online please click the 'Apply' button below. For a confidential discussion about this role please contact Joanna San on +852 3476 6339", "employment_types": ["Full Time"], "selling_points": [], "locations": ["Tsim Sha Tsui"], "categories": ["Professional Services", "Business Consultancy"], "post_time": "2022-01-10T16:59:36Z", "salary": {"currency": null, "max": null, "min": null, "period": "monthly", "term": null}, "salary_visible": false, "title_keywords": ["consultant", "assistant"], "responsibilities": ["recruitment process", "ad-hoc projects", "recruitment"], "requirements": {"degrees": ["degree or above", "bachelor"], "majors": [], "languages": [], "language_level": [], "hard_skills": [], "soft_skills": ["responsible", "work as a team", "timely", "teamwork", "integrity", "motivated individual", "inspiring", "team player", "innovative"], "languages_combined": []}, "experience_required": {"duration": ["minimum of one year"], "field": []}}, {"job_id": "100003009043444", "location_code": "hk", "company": "Swire Properties Limited", "job_title": "Manager, Sustainable Development (Ref: OS00109)", "description": "We are now growing our Advisory services team in East Asia and looking for talented candidates that bring general management consulting experience, skills and capabilities to join us in Hong Kong.\n\nResponsibilities:\n\nSupport the Project Leader in the delivery of projects by applying experience and skills in management consulting, change management and operation / process improvement\nCarry out research and data collection, processing, synthesis and analysis\nPrepare proposals and effectively communicate with clients, stakeholders and interested parties on data collection and / or result presentation by utilising consultative tools such as focus interviews, face-to-face / virtual workshops and surveys etc.\nManage projects and programmes, including project planning and implementation to ensure timely deliverables with high quality\nWork collaboratively with stakeholders to deliver their expectations, display excellent stakeholder engagement and problem resolution skills\nQualifications and Experiences required:\n\nDegree holder with relevant qualification in management consulting and business administration\nAt least 7 years of relevant experience in management consulting or relevant field\nExperience in engineering, healthcare and financial industry will be highly preferred\nDemonstrated knowledge and understanding in research method and stakeholder engagement\nKnowledge / skills in any of the following areas will be a distinct advantage:\nExcellent interpersonal and\u00a0 communication skillsExcellent interpersonal and communication skills\nProject management\nBenefits case development and delivery of feasibility studies, gap analysis and impact assessments\nProblem-solving and strategic planning ability\nExcellent interpersonal and communication skills\nProficiency in both written and spoken English and Chinese\n\n\n\nCandidates with less experience will be considered for the position of Senior Consultant or Consultant.\n\nWe offer a competitive remuneration package commensurate with qualifications and experience to the right candidate including Global Profit Share scheme, additional fringe benefits of maternity/paternity leave and long-term career development opportunities.\n\nFor interested applicants, please click \u201cApply Now\u201d to submit your online application.\n\nTo explore more job opportunities in Arup, please visit our website at http://www.arup.com/Careers/Experienced_Hires/ApplyForAJob\n\nPersonal data collected will be used for recruitment purpose only. Applicants not contacted within 8 weeks may consider their applications unsuccessful.\n", "employment_types": ["Full Time", "Permanent"], "selling_points": ["Annual sustainability & ESG report requirements", "Execute SD 2030 strategy & engagement programmes", "Drive changes through collaborations"], "locations": ["Quarry Bay"], "categories": ["Professional Services", "Business Analysis / Data Analysis", "Business Consultancy", "Sciences, Lab, R&D", "Environmental Science / Waste Management"], "post_time": "2022-01-12T11:59:38Z", "salary": {"currency": null, "max": null, "min": null, "period": null, "term": null}, "salary_visible": false, "title_keywords": ["manager"], "responsibilities": ["management", "change management", "consulting", "analysis", "data collection"], "requirements": {"degrees": [], "majors": [], "languages": [], "language_level": [], "hard_skills": ["analysis", "processing"], "soft_skills": [], "languages_combined": []}, "experience_required": {"duration": [], "field": ["management", "operation", "consulting", "team"]}}, {"job_id": "100003009043161", "location_code": "hk", "company": "Arup", "job_title": "Manager \u2013 Management Consulting", "description": "Payroll Officer (Corporate Services Company)\n\nJob Description\u00a0\u00a0\n\nResponsible for payroll calculation and execution\nInput data into payroll software and maintenance of staff information\nPrepare monthly MPF remittance statements and payment for submission\nManage benefits administration including but not limited to leave management and medical benefits\nPrepare Hong Kong tax reporting and respond to enquiries from employees, local regulators and tax authorities\n\nAssistant Accountant for Client Accounts (Fresh Graduate Welcome)\n\n\nJob Description\nResponsible for accurate and quick data entry into system\nAssist in preparing for\u00a0full sets of accounts and bookkeeping for client\nAssist in clients\u2019 cash management and payment administration\u00a0\nAssist in other ad hoc tasks\n\n\u00a0We are looking for:\n\nDegree / Associate degree / Higher diploma\u00a0in Human Resources Management, Accounting related disciplines\u00a0\nAble to work independently\nGood English required\nImmediate availability is preferred\nCandidate with less working experience/ Fresh graduates will be considered as Assistant Accountant\n\nWe offer:\n\nGood working conditions\u00a0\nGood medical and other benefits\n5-day week\u00a0\nDiscretionary bonus\nOn the job training including Xero\u00a0and third-party courses\nA wide range of exposure\nThe opportunity to grow with a high quality, service-oriented company", "employment_types": ["Full Time", "Permanent"], "selling_points": [], "locations": ["Kowloon City"], "categories": ["Professional Services", "Business Consultancy", "Engineering", "Engineering Project Management", "Management", "General Management"], "post_time": "2022-01-12T10:01:41Z", "salary": {"currency": null, "max": null, "min": null, "period": null, "term": null}, "salary_visible": false, "title_keywords": ["manager"], "responsibilities": ["mpf", "software", "maintenance", "data", "payment", "payroll"], "requirements": {"degrees": [], "majors": [], "languages": [], "language_level": [], "hard_skills": ["maintenance"], "soft_skills": ["responsible"], "languages_combined": []}, "experience_required": {"duration": [], "field": []}}, {"job_id": "100003009044546", "location_code": "hk", "company": "Primasia Corporate Services Limited", "job_title": "Payroll Officer / Assistant Accountant for Client Accounts (Fresh Graduate Welcome)", "description": "\u300a\u4e00\u7ad9\u5f0f\u9ad8\u7aef\u5ba2\u6236\u5e73\u53f0\u516c\u53f8\u300b\n\n\u5bcc\u4eba\u8ca1\u6280/\u4fdd\u55ae\u878d\u8cc7/\u5bcc\u4eba\u53d7\u8a17/\u907a\u7522\u7a05/\u5bb6\u65cf\u4fe1\u8a17/\u79c1\u4eba\u9280\u884c\n\n\u5de5\u4f5c\u7bc4\u7587\uff1a\n\n\u516c\u53f8\u505a\u9ad8\u7aef\u5ba2\u6236\u751f\u610f\uff08\u4fdd\u55ae\u878d\u8cc7/\u9ad8\u8cc7\u7522\u589e\u503c/\u907a\u7522\u7a05/\u5bb6\u65cf\u4fe1\u8a17\uff09\n\n\u4e3b\u8981\u5354\u52a9CEO\u65e5\u5e38\u5de5\u4f5c\n\n\u5354\u52a9CEO\u63a5\u898b\u9ad8\u7aef\u5ba2\u6236\n\n\u8ca0\u8cac\u958b\u6236\u53e3/\u5206\u6790\u8cc7\u91d1\u72c0\u6cc1/\u89e3\u91cbproposal\u00a0\u00a0\n\n\u8207\u9ad8\u7aef\u5ba2\u6236\u4fdd\u6301\u806f\u7d61\u00a0\u00a0\n\n\u6587\u4ef6\u8ddf\u9032\n\n\u798f\u5229\uff1a\n\n\u6709\u4f63\u91d1\u5206\uff0c\u82b1\u7d05\n\n\u89c0\u5858\u7532\u7d1a\u5546\u5834\u5beb\u5b57\u6a13\u5de5\u4f5c\n\n\u5730\u65b9\u5bec\u8eba\uff0c\u64c1\u6709\u8212\u9069\u4f11\u606f\u7a7a\u9593\n\nWork with CEO \u6642\u9593\u81ea\u4e3b\n\n\u4e00\u5e74\u53bb\u4e00\u6b21\u4e9e\u6d32\u8207\u6b50\u6d32\uff08\u6a5f\u7968\uff0b\u9152\u5e97)\u00a0\n\n\u8981\u6c42\uff1a\n\n\u80af\u5b78\uff0c\u6709\u8010\u6027\uff01\n\n\u4e2d\u4e94\u7562\u696d\u53ca\u4e94\u79d1\u5408\u683c\n\n\u611b\u6e9d\u901a\uff0c\u4e3b\u52d5\uff0c\u6562\u65bc\u63a5\u53d7\u6311\u6230\n\n\u7d93\u9a57\u4e0d\u62d8\uff0c\u6b61\u8fce\u7562\u696d\u5927\u5b78\u751f\uff0c\u53ea\u8981\u80af\u5b78\n\n*******\u6709\u610f\u8005\u8acb\u7acb\u523b\u9ede\u64caApply Now\u4ee5\u5b89\u6392\u9762\u8a66\u00a0**********", "employment_types": ["Full Time", "Permanent"], "selling_points": [], "locations": ["Wan Chai"], "categories": ["Accounting", "Accountant", "Professional Services", "Business Consultancy", "Admin & HR", "Compensation & Benefits"], "post_time": "2022-01-13T04:31:22Z", "salary": {"currency": null, "max": null, "min": null, "period": "monthly", "term": null}, "salary_visible": false, "title_keywords": ["officer", "assistant accountant"], "responsibilities": [], "requirements": {"degrees": [], "majors": [], "languages": [], "language_level": [], "hard_skills": [], "soft_skills": [], "languages_combined": []}, "experience_required": {"duration": [], "field": []}}, {"job_id": "100003009047442", "location_code": "hk", "company": "Century City Holdings Limited", "job_title": "Company Secretarial Assistant", "description": "Diploma or Certificate holder in company secretaryship or related discipline\nHKCGI / CGI Student Member\n2 years\u2019 working experience in company secretarial field andpreferably in listed companies\nDiligent, self-motivated and willing to work under pressure\nProficiency in MS Office Application\nGood command of written and spoken English and Chinese\n\nWe offer attractive remuneration package to the right candidate. Please apply with full resume stating present and expected salaries to: Group Human Resources Department, Century City Holdings Limited, 11/F, 68 Yee Wo Street, Causeway Bay, Hong Kong or fax to 2895-5766.\n\nAll personal data / information provided by applicants to Century City Group will be used for recruitment and related purpose(s) only.\n\nWe are an Equal Opportunity Employer.", "employment_types": ["Full Time", "Permanent"], "selling_points": ["Diploma holder in related discipline", "HKCGI / CGI Student Member", "Proficiency in MS Office Application"], "locations": ["Causeway Bay"], "categories": ["Professional Services", "Business Consultancy", "Company Secretary", "Legal & Compliance"], "post_time": "2022-01-14T03:06:43Z", "salary": {"currency": null, "max": null, "min": null, "period": "monthly", "term": null}, "salary_visible": false, "title_keywords": ["company secretarial assistant"], "responsibilities": ["work under pressure"], "requirements": {"degrees": ["certificate", "diploma"], "majors": [], "languages": ["english", "chinese"], "language_level": ["good command"], "hard_skills": ["ms office"], "soft_skills": ["self-motivated", "diligent", "work under pressure"], "languages_combined": [{"language": "english", "language_level": ["good command"]}, {"language": "chinese", "language_level": ["good command"]}]}, "experience_required": {"duration": ["2 years"], "field": ["secretarial"]}}, {"job_id": "100003009046977", "location_code": "hk", "company": "Thales Transport & Security (Hong Kong) Limited", "job_title": "Contract Manager", "description": "Responsibilities\n\nBids / RFPs preparation and reviews RFPs\nDuring the bid phase (bid / no bid, bid preparation, contract drafting, etc.) supports the Capture Leader in understanding customer requirements; ensuring the pertinence of commitments; identifies contractual risks and participates in the negotiation of contractual clauses and in the establishment of a clear and coherent contractual baseline\nContract Documentation, procedures and dashboards\nDuring the project phase (launch and monitoring) supports Project Manager in strictly monitoring contract performance through to completion and managing change requests, including consequent evolutions to contractual baseline; reports on potential problems; proposes actions to minimise risk and maximise opportunities for the project ; participates, as required, in the resolution of contract disputes\nClaims, VO requests assessment, preparation, payment and submission, disputes\nContractual documentation management and preparation of documentation submittal to Customer, subcontractors together with monitoring of timing of responses\nPrepare opportunity review for change/variation orders, draft and lead negotiation of the same. Ensure timely collection of all relevant records, data and information to support and draft claims\nSubcontractors\nDraft and negotiate subcontracts in an effort to minimize Thales risks (flow-down of T&Cs and contractual risks)\nSupervise and review commercial and contractual management of sub-contractors including review of contract notices, preparation of correspondence, review of applications for payment, progress, variations, claims, etc\n\nRequirements\n\nMinimum of 5 years\u2019 legal or contract management working experience in international engineering or high-technology environment or equivalent. Experience with FIDIC type contracts or the equivalent will be much appreciated\nSound negotiation and drafting skills\nLaw degree or paralegal qualification is a must. Can read and draft legal document in Chinese\nAble to organize and prioritize contractual and commercial risks and issues\nAbility to effectively reach negotiated compromises (win-win approach). Trouble-shooting oriented\nStrong communication and inter-personal skills. Capacity to influence decisions thanks to a convincing character and natural authority\nWorks independently, with efficient reporting discipline\nTransparency and clearness in messages delivery and formal reporting\nProficient with MS Office tools\nOccasional overseas travelling may be required", "employment_types": ["Full Time", "Permanent"], "selling_points": ["5+ experience in Contract Management", "Cover HK & Toronto region", "Work from home arrangement"], "locations": ["Mong Kok"], "categories": ["Professional Services", "Business Consultancy", "Legal & Compliance"], "post_time": "2022-01-14T01:55:27Z", "salary": {"currency": null, "max": null, "min": null, "period": "monthly", "term": null}, "salary_visible": false, "title_keywords": ["manager"], "responsibilities": ["management", "data", "monitoring", "procedures", "review", "resolution", "payment", "contract documentation", "reports", "documentation"], "requirements": {"degrees": ["degree"], "majors": ["law"], "languages": ["chinese"], "language_level": [], "hard_skills": ["ms office"], "soft_skills": ["efficient", "independently", "inter-personal skills", "prioritize", "communication", "sound negotiation"], "languages_combined": [{"language": "chinese", "language_level": []}]}, "experience_required": {"duration": ["minimum of 5 years"], "field": ["management", "engineering", "legal"]}}, {"job_id": "100003009039704", "location_code": "hk", "company": "Joy Kind International Limited", "job_title": "Business Development Manager (30K+)", "description": "Job Highlights\nPassionate in career\nConfident, friendly and outgoing person\n3 yrs experience in business development/marketing/sales position\nJob Description\n\nBusiness Development Manager\u00a0at JOY KIND INT'L\nFantastic opportunity to join a leading fast-growing Asia company.\u00a0\n\nAs the Business Development Manager at JOY KIND, you will be responsible for identifying new opportunities, account management and driving the growth across the company products. You will have to achieve sale targets while delivering outstanding client relationships management. Also, you are not shy to expand your network through a strategic approach to the market.\n\n\u00a0Your role\u00a0\n-Develop and implement the appropriate business development strategies to achieve business objectives of increasing revenue, profitability and market share for the company\n-\u00a0Conduct research on key and potential clients to assist Director with the understanding of clients\u2019 business profiles\n-\u00a0Manage and execute complete sales cycle from prospecting, qualifying, closing and forecasting\n- Successfully achieve specified targets and performance objectives for sponsorship within your remit\n- Make outgoing sales calls to potential clients and with a big focus on new business clients as we enter a new market for the brand to maximize revenue for sponsorship\n- Be knowledgeable about the industries, client profile, competitors and products in order to sell the right solutions to the potential clients\n- Maintain a strong sales pipeline through effective relationship building, call management and lead generation\n- Ensure accurate use and maintenance of system supporting sales activities\n- Handle sales administration activities (reports, meetings, plans etc.) efficiently\n- Works closely with other internal teams to ensure all clients related activities are fulfilled\n- Proactively looking for better solutions for sales strategies and client service management\n\nWho you are\n- Bachelor degree/Diploma holder\n- Minimum 3 years of\u00a0 experience in sales position, business development or marketing\n- Fluency in English, Cantonese and Mandarin is preferable\n\n\nAbilities we are looking for\n\n- A confident and friendly person\u00a0\n- Great analytic skills\n- Detail-oriented, excellent time management and manage multiple tasks\n- Eager to grow and willing to take challenges\n- A team player but also be able to work independently\n- Excellent communication and strong coordination skills, comfortable to reach out to new clients\n- Enjoy working in a fast-paced environment", "employment_types": ["Full Time", "Permanent"], "selling_points": ["Promising prospect", "High salary plus commission", "Friendly environment"], "locations": ["Wan Chai"], "categories": ["Professional Services", "Business Consultancy", "Sales, CS & Business Devpt", "Business Development", "Marketing / Public Relations", "Marketing - Direct Marketing"], "post_time": "2022-01-11T10:35:34Z", "salary": {"currency": "HKD", "max": 29999, "min": 20000, "period": "monthly", "term": null}, "salary_visible": true, "title_keywords": ["business development manager"], "responsibilities": ["sales activities", "management", "sales administration", "maintenance", "teams", "maintain", "reports", "plans", "forecasting", "conduct research"], "requirements": {"degrees": ["diploma holder", "degree", "bachelor"], "majors": [], "languages": ["cantonese", "english", "mandarin"], "language_level": ["fluency"], "hard_skills": ["analytic skills"], "soft_skills": ["confident", "work independently", "coordination skills", "multiple tasks", "fast-paced environment", "enjoy working", "detail-oriented", "communication", "friendly", "team player", "time management"], "languages_combined": [{"language": "cantonese", "language_level": ["fluency"]}, {"language": "english", "language_level": ["fluency"]}, {"language": "mandarin", "language_level": ["fluency"]}]}, "experience_required": {"duration": ["minimum 3 years"], "field": ["business development", "marketing"]}}, {"job_id": "100003009037008", "location_code": "hk", "company": "CEO mindPower Ltd", "job_title": "Business Consultant", "description": "What you will do\n\nYou will play an active role in further expansion of our business.\n\n\nSupport the Senior Business Development Manager & CEO in achieving company sales and profit targets\nSupport the business development efforts and account servicing of the company\nSupport in preparing proposals, quantitative forecasts, market analysis and other related Business Development activities\nManage and create content for the social media accounts and website of the company and the CEO\nCompile regular reports on performance of website traffic, Google Ads, and social media accounts\nSupport in administration and ad hoc project management tasks as required by the company\n\nWhat is required of you\n\n\nDegree holder or above in Business or related fields\nExcellent communication skills in oral & written English & Chinese (Cantonese & Mandarin)\n2 to 3 years of work experience\nStrong interest in business consultancy and training\nExcellent interpersonal skills and works well under pressure\nExcellent multi-tasker, detail-orientated, and independent worker\nSelf-motivated and strives for excellence\nProficient computer skills with expertise in using MS Word, Excel, PowerPoint\nAdobe Photoshop and/or Adobe Illustrator and video-editing skills preferred\nSEO and Google Ads knowledge preferred\n\nAn attractive remuneration package with career advancement opportunities will be offered with the right candidate.\n\nCome join us now! Send your detailed CV highlighting your career objectives to us.\n\nFind out more about us at www.ceompower.com", "employment_types": ["Full Time"], "selling_points": [], "locations": ["Wan Chai"], "categories": ["Professional Services", "Business Consultancy", "Sales, CS & Business Devpt", "Business Development", "Management", "General Management"], "post_time": "2022-01-11T01:17:38Z", "salary": {"currency": null, "max": null, "min": null, "period": "monthly", "term": null}, "salary_visible": false, "title_keywords": ["consultant"], "responsibilities": ["social media", "ad hoc", "seo", "website", "communication", "project management", "market analysis", "reports", "editing", "administration"], "requirements": {"degrees": ["degree holder"], "majors": ["business"], "languages": ["cantonese", "english", "chinese", "mandarin"], "language_level": ["excellent"], "hard_skills": ["excel", "seo", "analysis", "adobe photoshop", "powerpoint", "adobe illustrator", "project management", "computer skills", "ms word"], "soft_skills": ["communication skills", "oral", "self-motivated", "under pressure", "independent", "project management", "interpersonal skills", "active", "detailed"], "languages_combined": [{"language": "cantonese", "language_level": ["excellent"]}, {"language": "english", "language_level": ["excellent"]}, {"language": "chinese", "language_level": ["excellent"]}, {"language": "mandarin", "language_level": ["excellent"]}]}, "experience_required": {"duration": ["2 to 3 years"], "field": []}}, {"job_id": "100003009043487", "location_code": "hk", "company": "CRE Properties (Hong Kong) Limited", "job_title": "\u6218\u7565\u7ba1\u7406\u52a9\u7406\u7ecf\u7406/\u526f\u7ecf\u7406 Assistant Strategy Manager/Deputy Strategy Manager", "description": "\u5de5\u4f5c\u804c\u8d23\n1.\u00a0\u00a0\u5354\u52a9\u516c\u53f8\u6574\u9ad4\u5e74\u5ea6\u5546\u696d\u8a08\u5283\u7684\u5236\u5b9a\u8207\u5be6\u65bd\uff0c\u4e26\u8a55\u4f30\u6230\u7565\u5be6\u65bd\u6548\u679c\uff1b\n2. \u8ca0\u8cac\u5c0d\u76f8\u95dc\u5c0d\u6a19\u4f01\u696d\u9032\u884c\u5206\u6790\u53ca\u5c08\u984c\u9805\u76ee\u7684\u6230\u7565\u7814\u7a76\u8abf\u7814\u5de5\u4f5c\uff1b\n3. \u7d44\u7e54\u53ec\u958b\u516c\u53f8\u76f8\u95dc\u696d\u52d9\u5de5\u4f5c\u6703\u8b70\uff0c\u5b8c\u6210\u6703\u8b70\u7d00\u8981\u4e26\u8ddf\u9032\u6703\u8b70\u8981\u6c42\u7684\u843d\u5be6\uff1b\n4. \u53c3\u8207\u5236\u5b9a\u6f5b\u5728\u9805\u76ee\u53ef\u884c\u6027\u5206\u6790\u5831\u544a\u548c\u91cd\u5927\u9805\u76ee\u7684\u6295\u8cc7\u5f8c\u8a55\u4f30\u5831\u544a\uff1b\n5. \u63a2\u8a0e\u65b0\u6a21\u5f0f/\u65b0\u7ba1\u7406\u7cfb\u7d71\u7684\u898f\u5283\u3001\u65b0\u589e\u9577\u9ede/\u65b0\u7522\u696d\u7684\u898f\u5283\u548c\u5b75\u5316\uff1b\n6. \u5b8c\u6210\u516c\u53f8\u5b89\u6392\u7684\u5176\u4ed6\u4efb\u52d9\n\n\u4efb\u804c\u8981\u6c42\n1.\u00a0\u00a0\u672c\u79d1\u53ca\u4ee5\u4e0a\u5b78\u6b77\uff0c\u5c08\u696d\u4e0d\u9650\uff1b\n2. 2-3\u5e74\u7ba1\u7406\u8aee\u8a62\u3001\u6230\u7565\u7ba1\u7406\u76f8\u95dc\u5de5\u4f5c\u7d93\u9a57\uff0c\u56db\u5927\u8aee\u8a62\u5de5\u4f5c\u7d93\u9a57\u512a\u5148\uff1b\n3. \u5177\u5099\u7368\u7acb\u5831\u544a\u64b0\u5beb\u80fd\u529b\uff0c\u512a\u79c0\u7684\u6587\u5b57\u8868\u9054\u80fd\u529b\uff0c\u908f\u8f2f\u6027\u5f37\uff1b\n4. \u5177\u6709\u8f03\u5f37\u7684\u6e9d\u901a\u8207\u5354\u8abf\u80fd\u529b\uff0c\u5de5\u4f5c\u56b4\u8b39\uff0c\u6709\u5718\u968a\u610f\u8b58\uff0c\u8cac\u4efb\u5fc3\u5f37\u3002", "employment_types": ["Full Time", "Permanent"], "selling_points": [], "locations": ["Wan Chai"], "categories": ["Professional Services", "Business Analysis / Data Analysis", "Business Consultancy"], "post_time": "2022-01-12T13:56:55Z", "salary": {"currency": null, "max": null, "min": null, "period": "monthly", "term": null}, "salary_visible": false, "title_keywords": ["manager", "assistant"], "responsibilities": [], "requirements": {"degrees": [], "majors": [], "languages": [], "language_level": [], "hard_skills": [], "soft_skills": [], "languages_combined": []}, "experience_required": {"duration": [], "field": []}}, {"job_id": "100003009045094", "location_code": "hk", "company": "CEVA Logistics (Hong Kong) Limited", "job_title": "Legal Manager", "description": "YOUR ROLE\n\nTo partner with Business to negotiate and close deals. Ability to fix complex issues and provide solution. Ability to interact with different levels of management with solid communication and people management skills.Cultivate great sense of governance and compliance within the organisation\u00a0\n\nWHAT ARE YOU GOING TO DO?\u00a0\n\nPrimarily commercial contracts drafting, review, negotiation according to internal rules and regulations and provide legal advice to business units and supporting functions on a day-to-day basis;\nContract negotiation and ability to strategize for solutions to complex issues.\nFamiliar with corporate secretarial matters , company restructuring & M&A transactions.\nWell conversant with local laws and able to attend courts hearings and labor mediation.\nStrategize and manage outside counsels in handling civil litigation or arbitration cases.\nConduct training of company rules and policies and other topics of interest such as data privacy in Hong Kong ; and\nAny other duties as assigned from time to time.\n\n\nWHAT ARE WE LOOKING FOR?\u00a0\n\nHolds a law degree from a reputable university in Hong Kong or overseas.\nQualified as a practicing lawyer in Hong Kong\nMinimum 5 years of post-qualification experience with a reputable law firm in Hong Kong or as in-house counsel with a multinational corporation preferably in the logistics industry;\nStrong communication, negotiation and drafting skills with excellent problem-solving and partnering abilities;\nOutgoing personality, self-motivated and has a high level of individual responsibility and ability to withstand work pressure and can drive contracts negotiation together with Business Development to close deals;\nAbility to multi-task is needed.\nHigh proficiency in both written and spoken English and Chinese (Mandarin). Ability to speak and write a foreign language like Japanese or Korean is an advantage; and\u00a0\nStrong in PowerPoint and presentation skills.\n\n\u00a0WHAT DO WE HAVE TO OFFER?\u00a0\n\nWith a genuine culture of reward and recognition, we want our employees to grow, develop and be part of our journey. We offer a benefits package that includes competitive annual leave entitlement, pension and medical insurance along with other cash and holiday gifts. There\u2019s no doubt that you will be compensated for your hard work and commitment so if you\u2019d like to work for one of the top Logistics providers in the world then please do get in touch to find your next role.\n\n\u00a0ABOUT TOMORROW\u00a0\n\nWe value your professional and personal growth. That\u2019s why we share plenty of career opportunities for you to thrive within CEVA. Join CEVA for a challenging career.\u00a0", "employment_types": ["Full Time", "Permanent"], "selling_points": ["Inhouse Legal Manager in MNC", "Strong communication & negotiation skills", "Qualified as a practicing lawyer"], "locations": ["Kowloon Bay"], "categories": ["Professional Services", "Business Consultancy", "Legal & Compliance", "Transportation & Logistics", "Freight Forwarding"], "post_time": "2022-01-13T07:10:04Z", "salary": {"currency": null, "max": null, "min": null, "period": null, "term": null}, "salary_visible": false, "title_keywords": ["manager"], "responsibilities": ["regulations", "any other duties", "management", "data", "contracts", "policies", "compliance", "review", "transactions", "develop", "communication", "logistics"], "requirements": {"degrees": ["degree"], "majors": ["law"], "languages": ["english", "mandarin", "japanese", "korean", "chinese"], "language_level": ["advantage", "proficiency"], "hard_skills": ["problem-solving", "powerpoint"], "soft_skills": ["outgoing personality", "self-motivated", "multi-task", "negotiation", "problem-solving", "communication", "presentation skills", "organisation", "genuine"], "languages_combined": [{"language": "english", "language_level": ["proficiency"]}, {"language": "mandarin", "language_level": []}, {"language": "japanese", "language_level": ["advantage"]}, {"language": "korean", "language_level": ["advantage"]}, {"language": "chinese", "language_level": ["proficiency"]}]}, "experience_required": {"duration": ["minimum 5 years"], "field": ["logistics industry", "post-qualification"]}}, {"job_id": "100003009042542", "location_code": "hk", "company": "Divine Consultancy", "job_title": "Management Trainee Program (Ref:At)", "description": "Responsibilities:\n\nClients relationship management, maintain and expand clients\u2019 network\u00a0\nProvide investment consultancy services, monitor the financial status of the clients and propose tailor-made solutions which satisfy their needs\nEstablish and manage professional financial planning\u00a0\nMaintain ongoing client relationship\nPromoting our Premier Service to potential clients, exploring their needs and making referrals to other business units where appropriate\nCommunicate and coordinate operational activities with regional offices and business partners\n\nRequirements:\n\nUniversity graduate with degree in Economics, Business Administration or related discipline\nNo relevant experience will also be considered\nStrong communication and presentation skills\nGood command in written and spoken English and Chinese. Fluent in Mandarin is advantage\nComputer literate in MS Office including Chinese word processing\nCustomer focused, people-oriented, positive attitude, outgoing, proactive and good problem solving skills", "employment_types": ["Full Time", "Permanent"], "selling_points": [], "locations": ["Wan Chai"], "categories": ["Accounting", "Financial Analyst", "Professional Services", "Business Consultancy", "Management", "Management Trainee"], "post_time": "2022-01-12T07:57:09Z", "salary": {"currency": "HKD", "max": 34999, "min": 25000, "period": "monthly", "term": null}, "salary_visible": true, "title_keywords": ["management trainee"], "responsibilities": ["management", "monitor", "coordinate", "maintain", "planning"], "requirements": {"degrees": ["university graduate", "degree"], "majors": ["economics", "business administration"], "languages": ["english", "chinese", "mandarin"], "language_level": ["advantage", "good command", "fluent"], "hard_skills": ["no", "chinese word processing", "problem solving skills", "ms office"], "soft_skills": ["outgoing", "focused", "communication", "positive attitude", "presentation skills", "people-oriented", "problem solving skills", "proactive"], "languages_combined": [{"language": "english", "language_level": ["good command"]}, {"language": "chinese", "language_level": ["good command"]}, {"language": "mandarin", "language_level": ["fluent", "advantage"]}]}, "experience_required": {"duration": [], "field": ["relevant experience"]}}, {"job_id": "100003009035986", "location_code": "hk", "company": "Olympus Corporation of Asia Pacific Limited", "job_title": "Digital Transformation Manager", "description": "At Olympus, our shared aim is to use our innovative optical and digital solutions in medical technologies, life sciences and industrial solutions to making people\u2019s lives healthier, safer and more fulfilling, which consists of our Core Values of Integrity, Empathy, Long-Term View, Agility and Unity forming the strong foundations and commitment to our people-focused culture and guide the way we think and behave, every day.\u00a0 You can look forward to exciting challenges in an international working environment, in which you will be constantly developing on both a professional and personal level. We are currently looking for a\u00a0Digital Transformation Manager to join our Medical Systems Division - Customer Experience Department in our Hong Kong office\u00a0\n\nResponsibilities:\n\nDevelop digital capabilities and channel orchestration to support digital experience for enterprise-scale digital product transformation projects and omnichannel strategies\nWork collaboratively with internal and external stakeholders across APAC countries including Sales, Marketing, Legal, Compliance and 3rd party vendors to innovate, validate and commercialize digital solutions as an expert advisor to support business activities and metrics\nExecute digital readiness activities including development, UAT, training, procedure manual preparation, communication and release\nPerform gap analysis of digital asset capabilities to identify opportunities and improvements\nSupport customer digital behaviour analysis and segmentation, development of digital personas and creation of digital preferences\nConduct research on market competitive landscapes, benchmark digital performance and processes against industry best practice and identify digital opportunities to grow business\nResponsible for the management of all digital marketing platforms in B2B business model\nDigital content collection, generation and review to support the marketing campaigns\nManage digital campaign effectiveness, analyse metrics and identify areas of opportunity to provide guidance in optimization and drive business metrics\u00a0\nLead/ co-lead cross functional workstreams to create, implement and monitor marketing campaigns\nSupport for other ad hoc assignments and projects\nRequirements:\n\nBachelor\u2019s Degree in Business Management, Computer Science or equivalent\nAt least 8 years\u2019 experience in driving digital transformation with APAC scope\nStrong expertise in the following channels and capabilities in marketing automation, such as email, websites, apps, digital advertising, SEO/SEM, social media platforms, webcasting and digital sales tools. Basic level in HTML design\nExpertise in marketing automation especially on Salesforce Marketing Cloud (SFMC) would be a plus\nSalesforce and SAP competency is a plus\nKnowledge of CRM and ERP preferably in MedTech industry context\nIndustry certifications: PMI-PMP, PMI-ACP, Scrum Master, CCXP, PRINCE2 Practitioner; 25% travelling is required \u2022 Strong knowledge in technologies, digital innovations, solutions and business models available for corporate adoption\nExcellent Project Management skills and communication skills\nGood negotiation and interpersonal skills, and ability to engage a wide range of stakeholders to agree on scope and requirements\nStrong in working at different levels of granularity and capable of visualizing the big picture and analysing at a detailed level where required\nGood command of written and spoken English and Chinese\nWe offer attractive remuneration and career development opportunity.\u00a0 Interested parties, please send your resume together with availability, present and expected salaries by clicking \"Apply Now\".\u00a0\n\n\nAll personal information collected will be treated in strict confidence and used for recruitment purpose only.\u00a0", "employment_types": ["Full Time", "Permanent"], "selling_points": ["Drive and initiate digital omnichannel initiatives", "Act as the Digital Product Owner for APAC business", "8 yrs experience in driving digital transformation"], "locations": ["Kwai Tsing Area"], "categories": ["Professional Services", "Business Consultancy", "Marketing / Public Relations", "Marketing - Direct Marketing", "E-commerce", "Marketing - Brand / Product Management"], "post_time": "2022-01-10T09:00:44Z", "salary": {"currency": null, "max": null, "min": null, "period": "monthly", "term": null}, "salary_visible": false, "title_keywords": ["manager"], "responsibilities": ["3rd party vendors", "management", "uat", "analysis", "compliance", "review", "monitor", "develop", "communication", "digital marketing", "ad hoc assignments", "marketing campaigns", "provide guidance", "conduct research", "business activities", "analyse"], "requirements": {"degrees": ["degree", "bachelor", "master"], "majors": ["business", "computer science"], "languages": ["english", "chinese"], "language_level": ["good command"], "hard_skills": ["business management", "plus", "seo", "basic", "salesforce", "sap", "html", "erp", "project management", "sem", "pmp"], "soft_skills": ["communication skills", "capable", "negotiation", "project management skills", "interpersonal skills", "detailed"], "languages_combined": [{"language": "english", "language_level": ["good command"]}, {"language": "chinese", "language_level": ["good command"]}]}, "experience_required": {"duration": ["at least 8 years"], "field": ["digital"]}}, {"job_id": "100003009043219", "location_code": "hk", "company": "Automated Systems (HK) Ltd", "job_title": "Solution Consultant (Pre-sales)", "description": "There exists an exciting Compliance opportunity as Vistra expands our Private Wealth/Trust team in the region.\u00a0 Reporting into the Trust Compliance Director in Singapore and supported by our established Compliance team in Hong Kong.\u00a0\n\nResponsibilities\n\nAssist in carrying out the Compliance function of the Asia Trust business (regulated by the Monetary Authority of Singapore and the Company Registry in Hong Kong)\nKeep senior management of Asia Trust abreast of new regulatory developments in their business footprint\nMaintain constructive and effective relationships with and support key Asia Trust stakeholders\nSupport Asia Trust senior management on regulatory relationships with the applicable regulators\nPromote the culture and practice of adherence to compliance standards (including conducting business within regulatory and Group requirements)\nDevelop, implement and maintain Compliance policies and procedures, guidance documents and SOP\nImplement Group Compliance and other relevant Group functional policies across the Asia Trust business (as applicable)\nReview existing and develop new internal forms and Compliance processes\nConduct Client Due Diligence on new and existing trust structures, including providing advice and as point of escalation\nPerform client risk profiling to ensure up-to-date records of clients\u2019 risk ratings\nPromote and advise on periodic reviews of structures based on clients\u2019 risk profiles\nManage and address compliance escalations from Asia Trust stakeholders\nProvide Compliance support and guidance to the Business, including data protection, outsourcing arrangements, Business Continuity Management, technology risk management, etc.\nParticipate in Asia Trust related Board meetings and business/risk committee meetings (as required)\nGuide Asia Trust stakeholders on regulatory inspections, internal and external audits, in particular to address any audit points\nAssist with compilation of data and preparation of reports for submission to Group Compliance\nAssist with regulators\u2019 queries and requests for information\nDeliver compliance monitoring under a defined program to ensure that Asia Trust business is conducted in accordance with Group and local policies and procedures\nMaintain risk registers (e.g. PEP, Other High Risk Clients, etc.), and review transactions of clients of various risk ratings\nPrepare, file and monitor Suspicious Transaction Reports\nRequirements\n\nDegree in Business, Law, Risk Management or related discipline\nAt least 8-10+ years\u2019 of Compliance experience within the Private Wealth industry, may suit someone with a Bank, Private Bank or similar background\nStrong Private Wealth Compliance technical knowledge is advantageous\nRelevant Compliance qualification / certification\nIndependent and self-motivated\nTeam player with high degree of professional integrity, and a can-do attitude\nCollaborative yet tactfully firm where required\nExcellent spoken and written English\nAbility to communicate in Mandarin and understand documents in Chinese is required\nProficient user of Microsoft Office including Powerpoint, Excel and Word\nBeing IT savvy will be an advantage\nAll personal information collected will be used for recruitment purpose only.", "employment_types": ["Full Time", "Permanent"], "selling_points": ["University degree or above", "Perm pre-sales role in commercial sales division", "Support your career advancement"], "locations": ["Shatin Area"], "categories": ["Professional Services", "Business Consultancy", "Information Technology (IT)", "IT Project Management / Team Lead", "Sales, CS & Business Devpt", "Technical Sales / Sales Engineer"], "post_time": "2022-01-12T10:15:02Z", "salary": {"currency": null, "max": null, "min": null, "period": "monthly", "term": null}, "salary_visible": false, "title_keywords": ["consultant", "sales"], "responsibilities": ["business continuity", "data", "audit", "transactions", "maintain", "senior management", "due diligence", "compliance", "monitor", "develop", "reports", "guidance", "management", "review", "procedures", "internal and external audits", "monitoring", "regulatory inspections", "policies"], "requirements": {"degrees": ["degree"], "majors": ["risk management", "business", "law"], "languages": ["english", "chinese", "mandarin"], "language_level": ["excellent"], "hard_skills": ["excel", "word", "powerpoint", "microsoft office"], "soft_skills": ["self-motivated", "independent", "can-do attitude", "integrity", "collaborative", "team player"], "languages_combined": [{"language": "english", "language_level": ["excellent"]}, {"language": "chinese", "language_level": []}, {"language": "mandarin", "language_level": []}]}, "experience_required": {"duration": ["10+ years"], "field": ["compliance"]}}, {"job_id": "100003009040201", "location_code": "hk", "company": "Accenture Company Limited", "job_title": "Interactive - Project Manager", "description": "Job Description:\n\nPrimarily responsible for solution formulation, approach and communicate with delivery team\n\nTranslate customer requirements into high-level design\u00a0\nTo be able to collect requirement from customer, to resolve customer pain points.\nTo articulate the solution value for customers in favor of being their trusted advisor.\nLead technical discussion and prepare proposal and conduct presentation to prospect customers\nCollaborate between project delivery teams\nExplore knowledge of new technologies, drive for innovation\u00a0and think out-of-the-box\nFlexible career path developing new skills with training subsidy support.\nJob Requirements:\n\nUniversity degree holders or above\u00a0\n3 years+ working experiences (infra, cloud, data, network & security)\nDemonstration problem solving capability\nResult oriented and creative in problem solving\nGood written and verbal communication skill\nCandidates with more experiences will be considered as Senior Consultant.\nFresh graduates welcomed\nWe offer 5-day week, excellent career opportunities, remuneration and benefits to the right candidates. \u00a0If you have the desire for an exciting and rewarding career, please send us your resume,\u00a0stating your notice period, present and expected salary to Human Resources Department by clicking\u00a0\"Apply Now\".\u00a0\n\nTo learn us more, please visit our website:\u00a0www.asl.com.hk\n\nWe are an equal opportunity employer. All applications will be treated in strict confidence. We regret that only shortlisted candidates will be notified. All personal data will be destroyed within six months after the selection process.", "employment_types": ["Full Time", "Permanent"], "selling_points": ["5+ years hands-on experience", "Digital transformation projects", "Project management and software delivery"], "locations": ["Not Specified"], "categories": ["Professional Services", "Business Consultancy", "Information Technology (IT)", "IT Project Management / Team Lead", "Product Management / Business Analyst"], "post_time": "2022-01-12T01:51:17Z", "salary": {"currency": null, "max": null, "min": null, "period": "monthly", "term": null}, "salary_visible": false, "title_keywords": ["project manager"], "responsibilities": ["communicate with", "collaborate", "teams", "developing", "design"], "requirements": {"degrees": ["university degree"], "majors": [], "languages": [], "language_level": [], "hard_skills": ["problem solving"], "soft_skills": ["problem solving", "communication skill", "result oriented", "creative"], "languages_combined": []}, "experience_required": {"duration": [], "field": ["security"]}}, {"job_id": "100003009033096", "location_code": "hk", "company": "Links International", "job_title": "Strategy Manager (Consulting Firm background welcome )", "description": "About Accenture\uff1a\n\nAccenture is a global professional services company with leading capabilities in digital, cloud and security. Combining unmatched experience and specialized skills across more than 40 industries, we offer Strategy and Consulting, Interactive, Technology and Operations services\u2014all powered by the world\u2019s largest network of Advanced Technology and Intelligent Operations centers. Our 506,000 people deliver on the promise of technology and human ingenuity every day, serving clients in more than 120 countries. We embrace the power of change to create value and shared success for our clients, people, shareholders, partners and communities.\n\nThe company has been operating in Greater China for over 30 years. Today, it has more than 17,000 people servicing clients across the region with offices in the cities including Beijing, Shanghai, Dalian, Chengdu, Guangzhou, Shenzhen, Hong Kong and Taipei. As a trusted Partner of Choice for digital transformation, Accenture is bringing more innovation to the business and technology ecosystems and helping Chinese enterprises and the government to embrace digitization and enhance global competitiveness to succeed in the new era.\n\nFor more information about Accenture, please visit its corporate homepage www.accenture.com and its Greater China homepage www.accenture.cn .\n\n\n\nAbout Accenture Interactive\uff1a\n\nAs one of the key services under Accenture, Accenture Interactive is in the\u00a0business of Experience. We connect deep human and business insights with the possibilities of technology to define and deliver new realities. We're committed to helping clients design, build, communicate and run Experiences that make peoples' lives better, more productive and more meaningful. Visit http://www.accentureinteractive.com to find out more about us.\n\nKey Responsibilities\n\nProvide the end-to-end project management from managing the client, resources, budget, timeline to deliverables\nResponsible for budgeting and overall planning, developments and to deliver different kinds of digital projects\nProficient to develop a detailed project plan and monitor progress against it\nCollaborate with internal teams to design, develop and implement digital projects\nCapable to handle impediment and provides alternatives\nDeliver projects on time with ensuring certain quality standards are met\nDevelop support documentation example with risk logs and requirement specifications\nCommunicate with the team and ensure all members are on board with delegated tasks\nHighlight potential risks or malfunctions and act proactively to resolve issues\nIncrease efficiency of team cooperation by improving communication and process\nSupport pre-sales activities including overall solutioning, project sizing, proposal preparation and presentation\n\nExperience, Attributes and Qualifications:\n\nUniversity degree holder in Information Technology, Information System, or related disciplines\n5+ years hands-on experience in large scale digital project management and software delivery\nExcellent organization and time management skills\nEffective communicator to different levels of stakeholders and can present complex ideas and technical details into layman terms\nDemonstrate a proactive working attitude to achieve common goals with good influential and negotiation skills\nStrong knowledge on different kinds of project management tools (e.g.: MS Project, JIRA, etc.)\nStrong oral and written English language skills\nProficiency in Cantonese and Putonghua (written and spoken) is an advantage\nScrum Master certification (CSM / PSM 1) is an advantage\nExperience in working in DevOps environment is an advantage", "employment_types": ["Full Time", "Permanent"], "selling_points": ["TMT Industry", "Attractive Package", "Big 4 Strategy Consulting candiate welcome"], "locations": ["Not Specified"], "categories": ["Professional Services", "Business Consultancy"], "post_time": "2022-01-08T08:17:59Z", "salary": {"currency": null, "max": null, "min": null, "period": "monthly", "term": null}, "salary_visible": false, "title_keywords": ["manager"], "responsibilities": ["collaborate with", "ideas", "software", "consulting", "monitor progress", "operations", "budgeting", "budget", "quality", "design", "communication", "teams", "develop", "management", "specifications", "documentation", "communicate with", "sales activities", "project plan", "project management", "planning"], "requirements": {"degrees": ["university degree", "master"], "majors": ["related disciplines", "information technology"], "languages": ["cantonese", "putonghua", "english", "chinese"], "language_level": ["advantage", "proficiency"], "hard_skills": ["devops", "information system", "make", "project management", "documentation"], "soft_skills": ["productive", "oral", "advanced", "responsible", "capable", "time management skills", "deep", "communication", "committed", "project management", "hands-on", "influential", "negotiation skills", "communicator", "proactive", "presentation", "detailed"], "languages_combined": [{"language": "cantonese", "language_level": ["proficiency", "advantage"]}, {"language": "putonghua", "language_level": ["proficiency", "advantage"]}, {"language": "english", "language_level": []}, {"language": "chinese", "language_level": []}]}, "experience_required": {"duration": ["5+ years"], "field": ["consulting", "devops", "design", "project management", "business", "digital"]}}, {"job_id": "100003009035207", "location_code": "hk", "company": "3 Screens Strategic Advisors Limited", "job_title": "Digital Business Director", "description": "Responsibilities:\n\nTo review margin analysis, billing disputes materials and other documentation for supporting management approval\nTo prepare analysis to show the market trend on pricing and discount policy for data services\nTo participate in ah-hoc project assigned by the supervisor\nTo provide administrative support to the team\n\nRequirements:\n\nBachelor's degree and or above\nMinimum 1-2 years of relevant experience, prior experience in global telecom market is preferred\nExcellent teamwork, hardworking, self-motived and able to work under pressure\nProficiency in MS Office applications and Chinese Word Processing\nExcellent written and verbal communication skills in both English and Chinese\n\nImmediate availability is preferred.\u00a0\n\nInterested parties please send your full resume with current and expected salary to us. Please also be reminded to indicate the reference number on the subject line.\n\nAll personal data collected will be used for recruitment and employment related purpose only.", "employment_types": ["Full Time", "Permanent"], "selling_points": [], "locations": ["Central"], "categories": ["Media & Advertising", "Account Servicing", "Professional Services", "Business Consultancy", "Marketing / Public Relations", "Digital Marketing"], "post_time": "2022-01-10T06:26:02Z", "salary": {"currency": "HKD", "max": 69999, "min": 55000, "period": "monthly", "term": null}, "salary_visible": true, "title_keywords": ["director"], "responsibilities": ["management", "data", "analysis", "review", "documentation", "provide administrative support"], "requirements": {"degrees": ["degree", "bachelor"], "majors": [], "languages": ["english", "chinese"], "language_level": ["proficiency", "excellent"], "hard_skills": ["chinese word processing", "ms office"], "soft_skills": ["communication skills", "teamwork", "hardworking", "work under pressure"], "languages_combined": [{"language": "english", "language_level": ["excellent"]}, {"language": "chinese", "language_level": ["proficiency", "excellent"]}]}, "experience_required": {"duration": ["minimum 1-2 years"], "field": ["relevant experience"]}}, {"job_id": "100003009035235", "location_code": "hk", "company": "3 Screens Strategic Advisors Limited", "job_title": "Digital Account Managers", "description": "Responsibilities:\u00a0\n\nPrepare and review tax compliance work in accordance to the relevant tax law and regulations\nSupport in half-year and year-end tax reporting preparation and review process\nSupport international tax and transfer pricing related issues\nWork closely with external tax advisor and colleagues in overseas to compute and analyze direct/indirect tax\nAssist in tax advisory for international business operations and expansion\nKeep abreast of the new tax laws & regulations and assess the impacts brought on different businesses\nCoordinate engagement and maintain productive working relationship with external tax advisor\nInvolve in preparation of tax proposals to senior management\nHandle ad-hoc projects as instructed by supervisor\n\nRequirements:\n\nDegree holder in Accounting/Finance or any other business related discipline and ideally with professional qualification (e.g. CPA, ACCA)\nAt least 4-5 years of corporate tax /indirect tax related working experience gained from Big 4 and/or MNCs is preferable; Candidate with less experience could be considered as Tax Officer\nKnowledge in regional/international tax, tax accounting is a plus\nExperiences from Telecom industry is definitely an advantage\nSelf-motivated with good tax accounting skill\nTeam player with strong interpersonal, research and presentation skills\nProficiency in MS Office applications and Chinese Word Processing\nGood command in both spoken Chinese & English; Putonghua is a MUST\nQuick learner and willing to work in dynamic environment\n\nInterested parties please send your full resume with current & expected salary\u00a0by clicking \"Apply Now\".\n\n\u00a0All personal data collected will be used for recruitment and employment related purpose only.", "employment_types": ["Full Time", "Permanent"], "selling_points": [], "locations": ["Central"], "categories": ["Media & Advertising", "Account Servicing", "Professional Services", "Business Consultancy", "Marketing / Public Relations", "Digital Marketing"], "post_time": "2022-01-10T06:27:48Z", "salary": {"currency": "HKD", "max": 34999, "min": 20000, "period": "monthly", "term": null}, "salary_visible": true, "title_keywords": [], "responsibilities": ["tax", "year-end", "regulations", "reporting", "ad-hoc projects", "operations", "compliance", "review", "coordinate", "maintain", "senior management"], "requirements": {"degrees": ["degree holder"], "majors": ["business", "finance", "accounting"], "languages": ["putonghua", "english", "chinese"], "language_level": ["proficiency", "good command"], "hard_skills": ["acca", "plus", "chinese word processing", "cpa", "dynamic", "ms office"], "soft_skills": ["self-motivated", "dynamic environment", "quick learner", "presentation skills", "team player", "interpersonal"], "languages_combined": [{"language": "putonghua", "language_level": []}, {"language": "english", "language_level": ["good command"]}, {"language": "chinese", "language_level": ["proficiency", "good command"]}]}, "experience_required": {"duration": ["at least 4-5 years"], "field": ["related", "big 4"]}}, {"job_id": "100003009035226", "location_code": "hk", "company": "3 Screens Strategic Advisors Limited", "job_title": "Digital Account Executives", "description": "Responsibilities:\n\nSet target for international business and individual business unit, track and analyze the performance of each unit, research and analyze incentive policies for key projects and products\nDevelop and improve the work mechanism, coordinate across divisions to promote Company services and products to overseas market, enhance oversea subnet product capabilities\nResearch key issues fronted by international business\nSet up and refine policies and process on international business development and support\nComplete other tasks assigned by management\n\nRequirement:\n\nBachelor degree or above\nMinimum 4 years relevant working experience\nPrior experience in mobile market or Government and Enterprise market in Telecommunication environment is a plus\nOpen-minded, responsive, attention to details and able to work under pressure\nStrong communication skill and able to work as a team\nGood command of spoken and written Chinese and English, proficiency in Putonghua is an advantage\nProficient in MS office applications and Chinese Word Processing\n\nInterested parties please apply in\u00a0full resume with current and expected salary\u00a0by e-mail to\u00a0hr\u00a0@\u00a0cmi.chinam obil e.com.\u00a0 Please indicate the reference in the subject line.\n\nAll personal data collected will be used for recruitment and employment related purpose only.", "employment_types": ["Full Time", "Permanent"], "selling_points": [], "locations": ["Central"], "categories": ["Media & Advertising", "Account Servicing", "Professional Services", "Business Consultancy", "Marketing / Public Relations", "Digital Marketing"], "post_time": "2022-01-10T06:27:18Z", "salary": {"currency": "HKD", "max": 19999, "min": 14000, "period": "monthly", "term": null}, "salary_visible": true, "title_keywords": [], "responsibilities": ["management", "policies", "develop", "coordinate", "other tasks"], "requirements": {"degrees": ["degree or above", "bachelor"], "majors": [], "languages": ["putonghua", "english", "chinese"], "language_level": ["advantage", "proficiency", "good command", "proficient"], "hard_skills": ["mobile", "plus", "chinese word processing", "ms office"], "soft_skills": ["work as a team", "open-minded", "communication skill", "attention to details", "responsive", "work under pressure"], "languages_combined": [{"language": "putonghua", "language_level": ["proficiency", "advantage", "good command"]}, {"language": "english", "language_level": ["advantage", "good command"]}, {"language": "chinese", "language_level": ["proficiency", "advantage", "good command", "proficient"]}]}, "experience_required": {"duration": ["minimum 4 years"], "field": ["relevant working experience"]}}, {"job_id": "100003009038191", "location_code": "hk", "company": "Lauris Walton International Limited", "job_title": "Associate / Senior Associate - Forensic Accounting / Restructuring / Insolvency", "description": "Your Bright Future Starts Here\n\nThe Global Graduate Trainee Program is designed as a 12-month fast-track career development for talented university graduates in our regional office. We aim to unleash your potential and lead you a promising career at China Mobile International Limited (CMI) with the following program details.\n\nStart YOUR career journey with CMI by 3 Streams:\n\nTechnology and Network Stream\u00a0 (e.g. Solution Management, Project Management, Network Planning & Development, Implementation Engineer, Information Technology, etc)\nBusiness Stream\u00a0 (e.g. Sales & Business Development, Product Management, Marketing & Market Analysis, Business Operations Support, etc.)\nGeneral Supporting Stream\u00a0 (e.g. Human Resources, Finance & Accounting, Merge & Acquisition, Procurement, Legal, etc.)\n\nProgram Structure:\n\nIntensive learning and development program to acquire core job knowledge and skillsets\nFor Hong Kong applicants, he/she will be based in Hong Kong Global Headquarters with International assignment participation\nOverseas Working Opportunities and Job Rotation in global operations\nValuable opportunity for personal development and catch the exponential growth of CMI\nCross-departmental and international exposure through various projects to understand company business and operations\nDirect coaching and mentoring provided by managers\n\nExploring by Visit and Activities:\n\nGlobal Network Center Visit\nChina Mobile Southern Base Visit\nStrategic Partner Learning Tour\nCMCC Learning Tour\nCMI Corporate Social Responsibility Activities\n\nQualification\uff1a\n\n\n\nFinal year students or recent graduates from Business, Engineering and Information Technology or related disciplines\nEntrepreneurial and innovative\nPassionate in the IT & Telecommunications industry\nExcellent command of written and spoken English\nKnowledge of Mandarin and Cantonese will be an advantage\n\nApplication Method:\n\nPlease submit your application through our online application system on or before 13 March 2022 (Sunday)\n(https://careers.cmi.chinamobile.com/#/recruitIndex?channel=school&location=school&channelId=1001S31000000003WCK6&publishId=1001S3100000000GI80Y&isApplicant=true)\n\nYou may visit our Career Page for more details of GGT 2022 Program.(https://www.cmi.chinamobile.com/corporate-information/who-you-can-be).\n\nFor any enquiries on our Global Graduate Trainee Program, please contact us by email, HR.GTProgram @ cmi.chinamobile.com and state the apply location on email subjects, e.g. \"Hong Kong\u00a0- Global Graduate Trainee\".", "employment_types": ["Full Time", "Permanent"], "selling_points": [], "locations": ["Not Specified"], "categories": ["Accounting", "Audit", "Others", "Professional Services", "Business Consultancy"], "post_time": "2022-01-11T05:58:25Z", "salary": {"currency": null, "max": null, "min": null, "period": "monthly", "term": null}, "salary_visible": false, "title_keywords": ["senior associate", "associate", "accounting"], "responsibilities": ["management", "operations", "hr", "implementation", "application system", "project management", "market analysis", "contact", "career development", "planning"], "requirements": {"degrees": [], "majors": [], "languages": ["cantonese", "english", "mandarin"], "language_level": ["advantage", "excellent"], "hard_skills": ["mobile", "project management", "analysis", "application system"], "soft_skills": ["passionate", "project management", "learning", "innovative"], "languages_combined": [{"language": "cantonese", "language_level": ["advantage"]}, {"language": "english", "language_level": ["excellent"]}, {"language": "mandarin", "language_level": ["advantage"]}]}, "experience_required": {"duration": [], "field": []}}, {"job_id": "100003009036043", "location_code": "hk", "company": "ELEVATE Hong Kong Holdings Limited", "job_title": "Sourcing Specialist", "description": "Job Responsibilities:\n\nManage bank account opening/ closing/ signature updates for Hong Kong and overseas entities\nResponsible for online banking platforms setting\nHandle bank transactions including loans, LC, guarantees\nPlan and modernize treasury process and policy\nResponsible for liaison with internal and external auditors\nEnsure the compliance of Treasury policy and SOX\nAssist in formulating and implementing hedging plans and its execution\nHandle ad hoc projects assigned\n\nJob Requirements:\n\nDegree holder in Accounting, Finance or related disciplines\nQualified Accountant under ACCA/HKICPA\nAt least 5 years relevant treasury management experience, preferably from sizeable multinational corporations or financial institutions\nSolid experience in cash management and foreign exchange\nGood knowledge in hedging, risk management, financial products and derivatives Knowledge in accounting for derivatives and hedging preferred\nProficiency in excel VBA, Powerpoint, Word (Chinese & English),\nPositive, self-motivated, good analytical skills and communication skills\nGood interpersonal skills\nGood command of spoken and written Chinese and English, proficiency in Putonghua is a MUST\nCandidates with less experience would be considered as Senior Accountant\n\nInterested parties please send your full resume with current & expected salary\u00a0by clicking \"Apply Now\".\n\nAll personal data provided will be used for consideration of your job application only.\n\nManage bank account opening/closing/signature updates for Hong Kong and overseas entities", "employment_types": ["Full Time", "Permanent"], "selling_points": ["Research and identify new and potential suppliers", "Inspect and evaluate the quality of quotes", "3+ years of experience in related industry"], "locations": ["Quarry Bay"], "categories": ["Professional Services", "Business Consultancy", "Merchandising & Purchasing", "Sundries", "Others"], "post_time": "2022-01-10T09:10:50Z", "salary": {"currency": null, "max": null, "min": null, "period": "monthly", "term": null}, "salary_visible": false, "title_keywords": ["specialist"], "responsibilities": ["account opening", "compliance", "transactions", "ad hoc projects", "plan", "banking", "plans", "external auditors"], "requirements": {"degrees": ["degree holder"], "majors": ["related disciplines", "finance", "accounting"], "languages": ["putonghua", "english", "chinese"], "language_level": ["proficiency", "good command"], "hard_skills": ["excel", "acca", "vba", "word", "powerpoint", "analytical skills", "hkicpa", "exchange"], "soft_skills": ["communication skills", "self-motivated", "analytical skills", "interpersonal skills", "positive"], "languages_combined": [{"language": "putonghua", "language_level": ["proficiency", "good command"]}, {"language": "english", "language_level": ["good command"]}, {"language": "chinese", "language_level": ["proficiency", "good command"]}]}, "experience_required": {"duration": ["at least 5 years"], "field": ["management", "financial institutions", "senior accountant"]}}, {"job_id": "100003009037696", "location_code": "hk", "company": "Moses Wills Limited", "job_title": "Sustainability Manager (Team Lead)", "description": "Responsibilities:\n\nDesign and Optimization the user experience and for mCloud platform, provide high quality GUI design timely\nEvaluate and balance business needs with user goals, improve the business interactive process.\nWork closely with RD team, able to conduct risk control and resource management, meet project timeline and ensure the design delivery.\nCarry out routinely user experience analysis and improvements for the platform to meet internal and customer needs.\nWork with overseas customers/co-workers during non-office hour if necessary.\nCoordinate with internal /external parties to enhance the design level if necessary.\nParticipate in the ad-hoc assignment if needed\n\nRequirements:\n\nBachelor's degree or above\nHCI, industrial design, information design, computer and other related majors\nMinimum 3 years of experience, preferable in relevant industry, Carriers or other ICT service providers;\nIndependent design experience in medium and large-scale projects and successful cases is preferred;\nSolid design skills, able to explore cutting-edge design trends.\nProficient in using office toolkit and design software, e.g. Photoshop, Sketch, Adobe illustrator, Axure and other design software.\nBasic understanding of various front-end technologies (including HTML / CSS / JavaScript, etc.)\nExcellent teamwork skills, self-motived and able to work under pressure\nOpen-minded, ownership, be creative and think out of the box;\nCurious about cutting-edge user research theories and design tr'ends;\nGood communication and coordination skills, certain management experience;\nExcellent written and verbal communication skills in both English and Mandarin;\nStrong logical thinking, be able to produce excellent design schemes in complex business scenarios; Technical foundation is preferred\n\n** Candidate with less experience will also be considered.\n\nInterested parties please send your full resume with current & expected salary to\u00a0hr@ cmi.chinamobile.com. Please indicate the reference number in the subject line.\n\nAll personal data collected will be used for recruitment and employment related purpose only", "employment_types": ["Full Time", "Permanent"], "selling_points": ["Environmental consulting firm", "min. 6 yrs  working experiences", "Knowledge in sustainability and climate related"], "locations": ["Not Specified"], "categories": ["Accounting", "Consulting", "Professional Services", "Business Analysis / Data Analysis", "Business Consultancy"], "post_time": "2022-01-11T03:32:42Z", "salary": {"currency": "HKD", "max": 44999, "min": 35000, "period": "monthly", "term": null}, "salary_visible": true, "title_keywords": ["manager", "lead"], "responsibilities": ["ad-hoc", "control", "management", "analysis", "external parties", "quality", "user experience", "design", "coordinate with", "evaluate"], "requirements": {"degrees": ["degree or above", "bachelor"], "majors": [], "languages": ["english", "mandarin"], "language_level": ["excellent"], "hard_skills": ["basic", "html", "adobe illustrator", "javascript", "css", "photoshop"], "soft_skills": ["communication skills", "independent", "coordination skills", "cutting-edge", "open-minded", "teamwork", "communication", "creative", "work under pressure"], "languages_combined": [{"language": "english", "language_level": ["excellent"]}, {"language": "mandarin", "language_level": ["excellent"]}]}, "experience_required": {"duration": ["minimum 3 years"], "field": ["management", "design"]}}, {"job_id": "100003009042917", "location_code": "hk", "company": "Tahoe Life Insurance Company Limited", "job_title": "Head of Risk Management and Control", "description": "\u00a0Job Description:\n\nIP network configuration, including switches and routers of Cisco, Huawei, Juniper\nManage network resources, including POPs, connectivity capacity and network devices\nParticipate in network projects for smooth implementation\nCoordinate with external vendors for delivery of required services\nSupport Management on ad hoc report compilation\u00a0\n\n\u00a0Job\u00a0Requirement:\n\nBachelor Degree or above\u00a0in Information Technology, Computer Science or other related disciplines\nMinimum\u00a03 years of experience; with telecom experiences are preferred\nKnowledge of IP network, IP routing knowledge or MPLS, VPN\nOrganized, proactive and\u00a0a good team-player\nMature, independent and problem-solver\u00a0\nExcellent written and spoken English, Chinese and Mandarin\n\nInterested parties please send your full resume with current & expected salary\u00a0by e-mail to\u00a0hr @ cmi.chinamobile.com.\u00a0 Please indicate the reference in the subject line.\n\nAll personal data provided will be used for consideration of your job application only.", "employment_types": ["Full Time", "Permanent"], "selling_points": ["Report to CEO", "10+ yrs\u2019 exp. in insurance industry", "Risk Management"], "locations": ["Tsim Sha Tsui"], "categories": ["Professional Services", "Business Consultancy", "Management", "General Management", "Insurance", "Others"], "post_time": "2022-01-12T09:14:37Z", "salary": {"currency": null, "max": null, "min": null, "period": "monthly", "term": null}, "salary_visible": false, "title_keywords": [], "responsibilities": ["management", "configuration", "ad hoc report", "coordinate with", "implementation"], "requirements": {"degrees": ["degree or above", "bachelor"], "majors": ["related disciplines", "computer science", "information technology"], "languages": ["english", "chinese", "mandarin"], "language_level": ["excellent"], "hard_skills": ["ip", "vpn"], "soft_skills": ["organized", "independent", "team-player", "mature", "proactive"], "languages_combined": [{"language": "english", "language_level": ["excellent"]}, {"language": "chinese", "language_level": ["excellent"]}, {"language": "mandarin", "language_level": ["excellent"]}]}, "experience_required": {"duration": ["minimum 3 years"], "field": []}}, {"job_id": "100003009043740", "location_code": "hk", "company": "Klook Travel Technology Limited", "job_title": "Company Secretarial Lead", "description": "Responsibilities:\n\nDesign, plan and participate in project related to\u00a0development of\u00a0international network which consists of PoP sites, data centers, internet and internal IP backbones.\nTrack\u00a0network project progress\u00a0including\u00a0solution evaluation and selection, migration, expansion, feature development, software upgrade.\nProvide technical support relate to mobile service.\nProvide support in daily operation and emergency\u00a0services\u00a0\n\nRequirements:\n\nUniversity degree in Electrical/ Telecommunications or related disciplines, with definite advantage by processing relevant professional certification\nMinimum 3 years or above relevant experience in Mobile and IP network engineering\nExposure to\u00a0the design, planning,\u00a0implementation, maintenance and support of Mobile or IP network is an advantage\nProficiency in MS Office applications and Chinese Word Processing\nGood command of spoken and written Chinese and English, proficiency in Putonghua is an advantage\n\nInterested parties please send your full resume with current & expected salary by email to hr@ cmi.chinamobile.com.\u00a0Please indicate the reference number in the subject line.\n\nAll personal data provided will be used for consideration of your job application only.", "employment_types": ["Full Time"], "selling_points": ["Handling full range of company secretarial duties", "Leading new entity set up", "Handling statutory compliance"], "locations": ["Not Specified"], "categories": ["Professional Services", "Business Consultancy", "Company Secretary", "Information Technology (IT)", "Others"], "post_time": "2022-01-13T01:45:02Z", "salary": {"currency": null, "max": null, "min": null, "period": "monthly", "term": null}, "salary_visible": false, "title_keywords": ["lead"], "responsibilities": ["provide support", "software", "data", "technical support", "daily operation", "project progress", "design", "plan", "evaluation", "migration"], "requirements": {"degrees": ["university degree"], "majors": ["related disciplines"], "languages": ["putonghua", "english", "chinese"], "language_level": ["advantage", "proficiency", "good command"], "hard_skills": ["chinese word processing", "maintenance", "mobile", "ip", "processing", "ms office"], "soft_skills": [], "languages_combined": [{"language": "putonghua", "language_level": ["proficiency", "advantage", "good command"]}, {"language": "english", "language_level": ["advantage", "good command"]}, {"language": "chinese", "language_level": ["proficiency", "advantage", "good command"]}]}, "experience_required": {"duration": ["minimum 3 years"], "field": ["relevant experience", "engineering"]}}, {"job_id": "100003009042095", "location_code": "hk", "company": "Red Consultancy Services", "job_title": "Assistant / Legal Manager (Sizable IT Group)", "description": "Responsibilities:\n\nDesign the architecture of operation data analysis according to internal or customer needs, provide daily operation data analysis support.\nManage and provide regular operation data analysis and product quality report to meet internal and customer needs.\nResearch operation data analysis and product quality management methods.\nConduct risk management, procedure optimization and escalate all outstanding issue during provisioning stage.\nEstablish and maintain a good relationship with customers, internal teams.\nCoordinate with internal parties to enhance the quality level if necessary.\nConsolidate, revise and update internal reports weekly and monthly.\nParticipate in the ad-hoc assignment if needed\n\nRequirements:\n\nBachelor's degree or above\nOperation data analysis and product quality management experiences are preferred\nMinimum 5 years of experience;\nDeeply understand operation data analysis and product quality management methods.\nFamiliar with the tools of operation data analysis and product quality management.\nAbility of operation data analysis and product quality management scheme and architecture design and implementation.\nExcellent teamwork skills, hardworking, self-motived and able to work under pressure\nExcellent written and verbal communication skills in both English and Mandarin\n\nInterested parties please send your full resume with current and expected salary to hr @ cmi.chinamobile.com . Please indicate the reference number in the subject line.\n\nAll personal data provided will be used for consideration of your job application only.", "employment_types": ["Full Time", "Permanent"], "selling_points": ["In-hse Legal Manager- Legal & Regulatory (MNC)", "Attractive package + friendly team + good career", "Overseas licenses and bus. strategic legal advices"], "locations": ["Not Specified"], "categories": ["Professional Services", "Business Consultancy", "Information Technology (IT)", "Others", "Legal & Compliance"], "post_time": "2022-01-12T06:05:16Z", "salary": {"currency": null, "max": null, "min": null, "period": "monthly", "term": null}, "salary_visible": false, "title_keywords": ["manager", "assistant"], "responsibilities": ["ad-hoc", "management", "quality", "daily operation", "design", "teams", "data analysis", "good relationship", "coordinate with", "maintain", "reports", "architecture", "internal parties", "report"], "requirements": {"degrees": ["degree or above", "bachelor"], "majors": [], "languages": ["english", "mandarin"], "language_level": ["excellent"], "hard_skills": ["analysis", "scheme"], "soft_skills": ["communication skills", "teamwork", "hardworking", "work under pressure"], "languages_combined": [{"language": "english", "language_level": ["excellent"]}, {"language": "mandarin", "language_level": ["excellent"]}]}, "experience_required": {"duration": ["minimum 5 years"], "field": ["data analysis", "operation", "quality management"]}}, {"job_id": "100003009041425", "location_code": "hk", "company": "Ahan Thai", "job_title": "\u897f\u6cf0\u83dc\u9910\u5ef3\u98f2\u54c1\u6c96\u8abf\u54e1", "description": "Responsibilities:\n\nPrepare and manage product planning, strategies and development\nSupport existing and new product life-cycle, and all related management work, such as preparing product portfolios, P&L models, business forecasts, budget formulation, service improvement plan, contractual SLA details, MSA and sales order documentation, product workflow, etc.\nFormulate and implement pricing/promotion offer strategies and policies\nManage global partners, vendors and suppliers programs\nConduct market researches, prepare product status analysis reports and recommendations for management review, e.g. monthly P&L reports as well as provide product training and assist marketing events, etc.\nSupport important Sales activities, such as preparing Sales collateral materials and pre-sales solution\n\nRequirements:\n\nBachelor's degree or above in related disciplines\nMinimum 3 years of experience in Telecom and/or IDC industries\nSolid experience on product development and management\nExcellent teamwork skills, hardworking, self-motived and able to work under pressure\nProficiency in MS\u00a0 Office applications and Chinese Word Processing\nGood command of spoken and written Chinese and English, proficiency in Putonghua is an advantage\n\nCandidate with less experience will be considered as Senior Product Specialist.\n\nInterested parties please send your full resume with current & expected salary\u00a0by e-mail to\u00a0hr @ cmi.chinamobile.com.\u00a0 Please indicate the reference in the subject line.\n\nAll personal data provided will be used for consideration of your job application only.", "employment_types": ["Full Time"], "selling_points": [], "locations": ["Kwun Tong"], "categories": ["Professional Services", "Business Consultancy", "Insurance", "Others", "Others", "Student / Fresh Graduate / No Experience"], "post_time": "2022-01-12T03:52:58Z", "salary": {"currency": null, "max": null, "min": null, "period": "monthly", "term": null}, "salary_visible": false, "title_keywords": [], "responsibilities": ["marketing events", "management", "sales activities", "analysis reports", "policies", "budget", "p&l", "reports", "plan", "documentation", "management review", "planning"], "requirements": {"degrees": ["degree or above", "bachelor"], "majors": ["related disciplines"], "languages": ["putonghua", "english", "chinese"], "language_level": ["advantage", "proficiency", "good command"], "hard_skills": ["chinese word processing", "office applications"], "soft_skills": ["teamwork", "hardworking", "work under pressure"], "languages_combined": [{"language": "putonghua", "language_level": ["proficiency", "advantage", "good command"]}, {"language": "english", "language_level": ["advantage", "good command"]}, {"language": "chinese", "language_level": ["proficiency", "advantage", "good command"]}]}, "experience_required": {"duration": ["minimum 3 years"], "field": ["product development", "management"]}}, {"job_id": "100003009035053", "location_code": "hk", "company": "Moses Wills Limited", "job_title": "Recruitment Consultant (Basic Salary plus Commission)", "description": "Job Responsibilities:\n\nPerform operation and maintenance support covering Mobile network system\nMonitor the mobile network and ensure proper system performance\nTroubleshoot & resolve the incidents and problem tickets according to Service Level Agreement\nInteract with internal stakeholders and external vendors to resolve network issues\n\n\nJob\u00a0Requirements:\n\nDegree in Electronics, Information engineering or Telecommunications is preferred\nMinimum 3-year relevant working experience. Candidates with lesser experience will also be considered.\nFamiliar with data\u00a0communication and\u00a0mobile network\nPossess IT/Telecom related certificates is a definite advantage\nPositive attitude, self-motivated with good communication and interpersonal skills\nGood command of spoken and written English, Chinese and Mandarin\nAble to perform shift duty (7x24 shift)\n\nInterested parties please apply in full resume with working experience, current and expected salary together with a contact telephone number by email to hr @ cmi.chinamobile.com.\n\nAll personal data collected will be used for recruitment and employment-related purpose only.", "employment_types": ["Full Time"], "selling_points": ["experience in recruitment preferred", "Start-up Culture", "Local recruitment firm"], "locations": ["Lai Chi Kok"], "categories": ["Professional Services", "Business Consultancy", "Sales, CS & Business Devpt", "Business Development", "Admin & HR", "Recruitment / Executive Search"], "post_time": "2022-01-10T05:39:30Z", "salary": {"currency": null, "max": null, "min": null, "period": "monthly", "term": null}, "salary_visible": false, "title_keywords": ["recruitment consultant"], "responsibilities": ["network issues", "maintenance support", "monitor", "troubleshoot"], "requirements": {"degrees": ["degree"], "majors": ["engineering"], "languages": ["english", "chinese", "mandarin"], "language_level": ["good command"], "hard_skills": ["mobile"], "soft_skills": ["communication", "positive attitude", "self-motivated", "communication and interpersonal skills"], "languages_combined": [{"language": "english", "language_level": ["good command"]}, {"language": "chinese", "language_level": ["good command"]}, {"language": "mandarin", "language_level": ["good command"]}]}, "experience_required": {"duration": ["minimum 3-year"], "field": ["relevant working experience"]}}, {"job_id": "100003009034585", "location_code": "hk", "company": "\u51dd\u92b7\u6709\u9650\u516c\u53f8", "job_title": "Senior Account Executive", "description": "Responsibilities:\n\n\nResponsible for BOSS (business operation support system) maintenance and support, mainly on web module\nProvide leadership in the design, development, testing, implementation, and maintenance of web-based information systems\nCollecting, identifying, and analyzing business requirements\nCoordinating projects and operation tasks with vendor\nConducting UAT and providing training to internal or external users\n\nRequirements:\n\nBachelor or above in Computer Science/Engineering or other IT related disciplines\n2+ years of work experiences in IT or telecommunication industry\nExperience in business support systems such as CRM, Order Processing, experience in web-based application and API is an advantage\nExperience in using Google Analytics, Drupal, Vue, React\nGood knowledge on HTML, CSS, JavaScript, SQL, PHP, JSON, Python\nFamiliar with DBMS and software development lifecycle. Experience in development or maintenance of backend service and database procedure is an advantage\nPositive, persistent, \u201ccan do\u201d personality, passionate with continuous improvement\nGood verbal and written English and Chinese. Fluent Putonghua is a plus\nCandidates with less experience will be considered as Application Engineer\n\nInterested parties please send your full resume with current & expected salary by clicking \"Apply Now\".\u00a0\u00a0\n\nAll personal data provided will be used for consideration of your job application only.", "employment_types": ["Full Time"], "selling_points": [], "locations": ["Ngau Tau Kok"], "categories": ["Professional Services", "Business Consultancy", "Sales, CS & Business Devpt", "Account Servicing", "Marketing / Public Relations", "Digital Marketing"], "post_time": "2022-01-10T03:44:37Z", "salary": {"currency": "HKD", "max": 16999, "min": 14000, "period": "monthly", "term": null}, "salary_visible": true, "title_keywords": ["senior account executive"], "responsibilities": ["business operation", "uat", "maintenance", "systems", "implementation", "design", "testing"], "requirements": {"degrees": ["bachelor"], "majors": ["related disciplines", "it", "engineering", "computer science"], "languages": ["putonghua", "english", "chinese"], "language_level": ["fluent", "good"], "hard_skills": ["google analytics", "plus", "web", "react", "php", "maintenance", "html", "sql", "dbms", "javascript", "order processing", "python", "css"], "soft_skills": ["passionate", "persistent", "positive"], "languages_combined": [{"language": "putonghua", "language_level": ["fluent"]}, {"language": "english", "language_level": ["good"]}, {"language": "chinese", "language_level": ["good"]}]}, "experience_required": {"duration": ["2+ years"], "field": ["maintenance", "business support", "development", "it", "order processing", "database"]}}, {"job_id": "100003009037823", "location_code": "hk", "company": "Ray White (Hong Kong) Limited", "job_title": "Visa Processing Consultant", "description": "Responsibilities:\n\nCooperate with cloud providers such as AWS/ Huawei to build CMI's edge computing products\nFamiliar with pre-sale, in-sale and post-sale processes of the cloud product\nInternal training for sales and pre-sales team\nProduct supporting for sales and pre-sales team\nProcess management and pricing of edge computing products\nBusiness model design of CMI's edge computing products\nResearch the industry development trend of public cloud, private cloud and hybrid cloud\nResearch customer needs and business competitor's cloud products, and make forward-looking cloud product product innovation\nOther ad hoc duties as assigned\u00a0\n\nRequirements\n\nBachelor degree or above\nMinimum 3 years of relevant experience\u00a0\nProfessional qualification in cloud production certification,\u00a0e.g. AWS, Azure is preferred\nExcellent teamwork skills, hardworking, self-motivated and able to work under pressure\nExcellent written and verbal communication skills in both English and Chinese\nDeeply understand the business model of Cloud Computing products\nFamiliar with service process of cloud product\u00a0\n\nInterested parties please send your full resume with current & expected salary to hr @ cmi. chinamobile. com. Please indicate the reference number in the subject line.\n\nAll personal data collected will be used for recruitment and employment related purpose only", "employment_types": ["Full Time", "Permanent"], "selling_points": ["Preparation of client Australian visa applications", "Draft detailed case submissions", "Handle general correspondence"], "locations": ["Tsim Sha Tsui"], "categories": ["Professional Services", "Business Consultancy", "Sales, CS & Business Devpt", "Customer Service - Manager", "Legal & Compliance"], "post_time": "2022-01-11T03:57:56Z", "salary": {"currency": null, "max": null, "min": null, "period": "monthly", "term": null}, "salary_visible": false, "title_keywords": ["consultant"], "responsibilities": ["ad hoc duties", "management", "design", "sales team", "cooperate with"], "requirements": {"degrees": ["degree or above", "bachelor"], "majors": [], "languages": ["english", "chinese"], "language_level": ["excellent"], "hard_skills": ["azure", "aws"], "soft_skills": ["communication skills", "self-motivated", "teamwork", "hardworking", "work under pressure"], "languages_combined": [{"language": "english", "language_level": ["excellent"]}, {"language": "chinese", "language_level": ["excellent"]}]}, "experience_required": {"duration": ["minimum 3 years"], "field": ["relevant experience"]}}, {"job_id": "100003009037636", "location_code": "hk", "company": "Michael Page", "job_title": "Governance and Compliance Director - Business Service Provider", "description": "Responsibilities:\n\nSupport Sales team in providing pre-sales solutions and assistance during sales cycle\nIdentifies customer\u2019s needs and technical requirements to derive Data Center related solutions\nProvides support to customers pertaining to global deployments of solution design and deliverables\nProject management in developing the deployment schedule and ensure implementation according to schedule and minimize potential risk\nComplete service acceptance and project handover to operation team\u00a0\n\nRequirements:\n\nUniversity degree in Electrical Engineering/ Mechanical Engineering related disciplines\nMinimum 5 years or above relevant experience in\u00a0Pre-Sales\u00a0/ Facility Management\nExperience in Telecommunications, Networking, Internet, Data Center are preferred\nExcellent Communication and problem-solving skills\nFlexible, Result-oriented, and Organized\nProficiency in MS Office applications and Chinese Word Processing\nGood command of spoken and written Chinese and English, proficiency in Putonghua is an advantage\n\nInterested parties please send your full resume with current & expected salary by email to hr@ cmi.chinamobile.com.\u00a0Please indicate the reference number in the subject line.\n\nAll personal data provided will be used for consideration of your job application only.", "employment_types": ["Full Time", "Permanent"], "selling_points": ["Exciting new headcount !", "Global Compliance role !", "Open to compliance consulting background !"], "locations": ["Not Specified"], "categories": ["Accounting", "Consulting", "Professional Services", "Business Consultancy", "Legal & Compliance"], "post_time": "2022-01-11T03:20:24Z", "salary": {"currency": "HKD", "max": 119999, "min": 90000, "period": "monthly", "term": null}, "salary_visible": true, "title_keywords": ["director"], "responsibilities": ["data", "developing", "design", "implementation", "project management", "project handover", "sales team", "schedule"], "requirements": {"degrees": ["university degree"], "majors": ["related disciplines", "electrical engineering", "mechanical engineering"], "languages": ["putonghua", "english", "chinese"], "language_level": ["advantage", "proficiency", "good command"], "hard_skills": ["problem-solving skills", "chinese word processing", "ms office"], "soft_skills": ["flexible", "organized", "communication", "problem-solving skills", "result-oriented"], "languages_combined": [{"language": "putonghua", "language_level": ["proficiency", "advantage", "good command"]}, {"language": "english", "language_level": ["advantage", "good command"]}, {"language": "chinese", "language_level": ["proficiency", "advantage", "good command"]}]}, "experience_required": {"duration": ["minimum 5 years"], "field": ["telecommunications", "management", "relevant experience"]}}, {"job_id": "100003009041522", "location_code": "hk", "company": "BUPA Asia Limited", "job_title": "Privacy Risk and Controls Manager", "description": "Responsibilities:\n\n\nDraft, review and negotiate a broad range of agreements, with a primary focus on tech wholesale service, network procurement and maintenance, information technology solutions, but also including marketing, general procurement such as software installation, licenses and support, etc.\u00a0\nTackle local and overseas regulatory affairs, such as telecommunications license application, renewal, filing of statutory returns, liaison with regulators, other regulatory compliance matters.\nAssist in developing and implementing improvements to business process to support the contracting process and ongoing compliance\nAdvise internal clients of company processes, contract status, and make recommendations based on company policies and standards\nRegularly contribute to and refine templates, playbooks, legal training, and guidance documents, archive the latest contracts and agreement templates\nConduct legal and regulatory research, support and analysis\nParticipate in the ad-hoc assignment if needed\n\nRequirements:\n\n\nBachelor of Laws (LLB) in Common Law\nMinimum 7 years of relevant working experience strongly preferred in telecommunications or related industry. Experience in telecommunications regulatory affairs is a merit.\nSelf-motivated, attention to details with strong sense of responsibility, and able to work independently\nGood command of spoken and written Chinese and English\n\nCandidate with less experience may be considered in Junior position.\n\n\n\n\nInterested parties please send your full resume with current and expected salary to hr @ cmi.chinamobile.com . Please indicate the reference number in the subject line.\u00a0\n\nAll personal data collected will be used for recruitment and employment related purpose only.\n\nParticipate in public consultations initiated by local governments and regulators, and prepare regulatory submission, compliance, reports", "employment_types": ["Full Time", "Permanent"], "selling_points": ["5+ years of related exp", "Implement Risk Management Framework", "Oversight of the Privacy Maturity Uplift Programme"], "locations": ["Not Specified"], "categories": ["Professional Services", "Business Consultancy", "Insurance", "Others", "Banking / Finance", "Risk Management"], "post_time": "2022-01-12T03:59:41Z", "salary": {"currency": null, "max": null, "min": null, "period": "monthly", "term": null}, "salary_visible": false, "title_keywords": ["manager"], "responsibilities": ["make recommendations", "installation", "guidance", "ad-hoc", "software", "maintenance", "policies", "contracts", "review", "compliance", "developing", "analysis", "business process", "license application", "contracting"], "requirements": {"degrees": ["bachelor"], "majors": ["laws", "law"], "languages": ["english", "chinese"], "language_level": ["good command"], "hard_skills": [], "soft_skills": ["self-motivated", "work independently", "attention to details", "sense of responsibility"], "languages_combined": [{"language": "english", "language_level": ["good command"]}, {"language": "chinese", "language_level": ["good command"]}]}, "experience_required": {"duration": ["minimum 7 years"], "field": ["telecommunications", "regulatory affairs", "relevant working experience", "related"]}}, {"job_id": "100003009033785", "location_code": "hk", "company": "APAC Asset Valuation and Consulting Limited", "job_title": "(Fresh Graduates Welcomed) Assistant Valuer / Valuer", "description": "Responsibilities:\n\nTo achieve sales & revenue targets by identifying and securing business opportunities from prospective enterprise customers\n\nResponsible and liaise with parties in headquarters and overseas offices to drive the global opportunities and global deals.\nThe key person to identify and develop new business opportunities\u00a0of large\u00a0enterprises\nFormulate a Sales & Marketing Strategy and assist department head to deploy effective marketing events to our targeted customers.\nEstablish, develop and maintain effective business relationships with nominated accounts and develop long term partnership with them.\nStrengthen customer confidence into loyalty.\nReview & analyze the market situation and report to senior management periodically.\n\n\u00a0Requirements:\n\nMinimum 5 years sales experience in IT & Telecom industry.\n\nProven sales track record with Enterprise Clients\u00a0is preferred. Prior experience in government & public sector / Chinese enterprises is a definite advantage.\nSound knowledge in selling Telecom products (e.g. MPLS, IP Transit, VPN, Data Centre, etc.) and ICT Solutions.\nHands on experiences of developing new markets.\nBe able to establish solid relationship with senior executive contact\nExcellent interpersonal, organization, negotiation and presentation skills\nPositive mindset, result-oriented, high level of initiative and integrity\nGood command of both spoken and written English and Chinese. Fluency in Putonghua is a must\nCandidates with less experience will be considered as Assistant Sales Manager\n\nInterested parties please apply in\u00a0full resume with current and expected salary\u00a0by e-mail to\u00a0hr\u00a0@\u00a0cmi.\u00a0chinamobile.\u00a0com.\u00a0 Please indicate the reference in the subject line.\n\nAll personal data collected will be used for recruitment and employment related purpose only.", "employment_types": ["Full Time", "Permanent", "Temporary", "Contract", "Internship"], "selling_points": [], "locations": ["Sheung Wan"], "categories": ["Accounting", "Financial Analyst", "Banking / Finance", "Analyst", "Professional Services", "Business Consultancy"], "post_time": "2022-01-10T01:47:58Z", "salary": {"currency": null, "max": null, "min": null, "period": "monthly", "term": null}, "salary_visible": false, "title_keywords": ["valuer", "assistant valuer"], "responsibilities": ["marketing events", "develop new business", "business opportunities", "review", "develop", "maintain", "deploy", "liaise with", "senior management", "report"], "requirements": {"degrees": [], "majors": [], "languages": ["putonghua", "english", "chinese"], "language_level": ["fluency", "advantage", "good command"], "hard_skills": ["ip", "vpn"], "soft_skills": ["result-oriented", "negotiation", "positive mindset", "integrity", "presentation skills", "hands on", "initiative", "interpersonal"], "languages_combined": [{"language": "putonghua", "language_level": ["fluency"]}, {"language": "english", "language_level": ["good command"]}, {"language": "chinese", "language_level": ["advantage", "good command"]}]}, "experience_required": {"duration": ["minimum 5 years"], "field": ["it", "developing"]}}, {"job_id": "100003009043342", "location_code": "hk", "company": "David James Recruitment Limited", "job_title": "Deputy Company Secretary \u2013 Local Conglomerate ($40 \u2013 45K)", "description": "Responsibilities:\n\nAct as destination manager and execute Routing Management for CMI voice business\nAnalyze P&L for individual business case\nReview contracts\nRouting analysis and reporting\nWorkflow and system development support and other project based tasks\n\nRequirements:\n\nUniversity graduate in Accounting, Finance, Mathematics or business related subjects\nAt least 2-5 years of solid voice routing management experience in telecommunication industry is a must\nVoice routing system operation and excel analysis experience is a must\nHighly responsible and reliable,\u00a0Proactive, patient\nVery strong analytical minded and business sense.\nVery good at numbers and\u00a0detail minded\nGood interpersonal and presentation\nCan work independently and willing to learn\nExcellent in English and Chinese\n***Candidate with more / less experience will be considered as well***\n\n\n\nInterested parties please apply in\u00a0full resume with current and expected salary\u00a0by e-mail to\u00a0hr\u00a0@\u00a0cmi.chinam obil e.com.\u00a0 Please indicate the reference in the subject line.\n\nAll personal data collected will be used for recruitment and employment related purpose only.\n\n\n\n\n\n", "employment_types": ["Full Time", "Permanent"], "selling_points": ["Listed in-house role in a local conglomerate", "Handle mainly HK entitles", "Stable working environment"], "locations": ["Eastern Area"], "categories": ["Professional Services", "Business Consultancy", "Company Secretary", "Legal & Compliance"], "post_time": "2022-01-12T10:56:31Z", "salary": {"currency": null, "max": null, "min": null, "period": "monthly", "term": null}, "salary_visible": false, "title_keywords": ["company secretary"], "responsibilities": ["reporting", "management", "contracts", "analysis", "review", "p&l"], "requirements": {"degrees": ["university graduate"], "majors": ["business", "finance", "accounting", "mathematics"], "languages": ["english", "chinese"], "language_level": ["excellent"], "hard_skills": ["excel", "analysis"], "soft_skills": ["work independently", "proactive", "responsible", "business sense", "presentation", "willing to learn", "patient", "reliable", "interpersonal"], "languages_combined": [{"language": "english", "language_level": ["excellent"]}, {"language": "chinese", "language_level": ["excellent"]}]}, "experience_required": {"duration": ["at least 2-5 years"], "field": ["management", "operation"]}}, {"job_id": "100003009037579", "location_code": "hk", "company": "Robert Walters (HK)", "job_title": "Head of Strategic Planning | HK listed bluechip", "description": "Responsibilities:\n\nWork closely with external and internal parties, engineering team and support team to develop innovative products and/or new differentiated product features\nConduct network integration with selected overseas carriers and service providers\nProduct operation support: Product troubleshooting and complaint handling; product pricing and coverage optimization\nResources management: manage numbering resources provided by partners\nWork with business partners to enhance product portfolio and service quality\nHandle ad-hoc projects as required and other company routine tasks\u00a0\n\nRequirements:\n\nDegree or above in Telecommunications, Engineering or related disciplines\n\nMinimum\u00a05 years\u2019 experience in mobile communication industry, experience in mobile core network, SCCP, DIAMETER and S8/GRX integration will be an advantage\nExperience in mobile product management is preferred\nExcellent teamwork spirit, hardworking, self-motived and able to work under pressure\nStrong analytical & problem-solving skills, leadership, self-motivation and good interpersonal skills\nProficiency in MS Office applications and Chinese Word Processing\nFluent in both spoken and written English and Chinese; Fluent in Putonghua is definitely an advantage\nCandidates with less experience will be considered as Product Specialist\n\nInterested parties please send your full resume with current & expected salary by e-mail to\u00a0hr @cmi.chinamobile.com . Please indicate the reference in the subject line.\n\u00a0\n\nAll personal data provided will be used for consideration of your job application only.", "employment_types": ["Full Time", "Permanent"], "selling_points": ["Hk listed blue chip", "Strategic planning/corporate development", "Stable environment with great culture"], "locations": ["Not Specified"], "categories": ["Accounting", "Consulting", "Media & Advertising", "Strategic Planning", "Professional Services", "Business Consultancy"], "post_time": "2022-01-11T03:11:23Z", "salary": {"currency": "HKD", "max": 159999, "min": 90000, "period": "monthly", "term": null}, "salary_visible": true, "title_keywords": [], "responsibilities": ["management", "quality", "troubleshooting", "develop", "ad-hoc projects", "network integration", "internal parties"], "requirements": {"degrees": ["degree or above"], "majors": ["related disciplines", "engineering"], "languages": ["putonghua", "english", "chinese"], "language_level": ["advantage", "proficiency", "fluent"], "hard_skills": ["chinese word processing", "mobile", "integration", "problem-solving skills", "ms office"], "soft_skills": ["communication", "self-motivation", "teamwork spirit", "interpersonal skills", "problem-solving skills", "leadership", "hardworking", "work under pressure"], "languages_combined": [{"language": "putonghua", "language_level": ["fluent", "advantage"]}, {"language": "english", "language_level": ["fluent"]}, {"language": "chinese", "language_level": ["fluent", "proficiency"]}]}, "experience_required": {"duration": ["minimum 5 years"], "field": ["product management"]}}, {"job_id": "100003009046222", "location_code": "hk", "company": "Sing Tao Management Services Limited", "job_title": "Legal Counsel", "description": "Responsibilities:\n\nUndertake content marketing business, take initiative to achieve business target, including UI design, promotion, and formulation of strategic plans\nResponsible to product positioning, explore audience needs and maintain product content\nMeasure and evaluate business performance, identify and trouble shooting in response to global content operations\nConsolidate and analyze content business operations report in a regular basis. Participate in devising business plans, content roadmap and so on to improve engagement through innovative online activities\nForecast/ identify market trends and insights to optimize/ maximize content performance\n\nRequirements:\n\nBachelor Degree of above\nMinimum 3 years\u2019 working experience in content operations\nExperience in OTT, new media, TV and film industry, knowledge in Telecom industry in preferred\nPassion on content business, keen to develop new business, proactive problem solving attitude, team work\nGood interpersonal skills, well-organized, self-motivated, innovative and able to work under pressure\nProficiency in graphics/ video software, MS Office applications and Chinese Word Processing\nFluent in both spoken and written English and Chinese; Fluent in Putonghua is definitely an advantage\nCandidate with more experience will also be considered.\u00a0\n\nInterested parties please send your full resume with current & expected salary by e-mail to\u00a0hr @cmi.chinamobile.com . Please indicate the reference in the subject line.\n\u00a0\n\nAll personal data provided will be used for consideration of your job application only.", "employment_types": ["Full Time", "Permanent"], "selling_points": [], "locations": ["Tseung Kwan O"], "categories": ["Professional Services", "Business Consultancy", "Company Secretary", "Legal & Compliance"], "post_time": "2022-01-13T10:00:55Z", "salary": {"currency": null, "max": null, "min": null, "period": "monthly", "term": null}, "salary_visible": false, "title_keywords": ["legal counsel"], "responsibilities": ["strategic plans", "operations", "design", "business plans", "evaluate", "maintain", "forecast", "product content", "ui", "report"], "requirements": {"degrees": ["degree", "bachelor"], "majors": [], "languages": ["putonghua", "english", "chinese"], "language_level": ["advantage", "proficiency", "fluent"], "hard_skills": ["problem solving", "chinese word processing", "graphics", "ms office"], "soft_skills": ["self-motivated", "keen", "well-organized", "innovative", "problem solving", "interpersonal skills", "proactive", "work under pressure"], "languages_combined": [{"language": "putonghua", "language_level": ["fluent", "advantage"]}, {"language": "english", "language_level": ["fluent"]}, {"language": "chinese", "language_level": ["fluent", "proficiency"]}]}, "experience_required": {"duration": ["minimum 3 years"], "field": ["media"]}}, {"job_id": "100003009036455", "location_code": "hk", "company": "Otis Elevator Co (HK) Limited", "job_title": "Senior Engineer, Quality and Efficiency", "description": "Responsibilities:\n\n\nProvide adequate administrative support to the office;\nPrepare and manage the process of the \u2018Welcome Onboard\u2019 arrangement for the new joiner.\nHandle the internal customer enquiry for administrative matter.\nAssist to Setup and reinstate the conference room facilities as per the requirement.\nHandle outdoor administrative tasks when necessary.\nMonitor the consumption and replenish the office supply and consumables when necessary.\nAssist in clerical works including invoice settlement, report preparation & filing.\nData input for administrative report.\nHandle outdoor tasks when necessary.\nProvide administrative support of any ad hoc duties in the office such as travel arrangement, company event, staff activity when necessary.\nRequirements:\n\n\nDegree holder\nHave relevant experience in administration area is preferrable.\nGood communication and interpersonal skills\nResponsible, detail-minded, good organization skills and the ability to multi-task.\nGood at problem solving and able to work in a fast- paced environment.\nProficiency in MS Office applications and Chinese Word Processing\nExcellent command of spoken and written Chinese and English, proficiency in Putonghua is an advantage\nInterested parties please send your full resume with current & expected salary by e-mail to hr @ cm i.ch ina mobil e.co m. Please indicate the reference in the subject line.\n\u00a0\nAll personal data provided will be used for consideration of your job application only.", "employment_types": ["Full Time", "Permanent"], "selling_points": ["13-month bonus + performance bonus", "Employee Scholar Program up to $160,000", "Excellent development opportunity"], "locations": ["Kowloon Bay"], "categories": ["Professional Services", "Business Analysis / Data Analysis", "Business Consultancy", "Engineering", "Mechanical"], "post_time": "2022-01-10T10:29:30Z", "salary": {"currency": null, "max": null, "min": null, "period": "monthly", "term": null}, "salary_visible": false, "title_keywords": ["senior engineer"], "responsibilities": ["ad hoc duties", "administrative support", "invoice", "monitor", "data input", "travel arrangement", "administrative tasks", "provide administrative support", "setup", "report"], "requirements": {"degrees": ["degree holder"], "majors": [], "languages": ["putonghua", "english", "chinese"], "language_level": ["advantage", "proficiency", "excellent"], "hard_skills": ["problem solving", "chinese word processing", "ms office"], "soft_skills": ["detail-minded", "multi-task", "responsible", "problem solving", "communication and interpersonal skills", "organization skills"], "languages_combined": [{"language": "putonghua", "language_level": ["proficiency", "advantage", "excellent"]}, {"language": "english", "language_level": ["advantage", "excellent"]}, {"language": "chinese", "language_level": ["proficiency", "advantage", "excellent"]}]}, "experience_required": {"duration": [], "field": ["relevant experience", "administration"]}}, {"job_id": "100003009037332", "location_code": "hk", "company": "Computershare Hong Kong Investor Services Limited", "job_title": "Officer, Governance Services", "description": "Job Purpose\n\nEstablish and strengthen relations with existing and potential telecom carrier partners on M2M / IoT business and help to develop business to achieve revenue goals.\n\nJob Functions & Required Skills / Knowledge\n\nWork in the fast-growing team to coordinate M2M / IoT related requirements from telecom carriers and sales units and develop opportunities to meet sales target\nDevelop M2M / IoT business model with telecom carriers on different industry applications\nKeep studying and following M2M/IoT market trend and make regular business reports including business research, pricing and costing analysis, competitive activities analysis, etc.\nHandle coordination work with internal and external parties and service providers to ensure the M2M / IoT services and partnership programs are delivered in good quality\n\nJob Requirements\n\nBachelor\u2019s Degree in Business Administration, Telecommunication, Information System, Engineering, or a related field required.\n5+ years of experience in a job in the Telecom / IT / Enterprise Sales sectors is preferred.\n4 year of progressively responsible positions in M2M / IoT would be an advantage.\nBasic Telecommunication Knowledge are preferred\nTeam player with strong sense of teamwork (e.g. communications, personality, working attitudes, etc)\nFluent in English, Mandarin and Cantonese\n\n\u00a0*** Candidates with less experience will be considered for junior positions. ***\n\nInterested parties please send your full resume with current & expected salary by e-mail to hr @ cmi. chinamobile. com\u00a0. Please indicate the reference in the subject line.\n\nAll personal data provided will be used for consideration of your job application only.", "employment_types": ["Full Time", "Permanent"], "selling_points": ["Exciting opportunity for company secretaries!", "Join an established global firm where you can grow", "Fantastic working culture and benefits"], "locations": ["Wan Chai Area"], "categories": ["Banking / Finance", "Others", "Professional Services", "Business Consultancy", "Company Secretary"], "post_time": "2022-01-11T02:31:16Z", "salary": {"currency": null, "max": null, "min": null, "period": "monthly", "term": null}, "salary_visible": false, "title_keywords": ["officer"], "responsibilities": ["sales target", "analysis", "internal and external parties", "quality", "develop", "coordinate", "reports", "coordination", "costing analysis", "administration"], "requirements": {"degrees": ["degree", "bachelor"], "majors": ["business administration", "engineering"], "languages": ["cantonese", "english", "mandarin"], "language_level": ["fluent"], "hard_skills": ["make", "analysis", "basic", "information system"], "soft_skills": ["team player", "teamwork", "coordination", "responsible"], "languages_combined": [{"language": "cantonese", "language_level": ["fluent"]}, {"language": "english", "language_level": ["fluent"]}, {"language": "mandarin", "language_level": ["fluent"]}]}, "experience_required": {"duration": ["5+ years"], "field": ["it"]}}, {"job_id": "100003009035550", "location_code": "hk", "company": "Kaizen CPA Limited", "job_title": "Company Secretarial Officer (Japanese Speaker) (5-Day work)", "description": "Responsibilities:\n\n\nPerform customer credit assessment and review company contract to protect customer financial risk\nPrepare monthly AR aging reports, netting reports for collection purpose\nFollow up overdue customers\u2019 payment and work closely with business units and billing team to resolve dispute issues\nSupport monthly closing and regular audit activities\nParticipate in system automation to improve operation efficiency\nSupport the team on ad hoc projects\n\nRequirements:\n\nUniversity Degree or above in Accounting or related disciplines\nQualified Accountant is an advantage\nMinimum 5 years\u2019 accounting experience\nMS office, especially in MS Excel & PowerPoint\nGood communication and interpersonal skills, can work under pressure with tight schedule independently\nGood command of both written and spoken English and Chinese (Cantonese)\nFluent in Mandarin will be an advantage\n\nInterested parties please send your full resume with current & expected salary by clicking \"Apply Now\".\u00a0\u00a0\n\n\u00a0All personal data provided will be used for consideration of your job application only.", "employment_types": ["Full Time", "Permanent"], "selling_points": ["Good career prospects and learning opportunities", "Group medical insurance, study and exam leave", "Attractive package"], "locations": ["Kwun Tong"], "categories": ["Admin & HR", "Clerical / Admin Staff", "Professional Services", "Business Consultancy", "Company Secretary"], "post_time": "2022-01-10T07:37:22Z", "salary": {"currency": null, "max": null, "min": null, "period": "monthly", "term": null}, "salary_visible": false, "title_keywords": ["company secretarial officer"], "responsibilities": ["ar", "review", "audit", "payment", "reports", "ad hoc projects", "support the team"], "requirements": {"degrees": ["degree or above"], "majors": ["related disciplines", "accounting"], "languages": ["cantonese", "english", "chinese", "mandarin"], "language_level": ["advantage", "good command", "fluent"], "hard_skills": ["ms excel", "powerpoint", "ms office"], "soft_skills": ["independently", "communication and interpersonal skills", "work under pressure"], "languages_combined": [{"language": "cantonese", "language_level": ["good command"]}, {"language": "english", "language_level": ["good command"]}, {"language": "chinese", "language_level": ["good command"]}, {"language": "mandarin", "language_level": ["fluent", "advantage"]}]}, "experience_required": {"duration": ["minimum 5 years"], "field": ["accounting experience"]}}, {"job_id": "100003009037137", "location_code": "hk", "company": "Pacific Century Premium Developments Limited", "job_title": "Analyst \u2013 Property Development", "description": "Responsibilities:\n\nReviewing, comparing, analyzing, and approving products and services to be purchased\nMaintain records of purchases, pricing, and other important data\nMaintaining good supplier relations and negotiating contracts\nResearching and evaluating prospective suppliers\nPreparing budgets, cost analyses, and reports\n\nRequirements:\n\nBachelor in supply chain management or similar field preferred\nMinimum 3 years\u2019 experience\nProficiency in PC and MS Office and Chinese word processing\nPolite, self-motivated, responsible and organized\nGood communication skills with good written and spoken in Cantonese and Mandarin\nImmediately available is highly preferred\n\nInterested parties please send your full resume with current & expected salary\u00a0by clicking \"Apply Now\".", "employment_types": ["Full Time", "Permanent"], "selling_points": ["Real Estate Investment Analyst", "Degree holder in Finance/Accounting/Real Estate", "At least 3 years\u2019 relevant working experience"], "locations": ["Southern Area"], "categories": ["Accounting", "Financial Analyst", "Professional Services", "Business Consultancy", "Property / Real Estate", "Others"], "post_time": "2022-01-11T01:52:29Z", "salary": {"currency": null, "max": null, "min": null, "period": "monthly", "term": null}, "salary_visible": false, "title_keywords": ["analyst"], "responsibilities": ["budgets", "cost", "maintaining", "data", "contracts", "maintain", "reports"], "requirements": {"degrees": ["bachelor"], "majors": [], "languages": ["cantonese", "chinese", "mandarin"], "language_level": ["proficiency", "good"], "hard_skills": ["pc", "chinese word processing", "ms office"], "soft_skills": ["communication skills", "organized", "self-motivated", "polite", "responsible"], "languages_combined": [{"language": "cantonese", "language_level": ["good"]}, {"language": "chinese", "language_level": ["proficiency"]}, {"language": "mandarin", "language_level": ["good"]}]}, "experience_required": {"duration": ["minimum 3 years"], "field": []}}, {"job_id": "100003009040604", "location_code": "hk", "company": "Wealthaxis Family Office Company Limited", "job_title": "Family Wealth Management Trainee", "description": "Responsibilities:\n\nPerform quantitative and qualitative analysis for prospective investment opportunities, including conducting market research, performing fundamental analysis and constructing financial models\nLead end-to-end deal execution, including due diligence, valuation, deal structuring, post-acquisition integration plan, transaction document negotiation & drafting and closing. Manage and work with external advisors where relevant\nContribute to internal approval and reporting process by drafting investment memo/investment analysis report, communicating with & managing internal stakeholders, presenting to management team and following up comments.\nWork with both internal and external parties for post-acquisition management and integration implementation.\nSupport investment origination by keeping track of industry trends, updating potential acquisition list and building sector knowledge & network overtime\nConduct in-depth research on selected topics as assigned by senior management.\nAd hoc project if necessary\nRequirements:\n\nBachelor\u00a0Degree or above, MBA is a plus\nProfessional qualification such as CPA/ CFA/ CAIA preferred\nAt least 5 years\u2019 solid work experience in reputable private equity, corporate development (M&A focus), investment banking or corporate finance advisory firms. Proven record of overseas M&A is a definite advantage\nStrong in research, financial modelling and presentation skills\nExcellent command of English and Chinese, including Mandarin\nCandidate with less experience will also be considered.\n\n\nInterested parties please send your full resume with current & expected salary\u00a0by e-mail to\u00a0hr @ cmi.chinamobile.com.\u00a0 Please indicate the reference in the subject line.\n\nAll personal data provided will be used for consideration of your job application only.", "employment_types": ["Full Time", "Part Time"], "selling_points": ["Monthly allowance + Full commission + Bonus", "Fast track promotion", "Strong support of family office"], "locations": ["Mong Kok"], "categories": ["Banking / Finance", "Private Banking", "Professional Services", "Business Consultancy", "Management", "Management Trainee"], "post_time": "2022-01-12T02:51:55Z", "salary": {"currency": null, "max": null, "min": null, "period": "monthly", "term": null}, "salary_visible": false, "title_keywords": ["wealth management", "trainee"], "responsibilities": ["due diligence", "valuation", "reporting", "management team", "investment analysis", "management", "memo", "ad hoc", "financial models", "analysis", "comments", "internal and external parties", "market research", "implementation", "communicating with", "plan", "senior management", "report"], "requirements": {"degrees": ["degree or above", "bachelor"], "majors": [], "languages": ["english", "chinese", "mandarin"], "language_level": ["excellent"], "hard_skills": ["plus", "cfa", "cpa", "focus", "private equity"], "soft_skills": ["focus", "presentation skills"], "languages_combined": [{"language": "english", "language_level": ["excellent"]}, {"language": "chinese", "language_level": ["excellent"]}, {"language": "mandarin", "language_level": ["excellent"]}]}, "experience_required": {"duration": ["at least 5 years"], "field": ["development", "corporate finance", "investment", "banking"]}}, {"job_id": "100003009037829", "location_code": "hk", "company": "Gary Cheng CPA Limited", "job_title": "Manager/ Supervisor, Tax & Advisory", "description": "Responsibilities:\n\n\nResponsible for BOSS (business operation support system), mainly on billing and invoice management modules\nResponsible for billing operation tasks such as monthly bill run, invoice distribution and dispute handling\nCollecting, identifying, and analyzing business requirements\nCoordinating projects and operation tasks with vendor\nConducting UAT and providing training to internal or external users\u00a0\n\nRequirements:\n\nBachelor or above in Computer Science/Engineering or other IT related disciplines\n5+ years of work experiences in IT or telecommunication industry\nExperience in business support systems such as CRM, Order Processing, especially Billing is an advantage\nFamiliar with DBMS and software development lifecycle. Experience in development or maintenance of backend service and database procedure is an advantage\nPositive, persistent, \u201ccan do\u201d personality, passionate with continuous improvement\nGood verbal and written English and Chinese. Fluent Putonghua is a plus\nCandidates with less experience will be considered as Application Engineer\n\nInterested parties please send your full resume with current & expected salary by clicking \"Apply Now\".\u00a0\u00a0\n\nAll personal data provided will be used for consideration of your job application only.", "employment_types": ["Full Time", "Permanent"], "selling_points": ["Degree holder in Accounting or equivalent", "Work independently with project ownership mindset", "3 years+ experience, able to make recommendations"], "locations": ["Kwun Tong"], "categories": ["Accounting", "Audit", "Taxation", "Professional Services", "Business Consultancy"], "post_time": "2022-01-11T03:59:43Z", "salary": {"currency": null, "max": null, "min": null, "period": "monthly", "term": null}, "salary_visible": false, "title_keywords": ["manager", "supervisor"], "responsibilities": ["invoice", "business operation", "management", "uat"], "requirements": {"degrees": ["bachelor"], "majors": ["related disciplines", "it", "engineering", "computer science"], "languages": ["putonghua", "english", "chinese"], "language_level": ["fluent", "good"], "hard_skills": ["dbms", "maintenance", "order processing", "plus"], "soft_skills": ["passionate", "persistent", "positive"], "languages_combined": [{"language": "putonghua", "language_level": ["fluent"]}, {"language": "english", "language_level": ["good"]}, {"language": "chinese", "language_level": ["good"]}]}, "experience_required": {"duration": ["5+ years"], "field": ["billing", "business support", "maintenance", "development", "it", "order processing", "database"]}}, {"job_id": "100003009033095", "location_code": "hk", "company": "Links International", "job_title": "Strategy Director  /Partner (Leading Consulting Firm  )", "description": "Job Purposes:\nResponsible for the daily operation of wholesale SMS business, and to ensure the business operate smoothly.\u00a0\n\u00a0Responsibilities:\nPrepare quotation, price list and handle special pricing request\nResponsible in customer and supplier management in aspect of interconnection, cost analysis, route change and suggestions, etc.\nAssist and follow up sales orders, including solution consultation, system input, route testing, etc.\nWork closely with partners on customer / supplier disputes and complaints\n\u00a0Job Requirement:\nBachelor's degree or above\n2+ years working experience in large enterprises\nExperience in telecom industry and A2P product\nAttention to details, strong in numerical sense and analytical skills\nProficiency in MS Office applications and Chinese Word Processing\nGood interpersonal skills, well-organized, self-motivated and able to work under pressure\nFluent in both spoken and written English and Chinese; Fluent in Putonghua is definitely an advantage.\n*** Candidates with less experiences would be considered for junior positions. ***\nInterested parties please apply in full resume with current and expected salary by e-mail to\u00a0hr @\u00a0 cmi.chinamobile.com.\u00a0 Please indicate the reference in the subject line.\n\u00a0All personal data collected will be used for recruitment and employment related purpose only.", "employment_types": ["Full Time", "Permanent"], "selling_points": ["Experience in Retail /FMCG Industry", "Omni-channel experience", "Big 4 Strategy Consulting candiate welcome"], "locations": ["Not Specified"], "categories": ["Professional Services", "Business Consultancy"], "post_time": "2022-01-08T08:17:54Z", "salary": {"currency": null, "max": null, "min": null, "period": "monthly", "term": null}, "salary_visible": false, "title_keywords": ["director"], "responsibilities": ["management", "quotation", "testing", "system input", "cost analysis"], "requirements": {"degrees": ["degree or above", "bachelor"], "majors": [], "languages": ["putonghua", "english", "chinese"], "language_level": ["advantage", "proficiency", "fluent"], "hard_skills": ["chinese word processing", "ms office", "analytical skills"], "soft_skills": ["self-motivated", "well-organized", "analytical skills", "interpersonal skills", "attention to details", "work under pressure"], "languages_combined": [{"language": "putonghua", "language_level": ["fluent", "advantage"]}, {"language": "english", "language_level": ["fluent"]}, {"language": "chinese", "language_level": ["fluent", "proficiency"]}]}, "experience_required": {"duration": ["2+ years"], "field": []}}, {"job_id": "100003009033290", "location_code": "hk", "company": "", "job_title": "Manager / Asst. Manager  (5 days work)", "description": "Our client is a global top tier management consulting firm.They are currently looking for an experienced candidate to join as Director/Partner for their strategy team across APAC.\n\nJob Scope\n\nAct as a business advisory and lead the Strategy consulting team\nDeveloped customer strategy at procedure level\nOrganized and delivered internal consulting training\nSupport cross functional business partners with analytical insights and problem solving\nBuild cross functional partnerships and consensus\nAlign processes, resources-planning and functional goals with overall strategy\nMonitor and analyses industry trends and market changes\n\nRequirements\n\nBachelor degree and above\n10 years management consulting firm or in-house related working experience\nRetail, digital and omni-channel projects equivalent professional experience\nProjects experience in retail company (Beauty, Cosmetics, Sport Ware and Luxury) is preferred\nExcellent command of English and Chinese\nExcellent leadership and track records in project management , process improvement\nImmediate available is highly preferable", "employment_types": ["Full Time", "Permanent"], "selling_points": ["Coaching & team building, develop new market", "International & friendly working environment", "very attractive remuneration  package"], "locations": ["Not Specified"], "categories": ["Professional Services", "Business Consultancy", "Management", "General Management", "Sales, CS & Business Devpt", "Sales - Sales Management"], "post_time": "2022-01-09T05:05:27Z", "salary": {"currency": "HKD", "max": 69999, "min": 25000, "period": "monthly", "term": null}, "salary_visible": true, "title_keywords": ["asst. manager", "manager"], "responsibilities": ["management", "consulting", "monitor", "project management", "team across", "planning"], "requirements": {"degrees": ["degree", "bachelor"], "majors": [], "languages": ["english", "chinese"], "language_level": ["excellent"], "hard_skills": ["problem solving", "project management"], "soft_skills": ["problem solving", "organized", "project management", "leadership"], "languages_combined": [{"language": "english", "language_level": ["excellent"]}, {"language": "chinese", "language_level": ["excellent"]}]}, "experience_required": {"duration": ["10 years"], "field": ["management", "consulting", "related", "beauty", "digital", "retail"]}}, {"job_id": "100003009036261", "location_code": "hk", "company": "D&P China (HK) Limited", "job_title": "Senior Associate, Compliance Consulting, Hong Kong", "description": "In a world of disruption and increasingly complex business challenges, our professionals bring truth into focus with the Kroll Lens. Our sharp analytical skills, paired with the latest technology, allow us to give our clients clarity\u2014not just answers\u2014in all areas of business. We embrace diverse backgrounds and global perspectives, and we cultivate diversity by respecting, including, and valuing one another. As part of\u00a0One team, One Kroll, you\u2019ll contribute to a supportive and collaborative work environment that empowers you to excel.\n\nKroll\u2019s Compliance Consulting practice assists clients in setting up firms, obtaining their initial authorization or registration, and providing them with ongoing compliance advice to navigate the rapidly changing regulatory landscape.\n\nAt Kroll, your work will help deliver clarity to our clients\u2019 most complex governance, risk, and transparency challenges. Apply now to join\u00a0One team, One Kroll.\n\nRESPONSIBILITIES:\n\nManaging a portfolio of clients regulated by the SFC, SEC\u00a0and other global regulators\nPreparing compliance manuals and other related policies and procedures\u00a0\nSetting up the compliance infrastructure and assisting ongoing compliance monitoring\nUndertaking periodic compliance monitoring reviews at client premises\nWriting compliance monitoring reports\nManaging regulatory\u00a0filing and reporting schedules\nProviding ad hoc regulatory advice and creative solutions\nUpdating clients on regulatory change\nNetworking and relationship building with industry professionals and industry bodies\n\nREQUIREMENTS:\n\nProven experience in a compliance role, for example within an SFC regulated firm or a compliance consultancy practice\nDetailed understanding of SFC, SEC rules and regulations\nUnderstanding of the financial services industry i.e. asset management and broking sectors\nBroad understanding of the alternative asset management industry\nAbility to work on own initiative and as part of a team\nClient facing, solutions focused skills\nClear, logical thought processes, ability to make decisions and articulate these clearly\nStrong\u00a0English oral and written communication skills\nTime management skills and ability to work within deadlines\nSolution-driven and problem-solving attitude\nLegal or audit background would be useful\nCandidates with less experience will be considered as an Analyst\n\nIn order to be considered for a position, you must formally apply via careers.kroll.com.", "employment_types": ["Full Time", "Permanent"], "selling_points": ["Global work and exposure opportunities", "Amazing development, progression and culture", "SFC, SEC rules and regulations knowledge"], "locations": ["Admiralty"], "categories": ["Banking / Finance", "Fund Management", "Professional Services", "Business Consultancy", "Legal & Compliance"], "post_time": "2022-01-10T09:50:49Z", "salary": {"currency": null, "max": null, "min": null, "period": "monthly", "term": null}, "salary_visible": false, "title_keywords": ["senior associate"], "responsibilities": ["reporting", "ad hoc", "schedules", "policies", "monitoring", "compliance", "procedures", "infrastructure", "reports"], "requirements": {"degrees": [], "majors": [], "languages": ["english"], "language_level": [], "hard_skills": ["make", "problem-solving"], "soft_skills": ["communication skills", "oral", "focused", "time management skills", "problem-solving", "driven", "clear", "articulate", "initiative", "detailed"], "languages_combined": [{"language": "english", "language_level": []}]}, "experience_required": {"duration": [], "field": ["compliance"]}}, {"job_id": "100003009036088", "location_code": "hk", "company": "Tricor Staffing Solutions Limited", "job_title": "Assistant Manager / Senior Recruitment Consultant \u2013 Executive search and Recruitment", "description": "Tricor Group today is Asia's leading provider of integrated business, corporate, investor, human resources & payroll, and corporate trust & debt services with over 50,000 clients in Asia, a staff length of over 2,600 and a network of offices in 47 cities across 31 countries and territories.\n\nWe are looking for a high\u00a0caliber\u00a0professional to join our Tricor staffing solution team under Tricor Services Limited\u00a0as\u00a0Assistant Manager / Senior Recruitment Consultant to cope with our permanent recruitment business.\n\nYour duties include:\n\nManage full spectrum of recruitment services including provision of advice, attraction and sourcing strategies, and candidate management.\nIdentifying and developing new client/business relationships.\nSales oriented mindset with strong commercial acumen and the ability to work autonomously.\nActively build pipeline and maintaining client and candidate database.\nSourcing suitable candidates and briefing them on the opportunities offered by the client.\nManaging the process through interview to offer stage and beyond.\nAchieve business target and develop new opportunities with existing and potential client\nThe right candidate will have:\n\n\nIdeally 3-5 years of successful Recruitment experience in an agency setting\nProven track record of high performance in recruitment fee earning and quality of work\nBe enthusiastic, motivated, target driven and enjoy building relationships\nStrong Billing Records in Finance & Accounting, HR, Technology and Legal recruitment would be an advantage, or another specialty\nCandidates with more experience will be considered for the recruitment manager position\u00a0 \u00a0 \u00a0\u00a0\u00a0\n\nWe offer a competitive package with excellent benefits, and most importantly an exceptional commission scheme as well as a clear, attractive career path.", "employment_types": ["Full Time", "Part Time", "Permanent", "Temporary", "Contract", "Internship", "Freelance"], "selling_points": ["MNC, Asia\u2019s Leading Business Expansion Specialis", "Base Salary + High commission", "Over 30 years of recruitment experiences"], "locations": ["Wan Chai Area"], "categories": ["Professional Services", "Business Consultancy", "Sales, CS & Business Devpt", "Business Development", "Admin & HR", "Recruitment / Executive Search"], "post_time": "2022-01-10T09:19:03Z", "salary": {"currency": null, "max": null, "min": null, "period": "monthly", "term": null}, "salary_visible": false, "title_keywords": ["assistant manager", "executive", "recruitment consultant"], "responsibilities": ["management", "maintaining", "hr", "quality", "developing", "develop", "recruitment", "database", "payroll"], "requirements": {"degrees": [], "majors": [], "languages": [], "language_level": [], "hard_skills": ["scheme", "acumen"], "soft_skills": ["clear", "motivated", "driven", "enthusiastic"], "languages_combined": []}, "experience_required": {"duration": ["3-5 years"], "field": ["agency", "recruitment"]}}]