[{"job_id": "100003009054533", "location_code": "hk", "company": "Tianjin Port Development Holdings Limited", "job_title": "Company Secretarial Officer", "description": "Tianjin Port Development Holdings Limited is a company listed on the Hong Kong Stock Exchange. We are seeking a high potential candidate to fill the following position.\nResponsibilities:\nHandle full spectrum of company secretarial matters including the preparation of minutes, resolutions, meeting papers and statutory forms.\nPrepare and arrange for statutory filings, maintain and update statutory records, database and filing systems\nAssist in preparing annual / interim reports, announcements and circulars;\nCompose and translate corporate correspondence and other communication materials.\nAssist in ad hoc projects and other duties as assigned.\nRequirements:\nDegree holder and HKICS graduate or student member.\nAt least 2 years company secretarial experience gained in listed companies.\nKnowledge in Companies Ordinance and Listing Rules.\nGood command of written and spoken English and Chinese (including Putonghua).\nDetail-oriented, meticulous, self-motivated with a strong sense of responsibility.\nAbility to work independently, under pressure and able to meet tight schedules.\nWe offer 5-day work and attractive remuneration package to the right candidate. Interested parties please send us full resume with current and expected salary and available date information. Please visit our company website www.tianjinportdev.com for more information.\nPersonal data and information collected will be kept confidential and used for recruitment purpose only.", "employment_types": ["Full Time", "Permanent"], "selling_points": [], "locations": ["Causeway Bay"], "categories": ["Professional Services", "Company Secretary"], "post_time": "2022-01-17T09:54:28Z", "salary": {"currency": null, "max": null, "min": null, "period": "monthly", "term": null}, "salary_visible": false, "title_keywords": ["company secretarial officer"], "responsibilities": ["other duties", "systems", "communication", "maintain", "reports", "ad hoc projects", "database"], "requirements": {"degrees": ["degree holder"], "majors": [], "languages": ["putonghua", "english", "chinese"], "language_level": ["good command"], "hard_skills": ["companies ordinance"], "soft_skills": ["meticulous", "self-motivated", "work independently", "under pressure", "sense of responsibility", "detail-oriented", "meet tight schedules"], "languages_combined": [{"language": "putonghua", "language_level": ["good command"]}, {"language": "english", "language_level": ["good command"]}, {"language": "chinese", "language_level": ["good command"]}]}, "experience_required": {"duration": ["at least 2 years"], "field": ["secretarial"]}}, {"job_id": "100003009054369", "location_code": "hk", "company": "The Garden Company Limited", "job_title": "Company Secretarial Officer", "description": "Responsibilities:\n\nHandle all-round company secretarial and compliance affairs for listed company and its subsidiaries, including HK, BVI and other jurisdictions;\nAssist in preparation of general meetings of shareholders, board meetings and sub-committee meetings\nAssist in preparation of announcements, circulars, interim and annual reports in a timely and accurate manner\nLiaise with various parties, including the printers, lawyers, auditors, share registrars and ESG reporting consultancy\nUpdate and maintain efficient statutory and corporate filing systems\nProvide administrative support to the team and assist in ad hoc projects\n\nRequirements:\n\nBachelor degree or above in Finance, Legal, Corporate Governance or Language related disciplines is preferable\nMember or Student Member of HKICS/ ICSA\nMinimum 2 years\u2019 relevant experience gained in listed companies or professional firms\nFamiliar with the Listing Rules, Securities and Futures Ordinance and other relevant regulations\nA good team player with strong comprehensive analysis, communication and coordination skills\nGood writing and reading in both Chinese and English, fluent Putonghua is a must\nImmediate available is highly preferred", "employment_types": ["Full Time"], "selling_points": ["Company Secretarial Duties", "Corporate Level", "New Headcount"], "locations": ["Tsuen Wan Area"], "categories": ["Professional Services", "Company Secretary"], "post_time": "2022-01-17T09:18:35Z", "salary": {"currency": null, "max": null, "min": null, "period": "monthly", "term": null}, "salary_visible": false, "title_keywords": ["company secretarial officer"], "responsibilities": ["reporting", "compliance", "systems", "maintain", "reports", "ad hoc projects", "liaise with", "provide administrative support"], "requirements": {"degrees": ["degree or above", "bachelor"], "majors": ["related disciplines", "finance"], "languages": ["putonghua", "english", "chinese"], "language_level": ["fluent", "good"], "hard_skills": ["analysis", "securities and futures ordinance"], "soft_skills": ["communication", "good team player", "comprehensive", "coordination skills"], "languages_combined": [{"language": "putonghua", "language_level": ["fluent", "good"]}, {"language": "english", "language_level": ["good"]}, {"language": "chinese", "language_level": ["good"]}]}, "experience_required": {"duration": ["minimum 2 years"], "field": ["relevant experience"]}}, {"job_id": "100003009054214", "location_code": "hk", "company": "ISP Construction (Engineering) Limited", "job_title": "Assistant Company Secretarial Manager (Ref: CoSec-ISP)", "description": "To cope with our expansion, we are looking for an energetic person with PRC experience to join our Company.\u00a0 You will report directly to the Company Secretary and be responsible for the following duties:\n\nResponsibilities:\n\nAssist in handling company secretarial duties for the group of companies;\nAssist in contract drafting and review, contract management and other legal matters;\nAssist in handling insurance matters;\nAssist in ad-hoc projects and tasks as assigned.\n\nQualifications:\n\nDegree or above in Corporate Governance or related discipline, member of HKICS / ICSA;\nAt least 5 years' relevant experiences gained in large-scale corporations or professional firms, candidates with more experience\u00a0may be\u00a0considered\u00a0for a senior role;\nSound experience in preparing corporate secretarial and legal documents for PRC will be an advantage;\nGood command of the English, Cantonese and Mandarin;\nProficient in Microsoft Office (i.e. MS Word, Excel, PowerPoint);\nSelf-motivated, independent, requires minimal supervision, diligent and resourceful;\nImmediate availability is preferred.\nWorking Location: Sham Tseng (Free Shuttle Bus Service running along different locations in Yuen Long, Tuen Mun, Tsuen Wan and Shamshuipo to / from office are provided)", "employment_types": ["Full Time", "Permanent"], "selling_points": ["At least 6 yrs' relevant exp.", "Independent, well-organized & fast-paced", "Graduate/ Finalist member of HKICS/ICSA"], "locations": ["Ngau Tau Kok"], "categories": ["Professional Services", "Company Secretary"], "post_time": "2022-01-17T08:49:59Z", "salary": {"currency": null, "max": null, "min": null, "period": "monthly", "term": null}, "salary_visible": false, "title_keywords": ["company secretarial manager", "assistant"], "responsibilities": ["review", "contract management", "ad-hoc projects", "insurance", "report"], "requirements": {"degrees": ["degree or above"], "majors": [], "languages": ["cantonese", "english", "mandarin"], "language_level": ["good command"], "hard_skills": ["excel", "microsoft office", "powerpoint", "wan", "ms word"], "soft_skills": ["self-motivated", "independent", "responsible", "resourceful", "diligent", "energetic"], "languages_combined": [{"language": "cantonese", "language_level": ["good command"]}, {"language": "english", "language_level": ["good command"]}, {"language": "mandarin", "language_level": ["good command"]}]}, "experience_required": {"duration": ["at least 5 years"], "field": ["secretarial", "legal"]}}, {"job_id": "100003009056100", "location_code": "hk", "company": "Albert S C Young", "job_title": "COMPANY SECRETARY FOR SECRETARIAL FIRM (5 days work)", "description": "Responsibilities\n\n\nResponsible for providing day-to-day company secretarial duties and statutory compliance for listed companies\nPrepare corporate secretarial documents and statutory forms\nHandle ad-hoc projects as required\n\nRequirements\n\n\nDegree holder in Corporate Administration or relevant disciplines\nGraduate/ Finalist member of HKICS/ICSA\u00a0\nAt least 6 years' relevant experiences gained in listed company, large-scale corporations or professional firms, experiences gained from construction related industries will be advantage\nUnderstanding of Hong Kong Company Ordinance and listing rules\nWell-organized, detail-oriented, fast-paced, proactive, independent and eager to learn\nFluent in spoken and written English and Chinese", "employment_types": ["Full Time"], "selling_points": ["SECRETARIAL FIRM NEEDS A COMPANY SECRETARY", "Must be able to work independently", "Client friendly"], "locations": ["Sheung Wan"], "categories": ["Professional Services", "Company Secretary"], "post_time": "2022-01-18T03:18:45Z", "salary": {"currency": null, "max": null, "min": null, "period": "monthly", "term": null}, "salary_visible": false, "title_keywords": ["company secretary"], "responsibilities": ["statutory compliance", "ad-hoc projects"], "requirements": {"degrees": ["degree holder"], "majors": [], "languages": ["english", "chinese"], "language_level": ["fluent"], "hard_skills": [], "soft_skills": ["independent", "well-organized", "detail-oriented", "eager to learn", "proactive"], "languages_combined": [{"language": "english", "language_level": ["fluent"]}, {"language": "chinese", "language_level": ["fluent"]}]}, "experience_required": {"duration": ["at least 6 years"], "field": ["related", "construction"]}}, {"job_id": "100003009056032", "location_code": "hk", "company": "ConnectedGroup Limited", "job_title": "Assistant Manager, Company Secretariat (HK$ 40k-55k)", "description": "C P YOUNG (SECRETARIAL) CO LTDSheung Wan\n\u00a020 April 2021\n\nWe are a secretarial firm and need a staff to manage general company secretarial work\u00a0\nFiling of documents to Company registry, including annual returns, change of company's structure, allotment of shares etc.\u00a0\nHandle general coordination works with clients\nGeneral client's administration work\nYear end bonus\nFlexible working hours and little over-time requirements\u00a0\n5-days work week\nFriendly working environment\n\nRequire Qualifications & Experience\n\nRelevant experience is essential\nMust be able to handle job independently, including filing of annual return, formation of company, application of business registration\nKnowledge in computer operation\nWilling to learn & self-motivated\n\nApplication:\n\nSalary will commensurate with qualification & experience.\u00a0 Interested candidates please send resume, salary expected by clicking \"Apply Now\".\n\nPersonal data collected will be used for recruitment purpose only.", "employment_types": ["Full Time", "Permanent"], "selling_points": ["Cover a wide range of company secretarial matters", "Top-tier Property Developer", "Qualified Member of HKCGI/CGI"], "locations": ["Kwun Tong Area"], "categories": ["Professional Services", "Company Secretary", "Legal & Compliance"], "post_time": "2022-01-18T03:12:29Z", "salary": {"currency": "HKD", "max": 54999, "min": 45000, "period": "monthly", "term": null}, "salary_visible": true, "title_keywords": ["assistant manager,"], "responsibilities": ["coordination works", "administration"], "requirements": {"degrees": [], "majors": [], "languages": [], "language_level": [], "hard_skills": ["wan", "c"], "soft_skills": ["flexible", "self-motivated", "independently", "willing to learn", "friendly", "coordination"], "languages_combined": []}, "experience_required": {"duration": [], "field": ["relevant experience"]}}, {"job_id": "100003009055377", "location_code": "hk", "company": "Manpower Services (Hong Kong) Limited", "job_title": "Company Secretary & IR senior officer--  Listed company (HKICS member preferred) 35K", "description": "Assistant Manager - Company Secretariat\n\nOur client is a well-established and reputable property developer listed in Hong Kong. We are assisting them looking for a talented individual to take up the Assistant Manager, Company Secretariat.\n\nSalary: HK$ 40,000 - 55,000x 12 month + bonus\n\nJob Summary:\n\nProviding company secretarial services for Board and company\nFamilir with Hong Kong Listing Rules and Securities and Futures Ordinance\n\nJob Duties:\n\nResponsible for full spectrum of company secretarial duties, corporate governance and compliance functions for listed company and private subsidiaries\nDraft and prepare annual and interim reports, announcements and circulars\nOrganize meetings for the board, committees and shareholders, and prepare relevant board papers, minutes and resolutions\nMaintain and update statutory records and filings in compliance with the Code on Real Estate Investment Trusts, Securities and Futures Ordinance, Listing Rules, applicable laws and regulations and implement compliance procedures as required\nLiaise with professional advisors and various regulatory bodies\nParticipate in ad hoc projects and tasks assigned from time to time\n\nRequirements:\n\nDegree holder in Corporate Administration or relevant disciplines\nQualified Member of HKCGI/CGI\nAt least 8 to 10 years of company secretarial experience gained in listed company, large-scale corporations or professional firms\nSolid experience in Hong Kong Listing Rules, Securities and Futures Ordinance and Hong Kong Companies\nExperience in handling compliance matters with the Securities and Futures Commission is an advantage\nExcellent command of written and spoken English and Chinese\nProven track record of minute taking and stakeholder management.\nCandidates with more experience will be considered as Manager\n\nInterested individuals should \"Apply Now\", due to an influx of applicants, we regret to inform you that ONLY suitable candidates will be contacted.\n\nFor a more comprehensive list of our vacancies, please visit: www.connectedgroup.com", "employment_types": ["Full Time"], "selling_points": ["HKICS member", "IR experience is an advantage", "Company Secretary experience with Listed company"], "locations": ["Not Specified"], "categories": ["Professional Services", "Company Secretary", "Legal & Compliance", "Marketing / Public Relations", "Marketing - General / Support"], "post_time": "2022-01-18T02:23:11Z", "salary": {"currency": null, "max": null, "min": null, "period": "monthly", "term": null}, "salary_visible": false, "title_keywords": ["company secretary", "senior officer"], "responsibilities": ["regulations", "compliance", "procedures", "maintain", "reports", "ad hoc projects", "liaise with", "listing"], "requirements": {"degrees": ["degree holder"], "majors": [], "languages": ["english", "chinese"], "language_level": ["excellent"], "hard_skills": ["inform", "securities and futures ordinance"], "soft_skills": ["comprehensive"], "languages_combined": [{"language": "english", "language_level": ["excellent"]}, {"language": "chinese", "language_level": ["excellent"]}]}, "experience_required": {"duration": ["at least 8 to 10 years"], "field": ["secretarial", "compliance", "securities"]}}, {"job_id": "100003009053372", "location_code": "hk", "company": "Rotam Agrochemical Company Limited", "job_title": "Executive, Company Secretarial", "description": "Job Duties:\n\nHands on source-to-pay procurement process with multiple categories focus (mainly in IT & Telcom, Facility Services & Marketing Services), mainly operates in company's in-house group procurement platform.\nProvides full process support with internal stakeholders and external suppliers in order to achieve business targets by implementing sourcing & procurement execution within the group procurement policy and procedures.\u00a0\nEnhance user experience both internal & external by sound project planning & correspondence, as well as timely reactions in addressing queries & problem solving.\nKeep constant collaboration with central Group Procurement team in Hangzhou, as well as other regional teams, to maintain the synergy of category strategies, process improvement, and best practice sharing of overseas procurement operation.\nCollaborates with other functions such as Finance, Legal, HR in maintaining overall process control and mutual key performance metrics.\nExecuting project-based sourcing with guidance of the line manager. Develop local category strategy and expand local supply base.\nData reporting on a regular basis.\n\nRequirements:\n\nBachelor's Degree or above\nWorking experience in procurement or similar scope is an advantage\nFast learning in a very dynamic and fast pace environment\nPatient with sense of customer care, open-minded and willing to pro-actively communicate with others\nProficient in English and Mandarin, other language is a plus\nFamiliar with online procurement tools as well as major IT tools, advanced user of Excel and Power Point, or database tools is a plus\nCandidate with no experiences or fresh graduate will also be considered", "employment_types": ["Full Time", "Permanent"], "selling_points": ["Co Sec matters for various jurisdictions& offshore", "Assist in preparing minutes and info for the Group", "Min 2 yrs exp., exp in handling offshore companies"], "locations": ["Chai Wan"], "categories": ["Accounting", "Others", "Professional Services", "Company Secretary", "Legal & Compliance"], "post_time": "2022-01-17T06:52:23Z", "salary": {"currency": null, "max": null, "min": null, "period": "monthly", "term": null}, "salary_visible": false, "title_keywords": ["executive"], "responsibilities": ["guidance", "project planning", "control", "reporting", "maintaining", "data", "hr", "procedures", "user experience", "teams", "performance metrics", "develop", "maintain", "executing"], "requirements": {"degrees": ["degree or above", "bachelor", "fresh graduate"], "majors": [], "languages": ["english", "mandarin"], "language_level": ["proficient"], "hard_skills": ["excel", "plus", "no", "dynamic", "power point"], "soft_skills": ["advanced", "open-minded", "dynamic", "learning", "patient"], "languages_combined": [{"language": "english", "language_level": ["proficient"]}, {"language": "mandarin", "language_level": ["proficient"]}]}, "experience_required": {"duration": [], "field": ["procurement"]}}, {"job_id": "100003009052182", "location_code": "hk", "company": "Rodney Street Limited", "job_title": "Company Secretarial Assistant", "description": "Job Duties:\n\nDesign and prepare Test Plan\nTest Scenarios and Test Cases according to user requirements\nPerform functional test and user scenario test on a non-Production system\nFind out and bug fixing\nProvide clear and detailed test reports\nPerform any ad hoc project/tasks\n\nRequirements:\n\nDiploma or above in Information System, Computer Science, or related diploma\nAt least 1 year of relevant experience in the IT industry\nExperience in Quality Assurance is preferred\nKnowledge of any test management tools (Zephyr, XRay, PractiTest, Testlink, Testrail, Testflow)\nDetail oriented and well organized and able to work under pressure.\nGood command of both written and spoken English and Chinese (Cantonese & Mandarin)\nFresh Graduates are also welcome", "employment_types": ["Full Time"], "selling_points": ["Company Secretarial Assistant", "HKICS", "CSA"], "locations": ["Admiralty"], "categories": ["Professional Services", "Company Secretary"], "post_time": "2022-01-17T02:24:16Z", "salary": {"currency": null, "max": null, "min": null, "period": "monthly", "term": null}, "salary_visible": false, "title_keywords": ["company secretarial assistant"], "responsibilities": ["ad hoc", "reports", "design", "plan"], "requirements": {"degrees": ["diploma", "diploma or above"], "majors": ["computer science"], "languages": ["cantonese", "english", "chinese", "mandarin"], "language_level": ["good command"], "hard_skills": ["information system"], "soft_skills": ["detail oriented", "well organized", "work under pressure"], "languages_combined": [{"language": "cantonese", "language_level": ["good command"]}, {"language": "english", "language_level": ["good command"]}, {"language": "chinese", "language_level": ["good command"]}, {"language": "mandarin", "language_level": ["good command"]}]}, "experience_required": {"duration": ["at least 1 year"], "field": ["it", "relevant experience", "quality assurance"]}}, {"job_id": "100003009052947", "location_code": "hk", "company": "Fung, Yu & Co. CPA Limited", "job_title": "Company Secretarial Assistant - Corporate Services Department (5 days work)", "description": "Responsibilities:\n\nProofreading and manage the quality process of mobile apps project.\nConduct compliance awareness for the content review process and normalization.\nManage the accuracy and timely delivery of production and projects.\n\nRequirements:\n\nUniversity graduate in any discipline.\n1 year or above relevant experience.\nNative Chinese & English Speaker\nHong Kong PR; No remote working is allowed. It is a full-time job in Hong Kong", "employment_types": ["Full Time", "Permanent"], "selling_points": ["14 days Annual Leave with annual increment", "Birthday leave, Study leave and Exam leave", "OT compensation and Medical allowance"], "locations": ["Sheung Wan"], "categories": ["Professional Services", "Company Secretary", "Legal & Compliance"], "post_time": "2022-01-17T04:39:35Z", "salary": {"currency": null, "max": null, "min": null, "period": "monthly", "term": null}, "salary_visible": false, "title_keywords": ["company secretarial assistant"], "responsibilities": ["compliance", "review", "proofreading", "quality"], "requirements": {"degrees": ["university graduate"], "majors": [], "languages": ["english", "chinese"], "language_level": ["native"], "hard_skills": ["no"], "soft_skills": [], "languages_combined": [{"language": "english", "language_level": ["native"]}, {"language": "chinese", "language_level": ["native"]}]}, "experience_required": {"duration": ["1 year"], "field": ["relevant experience"]}}, {"job_id": "100003009054373", "location_code": "hk", "company": "Bright Smart Securities International (H.K.) Limited", "job_title": "Company Secretary", "description": "Responsibilities:\n\nPerform company secretarial duties for the Group, listed company and its subsidiaries;\nDraft and prepare annual / interim reports, announcements and circulars;\nOrganize meetings for the board, committees and shareholders, and prepare relevant board papers and minutes;\nMaintain and update statutory records / filings in compliance with HK Listing Rules;\nAssist to review on all legal and compliance documents including internal, external contracts and agreements;\nPerform any ad hoc projects and tasks assigned from management.\nRequirements:\n\nDegree holder, preferably with associate / graduate of HKICS / ICSA or equivalent;\nMinimum of 4 years or above relevant experience in listed companies is required;\nPrior hands-on working experience in handling company secretarial matters is a MUST;\nKnowledge in Companies Ordinance and Listing Rules;\nExcellent command of English and Chinese;\nWell-organized,\u00a0self-motivated and able to work independently;\nCandidates with more experience will be considered as Assistant Manager.\nWe Offer:\nCompetitive remuneration package\n5 Days Work & Bank Holidays\nAttendance Bonus\nMeal Allowance\nDiscretionary Bonus\nMedical Insurance\nWe provide attractive remuneration package and fringe benefits for the right candidate. Interested parties please send detailed resume with current and expected salaries to\u00a0Human Resources Department by clicking \"Apply Now\" or fax to: 2530 2218.\nAll information collected will be used for recruitment purpose only, only shortlisted candidates will be notified.\n\nWelcome to visit our website: http://www.bsgroup.com.hk/ for more information.", "employment_types": ["Full Time", "Permanent"], "selling_points": [], "locations": ["Central"], "categories": ["Banking / Finance", "Others", "Professional Services", "Company Secretary", "Legal & Compliance"], "post_time": "2022-01-17T09:18:37Z", "salary": {"currency": null, "max": null, "min": null, "period": "monthly", "term": null}, "salary_visible": false, "title_keywords": ["company secretary"], "responsibilities": ["management", "contracts", "compliance", "review", "maintain", "reports", "ad hoc projects", "listing"], "requirements": {"degrees": ["degree holder"], "majors": [], "languages": ["english", "chinese"], "language_level": ["excellent"], "hard_skills": ["companies ordinance"], "soft_skills": ["hands-on", "well-organized", "work independently", "self-motivated"], "languages_combined": [{"language": "english", "language_level": ["excellent"]}, {"language": "chinese", "language_level": ["excellent"]}]}, "experience_required": {"duration": ["minimum of 4 years"], "field": ["secretarial", "relevant experience"]}}, {"job_id": "100003009055518", "location_code": "hk", "company": "Beijing Energy International Investment Limited", "job_title": "Company Secretarial Officer", "description": "Responsibilities:\n\nHandle all-round company secretarial and compliance affairs for listed company and its subsidiaries, including HK, BVI and other jurisdictions;\nAssist in preparation of general meetings of shareholders, board meetings and sub-committee meetings\nAssist in preparation of announcements, circulars, interim and annual reports in a timely and accurate manner\nLiaise with various parties, including the printers, lawyers, auditors, share registrars and ESG reporting consultancy\nUpdate and maintain efficient statutory and corporate filing systems\nProvide administrative support to the team and assist in ad hoc projects\n\nRequirements:\n\nBachelor degree or above in Finance, Legal, Corporate Governance or Language related disciplines is preferable\nMember or Student Member of HKICS/ ICSA\nMinimum 2 years\u2019 relevant experience gained in listed companies or professional firms\nFamiliar with the Listing Rules, Securities and Futures Ordinance and other relevant regulations\nA good team player with strong comprehensive analysis, communication and coordination skills\nGood writing and reading in both Chinese and English, fluent Putonghua is a must\nImmediate available is highly preferred", "employment_types": ["Full Time"], "selling_points": ["Minimum 2 years\u2019 relevant experience", "Member or Student Member of HKICS/ ICSA", "Immediate available is highly preferred"], "locations": ["Sheung Wan"], "categories": ["Professional Services", "Company Secretary", "Legal & Compliance", "Translation"], "post_time": "2022-01-18T02:40:30Z", "salary": {"currency": null, "max": null, "min": null, "period": "monthly", "term": null}, "salary_visible": false, "title_keywords": ["company secretarial officer"], "responsibilities": ["reporting", "compliance", "systems", "maintain", "reports", "ad hoc projects", "liaise with", "provide administrative support"], "requirements": {"degrees": ["degree or above", "bachelor"], "majors": ["related disciplines", "finance"], "languages": ["putonghua", "english", "chinese"], "language_level": ["fluent", "good"], "hard_skills": ["analysis", "securities and futures ordinance"], "soft_skills": ["communication", "good team player", "comprehensive", "coordination skills"], "languages_combined": [{"language": "putonghua", "language_level": ["fluent", "good"]}, {"language": "english", "language_level": ["good"]}, {"language": "chinese", "language_level": ["good"]}]}, "experience_required": {"duration": ["minimum 2 years"], "field": ["relevant experience"]}}, {"job_id": "100003009050522", "location_code": "hk", "company": "HH Partners", "job_title": "Company Secretary", "description": "Responsibilities\n\nReporting to the General Manager of the Company Secretarial Department, the successful candidate will be responsible for performing a full range of company secretarial duties and services as well as statutory compliance for listed and private companies. He/she will assist to advise on the Company\u2019s major decisions, build and maintain regulations and legal compliance framework, draft and review announcement, provide training to staff and coordinate with other departments on compliance issues of the Company. He/she will also undertake special projects as assigned by the Company from time to time.\n\nRequirements\n\n-\u00a0\u00a0\u00a0\u00a0\u00a0\u00a0\u00a0\u00a0\u00a0 Recognized university degree in relevant discipline, holder of law degree advantage;\n\n-\u00a0\u00a0\u00a0\u00a0\u00a0\u00a0\u00a0\u00a0\u00a0 Member of The Chartered Governance Institute;\n\n-\u00a0\u00a0\u00a0\u00a0\u00a0\u00a0\u00a0\u00a0\u00a0 Minimum 10 years\u2019 relevant company secretarial experience, of which at least 5 years at managerial level in Hong Kong listed companies;\n\n-\u00a0\u00a0\u00a0\u00a0\u00a0\u00a0\u00a0\u00a0\u00a0 Well-versed in Hong Kong Listing Rules, Companies Ordinance, Securities and Futures Ordinance and relevant rules and regulations;\n\n-\u00a0\u00a0\u00a0\u00a0\u00a0\u00a0\u00a0\u00a0\u00a0 Strong business acumen, good analytical, interpersonal, communication and managerial skills;\n\n-\u00a0\u00a0\u00a0\u00a0\u00a0\u00a0\u00a0\u00a0\u00a0 Mature, meticulous, well organized and able to work under pressure with strong sense of responsibility;\n\n-\u00a0\u00a0\u00a0\u00a0\u00a0\u00a0\u00a0\u00a0\u00a0 Well organized, independent and able to work under pressure; and\n\n-\u00a0\u00a0\u00a0\u00a0\u00a0\u00a0\u00a0\u00a0\u00a0 Proficiency in both spoken and written English and Chinese (Cantonese and Putonghua).\n\n\u00a0Attractive and competitive remuneration package will be offered to the right candidate. Candidates with less experience will be considered as Deputy Secretarial Manager or Secretarial Officer.\n\nApplication with full resume, current and expected salary, and date of availability should be sent through email. For details of the Company, please visit our website: www.gdi.com.hk.\n\nInformation provided will be for recruitment purpose within the GDI group and only short-listed candidates will be contacted. We comply with all applicable laws and regulations of HKSAR in handling applications.", "employment_types": ["Full Time", "Part Time"], "selling_points": ["Work-life balance - work from home", "CSA, Microsoft office proficient", "Wanchai"], "locations": ["Wan Chai"], "categories": ["Admin & HR", "Administration / Operation Manager", "Professional Services", "Company Secretary"], "post_time": "2022-01-14T10:36:44Z", "salary": {"currency": null, "max": null, "min": null, "period": "monthly", "term": null}, "salary_visible": false, "title_keywords": ["company secretary"], "responsibilities": ["regulations", "reporting", "provide training", "statutory compliance", "compliance", "review", "coordinate with", "maintain"], "requirements": {"degrees": ["university degree", "degree"], "majors": ["law"], "languages": ["cantonese", "putonghua", "english", "chinese"], "language_level": ["proficiency"], "hard_skills": ["companies ordinance", "securities and futures ordinance", "acumen"], "soft_skills": ["meticulous", "independent", "sense of responsibility", "well organized", "mature", "communication", "business acumen", "interpersonal", "work under pressure"], "languages_combined": [{"language": "cantonese", "language_level": []}, {"language": "putonghua", "language_level": []}, {"language": "english", "language_level": ["proficiency"]}, {"language": "chinese", "language_level": ["proficiency"]}]}, "experience_required": {"duration": ["at least 5 years", "minimum 10 years"], "field": ["managerial", "secretarial"]}}, {"job_id": "100003009048230", "location_code": "hk", "company": "CW Secretarial Services Limited", "job_title": "Company Secretarial Assistant", "description": "Job Responsibilities:\u00a0\n\nPrepare announcement, annual and interim reports;\u00a0\nResponsible for company secretarial duties of subsidiaries;\u00a0\u00a0\nAssist in drafting transactions and company secretarial tasks of listed company;\u00a0\nCoordinate and organize shareholder and board meeting;\u00a0\u00a0\nProvide investor relations (IR) support on presentation materials and event coordination;\nHandle any ad-hoc assignments.\n\nJob Requirements:\u00a0\n\nDegree holder with minimum 3 years\u2019 experience in Company Secretarial disciplines;\nChartered Company Secretary and familiar with Hong Kong Listing Rule is highly preferred;\u00a0\u00a0\nExperience in Chinese based companies/ property developer/ listed company is an advantage;\nExcellent command in both written and spoken English and Mandarin;\nWilling to learn and with \u201cCan do\u201d attitude;\nCandidates with more experience will be considered as Assistant Manager, IR & Company Secretary\n\nWe offer attractive remuneration package and excellent career development to the right candidate. Interested parties please clicking \"Apply Now\" to submit full resume with availability, current and expected salary to us.\n\nWe are an equal opportunity employer and welcome applications from all qualified candidates. All information provided by applicants will be treated in strictest confidence and handled confidentially for recruitment-related purposes within the company and our associated company. Applicants may be considered for other suitable positions within the company over a one-year period, after which their personal data will be destroyed.\u00a0", "employment_types": ["Full Time", "Permanent"], "selling_points": ["5-day work", "Medical, Study and Exam Leave", "2-3 years company secretarial experience"], "locations": ["Tsim Sha Tsui"], "categories": ["Professional Services", "Business Consultancy", "Company Secretary"], "post_time": "2022-01-14T08:23:31Z", "salary": {"currency": null, "max": null, "min": null, "period": "monthly", "term": null}, "salary_visible": false, "title_keywords": ["company secretarial assistant"], "responsibilities": ["ad-hoc assignments", "transactions", "coordinate", "reports", "coordination"], "requirements": {"degrees": ["degree holder"], "majors": [], "languages": ["english", "chinese", "mandarin"], "language_level": ["advantage", "excellent"], "hard_skills": [], "soft_skills": ["willing to learn"], "languages_combined": [{"language": "english", "language_level": ["excellent"]}, {"language": "chinese", "language_level": ["advantage"]}, {"language": "mandarin", "language_level": ["excellent"]}]}, "experience_required": {"duration": ["minimum 3 years"], "field": ["developer", "secretarial"]}}, {"job_id": "100003009048420", "location_code": "hk", "company": "Guangdong Investment Ltd", "job_title": "SECRETARIAL MANAGER /DEPUTY SECRETARIAL MANAGER /SECRETARIAL OFFICER", "description": "We are hiring an incumbent in Company Secretarial Department on temporary contract as a maternity leave cover for 6 months from March to August 2022 with below job details.\u00a0\n\nJob Responsibilities:\n\nAssist in full spectrum of company secretarial matters for HK and China companies to ensure compliance with corporate governance, statutory, regulatory and group requirements\nLiaise and coordinate with internal and external parties on all related company secretarial matters\nMaintain company secretarial records, statutory filings and related documents\nAssist in departmental administration and participate in ad hoc projects as assigned\nJob Requirements:\n\nDiploma / Degree holder or its equivalent in related discipline\nMember of HKCGI/CGI (student member will also be considered)\n3-4 years\u2019 hands-on solid company secretarial experience, preferably with exposure in commercial organizations or professional firms, experience in PRC company secretarial matters an advantage\nWell-versed in HK Companies Ordinance\nGood command of English and Mandarin\nStrong PC knowledge in MS Office applications and Chinese word processing\nSelf-motivated, proactive, well-organized, detail-minded and able to work independently\nCandidate with less experience and qualifications will be considered for the post of \u201cTemporary Assistant \u2013 Company Secretarial\u201d\nWorking Location: Tsuen Wan, New Territories, HONG KONG (near MTR)\n\n\n\nInterested parties please send your full resume quoting job reference number (Ref: JDB/SDMSL/TCSO/20211231) with present salary, expected salary and\u00a0available date via e-mail to\u00a0ghr-recruitment.sdms @simedarby.com.hk\u00a0\n\nFor more information about us, please visit our website.\n\nFollow us on\u00a0our\u00a0LinkedIn\u00a0and stay tuned!\n\n\nAll information provided by applicants will be treated in strict confidence and used for recruitment purpose only.", "employment_types": ["Full Time"], "selling_points": ["Organise shareholder and board meetings", "Participate in M&A projects", "Provide Listing Rules compliance advice"], "locations": ["Sheung Wan"], "categories": ["Professional Services", "Company Secretary"], "post_time": "2022-01-14T06:30:25Z", "salary": {"currency": null, "max": null, "min": null, "period": "monthly", "term": null}, "salary_visible": false, "title_keywords": ["officer", "manager"], "responsibilities": ["liaise", "related documents", "internal and external parties", "coordinate with", "ensure compliance", "maintain", "ad hoc projects", "administration"], "requirements": {"degrees": ["diploma", "degree holder"], "majors": [], "languages": ["english", "chinese", "mandarin"], "language_level": ["good command"], "hard_skills": ["chinese word processing", "companies ordinance", "pc knowledge", "wan", "ms office"], "soft_skills": ["detail-minded", "self-motivated", "work independently", "well-organized", "hands-on", "proactive"], "languages_combined": [{"language": "english", "language_level": ["good command"]}, {"language": "chinese", "language_level": []}, {"language": "mandarin", "language_level": ["good command"]}]}, "experience_required": {"duration": ["3-4 years"], "field": ["commercial", "secretarial"]}}, {"job_id": "100003009044538", "location_code": "hk", "company": "VTech Corporate Services Limited", "job_title": "Company Secretarial Officer  (VCO214/J01)", "description": "\u00a0Responsibilities:\n\nHandle full spectrum of company secretarial matters;\nReview and supervise junior company secretary;\nOther ad hoc projects.\n\nRequirements:\n\nDegree or diploma holder in Business Administration/Corporate Governance or a related discipline\nQualified professional member or student member of ICSA/HKICS\n\nKnowledge in Corporate Affair System (\"CAS\") is preferred\n3 years or above hands on and solid company secretary experience\nProficient in MS Office,\u00a0English and Chinese typing\nFluent English, Cantonese and Mandarin\nPositive attitude with excellent interpersonal and communication skills\nStrong sense of responsibility and ability to work independently with minimum supervision\n\nBenefits:\n\n\u00a0\u00a0\u00a0\u00a0\u00a0\u00a0\u00a0\u00a0 5 days work\n\u00a0\u00a0\u00a0\u00a0\u00a0\u00a0\u00a0\u00a0 Excellent career advancement opportunities with attractive remuneration and allowance\n\u00a0\u00a0\u00a0\u00a0\u00a0\u00a0\u00a0\u00a0 Gain valuable experience in providing professional services to clients in various sectors\n\u00a0\u00a0\u00a0\u00a0\u00a0\u00a0\u00a0\u00a0 Annual Leave, Paid Sick Leave, Medical benefits, Exam Leave and Study Leave\n\nSalary will be commensurate with the qualification and working experience of the candidate.\u00a0All information received will be kept in strict confidence and for employment related purpose(s) only.", "employment_types": ["Full Time", "Permanent"], "selling_points": ["1-3 years listed company secretarial experience", "Full spectrum of company secretarial duties", "Detailed-oriented, well-organized and responsible"], "locations": ["Tai Po Area"], "categories": ["Professional Services", "Company Secretary"], "post_time": "2022-01-13T04:29:37Z", "salary": {"currency": null, "max": null, "min": null, "period": "monthly", "term": null}, "salary_visible": false, "title_keywords": ["company secretarial officer"], "responsibilities": ["review", "ad hoc projects"], "requirements": {"degrees": ["diploma holder", "degree"], "majors": ["business administration"], "languages": ["cantonese", "english", "chinese", "mandarin"], "language_level": ["fluent", "proficient"], "hard_skills": ["typing", "ms office"], "soft_skills": ["communication skills", "work independently", "sense of responsibility", "positive attitude", "hands on", "interpersonal"], "languages_combined": [{"language": "cantonese", "language_level": ["fluent"]}, {"language": "english", "language_level": ["fluent", "proficient"]}, {"language": "chinese", "language_level": ["proficient"]}, {"language": "mandarin", "language_level": ["fluent"]}]}, "experience_required": {"duration": ["3 years"], "field": []}}, {"job_id": "100003009048593", "location_code": "hk", "company": "Logan Group Company Limited", "job_title": "Senior Officer/ Assistant Manager, Company Secretary", "description": "Diploma or Certificate holder in company secretaryship or related discipline\nHKCGI / CGI Student Member\n2 years\u2019 working experience in company secretarial field andpreferably in listed companies\nDiligent, self-motivated and willing to work under pressure\nProficiency in MS Office Application\nGood command of written and spoken English and Chinese\n\nWe offer attractive remuneration package to the right candidate. Please apply with full resume stating present and expected salaries to: Group Human Resources Department, Century City Holdings Limited, 11/F, 68 Yee Wo Street, Causeway Bay, Hong Kong or fax to 2895-5766.\n\nAll personal data / information provided by applicants to Century City Group will be used for recruitment and related purpose(s) only.\n\nWe are an Equal Opportunity Employer.", "employment_types": ["Full Time", "Permanent"], "selling_points": ["Handle Subsidiary, Annual Report, Organize Meeting", "Chartered with 3 yrs exp, Can do attitude, Stable", "5 days work, double pay, medical, bonus, meal"], "locations": ["Tsim Sha Tsui"], "categories": ["Professional Services", "Company Secretary", "Legal & Compliance", "Property / Real Estate", "Others"], "post_time": "2022-01-14T06:52:09Z", "salary": {"currency": null, "max": null, "min": null, "period": "monthly", "term": null}, "salary_visible": false, "title_keywords": ["company secretary", "senior officer", "assistant manager,"], "responsibilities": ["work under pressure"], "requirements": {"degrees": ["certificate", "diploma"], "majors": [], "languages": ["english", "chinese"], "language_level": ["good command"], "hard_skills": ["ms office"], "soft_skills": ["self-motivated", "diligent", "work under pressure"], "languages_combined": [{"language": "english", "language_level": ["good command"]}, {"language": "chinese", "language_level": ["good command"]}]}, "experience_required": {"duration": ["2 years"], "field": ["secretarial"]}}, {"job_id": "100003009050770", "location_code": "hk", "company": "Linkpath CPA Limited", "job_title": "Company Secretarial  Senior / Supervisor", "description": "Who are we?\n\nSleek.com\u00a0is the SMEs operating system - we help them register companies in Singapore, Hong Kong, Australia & the United Kingdom and assist them with the management of their accounting, audit and taxes, in a 100% digital manner. We build cutting edge technology to automate manual work, and provide a delightful experience to our 6,000+ clients. Naturally, we are continuously looking for great people to join our dynamic team!\n\nWe are a team of 200+ builders from 17 countries, with offices in Singapore, Hong Kong, Australia, the United Kingdom & the Philippines, committed to delivering a great experience to our clients.\n\nAt Sleek, you will find a fast-paced environment focused on building great solutions, and endless opportunities for learning and knowledge sharing, whether it\u2019s around a coffee with your colleagues at the office, or via video calls with your peers based overseas!\n\nWe are looking for a Company Secretary Assistant to join our Hong Kong team!\n\n\n\nTo do what?\n\n\nAs a Company Secretary Executive, you will play a key role within Sleek by helping business owners and entrepreneurs start their projects with the registration of legal entities and the ongoing governance management!\n\nMore specifically?\n\nIncorporation, annual maintenance and deregistration of Hong Kong companies\nPreparation of minutes, resolutions, annual return, AGM etc.\u00a0\nUpdating and maintaining statutory filings and corporate records\nChanging in company structure / particulars e.g. shareholdings and directorships\nWork with accounting team and auditors to ensure clients\u2019 companies are in good compliance\nAdvise external and internal clients on company secretarial matters, also handling non statutory matters such as due diligence or regular review\nWho are you?\n\nDegree or diploma in Business Administration/Corporate Governance or a related discipline\n3-5 years of related company secretarial experience in a professional firm or law firm (for HK companies)\nQualified professional member or student member of ICSA/HKICS will be an advantage\nGood knowledge of corporate secretarial law and familiar with Companies Ordinance, rules and regulations of regulatory bodies\nExcellent written and spoken English and Chinese, conversational Mandarin will be an advantage\nIndependent, meticulous, pro-active, attentive to details, self-motivated, keen to learn\nWilling to take on new challenges and excellent communication skills with people\n\nHow about the Company & work environment?\n\nOur values are: Simplicity, Loyalty, Excellence, Entrepreneurship, Kindness\nWe take corporate social responsibility very seriously\u00a0at company level and absorb the yearly carbon footprint of all of our employees\nMulticultural team with 15+ nationalities and as many languages spoken internally!\nOne day of work from home per week\nA pool of HKD 7,000/year of Health & Benefits\nA great and vast high floor corner office in the heart of Central with an amazing view over Hong Kong and the mountains\n\nWhat you need to do now?\n\nSend your full resume with present and expected salary to HR Team by clicking \"APPLY NOW\". Candidates with less experiences will be considered if you are able to proof yourself. We regret that only shortlisted candidates will be notified.\n\n(Information provided will be treated in strict confidence and will only be used for recruitment-related purposes.)", "employment_types": ["Full Time", "Permanent"], "selling_points": [], "locations": ["Sheung Wan"], "categories": ["Professional Services", "Company Secretary"], "post_time": "2022-01-14T11:20:30Z", "salary": {"currency": null, "max": null, "min": null, "period": "monthly", "term": null}, "salary_visible": false, "title_keywords": ["supervisor"], "responsibilities": [], "requirements": {"degrees": [], "majors": [], "languages": [], "language_level": [], "hard_skills": [], "soft_skills": [], "languages_combined": []}, "experience_required": {"duration": [], "field": []}}, {"job_id": "100003009047442", "location_code": "hk", "company": "Century City Holdings Limited", "job_title": "Company Secretarial Assistant", "description": "Our Client is a listed food company in Hong Kong, to cope with their fast expansion, they are currently seeking a Financial Controller cum Company Secretary to join their team.\n\n\n\nResponsibilities:\n\nOversee and manage the whole finance, accounting and taxation functions\u00a0in HK\nEnsure all accounting procedures comply with the internal policy and legal compliance\nAdvise the Board on appropriate financial policies and strategies in order to achieve the organization\u2019s mission and objectives.\nPrepare monthly financial reports and consolidated management reports\nPrepare budget & forecast, raise out any potential variances\nLiaise with auditors and other professionals in annual audit, tax and company\u00a0secretarial filing\nImproving efficiencies and reducing costs across the business\nAd hoc projects and assignments\n\n\u00a0Requirements:\n\nDegree holder in Accounting, Finance or a related discipline\nQualified Accountant and memberof HKICPA, ACCA, CPAA\nAt least 10 years of accounting experience in listed companies with all rounded and hands on operation accounting background preferably with company secretary knowledge\nGood knowledge of Hong Kong listing rules, Hong Kong tax regulations policies and accounting system\nFMCG, manufacturing or food industry experience is preferable\nStrong command of languages (English, Cantonese and Mandarin)\nAdaptable, demonstrate strong leadership and able to communicate well with different level of colleagues", "employment_types": ["Full Time", "Permanent"], "selling_points": ["Diploma holder in related discipline", "HKCGI / CGI Student Member", "Proficiency in MS Office Application"], "locations": ["Causeway Bay"], "categories": ["Professional Services", "Business Consultancy", "Company Secretary", "Legal & Compliance"], "post_time": "2022-01-14T03:06:43Z", "salary": {"currency": null, "max": null, "min": null, "period": "monthly", "term": null}, "salary_visible": false, "title_keywords": ["company secretarial assistant"], "responsibilities": ["tax", "taxation", "financial reports", "annual audit", "financial policies", "compliance", "procedures", "budget", "management reports", "ad hoc projects", "forecast", "liaise with", "costs"], "requirements": {"degrees": ["degree holder"], "majors": ["finance", "accounting"], "languages": ["cantonese", "english", "mandarin"], "language_level": [], "hard_skills": ["acca", "accounting system", "hkicpa"], "soft_skills": ["adaptable", "hands on", "leadership"], "languages_combined": [{"language": "cantonese", "language_level": []}, {"language": "english", "language_level": []}, {"language": "mandarin", "language_level": []}]}, "experience_required": {"duration": ["at least 10 years"], "field": ["manufacturing", "fmcg", "accounting experience", "food industry", "operation", "accounting"]}}, {"job_id": "100003009051212", "location_code": "hk", "company": "One Recruitment Limited", "job_title": "Paralegal - Corporate Finance (40k + OT)", "description": "Excellent mid-level opportunity for company secretary with experience gained from banking/ insurance sector!\n\nYour new company\nOur client is a financial institution that endeavours to better their service and pursue breakthroughs in every way possible. Time and time again, they have proven themselves the industry's avant-garde leading in the front and be the best at what they do. To maintain their position as a market leader, they are currently hiring a company secretary of high calibre to join their team.\n\nYour new role\n\nHandle a full spectrum of company secretarial duties for the group as well as its subsidiaries\nEnsure regulatory compliance and keep abreast of any corporate governance related updates\nOrganise board, committee and shareholders' meetings and prepare relevant minutes and papers\nUpdate and ensure maintenance of statutory records and filings\nHandle ad hoc projects when required\n\nWhat you'll need to succeed\n\nAssociate member of HKCGI\n7+ years of company secretarial experience, preferably gained from Hong Kong listed companies/ banks/ insurance companies\nExcellent command in Chinese and English\n\n\nWhat you need to do now\n\nIf you're interested in this role, click 'apply now' to forward an up-to-date copy of your CV, or call us now. If this job isn't quite right for you but you are looking for a new position, please contact Natalie Kwok at +852 2230 7948 or natalie.kwok@hays.com.hk for a confidential discussion on your career.", "employment_types": ["Full Time", "Permanent"], "selling_points": ["Good Job Satisfaction", "Prime Working Location", "Attractive Remuneration Package"], "locations": ["Central"], "categories": ["Banking / Finance", "Investment", "Professional Services", "Company Secretary", "Legal & Compliance"], "post_time": "2022-01-15T04:53:32Z", "salary": {"currency": "HKD", "max": 44999, "min": 35000, "period": "monthly", "term": null}, "salary_visible": true, "title_keywords": ["paralegal", "corporate finance"], "responsibilities": ["maintenance", "compliance", "maintain", "ad hoc projects", "contact", "banking", "insurance"], "requirements": {"degrees": [], "majors": [], "languages": ["english", "chinese"], "language_level": ["excellent"], "hard_skills": ["maintenance"], "soft_skills": ["interested in"], "languages_combined": [{"language": "english", "language_level": ["excellent"]}, {"language": "chinese", "language_level": ["excellent"]}]}, "experience_required": {"duration": ["7+ years"], "field": ["secretarial", "insurance", "banking"]}}, {"job_id": "100003009046528", "location_code": "hk", "company": "Sun Hung Kai Properties Ltd", "job_title": "COMPANY SECRETARIAL ASSISTANT", "description": "\u8077\u8cac:\n1.\u8ca0\u8cac\u516c\u53f8\u5408\u898f\u7ba1\u7406\u9ad4\u7cfb\u5efa\u8a2d\uff0c\u4e26\u6307\u5c0e\u4e0b\u5c6c\u55ae\u4f4d\u7684\u5408\u898f\u7ba1\u7406\u5de5\u4f5c\uff1b\n2.\u8ca0\u8cac\u5408\u898f\u98a8\u96aa\u8b58\u5225\u8207\u8a55\u4f30\uff0c\u5c0d\u91cd\u5927\u98a8\u96aa\u9032\u884c\u76e3\u63a7\uff0c\u7de8\u5236\u98a8\u96aa\u7ba1\u7406\u5831\u544a\uff1b\n3.\u8ca0\u8cac\u5236\u5b9a\u3001\u4fee\u8a02\u516c\u53f8\u5408\u898f\u7ba1\u7406\u76f8\u95dc\u88fd\u5ea6\u3001\u624b\u518a\u7b49\u6587\u4ef6\uff1b\n4.\u8ca0\u8cac\u516c\u53f8\u88fd\u5ea6\u7b49\u6587\u4ef6\u7684\u5408\u898f\u6027\u5be9\u6838\u8207\u7ba1\u7406\uff1b\n5.\u8ca0\u8cac\u958b\u5c55\u5408\u898f\u76e3\u7763\u8abf\u67e5\u3001\u5408\u898f\u5ba3\u50b3\u3001\u5408\u898f\u57f9\u8a13\u6d3b\u52d5\uff1b\n6.\u8ca0\u8cac\u5408\u898f\u7ba1\u7406\u4fe1\u606f\u5316\u5e73\u53f0\u7684\u5efa\u8a2d\u3001\u7ba1\u7406\u548c\u63a8\u5ee3\u904b\u7528\uff1b\n7.\u914d\u5408\u96c6\u5718\u516c\u53f8\u5408\u898f\u7ba1\u7406\u5de5\u4f5c\u7684\u5efa\u8a2d\uff1b\n8.\u5176\u4ed6\u81e8\u6642\u6027\u5de5\u4f5c\u3002\n\n\u8981\u6c42:\n1.\u5177\u67093\u5e74\u4ee5\u4e0a\u4f01\u696d\u5408\u898f\u3001\u5167\u63a7\u3001\u98a8\u96aa\u7ba1\u7406\u6216\u6cd5\u52d9\u5de5\u4f5c\u7d93\u9a57\u512a\u5148\uff1b\n2.\u5177\u6709\u4e2d\u570b\u5167\u5730\u6cd5\u5f8b\u8077\u696d\u8cc7\u683c\u6216\u666e\u901a\u6cd5\u570b\u5bb6\u6216\u5730\u5340\u5f8b\u5e2b\u8cc7\u683c\u3001\u8a3b\u518a\u6703\u8a08\u5e2b\u7b49\u8cc7\u8cea\u512a\u5148\uff1b\n3.\u5177\u6709\u826f\u597d\u7684\u6e9d\u901a\u80fd\u529b\u3001\u5206\u6790\u80fd\u529b\u53ca\u5718\u968a\u5408\u4f5c\u80fd\u529b\uff1b\n4.\u5177\u6709\u8f03\u5f37\u7684\u6587\u5b57\u5beb\u4f5c\u80fd\u529b\uff0c\u826f\u597d\u7684\u4e2d\u82f1\u6587\u8868\u9054\u80fd\u529b\uff1b\n5.\u5177\u6709\u826f\u597d\u7684\u8077\u696d\u64cd\u5b88\uff0c\u8a8d\u540c\u4f01\u696d\u5408\u898f\u6587\u5316\u3002", "employment_types": ["Full Time", "Permanent"], "selling_points": ["Finalist of ICSA or HKICS with 2 yrs' exp", "Knowledge in CSA will be an advantage", "Company secretarial matters for the Group"], "locations": ["Wan Chai"], "categories": ["Professional Services", "Company Secretary", "Legal & Compliance"], "post_time": "2022-01-13T13:13:44Z", "salary": {"currency": null, "max": null, "min": null, "period": null, "term": null}, "salary_visible": false, "title_keywords": ["company secretarial assistant"], "responsibilities": [], "requirements": {"degrees": [], "majors": [], "languages": [], "language_level": [], "hard_skills": [], "soft_skills": [], "languages_combined": []}, "experience_required": {"duration": [], "field": []}}, {"job_id": "100003009056191", "location_code": "hk", "company": "JFE Consulting Limited", "job_title": "HR Assistant/Secretary - LEGAL", "description": "Our client, one of the leading law firms, is looking for high calibres to join their winning team:-\n\nResponsiblities:\n\nPrepares variety of legal documents under guidance of staff attorneys and firm management, including summonses, subpoenas, complaints, and responses\nSupports attorney trial proceedings, assisting in collecting evidence, compiling artefacts, consolidating facts, preparing documents as needed, and tracking cases\nDevelops cases by providing research for assigned attorney, maintaining communications with involved parties, and cataloguing information provided\nMaintains regular communication with clients, helping to keep them informed on case progresses\nRequirements:\n\nDiploma/Bachelor's degree preferred\nMinimu two-year degree required.\nExperience working in a legal setting strongly preferred.\nStrong analytical skills, ability to work as part of a team.", "employment_types": ["Full Time", "Permanent"], "selling_points": ["Leading law firm", "HR Assistant/Legal Secretary", "5-day work, attractive salary"], "locations": ["Central"], "categories": ["Professional Services", "Company Secretary", "Legal & Compliance", "Translation"], "post_time": "2022-01-18T03:31:02Z", "salary": {"currency": null, "max": null, "min": null, "period": "monthly", "term": null}, "salary_visible": false, "title_keywords": ["secretary", "hr assistant"], "responsibilities": ["guidance", "management", "communications with", "maintaining", "communication", "tracking"], "requirements": {"degrees": ["diploma", "degree", "bachelor"], "majors": [], "languages": [], "language_level": [], "hard_skills": ["analytical skills"], "soft_skills": ["analytical skills"], "languages_combined": []}, "experience_required": {"duration": [], "field": ["legal"]}}, {"job_id": "100003009043740", "location_code": "hk", "company": "Klook Travel Technology Limited", "job_title": "Company Secretarial Lead", "description": "Job Description:\n\n\nWorking experienced in company secretarial practice under the Hong Kong New Companies Ordinance, Hong Kong Listing Rules and Securities and Futures Ordinance\nAssisting in handling full set of company secretarial duties of all private companies in Hong Kong under the New Companies Ordinance\nAssist in preparing and submitting statutory and regulatory filings\nAssist in preparation of interim and annual reports, announcements, circulars and SFO filings\nCoordinate with company secretarial teams of the Company's subsidiaries worldwide to ensure that proper corporate records are kept and relevant company laws/regulations are complied with\nAssist in preparing corporate documentation to shareholders including interim/annual report, circular and announcements\nAssist in organizing Board, Shareholders and Committees meetings\nProvide secretarial and administrative support to the department\nPerform ad hoc duties as assigned\n\nMinimum Qualifications:\n\n\nDegree-holder, preferably in corporate administration, law, accounting or company secretarial studies\nAssociate of The Hong Kong Chartered Governance Institute / The Chartered Governance Institute\n1- 3 years company secretarial work experiences preferably in a listed company on the Main Board of Hong Kong Stock Exchange\nGood command of written and spoken English and Chinese as well as translation skills\nAble to work independently, strong analytical, interpersonal and communications skills\nPossess multi-tasking ability, pleasant, detail-oriented, well-organised and strong sense of responsibility\nProficiency in MS Word, Excel and PowerPoint and Chinese Words input and have experience in using Hong Kong Stock Exchange electronic submission system\n\nWe offer an attractive remuneration package including 5-day work, flexible work hours and other benefits to the right candidates. Interested parties please forward full resume with expected salary and quote job reference number by \"Apply Now\" or to\n\nVTech Group of Companies,\nThe Human Resources and Administration Department,\n23/F, Block 1, Tai Ping Industrial Centre,\n57 Ting Kok Road, Tai\u00a0Po,\u00a0Hong Kong\n\nFor more information about us, please visit our website at:\u00a0www.vtech.com\u00a0\u00a0\u00a0\nAll applications will be used for the purpose of recruitment only. Applicants not invited for an interview within 4 weeks may consider their applications unsuccessful. We will retain the applications for a maximum period of six months and may refer them to suitable openings within our Group.\u00a0\n", "employment_types": ["Full Time"], "selling_points": ["Handling full range of company secretarial duties", "Leading new entity set up", "Handling statutory compliance"], "locations": ["Not Specified"], "categories": ["Professional Services", "Business Consultancy", "Company Secretary", "Information Technology (IT)", "Others"], "post_time": "2022-01-13T01:45:02Z", "salary": {"currency": null, "max": null, "min": null, "period": "monthly", "term": null}, "salary_visible": false, "title_keywords": ["lead"], "responsibilities": ["regulations", "ad hoc duties", "administration", "administrative support", "teams", "coordinate with", "reports", "documentation", "listing", "report"], "requirements": {"degrees": ["degree"], "majors": ["accounting", "law"], "languages": ["english", "chinese"], "language_level": ["proficiency", "good command"], "hard_skills": ["excel", "words", "ms word", "translation", "securities and futures ordinance", "powerpoint", "documentation", "companies ordinance", "sfo", "exchange"], "soft_skills": ["work independently", "sense of responsibility", "detail-oriented", "pleasant", "multi-tasking", "well-organised", "interpersonal"], "languages_combined": [{"language": "english", "language_level": ["good command"]}, {"language": "chinese", "language_level": ["proficiency", "good command"]}]}, "experience_required": {"duration": ["1- 3 years"], "field": ["secretarial"]}}, {"job_id": "100003009047571", "location_code": "hk", "company": "Intertrust Hong Kong Limited", "job_title": "Company Secretarial Associate - Offshore Cayman / BVI", "description": "What you will do:\nHandling full range of company secretarial duties covering all group entities globally, including drafting board minutes and arranging for notorisation\nLeading new entity set up and liaising with internal stakeholders and external advisors\nAssisting with enhancing corporate governance systems and procedures\nHandling statutory compliance and licensing matters, with assistance from external advisors\n\nWhat you will need:\n\nAt least 6 years of experience in company secretarial or corporate governance support\nQualification in company secretary, corporate governance or related disciplines preferred\nWell-organized, collaborative, proactive and strong sense of ownership; ability to work independently\n\nInterested parties please click [via APPLY NOW] \u00a0to apply job.\n\n\u6709\u610f\u7533\u8acb\u8005\u8acb \u6309 APPLY NOW\u7533\u8acb\n\n", "employment_types": ["Full Time", "Permanent"], "selling_points": ["Fresh graduates are welcomed", "Career development in global company", "A team player and proactive learning attitude"], "locations": ["Wan Chai"], "categories": ["Banking / Finance", "Others", "Professional Services", "Company Secretary", "Legal & Compliance"], "post_time": "2022-01-14T03:28:41Z", "salary": {"currency": null, "max": null, "min": null, "period": "monthly", "term": null}, "salary_visible": false, "title_keywords": ["associate"], "responsibilities": ["statutory compliance", "systems", "procedures", "liaising with"], "requirements": {"degrees": [], "majors": [], "languages": [], "language_level": [], "hard_skills": [], "soft_skills": ["work independently", "proactive", "well-organized", "collaborative"], "languages_combined": []}, "experience_required": {"duration": ["at least 6 years"], "field": ["secretarial"]}}, {"job_id": "100003009042481", "location_code": "hk", "company": "Bank of Communications Trustee Limited", "job_title": "Company Secretarial Senior Officer", "description": "We are looking for an ambitious and energetic Company Secretarial Administrator to join us.\n\nYour Position\nWe enable our clients to incorporate a legal entity quickly and efficiently with the formation and transaction support services through our global network of own and third party offices. You will work closely with the team with core areas of responsibility including:\u00a0\nAll company secretarial matters including the setting up of entities (including companies and partnerships) in offshore jurisdictions (Cayman and BVI), updating statutory registers and effectuating other company transactions\nManage statutory filings and non-statutory matters such as due diligence on clients and opening of bank accounts\nHandle and deal with company secretarial services enquiries from clients\nLiaise with other Intertrust offices to ensure company secretarial services are provided on a timely basis\n\nYour profile\n\n\nBachelor Degree/diploma holder in business administration/corporate governance or equivalent\u00a0\nQualified professional member or student member of ICSA/HKICS\nMinimum of 2 years\u2019 of relevant experience in a professional firm or law firm\nGood command of both written and spoken English, conversational Mandarin\nIndependent, meticulous, pro-active, attentive to details, self-motivated, outspoken, keen to learn\nAble to adapt in new challenges and with excellent communication skills and a team player\n\nWe offer\nWorking at Intertrust means entering a dynamic, international and growth-orientated company. We provide you with outstanding opportunities for your professional and personal development through our local and global Intertrust Academies. Our International Mobility program enables talented employees to gain working experience abroad. We offer a competitive salary and benefits, commensurate with your qualifications and experience.\n\nInterested?\nInterested candidates, please contact us at 2901 2182 for more information.\nWe are looking forward to meeting you!", "employment_types": ["Full Time", "Permanent"], "selling_points": ["Provide guidance and support to junior staff", "Degree Holder or above", "2 years or above relevant experiences"], "locations": ["Not Specified"], "categories": ["Banking / Finance", "Financial Services", "Professional Services", "Company Secretary"], "post_time": "2022-01-12T07:39:57Z", "salary": {"currency": null, "max": null, "min": null, "period": "monthly", "term": null}, "salary_visible": false, "title_keywords": ["senior officer"], "responsibilities": ["due diligence", "support services", "transactions", "communication", "liaise with", "third party", "administration"], "requirements": {"degrees": ["diploma holder", "degree", "bachelor"], "majors": ["business administration"], "languages": ["english", "mandarin"], "language_level": ["conversational", "good command"], "hard_skills": [], "soft_skills": ["meticulous", "self-motivated", "communication skills", "independent", "attentive to details", "keen", "timely", "outspoken", "pro-active", "team player", "energetic"], "languages_combined": [{"language": "english", "language_level": ["good command"]}, {"language": "mandarin", "language_level": ["conversational", "good command"]}]}, "experience_required": {"duration": ["minimum of 2 years"], "field": ["relevant experience"]}}, {"job_id": "100003009049427", "location_code": "hk", "company": "JCK & Associates Limited", "job_title": "Company Secretarial Assistant \u2013 5 days work in Wan Chai - Knowledge in CSA -3 years working exp.", "description": "Responsibilities\nTo introduce, maintain and provide full spectrum of company secretarial services for the group of companies and client companies in various jurisdictions\nTo ensure compliance with regulatory disclosure, reporting and statutory filing requirements\nTo assist in organizing board / shareholders meeting\nTo provide guidance and support to junior staff\nTo prepare minutes, resolutions and statutory forms\nTo prepare documents for the opening of bank accounts and handle enquiries\nTo maintain proper statutory records and filing systems\nTo perform daily operations, processes, ad-hoc project and assignment as assigned by the superior(s)\nRequirements\nDegree Holder or above\nMember of HKCGI\n2 years or above relevant experiences preferably gained in sizeable listed companies or professional firms\nPositive attitude with good analytical , interpersonal and communication skills\nMeticulous, well-organised, self-motivated, strong sense of responsibility and able to work independently\nFluent in spoken and written English, Cantonese and Mandarin\nComputer literate including MS words, Excel, Power point and CSA\nPrevious experience working in financial institutions is an advantage\nPlease click \"Apply Now\" to submit your application.\nPersonal data collected will be used for recruitment purpose only.", "employment_types": ["Full Time", "Permanent"], "selling_points": ["3 years\u2019 working experiences", "Provide company secretarial services", "Handle general coordination & administrative work"], "locations": ["Wan Chai Area"], "categories": ["Professional Services", "Company Secretary"], "post_time": "2022-01-14T08:36:39Z", "salary": {"currency": null, "max": null, "min": null, "period": "monthly", "term": null}, "salary_visible": false, "title_keywords": ["company secretarial assistant"], "responsibilities": ["ad-hoc", "reporting", "systems", "ensure compliance", "handle enquiries", "daily operations", "maintain", "provide guidance", "prepare documents"], "requirements": {"degrees": ["degree holder"], "majors": [], "languages": ["cantonese", "english", "mandarin"], "language_level": ["fluent"], "hard_skills": ["power point", "excel", "ms words"], "soft_skills": ["communication skills", "meticulous", "self-motivated", "work independently", "sense of responsibility", "positive attitude", "well-organised", "interpersonal"], "languages_combined": [{"language": "cantonese", "language_level": ["fluent"]}, {"language": "english", "language_level": ["fluent"]}, {"language": "mandarin", "language_level": ["fluent"]}]}, "experience_required": {"duration": ["2 years"], "field": ["financial institutions"]}}, {"job_id": "100003009044172", "location_code": "hk", "company": "Billy Ho and Associates CPA Limited", "job_title": "Company Secretarial Assistant", "description": "Our client, an international law firm is urgently looking for a Paralegal, Corporate Finance to join their dynamic team in Central office.\n\nJob Responsibilities:\n\nMaintain proper filing management system for IPO transactions of HK/China regions\nConduct legal research, due diligence and documentation\nHandle interview and attend meetings with Associates on listing matters and requirements\nAssist in preparing verification note and related coordination\nHandle translations and drafting\nProvide full spectrum legal support to Partners and Associate\nJob Requirements:\n\nBachelor degree of law with at least 1 year experience in corporate finance areas within legal firms/ brokerage firms\nPrevious experience in Corporate in one of the following, such as M&A/IPO/DD/DCM is preferred\nFluency of English with native Mandarin is highly recommended\u00a0\nAble to work under pressure\nGood interpersonal and communication skills", "employment_types": ["Full Time", "Permanent"], "selling_points": ["We are professional firm company secretarial dept", "We offer attractive salary + bonus + overtime pay", "We offer medical insurance"], "locations": ["Tsim Sha Tsui"], "categories": ["Professional Services", "Company Secretary"], "post_time": "2022-01-13T03:17:03Z", "salary": {"currency": null, "max": null, "min": null, "period": "monthly", "term": null}, "salary_visible": false, "title_keywords": ["company secretarial assistant"], "responsibilities": ["due diligence", "management", "transactions", "maintain", "attend meetings", "coordination", "documentation", "listing"], "requirements": {"degrees": ["degree", "bachelor"], "majors": ["finance", "law"], "languages": ["english", "mandarin"], "language_level": ["fluency", "native"], "hard_skills": [], "soft_skills": ["communication skills", "interpersonal", "work under pressure"], "languages_combined": [{"language": "english", "language_level": ["fluency"]}, {"language": "mandarin", "language_level": ["native", "fluency"]}]}, "experience_required": {"duration": ["at least 1 year"], "field": ["brokerage", "legal", "corporate finance"]}}, {"job_id": "100003009043342", "location_code": "hk", "company": "David James Recruitment Limited", "job_title": "Deputy Company Secretary \u2013 Local Conglomerate ($40 \u2013 45K)", "description": "Duties:\n\nProvide company secretarial services and support to local and International clients for Hong Kong and Offshore companies incorporation;\nArrange annual return and other statutory filings and prepare minutes;\nEdit and update corporate materials;\nHandle general coordination and administrative work of company secretarial department;\nBack up support between team members on any ad-hoc matters\n\nRequirements:\n\nHolder of diploma or above in law, company secretarial studies or related discipline\nKnowledge in CSA programme is an advantage\nGood command of spoken and written English/Chinese, fluency in Mandarin\n3 years\u2019 working experiences in Company Secretary field is an advantage\nAdministrative working experiences in Company Secretarial Department of Professional Firm would also be considered\nGood computer knowledge and familiar with MS office and Chinese word processing\nWell organized and systematic, detail-oriented, self-motivated with a strong sense of responsibility, good communication and interpersonal skills\n\nWe offer 5 days work and bank holidays. Interested parties please apply with full CV quoting expected and last salary and availability emailing Attn: Ms. Angel LI by clicking \"Apply Now\".\n\n\n[Personal data collected will be used for recruitment purpose only]", "employment_types": ["Full Time", "Permanent"], "selling_points": ["Listed in-house role in a local conglomerate", "Handle mainly HK entitles", "Stable working environment"], "locations": ["Eastern Area"], "categories": ["Professional Services", "Business Consultancy", "Company Secretary", "Legal & Compliance"], "post_time": "2022-01-12T10:56:31Z", "salary": {"currency": null, "max": null, "min": null, "period": "monthly", "term": null}, "salary_visible": false, "title_keywords": ["company secretary"], "responsibilities": ["ad-hoc", "administrative work", "coordination"], "requirements": {"degrees": ["diploma or above"], "majors": ["law"], "languages": ["english", "chinese", "mandarin"], "language_level": ["fluency", "good command", "good"], "hard_skills": ["chinese word processing", "ms office"], "soft_skills": ["self-motivated", "sense of responsibility", "well organized", "systematic", "detail-oriented", "communication and interpersonal skills"], "languages_combined": [{"language": "english", "language_level": ["fluency", "good command", "good"]}, {"language": "chinese", "language_level": ["fluency", "good command", "good", "good"]}, {"language": "mandarin", "language_level": ["fluency", "good command", "good"]}]}, "experience_required": {"duration": ["3 years"], "field": ["secretarial", "administrative"]}}, {"job_id": "100003009043217", "location_code": "hk", "company": "Emperor Group", "job_title": "Senior Company Secretarial Officer / Assistant Company Secretarial Manager", "description": "Our related company, Bedford Consultants Limited, now looks for full time candidate for our Company Secretarial Assistant position with the following job duties:\n\nAssist in full range company secretarial and administrative duties for the private companies and associations;\nHandle filings and correspondences with the relevant regulatory and statutory authorities; and\nMaintain corporate records, filing documents and draft documents for clients.\n\n\u00a0Successful candidates will be:\n\nDiploma or above;\nGood command in spoken and written English and Cantonese, fair in Putonghua;\nSelf-motivated, well-organized and detail-oriented;\nGood analytical and problem-solving skills;\nGood at reading and following rules and regulations;\nProficient in Microsoft Office and Chinese Word Processing;\nStrong interpersonal skills;\nAble to work under pressure and multi-task;\nProficiency in CSA software is an advantage; and\nNo experiences are required, and welcome fresh graduate\n\nOur office is located in Tsim Sha Tsui East. Successful candidates will work in our company secretarial department under the supervision of manager to carry out the said duties.\n\nSuccessful candidates will receive:\n\nProfessional career with attractive salary + bonus, with overtime pay;\n5 days work, Mon- Fri from 9 am to 6 pm;\nExamination and study leave for recognized examinations;\n7 days annual leave in the first 2 years of employment;\nMedical insurance.\n\nIf you are interested, please send in your CV and cover letter with your expected salary.", "employment_types": ["Full Time", "Permanent"], "selling_points": ["Handle full spectrum of company secretarial matter", "Qualified member of HKCGI / CGI", "8 years or above company secretarial experience"], "locations": ["Wan Chai"], "categories": ["Professional Services", "Company Secretary", "Legal & Compliance", "Others", "Others"], "post_time": "2022-01-12T10:18:11Z", "salary": {"currency": null, "max": null, "min": null, "period": null, "term": null}, "salary_visible": false, "title_keywords": ["company secretarial manager", "company secretarial officer", "assistant"], "responsibilities": ["regulations", "software", "maintain", "administrative duties", "insurance", "work under pressure"], "requirements": {"degrees": ["fresh graduate", "diploma or above"], "majors": [], "languages": ["cantonese", "putonghua", "english", "chinese"], "language_level": ["good command", "proficient"], "hard_skills": ["problem-solving skills", "no", "chinese word processing", "microsoft office"], "soft_skills": ["self-motivated", "multi-task", "well-organized", "detail-oriented", "interpersonal skills", "problem-solving skills", "work under pressure"], "languages_combined": [{"language": "cantonese", "language_level": ["good command"]}, {"language": "putonghua", "language_level": ["good command"]}, {"language": "english", "language_level": ["good command"]}, {"language": "chinese", "language_level": ["proficient"]}]}, "experience_required": {"duration": [], "field": []}}, {"job_id": "100003009042748", "location_code": "hk", "company": "Guosen Securities (HK) Financial Holdings Company, Limited", "job_title": "Assistant (Strategic Development)", "description": "Our client is a sizable and well-established company. To cope with their expansion plan, they are now looking for a Deputy Company Secretary\n\nResponsibilities:\n\nHandle full spectrum of Company Secretarial matters for its listed and subsidiary entitles\nPrepare annual reports, interim reports, announcements, and circulars\nEnsure rules and regulations are compiled to government\u2019s requirements\nDraft and review all related documents and overseeing the compliance work\nCarry out ad-hoc tasks\n\nRequirements:\n\nDegree holder with Associate membership of HKICS/ICSA\n6 years+ related work experience\nExperience gained in listed companies is an advantage\n\u00a0Great attention to details and independency\n\nTo Apply\n\nInterested parties please send us your updated resume with your latest and expected salaries or please call +852 3611 7780 for a confidential discussion.", "employment_types": ["Full Time", "Permanent"], "selling_points": ["Attractive remuneration", "Prepare meeting minutes", "Experience in simplified Chinese writing"], "locations": ["Admiralty"], "categories": ["Admin & HR", "Secretary", "Banking / Finance", "Others", "Professional Services", "Company Secretary"], "post_time": "2022-01-12T08:39:40Z", "salary": {"currency": null, "max": null, "min": null, "period": "monthly", "term": null}, "salary_visible": false, "title_keywords": ["assistant"], "responsibilities": ["regulations", "related documents", "ad-hoc tasks", "review", "compliance", "reports"], "requirements": {"degrees": ["degree holder"], "majors": [], "languages": [], "language_level": [], "hard_skills": [], "soft_skills": ["attention to details"], "languages_combined": []}, "experience_required": {"duration": [], "field": ["related"]}}, {"job_id": "100003009043166", "location_code": "hk", "company": "ConnectedGroup Limited", "job_title": "Assistant Manager, Company Secretariat (HK$ 40k-55k)", "description": "Responsibilities:\n\n\nHandle independently full spectrum of company secretarial matters for the group companies\nPrepare directors\u2019 report, corporate governance report, interim report, announcements and circulars of listed members\nOrganize and general attendance to meetings of Board / Board committees / shareholders and handle relevant meeting materials\nProvide professional corporate governance support to the group to ensure due compliance with all statutory requirements\nParticipate and assist in ad-hoc projects as assigned\nWhere appropriate, take a supervisory role to a team of junior secretarial staff\nRequirements:\n\nAt least 8 years or above company secretarial experience in listed companies\nBachelor Degree or above in company secretarial studies or related discipline\nQualified member of HKCGI/CGI\nGood knowledge in compliance rules and regulations & ordinances, including Companies Ordinance, Listing Rules and Securities & Futures Ordinance\nProficient in MS Office and Chinese Word Processing\nFamiliarize with CSA\nExcellent command in written & spoken English & Chinese\nWell-organized, attentive to details, strong sense of responsibility, good communication and interpersonal skills\nCandidate with more experience will be considered as\u00a0Assistant Company Secretarial Manager\n\nWe offer\u00a05-day-work\u00a0week with competitive remuneration and benefit packages to the right candidate. Interested parties please send your application letter, resume, expected salary and availability to Human Resources Department, 28/F, Emperor Group Centre, 288 Hennessy Road, Wanchai, Hong Kong or by fax 2835-6677 or by clicking the \"Apply Now\" button below.\n\nWe are an equal opportunity employer & welcome applications from all qualified candidates. The information provided will be treated in strict confidence & be used only for consideration of your application for relevant / similar posts within the Emperor Group. Applicants not hearing from us within four weeks may consider their applications unsuccessful. We may retain the unsuccessful applications for a maximum period of\u00a024 months.", "employment_types": ["Full Time", "Permanent"], "selling_points": ["Cover a wide range of company secretarial matters", "Top-tier Property Developer", "Qualified Member of HKCGI/CGI"], "locations": ["Kwun Tong Area"], "categories": ["Professional Services", "Company Secretary", "Legal & Compliance"], "post_time": "2022-01-12T09:59:39Z", "salary": {"currency": "HKD", "max": 54999, "min": 45000, "period": "monthly", "term": null}, "salary_visible": true, "title_keywords": ["assistant manager,"], "responsibilities": ["attendance", "compliance", "statutory requirements", "ad-hoc projects", "report"], "requirements": {"degrees": ["degree or above", "bachelor"], "majors": [], "languages": ["english", "chinese"], "language_level": ["excellent", "proficient"], "hard_skills": ["companies ordinance", "chinese word processing", "ms office"], "soft_skills": ["communication and interpersonal skills", "well-organized", "attentive to details", "sense of responsibility"], "languages_combined": [{"language": "english", "language_level": ["excellent"]}, {"language": "chinese", "language_level": ["excellent", "proficient"]}]}, "experience_required": {"duration": ["at least 8 years"], "field": ["secretarial"]}}, {"job_id": "100003009043744", "location_code": "hk", "company": "Michael Page", "job_title": "Company Secretary Officer", "description": "Responsibilities:\n\nProvide general administration support to the department\nPrepare meeting minutes, reporting materials, and corporate-related documents in simplified Chinese mainly\nAssist in daily company secretarial duties and legal documents\nEnsure relevant statutory and regulatory matters of the Group, as well as issues of corporate governance\nDocument translation when needed\nUpdate and maintain a filing system\nAble to meet a tight deadline, flexible personality, and hardworking\nTo perform ad hoc projects as required\n\n\u00a0Requirements:\n\nDegree holder in Finance, Law, Business, Company secretarial, Journalism, Language, Translation or other related disciplines\n1 - 2 year\u2019s working experience preferred\nExperience in simplified Chinese writing and translation is preferred;\nFamiliar with the requirements of the Company Ordinance, and equivalent laws/ regulations in offshore jurisdictions are preferred\nSelf-motivated, detail-oriented, strong sense of responsibility and able to work under pressure\nGood communication and interpersonal skills\nGood command of written and spoken English and Chinese, fluency in Putonghua\nProficient in computer skills, e.g. Excel, MS Word, PowerPoint, Chinese Word Processing\nStrong sense of responsibility, Independent, initiative & excellent communication skill\n\n\u00a0Attractive remuneration will be offered to the right candidate.\u00a0 Interested parties please email your full resume with present & expected salary and date of availability to hrm @guosen.com.hk or via \"Apply Now\".\n\n\nPersonal data collected would be used for recruitment purpose only.", "employment_types": ["Full Time", "Permanent"], "selling_points": ["Local Conglomerate", "Listed Company", "HKCGI/HKICS Membership"], "locations": ["Not Specified"], "categories": ["Professional Services", "Company Secretary", "Legal & Compliance"], "post_time": "2022-01-13T01:46:48Z", "salary": {"currency": null, "max": null, "min": null, "period": "monthly", "term": null}, "salary_visible": false, "title_keywords": ["company secretary", "officer"], "responsibilities": ["reporting", "related documents", "prepare meeting minutes", "maintain", "ad hoc projects", "administration"], "requirements": {"degrees": ["degree holder"], "majors": ["law", "finance", "journalism", "related disciplines", "business"], "languages": ["putonghua", "english", "chinese"], "language_level": ["fluency", "good command"], "hard_skills": ["excel", "chinese word processing", "powerpoint", "computer skills", "translation", "ms word"], "soft_skills": ["self-motivated", "independent", "sense of responsibility", "communication skill", "detail-oriented", "communication and interpersonal skills", "initiative", "work under pressure"], "languages_combined": [{"language": "putonghua", "language_level": ["fluency", "good command"]}, {"language": "english", "language_level": ["fluency", "good command"]}, {"language": "chinese", "language_level": ["fluency", "good command"]}]}, "experience_required": {"duration": ["1 - 2 year"], "field": ["writing"]}}, {"job_id": "100003009049150", "location_code": "hk", "company": "Hong Kong Interbank Clearing Ltd", "job_title": "Manager (Legal & Compliance)", "description": "Assistant Manager - Company Secretariat\n\nOur client is a well-established and reputable property developer listed in Hong Kong. We are assisting them looking for a talented individual to take up the Assistant Manager, Company Secretariat.\n\nSalary: HK$ 40,000 - 55,000x 12 month + bonus\n\nJob Summary:\n\nProviding company secretarial services for Board and company\nFamilir with Hong Kong Listing Rules and Securities and Futures Ordinance\n\nJob Duties:\n\nResponsible for full spectrum of company secretarial duties, corporate governance and compliance functions for listed company and private subsidiaries\nDraft and prepare annual and interim reports, announcements and circulars\nOrganize meetings for the board, committees and shareholders, and prepare relevant board papers, minutes and resolutions\nMaintain and update statutory records and filings in compliance with the Code on Real Estate Investment Trusts, Securities and Futures Ordinance, Listing Rules, applicable laws and regulations and implement compliance procedures as required\nLiaise with professional advisors and various regulatory bodies\nParticipate in ad hoc projects and tasks assigned from time to time\n\nRequirements:\n\nDegree holder in Corporate Administration or relevant disciplines\nQualified Member of HKCGI/CGI\nAt least 8 to 10 years of company secretarial experience gained in listed company, large-scale corporations or professional firms\nSolid experience in Hong Kong Listing Rules, Securities and Futures Ordinance and Hong Kong Companies\nExperience in handling compliance matters with the Securities and Futures Commission is an advantage\nExcellent command of written and spoken English and Chinese\nProven track record of minute taking and stakeholder management.\nCandidates with more experience will be considered as Manager\n\nInterested individuals should \"Apply Now\", due to an influx of applicants, we regret to inform you that ONLY suitable candidates will be contacted.\n\nFor a more comprehensive list of our vacancies, please visit: www.connectedgroup.com", "employment_types": ["Full Time", "Permanent"], "selling_points": [], "locations": ["Ngau Tau Kok"], "categories": ["Banking / Finance", "Financial Services", "Professional Services", "Company Secretary", "Legal & Compliance"], "post_time": "2022-01-14T08:11:01Z", "salary": {"currency": null, "max": null, "min": null, "period": null, "term": null}, "salary_visible": false, "title_keywords": ["manager"], "responsibilities": ["regulations", "compliance", "procedures", "maintain", "reports", "ad hoc projects", "liaise with", "listing"], "requirements": {"degrees": ["degree holder"], "majors": [], "languages": ["english", "chinese"], "language_level": ["excellent"], "hard_skills": ["inform", "securities and futures ordinance"], "soft_skills": ["comprehensive"], "languages_combined": [{"language": "english", "language_level": ["excellent"]}, {"language": "chinese", "language_level": ["excellent"]}]}, "experience_required": {"duration": ["at least 8 to 10 years"], "field": ["secretarial", "compliance", "securities"]}}, {"job_id": "100003009046500", "location_code": "hk", "company": "Hays", "job_title": "Company Secretary, Insurance, Immediately available", "description": "Our client is currently looking for a company secretary who is familiar with the Companies Ordinance and Hong Kong Listing Rules to join their growing business.\n\nClient Details\n\nOur client is a well-established listed company based in Hong Kong, they have strong track record across multiple business sectors, including the media industry.\n\nDescription\n\nThe company secretary is responsible for:\n\nProviding full spectrum of company secretarial support to the listed company and its subsidiaries\nDrafting and reviewing annual & interim reports, circulars and other documents\nArranging internal meetings and liaising with external parties\nMaintaining statutory filings & records and ensure all information are up-to-date\nHandling any ad-hoc projects\n\nProfile\n\nThe successful candidate must have at least 3 years of relevant company secretarial experience (listed company) with good command of English and Chinese. Member of HKCGI/HKICS is highly preferred.\n\nJob Offer\n\nAttractive remuneration package will be offered to the chosen candidate.", "employment_types": ["Full Time", "Permanent"], "selling_points": ["Instantly recognisable brand", "Fast-growing business", "Broad exposure"], "locations": ["Not Specified"], "categories": ["Professional Services", "Company Secretary", "Legal & Compliance"], "post_time": "2022-01-13T12:16:53Z", "salary": {"currency": null, "max": null, "min": null, "period": "monthly", "term": null}, "salary_visible": false, "title_keywords": ["company secretary"], "responsibilities": ["maintaining", "external parties", "liaising with", "reports", "secretarial support", "ad-hoc projects", "listing"], "requirements": {"degrees": [], "majors": [], "languages": ["english", "chinese"], "language_level": ["good command"], "hard_skills": ["companies ordinance"], "soft_skills": ["responsible"], "languages_combined": [{"language": "english", "language_level": ["good command"]}, {"language": "chinese", "language_level": ["good command"]}]}, "experience_required": {"duration": ["at least 3 years"], "field": ["secretarial"]}}, {"job_id": "100003009048000", "location_code": "hk", "company": "Fiducia Limited", "job_title": "Corporate Services Assistant (MNC)", "description": "Major Responsibilities\n\nHandle relevant legal and compliance matters of the company, including drafting and review of documents, participating in project-related meetings, etc.\nSupport compliance work for new projects/services which are designated under Payment Systems and Stored Value Facilities Ordinance (PSSVFO)\nSupport legal and compliance aspects of local and cross-border technological/FinTech initiatives\nConduct compliance self-assessment to meet oversight requirement of HKMA\nPerform research on regulatory updates and relevant compliance issues\nPerform other duties as assigned by supervisor(s)\nRequirements\n\nUniversity degree holder in Laws (LLB) or equivalent\nMinimum 5 years of relevant post-qualification experience, preferably gained from banking or financial sector\nWell versed in the ordinances related to the banking/financial/information technology industry and good knowledge of compliance rules, regulatory requirements, procedures and guidelines\nGood drafting skill in English and Chinese\nExcellent command of spoken and written English and Chinese, proficiency in Putonghua will be an advantage\nStrong interpersonal, supervisory and analytical skills; self-motivated and independent\nHow to Apply\nInterested parties please send your curriculum vitae stating your current and expected salaries, and the contact phone number to the Human Resources Division, Unit B, 25/F, MG Tower, 133 Hoi Bun Road, Kwun Tong, Kowloon\u00a0\u00a0by clicking the \"Apply Now\" button below.\nAll applications and personal information collected will be treated in strict confidence and only be used for the purpose of recruitment and selection.\u00a0 The information collected will be accessed by our authorized personnel only.\u00a0 Those applicants not contacted by the Human Resources Division within two months from their application date should consider their applications filed for future reference which will be retained for one year for possible future job matching, and will be destroyed after the expiry of one year.", "employment_types": ["Full Time", "Permanent"], "selling_points": ["Provide company secretarial services to client", "Minimum 1 years related experience", "12+2 Behavioural Goals Bonuses"], "locations": ["Wan Chai"], "categories": ["Admin & HR", "Secretary", "Professional Services", "Company Secretary", "Legal & Compliance"], "post_time": "2022-01-14T04:28:03Z", "salary": {"currency": null, "max": null, "min": null, "period": "monthly", "term": null}, "salary_visible": false, "title_keywords": ["assistant"], "responsibilities": ["perform other duties", "review", "compliance", "systems", "payment"], "requirements": {"degrees": ["university degree"], "majors": ["laws"], "languages": ["putonghua", "english", "chinese"], "language_level": ["advantage", "excellent", "proficiency", "good"], "hard_skills": ["analytical skills"], "soft_skills": ["self-motivated", "independent", "interpersonal", "analytical skills"], "languages_combined": [{"language": "putonghua", "language_level": ["proficiency", "excellent"]}, {"language": "english", "language_level": ["advantage", "proficiency", "excellent", "good"]}, {"language": "chinese", "language_level": ["advantage", "proficiency", "excellent", "good"]}]}, "experience_required": {"duration": ["minimum 5 years"], "field": ["post-qualification", "financial", "banking"]}}, {"job_id": "100003009052941", "location_code": "hk", "company": "JFE Consulting Limited", "job_title": "Legal Secretary - Civil Litigation", "description": "We are looking for a high calibre professional to join our Corporate & Accounting Team in Hong Kong office.\n\nJob Description\n\nProvide full range of Company Secretarial services to client's companies in compliance with corporate governance and statutory requirements\nManage statutory books and records, registers, database, routine filings on behalf of client's companies\nHandle Company Secretarial matters such as drafting corporate documents, filing statutory returns and liaising with various regulatory bodies and professional parties\nAbility to handle company secretarial matters for companies in the PRC advantageous\n\nRequirements\n\nDegree with ICSA / HKICS qualification\nGood writing skills in English and Chinese and good command of spoken Putonghua\nWell versed in Hong Kong Companies Ordinance and familiar with regulations of other common offshore jurisdictions\nMinimum 1 years\u2019 experience in full spectrum of company secretarial experience in a similar service provider\nSound business knowledge and analytical skills and strong interpersonal & communication skills\nAbility to work with ViewPoint\u00a0\nProficiency in MS office applications\nInterested in accepting the challenge of handling companies with different structures & requirements\nStrong leadership, communication and team building skills\u00a0\u00a0\u00a0\u00a0\u00a0\u00a0\u00a0\nMeticulous and attention to detail\nWell organized person, willing to work independently\n\nWhat we offer:\n\nBirthday Leave\nCareer growth opportunities\nFlexible working hours\nMedical insurance\nMembership Fee Sponsorship\nRental Reimbursement Scheme\nTeam-building and CSR activities\nTraining allowance\n\nPlease refer to our Company Website:\u00a0http://www.fiducia-china.com. Please submit your full CV with expected salary, plus availability to us. If you do not hear from us within four weeks, you can assume that your application is unsuccessful.", "employment_types": ["Full Time", "Permanent"], "selling_points": ["Legal Secretary", "Civil Litigation", "5-day work; attractive salary"], "locations": ["Central"], "categories": ["Professional Services", "Company Secretary", "Legal & Compliance", "Translation"], "post_time": "2022-01-17T04:37:47Z", "salary": {"currency": null, "max": null, "min": null, "period": "monthly", "term": null}, "salary_visible": false, "title_keywords": ["legal secretary"], "responsibilities": ["corporate documents", "compliance", "liaising with", "statutory requirements", "database"], "requirements": {"degrees": ["degree"], "majors": [], "languages": ["putonghua", "english", "chinese"], "language_level": ["good command", "good"], "hard_skills": ["companies ordinance", "ms office", "writing skills", "analytical skills"], "soft_skills": ["communication skills", "meticulous", "work independently", "interested in", "well organized", "writing skills", "analytical skills", "communication", "attention to detail", "leadership", "interpersonal"], "languages_combined": [{"language": "putonghua", "language_level": ["good command"]}, {"language": "english", "language_level": ["good", "good command"]}, {"language": "chinese", "language_level": ["good", "good command"]}]}, "experience_required": {"duration": ["minimum 1 years"], "field": ["secretarial"]}}, {"job_id": "100003009041809", "location_code": "hk", "company": "", "job_title": "Company Secretary and Administration Manager", "description": "Job Descriptions:\n\nTo ensure the Group complies with the Hong Kong Listing Rules, Securities and Futures Ordinance, and other laws and regulations applicable to listed companies\nIn charge of and handle full set of company secretarial duties, corporate governance and compliance functions of the Group, and HR and administrative functions of the Hong Kong headquarter\nProvide support and advice to the board of directors and committee on corporate governance, compliance and regulatory matters\nCoordinate with Company's subsidiaries and associate to ensure that proper corporate records, filings with relevant company laws/regulations complied with\nLiaise with professional advisors and various governmental/regulatory authorities regarding company secretarial and compliance matters\nResponsible for preparing corporate documentation to shareholders including interim/annual report, circular and announcements\nArrange and organize\u00a0board of directors, committees and shareholders' meetings as well as prepare papers and minutes/resolutions\nKeep abreast of the\u00a0market and regulatory updates, and ensure the management are aware of those changes\nPerform and support ad hoc duties or assignments relating to corporate governance, legal and regulatory, M&A matters as required\n\nRequirements:\n\nDegree-holder, preferably in business administration, corporate governance or related disciplines\nMember of HKICS / ICSA\n10+ years company secretarial work experiences preferably in a listed company on the Main Board of Hong Kong Stock Exchange\u00a0or in professional firms\nGood knowledge in Hong Kong Listing Rules and practices, and Securities & Futures Ordinance, Hong Kong New Companies\u00a0and other statutory compliance requirements in BVI, Bermuda, PRC and other jurisdictions\nGood command of written and spoken English and Chinese, including Mandarin\nAble to work independently, strong analytical, interpersonal and communication skills\nMature, detail-oriented, well-organized and strong sense of responsibility\nProficiency in MS Word, Excel and PowerPoint and with experience in using Hong Kong Stock Exchange electronic submission system\nInterested candidates, please contact us at 92990984 for company details before applying.", "employment_types": ["Full Time"], "selling_points": [], "locations": ["Wan Chai"], "categories": ["Admin & HR", "Administration / Operation Manager", "Secretary", "Professional Services", "Company Secretary"], "post_time": "2022-01-12T04:56:56Z", "salary": {"currency": null, "max": null, "min": null, "period": "monthly", "term": null}, "salary_visible": false, "title_keywords": ["company secretary", "administration manager"], "responsibilities": ["regulations", "ad hoc duties", "provide support", "documentation", "management", "hr", "compliance", "coordinate with", "liaise with", "listing", "report"], "requirements": {"degrees": ["degree"], "majors": ["related disciplines", "business administration"], "languages": ["english", "chinese", "mandarin"], "language_level": ["good command"], "hard_skills": ["ms word", "excel", "powerpoint", "exchange"], "soft_skills": ["communication skills", "work independently", "sense of responsibility", "well-organized", "mature", "detail-oriented", "interpersonal"], "languages_combined": [{"language": "english", "language_level": ["good command"]}, {"language": "chinese", "language_level": ["good command"]}, {"language": "mandarin", "language_level": ["good command"]}]}, "experience_required": {"duration": ["10+ years"], "field": ["secretarial"]}}, {"job_id": "100003009041581", "location_code": "hk", "company": "Tricor Services Limited", "job_title": "Company Secretarial Manager/ Assistant Manager", "description": "Major Responsibilities\n\nProviding high standards of secretariat services for the senior executive office, the HKICL Board and its Sub-Committees\nAssisting in organizing and coordinating Board and Committee meetings involving the senior executive office\nDrafting, reviewing and coordinating different types of business documents, including meeting agendas, papers, minutes, reports, proposals, presentations and letters, etc.\nAssisting in following up to matters raised at meetings to ensure appropriate follow-up actions are taken\nAssisting in managing protocols between the Board and the senior executive office\nCoordinating committee work and liaising with both internal and external parties in a professional manner\nCoordinating with departmental secretariat regarding secretarial issues\nMaintaining an organized and effective document management system for confidential files and records\n\nRequirements\n\nUniversity education in finance, business management or related disciplines\nAt least 5 years\u2019 working experience in committee work, preferably in the banking, finance, public or government sector\nExcellent writing skills in both English and Chinese\nGood command of spoken English and Chinese (Cantonese and Putonghua)\nCapable of dealing with internal and external business executives and officials\nResponsible, independent, well-organized and self-motivated with strong communication and interpersonal skills\nHow to Apply\nInterested parties please send your curriculum vitae stating your current and expected salaries, and the contact phone number to the Human Resources Division, Unit B, 25/F, MG Tower, 133 Hoi Bun Road, Kwun Tong, Kowloon\u00a0\u00a0by clicking the \"Apply Now\" button below.\nAll applications and personal information collected will be treated in strict confidence and only be used for the purpose of recruitment and selection.\u00a0 The information collected will be accessed by our authorized personnel only.\u00a0 Those applicants not contacted by the Human Resources Division within two months from their application date should consider their applications filed for future reference which will be retained for one year for possible future job matching, and will be destroyed after the expiry of one year.", "employment_types": ["Full Time", "Permanent"], "selling_points": ["At least 5 years\u2019 work experience", "Excellent command of spoken and written English", "5-day work, 20-day AL, life & medical insurance"], "locations": ["Ngau Tau Kok"], "categories": ["Banking / Finance", "Others", "Professional Services", "Company Secretary", "Legal & Compliance"], "post_time": "2022-01-12T04:03:52Z", "salary": {"currency": null, "max": null, "min": null, "period": "monthly", "term": null}, "salary_visible": false, "title_keywords": ["assistant manager", "company secretarial manager"], "responsibilities": ["management", "maintaining", "internal and external parties", "letters", "liaising with", "presentations", "professional manner", "reports", "committee work"], "requirements": {"degrees": [], "majors": [], "languages": ["cantonese", "putonghua", "english", "chinese"], "language_level": ["excellent", "good command"], "hard_skills": ["business management", "writing skills"], "soft_skills": ["self-motivated", "independent", "capable", "responsible", "well-organized", "writing skills", "communication and interpersonal skills"], "languages_combined": [{"language": "cantonese", "language_level": ["good command"]}, {"language": "putonghua", "language_level": ["good command"]}, {"language": "english", "language_level": ["excellent", "good command"]}, {"language": "chinese", "language_level": ["excellent", "good command"]}]}, "experience_required": {"duration": ["at least 5 years"], "field": ["finance", "banking"]}}, {"job_id": "100003009049823", "location_code": "hk", "company": "Beijing Tong Ren Tang Chinese Medicine Company Limited", "job_title": "\u5408\u898f\u5c08\u54e1 Compliance Assistant", "description": "Key Responsibilities:\n\nHandle company secretarial or administrative works for our clients\nPrepare documents for bank accounts opening / maintenance of bank accounts of HK private and offshore companies\nPrepare various minutes and statutory returns for HK private and Offshore companies\nPrepare documents for incorporation of HK private and offshore companies\nFiling minute book records\nArrange for documents required for acceptance of new clients\nHandle invoices and follow up payment\nHandle any ad hoc duties as assigned\nKey Requirements:\n\nDegree holder or above\nQualified company secretary with membership of HKICS/ ICSA is a MUST\nAt least 4 years of experience in company secretarial practice, preferably obtained from a CPA firm, professional firm or law firm\nResponsible, detail-minded and willing to learn\nAble to work in a fast-paced environment\nIndependent correspondence\nPolite with good customer servicing skills\nA team player with good communication skills\nCandidate with less experience will consider as Associate\u00a0\nProspective candidates please apply below stating your current & expected salary", "employment_types": ["Full Time"], "selling_points": [], "locations": ["Wan Chai"], "categories": ["Professional Services", "Company Secretary", "Legal & Compliance", "Banking / Finance", "Risk Management"], "post_time": "2022-01-14T09:17:10Z", "salary": {"currency": null, "max": null, "min": null, "period": "monthly", "term": null}, "salary_visible": false, "title_keywords": ["compliance assistant"], "responsibilities": ["ad hoc duties", "invoices", "maintenance", "payment", "prepare documents"], "requirements": {"degrees": ["degree holder"], "majors": [], "languages": [], "language_level": [], "hard_skills": ["cpa"], "soft_skills": ["detail-minded", "communication skills", "independent", "polite", "responsible", "fast-paced environment", "willing to learn", "team player"], "languages_combined": []}, "experience_required": {"duration": ["at least 4 years"], "field": ["secretarial", "cpa firm"]}}, {"job_id": "100003009049113", "location_code": "hk", "company": "Hong Kong Interbank Clearing Ltd", "job_title": "Assistant Management Executive", "description": "Responsibilities:\n\nTo handle trademark and patent application, renewal, and other related matters\nTo manage IP portfolio for client\nTo communicate with clients and foreign agents\nTo maintain up-to-date records\nTo provide legal support to supervisor\n\n\u00a0Requirements:\n\nHigher Diploma holder in Law\n3 years\u2019 or above working experience in legal field (preferably in intellectual property aspect)\nStrong communication skills with good commercial sense and team-work spirit\nResponsible, self-motivated, detail-oriented and well-organized\nProficient in MS Office including Word, Excel and Chinese WP\nGood command of written and spoken English, Cantonese and Mandarin\nImmediate available is highly preferred\n\n\n\nInterested parties please state your employment history, present and expected salary on your resume.\n\nWe are an equal opportunity employer and welcome applications from all qualified candidates. All personal information provided will be treated in strict confidence and used solely for recruitment purpose. It is possible that information about the applicant or the applicant\u2019s application will be shared within the Conpak Group.\n\nApplicants not hearing from us within 6 weeks from the date of advertisement may consider applications unsuccessful. Personal data of an unsuccessful applicant will normally be kept for a period of 2 years.", "employment_types": ["Full Time", "Permanent"], "selling_points": [], "locations": ["Ngau Tau Kok"], "categories": ["Admin & HR", "Secretary", "Banking / Finance", "Financial Services", "Professional Services", "Company Secretary"], "post_time": "2022-01-14T08:08:15Z", "salary": {"currency": null, "max": null, "min": null, "period": null, "term": null}, "salary_visible": false, "title_keywords": ["assistant management executive"], "responsibilities": ["communicate with", "maintain"], "requirements": {"degrees": ["higher diploma holder"], "majors": ["law"], "languages": ["cantonese", "english", "chinese", "mandarin"], "language_level": ["good command", "proficient"], "hard_skills": ["excel", "chinese wp", "word", "ms office"], "soft_skills": ["communication skills", "self-motivated", "responsible", "well-organized", "detail-oriented"], "languages_combined": [{"language": "cantonese", "language_level": ["good command"]}, {"language": "english", "language_level": ["good command"]}, {"language": "chinese", "language_level": ["proficient"]}, {"language": "mandarin", "language_level": ["good command"]}]}, "experience_required": {"duration": ["3 years"], "field": ["legal"]}}, {"job_id": "100003009039363", "location_code": "hk", "company": "Liansu Group Company Limited", "job_title": "Company Secretary \u2013 Assistant Manager/ Senior Officer", "description": "\u00a0\u5de5\u4f5c\u6642\u9593 : Mon-Sun 10:00a.m. - 9:00p.m.\n\n\u8077\u8cac\uff1a\n\n\u4ee5\u9867\u5ba2\u7232\u4e2d\u5fc3,\u00a0\u63d0\u4f9b\u6700\u4f73\u9867\u5ba2\u9ad4\u9a57\uff0c\u89e3\u7b54\u5ba2\u6236\u554f\u984c\uff0c\u5354\u52a9\u5e97\u8216\u65e5\u5e38\u71df\u904b\u5de5\u4f5c\n\n\u6b61\u8fce\u61c9\u5c46\u7562\u696d\u751f\n\n\u6d41\u5229\u5ee3\u6771\u8a71\uff0c\u57fa\u672c\u666e\u901a\u8a71\u53ca\u82f1\u8a9e\n\n\u6709\u610f\u52a0\u5165\u6211\u5011\uff0c\u8acb\u900f\u904e Apply Now \u905e\u4ea4\u5c65\u6b77\u8868/ \u53efWhatsApp 9171 6932 \u7533\u8acb", "employment_types": ["Full Time"], "selling_points": [], "locations": ["Tsim Sha Tsui"], "categories": ["Professional Services", "Company Secretary"], "post_time": "2022-01-11T16:01:50Z", "salary": {"currency": null, "max": null, "min": null, "period": "monthly", "term": null}, "salary_visible": false, "title_keywords": ["company secretary", "assistant manager", "senior officer"], "responsibilities": [], "requirements": {"degrees": [], "majors": [], "languages": [], "language_level": [], "hard_skills": [], "soft_skills": [], "languages_combined": []}, "experience_required": {"duration": [], "field": []}}, {"job_id": "100003009038590", "location_code": "hk", "company": "Avo Insurance Company Limited", "job_title": "Company Secretary", "description": "Date: Late March\n\nTime: 0730-2300 (8 hours per shift)\nSalary: Negotiable\n\n\nDuties:\n\n-Lead and manage the work of Support Staff; Produce list of confines regularly;\n\n-Liaise with and handle request and enquiries from different parties,etc.\nRequirement:\n-Bachelor\u2019s degree holder from a university in Hong Kong or equivalent;\n-Have 1-2 years data preparation aggregate experience\n-Good command of written and spoken English, Chinese & Mandarin\n\n\n**Apply with your Resume, all Job & Education certificates", "employment_types": ["Full Time", "Permanent"], "selling_points": [], "locations": ["Sai Ying Pun"], "categories": ["Professional Services", "Company Secretary"], "post_time": "2022-01-11T07:28:39Z", "salary": {"currency": null, "max": null, "min": null, "period": "monthly", "term": null}, "salary_visible": false, "title_keywords": ["company secretary"], "responsibilities": [], "requirements": {"degrees": ["degree holder"], "majors": [], "languages": ["english", "chinese", "mandarin"], "language_level": [], "hard_skills": [], "soft_skills": [], "languages_combined": [{"language": "english", "language_level": []}, {"language": "chinese", "language_level": []}, {"language": "mandarin", "language_level": []}]}, "experience_required": {"duration": ["1-2 years"], "field": []}}, {"job_id": "100003009036490", "location_code": "hk", "company": "Chesterton Consulting Co Limited", "job_title": "Company Secretary", "description": "Our Client is a HK listed company with rapid expansion plan.\u00a0 A need has arisen to hire a Chartered Company Secretary with the following responsibilities.\u00a0 This is an exciting opportunity with extensive overseas exposure.\u00a0\u00a0\n\nTo ensure operations in accordance with rules and regulations\nTo ensure the board functions efficiently and effectively\nTo facilitate good communication between the board, committees, senior management and non-executive directors, and shareholders\nTo take responsibility for the administration of the company, for example: maintaining statutory books, including registers of members, directors, and secretaries, and shareholders with all their past and present shareholdings, organising board meetings and annual general meetings (AGMs), preparing agendas and taking minutes\nTo file necessary documents with Companies House, such as annual tax returns and audit reports\nTo inform Companies House of any significant changes to the company\u2019s share capital, administration or registered address\nTo monitor changes in relevant legislation and the regulatory environment and take appropriate action\nTo liaise with external regulators and advisers, such as lawyers and auditors\nTo develop and oversee the systems that ensure the company complies with all applicable codes, in addition to its legal and statutory requirements\nTo qualify, you should be a Chartered Company Secretarial holder with around 20 years of relevant experience gained from large corporations.\u00a0 A mature mindset with the ability to work with different stakeholders including the Board.\u00a0 Excellent communication skills are expected with full fluency in English and Chinese.", "employment_types": ["Full Time", "Permanent"], "selling_points": ["Chartered Company Secretary", "HK Listed Company with Overseas Exposure", "Excellent Career Opportunity"], "locations": ["Others"], "categories": ["Accounting", "Others", "Professional Services", "Company Secretary", "Legal & Compliance"], "post_time": "2022-01-10T10:41:40Z", "salary": {"currency": null, "max": null, "min": null, "period": "monthly", "term": null}, "salary_visible": false, "title_keywords": ["company secretary"], "responsibilities": ["regulations", "tax", "maintaining", "operations", "systems", "monitor", "audit", "relevant legislation", "communication", "develop", "statutory requirements", "reports", "plan", "liaise with", "senior management", "administration"], "requirements": {"degrees": [], "majors": [], "languages": ["english", "chinese"], "language_level": ["fluency", "excellent"], "hard_skills": ["codes", "inform", "rapid"], "soft_skills": ["communication", "communication skills", "extensive", "mature"], "languages_combined": [{"language": "english", "language_level": ["fluency", "excellent"]}, {"language": "chinese", "language_level": ["fluency", "excellent"]}]}, "experience_required": {"duration": ["20 years"], "field": ["secretarial", "relevant experience"]}}, {"job_id": "100003009040196", "location_code": "hk", "company": "KOS International Limited", "job_title": "Senior Company Secretary - Financial services", "description": "About Our Client\n\nOur client is a financial service firm, they are currently in a growth phase as an organization and thus, an excellent opportunity has arisen for a high-calibre professional to join the company and potentially to lead the team.\n\nAbout The Role\n\nEnsure the firm is complied with Corporate Governance, relevant statutory and regulatory requirements\nEnsure full compliance with the statutory requirements, liaise with relevant authorities, including but not limited to HKEX, HKMA and SFC, prepare and submit any required documents, including announcements and circulars\nMaintain the accuracy of statutory documents to be filed with Companies Registry and other relevant regulatory and statutory authorities before deadline\nOrganize meetings of the Board of Directors and general meetings\nProvide professional advice to various business units of the Group\nHandle ad-hoc company secretarial duties as assigned from time to time\n\nRequirements\n\nDegree holder in relevant discipline with HKICS/ICSA qualification\nMin 8-10 years of experience as company secretary, preferably in Chinese financial industry\nAt least 2 years of experience after obtaining the relevant qualification\nExperience in organizing board meetings in listed companies\nWell-versed in Hong Kong listing rules and requirements, Companies Ordinance and other compliance regulations\nGood command in both written and spoken English and Chinese, including Mandarin\n\nClick \"Apply Now\" to apply for this position or call Jessie Chan at +852 3180 4945 for a confidential discussion. All information collected will be kept in strict confidence and will be used for recruitment purpose only.", "employment_types": ["Full Time", "Permanent"], "selling_points": ["managerial exposure", "prefer candidates from banking industry", "good command in English and Chinese"], "locations": ["Not Specified"], "categories": ["Banking / Finance", "Financial Services", "Professional Services", "Company Secretary"], "post_time": "2022-01-12T01:49:36Z", "salary": {"currency": null, "max": null, "min": null, "period": "monthly", "term": null}, "salary_visible": false, "title_keywords": ["senior company secretary"], "responsibilities": ["ad-hoc", "regulations", "regulatory requirements", "compliance", "statutory requirements", "maintain", "recruitment", "liaise with", "listing"], "requirements": {"degrees": ["degree holder"], "majors": [], "languages": ["english", "chinese", "mandarin"], "language_level": ["good command"], "hard_skills": ["hkma", "companies ordinance"], "soft_skills": ["confidence"], "languages_combined": [{"language": "english", "language_level": ["good command"]}, {"language": "chinese", "language_level": ["good command"]}, {"language": "mandarin", "language_level": ["good command"]}]}, "experience_required": {"duration": ["at least 2 years", "min 8-10 years"], "field": ["financial industry"]}}, {"job_id": "100003009044000", "location_code": "hk", "company": "Knight Recruitment Services Limited", "job_title": "Intellectual Property Senior Officer/Assistant Manager;HK$30K-$38Kx13m;5 Day; Sheung Wan", "description": "Intellectual Property Senior Officer/Assistant Manager;HK$30K-$38Kx13m;5 Day; Sheung Wan\n\nOur client is a large Conglomerate who is seeking a high caliber person to fill the\u00a0Intellectual Property Senior Officer/Assistant Manager position:\n\nJob Duties:\n\nHandle trademark and patent application, renewal, and other related matters\nConduct trademark pre-filing searches and assist in preparing advice on IP matters and strategies\nAssist in formulating, developing and refining IP related policies and SOPs\nLiaise with relevant stakeholders and external agents\nSupport in the delivery of IP-related education and updates\nSupport in handling files management and bills management on IP matters, update and maintain IP databases\n\nRequirements:\n\nDegree Holder in relevant discipline\u00a0\n5 years relevant experience in handling IP applications\u00a0\nGood command of spoken and written English and Chinese (Cantonese & Mandarin)\nFamiliar with MS Outlook, Excel, PowerPoint and Chinese Word Processing\nAbility to handle work under tight deadlines, working independently and with high attention to detail\nExcellent interpersonal, coordination and organization skills\nCheerful, strong sense of responsibility, team player and well organized\n\nFor more information, please send your resume complete with cover letter to yuki.wan@ knightrecruits.com\u00a0\n\nData collected will be used for recruitment purposes only. Personal data provided by job applicants will be used strictly in accordance with the Personal Data (Privacy) Ordinance. We regret that only the shortlisted candidates will be notified.", "employment_types": ["Full Time", "Permanent"], "selling_points": ["Large Conglomerate Group", "HK$30K-$38Kx13m;5 Day; Sheung Wan", "trade mark / patent experience"], "locations": ["Central"], "categories": ["Admin & HR", "Secretary", "Professional Services", "Company Secretary", "Legal & Compliance"], "post_time": "2022-01-13T02:45:03Z", "salary": {"currency": null, "max": null, "min": null, "period": "monthly", "term": null}, "salary_visible": false, "title_keywords": ["senior officer", "assistant"], "responsibilities": ["management", "policies", "developing", "maintain", "sops", "databases", "liaise with"], "requirements": {"degrees": ["degree holder"], "majors": [], "languages": ["cantonese", "english", "chinese", "mandarin"], "language_level": ["good command"], "hard_skills": ["excel", "chinese word processing", "powerpoint", "ip", "outlook"], "soft_skills": ["independently", "cheerful", "sense of responsibility", "well organized", "coordination", "attention to detail", "organization skills", "team player", "interpersonal"], "languages_combined": [{"language": "cantonese", "language_level": ["good command"]}, {"language": "english", "language_level": ["good command"]}, {"language": "chinese", "language_level": ["good command"]}, {"language": "mandarin", "language_level": ["good command"]}]}, "experience_required": {"duration": ["5 years"], "field": ["relevant experience"]}}, {"job_id": "100003009039920", "location_code": "hk", "company": "Henderson CPA Limited", "job_title": "Company Secretary (Fresh Graduates welcome)", "description": "Requirements:\u00a0\n\nDegree/Diploma holder,\nGood PC skills in Word, Excel, Chinese Word Processing\nGood command of written Chinese and English, fluent in Cantonese.\nPerform ad hoc duties assigned from time to time\nFresh graduates will also be considered.\n\nInterested parties, please send resume with expected salary by clicking \"Apply Now\".\n\nAll applications received will be used strictly for selection purposes only.", "employment_types": ["Full Time"], "selling_points": [], "locations": ["Sheung Wan"], "categories": ["Professional Services", "Company Secretary"], "post_time": "2022-01-11T15:25:47Z", "salary": {"currency": null, "max": null, "min": null, "period": "monthly", "term": null}, "salary_visible": false, "title_keywords": ["company secretary"], "responsibilities": ["ad hoc duties"], "requirements": {"degrees": ["diploma holder", "degree"], "majors": [], "languages": ["cantonese", "english", "chinese"], "language_level": ["fluent", "good command", "good"], "hard_skills": ["excel", "pc skills", "chinese word processing", "word"], "soft_skills": [], "languages_combined": [{"language": "cantonese", "language_level": ["fluent", "good command", "good"]}, {"language": "english", "language_level": ["good command", "good"]}, {"language": "chinese", "language_level": ["fluent", "good command", "good", "good"]}]}, "experience_required": {"duration": [], "field": []}}, {"job_id": "100003009035374", "location_code": "hk", "company": "PressLogic Limited", "job_title": "Executive Assistant to CEO", "description": "Responsibilities:\n\nPerform general company secretarial duties;\nProvide administrative support to CEO as personal assistant;\nManage business correspondence, minutes, meeting agenda, mails, emails, telephone calls, document filling and other administrative duties;\nHandle full set of company statutory records including but not limited to preparing minutes, statutory returns and filings;\nLiaise with internal and external parties on business issues independently;\nProactively take part in marketing roles which includes but not limited to marketing activities;\nDraft English and Chinese correspondences, emails, memo, presentations and reports;\nRequire to perform outdoor activities and communicate with different parties for project reviews and tracking reports;\nManage sensitive and confidential information with discretion and diplomacy\nOrganize and coordinate various projects, events and/or activities; and\u00a0\nAssist in various operations and/or ad-hoc project as assigned\n\nRequirements:\n\n\nUniversity degree with formal secretarial training is preferred\n3-5 years\u2019 solid experience in serving C-level or top management\nCandidate with experience working in Technology, Professional Services or Marketing a plus\nMature, responsible, trustworthy\nDetailed oriented, organized, calm, productive and adaptive\nSelf-motivated and loyal, with strong sense of commitment\nAble to work in a fast-paced and flexible environment\nAbility to manage sensitive and confidential information with discretion and diplomacy is a must\nExcellent interpersonal and communication skills as well as active listening skill\nProficiency in MS Office and Chinese Word Processing\nExcellent spoken and written English, Cantonese and Mandarin\n\nWe Offer:\n\n5 Days work\nFlexible Working Hour\nBirthday Leave & Anniversary Leave\nMedical Coverage\nFun, young and joyful office environment\u00a0\n\nInterested candidates, please email full resume with 1.) EXPECTED SALARY 2.) AVAILABILITY 3.) WORK REFERENCE\u00a0 to the HR department by clicking 'Apply Now'.\n\nFor company information, please refer to the website http://www.presslogic.com/.\n\nAll information received will be kept in strict confidence and only for employment-related purposes.", "employment_types": ["Full Time", "Permanent"], "selling_points": ["Full Spectrum of Secretarial Service to CEO", "Proactively take part in marketing role", "Assist in various operations and ad-hoc project"], "locations": ["Lai Chi Kok"], "categories": ["Admin & HR", "Personal / Executive Assistant", "Secretary", "Professional Services", "Company Secretary"], "post_time": "2022-01-10T06:57:51Z", "salary": {"currency": null, "max": null, "min": null, "period": "monthly", "term": null}, "salary_visible": false, "title_keywords": ["executive assistant to ceo"], "responsibilities": ["communicate with", "ad-hoc", "memo", "operations", "internal and external parties", "presentations", "coordinate", "liaise with", "administrative duties", "reports", "provide administrative support", "tracking"], "requirements": {"degrees": ["university degree"], "majors": [], "languages": ["cantonese", "english", "chinese", "mandarin"], "language_level": ["proficiency", "excellent"], "hard_skills": ["plus", "c", "chinese word processing", "ms office"], "soft_skills": ["productive", "organized", "self-motivated", "flexible", "detailed oriented", "communication skills", "trustworthy", "responsible", "mature", "calm", "loyal", "active", "interpersonal", "sensitive"], "languages_combined": [{"language": "cantonese", "language_level": ["excellent"]}, {"language": "english", "language_level": ["excellent"]}, {"language": "chinese", "language_level": ["proficiency"]}, {"language": "mandarin", "language_level": ["excellent"]}]}, "experience_required": {"duration": ["3-5 years"], "field": ["management", "marketing"]}}, {"job_id": "100003007859955", "location_code": "hk", "company": "Linkpath CPA Limited", "job_title": "Company Secretarial  Senior / Supervisor", "description": "\u00a0Responsibilities:\n\nHandle full spectrum of company secretarial matters;\nReview and supervise junior company secretary;\nOther ad hoc projects.\n\nRequirements:\n\nDegree or diploma holder in Business Administration/Corporate Governance or a related discipline\nQualified professional member or student member of ICSA/HKICS\n\nKnowledge in Corporate Affair System (\"CAS\") is preferred\n3 years or above hands on and solid company secretary experience\nProficient in MS Office,\u00a0English and Chinese typing\nFluent English, Cantonese and Mandarin\nPositive attitude with excellent interpersonal and communication skills\nStrong sense of responsibility and ability to work independently with minimum supervision\n\nBenefits:\n\n\u00a0\u00a0\u00a0\u00a0\u00a0\u00a0\u00a0\u00a0 5 days work\n\u00a0\u00a0\u00a0\u00a0\u00a0\u00a0\u00a0\u00a0 Excellent career advancement opportunities with attractive remuneration and allowance\n\u00a0\u00a0\u00a0\u00a0\u00a0\u00a0\u00a0\u00a0 Gain valuable experience in providing professional services to clients in various sectors\n\u00a0\u00a0\u00a0\u00a0\u00a0\u00a0\u00a0\u00a0 Annual Leave, Paid Sick Leave, Medical benefits, Exam Leave and Study Leave\n\nSalary will be commensurate with the qualification and working experience of the candidate.\u00a0All information received will be kept in strict confidence and for employment related purpose(s) only.", "employment_types": ["Full Time", "Permanent"], "selling_points": [], "locations": ["Sheung Wan"], "categories": ["Professional Services", "Company Secretary"], "post_time": "2022-01-10T10:54:03Z", "salary": {"currency": null, "max": null, "min": null, "period": "monthly", "term": null}, "salary_visible": false, "title_keywords": ["supervisor"], "responsibilities": ["review", "ad hoc projects"], "requirements": {"degrees": ["diploma holder", "degree"], "majors": ["business administration"], "languages": ["cantonese", "english", "chinese", "mandarin"], "language_level": ["fluent", "proficient"], "hard_skills": ["typing", "ms office"], "soft_skills": ["communication skills", "work independently", "sense of responsibility", "positive attitude", "hands on", "interpersonal"], "languages_combined": [{"language": "cantonese", "language_level": ["fluent"]}, {"language": "english", "language_level": ["fluent", "proficient"]}, {"language": "chinese", "language_level": ["proficient"]}, {"language": "mandarin", "language_level": ["fluent"]}]}, "experience_required": {"duration": ["3 years"], "field": []}}, {"job_id": "100003009043274", "location_code": "hk", "company": "BDO Financial Services Limited", "job_title": "Finance Manager, FP&A (Entertainment Business)", "description": "Our client is a HK based entertainment company and has businesses across Hong Kong, China and overseas.\u00a0 This is a newly created position and they looking for a young and energetic Finance professional to support their FP&A functions.\n\nResponsibilities:\u00a0\n\nTo drive business performance through financial planning and analysis and support decision making of business development, particularly in revenue and cost analysis, working capital and capex control, cash flow analysis, tax and operational efficiency assessment\nProvide highly relevant analytics and insight to business and financial performance, identify areas for improvement, and assist in the development and execution of strategic and operating plans\nBuild collaboration and drive effective communication partnering with operational teams for HK and China business\nOptimize planning or controlling tools and processes to increase efficiency, identify risk and opportunities to drive actions to mitigate\nPerforming other responsibilities and duties per assigned\u00a0\n\nRequirements:\n\nA qualified accountant with a degree in Finance, Accounting, Business Administration or related disciplines are preferable\nAt least 6 - 8 years relevant experience in financial analysis in sizable company and audit training in CPA firm is an advantage\nEntertainment business exposure in HK and PRC is a plus\nProficiency in Excel\nGood interpersonal, communication and presentation skills, with solid business acumen in serving the business unit\nFluent in both English, Cantonese and Mandarin (spoken and written)\nAble to work under pressure, handle multi-task and meet tight deadlines\nSolid analytical & research ability, self-motivated, and attention to details and accuracy\n\nInterested parties please send your application with full career history, current and expected salary by clicking Apply Now button. Applications will be treated in strict confidence. Personal data collected will be used for recruitment purposes only.", "employment_types": ["Full Time"], "selling_points": ["Fully in charge of FP&A", "Collaboration with HK and China Business", "Entertainment Business"], "locations": ["Not Specified"], "categories": ["Accounting", "Financial Analyst", "Banking / Finance", "Corporate Finance", "Professional Services", "Company Secretary"], "post_time": "2022-01-12T10:26:57Z", "salary": {"currency": null, "max": null, "min": null, "period": "monthly", "term": null}, "salary_visible": false, "title_keywords": ["finance manager"], "responsibilities": ["tax", "control", "analysis", "capex", "teams", "communication", "cash flow", "plans", "cost analysis", "planning"], "requirements": {"degrees": ["degree"], "majors": ["related disciplines", "finance", "accounting", "business administration"], "languages": ["cantonese", "english", "mandarin"], "language_level": ["fluent"], "hard_skills": ["excel", "plus", "financial analysis", "cpa", "acumen"], "soft_skills": ["meet tight deadlines", "self-motivated", "multi-task", "communication", "presentation skills", "attention to details", "business acumen", "interpersonal", "work under pressure"], "languages_combined": [{"language": "cantonese", "language_level": ["fluent"]}, {"language": "english", "language_level": ["fluent"]}, {"language": "mandarin", "language_level": ["fluent"]}]}, "experience_required": {"duration": ["at least 6 - 8 years"], "field": ["training", "cpa firm", "audit", "relevant experience", "financial"]}}, {"job_id": "100003009042176", "location_code": "hk", "company": "CR Construction Company Limited", "job_title": "Executive Secretary", "description": "Job Responsibilities:\n\nHandle administrative and secretarial support to the Executives\nAssist with travel arrangement, expense claims support, event planning, coordination and schedule arrangement\nProviding support to the office and personal affairs\nAssist in for ad-hoc work upon requests\n\nJob Requirement:\n\nExcellent command in English, Cantonese, and Mandarin\nAble to work independently and be detail-oriented\nExcellent communication, interpersonal skills\n\nWe offer attractive salary, medical plan and fringe benefits. Interested parties please click \"Apply Now\" or apply via our web site.\n(Data collected would be used for recruitment purpose only)", "employment_types": ["Full Time"], "selling_points": ["Double Pay", "Discretionary Bonus", "Medical Scheme"], "locations": ["Others"], "categories": ["Admin & HR", "Secretary", "Professional Services", "Company Secretary"], "post_time": "2022-01-12T06:27:40Z", "salary": {"currency": null, "max": null, "min": null, "period": "monthly", "term": null}, "salary_visible": false, "title_keywords": ["executive secretary"], "responsibilities": ["ad-hoc", "schedule", "coordination", "secretarial support", "travel arrangement", "providing support", "planning"], "requirements": {"degrees": [], "majors": [], "languages": ["cantonese", "english", "mandarin"], "language_level": ["excellent"], "hard_skills": [], "soft_skills": ["communication", "work independently", "interpersonal skills", "detail-oriented"], "languages_combined": [{"language": "cantonese", "language_level": ["excellent"]}, {"language": "english", "language_level": ["excellent"]}, {"language": "mandarin", "language_level": ["excellent"]}]}, "experience_required": {"duration": [], "field": []}}, {"job_id": "100003009037609", "location_code": "hk", "company": "Maples Fiduciary Services (Hong Kong) Limited", "job_title": "Assistant Corporate Administrator - Offshore Team", "description": "Position: Assistant Corporate Administrator - Offshore Team\nLocation: Hong Kong\n\nThe Maples Group is a standard bearer in financial and legal services, trusted by many of the world\u2019s largest hedge fund managers, private equity firms and international corporations.\n\nOur distinction flows from our carefully curated team: 2,000+ professionals characterised by tenacity, ethics and exacting excellence.\u00a0 We hire smart and sharpen smarter, arming talent with best-in-class resources and skills. \u00a0Operating in key financial centres across the Americas, Asia, Europe and the Middle East, our international presence offers a unique springboard for career development and cross-cultural immersion. \u00a0Our side-by-side financial and legal services are similarly ripe for interdisciplinary learning and growth. \u00a0\n\nThe Maples Group looks to add a Hong Kong-based Assistant Corporate Administrator to our team and invites eager and qualified candidates to apply. \u00a0We are committed to diversity, inclusion and equality of opportunity as we attract, retain and develop world-class talent.\n\nWho We Seek\nOur merit-based culture suits professionals in pursuit of boundless careers and lives.\u00a0 Beyond their acumen, team members are collaborative and conscientious, bringing a healthy sense of drive and purpose to each interaction and to all aspects of their work.\n\nAbout the Role\nThe Assistant Corporate Administrator under the supervision of the Senior Corporate Administrators will be responsible for the administration of a varied portfolio of clients where the Maples Group is providing registered office services to BVI and Cayman companies. Primary responsibilities include: \u00a0\n\nAssist the Senior Corporate Administrators to perform designated registered office services to BVI and Cayman client companies\nMaintain statutory books and records and databases in a systematic and efficient way\nPrepare and attend to statutory forms, resolutions, correspondence and government filings.\nProvide administrative support to the Offshore Team\n\nWhat You Bring\nIn addition to indisputably high ethical standards and autonomy, the ideal candidate possesses the following:\n\nDegree holder in relevant disciplines or fresh graduate in other disciplines\n2 years\u2019 relevant company secretarial experience in handling BVI and Cayman registered office services/ Hong Kong company secretarial matters\nExcellent communication skills as well as both verbal and written English and Chinese\nExcellent organisation and planning skills, be methodical, with strong attention to detail and the ability to deliver on tight timescales\nImmediately available is highly preferred\n\nBenefits & Rewards\nThe most enduring professional relationships are reciprocal relationships. \u00a0The Maples Group prioritises employee health and wellbeing. Depending on your location, we offer a range of benefits, including:\n\nComprehensive health coverage (medical, dental and optical)\nCompetitive vacation packages\nEducational assistance and professional development programmes\nSavings or pension plan\nLife insurance\nTravel insurance\nGlobal mental wellness programme\nSocial events\n\nAbout the Maples Group\n\nOver five decades, the Maples Group has grown from modest beginnings into one of the world's preeminent professional services firms, offering specialised fiduciary, fund administration, regulatory and compliance, entity formation and management and legal services on the laws of the British Virgin Islands, the Cayman Islands, Ireland, Jersey and Luxembourg.\n\nYou can learn more about the Maples Group on our corporate website.\u00a0 Experience our culture and our people on our Careers Page or on LinkedIn.\n\nDisclaimer: All personal information collected during the application process will be used for recruitment-related purposes only. Please refer to our Job Applicant Privacy Notice at maples.com/privacy for details on how we handle personal information relating to job applicants.", "employment_types": ["Full Time", "Permanent"], "selling_points": ["2+ years experience on BVI offshore experience", "company secretary", "Competitive package and excellent environment"], "locations": ["Wan Chai"], "categories": ["Professional Services", "Company Secretary"], "post_time": "2022-01-11T03:17:54Z", "salary": {"currency": null, "max": null, "min": null, "period": "monthly", "term": null}, "salary_visible": false, "title_keywords": ["administrator", "assistant"], "responsibilities": ["develop", "communication", "maintain", "planning", "databases", "career development", "provide administrative support", "administration"], "requirements": {"degrees": ["fresh graduate", "degree holder"], "majors": [], "languages": ["english", "chinese"], "language_level": ["excellent"], "hard_skills": ["private equity", "databases", "acumen"], "soft_skills": ["efficient", "communication skills", "planning skills", "ideal", "responsible", "collaborative", "unique", "systematic", "committed", "learning", "ethical", "organisation", "conscientious", "attention to detail", "methodical", "world-class"], "languages_combined": [{"language": "english", "language_level": ["excellent"]}, {"language": "chinese", "language_level": ["excellent"]}]}, "experience_required": {"duration": ["2 years"], "field": ["secretarial"]}}, {"job_id": "100003009039735", "location_code": "hk", "company": "Deliveroo Hong Kong Limited", "job_title": "Catering Operations Executive", "description": "Why Deliveroo?\n\nWhy Deliveroo? When you first think about Deliveroo, you probably think of getting great food to your house in less than half an hour. Awesome right? But behind the scenes is the real story. This story is one of high growth, huge challenges and an enormous opportunity ahead of us.\n\nWe want to be the definitive food company - the app you go to any time you have a hunger pang. We are transforming the way people think about food. We\u2019re a technology driven company at the forefront of the most rapidly expanding industry in the world, so come and join us for the ride.\n\nWhat you\u2019ll be doing\u2026\n\nAs a Catering Operations Executive, you will be joining a team focused on growing a new and exciting area of business at Deliveroo. In contrast to our core business, the Catering team focuses on servicing large orders for both corporate and individual customers, which require different operational needs and expertise.\n\nYou will...\n\nManage our dedicated trolley walker fleet while assisting with our van operations to service Catering orders and monitor large orders in real time to ensure we deliver an outstanding experience\nAssist in maintaining and expanding our selection of dedicated Catering Menus and work closely with Catering Partners to develop their menu offering and ensure smooth operations\nMake menu or restaurant suggestions to Corporate Account Managers to promote corporate catering orders while targeting other use cases including residential catering, boat parties, and school events\nHandle inbound customer enquiries and proactively come up with creative solutions to accommodate special customer requests or large, complex orders\nLiaise with other departments including Customer Service, Operations, and Restaurant Account Management to help scale our Catering business and proactively tackle issues that may arise\nDevelop an understanding of the challenges around our day-to-day operations and help drive improvements in the existing processes, as well as implement new ones\n\nSkills you\u2019ll need & Eligibility\u2026\n\nAt least 2 years of work experience with experience in a customer-facing role\nAble to take an idea, make a plan and get the job done\nOutstanding interpersonal skills as you will be liaising directly with customer, restaurant partners, and internal stakeholders on a regular basis\nAble to tackle several complex problems without missing a step\nAble to take ownership of problems and turn your solutions into a coherent action plan, while keeping a cool head in challenging situations\nUse the information available to you to build a plan with clear goals\nA good level of spoken and written English and spoken Cantonese\nHigh level of attention to detail\n\nBenefits:\n\nBecome one of the key employees of a fast-growing, exciting startup changing the food delivery landscape\nOpen, respectful and fun company culture\nSnacks and drinks provided (although not unlimited, you will never go thirsty or hungry)\nFriday lunches on us from the best local restaurants\u00a0\nWork with people who LOVE what they do\nMeal allowance if you are required to work late\nFree Deliveroo Plus - Free delivery and access to special offers\n\nLife at Deliveroo\n\nWe are a growing team, with very large impact, seeking to answer some of the most interesting questions out there. We move fast, we\u2019re always looking for new ideas and we\u2019re very transparent about the decisions we make and why we make them.\n\nThere are so many questions we need to answer and plenty more we haven\u2019t even encountered. How do data and technology help restaurants to grow as consumer habits change? How can we predict what someone wants to order for dinner long before the idea has even crossed their mind? At Deliveroo these are just some of the tough problems we are solving - and there is no challenge that cannot be yours. No solution is owned by a particular team, which means the scope for growth and personal impact is enormous.\n\nDiversity and Inclusion\n\nAt Deliveroo we know that people are the heart of the business and we prioritise their welfare. We offer a wide range of competitive benefits in areas including health, family, finance, community, convenience, growth, time away and relocation.\n\nIn 2018 we announced our decision to give every employee equity in the company. We did this because we wanted all of our employees, regardless of location, level or role to be owners and because we believe that this is the right thing to do. We believe this helps build a culture where everyone is committed and able to share in the company\u2019s success.\n\nWe believe a great workplace is one that represents the world we live in and how beautifully diverse it can be. That means we have no judgement when it comes to any one of the things that make you who you are - your gender, race, sexuality, religion or a secret aversion to coriander. All you need is a passion for (most) food and a desire to be part of one of the fastest growing start-up\u2019s around.", "employment_types": ["Full Time", "Permanent"], "selling_points": ["Handle inbound customer enquiries", "Assist in maintaining and expanding our selection", "Make menu or restaurant suggestions"], "locations": ["Central"], "categories": ["Admin & HR", "Personal / Executive Assistant", "Professional Services", "Company Secretary", "Hospitality / F & B", "Hospitality / Hotel Services"], "post_time": "2022-01-11T10:45:26Z", "salary": {"currency": null, "max": null, "min": null, "period": "monthly", "term": null}, "salary_visible": false, "title_keywords": ["operations executive"], "responsibilities": [], "requirements": {"degrees": [], "majors": [], "languages": [], "language_level": [], "hard_skills": ["go"], "soft_skills": [], "languages_combined": []}, "experience_required": {"duration": [], "field": []}}, {"job_id": "100003009037712", "location_code": "hk", "company": "Gemini Personnel Limited", "job_title": "Company Secretarial Specialist - Well-established Professional Firm in Central  (KIO-J077504)", "description": "A well-established professional firm, providing solutions to corporate clients on corporate secretarial, Trusts, Funds, taxation advisory and accounting, located in Central is hiring to cope with the growing business.\n\n\n\nResponsibilities\n\n\nAssist in handling company secretarial matters for both Hong Kong and offshore, listed or private companies\nPrepare documents for company and individual services, such as company incorporation, annual statutory filing, dissolution of companies in Hong Kong and overseas jurisdictions.\nAssist in handling works on\u00a0HK company incorporation, annual returns, shares transfer etc.\nLiaise with clients & overseas agents by email or phone for service rendered\nOther ad hoc duties assigned by the team manager\n\nRequirements\n\nDiploma or above with strong determination to develop professional career in company secretarial area\n2 years or above of of relevant experience gained in Bank, CPA or professional firms, better in customer serving role. For applicants with more applicant, will be considered for senior officer role.\u00a0Nice to have experience in company secretarial practice under the Hong Kong new Companies Ordinance, Company Acts in the major offshore jurisdictions.\nAcademic background and qualification in company secretarial and\u00a0corporate governance\nCantonese, Mandarin and English\n\nPackage\n\n5 days work\u00a0\nDiscretionary Bonus\u00a0\nTraining and Growth\nFeel free to explore with Ms. So at 98651077 or 35529113 for confidential discussion or exploration.\n", "employment_types": ["Full Time", "Permanent"], "selling_points": ["Company Secretarial Officer / Senior Officer", "2 year+ experience gained in professional firms", "Friendly team members with good work life balance"], "locations": ["Central"], "categories": ["Professional Services", "Company Secretary"], "post_time": "2022-01-11T03:35:59Z", "salary": {"currency": null, "max": null, "min": null, "period": "monthly", "term": null}, "salary_visible": false, "title_keywords": ["specialist"], "responsibilities": ["liaise with clients", "prepare documents", "ad hoc duties"], "requirements": {"degrees": ["diploma or above"], "majors": [], "languages": ["cantonese", "english", "mandarin"], "language_level": [], "hard_skills": ["cpa", "nice", "companies ordinance"], "soft_skills": [], "languages_combined": [{"language": "cantonese", "language_level": []}, {"language": "english", "language_level": []}, {"language": "mandarin", "language_level": []}]}, "experience_required": {"duration": ["2 years"], "field": ["secretarial", "relevant experience"]}}, {"job_id": "100003009041648", "location_code": "hk", "company": "KONCI (1989) LIMITED", "job_title": "Personal Assistant", "description": "Responsibilities:\n\nProvide full spectrum of professional secretarial and executive support to Chairman & Vice Chairman such as managing their calendar, prioritizing meetings and appointments, taking care of their social activities, travel and accommodation arrangements; updating their CV and biography regularly\nManage and Organize programmes, events and social activities for the Chairman & Vice Chairman\nPerform all Public appointments and Community services related job duties\nManage household workers recruitment, contract renewal, payroll and travel arrangements when necessary.\nPrepare and update driver roasters\nAssist in office decoration & renovation\nAnswer incoming telephone calls and attend guests; and\nPerform any other duties as directed and assigned by the Company at any time and from time to time\n\nRequirements:\n\nBachelor Degree holder with 5 years of relevant experience\nMature, self-motivated, proactive, well organized & attentive to details with excellent interpersonal & communication skills\nFluent in written & spoken English & Chinese\nProficient in MS Office especially Word, Excel, PowerPoint, Google-powered business tools (email, calendar, docs)", "employment_types": ["Full Time", "Permanent"], "selling_points": [], "locations": ["Causeway Bay"], "categories": ["Admin & HR", "Personal / Executive Assistant", "Professional Services", "Company Secretary"], "post_time": "2022-01-12T04:55:22Z", "salary": {"currency": null, "max": null, "min": null, "period": "monthly", "term": null}, "salary_visible": false, "title_keywords": ["personal assistant"], "responsibilities": ["any other duties", "travel arrangements", "renovation", "executive support", "recruitment", "payroll"], "requirements": {"degrees": ["bachelor degree holder"], "majors": [], "languages": ["english", "chinese"], "language_level": ["fluent"], "hard_skills": ["excel", "word", "powerpoint", "ms office"], "soft_skills": ["communication skills", "self-motivated", "attentive to details", "well organized", "mature", "proactive", "interpersonal"], "languages_combined": [{"language": "english", "language_level": ["fluent"]}, {"language": "chinese", "language_level": ["fluent"]}]}, "experience_required": {"duration": ["5 years"], "field": ["relevant experience"]}}, {"job_id": "100003009046222", "location_code": "hk", "company": "Sing Tao Management Services Limited", "job_title": "Legal Counsel", "description": "Responsibilities:\n\nDraft, review and negotiate various legal documentations and commercial contracts\nPartner with company secretarial team in handling a wide range of corporate matters, including preparation of annual/interim reports, announcements, board minutes or resolutions etc\nManage and collaborate with external counsels on legal and regulatory matters\u00a0\nAssist in maintaining and updating legal policies and procedures\nHandle ad hoc tasks/projects as assigned\n\nRequirements:\n\nHong Kong qualified lawyer; over 4 years of\u00a0post-qualification experience\nWell versed in HK listing rules compliance and company secretarial matters\nExcellent legal and analytical skill; strong business acumen\nAble to work independently with minimal supervision\nFluency in spoken and written English & Chinese\n\nInterested parties please click \u201cApply Now\" to submit your complete resume with\u00a0employment history, expected salary and REFERENCE NUMBER or by\u00a0post to\u00a0Human Resources Department,\u00a03/F,\u00a0Sing Tao News Corporation Building, 7 Chun Cheong Street, Tseung Kwan O Industrial Estate, Tseung Kwan O, New Territories, Hong Kong\n\nWe are an equal opportunity employer and welcome applications from all qualified candidates. Information provided will be treated in strict confidence and only be used for recruitment-related purposes. Applicant who is not invited for an interview within 6 weeks may consider their application not successful. All personal data of unsuccessful applicants will be destroyed within 6 months.\n\nhttp://www.singtaonewscorp.com/", "employment_types": ["Full Time", "Permanent"], "selling_points": [], "locations": ["Tseung Kwan O"], "categories": ["Professional Services", "Business Consultancy", "Company Secretary", "Legal & Compliance"], "post_time": "2022-01-13T10:00:55Z", "salary": {"currency": null, "max": null, "min": null, "period": "monthly", "term": null}, "salary_visible": false, "title_keywords": ["legal counsel"], "responsibilities": ["collaborate with", "maintaining", "contracts", "policies", "review", "procedures", "ad hoc tasks", "reports"], "requirements": {"degrees": [], "majors": [], "languages": ["english", "chinese"], "language_level": ["fluency"], "hard_skills": ["analytical skill", "acumen"], "soft_skills": ["business acumen", "analytical skill", "work independently"], "languages_combined": [{"language": "english", "language_level": ["fluency"]}, {"language": "chinese", "language_level": ["fluency"]}]}, "experience_required": {"duration": ["4 years"], "field": ["post-qualification"]}}, {"job_id": "100003009035658", "location_code": "hk", "company": "Creative Art (HK) Culture Communication Co., Limited", "job_title": "CEO\u884c\u653f\u79d8\u66f8", "description": "\u5de5\u4f5c\u8077\u8cac\uff1a\n\n-\u00a0\u8ddf\u9032\u5404\u90e8\u9580\u9805\u76ee\u9032\u5ea6\uff0c\u8655\u7406\u4e0a\u53f8\u5206\u914d\u7684\u500b\u4eba\u4e8b\u52d9\uff1b\n\n-\u00a0\u4e26\u6574\u7406\u5404\u9805\u76ee\u76f8\u95dc\u8cc7\u6599\uff0c\u5354\u8abf\u884c\u653f\u652f\u63f4\u548c\u8a18\u9304\uff1b\n\n-\u00a0\u5c0d\u63a5\u5916\u4f86\u6e20\u9053\u53ca\u4eba\u54e1\uff0c\u843d\u5be6\u5404\u9805\u5408\u4f5c\u6e9d\u901a\uff0c\u5b89\u6392\u65e5\u5e38\u884c\u7a0b\uff1b\n\n-\u00a0\u00a0\u64b0\u5beb\u7c21\u55ae\u516c\u5171\u6587\u66f8\uff0c\u5305\u62ec\uff08\u9805\u76ee\u8a08\u5283\u66f8\u3001\u62db\u6a19\u6587\u4ef6\u3001\u65b0\u805e\u7a3f\u4ef6\u7b49\uff09\uff1b\n\n-\u00a0\u00a0\u00a0\u8ca0\u8cac\u8655\u7406\u4e00\u822c\u884c\u653f\u53ca\u6587\u66f8\u5de5\u4f5c\uff0c\u5305\u62ec\u5404\u985e\u6587\u66f8\u8655\u7406\uff0c\u5831\u544a\u6574\u7406\u53ca\u5b58\u6a94\u3002\n\n\n\n\u4efb\u8077\u8981\u6c42\uff1a\n\n-\u00a0 \u5927\u5c08\u6216\u4ee5\u4e0a\u7a0b\u5ea6\u512a\u5148\u8003\u616e\n\n-\u00a0\u00a0\u00a0\u5177\u6700\u5c11\u4e00\u5e74\u76f8\u95dc\u79d8\u66f8\u5de5\u4f5c\u7d93\u9a57\uff0c\u53ca\u4eba\u529b\u8cc7\u6e90\u548c\u884c\u653f\u7ba1\u7406\u7d93\u9a57\u512a\u5148\n\n-\u00a0 \u00a0\u719f\u6089\u884c\u653f\u5de5\u4f5c\u5167\u5bb9\u53ca\u4f7f\u7528\u5404\u7a2e\u8fa6\u516c\u5ba4\u8edf\u4ef6\u548c\u8a2d\u5099\uff1b\n\n-\u00a0 \u00a0\u5de5\u4f5c\u7a4d\u6975\u3001\u7d30\u5fc3\u6709\u8010\u5fc3\uff0c\u826f\u597d\u6e9d\u901a\u80fd\u529b\u3001\u6027\u683c\u958b\u6717\uff1b\n\n-\u00a0 \u00a0\u7368\u7acb\u89e3\u6c7a\u554f\u984c\u7684\u80fd\u529b\uff0c\u7d44\u7e54\u5354\u8abf\u6280\u5de7\n\n-\u00a0 \u00a0\u719f\u6089\u4e2d\u82f1\u6587\u96fb\u8166\u6587\u66f8\u8655\u7406 \u3002", "employment_types": ["Full Time"], "selling_points": [], "locations": ["Mong Kok"], "categories": ["Admin & HR", "Administration / Operation Manager", "Secretary", "Professional Services", "Company Secretary"], "post_time": "2022-01-10T08:02:52Z", "salary": {"currency": null, "max": null, "min": null, "period": "monthly", "term": null}, "salary_visible": false, "title_keywords": [], "responsibilities": [], "requirements": {"degrees": [], "majors": [], "languages": [], "language_level": [], "hard_skills": [], "soft_skills": [], "languages_combined": []}, "experience_required": {"duration": [], "field": []}}, {"job_id": "100003009034140", "location_code": "hk", "company": "TMF Hong Kong Limited", "job_title": "Company Secretarial Associate (Fresh graduate are welcomed to apply)", "description": "TMF Group in Hong Kong is currently looking for a Associate\u00a0to join its Corporate Secretarial Team.\n\n\u00a0Responsibilities:\n\n\nAssist the Manager / Senior Manager in providing company secretarial services to a range of non-listed client companies.\nAssist in handling full set of company secretarial documents\nCommunicate with clients under supervision\nDraft and issue invoices, follow up debts\nMonitor the renewal of license fees for clients\u2019 companies\nArrange funds transfer for clients\u2019 companies and liaise with bankers to ensure payments are effected on a timely basis\nMaintain statutory records for clients\u2019 companies\nUpdate and maintain records/information in ViewPoint\nHandle duties as assigned by supervisors\n\nRequirements\n\nDegree holder with a minimum\u00a0of 1 year relevant experience gained in professional firm/ CPA firm/ law firm\nFresh graduate are welcomed to apply\nGood knowledge of corporate secretarial law and familiar with Companies Ordinance, rules and regulations of regulatory bodies\nGood computer skills, experience/knowledge in Viewpoint system is an advantage\nGood command of both spoken and written English and Chinese, fluent in Putonghua is preferred\nAttention to detail with high degree of accuracy\nOnly shortlisted candidates will be notified by Bobo Wai/Amanda Lim, recruiter from Malaysia Talent Acquisition Team, through contact number with Malaysia country code (+60) 280 XXXX.\n\n\nWe offer competitive remuneration package including annual leave, 13-month salary, discretionary bonus, life insurance, dental and medical coverage and study and examination leaves to the successful candidate. Please forward your personal profile to us with CURRENT & EXPECTED SALARY by online application.\n\nPersonal data collected will be used for recruitment purposes only and will be treated in strict confidence. Applicants not invited for interview within 4 weeks may consider their applications unsuccessful and all information submitted will be destroyed. \u00a0For further information, please visit our website on\u00a0www.tmf-group.com", "employment_types": ["Full Time", "Permanent"], "selling_points": ["Deliver CoSec services to our non-listed clients", "Professional development opportunities", "Work on a diverse client portfolio"], "locations": ["Causeway Bay"], "categories": ["Professional Services", "Company Secretary", "Legal & Compliance"], "post_time": "2022-01-10T02:49:08Z", "salary": {"currency": null, "max": null, "min": null, "period": "monthly", "term": null}, "salary_visible": false, "title_keywords": ["associate"], "responsibilities": ["communicate with", "invoices", "monitor", "maintain", "payments", "liaise with"], "requirements": {"degrees": ["degree", "fresh graduate", "degree holder"], "majors": ["law"], "languages": ["putonghua", "english", "chinese"], "language_level": ["good command", "fluent"], "hard_skills": ["code", "cpa", "computer skills", "companies ordinance"], "soft_skills": ["confidence", "attention to detail"], "languages_combined": [{"language": "putonghua", "language_level": ["fluent", "good command"]}, {"language": "english", "language_level": ["good command"]}, {"language": "chinese", "language_level": ["good command"]}]}, "experience_required": {"duration": ["minimum of 1 year"], "field": ["cpa firm", "relevant experience"]}}, {"job_id": "100003009037332", "location_code": "hk", "company": "Computershare Hong Kong Investor Services Limited", "job_title": "Officer, Governance Services", "description": "We give you a world of potential\n\nAn exciting new opportunity has recently opened up under our Governance team. We are currently looking to hire an Officer to support the delivery of Hong Kong Governance Advisory and managed service client engagements to cope with our fast growing practice.\n\nA role you will love\n\nThe Officer will be an active member of the global managed service team with responsibility for developing the global Governance Services practice and range of service offerings to multinational clients. You will be assisting to develop subject matter market insights, technical knowledge and global service delivery templates, processes, tools and materials. You will be essential in establishing and maintaining global client relationships and advising them on global compliance, governance and transaction related matters.\n\nSome of your key responsibilities will include:\u202f\u00a0\n\n\u00a0\u00a0\u00a0\u00a0\u00a0\u00a0 Assist the Manager on the delivery of global governance advisory and managed service client engagements.\n\u00a0\u00a0\u00a0\u00a0\u00a0\u00a0 Support and develop service delivery team members and third party providers across the global network.\n\u00a0\u00a0\u00a0\u00a0\u00a0\u00a0 Assist on all business development activities and client service contract negotiations.\n\u00a0\u00a0\u00a0\u00a0\u00a0\u00a0 As an SME, contribute to a variety of global projects and initiatives as and when required.\n\u00a0\u00a0\u00a0\u00a0\u00a0\u00a0 Keep abreast of both internal and external influences to help shape continuous growth and development of the global Governance Services business and offering.\n\u00a0\u00a0\u00a0\u00a0\u00a0\u00a0 Support the Managers for any ad hoc assignments as delegated.\u00a0\n\nWhat will you bring to the role?\u00a0\u00a0\u00a0\n\nYou will be a graduate or an associate member of the Hong Kong Chartered Governance Institute with a few years spent in a company secretarial, corporate administration and governance experience\u00a0gained within professional services and/or industry. You will bring practical experience in managing the global client\u2019s on-boarding and co-ordination work in different jurisdictions. Your drive and enthusiasm will help develop, manage and grow the domestic and global Governance Services business.\n\nYour expert networking and communication skills will be essential to influence and build effective relationships at all levels with clients and colleagues. You would have awareness of legal, regulatory and governance trends and developments.\n\nOther key skills required for the role include:\n\n\u00a0\u00a0\u00a0\u00a0\u00a0\u00a0 Attention to detail and track record of producing high quality work.\n\u00a0\u00a0\u00a0\u00a0\u00a0\u00a0 Resilient and composed under pressure, proactive, self-motivated, take ownership/responsibility for own work and work of others.\n\u00a0\u00a0\u00a0\u00a0\u00a0\u00a0 Effective business, financial and risk management skills and the ability to think/act strategically and commercially whilst protecting the reputation of the company.\n\u00a0\u00a0\u00a0\u00a0\u00a0\u00a0 Sound problem solving and analytical skill.\n\u00a0\u00a0\u00a0\u00a0\u00a0\u00a0 Good command of spoken and written English with fluent in Mandarin\n\nA company to be proud of\u00a0\n\nComputershare (ASX:CPU) is a world leader in financial administration with over 14,000 employees across 21 different countries delivering expertise to over 40,000 clients.\u00a0At Computershare, it\u2019s more than just a job, our open and inclusive culture means that we will help you to grow, to move forward and make the most of the world of opportunities we have available. With infinite possibilities, we could take you anywhere.\u00a0\u00a0#worldofpotential\n\nRewards designed for you\u00a0\u00a0\u00a0\n\nEmployee Share Plan.\u00a0Set aside salary to purchase shares in our company and you\u2019ll increase your investment when you receive a generous company contribution towards additional shares.\n\nPaid time away from work.\u00a0Our employees enjoy a competitive paid time off package, including a day each year to volunteer time for a good cause that is important to you.\n\nExtra Rewards.\u00a0From tuition reimbursement to cash bonus recruitment referral programs, our comprehensive benefits package offers a multitude of options.\n\nA diverse and inclusive place to work\u00a0\u00a0\n\nComputershare celebrates the diversity of our\u00a0people,\u00a0and we welcome applications from everyone.\u00a0\n\nWe believe that having a culture of inclusion is essential in delivering good results. Attracting, retaining, and developing a diverse workforce where employees feel valued, respected, and empowered allows people to reach their full potential. As a business this diversity helps us to better reflect and understand our customers\u2019 needs to allow us to drive better outcomes.\n\nWe are happy to accommodate individual needs during your application\u00a0journey. If you require disability accommodations or adjustments, please email us\u00a0detailing your requirements and contact information.\n\nComputershare is an equal opportunity employer. Qualified applicants will receive consideration for employment regardless of race, color, religion, sex, sexual orientation, gender identity or expression, national or ethnic origin, age, disability, protected veteran status, or other characteristics protected by applicable law.\u00a0\n\nCovid-secure\n\nWe\u2019ve kept our business running during the pandemic by moving most of our employees to remote working, and by creating and maintaining a safe environment for those people who need to be in the office. We carefully limit the amount of people at our locations and ensure that those who cannot work remotely are kept safe with proper distancing and protective equipment", "employment_types": ["Full Time", "Permanent"], "selling_points": ["Exciting opportunity for company secretaries!", "Join an established global firm where you can grow", "Fantastic working culture and benefits"], "locations": ["Wan Chai Area"], "categories": ["Banking / Finance", "Others", "Professional Services", "Business Consultancy", "Company Secretary"], "post_time": "2022-01-11T02:31:16Z", "salary": {"currency": null, "max": null, "min": null, "period": "monthly", "term": null}, "salary_visible": false, "title_keywords": ["officer"], "responsibilities": ["service delivery", "co-ordination work", "develop", "communication", "ad hoc assignments", "sme", "third party", "administration"], "requirements": {"degrees": [], "majors": [], "languages": ["english", "mandarin"], "language_level": ["good command", "fluent"], "hard_skills": ["problem solving", "make", "analytical skill"], "soft_skills": ["self-motivated", "under pressure", "problem solving and analytical skill", "attention to detail", "proactive"], "languages_combined": [{"language": "english", "language_level": ["good command"]}, {"language": "mandarin", "language_level": ["fluent", "good command"]}]}, "experience_required": {"duration": [], "field": []}}, {"job_id": "100003009041934", "location_code": "hk", "company": "\u83ef\u79d1\u8cc7\u672c\u6709\u9650\u516c\u53f8", "job_title": "Assistant Legal Manager", "description": "Responsibilities:\n\n\u00fc\u00a0\u00a0 Providing legal support to the company on a wide range of general corporate and commercial matters\n\n\u00fc\u00a0\u00a0 Drafting and reviewing legal documents\n\n\u00fc\u00a0\u00a0 Conducting legal research and advising business units on legal issues and regulatory matters\n\n\u00fc\u00a0\u00a0 Monitoring and reviewing business activities, transactions, documentation and other records in ensuring compliance with regulatory requirements\n\n\u00fc\u00a0\u00a0 Preparing, attending and participating in meetings with senior management, department heads, and/or external stakeholders\n\n\u00fc\u00a0\u00a0 Assisting in the establishment and implementation of internal policies and procedures\n\n\u00fc\u00a0\u00a0 Performing ad hoc projects as required\n\nRequirements:\n\n\u00fc\u00a0\u00a0 Law degree holder\n\n\u00fc\u00a0\u00a0 Minimum 5 years\u2019 legal and compliance experience\n\n\u00fc\u00a0\u00a0 Knowledge of the Hong Kong Listing Rules preferred\n\n\u00fc\u00a0\u00a0 Good command in English and Chinese, fluency in Putonghua an advantage\n\n\u00fc\u00a0\u00a0 Independent, self-initiative, attentive to details and standard, and a team player\n\n\nPlease submit your application to us with your availability\u00a0and expected salary.", "employment_types": ["Full Time"], "selling_points": [], "locations": ["Central"], "categories": ["Professional Services", "Company Secretary", "Management", "General Management", "Legal & Compliance"], "post_time": "2022-01-12T04:42:41Z", "salary": {"currency": null, "max": null, "min": null, "period": "monthly", "term": null}, "salary_visible": false, "title_keywords": ["manager", "assistant"], "responsibilities": ["regulatory requirements", "policies", "compliance", "monitoring", "implementation", "transactions", "procedures", "ad hoc projects", "documentation", "senior management", "business activities"], "requirements": {"degrees": ["degree holder"], "majors": ["law"], "languages": ["putonghua", "english", "chinese"], "language_level": ["fluency", "advantage", "good command"], "hard_skills": [], "soft_skills": ["attentive to details", "team player", "independent", "self-initiative"], "languages_combined": [{"language": "putonghua", "language_level": ["fluency", "good command"]}, {"language": "english", "language_level": ["fluency", "advantage", "good command"]}, {"language": "chinese", "language_level": ["fluency", "advantage", "good command"]}]}, "experience_required": {"duration": ["minimum 5 years"], "field": ["compliance", "legal"]}}, {"job_id": "100003009032858", "location_code": "hk", "company": "Tianjin Port Development Holdings Limited", "job_title": "Company Secretarial Officer", "description": "Tianjin Port Development Holdings Limited is a company listed on the Hong Kong Stock Exchange. We are seeking a high potential candidate to fill the following position.\nResponsibilities:\nHandle full spectrum of company secretarial matters including the preparation of minutes, resolutions, meeting papers and statutory forms.\nPrepare and arrange for statutory filings, maintain and update statutory records, database and filing systems\nAssist in preparing annual / interim reports, announcements and circulars;\nCompose and translate corporate correspondence and other communication materials.\nAssist in ad hoc projects and other duties as assigned.\nRequirements:\nDegree holder and HKICS graduate or student member.\nAt least 2 years company secretarial experience gained in listed companies.\nKnowledge in Companies Ordinance and Listing Rules.\nGood command of written and spoken English and Chinese (including Putonghua).\nDetail-oriented, meticulous, self-motivated with a strong sense of responsibility.\nAbility to work independently, under pressure and able to meet tight schedules.\nWe offer 5-day work and attractive remuneration package to the right candidate. Interested parties please send us full resume with current and expected salary and available date information. Please visit our company website www.tianjinportdev.com for more information.\nPersonal data and information collected will be kept confidential and used for recruitment purpose only.", "employment_types": ["Full Time", "Permanent"], "selling_points": [], "locations": ["Causeway Bay"], "categories": ["Professional Services", "Company Secretary"], "post_time": "2022-01-08T01:25:33Z", "salary": {"currency": null, "max": null, "min": null, "period": "monthly", "term": null}, "salary_visible": false, "title_keywords": ["company secretarial officer"], "responsibilities": ["other duties", "systems", "communication", "maintain", "reports", "ad hoc projects", "database"], "requirements": {"degrees": ["degree holder"], "majors": [], "languages": ["putonghua", "english", "chinese"], "language_level": ["good command"], "hard_skills": ["companies ordinance"], "soft_skills": ["meticulous", "self-motivated", "work independently", "under pressure", "sense of responsibility", "detail-oriented", "meet tight schedules"], "languages_combined": [{"language": "putonghua", "language_level": ["good command"]}, {"language": "english", "language_level": ["good command"]}, {"language": "chinese", "language_level": ["good command"]}]}, "experience_required": {"duration": ["at least 2 years"], "field": ["secretarial"]}}, {"job_id": "100003009043692", "location_code": "hk", "company": "Ho & Ip, Solicitors", "job_title": "Junior Secretary", "description": "Requirements:-\n\n\nForm 5 or above with certificate of secretarial training\nWith legal experience preferable\nGood command of written and spoken Chinese and English (knowledge of Putonghua is an advantage)\nHardworking, initiative and responsible\nImmediately available is preferred\nInterested candidate please apply with full resume and expected salary either by clicking \"Apply Now\" or by post to The Manager, 24/F., CMA Building, 64-66 Connaught Road Central, Hong Kong.\nData collected will be used for recruitment purpose only", "employment_types": ["Full Time", "Permanent"], "selling_points": [], "locations": ["Not Specified"], "categories": ["Admin & HR", "Secretary", "Others", "Professional Services", "Company Secretary"], "post_time": "2022-01-13T02:10:57Z", "salary": {"currency": null, "max": null, "min": null, "period": "monthly", "term": null}, "salary_visible": false, "title_keywords": ["junior secretary"], "responsibilities": ["recruitment", "data"], "requirements": {"degrees": ["certificate", "form 5 or above"], "majors": [], "languages": ["putonghua", "english", "chinese"], "language_level": ["advantage", "good command"], "hard_skills": [], "soft_skills": ["initiative", "hardworking", "responsible"], "languages_combined": [{"language": "putonghua", "language_level": ["advantage", "good command"]}, {"language": "english", "language_level": ["advantage", "good command"]}, {"language": "chinese", "language_level": ["advantage", "good command"]}]}, "experience_required": {"duration": [], "field": ["legal"]}}, {"job_id": "100003009034901", "location_code": "hk", "company": "Boardroom Corporate Services (HK) Limited", "job_title": "Associate - Corporate Secretarial", "description": "\u2728We are looking for suitably qualified professionals to join our ever-growing Corp Sec family! If you have a passion for\u00a0corporate secretarial field, filled with positive energy and able to persevere through any challenges, look no further and come JOIN US.\n\n\u2728 We take pride in our people and YOU can be a part of the BoardRoom Team. \u00a0An amazing opportunity awaits you!\n\n\nJob Description\n\n\n\nTo support CS team lead in executing CS-related engagements\nBe a team player and communicate among team members and provide leave cover for fellow team members.\nEncouraged to take initiatives in proposing work improvements via direct supervisor. Such initiatives will be considered and evaluated.\nDraft all communications with clients for review.\nExperienced Associates are expected to liaise and respond to clients' requests and queries regarding corporate secretarial matters after consultation with the direct supervisor.\nExperienced Associates are expected to provide good client service when dealing with clients.\nFollow-up with client on the return of documents and forms and ensuring submission of statutory forms and documents to the relevant authorities/ gatekeepers within the stipulated deadline.\nRemind clients on deadline of holding Annual General Meeting for their portfolio of clients.\nEnsure that statutory books are in order and updated for their portfolio of clients.\nGenerate and prepare documents and forms required for their portfolio of clients.\n\nRequirements:\n\nDiploma or above in corporate administration or business disciplines\n1 to 3 years of company secretarial experience gained preferably in professional firm/ CPA firm/ law firm\nAbility to be flexible and adaptable in working styles.\nMeticulous, organized, detailed and deadline-oriented.\nPro-active, willing to offer new suggestions and share knowledge.\nAbility to prioritize work and meet deadlines.\nAbility and willingness to take on duties outside job specification.\nAbility to work both in a team environment.\nAbility to work under pressure\n\nWe have been accredited by:\n\nHKICPA as Authorised Employer\nACCA as Approved Employer\n\nWe offer a competitive remuneration package and promising career prospect, 5-day work week, study/examination leave and medical insurance. To apply, please send your full resume, earliest availability, current salary package, expected salary and contact telephone number to HR & Admin Unit via JobsDB job application or via email. Please quote ref. \"CS\" on your application.\n\nWebsite:\u00a0www.boardroomlimited.com/hk\n\nAddress: 31/F, 148 Electric Road, North Point, Hong Kong.", "employment_types": ["Full Time", "Permanent"], "selling_points": ["Working From Home / Hybrid", "Career Growth Opportunity", "5-day Work, 15 Days AL, Study/Exam Leave"], "locations": ["North Point"], "categories": ["Professional Services", "Company Secretary", "Legal & Compliance"], "post_time": "2022-01-10T04:35:18Z", "salary": {"currency": null, "max": null, "min": null, "period": "monthly", "term": null}, "salary_visible": false, "title_keywords": ["associate"], "responsibilities": ["liaise", "communications with", "review", "executing", "prepare documents"], "requirements": {"degrees": ["diploma or above"], "majors": ["business"], "languages": [], "language_level": [], "hard_skills": ["cpa", "acca", "hkicpa"], "soft_skills": ["flexible", "meticulous", "organized", "adaptable", "work under pressure", "prioritize", "pro-active", "meet deadlines", "detailed"], "languages_combined": []}, "experience_required": {"duration": ["1 to 3 years"], "field": ["secretarial", "cpa firm"]}}, {"job_id": "100003009035550", "location_code": "hk", "company": "Kaizen CPA Limited", "job_title": "Company Secretarial Officer (Japanese Speaker) (5-Day work)", "description": "Job Requirements:\n\nHolder of Higher Diploma in Japanese Studies or Degree holder;\nFluent in spoken and written Japanese (JLPT N1), English, Cantonese & Mandarin;\nWorking experience in relevant field will be an advantage\nFresh graduates are also be welcomed\nExcellent telephone manner, communication and customer service skills\nProficient in MS Office & Chinese word processing\nSelf-motivated, patient, and good interpersonal skills, well organized\nImmediate available or short notice is highly preferred\n\nJob Responsibilities:\u00a0\n\nPreform a full range of company secretarial duties for\u00a0Hong Kong\u00a0and offshore companies;\nPrepare and arrange for statutory filings;\nMaintain and update statutory records, database and filing systems;\nMaintain business relationship with new and existing clients, especially for Japanese clients\nHandle ad-hoc assignments\n\nBenefits:\n\nFive-day work week\nMedical insurance\nPerformance bonus\nTransportation allowance\n\nInterested parties please email your full resume with present & expected salary via \"APPLY NOW\".\n\n\nFor further details on Kaizen, please visit our website www.kaizencpa.com.", "employment_types": ["Full Time", "Permanent"], "selling_points": ["Good career prospects and learning opportunities", "Group medical insurance, study and exam leave", "Attractive package"], "locations": ["Kwun Tong"], "categories": ["Admin & HR", "Clerical / Admin Staff", "Professional Services", "Business Consultancy", "Company Secretary"], "post_time": "2022-01-10T07:37:22Z", "salary": {"currency": null, "max": null, "min": null, "period": "monthly", "term": null}, "salary_visible": false, "title_keywords": ["company secretarial officer"], "responsibilities": ["ad-hoc assignments", "maintain", "database", "systems"], "requirements": {"degrees": ["diploma", "degree holder"], "majors": [], "languages": ["cantonese", "english", "mandarin", "japanese", "chinese"], "language_level": ["proficient", "fluent"], "hard_skills": ["chinese word processing", "ms office"], "soft_skills": ["customer service skills", "self-motivated", "well organized", "communication", "interpersonal skills", "patient", "telephone manner"], "languages_combined": [{"language": "cantonese", "language_level": ["fluent"]}, {"language": "english", "language_level": ["fluent"]}, {"language": "mandarin", "language_level": ["fluent"]}, {"language": "japanese", "language_level": ["fluent"]}, {"language": "chinese", "language_level": ["proficient"]}]}, "experience_required": {"duration": [], "field": []}}, {"job_id": "100003009041999", "location_code": "hk", "company": "Gallant", "job_title": "LEGAL SECRETARY", "description": "- Form 7 or above with formal secretarial training\n\n- With\u00a0at least two\u00a0years of relevant experience in legal firms\n\n\n- Good Command of both English and Chinese languages with the ability to speak Putonghua a preferred advantage.\n\n\n- Proficiency in MS Office and Chinese typing.\n\n- Good telephone manners\n\n- Immediately available preferred\n\n\n\nWe offer medical benefits and education allowance to the successful candidate. Interested parties may apply with full C.V., stating the current and expected salaries, and\u00a0click \"APPLY NOW\". All applications will be treated in strict confidence.", "employment_types": ["Full Time", "Permanent"], "selling_points": [], "locations": ["Central"], "categories": ["Admin & HR", "Secretary", "Professional Services", "Company Secretary", "Legal & Compliance"], "post_time": "2022-01-12T05:07:54Z", "salary": {"currency": null, "max": null, "min": null, "period": "monthly", "term": null}, "salary_visible": false, "title_keywords": ["legal secretary"], "responsibilities": [], "requirements": {"degrees": [], "majors": [], "languages": ["putonghua", "english", "chinese"], "language_level": ["advantage", "proficiency", "good command"], "hard_skills": ["typing", "ms office"], "soft_skills": [], "languages_combined": [{"language": "putonghua", "language_level": ["advantage", "good command"]}, {"language": "english", "language_level": ["good command"]}, {"language": "chinese", "language_level": ["proficiency", "good command"]}]}, "experience_required": {"duration": ["at least two years"], "field": ["relevant experience", "legal"]}}, {"job_id": "100003009043183", "location_code": "hk", "company": "Wong & Tang Solicitors", "job_title": "Legal Executive / Legal Secretary / Clerk", "description": "Good communication skills;\nMature, good interpersonal skills, well-organized and can work under pressure;\nFresh graduate with good working attitude will be considered;\nProficient in PC (Microsoft Word and Excel);\n1-2 year(s) experience in legal field is preferred; and\nImmediate available is preferable.", "employment_types": ["Full Time"], "selling_points": [], "locations": ["Wan Chai"], "categories": ["Professional Services", "Company Secretary", "Legal & Compliance"], "post_time": "2022-01-12T10:05:29Z", "salary": {"currency": null, "max": null, "min": null, "period": "monthly", "term": null}, "salary_visible": false, "title_keywords": ["legal executive", "clerk", "legal secretary"], "responsibilities": ["communication", "work under pressure"], "requirements": {"degrees": ["fresh graduate"], "majors": [], "languages": [], "language_level": [], "hard_skills": ["pc", "microsoft word", "excel"], "soft_skills": ["communication skills", "good working attitude", "well-organized", "mature", "interpersonal skills", "work under pressure"], "languages_combined": []}, "experience_required": {"duration": [], "field": ["legal"]}}, {"job_id": "100003009035994", "location_code": "hk", "company": "Bright Smart Securities International (H.K.) Limited", "job_title": "Legal Secretary", "description": "Responsibilities:\n\nProvide legal and secretarial support to the Chairman in all-round business affairs;\nReview a wide range of commercial agreements/legal documents\u00a0and assist in translation & interpretation;\nEngage in legal research and deliver practical legal advice to the Chairman;\nCoordinate and liaise with external professional firms and regulatory bodies;\nDeal with confidential matters with a high degree of professionalism, discretion and confidentiality;\nAssist Chairman in other administrative tasks, personal issues or ad hoc projects as assigned.\nRequirement & Qualifications:\n\nBachelor Degree in Business Administration or related disciplines;\nMinimum of 6 years\u2019 working experience preferably gained from financial or property industries;\nStrong legal background and analytical skills are required;\nProficient in PC applications, e.g. MS Office, Excel, PowerPoint and Chinese Word Processing is a MUST;\nPatient, organized and detail-minded, possess good communication and interpersonal skill;\nHardworking and able to work on multi-task and under pressure.\n\u00a0We Offer:\n\nCompetitive remuneration package\n5 Days Work & Bank Holidays\nAttendance Bonus\nMeal Allowance\nDiscretionary Bonus\nMedical Insurance\nWe provide attractive remuneration package and fringe benefits for the right candidate. Interested parties please send detailed resume with current and expected salaries to\u00a0Human Resources Department by clicking\u00a0\"Apply Now\"\u00a0or\u00a0fax to: 2530 2218.\n\nAll information collected will be used for recruitment purpose only, only shortlisted candidates will be notified.\n\nWelcome to visit our website: http://www.bsgroup.com.hk/ for more information.", "employment_types": ["Full Time", "Permanent"], "selling_points": [], "locations": ["Central"], "categories": ["Professional Services", "Business Consultancy", "Company Secretary", "Legal & Compliance"], "post_time": "2022-01-10T09:02:29Z", "salary": {"currency": null, "max": null, "min": null, "period": "monthly", "term": null}, "salary_visible": false, "title_keywords": ["legal secretary"], "responsibilities": ["review", "coordinate", "ad hoc projects", "secretarial support", "liaise with", "administrative tasks"], "requirements": {"degrees": ["degree", "bachelor"], "majors": ["related disciplines", "business administration"], "languages": ["chinese"], "language_level": [], "hard_skills": ["excel", "chinese word processing", "powerpoint", "pc applications", "analytical skills", "ms office"], "soft_skills": ["detail-minded", "organized", "multi-task", "under pressure", "analytical skills", "communication", "interpersonal skill", "patient", "hardworking"], "languages_combined": [{"language": "chinese", "language_level": []}]}, "experience_required": {"duration": ["minimum of 6 years"], "field": ["financial"]}}, {"job_id": "100003009035443", "location_code": "hk", "company": "Portcullis (Hong Kong) Limited", "job_title": "Trust Administrator", "description": "Job Description\n\n\u00a0Duties includes but not limited to:\n\nAssist in setting up private trusts\nDeal with daily administrative activities of trusts and asset holding companies\nPrepare documents for trust transactions\nPerform company secretarial duties in the maintenance of trust related entities\nAttend to clients\u2019 requests and support the team in client management duties\nMaintain proper records of documents and proper filing\nConduct reviews on existing trusts and company structures\nHandle ad hoc duties as assigned by supervisor\nThe ideal candidate should:\n\nBe a degree holder in law, accounting, business related disciplines (having relevant professional qualifications in Trust, Law, Accounting or Company Secretary will be an advantage)\nHave at least 2-3 years trust administration and/or company secretarial experience\nUnderstand good corporate governance and compliance\nPossess good communication and organization skills\nBe self-motivated, independent, detail-oriented and eager to learn\nBe proficient in English, with a working knowledge of Mandarin\nHave PC knowledge of MS Word and Chinese word processing", "employment_types": ["Full Time", "Permanent"], "selling_points": [], "locations": ["Central"], "categories": ["Professional Services", "Company Secretary", "Legal & Compliance"], "post_time": "2022-01-10T07:16:00Z", "salary": {"currency": null, "max": null, "min": null, "period": "monthly", "term": null}, "salary_visible": false, "title_keywords": ["administrator"], "responsibilities": ["ad hoc duties", "management", "maintenance", "compliance", "transactions", "support the team", "communication", "maintain proper records", "prepare documents", "administrative activities", "administration"], "requirements": {"degrees": ["degree holder"], "majors": ["business", "related disciplines", "accounting", "law"], "languages": ["english", "chinese", "mandarin"], "language_level": ["proficient"], "hard_skills": ["chinese word processing", "maintenance", "professional qualifications", "pc knowledge", "ms word"], "soft_skills": ["self-motivated", "independent", "detail-oriented", "communication", "eager to learn", "organization skills", "ideal"], "languages_combined": [{"language": "english", "language_level": ["proficient"]}, {"language": "chinese", "language_level": []}, {"language": "mandarin", "language_level": []}]}, "experience_required": {"duration": ["at least 2-3 years"], "field": ["secretarial", "administration"]}}, {"job_id": "100003009035266", "location_code": "hk", "company": "JNL Consulting Limited", "job_title": "Secretary / Executive Assistant \u2013 Global Insurance Firm, 12 months contract", "description": "Our client is a global insurance firm, seeking an experienced Secretary / Executive Assistant, initially on a 12 months contract basis.\n\nAs a Secretary / Executive Assistant, you will be responsible for the following:-\n\nPerform full spectrum of secretarial and administrative support on business routines\nCalendar/diary management, meeting coordination\nHandle expense claims/reports, daily mail, documents filing\nHandle periodic and ad-hoc reports, data entry and word processing within specified timeline\n\nTo be considered for this role as a Secretary / Executive Assistant, you possess the following:-\n\nAt least 3 years of experience as an Executive Assistant / Personal Assistant / Secretary\nAbility to prioritize work and work independently\nSuperior organization and time management skills\nFlexible and be prepared for changing requirements and issues as they arise\nExcellent command of MS functions\nExcellent verbal and written communication skills in English and Chinese\nImmediately available candidates will have an added advantage", "employment_types": ["Full Time", "Permanent", "Contract"], "selling_points": ["Global insurance firm, 12 months contract", "Secretary / Executive Assistant, admin support", "Excellent remuneration, career path & team culture"], "locations": ["Central & Western Area"], "categories": ["Admin & HR", "Personal / Executive Assistant", "Secretary", "Professional Services", "Company Secretary"], "post_time": "2022-01-10T06:34:29Z", "salary": {"currency": null, "max": null, "min": null, "period": "monthly", "term": null}, "salary_visible": false, "title_keywords": ["secretary", "executive assistant"], "responsibilities": ["ad-hoc", "management", "documents filing", "administrative support", "data entry", "communication", "reports", "coordination", "insurance"], "requirements": {"degrees": [], "majors": [], "languages": ["english", "chinese"], "language_level": ["excellent"], "hard_skills": ["word processing"], "soft_skills": ["flexible", "communication skills", "work independently", "responsible", "time management skills", "prioritize", "coordination", "superior"], "languages_combined": [{"language": "english", "language_level": ["excellent"]}, {"language": "chinese", "language_level": ["excellent"]}]}, "experience_required": {"duration": ["at least 3 years"], "field": []}}, {"job_id": "100003009033562", "location_code": "hk", "company": "East Asia Sentinel Limited", "job_title": "Corporate Services Officer / Assistant", "description": "Key Responsibilities:\n\nCarry out all aspects of corporate services including company secretarial duties, corporate governance and compliance functions; the preparation of annual returns, notices for AGM/GM, \u00a0annual / interim reports, minutes, resolutions, announcements and circulars\nOrganize board meetings, board committee meetings and shareholders\u2019 meetings\nUpdate and maintain statutory records and filing system\nHandle and follow up clients\u2019 inquiries\nLiaise with external regulators, advisers and authorities for all corporate services matters\nAssist in ad-hoc projects and corporate matters assigned from time to time\n\nRequirements:\n\nA bachelor degree in related field. Fresh graduates will also be considered\nStudent member of HKICS \u00a0and/or \u00a0ICSA is preferable but not essential\n2-3 years working experience (company secretarial / business field is preferred)\nGood written and spoken English and Chinese (both Cantonese and Putonghua) is essential\nResponsible, independent, self-motivated, detail oriented and a good team player\nCandidate with less experience will be considered as Corporate Services \u00a0Assistant\nImmediately available is an advantage\n\nJob Offer:\n\nWe provide 5 days\u2019 work week, a great working culture, a central location, and competitive remuneration package to the right candidate.\n\nPlease send your resume with full details of experience & qualifications, current and expected salary to Human Resources Manager, East Asia Sentinel Services Limited at 22/F., Tai Yau Building, 181 Johnston Road, Wanchai, Hong Kong or by email at", "employment_types": ["Full Time"], "selling_points": [], "locations": ["Wan Chai"], "categories": ["Professional Services", "Company Secretary"], "post_time": "2022-01-10T01:03:15Z", "salary": {"currency": null, "max": null, "min": null, "period": "monthly", "term": null}, "salary_visible": false, "title_keywords": ["officer", "assistant"], "responsibilities": ["compliance", "maintain", "reports", "liaise with", "ad-hoc projects"], "requirements": {"degrees": ["degree", "bachelor"], "majors": [], "languages": ["cantonese", "putonghua", "english", "chinese"], "language_level": ["good"], "hard_skills": [], "soft_skills": ["self-motivated", "good team player", "independent", "responsible", "detail oriented"], "languages_combined": [{"language": "cantonese", "language_level": ["good"]}, {"language": "putonghua", "language_level": ["good"]}, {"language": "english", "language_level": ["good"]}, {"language": "chinese", "language_level": ["good"]}]}, "experience_required": {"duration": ["2-3 years"], "field": ["secretarial", "business"]}}, {"job_id": "100003009033245", "location_code": "hk", "company": "ConnectedGroup Limited", "job_title": "Assistant Manager, Company Secretariat (HK$ 40k-55k)", "description": "Assistant Manager - Company Secretariat\n\nOur client is a well-established and reputable property developer listed in Hong Kong. We are assisting them looking for a talented individual to take up the Assistant Manager, Company Secretariat.\n\nSalary: HK$ 40,000 - 55,000x 12 month + bonus\n\nJob Summary:\n\nProviding company secretarial services for Board and company\nFamilir with Hong Kong Listing Rules and Securities and Futures Ordinance\n\nJob Duties:\n\nResponsible for full spectrum of company secretarial duties, corporate governance and compliance functions for listed company and private subsidiaries\nDraft and prepare annual and interim reports, announcements and circulars\nOrganize meetings for the board, committees and shareholders, and prepare relevant board papers, minutes and resolutions\nMaintain and update statutory records and filings in compliance with the Code on Real Estate Investment Trusts, Securities and Futures Ordinance, Listing Rules, applicable laws and regulations and implement compliance procedures as required\nLiaise with professional advisors and various regulatory bodies\nParticipate in ad hoc projects and tasks assigned from time to time\n\nRequirements:\n\nDegree holder in Corporate Administration or relevant disciplines\nQualified Member of HKCGI/CGI\nAt least 8 to 10 years of company secretarial experience gained in listed company, large-scale corporations or professional firms\nSolid experience in Hong Kong Listing Rules, Securities and Futures Ordinance and Hong Kong Companies\nExperience in handling compliance matters with the Securities and Futures Commission is an advantage\nExcellent command of written and spoken English and Chinese\nProven track record of minute taking and stakeholder management.\nCandidates with more experience will be considered as Manager\n\nInterested individuals should \"Apply Now\", due to an influx of applicants, we regret to inform you that ONLY suitable candidates will be contacted.\n\nFor a more comprehensive list of our vacancies, please visit: www.connectedgroup.com", "employment_types": ["Full Time", "Permanent"], "selling_points": ["Cover a wide range of company secretarial matters", "Top-tier Property Developer", "Qualified Member of HKCGI/CGI"], "locations": ["Kwun Tong Area"], "categories": ["Professional Services", "Company Secretary", "Legal & Compliance"], "post_time": "2022-01-09T00:01:01Z", "salary": {"currency": "HKD", "max": 54999, "min": 45000, "period": "monthly", "term": null}, "salary_visible": true, "title_keywords": ["assistant manager,"], "responsibilities": ["regulations", "compliance", "procedures", "maintain", "reports", "ad hoc projects", "liaise with", "listing"], "requirements": {"degrees": ["degree holder"], "majors": [], "languages": ["english", "chinese"], "language_level": ["excellent"], "hard_skills": ["inform", "securities and futures ordinance"], "soft_skills": ["comprehensive"], "languages_combined": [{"language": "english", "language_level": ["excellent"]}, {"language": "chinese", "language_level": ["excellent"]}]}, "experience_required": {"duration": ["at least 8 to 10 years"], "field": ["secretarial", "compliance", "securities"]}}, {"job_id": "100003009030455", "location_code": "hk", "company": "Tai United Holdings Limited", "job_title": "Company Secretarial Officer / Assistant", "description": "Responsibilities:\n\n- Assist in handling full spectrum of company secretarial matters for the listed Group and its subsidiaries\n\n- Arrange for filing of statutory forms and returns with registrars/regulatory authorities\n\n- Maintain/update secretarial records and registers\n\n- Assist in organizing Board/Committee and Shareholders meetings and prepare meeting materials\n\n- Assist in preparing of annual / interim reports, announcements and circulars\n\n- Assist in ad hoc projects and other duties as assigned\n\nRequirements:\n\n- Post-secondary graduate or equivalent with graduate/associate membership of HKICS / ICSA\n\n- 2-3 years of working experience in handling company secretarial duties\n\n- Good PC knowledge in MS Word, Excel, Powerpoint, and Chinese word processing\n\n- Good command of written and spoken English and Chinese (including Mandarin)\n\n- Experience in listed company is a must\n\n- Independent, attentive to details\n\n- Immediate availability is preferred\n\nInterested parties please send your detailed resume with current & expected salary and availability by clicking \"Apply Now\"\u00a0\n\n\n\n", "employment_types": ["Full Time"], "selling_points": [], "locations": ["North Point"], "categories": ["Professional Services", "Company Secretary"], "post_time": "2022-01-07T07:45:54Z", "salary": {"currency": null, "max": null, "min": null, "period": "monthly", "term": null}, "salary_visible": false, "title_keywords": ["company secretarial officer", "assistant"], "responsibilities": ["ad hoc projects", "maintain", "reports", "other duties"], "requirements": {"degrees": [], "majors": [], "languages": ["english", "chinese", "mandarin"], "language_level": ["good command", "good"], "hard_skills": ["excel", "chinese word processing", "powerpoint", "pc knowledge", "ms word"], "soft_skills": ["independent", "attentive to details"], "languages_combined": [{"language": "english", "language_level": ["good command", "good"]}, {"language": "chinese", "language_level": ["good command", "good", "good"]}, {"language": "mandarin", "language_level": ["good command", "good"]}]}, "experience_required": {"duration": ["2-3 years"], "field": ["secretarial"]}}, {"job_id": "100003009033136", "location_code": "hk", "company": "Global Vision CPA Limited", "job_title": "Company Secretarial", "description": "Job Highlights\n\u00a0We are professional firm company secretarial dept\n\u00a0We offer medical insurance\nJob Description\n\nOur related company, KV Pro Services Limited, now looks for full time candidate for our Company Secretarial position with the following job duties:\n\nAssist in full range company secretarial and administrative duties for the private companies and associations;\nHandle filings and correspondences with the relevant regulatory and statutory authorities; and\nMaintain corporate records, filing documents and draft documents for clients.\n\n\u00a0Successful candidates will be:\n\nDiploma or above;\nGood command in spoken and written English and Cantonese, fair in Putonghua;\nSelf-motivated, well-organized and detail-oriented;\nGood analytical and problem-solving skills;\nGood at reading and following rules and regulations;\nProficient in Microsoft Office and Chinese Word Processing;\nStrong interpersonal skills;\nAble to work under pressure and multi-task;\nNo experiences are required, and welcome fresh graduate\n\nOur office is located in Tsim Sha Tsui. Successful candidates will work in our company secretarial department under the supervision of manager to carry out the said duties.\n\nOur Benefit:\n\nExamination and study leave for recognized examinations;\n12 days annual leave\nMedical insurance.\n\nIf you are interested, please send in your CV and cover letter with your expected salary.", "employment_types": ["Full Time", "Permanent"], "selling_points": [], "locations": ["Tsim Sha Tsui"], "categories": ["Professional Services", "Company Secretary"], "post_time": "2022-01-08T10:39:10Z", "salary": {"currency": null, "max": null, "min": null, "period": "monthly", "term": null}, "salary_visible": false, "title_keywords": [], "responsibilities": [], "requirements": {"degrees": [], "majors": [], "languages": [], "language_level": [], "hard_skills": [], "soft_skills": [], "languages_combined": []}, "experience_required": {"duration": [], "field": []}}, {"job_id": "100003009041964", "location_code": "hk", "company": "C & W (CPA) Limited", "job_title": "Junior Audit/Senior Audit/ Audit Associate (5 Days Work)", "description": "Requirement:\n\nHigh Diploma/University Graduate (With Accounting Major)\nMin. 1 year related working experience\nProficient in P.C. Applications & Chinese Typing\nImmediate available is highly preferred\nWe Offer:\u00a0\n\n5-Days Work\n12 Days Annual Leave\nBirthday Leave, Paid Study Leave & Exam Leave\nMedical Insurance\n\nPlease send your resume and expected salary by clicking apply now button.", "employment_types": ["Full Time", "Permanent", "Temporary", "Contract"], "selling_points": [], "locations": ["Tsuen Wan Area"], "categories": ["Accounting", "Accounting Clerk / Supervisor", "Audit", "Professional Services", "Company Secretary"], "post_time": "2022-01-12T04:58:33Z", "salary": {"currency": null, "max": null, "min": null, "period": "monthly", "term": null}, "salary_visible": false, "title_keywords": ["associate", "junior"], "responsibilities": [], "requirements": {"degrees": ["high diploma", "university graduate"], "majors": ["accounting"], "languages": ["chinese"], "language_level": [], "hard_skills": ["c", "typing"], "soft_skills": [], "languages_combined": [{"language": "chinese", "language_level": []}]}, "experience_required": {"duration": ["1 year"], "field": ["related"]}}, {"job_id": "100003009031068", "location_code": "hk", "company": "Crazy Sports Group Limited", "job_title": "Company Secretary Assistant Manager", "description": "Crazy Sports Group Limited\n\nJob Description\n\nKey responsibilities:\n\nResponsible for full spectrum of company secretarial services to Hong Kong and offshore companies\nArrange and organize board, committees and shareholders' meetings as well as prepare papers and minutes accordingly\nLiaise with other professional advisors and various government authorities / regulations regarding company secretarial matters\nTo ensure compliance with all relevant statutory and regulatory matters such as Listing Rules, Companies Ordinance, Business Registration Ordinance and other relevant regulations\nMaintain and update the statutory records as required under the Companies Ordinance\u00a0and Bermuda laws\nHandle ac hoc assignments\u00a0\nMinimum requirements:\u00a0\n\nDegree or above in corporate governance, business administration, or related disciplines\nMember of HKICS is an advantage\n3+ years of company secretarial experience gained from sizeable companies or professional firms\nMature, proactive, self-motivated and well organized\nHands-on experience in group portfolio\nGood command of written and spoken English and Chinese, including Mandarin\n\nInterested parties please send your full resume with expected salary by clicking \"apply now\"", "employment_types": ["Full Time"], "selling_points": [], "locations": ["Causeway Bay"], "categories": ["Professional Services", "Company Secretary"], "post_time": "2022-01-07T08:54:54Z", "salary": {"currency": null, "max": null, "min": null, "period": "monthly", "term": null}, "salary_visible": false, "title_keywords": ["company secretary", "assistant manager"], "responsibilities": ["regulations", "ensure compliance", "maintain", "liaise with", "listing"], "requirements": {"degrees": ["degree or above"], "majors": ["related disciplines", "business administration"], "languages": ["english", "chinese", "mandarin"], "language_level": ["good command"], "hard_skills": [], "soft_skills": ["self-motivated", "well organized", "mature", "hands-on", "proactive"], "languages_combined": [{"language": "english", "language_level": ["good command"]}, {"language": "chinese", "language_level": ["good command"]}, {"language": "mandarin", "language_level": ["good command"]}]}, "experience_required": {"duration": ["3+ years"], "field": ["secretarial"]}}, {"job_id": "100003009030941", "location_code": "hk", "company": "Wanda Source Limited", "job_title": "Company Secretary", "description": "Job description\n\nHandle company secretarial works for HK/PRC and offshore corporations;\nMaintain and update statutory and relevant records;\nProvide general support to the team;\nOther duties and ad hoc assignments as required.\nRequirements\n\nDegree in Business Administration, Company Secretarial studies or equivalent;\nAssociate member of HKICS / ICSA;\n2-3 years company secretarial hands-on experience is preferred;\nKnowledge in CSA will be an advantage;\nSelf-motivated, mature and responsible;\nA good team player, well organized with ability to work under pressure\u00a0and independently;\nGood command in written English and Chinese, and in spoken English, Cantonese and Mandarin..\nInterested parties please send full resume with current and expected salary by clicking the \"APPLY NOW\" button below.\nAll information provided by applicants will be treated in strict confidence and used only for recruitment purposes. Applicants may be considered for other suitable positions by our Company & the subsidiaries over not more than 6 months, after which their personal data will be destroyed.", "employment_types": ["Full Time", "Permanent"], "selling_points": [], "locations": ["Ngau Tau Kok"], "categories": ["Professional Services", "Company Secretary", "Legal & Compliance"], "post_time": "2022-01-07T19:20:22Z", "salary": {"currency": null, "max": null, "min": null, "period": "monthly", "term": null}, "salary_visible": false, "title_keywords": ["company secretary"], "responsibilities": ["general support", "maintain", "ad hoc assignments", "other duties"], "requirements": {"degrees": ["degree"], "majors": ["business administration"], "languages": ["cantonese", "english", "chinese", "mandarin"], "language_level": ["good command"], "hard_skills": [], "soft_skills": ["good team player", "self-motivated", "independently", "responsible", "well organized", "mature", "hands-on", "work under pressure"], "languages_combined": [{"language": "cantonese", "language_level": ["good command"]}, {"language": "english", "language_level": ["good command"]}, {"language": "chinese", "language_level": ["good command"]}, {"language": "mandarin", "language_level": ["good command"]}]}, "experience_required": {"duration": ["2-3 years"], "field": ["secretarial"]}}, {"job_id": "100003009036775", "location_code": "hk", "company": "Austen Capital Partners Holding Limited", "job_title": "Executive Assistant", "description": "Responsibilities\n\nProvide personal assistance to CEO as required\nAssist with record keeping, payment and accounting services\nManage\u00a0correspondence and\u00a0schedule appointments\n\nRequirements\n\nHard-working\nPrior experience is an advantage but not a necessity\nManagement accounting knowledge and experience required\nExcellent in Microsoft Office (MS Word, Excel, PowerPoint)\nWell-organized, self-motivated and able to work independently\nExcellent command of verbal and written English and Chinese (Mandarin a plus)\n\nJob Offer\n\nAttractive package", "employment_types": ["Full Time", "Part Time", "Permanent"], "selling_points": ["Oversee office administration", "Provide secretarial support", "Co-ordinate internal and external meetings"], "locations": ["Tsim Sha Tsui"], "categories": ["Admin & HR", "Personal / Executive Assistant", "Media & Advertising", "Account Servicing", "Professional Services", "Company Secretary"], "post_time": "2022-01-10T14:03:10Z", "salary": {"currency": null, "max": null, "min": null, "period": "monthly", "term": null}, "salary_visible": false, "title_keywords": ["executive assistant"], "responsibilities": ["payment", "schedule"], "requirements": {"degrees": [], "majors": [], "languages": ["english", "chinese", "mandarin"], "language_level": ["excellent"], "hard_skills": ["excel", "plus", "microsoft office", "powerpoint", "ms word"], "soft_skills": ["self-motivated", "hard-working", "well-organized", "work independently"], "languages_combined": [{"language": "english", "language_level": ["excellent"]}, {"language": "chinese", "language_level": ["excellent"]}, {"language": "mandarin", "language_level": ["excellent"]}]}, "experience_required": {"duration": [], "field": ["management accounting"]}}, {"job_id": "100003009030424", "location_code": "hk", "company": "Hang Lung Properties Limited", "job_title": "Assistant Manager / Senior Officer \u2013 Company Secretarial", "description": "Responsibilities\u00a0\n\nProvide assistance in handling a full spectrum of company secretarial duties for a listed group, its subsidiaries and joint ventures, including drafting announcements and circulars; organizing meetings of the boards, committees and shareholders; preparing board resolutions and ensuring compliance with all relevant statutory and regulatory matters\nMaintain and update company secretarial records and registers and statutory filings\nProvide assistance in reviewing company secretarial related documents\nManage share options related matters\nAttend departmental administrative matters wherever necessary\n\nRequirements\n\nDegree holder in relevant disciplines and associate member or finalist of HKCGI\nMinimum 8 years\u2019 working experience in company secretarial field in sizeable listed companies\nGood communication skills, meticulous, well-organized, self-motivated with strong sense of responsibility and able to work independently\nAdvanced knowledge of MS office applications\nProficient in written and spoken Chinese and English, Mandarin is preferred\nLess experience will\u00a0be\u00a0considered as\u00a0Senior Officer\n\n\nWe offer an attractive remuneration package and excellent prospects for career advancement to the right candidate. Please send detailed resume to Human Resources Department by clicking \u201cApply Now\u201d button. For more information about our Company, please visit our website: http://www.hanglung.com.\n\nWe are an equal opportunity employer and welcome applications from all qualified candidates. Personal data collected will be treated in strict confidence and be used solely for recruitment purposes within the Hang Lung Group of companies. Applicants who do not hear from us within 8 weeks from the date of application may consider their applications unsuccessful and their information will be destroyed within 12 months of receipt.", "employment_types": ["Full Time", "Permanent"], "selling_points": ["Full spectrum of company secretarial duties", "Update Com Sec records and statutory filings", "8 years + relevant working experience"], "locations": ["Central"], "categories": ["Professional Services", "Company Secretary", "Legal & Compliance"], "post_time": "2022-01-07T07:27:43Z", "salary": {"currency": null, "max": null, "min": null, "period": null, "term": null}, "salary_visible": false, "title_keywords": ["assistant manager", "senior officer"], "responsibilities": ["maintain", "compliance", "provide assistance", "related documents"], "requirements": {"degrees": ["degree holder"], "majors": [], "languages": ["english", "chinese", "mandarin"], "language_level": ["proficient"], "hard_skills": ["ms office"], "soft_skills": ["communication skills", "self-motivated", "meticulous", "work independently", "advanced", "sense of responsibility", "well-organized"], "languages_combined": [{"language": "english", "language_level": ["proficient"]}, {"language": "chinese", "language_level": ["proficient"]}, {"language": "mandarin", "language_level": ["proficient"]}]}, "experience_required": {"duration": ["minimum 8 years"], "field": ["secretarial"]}}, {"job_id": "100003009032646", "location_code": "hk", "company": "The Wharf Group", "job_title": "Company Secretarial Assistant (Mainland Business)", "description": "Responsibilities:\n\nAssist in handling company secretarial duties and related work for Mainland business, for companies and subsidiaries registered in HK and PRC.\n\nRequirements:\n\n\nTertiary educated and a student member of HKICG preferred\n1-2 years\u2019 working experience, with exposure in handling company secretarial duties highly preferred but not essential. Fresh graduate also welcome.\nDetail-minded, meticulous, well-organized and self-motived\nGood command of written and spoken English & Chinese, including Putonghua\n\nWe work 5 days per week.\n\nInterested parties, please click \"APPLY NOW\" and attach with your application letter and full resume.\n\n\nFor further information of the Wharf Group, please visit our website: www.wharfholdings.com\u00a0", "employment_types": ["Full Time", "Permanent"], "selling_points": [], "locations": ["Tsim Sha Tsui"], "categories": ["Professional Services", "Company Secretary", "Legal & Compliance"], "post_time": "2022-01-07T19:21:15Z", "salary": {"currency": null, "max": null, "min": null, "period": null, "term": null}, "salary_visible": false, "title_keywords": ["company secretarial assistant"], "responsibilities": [], "requirements": {"degrees": ["fresh graduate"], "majors": [], "languages": ["putonghua", "english", "chinese"], "language_level": ["good command"], "hard_skills": [], "soft_skills": ["detail-minded", "meticulous", "well-organized"], "languages_combined": [{"language": "putonghua", "language_level": ["good command"]}, {"language": "english", "language_level": ["good command"]}, {"language": "chinese", "language_level": ["good command"]}]}, "experience_required": {"duration": ["1-2 years"], "field": ["secretarial"]}}, {"job_id": "100003009033044", "location_code": "hk", "company": "Sovereign Trust (Hong Kong) Limited", "job_title": "Corporate Services Manager", "description": "JOB DESCRIPTION for CORPORATE SERVICES MANAGER / ASSISTANT MANAGER\n\nJob title: \u00a0\u00a0\u00a0\u00a0\u00a0\u00a0\u00a0\u00a0\u00a0\u00a0\u00a0\u00a0\u00a0\u00a0\u00a0\u00a0\u00a0\u00a0\u00a0\u00a0\u00a0\u00a0\u00a0\u00a0\u00a0\u00a0\u00a0\u00a0\u00a0\u00a0 Corporate Services Manager / Assistant Manager\n\nDepartment: \u00a0\u00a0\u00a0\u00a0\u00a0\u00a0\u00a0\u00a0\u00a0\u00a0\u00a0\u00a0\u00a0\u00a0\u00a0\u00a0\u00a0\u00a0\u00a0\u00a0\u00a0\u00a0 Corporate Services Team\n\nReporting to: \u00a0\u00a0\u00a0\u00a0\u00a0\u00a0\u00a0\u00a0\u00a0\u00a0\u00a0\u00a0\u00a0\u00a0\u00a0\u00a0\u00a0\u00a0\u00a0\u00a0\u00a0\u00a0 Head of Corporate Services\n\nBackground to Sovereign\n\nSovereign Trust (Hong Kong) Limited is the Hong Kong TCSP licenced subsidiary of The Sovereign Group. See http://www.SovereignGroup.com. The Group provides a wide range of company formation, company management, trustee structuring services from 26 offices around the world.\n\nWe offer a competitive salary, excellent prospects and career development for the right candidate and also provide excellent secondary employment benefits.\n\nMain duties will be to:\n\n-\u00a0\u00a0\u00a0\u00a0\u00a0\u00a0\u00a0\u00a0\u00a0\u00a0 provide full spectrum of company secretarial services, corporate governance and compliance functions to companies for Hong Kong and Offshore jurisdictions (including listed/private companies)\n\n-\u00a0\u00a0\u00a0\u00a0\u00a0\u00a0\u00a0\u00a0\u00a0\u00a0 organize board meetings, committee and shareholders\u2019 meetings\n\n-\u00a0\u00a0\u00a0\u00a0\u00a0\u00a0\u00a0\u00a0\u00a0\u00a0 draft / review the announcements, circulars and quarterly / annual / interim reports\n\n-\u00a0\u00a0\u00a0\u00a0\u00a0\u00a0\u00a0\u00a0\u00a0\u00a0 handle wide variety of corporate secretarial transactions in corporate and business projects\n\nensure all companies\u2019 records and statutory registers are properly maintained and updated\n\n-\u00a0\u00a0\u00a0\u00a0\u00a0\u00a0\u00a0\u00a0\u00a0\u00a0 liaise with colleagues located at different offices worldwide with regards to administration, incorporation and compliancematters of companies\n\n-\u00a0\u00a0\u00a0\u00a0\u00a0\u00a0\u00a0\u00a0\u00a0\u00a0 Managing client expectations and providing excellent standard of customer service\n\n-\u00a0\u00a0\u00a0\u00a0\u00a0\u00a0\u00a0\u00a0\u00a0\u00a0 Be the first point of contact for clients and related parties of their companies\n\n-\u00a0\u00a0\u00a0\u00a0\u00a0\u00a0\u00a0\u00a0\u00a0\u00a0 Other ad hoc projects as assigned by the immediate supervisor\n\nRequirements:\n\n-\u00a0\u00a0\u00a0\u00a0\u00a0\u00a0\u00a0\u00a0\u00a0 Bachelor degree or above\n\n-\u00a0\u00a0\u00a0\u00a0\u00a0\u00a0\u00a0\u00a0\u00a0 HKCGI / HKICS graduate and/or minimum 4 years hands on company secretarial experience\n\n-\u00a0\u00a0\u00a0\u00a0\u00a0\u00a0\u00a0\u00a0\u00a0 Solid knowledge in Listing Rules, Companies Ordinance, compliance procedures is a must\n\n-\u00a0\u00a0\u00a0\u00a0\u00a0\u00a0\u00a0\u00a0\u00a0 Excellent command of written and spoken English and Chinese (Cantonese and Mandarin)\n\n-\u00a0\u00a0\u00a0\u00a0\u00a0\u00a0\u00a0\u00a0\u00a0 Quality driven, self-motivated, meticulous, hardworking\n\n-\u00a0\u00a0\u00a0\u00a0\u00a0\u00a0\u00a0\u00a0\u00a0 Good analytical and problem-solving skills\n\n-\u00a0\u00a0\u00a0\u00a0\u00a0\u00a0\u00a0\u00a0\u00a0 Capable of working independently, with a strong sense of responsibility\n\n-\u00a0\u00a0\u00a0\u00a0\u00a0\u00a0\u00a0\u00a0\u00a0 Team player with positive attitude\n\n-\u00a0\u00a0\u00a0\u00a0\u00a0\u00a0\u00a0\u00a0\u00a0 Well organized and detail orientated\n\n-\u00a0\u00a0\u00a0\u00a0\u00a0\u00a0\u00a0\u00a0\u00a0 Proactiveand have the ability to multi-task\n\nInterested candidates should send an email explaining their suitability for the position and stating their present and required salary full resume/CV to email address provided.\u00a0\u00a0We regret that only shortlisted candidates will be notified.\u00a0", "employment_types": ["Full Time", "Permanent"], "selling_points": ["Experienced company secretary", "TCSP licenced company", "Private and listed clients"], "locations": ["Sheung Wan"], "categories": ["Professional Services", "Company Secretary"], "post_time": "2022-01-08T06:37:00Z", "salary": {"currency": null, "max": null, "min": null, "period": "monthly", "term": null}, "salary_visible": false, "title_keywords": ["manager"], "responsibilities": ["business projects", "review", "compliance", "transactions", "customer service", "reports", "contact", "ad hoc projects", "liaise with", "administration"], "requirements": {"degrees": ["degree or above", "bachelor"], "majors": [], "languages": ["cantonese", "english", "chinese", "mandarin"], "language_level": ["excellent"], "hard_skills": ["problem-solving skills", "companies ordinance"], "soft_skills": ["meticulous", "self-motivated", "independently", "multi-task", "capable", "sense of responsibility", "well organized", "positive attitude", "hands on", "detail orientated", "problem-solving skills", "team player", "driven", "hardworking"], "languages_combined": [{"language": "cantonese", "language_level": ["excellent"]}, {"language": "english", "language_level": ["excellent"]}, {"language": "chinese", "language_level": ["excellent"]}, {"language": "mandarin", "language_level": ["excellent"]}]}, "experience_required": {"duration": ["minimum 4 years"], "field": ["secretarial"]}}, {"job_id": "100003009031398", "location_code": "hk", "company": "Besway Asia Limited", "job_title": "Senior Company Secretarial Officer", "description": "Our client is a listed property company in HK now looking for a outstanding to join\u00a0them:\n\u00a0\n\nJob Duties:\n\nPerform company secretarial duties for the listed company and its subsidiaries\nDraft and prepare annual and interim reports, announcements and circulars\nOrganize meetings for the board, committees and shareholders, and prepare relevant board papers, minutes and resolutions\nMaintain and update statutory records and filings in compliance with Companies Ordinance, HK Listing Rules and other overseas statutory requirements\nParticipate in ad hoc projects and tasks assigned from time to time\n\nRequirements:\n\nDegree holder, preferably with member or graduate of HKICS / ICSA or equivalent\nMinimum of 4 years relevant company secretarial experience in listed companies;\nGood command of English and Chinese;\nCompetent PC skills in MS Word, Excel & Chinese word processing;\nImmediate available is highly preferred;\nCandidate with more experience will consider as Assistant Manager.", "employment_types": ["Full Time"], "selling_points": ["4 Years Experience", "Listed Property Company", "Career advancement"], "locations": ["Not Specified"], "categories": ["Professional Services", "Company Secretary", "Legal & Compliance"], "post_time": "2022-01-07T09:17:54Z", "salary": {"currency": null, "max": null, "min": null, "period": "monthly", "term": null}, "salary_visible": false, "title_keywords": ["company secretarial officer"], "responsibilities": ["compliance", "statutory requirements", "maintain", "reports", "ad hoc projects", "listing"], "requirements": {"degrees": ["degree holder"], "majors": [], "languages": ["english", "chinese"], "language_level": ["good command"], "hard_skills": ["excel", "pc skills", "chinese word processing", "ms word"], "soft_skills": ["competent"], "languages_combined": [{"language": "english", "language_level": ["good command"]}, {"language": "chinese", "language_level": ["good command"]}]}, "experience_required": {"duration": ["minimum of 4 years"], "field": ["secretarial"]}}, {"job_id": "100003009044679", "location_code": "hk", "company": "Alpadis Trust (HK) Limited", "job_title": "Senior Accountant / Accountant", "description": "JOB RESPONSIBILITY\n\nPerform full set of clients\u2019 account in different nature of business\n\nPrepare periodic management accounts and financial reports to a portfolio of clients\n\nLiaise with client and back office in producing financial statements\n\nLiaise with external auditors to prepare statutory accounts and lodge the tax return on time\n\nPrepare financial statements according to the applicable accounting standards for corporate client\n\nCoordination with corporate service team\n\nLiaison with auditor\n\nResponsible for issuing invoices\n\nPerform ad hoc assignments as required\u00a0\n\nJOB REQUIREMENTS\n\nDiploma or above qualification in Finance / Accounting, with HKCPA or similar qualification is preferred\n\nKnowledge in Hong Kong tax regulations and Tax Return Filing\n\nA minimum of 5 years\u2019 experience as an accountant in professional service firm\n\nStable, good interpersonal and communication skill and a good team player\n\nAdhere to high standards of integrity and efficiency\n\nWell-organized, strong analytical skills, logical thinking and with high attention to details\n\nExperience in Letter of Credit is required\n\nSelf-motivate, able to work under pressure and meet tight deadlines\n\nGood command of both spoken and written English and Chinese.\n\nPC skills including Microsoft Word, Excel, PowerPoint\n\nIMMEDIATE availability preferred\n\nBENEFITS:\n\n5-days work, MPF, Medical Plan, 20 days annual leave\n\nAttractive remuneration package with study allowance\n\nWorking location in Wanchai\n\nShould you require further information about this position, please contact Ms\u00a0Yao at 2639 3600.", "employment_types": ["Full Time"], "selling_points": [], "locations": ["Wan Chai"], "categories": ["Accounting", "Accountant", "Professional Services", "Company Secretary"], "post_time": "2022-01-13T05:41:47Z", "salary": {"currency": null, "max": null, "min": null, "period": "monthly", "term": null}, "salary_visible": false, "title_keywords": ["accountant", "senior accountant"], "responsibilities": ["tax", "management", "financial reports", "invoices", "coordination with", "back office", "financial statements", "liaise with client", "ad hoc assignments", "liaise with", "external auditors"], "requirements": {"degrees": ["diploma or above"], "majors": ["finance", "accounting"], "languages": ["english", "chinese"], "language_level": ["good command"], "hard_skills": ["excel", "microsoft word", "powerpoint", "analytical skills", "pc skills"], "soft_skills": ["good team player", "meet tight deadlines", "communication skill", "integrity", "well-organized", "analytical skills", "attention to details", "stable", "interpersonal", "work under pressure"], "languages_combined": [{"language": "english", "language_level": ["good command"]}, {"language": "chinese", "language_level": ["good command"]}]}, "experience_required": {"duration": ["minimum of 5 years"], "field": []}}, {"job_id": "100003009030790", "location_code": "hk", "company": "Intertrust Hong Kong Limited", "job_title": "Company Secretarial Officer / Assistant Manager", "description": "The Position\n\nBy being the best at what we do, we empower businesses of all sizes, wherever they are in the world, to navigate the complexity of ever-changing rules and regulations.\u00a0We support them to grow and accelerate the possible.\u00a0We partner with them to transform and unleash the potential of their operating model by driving the efficiency, technology and insight needed to achieve a competitive edge.\u00a0We deliver the power they need to succeed.\u00a0No matter the size of client\u2019s business, we always take a personal approach and have a long-term perspective on our relationships. We provide formation, domiciliation, accounting & reporting, legal and regulatory compliance services. You will be a key member in our team responsible to provide professional company secretarial services to our clients with core areas of responsibility.\n\nYour Responsibilities\u00a0\n\nProvide advisory service to clients on company secretarial matters\nProactively seek new ideas and innovative solutions to support clients, seek opportunities for operational improvement to enhance efficiency\nHandle a full spectrum of company secretarial matters for a portfolio of HK and offshore companies professionally includingCoach and provide guidance to junior team members to empower their development\nincorporation and deregistration of companies in different jurisdictions\npreparation of minutes, resolutions, annual return, announcements, etc.\nmanaging and organizing the portfolio statutory filings\nreviewing agreements and contracts\nopening of bank accounts\nchanging in shareholdings and directorships\nCoordinate compliance and client acceptance\nOther ad hoc projects\nYour Profile\nDegree or diploma holder in business administration/corporate governance or a related discipline\nMinimum of 4 years\u2019 related experience in a professional firm or law firm\nQualified professional member or student member of ICSA/HKICS\nExcellent written and spoken in English and Chinese, conversational Mandarin will be an advantage\nIndependent, meticulous, pro-active, attentive to details, self-motivated, keen to learn\nAble to adapt in new challenges and with excellent communication skills\nWhat we offer you\nWorking at Intertrust means entering a dynamic, international and growth-oriented company. We provide you with outstanding opportunities for your professional and personal development through our local and global Intertrust Academies. Our International Mobility program enables talented employees to gain working experience abroad. We offer a competitive salary and benefits, commensurate with your qualifications and experience.\nApply now\nInterested? We\u2019d love to hear from you! Please apply directly via our career page with your CV and optional Cover Letter. For more information about this position, please contact\u00a0us at 2901 2182 for more information.", "employment_types": ["Full Time", "Permanent"], "selling_points": ["Career Exposure in Multinational Company", "Caring company and CBD working location", "Flexible working arrangement, 17+AL & others"], "locations": ["Wan Chai"], "categories": ["Professional Services", "Company Secretary", "Legal & Compliance"], "post_time": "2022-01-07T08:20:05Z", "salary": {"currency": null, "max": null, "min": null, "period": "monthly", "term": null}, "salary_visible": false, "title_keywords": ["assistant manager", "company secretarial officer"], "responsibilities": ["regulations"], "requirements": {"degrees": [], "majors": [], "languages": [], "language_level": [], "hard_skills": ["no"], "soft_skills": [], "languages_combined": []}, "experience_required": {"duration": [], "field": []}}, {"job_id": "100003009030016", "location_code": "hk", "company": "Tricor Services Limited", "job_title": "Company Secretarial Associate/ Senior Associate (Fresh graduate are welcome)", "description": "We are looking for talent from all disciplines to join our Corporate Services Division to work with our experienced professionals and to build a promising career.\n\nWhat the job role is:\n\n\nAssist in a full range of company secretarial matters for clients\nResponsible for statutory compliance duties including arranging for Annual Return and maintenance of corporate records\nHandle company incorporation with different jurisdictions\nAssist with compliance documentation collection and working with the compliance team\nProvide administrative support to team includes data entry, filing, and other administration duties\n\nWho we are looking for:\n\nDegree or above in corporate governance, business administration, or related disciplines\nMinimum 1 year of relevant working experience is preferred, but fresh graduates are also welcome\nStudent Membership of HKICS/ ICSA is an advantage\nAspired\u00a0to develop career in company secretarial field and prepared to sit for professional examinations\nSelf-motivated, well-organized and detail-oriented\nExcellent command of spoken and written English with fluent Mandarin\nGood analytical and problem-solving skills\nProficient in reading and interpreting rules and regulations is an added advantage\nWell versed in MS applications (PowerPoint, Excel, Word)\nCandidate will be considered for a position commensurate with experience\n\nWe offer to successful candidates 15-day annual leave, birthday leave, 5-day work, study/examination leave, qualifying premium upon completion of HKICS examinations, excellent job exposure and career prospects.\n\n\u00a0Applicants should send their full C.V., indicating the below to Human Resources Department by clicking \"Apply Now\"\n\n(1)\u00a0 The result of IELTS/ TOEFL, if any\n(2)\u00a0 The result of English Language & Chinese Language of both HKDSE/HKCEE & HKALE, (or equivalent\n(3)\u00a0 Expected salary\n\nPlease quote the ref:\u00a0\"Company Secretarial Associate/ Senior Associate\"\u00a0on your application.\n\nPersonal data provided by job applicants will be used strictly in accordance with the employer's personal data policies, a copy of which will be provided immediately upon request.", "employment_types": ["Full Time", "Permanent"], "selling_points": ["Company Secretarial function", "5 days work, Study leave, Exam leave, QP, training", "Excellent command of spoken and written English"], "locations": ["Ngau Tau Kok"], "categories": ["Professional Services", "Company Secretary", "Legal & Compliance", "Others", "Student / Fresh Graduate / No Experience"], "post_time": "2022-01-07T06:36:00Z", "salary": {"currency": null, "max": null, "min": null, "period": "monthly", "term": null}, "salary_visible": false, "title_keywords": ["senior associate", "associate"], "responsibilities": ["compliance documentation", "regulations", "maintenance", "data entry", "statutory compliance", "policies", "compliance", "develop", "provide administrative support", "personal data", "administration"], "requirements": {"degrees": ["degree or above", "hkdse"], "majors": ["related disciplines", "business administration"], "languages": ["english", "chinese", "mandarin"], "language_level": ["excellent", "fluent"], "hard_skills": ["excel", "ms applications", "maintenance", "word", "powerpoint", "c", "documentation", "problem-solving skills"], "soft_skills": ["self-motivated", "responsible", "well-organized", "detail-oriented", "problem-solving skills"], "languages_combined": [{"language": "english", "language_level": ["excellent"]}, {"language": "chinese", "language_level": []}, {"language": "mandarin", "language_level": ["fluent", "excellent"]}]}, "experience_required": {"duration": ["minimum 1 year"], "field": ["relevant working experience"]}}, {"job_id": "100003009030862", "location_code": "hk", "company": "Onestart Group Ltd", "job_title": "Company Secretarial Officer / Assistant", "description": "Duties & Responsibilities\n\nHandling client\u2019s enquiry about our services, especially about company formation & maintenance, bank account opening, accounting and other compliance work\nCollaborate with business partners and bankers to provide one-stop business solutions to clients\nLiaise and co-ordinate with external and internal parties\nSupporting corporate transaction review, due diligence & follow-up\nManage a portfolio of clients for HK and offshore company and related services\nContact with our client for renewal and/or addition of ComSec, Accounting & Audit services by phone call.\nAd-hoc support to supervisor / team in meeting company business objectives\n\nRequirements\n\nDegree / Diploma holder in relevant disciplines.\n2- 3 years of relevant company secretarial experience or listed companies experience is an advantage)\nStudent Membership or Membership of ICSA / HKICS or ICSA finalist & proficiency in CSA application are definite assets\nMature, Independent, positive, good team player, able to work under tight timeline\nGood communication, strong customer service mindset and multi-tasking skills\nGood command in both written and spoken English, Cantonese & Mandarin\nProficient in Microsoft applications, such as Word, Excel and PowerPoint\nImmediate available is highly preferred\n\nWe offer career prospects, friendly work environment, competitive remuneration packages including a 5-day work week, bank holiday, group medical scheme and family leave to the right candidate.\u00a0\n\nInterested parties please send your\u00a0full resume with date of availability, current and expected salary\u00a0by JobsDB\u00a0to us.\n\nAll information provided by applicants will be used for recruitment related purposes only and will be treated in the strictest confidence by authorized personnel.\n\nFor\u00a0further information on our company, please visit our website: https://www.onestartoffices.com/", "employment_types": ["Full Time", "Permanent"], "selling_points": [], "locations": ["Lai Chi Kok"], "categories": ["Professional Services", "Business Consultancy", "Company Secretary", "Legal & Compliance"], "post_time": "2022-01-07T10:39:15Z", "salary": {"currency": null, "max": null, "min": null, "period": "monthly", "term": null}, "salary_visible": false, "title_keywords": ["company secretarial officer", "assistant"], "responsibilities": ["collaborate with", "liaise", "due diligence", "ad-hoc", "maintenance", "co-ordinate with", "account opening", "compliance", "review", "audit", "contact", "internal parties"], "requirements": {"degrees": ["diploma holder", "degree"], "majors": [], "languages": ["cantonese", "english", "mandarin"], "language_level": ["good command"], "hard_skills": ["excel", "microsoft applications", "word", "powerpoint", "scheme"], "soft_skills": ["good team player", "independent", "mature", "communication", "customer service", "friendly", "multi-tasking skills", "positive"], "languages_combined": [{"language": "cantonese", "language_level": ["good command"]}, {"language": "english", "language_level": ["good command"]}, {"language": "mandarin", "language_level": ["good command"]}]}, "experience_required": {"duration": ["2- 3 years"], "field": ["secretarial"]}}, {"job_id": "100003009032044", "location_code": "hk", "company": "SWCS Corporate Services Group (Hong Kong) Limited", "job_title": "Company Secretarial/ Corporate Governance Professionals (Part-time /Temporary /4-6 mths contract)", "description": "KEY RESPONSIBILITIES\n\nAssist in handle full spectrum of company secretarial matters for listed or private companies\nHands on working experience in listing company secretarial and corporate governance practice under the Hong Kong new Companies Ordinance, Company Acts in the major offshore jurisdictions and the Listing Rules of Hong Kong Stock Exchange (\"HKEx Listing Rules\")\nAssist in reviewing / handling various transactions under the HKEx Listing Rules and Securities & Futures Ordinance (\"SFO\")\nPerform ad hoc duties as assigned\nREQUIREMENTS\n\nDegree-holder, preferably in corporate administration, law, accounting or company secretarial studies\nFinalist /\u00a0\u00a0Associate member of HKCGI / CGI / HKICPA or equivalents\nAt least 4 years of relevant listed company secretarial or corporate governance working experiences in professional firm, CPA firm, law firm or listed company\u00a0\nSound knowledge in Listing Rules of Hong Kong Stock Exchange, Securities & Futures Ordinance, HK New Companies Ordinances\nFluency in both English and Chinese (including Putonghua)\u00a0\nAble to work independently on daily correspondence and assist in handling clients with excellent interpersonal and communication skills\nPossess multi-tasking ability, pleasant, detail-orientated, well-organised and strong sense of responsibility\nProficiency in MS Word, Excel and PowerPoint and Chinese Words input\n\nWe offer attractive salary and benefits to successful candidates. Interested parties please click Apply Now.\u00a0 Applicants who are not contacted within six weeks may consider their application unsuccessful. Personal data collected will be used for recruitment-related purpose only.", "employment_types": ["Full Time", "Permanent"], "selling_points": ["Relevant listed company secretarial experience", "Working period: 2nd Quarter of 2022 &/or extend", "Detail-orientated, well-organised and strong sense"], "locations": ["Wan Chai"], "categories": ["Admin & HR", "Personal / Executive Assistant", "Secretary", "Professional Services", "Company Secretary"], "post_time": "2022-01-07T10:15:23Z", "salary": {"currency": null, "max": null, "min": null, "period": "monthly", "term": null}, "salary_visible": false, "title_keywords": [], "responsibilities": ["ad hoc duties", "listing", "transactions"], "requirements": {"degrees": ["degree"], "majors": ["accounting", "law"], "languages": ["putonghua", "english", "chinese"], "language_level": ["fluency", "proficiency"], "hard_skills": ["excel", "words", "ms word", "powerpoint", "cpa", "hkicpa", "exchange"], "soft_skills": ["communication skills", "work independently", "sense of responsibility", "pleasant", "multi-tasking", "well-organised", "interpersonal"], "languages_combined": [{"language": "putonghua", "language_level": []}, {"language": "english", "language_level": ["fluency"]}, {"language": "chinese", "language_level": ["fluency", "proficiency"]}]}, "experience_required": {"duration": ["at least 4 years"], "field": ["secretarial", "cpa firm"]}}, {"job_id": "100003009032834", "location_code": "hk", "company": "TMF Hong Kong Limited", "job_title": "Company Secretarial Senior Executive / Assistant Manager", "description": "Responsibilities\n\n1. Senior Executive\u00a0\n\nAssist the Manager / Senior Manager in providing company secretarial services to a range of non-listed client companies.\nAssist in handling full set of company secretarial documents\nCommunicate with clients under supervision\nMaintain statutory records for clients\u2019 companies\nUpdate and maintain records/information in ViewPoint\nHandle duties as assigned by supervisors\n2. Assistant Manager\n\nManage a portfolio of non-listed client companies by providing full set of corporate secretarial services;\nEnsure compliance with the Companies Ordinance and other regulatory and statutory requirements;\nMaintain good relationship with client;\nBuild up opportunities for additional services providing to existing clients;\nAssist in maintaining smooth operation of the team;\nSupervise and review subordinates\u2019 work;\nAssist the Manager to monitor & manage the productivity and effectiveness of the team.\n\nRequirements\n\nDegree holder with a minimum\u00a0of 2-3 years relevant experience gained in professional firm/ CPA firm/ law firm\nExperiences in liquidation process is added advantages.\u00a0\nGood knowledge of corporate secretarial law and familiar with Companies Ordinance, rules and regulations of regulatory bodies\nGood computer skills, experience/knowledge in Viewpoint system is an advantage\nGood command of both spoken and written English and Chinese, fluent in Putonghua is preferred\n\nWe offer competitive remuneration package including\n\n13-months salary + discretionary bonus\nProfessional membership sponsorship\nhybrid working arrangement & work life insurance\nStudy and examination leaves\nDental and medical coverage", "employment_types": ["Full Time"], "selling_points": ["Deliver CoSec services to our non-listed clients", "Hybrid working arrangement", "Professional development opportunities"], "locations": ["Causeway Bay"], "categories": ["Professional Services", "Company Secretary"], "post_time": "2022-01-08T00:08:29Z", "salary": {"currency": null, "max": null, "min": null, "period": "monthly", "term": null}, "salary_visible": false, "title_keywords": ["senior executive", "assistant manager"], "responsibilities": ["communicate with", "maintaining", "review", "monitor", "maintain good relationship", "ensure compliance", "statutory requirements", "maintain"], "requirements": {"degrees": ["degree holder"], "majors": ["law"], "languages": ["putonghua", "english", "chinese"], "language_level": ["good command", "fluent"], "hard_skills": ["cpa", "computer skills", "companies ordinance"], "soft_skills": [], "languages_combined": [{"language": "putonghua", "language_level": ["fluent", "good command"]}, {"language": "english", "language_level": ["good command"]}, {"language": "chinese", "language_level": ["good command"]}]}, "experience_required": {"duration": ["minimum of 2-3 years"], "field": ["cpa firm", "relevant experience"]}}, {"job_id": "100003009036651", "location_code": "hk", "company": "CT-INC. Limited", "job_title": "CEO Executive", "description": "Requirement:\n\nReporting to CEO and providing a full spectrum of business project and personal issues\nPrepare various correspondences, documents, presentations, and reports, etc.;\nTrack and drive key deliverable and follow up on outstanding executive action items;\nOrganize, prioritize and handle time-sensitive, confidential information and ensure appropriate action is taken;\nArrange meetings, calls, and conferences and ensure the readiness of all necessary information and relevant documents, etc.;\nPerform miscellaneous and ad hoc tasks as assigned.\n\nRequirement:\n\nDegree holder from reputable universities. Overseas graduates highly preferred\nRelevant PA experience in serving C-level gained with sizable companies or MNCs.\nWell organized, detail-minded, self-initiative, and hardworking\nExcellent command of languages; Cantonese, English, Putonghua\nWilling to travel\nCandidates meeting the above requirements but without PA experience are also welcome\n\n\n\nYou will enjoy Benefit\n\n\u00a05 Days Work\n\u00a014 days Annual Leave\n\u00a0 Double Pay\n\u00a0 \u00a0Performance Discretionary bonus\u00a0\u00a0\n\u00a0 \u00a0Medical Coverage\n\u00a0 \u00a0Friendly and collaborative work environment", "employment_types": ["Full Time", "Permanent"], "selling_points": ["Excellent English, Cantonese, fluent Mandarin", "Good writing and presentation skills", "Support Group CEO"], "locations": ["Lai Chi Kok"], "categories": ["Admin & HR", "Secretary", "Sales, CS & Business Devpt", "Business Development", "Professional Services", "Company Secretary"], "post_time": "2022-01-10T11:44:21Z", "salary": {"currency": null, "max": null, "min": null, "period": "monthly", "term": null}, "salary_visible": false, "title_keywords": ["executive", "ceo"], "responsibilities": ["reporting", "ad hoc tasks", "presentations", "conferences", "reports", "arrange meetings"], "requirements": {"degrees": ["degree holder"], "majors": [], "languages": ["cantonese", "putonghua", "english"], "language_level": [], "hard_skills": ["sizable companies", "c", "presentations"], "soft_skills": ["detail-minded", "well organized", "collaborative", "prioritize", "self-initiative", "friendly", "sensitive", "hardworking"], "languages_combined": [{"language": "cantonese", "language_level": []}, {"language": "putonghua", "language_level": []}, {"language": "english", "language_level": []}]}, "experience_required": {"duration": [], "field": []}}, {"job_id": "100003009024488", "location_code": "hk", "company": "Lai Sun Group", "job_title": "Company Secretarial Officer", "description": "Job Duties:\n\nPerform company secretarial duties for the listed company and its subsidiaries\nDraft and prepare annual and interim reports, announcements and circulars\nOrganize meetings for the board, committees and shareholders, and prepare relevant board papers, minutes and resolutions\nMaintain and update statutory records and filings in compliance with Companies Ordinance, HK Listing Rules and other overseas statutory requirements\nParticipate in ad hoc projects and tasks assigned from time to time\n\nRequirements:\n\nDegree holder, preferably with member or graduate of HKICS / ICSA or equivalent\nMinimum of 4 years relevant company secretarial experience in listed companies;\nPrior hands-on working experience in handling matters is a MUST;\nFamiliar with Companies Ordinance, HK Listing Rules, Securities and Futures Ordinance, and Takeovers Code\nGood command of English and Chinese\nCompetent PC skills in MS Word, Excel & Chinese word processing\nImmediate available is highly preferred\n\nWe offer attractive remuneration to successful candidates. To apply, please send your full resume stating date available, present and expected salary by mail to Group Human Resources & Administration Controller, Lai Sun Development Company Limited, 11/F Lai Sun Commercial Centre, 680 Cheung Sha Wan Road, Kowloon or click the button \"APPLY NOW\" shown below to send your application via email.\n\nWebsite:\u00a0www.laisun.com\n\nPersonal data provided in the employment applications will be treated in strict confidence and used only for recruitment purpose by the Lai Sun Group Companies. All unsuccessful applications will be destroyed upon completion of the process.", "employment_types": ["Full Time", "Permanent"], "selling_points": ["Prepare annual & interim reports & announcements", "Arrange board meetings & prepare minutes & papers", "Update statutory records and filings"], "locations": ["Lai Chi Kok"], "categories": ["Professional Services", "Company Secretary", "Legal & Compliance"], "post_time": "2022-01-06T01:17:22Z", "salary": {"currency": null, "max": null, "min": null, "period": "monthly", "term": null}, "salary_visible": false, "title_keywords": ["company secretarial officer"], "responsibilities": ["compliance", "statutory requirements", "maintain", "reports", "ad hoc projects", "listing"], "requirements": {"degrees": ["degree holder"], "majors": [], "languages": ["english", "chinese"], "language_level": ["good command"], "hard_skills": ["excel", "chinese word processing", "securities and futures ordinance", "code", "companies ordinance", "pc skills", "ms word"], "soft_skills": ["hands-on", "competent"], "languages_combined": [{"language": "english", "language_level": ["good command"]}, {"language": "chinese", "language_level": ["good command"]}]}, "experience_required": {"duration": ["minimum of 4 years"], "field": ["secretarial"]}}, {"job_id": "100003009033581", "location_code": "hk", "company": "Kee Wah Group Limited", "job_title": "Legal Administrative Executive (4-months Contract)", "description": "Responsibilities\n\nPro-read and draft legal agreements independently\nHandle trademarks portfolio and maintain records\nReview and handle simple legal documents under the supervision\nWork closely with business team to provide the necessary legal support\u00a0\u00a0\nPerform secretarial and administrative support to Senior Executive\nAssist on other ad-hoc legal-related duties and assignments as requested\n\nRequirements\n\nDiploma in Legal Studies / Company Secretary or above in Law or related disciplines\nMinimum 2 years of work experience in handling tenancy matters / legal field / company secretary / trademarks is preferred\nSelf-motivated, attention to detail with strong analytical skills and able to work under pressure\nGood command of written and spoken English, Mandarin and Chinese\nProficient in MS office applications\n\n\u00a0Please apply with detailed resume, stating current and expected salary and availability.\n(Personal data\u00a0relating to employment applications will be used for recruitment only)", "employment_types": ["Contract"], "selling_points": ["Excellent career development opportunity", "Leading brand and sizable company", "Competitive pay and benefits"], "locations": ["Lai Chi Kok"], "categories": ["Professional Services", "Business Consultancy", "Company Secretary", "Legal & Compliance"], "post_time": "2022-01-10T01:10:01Z", "salary": {"currency": null, "max": null, "min": null, "period": "monthly", "term": null}, "salary_visible": false, "title_keywords": ["administrative executive"], "responsibilities": ["ad-hoc", "review", "maintain", "administrative support"], "requirements": {"degrees": ["diploma"], "majors": ["related disciplines", "law"], "languages": ["english", "chinese", "mandarin"], "language_level": ["good command"], "hard_skills": ["ms office", "analytical skills"], "soft_skills": ["self-motivated", "detailed", "analytical skills", "attention to detail", "work under pressure"], "languages_combined": [{"language": "english", "language_level": ["good command"]}, {"language": "chinese", "language_level": ["good command"]}, {"language": "mandarin", "language_level": ["good command"]}]}, "experience_required": {"duration": ["minimum 2 years"], "field": ["legal"]}}, {"job_id": "100003009033045", "location_code": "hk", "company": "Sovereign Trust (Hong Kong) Limited", "job_title": "Corporate Services Executive", "description": "JOB DESCRIPTION for CORPORATE SERVICES EXECUTIVE\u00a0\u00a0\n\nJob title: \u00a0\u00a0\u00a0\u00a0\u00a0\u00a0\u00a0\u00a0\u00a0\u00a0\u00a0\u00a0\u00a0\u00a0\u00a0\u00a0\u00a0\u00a0\u00a0\u00a0\u00a0\u00a0\u00a0\u00a0\u00a0\u00a0\u00a0\u00a0\u00a0\u00a0 Corporate Services Executive\n\nDepartment: \u00a0\u00a0\u00a0\u00a0\u00a0\u00a0\u00a0\u00a0\u00a0\u00a0\u00a0\u00a0\u00a0\u00a0\u00a0\u00a0\u00a0\u00a0\u00a0\u00a0\u00a0\u00a0 Corporate Services Team\n\nReporting to: \u00a0\u00a0\u00a0\u00a0\u00a0\u00a0\u00a0\u00a0\u00a0\u00a0\u00a0\u00a0\u00a0\u00a0\u00a0\u00a0\u00a0\u00a0\u00a0\u00a0\u00a0\u00a0 Head of Corporate Services\n\nBackground to Sovereign\n\nSovereign Trust (Hong Kong) Limited is the Hong Kong TCSP licenced subsidiary of The Sovereign Group. See http://www.SovereignGroup.com. The Group provides a wide range of company formation, company management, trustee structuring services from 26 offices around the world.\n\nWe offer a competitive salary, excellent prospects and career development for the right candidate and also provide excellent secondary employment benefits.\n\nMain duties will be to:\n\n-\u00a0\u00a0\u00a0\u00a0\u00a0\u00a0\u00a0\u00a0\u00a0\u00a0 provide full spectrum of company secretarial services, corporate governance and compliance functions to companies\n\n-\u00a0\u00a0\u00a0\u00a0\u00a0\u00a0\u00a0\u00a0\u00a0\u00a0 organize board meetings, committee and shareholders\u2019 meetings\n\n-\u00a0\u00a0\u00a0\u00a0\u00a0\u00a0\u00a0\u00a0\u00a0\u00a0 handle wide variety of corporate secretarial transactions in corporate and business projects\n\n-\u00a0\u00a0\u00a0\u00a0\u00a0\u00a0\u00a0\u00a0\u00a0\u00a0 handle \u00a0a wide range of administrative duties\n\n-\u00a0\u00a0\u00a0\u00a0\u00a0\u00a0\u00a0\u00a0\u00a0\u00a0 answer daily enquiries from clients in relation to administrative and company secretarial compliance matters\n\n-\u00a0\u00a0\u00a0\u00a0\u00a0\u00a0\u00a0\u00a0\u00a0\u00a0 liaise with colleagues located at different offices worldwide with regards to administration, \u00a0incorporation and compliance \u00a0matters of companies\n\nRequirements:\n\n\n-\u00a0\u00a0\u00a0\u00a0\u00a0\u00a0\u00a0\u00a0\u00a0 Bachelor degree or above\n\n-\u00a0\u00a0\u00a0\u00a0\u00a0\u00a0\u00a0\u00a0\u00a0 HKICS student and/or minimum 3 years hands on company secretarial experience\n\n-\u00a0\u00a0\u00a0\u00a0\u00a0\u00a0\u00a0\u00a0\u00a0 familiar with Companies Ordinance, compliance procedures\n\n-\u00a0\u00a0\u00a0\u00a0\u00a0\u00a0\u00a0\u00a0\u00a0 Knowledge of Listing Rules, trust formation and accounting an advantage\n\n-\u00a0\u00a0\u00a0\u00a0\u00a0\u00a0\u00a0\u00a0\u00a0 Excellent command of written and spoken English and Chinese\n\n-\u00a0\u00a0\u00a0\u00a0\u00a0\u00a0\u00a0\u00a0\u00a0 Quality driven, self-motivated, meticulous, hardworking\n\n-\u00a0\u00a0\u00a0\u00a0\u00a0\u00a0\u00a0\u00a0\u00a0 Capable of working independently, with a strong sense of responsibility\n\n-\u00a0\u00a0\u00a0\u00a0\u00a0\u00a0\u00a0\u00a0\u00a0 Team player with positive attitude\n\n-\u00a0\u00a0\u00a0\u00a0\u00a0\u00a0\u00a0\u00a0\u00a0 Well organized and detail orientated\n\n-\u00a0\u00a0\u00a0\u00a0\u00a0\u00a0\u00a0\u00a0\u00a0 Proactiveand have the ability to multi-task\n\nInterested candidates should send an email explaining their suitability for the position and stating their present and required salary full resume/CV to email address provided. We regret that only shortlisted candidates will be notified.\u00a0", "employment_types": ["Full Time", "Permanent"], "selling_points": ["Junior company secretary position", "Good career path", "TCSP licenced corporate services company"], "locations": ["Sheung Wan"], "categories": ["Professional Services", "Company Secretary"], "post_time": "2022-01-08T06:37:01Z", "salary": {"currency": null, "max": null, "min": null, "period": "monthly", "term": null}, "salary_visible": false, "title_keywords": ["executive"], "responsibilities": ["reporting", "management", "business projects", "compliance", "transactions", "administrative duties", "career development", "liaise with", "administration"], "requirements": {"degrees": ["degree or above", "bachelor"], "majors": [], "languages": ["english", "chinese"], "language_level": ["excellent"], "hard_skills": ["companies ordinance"], "soft_skills": ["meticulous", "self-motivated", "independently", "multi-task", "capable", "sense of responsibility", "well organized", "positive attitude", "hands on", "detail orientated", "team player", "driven", "hardworking"], "languages_combined": [{"language": "english", "language_level": ["excellent"]}, {"language": "chinese", "language_level": ["excellent"]}]}, "experience_required": {"duration": ["minimum 3 years"], "field": ["secretarial"]}}, {"job_id": "100003009032823", "location_code": "hk", "company": "TMF Hong Kong Limited", "job_title": "Company Secretarial Assistant Manager- Listing Services", "description": "Job Purpose\n\nThe\u00a0Company Secretarial Assistant Manager - Listing Services\u00a0is responsible for providing professional services on corporate secretarial matters for a portfolio of local and international clients, including incorporating and managing corporate structures.\u00a0 This role will lead the junior staff, to streamline processes, increase revenue & productivity and enhance morale.\u00a0 She/he also needs to ensure that all company secretarial matters of client companies are properly handled.\n\nResponsibilities\n\nManage a portfolio of Hong Kong listed company clients and their private companies\nPrepare and review documentation such as board minutes, resolutions, announcements, circulars and other corporate publications\nTake responsibility for technical accuracy of our client work, liaising and coordinating with other professional advisors and governmental bodies as required\nHandle complex advices and requests from clients\nMaintain good relationship with clients and intermediaries\nBe a coach in developing junior staff in the team\n\nRequirements\n\nA minimum of 6 years\u2019 company secretarial experience in large professional firms or law firms or listed companies\nGood working knowledge of Hong Kong Listing Rules, Companies Ordinance and relevant regulations\nA member of The Hong Kong Institute of Chartered Secretaries / The Chartered Governance Institute is highly preferred\nMeticulous, highly organised, conscientious and able to demonstrate high levels of initiative\nMotivated by multiple tasks and deadlines, with the ability to work under pressure and independently with minimum supervision\nGood interpersonal, leadership and communication skills, with spoken and written English, Cantonese and Mandarin are essential\n\n\n\nWe offer competitive remuneration package including\n\n13-months salary + discretionary bonus\nProfessional membership sponsorship\nhybrid working arrangement & work life insurance\nStudy and examination leaves\nDental and medical coverage", "employment_types": ["Full Time"], "selling_points": ["Portfolio of local and international clients", "Join an energetic and supportive team", "Hybrid working arrangement"], "locations": ["Causeway Bay"], "categories": ["Professional Services", "Company Secretary"], "post_time": "2022-01-07T23:54:04Z", "salary": {"currency": null, "max": null, "min": null, "period": "monthly", "term": null}, "salary_visible": false, "title_keywords": ["manager", "company secretarial assistant"], "responsibilities": ["documentation", "review", "developing", "maintain good relationship"], "requirements": {"degrees": [], "majors": [], "languages": ["cantonese", "english", "mandarin"], "language_level": ["good"], "hard_skills": ["companies ordinance"], "soft_skills": ["meticulous", "communication skills", "independently", "multiple tasks", "work under pressure", "motivated", "conscientious", "interpersonal", "leadership", "initiative", "organised"], "languages_combined": [{"language": "cantonese", "language_level": ["good"]}, {"language": "english", "language_level": ["good"]}, {"language": "mandarin", "language_level": ["good"]}]}, "experience_required": {"duration": ["minimum of 6 years"], "field": ["secretarial"]}}, {"job_id": "100003009029314", "location_code": "hk", "company": "Kowloon Development Company Ltd", "job_title": "COMPANY SECRETARIAL OFFICER / ASSISTANT COMPANY SECRETARIAL OFFICER", "description": "Responsibilities:\n\nDischarge a wide range of company secretarial duties for the Group in compliance with corporate governance and statutory rules and regulations\nAssist the senior to handle full set of statutory records for HK, PRC, Macau and offshore private companies of the Group\nAssist in preparation of annual and interim reports, SFO reporting, announcement and circular\nAssist in organizing various meetings including board meetings and general meetings of listed company\nAssist in control of various companies records and updating respective information\nHandle properties transfer documents\nPerform ad hoc duties as assigned\n\n\nRequirements:\n\nTertiary education of Corporate Secretarial Studies or relevant major and student member of HKCGI/CGI or equivalent\n3 years or above hands-on company secretarial experience in professional firms or equivalent\nAble to prepare statutory and corporate documents for the group of companies independently\nKnowledge of Companies Ordinance and other statutory compliance requirements in Hong Kong, BVI, Cayman Islands and other jurisdictions\nExperience in dealing with companies incorporated in PRC is an advantage\nGood command of spoken and written English and Chinese, Putonghua is preferable\nProficient in computer knowledge including MS office, Chinese word processing and CSA software\nAble to work independently with minimum supervision\nCandidates with less experience will be considered for Assistant Company Secretarial Officer position\nWe offer an attractive remuneration package and excellent career prospects to the right candidate. Interested parties are invited to send their applications with a cover letter quoting job reference number and\u00a0full resumes stating career history, qualifications, availability, current and expected salary, and contact telephone number by fax to 2394 1424 or by clicking \"APPLY NOW\".\u00a0 More information on the Company is available at www.kdc.com.hk.\n\n\n\nApplicants not invited for interview within two months may consider their applications unsuccessful. All personal data provided will be kept in strict confidence and only for employment purposes.\u00a0\u00a0", "employment_types": ["Full Time", "Permanent"], "selling_points": ["5 days work", "Double Pay and Discretionary Bonus", "3 years or above hands-on company secretarial exp"], "locations": ["Mong Kok"], "categories": ["Professional Services", "Company Secretary"], "post_time": "2022-01-07T04:41:33Z", "salary": {"currency": null, "max": null, "min": null, "period": null, "term": null}, "salary_visible": false, "title_keywords": ["company secretarial officer", "assistant"], "responsibilities": ["regulations", "reporting", "control", "ad hoc duties", "compliance", "reports"], "requirements": {"degrees": [], "majors": [], "languages": ["putonghua", "english", "chinese"], "language_level": ["good command", "proficient"], "hard_skills": ["companies ordinance", "chinese word processing", "ms office"], "soft_skills": ["hands-on", "independently", "work independently"], "languages_combined": [{"language": "putonghua", "language_level": ["good command"]}, {"language": "english", "language_level": ["good command"]}, {"language": "chinese", "language_level": ["good command", "proficient"]}]}, "experience_required": {"duration": ["3 years"], "field": ["secretarial"]}}, {"job_id": "100003009022951", "location_code": "hk", "company": "Montclair Limited", "job_title": "Company Secretarial Assistant and Paralegal", "description": "About us :\n\nWe are a corporate service, consulting and advisory service provider. We are looking for a suitable candidate to handle company secretarial and or consulting work in our cosy office.\n\nJob Description:\n\nHandling a full spectrum of company secretarial work;\nPreparing company resolutions, appointment or resignation of directors, instrument of transfer of shares. Register of directors, register of shareholders in English.\nCompleting statutory forms (e.g. ND2A, NAR, NSC, NRO, etc) for Hong Kong, companies for submission to the Hong Kong Companies Registry in English;\nPreparing Annual Returns in English for HK and offshore companies;\nPreparing Register of Directors and various other statutory registers,\nPreparing all documents needed under the current Know-your-client (KYC) requirements;\nAssisting in opening bank accounts or securities accounts forms, gathering documents + Certification for bank account opening for a company,\nCompleting Common Reporting Standards (CRS) forms and FATCA forms and W8Ben Form and CRS Form;\nUpdating records, registers, and data;\nRecord-keeping of all relevant documents.\n\nExperience and qualifications:\n\nPrior work experience gained in professional firms would be ideal, newly University graduates with interest in this field are welcome too.\nFair English and Chinese reading, understanding, writing and communications skills.\nKeen to learn, good altitude to work, organized and a team- player.\nGood computer word (English and Chinese), excel, PPT, charts and diagram skills.\nMandarin speaking is not a must, but would be a huge advantage.\u00a0\n\nWhat is on Offer : Market/commensurate with experience and a cosy work atmosphere, 5-day working week, medical insurance.\u00a0\u00a0", "employment_types": ["Full Time", "Permanent"], "selling_points": [], "locations": ["Admiralty"], "categories": ["Professional Services", "Business Consultancy", "Company Secretary", "Legal & Compliance"], "post_time": "2022-01-06T16:07:50Z", "salary": {"currency": null, "max": null, "min": null, "period": "monthly", "term": null}, "salary_visible": false, "title_keywords": ["paralegal", "company secretarial assistant"], "responsibilities": ["reporting", "consulting", "data", "account opening", "kyc", "insurance"], "requirements": {"degrees": [], "majors": [], "languages": ["english", "chinese", "mandarin"], "language_level": ["advantage", "good"], "hard_skills": ["crs", "excel", "account opening", "fatca", "word", "kyc"], "soft_skills": ["organized", "keen", "ideal"], "languages_combined": [{"language": "english", "language_level": ["good"]}, {"language": "chinese", "language_level": ["good"]}, {"language": "mandarin", "language_level": ["advantage"]}]}, "experience_required": {"duration": [], "field": ["insurance", "medical"]}}, {"job_id": "100003009031795", "location_code": "hk", "company": "SWCS Corporate Services Group (Hong Kong) Limited", "job_title": "Compliance Senior Officer/ Officer", "description": "KEY RESPONSIBILITIES\n\n\nAssist in on-going compliance monitoring of CDD/KYC and compliance requirements to ensure compliance with rules and regulation of the SFC, HKEX, the TCSP and trustee licensing requirements of CR, and other regulators as deemed appropriate;\nAssist to develop and enhance compliance related policies and procedures, inclusive of but not limited to AML, personal data privacy, anti-corruption and sanction laws;\nResearch and draft general compliance policy and procedures\u00a0\nHandle AML/KYC and sanction checking with automated tools and conduct other necessary investigations;\nPrepare training materials and conduct training in respect of AML and other compliance areas;\nKeep track of regulatory changes, conduct research on changes for further updates of internal compliance policies and procedures and for technical publication;\nLiaise with external vendors or service providers;\nHandling any ad hoc duties as assigned.\nREQUIREMENTS\nBachelor degree holder or above with major in law, accounting, corporate governance or other related disciplines;\nMinimum 2-3 years of related working experience;\nSelf-motivated and detail oriented;\nExcellent command of spoken and written English and Chinese (inclusive of Putonghua and Cantonese);\nKnowledge in Viewpoint is a plus;\nProven skills in Microsoft office software inclusive of Word, Excel and PowerPoint;\nImmediate availability is preferred.\nCandidates with more experience may be considered for senior post.\n\n\nWe offer attractive salary and benefits to successful candidates, including five-day work week, medical benefits\u00a0and performance bonus. Interested parties please click Apply Now.\u00a0 Applicants who are not contacted within six weeks may consider their application unsuccessful. Personal data collected will be used for recruitment-related purpose only.", "employment_types": ["Full Time", "Permanent"], "selling_points": ["Major in Law, Accounting, Corporate Governance", "2 - 3 years of related working experiences", "Attractive salary, Benefits & Performance Bonus"], "locations": ["Wan Chai"], "categories": ["Banking / Finance", "Financial Services", "Professional Services", "Company Secretary", "Legal & Compliance"], "post_time": "2022-01-07T09:46:08Z", "salary": {"currency": null, "max": null, "min": null, "period": "monthly", "term": null}, "salary_visible": false, "title_keywords": ["senior officer", "officer"], "responsibilities": ["ad hoc duties", "aml", "cdd", "policies", "monitoring", "compliance", "procedures", "checking", "ensure compliance", "develop", "kyc", "liaise with", "personal data", "conduct research", "publication"], "requirements": {"degrees": ["bachelor degree holder"], "majors": ["related disciplines", "accounting", "law"], "languages": ["cantonese", "putonghua", "english", "chinese"], "language_level": ["excellent"], "hard_skills": ["excel", "plus", "word", "powerpoint", "microsoft office software"], "soft_skills": ["detail oriented", "self-motivated"], "languages_combined": [{"language": "cantonese", "language_level": ["excellent"]}, {"language": "putonghua", "language_level": ["excellent"]}, {"language": "english", "language_level": ["excellent"]}, {"language": "chinese", "language_level": ["excellent"]}]}, "experience_required": {"duration": ["minimum 2-3 years"], "field": ["related"]}}, {"job_id": "100003009028678", "location_code": "hk", "company": "Hays", "job_title": "Company Secretarial Officer, Main Board, Immediately Available", "description": "Excellent opportunity for company secretary looking to make a move in-house!\n\nYour new company\nOur client is a main board Hong Kong listed company with a market cap of over 40 Billion. They are currently looking for a junior company secretary of high calibre to join their team.\n\nYour new role\n\nHandle a full spectrum of company secretarial duties for the listed company and its subsidiaries in Hong Kong, PRC and overseas\nEnsure compliance with listing rules requirements and other applicable rules and regulations\nPrepare annual / interim reports, announcements, circulars, board papers and minutes, and organize board and shareholders' meetings\nParticipate in ad hoc projects and tasks assigned from time to time\n\n\nWhat you'll need to succeed\n\nAssociate member of HKCGI\nCandidates without in-house experience are welcome\nGood command in both Chinese and English\nImmediately available preferred\n\n\nWhat you need to do now\nIf you're interested in this role, click 'apply now' or for further information and a confidential discussion on this role or to find out about more opportunities in the in-house legal space, please contact Natalie Kwok at Hays on +852 2230 7948 or email natalie.kwok@hays.com.hk", "employment_types": ["Full Time", "Permanent"], "selling_points": ["In-house opportunity", "Double pay", "Prime working location"], "locations": ["Not Specified"], "categories": ["Professional Services", "Business Consultancy", "Company Secretary", "Legal & Compliance"], "post_time": "2022-01-07T02:50:47Z", "salary": {"currency": null, "max": null, "min": null, "period": "monthly", "term": null}, "salary_visible": false, "title_keywords": ["company secretarial officer"], "responsibilities": ["regulations", "ensure compliance", "ad hoc projects", "reports", "contact", "listing"], "requirements": {"degrees": [], "majors": [], "languages": ["english", "chinese"], "language_level": ["good command"], "hard_skills": ["make"], "soft_skills": ["interested in"], "languages_combined": [{"language": "english", "language_level": ["good command"]}, {"language": "chinese", "language_level": ["good command"]}]}, "experience_required": {"duration": [], "field": []}}, {"job_id": "100003009026751", "location_code": "hk", "company": "iCareer Consultants Limited", "job_title": "Company Secretarial Officer / Senior Officer / Assistant Officer", "description": "Job Responsibilities:\n\nAssist in performing a full range of company secretarial duties as well as statutory compliance for the listed company and its subsidiaries in HK, PRC and overseas\nAttend to Hong Kong Companies Ordinance, Listing Rules and compliance issues\nPrepare the documentation regarding results announcement, notifiable transaction announcements, circulars, notices, board and committee meeting(s) of directors and members\u2019 meeting etc\nMaintain and update statutory records and proper filings;\nCarry out ad-hoc assignments as required\n\n\nJob Requirements:\n\nDegree or above in corporate governance or related disciplines;\nAssociate / Student Membership of the ICSA/ HKICS;\nMin. 2 years\u2019 experience in company secretarial field;\nGood communication and inter-personal skills;\u00a0\nGood command of both written and spoken English, Chinese and Mandarin\n\nOur client offers attractive remuneration package to the right candidate.\nPlease click \u201cAPPLY NOW\u201d to submit your application.\nOr apply through the link:\u00a0https://icareer.com.hk/job-125.php\n\n\nFor more jobs opportunities, please visit our website at www.icareer.com.hk\nAll information collected will be kept in strict confidence and will be used for recruitment purpose only.", "employment_types": ["Full Time", "Permanent"], "selling_points": ["Attractive remuneration package", "One of the Leading Hong Kong Brand", "5 days work, job in sizeable company"], "locations": ["Not Specified"], "categories": ["Accounting", "Accountant", "Professional Services", "Company Secretary", "Legal & Compliance"], "post_time": "2022-01-06T16:08:17Z", "salary": {"currency": null, "max": null, "min": null, "period": "monthly", "term": null}, "salary_visible": false, "title_keywords": ["assistant officer", "senior officer", "company secretarial officer"], "responsibilities": ["statutory compliance", "ad-hoc assignments", "compliance", "maintain", "documentation", "listing"], "requirements": {"degrees": ["degree or above"], "majors": ["related disciplines"], "languages": ["english", "chinese", "mandarin"], "language_level": ["good command"], "hard_skills": ["php"], "soft_skills": ["communication", "confidence", "inter-personal skills"], "languages_combined": [{"language": "english", "language_level": ["good command"]}, {"language": "chinese", "language_level": ["good command"]}, {"language": "mandarin", "language_level": ["good command"]}]}, "experience_required": {"duration": ["2 years"], "field": ["secretarial"]}}, {"job_id": "100003009026114", "location_code": "hk", "company": "ISP Construction (Engineering) Limited", "job_title": "Assistant Company Secretarial Manager (Ref: CoSec-ISP)", "description": "Responsibilities\n\n\nResponsible for providing day-to-day company secretarial duties and statutory compliance for listed companies\nPrepare corporate secretarial documents and statutory forms\nHandle ad-hoc projects as required\n\nRequirements\n\n\nDegree holder in Corporate Administration or relevant disciplines\nGraduate/ Finalist member of HKICS/ICSA\u00a0\nAt least 6 years' relevant experiences gained in listed company, large-scale corporations or professional firms, experiences gained from construction related industries will be advantage\nUnderstanding of Hong Kong Company Ordinance and listing rules\nWell-organized, detail-oriented, fast-paced, proactive, independent and eager to learn\nFluent in spoken and written English and Chinese", "employment_types": ["Full Time", "Permanent"], "selling_points": ["At least 6 yrs' relevant exp.", "Independent, well-organized & fast-paced", "Graduate/ Finalist member of HKICS/ICSA"], "locations": ["Ngau Tau Kok"], "categories": ["Professional Services", "Company Secretary"], "post_time": "2022-01-06T07:37:19Z", "salary": {"currency": null, "max": null, "min": null, "period": "monthly", "term": null}, "salary_visible": false, "title_keywords": ["company secretarial manager", "assistant"], "responsibilities": ["statutory compliance", "ad-hoc projects"], "requirements": {"degrees": ["degree holder"], "majors": [], "languages": ["english", "chinese"], "language_level": ["fluent"], "hard_skills": [], "soft_skills": ["independent", "well-organized", "detail-oriented", "eager to learn", "proactive"], "languages_combined": [{"language": "english", "language_level": ["fluent"]}, {"language": "chinese", "language_level": ["fluent"]}]}, "experience_required": {"duration": ["at least 6 years"], "field": ["related", "construction"]}}, {"job_id": "100003009031799", "location_code": "hk", "company": "SWCS Corporate Services Group (Hong Kong) Limited", "job_title": "Legal & Technical \u2013 Vice President/ Assistant Vice President", "description": "KEY RESPONSIBILITIES\n\nReporting to senior management, you will play a part in the following:\n\n\nProvide pro-active or timely technical advice or opinion on legal and company secretarial matters internally and externally;\nResolve technical company secretarial issues for listed and private companies by giving technical support/advice to professional service lines on legal and regulatory risks associated with engagements;\nLegal and technical research;\nDraft, negotiate and review engagement documentation with clients and other kind of agreements\nPrepare publication of regulatory updates and newsletters;\nServe as a member of internal Technical Working Group backing professional service teams;\nPrepare, review and streamline internal control processes and professional services practices by assisting to develop, review and update standard templates, procedures and company secretarial practices, checklists and technical bulletins;\nProvide and conduct technical regulatory briefing and training for internal staff and external parties;\nPrepare written submissions or replies to Stock Exchange, SFC or other regulatory bodies on relevant consultations and proposals in particular on those affecting the company\u2019s professional services; and\nAd hoc projects as assigned by CEO and senior management.\nREQUIREMENTS\n\n\u00a0A Hong Kong qualified solicitor with some post-qualification legal experience in a law or professional firm or in-house environment. Newly qualified with relevant experience will also be considered;\nPossess experience in corporate secretarial or legal and compliance practices in regulatory bodies is a plus and interest in corporate governance, Listing Rules, CO, SFO and AML/CFT compliance;\nPossess problem-solving ability in complicated situations involving legal and compliance issues and develop workable solutions for different scenarios;\nStrong project management skills with the ability to complete legal projects and to execute multiple projects with precision;\nStrong legal skills (drafting, research and analytical) and well-versed and deep understanding and practice in new Hong Kong Companies Ordinance, Listing Rules and Securities and Futures Ordinance;\nStrong communication, interpersonal skills and presentation skills;\nGood command of spoken English, Putonghua and Cantonese and written English and Chinese;\nHigh ethical standard, pleasant, detail-orientated, well-organised and strong sense of responsibility; and\nProficiency in MS Word, Excel and PowerPoint\u00a0and Chinese Words input.\u00a0\nCandidates with relevant experience will be considered for a position commensurate with experience.\n\n\nWe offer attractive salary and benefits to successful candidates, including five-day work week, medical benefits\u00a0and performance bonus. Interested parties please click Apply Now.\u00a0 Applicants who are not contacted within six weeks may consider their application unsuccessful. Personal data collected will be used for recruitment-related purpose only.", "employment_types": ["Full Time", "Permanent"], "selling_points": ["Qualified solicitor, post-qualification legal exp", "Exp in Corporate Secretarial/ Legal & Compliance", "Attractive salary and benefits"], "locations": ["Wan Chai"], "categories": ["Professional Services", "Company Secretary", "Legal & Compliance"], "post_time": "2022-01-07T09:46:20Z", "salary": {"currency": null, "max": null, "min": null, "period": "monthly", "term": null}, "salary_visible": false, "title_keywords": ["vice president", "assistant vice president"], "responsibilities": ["reporting", "technical support", "technical advice", "review", "teams", "procedures", "external parties", "develop", "ad hoc projects", "documentation", "senior management", "publication", "internal control"], "requirements": {"degrees": [], "majors": [], "languages": ["cantonese", "putonghua", "english", "chinese"], "language_level": ["proficiency", "good command"], "hard_skills": ["excel", "plus", "aml", "words", "problem-solving", "securities and futures ordinance", "powerpoint", "project management", "cft", "companies ordinance", "sfo", "ms word"], "soft_skills": ["sense of responsibility", "project management skills", "problem-solving", "deep", "pleasant", "communication", "presentation skills", "interpersonal skills", "ethical", "well-organised"], "languages_combined": [{"language": "cantonese", "language_level": ["good command"]}, {"language": "putonghua", "language_level": ["good command"]}, {"language": "english", "language_level": ["good command"]}, {"language": "chinese", "language_level": ["proficiency", "good command"]}]}, "experience_required": {"duration": [], "field": ["secretarial", "post-qualification", "legal", "compliance", "relevant experience"]}}, {"job_id": "100003009034557", "location_code": "hk", "company": "Lam and Lai", "job_title": "Legal Secretary", "description": "An expanding legal\u00a0firm in Central. We are looking for candidate to fill the following post:\n\n\u00a0\u00a0Legal Secretary\n\nProvide secretarial support to solicitors for the preparation of legal documents and any ad hoc legal & compliance-related matters;\nAt least 1 year's solid experience in law firm, preferably in litigation department;\nFast and accurate typing skill with good telephone manner, formal secretarial training is preferable;\nProficiency in MS Word, Excel and Chinese Word Processing;\nGood communication skills and strong sense of responsibility a must;\nBe pleasant, self-motivated, reliable and systematic;\nAble to work under pressure and willing to work overtime.\n\nInterested parties please send your resume with expected salary & available date either by clicking \"Apply Now\"\u00a0or send by mail to 17th\u00a0Floor, Two Chinachem Plaza, No.135 Des Voeux Road Central, Hong Kong. (Attn: Ms Lun).\n\n\u00a0Personal data collected will be used for recruitment purpose only.", "employment_types": ["Full Time", "Permanent"], "selling_points": [], "locations": ["Central"], "categories": ["Admin & HR", "Secretary", "Professional Services", "Company Secretary", "Legal & Compliance"], "post_time": "2022-01-10T03:39:34Z", "salary": {"currency": null, "max": null, "min": null, "period": "monthly", "term": null}, "salary_visible": false, "title_keywords": ["legal secretary"], "responsibilities": ["ad hoc", "compliance", "communication", "secretarial support", "work under pressure"], "requirements": {"degrees": [], "majors": [], "languages": ["chinese"], "language_level": ["proficiency"], "hard_skills": ["excel", "chinese word processing", "typing", "ms word"], "soft_skills": ["communication skills", "self-motivated", "work overtime", "sense of responsibility", "systematic", "pleasant", "reliable", "accurate", "telephone manner", "work under pressure"], "languages_combined": [{"language": "chinese", "language_level": ["proficiency"]}]}, "experience_required": {"duration": ["at least 1 year"], "field": []}}, {"job_id": "100003009029400", "location_code": "hk", "company": "ConnectedGroup Limited", "job_title": "Assistant Manager, Company Secretariat (HK$ 40k-55k)", "description": "Assistant Manager - Company Secretariat\n\nOur client is a well-established and reputable property developer listed in Hong Kong. We are assisting them looking for a talented individual to take up the Assistant Manager, Company Secretariat.\n\nSalary: HK$ 40,000 - 55,000x 12 month + bonus\n\nJob Summary:\n\nProviding company secretarial services for Board and company\nFamilir with Hong Kong Listing Rules and Securities and Futures Ordinance\n\nJob Duties:\n\nResponsible for full spectrum of company secretarial duties, corporate governance and compliance functions for listed company and private subsidiaries\nDraft and prepare annual and interim reports, announcements and circulars\nOrganize meetings for the board, committees and shareholders, and prepare relevant board papers, minutes and resolutions\nMaintain and update statutory records and filings in compliance with the Code on Real Estate Investment Trusts, Securities and Futures Ordinance, Listing Rules, applicable laws and regulations and implement compliance procedures as required\nLiaise with professional advisors and various regulatory bodies\nParticipate in ad hoc projects and tasks assigned from time to time\n\nRequirements:\n\nDegree holder in Corporate Administration or relevant disciplines\nQualified Member of HKCGI/CGI\nAt least 8 to 10 years of company secretarial experience gained in listed company, large-scale corporations or professional firms\nSolid experience in Hong Kong Listing Rules, Securities and Futures Ordinance and Hong Kong Companies\nExperience in handling compliance matters with the Securities and Futures Commission is an advantage\nExcellent command of written and spoken English and Chinese\nProven track record of minute taking and stakeholder management.\nCandidates with more experience will be considered as Manager\n\nInterested individuals should \"Apply Now\", due to an influx of applicants, we regret to inform you that ONLY suitable candidates will be contacted.\n\nFor a more comprehensive list of our vacancies, please visit: www.connectedgroup.com", "employment_types": ["Full Time", "Permanent"], "selling_points": ["", "", ""], "locations": ["Kwun Tong Area"], "categories": ["Professional Services", "Company Secretary", "Legal & Compliance"], "post_time": "2022-01-07T05:01:43Z", "salary": {"currency": "HKD", "max": 54999, "min": 45000, "period": "monthly", "term": null}, "salary_visible": true, "title_keywords": ["assistant manager,"], "responsibilities": ["regulations", "compliance", "procedures", "maintain", "reports", "ad hoc projects", "liaise with", "listing"], "requirements": {"degrees": ["degree holder"], "majors": [], "languages": ["english", "chinese"], "language_level": ["excellent"], "hard_skills": ["inform", "securities and futures ordinance"], "soft_skills": ["comprehensive"], "languages_combined": [{"language": "english", "language_level": ["excellent"]}, {"language": "chinese", "language_level": ["excellent"]}]}, "experience_required": {"duration": ["at least 8 to 10 years"], "field": ["secretarial", "compliance", "securities"]}}, {"job_id": "100003009027036", "location_code": "hk", "company": "Sun Wah Group", "job_title": "Company Secretarial Assistant", "description": "F. 7 / DSE graduate or above\nPossess Diploma or Degree in Corporate Governance or Company Secretary related discipline or a student member of HKCGI an added advantage\n1-3 years\u2019 working experience or above\nGood command of Chinese and English\nProficiency in computer, good Microsoft Word, Excel and Chinese word processing\nKnowledge in CSA company secretarial software and company secretarial working experience preferred\nAssist to perform company secretarial works including preparing minutes/resolutions, statutory documents and related documents for Hong Kong and offshore companies\nProvide secretarial support and assist ad-hoc assignments to company secretarial department\nMaintain company statutory records and routine filing\nLiaise with internal parties, external parties and government authorities\nGood working attitude and capable to work independently\nInterested parties, please send with full resume stating your present and expected salary and the available date by email by click \"APPLY NOW\".", "employment_types": ["Full Time"], "selling_points": [], "locations": ["Central"], "categories": ["Accounting", "Audit", "Professional Services", "Company Secretary", "Legal & Compliance"], "post_time": "2022-01-06T16:08:19Z", "salary": {"currency": null, "max": null, "min": null, "period": "monthly", "term": null}, "salary_visible": false, "title_keywords": ["company secretarial assistant"], "responsibilities": ["software", "related documents", "ad-hoc assignments", "external parties", "maintain", "secretarial support", "liaise with", "internal parties"], "requirements": {"degrees": ["diploma", "degree", "dse"], "majors": [], "languages": ["english", "chinese"], "language_level": ["proficiency", "good command", "good"], "hard_skills": ["excel", "microsoft word", "chinese word processing"], "soft_skills": ["good working attitude", "work independently", "capable"], "languages_combined": [{"language": "english", "language_level": ["good command", "good"]}, {"language": "chinese", "language_level": ["proficiency", "good command", "good", "good"]}]}, "experience_required": {"duration": ["1-3 years"], "field": ["secretarial"]}}]