[{"job_id": "100003009038499", "location_code": "hk", "company": "Estate Agents Authority", "job_title": "ASSISTANT MANAGER (Disciplinary Proceedings) (Ref No.: EAA-2021/24)", "description": "Key Responsibilities\n\nReporting to the Legal Counsel (Disciplinary Proceedings), the incumbent is responsible for the following:\n\nScrutinize and prepare disciplinary cases for submission to the Disciplinary Committee of the Authority\nProvide analysis on evidence to facilitate disposal of disciplinary cases\nPresent cases at disciplinary inquiry hearings conducted by the Disciplinary Committee\nSupervise and coach staff members to carry out the disciplinary proceedings function\nAssist the Section Head in the management of the Disciplinary Proceedings Section\nPerform such other duties as may from time to time be assigned\nRequirements\nA recognized university degree in Law\nAt least 3 years\u2019 relevant experience in prosecution or litigation preferably 2 years of which at supervisory level; or a qualified solicitor / barrister with at least 1 year\u2019s post-qualification experience in litigation practice\nGood command of both written and spoken English and Chinese (Preferably attained Grade \u201cC\u201d or above in English Language (Syllabus B) and Chinese Language in HKCEE, or Level 4 or above in HKDSEE, or equivalent)\nQualified legal practitioner, legal executive in litigation, or court/tribunal prosecutor preferred\nGood written and verbal presentation skill\nTerms of Appointment\nCompetitive remuneration package commensurate with the selected candidate\u2019s qualifications and experience will be offered. The appointee will initially be offered a 3-year contract, subject to renewal upon satisfactory performance and the service needs of the Authority.\nApplication Procedure\u00a0\u00a0\u00a0\u00a0\u00a0\u00a0\u00a0\u00a0\u00a0\u00a0\u00a0\u00a0\u00a0\u00a0\u00a0\u00a0\u00a0\u00a0\u00a0\u00a0\u00a0\u00a0\u00a0\u00a0\u00a0\u00a0\u00a0\u00a0\u00a0\u00a0\u00a0\u00a0\u00a0\u00a0\u00a0\u00a0\u00a0\u00a0\u00a0\nApplications with full resume indicating your current and expected salaries and your public examination results should be sent to: Human Resources Section, Estate Agents Authority, 7/F, E-Trade Plaza, 24 Lee Chung Street, Chaiwan, Hong Kong or email via \"Apply now\" at\u00a0 not later than 31 January 2022. Candidates who have already responded to our previous advertisement of the same post in November 2021 need not re-apply. Please mark \u201cPrivate and Confidential\u201d on the envelope and quote the post applied for and its reference number on the envelope.\nCandidates who are not invited to attend an interview within 6 weeks from the closing date may assume their applications unsuccessful. Applications may be considered for other suitable positions within the Authority. All applications will be treated in strict confidence. Personal data provided in the applications will only be used for recruitment-related purposes. All information on non-shortlisted applicants will be destroyed after 6 months.\n\n\nWE ARE AN EQUAL OPPORTUNITIES EMPLOYER", "employment_types": ["Full Time", "Contract"], "selling_points": ["Scrutinize and prepare disciplinary cases", "Present cases at disciplinary inquiry hearings", "A recognized university degree in Law"], "locations": ["Wan Chai"], "categories": ["Public / Civil", "Civil Services", "Professional Services", "Legal & Compliance"], "post_time": "2022-01-16T21:49:59Z", "salary": {"currency": null, "max": null, "min": null, "period": "monthly", "term": null}, "salary_visible": false, "title_keywords": ["assistant manager"], "responsibilities": ["reporting", "analysis", "management", "other duties"], "requirements": {"degrees": ["university degree"], "majors": ["law"], "languages": ["english", "chinese"], "language_level": ["good command"], "hard_skills": ["presentation skill", "c"], "soft_skills": ["presentation skill", "confidence"], "languages_combined": [{"language": "english", "language_level": ["good command"]}, {"language": "chinese", "language_level": ["good command"]}]}, "experience_required": {"duration": ["at least 3 years", "2 years", "at least 1 year"], "field": ["supervisory level", "post-qualification", "relevant experience"]}}, {"job_id": "100003009056236", "location_code": "hk", "company": "David Fenn & Co.", "job_title": "Trainee Solicitor /Paralegal/ Legal Assistant/ Secretary/ Legal Executive/ Litigation Clerk", "description": "Fluent in both written and spoken English and Chinese (Cantonese and Putonghua).\nDrafting basic correspondence, compiling document bundles for court hearing.\nAssisting general clerical secretarial and office work of firm.\nGood organizational skills and eye for detail\nIndependent, self-motivated, and organized.\nFamiliar with MS Word & Excel and Chinese word processing.\nImmediate availability preferred.\n\nWe provide good training in the area of litigation (both criminal and civil), commercial matters, and corporate compliance.\n\nPlease send your full curriculum vitae with expected salary to\u00a0David Fenn & Co.\u00a0Solicitors, to Suite 2812, 28th Floor, Shui On Centre, 6-8 Harbour Road, Wanchai, Hong Kong. Personal data provided by applicants will be treated in strict confidence and used for recruitment purposes only.", "employment_types": ["Full Time", "Permanent"], "selling_points": [], "locations": ["Wan Chai"], "categories": ["Admin & HR", "Clerical / Admin Staff", "Secretary", "Professional Services", "Legal & Compliance"], "post_time": "2022-01-18T03:58:59Z", "salary": {"currency": null, "max": null, "min": null, "period": "monthly", "term": null}, "salary_visible": false, "title_keywords": ["paralegal", "clerk", "legal executive", "legal assistant", "secretary", "trainee solicitor"], "responsibilities": [], "requirements": {"degrees": [], "majors": [], "languages": ["cantonese", "putonghua", "english", "chinese"], "language_level": ["fluent"], "hard_skills": ["excel", "chinese word processing", "basic", "ms word"], "soft_skills": ["organized", "organizational skills", "self-motivated", "independent", "eye for detail"], "languages_combined": [{"language": "cantonese", "language_level": []}, {"language": "putonghua", "language_level": []}, {"language": "english", "language_level": ["fluent"]}, {"language": "chinese", "language_level": ["fluent"]}]}, "experience_required": {"duration": [], "field": []}}, {"job_id": "100003009056048", "location_code": "hk", "company": "Randstad Hong Kong Limited", "job_title": "Paralegal - Crypto", "description": "about the company.\nWe are working with a crypto trading firm to look for a person to be involved supporting of the trading team, covering all aspects of the transactions.\nM&A advisory\ntransactions\nprepare legal contracts (NDAs, mandates, legal opinions etc)\nadvise on legal/ compliance issues\nwork with senior management\nskills & experiences required.\nat least 3 years of relevant experience\nlaw firm/ in house background\nspeaks Mandarin, Cantonese and English\npersonality with a can do spirit\n\nIf you're interested in this role, click 'apply now' or for further information and a confidential discussion on this role or to find out about more opportunities, please contact Sherman Ma on +852 2232 3463 or email sherman.ma@randstad.com.hk", "employment_types": ["Full Time", "Permanent"], "selling_points": ["exciting team", "great exposure", "good career progression"], "locations": ["Not Specified"], "categories": ["Professional Services", "Legal & Compliance"], "post_time": "2022-01-18T03:13:29Z", "salary": {"currency": null, "max": null, "min": null, "period": "monthly", "term": null}, "salary_visible": false, "title_keywords": ["paralegal"], "responsibilities": ["contracts", "compliance", "transactions", "contact", "senior management"], "requirements": {"degrees": [], "majors": [], "languages": ["cantonese", "english", "mandarin"], "language_level": [], "hard_skills": ["crypto"], "soft_skills": ["interested in"], "languages_combined": [{"language": "cantonese", "language_level": []}, {"language": "english", "language_level": []}, {"language": "mandarin", "language_level": []}]}, "experience_required": {"duration": ["at least 3 years"], "field": ["relevant experience"]}}, {"job_id": "100003009056231", "location_code": "hk", "company": "Randstad Hong Kong Limited", "job_title": "Legal Officer - IP", "description": "about the company.\nWe are working with a reputable company who is looking for a person to look after their IP/ trademarks and related matters.\nhandling trademarks, copyrights, domain names\nrecordkeeping\nad hoc researches and administrative tasks\nskills & experiences required.\nat least 2 years of relevant in house IP experiences\nhardworking and responsible\nspeaks English, Mandarin and Cantonese\n\nIf you're interested in this role, click 'apply now' or for further information and a confidential discussion on this role or to find out about more opportunities, please contact Sherman Ma on +852 2232 3463 or email sherman.ma@randstad.com.hk", "employment_types": ["Full Time", "Permanent"], "selling_points": ["Reputable Company", "Stable hours", "Good benefits"], "locations": ["Not Specified"], "categories": ["Professional Services", "Legal & Compliance"], "post_time": "2022-01-18T03:40:26Z", "salary": {"currency": null, "max": null, "min": null, "period": "monthly", "term": null}, "salary_visible": false, "title_keywords": ["officer"], "responsibilities": ["administrative tasks", "ad hoc", "contact"], "requirements": {"degrees": [], "majors": [], "languages": ["cantonese", "english", "mandarin"], "language_level": [], "hard_skills": ["ip"], "soft_skills": ["interested in", "hardworking", "responsible"], "languages_combined": [{"language": "cantonese", "language_level": []}, {"language": "english", "language_level": []}, {"language": "mandarin", "language_level": []}]}, "experience_required": {"duration": ["at least 2 years"], "field": []}}, {"job_id": "100003009054397", "location_code": "hk", "company": "Lein (H.K.) Network Technology Co., Limited", "job_title": "Legal and Compliance Officer", "description": "Job Duties:\n\n\u00a0Drafting or reviewing contracts and other legal documents;\n\u00a0Drafting or updating internal procedures or policies of the company;\n\u00a0Assisting in commercial negotiation, risk control and other compliance matters;\n\u00a0Handling or assisting in legal disputes for the company and/or its affiliates;\n\u00a0Conducting product-oriented legal research from a legal or compliance perspective, and advising in relevant business decisions of the company;\n\u00a0Liaising with external regulators and competent authorities;\n\u00a0Providing legal advice for the company\u2019s daily business operation;\n\u00a0Other ad hoc duties as assigned.\nWhat we need from you:\nDegree holder in Law (LLB, LLM & JD);\n2 years or above related working experience;\nExperience in Anti-money Laundering is an advantage;\nExcellent\u00a0in both Written & Spoken English & Cantonese\u00a0(Mandarin\u00a0is a must);\nProficient in using MS Office (especially in Excel);\nStrong sense of responsibility & accountability.\nWhat we offer:\n\nAttractive Package (Double Pay + Quarterly Bonus + Year end Bonus)\nLearning, Study & Travel Allowances\nOffice Hour (10:00 \u2013 18:30, Mon \u2013 Fri)\nTransparent and friendly working environment\nWork location: Kowloon East (6-8 mins from MTR station)\nInterested parties please submit your full resume with current and expected salary via \"Apply Now\".\u00a0\n\n\u00a0(We are an equal opportunity employer and welcome applications from all qualified candidates. All information provided will be treated strictly confidential and used for recruitment purpose only.)", "employment_types": ["Full Time", "Permanent"], "selling_points": [], "locations": ["Ngau Tau Kok"], "categories": ["Professional Services", "Company Secretary", "Information Technology (IT)", "Others", "Legal & Compliance"], "post_time": "2022-01-17T09:21:38Z", "salary": {"currency": null, "max": null, "min": null, "period": "monthly", "term": null}, "salary_visible": false, "title_keywords": ["compliance officer"], "responsibilities": ["ad hoc duties", "business operation", "control", "contracts", "policies", "compliance", "procedures", "liaising with"], "requirements": {"degrees": ["degree holder"], "majors": ["law"], "languages": ["cantonese", "english", "mandarin"], "language_level": ["excellent"], "hard_skills": ["excel", "anti-money laundering", "ms office"], "soft_skills": ["sense of responsibility", "negotiation", "accountability", "competent"], "languages_combined": [{"language": "cantonese", "language_level": ["excellent"]}, {"language": "english", "language_level": ["excellent"]}, {"language": "mandarin", "language_level": ["excellent"]}]}, "experience_required": {"duration": ["2 years"], "field": ["related"]}}, {"job_id": "100003009052887", "location_code": "hk", "company": "Beijing Tong Ren Tang Chinese Medicine Company Limited", "job_title": "\u6cd5\u52d9\u5c08\u54e1  Legal Assistant", "description": "\u8077\u8cac:\n\n\u8ca0\u8cac\u5be9\u6838\u6295\u8cc7\u6587\u4ef6\uff0c\u7af6\u8abf\u6750\u6599\uff0c\u5f9e\u6cd5\u5f8b\u53ca\u5408\u898f\u98a8\u96aa\u7b49\u65b9\u9762\u51fa\u5177\u5167\u90e8\u6cd5\u5f8b\u610f\u898b\n\u8ca0\u8cac\u8207\u5916\u8058\u5f8b\u5e2b\u5354\u8abf\u548c\u6e9d\u901a\n\u53c3\u8207\u6295\u8cc7\u9805\u76ee\u6d89\u53ca\u53ca\u6cd5\u5f8b\u6587\u4ef6\u9032\u884c\u8d77\u8349\u3001\u5be9\u6838\uff0c\u51fa\u5177\u5167\u90e8\u6cd5\u5f8b\u610f\u898b\uff0c\u5fc5\u8981\u6642\u53c3\u8207\u6e9d\u901a\u548c\u8ac7\u5224\u3002\n\u4e0a\u7d1a\u4ea4\u8fa6\u7684\u5176\u4ed6\u4e8b\u52d9\u3002\n\n\u8981\u6c42:\n\n\n\u6cd5\u5b78\u5c08\u696d\uff0c\u5177\u6709\u4e2d\u570b\u5167\u5730\u6cd5\u5f8b\u8077\u696d\u8cc7\u683c\uff0c\u5982\u517c\u5177\u666e\u901a\u6cd5\u570b\u5bb6\u6216\u5730\u5340\u5f8b\u5e2b\u8cc7\u683c\u512a\u5148\n\u67093\u5e74\u4ee5\u4e0a\u5f9e\u4e8b\u5883\u5167\u5916\u6295\u8cc7\u4f75\u8cfc\u9805\u76ee\u7684\u6cd5\u5f8b\u5de5\u4f5c\u7d93\u9a57\u512a\u5148\n\u5177\u6709\u5feb\u901f\u5b78\u7fd2\u80fd\u529b\uff0c\u826f\u597d\u7684\u6e9d\u901a\u5354\u8abf\u80fd\u529b\u53ca\u5718\u968a\u5408\u4f5c\u7cbe\u795e\n\u5177\u5099\u512a\u79c0\u7684\u5206\u6790\uff0c\u89e3\u6c7a\u554f\u984c\u80fd\u529b\u53ca\u624e\u5be6\u7684\u6cd5\u5f8b\u6587\u66f8\u8d77\u8349\u529f\u5e95\uff0c\u826f\u597d\u7684\u4e2d\u82f1\u6587\u6e9d\u901a\u80fd\u529b\n\u5177\u6709\u516c\u53f8\u6cd5\u52d9\u5de5\u4f5c\u7d93\u9a57\u512a\u5148", "employment_types": ["Full Time", "Permanent"], "selling_points": [], "locations": ["Wan Chai"], "categories": ["Professional Services", "Legal & Compliance", "Medical Services", "Pharmaceutical"], "post_time": "2022-01-17T04:25:54Z", "salary": {"currency": null, "max": null, "min": null, "period": "monthly", "term": null}, "salary_visible": false, "title_keywords": ["legal assistant"], "responsibilities": [], "requirements": {"degrees": [], "majors": [], "languages": [], "language_level": [], "hard_skills": [], "soft_skills": [], "languages_combined": []}, "experience_required": {"duration": [], "field": []}}, {"job_id": "100003009056299", "location_code": "hk", "company": "Healthportal Company Limited", "job_title": "Legal Manager / Assistant Manager \u2013 Family Office", "description": "Job Description:\n\nProviding full range of legal and compliance support and coordination of any projects that the Family Office is engaged in\nDrafting and reviewing legal documentation, including but not limited to sales and purchase agreement, joint venture agreement, shareholder\u2019s agreement, employment contract, service agreement, MOU, board resolutions and powers of attorney\nManaging existing investments, identifying legal and compliance issues, and providing proactive solutions on deal-related matters\nOverseeing corporate transactions, including the preparation of relevant documentation\nPreparing legal report on investment opportunities for internal use\nAdvising senior management on regulatory developments impacting the business\nHandling company secretarial work and compliance matters\nCompiling and maintaining proper and accurate record keeping\nCovering any ad hoc tasks that may require your assistance from time to time\n\nRequirements:\n\nDegree holder in Law\nMinimum 5 years of legal and compliance experience gained from family office, buy-side firm, or HK listed company\nSound knowledge of capital market and private equity is a plus\nStrong commercial awareness and attention to details\nExcellent legal analytical, research, and communication skills\nAbility to understand complex issues and work independently\nGood command of spoken and written English, Mandarin and Cantonese", "employment_types": ["Full Time"], "selling_points": [], "locations": ["Admiralty"], "categories": ["Professional Services", "Legal & Compliance"], "post_time": "2022-01-18T03:52:58Z", "salary": {"currency": null, "max": null, "min": null, "period": "monthly", "term": null}, "salary_visible": false, "title_keywords": ["assistant manager", "manager"], "responsibilities": ["maintaining", "compliance", "ad hoc tasks", "transactions", "purchase", "coordination", "documentation", "senior management", "report"], "requirements": {"degrees": ["degree holder"], "majors": ["law"], "languages": ["cantonese", "english", "mandarin"], "language_level": ["good command"], "hard_skills": ["plus", "private equity"], "soft_skills": ["communication skills", "work independently", "attention to details"], "languages_combined": [{"language": "cantonese", "language_level": ["good command"]}, {"language": "english", "language_level": ["good command"]}, {"language": "mandarin", "language_level": ["good command"]}]}, "experience_required": {"duration": ["minimum 5 years"], "field": ["compliance", "legal"]}}, {"job_id": "100003009054599", "location_code": "hk", "company": "Sinocap Showtime Investment Limited", "job_title": "\u6cd5\u52d9\u7d93\u7406\u517c\u516c\u53f8\u79d8\u66f8 Legal Manager and Company Secretary", "description": "\u8077\u4f4d:\u6cd5\u52d9\u7d93\u7406\u517c\u516c\u53f8\u79d8\u66f8\n\n\n\n\u6838\u5fc3\u529f\u80fd\uff1a\n\n\u00a0\u6cd5\u52d9\n\n\u00a0\u8d77\u8349,\u5be9\u67e5,\u8ac7\u5224,\u7ffb\u8b6f\u5404\u7a2e\u5546\u696d\u5408\u540c,\u5305\u62ec\u8207\u62db\u6a19,\u4e26\u8cfc,\u8cb7\u8ce3\u76f8\u95dc\u7684\u5354\u5b9a\u548c\u63d0\u4f9b\u6230\u7565\u5925\u4f34\u95dc\u4fc2\u7684\u652f\u63f4(\u4e2d\u82f1\u6587\uff09;\n\u00a0\u95dc\u6ce8\u6d41\u7a0b\u6548\u7387,\u5305\u62ec\u5408\u540c\u7684\u81ea\u52d5\u5316\u548c\u516c\u53f8\u5408\u540c\u8cc7\u6599\u5eab\u7684\u7dad\u8b77,\u4ee5\u53ca\u5c0d\u76f8\u95dc\u5229\u76ca\u76f8\u95dc\u65b9\u7684\u9069\u7576\u8a2a\u554f;\n\u00a0\u70ba\u696d\u52d9\u5408\u4f5c\u5925\u4f34\u63d0\u4f9b\u8aee\u8a62\u670d\u52d9,\u4f5c\u70ba\u6307\u5b9a\u5340\u57df\u6cd5\u5f8b\u4e8b\u52d9\u7684\u53ef\u4fe1\u8cf4\u9867\u554f;\n\u00a0 \u8207\u7522\u54c1\u548c\u696d\u52d9\u5718\u968a\u5bc6\u5207\u5408\u4f5c,\u5be9\u6838\u65b0\u7522\u54c1\u548c\u73fe\u6709\u7522\u54c1,\u4ee5\u78ba\u4fdd\u5408\u6cd5\u5408\u898f;\n\u00a0 \u958b\u5c55\u6cd5\u5f8b\u7814\u7a76\u4e26\u8a55\u4f30\u8207\u570b\u969b\u5340\u57df\u696d\u52d9\u904b\u71df\u76f8\u95dc\u7684\u98a8\u96aa;\n\u00a0\u901a\u904e\u5c0d\u5df2\u6279\u51c6\u5c08\u6848\u9032\u884c\u6cd5\u5f8b\u76e1\u8077\u8abf\u67e5,\u7ba1\u7406\u6211\u5011\u7684\u6295\u8cc7\u5c08\u6848\u5be9\u6838\u8a08\u756b;\n\u00a0\u89e3\u6c7a\u591a\u500b\u5229\u76ca\u76f8\u95dc\u65b9\u7684\u554f\u984c,\u4ee5\u4fbf\u5728\u5fc5\u8981\u6642\u63d0\u4f9b\u660e\u78ba\u7684\u6cd5\u5f8b\u6307\u5c0e;\n\u00a0\u5236\u5b9a\u548c\u8986\u6838\u5167\u90e8\u653f\u7b56\u4e26\u5c0d\u5718\u968a\u6210\u54e1\u9032\u884c\u57f9\u8a13,\u4ee5\u50b3\u64ad\u5c0d\u76f8\u95dc\u554f\u984c\u7684\u8a8d\u8b58;\n\u00a0\u806f\u7d61\u548c\u7ba1\u7406\u5916\u90e8\u9867\u554f\u5efa\u8b70;\n\u00a0\u7ba1\u7406\u653b\u64ca\u6027\u548c\u9632\u79a6\u6027\u7684\u7d22\u8ce0\u548c\u6cd5\u5f8b\u8a34\u8a1f,\u8abf\u89e3\u6216\u4ef2\u88c1;\n\u00a0\u5f59\u7de8\u6709\u95dc\u91cd\u5927\u6cd5\u5f8b\u98a8\u96aa\u548c\u7a0b\u5f0f\u7684\u5831\u544a,\u4ee5\u6eff\u8db3\u76f8\u95dc\u7684\u5167\u90e8\u548c\u5916\u90e8\u6cd5\u898f\u548c\u8981\u6c42;\n\u00a0\u78ba\u4fdd\u9075\u5b88\u65e2\u5b9a\u7684\u6cd5\u5f8b\u653f\u7b56\u548c\u7a0b\u5f0f;\n\n\u00a0\u516c\u53f8\u79d8\u66f8\n\n\u7ba1\u7406,\u7533\u8acb\u8a3b\u518a\u6216\u767b\u8a18\u5099\u6848\u96c6\u5718\u7684\u667a\u6167\u8ca1\u7522\u6b0a\n\u5411\u96c6\u5718\u516c\u53f8\u540c\u4e8b\u505a\u5c08\u696d\u5316\u57f9\u8a13\n\u70ba\u5728\u9999\u6e2f,\u82f1\u5c6c\u7dad\u723e\u4eac\u7fa4\u5cf6,\u958b\u66fc\u7fa4\u5cf6,\u4e2d\u570b\u53ca\u5176\u4ed6\u53f8\u6cd5\u7ba1\u8f44\u5340\u8a3b\u518a\u6210\u7acb,\u7e8c\u671f,\u8b8a\u66f4\u767b\u8a18,\u6ce8\u6d88\u7684\u672c\u96c6\u5718\u516c\u53f8\u53ca\u5408\u5925\u4f01\u696d\u5c65\u884c\u5168\u9762\u7684\u516c\u53f8\u79d8\u66f8\u8077\u8cac;\n\u8655\u7406\u81e8\u6642\u516c\u53f8\u5c08\u6848\u4e26\u8207\u5167\u90e8\u90e8\u9580\u548c\u5916\u90e8\u5404\u65b9(\u5305\u62ec\u5f8b\u5e2b,\u516c\u8b49\u4eba,\u5be9\u8a08\u5e2b\u548c\u4ee3\u7406\u4eba)\u5354\u8abf;\n\u7ba1\u7406\u96c6\u5718\u516c\u53f8\u7d50\u69cb\u4e26\u70ba\u7e3d\u90e8\u6e96\u5099\u5831\u544a;\n\u6e96\u5099\u4e2d\u82f1\u6587\u6703\u8b70\u8a18\u9304,\u8655\u7406\u8207\u6295\u8cc7\u5c08\u6848\u548c\u8cc7\u91d1\u6709\u95dc\u7684\u6b0a\u76ca\u62ab\u9732;\n\u5354\u52a9\u70ba\u516c\u53f8\u6cbb\u7406,\u6cd5\u5f8b,\u98a8\u96aa\u548c\u5167\u90e8\u5408\u898f\u8077\u80fd\u63d0\u4f9b\u4e00\u822c\u79d8\u66f8\u548c\u6587\u66f8\u652f\u63f4;\n\u7dad\u8b77\u548c\u66f4\u65b0\u6cd5\u5b9a\u8a18\u9304\u548c\u9069\u7576\u7684\u5099\u6848;\n\u5354\u52a9\u7ba1\u7406\u5167\u90e8\u548c\u5916\u90e8\u5408\u540c\u6a94\u7684\u5099\u6848\u7cfb\u7d71;\n\u5354\u52a9\u7d44\u7e54\u59d4\u54e1\u6703,\u8463\u4e8b\u6703\u548c\u80a1\u6771\u5927\u6703\u4ee5\u53ca\u6e96\u5099\u6703\u8b70\u8a18\u9304;\n\u5354\u52a9\u8d77\u8349\u548c\u7de8\u5236\u516c\u544a,\u901a\u544a\u548c\u5e74\u5ea6/\u4e2d\u671f\u5831\u544a;\n\u5728\u9700\u8981\u6642\u5354\u52a9\u7ba1\u7406\u5de5\u4f5c\u548c\u81e8\u6642\u4efb\u52d9\u3002\n\u6839\u64da\u9700\u8981\u57f7\u884c\u81e8\u6642\u5206\u914d\u3002\n\n\u00a0\u8981\u6c42\uff1a\n\n\u00a0\u7372\u5f97\u8a8d\u53ef\u7684\u5927\u5b78\u7684\u5b78\u4f4d\u6216\u4ee5\u4e0a\uff0c\u5177\u6cd5\u5f8b\u57fa\u672c\u77e5\u8b58\u6216\u8b49\u66f8\uff1b\n\u00a0ICSA / HKICS\u6703\u54e1\u512a\u5148;\n\u00a0\u5177IPO \u53ca\u4e0a\u5e02\u516c\u53f8\u7d93\u9a57\u512a\u5148;\n\u00a0\u81f3\u5c112\u5e74\u76f8\u95dc\u5de5\u4f5c\u7d93\u9a57(\u90e8\u5206\u5167\u90e8\u7d93\u9a57\u512a\u5148);\u00a0 \u5fc5\u9808\u5177\u5099\u6587\u5316\u65c5\u904a\u696d\u3001\u50b3\u5a92\u3001\u5e02\u5834\u884c\u92b7\u3001\u9152\u5e97\u7ba1\u7406\u3001\u4e3b\u984c\u516c\u5712\u7ba1\u7406\u7b49\u5c08\u696d\u5de5\u4f5c\u7d93\u9a57;\n\u00a0\u5f37\u5927\u7684\u6cd5\u5f8b\u8d77\u8349\u548c\u7814\u7a76\u6280\u80fd;\u5728\u7d44\u7e54\u5167\u81ea\u4e3b\u884c\u52d5\u7684\u80fd\u529b;\n\u00a0\u512a\u79c0\u7684\u66f8\u9762\u548c\u53e3\u982d\u6e9d\u901a\u6280\u5de7(\u9700\u8981\u82f1\u8a9e\u548c\u666e\u901a\u8a71);\n\u00a0\u81ea\u6211\u555f\u52d5,\u7a4d\u6975\u4e3b\u52d5,\u9069\u61c9\u80fd\u529b\u5f37\u7684\u500b\u4eba,\u53ef\u4ee5\u660e\u78ba\u5283\u5206\u512a\u5148\u9806\u5e8f\u4e26\u7ba1\u7406\u591a\u500b\u5c08\u6848;\n\u00a0\u8207\u570b\u969b\u5718\u968a\u5408\u4f5c\u7684\u7d93\u9a57;\u548c\n\u00a0\u9ad8\u5ea6\u7684\u8aa0\u4fe1,\u5c08\u696d,\u6210\u9577\u7684\u610f\u9858,\u80fd\u5920\u5728\u5feb\u7bc0\u594f\u7684\u74b0\u5883\u4e2d\u5de5\u4f5c,\u4e26\u80fd\u5920\u6eff\u8db3\u6700\u5f8c\u671f\u9650\u512a\u79c0\u7684\u4e2d\u6587\u5beb\u4f5c\u6280\u5de7\n\n\u6211\u5011\u70ba\u5408\u9069\u7684\u5019\u9078\u4eba\u63d0\u4f9b\u6709\u5438\u5f15\u529b\u7684\u85aa\u6c34\u548c\u9644\u52a0\u798f\u5229\u3002\u5982\u6709\u8208\u8da3,\u8acb\u5c07\u5b8c\u6574\u7684\u7c21\u6b77,\u73fe\u6709\u548c\u9810\u671f\u7684\u85aa\u8cc7\u5f85\u9047\u548c\u53ef\u4e0a\u73ed\u65e5\u671f\u767c\u9001\u96fb\u90f5\u3002\u00a0", "employment_types": ["Full Time"], "selling_points": ["5 days work", "Wanchai location", "14 annual leave, medical insurance"], "locations": ["Wan Chai"], "categories": ["Professional Services", "Company Secretary", "Legal & Compliance"], "post_time": "2022-01-17T10:11:42Z", "salary": {"currency": null, "max": null, "min": null, "period": "monthly", "term": null}, "salary_visible": false, "title_keywords": ["company secretary", "manager"], "responsibilities": [], "requirements": {"degrees": [], "majors": [], "languages": [], "language_level": [], "hard_skills": [], "soft_skills": [], "languages_combined": []}, "experience_required": {"duration": [], "field": []}}, {"job_id": "100003009054458", "location_code": "hk", "company": "Tai & Co., Solicitors", "job_title": "Legal Executive", "description": "Job Responsibilities:\u00a0\n\n\nProviding legal support to solicitor\u00a0\nPreparing\u00a0related\u00a0documents with minimal supervision\u202f\u00a0\nCarry out any other ad hoc matters\u00a0\u00a0\n\n\nJob Requirements:\u00a0\n\n\nAt least 2 years' experience or above in litigation,\u00a0matrimonial\u00a0and probate proceedings\u00a0\nCan handle litigation,\u00a0matrimonial\u00a0and probate cases with minimal supervision\u00a0\nGood command of English & Chinese will be an advantage\u00a0\nGood communication skills and good interpersonal skills\u00a0\nHandle ad-hoc duties as assigned\u00a0\nImmediate available is advantage\u00a0\nSalary can be negotiable\u00a0\n\nInterested parties please write your CV together with your present and expected salary to\u00a0our\u00a0Human Resources and Administration Department by clicking \"APPLY NOW\".\u2028\u2028(Personal data collected will be used for recruitment purpose only)\u00a0\n", "employment_types": ["Full Time", "Permanent"], "selling_points": [], "locations": ["Tsim Sha Tsui"], "categories": ["Professional Services", "Legal & Compliance"], "post_time": "2022-01-17T16:21:04Z", "salary": {"currency": null, "max": null, "min": null, "period": "monthly", "term": null}, "salary_visible": false, "title_keywords": ["legal executive"], "responsibilities": ["related documents", "ad hoc"], "requirements": {"degrees": [], "majors": [], "languages": ["english", "chinese"], "language_level": ["advantage", "good command"], "hard_skills": [], "soft_skills": ["communication skills", "interpersonal skills", "ad-hoc duties"], "languages_combined": [{"language": "english", "language_level": ["advantage", "good command"]}, {"language": "chinese", "language_level": ["advantage", "good command"]}]}, "experience_required": {"duration": ["at least 2 years"], "field": []}}, {"job_id": "100003009054871", "location_code": "hk", "company": "Nu Skin Enterprises Hong Kong, LLC", "job_title": "Legal Counsel", "description": "Job Responsibilities:\n\nWork with business managers and other in-house legal teams to ensure successful operations in compliance with applicable laws and regulations and to ensure global consistency with corporate policies and procedures. Responsible for coordinating and handling regional projects; identifying legal issues and providing legal solutions; and providing legal support to the Regional General Counsel and other legal counsels in business projects.\u00a0 \u00a0\u00a0 \u00a0 \u00a0 \u00a0 \u00a0 \u00a0 \u00a0 \u00a0 \u00a0 \u00a0 \u00a0 \u00a0 \u00a0 \u00a0 \u00a0 \u00a0 \u00a0 \u00a0 \u00a0 \u00a0 \u00a0 \u00a0 \u00a0 \u00a0 \u00a0 \u00a0 \u00a0 \u00a0 \u00a0\n\nJob Requirements:\n\n\nLLB or equivalent and admitted as a legal practitioner in Hong Kong or other common law jurisdiction\nMinimum 5 years working experience (including the period of traineeship or equivalent legal training) in corporate and commercial transactions, preferably with experience in advising multi-national companies with operations in Pan Asia region including the Greater China region and handling projects\nHave solid experience in handling projects and advising business units independently\nGood time management, well organized, detail-oriented, self-motivated, mature, independent & good interpersonal skill\nExcellent command of spoken and written English and Chinese (including Putonghua)\nStrong analytical skills, able to work both independently and as a team player.\nGood communication and interpersonal skill and with strong sense of responsibility\nWilling to travel on a regular basis", "employment_types": ["Full Time", "Permanent"], "selling_points": ["LLB or equivalent", "legal practitioner in Hong Kong", "experience in corporate and commercial transaction"], "locations": ["Tin Hau"], "categories": ["Professional Services", "Legal & Compliance"], "post_time": "2022-01-17T12:14:09Z", "salary": {"currency": null, "max": null, "min": null, "period": "monthly", "term": null}, "salary_visible": false, "title_keywords": ["legal counsel"], "responsibilities": ["regulations", "business projects", "operations", "policies", "compliance", "teams", "procedures"], "requirements": {"degrees": [], "majors": [], "languages": ["putonghua", "english", "chinese"], "language_level": ["excellent"], "hard_skills": ["analytical skills"], "soft_skills": ["self-motivated", "independently", "independent", "sense of responsibility", "well organized", "mature", "detail-oriented", "interpersonal skill", "analytical skills", "communication", "team player", "time management"], "languages_combined": [{"language": "putonghua", "language_level": ["excellent"]}, {"language": "english", "language_level": ["excellent"]}, {"language": "chinese", "language_level": ["excellent"]}]}, "experience_required": {"duration": ["minimum 5 years"], "field": ["commercial", "business", "training", "legal"]}}, {"job_id": "100003009052240", "location_code": "hk", "company": "Hongkong YunExpress Logistics Limited", "job_title": "Legal Counsel", "description": "Job Responsibilities:\n\n\nProvide daily legal support and legal risk management for the group's business in Asia-Pacific and emerging market countries, including but not limited to contract management, compliance management, and handling of various possible disputes\nResearch and analyze the laws, regulations and policies of each business area under its jurisdiction, and transform them into the group's legal risk management measures\nProvide legal consultation and legal training for local business and functional departments,\u00a0improve legal awareness of local management and employees\nDocking with relevant external lawyers, and control their service qualities and charges\nImplement the legal policies of the Group Legal Headquarters\nComplete other tasks assigned by the superior.\n\nJob Requirements:\n\nMaster degree in law\nPossess a legal education background in Hong Kong or other common law systems, a master's degree is preferred; if you have a Hong Kong legal education background, have completed the PCLL course, and a completion of the training contract is preferred\n4 years of experience in the legal affairs of multinational companies or well-known law firms, preferably with management experience;\nProfessional, rigorous and flexible, pragmatic, capable of execution and strong communication skills;\nProficient (writing and speaking) in Mandarin and English, other language skills will be a plus\nWork location: Hong Kong/Shenzhen; suitable for short-term business trips.", "employment_types": ["Full Time", "Temporary"], "selling_points": ["Daily legal affairs in HK and countries in APAC", "Four years of exp in MNCs or law firms", "5 days work with competitive package; start-up"], "locations": ["Kwai Fong"], "categories": ["Professional Services", "Legal & Compliance"], "post_time": "2022-01-17T02:32:18Z", "salary": {"currency": null, "max": null, "min": null, "period": "monthly", "term": null}, "salary_visible": false, "title_keywords": ["legal counsel"], "responsibilities": ["regulations", "management", "control", "policies", "compliance", "contract management", "other tasks"], "requirements": {"degrees": ["degree", "master degree", "master"], "majors": ["law"], "languages": ["english", "mandarin"], "language_level": ["proficient"], "hard_skills": ["plus"], "soft_skills": ["flexible", "communication skills", "capable"], "languages_combined": [{"language": "english", "language_level": ["proficient"]}, {"language": "mandarin", "language_level": ["proficient"]}]}, "experience_required": {"duration": ["4 years"], "field": ["management", "legal"]}}, {"job_id": "100003009054587", "location_code": "hk", "company": "ADECCO", "job_title": "Legal Executive (Trademark)", "description": "Our client, a leading bakery group in Hong Kong,\u00a0is expanding their winning team by looking for high-caliber candidates as\u00a0Legal Executive.\u00a0(4 Months Contract)\n\n\n\nJob Responsibilities\n\nHandle trademarks portfolio and maintain records\nWork with business team to provide the necessary legal support\u00a0\nDraft, review and approve agreements, contracts and other legal documents across the business to ensure rights and interests are protected\nAssist on other ad-hoc legal-related duties as requested\n\nJob Requirements\n\nHigher diploma in Legal Studies or related disciplines\nMinimum 2 years of work experience in legal field matters\nExcellent communications skills and proficiency in English and other languages (written & spoken)\nImmediate availability is highly preferred\n\nInterested parties, please CLICK HERE to apply online.\n\nOr if you would like to have a further discussion about this role, please Whatsapp Hoyin Siu at 9862 0297.\n\nPlease note that only short-listed candidates will be notified. All information gathered will be treated in strict confidence and solely used for recruitment purposes.", "employment_types": ["Full Time", "Temporary", "Contract"], "selling_points": [], "locations": ["Lai Chi Kok"], "categories": ["Professional Services", "Legal & Compliance"], "post_time": "2022-01-17T10:07:47Z", "salary": {"currency": "HKD", "max": 34999, "min": 25000, "period": "monthly", "term": null}, "salary_visible": true, "title_keywords": ["legal executive"], "responsibilities": ["ad-hoc", "contracts", "review", "maintain"], "requirements": {"degrees": ["diploma"], "majors": ["related disciplines"], "languages": ["english"], "language_level": ["excellent", "proficiency"], "hard_skills": [], "soft_skills": [], "languages_combined": [{"language": "english", "language_level": ["excellent", "proficiency"]}]}, "experience_required": {"duration": ["minimum 2 years"], "field": ["legal"]}}, {"job_id": "100003009052918", "location_code": "hk", "company": "JFE Consulting Limited", "job_title": "Paralegal - Civil Litigation", "description": "Our client, one of the leading law firms, is looking for high calires to join their winning team:-\n\nResponsibilities:\n\nProviding legal and administrative support\u00a0 (Civil Litigation lawyers)\nConducting pre-claim investigation, legal research and initial case assessments\nDrafting pleadings, motions and appellate documents and filing them with the court\nPerforming administrative duties (calendar hearings and deadlines, organize case files, manage logistics etc)\n\n\n\nRequirements:\n\nUniversity graduate with a law degree or related discipline\nProven working experience as a Litigation Paralegal\nApplicable knowledge of motions, discovery, evidence, litigation documentation, court rules and procedures, practices etc\nHighly organised with ability to juggle multiple deadlines in a fast-paced environment\nStrong writing and communication skills along with attention to detail\nExtensive computer and database expertise\n\n", "employment_types": ["Full Time", "Permanent"], "selling_points": ["Paralegal", "Civil Litigation", "5-day work; attractive salary"], "locations": ["Central"], "categories": ["Professional Services", "Company Secretary", "Legal & Compliance", "Translation"], "post_time": "2022-01-17T04:33:05Z", "salary": {"currency": null, "max": null, "min": null, "period": "monthly", "term": null}, "salary_visible": false, "title_keywords": ["paralegal"], "responsibilities": ["logistics", "administrative duties", "investigation", "administrative support"], "requirements": {"degrees": ["university graduate", "degree"], "majors": ["law"], "languages": [], "language_level": [], "hard_skills": ["documentation"], "soft_skills": ["communication skills", "fast-paced environment", "attention to detail", "organised", "extensive"], "languages_combined": []}, "experience_required": {"duration": [], "field": []}}, {"job_id": "100003009054486", "location_code": "hk", "company": "Tai & Co., Solicitors", "job_title": "Part-Time Helper (LLB Candidates)", "description": "Job Responsibilities:\u00a0\n\n\nWorking closely with and under the supervision of the solicitor on client matters and \u202fad-hoc \u202fassignments\u00a0\nProviding administrative support\u00a0\u00a0\nAssisting with client matters and conducting legal research, in addition to the above\u00a0\u00a0\n\nJob Requirements:\u00a0\n\n\nCurrent\u00a0LLB\u00a0students\u00a0\nHardworking, meticulous, responsible, well organized\u00a0and\u00a0ready to learn\u00a0\nGood command of English & Chinese will be an advantage\u00a0\nGood communication skills and good interpersonal skills\u00a0\nHandle ad-hoc duties as assigned\u00a0\nImmediate available is advantage\u00a0\n2nd year will also be considered\u00a0\nSalary, location\u00a0and working hours\u00a0can be negotiable\u00a0\n\n\nInterested parties please write your CV together with your present and expected salary to our Human Resources and Administration Department by clicking \"APPLY NOW\".\u2028\u2028(Personal data collected will be used for recruitment purpose only)\u00a0", "employment_types": ["Part Time"], "selling_points": [], "locations": ["Yau Tsim Mong Area"], "categories": ["Professional Services", "Legal & Compliance"], "post_time": "2022-01-17T16:21:05Z", "salary": {"currency": null, "max": null, "min": null, "period": "monthly", "term": null}, "salary_visible": false, "title_keywords": ["helper"], "responsibilities": ["ad-hoc", "administrative support"], "requirements": {"degrees": [], "majors": [], "languages": ["english", "chinese"], "language_level": ["advantage", "good command"], "hard_skills": [], "soft_skills": ["communication skills", "meticulous", "responsible", "well organized", "interpersonal skills", "ad-hoc duties", "hardworking"], "languages_combined": [{"language": "english", "language_level": ["advantage", "good command"]}, {"language": "chinese", "language_level": ["advantage", "good command"]}]}, "experience_required": {"duration": [], "field": []}}, {"job_id": "100003009054169", "location_code": "hk", "company": "Linklaters Business Services (H.K.) Limited", "job_title": "Analyst, Conflicts and Financial Crime, Legal & Risk", "description": "Role\n\nReporting to the Senior Advisor in Hong Kong, you will be a part of the Legal & Risk department.\nThe role primarily focuses on managing the firm\u2019s risk with regards to all new business acceptance, including conflicts checks, new client acceptance, anti-money laundering (AML) and reputational risk issues.\nResponsibilities\n\nInitiating and analyzing conflicts checks for new business in Intapp OPEN (firm's conflict checking system) and assisting with the resolution of legal and commercial conflicts with relevant stakeholders.\nConducting comprehensive CDD/AML checks on new business - clients, matters, and counterparties where appropriate.\nAdvising the firm and its lawyers on various queries related to new client acceptance, client identification procedures, AML queries, sanctions and reputational risk.\nChecking and clearing submitted new matter forms for completeness and errors/omissions.\nSetting up and maintaining information barriers to protect client confidential information.\nAdvising on the firm\u2019s client engagement terms policies, procedures and best practice.\nAssisting on various Legal & Risk projects and knowhow.\nWork closely with other members of the BA and Legal & Risk Department more broadly.\nLiaise with the practice and other Business Teams in relation to gathering information for basic conflict checks.\nEscalate any issues within the team or any complaints to BA Management or Senior Advisors/Analysts quickly and effectively to expedite resolution.\nProactively build relationships across the multi-cultural, multi-linguistic team by employing a collaborative approach, sharing skills & knowledge with others;\nMaintain a high level of professionalism and customer service to the practice.\nRequirements\n\nDegree holder or relevant experience\nMinimum of 1 year\u2019s previous experience in Conflicts, Compliance, Risk, AML or Financial Crime is preferred but not essential\nAbility to influence and motivate others along with hard-working and \u201ccan-do\u201d attitude\nTeam oriented and good at developing relationships with stakeholders across all levels\nAbility to cope under pressure, systematic, well organized and strong attention to detail\nComputer literate and ability to learn new IT systems quickly Fluency in English is mandatory and fluency in Chinese is advantageous\nThis list of duties and responsibilities above is not exhaustive. It is intended to describe the general content of, and requirements for, the performance of this job. As such, the role may also include the undertaking of additional tasks as required.", "employment_types": ["Full Time", "Permanent"], "selling_points": [], "locations": ["Central"], "categories": ["Professional Services", "Legal & Compliance"], "post_time": "2022-01-17T08:38:48Z", "salary": {"currency": null, "max": null, "min": null, "period": "monthly", "term": null}, "salary_visible": false, "title_keywords": ["analyst"], "responsibilities": ["management", "aml", "maintaining", "cdd", "policies", "procedures", "checking", "teams", "resolution", "maintain", "customer service", "liaise with"], "requirements": {"degrees": ["degree holder"], "majors": [], "languages": ["english", "chinese"], "language_level": ["fluency"], "hard_skills": ["aml"], "soft_skills": ["exhaustive", "under pressure", "well organized", "systematic", "hard-working", "can-do", "attention to detail"], "languages_combined": [{"language": "english", "language_level": ["fluency"]}, {"language": "chinese", "language_level": ["fluency"]}]}, "experience_required": {"duration": ["minimum of 1 year"], "field": ["compliance", "relevant experience", "financial"]}}, {"job_id": "100003009055916", "location_code": "hk", "company": "Michael Page", "job_title": "Legal Clerk / Court Clerk", "description": "Our client is one of the leading international law firms, they are looking for a junior legal clerk/ court clerk to join their litigation team in the Hong Kong office.\n\nClient Details\n\nOur client is a top-tier law firm with strong global presence, they have more than 30 offices across 6 continents.\n\nDescription\n\nProvide general assistance to a team of litigation lawyers (visit the court when needed)\nPrepare and file relevant legal and court documents\nCompile and organise trial materials\nConduct legal research\nPerform administrative and ad hoc duties as required\n\nProfile\n\nThe successful candidate should ideally have at least 1 year of legal clerk or court clerk experience. Proficient Cantonese is required for this role.\n\nJob Offer\n\nThe chosen candidate will be offered an excellent opportunity to join an international renowned law firm.", "employment_types": ["Full Time", "Permanent"], "selling_points": ["Top-tier Law Firm", "Litigation-focused", "1+ Year Experience"], "locations": ["Not Specified"], "categories": ["Professional Services", "Legal & Compliance"], "post_time": "2022-01-18T03:05:08Z", "salary": {"currency": null, "max": null, "min": null, "period": "monthly", "term": null}, "salary_visible": false, "title_keywords": ["clerk", "legal clerk"], "responsibilities": ["ad hoc duties"], "requirements": {"degrees": [], "majors": [], "languages": ["cantonese"], "language_level": ["proficient"], "hard_skills": [], "soft_skills": [], "languages_combined": [{"language": "cantonese", "language_level": ["proficient"]}]}, "experience_required": {"duration": ["at least 1 year"], "field": ["legal"]}}, {"job_id": "100003009052095", "location_code": "hk", "company": "UMP Healthcare Group", "job_title": "Company Secretary (Legal Department)", "description": "Job Duties and Responsibilities\n\n\n80% role in Company Secretry, 20% role in Paralegal\nReporting to General Counsel\u00a0\nDraft agreements and contracts, such as employment contracts and non-compete agreements.\nDrafting, filing and managing various corporate documents, including joint-venture agreements and investment agreements.\nResponsible for reviewing, tracking, and monitoring legislation that impacts the company\u2019s products and/or processes.\nAssist with Hong Kong Stock Exchange compliance including preparation of interim and annual reports.\nAssist with paperwork needed by regulatory bodies.\nUpdating leadership with timely analysis and summaries of new legislation/regulations affecting the business.\nAssists in implementing changes to contracts to comply with legislation/regulations.\nResponsible for support related to litigation, mediation, arbitration, and responses to complaints.\nRenewing and maintaining company licensing.\nCreate organizational documents, including articles of incorporation or dissolution, stock certificates and merger agreements.\nAssist with ethics and compliance programs.\nPerform legal research\nOrganizing and maintaining documents in a paper or electronic filing system.\n\nRequirements\n\n5 to 7 years relevant experience\nProficient with Microsoft Office, specifically Outlook, Word, and Excel.\nStrong oral and written communication skills.\nExcellent organizational skills.\nMust be able to effectively multi-task, manage time-sensitive documents and have exceptional organizational skills in a fast-paced environment.\nMust be able to function effectively in a busy, team-oriented environment.\n\nUMP Healthcare Group is an Equal Opportunity Employer. All qualified candidates will receive consideration for employment regardless of age, disability, protected veteran status, race, color, religious creed, national origin, citizenship, marital status, sex and sexual orientation or gender identity.\n\nPlease visit our website at: http://www2.ump.com.hk for more information about us.\n\nAll information obtained will be kept in strict confidence and used for recruitment and employment related purpose only.", "employment_types": ["Full Time", "Permanent"], "selling_points": ["Report to Legal Department", "5 to 7 years relevant experience", "Work in Central"], "locations": ["Central"], "categories": ["Professional Services", "Company Secretary", "Legal & Compliance"], "post_time": "2022-01-17T02:05:03Z", "salary": {"currency": null, "max": null, "min": null, "period": "monthly", "term": null}, "salary_visible": false, "title_keywords": ["company secretary"], "responsibilities": ["regulations", "reporting", "corporate documents", "maintaining", "contracts", "analysis", "monitoring", "compliance", "reports", "tracking"], "requirements": {"degrees": [], "majors": [], "languages": [], "language_level": [], "hard_skills": ["excel", "outlook", "word", "microsoft office"], "soft_skills": ["communication skills", "oral", "organizational skills", "multi-task", "confidence", "fast-paced environment", "sensitive"], "languages_combined": []}, "experience_required": {"duration": ["5 to 7 years"], "field": ["relevant experience"]}}, {"job_id": "100003009055617", "location_code": "hk", "company": "Cheung & Choy", "job_title": "SECRETARY", "description": "You will be responsible for:\n\n\u00a0\u00a0\u00a0\u00a0\u00a0\u00a0\u00a0\u00a0 Providing legal and administrative support to a team of Civil Litigation solicitors\n\u00a0\u00a0\u00a0\u00a0\u00a0\u00a0\u00a0\u00a0 Providing legal service to clients\n\u00a0\u00a0\u00a0\u00a0\u00a0\u00a0\u00a0\u00a0 Reviewing and drafting legal documents\n\u00a0\u00a0\u00a0\u00a0\u00a0\u00a0\u00a0\u00a0 Performing legal research\n\u00a0\u00a0\u00a0\u00a0\u00a0\u00a0\u00a0\u00a0 Preparing reports on a daily basis\n\u00a0\u00a0\u00a0\u00a0\u00a0\u00a0\u00a0\u00a0 Translating legal documents from Chinese into English, and vice versa\n\n\n\nQualifications and Personal Competencies:\n\n\u00a0\u00a0\u00a0\u00a0\u00a0\u00a0\u00a0\u00a0 University graduate with a law degree or related discipline\n\u00a0\u00a0\u00a0\u00a0\u00a0\u00a0\u00a0\u00a0 Litigation experience in the legal industry preferred\n\u00a0\u00a0\u00a0\u00a0\u00a0\u00a0\u00a0\u00a0 Excellent command of both written and spoken English and Chinese\n\u00a0\u00a0\u00a0\u00a0\u00a0\u00a0\u00a0\u00a0 Proficiency in MS applications including Chinese word processing\n\u00a0\u00a0\u00a0\u00a0\u00a0\u00a0\u00a0\u00a0 Strong time-management skills\n\u00a0\u00a0\u00a0\u00a0\u00a0\u00a0\u00a0\u00a0 Good inter-personal and teamwork skills\n\u00a0\u00a0\u00a0\u00a0\u00a0\u00a0\u00a0\u00a0 Adaptable and flexible\n\u00a0\u00a0\u00a0\u00a0\u00a0\u00a0\u00a0\u00a0 Availability at short notice\n\n\n\nWe offer competitive remuneration package to the right candidate and have a 5-day work-week.\n\n\n\nTo apply:\n\nPlease send your full resume with current and expected salary to career@ haldanes.com.\n\n\nPersonal Data Privacy Information\n\nAll applications will be treated in strict confidence and used for employment-related purposes.\u00a0 Candidates should consider their application unsuccessful if not being invited for interview within 6 weeks from your date of application.", "employment_types": ["Full Time", "Permanent"], "selling_points": ["Form 6 or above", "Strong sense of responsibility, flexible", "Proficient in PC skills"], "locations": ["Sheung Wan"], "categories": ["Professional Services", "Legal & Compliance"], "post_time": "2022-01-18T02:53:40Z", "salary": {"currency": null, "max": null, "min": null, "period": "monthly", "term": null}, "salary_visible": false, "title_keywords": ["secretary"], "responsibilities": ["management", "preparing reports", "administrative support"], "requirements": {"degrees": ["university graduate", "degree"], "majors": ["law"], "languages": ["english", "chinese"], "language_level": ["excellent", "proficiency"], "hard_skills": ["chinese word processing", "ms applications"], "soft_skills": ["flexible", "responsible", "inter-personal", "adaptable", "teamwork"], "languages_combined": [{"language": "english", "language_level": ["excellent"]}, {"language": "chinese", "language_level": ["excellent", "proficiency"]}]}, "experience_required": {"duration": [], "field": ["legal"]}}, {"job_id": "100003009052115", "location_code": "hk", "company": "Tricor Services Limited", "job_title": "Paralegal", "description": "\nRequirements:-\nResponsible for full range of secretarial duties\nPrepare, edit, and format legal documents\nPerforming ad hoc tasks\u00a0\nForm 6 or above\nRelevant experience preferably\nAble to communicate effectively in English, Cantonese and preferably Mandarin\nProficient in PC skills including Microsoft Applications and Chinese Word processing\nStrong sense of responsibility, flexible, self-motivated and well-organized\nAble to work independently, under pressure and multi-tasking\nImmediately available or short notice will be an advantage\n\nInterested parties, please send your full CV stating your availability, current and expected salary with quoting the job reference number by clicking \"Apply Now\"\n\n\nAll personal data collected will be treated in strict confidence and be used for recruitment purpose only. Unsuccessful applications will be destroyed after 3 months.", "employment_types": ["Full Time", "Permanent"], "selling_points": ["Legal and compliance", "5 years legal experience", "Paralegal"], "locations": ["Ngau Tau Kok"], "categories": ["Professional Services", "Business Consultancy", "Legal & Compliance"], "post_time": "2022-01-17T02:07:47Z", "salary": {"currency": null, "max": null, "min": null, "period": null, "term": null}, "salary_visible": false, "title_keywords": ["paralegal"], "responsibilities": ["ad hoc tasks"], "requirements": {"degrees": [], "majors": [], "languages": ["cantonese", "english", "chinese", "mandarin"], "language_level": ["proficient"], "hard_skills": ["pc skills", "chinese word processing", "microsoft applications"], "soft_skills": ["flexible", "self-motivated", "work independently", "under pressure", "responsible", "sense of responsibility", "well-organized", "multi-tasking"], "languages_combined": [{"language": "cantonese", "language_level": []}, {"language": "english", "language_level": []}, {"language": "chinese", "language_level": ["proficient"]}, {"language": "mandarin", "language_level": []}]}, "experience_required": {"duration": [], "field": ["relevant experience"]}}, {"job_id": "100003009051369", "location_code": "hk", "company": "Willa Legal", "job_title": "Paralegal / Legal Assistant", "description": "Reporting to Head of Legal, you are responsible to provide legal, compliance and secretarial/administration support and handle all relevant matters\n\nWhat the job role is:\n\nReview and comment on legal agreements or documents (client engagement agreement, confidentiality agreement, etc.\nCommunicate with different internal business departments for comments on the legal agreements, documentations and policies\nProvide secretarial/administration support to the legal team\nConduct legal research and assist on ad hoc projects\n\nWho we are looking for:\n\nDegree holder in Law is preferred\nApproximately 5 years legal experience as a paralegal\nSolid experience in reviewing and commenting on legal agreements and contracts written in Simplified/Traditional Chinese, English/Chinese or English only\nExperience or knowledge in company secretarial duties\u00a0is a plus\nWell versed in MS applications (PowerPoint, Excel, Word)\nExcellent command of written and spoken English and Chinese\n\nWe offer successful candidate 15-day annual leave, birthday leave, 5-day work, excellent job exposure and career prospects.\n\nApplicants should send their full C.V. and expected salary to Human Resources Department by clicking \u201cApply Now\u201d. Please quote ref. \"Paralegal\u201d on your application.\n\nPersonal data provided by job applicants will be used strictly in accordance with the employer's personal data policy, a copy of which will be provided upon request.\u00a0", "employment_types": ["Full Time"], "selling_points": [], "locations": ["Central"], "categories": ["Professional Services", "Legal & Compliance"], "post_time": "2022-01-15T12:07:16Z", "salary": {"currency": null, "max": null, "min": null, "period": "monthly", "term": null}, "salary_visible": false, "title_keywords": ["paralegal", "legal assistant"], "responsibilities": ["communicate with", "reporting", "policies", "contracts", "review", "compliance", "comments", "ad hoc projects", "administration"], "requirements": {"degrees": ["degree holder"], "majors": ["law"], "languages": ["english", "chinese"], "language_level": ["excellent"], "hard_skills": ["excel", "plus", "ms applications", "word", "powerpoint", "documentations"], "soft_skills": ["responsible"], "languages_combined": [{"language": "english", "language_level": ["excellent"]}, {"language": "chinese", "language_level": ["excellent"]}]}, "experience_required": {"duration": ["5 years"], "field": ["secretarial", "legal"]}}, {"job_id": "100003009056191", "location_code": "hk", "company": "JFE Consulting Limited", "job_title": "HR Assistant/Secretary - LEGAL", "description": "Willa Legal, a young and energetic Hong Kong law firm focusing on private fund formation matters, is hiring a paralegal/legal assistant. The successful candidate will work with the Founding Principal to manage and execute client matters, research on developments around fund-related laws and regulations and create presentation materials.\u00a0\n\n\u00a0Responsibilities\n\nDraft, amend and incorporate comments on legal documents including without limitation limited partnership agreements, private placement memoranda, side letters, investment management agreements, subscription agreements, non-disclosure agreements etc;\nCoordinate and lead closings and launch of funds; Prepare signing pack;\u00a0\nResearch and summarise developments on fund and fund management-related laws, regulations and policies;\nDraft and prepare research memo, presentation materials and client alerts and publication;\u00a0\nDraft engagement letters and collate and review KYC/AML documents provided by clients;\u00a0\nOrganize and maintain an accurate and up-to-date records for client folders; and\nOther reasonable duties as assigned from time to time.\u00a0\n\n\u00a0Qualifications\n\nLLB degree in Hong Kong or other common law jurisdictions.\nGood command of both written\u00a0and spoken English and Chinese (Cantonese and Mandarin Chinese).\nEfficient word processing ability in both English and Chinese and in using Acrobat and PowerPoint.\nAttentive to detail, organized, efficient, conscientious, analytical and problem solving.\nMature, quick to pick up new concepts and practices, and be able to independently work on repeated tasks.\nExperience in funds, capital markets, M&A, banking or other transactional practice in a law firm is highly preferred. Nevertheless, fresh graduates with a can-do attitude and good work ethics will also be considered.\u00a0\n\nPersonal Information Collection Statement\n\nAll information collected from and provided by the applicant to Willa Legal will be kept strictly confidential and solely used by Willa Legal, and Willa Services Limited, for assessing the applicant's suitability for the position. The applicant may make a request to access to, and to request correction of, his/her own personal data provided by the applicant to Willa Legal by contacting Willa Legal by email. Willa Legal has the right to charge a reasonable fee for processing applicant\u2019s data access and correction request. All personal data of applicants that are not employees of Willa Legal will be kept for a period of 12 months from the application date and will be destroyed afterwards.", "employment_types": ["Full Time", "Permanent"], "selling_points": ["Leading law firm", "HR Assistant/Legal Secretary", "5-day work, attractive salary"], "locations": ["Central"], "categories": ["Professional Services", "Company Secretary", "Legal & Compliance", "Translation"], "post_time": "2022-01-18T03:31:02Z", "salary": {"currency": null, "max": null, "min": null, "period": "monthly", "term": null}, "salary_visible": false, "title_keywords": ["secretary", "hr assistant"], "responsibilities": ["regulations", "management", "aml", "memo", "data", "policies", "comments", "letters", "review", "banking", "coordinate", "maintain", "kyc", "personal data", "publication"], "requirements": {"degrees": ["degree"], "majors": ["law"], "languages": ["cantonese", "english", "chinese", "mandarin chinese"], "language_level": ["good command"], "hard_skills": ["aml", "acrobat", "word processing", "powerpoint", "problem solving", "make", "kyc", "processing"], "soft_skills": ["efficient", "organized", "independently", "attentive to detail", "accurate", "can-do attitude", "mature", "problem solving", "conscientious", "energetic", "presentation"], "languages_combined": [{"language": "cantonese", "language_level": ["good command"]}, {"language": "english", "language_level": ["good command"]}, {"language": "chinese", "language_level": ["good command"]}, {"language": "mandarin chinese", "language_level": ["good command"]}]}, "experience_required": {"duration": [], "field": ["capital markets", "banking"]}}, {"job_id": "100003009054375", "location_code": "hk", "company": "Bright Smart Securities International (H.K.) Limited", "job_title": "Compliance Officer", "description": "Our client, one of the leading law firms, is looking for high calibres to join their winning team:-\n\nResponsiblities:\n\nPrepares variety of legal documents under guidance of staff attorneys and firm management, including summonses, subpoenas, complaints, and responses\nSupports attorney trial proceedings, assisting in collecting evidence, compiling artefacts, consolidating facts, preparing documents as needed, and tracking cases\nDevelops cases by providing research for assigned attorney, maintaining communications with involved parties, and cataloguing information provided\nMaintains regular communication with clients, helping to keep them informed on case progresses\nRequirements:\n\nDiploma/Bachelor's degree preferred\nMinimu two-year degree required.\nExperience working in a legal setting strongly preferred.\nStrong analytical skills, ability to work as part of a team.", "employment_types": ["Full Time", "Permanent"], "selling_points": [], "locations": ["Central"], "categories": ["Banking / Finance", "Others", "Professional Services", "Company Secretary", "Legal & Compliance"], "post_time": "2022-01-17T09:18:38Z", "salary": {"currency": null, "max": null, "min": null, "period": "monthly", "term": null}, "salary_visible": false, "title_keywords": ["compliance officer"], "responsibilities": ["guidance", "management", "communications with", "maintaining", "communication", "tracking"], "requirements": {"degrees": ["diploma", "degree", "bachelor"], "majors": [], "languages": [], "language_level": [], "hard_skills": ["analytical skills"], "soft_skills": ["analytical skills"], "languages_combined": []}, "experience_required": {"duration": [], "field": ["legal"]}}, {"job_id": "100003009056615", "location_code": "hk", "company": "WILLIAM KW LEUNG & CO", "job_title": "Account Clerk / Legal Secretary", "description": "Responsibilities:\n\n\nHandle general enquiries from SFC, HKEx and other regulators;\nCoordinate and liaise with regulators and frontline staffs on all licensing matters;\nPerform compliance monitoring such as declaration of staff dealing and fulfillment of CPT requirement;\nFacilitate the regulatory inspection and prepare documents/responses as required;\nAssist in consultation raised by operation team relating to compliance issues;\nKeep abreast of new regulatory requirements and update compliance policies and procedures;\nUndertake other ad hoc projects as required.\n\nRequirement & Qualifications:\n\n\nDegree in Accountancy, Finance, Law or related subjects;\nAt least 4 years or above relevant experiences in securities firm or financial institution;\nWell versed with SFO, KYC, AML guidelines and other regulatory requirements;\nGood understanding of securities products and operations;\nHardworking, self-motivated and a good team player;\nGood command of written and spoken English and Cantonese;\nProficient in MS Office and Chinese Word Processing.\n\nWe Offer:\n\nCompetitive remuneration package\n5 Days Work & Bank Holidays\nAttendance Bonus\nMeal Allowance\nDiscretionary Bonus\nMedical Insurance\nOn the Job Training\n\nWe provide attractive remuneration package and fringe benefits for the right candidate. Interested parties please send detailed resume with current and expected salaries to\u00a0Human Resources Department by clicking \"Apply Now\" or fax to: 2530 2218.\n\nAll information collected will be used for recruitment purpose only, only shortlisted candidates will be notified.\n\nWelcome to visit our website: http://www.bsgroup.com.hk/ for more information.", "employment_types": ["Full Time"], "selling_points": ["Openings in a thriving law firm in Central", "Competitive salary and commensurate experience", "Immediate availability will be an advantage"], "locations": ["Central"], "categories": ["Accounting", "Accounting Clerk / Supervisor", "Admin & HR", "Secretary", "Professional Services", "Legal & Compliance"], "post_time": "2022-01-18T05:08:43Z", "salary": {"currency": null, "max": null, "min": null, "period": "monthly", "term": null}, "salary_visible": false, "title_keywords": ["legal secretary", "account clerk"], "responsibilities": ["regulatory requirements", "fulfillment", "monitoring", "compliance", "policies", "procedures", "inspection", "coordinate", "ad hoc projects", "liaise with", "prepare documents"], "requirements": {"degrees": ["degree"], "majors": ["finance", "law", "accountancy"], "languages": ["cantonese", "english", "chinese"], "language_level": ["good command", "proficient"], "hard_skills": ["chinese word processing", "aml", "kyc", "sfo", "ms office"], "soft_skills": ["good team player", "self-motivated", "hardworking"], "languages_combined": [{"language": "cantonese", "language_level": ["good command"]}, {"language": "english", "language_level": ["good command"]}, {"language": "chinese", "language_level": ["proficient"]}]}, "experience_required": {"duration": ["at least 4 years"], "field": ["securities firm", "financial"]}}, {"job_id": "100003009056199", "location_code": "hk", "company": "ME Job Personnel Limited", "job_title": "Legal Office / Intellectual Property Officer", "description": "We are an expanding boutique law firm in Central specializing in corporate, commercial litigation and international arbitration. We are looking for an Account Clerk / Legal Secretary to join our team.\n\nAccount Clerk\n\nRequirements:\n\nHandle full set accounts including preparing vouchers, receipts, ledgers, cheques and financial reports;\nHandle daily accounting operations and maintain accounting records;\nPrepare for daily bank balance, bank reconciliation and transaction reports, cash-flow, budget and analysis;\nConduct month-end closing activities including bill settlement, profit and loss statement, expenses payment;\nLCCI intermediate level or above;\nKnowledge of Peachtree will be an advantage;\n1-year or above account experience and audit experience in a law firm is preferred;\n\nLegal Secretary\n\nRequirements:\n\nMatriculated or above;\nGood command of written and spoken English and Chinese\u00a0languages (Cantonese/Mandarin);\nProficient in PC skills, including MS Office applications, Chinese word processing, and document formatting;\nProvide administrative and secretarial support to lawyers;\nHandle incoming / outgoing calls or emails in a courteous manner;\nAssist in preparing and editing legal documents;\nOrganized, self-motivated, responsible, attentive to details, and quality-oriented\n\nAttractive salary and benefits will be offered to the right candidate. For more information about the firm, please visit\u00a0www.jwlw.com.\n\nIf you are interested in the above position, please apply with full resume and expected salary by clicking \u201cApply Now\u201d.", "employment_types": ["Full Time"], "selling_points": [], "locations": ["Central"], "categories": ["Professional Services", "Business Analysis / Data Analysis", "Legal & Compliance", "Marketing / Public Relations", "Marketing - Brand / Product Management"], "post_time": "2022-01-18T03:32:00Z", "salary": {"currency": null, "max": null, "min": null, "period": "monthly", "term": null}, "salary_visible": false, "title_keywords": ["property officer"], "responsibilities": ["financial reports", "receipts", "preparing vouchers", "analysis", "budget", "expenses", "daily accounting operations", "bank reconciliation", "audit", "quality", "cheques", "maintain", "reports", "month-end closing", "payment", "formatting", "secretarial support", "editing"], "requirements": {"degrees": [], "majors": [], "languages": ["cantonese", "english", "chinese", "mandarin"], "language_level": ["good command", "proficient"], "hard_skills": ["chinese word processing", "analysis", "peachtree", "pc skills", "ms office"], "soft_skills": ["outgoing", "organized", "courteous", "self-motivated", "responsible", "attentive to details"], "languages_combined": [{"language": "cantonese", "language_level": ["good command"]}, {"language": "english", "language_level": ["good command"]}, {"language": "chinese", "language_level": ["good command", "proficient"]}, {"language": "mandarin", "language_level": ["good command"]}]}, "experience_required": {"duration": ["1-year"], "field": ["audit experience"]}}, {"job_id": "100003009052596", "location_code": "hk", "company": "King and Company, Solicitors & Notaries", "job_title": "Litigation Clerk", "description": "LL.B, Legal Diploma, or Form 7 undertaking LL.B. program;\u00a0\nLaw firm experience preferred but not a must\nGood work attitude, honest, reliable, details oriented, diligent;\u00a0\nGood commands of English/Chinese;\u00a0\nChinese language not\u00a0must for native English speaker;\nComputer literate;\u00a0\nimmediate available preferred\u00a0\n\nBenefits:\n\nPerformance/Year End Bonus\nMedical Insurance\n\n*Interested candidate send your application with cover letter and CV (including last salary and expected salary);\u00a0 previous applicant not selected for interview is also welcome to apply;\u00a0 clicking \"Apply Now\" Attn: Ms. Kwok or via website https://www..evaklawfirm.com\n\npersonal data collected will be used for recruitment purpose only.", "employment_types": ["Full Time"], "selling_points": [], "locations": ["Central"], "categories": ["Professional Services", "Legal & Compliance"], "post_time": "2022-01-17T03:30:01Z", "salary": {"currency": null, "max": null, "min": null, "period": "monthly", "term": null}, "salary_visible": false, "title_keywords": ["clerk"], "responsibilities": [], "requirements": {"degrees": ["diploma"], "majors": [], "languages": ["english", "chinese"], "language_level": ["native", "good"], "hard_skills": [], "soft_skills": ["reliable", "diligent", "honest"], "languages_combined": [{"language": "english", "language_level": ["native", "good"]}, {"language": "chinese", "language_level": ["native", "good"]}]}, "experience_required": {"duration": [], "field": []}}, {"job_id": "100003009053894", "location_code": "hk", "company": "Spruson & Ferguson (Hong Kong) Limited", "job_title": "Trademark Specialist / Executive", "description": "One Seizable Company is URGENTLY looking for a suitable candidate for the Legal Management position.\n\n\u00a0\nJob Description:\n\nHandle a portfolio of intellectual property registrations, disputes and infringement matters, legal documentations in support of the company\u2019s business.\nPerform legal researches and conduct company due diligence for the purpose of ensuring compliance of laws & regulations and in support of the company\u2019s project]\nProvide legal advice and assist to resolve issues in consultation with the\u00a0 all legal and IP documents management.\n\n\u00a0Qualifications:\n\nHigh Diploma or above in Law.\nAt least 3-5 years experience in\u00a0handle\u00a0law field of Worldwide IP & Trademark documents\nStrong business acumen, with good analytical and communication skills.\nPositive attitude, mature and detailed mind, independent, self-motivated, strong sense of responsibility and willing to learn.\nExcellent command of both spoken and written Chinese and English\n\n\u00a0Location : Central\u00a0\n\nSalary : 30K-40K\n\n\nOur clients have offered a comprehensive benefits package to the successful candidate.\u00a0\n\nInterested parties, please send a detailed resume by clicking \"Apply Now\" (ATTN : Eddy.Tse) Hotline : 27066333.\u00a0\n\n\u00a0All information collected is strictly for recruitment purpose.\u00a0", "employment_types": ["Full Time", "Permanent"], "selling_points": ["HK or overseas qualified legal professional", "1-3 years' PQE preferred", "5 days work, up to 3 months bonus"], "locations": ["Wan Chai"], "categories": ["Professional Services", "Business Consultancy", "Legal & Compliance", "Translation"], "post_time": "2022-01-17T07:42:51Z", "salary": {"currency": null, "max": null, "min": null, "period": "monthly", "term": null}, "salary_visible": false, "title_keywords": ["specialist", "executive"], "responsibilities": ["regulations", "due diligence", "management", "compliance", "communication"], "requirements": {"degrees": ["high diploma or above"], "majors": ["law"], "languages": ["english", "chinese"], "language_level": ["excellent"], "hard_skills": ["ip", "documentations", "acumen"], "soft_skills": ["communication skills", "self-motivated", "independent", "sense of responsibility", "willing to learn", "mature", "positive attitude", "business acumen", "detailed mind"], "languages_combined": [{"language": "english", "language_level": ["excellent"]}, {"language": "chinese", "language_level": ["excellent"]}]}, "experience_required": {"duration": ["at least 3-5 years"], "field": []}}, {"job_id": "100003009052377", "location_code": "hk", "company": "Langham Hall Hong Kong Limited", "job_title": "Compliance Graduate", "description": "Requirements:\n\nAt least 1 year's relevant experience\u00a0\nGood command of English & Chinese\nWilling to learn\nTraining will be provided\nImmediate available is preferred\n\nInterested candidates please send your full resume with current & expected salary to 8/F Asia Standard Tower, 59-65 Queen\u2019s Road Central, Hong Kong or by email through \"Apply Now\".\u00a0 Personal data collected will be used for recruitment purpose only.", "employment_types": ["Full Time", "Permanent"], "selling_points": [], "locations": ["Central"], "categories": ["Professional Services", "Legal & Compliance"], "post_time": "2022-01-17T02:53:34Z", "salary": {"currency": null, "max": null, "min": null, "period": "monthly", "term": null}, "salary_visible": false, "title_keywords": [], "responsibilities": [], "requirements": {"degrees": [], "majors": [], "languages": ["english", "chinese"], "language_level": ["good command"], "hard_skills": [], "soft_skills": ["willing to learn"], "languages_combined": [{"language": "english", "language_level": ["good command"]}, {"language": "chinese", "language_level": ["good command"]}]}, "experience_required": {"duration": ["at least 1 year"], "field": ["relevant experience"]}}, {"job_id": "100003009051280", "location_code": "hk", "company": "Hutchison Telecommunications (Hong Kong) Limited", "job_title": "Legal Officer", "description": "Responsibilities:\n\nReview legal documents include Contracts, Tenancy and License Agreement\nLiaise with Company Secretary on Annual Returns, Invoices, etc. for various group companies\nMaintain and provide the up-to-date corporate information and proper filing\nProvide support on regular reporting to Office of the Communication Authority, and also enquiries from government agencies\n\nRequirements:\n\nDiploma holder in legal studies or equivalent\u00a0\n3-10 years experiences in legal firm or in legal department\nGood knowledge and experience in leasing and tenancy matters\nExperience in telecommunications industry is preferable\nConscientious, diligent, and a good team player with good analytical and interpersonal and communication skills\nExcellent command of both spoken and written English and Chinese\n\nApart from competitive remuneration package and exciting opportunity for career development within the Group, we provide attractive employee benefits such as free company shuttle, free company SIM card and preferential SIM plan offers, comprehensive medical & insurance schemes, as well as full range of other employee well-being provisions.\u00a0\u00a0\n\nInterested parties, please apply with full resume, present and expected salary, by clicking \u201cAPPLY NOW\u201d.\u00a0\n\nWe are an equal opportunity employer and welcome applications from all qualified candidates. Personal data collected will be treated in the strictest confidence and handled confidentially by authorised personnel for recruitment-related purposes only within the CK Hutchison Group of companies. The personal data of unsuccessful applicants will be destroyed after the recruitment exercise pursuant to the requirements of the Personal Data (Privacy) Ordinance in Hong Kong.", "employment_types": ["Full Time", "Permanent"], "selling_points": [], "locations": ["Tsing Yi"], "categories": ["Professional Services", "Legal & Compliance"], "post_time": "2022-01-15T07:15:44Z", "salary": {"currency": null, "max": null, "min": null, "period": "monthly", "term": null}, "salary_visible": false, "title_keywords": ["officer"], "responsibilities": ["reporting", "provide support", "invoices", "contracts", "review", "communication", "maintain", "liaise with"], "requirements": {"degrees": ["diploma holder"], "majors": [], "languages": ["english", "chinese"], "language_level": ["excellent"], "hard_skills": [], "soft_skills": ["communication skills", "good team player", "diligent", "comprehensive", "conscientious", "interpersonal"], "languages_combined": [{"language": "english", "language_level": ["excellent"]}, {"language": "chinese", "language_level": ["excellent"]}]}, "experience_required": {"duration": ["3-10 years"], "field": ["telecommunications", "legal"]}}, {"job_id": "100003009049166", "location_code": "hk", "company": "Haldanes", "job_title": "Paralegal - Civil Litigation", "description": "You will be responsible for:\n\n\u00a0\u00a0\u00a0\u00a0\u00a0\u00a0\u00a0\u00a0 Providing legal and administrative support to a team of Civil Litigation solicitors\n\u00a0\u00a0\u00a0\u00a0\u00a0\u00a0\u00a0\u00a0 Providing legal service to clients\n\u00a0\u00a0\u00a0\u00a0\u00a0\u00a0\u00a0\u00a0 Reviewing and drafting legal documents\n\u00a0\u00a0\u00a0\u00a0\u00a0\u00a0\u00a0\u00a0 Performing legal research\n\u00a0\u00a0\u00a0\u00a0\u00a0\u00a0\u00a0\u00a0 Preparing reports on a daily basis\n\u00a0\u00a0\u00a0\u00a0\u00a0\u00a0\u00a0\u00a0 Translating legal documents from Chinese into English, and vice versa\n\n\n\nQualifications and Personal Competencies:\n\n\u00a0\u00a0\u00a0\u00a0\u00a0\u00a0\u00a0\u00a0 University graduate with a law degree or related discipline\n\u00a0\u00a0\u00a0\u00a0\u00a0\u00a0\u00a0\u00a0 Litigation experience in the legal industry preferred\n\u00a0\u00a0\u00a0\u00a0\u00a0\u00a0\u00a0\u00a0 Excellent command of both written and spoken English and Chinese\n\u00a0\u00a0\u00a0\u00a0\u00a0\u00a0\u00a0\u00a0 Proficiency in MS applications including Chinese word processing\n\u00a0\u00a0\u00a0\u00a0\u00a0\u00a0\u00a0\u00a0 Strong time-management skills\n\u00a0\u00a0\u00a0\u00a0\u00a0\u00a0\u00a0\u00a0 Good inter-personal and teamwork skills\n\u00a0\u00a0\u00a0\u00a0\u00a0\u00a0\u00a0\u00a0 Adaptable and flexible\n\u00a0\u00a0\u00a0\u00a0\u00a0\u00a0\u00a0\u00a0 Availability at short notice\n\n\n\nWe offer competitive remuneration package to the right candidate and have a 5-day work-week.\n\n\n\nTo apply:\n\nPlease send your full resume with current and expected salary to career@ haldanes.com.\n\n\nPersonal Data Privacy Information\n\nAll applications will be treated in strict confidence and used for employment-related purposes.\u00a0 Candidates should consider their application unsuccessful if not being invited for interview within 6 weeks from your date of application.", "employment_types": ["Full Time", "Permanent"], "selling_points": [], "locations": ["Central"], "categories": ["Professional Services", "Legal & Compliance"], "post_time": "2022-01-14T08:12:32Z", "salary": {"currency": null, "max": null, "min": null, "period": "monthly", "term": null}, "salary_visible": false, "title_keywords": ["paralegal"], "responsibilities": ["management", "preparing reports", "administrative support"], "requirements": {"degrees": ["university graduate", "degree"], "majors": ["law"], "languages": ["english", "chinese"], "language_level": ["excellent", "proficiency"], "hard_skills": ["chinese word processing", "ms applications"], "soft_skills": ["flexible", "responsible", "inter-personal", "adaptable", "teamwork"], "languages_combined": [{"language": "english", "language_level": ["excellent"]}, {"language": "chinese", "language_level": ["excellent", "proficiency"]}]}, "experience_required": {"duration": [], "field": ["legal"]}}, {"job_id": "100003009051251", "location_code": "hk", "company": "Eva Kwok & Co., Solicitors", "job_title": "Paralegal/Legal Clerk", "description": "LL.B, Legal Diploma, or Form 7 undertaking LL.B. program;\u00a0\nLaw firm experience preferred but not a must\nGood work attitude, honest, reliable, details oriented, diligent;\u00a0\nGood commands of English/Chinese;\u00a0\nChinese language not\u00a0must for native English speaker;\nComputer literate;\u00a0\nimmediate available preferred\u00a0\n\nBenefits:\n\nPerformance/Year End Bonus\nMedical Insurance\n\n*Interested candidate send your application with cover letter and CV (including last salary and expected salary);\u00a0 previous applicant not selected for interview is also welcome to apply;\u00a0 clicking \"Apply Now\" Attn: Ms. Kwok or via website https://www..evaklawfirm.com\n\npersonal data collected will be used for recruitment purpose only.", "employment_types": ["Full Time", "Permanent"], "selling_points": [], "locations": ["Central"], "categories": ["Professional Services", "Legal & Compliance"], "post_time": "2022-01-15T06:19:57Z", "salary": {"currency": null, "max": null, "min": null, "period": "monthly", "term": null}, "salary_visible": false, "title_keywords": ["paralegal", "legal clerk"], "responsibilities": [], "requirements": {"degrees": ["diploma"], "majors": [], "languages": ["english", "chinese"], "language_level": ["native", "good"], "hard_skills": [], "soft_skills": ["reliable", "diligent", "honest"], "languages_combined": [{"language": "english", "language_level": ["native", "good"]}, {"language": "chinese", "language_level": ["native", "good"]}]}, "experience_required": {"duration": [], "field": []}}, {"job_id": "100003009048386", "location_code": "hk", "company": "HGC Global Communications Limited", "job_title": "Legal Assistant", "description": "Job Responsibilities:\n\nTo provide full range of support to Legal Counsels;\nTo Liaise with internal and external parties for work coordination;\nTo prepare and draft routine correspondences;\nHandle ad hoc tasks as assigned.\n\nJob Requirements:\n\nFrom 5 or DSE or above;\nMin. 4 years of secretarial or administrative experience in sizable organization, preferable in legal department;\nStrong interpersonal skills and communication skills;\nProactive, positive attitude, well organized, strong attention to details and able to work independently;\nProficiency in English and Chinese typing;\nGood PC skills in MS Word and Excel;\nGood command of written and spoken Chinese and English, proficient in Mandarin preferred.\n\nWe offer competitive salary package and career development opportunity. Free company coach is provided.\u00a0 Interested parties, please quote our reference number and apply with full resume, present and expected salary, by clicking \u201cAPPLY NOW\u201d.\u00a0\n\nWe are an equal opportunity employer and welcome applications from all qualified candidates. Information provided will be treated in strict confidence and only be used for consideration of your application for the relevant post within HGC Global Communications Limited. Personal data provided by job applicants will be used strictly according to our Personal Information Collection Statement, a copy of which will be available upon written request. Information of unsuccessful candidates will be destroyed within six months.", "employment_types": ["Full Time", "Permanent"], "selling_points": ["Min. 4 years of secretarial exp. in Legal Dept.", "Provide full range of support to Legal Counsels", "Liaise with internal and external parties"], "locations": ["Tsing Yi"], "categories": ["Admin & HR", "Secretary", "Professional Services", "Legal & Compliance"], "post_time": "2022-01-14T06:27:17Z", "salary": {"currency": null, "max": null, "min": null, "period": "monthly", "term": null}, "salary_visible": false, "title_keywords": ["legal assistant"], "responsibilities": ["liaise with", "internal and external parties", "ad hoc tasks", "coordination"], "requirements": {"degrees": ["dse"], "majors": [], "languages": ["english", "chinese", "mandarin"], "language_level": ["proficiency", "good command", "proficient"], "hard_skills": ["excel", "pc skills", "typing", "ms word"], "soft_skills": ["communication skills", "work independently", "well organized", "positive attitude", "interpersonal skills", "attention to details", "proactive"], "languages_combined": [{"language": "english", "language_level": ["proficiency", "good command"]}, {"language": "chinese", "language_level": ["proficient", "proficiency", "good command"]}, {"language": "mandarin", "language_level": ["good command"]}]}, "experience_required": {"duration": ["4 years"], "field": ["sizable organization", "secretarial", "administrative", "legal"]}}, {"job_id": "100003009054762", "location_code": "hk", "company": "Public Finance Limited", "job_title": "Compliance Officers", "description": "Responsibilities:\nAssist in reviewing policies and/or conducting compliance control/audit\nPrepare compliance reports for management review\nRequirements:\nDegree holder\nSome practical experience in compliance control or auditing is preferred but not a must\nThose candidates without compliance control experience but engaging in auditing field are welcome\nGood command in both spoken and written English\nSelf-motivated, good communication and interpersonal skills\nCandidates with less experience will be considered as Compliance Assistant\nBenefits\nDouble Pay\nDiscretionary Bonus\nInsurance Benefits\nStudy subsidy\nApplication Method:\n\nBy Whatsapp : 9309 2925\nBy E-mail via \"Apply Now\"\nPersonal data collected will be treated in the strictest confidence in accordance with our\u00a0Personal Information Collection Statement\u00a0and\u00a0Privacy Policy\u00a0and will be handled by authorized personnel for recruitment-related purposes only. All applications will be kept for a maximum period of one year as may be considered for other suitable positions within Public Finance Ltd. and its associated companies. For details, please visit the Company\u2019s website\u00a0http://www.publicfinance.com.hk", "employment_types": ["Full Time", "Permanent"], "selling_points": [], "locations": ["Not Specified"], "categories": ["Accounting", "Audit", "Banking / Finance", "Others", "Professional Services", "Legal & Compliance"], "post_time": "2022-01-17T10:59:01Z", "salary": {"currency": null, "max": null, "min": null, "period": "monthly", "term": null}, "salary_visible": false, "title_keywords": [], "responsibilities": ["control", "policies", "compliance", "audit", "reports", "management review"], "requirements": {"degrees": ["degree holder"], "majors": [], "languages": ["english"], "language_level": ["good command"], "hard_skills": [], "soft_skills": ["self-motivated", "communication and interpersonal skills"], "languages_combined": [{"language": "english", "language_level": ["good command"]}]}, "experience_required": {"duration": [], "field": ["compliance"]}}, {"job_id": "100003009052831", "location_code": "hk", "company": "Woo Kwan Lee & Lo", "job_title": "Junior Secretary", "description": "Fresh graduate (Form 6 (DSE)/Diploma of Legal Studies)\nCommand of written and spoken English, Cantonese and Mandarin\nWorking experience not required\nGood computer skills\nMature, independent and hardworking\n\n\nInterested parties please send detailed CV with expected salary by apply now.", "employment_types": ["Full Time", "Permanent"], "selling_points": ["Junior Secretary", "Legal Firm", "Mature and hardworking"], "locations": ["Wan Chai Area"], "categories": ["Admin & HR", "Secretary", "Professional Services", "Legal & Compliance"], "post_time": "2022-01-17T04:13:24Z", "salary": {"currency": null, "max": null, "min": null, "period": "monthly", "term": null}, "salary_visible": false, "title_keywords": ["junior secretary"], "responsibilities": [], "requirements": {"degrees": ["diploma", "fresh graduate", "dse"], "majors": [], "languages": ["cantonese", "english", "mandarin"], "language_level": [], "hard_skills": ["computer skills"], "soft_skills": ["hardworking", "independent", "mature"], "languages_combined": [{"language": "cantonese", "language_level": []}, {"language": "english", "language_level": []}, {"language": "mandarin", "language_level": []}]}, "experience_required": {"duration": [], "field": []}}, {"job_id": "100003009052109", "location_code": "hk", "company": "Associated Maritime Company (Hong Kong) Limited", "job_title": "\u6cd5\u5f8b\u5408\u898f\u5d17\uff08Shipping Law & Marine Insurance\uff09", "description": "\u5de5\u4f5c\u8077\u8cac\uff1a\n\n1\uff0e\u8655\u7406\u6cd5\u5f8b\u98a8\u63a7,\u5408\u898f\u76f8\u95dc\u4e8b\u52d9\uff1b\n\n2\uff0e\u8349\u64ec\u548c\u5ba1\u9605\u516c\u53f8\u958b\u5c55\u696d\u52d9\u6240\u9700\u7684\u5404\u9805\u898f\u7ae0\u5236\u5ea6\uff1b\n\n3\uff0e\u5be9\u95b1\u5408\u540c\u689d\u6b3e\u4ee5\u53ca\u5176\u4ed6\u6cd5\u5f8b\u6027\u6587\u4ef6\uff1b\u8d1f\u8d23\u5408\u540c\u7ba1\u7406\u5de5\u4f5c\uff1b\n\n4\uff0eKYC;\n\n5\uff0e\u70ba\u516c\u53f8\u65e5\u5e38\u7d93\u71df\u696d\u52d9\u6d3b\u52d5\u63d0\u4f9b\u6cd5\u5f8b\u610f\u898b\u3002\n\n\u4efb\u8077\u8981\u6c42\uff1a\n\n1.\u00a0 \u00a0\u5168\u65e5\u5236\u5927\u5b78\u822a\u904b\u6216\u6cd5\u5b78\u672c\u79d1\u6216\u4ee5\u4e0a\u5b78\u6b77\u6559\u80b2\u80cc\u666f\u8005\u512a\u5148\uff1b\n\n2.\u00a0 \u00a0\u5177\u5099\u4e2d\u570b\u6216\u82f1\u7f8e\u6cd5\u5f8b\u570b\u5bb6(\u6216\u5730\u5340)\u6cd5\u5f8b\u8077\u696d\u8cc7\u683c\u6216\u5f8b\u5e2b\u8cc7\u683c\u512a\u5148\uff1b\n\n3.\u00a0 \u00a0\u5177\u5099\u98a8\u63a7\u3001\u5408\u898f\u5de5\u4f5c\u7d93\u9a57\u4f18\u5148\uff1b\n\n4.\u00a0 \u00a0\u826f\u597d\u7684\u666e\u901a\u8a71\u4ee5\u53ca\u82f1\u8a9e\u53e3\u982d\u8868\u9054\u548c\u66f8\u5beb\u80fd\u529b\uff1b\n\n5.\u00a0 \u00a0\u5de5\u4f5c\u7a4d\u6975\u4e3b\u52d5\uff0c\u6709\u7368\u7acb\u5de5\u4f5c\u80fd\u529b\uff0c\u517c\u5177\u9ad8\u5ea6\u7684\u5718\u968a\u5408\u4f5c\u7cbe\u795e\u548c\u826f\u597d\u7684\u6e9d\u901a\u80fd\u529b\u3002", "employment_types": ["Full Time"], "selling_points": ["\u5be9\u95b1\u6cd5\u5f8b\u6027\u6587\u4ef6", "\u6cd5\u5f8b\u98a8\u63a7,\u5408\u898f\u4e8b\u52d9", "\u5168\u65e5\u5236\u5927\u5b78\u822a\u904b\u6216\u6cd5\u5b78\u672c\u79d1\u5b78\u6b77\u6559\u80b2\u80cc\u666f"], "locations": ["Sheung Wan"], "categories": ["Professional Services", "Legal & Compliance", "Transportation & Logistics", "Shipping"], "post_time": "2022-01-17T02:06:53Z", "salary": {"currency": "HKD", "max": 54999, "min": 30000, "period": "monthly", "term": null}, "salary_visible": true, "title_keywords": [], "responsibilities": [], "requirements": {"degrees": [], "majors": [], "languages": [], "language_level": [], "hard_skills": [], "soft_skills": [], "languages_combined": []}, "experience_required": {"duration": [], "field": []}}, {"job_id": "100003009055439", "location_code": "hk", "company": "BOCI", "job_title": "VP, Compliance", "description": "The Role\n\nCompliance role for our regulated SFC businesses.\n\nKey Accountabilities\n\nDevelop and implement compliance policies and procedures\nProvide compliance guidance, conduct training and make recommendations for improvement areas to minimize compliance risk\nParticipate in compliance system projects and to provide support in preparing compliance management report to Head Office and management\nLiaise with regulators, auditors on regulatory and licensing matters\n\nSkills & Experience\n\nDegree holder in business, accounting, law or related disciplines\n8+ years of compliance experience with particular focus on compliance advisory, regulatory enquiries and licensing\nStrong language skills including written Chinese and spoken Mandarin\n\nOther Information\n\nNotes to applicants:\n1. Please apply in strict confidence with full resume, academic record, current and expected salaries.\n2. The personal data provided will be used for consideration of recruitment only. All personal data of unsuccessful candidate will be destroyed within 24 months.\n3. Candidates with Enhanced Competency Framework (ECF): please state on the CV.\n\nAbout BOCI\n\nAs a leading investment bank in China and Hong Kong region, the investment banking arm of Bank of China, BOC International Holdings Limited (\u201cBOCI\u201d), is now seeking highly motivated, creative and success-oriented professional who would like to pursue the career in our group.\u00a0", "employment_types": ["Full Time"], "selling_points": ["8+ years of general compliance experience", "Banking / securities experience a must", "Knowledge in regulatory guidelines"], "locations": ["Sheung Wan"], "categories": ["Banking / Finance", "Investment", "Professional Services", "Legal & Compliance"], "post_time": "2022-01-18T02:35:25Z", "salary": {"currency": null, "max": null, "min": null, "period": "monthly", "term": null}, "salary_visible": false, "title_keywords": [], "responsibilities": ["make recommendations", "guidance", "provide support", "management", "policies", "compliance", "procedures", "develop", "recruitment", "banking", "liaise with", "personal data", "management report"], "requirements": {"degrees": ["degree holder"], "majors": ["related disciplines", "business", "accounting", "law"], "languages": ["chinese", "mandarin"], "language_level": [], "hard_skills": ["make", "focus"], "soft_skills": ["make recommendations", "confidence", "motivated", "focus", "creative"], "languages_combined": [{"language": "chinese", "language_level": []}, {"language": "mandarin", "language_level": []}]}, "experience_required": {"duration": ["8+ years"], "field": ["compliance"]}}, {"job_id": "100003009054353", "location_code": "hk", "company": "Rouse & Co. International (Overseas) Limited", "job_title": "Compliance Services Officer", "description": "Rouse & Co. International is a global intellectual property (IP) consulting firm. We are seeking a mature and dependable Compliance Services Officer for immediate placement.\n\nCompliance Services Officer\n\nResponsibilities:\n\n\n\nMonitoring and processing requests coming into the Compliance Services Team\nConducting new client take on searches\nConducting new matter conflict checks\nCompiling reports for search results\nResponding to requests for additional information\n\nRequirements:\n\n\n\nDegree holder; good command of written English\nDetail oriented and good analytical skill\nA mature personality who is able to work efficiently and independently\nWell-motivated with a strong sense of responsibility\nTwo years working experience is required\n\nInterested parties, please send full resume with salary expectation by clicking \"Apply Now\".\n\nPersonal data collected will be used for recruitment purposes only.", "employment_types": ["Full Time", "Permanent"], "selling_points": ["Degree holder", "Conduct internet search for client", "Compile reports for search results"], "locations": ["Wan Chai"], "categories": ["Professional Services", "Legal & Compliance"], "post_time": "2022-01-17T09:15:05Z", "salary": {"currency": null, "max": null, "min": null, "period": "monthly", "term": null}, "salary_visible": false, "title_keywords": ["officer"], "responsibilities": ["compliance", "monitoring", "reports"], "requirements": {"degrees": ["degree holder"], "majors": [], "languages": ["english"], "language_level": ["good command"], "hard_skills": ["analytical skill"], "soft_skills": ["analytical skill", "independently", "sense of responsibility", "detail oriented", "mature", "motivated"], "languages_combined": [{"language": "english", "language_level": ["good command"]}]}, "experience_required": {"duration": ["two years"], "field": []}}, {"job_id": "100003009048941", "location_code": "hk", "company": "The Hong Kong University of Science and Technology", "job_title": "Senior Legal Manager / Legal Manager (Job ID: 7060)", "description": "Job Title:\u00a0\u00a0\u00a0\u00a0\u00a0\u00a0\u00a0\u00a0Senior Legal Manager / Legal Manager\nDepartment:\u00a0 \u00a0Legal Office\nJob ID:\u00a0 \u00a0 \u00a0 \u00a0 \u00a0 \u00a0\u00a07060\n\nJob Posting Details\n\nThe Legal Office is looking for a competent, passionate and good team player to join our in-house legal team.\u00a0 Reporting to the Head of Legal, the successful candidate will assist the University in a broad range of non-contentious and contentious legal matters including commercial, governance, employment, personal data, litigation and intellectual property rights issues. \u00a0The job responsibilities include:\u00a0\n\nproviding advice, guidance and oversight on legal issues to support the senior management of the University;\ndrafting, reviewing and negotiating a broad range of business contracts/agreements, correspondences and legal documents;\ndrafting, reviewing and enforcing University-wide policies, regulations and guidelines;\nadvising and managing contentious matters and disputes with counter-parties; and\nworking directly with the senior management and attending to all matters required of the services of the Legal Office.\n\nApplicants should have a law degree or postgraduate degree with a minimum of 8 years of post-qualification experience (PQE) in legal and compliance field with law firms and/or in-house legal departments with relevant expertise in commercial, governance, employment, personal data and intellectual property rights areas. \u00a0The ideal candidate should be a qualified lawyer in Hong Kong. \u00a0Excellent command of both written and spoken English & Chinese (including Putonghua), excellent legal analytical and research skills, strong commercial awareness together with excellent drafting skills are required. \u00a0The appointee should have strong communication and interpersonal skills, be self-motivated, responsible, committed and able to meet deadlines. \u00a0Candidates with less than 8 years PQE but more than 4 years PQE may apply for consideration as Legal Manager.(Duration: 2 years, renewable)\n\nStarting salary will be commensurate with qualifications and experience.\u00a0 Fringe benefits including annual leave, medical and dental benefits will be provided.\u00a0 A gratuity will be payable upon successful completion of contract.\n\nApplication Procedure\nIn support of a green work environment, we accept applications submitted online only.\u00a0 To apply, please complete an online application form through the HKUST Careers website (https://hkustcareers.ust.hk) and return it online to the Human Resources Office on or before Friday, 11 February 2022.\u00a0 Applicants will receive an acknowledgement by email upon successful submission.\u00a0 We thank applicants for their interest, but advise that only shortlisted candidates will be notified of the result of the application.\n\n(Information provided by applicants will be used for recruitment and other employment-related purposes only.)\n\nHKUST is an equal opportunities employer and is committed to our core values of\ninclusiveness, diversity, and respect.", "employment_types": ["Full Time"], "selling_points": ["Providing advice, guidance", "Drafting, reviewing and negotiating", "Advising and managing contentious matters"], "locations": ["Sai Kung"], "categories": ["Admin & HR", "Administration / Operation Manager", "Education", "Others", "Professional Services", "Legal & Compliance"], "post_time": "2022-01-14T07:45:17Z", "salary": {"currency": null, "max": null, "min": null, "period": "monthly", "term": null}, "salary_visible": false, "title_keywords": ["senior legal manager", "manager"], "responsibilities": ["regulations", "guidance", "reporting", "guidelines", "contracts", "policies", "compliance", "communication", "personal data", "senior management"], "requirements": {"degrees": ["degree"], "majors": ["law"], "languages": ["putonghua", "english", "chinese"], "language_level": ["excellent"], "hard_skills": ["id"], "soft_skills": ["passionate", "good team player", "self-motivated", "research skills", "responsible", "competent", "committed", "communication and interpersonal skills", "meet deadlines", "ideal"], "languages_combined": [{"language": "putonghua", "language_level": ["excellent"]}, {"language": "english", "language_level": ["excellent"]}, {"language": "chinese", "language_level": ["excellent"]}]}, "experience_required": {"duration": ["minimum of 8 years"], "field": ["commercial", "compliance", "post-qualification", "legal"]}}, {"job_id": "100003009053059", "location_code": "hk", "company": "Tung, Ng, Tse & Lam, Solicitors", "job_title": "Secretary", "description": "Minimum 1-2 years' experience in the legal firms\nWell versed in MS Word (English and Chinese word processing) and Excel\nAttention to details, organized and self-motivated\nExcellent communication skills in both written and spoken English and Chinese, and Mandarin an advantage\n\nAll applications will be treated in strict confidence.", "employment_types": ["Full Time"], "selling_points": [], "locations": ["Central"], "categories": ["Professional Services", "Legal & Compliance"], "post_time": "2022-01-17T05:30:16Z", "salary": {"currency": null, "max": null, "min": null, "period": "monthly", "term": null}, "salary_visible": false, "title_keywords": ["secretary"], "responsibilities": ["communication"], "requirements": {"degrees": [], "majors": [], "languages": ["english", "chinese", "mandarin"], "language_level": ["advantage", "excellent"], "hard_skills": ["excel", "chinese word processing", "ms word"], "soft_skills": ["communication skills", "organized", "self-motivated", "confidence", "attention to details"], "languages_combined": [{"language": "english", "language_level": ["excellent"]}, {"language": "chinese", "language_level": ["excellent"]}, {"language": "mandarin", "language_level": ["advantage", "excellent"]}]}, "experience_required": {"duration": ["minimum 1-2 years"], "field": ["legal"]}}, {"job_id": "100003009055438", "location_code": "hk", "company": "BOCI", "job_title": "AVP, AML Compliance", "description": "The Role\n\nAML Advisory role for all lines of our business - investment banking, equity derivatives, trading and research, etc.\n\nKey Accountabilities\n\nAssist the Money Laundering Reporting Officer (MLRO) in implementing effective AML measures and controls\nProvide advice to business units, including investment banking, equity sales and derivatives, financial products, sales, trading and research, global commodities and overseas offices if necessary, on AML, KYC and CDD matters\nReview the completeness of customers' KYC / CDD information, supporting documentation and risk assessment before granting approvals for new relationship or CCDD reviews whenever necessary\nIdentify, investigate and report suspicious activity and transaction, and escalate any material risk relevant information to MLRO and submit suspicious transaction reports to the JFIU on timely manner\nProduce regular AML reports for internal stakeholders\nPerform supervisory control and quality assurance of the KYC tasks within the compliance function, as second line of defense\nIdentify risk issues and propose recommendations / rectifications to senior management for resolution\nParticipate in the AML compliance projects to ensure the effective enhancements of the compliance control framework\nAct as project manager to advise on FinTech / RegTech AML systems\nAssist to organize and deliver AML training in relation to internal controls and regulatory updates\n\nSkills & Experience\n\nDegree holder of law, accounting, finance or other related disciplines\nMinimum 6 years relevant working experience in KYC or AML compliance\nRelevant industry qualifications in AML (ICA or ACAMS) preferred\nStrong knowledge of Hong Kong regulatory regime, especially KYC requirements and standards, preferably from investment and corporate banking services aspects\nStrong team player who is highly motivated, independent and able to work under pressure and tight timelines\nFluent in written and spoken Cantonese, Mandarin and English\n\nOther Information\n\nNotes to applicants:\n1. Please apply in strict confidence with full resume, academic record, current and expected salaries.\n2. The personal data provided will be used for consideration of recruitment only. All personal data of unsuccessful candidate will be destroyed within 24 months.\n3. Candidates with Enhanced Competency Framework (ECF): please state on the CV.\n\nAbout BOCI\n\nAs a leading investment bank in China and Hong Kong region, the investment banking arm of Bank of China, BOC International Holdings Limited (\u201cBOCI\u201d), is now seeking highly motivated, creative and success-oriented professional who would like to pursue the career in our group.\u00a0", "employment_types": ["Full Time"], "selling_points": ["5-8 years of AML compliance experience", "AML / KYC / CDD", "Banking experience a must"], "locations": ["Sheung Wan"], "categories": ["Banking / Finance", "Analyst", "Professional Services", "Business Consultancy", "Legal & Compliance"], "post_time": "2022-01-18T02:35:21Z", "salary": {"currency": null, "max": null, "min": null, "period": "monthly", "term": null}, "salary_visible": false, "title_keywords": ["aml compliance"], "responsibilities": ["quality", "personal data", "senior management", "work under pressure", "control", "cdd", "compliance", "resolution", "reports", "banking", "kyc", "report", "reporting", "review", "documentation", "aml", "systems", "provide advice", "recruitment"], "requirements": {"degrees": ["degree holder"], "majors": ["related disciplines", "finance", "accounting", "law"], "languages": ["cantonese", "english", "mandarin"], "language_level": ["fluent"], "hard_skills": ["aml", "cdd", "kyc", "documentation", "acams"], "soft_skills": ["confidence", "independent", "timely", "motivated", "team player", "creative", "work under pressure"], "languages_combined": [{"language": "cantonese", "language_level": ["fluent"]}, {"language": "english", "language_level": ["fluent"]}, {"language": "mandarin", "language_level": ["fluent"]}]}, "experience_required": {"duration": ["minimum 6 years"], "field": ["compliance", "relevant working experience"]}}, {"job_id": "100003009051213", "location_code": "hk", "company": "One Recruitment Limited", "job_title": "Paralegal, Litigation", "description": "Our client, an international law firm is urgently looking for a Paralegal, Litigation to join their dynamic team in HK office.\n\nJob Responsibilities:\n\nDraft court documents, handle correspondence with clients and keep track of legal research\nResponsible for venue and transcripts preparation and arrangement\u00a0\nHandle market research and investigation\nAttend conferences\u00a0with\u00a0clients and Counsel and conduct subsequent follow up,\u00a0such as preparing bundles for hearing, conducting site visit and locate witness to take particular statements\n\nJob Requirements:\n\nBachelor degree holder with at least 1 year experience in litigation/dispute resolution or arbitration\nPrevious experience in arbitration is a definite advantage\nFamiliar\u00a0with court procedures and related\u00a0documents\u00a0arrangement\u00a0and preparation\n\nGood English written skills is required\nAble to speak Mandarin is a definite advantage but not essential\nLess experience will be considered a Law Clerk\u00a0", "employment_types": ["Full Time", "Permanent"], "selling_points": ["Excellent Career Advancement", "Good Job Prospects", "Competitive Remuneration Package (30-45k)"], "locations": ["Admiralty"], "categories": ["Professional Services", "Legal & Compliance"], "post_time": "2022-01-15T04:54:36Z", "salary": {"currency": "HKD", "max": 44999, "min": 30000, "period": "monthly", "term": null}, "salary_visible": true, "title_keywords": ["paralegal"], "responsibilities": ["conferences", "market research", "investigation"], "requirements": {"degrees": ["bachelor degree holder"], "majors": [], "languages": ["english", "mandarin"], "language_level": ["advantage", "good"], "hard_skills": [], "soft_skills": [], "languages_combined": [{"language": "english", "language_level": ["good"]}, {"language": "mandarin", "language_level": ["advantage"]}]}, "experience_required": {"duration": ["at least 1 year"], "field": []}}, {"job_id": "100003009050213", "location_code": "hk", "company": "The Law Society of Hong Kong", "job_title": "Assistant, Compliance Department (Ref: COM/ASST)", "description": "The Law Society seeks applications from an enthusiastic and responsible person to fill the position of Assistant in the Compliance Department.\u00a0\n\nJob Duties:\n\nTo perform secretarial and clerical support to Investigation Counsel (\u201cIC\u201d);\nTo assist the IC to handle complaints and answer enquiries from the public and members;\nTo collate documents and assist the IC to prepare relevant reports;\nTo prepare draft correspondence (including memorandum and letters), keep relevant outgoing records and maintain proper filing both physically and digitally;\nTo fill in forms for conducting land searches, company searches, bankruptcy searches and death searches, etc.\n\nRequirements:\n\nF.6 or above with a good command of written and spoken English and Chinese (including Putonghua);\nAt least 1 year secretarial/ clerical working experience;\nProficiency in MS Word, Excel, Chinese Word Processing;\nGood telephone manner; and\nImmediate availability is preferable.\u00a0\n\nInterested parties please send your full curriculum vitae stating the reference number, current and expected salary to the Assistant Director of Administration and Human Resources, The Law Society of Hong Kong, 3/F, Wing On House, 71 Des Voeux Road Central, Hong Kong or click \"APPLY NOW\".\u00a0\u00a0Please mark \u201cPrivate and Confidential\u201d on the envelope.\n\n*Personal data provided by job applicants will be used strictly in accordance with the Law Society\u2019s personal data policies as set out in the Personal Information Collection Statement. \u00a0A copy of the Statement can be obtained from Assistant Director of Administration & Human Resources by calling 2846 0586. \u00a0Applicants not invited for interview within 6 weeks may consider their applications unsuccessful.*", "employment_types": ["Full Time", "Permanent"], "selling_points": [], "locations": ["Central"], "categories": ["Admin & HR", "Clerical / Admin Staff", "Professional Services", "Legal & Compliance", "Others", "Student / Fresh Graduate / No Experience"], "post_time": "2022-01-14T09:56:59Z", "salary": {"currency": null, "max": null, "min": null, "period": "monthly", "term": null}, "salary_visible": false, "title_keywords": ["assistant"], "responsibilities": ["relevant reports", "letters", "clerical support", "investigation", "handle complaints", "maintain"], "requirements": {"degrees": [], "majors": [], "languages": ["putonghua", "english", "chinese"], "language_level": ["proficiency", "good command"], "hard_skills": ["excel", "chinese word processing", "ms word"], "soft_skills": ["telephone manner"], "languages_combined": [{"language": "putonghua", "language_level": ["good command"]}, {"language": "english", "language_level": ["good command"]}, {"language": "chinese", "language_level": ["proficiency", "good command"]}]}, "experience_required": {"duration": ["at least 1 year"], "field": ["secretarial", "clerical"]}}, {"job_id": "100003009055897", "location_code": "hk", "company": "Hays", "job_title": "Senior Legal Counsel, Global Fund Manager", "description": "Top tier fund management looking for a mid to senior level corporate / funds lawyer!\n\nHong Kong\n\nYour new company\n\nOur client is a global fund management company that specialises in real estate, infrastructure and related technologies. They are growing at a rapid pace due to the expansion of the business and they are looking to hire and bring on another lawyer to join their team of 6.\n\nYour new role\n\nProvide advice and guidance to the deal team across the globe at any time.\nAct as deal facilitator who effectively balances legal and business risks whilst ensuring the firm's and fund's interests are represented and protected enabling legitimate opportunities to be furthered.\nIdentify issues and provide proactive solutions on deal-related legal matters.\nProvide legal support to the business on a range of operational matters, reviewing tenders, and corporate governance.\nManage outside counsel and ensure the highest and best use of their services. Defer to outside counsel's expertise where appropriate and avoid replicating their work.\nNegotiate and interact with the company's key customers, business partners and investors\n\n\nWhat you'll need to succeed\n\nJ.D. or equivalent legal qualification from a highly regarded university.\nInternational experience is preferred.\n6 to 12 years of post-qualification experience gained in a leading law firm and /or in-house with investment funds experience.\nSolid experience negotiating, executing and managing deals.\nChinese is preferred but not essential\n\n\nWhat you need to do now\n\nIf you're interested in this role, click 'apply now' to forward an up-to-date copy of your CV, or call us now. If this job isn't quite right for you but you are looking for a new position, please contact Adrian Lam at +852 2230 7432 or adrian.lam@hays.com.hk for a confidential discussion on your career.", "employment_types": ["Full Time", "Permanent"], "selling_points": ["Attractive Remuneration Package", "Tier one brand name", "Great culture and working environment"], "locations": ["Not Specified"], "categories": ["Professional Services", "Legal & Compliance"], "post_time": "2022-01-18T03:03:48Z", "salary": {"currency": null, "max": null, "min": null, "period": "monthly", "term": null}, "salary_visible": false, "title_keywords": ["senior legal counsel", "manager"], "responsibilities": ["guidance", "management", "infrastructure", "team across", "provide advice", "executing", "contact", "operational matters"], "requirements": {"degrees": [], "majors": [], "languages": ["chinese"], "language_level": [], "hard_skills": ["rapid"], "soft_skills": ["interested in", "proactive"], "languages_combined": [{"language": "chinese", "language_level": []}]}, "experience_required": {"duration": ["6 to 12 years"], "field": ["post-qualification", "investment"]}}, {"job_id": "100003009048670", "location_code": "hk", "company": "Ferragamo Retail HK Limited", "job_title": "Senior Legal Manager/ Counsel, Asia", "description": "JOB DESCRIPTION\n\n1. Legal\n\nReview, comment and advise on agreements, in particular leases, concession/consignment agreements, distribution agreements, sales/franchise agreements and services / procurement agreements in relation to the legal entities across the Region;\nConduct legal researches in respect of the legislative changes with impact to the business operation in the region as necessary;\nHandle internal enquiries and reporting in relation to legal matters for all the Region;\nCoordinate with and manage external legal advisors in respect of major / specific legal matters\n\n2. Company Secretarial\n\nPrepare the resolutions for the board and shareholders for the entities in the Region, in particular entities under the JVA;\nCoordinate with internal stakeholders and external advisors (in particular the company secretaries), as the case necessary, for completing the statutory filings;\nSupport the convening of the board meetings;\n\n3. Compliance\n\nEnsure compliance of relevant requirements pursuant to (i) the group policies and (ii) the joint ventures;\nManage the HQ contract database\nHandle and response to enquiries and request from internal auditor, external auditor and banks from time to time\n\n4. IP enforcement\u00a0\n\nCoordinate with HQ for necessary IP issues in the Region\n\n\n\nPROFESSIONAL REQUIREMENTS\n\nLaw graduate is required;\nAt least 6 -8 years of relevant experience as in-house legal;\nWith regional exposures and a proven team player within multi-cultural environment\nDrafting skills;Legal research skills;Business acumen\nFamiliar with the legal framework applicable in the region;\nProficiency (both written and spoken) in English and Chinese (both traditional and simplified);\nStrong organizational skills and ability to prioritize works in a fast-paced and dynamic working environment;\nStrong interpersonal communication skills with people within the organization;\nAttention to details; Analytical;\nImpeccable integrity and strong sense of ownership", "employment_types": ["Full Time", "Permanent"], "selling_points": ["Competitive and attractive remuneration package", "Flexible work environment", "Luxury Retail"], "locations": ["Southern Area"], "categories": ["Professional Services", "Legal & Compliance"], "post_time": "2022-01-14T07:02:23Z", "salary": {"currency": null, "max": null, "min": null, "period": "monthly", "term": null}, "salary_visible": false, "title_keywords": ["senior legal manager"], "responsibilities": ["business operation", "reporting", "policies", "review", "compliance", "coordinate with", "ensure compliance", "database"], "requirements": {"degrees": [], "majors": [], "languages": ["english", "chinese"], "language_level": ["proficiency"], "hard_skills": ["dynamic", "acumen"], "soft_skills": ["organizational skills", "communication skills", "research skills", "integrity", "prioritize", "dynamic", "attention to details", "business acumen", "team player", "interpersonal"], "languages_combined": [{"language": "english", "language_level": ["proficiency"]}, {"language": "chinese", "language_level": ["proficiency"]}]}, "experience_required": {"duration": ["at least 6 -8 years"], "field": ["relevant experience", "legal"]}}, {"job_id": "100003009049909", "location_code": "hk", "company": "Kering Asia Pacific Ltd.", "job_title": "KERING Legal Intern", "description": "Summary\n\nAbout us\nA global Luxury group, Kering manages the development of a series of renowned Houses in Fashion, Leather Goods, Jewelry and Watches: Gucci, Saint Laurent, Bottega Veneta, Balenciaga, Alexander McQueen, Brioni, Boucheron, Pomellato, Dodo, Qeelin, Ulysse Nardin, Girard-Perregaux, as well as Kering Eyewear. By placing creativity at the heart of its strategy, Kering enables its Houses to set new limits in terms of their creative expression while crafting tomorrow's Luxury in a sustainable and responsible way. We capture these beliefs in our signature: \u201cEmpowering Imagination.\u201d In 2017, Kering had nearly 29,000 employees and restated revenue of \u20ac10.816 billion.\n\nJob Description\n\nYour opportunity\n\nThis position is responsible to support and assist the Intellectual Property of Legal Department in secretarial and administrative matters.\n\nHow you will contribute\n\nTo assist of in the preparation of monthly budget reports\nTo manage invoices and liaise with Brands and Vendors\nTo prepare and/or submit travel reimbursements\nTo perform legal and/or online research (IP related)\nTo maintain confidential document filing system regarding corporate communications, financial information, and company policy\nTo prepare PowerPoint presentations, Excel spreadsheets, reports, memorandums and meeting materials\nTo provide general secretarial duties within the team\nTo perform other related duties as required and/or assigned\n\nWho you are\n\nCurrent BBA or Finance students\nExposure to Intellectual Property is a plus, but not essential\nExcellent command of written and spoken English and Putonghua\nAble to handle multi-task effectively and strong organizational skills\nProactive, pleasant with excellent communication skills\nProficiency in MS Office applications\n\nJob Type\n\nStudent (Fixed Term) (Trainee)\n\nStart Date\n\n2022-01-08\n\nSchedule\n\nPart time\n\nOrganization\n\nKering Asia Pacific Ltd.", "employment_types": ["Part Time"], "selling_points": ["Preparation of monthly budget reports and invoice", "Maintain confidential document filing system", "Prepare memorandums and meeting materials"], "locations": ["Quarry Bay"], "categories": ["Professional Services", "Legal & Compliance"], "post_time": "2022-01-14T09:26:36Z", "salary": {"currency": null, "max": null, "min": null, "period": "monthly", "term": null}, "salary_visible": false, "title_keywords": ["intern"], "responsibilities": ["document filing", "budget reports", "invoices", "presentations", "maintain", "reports", "liaise with"], "requirements": {"degrees": [], "majors": [], "languages": ["putonghua", "english"], "language_level": ["excellent"], "hard_skills": ["plus", "ms office"], "soft_skills": ["communication skills", "organizational skills", "multi-task", "pleasant", "proactive"], "languages_combined": [{"language": "putonghua", "language_level": ["excellent"]}, {"language": "english", "language_level": ["excellent"]}]}, "experience_required": {"duration": [], "field": []}}, {"job_id": "100003009055920", "location_code": "hk", "company": "KOS International Limited", "job_title": "Compliance Officer/Analyst", "description": "About Our Client\n\nMy client is a growing securities firm with SFC license type 1,2,4, 6 and 9 and they are looking for a compliance officer/analyst.\n\nAbout The Role\n\nHandle general enquiries from SFC, HKEx and other regulators;\nCoordinate and liaise with regulators and frontline staffs on all licensing matters;\nPerform compliance monitoring such as declaration of staff dealing and fulfillment of CPT requirement;\nFacilitate the regulatory inspection and prepare documents/responses as required;\nConducting trading compliance surveillance;\nUndertake other ad hoc projects as required.\n\nRequirements\n\nBachelor's degree in Law, Corporate Governance, Finance or Accounting or other related disciplines;\n2-3 years or above relevant experiences in securities firm or financial institution;\nExperience in AML, fintech, finance, data privacy, legal, compliance and / or the relevant fields would be a plus;\nKnowledge with SFC's regulation is preferable\nStrong command of both written and spoken English and Chinese is a MUST;\nProficiency in Microsoft Office and Exchange\nDetail-oriented and highly motivated mindset\n\nClick \"Apply Now\" to apply for this position or call Jessie Chan at +852 3180 4945 for a confidential discussion. All information collected will be kept in strict confidence and will be used for recruitment purpose only.", "employment_types": ["Full Time", "Permanent"], "selling_points": ["Growing platform", "Around 3 years of relevant work experience", "Excellent culture"], "locations": ["Not Specified"], "categories": ["Banking / Finance", "Investment", "Financial Services", "Professional Services", "Legal & Compliance"], "post_time": "2022-01-18T03:05:23Z", "salary": {"currency": null, "max": null, "min": null, "period": "monthly", "term": null}, "salary_visible": false, "title_keywords": ["analyst", "compliance officer"], "responsibilities": ["aml", "data", "fulfillment", "monitoring", "compliance", "inspection", "coordinate", "ad hoc projects", "recruitment", "liaise with", "prepare documents"], "requirements": {"degrees": ["degree", "bachelor"], "majors": ["related disciplines", "finance", "accounting", "law"], "languages": ["english", "chinese"], "language_level": [], "hard_skills": ["plus", "aml", "microsoft office", "sfc license", "exchange"], "soft_skills": ["motivated", "confidence", "detail-oriented"], "languages_combined": [{"language": "english", "language_level": []}, {"language": "chinese", "language_level": []}]}, "experience_required": {"duration": ["2-3 years"], "field": ["legal", "finance", "compliance", "securities firm", "financial"]}}, {"job_id": "100003009054151", "location_code": "hk", "company": "ALS International Limited", "job_title": "Litigation Analyst (HK Qualified Solicitor or Barrister)", "description": "In this role, you'll work alongside some experienced litigators on challenging, highly complex disputes with an international scope. Whether you are a qualified solicitor or barrister, you can be sure to have an exciting and challenging career in a supportive environment and inclusive culture.\n\nSuccessful candidates will have strong academic credentials, excellent interpersonal skills with the ability to interface at all levels, and have the ability to work autonomously.\n\nJob Scope:\n\nYou will work as part of a passionate and supportive team on a variety of matters for an enviable client base across a range of sectors, reporting to the senior team members.\nYou will work with the team to pursue opportunities, to build new client relationships and to devise new and innovative approaches to service delivery.\nConducting in-depth investigations of matters based on review of documents on e-discovery platforms.\nAnalysing financial statements and audit working papers to identify anomalies and present findings in a logical and coherent manner.\nPreparing investigation packs based on publicly available information for client meetings and business development purposes.\nWorking externally with forensic accountants, Mainland solicitors and Mainland experts on projects.\nProject managing and quality assurance for translation of Chinese/English documents for cases.\nWorking in a team environment with both fee and non-fee earners including partners and associates, litigation analysts, translators, PAs and IT.\n\n\nDesired skills and attributes include:\n\n\n\nQualified Solicitor or Barrister\nUnderstanding of audits, financial statements and accounting concepts.\nPrior experience in writing detailed reports.\nPossess keen attention to detail.\nMust be highly fluent in both English and Chinese.\u201d\n\nInterested candidates should send their resume in Word file, please click \"APPLY NOW\" below for further information.", "employment_types": ["Full Time"], "selling_points": [], "locations": ["Central"], "categories": ["Professional Services", "Legal & Compliance"], "post_time": "2022-01-17T08:34:48Z", "salary": {"currency": null, "max": null, "min": null, "period": "monthly", "term": null}, "salary_visible": false, "title_keywords": ["analyst"], "responsibilities": ["service delivery", "reporting", "review", "quality", "audit", "financial statements", "investigation", "client base", "reports", "audits"], "requirements": {"degrees": [], "majors": [], "languages": ["english", "chinese"], "language_level": ["fluent"], "hard_skills": ["translation"], "soft_skills": ["passionate", "supportive", "keen", "coherent", "interpersonal skills", "attention to detail", "innovative", "detailed"], "languages_combined": [{"language": "english", "language_level": ["fluent"]}, {"language": "chinese", "language_level": ["fluent"]}]}, "experience_required": {"duration": [], "field": ["writing"]}}, {"job_id": "100003009044968", "location_code": "hk", "company": "Michelle Ip & Co. Solicitor", "job_title": "Legal Clerk / Legal Executive", "description": "We earnestly invite applications for the above position to join our team.\n\nJob Duties:\n\nProviding legal support to solicitor\nPreparing court documents with minimal supervision\u00a0\nDrafting bills\u00a0\n\nRequirements:\n\nAt least 3 years' experience or above in civil\u00a0 litigation and matrimonial proceedings\nCan handle civil and matrimonial cases with minimal supervision\nWilling to co-operate and able to work independently\nGood communication skills in both spoken and written English and Chinese\nProficient in MS Office and Chinese typing\n\nWe offer competitive salary, discretionary bonus, 5-day work week and bank holidays.\u00a0 Interested parties please send your resume stating the current & expected salaries and time of availability our email at\u00a0Immediate availability would be an advantage. For further details, please contact Ms. Ip at 2111 0182.\u00a0", "employment_types": ["Full Time"], "selling_points": [], "locations": ["Sheung Wan"], "categories": ["Professional Services", "Legal & Compliance"], "post_time": "2022-01-15T03:49:25Z", "salary": {"currency": null, "max": null, "min": null, "period": "monthly", "term": null}, "salary_visible": false, "title_keywords": ["legal executive", "legal clerk"], "responsibilities": [], "requirements": {"degrees": [], "majors": [], "languages": ["english", "chinese"], "language_level": ["proficient", "good"], "hard_skills": ["typing", "ms office"], "soft_skills": ["communication skills", "work independently"], "languages_combined": [{"language": "english", "language_level": ["good"]}, {"language": "chinese", "language_level": ["proficient", "good"]}]}, "experience_required": {"duration": ["at least 3 years"], "field": []}}, {"job_id": "100003009052941", "location_code": "hk", "company": "JFE Consulting Limited", "job_title": "Legal Secretary - Civil Litigation", "description": "Our client, one of the leading law firms, is looking for high calibres to join them:-\n\nResponsibilities:\n\nProviding administrative support to one or more lawyers\nEffectively communicating with witnesses, clients, colleagues and partners\nGreeting visitors and perform initial screening of clients\nProduce and file various legal documents such as appeals, motions or petitions\nPreserve an updated case record system\nAnswer phone calls, take notes/messages and redirect calls when appropriate\nMaintain and update inventories of contact details\n\nQualifications and Personal Competencies:\n\nMatriculated or above or relevant qualification\nKnowledge of MS Office and ability to work with legal technology (court-filing computer systems, transcription software, dictaphone etc)\nWorking knowledge of litigation management software systems is a plus\nExperience in using the Elite 3E System an advantage", "employment_types": ["Full Time", "Permanent"], "selling_points": ["Legal Secretary", "Civil Litigation", "5-day work; attractive salary"], "locations": ["Central"], "categories": ["Professional Services", "Company Secretary", "Legal & Compliance", "Translation"], "post_time": "2022-01-17T04:37:47Z", "salary": {"currency": null, "max": null, "min": null, "period": "monthly", "term": null}, "salary_visible": false, "title_keywords": ["legal secretary"], "responsibilities": ["management", "software", "administrative support", "systems", "computer systems", "maintain", "communicating with", "contact", "answer phone calls", "greeting visitors"], "requirements": {"degrees": [], "majors": [], "languages": [], "language_level": [], "hard_skills": ["plus", "computer systems", "ms office"], "soft_skills": [], "languages_combined": []}, "experience_required": {"duration": [], "field": []}}, {"job_id": "100003009056331", "location_code": "hk", "company": "Project Umbrella", "job_title": "\u4e0d\u4e00\u6a23\u7684\u7406\u8ca1\u9867\u554f/\u4fdd\u96aa\u4ee3\u7406 (\u6539\u9769\u4fdd\u96aa\u696d)", "description": "\u5e02\u5834\u6982\u6cc1\uff1a\n\u64ab\u5fc3\u81ea\u554f\uff0c\u4f60\u559c\u6b61\u6bcf\u5929\u671d\u4e5d\u665a\u4e5d\uff0c\u4e00\u6210\u4e0d\u8b8a\u7684\u751f\u6d3b\u55ce\uff1f\u4f60\u559c\u6b61\u6bcf\u5929\u5728\u8fa6\u516c\u5ba4\u52fe\u5fc3\u9b25\u89d2\uff0c\u723e\u865e\u6211\u8a50\u7684\u74b0\u5883\u55ce\uff1f\u62ff\u8457\u56fa\u5b9a\u7684\u85aa\u916c\u6bcf\u5929\u52a0\u73ed\u70ba\u8001\u95c6\u5275\u9020\u6536\u76ca\u771f\u7684\u662f\u4f60\u60f3\u8981\u7684\u55ce\uff1f\u4f55\u4e0d\u8d81 2022 \u8df3\u51fa\u81ea\u5df1\u7684\u8212\u9069\u5340\uff0c\u7d66\u4fdd\u96aa\u4e00\u500b\u6a5f\u6703\uff0c\u5617\u8a66\u4e3b\u5bb0\u81ea\u5df1\u7684\u4eba\u751f\uff1f\n\n\u8207\u4e00\u822c\u4fdd\u96aa\u71df\u92b7\u6709\u5225\uff0cProject Umbrella\u6295\u653e\u5927\u91cf\u8cc7\u6e90\u65bc\u5275\u65b0\u6027\u7684\u7db2\u7d61\u71df\u92b7\uff0c\u5438\u5f15\u5927\u91cf\u6709\u4fdd\u96aa\u610f\u8b58\u7684\u5ba2\u6236\u4e3b\u52d5\u67e5\u8a62\u3002\u7db2\u7d61\u71df\u92b7\u5c07\u6703\u662f\u4fdd\u96aa\u696d\u767c\u5c55\u7684\u4e3b\u6d41\u65b9\u5411\uff0c\u800cProject Umbrella\u7684\u76ee\u6a19\u662f\u63d0\u4f9b\u4e00\u500b\u4ecb\u4e4e\u65bc\u50b3\u7d71\u4fdd\u96aa\u8207\u865b\u64ec\u4fdd\u96aa\u4e4b\u9593\u7684\u5e73\u53f0\u53ca\u670d\u52d9\u3002\n\nProject Umbrella (Redefining Standards with Utmost Good Faith)\uff1a\n\u5c08\u696d\u5316\nProject Umbrella \u662fAXA\u65d7\u4e0b\u7684\u4e00\u652f\u5718\u968a\uff0c\u75313\u540d\u524d\u6fb3\u6d32\u57f7\u696d\u5f8b\u5e2b\u548c\u4e00\u4f4d\u5e02\u5834\u884c\u92b7\u5c08\u5bb6\u6210\u7acb\uff0c\u76ee\u6a19\u662f\u5efa\u7acb\u4f86\u81ea\u4e0d\u540c\u80cc\u666f\u5e74\u8f15\u5c08\u696d\u5316\u7684\u5718\u968a\uff0c\u6210\u54e1\u5305\u62ec\u528d\u6a4bMBA\u3001\u66fe\u4efb\u6559\u7cbe\u7b97\u7cfb\u7684\u535a\u58eb\u3001\u6578\u5b78\u7cfb\u78a9\u58eb\u3001\u5f8b\u5e2b\u3001\u6301\u724c\u6838\u6578\u5e2b\u3001\u6295\u884c\u5206\u6790\u5e2b\u3001IT\u516c\u53f8Director\u3001\u6301\u724c\u6703\u8a08\u5e2b\u548c\u5e02\u5834\u884c\u92b7\u5c08\u624d\u7b49\u7b49\u3002\n\n\u570b\u969b\u5316\n\u6211\u5011\u7684\u968a\u54e1\u5305\u542b\u4f46\u4e0d\u9650\u65bc\u672c\u5730\u9999\u6e2f\u4eba\uff0c\u5167\u5730\u4eba\uff0c\u82f1\u570b\u4eba\uff0c\u52a0\u62ff\u5927\u4eba\uff0c\u83f2\u5f8b\u8cd3\u4eba\uff0c\u5370\u5ea6\u4eba\u7b49\u7b49\u3002\u5e73\u6642\u6e9d\u901a\u5169\u6587\u4e09\u8a9e\uff0c\u61c9\u6709\u76e1\u6709\u3002\u6211\u5011\u6df1\u4fe1\u4e0d\u540c\u6587\u5316\uff0c\u4e0d\u540c\u80cc\u666f\u7684\u78b0\u649e\u624d\u53ef\u4ee5\u5e36\u4f86\u9032\u6b65\u3002\u6211\u5011\u7684\u5ba2\u6236\u4f86\u81ea\u4e16\u754c\u5404\u5730\uff0c\u5f9e\u672c\u5730\u4eba\uff0c\u5167\u5730\u4eba\u5230\u5916\u570b\u4eba\u3002\n\n\u52a0\u5165\u4fdd\u96aa\u696d\u5c31\u662f\u5275\u696d\uff0c\u518d\u6c92\u6709\u4eba\u6703\u7763\u4fc3\u4f60\u6bcf\u5929\u5de5\u4f5c\u3002\u4f60\u7684\u6c7a\u5fc3\u548c\u76ee\u6a19\u5c07\u6210\u70ba\u4f60\u5de5\u4f5c\u6700\u5927\u63a8\u52d5\u529b\u3002\n\n\u4f5c\u70ba\u65b0\u5165\u8077\u7684\u4f60\u521d\u671f\u7e3d\u6703\u9762\u5c0d\u5404\u7a2e\u56f0\u96e3\uff0c\u800c\u6bcf\u500b\u4eba\u6210\u529f\u9054\u5230\u76ee\u6a19\u7684\u65b9\u6cd5\u90fd\u4e0d\u4e00\u6a23\u3002\u6b63\u56e0\u70ba\u6211\u5011\u90fd\u8d70\u904e\u76f8\u540c\u7684\u8def\uff0c\u6211\u5011\u660e\u767d\u4f60\u6240\u9762\u5c0d\u7684\u60c5\u5883\u3002\u7d93\u7406\u4e0d\u662f\u4f60\u7684\u4e0a\u7d1a\uff0c\u800c\u662f\u4f5c\u70ba\u4e00\u500b\u5f15\u5c0e\u8005\uff0c\u662f\u4f60\u5de5\u4f5c\u4e0a\u7684\u5408\u5925\u4eba\uff0c\u5728\u4f60\u5275\u696d\u7684\u8def\u4e0a\u63d0\u4f9b\u652f\u63f4\u3002\n\n\u6700\u5f8c\uff0c\u6211\u5011\u5e0c\u671b\u5f7c\u6b64\u4e0d\u53ea\u662f\u5de5\u4f5c\u4e0a\u7684\u4f19\u4f34\uff0c\u800c\u4e14\u662f\u751f\u6d3b\u4e0a\uff0c\u4eba\u751f\u9053\u8def\u4e0a\u7684\u4f19\u4f34\u3002\n\u6309\u6b64\u4e86\u89e3\u6211\u5011\u66f4\u591a: https://www.facebook.com/projectumbrellahk\n\n\u5718\u968a\u7406\u5ff5\uff1a\n\u6211\u5011\u6709\u4e00\u500b\u7406\u5ff5\uff0c\u5c31\u662f\u8981\u5c07\u5c08\u696d\u77e5\u8b58\u3001\u8cac\u4efb\u611f\u53ca\u8aa0\u4fe1\u5e36\u9032\u4fdd\u96aa\u696d\uff0c\u4e26\u6ce8\u91cd\u6bcf\u500b\u4eba\u5728\u500b\u4eba\u696d\u52d9\u548c\u5efa\u7acb\u5718\u968a\u4e0a\u7684\u767c\u5c55\u3002\u4f60\u7684\u6210\u529f\u5c31\u662f\u6211\u5011\u7684\u6210\u529f\uff0c\u5718\u968a\u5408\u4f5c\u662f\u5718\u968a\u53ef\u6301\u7e8c\u767c\u5c55\u7684\u95dc\u9375\u3002\u4fdd\u96aa\uff0c\u65e2\u662f\u4e00\u500b\u5fc5\u9700\u54c1\uff0c\u4e5f\u662f\u4e00\u9580\u5c08\u696d\u3002\u9019\u500b\u5718\u968a\u5c07\u6709\u4e00\u5929\u6703\u6539\u8b8a\u9999\u6e2f\u4eba\u5c0d\u4fdd\u96aa\u7684\u65e2\u6709\u5370\u8c61\u3002\n\n\u60a8\u7684\u8cac\u4efb:\n1. \u70ba\u9999\u6e2f\u3001\u5167\u5730\u53ca\u6d77\u5916\u5ba2\u6236\u63d0\u4f9b\u6709\u5225\u4e8e\u9280\u884c\u7684\u5c08\u696d\u7406\u8ca1\u898f\u5283\uff0c\u5305\u62ec\uff1a\u4fdd\u96aa/\u98a8\u96aa\u7ba1\u7406\u7b56\u5283\u3001\u8ca1\u5bcc\u7ba1\u7406\u5efa\u8b70\u3001\u6295\u8cc7\u7b56\u5283\u3001\u53ca\u9000\u4f11\u7b56\u5283\n2. \u4e86\u89e3\u5ba2\u6236\u9700\u6c42\uff0c\u63d0\u4f9b\u5c08\u696d\u610f\u898b\u53ca\u5ea6\u8eab\u8a02\u9020\u7684\u7406\u8ca1\u53ca\u98a8\u96aa\u7ba1\u7406\u65b9\u6848\n3. \u5efa\u7acb\u500b\u4eba\u5f62\u8c61\u3001\u5de5\u4f5c\u7406\u5ff5\u53ca\u5718\u968a\u7406\u5ff5\n4. \u5354\u52a9\u4e26\u53c3\u8207\u5718\u968a\u7db2\u4e0a\u884c\u92b7\n5. \u5efa\u7acb\u53ca\u7ba1\u7406\u5c6c\u65bc\u81ea\u5df1\u7684\u5718\u968a\uff0c\u70ba\u5c07\u4f86\u6210\u70ba\u9818\u5c0e\u8005\u800c\u92ea\u8def\n\n\u62db\u52df\u5c0d\u8c61:\n1. \u826f\u597d\u6e9d\u901a\u80fd\u529b\n2. \u9858\u610f\u5b78\u7fd2\u4ee5\u53ca\u6311\u6230\u81ea\u6211\n3. \u5927\u5b78\u751f\u512a\u5148\uff0c\u6b61\u8fce\u61c9\u5c46\u7562\u696d\u751f\u53caIANG\uff0c\u5927\u5b78\u5b78\u4f4d\u6216\u4ee5\u4e0a\u53ef\u4eab\u984d\u5916\u6d25\u8cbc\n\n\n\u5f85\u9047\uff1a\n\u5b9a\u984d\u6e96\u8cbc\uff08$10,000 -$50,000) + \u4f63\u91d1\u00a0\u00a0(\u5927\u5b78\u7562\u696d\u751f\u53efDouble\u50ad\u91d1)\n\u5168\u6e2f\u6700\u591a\uff0c\u4e00\u5e749\u6b21\u82b1\u7d05\nProject Umbrella \u5c0e\u5e2b\u89aa\u81ea\u9032\u884c\u65b0\u4eba\u6559\u5b78\uff0c\u9996\u5e74\u8cbc\u8eab\u8f14\u52a9\n\u9054\u6a19\u4eab\u53d7\u516c\u53f8\u91ab\u7642\u798f\u5229\n\u516c\u53f8\u6d77\u5916\u65c5\u904a\u734e\u8cde\n\u5340\u57df\u6d77\u5916\u65c5\u904a\u734e\u8cde\n\u5354\u52a9\u7533\u8acbIANG\nAXA \u5c08\u696d\u57f9\u8a13\u5b78\u9662\u63d0\u4f9b\u5168\u9762\u5165\u8077\u53ca\u5728\u8077\u57f9\u8a13\n\n\u6709\u8208\u8da3\u7533\u8acb\u8005\u8acb\u6309Apply Now \u7533\u8acb\u3002", "employment_types": ["Full Time", "Part Time", "Freelance"], "selling_points": ["3\u540d\u5f8b\u5e2b\u5efa\u7acb\u7684\u9ad8\u5b78\u6b77\u9ad8\u54c1\u683c\u5718\u968a", "\u500b\u4eba\u5316\u57f9\u8a13 ; \u5e74\u8f15\u5c08\u696d\u570b\u969b\u5316", "\u52a9\u4f60\u8d70\u4e0d\u4e00\u6a23\u7684\u8def"], "locations": ["Kwun Tong"], "categories": ["Banking / Finance", "Retail Banking", "Insurance", "Insurance Agent / Broker", "Professional Services", "Legal & Compliance"], "post_time": "2022-01-18T03:58:59Z", "salary": {"currency": null, "max": null, "min": null, "period": "monthly", "term": null}, "salary_visible": false, "title_keywords": ["\u4fdd\u96aa\u4ee3\u7406"], "responsibilities": ["facebook"], "requirements": {"degrees": [], "majors": [], "languages": [], "language_level": [], "hard_skills": ["facebook"], "soft_skills": [], "languages_combined": []}, "experience_required": {"duration": [], "field": []}}, {"job_id": "100003009049391", "location_code": "hk", "company": "Lam Soon (Hong Kong) Limited", "job_title": "Legal Manager / Legal Executive (Ref:. JDB_21_035)", "description": "RESPONSIBILITIES\n\nWork closely with our HK and PRC Legal Team to draft and review various legal documents and correspondences with a diverse range of counterparties including suppliers, distributors, service providers and contractors to identify all key risks, relevant terms and conditions, as well as recommend appropriate solutions;\nProvide legal advice to business and operational units (covering corporate, commercial, and litigation matters) within the Group;\nWith the assistance of external counsel, handle intellectual property matters for business and operational units;\nProvide support to the Head of Legal in corporate and project-based transactions;\nMonitor development in laws, regulations and on-going compliance issues that will impact the business, and prepare reports on relevant matters to the Head of Legal;\nLiaising with external counsel and other counterparties (when required);\nSuch other tasks and responsibilities as identified by the Head of Legal.\n\n\nQUALIFICATIONS & WORK EXPERIENCES\n\u00a0 \u00a0 \u00a0 \u00a0 \u00a0 \u00a0 Legal Manager\n\u00a0 \u00a0 \u00a0 \u00a0 \u00a0 \u00a0 -\u00a0 A solicitor qualified to practise in HK or PRC, or holder of a degree in Law\n\u00a0 \u00a0 \u00a0 \u00a0 \u00a0 \u00a0 -\u00a0 2 \u2013 6 years\u2019 post qualification experience (in-house experience in Fast Moving\n\u00a0 \u00a0 \u00a0 \u00a0 \u00a0 \u00a0 \u00a0 \u00a0Consumer Goods sector will be an advantage although not a pre-requisite)\n\n\u00a0 \u00a0 \u00a0 \u00a0 \u00a0 \u00a0 Legal Executive\u00a0\n\u00a0 \u00a0 \u00a0 \u00a0 \u00a0 - \u00a0Minimum 2 years' experience in a law firm or an in-house environment (a\n\u00a0 \u00a0 \u00a0 \u00a0 \u00a0 \u00a0 \u00a0degree in Law will be an advantage but not a pre-requisite)\n\n\n\nREQUIREMENTS\n\n\nGood command of spoken and written Chinese and English\nBe able to handle matters independently, well organized with attention to details, proactive with strong sense of responsibility\nGood team player and strong interpersonal skills\nGood command in MS Office & Chinese Word processing\n\n\n\nWe offer transportation arrangements as part of our comprehensive benefits to the right candidate. Please apply with full resume, together with your present and expected salary and contact telephone number by clicking \"Apply Now\".\nFor more company details, please visit our website www.lamsoon.com\n\n(Data collected will be treated in the strictest confidence and only be used for recruitment purpose only.)\u00a0\n\nLam Soon Hong Kong Group\n21 Dai Fu Street, Tai Po Industrial Estate, Tai Po, Hong Kong SAR", "employment_types": ["Full Time", "Permanent"], "selling_points": ["2 \u2013 6 years relevant work experience", "Holder of a degree in Law", "Good team player and strong interpersonal skills"], "locations": ["Tai Po Area"], "categories": ["Professional Services", "Legal & Compliance"], "post_time": "2022-01-14T08:32:47Z", "salary": {"currency": null, "max": null, "min": null, "period": "monthly", "term": null}, "salary_visible": false, "title_keywords": ["legal executive", "manager"], "responsibilities": ["regulations", "provide support", "review", "monitor", "compliance", "transactions", "liaising with", "other tasks", "prepare reports"], "requirements": {"degrees": [], "majors": [], "languages": ["english", "chinese"], "language_level": ["good command"], "hard_skills": ["chinese word processing", "ms office"], "soft_skills": ["good team player", "independently", "sense of responsibility", "well organized", "interpersonal skills", "attention to details", "proactive"], "languages_combined": [{"language": "english", "language_level": ["good command"]}, {"language": "chinese", "language_level": ["good command", "good command"]}]}, "experience_required": {"duration": [], "field": []}}, {"job_id": "100003009049537", "location_code": "hk", "company": "William Lee and Associates", "job_title": "Paralegal / Legal Executive / Trainee Solicitor / Legal Secretary", "description": "Paralegal / Legal Executive\u00a0\u00a0\n\nCandidates with experience will be preferred but not strictly necessary\nCandidate will be trained to handle cases with good initiative under\u00a0supervision\nGood command of English & Chinese will be an advantage\nAble and willing to learn\nFresh or recent graduate (whether from the Faculty of Law or not) will be considered\nProficient in PC skills (e.g. Word, Excel & etc.) and Chinese Word Processing\n\nTrainee Solicitor\n\n\nGood Academic background will be an advantage\nHardworking, meticulous, responsible, well organized & ready to learn\nGood Command in both written & spoken English & Chinese\nProficient in PC skills\n2nd year will also be considered\n\nLegal Secretary\n\nExpected to be responsible, diligent, punctual, conscientious and courteous\nGood knowledge in both English and Chinese Languages\nProficient in PC skills (Word, Excel & etc.)\nFast & accurate typing skill (Both English & Chinese)\n\nInterested candidates please apply with full C.V., stating the latest and expected salary to The Principal of William Lee and Associates, 16/F, Dah Sing Life Building, 99 Des Voeux Road Central or by clicking \"Apply Now\".\n\nData collected will be used for recruitment purpose only.", "employment_types": ["Full Time", "Permanent"], "selling_points": [], "locations": ["Central"], "categories": ["Professional Services", "Legal & Compliance"], "post_time": "2022-01-14T09:30:44Z", "salary": {"currency": null, "max": null, "min": null, "period": "monthly", "term": null}, "salary_visible": false, "title_keywords": ["legal executive", "paralegal", "legal secretary", "trainee solicitor"], "responsibilities": [], "requirements": {"degrees": [], "majors": [], "languages": ["english", "chinese"], "language_level": ["advantage", "good command", "good"], "hard_skills": ["excel", "chinese word processing", "word", "typing", "pc skills"], "soft_skills": ["meticulous", "courteous", "responsible", "willing to learn", "well organized", "diligent", "conscientious", "accurate", "initiative", "hardworking"], "languages_combined": [{"language": "english", "language_level": ["advantage", "good command", "good command", "good", "good", "good"]}, {"language": "chinese", "language_level": ["advantage", "good command", "good command", "good", "good", "good"]}]}, "experience_required": {"duration": [], "field": []}}, {"job_id": "100003009054955", "location_code": "hk", "company": "Harneys (Asia) Limited", "job_title": "Client Services Assistant", "description": "THE ROLE\n\nWe are looking for Client Services Assistant within Harneys Fiduciary Business Development Team.\n\n\u00a0RESPONSIBILITIES\n\nAssist to handle phone call or correspondence with clients\nProactively support business development team members to develop lists of target clients, attend client meetings, prepare quotations and marketing materials\nMaintain good communication with clients on a regular basis\nHandling marketing data entry (name card and sugar)\nAssisting on KYC admin duty\nPreparing Template and information sheet for incorporation, transfer in, company name change\nAssisting on Conference & Event Update\nPreparing Compliance guideline\nCreating FAQ for client and PowerPoint /PDF if need.\nAssisting on any other ad Hoc job tasks and projects as required\n\nQUALIFICATIONS & EXPERIENCE\n\nDegree Holder in related discipline\nExperience in administration related roles is preferred but not essential\nWe welcome applicants who are going to graduate this summer\nAbility to communicate properly and effectively (orally and in writing)\nAbility to work in a face-paced environment with tight deadlines\nProficient in MS Office applications and necessary software used by the department\nHigh level of trust and attention to detail", "employment_types": ["Full Time", "Permanent"], "selling_points": ["Provide administrative support", "Fresh graduates are welcome", "Attractive remuneration package"], "locations": ["Sheung Wan"], "categories": ["Admin & HR", "Clerical / Admin Staff", "Professional Services", "Legal & Compliance"], "post_time": "2022-01-17T14:57:06Z", "salary": {"currency": null, "max": null, "min": null, "period": "monthly", "term": null}, "salary_visible": false, "title_keywords": ["assistant"], "responsibilities": ["ad hoc", "software", "data entry", "compliance", "maintain good communication", "develop", "kyc", "marketing materials", "administration"], "requirements": {"degrees": ["degree holder"], "majors": [], "languages": [], "language_level": [], "hard_skills": ["powerpoint", "ms office", "sugar", "kyc"], "soft_skills": ["communication", "attention to detail", "orally"], "languages_combined": []}, "experience_required": {"duration": [], "field": ["related", "administration"]}}, {"job_id": "100003009049823", "location_code": "hk", "company": "Beijing Tong Ren Tang Chinese Medicine Company Limited", "job_title": "\u5408\u898f\u5c08\u54e1 Compliance Assistant", "description": "\u8077\u8cac:\n1.\u8ca0\u8cac\u516c\u53f8\u5408\u898f\u7ba1\u7406\u9ad4\u7cfb\u5efa\u8a2d\uff0c\u4e26\u6307\u5c0e\u4e0b\u5c6c\u55ae\u4f4d\u7684\u5408\u898f\u7ba1\u7406\u5de5\u4f5c\uff1b\n2.\u8ca0\u8cac\u5408\u898f\u98a8\u96aa\u8b58\u5225\u8207\u8a55\u4f30\uff0c\u5c0d\u91cd\u5927\u98a8\u96aa\u9032\u884c\u76e3\u63a7\uff0c\u7de8\u5236\u98a8\u96aa\u7ba1\u7406\u5831\u544a\uff1b\n3.\u8ca0\u8cac\u5236\u5b9a\u3001\u4fee\u8a02\u516c\u53f8\u5408\u898f\u7ba1\u7406\u76f8\u95dc\u88fd\u5ea6\u3001\u624b\u518a\u7b49\u6587\u4ef6\uff1b\n4.\u8ca0\u8cac\u516c\u53f8\u88fd\u5ea6\u7b49\u6587\u4ef6\u7684\u5408\u898f\u6027\u5be9\u6838\u8207\u7ba1\u7406\uff1b\n5.\u8ca0\u8cac\u958b\u5c55\u5408\u898f\u76e3\u7763\u8abf\u67e5\u3001\u5408\u898f\u5ba3\u50b3\u3001\u5408\u898f\u57f9\u8a13\u6d3b\u52d5\uff1b\n6.\u8ca0\u8cac\u5408\u898f\u7ba1\u7406\u4fe1\u606f\u5316\u5e73\u53f0\u7684\u5efa\u8a2d\u3001\u7ba1\u7406\u548c\u63a8\u5ee3\u904b\u7528\uff1b\n7.\u914d\u5408\u96c6\u5718\u516c\u53f8\u5408\u898f\u7ba1\u7406\u5de5\u4f5c\u7684\u5efa\u8a2d\uff1b\n8.\u5176\u4ed6\u81e8\u6642\u6027\u5de5\u4f5c\u3002\n\n\u8981\u6c42:\n1.\u5177\u67093\u5e74\u4ee5\u4e0a\u4f01\u696d\u5408\u898f\u3001\u5167\u63a7\u3001\u98a8\u96aa\u7ba1\u7406\u6216\u6cd5\u52d9\u5de5\u4f5c\u7d93\u9a57\u512a\u5148\uff1b\n2.\u5177\u6709\u4e2d\u570b\u5167\u5730\u6cd5\u5f8b\u8077\u696d\u8cc7\u683c\u6216\u666e\u901a\u6cd5\u570b\u5bb6\u6216\u5730\u5340\u5f8b\u5e2b\u8cc7\u683c\u3001\u8a3b\u518a\u6703\u8a08\u5e2b\u7b49\u8cc7\u8cea\u512a\u5148\uff1b\n3.\u5177\u6709\u826f\u597d\u7684\u6e9d\u901a\u80fd\u529b\u3001\u5206\u6790\u80fd\u529b\u53ca\u5718\u968a\u5408\u4f5c\u80fd\u529b\uff1b\n4.\u5177\u6709\u8f03\u5f37\u7684\u6587\u5b57\u5beb\u4f5c\u80fd\u529b\uff0c\u826f\u597d\u7684\u4e2d\u82f1\u6587\u8868\u9054\u80fd\u529b\uff1b\n5.\u5177\u6709\u826f\u597d\u7684\u8077\u696d\u64cd\u5b88\uff0c\u8a8d\u540c\u4f01\u696d\u5408\u898f\u6587\u5316\u3002", "employment_types": ["Full Time"], "selling_points": [], "locations": ["Wan Chai"], "categories": ["Professional Services", "Company Secretary", "Legal & Compliance", "Banking / Finance", "Risk Management"], "post_time": "2022-01-14T09:17:10Z", "salary": {"currency": null, "max": null, "min": null, "period": "monthly", "term": null}, "salary_visible": false, "title_keywords": ["compliance assistant"], "responsibilities": [], "requirements": {"degrees": [], "majors": [], "languages": [], "language_level": [], "hard_skills": [], "soft_skills": [], "languages_combined": []}, "experience_required": {"duration": [], "field": []}}, {"job_id": "100003009055518", "location_code": "hk", "company": "Beijing Energy International Investment Limited", "job_title": "Company Secretarial Officer", "description": "Responsibilities:\n\nHandle all-round company secretarial and compliance affairs for listed company and its subsidiaries, including HK, BVI and other jurisdictions;\nAssist in preparation of general meetings of shareholders, board meetings and sub-committee meetings\nAssist in preparation of announcements, circulars, interim and annual reports in a timely and accurate manner\nLiaise with various parties, including the printers, lawyers, auditors, share registrars and ESG reporting consultancy\nUpdate and maintain efficient statutory and corporate filing systems\nProvide administrative support to the team and assist in ad hoc projects\n\nRequirements:\n\nBachelor degree or above in Finance, Legal, Corporate Governance or Language related disciplines is preferable\nMember or Student Member of HKICS/ ICSA\nMinimum 2 years\u2019 relevant experience gained in listed companies or professional firms\nFamiliar with the Listing Rules, Securities and Futures Ordinance and other relevant regulations\nA good team player with strong comprehensive analysis, communication and coordination skills\nGood writing and reading in both Chinese and English, fluent Putonghua is a must\nImmediate available is highly preferred", "employment_types": ["Full Time"], "selling_points": ["Minimum 2 years\u2019 relevant experience", "Member or Student Member of HKICS/ ICSA", "Immediate available is highly preferred"], "locations": ["Sheung Wan"], "categories": ["Professional Services", "Company Secretary", "Legal & Compliance", "Translation"], "post_time": "2022-01-18T02:40:30Z", "salary": {"currency": null, "max": null, "min": null, "period": "monthly", "term": null}, "salary_visible": false, "title_keywords": ["company secretarial officer"], "responsibilities": ["reporting", "compliance", "systems", "maintain", "reports", "ad hoc projects", "liaise with", "provide administrative support"], "requirements": {"degrees": ["degree or above", "bachelor"], "majors": ["related disciplines", "finance"], "languages": ["putonghua", "english", "chinese"], "language_level": ["fluent", "good"], "hard_skills": ["analysis", "securities and futures ordinance"], "soft_skills": ["communication", "good team player", "comprehensive", "coordination skills"], "languages_combined": [{"language": "putonghua", "language_level": ["fluent", "good"]}, {"language": "english", "language_level": ["good"]}, {"language": "chinese", "language_level": ["good"]}]}, "experience_required": {"duration": ["minimum 2 years"], "field": ["relevant experience"]}}, {"job_id": "100003009045287", "location_code": "hk", "company": "Henry Wai & Co.,Solicitors LLP", "job_title": "Paralegal / PRC Legal Assistant", "description": "We are a firm specializing in cross-border (i) commercial and corporate litigation and arbitration and (ii) commercial and corporate transactions, in the Greater China Region.\n\nRequirements:\n\nLaw graduates with\u00a0LL.B. or J.D. degree\u00a0in Hong Kong or other common law jurisdictions for Paralegal.\nLaw graduates from top universities in Mainland China with Master of Laws degree in Hong Kong or other common law jurisdiction for PRC Legal Assistant.\nWork experience in either Hong Kong law firm(s) or PRC other is preferred.\nGood command of both written\u00a0and spoken English and Chinese (Cantonese and Mandarin Chinese).\nEfficient word processing ability in both English and Chinese and in using Excel and PowerPoint.\nWe offer attractive remuneration package to the right candidates.\nImmediately available or short notice is preferred.\n\nPlease send applications together with full CV to the\u00a0Senior Partner, Henry Wai & Co., Solicitors LLP\u00a0by clicking \u201cApply Now\u201d below to submit your application.\n\nAll personal data collected will be used for recruitment purpose only.\u00a0 Applicants not hearing from us within 3 months may consider their applications filed for future reference.\u00a0 All personal data collected will be kept in strict confidence and only for employment-related purposes.", "employment_types": ["Full Time", "Contract"], "selling_points": ["Law degree above", "We offer attractive remuneration package", "Immediately available or short notice is preferred"], "locations": ["Admiralty"], "categories": ["Professional Services", "Legal & Compliance"], "post_time": "2022-01-13T07:33:12Z", "salary": {"currency": null, "max": null, "min": null, "period": "monthly", "term": null}, "salary_visible": false, "title_keywords": ["paralegal", "legal assistant"], "responsibilities": ["transactions"], "requirements": {"degrees": ["degree", "master"], "majors": ["laws", "law"], "languages": ["cantonese", "english", "chinese", "mandarin chinese"], "language_level": ["good command"], "hard_skills": ["excel", "word processing", "powerpoint"], "soft_skills": ["efficient"], "languages_combined": [{"language": "cantonese", "language_level": ["good command"]}, {"language": "english", "language_level": ["good command"]}, {"language": "chinese", "language_level": ["good command"]}, {"language": "mandarin chinese", "language_level": ["good command"]}]}, "experience_required": {"duration": [], "field": []}}, {"job_id": "100003009056132", "location_code": "hk", "company": "Solomon Systech Limited", "job_title": "IP Administrator / Manager (Part-time / Full time)", "description": "Job Responsibilities:\nWork closely with design teams to develop and explore intellectual property opportunities;\nResearch and analyze inventions and patent information and to identify prior arts;\nConduct patent research of intellectual property such as novelty search, infringement research to identify patent assets before patent application;\nLiaise with external parties such as attorneys and inventors to define patent specification, and follow up and review documents;\nAssist in registration and renewal of patent both locally and internationally;\nPerform administrative duties such as maintain database for IP, filing applications and granted patents.\nJob Requirements:\nB.Sc or above in Engineering / Law or equivalent;\nWith at least 1-year relevant experience in the areas of IP / patent administration;\nGood command in both English and Chinese (include Mandarin);\nHighly sensitive to timelines and meeting deliverables;\nCandidate with more experience will be consider as IP Manager.", "employment_types": ["Full Time", "Part Time", "Permanent"], "selling_points": ["Well Established Semiconductor Company", "Develop intellectual property opportunities", "Conduct patent research of intellectual property"], "locations": ["Shatin Area"], "categories": ["Engineering", "Electrical / Electronics", "Others", "Professional Services", "Legal & Compliance"], "post_time": "2022-01-18T03:22:14Z", "salary": {"currency": null, "max": null, "min": null, "period": "monthly", "term": null}, "salary_visible": false, "title_keywords": ["administrator", "manager"], "responsibilities": ["external parties", "teams", "review", "design", "develop", "maintain", "administrative duties", "database", "liaise with"], "requirements": {"degrees": [], "majors": [], "languages": ["english", "chinese", "mandarin"], "language_level": ["good command"], "hard_skills": ["ip"], "soft_skills": ["sensitive to"], "languages_combined": [{"language": "english", "language_level": ["good command"]}, {"language": "chinese", "language_level": ["good command"]}, {"language": "mandarin", "language_level": ["good command"]}]}, "experience_required": {"duration": ["at least 1-year"], "field": ["relevant experience", "administration"]}}, {"job_id": "100003009055104", "location_code": "hk", "company": "Autotoll Limited", "job_title": "Finance, Audit and Compliance Team Leader", "description": "To cope with our expansion and continuous growth in the transportation and logistics related service, we are inviting talents to join our professional team.\n\nAbout The Role:\n\nPrepare monthly report as required\nReview the daily report for monies received from all channels; daily toll reports & revenue reports\nReview the redemption report and arrange the refund\nReview the daily report for fund transfer to Government account\n\n\nAbout You:\n\nHolder of university degree or equivalent qualification\nAt least four years post-qualification full time working experience in customer service roles, of which at least two years shall be at managerial or supervisory level\n\nOr\n\nDSE or above; LCC level 2 or above\nOver five years working experience in Accounting and at least three years in supervisory grade\n\n\n\n\nWhat you can get from us:\n\nOn-the-job training, learning and development\u00a0provided\nExecutive workshops, interest class, corporate purchase discount offered by SHKP\nCompetitive salary and annual leaves\nFlexible working opportunities\n\nInterested parties, please send full resume with\u00a0expected salary\u00a0and\u00a0available date\u00a0to Human Resources and Administration Department by e-mail or by fax 2111 9459.\n\n(Data collected will be used for recruitment purpose only.)", "employment_types": ["Full Time", "Permanent"], "selling_points": ["Holder of university degree", "At least four years experience in cs roles", "5-day work, bank holiday, AL & medical plan."], "locations": ["Kowloon Bay"], "categories": ["Banking / Finance", "Others", "Professional Services", "Legal & Compliance", "Others", "Others"], "post_time": "2022-01-18T01:15:13Z", "salary": {"currency": null, "max": null, "min": null, "period": "monthly", "term": null}, "salary_visible": false, "title_keywords": ["team leader"], "responsibilities": ["review", "purchase", "customer service", "logistics", "reports", "monthly report", "daily report", "report"], "requirements": {"degrees": ["university degree", "dse"], "majors": [], "languages": [], "language_level": [], "hard_skills": ["workshops", "lcc"], "soft_skills": ["flexible", "customer service", "learning"], "languages_combined": []}, "experience_required": {"duration": ["at least three years", "at least two years", "five years", "at least four years"], "field": ["managerial", "supervisory", "post-qualification", "customer service", "supervisory level", "accounting"]}}, {"job_id": "100003009054953", "location_code": "hk", "company": "Harneys (Asia) Limited", "job_title": "AML Officer Services Manager, Asia", "description": "The successful candidate will be appointed as the Anti-Money Laundering Compliance Officer (\u201cAMLCO\u201d) and/or Money Laundering Reporting Officer (\u201cMLRO\u201d) or Deputy MLRO (\u201cDMLRO\u201d) as required under the Cayman Islands Anti-Money Laundering laws and regulation to a portfolio of external clients and is expected to implement, advise on and monitor effective AML/CFT/CPF and Sanctions systems, procedures and controls.\n\n\nJob Duties\n\n\nProvide Anti-Money Laundering Compliance Officer and Money Laundering Reporting Officer services to a portfolio of external clients.\nUnderstand and apply the Cayman Islands AML/CFT/CPF laws and regulations and international standards to client portfolio\u2019s\nDevelop and undertake regular risk assessments on investors, clients and investment activities including analysing the geographical and business relationship, products, transactions and delivery channels etc\nConsider and identify risks in the business, it\u2019s activities and clients and advise accordingly\nProvide advice, identifying key compliance issues and addressing controlling parties/board of directors of key findings on a regular basis\nBe able to communicate and understand risk matrixes with third party service providers\nConsider and make suspicious activity filings\nPerform AML/CFT/CPF and Sanctions audits, testing\u2019s and AML reviews\nMaintaining logs, as necessary, with respect to declined business, politically exposed persons, non-compliance etc;\nAnalyse legal & regulatory changes affecting the clients compliance environment and their impact on existing policies & procedures\nDay to day management of client regulatory, compliance, monitoring risks.\nManage the client life cycle from new business take on through to business as usual, e.g. client set up, monitoring, billing and invoicing.\nDevelop key AML/CFT/CPF policies, operating procedures and management information reporting procedures as they pertain to the relevant service line.\nEnsure regular reviews of clients AML/CFT programs.\nManage escalation issues appropriately and in a timely manner\nAssist with regulatory visits by the Cayman Islands Monetary Authority, and internal/external audit\nProvide guidance on client business procedures / processes as and when required.\nConduct client AML/ CFT / CPF and Sanctions training.\nDeliver departmental projects to quality standards, deadlines and costs.\nDevelop systems and controls for the conduct and on-going monitoring of clients and help with identifying any AML/CTF loopholes and coordinating projects to bridge those gaps\n\nRequirements\n\nA legal, compliance or corporate secretarial degree.\nAbility to manage own client portfolio with little direction\n5 + years of practical experience in an external AML Officer role, or other legal or regulatory experience in Cayman and/or BVI investment funds industry.\nPrevious CIMA regulatory authority approval as an AML Officer an advantage.\nSolid understanding of Cayman Islands and BVI corporate structures, in particular mutual and private funds .\nSelf-motivated, analytical and can deliver under pressure to deadlines.\nStrong attention to detail with the ability to deliver accurate documentation under tight timescales.\nUse of initiative to improve processes and ability to review and implement strategy.\nEffective written and oral communication skills.\nEncourage team spirit and professionalism, assisting colleagues and the business as needed.\nHighly proficient in Microsoft Word, Excel, Outlook.\nAbility to review, understand and implement systems, controls and procedures and document changes as needed.\nBusiness fluent Mandarin and Cantonese is preferred", "employment_types": ["Full Time", "Permanent"], "selling_points": ["Compliance Outsourcing Services", "5+ years of experience in relevant industry", "Attractive remuneration package"], "locations": ["Central"], "categories": ["Professional Services", "Legal & Compliance"], "post_time": "2022-01-17T14:56:05Z", "salary": {"currency": null, "max": null, "min": null, "period": "monthly", "term": null}, "salary_visible": false, "title_keywords": ["officer", "manager"], "responsibilities": ["regulations", "quality", "audit", "transactions", "costs", "maintaining", "compliance", "develop", "testing", "reporting", "management", "monitoring", "procedures", "audits", "provide guidance", "third party", "aml", "policies", "systems", "a timely manner", "invoicing", "provide advice", "analyse"], "requirements": {"degrees": ["degree"], "majors": [], "languages": ["cantonese", "mandarin"], "language_level": ["fluent"], "hard_skills": ["excel", "microsoft word", "aml", "outlook", "cima", "documentation"], "soft_skills": ["communication skills", "self-motivated", "oral", "under pressure", "team spirit", "attention to detail", "accurate", "initiative"], "languages_combined": [{"language": "cantonese", "language_level": ["fluent"]}, {"language": "mandarin", "language_level": ["fluent"]}]}, "experience_required": {"duration": ["5 + years"], "field": ["investment", "legal"]}}, {"job_id": "100003009055472", "location_code": "hk", "company": "API Lab Testing Limited", "job_title": "TCF Engineer (Textile)", "description": "Job Overview:\n\nAs a TCF Textile Engineer, he/she need to conduct the compliance and tracerabaility documentation check under the projects from fibre, style and final product accrording to the customer request. He/she need to contact and communicate with the worldwide suppliers for chasing the documents, reviewing the document, providing the status report to customer and joining the customer review meeting with KAM and other managmnent occasionally & regularly.\n\nEssential Duties and Responsibilities:\n\nCollecting, reviewing and validating certificates and test reports from suppliers reg. traceability.\nKeep clients and their suppliers updated and monitor the program status.\nUndertake any other duties in coping with the business growth.\nAssists in other duties as directed by the Manager.\n\nExperience & Competencies Required:\n\nAt least 2 years' experience in textile product testing or textile trading / manufacturing company,\nFamiliar with raw material / fabric/ garment compliance/ supply chain traceability\nExtensive knowledge of textile manufacturing processes will be strong plus.\nWorking experience in commercial testing laboratory/ in house testing laboratory will be an advantage\nFamiliar with EU/US regulation on Textile, knowledge on other categories such as toys, furniture, chemical and related regulations are highly preferable\nCandidate with more experience will be considered as Senior Engineer.\nHighly-organized, capable of working under pressure with multi-task assignments\nGood command of English and Chinese.\n\nEducation and Qualifications Required:\n\nHigh Diploma or above in Textile or related discipline\n\nTools Skills:\n\nProficient in Microsoft Programs, including Word, Excel, PowerPoint and Outlook.\n\nDisclaimer:\n\nJob duties and requirements are subject to change. The company reserves the right to modify position descriptions accordingly at any time with little or no prior notice.", "employment_types": ["Full Time"], "selling_points": ["TCF Engineer, Textile, Lai Chi Kok", "Material, Fabric, Garment Compliance, Supply chain", "Reviewing & Validating Certificates, Quality"], "locations": ["Kowloon City"], "categories": ["Manufacturing", "Garment / Textile", "Professional Services", "Legal & Compliance", "Quality Assurance, Control & Testing / ISO"], "post_time": "2022-01-18T02:38:04Z", "salary": {"currency": "HKD", "max": 24999, "min": 20000, "period": "monthly", "term": null}, "salary_visible": true, "title_keywords": ["engineer"], "responsibilities": ["communicate with", "any other duties", "regulations", "other duties", "compliance", "review", "monitor", "testing", "reports", "contact", "documentation", "report"], "requirements": {"degrees": ["high diploma or above"], "majors": [], "languages": ["english", "chinese"], "language_level": ["good command"], "hard_skills": ["excel", "plus", "no", "word", "powerpoint", "outlook", "documentation"], "soft_skills": ["organized", "under pressure", "capable", "multi-task", "extensive"], "languages_combined": [{"language": "english", "language_level": ["good command"]}, {"language": "chinese", "language_level": ["good command"]}]}, "experience_required": {"duration": ["at least 2 years"], "field": ["laboratory", "manufacturing", "senior engineer", "testing", "commercial", "textile", "trading"]}}, {"job_id": "100003009054373", "location_code": "hk", "company": "Bright Smart Securities International (H.K.) Limited", "job_title": "Company Secretary", "description": "Responsibilities:\n\nPerform company secretarial duties for the Group, listed company and its subsidiaries;\nDraft and prepare annual / interim reports, announcements and circulars;\nOrganize meetings for the board, committees and shareholders, and prepare relevant board papers and minutes;\nMaintain and update statutory records / filings in compliance with HK Listing Rules;\nAssist to review on all legal and compliance documents including internal, external contracts and agreements;\nPerform any ad hoc projects and tasks assigned from management.\nRequirements:\n\nDegree holder, preferably with associate / graduate of HKICS / ICSA or equivalent;\nMinimum of 4 years or above relevant experience in listed companies is required;\nPrior hands-on working experience in handling company secretarial matters is a MUST;\nKnowledge in Companies Ordinance and Listing Rules;\nExcellent command of English and Chinese;\nWell-organized,\u00a0self-motivated and able to work independently;\nCandidates with more experience will be considered as Assistant Manager.\nWe Offer:\nCompetitive remuneration package\n5 Days Work & Bank Holidays\nAttendance Bonus\nMeal Allowance\nDiscretionary Bonus\nMedical Insurance\nWe provide attractive remuneration package and fringe benefits for the right candidate. Interested parties please send detailed resume with current and expected salaries to\u00a0Human Resources Department by clicking \"Apply Now\" or fax to: 2530 2218.\nAll information collected will be used for recruitment purpose only, only shortlisted candidates will be notified.\n\nWelcome to visit our website: http://www.bsgroup.com.hk/ for more information.", "employment_types": ["Full Time", "Permanent"], "selling_points": [], "locations": ["Central"], "categories": ["Banking / Finance", "Others", "Professional Services", "Company Secretary", "Legal & Compliance"], "post_time": "2022-01-17T09:18:37Z", "salary": {"currency": null, "max": null, "min": null, "period": "monthly", "term": null}, "salary_visible": false, "title_keywords": ["company secretary"], "responsibilities": ["management", "contracts", "compliance", "review", "maintain", "reports", "ad hoc projects", "listing"], "requirements": {"degrees": ["degree holder"], "majors": [], "languages": ["english", "chinese"], "language_level": ["excellent"], "hard_skills": ["companies ordinance"], "soft_skills": ["hands-on", "well-organized", "work independently", "self-motivated"], "languages_combined": [{"language": "english", "language_level": ["excellent"]}, {"language": "chinese", "language_level": ["excellent"]}]}, "experience_required": {"duration": ["minimum of 4 years"], "field": ["secretarial", "relevant experience"]}}, {"job_id": "100003009046105", "location_code": "hk", "company": "TRM (HK) Ltd", "job_title": "Legal Clerk/Paralegal/Loss Adjuster Trainee", "description": "Paralegal/Legal Clerk\nResponsibilities:\n\n\n\u00a0 \u00a0Assist in-house lawyers with the daily handling of claim and legal cases\n\u00a0\u00a0 Communicate and liaise with clients\n\u00a0\u00a0 Provide general clerical support to the team\n\nRequirements:\n\nHigher Diploma, Degree in legal studies or equivalent\u00a0\nLegal Executive qualification an advantage\nExperience in legal or insurance-related firms preferred\nWell-organized, attention to details and responsible\nProficient in English and Chinese typing\nProficient in MS Office software including Word, Excel and Outlook\n\nWe offer attractive compensation package for the right candidate.\n\nLoss Adjuster Trainee\nResponsibilities:\n\n\nConduct interviews and on-site investigations\nPrepare investigation reports to clients\nComment on liability and reserve\nRequirements:\n\nDegree equivalent or above\nWell-organized, attention to details with good analytical and communication skills\nProficient in English and Chinese typing\nProficient in MS Office software including Word, Excel and Outlook\nManage Chinese Typing\nFresh graduates will be considered\nWe offer attractive compensation package with good career prospects.\u00a0 In service trainings will be provided for the right candidate.\u00a0\u00a0\n\nInterested parties, please send us your CV with availability, current and expected salary.\u00a0 All applications will be treated in strict confidence and used for recruitment purposes only.", "employment_types": ["Full Time", "Permanent"], "selling_points": ["Legal case handling, Loss Adjuster", "Statement taking, site investigation, Liability", "Paralegal, legal clerk, settlement negotiation"], "locations": ["Wan Chai"], "categories": ["Insurance", "Claims Officer", "Professional Services", "Legal & Compliance"], "post_time": "2022-01-13T09:38:09Z", "salary": {"currency": null, "max": null, "min": null, "period": "monthly", "term": null}, "salary_visible": false, "title_keywords": ["loss adjuster trainee", "paralegal", "legal clerk"], "responsibilities": ["liaise with clients", "clerical support"], "requirements": {"degrees": ["diploma", "degree"], "majors": [], "languages": ["english", "chinese"], "language_level": ["proficient"], "hard_skills": ["excel", "typing", "word", "outlook", "ms office"], "soft_skills": ["well-organized", "attention to details", "responsible"], "languages_combined": [{"language": "english", "language_level": ["proficient", "proficient"]}, {"language": "chinese", "language_level": ["proficient", "proficient"]}]}, "experience_required": {"duration": [], "field": ["related", "insurance", "legal"]}}, {"job_id": "100003009051212", "location_code": "hk", "company": "One Recruitment Limited", "job_title": "Paralegal - Corporate Finance (40k + OT)", "description": "Our client, an international law firm is urgently looking for a Paralegal, Corporate Finance to join their dynamic team in Central office.\n\nJob Responsibilities:\n\nMaintain proper filing management system for IPO transactions of HK/China regions\nConduct legal research, due diligence and documentation\nHandle interview and attend meetings with Associates on listing matters and requirements\nAssist in preparing verification note and related coordination\nHandle translations and drafting\nProvide full spectrum legal support to Partners and Associate\nJob Requirements:\n\nBachelor degree of law with at least 1 year experience in corporate finance areas within legal firms/ brokerage firms\nPrevious experience in Corporate in one of the following, such as M&A/IPO/DD/DCM is preferred\nFluency of English with native Mandarin is highly recommended\u00a0\nAble to work under pressure\nGood interpersonal and communication skills", "employment_types": ["Full Time", "Permanent"], "selling_points": ["Good Job Satisfaction", "Prime Working Location", "Attractive Remuneration Package"], "locations": ["Central"], "categories": ["Banking / Finance", "Investment", "Professional Services", "Company Secretary", "Legal & Compliance"], "post_time": "2022-01-15T04:53:32Z", "salary": {"currency": "HKD", "max": 44999, "min": 35000, "period": "monthly", "term": null}, "salary_visible": true, "title_keywords": ["paralegal", "corporate finance"], "responsibilities": ["due diligence", "management", "transactions", "maintain", "attend meetings", "coordination", "documentation", "listing"], "requirements": {"degrees": ["degree", "bachelor"], "majors": ["finance", "law"], "languages": ["english", "mandarin"], "language_level": ["fluency", "native"], "hard_skills": [], "soft_skills": ["communication skills", "interpersonal", "work under pressure"], "languages_combined": [{"language": "english", "language_level": ["fluency"]}, {"language": "mandarin", "language_level": ["native", "fluency"]}]}, "experience_required": {"duration": ["at least 1 year"], "field": ["brokerage", "legal", "corporate finance"]}}, {"job_id": "100003009046476", "location_code": "hk", "company": "CTBAT International Co. Limited", "job_title": "Assistant Legal Manager", "description": "\u00a0Responsibilities:\n\nHandle a range of legal work, including revising and negotiation agreements\nTackle local and overseas regulatory affairs and compliance matters\nHandle independently full spectrum of company secretarial\u00a0matters\nOrganize and attend Board / Board committee / shareholder meetings and prepare relevant meeting materials\nUpdate company policies and conduct legal training\nManage external trademark counsel\nConduct legal and regulatory research and analysis\nAd hoc tasks upon\u00a0request\n\n\u00a0Requirements:\n\nBachelor of Laws (LLB) in Law\nMinimum 5 years of relevant work experience preferred with PRC experience\nSelf-motivated, attention to details with strong sense of responsibility, and able to work independently\nGood interpersonal\u00a0communication skills and strong command of spoken and written Mandarin and English\nGood PC skills in MS Office and Chinese Word Processing\n\nCompetitive remuneration package and fringe benefits will be offered to successful candidates. Please send\u00a0your\u00a0resume with present and expected salary\u00a0to\u00a0The Human Resources\u00a0Department, CTBAT International Co. Limited, 29/F., Oxford House, Taikoo Place, 979 King's Road, Quarry Bay, Hong Kong.\n\nCTBAT International\u00a0Co. Limited is an equal opportunity employer, all the qualified candidates are welcome\u00a0to apply for the position.\n\nAll the data collected will be treated as strictly confidential and will\u00a0be used on employment related purpose only.", "employment_types": ["Full Time", "Permanent"], "selling_points": [], "locations": ["Quarry Bay"], "categories": ["Professional Services", "Company Secretary", "Legal & Compliance"], "post_time": "2022-01-13T11:42:25Z", "salary": {"currency": null, "max": null, "min": null, "period": "monthly", "term": null}, "salary_visible": false, "title_keywords": ["manager", "assistant"], "responsibilities": ["policies", "analysis", "compliance", "ad hoc tasks"], "requirements": {"degrees": ["bachelor"], "majors": ["laws", "law"], "languages": ["english", "chinese", "mandarin"], "language_level": ["good"], "hard_skills": ["pc skills", "chinese word processing", "ms office"], "soft_skills": ["communication skills", "self-motivated", "work independently", "sense of responsibility", "attention to details", "interpersonal"], "languages_combined": [{"language": "english", "language_level": ["good"]}, {"language": "chinese", "language_level": ["good"]}, {"language": "mandarin", "language_level": ["good"]}]}, "experience_required": {"duration": ["minimum 5 years"], "field": []}}, {"job_id": "100003009055921", "location_code": "hk", "company": "Michael Page", "job_title": "AVP Central Compliance - US Investment Bank", "description": "Responsible for central compliance duties including surveillance, disclosure of interest, regulatory licensing, compliance training, and personal account dealing. Report directly to the HK Head of Compliance.\n\nClient Details\n\nMy client is a boutique sized US based investment bank. They have about 120 staff in Hong Kong and have a strong footprint in Asia.\n\nDescription\n\nReport directly to the HK Head of Compliance working alongside other compliance staff\nDisclosure of Interest reporting, regulatory licensing, compliance training, surveillance and PAD\n\nProfile\n\n3-6years+ of compliance experience within investment bank\nopen to big 4 candidates with compliance consulting experience\ncandidate should have experience in surveillance and DOI\nmust be able to work independently\nmust be articulate in english\n\nJob Offer\n\ngreat work culture\ninternational firm\ntop tier investment bank\n\nTo apply online please click the 'Apply' button below. For a confidential discussion about this role please contact Monica Wong on +852 2848 9520.", "employment_types": ["Full Time", "Permanent"], "selling_points": ["US based investment bank !", "top tier firm !", "broad exposure !"], "locations": ["Not Specified"], "categories": ["Accounting", "Audit", "Banking / Finance", "Financial Services", "Professional Services", "Legal & Compliance"], "post_time": "2022-01-18T03:05:28Z", "salary": {"currency": "HKD", "max": 69999, "min": 55000, "period": "monthly", "term": null}, "salary_visible": true, "title_keywords": [], "responsibilities": ["reporting", "consulting", "compliance", "contact", "report"], "requirements": {"degrees": [], "majors": [], "languages": ["english"], "language_level": [], "hard_skills": [], "soft_skills": ["articulate", "work independently", "responsible"], "languages_combined": [{"language": "english", "language_level": []}]}, "experience_required": {"duration": [], "field": ["compliance", "big 4", "investment bank", "consulting"]}}, {"job_id": "100003009052591", "location_code": "hk", "company": "King and Company, Solicitors & Notaries", "job_title": "Company Secretary", "description": "Requirements:\n\nMinimum 5 years' solid experience in company secretarial field, experience in professional firms preferred\nAble to work independently\nStudent or above of HKCGI/CGI\nFamiliar with CSA software\nGood command of written and spoken English & Chinese (including Putonghua)\nImmediate available is preferred\n\nInterested candidates please send your full resume with current & expected salary to 8/F Asia Standard Tower, 59-65 Queen\u2019s Road Central, Hong Kong or by email through \"Apply Now\".\u00a0 Personal data collected will be used for recruitment purpose only.", "employment_types": ["Full Time"], "selling_points": [], "locations": ["Central"], "categories": ["Professional Services", "Company Secretary", "Legal & Compliance"], "post_time": "2022-01-17T03:29:44Z", "salary": {"currency": null, "max": null, "min": null, "period": "monthly", "term": null}, "salary_visible": false, "title_keywords": ["company secretary"], "responsibilities": ["software"], "requirements": {"degrees": [], "majors": [], "languages": ["putonghua", "english", "chinese"], "language_level": ["good command"], "hard_skills": [], "soft_skills": ["work independently"], "languages_combined": [{"language": "putonghua", "language_level": ["good command"]}, {"language": "english", "language_level": ["good command"]}, {"language": "chinese", "language_level": ["good command"]}]}, "experience_required": {"duration": ["minimum 5 years"], "field": ["secretarial"]}}, {"job_id": "100003009050485", "location_code": "hk", "company": "Chevalier Group - Corporate Office", "job_title": "Legal Counsel", "description": "Our\u00a0Legal Department is now inviting high calibre persons to apply for this position :\n\nResponsibilities\n\nProvide legal advice on corporate and commercial matters\nHandle and monitor contentious and non-contentious matters\nDraft and review legal documents\nHandle ad hoc tasks as assigned\n\nRequirements\n\nDegree or above in Law\nQualified solicitor with at least 3 years PQE in real estate, construction or corporate and commercial matters\nRelevant in-house experience is preferred\nGood interpersonal skills, detail-minded and able to work independently\u00a0\nExcellent command of both written and spoken English and Chinese\n\nAttractive remuneration package will be offered to the right candidate. Interested parties, please send your resume with current and expected salary by clicking \"Apply Now\" or mail to:\n\nThe Human Resources Manager, Chevalier Group, 22F, Chevalier\u00a0Commercial Centre,\u00a08\u00a0Wang Hoi\u00a0Road, Kowloon Bay, Hong Kong\n\nWe are an equal opportunity employer and welcome applications from all qualified candidates. Personal data collected would be used for recruitment purpose only.", "employment_types": ["Full Time", "Permanent"], "selling_points": ["Qualified solicitor", "In-house experience is preferred", "3+PQE(Real Estate/Construction/Commercial matters)"], "locations": ["Kowloon Bay"], "categories": ["Professional Services", "Legal & Compliance"], "post_time": "2022-01-14T10:30:13Z", "salary": {"currency": null, "max": null, "min": null, "period": null, "term": null}, "salary_visible": false, "title_keywords": ["legal counsel"], "responsibilities": ["review", "monitor", "ad hoc tasks"], "requirements": {"degrees": ["degree or above"], "majors": ["law"], "languages": ["english", "chinese"], "language_level": ["excellent"], "hard_skills": [], "soft_skills": ["detail-minded", "work independently", "interpersonal skills"], "languages_combined": [{"language": "english", "language_level": ["excellent"]}, {"language": "chinese", "language_level": ["excellent"]}]}, "experience_required": {"duration": [], "field": []}}, {"job_id": "100003009049390", "location_code": "hk", "company": "Success Universe Group", "job_title": "Legal Counsel", "description": "Responsibilities :\n\nReporting to the Group Chairman, the successful applicant will lead the legal and company secretarial team\u00a0and\u00a0responsible for :\n\n\nProviding legal and regulatory advices to the management;\nManage and answering enquiries from SFC and other regulatory bodies on all compliance related matters;\nAdvising on the latest legal and regulatory developments that may be relevant to the Group;\nLiaise with\u00a0external lawyers to manage litigation or dispute resolution issues;\nPreparing and reviewing legal and other documents and participating in contract negotiations;\nSupporting the Board and management on corporate governance matters; and\nPerforming other duties as may be required by the Group.\n\nRequirements :\u00a0 \u00a0 \u00a0 \u00a0 \u00a0 \u00a0 \u00a0 \u00a0 \u00a0 \u00a0 \u00a0 \u00a0 \u00a0 \u00a0 \u00a0 \u00a0 \u00a0 \u00a0 \u00a0 \u00a0 \u00a0 \u00a0 \u00a0 \u00a0 \u00a0\u00a0\n\nA qualified lawyer with at least 10 years of PQE gained preferably from law firms or Listed Company;\nExperience in legal drafting and contract negotiation;\nAbility to work independently with strong attention to details and commercial sense;\nGood command of written and spoken English and Chinese languages; and\nExcellent interpersonal, communication and presentation skills.\n\nWe offer 5 days week to the right candidate and you are welcome to visit our website at\u00a0http://www.successuniversegroup.com.\n\nInterested parties please send your resume with\u00a0current\u00a0and\u00a0expected salary\u00a0by clicking below \"APPLY NOW\".\n\n\n(Personal data collected will be treated in the strictly confidence and only be used for recruitment related purpose.)", "employment_types": ["Full Time", "Permanent"], "selling_points": [], "locations": ["Admiralty"], "categories": ["Professional Services", "Legal & Compliance"], "post_time": "2022-01-14T08:32:46Z", "salary": {"currency": null, "max": null, "min": null, "period": "monthly", "term": null}, "salary_visible": false, "title_keywords": ["legal counsel"], "responsibilities": ["reporting", "management", "other duties", "compliance", "resolution", "communication", "liaise with"], "requirements": {"degrees": [], "majors": [], "languages": ["english", "chinese"], "language_level": ["good command"], "hard_skills": [], "soft_skills": ["work independently", "negotiation", "responsible", "communication", "presentation skills", "attention to details", "interpersonal"], "languages_combined": [{"language": "english", "language_level": ["good command"]}, {"language": "chinese", "language_level": ["good command"]}]}, "experience_required": {"duration": [], "field": ["legal"]}}, {"job_id": "100003009052289", "location_code": "hk", "company": "Standard Chartered Bank (Hong Kong) Ltd", "job_title": "Associate, FCC, Investigations - (2100035561)", "description": "About Standard Chartered\u00a0\nWe are a leading international bank focused on helping people and companies prosper across Asia, Africa and the Middle East.\u00a0\n\nTo us, good performance is about much more than turning a profit.\u00a0 It's about showing how you embody our valued behaviours - do the right thing, better together and never settle - as well as our brand promise, Here for good.\n\nWe're committed to promoting equality in the workplace and creating an inclusive and flexible culture - one where everyone can realise their full potential and make a positive contribution to our organisation. This in turn helps us to provide better support to our broad client base.\nThe Role Responsibilities\nResponsible in analysing alerts generated by transaction monitoring system as well as other non-automated cases with financial crime or money laundering concern.\nUndertake investigations to identify suspicious account activities and prepare and file Suspicious Activity Reports (\u201cSAR\u201d) to the law enforcement agencies (\u201cLEA\u201d) where necessary in a timely manner.\nEnsure that significant cases of suspected money laundering/terrorist financing are subject to appropriate investigations and disclosures where necessary.\nEnsure the suitability and quality of case data maintained on enterprise case management systems.\nCoordinate with the relevant operations units to ensure that the relevant lists and database used in the transaction monitoring / screening systems and investigation are up to date and relevant.\nPropose control improvements, enhancements and simplifications where appropriate.\nProvide advice on AML matters when required and maintain sound working relationship with stakeholders and peers.\nEnsure timely reporting and escalation of significant AML/CTF issues to management.\nMake recommendations (and/or implement) to relevant stakeholders on possible risk management responses to identified risks and/or findings of concerns from investigations.\nAnalyse significant financial crime risk events (e.g. SAR\u2019s, non-compliant transactions, production orders) to ensure that all connected parties, particularly cross-border are identified and reported at the appropriate levels internally as well as externally across all relevant jurisdictions.\nUnderstand technical aspects of systems relevant to CDD, Client Risk Assessments, Name and Transaction Screening, AML Monitoring and Case Management.\nApply risk and data analytic tools/techniques to optimise and tune relevant detection scenarios, and screening and monitoring systems.\nEnsure that detection scenarios that are developed and deployed are fit-for-purpose.\nCollate, analyse, interpret data and prepare MI reports on FCC related metrics to senior management and relevant governance / risk committees.\nSupport all control checks undertaken by FCC, and to ensure quality assurance is in place on transaction screening / monitoring and customer name screening.\n\nStrategy\n\nEnsure that there is adequate support (people, processes, tools, frameworks, systems) in the Country/Department for necessary FCC controls.\nSupport and implement the vision, strategy, direction and leadership for the Country/Department, consistent with the vision and strategy for Conduct, Financial Crime & Compliance (\u201cCFCC\u201d) and in support of the Bank\u2019s and the Group\u2019s strategic direction and growth aspirations.\nPromote the culture and practice of compliance with compliance standards (including conducting business within regulatory requirements, and to high ethical standards) within the Bank and embed a Here for good culture and the Group Code of Conduct.\nThrough the development of an overall strategy across CIB & CB for delivering appropriate regulatory guidance, and the establishment of an integrated programme to identify, manage, monitor, and report Compliance risk.\n\nBusiness\n\nAssist the CFCC Project Manager in a project for the integration of a new business into SCB HK (\u201cthe Project\u201d).\nAt the Project stage:\nTo assist in integration of the AML system including name screening, transaction screening, transaction monitoring, etc. into SCB HK.\nTo assist in the development of the relevant policies and procedures for the Project after integration, DOI / process for the transaction monitoring, CDD procedure and other surveillance work for the FCC team.\u00a0\nTo support the CFCC Project Manager in working with various stakeholders to ensure a smooth transition of FCC framework including control and monitoring to SCB HK.\u00a0\nAfter Implementation:\nTo focus on name screening and transaction monitoring for the transactions related to the new business.\n\nProcesses\n\nDevelop, keep up to date and recommend for approval by the relevant Risk Committee, appropriate policies/processes/DOIs to address financial crime risks, aligning with relevant regulatory requirements.\nProvide governance and oversight over the implementation of FCC-related policies and procedures, and policies and procedures of CIB and CB in Country/Business to ensure compliance with such policies and procedures.\nProvide advice to relevant stakeholders on compliance with Group standards relating to AML/Sanctions/ABC, and other compliance policies, procedures and standards in CIB and CB businesses.\n\nPeople and Talent\n\nLead through example and build the appropriate culture and values. Set appropriate tone and expectations from their team and work in collaboration with risk and control partners.\nEnsure the provision of ongoing training and development of people, and ensure that holders of all critical functions are competent, suitably skilled and qualified for their roles ensuring that they have effective supervision in place to mitigate any risks.\nEmploy, engage and retain high quality people, with succession planning for critical roles.\nResponsibility to review team structure/capacity plans.\nSet and monitor job descriptions and objectives for direct reports and provide feedback and rewards in line with their performance against those responsibilities and objectives.\nRegularly and on a timely basis appraise performance as well as proactively manage attrition when needed.\nEnsure regular and documented management meetings with direct reports.\nAssess competency and skill of the team on an ongoing basis to ensure alignment of skill set to the risk management demands of the business.\nEnsure teams are adequately resourced and capacitised.\n\nRisk Management\n\nAct as Risk Owner under the Group\u2019s Risk Management Framework for CIB & CB processes where Compliance is the second line Risk Owner.\nIn collaboration with the Country Compliance Assurance team ensure that local risks associated with the business in the Country are reflected in country risk assessments, with compliance reviews established where necessary and ensure Compliance involvement in the resolving and identified regulatory or compliance issues relevant to the businesses. Escalate to Regional Compliance where required.\nEnsure effective management of compliance matters, and in collaboration with the rest of the Compliance team, effectively manage regulatory issues that have a significant impact on the Bank.\nCollaborate with the other Products Compliance teams and the Compliance Management Group to anticipate horizon risks that may have a significant impact on the Bank and develop effective strategies to mitigate such horizon risks including global standards for conduct of business.\nIn the event of serious regulatory breaches, or where risk tolerances have been breached, ensure senior management in the Bank and relevant regulators are informed and that actions are taken quickly to remediate and/or activities are ceased. Ensure proactive and timely identification, assessment, advice and dissemination of evolving regulatory changes/practices and associated risks, and proactive engagement in regulatory reform.\nProvide reports to relevant Country and Business risk and control committees and management group on key compliance risks and issues.\nMaintain adequate management MI / trackers across all aspects of their coverage and responsibility to ensure all issues and matters are tracked, followed, regularly assessed and reported on.\nEnsure global standards are understood and implemented in locally, with any identified exceptions, or need for more/less stringent standards escalated to Regional Compliance for joint decision-making. Provide Country thought leadership and execution on local and global regulatory reform.\n\nGovernance\n\nWithin the Group's overall Risk Management Framework, establish and maintain appropriate risk based compliance frameworks for identifying, assessing, managing, monitoring, mitigating and reporting compliance risks across CIB & CB businesses.\nDevelop and recommend (for approval by the relevant Risk Committee), appropriate compliance policies and procedures.\nEnsure appropriate product governance measures are in place so that product approval documents reflect all relevant regulatory requirements.\nManage Country governance and coordination activities such as participating in Country governance committees and aggregating logistics and support for the function.\n\nRegulatory & Business Conduct\n\nDisplay exemplary conduct and live by the Group\u2019s Values and Code of Conduct.\nTake personal responsibility for embedding the highest standards of ethics, including regulatory and business conduct, across Standard Chartered Bank. This includes understanding and ensuring compliance with, in letter and spirit, all applicable laws, regulations, guidelines and the Group Code of Conduct.\nAssist CIB & CB Compliance Team to achieve the outcomes set out in the Bank\u2019s Conduct Principles: Fair Outcomes for Clients; Financial Crime Compliance;\u00a0Creating the Right Environment.\nEffectively and collaboratively identify, escalate, mitigate and resolve risk, conduct and compliance matters.\n\nKey Stakeholders\n\nMandatory Provident Fund Schemes Authority (\u201cMPFA\u201d)\nSecurities and Futures Commission (\u201cSFC\u201d)\nHong Kong Monetary Authority (\u201cHKMA\u201d)\nBusiness Management\u00a0\u00a0\u00a0\u00a0\u00a0\u00a0\u00a0\u00a0\u00a0\u00a0\u00a0\u00a0\nRisk\u00a0\nInternal Audit\n\nOther Responsibilities\n\nEmbed Here for good and Group\u2019s brand and values in CIB & CB Compliance Team.\nPerform other responsibilities assigned under Group, Country, Business or Functional policies and procedures.\n\nOur Ideal Candidate\n\nA recognised university degree or professional qualification in Law / Finance / Accounting / Business or related disciplines\nHave a good knowledge of Financial Crime Risk, as well as knowledge of the local regulations and legislation on AML/CTF and sanctions\nA sound understanding of suitability considerations, and demonstrate them when reviewing alerts or investigating incidents\nGood analytical, reporting writing and methodical skills\nExcellent team player with strong written and oral communications\nExercise judgment when to escalate or how to investigate a case, as well as the severity of any exception\nApply now to join the Bank for those with big career ambitions.\n", "employment_types": ["Full Time"], "selling_points": ["Embed Here for good and Group\u2019s brand", "Perform other responsibilities assigned", "A recognised university degree"], "locations": ["Not Specified"], "categories": ["Professional Services", "Legal & Compliance"], "post_time": "2022-01-17T02:39:21Z", "salary": {"currency": null, "max": null, "min": null, "period": "monthly", "term": null}, "salary_visible": false, "title_keywords": ["associate"], "responsibilities": ["collaborate with", "regulations", "internal audit", "data", "operations", "regulatory requirements", "quality", "transactions", "maintain", "planning", "database", "plans", "senior management", "make recommendations", "control", "cdd", "compliance", "monitor", "implementation", "teams", "develop", "provide reports", "client base", "reports", "logistics", "report", "reporting", "management", "guidance", "monitoring", "coordinate with", "procedures", "investigation", "review", "aml", "guidelines", "policies", "systems", "a timely manner", "ensure compliance", "provide advice", "coordination", "analyse"], "requirements": {"degrees": ["university degree"], "majors": ["law", "finance", "related disciplines", "business", "accounting"], "languages": [], "language_level": [], "hard_skills": ["business management", "aml", "hkma", "cdd", "abc", "make", "integration", "code", "focus"], "soft_skills": ["oral", "focused", "team player", "focus", "leadership", "make recommendations", "committed", "ethical", "smooth", "ideal", "competent", "positive", "flexible", "responsible", "timely", "organisation", "coordination", "methodical", "proactive"], "languages_combined": []}, "experience_required": {"duration": [], "field": []}}, {"job_id": "100003009046972", "location_code": "hk", "company": "Centaline Property Agency Ltd", "job_title": "Legal Assistant", "description": "Responsibilities:\n\nResponsible of answering phone calls and handling inquiries\n\nAssist in preparing legal document and perform clerical work\n\nRequirements:\n\nHigher Diploma or above in any disciplines\nRelevant experience in customer services field is preferable\nGood presentation skill and interpersonal skill\nGood command of written and spoken in English and Chinese\u00a0\nInitiative, independent and\u00a0willing to learn\n\nWe provide its staff members with professional training, attractive remuneration package and excellent career prospects. For application, please send full resume with present and expected salary to\u00a0Human Resources Department,\u00a010/F., Wharf T & T Centre, Harbour City, No. 7 Canton Road, Tsimshatsui, Kowloon\u00a0or by email.\n\nFor more information about us, please visit our website at:\u00a0www.centanet.com\n\nData collected will be used for recruitment purpose only.", "employment_types": ["Full Time", "Permanent"], "selling_points": ["Higher Diploma or above in any disciplines", "Relevant experience in customer services field", "Good presentation skill and interpersonal skill"], "locations": ["Tsim Sha Tsui"], "categories": ["Professional Services", "Legal & Compliance"], "post_time": "2022-01-14T01:54:59Z", "salary": {"currency": null, "max": null, "min": null, "period": "monthly", "term": null}, "salary_visible": false, "title_keywords": ["legal assistant"], "responsibilities": ["phone calls"], "requirements": {"degrees": ["higher diploma or above"], "majors": ["any disciplines"], "languages": ["english", "chinese"], "language_level": ["good command"], "hard_skills": ["presentation skill"], "soft_skills": ["presentation skill", "independent", "willing to learn", "interpersonal skill", "initiative"], "languages_combined": [{"language": "english", "language_level": ["good command"]}, {"language": "chinese", "language_level": ["good command"]}]}, "experience_required": {"duration": [], "field": ["relevant experience", "customer services"]}}, {"job_id": "100003009052724", "location_code": "hk", "company": "E.SUN Commercial Bank, Ltd.", "job_title": "Compliance Specialist / Senior Compliance Specialist", "description": "Main Responsibilities :\n\nDraw up and execute compliance testing & review program and report to the bank\u2019s Chief Compliance Officer (\u201cCCO\u201d).\nKeep abreast of regulatory changes, conduct gap analysis, assess their potential impact to the bank and assist the compliance of business units by reviewing their revised internal procedures in accordance with the changes.\nCommunicate with authority\u2019s case manager (if applicable) under the supervision of the bank\u2019s CCO, including but not limited to HKMA, SFC, IA, DPB, CR, IRD, and FSC of Taiwan, to clarify authority\u2019s enquiry and submit the bank\u2019s response in a timely manner.\nFormulate and review compliance-related policies and procedures to address relevant regulatory changes and align with banking group standard.\nReview legal documents and forms on loans and account transactions to form analysis and discuss with external consultant or lawyer.\nDisseminate compliance related information and publication to all relevant staff or business units.\n\nRequirements :\n\nCapable of executing compliance tasks independently, including but not limited to performing compliance testing & review, generating compliance report and communicating the compliance requirements to business units effectively;\nBachelor's degree, preferably majoring in law;\nMinimum two years of working experience in financial industry of Hong Kong, preferably in compliance or AML function for over one year;\nSound knowledge in banking laws and regulations, operations and internal controls of main banking products and services.\nFluent in Mandarin speaking and Chinese reading and writing.\n\nWe offer attractive remuneration package including five-day work week, double pay, medical insurance coverage, performance bonus, OT allowance, public holiday, excellent career development opportunities and others benefit package to the right candidate. Interested parties please forward your resume (in both Chinese and English versions are preferred) with current and expected salary to Human Resources Department by \"APPLY NOW\".\n\nPlease visit our website at https://www.esunbank.com.tw/bank/corporate/overseas-branch/overseas-branch/hong-kong for more information.\n\nAll information received will be kept in strictly confidential and only for employment related purposes.", "employment_types": ["Full Time", "Permanent"], "selling_points": ["General Compliance Team", "Self-motivated, responsible and teamwork", "Young & Energetic Working Culture"], "locations": ["Tsim Sha Tsui"], "categories": ["Banking / Finance", "Corporate Banking", "Others", "Professional Services", "Legal & Compliance"], "post_time": "2022-01-17T03:49:07Z", "salary": {"currency": null, "max": null, "min": null, "period": "monthly", "term": null}, "salary_visible": false, "title_keywords": ["specialist"], "responsibilities": ["communicate with", "policies", "analysis", "review", "compliance", "procedures", "a timely manner", "testing", "transactions", "banking", "publication", "report"], "requirements": {"degrees": ["degree", "bachelor"], "majors": ["law"], "languages": ["chinese", "mandarin"], "language_level": ["fluent"], "hard_skills": ["aml", "banking laws"], "soft_skills": ["independently", "capable"], "languages_combined": [{"language": "chinese", "language_level": ["fluent"]}, {"language": "mandarin", "language_level": ["fluent"]}]}, "experience_required": {"duration": ["one year", "minimum two years"], "field": ["compliance", "financial industry"]}}, {"job_id": "100003009048833", "location_code": "hk", "company": "Mike So, Joseph Lau & Co.", "job_title": "Conveyancing Clerk", "description": "- Proficiency in MS Word & Excel\n\n- Good command of English and Chinese\n\n- At least\u00a03 year relevant working experience", "employment_types": ["Full Time"], "selling_points": ["Legal Services", "Sheung Wan", "Full Time"], "locations": ["Sheung Wan"], "categories": ["Professional Services", "Legal & Compliance"], "post_time": "2022-01-14T07:23:03Z", "salary": {"currency": null, "max": null, "min": null, "period": "monthly", "term": null}, "salary_visible": false, "title_keywords": ["clerk"], "responsibilities": [], "requirements": {"degrees": [], "majors": [], "languages": ["english", "chinese"], "language_level": ["good command"], "hard_skills": ["excel", "ms word"], "soft_skills": [], "languages_combined": [{"language": "english", "language_level": ["good command"]}, {"language": "chinese", "language_level": ["good command"]}]}, "experience_required": {"duration": ["at least 3 year"], "field": ["relevant working experience"]}}, {"job_id": "100003009041579", "location_code": "hk", "company": "ZM Lawyers", "job_title": "Paralegal", "description": "We are currently looking for a Paralegal to work under Corporate Team, supporting IPO cases and corporate finance work. The role will be supporting the team. Candidates with excellent English language skill and strong legal documentation experience are preferred.\n\nCompany Details\n\nAs a fast growing law firm, we provide high-quality legal services to clients worldwide. Our firm has a very friendly culture and places an emphasis on teamwork and communication.\n\nDescription\n\nBeing a paralegal under our corporate finance team, you will gain all-rounded exposures to various corporate projects and experience in supporting lawyers. Major tasks would include:\n\nAssist in drafting and legal researches\nConduct due diligence work\nPrepare, edit, format, and proof-read correspondences and documents\nAssist in litigation team\nAny other ad hoc assignments as assigned\n\nProfile\n\nCandidates with 1 year of legal firm experience or with accounting/translation background preferred\nChinese typing skills is required\nGood knowledge in Microsoft Office with strong document formatting skills\nGood learning and can-do attitude, good team player\nWill consider fresh grad; even with no corporate experience if personality fits\n\nJob Offer\n\nStable and flexible working hours, 9:30am \u2013 6:30pm (Mon to Fri)\nMedical insurance\nOffice located in Central\n\nInterested candidates please send with full resume by clicking \u201cApply Now\u201d and submit your application together with the following information.\n\nCurrent and expected salary\nDate of availability", "employment_types": ["Full Time"], "selling_points": [], "locations": ["Central"], "categories": ["Professional Services", "Legal & Compliance"], "post_time": "2022-01-14T02:25:49Z", "salary": {"currency": null, "max": null, "min": null, "period": "monthly", "term": null}, "salary_visible": false, "title_keywords": ["paralegal"], "responsibilities": ["documentation"], "requirements": {"degrees": [], "majors": [], "languages": ["english"], "language_level": ["excellent"], "hard_skills": ["documentation"], "soft_skills": [], "languages_combined": [{"language": "english", "language_level": ["excellent"]}]}, "experience_required": {"duration": [], "field": ["legal"]}}, {"job_id": "100003009052662", "location_code": "hk", "company": "Hong Kong Loving Family Limited", "job_title": "Senior Consultant (\u9ad8\u7d1a\u9867\u554f) (Financial/ Insurance/ Immigration/ Medical)", "description": "\u8077\u8cac:\n\n\u719f\u6089\u6216\u7565\u61c2\u9999\u6e2f\u79fb\u6c11\u653f\u7b56\u53ca\u7c3d\u8b49\u7684\u7533\u8acb\u7a0b\u5e8f\n\u8207\u5408\u4f5c\u65b9\u6e9d\u901a\u4e26\u5c31\u670d\u52d9\u7522\u54c1\u9032\u884c\u54a8\u8a62\n\u8ddf\u9032\u5ba2\u6236\u7684\u54a8\u8a62\uff0c\u4e86\u89e3\u5ba2\u6236\u9700\u8981\u53ca\u63d0\u4f9b\u76f8\u61c9\u65b9\u6848\n\u8ca0\u8cac\u670d\u52d9\u7c3d\u7d04\u7684\u5ba2\u6236\uff0c\u5305\u62ec\u89e3\u7b54\u9805\u76ee\u554f\u984c\uff0c\u4ee5\u53ca\u6536\u96c6\u5ba2\u6236\u7684\u8cc7\u6599\u5be9\u6838\u7121\u8aa4\u5f8c\u9032\u884c\u905e\u4ea4\n\u8981\u6c42:\n\n\u5927\u5b78\u6216\u4ee5\u4e0a\u5b78\u6b77\n\u64c1\u6709\u81f3\u5c11\u4e00\u5e74\u5728\u4fdd\u96aa\u3001\u6295\u8cc7\u3001\u79fb\u6c11\u3001\u623f\u5730\u7522\u3001\u91ab\u7642\uff0c\u6216\u662f\u6559\u80b2\u65b9\u9762\u7684\u7d93\u9a57\n\u6e9d\u901a\u80fd\u529b\u597d\uff0c\u4e26\u7cbe\u901a\u666e\u901a\u8a71\uff0c\u61c2\u807d\u5beb\u8aaa\u4e2d\u6587\u53ca\u82f1\u6587\n\u6210\u719f\u6b63\u9762\u7684\u5de5\u4f5c\u614b\u5ea6\u3001\u6709\u8010\u5fc3\u3001\u4e0a\u9032\u5fc3\uff0c\u80fd\u5920\u70ba\u5ba2\u6236\u7d30\u5fc3\u670d\u52d9\n\u61c2\u5f97\u4e00\u822c\u7684\u6587\u66f8\u5de5\u4f5c\n*\u6b61\u8fceIANG \u4eba\u58eb\u7533\u8acb\n\u5982\u6709\u8208\u8da3\uff0c\u53ef\u5230\u6211\u5011\u516c\u53f8\u7db2\u7ad9\u700f\u89bd\u8a73\u60c5\u4e86\u89e3\u66f4\u591a: https://hkfamily.com.hk/\uff0c\u4e26\u76f4\u63a5\u6309 \"Apply Now\" \u89aa\u81e8\u516c\u53f8\u9032\u884c\u9762\u8a66\u3002\n\n\n\nJob Description\nResponsibilities:\u00a0\n\nProvide consultation services to customer that correspond to their needs\nFamiliar with HK immigration policy and understand the procedure of HK immigration\nCommunicate with outside service providers\nHandle the daily enquiries and follow up with the potential customers\nDeliver highest level customer service and maintain good relationship with the customers in a professional manner\nPerform ad hoc projects as assigned by seniors\nRequirements:\n\nBachelor\u2019s degree in any disciplines or above\nAt least 1-year relevant experience in Insurance, Immigration, Medical, Overseas Education or Real Estate fields are preferred\u00a0\nStrong business sense with excellent communication and interpersonal skills\nMature with a positive attitude, patient, self-motivated, and strong desire to deliver exceptional results with great attention to accuracy and details\nProficient in Mandarin, Cantonese, and good common of English\nProficient in computer skills, e.g.: Microsoft Office, English and Chinese typing\nIANG holders are welcomed\nFor more details, please visit our official website: https://hkfamily.com.hk/ and click ''Apply Now'' to join us now!\n\n\nThe information provided by applicants will be\u00a0used solely for recruitment purpose only", "employment_types": ["Full Time"], "selling_points": [], "locations": ["Shatin Area"], "categories": ["Insurance", "Insurance Agent / Broker", "Professional Services", "Legal & Compliance", "Property / Real Estate", "Property Consultancy"], "post_time": "2022-01-17T03:39:58Z", "salary": {"currency": null, "max": null, "min": null, "period": "monthly", "term": null}, "salary_visible": false, "title_keywords": ["senior consultant"], "responsibilities": ["communicate with", "professional manner", "maintain good relationship", "customer service", "ad hoc projects"], "requirements": {"degrees": ["degree", "bachelor"], "majors": ["any disciplines"], "languages": ["cantonese", "english", "chinese", "mandarin"], "language_level": ["good", "proficient"], "hard_skills": ["computer skills", "typing", "microsoft office"], "soft_skills": ["self-motivated", "business sense", "mature", "positive attitude", "communication and interpersonal skills", "patient"], "languages_combined": [{"language": "cantonese", "language_level": ["good", "proficient"]}, {"language": "english", "language_level": ["good", "proficient"]}, {"language": "chinese", "language_level": []}, {"language": "mandarin", "language_level": ["good", "proficient"]}]}, "experience_required": {"duration": ["at least 1-year"], "field": ["insurance", "relevant experience", "education", "medical"]}}, {"job_id": "100003009051928", "location_code": "hk", "company": "Octopus Holdings Limited", "job_title": "AML Compliance Specialist (1-year contract) REF: OCL/RMC/2021-210", "description": "Job Responsibilities\n\n\nPerform a checker role on customer due diligence and ongoing monitoring for Octopus wallet and merchant customers (tasks including on boarding, name screening,trigger event review, etc.)\nProvide supervision and guidance to junior staff so as to improve the quality of deliverables\nConduct regular high-risk review to existing customers (both individuals and merchants)and trigger event reviews (where necessary)\nGather relevant information and prepare regular reports for management review and for regulatory reporting\nContribute to the review, standardization and rollout of policies, procedures, processes and systems if necessary\nPerform ad-hoc tasks as assigned by the management and assist other team members where necessary\nRequirements\n\n\nDegree holder preferably in Risk Management, Engineering or Computer Science discipline\nAt least 3years of relevant experience in financial services industry with sound experience in AML Compliance\nKnowledgeable in Payment Systems and Stored Value Facilities Ordinance/Banking Ordinance and HKMA\u2019s AML Guideline is a plus\nProficient in MS PowerPoint,Word and Excel (hands-on experience in MS Excel functions e.g. Pivot tables, VLOOKUP etc. is an advantage)\nAttentive to details and multi-tasking\nQuick learner and proactive with can-do attitude\nAble to provide quality work under tight schedule and minimal supervision\nGood communication, interpersonal and problem-solving skills\nGood command of written and spoken English and Chinese\n\nWe offer successful candidate an attractive remuneration package and excellent career prospects. Interested parties please send your resume, present and expected salary, contact details and quoting the reference number by clicking \"Apply Now\"Visit our web site:\u00a0http://www.octopus.com.hk/\n\nThe personal data collected will be used for recruitment purposes only. If you are not contacted by us within six weeks, you may consider your application unsuccessful. Personal data with an unsuccessful applicant will be destroyed 12 months after rejection of the application. During this retention period, you have the right to request for correction or destruction of your personal data at any time. Any request for the correction or destruction of personal data should be addressed in writing to our Human Resources & Administration Department.\n\nOctopus is an equal opportunity employer and all employment decisions and Human Resources policies are administered; especially those relating to recruitment & selection, compensation & benefits, promotion & transfer, training & development and termination & redundancy; without discrimination on the basis of age, race, colour, religion, sex, national origin, marital status, pregnancy, physical and mental disability and family status but on genuine occupational qualification, job performance, employees\u2019 ability and internal/ external relativities.", "employment_types": ["Contract"], "selling_points": ["Provide supervision and guidance to junior staff", "Degree holder preferably in Risk Management", "At least 3 years of relevant experience"], "locations": ["Kowloon Bay"], "categories": ["Banking / Finance", "Financial Services", "Professional Services", "Legal & Compliance", "Risk Management"], "post_time": "2022-01-17T01:32:42Z", "salary": {"currency": null, "max": null, "min": null, "period": "monthly", "term": null}, "salary_visible": false, "title_keywords": ["specialist", "aml compliance"], "responsibilities": ["guidance", "reporting", "management", "policies", "ad-hoc tasks", "review", "monitoring", "quality", "provide supervision", "procedures", "systems", "customer due diligence", "regular reports for management"], "requirements": {"degrees": ["degree holder"], "majors": ["risk management", "engineering", "computer science"], "languages": ["english", "chinese"], "language_level": ["good command"], "hard_skills": ["excel", "plus", "aml", "hkma", "vlookup", "word", "ms excel", "problem-solving skills", "ms powerpoint"], "soft_skills": ["attentive to details", "can-do attitude", "quick learner", "communication", "multi-tasking", "hands-on", "problem-solving skills", "proactive", "interpersonal"], "languages_combined": [{"language": "english", "language_level": ["good command"]}, {"language": "chinese", "language_level": ["good command"]}]}, "experience_required": {"duration": [], "field": ["financial services industry", "compliance", "relevant experience"]}}, {"job_id": "100003009050292", "location_code": "hk", "company": "Kaisa Holdings Limited", "job_title": "Compliance Officer (SFC Type 1,4,9 licensing)", "description": "About Standard Chartered\u00a0\nWe are a leading international bank focused on helping people and companies prosper across Asia, Africa and the Middle East.\u00a0\n\nTo us, good performance is about much more than turning a profit.\u00a0 It's about showing how you embody our valued behaviours - do the right thing, better together and never settle - as well as our brand promise, Here for good.\n\nWe're committed to promoting equality in the workplace and creating an inclusive and flexible culture - one where everyone can realise their full potential and make a positive contribution to our organisation. This in turn helps us to provide better support to our broad client base.\nAbout Mox\nAs one of the biggest banks in market, we are rapidly expanding by growing a new virtual banking business in Hong Kong. We see ourselves as a fast growing start-up company where you will enjoy autonomy and teamwork at the same time, solving new and exciting problems in a nimble and agile way. Join us and be part of history making for future banking experience!\nThe Role Responsibilities\nCoordinate the new product approval process of all investment products and services and ensure compliance to the corresponding product program\nLead the establishment of operating procedures for all investment product and services under management\nLead the formulation of product due diligence, product risk rating, customer risk profiling and suitability assessment framework and related procedures\nLead the conduct of investment product due diligence and ongoing monitoring\nEstablish regulatory reporting procedures and ensure timely submission\nAssist in formulating and provide secretarial support to related wealth/investment Committee\nMonitor local and overseas regulations closely and ensure that operational processes have the appropriate controls in place to satisfy compliance and external regulatory/internal policy requirements.\nDevelop post trade monitoring control framework\nSupport the team in the development and management of investment product platforms\nAct as Subject Matter Experts to support Product Owner in the development of new investment products/services\u200b\u200b\u200b\u200b\u200b\u200b\u200b\nOur Ideal Candidate\nRelevant experience in a similar capacity\nAdept at managing and working with various stakeholders\nStrong understanding of investment products and the regulatory requirements\nHands on experience in investment product diligence work\nOpen to challenge status quo and keen to uplift the banking experience for customers\nStrong presentation and interpersonal skills, with a positive mindset\nGood written and oral communication skills in English and Chinese\nProficiency in PC applications such as Microsoft\nQualify as an SFC Responsible Officer (RO) and a HKMA Executive Officer (EO) to supervise\u00a0 Types 1 and 4 regulated activities within the bank and manage risks associated with the business\nApply now to join the Bank for those with big career ambitions.\n", "employment_types": ["Full Time", "Permanent"], "selling_points": ["AML and KYC account opening procedures", "Degree", "At least 2-3 years of relevant work experience"], "locations": ["Central"], "categories": ["Professional Services", "Legal & Compliance"], "post_time": "2022-01-14T10:04:49Z", "salary": {"currency": null, "max": null, "min": null, "period": "monthly", "term": null}, "salary_visible": false, "title_keywords": ["compliance officer"], "responsibilities": ["regulations", "reporting", "management", "control", "product due diligence", "regulatory requirements", "monitoring", "procedures", "monitor", "compliance", "ensure compliance", "coordinate", "develop", "communication", "client base", "secretarial support", "banking", "support the team"], "requirements": {"degrees": [], "majors": [], "languages": ["english", "chinese"], "language_level": ["good"], "hard_skills": ["agile", "hkma", "investment products", "pc applications", "make"], "soft_skills": ["flexible", "communication skills", "oral", "agile", "focused", "positive mindset", "responsible", "keen", "timely", "teamwork", "committed", "hands on", "interpersonal skills", "organisation", "adept", "presentation", "positive", "ideal"], "languages_combined": [{"language": "english", "language_level": ["good"]}, {"language": "chinese", "language_level": ["good"]}]}, "experience_required": {"duration": [], "field": ["relevant experience", "investment", "banking experience"]}}, {"job_id": "100003009050211", "location_code": "hk", "company": "The Law Society of Hong Kong", "job_title": "Assistant, Registration (Ref: COM/REG/ASST)", "description": "The Law Society seeks applications from enthusiastic, detail-oriented and accountable person to fill the position of Temporary Assistant in the Compliance Department.\n\nJob Duties:\n\nTo compile indices of files in MS Excel format;\nTo peruse files and locate original documents;\nTo pack files into boxes for storage; and\nTo\u00a0perform other duties assigned by the Law Society.\n\nRequirements:\n\nForm 5 or above;\nOffice working experience is preferred;\nProficiency in MS Excel and Chinese Word Processing is a must;\nMature, responsible, organized and able to work independently;\u00a0and\nImmediate availability.\nOthers:\n\nOn-the-job training will be provided\nWorking hours: 9:00 a.m. to 5:45 p.m. from Mondays to Fridays\n\nInterested parties please send your full curriculum vitae stating the reference number, expected salary and your available working period to the Assistant Director of Administration and Human Resources, The Law Society of Hong Kong, 3/F, Wing On House, 71 Des Voeux Road Central, Hong Kong or click \"APPLY NOW\".\u00a0\u00a0Please mark \u201cPrivate and Confidential\u201d on the envelope.\n\n\n*Personal data provided by job applicants will be used strictly in accordance with the Law Society\u2019s personal data policies as set out in the Personal Information Collection Statement. \u00a0A copy of the Statement can be obtained from Assistant Director of Administration & Human Resources by calling 2846 0586. \u00a0Applicants not invited for interview within 6 weeks may consider their applications unsuccessful.*", "employment_types": ["Full Time", "Permanent"], "selling_points": [], "locations": ["Central"], "categories": ["Admin & HR", "Clerical / Admin Staff", "Professional Services", "Legal & Compliance", "Others", "Student / Fresh Graduate / No Experience"], "post_time": "2022-01-14T09:56:59Z", "salary": {"currency": null, "max": null, "min": null, "period": "monthly", "term": null}, "salary_visible": false, "title_keywords": ["assistant"], "responsibilities": ["perform other duties"], "requirements": {"degrees": ["form 5 or above"], "majors": [], "languages": ["chinese"], "language_level": ["proficiency"], "hard_skills": ["ms excel", "chinese word processing"], "soft_skills": ["organized", "work independently", "mature", "responsible"], "languages_combined": [{"language": "chinese", "language_level": ["proficiency"]}]}, "experience_required": {"duration": [], "field": []}}, {"job_id": "100003009045416", "location_code": "hk", "company": "Jun He Law Offices", "job_title": "Legal Secretary (New Headcount)", "description": "The Law Society seeks applications from enthusiastic, responsible person to fill the position of Assistant in the Registration Section of the Compliance Department.\n\nJob Duties:\n\nTo\u00a0provide clerical support to the Registration Officers and Assistant Director, Registration;\nTo assist the Registration Officers in processing applications for admission, renewal of membership and practising certificates, registration of training contracts, registration of foreign lawyers and foreign law firms, and to prepare relevant reports;\nTo answer enquiries from the public and members;\nTo process and issue membership cards for solicitors, trainee solicitors, registered foreign lawyers and student members; and\nTo arrange dispatch of documents, maintain the relevant outgoing records and oversee the filing system.\n\nRequirements:\n\nF. 6 or above with good command of both written and spoken English and Chinese, fluent in Putonghua preferred;\nMinimum 1 year of clerical experience, those gained in the legal field an advantage;\nGood command of MS Office and Chinese Word Processing, proficient in Excel application is a must;\nGood telephone manner;\nA good team player, organized, hardworking and efficient; and\nImmediately available is highly preferred.\n\nInterested parties please send your\u00a0full curriculum vitae stating the reference number, current and expected salary to the Assistant Director, Administration & Human Resources, The Law Society of Hong Kong, 3/F, Wing On House, 71 Des Voeux Road, Central, Hong Kong., or click \"APPLY NOW\".\u00a0 Please mark \"Private and Confidential\" on the envelope.\n\n*Personal data provided by job applicants will be used strictly in accordance with the Law Society\u2019s personal data policies as set out in the Personal Information Collection Statement.\u00a0 A copy of the Statement can be obtained from Assistant Director, Administration & Human Resources by calling 2846 0586. Applicants not invited for interview within 6 weeks may consider their applications unsuccessful.*", "employment_types": ["Full Time"], "selling_points": [], "locations": ["Central"], "categories": ["Professional Services", "Legal & Compliance"], "post_time": "2022-01-13T07:51:25Z", "salary": {"currency": null, "max": null, "min": null, "period": "monthly", "term": null}, "salary_visible": false, "title_keywords": ["legal secretary"], "responsibilities": ["provide clerical support", "contracts", "relevant reports", "maintain"], "requirements": {"degrees": [], "majors": [], "languages": ["putonghua", "english", "chinese"], "language_level": ["proficient", "good command", "fluent"], "hard_skills": ["excel", "chinese word processing", "ms office"], "soft_skills": ["efficient", "organized", "good team player", "telephone manner", "hardworking"], "languages_combined": [{"language": "putonghua", "language_level": ["fluent", "good command"]}, {"language": "english", "language_level": ["fluent", "good command"]}, {"language": "chinese", "language_level": ["fluent", "proficient", "good command", "good command"]}]}, "experience_required": {"duration": ["minimum 1 year"], "field": ["legal", "clerical"]}}, {"job_id": "100003009038432", "location_code": "hk", "company": "Ricacorp Properties Limited", "job_title": "Legal Officer", "description": "Responsibilities\u00a0\n\u00a0\u00a0\u00a0\u00a0\u00a0\u00a0\u00a0\u00a0 Provide secretarial and administrative support to fee earners\n\u00a0\u00a0\u00a0\u00a0\u00a0\u00a0\u00a0\u00a0 Draft & issue bills, day-to-day filing, handle claims & bookings etc.\n\u00a0\u00a0\u00a0\u00a0\u00a0\u00a0\u00a0\u00a0 Back up receptionist duty\u00a0\u00a0\n\u00a0\u00a0\u00a0\u00a0\u00a0\u00a0\u00a0\u00a0 Perform other duties as assigned\n\n\u00a0Job Requirements\u00a0\n\n\u00a0\u00a0\u00a0\u00a0\u00a0\u00a0\u00a0\u00a0 At least 2-years solid law firm experience\n\u00a0\u00a0\u00a0\u00a0\u00a0\u00a0\u00a0\u00a0 Excellent command of spoken & written English & Chinese (including Mandarin)\n\u00a0\u00a0\u00a0\u00a0\u00a0\u00a0\u00a0\u00a0 Well versed in MS Office applications. 3E literacy is definitely an advantageous\u00a0\n\u00a0\u00a0\u00a0\u00a0\u00a0\u00a0\u00a0\u00a0 Good interpersonal and communication skills\n\u00a0\u00a0\u00a0\u00a0\u00a0\u00a0\u00a0\u00a0 Energetic, flexible, hard-working, responsible and detail minded applicants are highly preferred\n\nWe offer competitive remuneration package, 5-day work week, medical insurance with dental cover. Simply click\u00a0APPLY NOW\u00a0to send your CV with\u00a0present and expected salaries\u00a0for application.\u00a0\n\nOffice Location: Suites 3701-10, 37/F, Jardine House, 1 Connaught Place, Central, Hong Kong\nWebsite:\u00a0www.junhe.com", "employment_types": ["Full Time"], "selling_points": ["Seasonal bonus", "5-Days work week", "Medical and Education allowance"], "locations": ["Wan Chai"], "categories": ["Professional Services", "Legal & Compliance"], "post_time": "2022-01-11T06:52:32Z", "salary": {"currency": null, "max": null, "min": null, "period": "monthly", "term": null}, "salary_visible": false, "title_keywords": ["officer"], "responsibilities": ["perform other duties", "administrative support"], "requirements": {"degrees": [], "majors": [], "languages": ["english", "chinese", "mandarin"], "language_level": ["excellent"], "hard_skills": ["ms office"], "soft_skills": ["flexible", "communication skills", "responsible", "hard-working", "energetic", "interpersonal"], "languages_combined": [{"language": "english", "language_level": ["excellent"]}, {"language": "chinese", "language_level": ["excellent"]}, {"language": "mandarin", "language_level": ["excellent"]}]}, "experience_required": {"duration": [], "field": []}}, {"job_id": "100003009049627", "location_code": "hk", "company": "Henry Wai & Co.,Solicitors LLP", "job_title": "HR and Administrative Executive", "description": "Responsibilities:\n\n\u25cf Provide legal support on drafting, reviewing and editing documents and contracts in relation to the business of the company;\n\u25cf To handle, assist and/or coordinate the handling of litigation or other legal proceedings;\n\u25cf Handle various legal related matters;\n\u25cf Assist in ad hoc projects and assignments.\n\nRequirements:\n\n\u25cf Degree or above;\n\u25cf 1-2 years\u2019 experience in litigation work or claims handling or relevant working experience will be an advantage;\n\u25cf With knowledge of MS Word, MS Excel and Chinese Word Processing;\n\u25cf Capability to work under pressure;\n\u25cf Candidate with less experience will be considered as Assistant Legal Officer.\n", "employment_types": ["Full Time", "Permanent"], "selling_points": ["Work experience in law firms is an advantage", "We offer attractive remuneration package", "Immediately available or short notice is preferred"], "locations": ["Admiralty"], "categories": ["Admin & HR", "HR Supporting Staff", "Professional Services", "Legal & Compliance"], "post_time": "2022-01-14T08:59:27Z", "salary": {"currency": null, "max": null, "min": null, "period": "monthly", "term": null}, "salary_visible": false, "title_keywords": ["hr", "administrative executive"], "responsibilities": ["coordinate", "contracts", "editing", "ad hoc projects"], "requirements": {"degrees": ["degree or above"], "majors": [], "languages": ["chinese"], "language_level": [], "hard_skills": ["ms excel", "chinese word processing", "ms word"], "soft_skills": ["work under pressure"], "languages_combined": [{"language": "chinese", "language_level": []}]}, "experience_required": {"duration": ["1-2 years"], "field": ["relevant working experience", "legal"]}}, {"job_id": "100003009053206", "location_code": "hk", "company": "Asia Progress Executive Limited", "job_title": "Associate, Financial Crime Compliance (Private Banking)  - Compliance Department", "description": "Responsibilities:-\n\nHolder of Bachelor degree in HR and/or Administration (or equivalent).\nNot less than 3 years' working experience in HR and Administration in Hong Kong.\nGood standard of English and Chinese and fluent in both Cantonese and Mandarin Chinese.\nGood computer skills and good working knowledge of computer operating systems.\nWe offer attractive remuneration package to the right candidates.\nImmediately available or short notice is preferred.\n\nPlease send applications together with full CV by clicking \u201cApply Now\u201d below to submit your application.\n\nAll personal data collected will be used for recruitment purpose only.\u00a0 Applicants not hearing from us within 3 months may consider their applications filed for future reference.\u00a0 All personal data collected will be kept in strict confidence and only for employment-related purposes.", "employment_types": ["Full Time"], "selling_points": ["Deg 5yr Financial crime compliance privatebanking", "AMLtransaction monitoring&manage AML tools&System", "AML/KYC review/CDD periodic review, CDD advisory"], "locations": ["Central & Western Area"], "categories": ["Banking / Finance", "Private Banking", "Professional Services", "Legal & Compliance", "Wealth Management"], "post_time": "2022-01-17T06:26:38Z", "salary": {"currency": null, "max": null, "min": null, "period": "monthly", "term": null}, "salary_visible": false, "title_keywords": ["associate", "private banking"], "responsibilities": ["hr", "operating systems", "administration"], "requirements": {"degrees": ["degree", "bachelor"], "majors": [], "languages": ["cantonese", "english", "chinese", "mandarin chinese"], "language_level": ["fluent", "good"], "hard_skills": ["computer skills"], "soft_skills": [], "languages_combined": [{"language": "cantonese", "language_level": ["good"]}, {"language": "english", "language_level": ["fluent", "good"]}, {"language": "chinese", "language_level": ["fluent", "good"]}, {"language": "mandarin chinese", "language_level": ["good"]}]}, "experience_required": {"duration": ["3 years"], "field": ["hr", "administration"]}}, {"job_id": "100003009050779", "location_code": "hk", "company": "Harneys (Asia) Limited", "job_title": "Paralegal - Dispute Resolution", "description": "Our client is a European Private Banking to cope with the rapid business\u00a0expansion, they are now inviting high caliber candidates to join the team\n\nAssociate ,Financial Crime Compliance ( Private Banking) - Compliance Department\u00a0\n\nResponsibilities:\n\nAssist the Head of Financial Crime to establish, review and update the AML related guidelines, policies and procedural manuals to ensure they are in line with Group and regulatory requirements;\nReview and investigate transactions triggered by monitoring systems or escalated by front office or other monitoring parties for potential financial crime risks; Report suspicious transactions and escalate for management oversight timely to ensure adequate follow up actions and ongoing monitoring;\nMonitor effective operation of AML tools and processes for transaction monitoring, client screening, payment screening and client risk assessment; Escalate issues for timely resolution and manage necessary remediation;\nConduct regular recalibration and tuning of parameters and drive enhancements for AML tools and systems;\nReview escalated alerts stopped on payment screening system and escalate transactions potentially related to money laundering and sanctions;\nReview alerts from ongoing client screening and manage the escalation of true hits for risk reclassification and monitoring follow up actions;\nTrigger follow up actions and KYC updates upon irregularities noted from transaction monitoring or client screening;\nAssist the Head of AML / Compliance in preparing internal AML training materials;\nPrepare materials for periodic AML governance meetings;\nPerform ad hoc tasks as assigned by Head of AML/Compliance from time to time;\nAssist in audits and inspections, and investigations where required\nInvolvement in special work projects as and when required\nAssist Head of Compliance, Hong Kong and the Compliance team in any other work matters;\nMust solid exp in transaction monitoring and manage AML tools and System\u00a0\n\nCompetencies:\n\nBasic bachelor degree; \u00a0\n5 \u2013 8 years of relevant experience in general compliance and financial crime compliance in private banking industry\u00a0\nMust solid exp in transaction monitoring and manage AML tools and System\u00a0\nA keen interest to learn and perform compliance matters;\nGood interactive, communication and writing skills;\nAble to provide alternative solutions to business;\nMotivated and innovative; able to handle issues and resolve challenges in collaboration with colleagues;\nTeam player\n\nPlease send full resume with\u00a0present & expected\u00a0salary to expedite sourcing\u00a0in\u00a0MS-WORD\u00a0format by clicking \u201cAPPLY NOW\u201d\nPlease quote our reference in your application\nPersonal data provided by job applicants will be used strictly in accordance with the employer\u2019s personal data policies, a copy of which will be provided upon request\nAll information provided will be used for recruitment purpose only", "employment_types": ["Full Time"], "selling_points": ["Dispute Resolution", "Offshore law firm experience", "Attractive package"], "locations": ["Central"], "categories": ["Professional Services", "Legal & Compliance"], "post_time": "2022-01-14T11:21:44Z", "salary": {"currency": null, "max": null, "min": null, "period": "monthly", "term": null}, "salary_visible": false, "title_keywords": ["paralegal"], "responsibilities": ["regulatory requirements", "transactions", "communication", "payment", "personal data", "compliance", "monitor", "resolution", "kyc", "banking", "report", "management", "review", "monitoring", "ad hoc tasks", "audits", "aml", "irregularities", "guidelines", "policies", "systems", "recruitment"], "requirements": {"degrees": ["degree", "bachelor"], "majors": [], "languages": [], "language_level": [], "hard_skills": ["ms-word", "basic", "aml", "writing skills", "rapid", "kyc"], "soft_skills": ["keen", "timely", "writing skills", "communication", "motivated", "team player", "innovative"], "languages_combined": []}, "experience_required": {"duration": ["8 years"], "field": ["banking industry", "compliance", "general compliance", "relevant experience", "financial"]}}, {"job_id": "100003009048733", "location_code": "hk", "company": "Madison Holdings Group Limited", "job_title": "Company Secretarial Assistant", "description": "ABOUT US\n\nHarneys is a global offshore law firm. We provide advice on British Virgin Islands, Cayman Islands, Cyprus and Anguilla law to an international client base which includes the world\u2019s top law firms, financial institutions and investment funds, as well as high net worth individuals. Our network is the largest among offshore law firms with 13 locations including market-facing offices in Hong Kong, London, Montevideo, S\u00e3o Paulo, Shanghai, Singapore and Vancouver.\n\nTHE ROLE\n\nWe are looking for a paralegal to join the dispute resolution team at Harneys Hong Kong. The award winning and industry leading team advise on full spectrum of commercial dispute matters including shareholder disputes, fraud, cross-border and multi-jurisdictional litigation, asset tracing as well as restructuring and insolvency matters.\n\nOur dispute resolution group has been involved in the most significant global offshore disputes and complex cross-border restructurings and insolvencies of recent times, winning keynote victories for our clients and often helping shape the law. As a key part of the team you will work on a range of commercial litigation matters, including shareholder disputes, injunctions and commercial trials. You may also get involved in insolvency litigation proceedings..\n\nThe successful candidate must be a self-starter, eager to learn and trilingual (Cantonese, English and Mandarin). He/she will have the opportunity to review documents, draft legal advice, and assist the team on general legal issues. We welcome applications from candidates who have just completed legal studies.", "employment_types": ["Full Time"], "selling_points": [], "locations": ["Southern Area"], "categories": ["Professional Services", "Company Secretary", "Legal & Compliance"], "post_time": "2022-01-16T21:50:21Z", "salary": {"currency": null, "max": null, "min": null, "period": "monthly", "term": null}, "salary_visible": false, "title_keywords": ["company secretarial assistant"], "responsibilities": ["resolution", "client base", "review", "provide advice"], "requirements": {"degrees": [], "majors": [], "languages": ["cantonese", "english", "mandarin"], "language_level": [], "hard_skills": [], "soft_skills": ["eager to learn"], "languages_combined": [{"language": "cantonese", "language_level": []}, {"language": "english", "language_level": []}, {"language": "mandarin", "language_level": []}]}, "experience_required": {"duration": [], "field": []}}, {"job_id": "100003009056047", "location_code": "hk", "company": "Chong Hing Bank Ltd", "job_title": "Vice President \u2013 AML Compliance Checking", "description": "\n*** Premium Office opposite to Wong Chuk Hang MTR ***\n\n\nResponsibilities:\n\nNew headcount for business expansion\nAssist in a full range of company secretarial and compliance duties for HK and offshore jurisdiction (i.e. BVI, Cayman Islands)\nAssist in the preparation of quarterly/interim/annual reports\nOrganize and prepare for board meetings, shareholder meetings\nArrange notification of corporate changes to the relevant authorities\nAssist in the handling of ad-hoc projects\n\nRequirements:\n\nDegree holder in relevant disciplines\nAssociate member of HKICS/ICSA\nAt least 3 years or above of solid company secretarial experience in a pro-firm or a listed company\nFamiliar with Company Ordinance, Listing Rules, Securities and Future Ordinance is an advantage\nExcellent command of Mandarin, Cantonese and English\nProactive, well organized, detail-oriented and hardworking\nWe offer competitive remuneration and career opportunities to the right candidate. Please send a full resume with current & expected salary to us.\n\n\n*Resume without stating current and expected salary will not be considered.\n\n(Data collected would be used for recruitment purpose only)", "employment_types": ["Full Time"], "selling_points": ["Lead and supervise AML Compliance Checking Team", "Perform offsite enhanced CDD review", "Minimum 8 years\u2019 experience"], "locations": ["Not Specified"], "categories": ["Banking / Finance", "Others", "Professional Services", "Legal & Compliance"], "post_time": "2022-01-18T03:13:29Z", "salary": {"currency": null, "max": null, "min": null, "period": "monthly", "term": null}, "salary_visible": false, "title_keywords": ["vice president", "aml compliance"], "responsibilities": ["ad-hoc projects", "compliance", "reports"], "requirements": {"degrees": ["degree holder"], "majors": [], "languages": ["cantonese", "english", "mandarin"], "language_level": ["excellent"], "hard_skills": [], "soft_skills": ["proactive", "well organized", "hardworking", "detail-oriented"], "languages_combined": [{"language": "cantonese", "language_level": ["excellent"]}, {"language": "english", "language_level": ["excellent"]}, {"language": "mandarin", "language_level": ["excellent"]}]}, "experience_required": {"duration": ["at least 3 years"], "field": ["secretarial"]}}, {"job_id": "100003009052311", "location_code": "hk", "company": "Cartus Relocation Hong Kong Limited", "job_title": "Consultant, Immigration Services", "description": "Responsibilities\u00a0\n\n\nAssist in handling company secretarial matters relating to associated companies of the Group under various jurisdictions;\nMaintain up-to-date records such as annual return and general meeting papers and attending to local filings;\nAssist in preparing relevant minutes and various information for public disclosures, compliance issues and corporate exercises of the Group;\nPerform ad hoc assignments as required.\nRequirements\n\n\nA degree holder with a student member of HKCGI;\nMinimum 2 years\u2019 experience in company secretarial field;\nExperience in handling offshore companies is an advantage;\nProficiency in MS Office applications, Chinese Word Processing and CSA;\nExcellent written and spoken English and Chinese. Mandarin is essential;\nGood interpersonal and organization skills;\nMeticulous, self-motivated, responsible and independent;\nImmediately available is highly preferred.\nCandidates with more experience will be considered as Senior Executive, Company Secretarial.\n\n\nWe provide competitive remuneration with career prospect to the right candidate. Interested parties please send your detailed resume with current & expected salary, contact number, availability with reference no.RA-CSE-2021 on subject line.\n\nCorporate Office Address: 26/F, E-Trade Plaza, 24 Lee Chung Street, Chai Wan, Hong Kong (5 minutes' walking distance to MTR station)\u00a0\u00a0\n\nFor more company information, please feel free to visit: www.rotam.com\u00a0\n\n(Personal data collected will be used for recruitment purpose only.)\u00a0", "employment_types": ["Full Time", "Permanent"], "selling_points": ["Excellent Customer Service, Visa and Immigration", "19+ days Leaves per year", "Attractive Benefits"], "locations": ["Wan Chai"], "categories": ["Professional Services", "Legal & Compliance"], "post_time": "2022-01-17T04:10:52Z", "salary": {"currency": null, "max": null, "min": null, "period": "monthly", "term": null}, "salary_visible": false, "title_keywords": ["consultant"], "responsibilities": ["compliance", "maintain", "ad hoc assignments"], "requirements": {"degrees": ["degree holder"], "majors": [], "languages": ["english", "chinese", "mandarin"], "language_level": ["proficiency", "excellent"], "hard_skills": ["chinese word processing", "ms office"], "soft_skills": ["meticulous", "self-motivated", "independent", "responsible", "organization skills", "interpersonal"], "languages_combined": [{"language": "english", "language_level": ["excellent"]}, {"language": "chinese", "language_level": ["proficiency", "excellent"]}, {"language": "mandarin", "language_level": []}]}, "experience_required": {"duration": ["minimum 2 years"], "field": ["secretarial"]}}, {"job_id": "100003009043212", "location_code": "hk", "company": "Animoca Brands Limited", "job_title": "Legal Secretary/Paralegal (in-house role)", "description": "As a member of the corporate Intellectual Property team, this is an excellent opportunity for you to get exposure in global Intellectual Property (Patent, Trademark and etc.) projects and develop high professionalism in a global diverse environment. If you are the one with passion to grow and learn, come and join us.\n\nResponsibilities:\n\n\nDraft patent specification and prepare patent & trademark application documents;\nConduct legal research and technical searches of patents internationally in the area of chemistry; with ability to screen and provide an efficient shortlist;\nManage the application of intellectual property (patent & trademark) globally;\nConduct literature review and market research;\nMaintain an efficient database for easy retrieval of information;\nAs a record keeping of the department, including patent application & trademarks;\nPerform other duties as assigned.\n\nRequirements\n\n\nBachelor degree or above in Chemistry, Biochemistry or related discipline;\nFresh graduates are welcome\nExperience in patent and trademark handling is highly preferable;\nGood PC knowledge, include MS Office applications and Chinese Word Processing;\nExcellent interpersonal, communication, negotiation and organization skills;\nAble to read and write business correspondences in English and Chinese.\u00a0 Proficiency in Mandarin would be an advantage.\u00a0\n\nWe provide competitive remuneration with career prospect to the right candidate. Interested parties please send your detailed resume with current & expected salary, contact number, availability\u00a0with reference no. RA-AEIP-20211228\u00a0on subject line.\n\nCorporate Office Address: 26/F, E-Trade Plaza, 24 Lee Chung Street, Chai Wan, Hong Kong (5 minutes' walking distance to MTR station)\u00a0\n\nFor more company information, please feel free to visit: www.rotam.com\n\n(Personal data collected will be used for recruitment purpose only.)\u00a0\u00a0", "employment_types": ["Full Time"], "selling_points": ["In house role", "Blockchain and cryptocurrency", "Exposure in diversified business projects"], "locations": ["Pok Fu Lam"], "categories": ["Professional Services", "Legal & Compliance"], "post_time": "2022-01-12T10:14:19Z", "salary": {"currency": null, "max": null, "min": null, "period": "monthly", "term": null}, "salary_visible": false, "title_keywords": ["paralegal", "legal secretary"], "responsibilities": [], "requirements": {"degrees": [], "majors": [], "languages": [], "language_level": [], "hard_skills": [], "soft_skills": [], "languages_combined": []}, "experience_required": {"duration": [], "field": []}}, {"job_id": "100003009050120", "location_code": "hk", "company": "Luen Thai International Group Ltd", "job_title": "Company Secretarial Officer/Assistant", "description": "Responsibilities:\n\n-Provide secretarial support to the legal team in administrative and secretarial matters.\n-Work closely with related parties to manage transactions from the documentation phase to closing; maintain the Company's legal documentation and contracts database.\n-Support the management team in legal matters relating to the Group's investments, M&A activities, development, production, distribution and sale of technology and digital media products.\n-Liaise and communicate with internal and external stakeholders.\n-Conduct research and liaise with external counsel in all relevant jurisdictions.\n-Assist\u00a0in ad-hoc assignments and operational legal matters.\n-Supporting company secretarial matters.\n-Not required, but a big plus: ability to draft and review a full range of commercial\u00a0 and legal documents, including non-disclosure agreements, development agreements, work-for-hire agreements, distribution and licensing agreements, share subscription agreements, share sale and purchase agreements and shareholders agreement.\n-Any other ad hoc assignments as assigned.\n\n\n\n\nRequirements:\n\n-Degree or above with minimum 3 years' paralegal or legal secretary experience from in-house legal team.\n-Systematic, punctual and hardworking with excellent organisational skills.\n-Meticulous and attention to detail.\n-Experience with corporate governance and regulatory compliance requirements.\n-Exposure and track record in corporate and licensing matters with some knowledge in intellectual property.\n-Candidates must also demonstrate excellent interpersonal skills, be positive, adaptable, detail-minded and a team player.\n-Excellent communication skills in spoken and written English is essential.\n-Willing to work overtime when required and able to work independently under pressure to meet tight deadlines.\n-Immediately available is an advantage.\n\n\n\n\nThe Perks:\u00a0\n\n5-day work week.\n15 days annual leave.\nMedical, Life & Personal Accident insurance\nTransportation allowance\nCasual work attire.\nFree coffee, tea and fruit daily.\nMulti-cultural work environment (15 nationalities and counting).\nFlat company structure: your ideas get heard by the right people very quickly.\nDiverse range of game and app genres: learn and try different projects from time to time.\nRegular (and fun) company activities.\nOther leave (marriage leave, compassionate leave, exam leave).\n\nTo apply for this position please send your resume with position applied, academic transcript (for recent graduates), current and expected salary. Short-listed candidates will be contacted.\n\nInformation provided will be treated in strict confidence and will only be used for recruitment-related purposes. Only short-listed candidates will be contacted. Information of unsuccessful applicants will be destroyed after six months.", "employment_types": ["Full Time", "Permanent"], "selling_points": ["2-3 years of comp. sec. experience", "Degree or diploma in BA or Corp. Gov.", "Independent, attentive to details, self-motivated"], "locations": ["Kwun Tong"], "categories": ["Banking / Finance", "Corporate Finance", "Professional Services", "Company Secretary", "Legal & Compliance"], "post_time": "2022-01-14T09:48:32Z", "salary": {"currency": null, "max": null, "min": null, "period": "monthly", "term": null}, "salary_visible": false, "title_keywords": ["company secretarial officer", "assistant"], "responsibilities": ["communicate with", "management team", "contracts", "ad-hoc assignments", "review", "transactions", "liaise with", "purchase", "maintain", "secretarial support", "database", "ad hoc assignments", "documentation"], "requirements": {"degrees": [], "majors": [], "languages": ["english"], "language_level": [], "hard_skills": ["transcript", "tea", "fun"], "soft_skills": ["detail-minded", "communication skills", "work overtime", "hardworking", "work independently", "under pressure", "meet tight deadlines", "confidence", "adaptable", "diverse", "organisational skills", "interpersonal skills", "attention to detail", "team player", "positive"], "languages_combined": [{"language": "english", "language_level": []}]}, "experience_required": {"duration": ["minimum 3 years"], "field": ["legal", "team"]}}, {"job_id": "100003009036423", "location_code": "hk", "company": "Anthony Siu & Co.", "job_title": "Paralegal", "description": "Responsibilities:\n\nAssist in handling full spectrum of company secretarial matters for the listed Group and its subsidiaries;\nArrange for filing of statutory forms and returns with registrars/regulatory authorities in accordance with relevant legal and compliance requirements as well as maintain/update secretarial records and registers;\nAssist in organizing Board/Committee and Shareholders meetings and prepare meeting materials;\nAssist in preparing of annual / interim reports, announcements and circulars;\nAssist in ad hoc projects and other duties as assigned.\n\n\nRequirements:\n\nDegree or diploma holder in Business Administration/Corporate Governance or a related discipline;\n2-3 years of working experience in handling company secretarial duties (fresh graduate will also be considered);\nGood PC knowledge in MS Word, Excel, Powerpoint, and Chinese word processing;\nGood command of written and spoken English and Chinese (including Mandarin);\nExperience in listed company will be an advantage;\nIndependent, attentive to details, self-motivated with a strong sense of responsibility;\nImmediate\u00a0availability is preferred.\n\nWe offer an attractive remuneration package to qualified candidates who wish to advance their careers in a people-centered business. Interested parties please send your detailed resume with current & expected salary and availability.\n\nFor more information, please visit www.luenthai.com.\n\nAll applications will be treated in strict confidence and only be used for recruitment related purpose.", "employment_types": ["Full Time"], "selling_points": ["Law Degree", "Minimum of 2 years\u2019 experience in legal industry", "Immediate availability preferred"], "locations": ["Central"], "categories": ["Professional Services", "Legal & Compliance"], "post_time": "2022-01-10T10:22:53Z", "salary": {"currency": "HKD", "max": 24999, "min": 17000, "period": "monthly", "term": null}, "salary_visible": true, "title_keywords": ["paralegal"], "responsibilities": ["other duties", "compliance", "maintain", "ad hoc projects", "reports"], "requirements": {"degrees": ["diploma holder", "degree", "fresh graduate"], "majors": ["business administration"], "languages": ["english", "chinese", "mandarin"], "language_level": ["good command", "good"], "hard_skills": ["excel", "chinese word processing", "powerpoint", "pc knowledge", "ms word"], "soft_skills": ["self-motivated", "independent", "attentive to details", "sense of responsibility"], "languages_combined": [{"language": "english", "language_level": ["good command", "good"]}, {"language": "chinese", "language_level": ["good command", "good", "good"]}, {"language": "mandarin", "language_level": ["good command", "good"]}]}, "experience_required": {"duration": ["2-3 years"], "field": ["secretarial"]}}, {"job_id": "100003009043433", "location_code": "hk", "company": "Industrial and Commercial Bank of China (Asia) Limited", "job_title": "Assistant Manager to Senior Manager, Mainland China Legal, Compliance and Legal Department", "description": "Requirement :-\n\nHolder of law degree\nMinimum of 2 years' experience in legal industry\nFluent in both written and spoken English and Chinese (Putonghua is an advantage)\nIndependent, self-motivated, organized, and able to work under pressure\nImmediate availability preferred\n\nWe offer medical insurance including dental benefits and attractive remuneration to the right candidate. Interested applicants are requested to apply under a confidential cover (in English) with a detailed resume, current salary and expected salary by clicking 'Apply Now'.\n\u00a0\n\nPersonal data collected will be used for recruitment purpose only.", "employment_types": ["Full Time", "Permanent"], "selling_points": [], "locations": ["Central & Western Area"], "categories": ["Professional Services", "Legal & Compliance"], "post_time": "2022-01-12T11:44:16Z", "salary": {"currency": null, "max": null, "min": null, "period": null, "term": null}, "salary_visible": false, "title_keywords": ["senior manager", "assistant manager"], "responsibilities": ["work under pressure"], "requirements": {"degrees": ["degree"], "majors": ["law"], "languages": ["putonghua", "english", "chinese"], "language_level": ["advantage", "fluent"], "hard_skills": [], "soft_skills": ["organized", "self-motivated", "independent", "work under pressure"], "languages_combined": [{"language": "putonghua", "language_level": ["advantage", "fluent"]}, {"language": "english", "language_level": ["advantage", "fluent"]}, {"language": "chinese", "language_level": ["advantage", "fluent"]}]}, "experience_required": {"duration": ["minimum of 2 years"], "field": ["legal"]}}, {"job_id": "100003009045094", "location_code": "hk", "company": "CEVA Logistics (Hong Kong) Limited", "job_title": "Legal Manager", "description": "Responsibilities and Duties\n\nDraft, review and negotiate legal documents relating to all aspects of the bank's business based on Chinese laws and regulations\nIdentify potential legal issues arising in business operation and providing legal solutions.\nLiaise and collaborate with external lawyers\nConduct legal research relate to cross border laws and regulations, and carry out legal training\nReview and update legal related policies and procedures\nOffer support on other ad hoc assignments as required\n\nJob Skills and Qualifications\n\nPRC qualified solicitor with at least with at least 2 years of experience in the legal industry, whether in a law firm or in a legal department\nSome knowledge of the banking and financial industry is preferred\nFluent English and Chinese language skills\nFamiliarity with Microsoft Office and Kingsoft (Word, Excel, and Powerpoint)\nAdaptability and a willingness to co-operate in a diverse environment\n", "employment_types": ["Full Time", "Permanent"], "selling_points": ["Inhouse Legal Manager in MNC", "Strong communication & negotiation skills", "Qualified as a practicing lawyer"], "locations": ["Kowloon Bay"], "categories": ["Professional Services", "Business Consultancy", "Legal & Compliance", "Transportation & Logistics", "Freight Forwarding"], "post_time": "2022-01-13T07:10:04Z", "salary": {"currency": null, "max": null, "min": null, "period": null, "term": null}, "salary_visible": false, "title_keywords": ["manager"], "responsibilities": ["regulations", "business operation", "collaborate with", "liaise", "policies", "review", "procedures", "ad hoc assignments", "banking"], "requirements": {"degrees": [], "majors": [], "languages": ["english", "chinese"], "language_level": ["fluent"], "hard_skills": ["excel", "word", "powerpoint", "microsoft office"], "soft_skills": ["diverse", "adaptability"], "languages_combined": [{"language": "english", "language_level": ["fluent"]}, {"language": "chinese", "language_level": ["fluent"]}]}, "experience_required": {"duration": ["at least 2 years"], "field": ["legal"]}}, {"job_id": "100003009040327", "location_code": "hk", "company": "SO KEUNG YIP & SIN", "job_title": "Paralegal / Legal Clerk \u2013 Intellectual Property", "description": "YOUR ROLE\n\nTo partner with Business to negotiate and close deals. Ability to fix complex issues and provide solution. Ability to interact with different levels of management with solid communication and people management skills.Cultivate great sense of governance and compliance within the organisation\u00a0\n\nWHAT ARE YOU GOING TO DO?\u00a0\n\nPrimarily commercial contracts drafting, review, negotiation according to internal rules and regulations and provide legal advice to business units and supporting functions on a day-to-day basis;\nContract negotiation and ability to strategize for solutions to complex issues.\nFamiliar with corporate secretarial matters , company restructuring & M&A transactions.\nWell conversant with local laws and able to attend courts hearings and labor mediation.\nStrategize and manage outside counsels in handling civil litigation or arbitration cases.\nConduct training of company rules and policies and other topics of interest such as data privacy in Hong Kong ; and\nAny other duties as assigned from time to time.\n\n\nWHAT ARE WE LOOKING FOR?\u00a0\n\nHolds a law degree from a reputable university in Hong Kong or overseas.\nQualified as a practicing lawyer in Hong Kong\nMinimum 5 years of post-qualification experience with a reputable law firm in Hong Kong or as in-house counsel with a multinational corporation preferably in the logistics industry;\nStrong communication, negotiation and drafting skills with excellent problem-solving and partnering abilities;\nOutgoing personality, self-motivated and has a high level of individual responsibility and ability to withstand work pressure and can drive contracts negotiation together with Business Development to close deals;\nAbility to multi-task is needed.\nHigh proficiency in both written and spoken English and Chinese (Mandarin). Ability to speak and write a foreign language like Japanese or Korean is an advantage; and\u00a0\nStrong in PowerPoint and presentation skills.\n\n\u00a0WHAT DO WE HAVE TO OFFER?\u00a0\n\nWith a genuine culture of reward and recognition, we want our employees to grow, develop and be part of our journey. We offer a benefits package that includes competitive annual leave entitlement, pension and medical insurance along with other cash and holiday gifts. There\u2019s no doubt that you will be compensated for your hard work and commitment so if you\u2019d like to work for one of the top Logistics providers in the world then please do get in touch to find your next role.\n\n\u00a0ABOUT TOMORROW\u00a0\n\nWe value your professional and personal growth. That\u2019s why we share plenty of career opportunities for you to thrive within CEVA. Join CEVA for a challenging career.\u00a0", "employment_types": ["Full Time", "Permanent"], "selling_points": [], "locations": ["Sheung Wan"], "categories": ["Admin & HR", "Clerical / Admin Staff", "Professional Services", "Legal & Compliance"], "post_time": "2022-01-13T18:54:48Z", "salary": {"currency": null, "max": null, "min": null, "period": "monthly", "term": null}, "salary_visible": false, "title_keywords": ["paralegal", "legal clerk"], "responsibilities": ["regulations", "any other duties", "management", "data", "contracts", "policies", "compliance", "review", "transactions", "develop", "communication", "logistics"], "requirements": {"degrees": ["degree"], "majors": ["law"], "languages": ["english", "mandarin", "japanese", "korean", "chinese"], "language_level": ["advantage", "proficiency"], "hard_skills": ["problem-solving", "powerpoint"], "soft_skills": ["outgoing personality", "self-motivated", "multi-task", "negotiation", "problem-solving", "communication", "presentation skills", "organisation", "genuine"], "languages_combined": [{"language": "english", "language_level": ["proficiency"]}, {"language": "mandarin", "language_level": []}, {"language": "japanese", "language_level": ["advantage"]}, {"language": "korean", "language_level": ["advantage"]}, {"language": "chinese", "language_level": ["proficiency"]}]}, "experience_required": {"duration": ["minimum 5 years"], "field": ["logistics industry", "post-qualification"]}}, {"job_id": "100003008996709", "location_code": "hk", "company": "Michael Li & Co.", "job_title": "Paralegal/Legal Executive", "description": "Good academic background\nRelevant experience in commercial and/or corporate matters\nGood drafting and communication skills in both English and Chinese (Putonghua and Cantonese)\nThe candidates are expected to assist in verification and due diligence exercise, draft and review documents, and provide support on other corporate and commercial matters\n\nInterested candidates, please email by clicking 'Apply Now' with expected and present salary for application enquiry.\n\nAll Personal data collected will be used for recruitment purpose only.", "employment_types": ["Full Time", "Permanent"], "selling_points": ["Good academic background", "assist in verification and due diligence exercise", "Good drafting and communication skills"], "locations": ["Central"], "categories": ["Professional Services", "Legal & Compliance"], "post_time": "2022-01-12T02:43:32Z", "salary": {"currency": null, "max": null, "min": null, "period": "monthly", "term": null}, "salary_visible": false, "title_keywords": ["legal executive", "paralegal"], "responsibilities": ["communication", "due diligence", "provide support", "review"], "requirements": {"degrees": [], "majors": [], "languages": ["cantonese", "putonghua", "english", "chinese"], "language_level": ["good"], "hard_skills": [], "soft_skills": ["communication skills"], "languages_combined": [{"language": "cantonese", "language_level": ["good"]}, {"language": "putonghua", "language_level": ["good"]}, {"language": "english", "language_level": ["good"]}, {"language": "chinese", "language_level": ["good"]}]}, "experience_required": {"duration": [], "field": ["commercial", "relevant experience"]}}, {"job_id": "100003009056032", "location_code": "hk", "company": "ConnectedGroup Limited", "job_title": "Assistant Manager, Company Secretariat (HK$ 40k-55k)", "description": "Working experience in a law firm essential\nMinimum 2 years filing and prosecuting trade marks using the e-filing system\nExperienced in filing design applications and patent applications using the e-filing system\nMust be accurate and detail oriented\nMust be conscientious, mature and be able to work independently\nMust be able to work efficiently and productively\nMust be able to co-operate with and support other team members\nNeed good communications and interpersonal skills\nMust be a team player\nGood command of written and spoken English and Cantonese\nProficient in Microsoft word and excel, and typical information technology/computer systems.\n\nWe offer an attractive remuneration package to the right candidate.\n\nInterested parties please apply sending your full resume including latest and expected salary by clicking \"Apply Now\".\n\n(By applying you agree that we can use your personal data for recruitment purposes \u2013 including verification \u2013 and that we can hold such data for up to three months even if we do not offer you a job. Your data will be destroyed if you are not employed by us within 3 months of receipt.)", "employment_types": ["Full Time", "Permanent"], "selling_points": ["Cover a wide range of company secretarial matters", "Top-tier Property Developer", "Qualified Member of HKCGI/CGI"], "locations": ["Kwun Tong Area"], "categories": ["Professional Services", "Company Secretary", "Legal & Compliance"], "post_time": "2022-01-18T03:12:29Z", "salary": {"currency": "HKD", "max": 54999, "min": 45000, "period": "monthly", "term": null}, "salary_visible": true, "title_keywords": ["assistant manager,"], "responsibilities": ["co-operate with", "computer systems", "design"], "requirements": {"degrees": [], "majors": [], "languages": ["cantonese", "english"], "language_level": ["good command"], "hard_skills": ["excel", "microsoft word", "computer systems"], "soft_skills": ["work independently", "detail oriented", "mature", "interpersonal skills", "conscientious", "team player", "accurate"], "languages_combined": [{"language": "cantonese", "language_level": ["good command"]}, {"language": "english", "language_level": ["good command"]}]}, "experience_required": {"duration": [], "field": []}}, {"job_id": "100003009043183", "location_code": "hk", "company": "Wong & Tang Solicitors", "job_title": "Legal Executive / Legal Secretary / Clerk", "description": "Assistant Manager - Company Secretariat\n\nOur client is a well-established and reputable property developer listed in Hong Kong. We are assisting them looking for a talented individual to take up the Assistant Manager, Company Secretariat.\n\nSalary: HK$ 40,000 - 55,000x 12 month + bonus\n\nJob Summary:\n\nProviding company secretarial services for Board and company\nFamilir with Hong Kong Listing Rules and Securities and Futures Ordinance\n\nJob Duties:\n\nResponsible for full spectrum of company secretarial duties, corporate governance and compliance functions for listed company and private subsidiaries\nDraft and prepare annual and interim reports, announcements and circulars\nOrganize meetings for the board, committees and shareholders, and prepare relevant board papers, minutes and resolutions\nMaintain and update statutory records and filings in compliance with the Code on Real Estate Investment Trusts, Securities and Futures Ordinance, Listing Rules, applicable laws and regulations and implement compliance procedures as required\nLiaise with professional advisors and various regulatory bodies\nParticipate in ad hoc projects and tasks assigned from time to time\n\nRequirements:\n\nDegree holder in Corporate Administration or relevant disciplines\nQualified Member of HKCGI/CGI\nAt least 8 to 10 years of company secretarial experience gained in listed company, large-scale corporations or professional firms\nSolid experience in Hong Kong Listing Rules, Securities and Futures Ordinance and Hong Kong Companies\nExperience in handling compliance matters with the Securities and Futures Commission is an advantage\nExcellent command of written and spoken English and Chinese\nProven track record of minute taking and stakeholder management.\nCandidates with more experience will be considered as Manager\n\nInterested individuals should \"Apply Now\", due to an influx of applicants, we regret to inform you that ONLY suitable candidates will be contacted.\n\nFor a more comprehensive list of our vacancies, please visit: www.connectedgroup.com", "employment_types": ["Full Time"], "selling_points": [], "locations": ["Wan Chai"], "categories": ["Professional Services", "Company Secretary", "Legal & Compliance"], "post_time": "2022-01-12T10:05:29Z", "salary": {"currency": null, "max": null, "min": null, "period": "monthly", "term": null}, "salary_visible": false, "title_keywords": ["legal executive", "clerk", "legal secretary"], "responsibilities": ["regulations", "compliance", "procedures", "maintain", "reports", "ad hoc projects", "liaise with", "listing"], "requirements": {"degrees": ["degree holder"], "majors": [], "languages": ["english", "chinese"], "language_level": ["excellent"], "hard_skills": ["inform", "securities and futures ordinance"], "soft_skills": ["comprehensive"], "languages_combined": [{"language": "english", "language_level": ["excellent"]}, {"language": "chinese", "language_level": ["excellent"]}]}, "experience_required": {"duration": ["at least 8 to 10 years"], "field": ["secretarial", "compliance", "securities"]}}, {"job_id": "100003009050234", "location_code": "hk", "company": "CNCB (Hong Kong) Investment Limited", "job_title": "Vice President - Compliance", "description": "Good communication skills;\nMature, good interpersonal skills, well-organized and can work under pressure;\nFresh graduate with good working attitude will be considered;\nProficient in PC (Microsoft Word and Excel);\n1-2 year(s) experience in legal field is preferred; and\nImmediate available is preferable.", "employment_types": ["Full Time", "Permanent"], "selling_points": ["Minimum 5 years related work experience", "Exposure in RA 1, 4, 6 or 9", "General Compliance"], "locations": ["Admiralty"], "categories": ["Professional Services", "Legal & Compliance"], "post_time": "2022-01-14T10:01:06Z", "salary": {"currency": null, "max": null, "min": null, "period": "monthly", "term": null}, "salary_visible": false, "title_keywords": ["vice president"], "responsibilities": ["communication", "work under pressure"], "requirements": {"degrees": ["fresh graduate"], "majors": [], "languages": [], "language_level": [], "hard_skills": ["pc", "microsoft word", "excel"], "soft_skills": ["communication skills", "good working attitude", "well-organized", "mature", "interpersonal skills", "work under pressure"], "languages_combined": []}, "experience_required": {"duration": [], "field": ["legal"]}}, {"job_id": "100003009050576", "location_code": "hk", "company": "Legacy Trust Company Limited", "job_title": "Compliance Officer (5-day work)", "description": "Responsibilities:\n\nProvide compliance consultation and advice on license business;\nDraft, review and comment internal policies related to securities trading, securities advising business and corporate finance;\nPerform and review the compliance monitoring program regularly;\nPrepare internal compliance reports required by the Head Office;\nHandle SFC license applications and notifications;\nHandle internal monitoring for preventing conflicts of interest;\nOrganize compliance training and monitor CPT hours of the staff\nLiaise with regulators on any business-related compliance matters\nPerform ad hoc projects and other tasks as assigned\n\nRequirements:\n\nMinimum 5 years related compliance\u00a0work experience;\nWith experience in financial institutions, exposure in RA 1, 4, 6 or\u00a09\u00a0is highly preferred;\nExcellent regulatory knowledge of the financial industry, especially on Securities and Futures Ordinance;\nStrong communication skills with a good sense of teamwork;\nStrong written and spoken Chinese/ Mandarin and English.", "employment_types": ["Full Time", "Permanent"], "selling_points": [], "locations": ["Admiralty"], "categories": ["Professional Services", "Legal & Compliance"], "post_time": "2022-01-14T10:47:57Z", "salary": {"currency": null, "max": null, "min": null, "period": "monthly", "term": null}, "salary_visible": false, "title_keywords": ["compliance officer"], "responsibilities": ["policies", "review", "compliance", "monitoring", "monitor", "other tasks", "reports", "ad hoc projects", "liaise with", "license applications"], "requirements": {"degrees": [], "majors": [], "languages": ["english", "chinese", "mandarin"], "language_level": [], "hard_skills": ["securities and futures ordinance"], "soft_skills": ["communication skills", "teamwork"], "languages_combined": [{"language": "english", "language_level": []}, {"language": "chinese", "language_level": []}, {"language": "mandarin", "language_level": []}]}, "experience_required": {"duration": ["minimum 5 years"], "field": ["related", "financial institutions", "compliance"]}}, {"job_id": "100003009050894", "location_code": "hk", "company": "Bank of Communications Co., Ltd. Hong Kong Branch", "job_title": "Officer, Financial Crime Compliance \u2013 1 year contract", "description": "Responsibilities:\n\n\nAssist Head of Compliance in AML monitoring on full range of business activities;\nAssist in handling regulatory reporting, inquiries from banks and regulatory authorities;\nAssist in external and internal compliance audits, inspections, and investigations;\nConduct due diligence KYC on all client onboarding, business activities and counterparts;\nConduct operational audits to ensure the internal processes meet compliance requirements;\nMeet overall client satisfaction while meeting the company's global audit, compliance, risk and control requirements;\nActively engage in available training and education programs to maintain current status on policies, procedures and risk awareness;\nConduct internal regulatory & compliance training to staffs such as AML Training etc;\nMaintain company Compliance Policies to ensure policies are up to date with regulatory changes;\nPerform other duties as assigned by the Management from time to time, reporting to Head of Compliance.\n\nRequirements:\n\n\nBachelor\u2019s degree in Law, Corporate Governance, Finance or Accounting or other related disciplines from a recognised university;\nAt least 2 years of experience in compliance preferably with multinational financial companies or banks;\nExperience in and knowledge of the Trust industry would be an advantage;\nExperience in AML, finance, compliance and/or the relevant fields would be a plus;\nStrong command of both written and spoken English and Chinese is a MUST;\nProficiency in Microsoft Office and Exchange;\nDetail-oriented and highly motivated mindset.\n\nWe offer nice work environment in Admiralty, 5-day working week and good career prospects. Applicants should provide their resume with contact number, current and expected salary to the HR Department by clicking \"Apply Now\" below.\n\nFor more details, please kindly take a look to our website at\u00a0legacytrust.com.hk\n\n\nAll personal data collected would be used for recruitment purposes only and will be kept confidentially. Only short-listed candidates will be notified.\u00a0", "employment_types": ["Full Time", "Contract"], "selling_points": [], "locations": ["Not Specified"], "categories": ["Banking / Finance", "Others", "Professional Services", "Legal & Compliance", "Risk Management"], "post_time": "2022-01-14T11:41:26Z", "salary": {"currency": null, "max": null, "min": null, "period": "monthly", "term": null}, "salary_visible": false, "title_keywords": ["officer"], "responsibilities": ["reporting", "due diligence", "control", "aml", "perform other duties", "management", "policies", "monitoring", "compliance", "audit", "procedures", "maintain", "kyc", "audits", "business activities"], "requirements": {"degrees": ["degree", "bachelor"], "majors": ["related disciplines", "finance", "accounting", "law"], "languages": ["english", "chinese"], "language_level": [], "hard_skills": ["exchange", "plus", "aml", "microsoft office"], "soft_skills": ["motivated", "detail-oriented"], "languages_combined": [{"language": "english", "language_level": []}, {"language": "chinese", "language_level": []}]}, "experience_required": {"duration": ["at least 2 years"], "field": ["finance", "compliance", "financial"]}}, {"job_id": "100003009048191", "location_code": "hk", "company": "Vistra (Hong Kong) Limited", "job_title": "Associate, Client Acceptance (KYC / CDD)", "description": "Career Level\nEntry Level\nQualification\nDegree\nJob Type\nFull Time, Contract\nJob Functions\nBanking / Finance, Others, Professional Services, Legal & Compliance, Risk Management", "employment_types": ["Full Time", "Permanent"], "selling_points": ["Handle KYC / CDD function for corporate clients", "Exposure to offshore jurisdictions regulations", "Good communications and interpersonal skills"], "locations": ["Causeway Bay"], "categories": ["Banking / Finance", "Financial Services", "Professional Services", "Legal & Compliance"], "post_time": "2022-01-14T05:49:18Z", "salary": {"currency": null, "max": null, "min": null, "period": "monthly", "term": null}, "salary_visible": false, "title_keywords": ["associate"], "responsibilities": ["management", "compliance", "banking"], "requirements": {"degrees": ["degree"], "majors": [], "languages": [], "language_level": [], "hard_skills": [], "soft_skills": [], "languages_combined": []}, "experience_required": {"duration": [], "field": []}}, {"job_id": "100003009037316", "location_code": "hk", "company": "METRO Sourcing International Limited", "job_title": "Assistant Legal & Compliance Officer", "description": "Role Purpose:\nOur\u00a0Assistant Legal & Compliance Officer is responsible for daily legal and compliance support.\n\nWhat you will be handling:\n\nDrafting / reviewing simple contracts, claim letters, board resolution and other documentation\nLiaise and arrange signing and collection of contracts and documents\nAssist in provision of company secretarial supports to offices in HK, China, Vietnam, Turkey and Germany\nCarry out clerical / administrative duties in the department, maintain filing system and due diligence database\nOrganize internal legal and compliance trainings and conduct simple trainings after on-job-training if capable\nConduct research relating to various jurisdictions on legal and compliance matters\nPerform ad hoc tasks as being assigned\nTalent that we are looking for:\n\nWell organized and attention to details\nWilling to learn and cope with changes\nPossess strong sense of ownership and high degree of independence\nSelf-motivated, able to work under pressure and meet tight deadline\nEnergetic to drive for customer success and excellent service\nPassionate in connecting with people and adopting high level of interpersonal skills\nAble to liaise with internal departments and external business partners\nExperience, knowledge and skills required:\n\nDiploma or Degree holder in Legal Studies or equivalent discipline (e.g. corporate governance)\nAt least 2 years\u2019 relevant experience gained from law firm or in-house\nTraining experience would be an advantage but not a must\nGood command of both spoken and written English and Mandarin\nProficiency in MS Word, Excel, PowerPoint and Chinese word processing\nYou can enjoy:\n\nDiverse and Inclusive work environment\nFlexi Office Space with flexible working hours and home office option\n5-day work week, 13th month salary & performance bonus\nProfessional training and career advancement opportunities\nTraining Sponsorship for personal professional development\nJoin us and apply now!\nPlease send your full resume with available date, present and expected salary to us.\nResume and personal data collected will be kept strictly confidential and used for recruitment purpose only.", "employment_types": ["Full Time", "Permanent"], "selling_points": ["Exp in Law firm or In-house Legal/Compliance Dept.", "Support on legal & compliance duties", "MNC, 5 days work, double pay, performance bonus"], "locations": ["Kowloon Bay"], "categories": ["Professional Services", "Legal & Compliance"], "post_time": "2022-01-11T16:01:39Z", "salary": {"currency": null, "max": null, "min": null, "period": "monthly", "term": null}, "salary_visible": false, "title_keywords": ["compliance officer", "assistant"], "responsibilities": ["liaise", "due diligence", "contracts", "compliance", "letters", "ad hoc tasks", "resolution", "liaise with", "maintain", "administrative duties", "recruitment", "database", "documentation", "personal data", "conduct research", "work under pressure"], "requirements": {"degrees": ["diploma", "degree", "degree holder"], "majors": [], "languages": ["english", "chinese", "mandarin"], "language_level": ["proficiency", "good command"], "hard_skills": ["simple", "excel", "chinese word processing", "powerpoint", "documentation", "ms word"], "soft_skills": ["passionate", "flexible", "self-motivated", "capable", "responsible", "willing to learn", "well organized", "diverse", "interpersonal skills", "attention to details", "meet tight deadline", "energetic", "work under pressure"], "languages_combined": [{"language": "english", "language_level": ["good command"]}, {"language": "chinese", "language_level": ["proficiency"]}, {"language": "mandarin", "language_level": ["good command"]}]}, "experience_required": {"duration": ["at least 2 years"], "field": ["relevant experience", "training"]}}, {"job_id": "100003009052947", "location_code": "hk", "company": "Fung, Yu & Co. CPA Limited", "job_title": "Company Secretarial Assistant - Corporate Services Department (5 days work)", "description": "Responsibilities\n\nPerform risk analysis of supplier base based on audits reports/ assessment results.\nConduct factory assessments, shadow assessments, investigation where necessary.\nCooperate with service providers such as third party audit firms and ensure standards of operations.\nRepresent the company during assessments and suppliers meetings.\u00a0\u00a0\nIdentify and follow up the implementation of corrective action plan with the importers where required.\nPosition based in Hong Kong, up to 50% travelling is required (mainly China, and other South East Asian countries).\nYour Profile\n\nDegree holder in business or other relevant disciplines\nMinimum total of 5 years of relevant experience in similar position(s) gained in sizable organization.\nPractical hands-on experience as Auditor/ Monitoring function in CR field, with At least 3 years of working experience in factory audit.\nGood knowledge in hardgoods/softline production/ sourcing businesses.\nCantonese and Mandarin Speaker; fluency in both verbal and written business English.\nAttention to details and good organizational, coordination and planning as well as good logical and problem-solving skills\nWillingness to travel extensively (mainly in China, Bangladesh and South East Asia).\nCandidate with less experiences will be considered as Corporate Social Responsibility Associate.\n\nKey Benefits of working at ALDI.\n\nMarket leading remuneration package\n\nRewarding, attractive remuneration package.\nGroup Medical Insurance covering dental and maternity* benefits .\n\nWork-life balance\n\nFull time, permanent position, 5-day-work-week.\n20 days of paid Annual Leave.\n\nBeing part of a pleasant, successful, growing business\n\nALDI\u2019s business is expanding, same for the Hong Kong Office with lots of opportunities for growth and development.\nPleasant working atmosphere where proactive communication, teamwork and collaboration is highly valued.\nPeople Focused\n\nStructured, comprehensive orientation and on-the-job training.\nALDI empowers our people allowing staff ownership of their areas of responsibilities.\nTrust and Integrity\n\nWE DO WHAT WE SAY\u00a0-\u00a0 for us there is no grey area, we have robust business processes, procedures and strong governance in place.\nWe treat our staff members, customers, suppliers and service providers with trust and fairness as business partners.\n\n* Maternity benefits only apply for female employees due to local Insurance policy\n\nHow to apply\u00a0\u00a0\n\nIf you are interested in applying for the job, we look forward to receiving your full application in English, including salary expectation and possible starting date. The application should be sent through JobsDB by clicking icon \u201cApply Now\u201d or addressed to\u00a0ALDI HR Department,\u00a018/F, Millennium City 6, 392 Kwun Tong Road,\u00a0Kwun Tong, Kowloon, Hong Kong.\n\nALDI is an Equal Opportunity employer.\n\nAll personal data collected will be used for recruitment purposes only and be treated in strictest confidence and highest security level in accordance with Hong Kong Data (Privacy) Ordinance as well as ALDI internal Security Policy.\n\nNo part of this job content including but not limited to company information, logo and job description may be reproduced, presented, uploaded, transmitted, modified or distributed \u00a0in any form or by any means without prior permission of ALDI Services Asia Limited / ALDI Sourcing Asia Limited (\u201cthe Company\u201d). The Company reserves the right to take legal action on any unauthorized reproduction, presentation, upload, transmission, modification or distribution. Only applications submitted directly to the Company in response to this advertisement will be considered and any application received by the Company through unauthorized third party agents or via any other channels will not be considered.\n\n\n", "employment_types": ["Full Time", "Permanent"], "selling_points": ["14 days Annual Leave with annual increment", "Birthday leave, Study leave and Exam leave", "OT compensation and Medical allowance"], "locations": ["Sheung Wan"], "categories": ["Professional Services", "Company Secretary", "Legal & Compliance"], "post_time": "2022-01-17T04:39:35Z", "salary": {"currency": null, "max": null, "min": null, "period": "monthly", "term": null}, "salary_visible": false, "title_keywords": ["company secretarial assistant"], "responsibilities": ["operations", "monitoring", "audit", "investigation", "implementation", "reports", "risk analysis", "plan", "coordination", "audits", "cooperate with", "third party", "planning"], "requirements": {"degrees": ["degree holder"], "majors": ["business"], "languages": ["cantonese", "english", "mandarin"], "language_level": ["fluency"], "hard_skills": ["problem-solving skills", "analysis"], "soft_skills": ["organizational", "hands-on", "coordination", "attention to details", "problem-solving skills"], "languages_combined": [{"language": "cantonese", "language_level": []}, {"language": "english", "language_level": ["fluency"]}, {"language": "mandarin", "language_level": []}]}, "experience_required": {"duration": ["at least 3 years", "of 5 years"], "field": ["sizable organization", "relevant experience", "audit", "corporate social responsibility"]}}, {"job_id": "100003009046222", "location_code": "hk", "company": "Sing Tao Management Services Limited", "job_title": "Legal Counsel", "description": "In over 50 years, we have grown rapidly as one of the top-tier Hong Kong CPA firms with total 6 offices in China and Europe are actively are expanding our foothold across the globe.\u00a0 Please visit us at www.fungyucpa.com for more details. To support our fast-growing international business, we are seeking professionals with following expertise to be part of us.\n\n\u00a0Opportunities:\u00a0\n\nWe offer excellent career advancement opportunities to staff who join our\u00a0Corporate Services Department\u00a0\nYou will gain valuable experience in providing professional company secretary services to our clients, mainly median to large sized private companies and listed companies\nWe offer frequent training, stable office hours and great exposure in pursuing your professional qualifications\n\n\u00a0Job Duties:\n\nAssist to handle a full range of company secretarial duties and services as well as statutory compliance for listed and private companies\n\nPrepare annual/interim reports, announcements, circulars, board papers, board minutes and resolutions\nOrganize board and shareholders\u2019 meetings\nMaintain\u00a0statutory records and\u00a0ensure effective filing and retrieval systems for all company records\n\u00a0Perform other\u00a0administrative matters, clerical and various tasks as assigned\n\u00a0Incorporation of\u00a0 Hong Kong and offshore companies such as Cayman, BVI, Seychelles and Samoa\n\nRequirements:\n\nHigher diploma/Associate degree/University degree holder\nHKICS student member is preferred\nProficiency in CSA software, MS Office and Chinese Word Processing is preferred\nGood command of both spoken and written English and Cantonese with conversational Mandarin\nWell-organized, independent, self-motivated, hardworking and able to work under pressure\n\n5 days work, 14 days annual leave with annual increment, birthday leave, OT compensation and medical allowance.\u00a0 We offer a highly competitive salary and benefit package commensurate with qualifications and experience.\u00a0 Please submit your application by clicking \u201cApply Now\u201d button and visit our company website at http://www.fungyucpa.com/join-us/ for more information.\n\nPersonal data collected will be used for recruitment purpose only.", "employment_types": ["Full Time", "Permanent"], "selling_points": [], "locations": ["Tseung Kwan O"], "categories": ["Professional Services", "Business Consultancy", "Company Secretary", "Legal & Compliance"], "post_time": "2022-01-13T10:00:55Z", "salary": {"currency": null, "max": null, "min": null, "period": "monthly", "term": null}, "salary_visible": false, "title_keywords": ["legal counsel"], "responsibilities": [], "requirements": {"degrees": [], "majors": [], "languages": [], "language_level": [], "hard_skills": [], "soft_skills": [], "languages_combined": []}, "experience_required": {"duration": [], "field": []}}]