[{"job_id": "100003009050344", "location_code": "hk", "company": "Fly King Transportation Company Ltd", "job_title": "Training Supervisor", "description": "Responsibilities\nConduct classroom training courses\nProvide on-site coaching to frontline staff\nMaintain training schedules and keep training record up-to-dated\nPrepare and review training materials and documents\nCooperate with CPSL training team for training related programs\nAny ad hoc duties as assigned by superior\nRequirements\n2-3 years\u2019 relevant experience in air cargo industry is a must\nExcellent presentation and communication skills\nStrong sense of responsibility and good interpersonal skills\nFluency in spoken and written Chinese and English\nProficient in MS applications including Word, Excel and Powerpoint\nInterested parties, please send application with full particulars of qualifications, experience, current and expected salary by email via \"Apply Now\"\nAll information will be kept confidential and used for recruitment purpose only.", "employment_types": ["Full Time", "Permanent"], "selling_points": [], "locations": ["Airport Area"], "categories": ["Transportation & Logistics", "Aerospace", "Others", "Admin & HR", "Training & Development"], "post_time": "2022-01-14T10:10:34Z", "salary": {"currency": null, "max": null, "min": null, "period": "monthly", "term": null}, "salary_visible": false, "title_keywords": ["supervisor"], "responsibilities": ["ad hoc duties", "schedules", "review", "maintain", "cooperate with"], "requirements": {"degrees": [], "majors": [], "languages": ["english", "chinese"], "language_level": ["fluency"], "hard_skills": ["excel", "ms applications", "word", "powerpoint"], "soft_skills": ["communication skills", "interpersonal skills", "presentation", "sense of responsibility"], "languages_combined": [{"language": "english", "language_level": ["fluency"]}, {"language": "chinese", "language_level": ["fluency"]}]}, "experience_required": {"duration": ["2-3 years"], "field": ["relevant experience"]}}, {"job_id": "100003009044799", "location_code": "hk", "company": "Cathay Pacific Airways Ltd", "job_title": "Assistant Manager Group Quality Assurance - Ground", "description": "Reports to:\u00a0Group Quality Assurance Manager - Ground\nDepartment: Group Safety & Operation Risk Mgt (GSR)\n\nRole Introduction\n\n\nResponsible for supporting, administering, implementing and maintaining an effective quality assurance program across the ground operations departments of Cathay Pacific Airways and with relevant suppliers of operational services.\nSupport the Ground Quality Team to ensure the audit programs are maintained and monitored for effective delivery.\nKey Responsibilities\n\n\nSupport the delivery of an effective, efficient risk-based quality assurance program for Cathay Pacific by:\n\nPreparing the annual Consolidated Port Audit Program Schedule, maintaining and updating the audit program checklists, information package and audit report template\nConsolidating and producing a master internal/supplier audit plan and reviewing it with GQMs regularly to maintain robust records of any changes and cancellations\nAssisting the GQAMG in preparation of the ISARP matrix, yearly schedule, checklist creation etc\nAssisting the GQAMG with the biennial IATA Operational Safety Audit. This includes the ownership and assessment of operational activities against relevant ISARPs, briefings of ground operations teams, production of the conformance report for CGO & GRH disciplines\nAssisting with logistical support for the IOSA and annual external audit of GSORM\nMonitoring all audit program schedules, status, sending a survey to auditees after audit completion, report preparation and sign off process, including report follow-up with GQM and HGQ\nMaintaining the dashboard of the audit programs\nManaging the new joiner learning path, inclusive of preparing and delivering the Provisional Auditor briefing kit, onsite familiarization and recurrent training package for all applicable audit programs, and ensuring the completeness of the training records of all certified auditors\nPerforming duties of a Lead Auditor and/or Auditor in all applicable audit programs\nAssisting the GQAMG with Continuous Monitoring Inspection Checklist management, i-Auditor system management and oversight of contracted supplier and (Safety Culture)\nAssisting HGQ to prepare the annual Air Safety Review Committee and Management Review presentations\nProviding valuable input to different safety groups i.e. JSWG, RSWG and LCGW.\nAssisting with internal quality educational/training programs to promote quality systems awareness throughout the company\nPreparing, updating and managing the Quality Briefings and Quality Deliverables reporting to all relevant senior management\nAssisting HGQ in coordination and record keeping of the Quality Meeting, agenda preparation, annual kick-off meeting, and special purpose meetings, coordination of presenters and contributors and meeting record keeping\nAssisting in the preparation and maintenance of all Air Operator Certificate documentation and communication with HKCAD\nMaintaining, and ensuring the regular review by senior management of the Operations and Management Services Agreements and associated appendices between CPA, AHK and HKE\nMaintaining the GSORM Quality Internal SharePoint site and ensuring site managers update and maintain content for \u2018The Hub\u2019 (intranet) page of GSORM Quality\n\nAudit Database\n\nMaintain, support, and update the audit database to ensure that it is accurate at all times\nConsolidate and analyse audit database user feedback to provide to the database supplier (Rolls-Royce)\nAssist to conduct User Acceptance Test for upgrades to the audit database\n\nGeneral Tasks\n\nAssist the GQMG and GQAMG to manage the ground quality team.\nRepresent the Company and/or Department at relevant meetings in a professional and loyal manner\nAssist in the response to a crisis involving Cathay Pacific as a member of the Care Team\nDevelop and maintain an effective relationship with the Group Quality team, extended team members, and ground operations departments, including participation in departmental management meetings\nProvide input to HGQ in relation to budgeting for Consolidated Port Audits and related matters\nDeputize for the GQAMG as required\nExtensive duty travel required\nRequirements\n\n\nEducation qualifications\n\nHKDSE: Minimum Level 2 or equivalent in 5 NSS subjects including English, or HKCEE: Minimum Grade E in 5 HKCEE subjects (Including level 2 or above in English Language).\nTertiary education or equivalent.\n\nProfessional qualifications\n\nLead Auditor qualifications.\nDangerous Goods Awareness.\n\n\u00a0Experiences\n\n3-5 years operational experience in the airline industry, preferably in either Engineering, Flight Operations, Inflight Services, Ground Operations, or Cargo Operations.\n1-3 years in a management or supervisory role.\nAdequate and appropriate auditing or quality systems experience.\n\nJob related knowledge\n\nUnderstanding of airline ground, cargo and flight operations.\nCare Team training.\n\nSkills and language requirements\n\nExcellent command of both spoken and written English.\nInterpersonal and communication skills.\nStrong problem solving and analytical skills.\nData- and process-literate.\nComputer literate - Microsoft Office.\nApplication deadline: 27 January 2022\n\n\n\nCathay Pacific is an Equal Opportunities Employer. Personal data provided by job applicants will be used strictly in accordance with our personal data policy and for recruitment purposes only. Candidates not notified within eight weeks may consider their application unsuccessful. All related information will be kept in our file for up to 24 months. A copy of our Personal Information Collection Statement will be provided upon request by contacting our Data Protection Officer.\n\nPlease note that with effect from 1 December 2021, all employees must be vaccinated in order to access Cathay City and all other Cathay Group Company premises in Hong Kong. Consideration will be given to those who are unable to get vaccinated for valid medical reasons.", "employment_types": ["Full Time", "Permanent"], "selling_points": ["3-5 years operational experience", "Quality assurance across the ground operations", "Travel Benefits, 5-day work, Medical Benefits"], "locations": ["Lantau Island"], "categories": ["Transportation & Logistics", "Aerospace", "Freight Forwarding", "Others", "Security / Safety Control"], "post_time": "2022-01-13T06:18:49Z", "salary": {"currency": null, "max": null, "min": null, "period": "monthly", "term": null}, "salary_visible": false, "title_keywords": ["assistant manager"], "responsibilities": ["schedules", "operations", "budgeting", "quality", "audit", "communication", "regular review", "maintain", "plan", "database", "senior management", "management review", "maintaining", "teams", "presentations", "develop", "schedule", "report", "reporting", "management", "upgrades", "monitoring", "review", "inspection", "continuous monitoring", "documentation", "audits", "maintenance", "systems", "coordination", "analyse"], "requirements": {"degrees": ["hkdse"], "majors": [], "languages": ["english"], "language_level": ["excellent"], "hard_skills": ["microsoft office", "professional qualifications", "airline", "analytical skills", "problem solving"], "soft_skills": ["problem solving and analytical skills", "communication skills", "interpersonal"], "languages_combined": [{"language": "english", "language_level": ["excellent"]}]}, "experience_required": {"duration": ["3-5 years"], "field": ["engineering"]}}, {"job_id": "100003009016935", "location_code": "hk", "company": "Hong Kong Business Aviation Centre Ltd", "job_title": "\u9ad8\u7d1a\u822a\u7dda\u670d\u52d9\u6280\u8853\u54e1  (Senior Line Service Technician) /  \u822a\u7dda\u670d\u52d9\u6280\u8853\u54e1  ( Line Service Technician)", "description": "\u8077\u8cac\n\n\u00a0 \u00a0 \u00a0 \u00a0 \u00a0\u70ba\u62b5\u6e2f/\u96e2\u6e2f\u822a\u73ed\u63d0\u4f9b\u670d\u52d9\n\u00a0 \u00a0 \u00a0 \u00a0 \u00a0\u65bc\u505c\u6a5f\u576a\u548c\u6a5f\u5eab\u57f7\u884c\u98db\u6a5f\u505c\u6cca\u8abf\u52d5\u3001\u62d6\u884c\u548c\u5f15\u9818\u5de5\u4f5c\n\u00a0 \u00a0 \u00a0 \u00a0 \u00a0\u8ca0\u8cac\u70ba\u98db\u6a5f\u52a0\u6cb9\u3001\u00a0\u88dc\u5145\u98df\u6c34\u3001\u88dd\u5378\u884c\u674e\u3001\u00a0\u5916\u7f6e\u96fb\u6e90\u63a5\u99c1\u548c\u64cd\u4f5c\u5730\u52e4\u8a2d\u5099\n\u00a0 \u00a0 \u00a0 \u00a0 \u00a0\u70ba\u98db\u6a5f\u9032\u884c\u57fa\u672c\u6aa2\u67e5\u5305\u62ec\u8033\u6a5f\u901a\u8a0a\u5c0d\u8a71\u53ca\u98db\u6a5f\u6a5f\u8eab\u640d\u58de\u6aa2\u67e5\n\u00a0 \u00a0 \u00a0 \u00a0 \u00a0\u8a18\u9304\u71c3\u6599\u6578\u91cf\u4e26\u8655\u7406\u5de5\u4f5c\n\u5165\u8077\u8981\u6c42\n\n\u00a0 \u00a0 \u00a0 \u00a0 \u00a0\u4e2d\u4e94\u6216\u4ee5\u4e0a\u7a0b\u5ea6\u53ca\u4e94\u5e74\u76f8\u95dc\u5de5\u4f5c\u7d93\u9a57\n\u00a0 \u00a0 \u00a0 \u00a0 \u00a0\u5fc5\u9808\u6301\u6709\u6709\u6548\u9999\u6e2f\u99d5\u99db\u57f7\u7167\u7b2c1,2\u00a0\u985e\u53ca\u826f\u597d\u99d5\u99db\u7d00\u9304;\u00a0\u53e6\u6301\u6709\u99d5\u99db\u57f7\u7167\u7b2c18, 19\u985e\u66f4\u4f73\n\u00a0 \u00a0 \u00a0 \u00a0 \u00a0\u80fd\u64cd\u7c21\u55ae\u82f1\u8a9e\u53ca\u666e\u901a\u8a71\n\u00a0 \u00a0 \u00a0 \u00a0 \u00a0\u52e4\u596e\u5b88\u6642\u00a0\u3001\u5177\u8cac\u4efb\u5fc3\u548c\u826f\u597d\u5718\u968a\u7cbe\u795e\n\u00a0 \u00a0 \u00a0 \u00a0 \u00a0\u9700\u6236\u5916\u5de5\u4f5c(\u6a5f\u5834\u505c\u6a5f\u576a)\u00a0\u53ca\u8f2a\u73ed(\u65e9\u3001\u4e2d\u53ca\u901a\u5bb5\u73ed)\n\u00a0 \u00a0 \u00a0 \u00a0 \u00a0\u7d93\u9a57\u8f03\u6dfa\u8005\u5c07\u8003\u616e\u70ba\u00a0\"\u822a\u7dda\u670d\u52d9\u6280\u8853\u54e1\u201d\n\n\u5de5\u4f5c\u5730\u9ede:\u00a0\u6a5f\u5834\u7bc4\u570d\n\n\u672c\u516c\u53f8\u63d0\u4f9b\u5b8c\u5584\u798f\u5229\u5305\u62ec\u4e94\u5929\u5de5\u4f5c\u3001\u751f\u65e5\u5047\u671f\u3001\u5e74\u5c3e\u82b1\u7d05\u3001\u914c\u60c5\u916c\u91d1\u3001\u4ea4\u901a\u6d25\u8cbc\u3001\u7259\u79d1\u53ca\u91ab\u7642\u798f\u5229\u3002\u672c\u516c\u53f8\u9075\u5b88\u516c\u5e73\u5c31\u696d\u6a5f\u6703\u539f\u5247\uff0c\u6b61\u8fce\u6240\u6709\u5408\u8cc7\u683c\u4eba\u58eb\u7533\u8acb\u3002\u7533\u8acb\u4eba\u6240\u63d0\u4f9b\u7684\u8cc7\u6599\uff0c\u6703\u88ab\u4fdd\u5bc6\u4e26\u53ea\u4f9b\u62db\u8058\u4e4b\u7528\u3002\n\nJob Duties:\n\nProvide aircraft arrival / departure routine services\nHandle aircraft refuelling, aircraft towing in both apron and hangar, lavatory service, potable water supply service, luggage handling, external power supply and ground equipment\nPerform daily inspection and routine check on GSE\nProvide driving support for operational needs\nAct as headset man and perform walk around check of inbound and outbound flight movements\nHandle aircraft fuelling\u00a0operations and associated documentations and records\nResponsible for basic data input in HKBAC system\nPerform other duties as assigned by Superior\n\u00a0\u00a0Requirements:\n\nForm 5 or above with minimum 5 years\u2019 relevant experience\nMust hold a valid Hong Kong Driving License Class 1 and 2, and holding a valid Hong Kong Driving License Class 18 Class 19 is definitely an advantage\nGood command of both spoken and written English and Chinese\nShift duty is required\nCandidate with less experience will be considered as\u00a0Line Service Technician\nJob Location: Airport Area\n\n\nWe offer attractive remuneration package including: 5-day work, year-end bonus, discretionary bonus, transportation allowance, birthday leave, dental and medical coverage.\n\nInterested parties please forward a copy of full CV with expected salary to The Human Resources Department by fax 2215 3900 or by\u00a0clicking \"Apply now\".\n\nWe are an equal opportunity employer and welcome applications from all qualified candidates. All information received will be kept in strict confidence and for recruitment purpose only. Applicants not hearing from us within 4 weeks may consider their application unsuccessful.", "employment_types": ["Full Time", "Permanent"], "selling_points": ["\u65bc\u505c\u6a5f\u576a\u548c\u6a5f\u5eab\u57f7\u884c\u98db\u6a5f\u505c\u6cca\u8abf\u52d5\u3001\u62d6\u884c\u548c\u5f15\u9818\u5de5\u4f5c", "\u63d0\u4f9b\u5730\u52e4\u670d\u52d9\u4f8b\u5982\u70ba\u98db\u6a5f\u52a0\u6cb9\u3001\u885b\u751f\u670d\u52d9\u3001 \u88dc\u5145\u98df\u6c34\u3001\u88dd\u5378\u884c\u674e\u3001 \u5916\u7f6e\u96fb\u6e90\u63a5\u99c1\u548c\u64cd\u4f5c\u5730\u52e4\u8a2d\u5099", "\u4e2d\u4e94\u6216\u4ee5\u4e0a\u7a0b\u5ea6\u53ca\u4e94\u5e74\u76f8\u95dc\u5de5\u4f5c\u7d93\u9a57"], "locations": ["Airport Area"], "categories": ["Transportation & Logistics", "Aerospace", "Aviation Services", "Others"], "post_time": "2022-01-03T10:09:22Z", "salary": {"currency": null, "max": null, "min": null, "period": "monthly", "term": null}, "salary_visible": false, "title_keywords": ["technician"], "responsibilities": ["operations", "perform other duties", "data input", "inspection"], "requirements": {"degrees": ["form 5 or above"], "majors": [], "languages": ["english", "chinese"], "language_level": ["good command"], "hard_skills": [], "soft_skills": [], "languages_combined": [{"language": "english", "language_level": ["good command"]}, {"language": "chinese", "language_level": ["good command"]}]}, "experience_required": {"duration": ["minimum 5 years"], "field": ["relevant experience"]}}, {"job_id": "100003009056698", "location_code": "hk", "company": "BAA Jet Management Ltd", "job_title": "Cabin Attendant (Hong Kong Based)", "description": "Key responsibility:\n\nPerform cabin crew duty\nOrganize catering and aircraft supplies\nBe proficient in aircraft safety equipment\nProvide emergency assistance to passengers when necessary\nCoordinate with other flight crew members\nBased in Hong Kong (stable and long-term residence in Mainland before free transit of borders is a must)\n\nRequirements:\n\nTertiary education with experience in international flight services\nExcellent command of spoken & written English & Chinese, including Putonghua\nPresentable, professional and resourceful, self-motivated and be able to initiate and finalize projects independently\nFlexible and able to work under pressure\nGood team player with excellent communication & interpersonal skills\n\nInterested parties please email full resume with a recent photo, current & expected salary and availability\u00a0by clicking \"Apply Now\".\u00a0 All applications will be treated in strict confidence.\n\nWe are an equal opportunity employer. Data held by the company relating to employment applications will be kept confidential and used only for processing applications. Applicants who are not contacted within one month may consider their application unsuccessful. The company may retain their applications for a maximum period of 6-month and may refer suitable applicants to other vacancies within the company.", "employment_types": ["Full Time", "Permanent"], "selling_points": ["Perform cabin crew duty", "Organize catering and aircraft supplies", "Coordinate with other flight crew members"], "locations": ["Not Specified"], "categories": ["Transportation & Logistics", "Aerospace", "Aviation Services"], "post_time": "2022-01-18T05:50:49Z", "salary": {"currency": null, "max": null, "min": null, "period": "monthly", "term": null}, "salary_visible": false, "title_keywords": [], "responsibilities": ["coordinate with", "catering"], "requirements": {"degrees": [], "majors": [], "languages": ["putonghua", "english", "chinese"], "language_level": ["excellent"], "hard_skills": [], "soft_skills": ["flexible", "self-motivated", "independently", "good team player", "resourceful", "presentable", "communication", "interpersonal skills", "work under pressure"], "languages_combined": [{"language": "putonghua", "language_level": ["excellent"]}, {"language": "english", "language_level": ["excellent"]}, {"language": "chinese", "language_level": ["excellent"]}]}, "experience_required": {"duration": [], "field": ["education"]}}, {"job_id": "100003009056022", "location_code": "hk", "company": "PCCW Solutions", "job_title": "Technical Officer - Civil Aviation Engineering- Open For Fresh Graduates", "description": "Technical Officer of Civil Aviation Engineering (Air Traffic Control Systems Operation and Maintenance / Project)\n\nThe Job:\n\nDepartment of Travel and Transportation is looking for Technical Officer(s) in following Civil Aviation Engineering teams:\n\n\u00a0Air Traffic Control Systems Operation and Maintenance Team\n\nAssist in performing technical operations, maintenance/repair for air traffic control (ATC), airport related systems or electronic/communication/IT equipment/systems and its ancillary support facilities\nAssist in planning, organizing, supervising and/or directly carrying out maintenance/repair works of systems/equipment and conducting system review to ensure system reliability and availability\nAssist in or directly and dependently carrying out equipment preventive/corrective maintenance, on-site equipment installation, testing and commissioning, fault diagnosis and repair according to a rectification plan/solution as well as helping one\u2019s supervisor in preparing fault/problem investigation report and/or procurement plan for spare parts or maintenance/repair services\nAssist in coordination with various internal and external parties such as various government departments, local or overseas airport authority, vendors/suppliers, sub-contractors and so on for operations and maintenance works\n\n\u00a0Project Team\n\nAssist in performing project work for air traffic control (ATC), airport related systems or electronic/communication/IT equipment/systems and its ancillary support facilities\nAssist in preparing solution for project tender bidding and implementation of project including drafting design submission, requirements for materials/service procurement, supervision/monitoring of sub-contractors installation works, preparation of test plan/report, conduct testing and commissioning\nAssist in project progress monitoring, financial monitoring and control of projects to ensure satisfactory completion of project within budget and schedule and help one\u2019s supervisor to prepare project/works progress reports for submission or logistics support\nAssist in coordination with various internal and external parties such as various government departments, local or overseas airport authority, vendors/suppliers, sub-contractors and so on for operations and maintenance works\n\nTeam allocation is based on qualifications, experience and personal attributes of the appointee.\n\nThe Person\n\nCertificate or above in Electronics/Electrical/Telecommunication/Computer/ Software/Information/e-logistics/Industrial Engineering or other related disciplines\nPossession of training record of Air Traffic Safety Electronic Personnel/Professional (ATSEP) training course is an advantage\nPossessing track record of relevant hands-on working experience in system design, building, testing and commissioning, operations and maintenance in mission critical service or project is highly preferable\nGood team player, customer-focused mindset, open-mindedness, proactive, result/service oriented, total quality management and safety concept with strong logical analytical, communication and interpersonal skills\nAble to work independently under pressure with strong desire and commitment to deliver high quality of works in short notice\nGood spoken and written English is a must. Knowledge of Putonghua is preferred\nFresh graduates will also be considered\nPossessing driving license is an advantage\nMay work in shift duty and/or irregular hours including overnight, Saturdays, Sundays and public holidays and/or outdoor as required", "employment_types": ["Full Time"], "selling_points": [], "locations": ["Tung Chung"], "categories": ["Transportation & Logistics", "Aerospace", "Engineering", "Electrical / Electronics", "Telecommunication / Wireless / Radio"], "post_time": "2022-01-18T03:11:54Z", "salary": {"currency": null, "max": null, "min": null, "period": "monthly", "term": null}, "salary_visible": false, "title_keywords": ["technical officer"], "responsibilities": ["supervising", "operations", "coordination with", "internal and external parties", "budget", "design", "communication", "plan", "control", "progress reports", "teams", "implementation", "project progress", "testing", "logistics", "schedule", "tender", "report", "installation", "commissioning", "review", "rectification", "monitoring", "investigation", "maintenance", "systems", "repair", "it equipment", "planning"], "requirements": {"degrees": ["certificate"], "majors": ["related disciplines", "engineering"], "languages": ["putonghua", "english"], "language_level": ["good"], "hard_skills": ["system design", "maintenance"], "soft_skills": ["good team player", "work independently", "under pressure", "customer-focused mindset", "hands-on", "communication and interpersonal skills", "proactive"], "languages_combined": [{"language": "putonghua", "language_level": []}, {"language": "english", "language_level": ["good"]}]}, "experience_required": {"duration": [], "field": ["system design", "maintenance", "testing"]}}, {"job_id": "100003009051950", "location_code": "hk", "company": "Howmet (Hong Kong) Limited", "job_title": "Quality Inspector - Fasteners for Aerospace industry", "description": "Job responsibilities:\n-\u00a0A variety of Quality checks; Testing and Release of products within the Inspection framework by the Products received.\u00a0 Product shipments, and Products returned from customers;\n- Use of a company issued inspection control stamp to release or quarantine products;\n-\u00a0Requests all missing or incorrect documents from Suppliers and Manufacturers for products received and pursue the problem until resolution has been achieved;\n- Scanning and keywork filing of Certificates, Drawings, etc. in Docuware;\n-\u00a0Loading delivery documents in the system and archiving.\u00a0 Management and custodial oversight of the Documentation Archive;\n- Manage Quality documentation and support other generic office/warehouse duties.\n\nJob requirements:\n-\u00a0Technical trade school and/or Commercial experience in the metal sector and/or experience in Quality control, able to distinguish between standard and special constructive products.\n- The Position candidate will keep up-to-date technical knowledge and education requirements.\n\n\nLanguage & skills:\n- Language: Cantonese, English, Mandarin\n- Computer: MS Office", "employment_types": ["Full Time", "Permanent"], "selling_points": ["5-day work", "medical for employee & the dependents", "discretionary performance bonus"], "locations": ["Tsing Yi"], "categories": ["Transportation & Logistics", "Aerospace"], "post_time": "2022-01-17T01:36:52Z", "salary": {"currency": null, "max": null, "min": null, "period": "monthly", "term": null}, "salary_visible": false, "title_keywords": [], "responsibilities": ["scanning", "control", "management", "quality", "inspection", "resolution", "testing", "drawings", "documentation"], "requirements": {"degrees": [], "majors": [], "languages": ["cantonese", "english", "mandarin"], "language_level": [], "hard_skills": ["ms office"], "soft_skills": ["constructive"], "languages_combined": [{"language": "cantonese", "language_level": []}, {"language": "english", "language_level": []}, {"language": "mandarin", "language_level": []}]}, "experience_required": {"duration": [], "field": ["commercial", "quality control"]}}, {"job_id": "100003009018369", "location_code": "hk", "company": "Topcast Aviation Services Limited", "job_title": "Production Planner", "description": "Responsibilities:\n\nAble to utilize available resources to achieve the maximum output within the available maintenance slot period;\nCoordinate Maintenance activity planning actions in support of production plans with other concerned activities;\nSchedule and conduct all Maintenance scheduling meetings;\nManage and control various man hour booking, cost, material, trend analysis, etc.;\nDistribute Daily, Weekly and Monthly production KPI reports to authorized users;\nReview training schedule to minimize impact on production;\nEnsure appropriate communication throughout the delivery of the Maintenance Activities;\nCarry out any other duties that are assigned by Operations Manager\n\nRequirements:\n\nAt least 5 years experience in Aviation MRO environment. Familiarity with resource and material planning;\nExcellent communication skills and ability to communicate info and data to all levels in the organization;\nAbility to think analytically and solve problems efficiently and effectively;\nAbility to work under intense pressure in MRO environment;\nExtensive knowledge of monitoring work schedules and creating backup plans;\nKnowledge of PC and Microsoft office applications. MS Project skill is essential;\nAbility to communicate in English both orally and in writing", "employment_types": ["Full Time", "Permanent"], "selling_points": ["Experience in Aviation MRO industry", "Familiarity with resource and material planning", "5 days work, Basic Salary + Double pay + Bonus"], "locations": ["Shatin Area"], "categories": ["Transportation & Logistics", "Aerospace", "Aviation Services", "Engineering", "Electrical / Electronics"], "post_time": "2022-01-04T03:27:19Z", "salary": {"currency": null, "max": null, "min": null, "period": "monthly", "term": null}, "salary_visible": false, "title_keywords": [], "responsibilities": ["any other duties", "control", "cost", "maintenance", "operations", "analysis", "review", "coordinate", "scheduling", "communication", "reports", "schedule", "booking", "plans", "planning"], "requirements": {"degrees": [], "majors": [], "languages": ["english"], "language_level": [], "hard_skills": ["pc", "microsoft office"], "soft_skills": ["communication skills", "solve problems", "orally", "extensive"], "languages_combined": [{"language": "english", "language_level": []}]}, "experience_required": {"duration": ["at least 5 years"], "field": []}}]