[{"job_id": "100003009053052", "location_code": "hk", "company": "Relosmart Limited", "job_title": "Customer Service Representative (Removals/Shipping/Logistics)", "description": "We are looking for intelligent, enthusiastic, caring individuals to fill the following vacancy:\u00a0\n\nCustomer Service Representative (Hong Kong)\n\nWorking with our young, multinational team, you will be a primary point of contact for our clients, assisting & coordinating\u00a0 every aspect of the services that we provide to them. This includes handling of shipping documents,\u00a0execute new bookings, communication with existing and new clients.\n\nWhat we seek\n\nBoth English & Cantonese must be spoken to a \u201cmother tongue\u201d level\nOne year of work experience necessary within administration and/or shipping backgroundOverseas graduate a plus\n\nMonthly salary HK$15,000 to HK$19,000\n\nWhat we offer\n\nWe\u2019re wired a bit differently and we pursue ambitious goals in an intriguing environment. We love a dynamic corporate culture with flat hierarchies. We offer a start-up atmosphere with excellent development opportunities. Are you enthusiastic about tackling new challenges that suit your personality and abilities? Perfect! Because as a\u00a0Customer Service Representative\u00a0working full time in our office in Hong Kong, you\u2019re able to actively shape our future success. And it's important to know: We hire for attitude and train for skills!\n\nPlease send your resume, salary expectation and availability to enquiry at relosmart.asia", "employment_types": ["Full Time", "Permanent", "Contract"], "selling_points": ["Customer Service", "Shipping Moving Logistic", "Relocation Call Center"], "locations": ["Kwun Tong"], "categories": ["Sales, CS & Business Devpt", "Customer Service - Manager", "Transportation & Logistics", "Freight Forwarding", "Shipping"], "post_time": "2022-01-17T16:20:58Z", "salary": {"currency": "HKD", "max": 19999, "min": 14000, "period": "monthly", "term": null}, "salary_visible": true, "title_keywords": ["shipping", "logistics", "customer service representative"], "responsibilities": ["customer service"], "requirements": {"degrees": [], "majors": [], "languages": [], "language_level": [], "hard_skills": [], "soft_skills": ["customer service", "enthusiastic"], "languages_combined": []}, "experience_required": {"duration": [], "field": []}}, {"job_id": "100003009055730", "location_code": "hk", "company": "NVD Asia Logistics Hong Kong Limited", "job_title": "Operation - Sea Freight (5 Day Work)", "description": "We are a young and dynamic freight forwarder company located in Wan Chai looking for\u00a0high-calibre people with enthusiasm to join us.\n\nJob Duties:\n\n-\u00a0\u00a0\u00a0\u00a0\u00a0\u00a0\u00a0\u00a0\u00a0 Handle and follow up customer inquiries and shipment booking\n\n-\u00a0\u00a0\u00a0\u00a0\u00a0\u00a0\u00a0\u00a0\u00a0 Handle full set of Sea-freight documents\n\n-\u00a0\u00a0\u00a0\u00a0\u00a0\u00a0\u00a0\u00a0\u00a0 Coordinate with overseas agents regarding cargo status and quotation.\n\n-\u00a0\u00a0\u00a0\u00a0\u00a0\u00a0\u00a0\u00a0\u00a0 Input Operation System data entry & filing\n\n-\u00a0\u00a0\u00a0\u00a0\u00a0\u00a0\u00a0\u00a0\u00a0 Perform other duties as assigned by Managers\n\n-\u00a0\u00a0\u00a0\u00a0\u00a0\u00a0\u00a0\u00a0\u00a0 Other ad-hoc tasks\n\nRequirements:\n\n-\u00a0\u00a0\u00a0\u00a0\u00a0\u00a0\u00a0\u00a0\u00a0 Minimum 3 years\u2019 operation experience in Freight Forwarding Industry\n\n-\u00a0\u00a0\u00a0\u00a0\u00a0\u00a0\u00a0\u00a0\u00a0 Good communication and interpersonal skills\n\n-\u00a0\u00a0\u00a0\u00a0\u00a0\u00a0\u00a0\u00a0\u00a0 Good command of written and spoken English and Mandarin.\n\n-\u00a0\u00a0\u00a0\u00a0\u00a0\u00a0\u00a0\u00a0\u00a0 Proficient in computer (Microsoft Office) skills.\n\n-\u00a0\u00a0\u00a0\u00a0\u00a0\u00a0\u00a0\u00a0\u00a0 Able to work independently and work under tight deadlines.\n\n-\u00a0\u00a0\u00a0\u00a0\u00a0\u00a0\u00a0\u00a0\u00a0 Immediately available is preferable.", "employment_types": ["Full Time"], "selling_points": ["Young Team", "5 day work", "Double paid"], "locations": ["Wan Chai"], "categories": ["Transportation & Logistics", "Freight Forwarding"], "post_time": "2022-01-18T02:53:57Z", "salary": {"currency": null, "max": null, "min": null, "period": "monthly", "term": null}, "salary_visible": false, "title_keywords": [], "responsibilities": ["perform other duties", "customer inquiries", "ad-hoc tasks", "quotation", "coordinate with", "system data", "booking"], "requirements": {"degrees": [], "majors": [], "languages": ["english", "mandarin"], "language_level": ["good command"], "hard_skills": ["microsoft office"], "soft_skills": ["work independently", "communication and interpersonal skills"], "languages_combined": [{"language": "english", "language_level": ["good command"]}, {"language": "mandarin", "language_level": ["good command"]}]}, "experience_required": {"duration": ["minimum 3 years"], "field": ["operation"]}}, {"job_id": "100003009052931", "location_code": "hk", "company": "Shipco Transport (HK) Ltd", "job_title": "PNL Specialists", "description": "Job Responsibilities:-\n\nResponse to customer\nHandling inbound/outbound Ocean Freight shipment and planning\nManage Ocean Freight shipment data and ensure data integrity\nCommunicate with other branches/ origin offices\nRequirements:-\n\nFluent in English and Chinese\nMinimum 2 years relevant working experience\nFluent in English and Mandarin, both written and spoken\nImmediate available is\u00a0highly preferred\n\n\nPlease send full resume with present & expected salary for consideration.", "employment_types": ["Full Time", "Permanent"], "selling_points": ["Manage, assist for import and export department", "DSE or above", "At least 2 years relevant operations experience"], "locations": ["Not Specified"], "categories": ["Transportation & Logistics", "Others", "Freight Forwarding", "Shipping"], "post_time": "2022-01-17T04:34:50Z", "salary": {"currency": null, "max": null, "min": null, "period": "monthly", "term": null}, "salary_visible": false, "title_keywords": [], "responsibilities": ["communicate with", "data", "planning"], "requirements": {"degrees": [], "majors": [], "languages": ["english", "chinese", "mandarin"], "language_level": ["fluent"], "hard_skills": [], "soft_skills": [], "languages_combined": [{"language": "english", "language_level": ["fluent", "fluent"]}, {"language": "chinese", "language_level": ["fluent", "fluent"]}, {"language": "mandarin", "language_level": ["fluent", "fluent"]}]}, "experience_required": {"duration": ["minimum 2 years"], "field": ["relevant working experience"]}}, {"job_id": "100003009053969", "location_code": "hk", "company": "Global Airlift Solutions (Asia) Limited", "job_title": "Charter & Emergency Manager / Executive, Asia Pacific", "description": "Job Description\n\nExplore new business opportunities and generate sales leads, formulate business solution per the account requirements in Hong Kong & South China\nTo achieve the individual new win business target in term of volume, sales and net revenue\nIdentify, develop and build business network and relationship with all customer\u2019s\u00a0 contact levels to retain and penetrate into the account\nCoordinate with internal and external stakeholders to drive for success on business tenders and collect reference business intelligent for revaluation.\nTake lead of business project or campaign , to formulate business strategy, execution and monitoring to deliver the expected result\u00a0\u00a0\u00a0\nMaintain healthy pipeline in sales system to ensure new win target can be achieved\n\nJob Requirement\n\nDegree holder with at least 3 years' experience in logistics field, prefer field sales experience\nStrong sales drive\nProfessional\u00a0 qualification\u00a0 on DG, clearance or other expertise in logistics is an advantage\nGood command of spoken and written Chinese and English, additional language is a plus\nExcellent communication and interpersonal skills\nAggressive, out-going, enjoy face-to-face connection\n\nCompany Benefits\n\nSales incentive program\nDouble pay\nFive-day work week\nFree shuttle bus\nMedical insurance\n\nAttractive remuneration package will be given to the right candidates.", "employment_types": ["Full Time"], "selling_points": ["Salary negotiable, depends on experience", "Flexible, ready to work in shifts and weekends", "Good in English, Teamwork"], "locations": ["Tsuen Wan Area"], "categories": ["Transportation & Logistics", "Aviation Services", "Freight Forwarding", "Supply Chain"], "post_time": "2022-01-17T07:52:30Z", "salary": {"currency": null, "max": null, "min": null, "period": "monthly", "term": null}, "salary_visible": false, "title_keywords": ["manager", "executive"], "responsibilities": ["explore new business opportunities", "monitoring", "coordinate with", "develop", "maintain", "generate sales leads", "contact"], "requirements": {"degrees": ["degree holder"], "majors": [], "languages": ["english", "chinese"], "language_level": ["good command"], "hard_skills": ["plus"], "soft_skills": ["communication and interpersonal skills"], "languages_combined": [{"language": "english", "language_level": ["good command"]}, {"language": "chinese", "language_level": ["good command"]}]}, "experience_required": {"duration": ["at least 3 years"], "field": ["logistics"]}}, {"job_id": "100003009053683", "location_code": "hk", "company": "Atlantx Partners Limited", "job_title": "LCL Product Manager", "description": "Job description and responsibilities:\n\n\nSales & Marketing Activities\u00a0:\u00a0\u00a0\nMaintain active business relationship with potential and existing carriers and service providers\nIntroduce our service (Cargo Charter / On Board Courier / Critical Care Solutions - Express Airfreight) to customers / freight forwarders\nReceive visitors\u00a0\nProcess Air Cargo Charter and Emergency Requests :\nCharter quotations to GAS customers and GAS stations,\u00a0Issue contracts and perform customer order until completion\nResponsible to negotiate best possible terms and conditions with the suppliers to provide best in class emergency transport solutions (On Board Couriers and Critical Care Solutions, Express Airfreight)\nCommunicates new business opportunities\u00a0internally and externally, and the cooperation with (new) service providers.\nArrange cargo charter flight / Express Airfreight / On Board Courier operation and billing invoices / documentation\u00a0\n\u00a0Administration:\nResponsible for the invoicing of the handled jobs and accruals of the incoming jobs. Has the financial responsibility for own files.\n\u00a0Team Work:\nAssure the best possible team spirit within the team.\nFollow the procedures set on the team and effectively communication at all times with all parties involved during the charter and OBC operations.\n\nJob requirements:\nTeam player, Results-driven work style,\u00a0Be Fearless, Aggressive, Ambitious\nCreative problem solving skills / quick thinking / Multi-Tasking /\u00a0negotiation, communication & decision making skills\u00a0\nAbility to work with a flexible schedule, including morning / night shift and weekends, to adapt and grow in a changing, fast-paced work environment.\nGood verbal and written knowledge of English and one or more local language(s), fluent in Korean or Japanese Speaking is an advantage\nSeveral years of Airfreight Forwarding experience with an Airlines, Broker or Freight Forwarder is required\u00a0\nBasic knowledge of MS Office (Word, Excel, Outlook) and flair for IT systems as a user\n\nInterested parties please send full resume with experience, qualification with expected salary to Unit 10, 17/F, Grand City Plaza, Tsuen Wan, Hong Kong, fax via +852 3188 9719, or click \"Apply Now\" to apply\n\nPersonal data collected will be treated as strictly confidential and used for recruitment purpose only.\u00a0\n\nCandidate\u00a0with less experience will be considered as Charter & Emergency Executive, Asia Pacific\u00a0", "employment_types": ["Full Time"], "selling_points": ["LCL Products & Strategies Initiatives", "Implementation of Sales Strategy", "Dynamic & Stable Environment"], "locations": ["Central & Western Area"], "categories": ["Transportation & Logistics", "Freight Forwarding", "Shipping", "Supply Chain"], "post_time": "2022-01-17T07:45:06Z", "salary": {"currency": null, "max": null, "min": null, "period": "monthly", "term": null}, "salary_visible": false, "title_keywords": ["product manager"], "responsibilities": ["issue contracts", "invoices", "operations", "business opportunities", "procedures", "invoicing", "communication", "maintain", "sales & marketing activities", "documentation", "administration"], "requirements": {"degrees": [], "majors": [], "languages": ["japanese", "english", "korean"], "language_level": ["advantage", "fluent", "good"], "hard_skills": ["excel", "basic", "word", "outlook", "airlines", "problem solving skills", "ms office"], "soft_skills": ["flexible", "decision making skills", "negotiation", "communication", "multi-tasking", "problem solving skills", "team player", "creative", "driven"], "languages_combined": [{"language": "japanese", "language_level": ["advantage", "good"]}, {"language": "english", "language_level": ["advantage", "good"]}, {"language": "korean", "language_level": ["fluent", "advantage", "good"]}]}, "experience_required": {"duration": [], "field": []}}, {"job_id": "100003009055324", "location_code": "hk", "company": "Sinotrans (HK) Warehousing Limited", "job_title": "Customer Services Executive (Logistic/Freight Forwarding)", "description": "Our client, a Hong Kong based freight forwarding company with global offices is now seeking for a LCL product specialist to join their dynamic team\u00a0\n\n\n\nJob Responsibilities\n\nIdentify LCL Product opportunities and deliver Strategy for Group LCL Product\nAnalyze market opportunities and develop new product solutions and market entry opportunities aligned with Corporate LCL Strategy\nProduct set-up and execution of SOP\nBuild bridges between Product Development, Operations and Sales and Customer Experience Management\nNegotiate and benchmark vendor rates, participate in RFQs, work closely on procurement of LCL service from globally approved partners.\n\nRequirements\n\nBachelor or higher diploma in any discipline (Logistic/Supply Chain) would be a plus\nMinimum 8 years of of shipping industry experience and LCL product\nSolid experiences in Ocean Freights operations and customer service in NVOCC business, solution design & PL ownership\nWell written and spoken English is a\u00a0MUST, also fluent in Mandarin and Cantonese\nCompetent communicator who could work well under-pressure, meet deadline, be proactive and attention to details\nPlease email CV to\u00a0cs @ atlantxpartners.com", "employment_types": ["Full Time"], "selling_points": ["CS experience in Logistic/freight forwarding ind", "Provide quality services both internal/external", "Double Pay w/ competitive remuneration package"], "locations": ["Tin Shui Wai"], "categories": ["Sales, CS & Business Devpt", "Customer Service - Supervisor / Officer", "Transportation & Logistics", "Freight Forwarding", "Inventory / Warehousing"], "post_time": "2022-01-18T02:12:03Z", "salary": {"currency": null, "max": null, "min": null, "period": "monthly", "term": null}, "salary_visible": false, "title_keywords": ["executive"], "responsibilities": ["operations", "management", "develop"], "requirements": {"degrees": ["diploma", "bachelor"], "majors": [], "languages": ["cantonese", "english", "mandarin"], "language_level": ["fluent"], "hard_skills": ["plus", "pl"], "soft_skills": ["competent", "customer service", "attention to details", "communicator", "proactive"], "languages_combined": [{"language": "cantonese", "language_level": ["fluent"]}, {"language": "english", "language_level": ["fluent"]}, {"language": "mandarin", "language_level": ["fluent"]}]}, "experience_required": {"duration": ["minimum 8 years"], "field": ["business", "customer service", "shipping industry", "design"]}}, {"job_id": "100003009053272", "location_code": "hk", "company": "Shipco Transport (HK) Ltd", "job_title": "Key Account Assistant", "description": "Job Responsibilities:\u00a0\u00a0\nTo\u00a0handle and follow up enquiries from customers, overseas agents and inner group company\u00a0\nTo collaborate closely with internal and external operations to deliver quality services\nTo\u00a0input data in operating system timely and accurately\n\nJob Requirements:\n\nProficiency in written and spoken English is a must.\nUniversity Graduate or above\n2-3 years relevant working experience in customer service in logistics / freight forwarding industries\nIndependent, responsible, well-organized & able to work under pressure\nProficiency in using MS Office applications\nImmediately available is preferable", "employment_types": ["Full Time", "Permanent"], "selling_points": ["Maintain tariff and pricing in-house", "Serve quotation to customers on both import", "DSE or above in qualification"], "locations": ["Not Specified"], "categories": ["Transportation & Logistics", "Freight Forwarding", "Shipping", "Sales, CS & Business Devpt", "Account Servicing"], "post_time": "2022-01-17T06:38:21Z", "salary": {"currency": null, "max": null, "min": null, "period": "monthly", "term": null}, "salary_visible": false, "title_keywords": ["key account assistant"], "responsibilities": ["collaborate", "operations", "quality", "data"], "requirements": {"degrees": ["university graduate or above"], "majors": [], "languages": ["english"], "language_level": ["proficiency"], "hard_skills": ["ms office"], "soft_skills": ["independent", "responsible", "well-organized", "customer service", "work under pressure"], "languages_combined": [{"language": "english", "language_level": ["proficiency"]}]}, "experience_required": {"duration": ["2-3 years"], "field": ["customer service", "logistics", "relevant working experience"]}}, {"job_id": "100003009053183", "location_code": "hk", "company": "DHL Global Forwarding (Hong Kong) Limited", "job_title": "Air Freight Executive", "description": "Work Location: Kwai Hing\n5.5 days (Saturday long-short week)\n\n\nResponsibilities\nHandle general export/import shipments as per standard operation procedures\nHandle customer booking, enquiries & complaints\nAssist in\u00a0handling cross-trade shipments\nCoordinate with operations and sales departments on shipments and rates respectively\nMaintain\u00a0effective communication with customers and overseas stations to achieve service excellence\n\u00a0Requirements\nForm 7 or above or qualification equivalent to Qualifications Framework (QF).\nPreferably with 3-4 years relevant experience in logistics industry.\u00a0\nGood interpersonal, negotiation and communication skills\nGood command of both written and spoken English and Mandarin\nGood PC operations knowledge, particularly in MS Excel\n\nWe offer attractive remuneration package fringe benefits including\u00a0Banking Holiday,\u00a0Annual Leaves,\u00a0Double Pay, Discretionary Bonus\u00a0&\u00a0Medical Insurance to the right candidate.\n\nApplications will be treated in strict confidence. Please send application with full particulars of qualifications, experience, current and expected salary by clicking the Apply now button or by post to Human Resources Department, 4/F, EDGE, Nos. 30 \u2013 34 Kwai Wing Road, Kwai Chung, New Territories, Hong Kong. \u00a0\n\n\nApplicants not contacted within six weeks may consider their applications unsuccessful.\n\n\nPersonal Information Collection Statement pertaining to Recruitment\n\n\nDHL Global Forwarding (Hong Kong) Limited (\u201cDHL\u201d) is committed to protecting and respecting your privacy in accordance with the Personal Data (Privacy) Ordinance of Hong Kong (the \u201cOrdinance\u201d) and DHL\u2019s Personal Data Protection Policy (the \u201cPolicy\u201d) at http://www.dhl.com.hk/en/legal.html#pdpp\nBy proceeding to respond to this recruitment advertisement you consent that we may use, retain, process, transfer or otherwise handle the personal data that we collect from you for recruitment purposes (including any other purposes directly related thereto) in accordance with the Policy.\n\n\nAll personal data of unsuccessful applicants will be retained for future recruitment purposes for a period of not more than six (6) months, after which such data will be destroyed.\n\n\nYou have the right at any time to make a data access or correction request concerning your personal data held by us. In addition, you may request us to delete your personal data that is no longer required for the relevant purposes which you have given consent. Should you wish to exercise such rights or have any question in relation to your personal data or the Policy, please contact our Human Resources Department.", "employment_types": ["Full Time", "Permanent"], "selling_points": [], "locations": ["Kwai Hing"], "categories": ["Sales, CS & Business Devpt", "Customer Service - Supervisor / Officer", "Transportation & Logistics", "Freight Forwarding"], "post_time": "2022-01-17T07:23:01Z", "salary": {"currency": null, "max": null, "min": null, "period": "monthly", "term": null}, "salary_visible": false, "title_keywords": ["executive"], "responsibilities": [], "requirements": {"degrees": [], "majors": [], "languages": [], "language_level": [], "hard_skills": [], "soft_skills": [], "languages_combined": []}, "experience_required": {"duration": [], "field": []}}, {"job_id": "100003009054690", "location_code": "hk", "company": "Nesta (Hong Kong) Limited", "job_title": "Load Control Officer / Flight Planning Officer / Cargo Service Officer (18-20K, 5days)", "description": "Our client is a world\u2019s premier company specializing in Express Service is now seeking for a high caliber to join their team as Load Control Officer / Flight Planning Officer / Cargo Service Officer.\n\nJOB RESPONSIBILITY\n\nHandle shipment booking enquiries from overseas countries for flight arrangement\nCommunicate with other Hubs and Gateways on real time flight and shipment monitoring\nPerform customer service for network tracing and investigation of shipment\u00a0 issues\nPrepare reports and\u00a0 Unit Load Device (ULD) inventory management\u00a0\n\nJOB REQUIREMENT\n\nDiploma holder or above\n2 years experience in industry of\u00a0transportation, logistics, airlines, airport operations or freight forwarding\u00a0\nGood command of written and spoken English\nGood analytical, telephone manner customer services skills", "employment_types": ["Full Time"], "selling_points": ["MNC Logistic Company with Good Package", "18-20K, 5days", "Airline / Ground Services Experience preferred!!"], "locations": ["Not Specified"], "categories": ["Transportation & Logistics", "Aviation Services", "Freight Forwarding", "Shipping"], "post_time": "2022-01-17T10:35:28Z", "salary": {"currency": null, "max": null, "min": null, "period": "monthly", "term": null}, "salary_visible": false, "title_keywords": ["officer"], "responsibilities": ["communicate with", "monitoring", "investigation", "inventory management", "customer service", "booking", "prepare reports"], "requirements": {"degrees": ["diploma holder"], "majors": [], "languages": ["english"], "language_level": ["good command"], "hard_skills": ["airlines"], "soft_skills": ["telephone manner", "customer services skills"], "languages_combined": [{"language": "english", "language_level": ["good command"]}]}, "experience_required": {"duration": ["2 years"], "field": ["logistics"]}}, {"job_id": "100003009052702", "location_code": "hk", "company": "Headsearch21 Consultancy Ltd", "job_title": "Logistic CS Supervisor (MNC)", "description": "Continuous evaluation and improvement/enhancement of existing operational and\u00a0system \u00a0in attaining the highest level of operations efficiency and integrity.\u00a0\nEnsure the execution of work processes are in accordance with the established SOPs.\nInvestigate fully all non-conformities with root cause analysis, preventive measures\u00a0and follow-up.\nAssist the warehouse operations teams and customer service teams to render high-quality\u00a0service at all times.\nMaintain a good relationships with all business partners, including vendors and contractors.\u00a0\nAssist in management and performance reports preparation and analysis.\nCarry out KPI for the warehouse operations and customer service teams.\nBridging of gaps between management and staff through constant communications\nAssist in planning, execute and review of induction & probation training of new hires\n\nRequirements:\n\n\u00a0\u00a0\u00a0\u00a0\u00a0\u00a0\u00a0\u00a0 2 years or above solid experience in the Air Freight Forwarding/Logistics Industry is preferable\n\u00a0\u00a0\u00a0\u00a0\u00a0\u00a0\u00a0\u00a0 Candidates with the certificate for RAR (Regulated Agent Regime) or DGR (Dangerous good Regulation) is preferred but not essential;\n\u00a0\u00a0\u00a0\u00a0\u00a0\u00a0\u00a0\u00a0 Responsible, mature, detailed mind and good team player\n\u00a0\u00a0\u00a0\u00a0\u00a0\u00a0\u00a0\u00a0 Good spoken and written English & Chinese;\n\u00a0\u00a0\u00a0\u00a0\u00a0\u00a0\u00a0\u00a0 Proficiency in MS Windows, MS Office (Word, Excel, etc.)\n\u00a0\u00a0\u00a0\u00a0\u00a0\u00a0\u00a0\u00a0 Immediate available is highly preferable", "employment_types": ["Full Time", "Permanent"], "selling_points": ["4 years CS exp in Logistic Co. / Forwarder / 3PL", "SAP / WMS system (Prefer)", "Near MTR / Modern Office Design"], "locations": ["Not Specified"], "categories": ["Sales, CS & Business Devpt", "Customer Service - Supervisor / Officer", "Transportation & Logistics", "Freight Forwarding", "Shipping"], "post_time": "2022-01-17T03:45:08Z", "salary": {"currency": "HKD", "max": 19999, "min": 14000, "period": "monthly", "term": null}, "salary_visible": true, "title_keywords": ["supervisor"], "responsibilities": ["management", "performance reports", "air freight", "operations", "analysis", "review", "teams", "quality", "customer service", "maintain", "logistics", "sops", "evaluation", "warehouse operations", "planning"], "requirements": {"degrees": ["certificate"], "majors": [], "languages": ["english", "chinese"], "language_level": ["good"], "hard_skills": ["excel", "ms windows", "analysis", "word", "ms office"], "soft_skills": ["good team player", "responsible", "integrity", "mature", "customer service", "detailed mind"], "languages_combined": [{"language": "english", "language_level": ["good"]}, {"language": "chinese", "language_level": ["good"]}]}, "experience_required": {"duration": ["2 years"], "field": ["logistics industry"]}}, {"job_id": "100003009053586", "location_code": "hk", "company": "We World Express Limited", "job_title": "Senior operation clerk ( General cargo )", "description": "Job Responsibilities\n\nResponsible for Handle full set of import customer service and documentation\nContact co-loader and carrier to obtain shipment arrival and payment\nPrepare documents and payment to exchange the delivery order with co-loader and carrier before the vessel arrives\nResponsible to provide arrival notice, invoice, delivery order to consignee in timely manner\nPrepare monthly customer report and achieve customer KPI\nCoordinate with co-loader and subcontractor for door delivery\nComplete the company and customer KPI within timeframe\n\nJob Requirements\n\nF.5 or DSE or\u00a0 above\nRelevant working experience in sea freight forwarding industry is an advantage\nExperience in handling full set of Ocean Import flow and Cargowise is an advantage\nCandidates with less working experience would also be considered\nGood communication skills and able to work independently under pressure\nGood command in written and spoken English and Mandarin\nProficient in the use of Microsoft Word and Excel\nSelf-motivated and Responsible\u00a0\n\nWe offer attractive remuneration packages to the right candidates. Interested parties, please send your FULL resume with CURRENT and EXPECTED SALARY by clicking \"APPLY NOW\". For further information of our company, please visit our website: http://www.cevalogistics.com.\u00a0\u00a0", "employment_types": ["Full Time"], "selling_points": ["Good spoken and written English & Chinese", "Proficiency in MS Windows, MS Office", "Immediate available is highly preferable"], "locations": ["Kwai Fong"], "categories": ["Transportation & Logistics", "Freight Forwarding"], "post_time": "2022-01-17T16:21:00Z", "salary": {"currency": null, "max": null, "min": null, "period": "monthly", "term": null}, "salary_visible": false, "title_keywords": ["operation clerk"], "responsibilities": ["invoice", "coordinate with", "payment", "customer service", "contact", "documentation", "prepare documents", "report"], "requirements": {"degrees": ["dse"], "majors": [], "languages": ["english", "mandarin"], "language_level": ["good command"], "hard_skills": ["excel", "microsoft word"], "soft_skills": ["communication skills", "work independently", "self-motivated", "under pressure", "responsible"], "languages_combined": [{"language": "english", "language_level": ["good command"]}, {"language": "mandarin", "language_level": ["good command"]}]}, "experience_required": {"duration": [], "field": ["relevant working experience"]}}, {"job_id": "100003009052669", "location_code": "hk", "company": "Canon Engineering Hong Kong Co Ltd", "job_title": "Logistics Clerk", "description": "Responsibilities:\n1) Note queries from Transporters on their bills by emails or telephone calls(about6perweek) and convey internally by email in English.\n2)\u00a0\u00a0Need to work approx.32 to 40 \u00a0hours per week homebased.\n3)\u00a0\u00a0No specific qualification needed (training on the job).\n\nRequirements:\n1)\u00a0Working\u00a0knowledge\u00a0of English and Mandarin/Cantonese is essential.\n2)\u00a0High school or University qualifications.\n3)\u00a0No previous work experience required but motivated and willing to learn.\n4) Able to work well with Microsoft Excel and Word", "employment_types": ["Full Time", "Permanent"], "selling_points": [], "locations": ["Kwai Hing"], "categories": ["Transportation & Logistics", "Others", "Freight Forwarding", "Shipping"], "post_time": "2022-01-17T03:40:49Z", "salary": {"currency": null, "max": null, "min": null, "period": "monthly", "term": null}, "salary_visible": false, "title_keywords": ["logistics clerk"], "responsibilities": [], "requirements": {"degrees": ["high school"], "majors": [], "languages": ["cantonese", "english", "mandarin"], "language_level": [], "hard_skills": ["no", "word", "microsoft excel"], "soft_skills": ["motivated", "willing to learn"], "languages_combined": [{"language": "cantonese", "language_level": []}, {"language": "english", "language_level": []}, {"language": "mandarin", "language_level": []}]}, "experience_required": {"duration": [], "field": []}}, {"job_id": "100003009053775", "location_code": "hk", "company": "CBest Solutions Limited", "job_title": "Business Assistant", "description": "Day-to-day operations to check and verify the freight invoices correctness\nCommunicate (e.g. E-mail) with overseas agent / back office to clarify the freight invoices\nManage, assist for import and export department to allocate the freight cost\nAd-hoc duty as needed\nRequirements\nDSE or above with at least 2 years relevant operations experience in sea freight forwarding company\nPreferred candidates with hands on experience on operations\nFair English and Mandarin\nLearning Opportunity\nCommunication skills with overseas offices, agents and internal department\nTransshipment costing between import & export department\nInterested parties please send full resume with employment history and expected salary to Mr Lee by clicking \"Apply Now\"\u00a0for internal review.", "employment_types": ["Full Time"], "selling_points": ["Work from home during office hours.", "No previous experience required.", "Training on the job with full support"], "locations": ["Others"], "categories": ["Transportation & Logistics", "Freight Forwarding"], "post_time": "2022-01-17T07:33:03Z", "salary": {"currency": null, "max": null, "min": null, "period": "monthly", "term": null}, "salary_visible": false, "title_keywords": ["assistant"], "responsibilities": ["ad-hoc", "cost", "invoices", "sea freight", "operations", "day-to-day operations", "back office", "communication"], "requirements": {"degrees": ["dse"], "majors": [], "languages": ["english", "mandarin"], "language_level": [], "hard_skills": ["import and export"], "soft_skills": ["communication skills", "hands on", "learning"], "languages_combined": [{"language": "english", "language_level": []}, {"language": "mandarin", "language_level": []}]}, "experience_required": {"duration": ["at least 2 years"], "field": []}}, {"job_id": "100003009052618", "location_code": "hk", "company": "", "job_title": "Shipping Clerk / Logistics Clerk  (5-day)", "description": "Responsibilities\n\n\nAnalyze tenders and coorindate with respective stations and agents;\nSet up RFQ pre-alignment call and final call with RFQ key stakeholders;\nConvert customer rate file into internal rate file;\nBeing responsible for validating information and consolidation of pricing data for the RFQ submission;\nReview RFQ pricing with key stakeholders;\nMaintain tender data profiling and records;\nperform any ad-hoc assignments when required.\n\nQualifications\n\nBachelor degree or above with at least 3 years of experiences in sales, pricing, RFQ, tender management or customer service in freight forwarding industry;\nFamiliar with worldwide markets;\nFluent in spoken and written English, and a local language;\nStrong computer skills e.g. MS Excel pivot tables and formulas.\n\nInterested parties, please send full resume, availability and expected salary to our Company.\n\nAll information provided by applicants will be treated in strict confidence and used only for employment-related purposes. All personal data of unsuccessful applicants will be destroyed within 6 months.", "employment_types": ["Full Time", "Permanent", "Temporary"], "selling_points": ["At least 1 year exp shipping or logistic (Sea/Air)", "With forwarder/logistic/trading company exp prefer", "Garantee Double Pay, Bonus, Medical Insurance, etc"], "locations": ["Lai Chi Kok"], "categories": ["Admin & HR", "Clerical / Admin Staff", "Transportation & Logistics", "Freight Forwarding", "Shipping"], "post_time": "2022-01-17T03:37:38Z", "salary": {"currency": null, "max": null, "min": null, "period": "monthly", "term": null}, "salary_visible": false, "title_keywords": ["logistics clerk", "shipping clerk"], "responsibilities": ["management", "data", "ad-hoc assignments", "review", "maintain", "customer service", "tender"], "requirements": {"degrees": ["degree or above", "bachelor"], "majors": [], "languages": ["english"], "language_level": ["fluent"], "hard_skills": ["ms excel", "computer skills"], "soft_skills": ["customer service", "responsible"], "languages_combined": [{"language": "english", "language_level": ["fluent"]}]}, "experience_required": {"duration": ["at least 3 years"], "field": ["management", "customer service"]}}, {"job_id": "100003009055410", "location_code": "hk", "company": "Morrison Express Co Ltd", "job_title": "Specialist, Tender Management (Regional Role)", "description": "Job Duties:\n\nHandle full set of import & export shipping documents (e.g. L/C, D/P, D/A, T/T)\nCommunicate and liaise with forwarder / logistic company / warehouse\nHandle order processing and shipment schedule\nApply import permit from Government (FEHD) / Trade and Industry Dept.\nData entry by using the company system\n\n\u00a0Requirements:\n\nDiploma or above with 3 years relevant experience in supply chain / logistics / shipping field\nGood command of Cantonese, English, and Mandarin\nProficiency in MS Word, Excel & Chinese Word Processing\nContributes to the development of processes & procedures\nStrong communication & coordinating capability\nGood knowledge of L/C and banking document, Tradelink system\n\n\n\nRemuneration:\n\n5 working days\nBank holidays\nDouble pay\nDental & medical coverage\n\n\n\nWe offer attractive remuneration package to the right candidate.\u00a0 Interested parties please send full resume with present & expected salary and available date by clicking \"Apply Now\"\n\n\n\nAll personal data collected will be used for recruitment purpose only.", "employment_types": ["Full Time", "Permanent"], "selling_points": ["Excellent Industry Exposure, Good Career Insight", "Sales, Tender Mgmt, Freight Forwarding Industry", "Min. 3 yr exp in pricing, RFQ, sales operations"], "locations": ["Kwai Tsing Area"], "categories": ["Transportation & Logistics", "Freight Forwarding", "Supply Chain", "Sales, CS & Business Devpt", "Sales - Sales Management"], "post_time": "2022-01-18T02:29:38Z", "salary": {"currency": null, "max": null, "min": null, "period": "monthly", "term": null}, "salary_visible": false, "title_keywords": ["specialist"], "responsibilities": ["data entry", "import & export shipping documents", "schedule", "order processing", "liaise with"], "requirements": {"degrees": ["diploma or above"], "majors": [], "languages": ["cantonese", "english", "chinese", "mandarin"], "language_level": ["proficiency", "good command"], "hard_skills": ["excel", "c", "chinese word processing", "ms word"], "soft_skills": ["communication"], "languages_combined": [{"language": "cantonese", "language_level": ["good command"]}, {"language": "english", "language_level": ["good command"]}, {"language": "chinese", "language_level": ["proficiency"]}, {"language": "mandarin", "language_level": ["good command"]}]}, "experience_required": {"duration": ["3 years"], "field": ["supply chain", "logistics", "relevant experience"]}}, {"job_id": "100003009052474", "location_code": "hk", "company": "Foodgears Industrial International Limited", "job_title": "Import & Export Officer", "description": "Responsbilities\nHandle full set of inbound and outbound cargo handling procedures and activities\u00a0\nHandle daily import and export documents\nLiaise with different internal departments for transportation arrangement within the organization\nPerform ad-hoc duties assigned by dept manager\nSome physical work when performing the job is required\n\nRequirements\n\nHKCEE, HKDSE, Technical College(e.g..VTC) education level or above\nWith some experience in logistic will be an advantage but not a must\nProficiency in PC Skills\nGood command of written and spoken English and Cantonese\nOutgoing, independent, mature, self-motivated and good team player\nFresh Graduates are welcome\nWorking location : Airport Super Terminal 1\n\nWe offer attractive remuneration package fringe benefits including\u00a0Banking Holiday, Annual Leaves, Discretionary Bonus, Additional Pension Contribution from Company, Medical Insurance\u00a0etc.\u00a0If you have the desire to join us, please send us your resume immediately with your present and expected salary via email\u00a0marking\u00a0Application for Airport Operations Officer / Assistant\n\n\u00a0(The information provided will be used for employment related\u00a0purpose only. All information of unsuccessful applicants will be destroyed within six months.)", "employment_types": ["Full Time", "Permanent"], "selling_points": [], "locations": ["Wong Tai Sin Area"], "categories": ["Transportation & Logistics", "Freight Forwarding", "Shipping", "Supply Chain"], "post_time": "2022-01-17T03:07:20Z", "salary": {"currency": null, "max": null, "min": null, "period": "monthly", "term": null}, "salary_visible": false, "title_keywords": ["officer"], "responsibilities": ["liaise with", "procedures", "ad-hoc duties"], "requirements": {"degrees": ["hkdse"], "majors": [], "languages": ["cantonese", "english"], "language_level": ["good command"], "hard_skills": ["pc skills"], "soft_skills": ["outgoing", "good team player", "self-motivated", "independent", "mature"], "languages_combined": [{"language": "cantonese", "language_level": ["good command"]}, {"language": "english", "language_level": ["good command"]}]}, "experience_required": {"duration": [], "field": []}}, {"job_id": "100003009052892", "location_code": "hk", "company": "Shipco Transport (HK) Ltd", "job_title": "Export Operations Coordinator - Asia", "description": "Responsibilities:\nHandle daily rate request and related pricing inquiries (preferably Oceania/Intra Asia/Import trade lanes)\nRegular rate sheet and pricing database update and distribution to relevant stake holders\nSpace / allocation coordination / arrangement with local offices and carriers\nStatistics and reports, market information update (e.g. FAK/NAC/Spot Rate Update, Utilization Levels, Blank Sailings etc.)\nCoordination between carriers, sales & operation team\nInvoice / billing management\nRequirements:\nDiploma or above\nPreferred 1-3 years experience in Logistics Service Providers / Carriers\nBasic knowledge in shipping industry knowledge\nKnowledge or experience in pricing / ocean product will be an advantage\nGood command of spoken and written English and Mandarin\nProficient in MS office, especially Excel\nStrong sense of responsibility and team player\nPleasant and cooperative\nCandidate with\u00a0less experience will also be considered\nBenefits:\nDouble Pay\nFive-day work week\nBirthday Leave\nMedical Insurance\nFree Shuttle Bus\nTraining Allowance\nAttractive remuneration package and excellent career development opportunities will be offered to the successful candidate.\u00a0 For Interested parties, please apply with a detailed resume stating present and stating present and expected salary by clicking \"Apply Now\".\u00a0 You are welcome to visit our website at http://www.cargofe.com.\nPersonal data collected will be used for recruitment purposes only and be treated in strict confidence.\u00a0 Cargo Services treats all applicants for employment in the same way, regardless of age, sex, marriage and civil partnership, race, disability, religion or belief.", "employment_types": ["Full Time", "Permanent"], "selling_points": ["Negotiate rates with shipping lines", "Experience on operation in South East Asia/OCEANIA", "Transportation arrangement"], "locations": ["Not Specified"], "categories": ["Transportation & Logistics", "Others", "Sales, CS & Business Devpt", "Customer Service - Supervisor / Officer", "Freight Forwarding"], "post_time": "2022-01-17T04:27:15Z", "salary": {"currency": null, "max": null, "min": null, "period": "monthly", "term": null}, "salary_visible": false, "title_keywords": ["export operations coordinator"], "responsibilities": ["management", "market information", "invoice", "reports", "coordination", "database"], "requirements": {"degrees": ["diploma or above"], "majors": [], "languages": ["english", "mandarin"], "language_level": ["good command"], "hard_skills": ["excel", "basic", "ms office"], "soft_skills": ["cooperative", "pleasant", "team player", "sense of responsibility"], "languages_combined": [{"language": "english", "language_level": ["good command"]}, {"language": "mandarin", "language_level": ["good command"]}]}, "experience_required": {"duration": ["1-3 years"], "field": ["logistics"]}}, {"job_id": "100003009054216", "location_code": "hk", "company": "Brink's Hong Kong Limited", "job_title": "Airport Operations Officer / Assistant", "description": "Key Responsibilities:\n\nDevelop strategic plans for further growth in business of Logistics\nCreate ''One Stop Solution\" logistics service and ecommerce B2C service for new or current clients\nReview and maintain business relationships with local and overseas clients and business partners\nAchieve commitments and clients inquiries\nCooperate with management and other divisions\nExtensive skills to integrate and coordinate resources across functions and borders\nGood ability to lead people, including hiring and retaining talent, directing reports, defining KPI's and monitoring performance\n\nRequirements\n\n3-5 years experience in regional or global sales experience\nSolid experience of handling logistics projects for well-known clients\nSelf-standing, proactive, interpersonal, analysis, negotiation, implementation and problem solving skills\nAble to act as a team player to execute the operation among multiple divisions\nAble to prepare reports as agreed with customers\nAble to tackle problematic area and enhance service quality\nNumeric analysis ability\nMiddle user level of MS Excel and PowerPoint with good presentation skill\nProficiency in written and verbal in English and Mandarin", "employment_types": ["Full Time", "Permanent"], "selling_points": ["Handle full set of cargo handling procedures", "Liaise with different internal departments", "Some physical work required"], "locations": ["Tung Chung"], "categories": ["Transportation & Logistics", "Aviation Services", "Freight Forwarding", "Others", "Student / Fresh Graduate / No Experience"], "post_time": "2022-01-17T08:50:16Z", "salary": {"currency": null, "max": null, "min": null, "period": "monthly", "term": null}, "salary_visible": false, "title_keywords": ["airport operations officer", "assistant"], "responsibilities": ["management", "strategic plans", "review", "monitoring", "develop", "coordinate", "maintain", "logistics", "reports", "cooperate with"], "requirements": {"degrees": [], "majors": [], "languages": ["english", "mandarin"], "language_level": ["proficiency"], "hard_skills": ["presentation skill", "analysis", "powerpoint", "ms excel", "problem solving skills"], "soft_skills": ["presentation skill", "negotiation", "team player", "problem solving skills", "proactive", "interpersonal"], "languages_combined": [{"language": "english", "language_level": ["proficiency"]}, {"language": "mandarin", "language_level": ["proficiency"]}]}, "experience_required": {"duration": ["3-5 years"], "field": ["logistics"]}}, {"job_id": "100003009053150", "location_code": "hk", "company": "Fly King Transportation Company Ltd", "job_title": "Operation Manager", "description": "The incumbent is responsible to assist the Assistant Manager in leading and managing the overall operations to ensure high quality service in line with department work procedure and customer requirement.\n\nYour task:\n\n\nLiaise with customers on shipment arrangement according to the customers\u2019 instruction\nCoach the operation team on their daily works to meet both department and customers\u2019 standard\nMonitor the team works to ensure the shipments process on the right track\nDirect the team on the understanding of department working procedure and systems, also the understanding of the customer requirements\nSupport and backup to the team and Manager in order to maintain the team works in a stipulated standard\n\nYour qualifications, experience & skills\n\nSecondary school graduated or above\nMinimum 5 years working experience in the freight forwarding industry with minimum 1-2 years supervisory experience\nGood command of written and spoken English\nPossess core competences including leadership, managing change, entrepreneurial responsibility, target and result focus, team steering and punctuality\nProficiency in MS Office including MS Word and Excel\nWork location:\u00a0 Tsing Yi\n\nInterested? We are looking forward to receiving your online application including availability and salary expectations.\n\n(Please quote the Job Reference Number on the subject of your application)\n\n(All information collected will be used for recruitment purpose only)\n\nTo know more about us, please visit\u00a0www.dbschenker.com/cn", "employment_types": ["Full Time", "Permanent"], "selling_points": [], "locations": ["Airport Area"], "categories": ["Transportation & Logistics", "Others", "Freight Forwarding", "Inventory / Warehousing"], "post_time": "2022-01-17T06:08:20Z", "salary": {"currency": null, "max": null, "min": null, "period": "monthly", "term": null}, "salary_visible": false, "title_keywords": ["operation manager"], "responsibilities": ["shipment arrangement", "operations", "systems", "monitor", "quality", "maintain", "liaise with"], "requirements": {"degrees": [], "majors": [], "languages": ["english"], "language_level": ["good command"], "hard_skills": ["ms word", "excel", "focus", "ms office"], "soft_skills": ["focus", "leadership", "responsible"], "languages_combined": [{"language": "english", "language_level": ["good command"]}]}, "experience_required": {"duration": ["minimum 5 years", "minimum 1-2 years"], "field": ["supervisory experience"]}}, {"job_id": "100003009048850", "location_code": "hk", "company": "Vanguard Logistics Services (HK) Ltd", "job_title": "Senior / Export Operations Clerk", "description": "The incumbent is\u00a0responsible for successfully implementing new airfreight business gained by working closely with Operation, Customer Service and corresponding account owners as well as monitoring the progress after implementation.\u00a0 In addition, this position needs to work closely with local sales team to identify and develop new local controlled SME and China MNC airfreight business.\n\n\nWork closely with corresponding Sale Team stakeowner, Airfreight Operation and Customer Service to implement new business as per SOP and customer requirement\nMonitoring\u00a0progress of implementation and identify areas of improvement\nRegular\u00a0review with local sales to identify potential SME and China MNC account and drive corresponding opportunities\nJoint visits to customers with sales teams are required\nYour qualifications, experience & skills:\n\n\nDegree holder or above\nMinimum 5 years of working experience in freight forwarding industry\nStrong operational background in airfreight forwarding industry\nExperience in business implementation is required\nGod command of written and spoken English and Mandarin\nStrong in communication skills\nWork location: Tsing Yi\u00a0\n\nInterested? We are looking forward to receiving your online application including availability and salary expectations.\n\n(Please quote the Job Reference Number on the subject of your application)\n\n(All information collected will be used for recruitment purpose only)\n\nTo know more about us, please visit\u00a0www.dbschenker.com/cn\u00a0", "employment_types": ["Full Time", "Permanent"], "selling_points": ["Export Operations Clerk", "Shipping Clerk", "Forwarder"], "locations": ["Sheung Wan"], "categories": ["Transportation & Logistics", "Freight Forwarding", "Shipping", "Maritime - General"], "post_time": "2022-01-14T07:26:53Z", "salary": {"currency": null, "max": null, "min": null, "period": "monthly", "term": null}, "salary_visible": false, "title_keywords": ["operations clerk"], "responsibilities": ["monitoring", "teams", "implementation", "develop", "regular review", "communication", "customer service", "sales team", "sme"], "requirements": {"degrees": ["degree holder"], "majors": [], "languages": ["english", "mandarin"], "language_level": [], "hard_skills": [], "soft_skills": ["controlled", "communication skills", "customer service", "responsible"], "languages_combined": [{"language": "english", "language_level": []}, {"language": "mandarin", "language_level": []}]}, "experience_required": {"duration": ["minimum 5 years"], "field": ["business"]}}, {"job_id": "100003009052624", "location_code": "hk", "company": "YTO Express (International) Holdings Limited", "job_title": "Trade Lane Manager", "description": "We look for additional teammate in joining our key account team. Main goals are to expand customer services to our key customers and gear business growth and relationship with them moving forward. Seafreight activities in LCL service are our major roles.\nJob descriptions\nReport to Key Account Manager and assist for building up and developing good relationship with customers\nProvide export booking and import routing order services, co-ordinate with internal team during shipping progress, be first contact window to assigned customers\nServe quotation to customers on both import and export activities, follow up feedback after rate quote\nFollow routing order instruction to our overseas offices/agents for execution including cost checking, keep our import clients for cargo progress, co-ordinate with internal team for billing\nMaintain tariff and pricing in-house\nPrepare data report to manager during customer visit purposes, joint visit whenever is in need\nRequirements\nDSE or above in qualification\nOver 2 years of working experiences in shipping industries is preferable, an advantage in freight forwarding or shipping line\nCustomer-oriented, good communications skills, self-motivated, able to work under pressure and overtime if required\nGood demand of spoken and written English and Cantonese, Mandarin with advantage\nProficient in using MS Word & Excel\nAny candidate who is interested in this position is requested to send email to Mr. Sunny via \"Apply Now\" for internal review)", "employment_types": ["Full Time", "Permanent"], "selling_points": ["Trade Lane Development", "Overseas Agents & Partners", "South American region countries"], "locations": ["Kowloon Bay"], "categories": ["Sales, CS & Business Devpt", "Business Development", "Transportation & Logistics", "Freight Forwarding", "Supply Chain"], "post_time": "2022-01-17T03:35:33Z", "salary": {"currency": null, "max": null, "min": null, "period": "monthly", "term": null}, "salary_visible": false, "title_keywords": ["manager"], "responsibilities": ["cost", "shipping", "data", "co-ordinate with", "quotation", "developing", "checking", "good relationship", "maintain", "booking", "contact", "report"], "requirements": {"degrees": ["dse"], "majors": [], "languages": ["cantonese", "english", "mandarin"], "language_level": ["advantage", "good"], "hard_skills": ["excel", "ms word"], "soft_skills": ["customer-oriented", "interested in", "self-motivated", "work under pressure"], "languages_combined": [{"language": "cantonese", "language_level": ["good"]}, {"language": "english", "language_level": ["good"]}, {"language": "mandarin", "language_level": ["advantage", "good"]}]}, "experience_required": {"duration": ["2 years"], "field": []}}, {"job_id": "100003009055217", "location_code": "hk", "company": "Sinotrans (HK) Warehousing Limited", "job_title": "Sales Manager (Logistic / Freight Forwarding)", "description": "Job Responsibilities:\n\nProvide administration support across Sales Team and Order Management Team\nSupport superior in managing day-to-day operating expenditures, supervise and coach the team to ensure operation runs efficiently\nPerform daily checking and monitoring of contract's shipments\nFile, scan properly and maintain necessary documents\nPrepare billings/invoices (including forwarder invoices, customer's L/C documents)(e.g. I/E shipping documents, customs, freight costs management)\nCoordinate with internal teams (Sales, Order Management, Quality, etc) to gather and verify information\nAnalyze data to monitor KPI performance and plan for improvements, streamline the logistics flow, refine SOP\nHandle ad hoc tasks as assigned\nJob Requirements:\n\nForm 5/DSE or aboveor equivalent level\nMinimum three years' experience in a similar role, with more experience may be considered as senior level post.\nBasic knowledge of machinery sales' shipment from Overseas to China.\nWorking knowledge onISO, full set of L/C document, logistic documents (Airway Bill, Bill of Lading, Insurance, Incoterm, bank guarantee).\nDemonstrate proficiencies in office productivity tools (e.g. Excel, Word and PowerPoint), skill in Chinese input.\nFluent in local language and ideally in English and Mandarin (Traditional & Simplified Chinese), both written and spoken\nExperience in Pharmaceutical field is an advantage\nCandidate with less experience will be considered as Assistant Supervisor\u00a0\n\nWorking Location: Kwai Chung\n\nWe offer performance bonus and attractive benefits including medical insurance.\u00a0Please apply with full particulars, contact number and current/ expected salary to\u00a0People & Organization Department, DKSH Hong Kong Limited, 23rd Floor, Tower A, Southmark, 11 Yip Hing Street, Wong Chuk Hang, Hong Kong or fax:2895 9711.\n\nAll personal data collected will be used for recruitment purpose only.\u00a0Candidates will be contacted within 2 weeks if the background and experience are closely relevant to the job requirement.\n\nDrive Growth. Be the Difference. Join DKSH.\n\nDKSH\u2019s strength lies in our great diversity of services, industries, clients, products, regions, and employees from various cultures. We are proud of our people: they are the best in the industry and the reason for our business success. They are passionate, energetic, and purposeful, positively touching millions of lives through the products and services we provide. Join us today if you are ready to \u201cDrive Growth. Be the Difference.\u201d With DKSH, you will experience a world of learning and development, own your career and take business responsibility, and have a positive impact that touches people\u2019s lives.", "employment_types": ["Full Time"], "selling_points": ["Better prospect", "Double pay, 5 Day Work on alternate weeks", "Proficiency in written and verbal in English"], "locations": ["Tin Shui Wai"], "categories": ["Transportation & Logistics", "Freight Forwarding", "Inventory / Warehousing", "E-commerce", "Business Development"], "post_time": "2022-01-18T01:50:38Z", "salary": {"currency": null, "max": null, "min": null, "period": "monthly", "term": null}, "salary_visible": false, "title_keywords": ["sales manager"], "responsibilities": ["shipping documents", "quality", "maintain", "plan", "costs", "administration", "invoices", "billings", "teams", "monitor", "logistics", "analyze data", "management", "monitoring", "coordinate with", "checking", "ad hoc tasks", "order management", "sales team"], "requirements": {"degrees": ["form 5", "dse"], "majors": [], "languages": ["english", "chinese", "mandarin"], "language_level": ["fluent"], "hard_skills": ["chinese input", "excel", "basic", "word", "powerpoint", "c"], "soft_skills": [], "languages_combined": [{"language": "english", "language_level": ["fluent"]}, {"language": "chinese", "language_level": ["fluent"]}, {"language": "mandarin", "language_level": ["fluent"]}]}, "experience_required": {"duration": ["minimum three years"], "field": ["pharmaceutical"]}}, {"job_id": "100003009051999", "location_code": "hk", "company": "Schenker International (H.K.) Limited", "job_title": "Operations Supervisor - Airfreight Import (Ref No: JD/AIR/034/220117)", "description": "Our client is a world leading 3PL. They are looking for a Business Development Manager (Logistics) to join their young and dynamic team.\n\nClient Details\n\nOur client is a world leading 3PL. It provides diverse supply chain and logistics products and services. They are looking for a Business Development Manager to join their young and dynamic team.\n\nDescription\n\nResponsible for account management for the company.\nCommunicate with new and existing customers, understand market needs and therefore able to provide the best fit solutions and services to the customers.\nEstablish excellent relationships with internal stakeholders and top management to improve efficiency.\n\nProfile\n\n6 -8 years of sales experience in the logistics, 3PL or freight forwarding industry.\nYou must have a proven sales track record of business growth.\nYou must have a great business mindset and the ability to develop long-term partnerships with clients and partners.\nThis candidate needs to have strong connection with clients.\nExcellent communication in both Cantonese, Mandarin and English is mandatory.\n\nJob Offer\n\nThe company offers attractive remuneration package. Also the company has dynamic culture and great opportunities for career development.\n\nTo apply online please click the 'Apply' button below. For a confidential discussion about this role please contact Phoebe Leung on +852 3412 4853.", "employment_types": ["Full Time", "Permanent"], "selling_points": ["Supervise Airfreight Import operations", "5-year experience,  with 1-2 year in supervision", "Double pay, Bonus, Medical Insurance, Allowances"], "locations": ["Tsing Yi"], "categories": ["Transportation & Logistics", "Others", "Freight Forwarding"], "post_time": "2022-01-17T01:48:01Z", "salary": {"currency": null, "max": null, "min": null, "period": "monthly", "term": null}, "salary_visible": false, "title_keywords": ["operations", "supervisor"], "responsibilities": ["communicate with", "management", "develop", "communication", "logistics", "contact", "career development"], "requirements": {"degrees": [], "majors": [], "languages": ["cantonese", "english", "mandarin"], "language_level": ["excellent"], "hard_skills": ["dynamic"], "soft_skills": ["communication", "diverse", "dynamic", "responsible"], "languages_combined": [{"language": "cantonese", "language_level": ["excellent"]}, {"language": "english", "language_level": ["excellent"]}, {"language": "mandarin", "language_level": ["excellent"]}]}, "experience_required": {"duration": ["6 -8 years"], "field": ["logistics"]}}, {"job_id": "100003009055708", "location_code": "hk", "company": "Michael Page", "job_title": "Business Development Manager- Logistics / 3PL", "description": "The incumbent is responsible to co-ordinate the shipment and follow up customer enquires for Key Account Team.\n\nYour tasks\n\n\nBeing part of the Key account team as the key window for customer, ensure customer satisfaction and sustainable business relationship.\nSupport Global Key Account Team on Customer Analysis (internal) and Customer Reporting (External)\nRespond to enquiries (general enquires & prepare quotation) in timely manner\nGenerate reports and support Global RFQ process as per Global account team instructions before the deadline\nSupport project management for ongoing account specific projects\n\nYour qualifications, experience & skills\n\nDiploma or above\n3-5 years relevant experience, with experience in Oceanfreight will be an advantage\nAbility to review, analyze performance report\nGood interpersonal and communication skills with positive mindset\nGood knowledge of Microsoft Office Software (Excel, Word, PowerPoint and others)\nPossess core competences including initiative, commitment for quality, planning, organizing, team building and cooperation, customer and services orientation\nInterested? We are looking forward to receiving your online application including availability and salary expectations.\n\n\n(Please quote the Job Reference Number on the subject of your application)\n\n(All information collected will be used for recruitment purpose only)\n\nTo know more about us, please visit\u00a0www.dbschenker.com/cn\u00a0", "employment_types": ["Full Time", "Permanent"], "selling_points": ["A well known logistics company", "Business Development", "Logistics industry"], "locations": ["Not Specified"], "categories": ["Transportation & Logistics", "Freight Forwarding", "Supply Chain", "Sales, CS & Business Devpt", "Account Servicing"], "post_time": "2022-01-18T02:52:22Z", "salary": {"currency": null, "max": null, "min": null, "period": "monthly", "term": null}, "salary_visible": false, "title_keywords": ["business development manager", "logistics"], "responsibilities": ["reporting", "software", "analysis", "quotation", "review", "quality", "communication", "project management", "planning", "reports", "recruitment", "report"], "requirements": {"degrees": ["diploma or above"], "majors": [], "languages": [], "language_level": [], "hard_skills": ["excel", "analysis", "word", "powerpoint", "project management", "microsoft office software"], "soft_skills": ["communication skills", "responsible", "positive mindset", "timely", "project management", "initiative", "interpersonal"], "languages_combined": []}, "experience_required": {"duration": ["3-5 years"], "field": ["relevant experience"]}}, {"job_id": "100003009051983", "location_code": "hk", "company": "Schenker International (H.K.) Limited", "job_title": "Sales Support Executive (Ref No: JD/SKM/034/220117)", "description": "Responsibilities\n\n-\u00a0Able to handle full set I/E Shipping documents\n\n- Familiar with operating CFS / CY / Consolidation Arrange bookings\n\n- Tradelink declaration\n\n- Direct communicate with clients, and forwarders for shipment arrangement\n\n- Responsible for data inputting, inventory and preparation of invoice\n\nRequirements\n\n-\u00a0At least 3-5 years in related fields (i.e. shipping or forwarder)\n\n- F.5 or DSE above\n\n- Good command of written Chinese and English, and Putonghua\n\n- Good communication and interpersonal skills\n\n- Familiar with PC operations (e.g. MS office, Chinese Word Processing)\n\n- Immediately available is preferred", "employment_types": ["Full Time", "Permanent"], "selling_points": ["Follow up customer enquires for Key Account Team", "Customer Analysis and Customer Reporting", "Double pay, Bonus, 5-day work, Medical Insurance"], "locations": ["Tsing Yi"], "categories": ["Transportation & Logistics", "Others", "Freight Forwarding", "Sales, CS & Business Devpt", "Others"], "post_time": "2022-01-17T01:45:16Z", "salary": {"currency": null, "max": null, "min": null, "period": "monthly", "term": null}, "salary_visible": false, "title_keywords": ["sales support executive"], "responsibilities": ["shipping documents", "communicate with", "shipment arrangement", "data", "inventory", "tradelink declaration", "preparation of invoice"], "requirements": {"degrees": ["dse"], "majors": [], "languages": ["putonghua", "english", "chinese"], "language_level": ["good command"], "hard_skills": ["pc operations", "chinese word processing", "ms office"], "soft_skills": ["communication and interpersonal skills"], "languages_combined": [{"language": "putonghua", "language_level": ["good command"]}, {"language": "english", "language_level": ["good command"]}, {"language": "chinese", "language_level": ["good command"]}]}, "experience_required": {"duration": [], "field": []}}, {"job_id": "100003009055827", "location_code": "hk", "company": "Page Personnel", "job_title": "Assistant Logistics Manager - EU Buying Office", "description": "With our fast-growing expansion in Greater China, an excellent opportunity new exists for a high calibre candidate to join us.\n\nFor our branch in\u00a0Hong Kong\u00a0we are currently looking for a:\n\n\u00a0Specific duties including, but not restricted to :\n\nResponsible for securing new customers, and maintaining and developing existing accounts.\nFind and develop qualified leads (cold calling), convert them through the sales process into prospects and customers.\nRegular client visit to validate our service levels and develop new revenue streams.\nMeet and exceed target set in terms of contributing and generating revenue.\nSet-up and execute customer SOP for ensuring operating procedure meets customer expectations.\nPromote the services and products of all entities, and coordinate sales efforts with other department sales.\n\n\u00a0\u00a0Job Requirements\n\nMinimum 3 years Sales experience in Freight Forwarding/ Logistics; experienced in business with Germany, France is preferable.\nHighly motivated individual with a strong product knowledge in import/export ocean (NVOCC) and air, and selling experience of value-added service 3PL solution.\nAbility to communicate effectively in English and Chinese, both verbally and in writing. Mandarin an advantage.\nKnowledge of personal computers, including Microsoft Word and Excel software.\u00a0\n\nWe offer\n\nAttractive incentive scheme\n5-days work\u00a0\nOn job sales training\n\nInterested parties please email your resume with current & expected salary and earliest available date to\u00a0\na p p l y . h k g @ r o h l i g . c o m\n\u00a0\nAll information received will be kept in strict confidence and only for employment-related purpose.", "employment_types": ["Full Time", "Permanent"], "selling_points": ["Freight forwarder management", "FOB/FCA shipment", "Attractive package"], "locations": ["Kowloon Bay"], "categories": ["Transportation & Logistics", "Others", "Freight Forwarding", "Shipping"], "post_time": "2022-01-18T02:59:22Z", "salary": {"currency": null, "max": null, "min": null, "period": "monthly", "term": null}, "salary_visible": false, "title_keywords": ["logistics manager", "assistant"], "responsibilities": ["software", "maintaining", "developing", "develop", "coordinate", "logistics"], "requirements": {"degrees": [], "majors": [], "languages": ["english", "chinese", "mandarin"], "language_level": ["advantage"], "hard_skills": ["excel", "microsoft word"], "soft_skills": ["motivated individual", "responsible"], "languages_combined": [{"language": "english", "language_level": []}, {"language": "chinese", "language_level": []}, {"language": "mandarin", "language_level": ["advantage"]}]}, "experience_required": {"duration": ["minimum 3 years"], "field": ["logistics"]}}, {"job_id": "100003009055186", "location_code": "hk", "company": "FedEx Trade Networks Transport & Brokerage (Hong Kong) Limited", "job_title": "Enterprise Regional Account Manager", "description": "Our client is a\u00a0software and collaborative platform provider, European leader in transportation management and global sourcing solutions.\u00a0You will work within the Customer Service team which is in charge of:\u00a0\n\nFunctional consulting:\n\nHandling software deployment projects for new and existing clients\n\nResearch, elaborate and provide functional / technical solutions regarding the customer needs\n\nAnimate analysis workshops with the customers\n\nAnalyze set-up and development requests\n\nWrite detailed functional specifications and associated test scenarios\n\nTest developments and fixes\n\nTrain key-users / end-users\n\nProvide product demonstrations, enquiries and RFQ follow-up\n\nProvide consulting service for potential customers\n\nProvide functional support and insights to the commercial team\n\nSupport the Product team to ensure the quality of the standard released versions of our applications\n\nCustomer support\n\n\nContribute to functional user support\n\nAnalyze and process enquiries of the active clients\n\nManaging the relationship with the active clients through a Web-based Hotline ticketing system\nRequirements:\n\n\nUniversity degree in Information Technology or Logistics\n\nAt least 2 years\u2019 experience in customer support / deployment of information system, ideally in the international logistics / supply chain field.\n\nExperience in working with retail and / or logistics customers in an international environment\n\nOracle knowledge and SQL mastery are a plus\n\nGood interpersonal and communication skills in both oral and written\u00a0English\n\nStrong analytical, problem solving and synthesis skills\n\nGood organization skills: ability to manage priorities and to take initiative\n\nFluent in English and Cantonese", "employment_types": ["Full Time", "Permanent"], "selling_points": ["Guarantee 14 months paid with attractive benefits", "Freight fowarding industry", "Solid Sales Experience"], "locations": ["Kwai Fong"], "categories": ["Sales, CS & Business Devpt", "Business Development", "Transportation & Logistics", "Freight Forwarding", "Account Servicing"], "post_time": "2022-01-18T01:42:19Z", "salary": {"currency": null, "max": null, "min": null, "period": "monthly", "term": null}, "salary_visible": false, "title_keywords": ["account manager"], "responsibilities": ["management", "software", "consulting", "analysis", "quality", "communication", "customer service", "specifications", "logistics"], "requirements": {"degrees": ["university degree"], "majors": ["information technology"], "languages": ["cantonese", "english"], "language_level": ["fluent", "good"], "hard_skills": ["plus", "web", "animate", "analysis", "information system", "sql", "problem solving", "deployment", "workshops", "oracle"], "soft_skills": ["initiative", "communication skills", "oral", "collaborative", "problem solving", "customer service", "organization skills", "active", "interpersonal", "detailed"], "languages_combined": [{"language": "cantonese", "language_level": ["fluent"]}, {"language": "english", "language_level": ["fluent", "good"]}]}, "experience_required": {"duration": ["at least 2 years"], "field": ["supply chain", "retail", "logistics"]}}, {"job_id": "100003009052137", "location_code": "hk", "company": "Drake Overload Ltd", "job_title": "Key Account Manager - Freight Forwarding", "description": "To cope with the expansion of the Company, our client is now looking for high caliber candidate to join the Customer Services Team in Hong Kong:\n\nResponsibilities:\n\nWork closely with overseas agents, carriers, co-loaders, customers, suppliers and warehouse team\nResponsible for arranging inbound & outbound shipment for customers\nAnswer customers' enquiries and handle complaints\nFollow up shipment and achieve on-time delivery\nMaintain up-to-date record\nHandle pre-alert and general correspondence\n\nRequirements:\n\nAt least 4 years CS experience in\u00a0Logistic Co. / Freight-Forwarder / 3PL\nForm 5 or above\nGood knowledge of general procedures of I/E documentation and custom declaration\nProficiency in MS Office or SAP / WMS system\nGood command\u00a0of English and Mandarin\nCandidate with less experience will also be considered as \"Logistic CS Officer\"\n\nInterested parties, please click the \"Apply Now\" or send\u00a0 your updated resume with\u00a0 Current\u00a0and\u00a0Expected salary\u00a0in MS word format to cv @headsearch21.com\u00a0\n\nFor more information please contact Ms. Leung at 3188 3072.\n\nRef #: SD01005\n\nAll information collected will be treated in strict confidence and be used for recruitment purpose only\n\nCompany Web-Site:\u00a0www.headsearch21.com", "employment_types": ["Full Time"], "selling_points": ["International Freight Forwarding Company", "5 yrs. of Account Mgt. exp in Freight Forwarding", "Double Pay w/ competitive remuneration package"], "locations": ["Others"], "categories": ["Transportation & Logistics", "Others", "Freight Forwarding", "Sales, CS & Business Devpt", "Account Servicing"], "post_time": "2022-01-17T02:14:09Z", "salary": {"currency": null, "max": null, "min": null, "period": "monthly", "term": null}, "salary_visible": false, "title_keywords": ["account manager"], "responsibilities": ["maintain", "inbound & outbound", "handle complaints"], "requirements": {"degrees": ["form 5 or above"], "majors": [], "languages": ["english", "mandarin"], "language_level": ["good command"], "hard_skills": ["documentation", "sap", "ms office"], "soft_skills": [], "languages_combined": [{"language": "english", "language_level": ["good command"]}, {"language": "mandarin", "language_level": ["good command"]}]}, "experience_required": {"duration": ["at least 4 years"], "field": ["cs"]}}, {"job_id": "100003009055187", "location_code": "hk", "company": "FedEx Trade Networks Transport & Brokerage (Hong Kong) Limited", "job_title": "Operations Analyst, Ocean / Associate Operations Analyst, Ocean", "description": "The successful candidate will be responsible for in charge\u00a0a team to provide 7 x 24 functional direction and leadership roles to the Airport Logistics Centre and acts as the primary interface on line haul performance with the line haul providers and with the Aviation commercial group management team.\u00a0\u00a0You also monitor the line haul performance to and from other regions, where the company owned or controlled aircraft are used.\n\nThe job holder\u2019s major responsibilities are to:\nReporting to the\u00a0Department Director, you will manage teams of supervisors and\u00a0operators to ensure effective management of transportation in the network service including daily space planning and optimize space allocation on network flights while meeting customers\u2019 requirements.\n\nYou will have to ensure timely provision of reports / information in terms of flight performance/incidents, capacity allocation, utilization, and line-haul reports, etc. to optimize capacity on network flights and improve the performance on commercials flights.\n\nYou will represent\u00a0Operation\u00a0Department\u00a0in building and maintaining good business relationship with\u00a0airlines, line-haul service providers / suppliers and negotiating for service performance improvement, flight information updating process and space booking issues.\u00a0\nYou will also be required to lead the team in proactively monitoring the inbound / outbound flight movements, providing real-time visibility of movement through systems, promptly responding to network requests and timely updates of service incidents.\n\nIn the event of potential service incidents with transit time impact, you are required to support contingency actions as planned by the regional team in order to keep the impact to its minimal.\u00a0\n\nRequirements:\n\nDegree holder, preferably in Transportation or Logistics related discipline\nLeast 10 years working experience in\u00a0flight dispatch/operation,\u00a0airline, transportation or logistics industry with supervisory level experience\nFamiliar with air transport practices and Hong Kong Customs rules and regulations is an advantage\nGood command of both spoken and written Business English and Cantonese\nStrong planning and data analysis skills\nStrong interpersonal and stakeholder management skills\nHigh level of energy, motivation and drive skills\nComfortable working in a relatively unstructured and multi-cultural environment\nLess experience will consideration as\u00a0Logistics Operation Officer\n\nOffer and Benefit :\n\n\u00a0Stable shift duty 5 Days' work in a week\u00a0\n\u00a0Medical scheme and transportation allowance\u00a0\n\u00a015 Days annul leave with annual performance bonus\n\u00a0Entitled the banking holidays with clear career promotion\u00a0\n\nMORE POSITIONS PLEASE VISIT OUR WEBSITE AT: http://www.prowess.hk\n\nWhatsApp to our consultant\u00a0:\u00a0https://wa.me/85291493008\u00a0or contact us at\u00a0+852\u00a0 2838 9621 for more information of the position.\nFor interested candidates, please submit your full resume with expected salary in MS Word format to us through the above email.\n\n", "employment_types": ["Full Time", "Permanent"], "selling_points": ["Guarantee 14 months paid with attractive benefits", "Freight fowarding industry & Ocean Operations", "Immediately available is highly preferred"], "locations": ["Kwai Fong"], "categories": ["Transportation & Logistics", "Freight Forwarding", "Shipping", "Supply Chain"], "post_time": "2022-01-18T01:42:19Z", "salary": {"currency": null, "max": null, "min": null, "period": "monthly", "term": null}, "salary_visible": false, "title_keywords": ["associate", "operations analyst"], "responsibilities": ["reporting", "management", "maintaining", "monitoring", "teams", "systems", "reports", "booking", "planning"], "requirements": {"degrees": ["degree holder"], "majors": [], "languages": ["cantonese", "english"], "language_level": ["good command"], "hard_skills": ["whatsapp", "analysis", "airline", "scheme"], "soft_skills": ["clear", "stable", "interpersonal"], "languages_combined": [{"language": "cantonese", "language_level": ["good command"]}, {"language": "english", "language_level": ["good command"]}]}, "experience_required": {"duration": ["least 10 years"], "field": ["logistics industry", "supervisory level", "operation", "logistics"]}}, {"job_id": "100003009056866", "location_code": "hk", "company": "Delmar International (Hong Kong) Limited", "job_title": "Ocean Freight Operations (5 Day Work)", "description": "Job Responsibilities:-\n\nResponse to customer\nHandling inbound/outbound Ocean Freight shipment and planning\nManage Ocean Freight shipment data and ensure data integrity\nCommunicate with other branches/ origin offices\nRequirements:-\n\nFluent in English and Chinese\nMinimum 2 years relevant working experience\nFluent in English and Mandarin, both written and spoken\nImmediate available is\u00a0highly preferred\n\n\nPlease send full resume with present & expected salary for consideration.", "employment_types": ["Full Time", "Permanent"], "selling_points": ["Immediate available is highly preferred", "Handling inbound/outbound shipment and planning", "5 Day Work Week"], "locations": ["Kwai Fong"], "categories": ["Transportation & Logistics", "Others", "Freight Forwarding", "Fulfillment"], "post_time": "2022-01-18T06:36:28Z", "salary": {"currency": null, "max": null, "min": null, "period": "monthly", "term": null}, "salary_visible": false, "title_keywords": ["operations"], "responsibilities": ["communicate with", "data", "planning"], "requirements": {"degrees": [], "majors": [], "languages": ["english", "chinese", "mandarin"], "language_level": ["fluent"], "hard_skills": [], "soft_skills": [], "languages_combined": [{"language": "english", "language_level": ["fluent", "fluent"]}, {"language": "chinese", "language_level": ["fluent", "fluent"]}, {"language": "mandarin", "language_level": ["fluent", "fluent"]}]}, "experience_required": {"duration": ["minimum 2 years"], "field": ["relevant working experience"]}}, {"job_id": "100003009056301", "location_code": "hk", "company": "CEVA Logistics (Hong Kong) Limited", "job_title": "Business Development Manager  - Freight Forwarding", "description": "Job Description\n\nExplore new business opportunities and generate sales leads, formulate business solution per the account requirements in Hong Kong & South China\nTo achieve the individual new win business target in term of volume, sales and net revenue\nIdentify, develop and build business network and relationship with all customer\u2019s\u00a0 contact levels to retain and penetrate into the account\nCoordinate with internal and external stakeholders to drive for success on business tenders and collect reference business intelligent for revaluation.\nTake lead of business project or campaign , to formulate business strategy, execution and monitoring to deliver the expected result\u00a0\u00a0\u00a0\nMaintain healthy pipeline in sales system to ensure new win target can be achieved\n\nJob Requirement\n\nDegree holder with at least 3 years' experience in logistics field, prefer field sales experience\nStrong sales drive\nProfessional\u00a0 qualification\u00a0 on DG, clearance or other expertise in logistics is an advantage\nGood command of spoken and written Chinese and English, additional language is a plus\nExcellent communication and interpersonal skills\nAggressive, out-going, enjoy face-to-face connection\n\nCompany Benefits\n\nSales incentive program\nDouble pay\nFive-day work week\nFree shuttle bus\nMedical insurance\n\nAttractive remuneration package will be given to the right candidates.", "employment_types": ["Full Time", "Permanent"], "selling_points": ["Knowledge in Freight Forwarding", "Field Sales experience", "Excellent communication and interpersonal skills"], "locations": ["Kowloon Bay"], "categories": ["Transportation & Logistics", "Freight Forwarding"], "post_time": "2022-01-18T03:53:19Z", "salary": {"currency": null, "max": null, "min": null, "period": null, "term": null}, "salary_visible": false, "title_keywords": ["business development manager"], "responsibilities": ["explore new business opportunities", "monitoring", "coordinate with", "develop", "maintain", "generate sales leads", "contact"], "requirements": {"degrees": ["degree holder"], "majors": [], "languages": ["english", "chinese"], "language_level": ["good command"], "hard_skills": ["plus"], "soft_skills": ["communication and interpersonal skills"], "languages_combined": [{"language": "english", "language_level": ["good command"]}, {"language": "chinese", "language_level": ["good command"]}]}, "experience_required": {"duration": ["at least 3 years"], "field": ["logistics"]}}, {"job_id": "100003009056303", "location_code": "hk", "company": "CEVA Logistics (Hong Kong) Limited", "job_title": "Ocean Freight Coordinator", "description": "Job Responsibilities\n\nResponsible for Handle full set of import customer service and documentation\nContact co-loader and carrier to obtain shipment arrival and payment\nPrepare documents and payment to exchange the delivery order with co-loader and carrier before the vessel arrives\nResponsible to provide arrival notice, invoice, delivery order to consignee in timely manner\nPrepare monthly customer report and achieve customer KPI\nCoordinate with co-loader and subcontractor for door delivery\nComplete the company and customer KPI within timeframe\n\nJob Requirements\n\nF.5 or DSE or\u00a0 above\nRelevant working experience in sea freight forwarding industry is an advantage\nExperience in handling full set of Ocean Import flow and Cargowise is an advantage\nCandidates with less working experience would also be considered\nGood communication skills and able to work independently under pressure\nGood command in written and spoken English and Mandarin\nProficient in the use of Microsoft Word and Excel\nSelf-motivated and Responsible\u00a0\n\nWe offer attractive remuneration packages to the right candidates. Interested parties, please send your FULL resume with CURRENT and EXPECTED SALARY by clicking \"APPLY NOW\". For further information of our company, please visit our website: http://www.cevalogistics.com.\u00a0\u00a0", "employment_types": ["Full Time", "Permanent"], "selling_points": ["Ocean Freight", "Fresh graduate will be considered", "Self-motivated and Responsible"], "locations": ["Kowloon Bay"], "categories": ["Sales, CS & Business Devpt", "Customer Service - Supervisor / Officer", "Transportation & Logistics", "Freight Forwarding", "Supply Chain"], "post_time": "2022-01-18T03:53:19Z", "salary": {"currency": null, "max": null, "min": null, "period": null, "term": null}, "salary_visible": false, "title_keywords": ["coordinator"], "responsibilities": ["invoice", "coordinate with", "payment", "customer service", "contact", "documentation", "prepare documents", "report"], "requirements": {"degrees": ["dse"], "majors": [], "languages": ["english", "mandarin"], "language_level": ["good command"], "hard_skills": ["excel", "microsoft word"], "soft_skills": ["communication skills", "work independently", "self-motivated", "under pressure", "responsible"], "languages_combined": [{"language": "english", "language_level": ["good command"]}, {"language": "mandarin", "language_level": ["good command"]}]}, "experience_required": {"duration": [], "field": ["relevant working experience"]}}, {"job_id": "100003009053636", "location_code": "hk", "company": "Cargo Services Far East Ltd", "job_title": "Executive - Ocean Freight Pricing", "description": "Responsibilities:\nHandle daily rate request and related pricing inquiries (preferably Oceania/Intra Asia/Import trade lanes)\nRegular rate sheet and pricing database update and distribution to relevant stake holders\nSpace / allocation coordination / arrangement with local offices and carriers\nStatistics and reports, market information update (e.g. FAK/NAC/Spot Rate Update, Utilization Levels, Blank Sailings etc.)\nCoordination between carriers, sales & operation team\nInvoice / billing management\nRequirements:\nDiploma or above\nPreferred 1-3 years experience in Logistics Service Providers / Carriers\nBasic knowledge in shipping industry knowledge\nKnowledge or experience in pricing / ocean product will be an advantage\nGood command of spoken and written English and Mandarin\nProficient in MS office, especially Excel\nStrong sense of responsibility and team player\nPleasant and cooperative\nCandidate with\u00a0less experience will also be considered\nBenefits:\nDouble Pay\nFive-day work week\nBirthday Leave\nMedical Insurance\nFree Shuttle Bus\nTraining Allowance\nAttractive remuneration package and excellent career development opportunities will be offered to the successful candidate.\u00a0 For Interested parties, please apply with a detailed resume stating present and stating present and expected salary by clicking \"Apply Now\".\u00a0 You are welcome to visit our website at http://www.cargofe.com.\nPersonal data collected will be used for recruitment purposes only and be treated in strict confidence.\u00a0 Cargo Services treats all applicants for employment in the same way, regardless of age, sex, marriage and civil partnership, race, disability, religion or belief.", "employment_types": ["Full Time", "Permanent"], "selling_points": ["Seafreight pricing - Oceania/Intra Asia/Import", "1-3 years relevant experiences", "Double Pay; 5-day week; Birthday Leave"], "locations": ["Kwai Tsing Area"], "categories": ["Transportation & Logistics", "Freight Forwarding", "Shipping", "Supply Chain"], "post_time": "2022-01-17T07:16:11Z", "salary": {"currency": null, "max": null, "min": null, "period": "monthly", "term": null}, "salary_visible": false, "title_keywords": ["executive"], "responsibilities": ["management", "market information", "invoice", "reports", "coordination", "database"], "requirements": {"degrees": ["diploma or above"], "majors": [], "languages": ["english", "mandarin"], "language_level": ["good command"], "hard_skills": ["excel", "basic", "ms office"], "soft_skills": ["cooperative", "pleasant", "team player", "sense of responsibility"], "languages_combined": [{"language": "english", "language_level": ["good command"]}, {"language": "mandarin", "language_level": ["good command"]}]}, "experience_required": {"duration": ["1-3 years"], "field": ["logistics"]}}, {"job_id": "100003009054771", "location_code": "hk", "company": "Schenker International (H.K.) Ltd", "job_title": "Assistant Manager - Business Implementation & Development - Airfreight (Ref no.: JD/AIR/052/220117)", "description": "The incumbent is\u00a0responsible for successfully implementing new airfreight business gained by working closely with Operation, Customer Service and corresponding account owners as well as monitoring the progress after implementation.\u00a0 In addition, this position needs to work closely with local sales team to identify and develop new local controlled SME and China MNC airfreight business.\n\n\nWork closely with corresponding Sale Team stakeowner, Airfreight Operation and Customer Service to implement new business as per SOP and customer requirement\nMonitoring\u00a0progress of implementation and identify areas of improvement\nRegular\u00a0review with local sales to identify potential SME and China MNC account and drive corresponding opportunities\nJoint visits to customers with sales teams are required\nYour qualifications, experience & skills:\n\n\nDegree holder or above\nMinimum 5 years of working experience in freight forwarding industry\nStrong operational background in airfreight forwarding industry\nExperience in business implementation is required\nGod command of written and spoken English and Mandarin\nStrong in communication skills\nWork location: Tsing Yi\u00a0\n\nInterested? We are looking forward to receiving your online application including availability and salary expectations.\n\n(Please quote the Job Reference Number on the subject of your application)\n\n(All information collected will be used for recruitment purpose only)\n\nTo know more about us, please visit\u00a0www.dbschenker.com/cn\u00a0", "employment_types": ["Full Time", "Permanent"], "selling_points": ["Airfreight business implementation", "Business implementation & development", "Double pay, bonus, 5-day work, medical"], "locations": ["Tsing Yi"], "categories": ["Transportation & Logistics", "Aviation Services", "Others", "Freight Forwarding"], "post_time": "2022-01-17T11:01:48Z", "salary": {"currency": null, "max": null, "min": null, "period": "monthly", "term": null}, "salary_visible": false, "title_keywords": ["assistant manager"], "responsibilities": ["monitoring", "teams", "implementation", "develop", "regular review", "communication", "customer service", "sales team", "sme"], "requirements": {"degrees": ["degree holder"], "majors": [], "languages": ["english", "mandarin"], "language_level": [], "hard_skills": [], "soft_skills": ["controlled", "communication skills", "customer service", "responsible"], "languages_combined": [{"language": "english", "language_level": []}, {"language": "mandarin", "language_level": []}]}, "experience_required": {"duration": ["minimum 5 years"], "field": ["business"]}}, {"job_id": "100003009054006", "location_code": "hk", "company": "DKSH Hong Kong Limited", "job_title": "Supervisor, Supply Chain Management (Shipping)", "description": "Job Responsibilities:\n\nProvide administration support across Sales Team and Order Management Team\nSupport superior in managing day-to-day operating expenditures, supervise and coach the team to ensure operation runs efficiently\nPerform daily checking and monitoring of contract's shipments\nFile, scan properly and maintain necessary documents\nPrepare billings/invoices (including forwarder invoices, customer's L/C documents)(e.g. I/E shipping documents, customs, freight costs management)\nCoordinate with internal teams (Sales, Order Management, Quality, etc) to gather and verify information\nAnalyze data to monitor KPI performance and plan for improvements, streamline the logistics flow, refine SOP\nHandle ad hoc tasks as assigned\nJob Requirements:\n\nForm 5/DSE or aboveor equivalent level\nMinimum three years' experience in a similar role, with more experience may be considered as senior level post.\nBasic knowledge of machinery sales' shipment from Overseas to China.\nWorking knowledge onISO, full set of L/C document, logistic documents (Airway Bill, Bill of Lading, Insurance, Incoterm, bank guarantee).\nDemonstrate proficiencies in office productivity tools (e.g. Excel, Word and PowerPoint), skill in Chinese input.\nFluent in local language and ideally in English and Mandarin (Traditional & Simplified Chinese), both written and spoken\nExperience in Pharmaceutical field is an advantage\nCandidate with less experience will be considered as Assistant Supervisor\u00a0\n\nWorking Location: Kwai Chung\n\nWe offer performance bonus and attractive benefits including medical insurance.\u00a0Please apply with full particulars, contact number and current/ expected salary to\u00a0People & Organization Department, DKSH Hong Kong Limited, 23rd Floor, Tower A, Southmark, 11 Yip Hing Street, Wong Chuk Hang, Hong Kong or fax:2895 9711.\n\nAll personal data collected will be used for recruitment purpose only.\u00a0Candidates will be contacted within 2 weeks if the background and experience are closely relevant to the job requirement.\n\nDrive Growth. Be the Difference. Join DKSH.\n\nDKSH\u2019s strength lies in our great diversity of services, industries, clients, products, regions, and employees from various cultures. We are proud of our people: they are the best in the industry and the reason for our business success. They are passionate, energetic, and purposeful, positively touching millions of lives through the products and services we provide. Join us today if you are ready to \u201cDrive Growth. Be the Difference.\u201d With DKSH, you will experience a world of learning and development, own your career and take business responsibility, and have a positive impact that touches people\u2019s lives.", "employment_types": ["Full Time", "Permanent"], "selling_points": ["Form 5/ DSE or above", "three years' experience in a similar role", "Prepare billings/invoices"], "locations": ["Kwai Tsing Area"], "categories": ["Transportation & Logistics", "Documentary Credit / Bills Processing", "Freight Forwarding", "Shipping"], "post_time": "2022-01-17T08:01:48Z", "salary": {"currency": null, "max": null, "min": null, "period": "monthly", "term": null}, "salary_visible": false, "title_keywords": ["shipping", "supervisor"], "responsibilities": ["shipping documents", "quality", "maintain", "plan", "costs", "administration", "invoices", "billings", "teams", "monitor", "logistics", "analyze data", "management", "monitoring", "coordinate with", "checking", "ad hoc tasks", "order management", "sales team"], "requirements": {"degrees": ["form 5", "dse"], "majors": [], "languages": ["english", "chinese", "mandarin"], "language_level": ["fluent"], "hard_skills": ["chinese input", "excel", "basic", "word", "powerpoint", "c"], "soft_skills": [], "languages_combined": [{"language": "english", "language_level": ["fluent"]}, {"language": "chinese", "language_level": ["fluent"]}, {"language": "mandarin", "language_level": ["fluent"]}]}, "experience_required": {"duration": ["minimum three years"], "field": ["pharmaceutical"]}}, {"job_id": "100003009053507", "location_code": "hk", "company": "The French Chamber of Commerce and Industry in HK", "job_title": "Functional Consultant", "description": "Our client is a\u00a0software and collaborative platform provider, European leader in transportation management and global sourcing solutions.\u00a0You will work within the Customer Service team which is in charge of:\u00a0\n\nFunctional consulting:\n\nHandling software deployment projects for new and existing clients\n\nResearch, elaborate and provide functional / technical solutions regarding the customer needs\n\nAnimate analysis workshops with the customers\n\nAnalyze set-up and development requests\n\nWrite detailed functional specifications and associated test scenarios\n\nTest developments and fixes\n\nTrain key-users / end-users\n\nProvide product demonstrations, enquiries and RFQ follow-up\n\nProvide consulting service for potential customers\n\nProvide functional support and insights to the commercial team\n\nSupport the Product team to ensure the quality of the standard released versions of our applications\n\nCustomer support\n\n\nContribute to functional user support\n\nAnalyze and process enquiries of the active clients\n\nManaging the relationship with the active clients through a Web-based Hotline ticketing system\nRequirements:\n\n\nUniversity degree in Information Technology or Logistics\n\nAt least 2 years\u2019 experience in customer support / deployment of information system, ideally in the international logistics / supply chain field.\n\nExperience in working with retail and / or logistics customers in an international environment\n\nOracle knowledge and SQL mastery are a plus\n\nGood interpersonal and communication skills in both oral and written\u00a0English\n\nStrong analytical, problem solving and synthesis skills\n\nGood organization skills: ability to manage priorities and to take initiative\n\nFluent in English and Cantonese", "employment_types": ["Full Time", "Permanent"], "selling_points": ["Logistics solution platform", "Customer Service", "Friendly working environment"], "locations": ["Central"], "categories": ["Information Technology (IT)", "Technical / Functional Consulting", "Transportation & Logistics", "Freight Forwarding", "Supply Chain"], "post_time": "2022-01-17T07:04:28Z", "salary": {"currency": null, "max": null, "min": null, "period": "monthly", "term": null}, "salary_visible": false, "title_keywords": ["consultant"], "responsibilities": ["management", "software", "consulting", "analysis", "quality", "communication", "customer service", "specifications", "logistics"], "requirements": {"degrees": ["university degree"], "majors": ["information technology"], "languages": ["cantonese", "english"], "language_level": ["fluent", "good"], "hard_skills": ["plus", "web", "animate", "analysis", "information system", "sql", "problem solving", "deployment", "workshops", "oracle"], "soft_skills": ["initiative", "communication skills", "oral", "collaborative", "problem solving", "customer service", "organization skills", "active", "interpersonal", "detailed"], "languages_combined": [{"language": "cantonese", "language_level": ["fluent"]}, {"language": "english", "language_level": ["fluent", "good"]}]}, "experience_required": {"duration": ["at least 2 years"], "field": ["supply chain", "retail", "logistics"]}}, {"job_id": "100003009054406", "location_code": "hk", "company": "Prowess Recruitment Consulting Limited", "job_title": "Logistics Operation Manager / Officer - Airport", "description": "The successful candidate will be responsible for in charge\u00a0a team to provide 7 x 24 functional direction and leadership roles to the Airport Logistics Centre and acts as the primary interface on line haul performance with the line haul providers and with the Aviation commercial group management team.\u00a0\u00a0You also monitor the line haul performance to and from other regions, where the company owned or controlled aircraft are used.\n\nThe job holder\u2019s major responsibilities are to:\nReporting to the\u00a0Department Director, you will manage teams of supervisors and\u00a0operators to ensure effective management of transportation in the network service including daily space planning and optimize space allocation on network flights while meeting customers\u2019 requirements.\n\nYou will have to ensure timely provision of reports / information in terms of flight performance/incidents, capacity allocation, utilization, and line-haul reports, etc. to optimize capacity on network flights and improve the performance on commercials flights.\n\nYou will represent\u00a0Operation\u00a0Department\u00a0in building and maintaining good business relationship with\u00a0airlines, line-haul service providers / suppliers and negotiating for service performance improvement, flight information updating process and space booking issues.\u00a0\nYou will also be required to lead the team in proactively monitoring the inbound / outbound flight movements, providing real-time visibility of movement through systems, promptly responding to network requests and timely updates of service incidents.\n\nIn the event of potential service incidents with transit time impact, you are required to support contingency actions as planned by the regional team in order to keep the impact to its minimal.\u00a0\n\nRequirements:\n\nDegree holder, preferably in Transportation or Logistics related discipline\nLeast 10 years working experience in\u00a0flight dispatch/operation,\u00a0airline, transportation or logistics industry with supervisory level experience\nFamiliar with air transport practices and Hong Kong Customs rules and regulations is an advantage\nGood command of both spoken and written Business English and Cantonese\nStrong planning and data analysis skills\nStrong interpersonal and stakeholder management skills\nHigh level of energy, motivation and drive skills\nComfortable working in a relatively unstructured and multi-cultural environment\nLess experience will consideration as\u00a0Logistics Operation Officer\n\nOffer and Benefit :\n\n\u00a0Stable shift duty 5 Days' work in a week\u00a0\n\u00a0Medical scheme and transportation allowance\u00a0\n\u00a015 Days annul leave with annual performance bonus\n\u00a0Entitled the banking holidays with clear career promotion\u00a0\n\nMORE POSITIONS PLEASE VISIT OUR WEBSITE AT: http://www.prowess.hk\n\nWhatsApp to our consultant\u00a0:\u00a0https://wa.me/85291493008\u00a0or contact us at\u00a0+852\u00a0 2838 9621 for more information of the position.\nFor interested candidates, please submit your full resume with expected salary in MS Word format to us through the above email.\n\n", "employment_types": ["Full Time", "Permanent", "Contract"], "selling_points": ["University degree least 10 years' experience", "Ability to work in fast-paced airport environment", "Excellent planning & good operation management"], "locations": ["Airport Area"], "categories": ["Transportation & Logistics", "Aviation Services", "Management", "General Management", "Freight Forwarding"], "post_time": "2022-01-17T09:24:09Z", "salary": {"currency": null, "max": null, "min": null, "period": "monthly", "term": null}, "salary_visible": false, "title_keywords": ["officer", "logistics", "operation manager"], "responsibilities": ["reporting", "management", "maintaining", "monitoring", "teams", "systems", "reports", "booking", "planning"], "requirements": {"degrees": ["degree holder"], "majors": [], "languages": ["cantonese", "english"], "language_level": ["good command"], "hard_skills": ["whatsapp", "analysis", "airline", "scheme"], "soft_skills": ["clear", "stable", "interpersonal"], "languages_combined": [{"language": "cantonese", "language_level": ["good command"]}, {"language": "english", "language_level": ["good command"]}]}, "experience_required": {"duration": ["least 10 years"], "field": ["logistics industry", "supervisory level", "operation", "logistics"]}}, {"job_id": "100003009053628", "location_code": "hk", "company": "Cargo Services Far East Limited", "job_title": "Key Account Executive (Ocean Freight)", "description": "Take responsibility of the customer experience by managing the customers\u2019 international supply chain in coordination with relevant stakeholders;\nBuild strong customer relationships, solve customer query about operations and be curious around their business needs and drivers, to better serve them and identify new business opportunities;\nEnsure smooth execution of the end-to-end shipment lifecycle, monitor agreed service level and build operational knowledge\n\n\u00a0\nRequirements:\nUniversity graduate with a Bachelor's degree from a recognised institution\nOr holder of Higher Diploma / Associate Degree with minimum 2 years working experience in logistics industry\nStrong communication and inter-personal skills\nHigh willingness to accept responsibility and drive results\nAbility to work with a high number of teams internationally and internal stakeholders on various projects\nGood command of both written and spoken English and Chinese\nProficient with Microsoft Office applications\nWilling to learn and work under pressure\nCandidates will more experienes will also be considered senior role\nBenefits:\nDouble Pay\n\nFive-day Work Week\n\nBirthday Leave\n\nMedical Insurance\n\nFree Shuttle Bus\u00a0\n\nTraining Allowance\nAttractive remuneration package and excellent career development opportunities will be offered to the right candidates. For Interested parties, please apply with a detailed resume stating present and expected salary by clicking \"Apply Now\". You are welcome to visit our website at http://www.cargofe.com.\n\nPersonal data collected will be used for recruitment purposes only and be treated in strict confidence.\u00a0 Cargo Services treats all applicants for employment in the same way, regardless of age, sex, marriage and civil partnership, race, disability, religion or belief.", "employment_types": ["Full Time", "Permanent"], "selling_points": ["Account Management in Freight Forwarder", "Five-day work week; Double Pay; Flexi-Office-Hours", "2+ years relevant experiences or Fresh graduates"], "locations": ["Kwai Tsing Area"], "categories": ["Transportation & Logistics", "Freight Forwarding", "Supply Chain", "Sales, CS & Business Devpt", "Account Servicing"], "post_time": "2022-01-17T07:15:41Z", "salary": {"currency": null, "max": null, "min": null, "period": "monthly", "term": null}, "salary_visible": false, "title_keywords": ["key account executive"], "responsibilities": ["operations", "business opportunities", "coordination with", "monitor", "teams", "communication", "logistics", "work under pressure"], "requirements": {"degrees": ["associate degree", "university graduate", "bachelor", "diploma", "degree"], "majors": [], "languages": ["english", "chinese"], "language_level": ["good command"], "hard_skills": ["microsoft office"], "soft_skills": ["willing to learn", "inter-personal skills", "communication", "coordination", "smooth", "work under pressure"], "languages_combined": [{"language": "english", "language_level": ["good command"]}, {"language": "chinese", "language_level": ["good command"]}]}, "experience_required": {"duration": ["minimum 2 years"], "field": ["logistics industry", "supply chain"]}}, {"job_id": "100003009054923", "location_code": "hk", "company": "Eternity Consultants (HK) Ltd", "job_title": "Shipping Clerk / Operation Clerk", "description": "Trading\n\n\u00a0\u00a0Requirements:\n\nF.5\nAt least 3 -8 years shipping experience in shipping in Trading or factory\n\nFull set of I/E, L/C documents\nContact with\u00a0vendor, overseas buyer, forwarder\nExperience in USA and Europe market\nGood communication and\n\nGood commend of both English and Mandarin\n\n*Interested parties, please Email full resume with current & expected salary & date available in MS WORD FORMAT ONLY to us\u00a0or fax to 3527 0634*\n\nFor more jobs, please visit our website: www.hketernity.com\n\n(Personal data submitted are for recruitment purpose only.)", "employment_types": ["Full Time", "Permanent"], "selling_points": ["5 days, bank holiday, 10 al", "Diploma or above", "3-8 yrs shipping exp in trading, factory"], "locations": ["Not Specified"], "categories": ["Transportation & Logistics", "Freight Forwarding", "Shipping", "Supply Chain"], "post_time": "2022-01-17T14:03:14Z", "salary": {"currency": null, "max": null, "min": null, "period": "monthly", "term": null}, "salary_visible": false, "title_keywords": ["shipping clerk", "operation clerk"], "responsibilities": ["communication", "shipping", "contact"], "requirements": {"degrees": [], "majors": [], "languages": ["english", "mandarin"], "language_level": ["good"], "hard_skills": ["c", "vendor"], "soft_skills": ["communication"], "languages_combined": [{"language": "english", "language_level": ["good"]}, {"language": "mandarin", "language_level": ["good"]}]}, "experience_required": {"duration": ["at least 3 -8 years"], "field": ["trading"]}}, {"job_id": "100003009056061", "location_code": "hk", "company": "Yusen Logistics (Hong Kong) Limited", "job_title": "Assistant Supervisor / Indoor Sales", "description": "Job Descriptions:\n\nDaily works include, but not limited to:\n\nSupport outdoor sales and teammates for sales related issues, not limited to rate inquiries or prepare quotations;\nPrepare tailor-made shipments and invoices reports;\nShipment coordination and problem solving for the stakeholders;\nFollow up invoice billing, chasing outstanding payment, and credit control.\nRequirements:\n\nDegree or above in any discipline;\nRelevant freight forwarding experience is required;\nFluent in written and spoken English and Mandarin;\nProactive, good interpersonal and analytical skills.\nInterested parties please send full resume with employment history and expected salary to HRA Division, Yusen Logistics (Hong Kong) Limited at Level 31, Tower 1, Kowloon Commerce Centre, 51 Kwai Cheong Road, Kwai Chung or by email to hr.ylhk@ hk.yusen-logistics.com .\n\n\n\nYusen Logistics (Hong Kong) is an equal opportunity employer. All information collected will be used for recruitment purpose only.", "employment_types": ["Full Time", "Permanent"], "selling_points": ["Degree holder", "Relevant freight forwarding experience is required", "Proactive, good interpersonal & analytical skills"], "locations": ["Kwai Hing"], "categories": ["Transportation & Logistics", "Freight Forwarding", "Shipping", "Supply Chain"], "post_time": "2022-01-18T03:14:31Z", "salary": {"currency": null, "max": null, "min": null, "period": "monthly", "term": null}, "salary_visible": false, "title_keywords": ["assistant supervisor", "sales"], "responsibilities": ["control", "invoices", "invoice", "payment", "reports", "coordination"], "requirements": {"degrees": ["degree or above"], "majors": [], "languages": ["english", "mandarin"], "language_level": ["fluent"], "hard_skills": ["analytical skills"], "soft_skills": ["proactive", "interpersonal", "analytical skills"], "languages_combined": [{"language": "english", "language_level": ["fluent"]}, {"language": "mandarin", "language_level": ["fluent"]}]}, "experience_required": {"duration": [], "field": []}}, {"job_id": "100003009052061", "location_code": "hk", "company": "OOCL Logistics Ltd", "job_title": "Manager/Assistant Manager, Pricing, Import & Export (Ref: M/AM/OPLUS)", "description": "At global level to develop and drive procurement strategy, defining guidelines and processes for responsibilities diversification between Corporate and Regions.\u00a0Drive to generate freight volumes across regions to support expansion and optimization of\u00a0carriers\u00a0portfolio and cost.\u00a0\n\n\u00a0Responsibilities:\u00a0\n\n\nDrive the volume growth while developing, and executing plans to enable future growth of assigned accounts\u00a0\nHandle daily rate and tender / RQF enquiry\u00a0\nParticipate in market research and prepare regular rate analysis\u00a0\nAchieve full renewals of agreement\u00a0\nDevelop the customers into strategic name account tier\u00a0\nAnalyze customers\u2019 support of our products and services, promote focused trade lanes and products including core\u00a0carriers\u00a0undertakings.\u00a0\nCollaborate with sales teams in selling cycles to achieve the business deals\nAssist support teams to onboard new customers\u00a0\nParticipate to generate and define business development plans and opportunities in line with carrier procurement direction\n\nRequirements:\u00a0\n\nUniversity graduate with minimum 5 years of proven ocean freight experience in Shipping, NVOCC or Freight Forwarding industries, pricing or sales/customer service experiences in sea-freight products would be an advantage\u00a0\nAccount management skills and experience, with high proficiency in MS Word, Excel and Power-point\u00a0\nStrong sales partner development skills and the ability to build and execute plans to increase sales partner performance\u00a0\u00a0\nExcellent interpersonal, communication, teamwork, and project management skills required\u00a0\nStrong analytical, negotiation, presentation and writing skills\u00a0\nProactive, detailed-minded\u00a0\u00a0\nGood command of English and Chinese\u00a0\nInterested parties, please submit your application letter together with detailed resume and copies of your latest transcript\u00a0by clicking \u201cApply Now\u201d.\n\n(Data collected will be used for recruitment purpose only.)", "employment_types": ["Full Time"], "selling_points": ["sea freight/freight fordwarding", "procurement & sales", "pricing, tender/RQF handling"], "locations": ["Kwun Tong"], "categories": ["Transportation & Logistics", "Freight Forwarding", "Shipping", "Supply Chain"], "post_time": "2022-01-17T02:00:18Z", "salary": {"currency": null, "max": null, "min": null, "period": "monthly", "term": null}, "salary_visible": false, "title_keywords": ["manager", "assistant manager,"], "responsibilities": ["collaborate with", "analysis", "teams", "developing", "market research", "develop", "executing", "tender", "plans"], "requirements": {"degrees": ["university graduate"], "majors": [], "languages": ["english", "chinese"], "language_level": ["good command"], "hard_skills": ["excel", "project management", "writing skills", "ms word"], "soft_skills": ["negotiation", "project management skills", "teamwork", "presentation", "writing skills", "communication", "customer service", "proactive", "interpersonal", "detailed"], "languages_combined": [{"language": "english", "language_level": ["good command"]}, {"language": "chinese", "language_level": ["good command"]}]}, "experience_required": {"duration": ["minimum 5 years"], "field": ["customer service", "account management"]}}, {"job_id": "100003009053766", "location_code": "hk", "company": "Asia Shipping International Transport (HK) Limited", "job_title": "Receptionist and Administration Clerk", "description": "Job Description\n\n\u00a0\u2022 Answer incoming calls; greet visitors\n\n\u00a0\u2022 Provide logistics support, including couriers and mailings\n\n\u00a0\u2022 Handle invoice, expenses claim and other paperwork\n\n\u00a0\u2022 Manage the schedule of meetings room, organize company events\n\n\u00a0\u2022 Liaise with building management department on maintenance of office facilities\n\n\u00a0\u2022 Assist in other office administrative tasks\n\nPrepare ad-hoc assignment from time to time assigned by Supervisor.\n\n\u00a0Requirements:\n\n\u00a0\u2022 F.5/ DSE or above with experience in hospitality industry is an advantage\n\n\u00a0\u2022 Good command of English receptionist\n\n\u00a0\u2022 Good communication and interpersonal skill with positive and helpful attitude\n\n\u00a0\u2022 Be patient, cheerful personality\n\n\u00a0\u2022 Immediate available is preferred\n\n\u00a0\u2022 Fresh graduate also welcome to apply", "employment_types": ["Full Time"], "selling_points": [], "locations": ["Cheung Sha Wan"], "categories": ["Admin & HR", "Clerical / Admin Staff", "Receptionist", "Transportation & Logistics", "Freight Forwarding"], "post_time": "2022-01-17T07:29:04Z", "salary": {"currency": null, "max": null, "min": null, "period": "monthly", "term": null}, "salary_visible": false, "title_keywords": ["receptionist", "clerk"], "responsibilities": ["ad-hoc", "maintenance", "invoice", "expenses", "provide logistics support", "building management", "schedule", "liaise with", "administrative tasks"], "requirements": {"degrees": ["fresh graduate", "dse"], "majors": ["hospitality"], "languages": ["english"], "language_level": ["good command"], "hard_skills": [], "soft_skills": ["cheerful", "interpersonal skill", "communication", "patient", "positive"], "languages_combined": [{"language": "english", "language_level": ["good command"]}]}, "experience_required": {"duration": [], "field": ["hospitality industry"]}}, {"job_id": "100003009051991", "location_code": "hk", "company": "Schenker International (H.K.) Limited", "job_title": "Customer Services Representative - Airfreight (Ref No: JD/AIR/029/220117)", "description": "The incumbent is responsible for handling customers' bookings and declarations, monitoring transportation issues, tracking and tracing shipments, and answering customers' enquiries.\n\nYour tasks\n\nArrange booking to carriers\nVerify the correctness of document provided by shipper and for licensed shipment\nPrepare export document for DG shipments\nLiaise with warehouse department and contractors to ensure the consolidation plan loaded and delivered to terminal in timely manner\n\nYour qualifications, experience & skills:\n\nHigher Diploma or above\nWith\u00a01-3 year working experience will be an advantage\nGood command of written and spoken English and Mandarin\nGood communication skills and customer-oriented\nBasic knowledge\u00a0in MS Office including MS Word and Excel\nWork location: Tsing Yi\nCandidate with more experiences will be considered as Senior CS Representative\nFresh graduate will also be considered\n\nInterested? We are looking forward to receiving your online application including availability and salary expectations.\n\n(Please quote the Job Reference Number on the subject of your application)\n\n(All information collected will be used for recruitment purpose only)\n\nTo know more about us, please visit\u00a0www.dbschenker.com/cn", "employment_types": ["Full Time", "Permanent"], "selling_points": ["Customer Services", "Fresh graduate will also be considered", "Double pay, Bonus, Medical Insurance"], "locations": ["Tsing Yi"], "categories": ["Sales, CS & Business Devpt", "Customer Service - Supervisor / Officer", "Transportation & Logistics", "Freight Forwarding", "Others", "Student / Fresh Graduate / No Experience"], "post_time": "2022-01-17T01:46:24Z", "salary": {"currency": null, "max": null, "min": null, "period": "monthly", "term": null}, "salary_visible": false, "title_keywords": ["customer services representative"], "responsibilities": ["monitoring", "communication", "booking", "plan", "liaise with", "tracking"], "requirements": {"degrees": ["higher diploma or above"], "majors": [], "languages": ["english", "mandarin"], "language_level": ["good command"], "hard_skills": ["excel", "basic", "bookings", "ms office", "ms word"], "soft_skills": ["communication skills", "timely", "customer-oriented", "responsible"], "languages_combined": [{"language": "english", "language_level": ["good command"]}, {"language": "mandarin", "language_level": ["good command"]}]}, "experience_required": {"duration": ["1-3 year"], "field": []}}, {"job_id": "100003009054217", "location_code": "hk", "company": "Brink's Hong Kong Limited", "job_title": "Jewellery Show Coordinator", "description": "Responsibilities\n\nProvide high quality customer services and maintain a good relationship with our existing clients\nProvide on-site assistance; pre-show and after-show secure delivery service support to the exhibitors\u00a0\nLiaise with internal department and Shows organizers to ensure and to secure the efficient delivery service for the exhibitors\nPerform ad hoc tasks assigned by team head/manager\nOpportunities for overseas business trips\n\nRequirements\n\nHigher Diploma or above, preferably in Logistic & Supply Chain Management, Business Studies or other related disciplines\n1 year relevant working experience preferred (experience in operations will be an advantage)\nStrong customer service, communication and project management skills\nMature, responsible, proactive, outgoing, well-organized and detail-minded\u00a0\nAble to work independently under pressure and meet tight deadlines\nGood command of both spoken and written English, Chinese and Mandarin\nProficiency in MS office\nImmediate available is highly preferred\n\nWe offer attractive remuneration package fringe benefits including\u00a0Banking Holiday, Annual Leaves, Discretionary Bonus, Additional Pension Contribution from Company, Medical Insurance, etc.\u00a0If you have the desire to join us, please send us your resume immediately with your present and expected salary by clicking \"Apply Now\"\n\n(The information provided will be used for employment related\u00a0purpose only. All information of unsuccessful applicants will be destroyed within six months.)", "employment_types": ["Full Time", "Permanent"], "selling_points": ["Exciting Opportunity to work in a unique business", "Friendly working environment", "Fresh graduates are also welcome"], "locations": ["Hung Hom"], "categories": ["Transportation & Logistics", "Freight Forwarding", "Marketing / Public Relations", "Public Relations - Event Management", "Others", "Student / Fresh Graduate / No Experience"], "post_time": "2022-01-17T08:50:16Z", "salary": {"currency": null, "max": null, "min": null, "period": "monthly", "term": null}, "salary_visible": false, "title_keywords": ["coordinator"], "responsibilities": ["quality", "ad hoc tasks", "customer services", "good relationship", "maintain", "liaise with"], "requirements": {"degrees": ["higher diploma or above"], "majors": ["related disciplines", "business"], "languages": ["english", "chinese", "mandarin"], "language_level": ["good command"], "hard_skills": ["project management", "ms office"], "soft_skills": ["outgoing", "detail-minded", "work independently", "meet tight deadlines", "under pressure", "responsible", "project management skills", "well-organized", "mature", "communication", "customer service", "proactive"], "languages_combined": [{"language": "english", "language_level": ["good command"]}, {"language": "chinese", "language_level": ["good command"]}, {"language": "mandarin", "language_level": ["good command"]}]}, "experience_required": {"duration": ["1 year"], "field": ["relevant working experience"]}}, {"job_id": "100003009051981", "location_code": "hk", "company": "HCT GROUP", "job_title": "Order Fulfillment Coordinator", "description": "Responsibilities:\n\n\u00a0\u00a0\u00a0\u00a0\u00a0 Manage the team for internally and externally regarding orders and transportation needs.\n\u00a0\u00a0\u00a0\u00a0\u00a0 Daily monitoring of client\u2019s EDI or web-based systems for PO\u2019s, updates and shipment details.\n\u00a0\u00a0\u00a0\u00a0\u00a0 Achieve timely dispatches with domestics and overseas vendors.\n\u00a0\u00a0\u00a0\u00a0\u00a0 Utilize various functions in SAP, including but not limited to item setup, creating orders, goods receipt, delivery, etc.\n\u00a0\u00a0\u00a0\u00a0\u00a0 Initiate timely invoicing and work closely with accounting department to ensure billing accuracy.\n\u00a0\u00a0\u00a0\u00a0\u00a0 Various SAP projects or other duties as they arise.\n\nRequirements:\n\n\u00a0\u00a0\u00a0\u00a0\u00a0 Hong Kong permanent resident\n\u00a0\u00a0\u00a0\u00a0\u00a0 1-2 years of experience in the field of purchasing or logistics\n\u00a0\u00a0\u00a0\u00a0\u00a0 Quick learner, detail oriented with proven ability to work efficiently with high accuracy\n\u00a0\u00a0\u00a0\u00a0\u00a0 Exceptional organization and time management skills with the ability to work effectively independently and in a team environment\n\u00a0\u00a0\u00a0\u00a0\u00a0 Strong knowledge of import/export documentation and solid understanding of Inco terms\n\u00a0\u00a0\u00a0\u00a0\u00a0 Proficiency in SAP (or other operating systems) Outlook, Excel and Word is required\n\u00a0\u00a0\u00a0\u00a0\u00a0 Strong verbal/written communication skills (English and Chinese) are essential\n\u00a0\u00a0\u00a0\u00a0\u00a0 Fluent in both spoken and written English, Mandarin and Cantonese.\n\u00a0\u00a0\u00a0\u00a0\u00a0 Ability to gather and analyze data and work with figures communicate effectively both narration and in writing\n\nWe offer 5 days work, attractive salary, medical insurance, harmony and excellent working environment to right candidate. Interested parties please send full resume in\u00a0MS Word\u00a0format, present and expected salary with full confidence attention to Ms. Mak.\n\nYou are welcome to visit our HCT Group website: https://hctgroup.com\n\n* ALL PERSONAL DATA RECEIVED WILL BE TREATED CONFIDENTIALLY AND USED FOR RECRUITMENT PURPOSE ONLY.*", "employment_types": ["Full Time"], "selling_points": [], "locations": ["Sheung Wan"], "categories": ["Transportation & Logistics", "Freight Forwarding", "Fulfillment", "Supply Chain"], "post_time": "2022-01-17T01:44:54Z", "salary": {"currency": null, "max": null, "min": null, "period": "monthly", "term": null}, "salary_visible": false, "title_keywords": ["coordinator"], "responsibilities": ["other duties", "systems", "invoicing", "daily monitoring", "setup"], "requirements": {"degrees": [], "majors": [], "languages": ["cantonese", "english", "chinese", "mandarin"], "language_level": ["fluent"], "hard_skills": ["excel", "sap", "word", "outlook", "documentation"], "soft_skills": ["work effectively", "communication skills", "independently", "time management skills", "detail oriented", "quick learner"], "languages_combined": [{"language": "cantonese", "language_level": ["fluent"]}, {"language": "english", "language_level": ["fluent"]}, {"language": "chinese", "language_level": []}, {"language": "mandarin", "language_level": ["fluent"]}]}, "experience_required": {"duration": ["1-2 years"], "field": ["purchasing", "logistics"]}}, {"job_id": "100003009056089", "location_code": "hk", "company": "The Jockey Club Kau Sai Chau Public Golf Course Ltd", "job_title": "\u6c34\u624b", "description": "\u8077\u8cac :\u5354\u52a9\u8239\u9577\u548c\u8f2a\u6a5f\u64cd\u4f5c\u54e1\u9032\u884c\u5ba2\u8259\u5167\u5916\u7684\u5404\u9805\u5de5\u4f5c\uff0c\u5354\u52a9\u63a5\u5f85\u4e58\u5ba2\u5b89\u5168\u5730\u4e0a\u843d\u8239\u96bb\uff0c\u4e00\u5e74\u5408\u7d04\n\u8cc7\u6b77 :\u6c92\u6709\u5b78\u6b77\u8981\u6c42; 1\u5e74\u7d93\u9a57; \u826f\u597d\u7cb5\u8a9e; \u4e00\u822c\u82f1\u8a9e; \u61c2\u8b80\u5beb\u4e2d\u6587; \u7565\u61c2\u8b80\u5beb\u82f1\u6587; \u9808\u5177\u5099\u57fa\u672c\u8239\u85dd\u53ca\u8239\u8236\u5b89\u5168\u77e5\u8b58\uff0c\u6709\u76f8\u95dc\u5de5\u4f5c\u7d93\u9a57\u512a\u5148\n\u5f85\u9047 :\u6bcf\u6708$13,000, \u6709\u5e74\u504712\u5929, \u5728\u8077\u57f9\u8a13, \u91ab\u7642\u4fdd\u96aa, \u6649\u5347\u6a5f\u6703, \u4f9b\u81b3\u98df \u53ca\u7d04\u6eff\u916c\u91d1, 24\u5c0f\u6642\u5de5\u4f5c\u53ca24\u5c0f\u6642\u4f11\u606f\u4e4b\u8f2a\u73ed\u4ea4\u66ff, \u6bcf\u9031\u5de5\u4f5c3\u5929\n\u7533\u8acb\u9808\u77e5 :\u6c42\u8077\u8005\u53ef\u81f4\u96fb27913373\u8207THE JOCKEY CLUB KAU SAI CHAU PUBLIC GOLF COURSE LTD\u5f35\u5148\u751f\u806f\u7d61\u3002", "employment_types": ["Full Time", "Contract"], "selling_points": [], "locations": ["Sai Kung"], "categories": ["Transportation & Logistics", "Freight Forwarding", "Shipping"], "post_time": "2022-01-18T03:15:52Z", "salary": {"currency": null, "max": null, "min": null, "period": "monthly", "term": null}, "salary_visible": false, "title_keywords": [], "responsibilities": [], "requirements": {"degrees": [], "majors": [], "languages": [], "language_level": [], "hard_skills": [], "soft_skills": [], "languages_combined": []}, "experience_required": {"duration": [], "field": []}}, {"job_id": "100003009054875", "location_code": "hk", "company": "Cathay Pacific Services Limited", "job_title": "Senior Business Intelligence Specialist", "description": "Responsibilities:\n\nConduct cargo terminal capacity review\u00a0for demand growth and new business development\nDevelop capacity modelling to expedite the capacity review / forecast process\u00a0\nConduct performance benchmarking/facility/resources planning study and prepare project brief/documents in support of new business development\nProvide analytics support to develop BI solutions including performance and forecast dashboards\nWork closely with IT Department to automate data reporting with actionable insights to facilitate decision making process\u00a0\nSupport for other ad-hoc analytics development projects\u00a0\nRequirements:\nUniversity degree in Statistics, Operations Research, Industrial Engineering, Logistics or related quantitative disciplines\nMinimum 6 years relevant experience in data analytics, data modelling or statistical analysis, preferably in Logistics industry\nStrong analytical and problem-solving skills, ideally with exposure in business intelligence project\nExposure in air cargo terminal operations will be a definite advantage\nProficient in Microsoft Excel, data visualisation tools such as Tableau, Power BI and knowledge in VBA programming is a plus\nFluent written and spoken English\nStrong influencing and interpersonal skills to interact with people at all levels of diverse\nSelf-motivated and good team player/project management skill\n\nTo apply, you may simply click the \"Apply Online\" or\u00a0email your confidential resume with date of availability, current and expected salary to\u00a0recruitment @cpsl.com.hk. Applicants not contacted within 6 weeks may consider their applications unsuccessful.\n\nCathay Pacific Services Limited is an Equal Opportunities Employer. Personal data provided by job applicants will be used strictly in accordance with our personal data policy and for recruitment purposes only. Candidates not notified within six weeks may consider their application unsuccessful. All related information will be kept in our file for up to 24 months.", "employment_types": ["Full Time", "Permanent"], "selling_points": ["Conduct Cargo Terminal Capacity Review", "Develop Capacity Modelling", "Conduct Performance Benchmarking Study"], "locations": ["Lantau Island"], "categories": ["Professional Services", "Business Analysis / Data Analysis", "Sales, CS & Business Devpt", "Business Development", "Transportation & Logistics", "Freight Forwarding"], "post_time": "2022-01-17T12:16:25Z", "salary": {"currency": null, "max": null, "min": null, "period": "monthly", "term": null}, "salary_visible": false, "title_keywords": ["specialist"], "responsibilities": ["ad-hoc", "reporting", "forecast process", "data", "review", "develop", "forecast", "planning"], "requirements": {"degrees": ["university degree"], "majors": ["statistics", "engineering"], "languages": ["english"], "language_level": ["fluent"], "hard_skills": ["vba", "plus", "bi", "statistical analysis", "data analytics", "tableau", "microsoft excel", "project management", "programming", "problem-solving skills", "business intelligence"], "soft_skills": ["self-motivated", "good team player", "diverse", "interpersonal skills", "project management skill", "problem-solving skills"], "languages_combined": [{"language": "english", "language_level": ["fluent"]}]}, "experience_required": {"duration": ["minimum 6 years"], "field": ["logistics industry", "relevant experience"]}}, {"job_id": "100003009052245", "location_code": "hk", "company": "METRO Sourcing International Limited", "job_title": "Logistics Specialist (Freight Analysis and Invoice handling)", "description": "Role Purpose:\n\nOur Logistics Specialist is in-charge of freight analysis, handling logistics invoices, mastering vary logistics data and prepare report with insight to management.\n\nTasks for a typical day:\n\nResponsible for logistics cost and income, fully in charge of freight rates and logistics services database\nIn-charge of logistics invoices checking, verification and trouble shooting (on e.g. rates, system, EDI, etc.)\nControl special invoices and work with accounting / controlling for payment\nWork closely with internal and external business partners to ensure the data accuracy in internal buying system\nFollow up various indexes (spot freight, bunker\u2026) and report weekly\nMonitor the performance of 3PL and other service providers (accuracy, on-time invoicing, business handling\u2026), and ensure the achievement of KPI\nTurn data / information into insights for business decisions and business opportunities. Provide various reports and presentations as needed\nProactive to identify potential supply chain issues and initiate preventive and continuous improvement projects\nTalent that we are looking for:\n\nSolid experience and industry expertise\nExcellent problem solving and project management skills\nCapable to manage complex business content\nHigh level of analytical skill, sensitive to data\nStrong presentation and negotiation skills\nWell organized, attention to details with solution-oriented mindset\nAbility to bring about change\nEnergetic to drive for customer success and excellent service\nPossess strong sense of ownership and high degree of independence\nPassionate in connecting with people\nExperience, knowledge and skills required:\n\nDegree holder in Logistics, Supply Chain Management or equivalent discipline\nAt least 5 years\u2019 relevant experience in multi-national trading companies or 3PL / Carriers\nExpertise in MS Excel, especially with using pivot table and formulas to handle complex database\nExperience with Logistics IT software solution / ERP system is advantageous\nProficient in both spoken and written English\nProficient in MS Office (Word / PowerPoint / Outlook) applications\nYou can enjoy:\n\nDiverse and Inclusive work environment\nFlexi Office Space with flexible working hours and home office option\n5-day work week, 13th month salary & performance bonus\nProfessional training and career advancement opportunities\nTraining Sponsorship for personal professional development\nJoin us and apply now\u00a0!\nPlease send your full resume with available date, present and expected salary to us.\nResume and personal data collected will be kept strictly confidential and used for recruitment purpose only.", "employment_types": ["Full Time", "Permanent"], "selling_points": ["Solid exp in logistics analysis & problem solving", "Resp. for freight analysis & invoices handling", "MNC, 5-day work, insurance, double pay, bonus"], "locations": ["Kowloon Bay"], "categories": ["Transportation & Logistics", "Documentary Credit / Bills Processing", "Freight Forwarding", "Supply Chain"], "post_time": "2022-01-17T02:32:53Z", "salary": {"currency": null, "max": null, "min": null, "period": "monthly", "term": null}, "salary_visible": false, "title_keywords": ["logistics specialist"], "responsibilities": ["software", "data", "payment", "database", "personal data", "continuous improvement projects", "control", "invoices", "presentations", "logistics", "reports", "report", "prepare report", "management", "cost", "business opportunities", "checking", "analysis", "invoicing", "project management", "recruitment", "monitor the performance"], "requirements": {"degrees": ["degree", "degree holder"], "majors": [], "languages": ["english"], "language_level": ["proficient"], "hard_skills": ["analytical skill", "analysis", "pivot table", "word", "presentations", "powerpoint", "problem solving", "project management", "ms excel", "erp system", "outlook", "ms office"], "soft_skills": ["passionate", "flexible", "analytical skill", "capable", "responsible", "project management skills", "well organized", "problem solving", "diverse", "sensitive to", "negotiation skills", "energetic", "attention to details", "proactive", "presentation"], "languages_combined": [{"language": "english", "language_level": ["proficient"]}]}, "experience_required": {"duration": ["at least 5 years"], "field": ["erp system", "it", "logistics", "relevant experience", "trading"]}}, {"job_id": "100003009052085", "location_code": "hk", "company": "\"K\" Line Logistics (Hong Kong) Ltd", "job_title": "Assistant Accountant (RE0122/01)", "description": "\u201cK\u201d Line Logistics (Hong Kong) Limited is a global logistics company offering total logistics solution including air and ocean freight, land transport and distribution etc.\u00a0 Our headquarters is based in Japan and our international network links more than 150 countries and cities worldwide. To cope with our expansion, we are inviting high caliber professional for the following position:\n\nASSISTANT ACCOUNTANT\u00a0\n\u00a0\n(Working location: Lai Chi Kok)\n\nThis position will be responsible to handle daily bank operations including payment & receipt vouchers as well as autopay arrangement, bank reconciliation, book-keeping, staff reimbursement. You are required to handle some ad hoc jobs.\n\n\nRequirements:\n\nForm 5 / DSE or above, Diploma or above in Accounting discipline;\nLCCI higher / ACCA level 1 or above;\nAt least 1 year accounting experience in which exposure in freight forwarder industry is an advantage;\nGood in spoken and written English and Chinese, Mandarin speaking is an advantage;\nGood computer skills with MS Office, Flex Accounting is preferable;\nStrong in communication and problem solving skills;\nDetailed minded, reliable, self-motivated and team player;\nImmediate available preferred\n\nWe offer attractive fringe benefits which include 5 days work-week, Double Pay, Performance Bonus, Training Allowances, Overtime Allowances, Medical & Dental Scheme, Mandatory Provident Fund and 12-21 days Annual Leave.\n\nIf you are interested in this position, please send application with detailed qualifications, experience, current and expected salary by click \u201cApply Now\u201d to submit your application.\n\n(All information provided are kept confidential and all personal data provided will be used for the recruitment purpose only)\n", "employment_types": ["Full Time", "Permanent"], "selling_points": [], "locations": ["Lai Chi Kok"], "categories": ["Accounting", "Accounting Clerk / Supervisor", "Others", "Transportation & Logistics", "Freight Forwarding"], "post_time": "2022-01-17T02:03:36Z", "salary": {"currency": null, "max": null, "min": null, "period": "monthly", "term": null}, "salary_visible": false, "title_keywords": ["assistant accountant"], "responsibilities": ["ad hoc", "operations", "bank reconciliation", "communication", "payment", "logistics", "book-keeping", "recruitment", "personal data", "autopay"], "requirements": {"degrees": ["diploma or above", "form 5", "dse"], "majors": ["accounting"], "languages": ["english", "chinese", "mandarin"], "language_level": ["advantage", "good"], "hard_skills": ["acca", "scheme", "flex accounting", "computer skills", "problem solving skills", "ms office"], "soft_skills": ["self-motivated", "responsible", "interested in", "communication", "team player", "problem solving skills", "reliable", "detailed"], "languages_combined": [{"language": "english", "language_level": ["advantage", "good"]}, {"language": "chinese", "language_level": ["advantage", "good"]}, {"language": "mandarin", "language_level": ["good"]}]}, "experience_required": {"duration": ["at least 1 year"], "field": ["accounting experience"]}}, {"job_id": "100003009054914", "location_code": "hk", "company": "Cathay Pacific Services Limited", "job_title": "Assistant Project Manager", "description": "Responsibilities:\n\nContribute to strategy and business model design of the business development projects, in particular Greater Bay Area, e-commerce business segment\n\u00a0Assist the Project Manager to organize the needs/requirements from different stakeholders and organize them into an actionable plan\nSupport overall project management execution and work streams deliverables (e.g. project planning, milestones execution and monitoring)\nCoordinate with different stakeholders to organize the project expectations\nEvaluate and identify challenges and utilizes resources to solve problems\nOrganize and track all project documents\nSupport design of project details and solutions through interpreting analysis findings, market information and working with relevant stakeholders (e.g operations, Engineering, IT)\nConduct research and propose initiatives to support the key business development project\u00a0\nKeep abreast on latest technology / best practices within the industry and deliver changes to support the strategy formulation\n\n\u00a0\nRequirements:\n\n\n\nAccredited university bachelor or master degrees\nMinimum 5 years relevant experience preferably in the logistics or consultancy industry, of which minimum 2 years in a supervisory level or above\nPRC exposure is an advantage\nSolid experience in strategic planning, market research and project management\nStrategic thinking mind-set to propose business development initiatives and strategy\nExcellent presentation skills, able to articulate complex ideas in simple terms\nAn effective communicator to interact with people at all levels and in multicultural environment with strong influencing and interpersonal skills\nExtensive PowerPoint knowledge and skills\nHighly motivated and strong perseverance\n\nTo apply, you may simply click the \"Apply Online\" or\u00a0email your confidential resume with date of availability, current and expected salary to\u00a0recruitment @cpsl.com.hk. Applicants not contacted within 6 weeks may consider their applications unsuccessful.\n\nCathay Pacific Services Limited is an Equal Opportunities Employer. Personal data provided by job applicants will be used strictly in accordance with our personal data policy and for recruitment purposes only. Candidates not notified within six weeks may consider their application unsuccessful. All related information will be kept in our file for up to 24 months.\n\n", "employment_types": ["Full Time", "Permanent"], "selling_points": ["Contribute to business development projects", "PRC exposure", "Project Management"], "locations": ["Airport Area"], "categories": ["Transportation & Logistics", "Freight Forwarding", "Marketing / Public Relations", "Marketing - Market Research", "E-commerce", "Business Development"], "post_time": "2022-01-17T13:41:12Z", "salary": {"currency": null, "max": null, "min": null, "period": "monthly", "term": null}, "salary_visible": false, "title_keywords": ["assistant project manager"], "responsibilities": ["project planning", "market information", "operations", "analysis", "monitoring", "coordinate with", "design", "evaluate", "project management", "project documents", "plan", "conduct research"], "requirements": {"degrees": ["bachelor", "master"], "majors": [], "languages": [], "language_level": [], "hard_skills": ["simple", "project management", "powerpoint"], "soft_skills": ["strategic thinking", "project management", "presentation skills", "motivated", "interpersonal skills", "articulate", "communicator", "extensive"], "languages_combined": []}, "experience_required": {"duration": ["minimum 2 years", "minimum 5 years"], "field": ["market research", "project management", "logistics", "relevant experience", "supervisory level", "planning"]}}, {"job_id": "100003009052238", "location_code": "hk", "company": "Drake Overload Ltd", "job_title": "Senior Business Development Manager - Freight Forwarding", "description": "Our Client\nOur client is a leading freight forwarding company with strong presence across the globe. Due to business needs, they are now seeking for a high caliber Business Development Manager to join their team.\n\nThe Role\n\n\nIdentify new business prospects & partnership and develop relationship with potential clients\nExpand client portfolios with focus in international freight focus\nDevelop business development strategies in order to grow market share\nConduct daily sales visit and coordinate sales activities with operation teams \u00a0\nHandle adhoc projects as assigned\n\nTo Qualify\n\nBachelor degree in logistics or related disciplines\n8 years of Business Development experience in Freight Forwarding industry\nExcellent Interpersonal and negotiation skill\nIndependent and able to work under pressure\nStrong analytical skills & business acumen\nProficient in both English & Chinese\nCandidate with less experience will be consider as Business Development Manager\nImmediate available is highly desirable\n\nTo Apply\nIf you have the right personality and professionalism to make an impact with this firm, don\u2019t miss this rare opportunity! Please click the Apply now button or email\u00a0achoi @ drake.com.hk\u00a0for more information.\u00a0\nDue to the volume of applicants, only shortlisted candidates will be notified.\u00a0", "employment_types": ["Full Time"], "selling_points": ["International Freight Forwarding Company", "8 yrs. of BD exp. in freight forwarding/logistics", "Double Pay w/ competitive remuneration package"], "locations": ["Others"], "categories": ["Sales, CS & Business Devpt", "Business Development", "Transportation & Logistics", "Freight Forwarding", "Account Servicing"], "post_time": "2022-01-17T02:31:46Z", "salary": {"currency": null, "max": null, "min": null, "period": "monthly", "term": null}, "salary_visible": false, "title_keywords": ["senior business development manager"], "responsibilities": ["sales activities", "teams", "develop", "coordinate", "logistics", "work under pressure"], "requirements": {"degrees": ["degree", "bachelor"], "majors": ["related disciplines"], "languages": ["english", "chinese"], "language_level": ["proficient"], "hard_skills": ["make", "focus", "acumen", "analytical skills"], "soft_skills": ["independent", "business acumen", "analytical skills", "negotiation skill", "focus", "interpersonal", "work under pressure"], "languages_combined": [{"language": "english", "language_level": ["proficient"]}, {"language": "chinese", "language_level": ["proficient"]}]}, "experience_required": {"duration": ["8 years"], "field": ["business development"]}}, {"job_id": "100003009053308", "location_code": "hk", "company": "DHL Global Forwarding (Hong Kong) Limited", "job_title": "Executive, Business Solution, Asia Pacific (with less experience will be considered)", "description": "Working Location : Kwai Hing\n\nResponsibilities:\n\nTo support Solution improvements for existing accounts\nTo support new business development by building creative solutions to meet customer needs\nTo support the implementation of new business and existing clients\nTo strive for positive feedback from global / region network\nTo support senior management in developing knowledge and skill sets that differentiate DHL from the competition in meeting the needs of Key customers in AP and Globally\nTo identify areas of improvement and provide suggestions for advanced solutions\nTo support Global Business Solutions teams\n\nRequirements:\n\nDegree qualified or higher in supply chain discipline\nExperience in exporting from Asia, consolidation, and ideally ocean & air freight in logistics industry\nKnowledge of Asia-Pacific freight forwarding, warehousing and logistics business practices\nKnowledge in basic EDI and API setup, ISC systems in particular (Infor Nexus, MicroStratagies) is an advantage\nStrong planning and analytical skills\nStrong problem solving-skills, with ability to think outside of the box\nStrong communication and interpersonal skills\nDetail oriented, self-motivated and good team player\nAble to work independently\nFluent in both written and spoken English and Chinese, knowledge in Mandarin is an advantage\nRemarks: Less experience or Fresh Graduate who is willing to learn and grow with DHL\u00a0will be also considered as Senior Coordinator\n5 days work, career development, attractive remuneration and benefits package will be offered to the right candidate.\nApplications will be treated in strict confidence. Please send application with full particulars of qualifications, experience, current and expected salary\u00a0by clicking the\u00a0Apply now\u00a0button\u00a0or\u00a0by post to Human Resources Department, 4/F, EDGE, Nos. 30 \u2013 34 Kwai Wing Road, Kwai Chung, New Territories, Hong Kong.\u00a0\u00a0\nApplicants not contacted within six weeks may consider their applications unsuccessful.\u00a0\nPersonal Information Collection Statement pertaining to Recruitment\nDHL ISC (Hong Kong) Limited (\u201cDHL\u201d) is committed to protecting and respecting your privacy in accordance with the Personal Data (Privacy) Ordinance of Hong Kong (the \u201cOrdinance\u201d) and DHL\u2019s Personal Data Protection Policy (the \u201cPolicy\u201d) at\u00a0http://www.dhl.com.hk/en/legal.html#pdpp\nBy proceeding to respond to this recruitment advertisement you consent that we may use, retain, process, transfer or otherwise handle the personal data that we collect from you for recruitment purposes (including any other purposes directly related thereto) in accordance with the Policy.\nAll personal data of unsuccessful applicants will be retained for future recruitment purposes for a period of not more than six (6) months, after which such data will be destroyed.\nYou have the right at any time to make a data access or correction request concerning your personal data held by us. In addition, you may request us to delete your personal data that is no longer required for the relevant purposes which you have given consent. Should you wish to exercise such rights or have any question in relation to your personal data or the Policy, please contact our Human Resources Department.\nWhat is International Supply Chain (ISC)\nAn International Supply Chain Management service providing end-to-end order management, visibility and reporting for customers\u2019 international shipment flows across all transportation modes.\nThe solution links the origin supply chain with the destination requirements, resulting in a more cost effective and efficient supply chain with complete visibility and control.", "employment_types": ["Full Time", "Permanent"], "selling_points": [], "locations": ["Kwai Hing"], "categories": ["Transportation & Logistics", "Freight Forwarding", "Shipping", "Supply Chain"], "post_time": "2022-01-17T06:44:16Z", "salary": {"currency": null, "max": null, "min": null, "period": "monthly", "term": null}, "salary_visible": false, "title_keywords": ["executive"], "responsibilities": ["ap", "teams", "implementation", "developing", "senior management"], "requirements": {"degrees": ["degree", "fresh graduate"], "majors": [], "languages": ["english", "chinese", "mandarin"], "language_level": ["advantage", "fluent"], "hard_skills": ["problem solving", "basic", "analytical skills"], "soft_skills": ["self-motivated", "good team player", "work independently", "detail oriented", "willing to learn", "analytical skills", "problem solving", "communication and interpersonal skills"], "languages_combined": [{"language": "english", "language_level": ["advantage", "fluent"]}, {"language": "chinese", "language_level": ["advantage", "fluent"]}, {"language": "mandarin", "language_level": ["advantage", "fluent"]}]}, "experience_required": {"duration": [], "field": ["logistics industry", "consolidation"]}}, {"job_id": "100003009049734", "location_code": "hk", "company": "P & A Consultant Limited", "job_title": "Shipping Clerk/Shipping Supervisor/Sea/Air Operation Clerk(Garment/Forwarder)X4(Urgent )", "description": "Shipping Clerk / Senior Shipping Clerk / Shipping Supervisor\u00a0\nLocation : Kwun Tong/ Central/ Kwai Chung, 5 Days , salary : 14-25K\u00a0\u00a0\n\n\nResponsibilities :\u00a0\n\nHandle full set of\u00a0I/E\u00a0Shipping document, L/C document\u00a0and declaration\nCoordinate with freight forwarders and shipping companies for shipment and transportation arrangement\u00a0\n\u00a0Monitor shipment status and order follow up\n\u00a0Other ad-hoc tasks designated by the supervisor\nRequirements\n\nF.5\u00a0or above\n2-15 years relevant working experience\nShipping Supervisor position must have LC exp\u00a0\nExcellent communication and interpersonal skill\nProficiency in computer knowledge\nGood command of English and Chinese\nSea or Air Operation Supervisor / Operation Clerk /Shipping Clerk/ Clerk x3( Urgent )\u00a0\n( Kwai Chung/ Tsuen Wan) 5 Days, Salary :13-22K\u00a0\nRequirements:\nF.5 or above, passed in English is preferred\u00a0\n0-3 year or above working experience in Shipping or Forwarder\nGood Command of English and Chinese, Mandarin Speaking will be an advantage\nHandle shipping document, packing list, invoice, etc...\u00a0\nMake sure the goods on time deliver accurately\nHave Forwarder exp is preferred but is not must\u00a0\nAny ad hoc assignment designated by the supervisor\nCandidates have less exp or Trading Shipping Exp also will be consider\u00a0\n\n\n\u00a0*** Personal data will be treated with strict confidential and used for recruitment purpose only.\n\nP & A consultant Ltd will not charge any fees from the above-stated job-seeker, your job apply to our company means your acceptance of our terms and conditions.", "employment_types": ["Full Time"], "selling_points": [], "locations": ["Kwun Tong"], "categories": ["Transportation & Logistics", "Freight Forwarding", "Inventory / Warehousing", "Shipping"], "post_time": "2022-01-15T03:50:35Z", "salary": {"currency": null, "max": null, "min": null, "period": "monthly", "term": null}, "salary_visible": false, "title_keywords": ["shipping clerk", "shipping supervisor"], "responsibilities": ["shipping", "ad-hoc tasks", "monitor", "coordinate with", "shipping document"], "requirements": {"degrees": [], "majors": [], "languages": ["english", "chinese", "mandarin"], "language_level": ["advantage", "good command"], "hard_skills": ["make", "wan", "shipping document"], "soft_skills": ["communication", "interpersonal skill"], "languages_combined": [{"language": "english", "language_level": ["advantage", "good command", "good command"]}, {"language": "chinese", "language_level": ["advantage", "good command", "good command"]}, {"language": "mandarin", "language_level": ["advantage", "good command"]}]}, "experience_required": {"duration": ["2-15 years", "0-3 year"], "field": ["relevant working experience"]}}, {"job_id": "100003009051053", "location_code": "hk", "company": "Air & Ground Logistics (H.K.) Limited", "job_title": "Senior Operations / Operations", "description": "Vacancy:\u00a0Senior Operations / Operations\n\nDuties & Responsibilities:\u00a0\u00a0\n\nAble to handle full set of ocean export/import shipment\u00a0 \u00a0\u00a0\nFollow up shipment status and handle ocean customers\nHandle daily operation related enquiries and correspondence\nLiaise with liner, co-loader and overseas offices/agents for shipment arrangement\n\n\u00a0Requirements:\n\nAble to handle full set of sea freight document and documentation\nAt least 2 years sold experience in sea freight operation\n\nSalary: Negotiable", "employment_types": ["Full Time"], "selling_points": [], "locations": ["Kwai Fong"], "categories": ["Transportation & Logistics", "Freight Forwarding"], "post_time": "2022-01-15T01:33:36Z", "salary": {"currency": null, "max": null, "min": null, "period": "monthly", "term": null}, "salary_visible": false, "title_keywords": ["operations", "senior operations"], "responsibilities": ["liaise with", "daily operation", "shipment arrangement"], "requirements": {"degrees": [], "majors": [], "languages": [], "language_level": [], "hard_skills": ["documentation"], "soft_skills": [], "languages_combined": []}, "experience_required": {"duration": ["at least 2 years"], "field": ["operation"]}}, {"job_id": "100003009055185", "location_code": "hk", "company": "FedEx Trade Networks Transport & Brokerage (Hong Kong) Limited", "job_title": "Hong Kong Management Trainee 2022", "description": "FedEx Management Trainee Program is designed to groom and develop young talents of high caliber as future leaders of FedEx.\u00a0 The 36-month program provides an excellent opportunity for a Management Trainee (MT) to gain an exposure and development in FTN.\u00a0 MT will go through on-the-job trainings, job rotation and get practical work experience including the chances of assuming an overseas assignment in APAC region. Upon completion of the 36-month training, it is expected that the Management Trainee will be assigned a permanent position at FTN.\n\n\u00a0What are the benefits for you?\n\n3-Year Program\nJob Rotation\nOverseas Assignment Opportunities\nOn-the-job Training\nCoaching & Buddy Support\nSenior Management Mentoring\n\nWhat do we offer?\u00a0\n\n14-month Pay\nDiscretionary Bonus\nMedical & Dental Benefits\nSpecial Leave\nFamily-friendly Leave\n\nResponsibilities :\n\nReceive training, and perform duties in several departments, in operations, products, and support functions in order to attain functional and departmental perspective on objectives by following the FedEx philosophy of People-Service-Profit and Purple Promise\nLearn various staff functions, operations workflow, management viewpoints and company policies and practices affecting each phase of FTN business development\nMeet performance goals and objectives set by management\nReport to management regularly on progress made in attaining goals and objectives\nObserve experienced talents in FTN to acquire knowledge of methods, procedures, and standards required for performance of departmental duties\nProvide support as needed by management in the various departments, including reporting, data-entry, presentation creation, strategic planning, and ad-hoc project work\n\nRequirements :\n\nUniversity graduates in all disciplines.\u00a0Degree in logistics, supply chain management, or industrial engineering is preferred but not essential\nKeen interest in Supply Chain Management & Freight Forwarder Industry\nSelf-motivated, passionate and energetic\nHighly committed, hardworking and consistently self-disciplined\nGood team player\nAble to work under pressure\nExcellent spoken and written English with strong interpersonal and presentation skills. Fluent Mandarin and Chinese are preferable.\nBe willing to relocate to Mainland China or other countries for short-term assignments.\n\nApplication deadline : February 28, 2022 (Monday)\n\nJoin FedEx and you'll be rewarded with an excellent salary and benefits package including guarantee two months' year-end bonus, medical and dental benefits, life insurance, provident fund, extra annual leave, and attractive promotional prospects.\n\nIf you are interested in joining us, please send us your resume, highlight graduation year, faculty, outstanding achievements, internship experience, etc.\n\nFor any inquiries regarding the MT programme, please contact us through whatsapp at +852 65801399.\n\nOur company addresses:\nUnit 801, 8/F, Metroplaza Tower 1\n223 Hing Fong Road, Kwai Fong\nN.T.\u00a0\n\nAll information provided by applicants will be treated in strict confidence and used only for recruitment purpose in accordance with the employer's personal data policies. A copy of Personal Information Collection Statement (PICS) will be provided upon request. Please write to the Human Resources Department. Applicants who are not invited to an interview within four weeks may consider their applications unsuccessful. All personal data of unsuccessful applicants will be destroyed after one year.", "employment_types": ["Full Time", "Permanent"], "selling_points": ["Guarantee 14 months paid with attractive benefits", "Management Trainee", "Fresh Graduates"], "locations": ["Kwai Fong"], "categories": ["Transportation & Logistics", "Freight Forwarding", "Supply Chain", "Others", "Student / Fresh Graduate / No Experience"], "post_time": "2022-01-18T01:42:18Z", "salary": {"currency": null, "max": null, "min": null, "period": "monthly", "term": null}, "salary_visible": false, "title_keywords": ["management trainee"], "responsibilities": [], "requirements": {"degrees": [], "majors": [], "languages": [], "language_level": [], "hard_skills": [], "soft_skills": [], "languages_combined": []}, "experience_required": {"duration": [], "field": []}}, {"job_id": "100003009052609", "location_code": "hk", "company": "Crane Worldwide Logistics Hong Kong Limited", "job_title": "Business Support Executive, eCommerce, South China & HK", "description": "To cope with our business development and expansion in eCommerce, our Hong Kong office is now inviting high caliber candidate to join us for the position of\u00a0Business Support Executive, eCommerce, South China & HK\n\u00a0\n\u00a0\nThe job\u00a0holder will assisting the Head of eCommerce, South China & HK, on the support all commercial activities and\u00a0client management of the eCommerce business for South China & HK markets through the following major responsibilities including but not limited to:\n\n\u00a0Duties & Responsibilities:\n\u00a0\nProvide support on client onboarding, system training, shipment tracking\u00a0and billing.\nHandle clients' enquiries and resolve complaint in timely and professional manner.\nIdentify clients' needs and new opportunities throughout regular communication with client.\nAdminister and maintain eCommerce portal.\nAssist in analyzing and monitoring performance and shipping trend of clients, and preparing monthly report to management.\n\nRequirements:\n\nDegree holder in Business Administration, Supply Chain Management or related discipline.\nMinimum 2 years' working experience, preferably in eCommerce industry.\nTeam player with good communication and problem-solving skills, and attention to details.\nPatient and proactive to build relationship with customers.\nFamiliarized with MS Office and data analytics applications and methodologies.\nGood command of both spoken and written English, Mandarin and Chinese\n\nWORKING CONDITIONS\n\nThe office working environment is generally favorable. We offer attractive remuneration and benefits including,\u00a05 days work per week, annual leave, discretionary bonus, medical & dental scheme and 13th payroll. Our office is located in Diamond Hill.", "employment_types": ["Full Time", "Permanent"], "selling_points": ["5 days work", "Medical & dental scheme", "competitive remuneration package and benefits"], "locations": ["Wong Tai Sin Area"], "categories": ["Transportation & Logistics", "Freight Forwarding", "E-commerce", "Product Management / Business Analyst", "Supply Chain"], "post_time": "2022-01-17T03:32:09Z", "salary": {"currency": null, "max": null, "min": null, "period": "monthly", "term": null}, "salary_visible": false, "title_keywords": ["executive"], "responsibilities": ["provide support", "shipping", "management", "monitoring", "professional manner", "communication", "maintain", "monthly report", "tracking"], "requirements": {"degrees": ["degree holder"], "majors": ["business administration"], "languages": ["english", "chinese", "mandarin"], "language_level": ["good command"], "hard_skills": ["problem-solving skills", "data analytics", "scheme", "ms office"], "soft_skills": ["patient", "communication", "attention to details", "problem-solving skills", "team player", "proactive"], "languages_combined": [{"language": "english", "language_level": ["good command"]}, {"language": "chinese", "language_level": ["good command"]}, {"language": "mandarin", "language_level": ["good command"]}]}, "experience_required": {"duration": ["minimum 2 years"], "field": ["ecommerce"]}}, {"job_id": "100003009052127", "location_code": "hk", "company": "OOCL Logistics Ltd", "job_title": "Business Analyst, Import & Export (Ref: AMSO/OPLUS/OLL)", "description": "Through participation in business projects and on-the-job training, the potential candidate shall gain experience and broaden the global perspectives in logistics business.\u00a0\n\n\u00a0Responsibilities:\u00a0\n\n\nDrive and promote\u202fcompliance\u202fwith\u00a0Government\u00a0rules and regulations in\u00a0NVOCC\u00a0operations\nMonitor\u00a0changes\u00a0in\u00a0NVOCC Customs Filing requirements\u00a0& regulations\u00a0and adapt\u00a0it in\u00a0processes\u00a0and\u00a0systems\n\nFormulate guidelines for internal compliance\u00a0and implement guidelines in business operations\n\nGuide\u00a0team\u00a0and train relevant parties on rules, processes and systems\n\nOrganize and house-keep Import/Export business\u00a0licenses\n\nLiaise with\u00a0agent\u00a0on handling\u00a0shipments and\u00a0to\u00a0ensure\u00a0smooth operation\n\nRequirements:\u00a0\n\n\nBachelor\u2019s Degree in Business Administration\u00a0or related disciplines\n2 years of experience in logistics or freight forwarding industry\n\nStrong analytical and problem-solving skills\nWell-organized and detail-minded\nProficient with MS Office and advanced functions of Excel\nExcellent spoken and written English and Chinese, proficiency in Mandarin will be an advantage\nPromising\u00a0candidate with less experience would be considered\u00a0as Officer\n\nInterested parties, please submit your application letter together with detailed resume and copies of your latest transcript\u00a0by clicking \u201cApply Now\u201d.\n\n(Data collected will be used for recruitment purpose only.)", "employment_types": ["Full Time", "Permanent"], "selling_points": ["Ensure rules and regulations compliance", "2 years\u2019 relevant work experience", "Degree holder (Fresh Graduates also welcome)"], "locations": ["Kwun Tong"], "categories": ["Transportation & Logistics", "Others", "Freight Forwarding", "Shipping"], "post_time": "2022-01-17T02:11:09Z", "salary": {"currency": null, "max": null, "min": null, "period": "monthly", "term": null}, "salary_visible": false, "title_keywords": ["business analyst"], "responsibilities": ["regulations", "guidelines", "operations", "compliance", "monitor", "systems", "liaise with"], "requirements": {"degrees": ["degree", "bachelor"], "majors": ["related disciplines", "business administration"], "languages": ["english", "chinese", "mandarin"], "language_level": ["advantage", "excellent", "proficiency"], "hard_skills": ["problem-solving skills", "excel", "ms office"], "soft_skills": ["detail-minded", "problem-solving skills", "well-organized", "advanced"], "languages_combined": [{"language": "english", "language_level": ["advantage", "excellent"]}, {"language": "chinese", "language_level": ["advantage", "excellent"]}, {"language": "mandarin", "language_level": ["proficiency", "advantage", "excellent"]}]}, "experience_required": {"duration": ["2 years"], "field": ["logistics"]}}, {"job_id": "100003009052258", "location_code": "hk", "company": "Kintetsu World Express (HK) Limited", "job_title": "Management Trainee (Forwarder)", "description": "Job Description:\n\nIllustrating a complete picture of international logistics management, our Management Trainee Program provides trainees with a global business insight and equips them with necessary knowledge and skills for their growth through:\non-the-job training with rotation among major business functions\nongoing guidance and coaching from senior executives\ncustomized training in diversified areas of business, personal development and management\nplenty of opportunity to demonstrate capability and potential by undertaking various projects as well as making presentations and recommendations to the senior management\nRequirements:\n\nWe are now inviting talented individuals of high calibre to join us and grow together with the Company:\nA degree from a recognized university in any discipline\nKeen to build a career in the global logistics industry\nStrong business acumen with a clear analytical mind\nA good team player with strong interpersonal and communication skills\nMature, self-motivated, presentable and confident\nProficient in both written and spoken English and Chinese\nDeadline:\n31 March 2022\n\nApplication Method:\n\nTo apply for the position of Management Trainee, please send us (a) resume with covering letter, (b) copy of public examination results, (c) copy of university transcript stating academic results with GPA score, (d) expected salary and earliest commencement date by clicking '' Apply Now''\n\nPersonal data collected will be used for recruitment purposes only.", "employment_types": ["Full Time"], "selling_points": [], "locations": ["Not Specified"], "categories": ["Transportation & Logistics", "Aviation Services", "Freight Forwarding", "Inventory / Warehousing"], "post_time": "2022-01-17T02:35:45Z", "salary": {"currency": null, "max": null, "min": null, "period": "monthly", "term": null}, "salary_visible": false, "title_keywords": ["management trainee"], "responsibilities": ["guidance", "management", "presentations", "logistics", "senior management"], "requirements": {"degrees": ["degree"], "majors": [], "languages": ["english", "chinese"], "language_level": ["proficient"], "hard_skills": ["transcript", "c", "acumen"], "soft_skills": ["confident", "communication skills", "good team player", "self-motivated", "keen", "mature", "presentable", "clear", "analytical mind", "business acumen", "interpersonal"], "languages_combined": [{"language": "english", "language_level": ["proficient"]}, {"language": "chinese", "language_level": ["proficient"]}]}, "experience_required": {"duration": [], "field": []}}, {"job_id": "100003009053571", "location_code": "hk", "company": "Boxful Limited", "job_title": "\u642c\u904b\u8ddf\u8eca (\u591a\u540d) (\u6708\u85aa\u53ef\u9ad8\u9054$20,000\u4ee5\u4e0a)", "description": "\n\u00a0 \u8077\u8cac:\n\u2022 \u8ca0\u8cac\u4e00\u822c\u642c\u904b\u53ca\u8ddf\u8eca\u5de5\u4f5c\n\u8cc7\u6b77:\n\u2022 \u5b78\u6b77\u4e0d\u62d8,\u8aa0\u5be6\u5b88\u6642\u3001\u6709\u79ae\u8c8c\u3001\u6709\u4e0a\u9032\u5fc3,\u6709\u5718\u968a\u7cbe\u795e\n\u6642\u9593: \u4e0a\u53488\u6642\u81f3\u665a\u4e0a6\u6642, \u6bcf\u9031\u5de5\u4f5c 6\u5929,\u8f2a\u4f11\n\u5730\u9ede: \u8475\u6d8c/\u5168\u6e2f (\u6574\u6f54,\u6709\u51b7\u6c23\u53ca\u8a2d\u6709\u54e1\u5de5\u4f11\u606f\u5ba4)\n\u6708\u85aa: $16,000\u8d77,\u6700\u9ad8\u53ef\u9054$20,000 ( \u901a\u904e\u8a66\u7528\u671f\u5f8c\u6703\u6309\u8868\u73fe\u9032\u884c\u85aa\u916c\u8abf\u6574,\u9023\u6d25\u8cbc \u5e73\u5747\u6708\u85aa\u9ad8\u9054$20,000 )\n\u5047\u671f\u53ca\u798f\u5229: 10\u5929\u6709\u85aa\u5e74\u5047\u3001\u8d85\u6642\u6d25\u8cbc\u3001\u500b\u4eba\u7e3e\u6548\u82b1\u7d05, \u91ab\u7642\u798f\u5229\u53ca\u6709\u85aa\u75c5\u5047\u7b49\n\u6211\u5011\u63d0\u4f9b\u4e00\u500b\u512a\u8cea\u53ca\u548c\u8ae7\u7684\u5de5\u4f5c\u74b0\u5883,\u5de5\u4f5c\u6c23\u6c1b\u8f15\u9b06\u6709\u6d3b\u529b,\u7bc0\u65e5\u65e9\u653e,\u4e0d\u5b9a\u671f\u54e1\u5de5\u6d3b\u52d5\u3002\u6b61\u8fce\u6309 Apply Now \u7533\u8acb,\u6709\u610f\u67e5\u8a62\u4f86\u96fb\u6216 whatsApp 6285 6262\u3002\n(\u6240\u6709\u7533\u8acb\u8005\u8cc7\u6599\u6703\u88ab\u4fdd\u5bc6\u8655\u7406\u4e26\u53ea\u4f5c\u62db\u8058\u7528\u9014)\n\n", "employment_types": ["Full Time"], "selling_points": [], "locations": ["Kwai Tsing Area"], "categories": ["Transportation & Logistics", "Freight Forwarding", "Inventory / Warehousing", "Supply Chain"], "post_time": "2022-01-17T07:10:55Z", "salary": {"currency": null, "max": null, "min": null, "period": "monthly", "term": null}, "salary_visible": false, "title_keywords": [], "responsibilities": [], "requirements": {"degrees": [], "majors": [], "languages": [], "language_level": [], "hard_skills": ["whatsapp"], "soft_skills": [], "languages_combined": []}, "experience_required": {"duration": [], "field": []}}, {"job_id": "100003009052657", "location_code": "hk", "company": "NET-A-PORTER", "job_title": "Logistic Assistant/ Advisor (Online Fashion Retailer, Fresh Graduates are welcome)", "description": "NET-A-PORTER are now seeking a talented Logistic Assistant/ Advisor join the team. Some of the essentials for you to know are:\n\nLocation:\u00a0Tsing Yi Office\n\nReporting into:\u00a0Trade & Transport Manager\n\nHere is a breakdown of what you\u2019ll be doing:\n\n\n\nInbound :\u00a0\n\nChecks all applicable documentations are in place and ensuring Government/Customs compliance is adhered to for all markets prior to ship\nProvides Shipping Instructions to the 3PL Carriers/Courier & prepare necessary shipping docs (if need)\nLiaises with vendors / internal business partners to resolve problem that could delay the release or movement of shipments\nFollow up shipment status and ensure the goods receiving is completed in WMS\u00a0\nOutbound :\n\nCustomer services support on all B2B courier shipping arrangement & inquiries\nGeneral Admin :\nObtain 3 PL quotation with comparison\nEnsure system data & daily operation log files are accurate and updated in timely manner\n3PL Billing validation & payment application to Finance\nAssist management for any ad hoc reporting and analysis tasks\n\n\u00a0The type of person we are looking for:\n\nPositive Thinking, Passionate in work, Paying Attention to Details, also a Team-Player\nExcellent communication and computer skills, especially Excel in advance level\nAn understanding of I/E shipping documentations and procedures\nFamiliar the Tradelink, DHL / UPS booking system\nSound working knowledge of International Customs laws/Regulations and Trade Compliance policies, is a definite plus\nCandidate with 1-2 experience is a plus, but fresh graduate will be considered\nBesides a competitive salary, we can offer you:\n\nPerformance bonus schemes\u00a0dependent\u00a0on the type of role you are in\nOur famous staff discount along with exclusive staff sales\nMPF plus voluntary contribution from the company\nMulti-purpose insurance\nRental Reimbursement Program\nFlexible working\nA chance to be part of a fun and caring team that support each other", "employment_types": ["Full Time", "Permanent"], "selling_points": ["Fresh graduates are welcome to apply", "Progressive career path; Good learning opportunity", "Advanced in MS Excel is ideal"], "locations": ["Tsing Yi"], "categories": ["Transportation & Logistics", "Freight Forwarding", "Shipping", "Supply Chain"], "post_time": "2022-01-17T03:39:23Z", "salary": {"currency": null, "max": null, "min": null, "period": "monthly", "term": null}, "salary_visible": false, "title_keywords": ["advisor", "assistant"], "responsibilities": ["regulations", "shipping", "quotation", "communication", "payment", "wms", "ad hoc", "tradelink", "compliance", "customer services", "reporting", "management", "mpf", "procedures", "system data", "booking", "policies", "analysis", "daily operation", "insurance"], "requirements": {"degrees": ["fresh graduate"], "majors": [], "languages": [], "language_level": [], "hard_skills": ["excel", "plus", "fun", "analysis", "computer skills", "pl", "documentations"], "soft_skills": ["passionate", "flexible", "team-player", "timely", "positive thinking", "communication", "attention to details", "accurate"], "languages_combined": []}, "experience_required": {"duration": [], "field": []}}, {"job_id": "100003009053610", "location_code": "hk", "company": "Gate Way Valve & Fitting Limited", "job_title": "\u540a\u8eca\u8ddf\u8eca\u54e1", "description": "\n\u8077\u8cac :\u8ddf\u8eca\u9001\u5efa\u7bc9\u7269\u6599\u5230\u5730\u76e4, \u9808\u57cb\u78bc\n\n\u8cc7\u6b77 :\u4e2d\u4e09\u7a0b\u5ea6; 1\u5e74\u7d93\u9a57; \u826f\u597d\u7cb5\u8a9e; \u61c2\u8b80\u5beb\u4e2d\u6587; \u7565\u61c2\u8b80\u5beb\u82f1\u6587; \u6301\u6709\u5e73\u5b89\u54ad; \u6301\u6709\u5efa\u9020\u696d\u5de5\u4eba\u8a3b\u518a\u8b49; \u9808\u6301\u6709A12\u9280\u5361\n\n\u5f85\u9047 :\u6bcf\u6708$18,000, \u6709\u96d9\u7ce7, \u9280\u884c\u5047\u671f \u53ca\u914c\u60c5\u6027\u82b1\u7d05, \u661f\u671f\u4e00\u81f3\u4e94: \u4e0a\u53488\u6642\u81f3\u4e0b\u53485\u6642\u534a\u53ca\u661f\u671f\u516d: \u4e0a\u53488\u6642\u81f3\u4e0b\u53484\u6642, \u6bcf\u9031\u5de5\u4f5c5\u5929\u81f36\u5929, \u661f\u671f\u516d\u9577\u77ed\u9031\n\n\u7533\u8acb\u9808\u77e5 :\u6c42\u8077\u8005\u53ef\u81f4\u96fb63544088\u8207\u57fa\u6cd5\u6c34\u7ba1\u914d\u4ef6\u6709\u9650\u516c\u53f8\u6797\u5148\u751f\u806f\u7d61\u3002\n\n", "employment_types": ["Full Time"], "selling_points": [], "locations": ["Yuen Long"], "categories": ["Transportation & Logistics", "Freight Forwarding", "Inventory / Warehousing", "Supply Chain"], "post_time": "2022-01-17T07:14:25Z", "salary": {"currency": null, "max": null, "min": null, "period": "monthly", "term": null}, "salary_visible": false, "title_keywords": [], "responsibilities": [], "requirements": {"degrees": [], "majors": [], "languages": [], "language_level": [], "hard_skills": [], "soft_skills": [], "languages_combined": []}, "experience_required": {"duration": [], "field": []}}, {"job_id": "100003009051222", "location_code": "hk", "company": "Easy Job Centre", "job_title": "Shipping Clerk / Senior Shipping Clerk", "description": "Basic Requirements:\n\nForm 7 or above\n1-2 years freight forwarding experience\nResponsible, reliable, patient, pro-active and aggressive\nGood communication skill\nProficient in MS Excel, MS Word and Chinese Word Processing\nWilling to work under pressure and overtime\nGood command of written and spoken English and Putonghua\n\n\u00a0Major Responsibilities:\n\nFollow-up shipment orders via liaising with branch offices, overseas agents and customers\nProvide full support to Operations Teams and co-operate with Sales Team\nPromote company services / products\u00a0to current customers and working partners\nVendors' management\nPrepare reports and quotation\nJoin sales visit if required\n\nIf you are the one we are looking for, please send your full resume with expected salary by clicking \"Apply Now\".\n\n\nResume without expected salary will not be considered.\n\nJob Location: Kwai Chung (Next to Lai King MTR Station)", "employment_types": ["Full Time"], "selling_points": [], "locations": ["Tsim Sha Tsui"], "categories": ["Transportation & Logistics", "Freight Forwarding", "Shipping", "Supply Chain"], "post_time": "2022-01-15T05:19:56Z", "salary": {"currency": null, "max": null, "min": null, "period": "monthly", "term": null}, "salary_visible": false, "title_keywords": ["shipping clerk"], "responsibilities": ["management", "operations", "quotation", "teams", "liaising with", "co-operate with", "sales team", "prepare reports"], "requirements": {"degrees": [], "majors": [], "languages": ["putonghua", "english", "chinese"], "language_level": ["good command", "proficient"], "hard_skills": ["chinese word processing", "ms excel", "basic", "ms word"], "soft_skills": ["responsible", "communication skill", "pro-active", "patient", "reliable", "work under pressure"], "languages_combined": [{"language": "putonghua", "language_level": ["good command"]}, {"language": "english", "language_level": ["good command"]}, {"language": "chinese", "language_level": ["proficient"]}]}, "experience_required": {"duration": ["1-2 years"], "field": []}}, {"job_id": "100003009049971", "location_code": "hk", "company": "V-Logic Limited", "job_title": "Customer Service Officer - International Freight (Near Lai King MTR Station)", "description": "Assist operations manager to manage cargo terminal and perform work.\nAssist in the handling of emergency and irregularities in the cargo terminal.\nAssist in investigating and analyzing reports of incidents and provide advice to ensure that incidents do not recur.\nMonitor the operation of the cargo terminal to ensure that employees comply with cargo terminal operating rules and working procedures to meet customer needs and ensure that work is done within the service commitment scope.\nRegular work review and motivation of staff to improve work performance.\nOptimize human resources to ensure that the services provided meet or exceed standards.\nRequirements\n2 years or above management experience\nCollege degree with priority in consideration\nGood writing and reading skills in Chinese and English\nLeadership and management skills\nCan work independently and work under pressure", "employment_types": ["Full Time", "Permanent"], "selling_points": [], "locations": ["Kwai Tsing Area"], "categories": ["Sales, CS & Business Devpt", "Customer Service - Supervisor / Officer", "Transportation & Logistics", "Freight Forwarding", "Shipping"], "post_time": "2022-01-14T09:33:48Z", "salary": {"currency": null, "max": null, "min": null, "period": "monthly", "term": null}, "salary_visible": false, "title_keywords": ["customer service officer"], "responsibilities": ["management", "irregularities", "operations", "review", "monitor", "procedures", "provide advice", "reports", "work under pressure"], "requirements": {"degrees": ["degree"], "majors": [], "languages": ["english", "chinese"], "language_level": ["good"], "hard_skills": [], "soft_skills": ["work independently", "leadership", "work under pressure"], "languages_combined": [{"language": "english", "language_level": ["good"]}, {"language": "chinese", "language_level": ["good"]}]}, "experience_required": {"duration": ["2 years"], "field": ["management"]}}, {"job_id": "100003009053398", "location_code": "hk", "company": "Winsome (Packing & Stationery) Limited", "job_title": "\u9001\u8ca8\u54e1 (\u8ddf\u8eca)", "description": "Responsibilities\n\n\n\nResponsible for airfreight export operation including updating the data in the systems\nInvoicing and verification of incoming invoices\u00a0\nHandle full set of documents & operations\nCo-ordinate with customers/overseas agents\nMaintain daily communication with overseas offices\nCo-ordinate with warehouse for goods received\n\nRequirements\n\n\nHKCEE F.5 or above / HKDSE / Diploma graduate or above\nMinimum 1 year experience in Airfreight forwarding company\nExperience in full set of Export documents and operations\nGood command in written and spoken English and Mandarin\nGood computer skills in MS office application\nShift duty is required\n\n\n\n\nWe offer attractive remuneration package with benefit including double pay, medical & dental insurance to the right candidate. Interested parties please send your resume stating expected salary, expected work location and date available by\u00a0Apply Now Button.\n\n\u00a0\"Personal data collected will be used for recruitment purpose only\"", "employment_types": ["Full Time"], "selling_points": [], "locations": ["Tsuen Wan Area"], "categories": ["Transportation & Logistics", "Freight Forwarding", "Inventory / Warehousing", "Supply Chain"], "post_time": "2022-01-17T06:55:36Z", "salary": {"currency": null, "max": null, "min": null, "period": "monthly", "term": null}, "salary_visible": false, "title_keywords": ["\u9001\u8ca8\u54e1", "\u8ddf\u8eca"], "responsibilities": ["invoices", "data", "co-ordinate with", "operations", "systems", "invoicing", "communication", "maintain"], "requirements": {"degrees": ["diploma", "hkdse"], "majors": [], "languages": ["english", "mandarin"], "language_level": ["good command"], "hard_skills": ["computer skills", "ms office"], "soft_skills": [], "languages_combined": [{"language": "english", "language_level": ["good command"]}, {"language": "mandarin", "language_level": ["good command"]}]}, "experience_required": {"duration": ["minimum 1 year"], "field": []}}, {"job_id": "100003009049880", "location_code": "hk", "company": "Bollore Logistics Hong Kong Limited", "job_title": "Airfreight Export Operations Clerk - Shift Duty", "description": "Responsibilities:\n\nHandle freight related documents\nHandle shipments and communication with overseas agents\nDevelop co-loading business\n\nRequirements:\n\nCompleted tertiary or related education\nOne to two years freight operations working experience is preferable\nExperience in working with and managing co-loader\nProactive and highly self-motivated in communicating with various parties\nGood team player\nAnalytical and logical thinking, positive and good working attitude\nProficient in both written and spoken English and Chinese\nHands-on PC knowledge, competent in MS Excel etc. is an advantage\nCandidates without working experience can be considered as Operations Clerk\n\n\nIf you are the one we are looking for, please send your full resume with expected salary by clicking \"Apply Now\".\n\n\nResume without expected salary will not be considered.\n\nJob Location: Kwai Chung (Next to MTR Station)", "employment_types": ["Full Time", "Permanent"], "selling_points": ["Airfreight export operation", "Handle full set of documents & operations", "Invoicing and verification of incoming invoices"], "locations": ["Kwai Fong"], "categories": ["Transportation & Logistics", "Freight Forwarding"], "post_time": "2022-01-14T09:22:55Z", "salary": {"currency": null, "max": null, "min": null, "period": "monthly", "term": null}, "salary_visible": false, "title_keywords": ["operations clerk"], "responsibilities": ["related documents", "communication", "develop"], "requirements": {"degrees": [], "majors": [], "languages": ["english", "chinese"], "language_level": ["proficient"], "hard_skills": ["pc knowledge", "ms excel"], "soft_skills": ["good working attitude", "good team player", "self-motivated", "competent", "hands-on", "proactive", "positive"], "languages_combined": [{"language": "english", "language_level": ["proficient"]}, {"language": "chinese", "language_level": ["proficient"]}]}, "experience_required": {"duration": ["one to two years"], "field": []}}, {"job_id": "100003009049941", "location_code": "hk", "company": "V-Logic Limited", "job_title": "International Freight - Operations Officer / Clerk (Near Lai King MTR Station)", "description": "The Job (Ocean/ Air Export Team):\n\nTo contact vendors for bookings and validating bookings against consignee\u2019s instruction\u00a0\nTo arrange cargo, document pick-up\u00a0and distribution in accordance with our operations procedure and customers\u2019 requirements\nTo file all shipment record correctly and timely, and monitor the computerized database\nTo answer general telephone enquiries\nTeams and working location(Please state the preferred team in CV):\n\u00a0Ocean Team: Kowloon Bay\nAir Export Team**: Chek Lap Kok\u00a0(**Shift duty is required, including overnight shift ; Shift allowance is provided).\u00a0 \u00a0\u00a0\u00a0 \u00a0\u00a0 \u00a0\n\nThe Qualifications:\n\nTertiary education graduate with 1-2 years\u2019 experience in freight forwarding or shipping industry\nFresh graduates with less experience will also be considered\nPossess strong interest to pursue long term career in the logistic solutions industry\nProficient PC knowledge\nGood communication skills and able to communicate in English and Chinese (Cantonese and Mandarin)\n\nThe Future:\n\nCandidate for supervisory position\n\nAttractive remuneration package with good career prospect will be offered to the right candidates. Interested parties, please send your full resume and expecting salary to the Manager-Administration, 36/F-37/F, Enterprise Square Three, 39 Wang Chiu Road, Kowloon Bay, Hong Kong or fax to 2721 9734\u00a0or by clicking \"Apply Now\" button below. Please quote the reference on your application. Further information about the Company can be obtained at Expeditors\u2019 website: http://www.expeditors.com. Shortlisted candidates will be notified within 6 weeks.\n\n\u00a0All information provided by candidates will be used solely for recruitment purposes. Unsuccessful application will be destroyed in strict confidence upon completion of recruitment process.\n\nExpeditors is an equal opportunities employer and works towards a smoke free environment.", "employment_types": ["Full Time", "Permanent"], "selling_points": [], "locations": ["Kwai Tsing Area"], "categories": ["Transportation & Logistics", "Freight Forwarding", "Shipping", "Supply Chain"], "post_time": "2022-01-14T09:28:33Z", "salary": {"currency": null, "max": null, "min": null, "period": "monthly", "term": null}, "salary_visible": false, "title_keywords": ["operations officer", "clerk"], "responsibilities": ["shipping", "operations", "teams", "monitor", "communication", "contact", "database"], "requirements": {"degrees": [], "majors": [], "languages": ["cantonese", "english", "chinese", "mandarin"], "language_level": ["good"], "hard_skills": ["bookings", "pc knowledge"], "soft_skills": ["communication skills", "timely"], "languages_combined": [{"language": "cantonese", "language_level": ["good"]}, {"language": "english", "language_level": ["good"]}, {"language": "chinese", "language_level": ["good"]}, {"language": "mandarin", "language_level": ["good"]}]}, "experience_required": {"duration": ["1-2 years"], "field": ["shipping industry", "education"]}}, {"job_id": "100003009050507", "location_code": "hk", "company": "Expeditors Hong Kong Limited", "job_title": "Logistics Coordinator (Freight Forwarding/ Attractive Bonus/ Fresh Graduates are welcome)", "description": "Role & Responsibilities\n\n\u00a0Responsible for full set Import shipping document\nResponsible for Import Declaration\nCommunicate with internal & overseas customer or vendors to ensure a smooth running of process\nControl the delivery time allocation\nAnswer rate and service inquiry\nCross check and submit job closing file by monthly end\nHandle ad hoc assignments by Supervisor\nEducation, Experience, Certification and Training requirements\n\n\nF.5 or above\nOver 1 years experience in freight forwarding for Sea import\n\nJob Skills and Competencies for this position\n\n\nImport declaration\nComputer- Word, Excel, PowerPoint, Access, FrontPage\nGood Command of spoken / written English & Fluent Mandarin\nGood timing management skill\nTyping \u2013 ENG 57 wpm ; Chinese 33 wpm\n\nWe offer\n\nDouble pay\nPerformance bonus\n5 days work\nFree shuttle bus\n\nIf you have the desire for an exciting and rewarding career, please send us your resume with stating your present and expected salary to Human Resources Department\n\nOnly short-listed candidates will be contacted.\n\nOn Time is an equal opportunity employer and welcomes applications from all qualified candidates. Information provided will be treated in strict confidence and will only be used for recruitment-related purposes. Personal data provided by job applicants will be used strictly in accordance.", "employment_types": ["Full Time", "Permanent"], "selling_points": [], "locations": ["Kowloon Bay"], "categories": ["Transportation & Logistics", "Freight Forwarding", "Shipping", "Supply Chain"], "post_time": "2022-01-14T10:35:04Z", "salary": {"currency": null, "max": null, "min": null, "period": "monthly", "term": null}, "salary_visible": false, "title_keywords": ["logistics coordinator"], "responsibilities": ["communicate with", "control", "management", "ad hoc assignments", "shipping document"], "requirements": {"degrees": [], "majors": [], "languages": ["english", "chinese", "mandarin"], "language_level": ["good command", "fluent"], "hard_skills": ["excel", "word", "powerpoint", "typing", "shipping document"], "soft_skills": ["responsible", "smooth"], "languages_combined": [{"language": "english", "language_level": ["fluent", "good command"]}, {"language": "chinese", "language_level": []}, {"language": "mandarin", "language_level": ["good command"]}]}, "experience_required": {"duration": ["1 years"], "field": ["training", "education"]}}, {"job_id": "100003009047932", "location_code": "hk", "company": "On Time Express Ltd", "job_title": "Import Operation Clerk, Sea Freight", "description": "Responsibilities\u00a0\nPrepare export shipping documents\nHandle local and China truck arrangement\nWork closely with clients and warehouse for delivery schedule planning\nProcess Tradelink declaration\n\nRequirements\n\nHKCEE F.5 or above / HKDSE / Diploma graduate or above\nMinimum 2 years' solid experience in freight forwarding industry\nExperience in handling China truck and local delivery arrangement is required\nGood command of written and spoken English, Chinese and Mandarin\nGood computer skills in MS office application\n\nWe offer attractive remuneration package with benefit including double pay, medical & dental insurance to the right candidate. Interested parties please send your resume stating expected salary, expected work location and date available by\u00a0Apply Now Button.\n\n\u00a0\"Personal data collected will be used for recruitment purpose only\"\n\n\n\n", "employment_types": ["Full Time", "Permanent"], "selling_points": ["Ocean import operation, handle import doc&booking", "Good team player & Customer-oriented", "Double pay, performance bonus & 5 days work"], "locations": ["Kowloon Bay"], "categories": ["Transportation & Logistics", "Freight Forwarding", "Shipping", "Maritime - General"], "post_time": "2022-01-14T04:18:03Z", "salary": {"currency": null, "max": null, "min": null, "period": "monthly", "term": null}, "salary_visible": false, "title_keywords": ["operation clerk"], "responsibilities": ["shipping documents", "planning", "tradelink declaration", "delivery schedule"], "requirements": {"degrees": ["diploma", "hkdse"], "majors": [], "languages": ["english", "chinese", "mandarin"], "language_level": ["good command"], "hard_skills": ["computer skills", "ms office"], "soft_skills": [], "languages_combined": [{"language": "english", "language_level": ["good command"]}, {"language": "chinese", "language_level": ["good command"]}, {"language": "mandarin", "language_level": ["good command"]}]}, "experience_required": {"duration": ["minimum 2 years"], "field": []}}, {"job_id": "100003009049879", "location_code": "hk", "company": "Bollore Logistics Hong Kong Limited", "job_title": "Seafreight Operations Executive", "description": "Our client, one of the leading Logistics companies, is looking for high calibres to join their winning team:\n\nResponsibilities:\n\nExperienced in Freight Fowarding industry.\nExport/import shipments,\n\nDirectly involved with all imported goods received into the country of destination.\n\nEnsure all necessary paperwork is complete and legally acceptable to Customs to allow clearance and entry into the country.\n\nYou will be required to obtain charges and cargo release details from freight forwarding agents and shipping lines.\n\nResponsible for ensuring any payments due are made in advance of any shipment as required. You will process all payments and raise necessary paperwork for accounting purposes inline with company requirements.\n\nRequirements:\n\n1-5 years of experience in Freight Fowarding industry (Ocean Freight Department)\n\nYou will have a solid understanding of all Customs clearance documentation and experience of preparation of Bills of Lading in particular.\n\nExcellent communication skills both verbal and written.\n\nYou must also be familiar with industry standard computer programs and be able to operate standard systems pertinent to the job.\n\nCandidates with more experience will be considered as Senior Operations.", "employment_types": ["Full Time", "Permanent"], "selling_points": ["Handle local and China truck arrangement", "Work closely clients for deliver schedule plan", "Prepare export shipping documents"], "locations": ["Kwai Fong"], "categories": ["Transportation & Logistics", "Freight Forwarding"], "post_time": "2022-01-14T09:22:54Z", "salary": {"currency": null, "max": null, "min": null, "period": "monthly", "term": null}, "salary_visible": false, "title_keywords": ["operations executive"], "responsibilities": ["shipping", "payments"], "requirements": {"degrees": [], "majors": [], "languages": [], "language_level": [], "hard_skills": ["documentation"], "soft_skills": ["communication skills"], "languages_combined": []}, "experience_required": {"duration": ["1-5 years"], "field": []}}, {"job_id": "100003009048954", "location_code": "hk", "company": "JFE Consulting Limited", "job_title": "(Senior) Seafreight Operations Clerk - LOGISTICS", "description": "Excellent opportunity for freight forwarding experts to work for a leading global forwarder.\n\nClient Details\n\nOur client is one of the most reputable companies within the freight forwarding industry. With over decades of history, they have been delivering the best products and services to the world. With steady and rapid expansion in business in Hong Kong, they are actively looking for a Key Account Executive to join their dynamic company.\n\nDescription\n\nMonitor freight and origin operation performance to satisfy customer's demand\nConduct analysis on KPI and provide logistics solution to tackle operation issues\nNegotiate with vendor and carrier for cost and schedule management\nDevelop logistics enhancement project to optimize business performance\nAssist in ad-hoc duties as per assigned\n\nProfile\n\nMin. 2 years of experience in Operation /Account Servicing experience in freight forwarding company\nStrong analytical skills with numerical sense\nOrganized and detail-oriented individual\nExcellent command in both English and Chinese\n\nJob Offer\n\nCareer progression\nCompetitive pay\n5-day work", "employment_types": ["Full Time", "Permanent"], "selling_points": ["Leading Logistics company,Freight forwarding", "Export/import shipments", "1 year related experience,attractive salary"], "locations": ["Not Specified"], "categories": ["Admin & HR", "Clerical / Admin Staff", "Transportation & Logistics", "Documentary Credit / Bills Processing", "Freight Forwarding"], "post_time": "2022-01-14T07:47:28Z", "salary": {"currency": null, "max": null, "min": null, "period": "monthly", "term": null}, "salary_visible": false, "title_keywords": ["operations clerk", "logistics"], "responsibilities": ["cost", "management", "analysis", "monitor", "develop", "logistics", "schedule", "ad-hoc duties"], "requirements": {"degrees": [], "majors": [], "languages": ["english", "chinese"], "language_level": ["excellent"], "hard_skills": ["analysis", "vendor", "analytical skills", "dynamic", "rapid"], "soft_skills": ["organized", "detail-oriented", "analytical skills", "dynamic", "ad-hoc duties"], "languages_combined": [{"language": "english", "language_level": ["excellent"]}, {"language": "chinese", "language_level": ["excellent"]}]}, "experience_required": {"duration": ["2 years"], "field": ["operation", "account servicing"]}}, {"job_id": "100003009049994", "location_code": "hk", "company": "Page Personnel", "job_title": "Key Account Executive - Global Freight Forwarding", "description": "Responsibilities\n\nResponsible for the optimization of process flow, operation plan, resource input, on-site management, quality improvement, and implementation of cost control\nStandardization of operations process (Promotion of operation mode, an inspection of Distribution Hub and preparation of sites certificate)\nMonitoring and managing the construction process of Distribution Hub, the preparation of operations flow design, and operations switching support\nOutsourcing management of Distribution Hub (Unit price calculation, tendering support, supplier evaluation, outsourcing input support, such operation survey for supplier)\nResponsible for supervising and promoting the implementation and application of logistics tools and equipment\nUndertake other work from the engineering department\nPerform any other ad hoc duties assigned by supervisor from time to time\nRequirements\n\nBachelor degree or above in Logistics/ Mathematics / Industrial Engineering / related majors\nSolid knowledge in basic machinery and logistics operation equipment\nFamiliar with operation management requirements, standardized operations, and able to implement various system processes according to the needs of various functional departments\nStrong statistical analysis and problem-solving skills\nPriority given to candidates with 2 years of relevant industry work experience\nStrong data analysis and communication skills; proficient in computer and related office software applications\nBasic understanding on Industrial Engineering\nInnovative, attention to detail, strong commitment at work and able to work under pressure\nGood in spoken and written Chinese and English, including Putonghua\nWe offer attractive remuneration package and fringe benefits to the right candidates. Interested parties please submit your application to us. If you do not want to apply as a JobsDB member, you may send your full resume with your availability, current and expected salaries to recruit01 at sf-express.com.\n\n\nYou are welcome to visit our website at\u00a0https://htm.sf-express.com/hk/tc/\u00a0for more information about us.\n\nCandidates who are not invited for an interview within 1-month may consider their applications unsuccessful.\n\nAll personal data provided by job applicants will be used only for recruitment purposes and will be treated strictly confidential. Unsuccessful applications will be retained for a maximum period of 24-month.", "employment_types": ["Full Time", "Permanent"], "selling_points": ["Ocean freight management", "Attractive benefits", "Medical, Dental"], "locations": ["Not Specified"], "categories": ["Transportation & Logistics", "Freight Forwarding", "Shipping", "Supply Chain"], "post_time": "2022-01-14T09:36:26Z", "salary": {"currency": null, "max": null, "min": null, "period": "monthly", "term": null}, "salary_visible": false, "title_keywords": ["key account executive"], "responsibilities": ["ad hoc duties", "management", "supervising", "operations", "monitoring", "quality", "site management", "implementation", "inspection", "design", "tendering", "logistics", "cost control", "evaluation", "operation plan"], "requirements": {"degrees": ["degree or above", "bachelor"], "majors": ["mathematics", "engineering"], "languages": ["putonghua", "english", "chinese"], "language_level": ["good"], "hard_skills": ["basic", "statistical analysis", "analysis", "problem-solving skills", "office software"], "soft_skills": ["communication skills", "attention to detail", "problem-solving skills", "innovative", "work under pressure"], "languages_combined": [{"language": "putonghua", "language_level": ["good"]}, {"language": "english", "language_level": ["good"]}, {"language": "chinese", "language_level": ["good"]}]}, "experience_required": {"duration": ["2 years"], "field": []}}, {"job_id": "100003009052026", "location_code": "hk", "company": "S.F. Express (Hong Kong) Limited", "job_title": "Logistics Officer (Hub Operations)", "description": "Responsibilities:\n\n\n\u00a0Perform multiple tasks to provide operation and documentation support for the Air Operations team;\n\u00a0Handle full set of air freight documents; air export knowledge is preferred and advantage;\u00a0\nHandle inquiries from oversea agents, customers\nArrange bookings with carriers, co-loaders and confirm cargo space on flight;\n\u00a0Knowledge of cargo consolidation planning\nRequirements:\n\n\u00a0HKCEE/DSE or above, who with DGR will be an advantage\nMore than 1 year relevant experience in air freight forwarding industry is preferred\nGood command in both written and spoken English and Chinese (Putonghua)\u00a0\nDetail minded, Self-motivated, aggressive, good communication skills and able to work under pressure\u00a0\nWilling to learn and work overtime, Day/Night shift duty (overnight) is required\nImmediate available is preferred", "employment_types": ["Full Time", "Permanent"], "selling_points": ["Free shuttle bus coverage", "2 months or above performance bonus", "Attractive remuneration package"], "locations": ["Tsing Yi"], "categories": ["Transportation & Logistics", "Freight Forwarding", "Inventory / Warehousing", "Supply Chain"], "post_time": "2022-01-17T01:52:20Z", "salary": {"currency": null, "max": null, "min": null, "period": "monthly", "term": null}, "salary_visible": false, "title_keywords": ["logistics officer", "operations"], "responsibilities": ["documentation", "operations", "planning", "air freight"], "requirements": {"degrees": ["dse"], "majors": [], "languages": ["putonghua", "english", "chinese"], "language_level": ["good command"], "hard_skills": [], "soft_skills": ["communication skills", "self-motivated", "work overtime", "willing to learn", "work under pressure"], "languages_combined": [{"language": "putonghua", "language_level": ["good command"]}, {"language": "english", "language_level": ["good command"]}, {"language": "chinese", "language_level": ["good command"]}]}, "experience_required": {"duration": ["1 year"], "field": ["relevant experience"]}}, {"job_id": "100003009050479", "location_code": "hk", "company": "Dachser Hong Kong Limited", "job_title": "SENIOR / CUSTOMER SERVICE COORDINATOR AIR FREIGHT EXPORT", "description": "Our Hong Kong team has been through a positive development in recent years with improved results, higher productivity and a growing customer base.\n\nWe are now looking for a high caliber individual to join our Air Freight Export\u00a0team. \u00a0This role plays a key part in coordinate with different parties, strengthening our operations processes and enhance productivity with good quality / service.\n\nSENIOR AIR FREIGHT EXPORT COORDINATOR (CARGO PLANNER)\n\nCOLLABORATE: your responsibilities\n\n\u00a0\u00a0\u00a0\u00a0\u00a0\u00a0\u00a0\u00a0 Assist to monitor the productivity and the daily operation of Air Freight Export Team\n\u00a0\u00a0\u00a0\u00a0\u00a0\u00a0\u00a0\u00a0 Coordinate with all applicable parties for all air export shipments, including internal parties, customers, operations team, sales team, warehouse and sub-contractors\n\u00a0\u00a0\u00a0\u00a0\u00a0\u00a0\u00a0\u00a0 Handle customer complaints and enquiries\n\u00a0\u00a0\u00a0\u00a0\u00a0\u00a0\u00a0\u00a0 Coordinating with airline or co-loader reservation\n\u00a0\u00a0\u00a0\u00a0\u00a0\u00a0\u00a0\u00a0 Prepare the flight planning and loading plan in cope with the cost & customer requirement\n\u00a0\u00a0\u00a0\u00a0\u00a0\u00a0\u00a0\u00a0 Monitor document completion process & delivery cargo before the airline cut-off time, ensure documents handed over to terminal accurately and timely\n\u00a0\u00a0\u00a0\u00a0\u00a0\u00a0\u00a0\u00a0 Perform any other duties as assigned by the Management\n\nCONTRIBUTE: your qualifications\n\n\u00a0\u00a0\u00a0\u00a0\u00a0\u00a0\u00a0\u00a0 Diploma or above in Logistics Management or related disciplines\n\u00a0\u00a0\u00a0\u00a0\u00a0\u00a0\u00a0\u00a0 Comprehensive product knowledge in air freight\n\u00a0\u00a0\u00a0\u00a0\u00a0\u00a0\u00a0\u00a0 5-8 years relevant experience with at least 2 years in supervisor level\n\u00a0\u00a0\u00a0\u00a0\u00a0\u00a0\u00a0\u00a0 Experience in handle DG, VAL and special cargo\n\u00a0\u00a0\u00a0\u00a0\u00a0\u00a0\u00a0\u00a0 Familiar with full set of air export documentation & cargo planning\n\u00a0\u00a0\u00a0\u00a0\u00a0\u00a0\u00a0\u00a0 Good command of both spoken/written English, Mandarin and Cantonese\n\u00a0\u00a0\u00a0\u00a0\u00a0\u00a0\u00a0\u00a0 Good computer knowledge in MS office especially in EXCEL\n\u00a0\u00a0\u00a0\u00a0\u00a0\u00a0\u00a0\u00a0 Good interpersonal, communication and problem solving skills\n\u00a0\u00a0\u00a0\u00a0\u00a0\u00a0\u00a0\u00a0 Independent, strong analytical and attention to details\n\nARE YOU INTERESTED?\n\nWe offer attractive remuneration packages to the successful candidate. Interested parties, please send your detailed resume, with\u00a0present and expected to Human Resources Department.\u00a0\u00a0\n\nWelcome to visit our website: www.dachser.com\n\n\nAll information provided by applicants will be treated in strictly confidential and used only for recruitment purposes. Applicants may be considered for other suitable positions by our Company not more than three months, after which their personal data will be destroyed.", "employment_types": ["Full Time", "Permanent"], "selling_points": ["Ensure customer satisfaction through good service", "Coordinate with operations and overseas office", "2-4 years of CS experience in AF export"], "locations": ["Tsuen Wan Area"], "categories": ["Transportation & Logistics", "Aviation Services", "Sales, CS & Business Devpt", "Customer Service - Supervisor / Officer", "Freight Forwarding"], "post_time": "2022-01-15T03:51:08Z", "salary": {"currency": null, "max": null, "min": null, "period": "monthly", "term": null}, "salary_visible": false, "title_keywords": ["customer service coordinator"], "responsibilities": ["collaborate", "any other duties", "cost", "management", "air freight", "customer complaints", "operations", "coordinate with", "quality", "monitor", "daily operation", "communication", "sales team", "logistics", "plan", "documentation", "internal parties", "planning"], "requirements": {"degrees": ["diploma or above"], "majors": ["related disciplines"], "languages": ["cantonese", "english", "mandarin"], "language_level": ["good command"], "hard_skills": ["planner", "excel", "airline", "documentation", "problem solving skills", "ms office"], "soft_skills": ["independent", "timely", "communication", "comprehensive", "attention to details", "problem solving skills", "interpersonal", "positive"], "languages_combined": [{"language": "cantonese", "language_level": ["good command"]}, {"language": "english", "language_level": ["good command"]}, {"language": "mandarin", "language_level": ["good command"]}]}, "experience_required": {"duration": ["at least 2 years", "5-8 years"], "field": ["relevant experience"]}}, {"job_id": "100003009050464", "location_code": "hk", "company": "Dachser Hong Kong Limited", "job_title": "SENIOR AIR FREIGHT EXPORT COORDINATOR (CARGO PLANNER)", "description": "Responsibilities:\n\n1. Responsible for handling daily inbound operation, daily report preparing, transportation arrangement, billing and filing.\n2. Communicate with internal & overseas customers to ensure a smooth running of the process;\n3. Assist to solve customers issues.\n4. Handle complaints and develop corrective measurement;\n5. Responsible for effective working practices with the customer.\n6. Import Declaration\n\nRequirements:\n\n1.\u00a0Tertiary education preferred\n2. Minimum 1 years of working experience in airfreight industry\n3. Good command of English & Chinese, good spoken Cantonese and Mandarin\n4. Independent strong personal motivation and well disciplines\n5. Responsible, self-managed and willing to work overtime.\n6. Good computer skill on Excel, Word and PowerPoint etc.\n7. Good analytical mind and commercial sense\n\nWe offer a rewarding package and company benefits including double pay, bonus, 15 days annual leave, medical insurance etc. Interested parties please send your full resume with current and expected salary to us.\n\nPersonal data collected will be used for recruitment purpose only.\n\nOur data processing are compliant with data protection regulations. To learn about GEODIS Privacy Policy or exercise your rights, go to http://geodis.com/dp/recruitment-privacy-policy\n\n", "employment_types": ["Full Time", "Permanent"], "selling_points": ["Strengthening our AF export operations processes", "Prepare the flight planning and loading plan", "Good interpersonal and communication skills"], "locations": ["Tsuen Wan Area"], "categories": ["Transportation & Logistics", "Aviation Services", "Freight Forwarding", "Supply Chain"], "post_time": "2022-01-14T10:28:35Z", "salary": {"currency": null, "max": null, "min": null, "period": "monthly", "term": null}, "salary_visible": false, "title_keywords": ["coordinator"], "responsibilities": ["communicate with", "measurement", "develop", "handle complaints", "daily report"], "requirements": {"degrees": [], "majors": [], "languages": ["cantonese", "english", "chinese", "mandarin"], "language_level": ["good command", "good"], "hard_skills": ["excel", "computer skill", "word", "powerpoint"], "soft_skills": ["work overtime", "independent", "responsible", "self-managed", "analytical mind"], "languages_combined": [{"language": "cantonese", "language_level": ["good", "good command"]}, {"language": "english", "language_level": ["good", "good command"]}, {"language": "chinese", "language_level": ["good", "good command"]}, {"language": "mandarin", "language_level": ["good", "good command"]}]}, "experience_required": {"duration": ["minimum 1 years"], "field": []}}, {"job_id": "100003009050749", "location_code": "hk", "company": "GEODIS Hong Kong Limited", "job_title": "Operation Clerk, Air Import", "description": "Responsibilities:\n\nProvide quality services both internal / external\nData entry and generation of reports\nProvide general support to the team\nCommunicate and co-ordinate with overseas office\n\n\u00a0Requirements:\n\nHKCEE / HKDSE or above\n1 year working experience is preferable\nGood command of English and Chinese (including Mandarin)\nGood in MS Office applications\nAble to work outside office hours and public holidays\nImmediately available is highly preferred\n\n\u00a0Benefits:\n\nMedical / Hospitalization Insurance\nLife Insurance\n5-Day Work Week\nBank Holidays\nDouble Pay\nPaid Sick Leave\nOvertime Allowance\nPerformance Bonus\n\nWe offer attractive remuneration package and good career prospect to the right candidates.\u00a0 Interested parties please send your detailed resume with expected salary and position applied by clicking \"Apply Now\".\n\n\nAll information collected will be used for recruitment purpose only.\n", "employment_types": ["Full Time", "Permanent"], "selling_points": ["Handle daily air import shipments", "15 days annual leave", "Medical & Dental Insurance Coverage"], "locations": ["Cheung Sha Wan"], "categories": ["Transportation & Logistics", "Others", "Freight Forwarding", "Supply Chain"], "post_time": "2022-01-14T11:16:03Z", "salary": {"currency": null, "max": null, "min": null, "period": "monthly", "term": null}, "salary_visible": false, "title_keywords": ["operation clerk"], "responsibilities": ["data entry", "co-ordinate with", "quality", "reports", "general support"], "requirements": {"degrees": ["hkdse"], "majors": [], "languages": ["english", "chinese", "mandarin"], "language_level": ["good command"], "hard_skills": ["ms office"], "soft_skills": [], "languages_combined": [{"language": "english", "language_level": ["good command"]}, {"language": "chinese", "language_level": ["good command"]}, {"language": "mandarin", "language_level": ["good command"]}]}, "experience_required": {"duration": ["1 year"], "field": []}}, {"job_id": "100003009049800", "location_code": "hk", "company": "Scanwell Logistics (Hong Kong) Ltd", "job_title": "Customer Services / Senior Customer Services", "description": "Principle Accountabilities\n\u00a0\n1.\u00a0Sea Freight Product Management\n\nReview and optimize current sea freight products\nBuild up new sea freight products to follow closely the market trends and response to client needs.\nImprove the competitive edge of sea freight products\nProduct promotion within the Group\n\n\u00a02.\u00a0Carrier Management and Procurement\n\nInitiate pricing strategy of all trades in accordance with Group strategy\nAnalyze cost and profitability in order to reduce cost\nRate negotiation and contract management with carriers\nTender management and allocation management\nProvide support to the Group Sea Freight Management team on rate negotiation and tender management\n\n\u00a03. Market Intelligence\u00a0\u00a0\n\nCollect and analyze updated market statistics and information\nRegular and timely update and alert of market trends, special incidents with Head of Ocean Product, Greater China and local team whenever needed\nAnalyze potential business opportunities and work closely with South China sales teams to create tender pipeline and understand customer needs\nCreate presentations to promote sea freight products and services internally and externally\n\n\u00a04.\u00a0Co-ordination\n\nCoordinate with the head office and other regions to ensure the best approach to important tenders for South China\nWork closely with sales teams to enhance business development of LCL/FCL, import/export\n\n\u00a05.\u00a0Management\n\nLiaise with Sea Freight Operations teams in South China to maintain high service standard\nEnhance the collaboration and knowledge sharing among the Sea Freight Operations teams in South China\nOptimize and manage all internal sea freight reports\u00a0\nParticipate annual appraisal of Sea Freight teams in South China\n\n\u00a06.\u00a0Networking\n\nDevelop and maintain strong relationships with co-loaders, carriers, suppliers and agents\nAttend external sea freight related events to enlarge network\n\nRequirements\n\nDegree holder in Logistics, Transportation, or International Trade\nMinimum 10 years of experiences in shipping lines and freight forwarding industry\n\nSolid experience and strong knowledge in sea freight operations, pricing and procurement of both LCL/FCL and import/export, especially in transpacific trade\nStrong relations and network with co-loaders and shipping lines in South China area\nGood financial, business and marketing awareness\nProficient English skills in both written and spoken; Chinese speaking is preferable; French, German, Spanish or Italian speaking is an advantage\nGood PC skills of MS Windows & Office\nExcellent communication, negotiation, presentation, networking and interpersonal skills\nStrong management and coordination skills\nStrong analytical, planning and problem solving skills\nTeam player. Comfortable working in multi-cultural environment.\nCapable to manage and work on multi-tasks with tight deadline\nWilling to travel domestically and internationally when required", "employment_types": ["Full Time", "Permanent"], "selling_points": ["Provide quality services both internal / external", "Fresh graduate will also be considered", "5-day work week"], "locations": ["Kowloon Bay"], "categories": ["Sales, CS & Business Devpt", "Customer Service - Supervisor / Officer", "Transportation & Logistics", "Freight Forwarding", "Sales Administration"], "post_time": "2022-01-14T09:14:56Z", "salary": {"currency": null, "max": null, "min": null, "period": "monthly", "term": null}, "salary_visible": false, "title_keywords": [], "responsibilities": ["understand customer needs", "shipping", "service standard", "operations", "communication", "maintain", "liaise with", "management team", "sea freight", "teams", "presentations", "develop", "reports", "logistics", "tender", "cost", "management", "provide support", "business opportunities", "review", "coordinate with", "contract management", "coordination", "planning"], "requirements": {"degrees": ["degree holder"], "majors": [], "languages": ["german", "english", "spanish", "french", "italian", "chinese"], "language_level": ["advantage", "proficient"], "hard_skills": ["problem solving skills", "pc skills", "ms windows", "presentations"], "soft_skills": ["negotiation", "coordination skills", "capable", "multi-tasks", "timely", "communication", "team player", "interpersonal skills", "problem solving skills", "presentation"], "languages_combined": [{"language": "german", "language_level": ["advantage"]}, {"language": "english", "language_level": ["proficient"]}, {"language": "spanish", "language_level": ["advantage"]}, {"language": "french", "language_level": ["advantage"]}, {"language": "italian", "language_level": []}, {"language": "chinese", "language_level": []}]}, "experience_required": {"duration": ["minimum 10 years"], "field": ["procurement"]}}, {"job_id": "100003009050092", "location_code": "hk", "company": "Clasquin (Far East) Ltd", "job_title": "Sea Freight Procurement Manager, South China", "description": "You will be the teammate of our well structured Air Freight Export team, responsible for processing export shipments and all related activities to facilitate shipment export. Candidates with positive attitude, strong independence\u00a0and willing to take night shift are welcome to apply. We offer long term and stable career to the right candidate.\n\nAIR FREIGHT EXPORT CLERK (OPERATIONS)\n\nCOLLABORATE: your responsibilities\n\n\nHandle full set of export documentations and provide daily operations support\nPrepare MAWB, HAWB, Cargo manifest and debit note\nCheck uplift status and prepare pre-alert to overseas\nResponsible for customers\u2019 enquiries and its correspondence\u00a0\n\n\u00a0\u00a0CONTRIBUTE: your qualifications\n\nHKDSE or above with 1-2 year(s) experience in air freight export operations\nGood computer knowledge in MS office\nResponsible, well-organized and detail-minded\nWilling to work overtime and able to work under pressure\nNight shift duty is required\nImmediate available is preferred\n\nARE YOU INTERESTED?\n\nWe offer attractive remuneration packages to the successful candidate. Interested parties, please send your detailed resume, with present and expected salary by \"Apply Now'\u00a0 button to the Human Resources Department.\n\nWelcome to visit our website: www.dachser.com\n\nAll information provided by applicants will be treated in strictly confidential and used only for recruitment purposes. Applicants may be considered for other suitable positions by our Company not more than three months, after which their personal data will be destroyed.", "employment_types": ["Full Time", "Permanent"], "selling_points": ["Review and optimize current sea freight products", "Initiate pricing strategy of all trades", "Collect & analyze updated market statistics & info"], "locations": ["Kwai Fong"], "categories": ["Transportation & Logistics", "Others", "Freight Forwarding", "Shipping"], "post_time": "2022-01-14T09:46:12Z", "salary": {"currency": null, "max": null, "min": null, "period": "monthly", "term": null}, "salary_visible": false, "title_keywords": ["manager"], "responsibilities": ["air freight"], "requirements": {"degrees": [], "majors": [], "languages": [], "language_level": [], "hard_skills": ["processing"], "soft_skills": ["positive attitude", "structured", "responsible"], "languages_combined": []}, "experience_required": {"duration": [], "field": []}}, {"job_id": "100003009050445", "location_code": "hk", "company": "Dachser Hong Kong Limited", "job_title": "AIR FREIGHT EXPORT CLERK (OPERATIONS)", "description": "Our client is a leading US fashion brand, they are now looking for talent in supply chain to join their expanding team in HK.\n\nJob responsibilities\n* Maintain steady stock level and review current inventory management plan when necessary\n* Monitor shipment and supervisor 3PL performance and delivery in timely manner\n* Coordinate with both internal and external parties to ensure inventory satisfactory\n* Liaise with suppliers & business partners to ensure smooth shipment scheduling & operation\n* Follow up on any unexpected situation and sort out solution to avoid shipment delay\n* Maintain good relationship with suppliers, vendors and forwarder to manage stable stock level\n\n\n\nJob requirements\n* Degree holder in Supply Chain, logistic or any related field\n* At least 3 years of experience in freight forwarding or supply chain\n* Strong interpersonal skill, detail minded and self-motivated\n* Proficient in MS Office especially in Excel, e.g. Pivot table, Vlookup\nExcellent command of both written and spoken English and Chinese including Mandarin", "employment_types": ["Full Time", "Permanent"], "selling_points": ["Handle full set of export documentations", "1-2 year(s) experience in export operations", "Night shift duty is required"], "locations": ["Tsuen Wan Area"], "categories": ["Transportation & Logistics", "Freight Forwarding", "Shipping", "Supply Chain"], "post_time": "2022-01-14T10:26:39Z", "salary": {"currency": null, "max": null, "min": null, "period": "monthly", "term": null}, "salary_visible": false, "title_keywords": ["operations", "clerk"], "responsibilities": ["inventory", "review", "monitor", "coordinate with", "internal and external parties", "maintain good relationship", "inventory management", "scheduling", "maintain", "plan", "liaise with suppliers"], "requirements": {"degrees": ["degree holder"], "majors": [], "languages": ["english", "chinese", "mandarin"], "language_level": ["excellent"], "hard_skills": ["excel", "pivot table", "vlookup", "ms office"], "soft_skills": ["self-motivated", "interpersonal skill"], "languages_combined": [{"language": "english", "language_level": ["excellent"]}, {"language": "chinese", "language_level": ["excellent"]}, {"language": "mandarin", "language_level": ["excellent"]}]}, "experience_required": {"duration": ["at least 3 years"], "field": ["supply chain"]}}, {"job_id": "100003009050785", "location_code": "hk", "company": "Walters People (HK)", "job_title": "Logistic Analyst (6 months contract)", "description": "Responsibilities:\n\n\nCoordinate air shipments between customers, overseas agents and operations\nMaintain relationship with existing customers and develop business through overseas agents\nProvide and communicate updated marketing information to customers and overseas agents\nHandle customer complaint in compliance with ISO standard\nTrace account receivable for C.O.D account\n\nRequirements:\n\n\nTertiary educated\u00a0or above, preferably with educational background in shipping/logistics studies\nMin.\u00a02 years of\u00a0relevant experience in freight forwarding industry\nPleasant personality with excellent customer service and communication skills\nGood verbal and written communication in English and Chinese with\u00a0fair Mandarin\nProficient in MS Word and Excel\nAble to work under pressure\n\nIf you are interested in the career opportunity stated above, please send your application letter and resume stating full details of your background, references and expected salary to us.\n\nPersonal data collected will be used for recruitment purpose only.\n\nOur data processing are compliant with data protection regulations. To learn about GEODIS Privacy Policy or exercise your rights, go to http://geodis.com/dp/recruitment-privacy-policy", "employment_types": ["Full Time", "Temporary"], "selling_points": ["US based fashion company", "MNC working environment", "Renewable contract"], "locations": ["Not Specified"], "categories": ["Transportation & Logistics", "Freight Forwarding", "Shipping", "Supply Chain"], "post_time": "2022-01-14T11:22:06Z", "salary": {"currency": "HKD", "max": 24999, "min": 20000, "period": "monthly", "term": null}, "salary_visible": true, "title_keywords": ["analyst"], "responsibilities": ["operations", "compliance", "develop", "coordinate", "maintain"], "requirements": {"degrees": [], "majors": [], "languages": ["english", "chinese", "mandarin"], "language_level": ["good"], "hard_skills": ["excel", "go", "processing", "ms word"], "soft_skills": ["communication skills", "interested in", "pleasant", "communication", "customer service", "work under pressure"], "languages_combined": [{"language": "english", "language_level": ["good"]}, {"language": "chinese", "language_level": ["good"]}, {"language": "mandarin", "language_level": ["good"]}]}, "experience_required": {"duration": ["2 years"], "field": ["relevant experience"]}}, {"job_id": "100003009050748", "location_code": "hk", "company": "GEODIS Hong Kong Limited", "job_title": "Customer Service Representative - Airfreight", "description": "Responsibilities:\n\nPerform the customs clearance and sort the shipment according to destination\nRelease the AAC shipment to the AAC customers\nRelease the ADC shipment to shuttle in order send to KC Depot\nPerform x-ray screening for outbound and transshipment\nAccept the outbound AAC shipments from AAC customers\nPerform pick up and delivery servies within Tung Chung and Airport area upon necessary\nPerform the ad-hoc tasks assigned by superior\n\nRequirements:\n\nForm 5 standard\n1 year working experience\nDriving license and basic computer skill\n\nWe offer excellent remuneration package including medical scheme, MPF scheme, travel allowance, labour holidays and discretionary bonus to the right candidate.\u00a0 Please forward your detailed resume indicating expected salary to our head office at Unit 907-910, 118 Connaught Road West, Sheung Wan, Hong Kong or fax to 2735-1372 or by clicking \u201cApply Now\u201d button to the attention of Ms. Peggy Yu. \u00a0\n\n(All information collected for recruitment purpose only)", "employment_types": ["Full Time", "Permanent"], "selling_points": ["Coordinate air shipments", "15 days annual leave", "Medical & Dental Insurance Coverage"], "locations": ["Cheung Sha Wan"], "categories": ["Transportation & Logistics", "Others", "Sales, CS & Business Devpt", "Customer Service - Supervisor / Officer", "Freight Forwarding"], "post_time": "2022-01-14T11:16:03Z", "salary": {"currency": null, "max": null, "min": null, "period": "monthly", "term": null}, "salary_visible": false, "title_keywords": ["customer service representative"], "responsibilities": ["ad-hoc tasks"], "requirements": {"degrees": ["form 5"], "majors": [], "languages": [], "language_level": [], "hard_skills": ["wan", "basic", "computer skill", "scheme"], "soft_skills": ["detailed"], "languages_combined": []}, "experience_required": {"duration": ["1 year"], "field": []}}, {"job_id": "100003009049818", "location_code": "hk", "company": "Lenton Group", "job_title": "Operations Assistant", "description": "Responsibilities:\n\n1. Manage Teams of Air Export Operations on 7 x 24 basis for dispatch handling at Hong Kong\n2. Ensure shipments and documentation are handed over to terminal timely and accurately\n3. Manage teams to update, entry in Cargowise system and ensure job level information are visible timely and accurately for both internal and external customers.\n4. Plan manpower in cost effective way to meet the budgeted headcount and the productivity\n5. Work closely with Customer Service Team, Key Account Management Team and Sales Team to provide excellent documentation service\n6. Work together with overseas Cargowise team to pursue enhancement of the system\n7. Streamline document flow and processing procedures and maintain the manual for team's reference\n8. Provide analysis on document team's performance\n9. Motivate, inspire, develop and engage all direct reports\n\nRequirements:\n\n1. Tertiary education preferred in Logistics discipline\n2. 7 years working experiences in airfreight forwarding operation with at least 5 years in supervisory level\n3. Preferably possess with DGR, RAR, and RACSF certificate\n4. Proficiency on airfreight operation, load planning & ULD loading\n5. Good knowledge of airline and air terminal operation\n6. Proven track record of continuous improvement and people management\n7. Good command of English and Chinese, Putonghua will be a plus\n\nIf you are interested in the career opportunity stated above, please send your resume stating full details of your background, references and expected salary to us.\n\nPersonal data collected will be used for recruitment purpose only.\n\nOur data processing are compliant with data protection regulations. To learn about GEODIS Privacy Policy or exercise your rights, go to http://geodis.com/dp/recruitment-privacy-policy\n\n", "employment_types": ["Full Time", "Permanent"], "selling_points": [], "locations": ["Airport Area"], "categories": ["Transportation & Logistics", "Freight Forwarding", "Inventory / Warehousing"], "post_time": "2022-01-14T09:20:27Z", "salary": {"currency": null, "max": null, "min": null, "period": "monthly", "term": null}, "salary_visible": false, "title_keywords": ["operations assistant"], "responsibilities": ["internal and external customers", "cost", "management team", "operations", "analysis", "teams", "procedures", "develop", "customer service", "sales team", "maintain", "plan", "reports", "documentation"], "requirements": {"degrees": ["certificate"], "majors": [], "languages": ["putonghua", "english", "chinese"], "language_level": ["good command"], "hard_skills": ["go", "plus", "processing", "airline"], "soft_skills": ["interested in"], "languages_combined": [{"language": "putonghua", "language_level": ["good command"]}, {"language": "english", "language_level": ["good command"]}, {"language": "chinese", "language_level": ["good command"]}]}, "experience_required": {"duration": ["7 years", "at least 5 years"], "field": ["supervisory level", "operation"]}}, {"job_id": "100003009050750", "location_code": "hk", "company": "GEODIS Hong Kong Limited", "job_title": "Air Export Operations Manager", "description": "\nJob Description\n\nResponsibilities:\n\u2022 Handle full set of Sea Freight Import & Export documents, operating consolidation, FCL & LCL shipments,\u00a0 transshipment, trucking arrangement, import & export customs declaration etc\n\u2022 Handle booking arrangement, quotations and B/L issue.\n\u2022 Perform cargo planning, maintain close communication with clients, co-loaders, carriers, overseas agents\n\nRequirement:\n\u2022 HKCEE / DSE or above\n\u2022 Experience in shipping and forwarding industry is\u00a0 necessary\n\u2022 Willing to work under pressure and provide better service to clients\nGood spoken & written English & Chinese (both Cantonese & Mandarin)\n", "employment_types": ["Full Time", "Permanent"], "selling_points": ["Manage airfreight forwarding operation team", "At least 5 years experience at supervisory level", "15 Days Annual Leave with Medical Insurance"], "locations": ["Cheung Sha Wan"], "categories": ["Transportation & Logistics", "Aviation Services", "Others", "Freight Forwarding"], "post_time": "2022-01-14T11:16:03Z", "salary": {"currency": null, "max": null, "min": null, "period": "monthly", "term": null}, "salary_visible": false, "title_keywords": ["air export operations manager"], "responsibilities": ["customs declaration", "sea freight", "communication", "maintain", "booking", "planning"], "requirements": {"degrees": ["dse"], "majors": [], "languages": ["cantonese", "english", "chinese", "mandarin"], "language_level": ["good"], "hard_skills": [], "soft_skills": ["work under pressure"], "languages_combined": [{"language": "cantonese", "language_level": []}, {"language": "english", "language_level": ["good"]}, {"language": "chinese", "language_level": ["good"]}, {"language": "mandarin", "language_level": []}]}, "experience_required": {"duration": [], "field": []}}, {"job_id": "100003009042904", "location_code": "hk", "company": "IFB International Freightbridge Limited", "job_title": "Sea Freight Operation", "description": "I.\u00a0Job Overview\n\nThis position will be responsible for managing the logistics of SEKO\u2019s key customers. Other responsibilities are to develop and maintain reports and KPIs, handle customer enquiries, requests, and quotations for the Commercial team. This position requires strong communication skills and excellent understanding of reports and data analysis using MS Excel to create pivot table, charts, etc.\n\nII. Roles and Responsibilities\n\nCarrier allocation management, oversee booking execution and manage exceptions\nProactively update customers about shipment process and status\nMonitor and liaise with Operations to ensure compliance of SOP\nProduce reports on a regular basis to manage performance and business trend\nCommunicate across multiple functions in the client organization\nRespond promptly and assist in providing quotations to customers\nEnsure the integrity and accuracy of invoicing\nReview current and setup new procedures for continuous improvements\nIII. Education and Experience requirements\nBachelor\u2019s degree or relevant qualification\n2 years\u2019 experience in Supply Chain, Logistics or Freight Forwarding industry\nFresh or recent graduates are encouraged to apply\nKnowledge of Ocean and Air Transportation modes\n\nIV. Job Skills, Personality and Competencies for this position\n\nExcellent with MS Excel in creating pivot tables and charts\u00a0for reports and data analysis\nKnowledge of CargoWise and BI Tools an advantage\nStrong communication and interpersonal skills\nGood command of spoken and written English, Cantonese and Mandarin\nDetail-minded, willing to learn and able to work independently", "employment_types": ["Full Time"], "selling_points": ["Sea Freight", "Shipping", "LCL"], "locations": ["Wan Chai"], "categories": ["Transportation & Logistics", "Freight Forwarding", "Shipping"], "post_time": "2022-01-12T09:11:24Z", "salary": {"currency": null, "max": null, "min": null, "period": "monthly", "term": null}, "salary_visible": false, "title_keywords": [], "responsibilities": ["continuous improvements", "management", "operations", "review", "monitor", "procedures", "ensure compliance", "invoicing", "reports", "booking", "liaise with", "setup"], "requirements": {"degrees": ["degree", "bachelor"], "majors": [], "languages": ["cantonese", "english", "mandarin"], "language_level": ["good command"], "hard_skills": ["bi", "ms excel", "analysis"], "soft_skills": ["detail-minded", "work independently", "communication and interpersonal skills", "willing to learn"], "languages_combined": [{"language": "cantonese", "language_level": ["good command"]}, {"language": "english", "language_level": ["good command"]}, {"language": "mandarin", "language_level": ["good command"]}]}, "experience_required": {"duration": ["2 years"], "field": ["supply chain", "logistics", "education"]}}, {"job_id": "100003009050616", "location_code": "hk", "company": "Seko Logistics (HK) Limited", "job_title": "Control Tower Executive - Commercial, Asia Pacific", "description": "\n\u8077\u8cac :\u4e00\u822c\u9001\u8ca8\u5de5\u4eba\u5de5\u4f5c, \u8ddf\u8eca\u9001\u8ca8, \u88dd\u5378\u8ca8\u7269, \u642c\u904b\u8ca8\u7269, \u64cd\u63a7\u8ca8\u8eca\u5c3e\u677f, \u5354\u52a9\u5009\u52d9\u5de5\u4f5c\n\n\u8cc7\u6b77 :\u4e2d\u4e09\u7a0b\u5ea6; \u826f\u597d\u7cb5\u8a9e; \u4e00\u822c\u666e\u901a\u8a71; \u4e00\u822c\u82f1\u8a9e; \u61c2\u8b80\u5beb\u4e2d\u6587; \u7565\u61c2\u8b80\u5beb\u82f1\u6587\n\n\u5f85\u9047 :\u6bcf\u6708$14,500, \u661f\u671f\u4e00\u81f3\u516d: \u4e0a\u53488\u6642\u534a\u81f3\u4e0b\u53486\u6642\u534a, \u6bcf\u9031\u5de5\u4f5c6\u5929, \u6bcf\u5929\u5de5\u4f5c 9 \u5c0f\u6642\n\n\u7533\u8acb\u9808\u77e5 :\u6c42\u8077\u8005\u53ef\u81f4\u96fb23626289\u8207\u83ef\u8208\u6587\u5100\u96c6\u5718\u6709\u9650\u516c\u53f8\u5340\u5c0f\u59d0\u806f\u7d61\u3002\n\n", "employment_types": ["Full Time", "Permanent"], "selling_points": ["2 years\u2019 experience in Supply Chain industry", "Fresh or recent graduates are encouraged to apply", "Knowledge of Ocean and Air Transportation modes"], "locations": ["Kowloon Bay"], "categories": ["Transportation & Logistics", "Freight Forwarding", "Supply Chain"], "post_time": "2022-01-14T10:57:46Z", "salary": {"currency": null, "max": null, "min": null, "period": "monthly", "term": null}, "salary_visible": false, "title_keywords": ["executive"], "responsibilities": [], "requirements": {"degrees": [], "majors": [], "languages": [], "language_level": [], "hard_skills": [], "soft_skills": [], "languages_combined": []}, "experience_required": {"duration": [], "field": []}}, {"job_id": "100003009053841", "location_code": "hk", "company": "Wah Hing Office Supplies Group Limited", "job_title": "\u8ddf\u8eca\u5de5\u4eba", "description": "Reports to: Cargo Digital Manager- Transformation and Analytics\u00a0\nDepartment:\u00a0Cargo Commercial\n\nRole Introduction\n\n\nTo support the Cargo Digital Manager \u2013 Transformation and Analytics to generate actionable insights to support the data driven culture within Cargo in decision making processes, and to proactively support both cargo commercial and service delivery teams in applying and integrating the right set of metrics, analytics model and visualization into day-to-day operations\nThis role is one of the key capabilities to enhance the analytics power for Cargo with new data, derived insight, tools and training with proper testing and requirement sets. This candidate will work to support Cargo Digital team to cover the\u00a0 whole Cargo function in ensure the compliance of quality & data governance policies and processes so to uphold security, quality and value of the analytics assets.\nKey Responsibility\u00a0\nWork closely with different Cargo business units to ensure a holistic view on analytics, identify potential synergy and ensure data requirements and impact of other databases are well thought through accommodated in any new Cargo digital transformation initiative\nDesign with different cargo business units to frame business questions and analytics / report use cases, identify quantitative / qualitative benefits, and iron out any development and BU action dependencies, such as process change, system integration, etc\nSupport the development of the long term analytics roadmap for cargo department aligning with CX digital strategy\nConsolidate data requirements per use case needs, and seek approval from data owner on data application\nPerform analysis and build dashboard visualizations per BU use case requirement. Conduct dashboard enhancements when needed\nAct as a bridge between Cargo and IT to facilitate analytics related technical development\u00a0\nBring in new data & insight, support data model design and data definitions to ensure proper and aligned application of data across different use cases\nFacilitate new data classification process with respective Cargo BU\nTrain and facilitate cargo business units in order to build up cargo analytics community to strengthen our data-driven decision making power across cargo business units \u00a0\nManage data quality by implementing quality metrics & regular monitoring, working on incidents to maintain accessibility and consistency of data as well as readiness of related analytics capabilities\nEnforce data governance practices to uphold the value of the data access, within the company and external parties\nSupport new digital analysis and data mining solutions to enable operational excellence improvement\n\n\nRequirements\n\n\nMinimum 4 years of working experience relating to data & analytics\nGood understanding of Cargo business is a plus\nStrong analytics abilities, numerate and familiar with statistical algorithms with good business acumen\nExpert in using analytics & query tools e.g. Alteryx and data modelling technique\nProficiency in data visualization tools, ideally QlikSense\nProficiency in scripting languages (Python / SQL)\nTeam player with strong communication & interpersonal skills, able to share effectively across different business streams\nCurious, meticulous, self-motivated and strong continuous improvement mindset\nWorking knowledge in project management / JIRA a plus\nApplication Deadline:\u00a031 Jan 2022\n\n\nPersonal & Application Information\n\nCathay Pacific is an Equal Opportunities Employer. Personal data provided by job applicants will be used strictly in accordance with our personal data policy and for recruitment purposes only. Candidates not notified within eight weeks may consider their application unsuccessful. All related information will be kept in our file for up to 24 months. A copy of our Personal Information Collection Statement will be provided upon request by contacting our Data\u00a0Protection Officer.\n\nPlease note that with effect from 1 December 2021, all employees must be vaccinated in order to access Cathay City and all other Cathay Group Company premises in Hong Kong. Consideration will be given to those who are unable to get vaccinated for valid medical reasons.\n\n\n\n", "employment_types": ["Full Time"], "selling_points": [], "locations": ["To Kwa Wan"], "categories": ["Transportation & Logistics", "Freight Forwarding", "Inventory / Warehousing", "Supply Chain"], "post_time": "2022-01-17T07:36:29Z", "salary": {"currency": null, "max": null, "min": null, "period": "monthly", "term": null}, "salary_visible": false, "title_keywords": [], "responsibilities": ["data", "analysis", "monitoring", "quality", "external parties", "design", "maintain", "databases", "data mining", "report"], "requirements": {"degrees": [], "majors": [], "languages": [], "language_level": [], "hard_skills": ["plus", "data visualization", "sql", "project management", "alteryx", "python", "acumen"], "soft_skills": ["meticulous", "self-motivated", "communication", "project management", "interpersonal skills", "business acumen", "team player"], "languages_combined": []}, "experience_required": {"duration": ["minimum 4 years"], "field": []}}, {"job_id": "100003009052243", "location_code": "hk", "company": "Cathay Pacific Airways Ltd", "job_title": "Assistant Manager - Cargo Digital Analytics", "description": "Garment Shipping x 2 Posts\nSundries Shipping x 1 Post\nForwarders / Liner x 2 Posts\n\nResponsibilities\n\nHandle full sets of import/export documents preferred\nCoordination with customers and vendors\n\nRequirements\n\nF.5 or above\n1-5 years relevant experiences\nDetail-minded, careful, good team player\nProficiently in MS office, Excel/Word\nAble to communication with English and Mandarin\u00a0\n\nInterested parties, please send your resume with expected salary by clicking the below \"apply now\" button.\u00a0You can ask click on the website\u00a0www.easyjobhk.com\u00a0for more details about the company", "employment_types": ["Full Time"], "selling_points": ["Minimum 4 years of working experience", "Data & analytics", "Travel Benefits, 5-days work, Medical Benefits"], "locations": ["Lantau Island"], "categories": ["Transportation & Logistics", "Freight Forwarding", "Supply Chain", "Information Technology (IT)", "Data Scientist"], "post_time": "2022-01-17T02:33:33Z", "salary": {"currency": null, "max": null, "min": null, "period": "monthly", "term": null}, "salary_visible": false, "title_keywords": ["assistant manager"], "responsibilities": ["coordination with"], "requirements": {"degrees": [], "majors": [], "languages": ["english", "mandarin"], "language_level": [], "hard_skills": ["excel", "word", "ms office"], "soft_skills": ["detail-minded", "good team player", "careful", "communication"], "languages_combined": [{"language": "english", "language_level": []}, {"language": "mandarin", "language_level": []}]}, "experience_required": {"duration": ["1-5 years"], "field": []}}, {"job_id": "100003009053096", "location_code": "hk", "company": "Tat Ming Wallpaper Company Limited", "job_title": "\u8ddf\u8eca\u9001\u8ca8\u54e1", "description": "Sr. Operation Manager/ Sea Operation Supervisor / Sea Operation Clerk / Air Operation Clerk/ Supervisor /\u00a0Customer Services Clerk / Logistic Clerk/ Warehouse Clerk ( Urgent )\u00a0x10\n\n( Tsuen Wan/ Kwai Chung ) , Salary :13-50K ( Nego)\u00a0\nRequirements:\nF.5 or above,\u00a0\n1-20 year or above working experience in Shipping or Forwarder\nGood Command of English and Chinese, Mandarin Speaking will be an advantage\nMinimum 5 years operation/ CS experience in forwarding business,\u00a0At least 3 years supervisory or management experience,\u00a0To overseeing all trade including ocean outbound and inbound traffic,\u00a0To supervise the team of ocean freight, around 15 colleagues( Assistant Manager Position)\n0-10 years operation exp or Sales exp or CS exp in Air or Sea operation.\u00a0\nImmediate available is preferable\nhave less exp also will be consider Operation Clerk / CS Executive/ Sales Executive /Logistic Clerk.\u00a0\n\nBusiness Development Manager / Sales Manager (Air Freight)\nLocation : Kwai Chung- 5 Days, Salary : 22-30K\u00a0\nResponsibilities:\n\n\nExplore and develop new customers in Air Freight\u00a0Forwarding industry.\nTo take the lead in developing and implementing the sales strategies for Global Account in order to achieve the business goals.\nCreate and enhance long-term business relationships with customers to maximize business growth and opportunities.\nCoordinate projects and prepare proposal or report for customers\nReport to Japanese General Manager.\nRequirements:\n\nBachelor Degree holder.\nMinimum 5 years of\u00a0 corporate sales experience in\u00a0 Logistics / Air Freight Forwarding industry.\nLess experience will be considered as Assistant\u00a0 Manager .\nGood at communication, presentation & consultative selling skills.\nGood command of both written and spoken English\u00a0and Chinese.\n\u00a0*** Personal data will be treated with strict confidential and used for recruitment purpose only.\n\nP & A consultant Ltd will not charge any fees from the above-stated job-seeker, your job apply to our company means your acceptance of our terms and conditions.", "employment_types": ["Full Time"], "selling_points": [], "locations": ["Not Specified"], "categories": ["Transportation & Logistics", "Freight Forwarding", "Inventory / Warehousing", "Supply Chain"], "post_time": "2022-01-17T05:50:18Z", "salary": {"currency": null, "max": null, "min": null, "period": "monthly", "term": null}, "salary_visible": false, "title_keywords": [], "responsibilities": ["business goals", "air freight", "developing", "develop", "coordinate", "communication", "logistics", "recruitment", "personal data", "report"], "requirements": {"degrees": [], "majors": [], "languages": ["english", "chinese", "mandarin"], "language_level": ["advantage", "good command"], "hard_skills": [], "soft_skills": [], "languages_combined": [{"language": "english", "language_level": ["advantage", "good command", "good command"]}, {"language": "chinese", "language_level": ["advantage", "good command", "good command"]}, {"language": "mandarin", "language_level": ["advantage", "good command"]}]}, "experience_required": {"duration": ["at least 3 years", "minimum 5 years", "1-20 year"], "field": ["supervisory", "management", "business", "operation", "cs", "team"]}}, {"job_id": "100003009050007", "location_code": "hk", "company": "P & A Consultant Limited", "job_title": "Sales Manager/Sr. Operation Manager/ Operation Supervisor/ CS Clerk/Warehouse Clerk (Forwarder)", "description": "Job Responsibilities:\u00a0\u00a0\n\nTo\u00a0handle and follow up enquiries, shipment booking from customers, overseas agents and overseas offices\nTo collaborate closely with internal and external operations to deliver quality services\nTo\u00a0input data in operating system timely and accurately\n\nJob Requirements:\n\nProficiency in written and spoken English is a must.\nUniversity Graduate or above\n2-3 years relevant working experience in customer service in logistics / freight forwarding industries\nIndependent, responsible, well-organized & able to work under pressure\nProficiency in using MS Office applications\nImmediately available is preferable", "employment_types": ["Full Time"], "selling_points": [], "locations": ["Tsuen Wan Area"], "categories": ["Sales, CS & Business Devpt", "Business Development", "Transportation & Logistics", "Freight Forwarding", "Inventory / Warehousing"], "post_time": "2022-01-15T03:50:47Z", "salary": {"currency": null, "max": null, "min": null, "period": "monthly", "term": null}, "salary_visible": false, "title_keywords": ["sales manager", "operation supervisor", "warehouse clerk", "clerk", "operation manager"], "responsibilities": ["collaborate", "data", "operations", "quality", "booking"], "requirements": {"degrees": ["university graduate or above"], "majors": [], "languages": ["english"], "language_level": ["proficiency"], "hard_skills": ["ms office"], "soft_skills": ["independent", "responsible", "well-organized", "customer service", "work under pressure"], "languages_combined": [{"language": "english", "language_level": ["proficiency"]}]}, "experience_required": {"duration": ["2-3 years"], "field": ["customer service", "logistics", "relevant working experience"]}}, {"job_id": "100003009050484", "location_code": "hk", "company": "Dachser Hong Kong Limited", "job_title": "CUSTOMER SERVICE COORDINATOR OCEAN FREIGHT EXPORT", "description": "Our Hong Kong team has been through a positive development in recent years with improved results, higher productivity and a growing customer base.\n\nWe are now looking for a high caliber individual to join our Ocean\u00a0Freight Export\u00a0team.\u00a0 This role plays a key part in managing the full export\u00a0process for a shipment, coordinate with customer and oversee agents to ensure deliveries are made in good time.\n\nCUSTOMER SERVICE COORDINATOR OCEAN FREIGHT EXPORT\n\nCOLLABORATE: your responsibilities\n\nResponsible for full set export shipments (release booking, issue BL, invoice, arrange pick up, arrange insurance and import / export declaration, etc)\nHandle customers\u2019 enquiries, pre-claims and overseas agent correspondence\nFollow up overseas routing order and booking from customers\nCo-ordinate with freight forwarder, carriers and overseas counterparts for shipment arrangement.\u00a0\n\nCONTRIBUTE: your qualifications\n\n\nHigher Diploma holder in Logistics Management or related disciplines\n2-4 years\u2019 experience in ocean freight export operations\nKnowledge on transshipment, export documents, import/export declaration\nHands-on PC operation in MS office / Lotus Notes\nGood command of written and spoken English and Mandarin\nGood communication & interpersonal skills\nGood team player, pro-active and attention to details\nAble to work independently and under pressure\n\nARE YOU INTERESTED?\n\nWe offer attractive remuneration packages to the successful candidate. Interested parties, please send your detailed resume, with\u00a0present and expected salary via email quoting advertisement reference to the Human Resources Department.\u00a0\u00a0\n\nWelcome to visit our website: www.dachser.com\n\n\nAll information provided by applicants will be treated in strictly confidential and used only for recruitment purposes. Applicants may be considered for other suitable positions by our Company not more than three months, after which their personal data will be destroyed.", "employment_types": ["Full Time", "Permanent"], "selling_points": ["Handle full set OF Export operations process", "Good team player, pro-active and detail-minded", "Good communication & interpersonal skills"], "locations": ["Tsuen Wan Area"], "categories": ["Sales, CS & Business Devpt", "Customer Service - Supervisor / Officer", "Transportation & Logistics", "Freight Forwarding", "Shipping"], "post_time": "2022-01-15T03:51:08Z", "salary": {"currency": null, "max": null, "min": null, "period": "monthly", "term": null}, "salary_visible": false, "title_keywords": ["customer service coordinator"], "responsibilities": ["collaborate", "management", "shipment arrangement", "invoice", "co-ordinate with", "operations", "coordinate with", "communication", "customer service", "logistics", "booking", "insurance"], "requirements": {"degrees": ["higher diploma holder"], "majors": ["related disciplines"], "languages": ["english", "mandarin"], "language_level": ["good command"], "hard_skills": ["pc", "ms office"], "soft_skills": ["good team player", "work independently", "under pressure", "responsible", "communication", "hands-on", "customer service", "interpersonal skills", "attention to details", "pro-active", "positive"], "languages_combined": [{"language": "english", "language_level": ["good command"]}, {"language": "mandarin", "language_level": ["good command"]}]}, "experience_required": {"duration": ["2-4 years"], "field": []}}, {"job_id": "100003009038959", "location_code": "hk", "company": "Scan Global Logistics Limited", "job_title": "Ocean Freight Operation", "description": "Job Descriptions:\n\nHandle full set ocean export operation shipments and document\u00a0(US Trade / EU Trade /Asia Trade)\nCo-ordinate with shipping line, co-loader, sub-contractor and warehouse\nHandle inquiries from overseas office, agents, customers\nIssue invoice for payment collection\nHandle License & Declaration\nOptimize profit per file\n\n\u00a0Requirement:\n\nF5 or above/HKDSE with at least 3 years working experience in Global Freight Forwarding\nFamiliar in PC knowledge, MS office\nGood Communication and interpersonal skills\nGeneral command of written and spoken English, Cantonese and Putonghua\nWell-organized, able to work independently and under pressure\nFlexible, adaptable to changes and willing to learn\nImmediately available is preferred", "employment_types": ["Full Time"], "selling_points": ["Double pay, 5 days work per week", "Medical Insurance, Dental insurance", "Overtime allowance"], "locations": ["Tin Hau"], "categories": ["Transportation & Logistics", "Freight Forwarding"], "post_time": "2022-01-11T08:13:32Z", "salary": {"currency": null, "max": null, "min": null, "period": "monthly", "term": null}, "salary_visible": false, "title_keywords": [], "responsibilities": ["co-ordinate with", "payment collection", "shipping", "invoice"], "requirements": {"degrees": ["hkdse"], "majors": [], "languages": ["cantonese", "putonghua", "english"], "language_level": [], "hard_skills": ["pc knowledge", "ms office"], "soft_skills": ["flexible", "work independently", "under pressure", "adaptable", "well-organized", "willing to learn", "communication and interpersonal skills"], "languages_combined": [{"language": "cantonese", "language_level": []}, {"language": "putonghua", "language_level": []}, {"language": "english", "language_level": []}]}, "experience_required": {"duration": ["at least 3 years"], "field": []}}, {"job_id": "100003009050457", "location_code": "hk", "company": "Expeditors Hong Kong Limited", "job_title": "Sales Coordinator (Logistics Solutions) (Fresh Graduates)", "description": "The Job:\n\nTo provide sales support to the assigned Business Development Manager, including handling Request for Quotation (RFQ), rate enquiry, customized data analysis report of listed customers and incoming sales calls, etc.\nTo assist in handling procedure set up for ensuring customer service compliance & follow up with operations departments for any service failure.\nTo participate in customer service reviews, customer satisfaction surveys and making analysis for designated account.\nTo perform monitoring function in the trial period of new secured business for ensuring customers\u2019 satisfaction.\nTo act as coordinator among different departments and gather related market information for salesmen to develop business.\n\nThe Qualifications:\n\nUniversity graduate with 1-2 years relevant experience.\nFresh graduates with positive attitude are also welcome.\nFluent spoken Cantonese, English and Mandarin.\nGood PC knowledge.\nOutgoing character with excellent communication skills and telephone manner.\nIndependent, initiative and willing to learn.\n\nThe Future:\n\nCandidate for supervisory\u00a0position.\n\nAttractive remuneration\u00a0package\u00a0with good career prospect will be offered to the right candidates. Interested parties, please send your full resume and expecting salary to the Manager-Administration, 36/F-37/F, Enterprise Square Three, 39 Wang Chiu Road, Kowloon Bay, Hong Kong or fax to 2721 9734\u00a0or by clicking \"Apply Now\" button below. Please quote the reference on your application. Further information about the Company can be obtained at Expeditors\u2019 website:\u00a0http://www.expeditors.com. Shortlisted candidates will be notified within 6 weeks.\n\n\u00a0All information provided by candidates will be used solely for recruitment purposes. Unsuccessful application will be destroyed in strict confidence upon completion of recruitment process.\n\nExpeditors is an equal opportunities employer and works towards a smoke free environment.", "employment_types": ["Full Time"], "selling_points": [], "locations": ["Kowloon Bay"], "categories": ["Transportation & Logistics", "Freight Forwarding", "Supply Chain", "Sales, CS & Business Devpt", "Sales Administration"], "post_time": "2022-01-14T10:27:57Z", "salary": {"currency": null, "max": null, "min": null, "period": "monthly", "term": null}, "salary_visible": false, "title_keywords": ["sales coordinator", "logistics"], "responsibilities": ["market information", "operations", "analysis", "compliance", "quotation", "monitoring", "develop", "data analysis", "communication", "customer service", "report"], "requirements": {"degrees": ["university graduate"], "majors": [], "languages": ["cantonese", "english", "mandarin"], "language_level": ["fluent"], "hard_skills": ["analysis", "sales support", "pc knowledge"], "soft_skills": ["outgoing", "communication skills", "independent", "willing to learn", "positive attitude", "customer service", "telephone manner", "initiative"], "languages_combined": [{"language": "cantonese", "language_level": ["fluent"]}, {"language": "english", "language_level": []}, {"language": "mandarin", "language_level": []}]}, "experience_required": {"duration": ["1-2 years"], "field": ["relevant experience"]}}, {"job_id": "100003009053944", "location_code": "hk", "company": "Lee Kum Kee (Hong Kong) Foods Ltd", "job_title": "\u9ad8\u7d1a\u5009\u52d9\u54e1", "description": "\u8077\u8cac :\u5354\u52a9\u5009\u5eab\u4e3b\u7ba1\u9032\u884c\u8ca8\u5009\u7ba1\u7406\u53ca\u904b\u4f5c\uff0c \u5305\u62ec\u6536\u8ca8\u3001\u57f7\u8ca8\u3001\u5206\u8ca8\u3001\u642c\u8ca8\u53ca\u76e4\u9ede\u7b49\uff1b\u8ca0\u8cac\u5ee0\u623f\u5167\u65e5\u5e38\u5305\u88dd\u7269\u6599\u904b\u9001\uff1b\u4fdd\u6301\u5009\u5eab\u6e05\u6f54\u4e7e\u6de8\n\u8cc7\u6b77 :\u4e2d\u4e09\u7a0b\u5ea6; 3\u5e74\u7d93\u9a57; \u826f\u597d\u7cb5\u8a9e; \u4e00\u822c\u666e\u901a\u8a71; \u4e00\u822c\u82f1\u8a9e; \u61c2\u8b80\u5beb\u4e2d\u6587; \u7565\u61c2\u8b80\u5beb\u82f1\u6587; \u5177\u6709\u57fa\u672c\u96fb\u8166\u64cd\u4f5c\u77e5\u8b58; \u61c2SAP\u7cfb\u7d71\u512a\u5148\uff1b\u6301\u6709\u6709\u6548\u4e4b\u6297\u8861\u5f0f\u93df\u8eca\u64cd\u4f5c\u8b49\u512a\u5148\n\u5f85\u9047 :\u6bcf\u6708$15,000 - $17,000, \u6709\u96d9\u7ce7, \u8d85\u6642\u5de5\u4f5c\u6d25\u8cbc, \u914c\u60c5\u6027\u82b1\u7d05, \u4f9b\u81b3\u98df, \u7a7f\u68ad\u5df4\u58eb\u670d\u52d9, \u91ab\u7642\u798f\u5229 \u53ca\u54e1\u5de5\u8cfc\u7269\u512a\u60e0, \u661f\u671f\u4e00\u81f3\u516d: \u4e0a\u53488\u6642\u534a\u81f3\u4e0b\u53486\u6642, \u6bcf\u9031\u5de5\u4f5c5\u5929\u81f36\u5929, \u6bcf\u5929\u5de5\u4f5c 9.5 \u5c0f\u6642, \u661f\u671f\u516d\u9577\u77ed\u9031", "employment_types": ["Full Time"], "selling_points": [], "locations": ["Tai Po Area"], "categories": ["Transportation & Logistics", "Freight Forwarding", "Inventory / Warehousing", "Shipping"], "post_time": "2022-01-17T07:48:46Z", "salary": {"currency": null, "max": null, "min": null, "period": "monthly", "term": null}, "salary_visible": false, "title_keywords": [], "responsibilities": [], "requirements": {"degrees": [], "majors": [], "languages": [], "language_level": [], "hard_skills": [], "soft_skills": [], "languages_combined": []}, "experience_required": {"duration": [], "field": []}}, {"job_id": "100003009047159", "location_code": "hk", "company": "CTI Logistics (HK) Co., Limited", "job_title": "\u7a7a\u904b / \u6d77\u904b\u64cd\u4f5c\u54e1 Air & Ocean Operations Clerk", "description": "\u8077\u8cac:\n\n\u8655\u7406\u65e5\u5e38\u8a02\u4f4d\u4e8b\u5b9c\u3002\n\u8655\u7406\u51fa\u5165\u53e3\u6587\u4ef6\uff0c\u8cc7\u6599\u8f38\u5165\u53ca\u6587\u4ef6\u5132\u5b58\u3002\n\n\n\u8981\u6c42:\n\n\u4e2d\u4e94\u7a0b\u5ea6\u00a0 (\u7121\u9700\u76f8\u95dc\u7d93\u9a57)\n\u64cd\u4f5c\u96fb\u8166\n\u9700\u8f2a\u73ed\u5de5\u4f5c\n\u53ef\u5373\u6642\u4e0a\u73ed\n\n\n\u6709\u8208\u8da3\u4eba\u58eb\uff0c\u53ef\u5c07\u5c65\u66c6\u53ca\u8981\u6c42\u5f85\u9047\u5f80: \"Apply Now\"\n\nResponsibilities:\n\nHandle daily bookings.\nHandle full set of export document, data entry and filing.\n\n\nRequirements:-\n\nForm 5 or above.\u00a0 (No experience is also welcome)\nKnowledge in PC operations.\nWork on shift\nImmediate Available\n\n\n\nFor those interested, please send resume with expected salary to \"Apply Now\"\n", "employment_types": ["Full Time", "Permanent"], "selling_points": [], "locations": ["Kwai Tsing Area"], "categories": ["Admin & HR", "Others", "Transportation & Logistics", "Freight Forwarding", "Shipping"], "post_time": "2022-01-14T02:29:43Z", "salary": {"currency": null, "max": null, "min": null, "period": "monthly", "term": null}, "salary_visible": false, "title_keywords": ["operations clerk"], "responsibilities": ["data entry and filing"], "requirements": {"degrees": ["form 5 or above"], "majors": [], "languages": [], "language_level": [], "hard_skills": ["no", "pc operations"], "soft_skills": [], "languages_combined": []}, "experience_required": {"duration": [], "field": []}}, {"job_id": "100003009051403", "location_code": "hk", "company": "NNR Global Logistics (HK) Limited", "job_title": "Sales Executive / Indoor Sales Executive", "description": "Responsibilities\u00a0 \u00a0 \u00a0 \u00a0 \u00a0\u00a0\n\n*Perform sales functions and assist in daily sales issues \u00b7\u00a0 \u00a0 \u00a0 \u00a0 \u00a0\u00a0\n\n*Develop freehand business opportunities with new and existing customers \u00b7\u00a0 \u00a0\n\n*Promote the full range of company services to potential customers and build own\u00a0 client base \u00b7\u00a0 \u00a0 \u00a0 \u00a0 \u00a0\u00a0\n\n*Conduct daily sales call & generate sales lead to overseas counterparts \u00b7\u00a0 \u00a0 \u00a0 \u00a0\n\n*Perform ad-hoc project assigned by the management \u00b7\u00a0 \u00a0 \u00a0 \u00a0 \u00a0\u00a0\n\n*On-The-Job Training will be provided\u00a0 \u00a0\u00a0\n\nRequirements: \u00b7\u00a0 \u00a0 \u00a0 \u00a0 \u00a0\u00a0\n\n*Certificate/ Diploma / Higher Diploma holder or above\u00a0\n\n*Good communication skill and presentation skill\u00a0 \u00a0 \u00a0 \u00a0 \u00a0\u00a0\n\n*Aggressive, self-driven & result-oriented with good interpersonal skill, able to work under pressure\u00a0 \u00a0 \u00a0 \u00a0 \u00a0\n\n*Good command of written and spoken English, Cantonese (Mandarin will be an advantage) \u00b7\u00a0 \u00a0 \u00a0 \u00a0 \u00a0\u00a0\n\n*2-4 years\u2019 experience in supply chain/ freight forwarding / carriers / logistics industry preferred\n\n*Incentive bonus will be provided if meet target\u00a0 \u00a0 \u00a0 \u00a0 \u00a0 \u00a0\n\n*More experienced candidate will be considered as\u00a0Senior Sales Executive", "employment_types": ["Full Time", "Permanent"], "selling_points": [], "locations": ["Lai Chi Kok"], "categories": ["Sales, CS & Business Devpt", "Business Development", "Transportation & Logistics", "Freight Forwarding", "Direct Sales"], "post_time": "2022-01-15T14:34:11Z", "salary": {"currency": null, "max": null, "min": null, "period": "monthly", "term": null}, "salary_visible": false, "title_keywords": ["indoor sales executive", "sales executive"], "responsibilities": ["ad-hoc", "management", "business opportunities", "develop", "client base"], "requirements": {"degrees": ["certificate", "diploma", "higher diploma holder"], "majors": [], "languages": ["cantonese", "english", "mandarin"], "language_level": ["advantage", "good command"], "hard_skills": ["presentation skill"], "soft_skills": ["presentation skill", "communication skill", "driven", "interpersonal skill", "result-oriented", "work under pressure"], "languages_combined": [{"language": "cantonese", "language_level": ["good command"]}, {"language": "english", "language_level": ["advantage", "good command"]}, {"language": "mandarin", "language_level": ["advantage", "good command"]}]}, "experience_required": {"duration": ["2-4 years"], "field": ["logistics industry", "supply chain"]}}, {"job_id": "100003009038984", "location_code": "hk", "company": "Scan Global Logistics Limited", "job_title": "Senior Air Freight Operation", "description": "Job Descriptions:\n\nHandle full set Air export operation and document\nCo-ordinate with airlines, co-loaders, sub-contractor and warehouse\nHandle inquiries with oversea agents and customers\n\n\u00a0Requirement:\n\n\u00a0F5 or above/HKDSE with at least 3 years working experience in Global Freight Forwarding.\n\u00a0Familiar in PC knowledge, MS office\n\u00a0Good Communication and interpersonal skills\n\u00a0General command of written and spoken English, Cantonese and Putonghua\n\u00a0Well-organized, able to work independently and under pressure\n\u00a0Flexible, adaptable to changes and willing to learn\n\u00a0Immediately available is preferred", "employment_types": ["Full Time"], "selling_points": ["Double pay, 5 days work per week", "Medical Insurance, Dental insurance", "Overtime allowance"], "locations": ["Tin Hau"], "categories": ["Transportation & Logistics", "Freight Forwarding"], "post_time": "2022-01-11T08:19:39Z", "salary": {"currency": null, "max": null, "min": null, "period": "monthly", "term": null}, "salary_visible": false, "title_keywords": ["air freight operation"], "responsibilities": ["co-ordinate with"], "requirements": {"degrees": ["hkdse"], "majors": [], "languages": ["cantonese", "putonghua", "english"], "language_level": [], "hard_skills": ["pc knowledge", "ms office"], "soft_skills": ["flexible", "work independently", "under pressure", "adaptable", "well-organized", "willing to learn", "communication and interpersonal skills"], "languages_combined": [{"language": "cantonese", "language_level": []}, {"language": "putonghua", "language_level": []}, {"language": "english", "language_level": []}]}, "experience_required": {"duration": ["at least 3 years"], "field": []}}, {"job_id": "100003009053973", "location_code": "hk", "company": "Wing Hang Medical Supplies Limited", "job_title": "\u5009\u52d9\u517c\u8ddf\u8eca\u9001\u8ca8\u54e1", "description": "\n\u8077\u8cac :\u8ca0\u8cac\u9001\u8ca8\u53ca\u5009\u5eab\u65e5\u5e38\u5de5\u4f5c(\u90f5\u5bc4:\u7c89\u5dba\u5b89\u6a02\u6751\u6a02\u696d\u8def11\u865f\u6c38\u6052\u4f01\u696d\u5927\u5ec8)\n\n\u8cc7\u6b77 :\u4e2d\u4e09\u7a0b\u5ea6; 1\u5e74\u7d93\u9a57; \u826f\u597d\u7cb5\u8a9e; \u4e00\u822c\u666e\u901a\u8a71; \u4e00\u822c\u82f1\u8a9e; \u61c2\u8b80\u5beb\u4e2d\u6587; \u7565\u61c2\u8b80\u5beb\u82f1\u6587\n\n\u5f85\u9047 :\u6bcf\u6708$12,500, \u6709\u96d9\u7ce7, \u9280\u884c\u5047\u671f \u53ca\u6bcf\u6708\u52e4\u5de5\u734e\u91d1$300, \u661f\u671f\u4e00\u81f3\u4e94: \u4e0a\u53488\u6642\u81f3\u4e0b\u53485\u6642\u534a\u53ca\u661f\u671f\u516d: \u4e0a\u53488\u6642\u81f3\u4e0b\u53481\u6642, \u6bcf\u9031\u5de5\u4f5c5\u5929\u81f35\u5929\u534a, \u661f\u671f\u516d\u9577\u77ed\u9031\n\n\u7533\u8acb\u9808\u77e5 :\u50b3\u771f(26026263)/\u96fb\u90f5(Apply Now)/\u90f5\u5bc4\u5c65\u6b77\u8868\u7d66\u6c38\u6052\u6d0b\u884c\u91ab\u7642\u7528\u54c1\u6709\u9650\u516c\u53f8\u3002\u5982\u8981\u7d22\u53d6\u6536\u96c6\u500b\u4eba\u8cc7\u6599\u8072\u660e, \u8acb\u8207\u9673/\u6c88\u5c0f\u59d0(Fax/Email/Post)\u806f\u7d61\n\n", "employment_types": ["Full Time"], "selling_points": [], "locations": ["Fanling"], "categories": ["Transportation & Logistics", "Freight Forwarding", "Inventory / Warehousing", "Supply Chain"], "post_time": "2022-01-17T07:52:56Z", "salary": {"currency": null, "max": null, "min": null, "period": "monthly", "term": null}, "salary_visible": false, "title_keywords": [], "responsibilities": [], "requirements": {"degrees": [], "majors": [], "languages": [], "language_level": [], "hard_skills": [], "soft_skills": [], "languages_combined": []}, "experience_required": {"duration": [], "field": []}}, {"job_id": "100003009050121", "location_code": "hk", "company": "NTL - Logistics (HK) Ltd", "job_title": "SALES EXECUTIVE (5 working days)", "description": "Job Duties:\nApproach potential clients and develop new customer base\nMaintain good support with customers and keep abreast of market & industry development\nCompile sales appointment and quotation to all clients\nHandle ad-hoc projects\nFulfill the sales tasks designated by manager and director\nJob Requirements:\nMatriculated or above\nAt least 2 years of working experience in freight forwarder/ shipping line/ logistics company is preferred\nGood communication, phone and interpersonal skill\nGood command of English & Mandarin\nHaving knowledge of Japanese would be an advantage but not necessary\nSelf-motivated, pro-active, aggressive and strong result-oriented\nAble to work under pressure and independently\nImmediate available is preferred\nAttractive compensation package:\n5 working days\u00a0\nDouble Pay\nMedical\nSalary is negotiable\nWe are located in Lai Chi Kok near MTR station. We offer attractive remuneration package and fringe benefits to the right candidate. For interested parties, please send full resume with employment history and expected salary to email by clicking \"Apply Now\" for a job application.", "employment_types": ["Full Time", "Permanent"], "selling_points": ["5 working days, Double Pay", "Bonus, Medical and OT payment", "Good opportunity for career development"], "locations": ["Lai Chi Kok"], "categories": ["Transportation & Logistics", "Freight Forwarding", "Shipping", "Sales, CS & Business Devpt", "Sales Administration"], "post_time": "2022-01-14T09:48:41Z", "salary": {"currency": null, "max": null, "min": null, "period": "monthly", "term": null}, "salary_visible": false, "title_keywords": ["sales executive"], "responsibilities": ["quotation", "ad-hoc projects", "maintain", "develop"], "requirements": {"degrees": [], "majors": [], "languages": ["japanese", "english", "mandarin"], "language_level": ["advantage", "good command"], "hard_skills": [], "soft_skills": ["self-motivated", "independently", "interpersonal skill", "communication", "pro-active", "result-oriented", "work under pressure"], "languages_combined": [{"language": "japanese", "language_level": ["advantage"]}, {"language": "english", "language_level": ["good command"]}, {"language": "mandarin", "language_level": ["good command"]}]}, "experience_required": {"duration": ["at least 2 years"], "field": ["logistics"]}}, {"job_id": "100003009049808", "location_code": "hk", "company": "FedEx Express", "job_title": "People Operations Advisor", "description": "Job Description:\n\nWork Location: Cyberport\n\nIn this regional role as part of the HR function, you will play a critical role in Workforce transition, Change Management Planning & Implementation and Operational workforce planning to support current and future business needs. This is a strategic position where you will partner with business leaders across functions and other HR team members and being the Regional lead to tailor regional projects and programs for effective local implementation.\n\n\u00a0Key responsibilities:\n\nPeople Advisory;\nChange Management Planning & Implementation;\nOperational workforce planning;\nHigh-volume recruitment and hiring / RPO;\nLocal Response Team (emergency responder);\nWorkforce transition;\nSub-regional or Country lead for HR project implementation\n\nTo be successful in this position, you will need:\n\nDeep knowledge of organizational best practices for strategic workforce and projects\nAt least 5 years\u2019 related experience in strategic workforce planning, preferably in multinational organizations in a regional capacity\nAbility to build strong relationships with stakeholders and work in a network team with other HR and non-HR colleagues\nStrong skills in planning and organization, project management and prioritization\nTo have curiosity and be adaptable to navigate new ways of working and innovative practices\nAbility to think and work with data to draw insights and analysis \u00a0\nStrategic thinking capabilities\nBachelor's\u00a0degree or equivalent, in any discipline\nFluency in written and spoken English\nWhat can you expect as a FedEx team member?\n\nCareer Mobility and Development: When you join FedEx, you\u2019re joining a team with possibilities that literally span the world\u2014from opportunities for advancement and location transfer, to training and leadership programs.\nTotal Compensation and Benefits Package: We want to keep our employees for a long time, so we offer competitive benefits, opportunities for flexible work arrangements, and programs to support well-being.\n\nApplication\n\nIf you think this is a good fit for your knowledge, skills and aspiration, please send your\u00a0resume\u00a0including the information of\u00a0expected salary range\u00a0and\u00a0date of availability.\u00a0We look forward to having you be part of our Purple Promise, which is to make every FedEx experience outstanding.\n\nTo learn more about FedEx and other opportunities, please visit:\u00a0https://careers.fedex.com/fedex\n\nAll information provided by applicants will be treated in strict confidence and used only for recruitment purpose in accordance with the employer's personal data policies. A copy of Personal Information Collection Statement (PICS) will be provided upon request. Please write to the Human Resources Department. Applicants who are not invited to an interview within four weeks may consider their applications unsuccessful. All personal data of unsuccessful applicants will be destroyed after two years.", "employment_types": ["Full Time", "Permanent"], "selling_points": ["Five (5) years of work experience in HR or related", "Bachelor's degree or equivalent, in any discipline", "Sub regional or Country lead for HR project"], "locations": ["Pok Fu Lam"], "categories": ["Admin & HR", "Others", "HR Supporting Staff", "Transportation & Logistics", "Freight Forwarding"], "post_time": "2022-01-14T09:15:26Z", "salary": {"currency": null, "max": null, "min": null, "period": "monthly", "term": null}, "salary_visible": false, "title_keywords": ["advisor", "operations"], "responsibilities": [], "requirements": {"degrees": [], "majors": [], "languages": [], "language_level": [], "hard_skills": [], "soft_skills": [], "languages_combined": []}, "experience_required": {"duration": [], "field": []}}, {"job_id": "100003009052871", "location_code": "hk", "company": "Fly King Transportation Company Ltd", "job_title": "\u8ca8\u904b\u7ad9\u4e3b\u7ba1 (Supervisor)", "description": "\u8077\u8cac\n\n\u76e3\u7763\u53ca\u5e36\u9818\u52a9\u7406\u7ba1\u7406\u54e1\uff0c\u57f7\u52e4\u8077\u52d9\n\u78ba\u4fdd\u670d\u52d9\u5728\u627f\u8afe\u7bc4\u570d\u5167\u5b8c\u6210\u5de5\u4f5c\n\u78ba\u4fdd\u53ca\u7dad\u6301\u7a7a\u904b\u7ad9\u5167\u904b\u4f5c\u66a2\u9806\n\u5354\u52a9\u5009\u5167\u5916\u65e5\u5e38\u5de5\u4f5c\n\n\u5165\u8077\u8981\u6c42\n\n\u5b8c\u6210\u4e2d\u5b78\u6703\u8003/\u4e2d\u5b78\u6587\u6191\u8a66(DSE)\u6216\u540c\u7b49\u5b78\u6b77\n\u80fd\u95b1\u8b80\u53ca\u66f8\u5beb\u4e2d\u3001\u82f1\u6587\n\u6210\u719f\u3001\u81ea\u4fe1\u3001\u6709\u826f\u597d\u6e9d\u901a\u6280\u5de7\u53ca\u80fd\u627f\u53d7\u5de5\u4f5c\u58d3\u529b\n\u51772-3\u5e74\u5009\u52d9\u5de5\u4f5c\u7d93\u9a57\n\n\u85aa\u916c\n\n\u6708\u5165\u53ef\u9054\u6e2f\u5e63$20,000 (\u5305\u62ec\u5e95\u85aa\u9023\u6d25\u8cbc\u798f\u5229)\n\n\u798f\u5229\u5f85\u9047\n\n\u5e74\u5047\u3001\u52de\u5de5\u5047\u3001\u5e74\u7d42\u914c\u60c5\u82b1\u7d05\u3001\u6bcf\u6708\u984d\u5916\u5047\u671f\u3001\u6bcf\u6708\u51fa\u52e4\u734e\u91d1\u3001\u6bcf\u6708\u91ab\u7642\u6d25\u8cbc\u3001\u8d85\u6642\u52a0\u73ed\u6d25\u8cbc\u3001\u901a\u5bb5\u73ed\u6d25\u8cbc\u3001\u5728\u8077\u57f9\u8a13\u3001\u826f\u597d\u6649\u5347\u6a5f\u6703\n\n\u5de5\u4f5c\u6642\u9593\n\n\u9700\u4e8c\u5341\u56db\u5c0f\u6642\u8f2a\u73ed\u5de5\u4f5c\uff0c\u8f2a\u4f11\n\u6bcf\u9031\u5de5\u4f5c\u516d\u5929\uff0c\u6bcf\u5929\u5de5\u4f5c\u4e5d\u5c0f\u6642\n\n\u5de5\u4f5c\u5730\u9ede\n\n\u8d64\u9c72\u89d2\u570b\u6cf0\u822a\u7a7a\u8ca8\u904b\u7ad9\n\n\u7533\u8acb\u8005\u8acb\u6309\"Apply Now\"\u63d0\u4f9b\u500b\u4eba\u5c65\u6b77\u9023\u540c\u85aa\u91d1\u8981\u6c42\u53ca\u53ef\u5230\u8077\u65e5\u671f\u3002\n\n\u67e5\u8a62\u8077\u4f4d\u8a73\u60c5\u53ef\u65bc\u8fa6\u516c\u6642\u9593\u5167 (\u661f\u671f\u4e00\u81f3\u4e94\uff1a0900-1800\uff0c\u661f\u671f\u516d\uff1a0900-1600) \u81f4\u96fb 23589123\u8207\u77f3\u5c0f\u59d0\u806f\u7d61\u3002\n\n\u7533\u8acb\u4eba\u6240\u63d0\u4f9b\u7684\u500b\u4eba\u8cc7\u6599\u526f\u672c\u5c07\u56b4\u683c\u6309\u7167\u50f1\u4e3b\u7684\u500b\u4eba\u8cc7\u6599\u653f\u7b56\u4f7f\u7528\u3002", "employment_types": ["Full Time", "Permanent"], "selling_points": [], "locations": ["Airport Area"], "categories": ["Transportation & Logistics", "Freight Forwarding", "Inventory / Warehousing", "Supply Chain"], "post_time": "2022-01-17T04:24:36Z", "salary": {"currency": null, "max": null, "min": null, "period": "monthly", "term": null}, "salary_visible": false, "title_keywords": ["supervisor"], "responsibilities": [], "requirements": {"degrees": [], "majors": [], "languages": [], "language_level": [], "hard_skills": [], "soft_skills": [], "languages_combined": []}, "experience_required": {"duration": [], "field": []}}, {"job_id": "100003009045836", "location_code": "hk", "company": "Eternity Consultants (HK) Ltd", "job_title": "Logistics Operation Assistant", "description": "Job Duties:\n\n\nFollow up cargoes;\nPrepare purchases & sales contracts;\nCo-ordinate with suppliers, buyers & head office to arrange loading schedules;\nHandle full set shipping documents & issue invoices, etc.\nFulfill other duties related to operations;\n\n\u00a0\nRequirement:\n\n\nUniversity graduate in Shipping Logistics and Global Supply Chain are highly preferred;\n\nProficiency in Mandarin, English and Chinese;\nSelf-motivated, Reliable, Independent, Team work, Detail-minded and able to work under pressure;\n1 to 2 years working experience in operations and logistics;\n\nFresh graduate will be also considered;\nImmediately Available.\n\n*Interested parties, please send full resume with current & expected salary & date available in MS WORD FORMAT ONLY to email: \u00a0jobs@HKETERNITY. com \u00a0\u00a0\u00a0or fax to 3527 0634\n\nHotline: (852) 3542 5082\n\nFor more jobs, please visit our website: www.hketernity.com\n\nWe are welcome applicants resend resumes to us even you have applied jobs in our company before.\n\n(Personal data submitted are for recruitment purpose only.)\u00a0", "employment_types": ["Full Time", "Permanent"], "selling_points": ["Follow up cargoes", "Handle purchase & sale contract, ship doc, invoice", "5 days work, bank holiday, medical, bonus, 13 mth"], "locations": ["Not Specified"], "categories": ["Transportation & Logistics", "Freight Forwarding", "Fulfillment", "Supply Chain"], "post_time": "2022-01-13T08:52:33Z", "salary": {"currency": null, "max": null, "min": null, "period": "monthly", "term": null}, "salary_visible": false, "title_keywords": ["operation assistant", "logistics"], "responsibilities": ["shipping documents", "invoices", "other duties", "co-ordinate with", "contracts", "schedules", "operations"], "requirements": {"degrees": ["university graduate", "fresh graduate"], "majors": [], "languages": ["english", "chinese", "mandarin"], "language_level": ["proficiency"], "hard_skills": [], "soft_skills": ["detail-minded", "self-motivated", "independent", "reliable", "work under pressure"], "languages_combined": [{"language": "english", "language_level": ["proficiency"]}, {"language": "chinese", "language_level": ["proficiency"]}, {"language": "mandarin", "language_level": ["proficiency"]}]}, "experience_required": {"duration": ["1 to 2 years"], "field": ["logistics"]}}]