[{"job_id": "100003009056364", "location_code": "hk", "company": "IKEA", "job_title": "Fulfilment Development & Multichannel Network Manager, North Asia", "description": "WHY YOU WILL LOVE US\n\nWe\u2019re a diverse group of down-to-earth, straightforward people with a passion for home furnishing. We come from all over the world, but we share an inspiring vision: \u201cto create a better everyday life for the many people\u201d. How we realize this vision is based on our shared humanistic values. These values guide our work and build our inclusive, open and honest culture. It\u2019s all based on a spirit of togetherness and enthusiasm. We work hard, but we have fun doing it. We\u2019re always looking for people who share our positive attitude and values.\n\nWHY WE WILL LOVE YOU\n\nYou have a University degree (Economics, Logistics, Supply Chain Management) or proven performance in logistics/commercial/supply chain management 4-6 years working experience in a management position (preferable in distribution, retail, logistics or similar)\nYou have proven successful leadership in a big organisation, delivering both business result and people development\nYou have the interest and experience in retail/ home furnishing/ supply chain/ customer service\nYou have experience of working as a management team member with proven ability to make a difference by positively influencing the business directly as well as through good collaboration\nYou have experience in securing the implementation of mid-term and long-term strategies and plans and set/follow up goals\nYou have proven ability to have a high level of influence in a matrix organisation\nYou have successfully led projects or processes on country/market/national level\n\nWHAT YOU WILL BE DOING DAY TO DAY\n\nContribute to the development of tools, processes and ways of working in co-creation with the groups function and take accountability for the market implementation of globally developed of tools, processes and ways of working to enable the design, establishment and continuous development of an efficient, effective and end to end multichannel distribution network on the market\nAccountable for defining the Fulfilment Development Roadmap on the market in tune with the evolving market benchmarks to enable IKEA results and succeed in a multichannel environment\nAccountable for organising communication and reporting of progress towards all relevant stakeholders through all stages of the multichannel network and development project(s) and taking needed actions to secure the readiness\nAccountable for preparing the investment request connected to Customer Fulfilment investments and the investment budget on the market level including securing all required support to market counterparts\nAccountable for providing business cases and enabling the implementation of development and innovation solutions\nAccountable for the testing of new technical/automated solutions in the fulfilment units and service fulfilment\nAccountable for keeping the total picture of fulfilment development and multichannel network together and synchronised on the market including capturing ideas from within the company\nAccountable for securing development and innovation of fulfilment units and service fulfilment through identifying, evaluating and scaling best practices within IKEA and through setting the right priorities based on input from market and group level, industry intelligence and benchmarking\nResponsible for the cooperation with key partners on within and outside of retail while contributing with both knowledge and resources to optimal operational and multichannel development, sourcing activities as well as to all matrices, global and market initiatives and competence networks\nAccountable to lead, coach and develop the Market Development and Multichannel Network\u00a0organisation\n\nTOGETHER AS A TEAM\n\nCustomer Fulfilment (CFF) is a fundamental part in making IKEA multichannel retailing in reality. CFF acts as a fully integrated, process-oriented organization with an end-to-end approach to develop our business and deliver results across functions together with our partners. We are focusing on providing seamless shopping experience with great quality in all touchpoints for the many.\n\nSTAFF BENEFITS\n\nAnnual Fixed Bonus, 5-Day Work Week, 17 days Public Holiday, Paid Leave (Paid Annual Leave, 14 weeks Maternity Leave, 5 days Paternity Leave, 1 week Marriage Leave), Employee Medical Coverage, Non-Contributory Retirement Plan, Staff Purchase Discount, Birthday Coupon, Referral Bonus, Excellent Career Path\n\nPersonal data collected will be kept and handled confidentially by authorized personnel for recruitment purposes only. It might also be disclosed to our subsidiaries, associates and agencies authorized to process the information for appointment. The Company will retain the applications of candidates not selected for a maximum period of 24 months after the selection process is finalized. Our Personal Information Collection Statement (PICS) is available at our career site and can be provided upon request by contacting our Human Resources Department. Applicants not heard from us within six weeks may consider their applications filed for future reference.\n\nIssued by The Dairy Farm Company, Limited\n\n\n", "employment_types": ["Full Time", "Permanent"], "selling_points": ["Report to Head of Customer Fulfilment, North Asia", "Defining the Fulfilment Development Roadmap", "Multichannel network and development projects"], "locations": ["Shatin Area"], "categories": ["Transportation & Logistics", "Others", "Fulfillment", "Supply Chain"], "post_time": "2022-01-18T04:05:49Z", "salary": {"currency": null, "max": null, "min": null, "period": "monthly", "term": null}, "salary_visible": false, "title_keywords": ["manager"], "responsibilities": ["management team", "management", "reporting", "ideas", "budget", "quality", "implementation", "design", "testing", "communication", "develop", "customer service", "logistics", "plans"], "requirements": {"degrees": ["university degree"], "majors": ["economics"], "languages": [], "language_level": [], "hard_skills": ["make", "fun"], "soft_skills": ["efficient", "accountability", "passion for", "responsible", "accountable", "positive attitude", "diverse", "communication", "customer service", "inspiring", "honest", "organisation", "team member", "leadership"], "languages_combined": []}, "experience_required": {"duration": ["4-6 years"], "field": ["management", "supply chain", "management position", "commercial", "customer service", "logistics", "business", "retail", "team"]}}, {"job_id": "100003009055341", "location_code": "hk", "company": "Possehl Electronics Hong Kong Ltd", "job_title": "Order Fulfillment Manager", "description": "Stryker is one of the world\u2019s leading medical technology companies and, together with our customers, is driven to make healthcare better. We offer innovative products and services in Orthopedics, Medical and Surgical, and Neurotechnology and Spine that help improve patient and hospital outcomes. We are proud to be named one of the World\u2019s Best Workplaces and a Best Workplace for Diversity by Fortune Magazine. Learn more about our award-winning organization by visiting careers.stryker.com\u00a0\n\nAbout the Role :\u00a0\n\nThe Order Management team acts as a primary interface with both external (i.e., hospitals or distributors) and internal customers (i.e. commercial, customer care, finance and planning teams), and triage/ respond to the sales order related enquiries. This team plays a crucial role towards the customer experience journey, and to the Order-to-Cash (\u201cOTC\u201d) process flow.\nIn this role, you will be the main person in Hong Kong for the Medical business - handling enquiries, processing orders and service billing along the OTC flow with external customers. You will also support internal requests such as master data maintenance, demo or stock transfer as part of the daily routine.\n\nWhat You Will Be Doing :\n\nPrimary point of contact on orders from order processing to order status follow-up within Operations and Planning teams.\nCollaborate with commercial and customer care teams to provide timely responses to customers\u2019 enquiries.\nTriage and/or resolve any problems or customer complaints based on process and data analytics.\nExecute the order management process and integrate with the 3PL management process to complete the entire Order-to-Cash flow.\nWork closely with other functional teams to identify opportunities to standardize and optimize the flow.\nWork with Sales, 3PL and customers to arrange timely deliveries for key orders.\nSupport in relevant master data setup in internal systems.\nCoordinating the dispatch, delivery, and billing of capital products.\nReducing inbound freight costs while keeping high service levels.\nGenerate relevant KPI reports and support the analysis.\u00a0\n\nWho We Are Looking For :\u00a0\n\nBachelor\u2019s degree in Business, Operations, Supply Chain or related fields.\nAbout 3 to 5 years' experience in order processing or sales support in MNC settings. Applicants with less experience will also be considered.\u00a0\nExcellent communications skills in verbal and written English.\nEnjoys the challenge of working in a growing business and playing a key role in building up processes.\nGreat interpersonal skills and able to tactfully influence and persuade stakeholders towards paths of action.\nEffective relationship building skills and ability to collaborate well with internal stakeholders across various functions.\nStrong sense of ownership and problem solving skills.\nProficiency in Microsoft Office tools including, Excel, PowerPoint.\nPrevious experience using an ERP system. (JDE and BI experience or equivalent).", "employment_types": ["Full Time", "Permanent"], "selling_points": ["5 days per week", "Work in Hong Kong", "Medical Insurance & Year End Bonus"], "locations": ["Tsuen Wan Area"], "categories": ["Transportation & Logistics", "Fulfillment", "Supply Chain", "Manufacturing", "Production Planning / Control"], "post_time": "2022-01-18T02:15:02Z", "salary": {"currency": null, "max": null, "min": null, "period": "monthly", "term": null}, "salary_visible": false, "title_keywords": ["manager"], "responsibilities": ["collaborate with", "collaborate", "order management", "management", "maintenance", "data", "customer complaints", "operations", "analysis", "teams", "cash flow", "costs", "reports", "contact", "order processing", "internal systems", "setup", "planning"], "requirements": {"degrees": ["degree", "bachelor", "master"], "majors": ["business"], "languages": ["english"], "language_level": ["excellent"], "hard_skills": ["excel", "bi", "sales support", "maintenance", "microsoft office", "data analytics", "analysis", "powerpoint", "make", "erp system", "order processing", "3pl management", "problem solving skills", "processing"], "soft_skills": ["timely", "interpersonal skills", "patient", "problem solving skills", "innovative", "driven"], "languages_combined": [{"language": "english", "language_level": ["excellent"]}]}, "experience_required": {"duration": ["3 to 5 years"], "field": ["erp system", "sales support", "order processing", "team"]}}, {"job_id": "100003009055473", "location_code": "hk", "company": "ConnectedGroup Limited", "job_title": "Assistant Logistics Manager - FMCG company", "description": "Our client is a well-established multinational company with a large presence in Hong Kong, they are now looking for an Assistant Logistics Manager to support the logistics operation.\n\nResponsibilities\n\nSupervise both inbound and outbound logistics operation.\nHandle shipment scheduling and planning\nManage shipment data and ensure data integrity\nEvaluate the SOP and provide suggestion / improvement plan.\nResponsible for 3PL management and ensure their performance meet KPI\nReview logistic cost and explore optimization plan. Negotiate with external third party to improve the cost structure\n\nRequirements:\n\nDegree holder in Business Administration, Supply Chain, or related disciplines\nMinimum of 4 years of experience in Logistic field especially in FMCG industry\nFamiliar with SAP system\nGood command of written and spoken English and Chinese", "employment_types": ["Full Time", "Permanent"], "selling_points": ["Well-established multinational company", "Attractive remuneration package", "Excellent career progression"], "locations": ["Not Specified"], "categories": ["Transportation & Logistics", "Others", "Fulfillment", "Supply Chain"], "post_time": "2022-01-18T02:38:01Z", "salary": {"currency": null, "max": null, "min": null, "period": "monthly", "term": null}, "salary_visible": false, "title_keywords": ["logistics manager", "assistant"], "responsibilities": ["management", "cost", "data", "review", "shipment scheduling and planning", "manage shipment data", "evaluate", "plan", "third party", "inbound and outbound logistics"], "requirements": {"degrees": ["degree holder"], "majors": ["related disciplines", "business administration"], "languages": ["english", "chinese"], "language_level": ["good command"], "hard_skills": ["fmcg industry", "sap"], "soft_skills": [], "languages_combined": [{"language": "english", "language_level": ["good command"]}, {"language": "chinese", "language_level": ["good command"]}]}, "experience_required": {"duration": ["minimum of 4 years"], "field": ["fmcg"]}}, {"job_id": "100003009055691", "location_code": "hk", "company": "Manpower Services (Hong Kong) Limited", "job_title": "Logistics Admin _Natural Resources_ Max 35K", "description": "Responsibilities\n\nCoordinate with the logistics team and plan shipments based on product availability and customer requests.\nTrack shipments to ensure timely deliveries.\nPrepare shipping documents on time (like invoices, purchase orders, and bills of lading).\nSchedule shifts with third parties to ensure continuous operation during public holidays.\nMaintain updated and accurate records of shipments, suppliers, and customers in the CTRM.\nProvide information to customers about the status of their orders.\nRaise change requests from the client and shipment issues on time.\nMake document presentations to the bank against the letter of credit or arrange prepayment from the clients.\nConduct any quality or quantity claim.\nInteract with both internal and external clients related to the deliveries, and cover the work while any colleague is on leave or absent.\nUndertake analysis to identify potential logistics issues and collaborate with different departments to take preventive and corrective actions.\nAd hoc projects as assigned.\n\nRequirements\n\nWork experience as a Logistics Administrator, Supply Change, or similar role.\nBasic accounting knowledge.\nExcellent organizational, time-management skills, and able to multi-task effectively.\nGood communication skills, fluent in English and Mandarin, Cantonese is an advantage.\nBSc in Supply chain management, Logistics, or relevant field.\nStrong knowledge of the letter of credit for import/export.\nStrong analytical and quantitative skills.\nExcellent in MS Word, Excel, and PowerPoint. Knowledge of ERP and CTRM is an advantage.\nInterested parties, please send your resume with availability and current and expected salary to jenny.chai@manpowergrc.hk.\u00a0", "employment_types": ["Permanent"], "selling_points": ["Exp in handling L/C & Supply Chain procedure", "Fluent English & Mandarin", "Immediatly Available"], "locations": ["Central"], "categories": ["Transportation & Logistics", "Fulfillment", "Shipping", "Supply Chain"], "post_time": "2022-01-18T02:51:17Z", "salary": {"currency": null, "max": null, "min": null, "period": "monthly", "term": null}, "salary_visible": false, "title_keywords": ["admin", "logistics"], "responsibilities": ["shipping documents", "collaborate with", "invoices", "analysis", "coordinate with", "quality", "presentations", "purchase", "maintain", "logistics", "schedule", "plan", "customer requests", "ad hoc projects"], "requirements": {"degrees": ["bsc"], "majors": [], "languages": ["cantonese", "english", "mandarin"], "language_level": ["advantage", "fluent", "good"], "hard_skills": ["excel", "basic", "erp", "powerpoint", "ms word"], "soft_skills": ["communication skills", "organizational", "multi-task"], "languages_combined": [{"language": "cantonese", "language_level": ["advantage", "good"]}, {"language": "english", "language_level": ["fluent", "good"]}, {"language": "mandarin", "language_level": ["fluent", "good"]}]}, "experience_required": {"duration": [], "field": ["logistics"]}}, {"job_id": "100003009056866", "location_code": "hk", "company": "Delmar International (Hong Kong) Limited", "job_title": "Ocean Freight Operations (5 Day Work)", "description": "Job Responsibilities:-\n\nResponse to customer\nHandling inbound/outbound Ocean Freight shipment and planning\nManage Ocean Freight shipment data and ensure data integrity\nCommunicate with other branches/ origin offices\nRequirements:-\n\nFluent in English and Chinese\nMinimum 2 years relevant working experience\nFluent in English and Mandarin, both written and spoken\nImmediate available is\u00a0highly preferred\n\n\nPlease send full resume with present & expected salary for consideration.", "employment_types": ["Full Time", "Permanent"], "selling_points": ["Immediate available is highly preferred", "Handling inbound/outbound shipment and planning", "5 Day Work Week"], "locations": ["Kwai Fong"], "categories": ["Transportation & Logistics", "Others", "Freight Forwarding", "Fulfillment"], "post_time": "2022-01-18T06:36:28Z", "salary": {"currency": null, "max": null, "min": null, "period": "monthly", "term": null}, "salary_visible": false, "title_keywords": ["operations"], "responsibilities": ["communicate with", "data", "planning"], "requirements": {"degrees": [], "majors": [], "languages": ["english", "chinese", "mandarin"], "language_level": ["fluent"], "hard_skills": [], "soft_skills": [], "languages_combined": [{"language": "english", "language_level": ["fluent", "fluent"]}, {"language": "chinese", "language_level": ["fluent", "fluent"]}, {"language": "mandarin", "language_level": ["fluent", "fluent"]}]}, "experience_required": {"duration": ["minimum 2 years"], "field": ["relevant working experience"]}}, {"job_id": "100003009054624", "location_code": "hk", "company": "IKEA", "job_title": "Shipping & Receiving Clerk \u8239\u52d9\u6587\u54e1", "description": "WHY YOU WILL LOVE US\n\nWe\u2019re a diverse group of down-to-earth, straightforward people with a passion for home furnishing. We come from all over the world, but we share an inspiring vision: \u201cto create a better everyday life for the many people\u201d. How we realize this vision is based on our shared humanistic values. These values guide our work and build our inclusive, open and honest culture. It\u2019s all based on a spirit of togetherness and enthusiasm. We work hard, but we have fun doing it. We\u2019re always looking for people who share our positive attitude and values.\n\nWHY WE WILL LOVE YOU\n\nYou have experience in being a valuable contributor to shipping activities\nYou can strike a balance between keeping a good overview and paying good attention to detail proven service mindset\nYou are self-reliant and motivated with proven ability to work as part a team as well as independently.\nYou can ensure integrity of the systems, guidelines and documents\nYou have good analytical and numerical skill\nYou have a Higher Diploma or above qualification in Logistics, Supply Chain Management or other relevant education\nYou have 1 years logistics, shipping or supply chain related working experience, fresh graduates are also welcomed\n\nWHAT YOU WILL BE DOING DAY TO DAY\n\n\nSecure an efficient and precise range management process to maintain a good stock structure\nCoordinate with relevant parties for shipment handling such as Haulage Contractor, Shipping Companies etc.\nProvides related documents to Goods flow team for devanning processes\nPrepare delivery orders, invoice and any other documents for update inventory\nEnsure that all transactions are correctly recorded in database in timely basis\nHandling and storage related shipping documents, reports and import / export declaration\nPrepare the claim reports for surplus / shortage in shipment if any\nAnswer the inquires from different parties about the shipment status\n\nSTAFF BENEFITS\n\nAnnual Fixed Bonus, 17 days Public Holiday, Paid Leave (Paid Annual Leave, 14 weeks Maternity Leave, 5 days Paternity Leave, 1 week Marriage Leave), Free Shuttle Bus, Employee Medical Coverage, Non-Contributory Retirement Plan, Staff Purchase Discount, Birthday Coupon, Referral Bonus, Excellent Career Path\n\nPersonal data collected will be kept and handled confidentially by authorized personnel for recruitment purposes only. It might also be disclosed to our subsidiaries, associates and agencies authorized to process the information for appointment. The Company will retain the applications of candidates not selected for a maximum period of 24 months after the selection process is finalized. Our Personal Information Collection Statement (PICS) is available at our career site and can be provided upon request by contacting our Human Resources Department. Applicants not heard from us within six weeks may consider their applications filed for future reference.\n\nIssued by The Dairy Farm Company, Limited\n\n", "employment_types": ["Full Time", "Permanent"], "selling_points": ["Passionate in Home Furnishing", "Working Location: Kwai Chung", "Responsible for Shipping Activities"], "locations": ["Kwai Tsing Area"], "categories": ["Transportation & Logistics", "Documentary Credit / Bills Processing", "Fulfillment", "Shipping"], "post_time": "2022-01-17T10:17:08Z", "salary": {"currency": null, "max": null, "min": null, "period": "monthly", "term": null}, "salary_visible": false, "title_keywords": ["shipping", "clerk"], "responsibilities": ["shipping documents", "management", "shipping", "guidelines", "related documents", "invoice", "systems", "coordinate with", "inventory", "transactions", "maintain", "logistics", "reports", "database", "shipment handling"], "requirements": {"degrees": ["higher diploma or above"], "majors": [], "languages": [], "language_level": [], "hard_skills": ["fun"], "soft_skills": ["efficient", "independently", "passion for", "timely", "integrity", "positive attitude", "diverse", "motivated", "inspiring", "honest", "attention to detail", "precise"], "languages_combined": []}, "experience_required": {"duration": ["1 years"], "field": ["related", "supply chain", "logistics"]}}, {"job_id": "100003009051981", "location_code": "hk", "company": "HCT GROUP", "job_title": "Order Fulfillment Coordinator", "description": "Responsibilities:\n\n\u00a0\u00a0\u00a0\u00a0\u00a0 Manage the team for internally and externally regarding orders and transportation needs.\n\u00a0\u00a0\u00a0\u00a0\u00a0 Daily monitoring of client\u2019s EDI or web-based systems for PO\u2019s, updates and shipment details.\n\u00a0\u00a0\u00a0\u00a0\u00a0 Achieve timely dispatches with domestics and overseas vendors.\n\u00a0\u00a0\u00a0\u00a0\u00a0 Utilize various functions in SAP, including but not limited to item setup, creating orders, goods receipt, delivery, etc.\n\u00a0\u00a0\u00a0\u00a0\u00a0 Initiate timely invoicing and work closely with accounting department to ensure billing accuracy.\n\u00a0\u00a0\u00a0\u00a0\u00a0 Various SAP projects or other duties as they arise.\n\nRequirements:\n\n\u00a0\u00a0\u00a0\u00a0\u00a0 Hong Kong permanent resident\n\u00a0\u00a0\u00a0\u00a0\u00a0 1-2 years of experience in the field of purchasing or logistics\n\u00a0\u00a0\u00a0\u00a0\u00a0 Quick learner, detail oriented with proven ability to work efficiently with high accuracy\n\u00a0\u00a0\u00a0\u00a0\u00a0 Exceptional organization and time management skills with the ability to work effectively independently and in a team environment\n\u00a0\u00a0\u00a0\u00a0\u00a0 Strong knowledge of import/export documentation and solid understanding of Inco terms\n\u00a0\u00a0\u00a0\u00a0\u00a0 Proficiency in SAP (or other operating systems) Outlook, Excel and Word is required\n\u00a0\u00a0\u00a0\u00a0\u00a0 Strong verbal/written communication skills (English and Chinese) are essential\n\u00a0\u00a0\u00a0\u00a0\u00a0 Fluent in both spoken and written English, Mandarin and Cantonese.\n\u00a0\u00a0\u00a0\u00a0\u00a0 Ability to gather and analyze data and work with figures communicate effectively both narration and in writing\n\nWe offer 5 days work, attractive salary, medical insurance, harmony and excellent working environment to right candidate. Interested parties please send full resume in\u00a0MS Word\u00a0format, present and expected salary with full confidence attention to Ms. Mak.\n\nYou are welcome to visit our HCT Group website: https://hctgroup.com\n\n* ALL PERSONAL DATA RECEIVED WILL BE TREATED CONFIDENTIALLY AND USED FOR RECRUITMENT PURPOSE ONLY.*", "employment_types": ["Full Time"], "selling_points": [], "locations": ["Sheung Wan"], "categories": ["Transportation & Logistics", "Freight Forwarding", "Fulfillment", "Supply Chain"], "post_time": "2022-01-17T01:44:54Z", "salary": {"currency": null, "max": null, "min": null, "period": "monthly", "term": null}, "salary_visible": false, "title_keywords": ["coordinator"], "responsibilities": ["other duties", "systems", "invoicing", "daily monitoring", "setup"], "requirements": {"degrees": [], "majors": [], "languages": ["cantonese", "english", "chinese", "mandarin"], "language_level": ["fluent"], "hard_skills": ["excel", "sap", "word", "outlook", "documentation"], "soft_skills": ["work effectively", "communication skills", "independently", "time management skills", "detail oriented", "quick learner"], "languages_combined": [{"language": "cantonese", "language_level": ["fluent"]}, {"language": "english", "language_level": ["fluent"]}, {"language": "chinese", "language_level": []}, {"language": "mandarin", "language_level": ["fluent"]}]}, "experience_required": {"duration": ["1-2 years"], "field": ["purchasing", "logistics"]}}, {"job_id": "100003009055198", "location_code": "hk", "company": "Tsit Wing Coffee Co Ltd", "job_title": "Shipping clerk", "description": "Responsibilities\u00a0\n\nResponsible for I/E Document preparation, declaration\nMonitor shipment status and order follow up\nCoordinate with freight forwarders and shipping companies for shipment and transportation arrangement\nAccurate and timely data input of shipment details to order system\nPerform any ad hoc projects as assigned\n\nRequirements\n\nDegree holder in relevant discipline\u00a0\n2 years\u2019 experiences preferably in shipping\nFresh graduates will be considered\nExcellent communication skills with both internal and exteral parties\nGood command of spoken English, Putonghua and Cantonese\nKnowledge of SAP system is preferred\n\nWorking location:\u00a0Kwai Chung\n\n\n\nStaff Benefit\n\nDiscretionary Bonus\nMedical & Life Insurance\nAnnual Leave\nPayable Sick Leave\nEncourage continuing education and on-job training\nOpen office working environment\nOffer promotion opportunities and long-term career path\u00a0\n\nWe offer a competitive remuneration package to the right candidate.\u00a0Interested parties\u00a0please click\u00a0\"Apply Now\"\u00a0to submit your application\u00a0or by email to\u00a0hr1 @twcoffee.com\n\n\u00a0(All personal data provided by applicants will be treated in strict confidence and used for employment-related purpose only.)", "employment_types": ["Full Time", "Permanent"], "selling_points": [], "locations": ["Kwai Fong"], "categories": ["Transportation & Logistics", "Fulfillment", "Shipping", "Merchandising & Purchasing", "Procurement / Purchasing / Sourcing"], "post_time": "2022-01-18T01:44:58Z", "salary": {"currency": null, "max": null, "min": null, "period": "monthly", "term": null}, "salary_visible": false, "title_keywords": ["shipping clerk"], "responsibilities": ["shipping", "monitor", "data input", "coordinate with", "ad hoc projects"], "requirements": {"degrees": ["degree holder"], "majors": [], "languages": ["cantonese", "putonghua", "english"], "language_level": ["good command"], "hard_skills": ["sap"], "soft_skills": ["communication skills"], "languages_combined": [{"language": "cantonese", "language_level": ["good command"]}, {"language": "putonghua", "language_level": ["good command"]}, {"language": "english", "language_level": ["good command"]}]}, "experience_required": {"duration": ["2 years"], "field": []}}, {"job_id": "100003009056631", "location_code": "hk", "company": "The Garden Company Limited", "job_title": "Assistant Logistics Planning Manager / Logistics Planning Manager", "description": "Responsibilities\n\nResponsible for strategic logistics operations planning\nReview on the implementation of operational initiatives in maximizing customer satisfaction, enhancing service quality and productivity\nStreamline the logistics flow\nEnhance the efficiency, cost control and resource optimization\nPerform other ad-hoc projects as assigned\n\nRequirements\n\nDegree holder in Business Management/ Logistics/Supply Chain Management\nWith 5 years related logistics experience in which at least 3 years supervisory level, preferably in local logistics / distribution center management\nComputer literate and accounting knowledge is a plus\nHaving driving license is preferable\nStrong communication, presentation and leadership skills\nMature and able to work independently and under pressure\n\nWorking Location: Sham Tseng\n\nInterested parties please click \"Apply Now\" or send the expected salary and available date, quote the job position and reference number to Human Resources Department, 1-11 Sham Tsz Street, Sham Tseng, New Territories, Hong Kong.\n\nAll the information collected will be used for the purpose of recruitment only.", "employment_types": ["Full Time", "Permanent"], "selling_points": ["Strategic logistics operations planning", "Enhance service quality and productivity", "Immediate available is highly preferred"], "locations": ["Tsuen Wan Area"], "categories": ["Transportation & Logistics", "Others", "Fulfillment", "Supply Chain"], "post_time": "2022-01-18T05:15:52Z", "salary": {"currency": null, "max": null, "min": null, "period": "monthly", "term": null}, "salary_visible": false, "title_keywords": ["assistant logistics planning manager", "logistics planning manager"], "responsibilities": ["operations", "review", "quality", "implementation", "logistics", "cost control", "ad-hoc projects", "planning"], "requirements": {"degrees": ["degree holder"], "majors": ["business"], "languages": [], "language_level": [], "hard_skills": ["business management", "plus"], "soft_skills": ["work independently", "under pressure", "leadership skills", "mature", "communication", "presentation"], "languages_combined": []}, "experience_required": {"duration": ["5 years", "at least 3 years"], "field": ["related", "supervisory level", "management", "logistics"]}}, {"job_id": "100003009056682", "location_code": "hk", "company": "Global Transit Supplychain Ltd", "job_title": "Project Executives / Trainees (Fresh Graduates are welcome)", "description": "Duties & Responsibilities:\n\nReceive training and perform duties in several functional areas, such as Marketing, Business Development, Operations, Customer Service & Support etc., in order to attain functional objectives and knowledge for effective implementation of the required duties\nAssist in managing and implementing various business projects and tasks as assigned by Supervisor/Management related to eCommerce Logistics service industry\nMeet performance goals and objectives set by Management and report regularly on progress made in attaining goals and objectives\nGain valuable work experience and exposure via Supervisor\u2019s and Management\u2019s mentorship and coaching\nAssist in ad hoc activities, tasks and projects as required\n\n\u00a0Requirements:\n\nHigher Diploma Holder or above or early career professionals with less than 2 years of working experience\nGood command in spoken and written Chinese and English\nGood interpersonal, communication and presentations skills\nProactive with positive & achieving mind-set and eager to earn\nWilling to take ownership and challenges with \u2018can-do\u2019 attitude\nProficient in computer application including MS Word, MS Excel, MS PowerPoint and Chinese word processing; knowledge of Adobe Illustrator would be an advantage\nImmediate availability preferred", "employment_types": ["Full Time", "Permanent"], "selling_points": ["Learn & grow from highly experienced Management", "Exposure to various duties for career development", "Good career development in eCom. Logistics market"], "locations": ["Tsuen Wan Area"], "categories": ["Transportation & Logistics", "Fulfillment"], "post_time": "2022-01-18T05:49:35Z", "salary": {"currency": null, "max": null, "min": null, "period": "monthly", "term": null}, "salary_visible": false, "title_keywords": [], "responsibilities": ["management", "ad hoc", "business projects", "operations", "implementation", "customer service", "logistics", "report"], "requirements": {"degrees": ["higher diploma holder"], "majors": [], "languages": ["english", "chinese"], "language_level": ["good command", "proficient"], "hard_skills": ["chinese word processing", "presentations", "adobe illustrator", "ms excel", "ms powerpoint", "ms word"], "soft_skills": ["communication", "can-do", "proactive", "interpersonal", "positive"], "languages_combined": [{"language": "english", "language_level": ["good command"]}, {"language": "chinese", "language_level": ["good command", "proficient"]}]}, "experience_required": {"duration": ["2 years"], "field": []}}, {"job_id": "100003009056687", "location_code": "hk", "company": "Sapphire Search Limited", "job_title": "Senior Demand Planner/ AM \u2013 FMCG", "description": "Headquartered in Europe, our client is\u00a0a reputable consumer brand with business across the globe. An exciting opportunity has arisen for a dynamic and analytical talent to join\u00a0their Supply Chain team in Hong Kong.\n\nReporting to the Function Lead, you will manage demand forecast and inventory control of merchandise for Hong Kong and Taiwan market. You will formulate and implement effective demand planning workflow, and drive S&OP process. Working closely with Sales & Marketing and Logistics teams, you will ensure product availability and inventory turn efficiency. You will identify inventory trend and conduct root cause analysis on deviation.\u00a0You will also support Logistics activities and global supply chain projects.\n\nSuccessful candidate will possess the following competencies and attributes:\n\nUniversity degree in Supply Chain, Statistics or any other related disciplines\nAt least 5 years' demand planning experience within FMCG or F&B sector; exposure to MNC will be preferred\u00a0\nHands-on experience in demand forecast and inventory analysis\nProficient in SAP system and Excel\nProactive, numeric-sensitive and a team player\nExcellent communication and interpersonal skills\nFluent in English and Mandarin is essential\n\nInterested parties, please submit your application via JobsDB, quoting job reference number \u201cA220104\u201d.\n\nInformation collected will be used for recruitment purposes only. Your interest will be treated in strict confidence and only suitable candidates will be notified.\u00a0\n\n", "employment_types": ["Full Time"], "selling_points": ["Renowned consumer brand", "Demand forecasting and S&OP focus", "Opportunity to gain full supply chain experience"], "locations": ["Not Specified"], "categories": ["Transportation & Logistics", "Fulfillment", "Inventory / Warehousing", "Supply Chain"], "post_time": "2022-01-18T05:48:43Z", "salary": {"currency": null, "max": null, "min": null, "period": "monthly", "term": null}, "salary_visible": false, "title_keywords": [], "responsibilities": ["reporting", "demand planning", "inventory", "teams", "analysis", "communication", "inventory control", "logistics", "forecast"], "requirements": {"degrees": ["university degree"], "majors": ["related disciplines", "statistics"], "languages": ["english", "mandarin"], "language_level": ["fluent"], "hard_skills": ["excel", "sap", "analysis", "demand planning", "dynamic"], "soft_skills": ["hands-on", "dynamic", "communication and interpersonal skills", "sensitive", "team player", "proactive"], "languages_combined": [{"language": "english", "language_level": ["fluent"]}, {"language": "mandarin", "language_level": ["fluent"]}]}, "experience_required": {"duration": ["at least 5 years"], "field": ["f&b", "fmcg", "planning"]}}, {"job_id": "100003009046079", "location_code": "hk", "company": "Shopkyo Limited", "job_title": "Operations Specialist (2 vacancies)", "description": "About this role:\nThis role is designed to facilitate the movement of shipments while discovering and driving efficiencies that smoothen and improve operations. You will serve as a liaison for our 3PLs, Customers, Sales Team, Customer Service Team, IT team, and other internal functions to ensure operational efficiency and excellent customer experience.\n\nYou will be responsible for ensuring that our 3PLs are executed according to plan, on time, and within budget.\nYou will have the opportunity to spot opportunities to improve customer experience, streamline processes, and introduce innovative ways of managing a supply chain.\nYou will gain experience in operation management, effective communication, relationship building, creative solution design, and deep industry knowledge with this role.\n\nYour day to day jobs (RESPONSIBILITIES):\n\nImplement operational procedures in the day-to-day workflow, and constantly identify and execute on opportunities to realize optimal efficiency and productivity.\nCoordinate day-to-day operations with internal and external partners such as vendor warehouse, express delivery carriers, domestic delivery carriers, the sales team, the customer representative team, and IT teams.\nDevelop and implement guidelines/ procedures to control and improve the operation efficiency and quality\nTimely shipment troubleshooting and exception escalation\n\nREQUIREMENTS:\n\nDiploma Graduate or above in any disciplines, preferred in Operations Management, Logistics, Supply Chain or related discipline\nAt least 1 year or above experience\nAbility to work independently and collaborate with a team\nPositive, optimistic, and confident person able to continue moving forward when faced with adversity\nProcess-oriented, structured thinking with strong problem-solving capabilities Excellent communication, interpersonal and organizational skills\nOperations Strong analytical and problem-solving skills with a good sense of risk management\nFluent spoken and written in English and Chinese including Mandarin\nLogistics/freight forwarding/e-commerce experience preferred but not required\nHolder of Dangerous Goods Awareness or Dangerous Goods Regulations would be an advantage\nImmediately Available is an advantage\n\nOur offer\n\nWe will give you the best support we possibly could for you to produce your best work. This includes providing you with:\n\nDiverse career advancement opportunity\nAllowance for self-learning (udemy, coursea, skillshare, etc)\nResult Driven Work Environment\n\nAdditional perks\n\n-Medical Insurance\n-Free Drinks, Snacks\n-Gym membership at Science Park\n\nMore info about Spaceship on\n\nLinkedIn:\u00a0https://hk.linkedin.com/company/spaceshiphk\nFacebook:\u00a0https://www.facebook.com/spaceshiphongkong\nWebsite:\u00a0https://spaceship.hk/", "employment_types": ["Full Time", "Permanent"], "selling_points": ["Market leading all-in-one smart logistic solution", "Start-up and energetic environment", "Great learning opportunity"], "locations": ["Tseung Kwan O"], "categories": ["Transportation & Logistics", "Fulfillment", "Shipping", "Supply Chain"], "post_time": "2022-01-13T09:33:26Z", "salary": {"currency": null, "max": null, "min": null, "period": "monthly", "term": null}, "salary_visible": false, "title_keywords": ["specialist", "operations"], "responsibilities": ["control", "guidelines", "teams", "day-to-day operations", "procedures", "develop", "coordinate", "quality", "troubleshooting", "operational procedures", "sales team"], "requirements": {"degrees": ["diploma"], "majors": ["any disciplines"], "languages": ["english", "chinese", "mandarin"], "language_level": ["fluent"], "hard_skills": ["problem-solving skills", "problem-solving", "facebook", "e-commerce"], "soft_skills": ["confident", "organizational skills", "work independently", "problem-solving", "driven", "communication", "diverse", "learning", "problem-solving skills", "structured", "interpersonal", "positive"], "languages_combined": [{"language": "english", "language_level": ["fluent"]}, {"language": "chinese", "language_level": ["fluent"]}, {"language": "mandarin", "language_level": ["fluent"]}]}, "experience_required": {"duration": ["at least 1 year"], "field": ["logistics", "e-commerce"]}}, {"job_id": "100003009050403", "location_code": "hk", "company": "Links International", "job_title": "Logistic Operation & CS Manager", "description": "Logistic Operation & CS Manager - Fashion Retailer\n\nOur client is a large international fashion retailer, looking for a Logistic Operation & CS Manager to join their organization. Oversee and manage the operation of 3PL warehouses and all trade logistics for Hong Kong and Macau Market.\n\nResponsibilities:\n\n\nLead and coach a team of specialists, coordinate with vendors in handling logistic operations such as inventory aging, sales orders pick-pack-ship process and shipment arrangement.\nMonitor all processes for receiving, processing, pick and pack and returns handling.\nWork closely with NBIL to manage local market IAS processes.\nCreate operations strategies and solutions based on global / regional strategic priorities.\nManage and refine warehouse operations, ensuring smooth and efficient operation.\nOversees and reports weekly, monthly, quarterly, and annual metrics.\nPerform regular audit of the local warehouse.\nIdentify cost savings opportunities, identify logistic trends and assesses opportunities to improve operational procedures and execution.\nWorks closely with regional operations team and Hong Kong finance team on other special planning and various new developing projects.\n\nQualifications:\n\n\nA strong educational background in Logistics, Supply Chain Management or related discipline is preferably\n10 years in supply chain and warehouse operation years in a multinational company is preferred. At least 5 years of working experience in operation management.\nKnowledge and experiences in supply chain optimization, warehouse operation, systems, inventory planning, shipping, order management, replenishment, CS\nBeing entrepreneurial; gets things done and constantly looking for ways to improve.\nExcellent command in both English and Chinese\nHigh motivation and self-discipline to work independently", "employment_types": ["Full Time", "Permanent"], "selling_points": ["Retail experience preferred", "HK & Macau Coverage, lead team", "Logistic and CS Management"], "locations": ["Not Specified"], "categories": ["Transportation & Logistics", "Fulfillment", "Inventory / Warehousing", "Supply Chain"], "post_time": "2022-01-14T10:19:05Z", "salary": {"currency": "HKD", "max": 54999, "min": 45000, "period": "monthly", "term": null}, "salary_visible": true, "title_keywords": ["manager"], "responsibilities": ["shipping", "operations", "inventory", "audit", "monitor", "developing", "operational procedures", "logistics", "reports", "finance team", "cost", "management", "shipment arrangement", "coordinate with", "inventory planning", "order management", "systems", "replenishment", "3pl warehouses", "warehouse operations", "planning"], "requirements": {"degrees": [], "majors": [], "languages": ["english", "chinese"], "language_level": ["excellent"], "hard_skills": ["processing"], "soft_skills": ["efficient", "work independently", "smooth"], "languages_combined": [{"language": "english", "language_level": ["excellent"]}, {"language": "chinese", "language_level": ["excellent"]}]}, "experience_required": {"duration": ["at least 5 years"], "field": ["management", "supply chain", "operation management", "operation", "cs", "planning"]}}, {"job_id": "100003009052192", "location_code": "hk", "company": "Educational Publishing House, Limited", "job_title": "Senior Sales Coordinator (Order Processing) \u9ad8\u7d1a\u92b7\u552e\u7d71\u7c4c", "description": "\u8077\u8cac:\n\n\u8655\u7406\u92b7\u552e\u8a02\u55ae\uff0c\u8207\u5b78\u6821\u3001\u66f8\u5546\u53ca\u5176\u4ed6\u5ba2\u6236\u8ddf\u9032\u8a02\u55ae\n\u8655\u7406\u5ba2\u6236\u67e5\u8a62\u53ca\u5176\u4ed6\u8ddf\u9032\u5de5\u4f5c\n\u7ba1\u7406\u92b7\u552e\u6578\u64da\u5eab\u8a18\u9304\u3001\u92b7\u552e\u5831\u544a\n\u4e00\u822c\u6587\u66f8\u5de5\u4f5c\n\u5354\u52a9\u7ba1\u7406\u5718\u968a\n\n\u8981\u6c42:\n\n\u6587\u6191\u6216\u4ee5\u4e0a\u7a0b\u5ea6\n\u81f3\u5c115\u5e74\u8a02\u55ae\u8655\u7406 /\u00a0\u5ba2\u6236\u670d\u52d9\u5de5\u4f5c\u7d93\u9a57\uff0c\u4e26\u51772-3\u5e74\u7763\u5c0e\u7d93\u9a57\n\u719f\u6089MS Office\uff0c\u6709\u7cfb\u7d71\u8f38\u5165\u7d93\u9a57\n\u826f\u597d\u6e9d\u901a\u6280\u5de7\u548c\u5ba2\u6236\u670d\u52d9\u6280\u5de7\n\u53ef\u5373\u6642\u5230\u8077\u8005\u512a\u5148\u8003\u616e\n\n\u672c\u516c\u53f8\u63d0\u4f9b\u826f\u597d\u4e8b\u696d\u767c\u5c55\u6a5f\u6703\u53ca\u826f\u597d\u85aa\u916c\u53ca\u798f\u5229\u3002\u6709\u8208\u8da3\u8005\u8acb\u6309\"APPLY NOW\"\u63d0\u4ea4\u500b\u4eba\u5c65\u6b77\u6216\u900f\u904e Whatsapp 96887362 \u4e86\u89e3\u8a73\u60c5\u3002\n\n\u6b61\u8fce\u700f\u89bd\u672c\u516c\u53f8\u7db2\u9801\u00a0http://www.popular.com.hk\u00a0\u6216\u00a0http://ephhk.popularworldhk.com\u00a0.\n\n\u6240\u6709\u8077\u4f4d\u7533\u8acb\u5c07\u4f5c\u6a5f\u5bc6\u8cc7\u6599\u8655\u7406\u53ca\u53ea\u4f5c\u62db\u8058\u7528\u9014\u3002", "employment_types": ["Full Time", "Permanent"], "selling_points": ["\u8a02\u55ae\u8655\u7406\u3001\u5354\u52a9\u7ba1\u7406\u5718\u968a", "\u4e94\u5929\u5de5\u4f5c, \u91ab\u7642\u53ca\u7259\u79d1\u4fdd\u96aa, \u914c\u60c5\u82b1\u7d05", "\u5a5a\u5047, \u6559\u80b2\u6d25\u8cbc, \u8343\u7063"], "locations": ["Tsuen Wan Area"], "categories": ["Sales, CS & Business Devpt", "Customer Service - Supervisor / Officer", "Transportation & Logistics", "Fulfillment", "Sales Administration"], "post_time": "2022-01-17T02:25:29Z", "salary": {"currency": null, "max": null, "min": null, "period": "monthly", "term": null}, "salary_visible": false, "title_keywords": ["coordinator", "senior sales"], "responsibilities": [], "requirements": {"degrees": [], "majors": [], "languages": [], "language_level": [], "hard_skills": ["whatsapp"], "soft_skills": [], "languages_combined": []}, "experience_required": {"duration": [], "field": []}}, {"job_id": "100003009049995", "location_code": "hk", "company": "V-Logic Limited", "job_title": "Sales and Business Development Officer  - Logistics Fulfilment", "description": "Responsibilities\u00a0\n\nWork with the Head of Business Development to implement company direction and business strategies to meet and exceed business revenue goals.\nIdentify business opportunities and develop eCommerce fulfillment/logistics and freight service products to clients and overseas agent partners.\nSourcing and maintaining of clients.\u00a0\nWork on quotations and negotiations to secure business.\nEstablish and maintain relationships with clients.\n\n\u00a0Requirements\n\nBachelor Degree in International Business or Logistics related disciplines is preferable.\nAt least 3-10 years of working experience in business development or sales & marketing with proven track records is preferable.\u00a0\nKnowledge and experience in logistics and eCommerce industries (especially e-fulfillment logistics).\u00a0\nKnowledge and experience in international freight forwarding is a plus.\nStrong interest in eCommerce logistics and supply chain management.\nAggressive, proactive, positive and self-driven working attitude.\nGood communication, coordination and presentation skills.\nPresentable, customer and result oriented.\nA team player and willing to take up challenges.\nGood command of both spoken and written English and Chinese is required.\u00a0 Proficiency in Putonghua is a plus.\n\n\u00a0If you are the one we are looking for, please send your full resume with expected salary by clicking \"Apply Now\".\n\n\n\u00a0Resume without expected salary will not be considered.\n\nJob Location: Kwai Chung (Next to Lai King\u00a0MTR Station)", "employment_types": ["Full Time", "Permanent"], "selling_points": [], "locations": ["Kwai Tsing Area"], "categories": ["Sales, CS & Business Devpt", "Business Development", "Transportation & Logistics", "Fulfillment", "Account Servicing"], "post_time": "2022-01-14T09:36:35Z", "salary": {"currency": null, "max": null, "min": null, "period": "monthly", "term": null}, "salary_visible": false, "title_keywords": ["logistics", "business development officer", "sales"], "responsibilities": ["maintain relationships", "identify business opportunities", "maintaining", "fulfillment", "develop", "logistics"], "requirements": {"degrees": ["degree", "bachelor"], "majors": ["related disciplines", "international business"], "languages": ["putonghua", "english", "chinese"], "language_level": ["proficiency", "good command"], "hard_skills": ["plus"], "soft_skills": ["presentable", "communication", "presentation skills", "result oriented", "coordination", "team player", "proactive", "driven", "positive"], "languages_combined": [{"language": "putonghua", "language_level": ["proficiency"]}, {"language": "english", "language_level": ["good command"]}, {"language": "chinese", "language_level": ["good command"]}]}, "experience_required": {"duration": ["at least 3-10 years"], "field": ["ecommerce", "business development", "logistics", "marketing"]}}, {"job_id": "100003009048702", "location_code": "hk", "company": "UAG Hong Kong Limited", "job_title": "Supply Chain Specialist", "description": "Company Overview\n\nAt Urban Armor Gear (UAG), our mission is to provide high quality mobile solutions combined with unparalleled customer service and industry leading warranties. We believe in empowering mobile users with highly valued products giving them complete peace of mind.\n\nUAG products are designed by adventure seekers for adventure seekers.\n\nAt UAG we work hard and play hard; channeling our inspiration into hard work and pushing the limits of conventional ideas to create superior products. We are a platoon of talented designers, engineers, and marketers corralled by unparalleled leadership. UAG products are sold worldwide through premium e-commerce channels including Amazon.com, eBay, and Rakuten Shopping and specialty retailers in the U.S.\n\nMission\n\nWe are looking for an energetic Supply Chain professional to help us move the company to the next stages of its evolution and growth. Your new role will work across the global SCM team to be accountable for analyze all activities associated with supply planning, logistic, demand planning, and inventory management.\u00a0 You will support 1) avoid the business interruptions and ensure continuity of supply; 2) minimize the logistic cost while maintain the efficient order fulfillment; 3) leverage cross-functions efforts in the global team to continually improve performance and deliver on supply, demand, and logistic KPIs.\n\nEssential Job Functions\n\nSupport the analysis work for weekly purchase decision\nMaintain and track logistical costs for reporting and efficiency\nManage the freight schedule to align the inventory availability and goods delivery to worldwide with the lowest possible cost.\nAssist in preparation of supply chain report to facilitate the decision making\nAssist in the inventory planning and stock control\n\nRequired Skills and Experience\n\n3 - 5 years of experience in supply chain role in short life cycle consumer goods/electronics\nBachelor\u2019s degree in Business Administration, Supply Chain Management or equivalent experience\nExperience using MS Office, ERP, data warehouse, and planning tools\nExcellent communication skills (written & oral)\nKnowledge of sophisticated supply chain concepts and processes, having manufacturing concept is a plus\nAbility to thrive in multi-tasking and fast-paced working environment\nStrong interest in the market trend of consumer electronic device\nEager in working with other teams across the world.", "employment_types": ["Full Time", "Permanent"], "selling_points": ["End to end supply chain role", "Global market exposure", "Fast-Paced Work Environments"], "locations": ["Kowloon Bay"], "categories": ["Transportation & Logistics", "Fulfillment", "Shipping", "Supply Chain"], "post_time": "2022-01-14T07:04:36Z", "salary": {"currency": null, "max": null, "min": null, "period": "monthly", "term": null}, "salary_visible": false, "title_keywords": ["specialist"], "responsibilities": ["ideas", "data", "demand planning", "quality", "inventory management", "communication", "purchase", "customer service", "maintain", "costs", "administration", "control", "inventory availability", "teams", "order fulfillment", "schedule", "kpis", "report", "reporting", "cost", "management", "inventory planning", "analysis", "planning"], "requirements": {"degrees": ["degree", "bachelor"], "majors": ["business administration"], "languages": [], "language_level": [], "hard_skills": ["supply planning", "plus", "amazon", "e-commerce", "data warehouse", "demand planning", "analysis", "erp", "mobile", "ms office"], "soft_skills": ["efficient", "communication skills", "oral", "sophisticated", "decision making", "accountable", "multi-tasking", "customer service", "energetic", "leadership", "superior"], "languages_combined": []}, "experience_required": {"duration": ["3 - 5 years"], "field": ["supply chain", "management", "business administration", "planning"]}}, {"job_id": "100003009048683", "location_code": "hk", "company": "UAG Hong Kong Limited", "job_title": "Supply Planning & Logistic Manager", "description": "Company Overview\n\nAt Urban Armor Gear (UAG), our mission is to provide high quality mobile solutions combined with unparalleled customer service and industry leading warranties. We believe in empowering mobile users with highly valued products giving them complete peace of mind.\n\nUAG products are designed by adventure seekers for adventure seekers.\n\nAt UAG we work hard and play hard; channeling our inspiration into hard work and pushing the limits of conventional ideas to create superior products. We are a platoon of talented designers, engineers, and marketers corralled by unparalleled leadership. UAG products are sold worldwide through premium e-commerce channels including Amazon.com, eBay, and Rakuten Shopping and specialty retailers in the U.S.\n\nMission\nWe are looking for an experienced Supply Chain professional to help us move the company to the next stages of its evolution and growth. Your new role will work closely with the CEO, is accountable for analyze all activities associated with supply planning, logistic, demand planning, and inventory management.\u00a0 You will 1) avoid the business interruptions and ensure continuity of supply; 2) minimize the logistic cost while maintain the efficient order fulfillment; 3) leverage cross-functions efforts in the global team to continually improve performance and deliver on supply, demand, and logistic KPIs.\n\nEssential Job Functions\n\nSupply Planning \u2013 Identify the need for POs based on demand plan and production/logistic lead times, initiating POs, and resolving variances.\u00a0 Well understand the product cycle and market trend in fast pacing environment, provide valuable advisory in stock replenishment.\u00a0\u00a0\u00a0\nDemand planning \u2013 collaborate with sales and operation team in the worldwide to translate forecast feedback into inventory strategies.\u00a0 Maintain demand plan, recommend purchase decisions based on target inventory levels, product velocity, and other demand variables.\u00a0 Create demand planning strategies and provide recommendations to improve processes\nSourcing \u2013 Participate in the new product development process to ensure inventory availability at launch and through the initial ramp.\nLogistics \u2013 Manage inbound/outbound freight program to ensure inventory availability and goods delivery to DC/customers at lowest possible cost.\nSupply Chain Analytics \u2013 Develop informative and actionable key performance indicator round the supply chain function.\n\nRequired Skills and Experience\n\n8+ years of experience in supply planning in short life cycle consumer goods/electronics\nBachelor\u2019s degree in Business Administration, Supply Chain Management or equivalent experience\nExperience using MS Office, ERP, data warehouse, and planning tools\nExcellent communication skills (written & oral)\nKnowledge of sophisticated supply chain concepts and processes, having manufacturing concept is a plus\nAbility to thrive in multi-tasking and fast-paced working environment\nHigh sense of personal accountability, a bias toward action, and attention to detail\nBeing a self-starter, mature thinking, energetic, and able to work with minimum supervision\nStrong interest in the market trend of consumer electronic device\nEager in working with other teams across the world.", "employment_types": ["Full Time"], "selling_points": ["All rounded Supply Chain Role", "Minimal Supervision", "Global Exposure"], "locations": ["Kowloon Bay"], "categories": ["Transportation & Logistics", "Fulfillment", "Inventory / Warehousing", "Supply Chain"], "post_time": "2022-01-14T07:02:35Z", "salary": {"currency": null, "max": null, "min": null, "period": "monthly", "term": null}, "salary_visible": false, "title_keywords": ["manager"], "responsibilities": ["collaborate with", "ideas", "data", "demand planning", "inventory", "quality", "inventory management", "communication", "purchase", "customer service", "maintain", "plan", "administration", "stock replenishment", "inventory availability", "teams", "develop", "order fulfillment", "logistics", "forecast", "kpis", "cost", "management", "provide recommendations", "planning"], "requirements": {"degrees": ["degree", "bachelor"], "majors": ["business administration"], "languages": [], "language_level": [], "hard_skills": ["supply planning", "plus", "amazon", "pos", "e-commerce", "data warehouse", "demand planning", "erp", "mobile", "dc", "ms office"], "soft_skills": ["efficient", "communication skills", "oral", "sophisticated", "accountability", "accountable", "mature", "multi-tasking", "customer service", "attention to detail", "energetic", "leadership", "superior"], "languages_combined": []}, "experience_required": {"duration": ["8+ years"], "field": ["supply chain", "management", "business administration", "planning"]}}, {"job_id": "100003009049237", "location_code": "hk", "company": "GEODIS Hong Kong Limited", "job_title": "Assistant Solutions & Implementation Manager", "description": "Responsibilities:\n\n\nLeading the solutions design (facility design and cost modelling) for new business opportunities, key interface between operations team and sales team to ensure quality proposal is delivered.\nLeading the implementation of new business opportunities\nLeading the continuous improvement program for all Contract Logistics operations in Hong Kong & South China, working closely with operations team to ensure annual cost savings target is met\nDriving operational standardization across all Contract Logistics operations in Hong Kong & South China with utilization of business intelligence reporting to improve operational quality and efficiency visibility\nRequirements:\n\n3-5\u00a0years of logistics operations or Solutions Design and Project Management experience\nAutoCAD experience is a must\nUndergraduate degree, engineering degree preferred\nExcellent MS Excel and PowerPoint skill, able to perform data analysis and prepare slides for presentation.\n\n** Less experience will be considered as Logistics Supervisor/ Senior Logistics Supervisor\n\nPersonal data collected will be used for recruitment purpose only.\n\nOur data processing are compliant with data protection regulations. To learn about GEODIS Privacy Policy or exercise your rights, go to http://geodis.com/dp/recruitment-privacy-policy", "employment_types": ["Full Time", "Permanent"], "selling_points": ["Logistics Solution Design", "Implementation of new business", "AutoCAD required"], "locations": ["Tuen Mun Area"], "categories": ["Transportation & Logistics", "Fulfillment", "Inventory / Warehousing", "Supply Chain"], "post_time": "2022-01-14T08:18:00Z", "salary": {"currency": null, "max": null, "min": null, "period": "monthly", "term": null}, "salary_visible": false, "title_keywords": ["manager", "assistant"], "responsibilities": ["reporting", "cost", "operations", "business opportunities", "quality", "implementation", "design", "sales team", "logistics"], "requirements": {"degrees": ["degree"], "majors": ["engineering"], "languages": [], "language_level": [], "hard_skills": ["analysis", "powerpoint", "project management", "ms excel", "go", "processing", "autocad"], "soft_skills": ["project management", "presentation"], "languages_combined": []}, "experience_required": {"duration": ["3-5 years"], "field": ["project management", "logistics", "design"]}}, {"job_id": "100003009052290", "location_code": "hk", "company": "Kerry Logistics", "job_title": "Graduate Trainee", "description": "Our Graduate Trainee (GT) Programme\u00a0is a comprehensive career development programme providing invaluable opportunities to enter the gate of logistics field. Experience different aspects of the industry & to apply innovative & technology elements into value-adding solutions.\n\nFeatures of Graduate Trainee Programme\n\nThrough intensive action-learning projects in Hong Kong, the programme prepares high potential graduates to take on early responsibility and shape their project leadership with industrial knowledge and hands-on experience.\n\n12-month programme\nAttach to 2 operation / business projects\nOn-job training supported with senior management guidance and coaching programme\nWide exposures from operations to key accounts management and business development\nRegular talent review and presentation to the management on business ideas and project improvement\nLearning curriculums to forge successful and sustainable career\n\n\u00a0Requirements\n\n2022 university graduates from any disciplines\nLogistics related study or work experience is an added advantage\u00a0\nPassionate\u00a0in taking leadership in 3PL project\nReady to take early responsibility and drive results\nProactive, adaptive, solution-focused\nProficiency in both English and Chinese\n\nApplication Period:\u00a0 3 January 2022 - 6 February 2022 (HK Intake)\n\n\nHow to apply\n\nSubmit your application only through\u00a0Kerry Logistics Job Application System\u00a0(yea.kerrylogistics.com). We do NOT accept email or other means of application.\n\nVirtual Information Session\n\nDate & time:\u00a0\u00a0\u00a0\u00a0\u00a028 January, 3pm via ZOOM\n\nRegistration:\u00a0 \u00a0 \u00a0Sign up\u00a0at\u00a0bit.ly/GT22info\u00a0by 25 January.\n\nA confirmation email with an access link will be sent on 26 January.\u00a0\n\n(We are an equal opportunity employer and welcomes applications from all qualified candidates.\u00a0All personal data will be kept in the strictest confidence and will be used for recruitment purpose only. All applicants maybe considered for other suitable positions in the Kerry Group and its members. All personal data of unsuccessful candidates will be destroyed.)", "employment_types": ["Full Time", "Permanent"], "selling_points": [], "locations": ["Kwai Fong"], "categories": ["Transportation & Logistics", "Others", "Fulfillment", "Supply Chain"], "post_time": "2022-01-17T02:39:29Z", "salary": {"currency": null, "max": null, "min": null, "period": "monthly", "term": null}, "salary_visible": false, "title_keywords": ["graduate trainee"], "responsibilities": ["recruitment", "personal data", "logistics", "application system"], "requirements": {"degrees": [], "majors": [], "languages": [], "language_level": [], "hard_skills": [], "soft_skills": ["passionate", "leadership"], "languages_combined": []}, "experience_required": {"duration": [], "field": ["related", "logistics"]}}, {"job_id": "100003009049462", "location_code": "hk", "company": "Amika", "job_title": "Senior Logistic Officer", "description": "Responsibilities:\n\nHandle day-to-day logistics operations and workflows including goods receiving, order handling, delivery arrangement, reverse logistics and warranty exchange\nClose collaboration with warehouse to ensure the services meet the business requirements\nWork with various departments to ensure a smooth supply chain system is in place\nInventory control to keep stock record align between WMS and ERP system\nHelp for stock planning, orders replenishment and delivery arrangement with suppliers\nConduct other ad hoc task as assigned\n\n\u00a0Job Requirements:\n\nHigh Diploma in Logistics or related field\n5+ years working experience preferably in cosmetic retail industry\nKnowledge in shipping is an advantage\nGood PC skills in MS Word and Excel, knowledge on POS System\nExcellent communication skill, proactive, multi-task, attention to details, organized and willing to learn\nGood command of both written & spoken Chinese and English\nImmediate availability is preferred.", "employment_types": ["Full Time", "Permanent"], "selling_points": ["5 years logistic experience cosmetic retail", "Proactive and a good communicator", "Work life balance, friendly working environment"], "locations": ["Kwun Tong"], "categories": ["Transportation & Logistics", "Fulfillment", "Inventory / Warehousing"], "post_time": "2022-01-14T08:45:17Z", "salary": {"currency": null, "max": null, "min": null, "period": "monthly", "term": null}, "salary_visible": false, "title_keywords": ["logistic officer"], "responsibilities": ["ad hoc", "operations", "replenishment", "inventory control", "logistics", "wms", "stock planning"], "requirements": {"degrees": ["high diploma"], "majors": [], "languages": ["english", "chinese"], "language_level": ["good command"], "hard_skills": ["excel", "pos system", "pc skills", "ms word"], "soft_skills": ["organized", "multi-task", "communication skill", "willing to learn", "attention to details", "proactive"], "languages_combined": [{"language": "english", "language_level": ["good command"]}, {"language": "chinese", "language_level": ["good command"]}]}, "experience_required": {"duration": ["5+ years"], "field": ["retail industry"]}}, {"job_id": "100003009050177", "location_code": "hk", "company": "Everlink HR Consulting Limited", "job_title": "Senior Supply Chain Planner, APAC (Beauty Brand)", "description": "Our client is a global leading Beauty Brand It is now looking for a Senior Supply Chain Planner, APAC to join their team.\n\nKey Responsibilities\n\n\n\nProvide support for all retail operations queries, facilities and maintenance issues, stationery and hygiene product orders.\nManage and streamline stock order to receipt flow, raising daily stock replenishment orders month-end processes\nProvide support and assistance to the regional Supply Chain Lead and the sales team on the performance of the day-to-day operations and operational concerns\nUnderstand operational and implement solutions to improve customer service and delivery efficiencies\nAwareness of short-term commercial and marketing activities which could have impacts on the effectiveness of the operations and pro-actively manage these business requirements with the support of key stakeholders.\n\nRequirements\n\nBachelor degree in Supply Chain\nAt least 4 years of working experience of supply chain field\nAble to demonstrate examples of building and improving customer relationships\nAble to demonstrate real examples of taking ownership of projects\u00a0\nExperience with ERP and POS system is preferred", "employment_types": ["Full Time", "Permanent"], "selling_points": ["Supply Chain", "Regional Explorsure", "stock replenishment"], "locations": ["Not Specified"], "categories": ["Transportation & Logistics", "Others", "Fulfillment", "Supply Chain"], "post_time": "2022-01-14T09:54:32Z", "salary": {"currency": null, "max": null, "min": null, "period": "monthly", "term": null}, "salary_visible": false, "title_keywords": ["supply chain planner"], "responsibilities": ["provide support", "stock replenishment", "maintenance", "operations", "day-to-day operations", "stationery", "month-end", "hygiene", "customer service", "sales team"], "requirements": {"degrees": ["degree", "bachelor"], "majors": [], "languages": [], "language_level": [], "hard_skills": ["pos system", "erp"], "soft_skills": [], "languages_combined": []}, "experience_required": {"duration": ["at least 4 years"], "field": ["supply chain"]}}, {"job_id": "100003009049583", "location_code": "hk", "company": "Chan Kee Foods Limited", "job_title": "Logistics Manager (Night shift)", "description": "Job Responsibilities\n\nEnd to end logistic management\nImplement and improve operation procedures, KPI and policies\nReview and implement efficiency improvement initiatives\nPlan and manage resources and manpower efficiently\nReport to management team\n\nJob Requirements\n\nDiploma or above in logistic, supply chain management or related discipline\nMinimum 3 years' supervisory experience in managing logistic operation, experience in FMCG or local distribution is an advantage\nStrong leadership, people management and problem solving skills\nCandidate with less experience will be considered as Assistant Logistic Manager\nStaff Benefits\n\n5 days work\nParking space / Traffic allowance\nBirthday leave\nFamily leave\nAnnual Bonus\nStaff discount\nMedical & Dental allowance\n\nInterested parties please send your resume stating your current or last salary, expected salary and available date via \"Apply now\" button.\n\n(All\u00a0collected\u00a0information will be used for recruitment related purpose only.)", "employment_types": ["Full Time", "Permanent"], "selling_points": ["5 days work week in Tseun Wan district", "Good career development in FMCG industry", "Flexible working hours, parking space provided"], "locations": ["Tsuen Wan Area"], "categories": ["Transportation & Logistics", "Fulfillment", "Inventory / Warehousing", "Supply Chain"], "post_time": "2022-01-14T08:54:19Z", "salary": {"currency": null, "max": null, "min": null, "period": "monthly", "term": null}, "salary_visible": false, "title_keywords": ["logistics manager"], "responsibilities": ["management team", "management", "policies", "review", "procedures", "plan", "report"], "requirements": {"degrees": ["diploma or above"], "majors": [], "languages": [], "language_level": [], "hard_skills": ["problem solving skills"], "soft_skills": ["problem solving skills", "leadership"], "languages_combined": []}, "experience_required": {"duration": ["minimum 3 years"], "field": ["fmcg", "operation", "supervisory experience"]}}, {"job_id": "100003009043041", "location_code": "hk", "company": "Links International", "job_title": "Logistic Operation & CS Manager", "description": "Logistic Operation & CS Manager - Fashion Retailer\n\nOur client is a large international fashion retailer, looking for a Logistic Operation & CS Manager to join their organization. Oversee and manage the operation of 3PL warehouses and all trade logistics for Hong Kong and Macau Market.\n\nResponsibilities:\n\nLead and coach a team of specialists, coordinate with vendors in handling logistic operations such as inventory aging, sales orders pick-pack-ship process and shipment arrangement.\nMonitor all processes for receiving, processing, pick and pack and returns handling.\nWork closely with NBIL to manage local market IAS processes.\nCreate operations strategies and solutions based on global / regional strategic priorities.\nManage and refine warehouse operations, ensuring smooth and efficient operation.\nOversees and reports weekly, monthly, quarterly, and annual metrics.\nPerform regular audit of the local warehouse.\nIdentify cost savings opportunities, identify logistic trends and assesses opportunities to improve operational procedures and execution.\nWorks closely with regional operations team and Hong Kong finance team on other special planning and various new developing projects.\n\nQualifications:\n\nA strong educational background in Logistics, Supply Chain Management or related discipline is preferably\n10 years in supply chain and warehouse operation years in a multinational company is preferred. At least 5 years of working experience in operation management.\nKnowledge and experiences in supply chain optimization, warehouse operation, systems, inventory planning, shipping, order management, replenishment, CS\nBeing entrepreneurial; gets things done and constantly looking for ways to improve.\nExcellent command in both English and Chinese\nHigh motivation and self-discipline to work independently", "employment_types": ["Full Time", "Permanent"], "selling_points": ["Retail experience preferred", "HK & Macau Coverage, lead team", "Logistic and CS Management"], "locations": ["Not Specified"], "categories": ["Transportation & Logistics", "Fulfillment", "Inventory / Warehousing", "Supply Chain"], "post_time": "2022-01-12T09:36:41Z", "salary": {"currency": "HKD", "max": 54999, "min": 45000, "period": "monthly", "term": null}, "salary_visible": true, "title_keywords": ["manager"], "responsibilities": ["shipping", "operations", "inventory", "audit", "monitor", "developing", "operational procedures", "logistics", "reports", "finance team", "cost", "management", "shipment arrangement", "coordinate with", "inventory planning", "order management", "systems", "replenishment", "3pl warehouses", "warehouse operations", "planning"], "requirements": {"degrees": [], "majors": [], "languages": ["english", "chinese"], "language_level": ["excellent"], "hard_skills": ["processing"], "soft_skills": ["efficient", "work independently", "smooth"], "languages_combined": [{"language": "english", "language_level": ["excellent"]}, {"language": "chinese", "language_level": ["excellent"]}]}, "experience_required": {"duration": ["at least 5 years"], "field": ["management", "supply chain", "operation management", "operation", "cs", "planning"]}}, {"job_id": "100003009041558", "location_code": "hk", "company": "Manrison Personnel Limited", "job_title": "Sales Coordinator \u2013 up to 18K \u2013 Japanese Firm", "description": "Our client is a global automobile solution company in Japan. They are now looking for Sales Coordinator to support their Hong Kong operation team.\n\nJob\u00a0Responsibilities:\n\nResponsible for handling the full process of order fulfilment and sales order arrangement\nClosely communicate with suppliers, customers and logistics parties for the daily logistics arrangement\nFollow up sales orders and monitor delivery schedule and prepare full set shipment documentation\nParticipate in daily administrative support such as data collection, filling and regular report preparation\n\nJob\u00a0Requirements:\n\nTertiary education or above in Shipping, Logistics or Supply Chain\nA year or up of working experience in shipping or trading environment\nKnowledge in shipping procedure or automobile trade process\nAbility in handling full set shipment arrangement or order fulfilment\nProficient in MS Office (Excel, Power Point, Word) and Tradelink\nGood communication skills in English and Chinese, both written and spoken\n\nTo apply for this position, please simply click on the \u201cAPPLY NOW\u201d bottom to forward an up-to-date copy of your resume. All applications will be treated in strict confidence and used for recruitment purposes only. If this job isn't quite right for you but you are looking for a new position, please contact Ms. Tsang at 37952319 for a confidential discussion on your career.", "employment_types": ["Full Time", "Permanent"], "selling_points": ["Experience in handling the full set shipment", "Tertiary education in Shipping or Logistics", "Passionate in Japanese culture"], "locations": ["Causeway Bay"], "categories": ["Transportation & Logistics", "Fulfillment", "Shipping", "Sales, CS & Business Devpt", "Sales Administration"], "post_time": "2022-01-12T04:02:21Z", "salary": {"currency": null, "max": null, "min": null, "period": "monthly", "term": null}, "salary_visible": false, "title_keywords": ["sales coordinator"], "responsibilities": ["communicate with", "logistics arrangement", "administrative support", "monitor", "delivery schedule", "logistics", "data collection", "documentation", "report"], "requirements": {"degrees": [], "majors": [], "languages": ["english", "chinese"], "language_level": ["good"], "hard_skills": ["power point", "excel", "word", "ms office"], "soft_skills": ["communication skills", "confidence"], "languages_combined": [{"language": "english", "language_level": ["good"]}, {"language": "chinese", "language_level": ["good"]}]}, "experience_required": {"duration": [], "field": ["trading"]}}, {"job_id": "100003009047372", "location_code": "hk", "company": "JEB International Limited", "job_title": "Operations Coordinator", "description": "JEB Working Environment\nWe pride ourselves on providing our team with the best tools, resources, and environment in which to be most effective and fulfilled. We create stimulating spaces in which to collaborate and be creative. We promote dynamic career progression, with a focus on developing staff to achieve their goals.\u00a0\n\nJEB Value Statement\nThe JEB team consists of diverse, passionate individuals, with varied backgrounds and experience. We celebrate our diversity and unique talents and share a collective dedication to Lead, Serve, Innovate and Create.\n\nOur values are shared by our team who have an attitude towards design and delivery that is of the highest quality of product and service. We actively maintain the JEB culture through;\n\nIntegrity; we act with honesty and integrity in everything we do\nClient service; we are dedicated to ensuring our clients always receive the highest level of service\nTeamwork; we work together to achieve common goals\nInnovation; we strive to deliver innovative solutions\n\nJob Responsibilities\n\nPrepare and follow up Purchase Orders\nVerify invoice for goods receiving procedure\nFollow up on shipment arrangements and status update\nSupport the team for all round admin and documentation support\nAssist in other ad-hoc duties assigned as required\n\n\u00a0Requirements\n\nProficient in MS Excel\u00a0\nGood command of written and spoken English and Chinese including Mandarin\u00a0\u00a0\u00a0\u00a0\u00a0\u00a0\u00a0\nDetail oriented, willing to learn, good communication skills\nFresh graduates will also be considered.\u00a0\n\nIf you have the knowledge, skills, and experience for this role, we would love to hear from you! Click\u00a0\"APPLY NOW\"\u00a0with your full resume quoting job ref. number [JILJD354], stating your availability, current and expected salary for our consideration. To stay tune\u00a0with our latest movements and openings, please visit\u00a0https://jebgroup.com/jeb-careers/\u00a0\u00a0", "employment_types": ["Full Time"], "selling_points": ["Career development and learning opportunities", "Performance bonus", "Fun working environment"], "locations": ["Tai Koo"], "categories": ["Transportation & Logistics", "Fulfillment", "Supply Chain", "Manufacturing", "Production Planning / Control"], "post_time": "2022-01-14T02:56:35Z", "salary": {"currency": null, "max": null, "min": null, "period": "monthly", "term": null}, "salary_visible": false, "title_keywords": ["operations", "coordinator"], "responsibilities": ["invoice", "purchase", "ad-hoc duties", "documentation", "support the team"], "requirements": {"degrees": [], "majors": [], "languages": ["english", "chinese", "mandarin"], "language_level": ["good command"], "hard_skills": ["ms excel"], "soft_skills": ["communication skills", "detail oriented", "willing to learn"], "languages_combined": [{"language": "english", "language_level": ["good command"]}, {"language": "chinese", "language_level": ["good command"]}, {"language": "mandarin", "language_level": ["good command"]}]}, "experience_required": {"duration": [], "field": []}}, {"job_id": "100003009043440", "location_code": "hk", "company": "Hays", "job_title": "Customer Service/ Shipping Coordinator", "description": "Your new company\nOur client is looking for a candidate with customer service and shipping experience to join their Hong Kong Team\n\nYour new role\n\nCommunicate with freight forwarders and internal stakeholders on shipping arrangement\nProvide support on inbound and outbound logistics queries for APAC market\nFollow up with customers enquiries\nHandle ad hoc issues\n\nWhat you'll need to succeed\n\nAt least 4 years of experience in shipping and order management, welcome candidates from 3PL background\nExperience in handling different markets\n\nWhat you'll get in return\n\nup to 25K\n5 days of work\nBenefit from work from home policy\n\nWhat you need to do now\nIf you're interested in this role, click 'apply now' to forward an up-to-date copy of your CV, or call us now.\nIf this job isn't quite right for you but you are looking for a new position, please contact us for a confidential discussion on your career.", "employment_types": ["Full Time", "Permanent"], "selling_points": ["MNC opportunity", "Work from home arrangements", "Competitive salary"], "locations": ["Not Specified"], "categories": ["Sales, CS & Business Devpt", "Customer Service - Supervisor / Officer", "Transportation & Logistics", "Fulfillment", "Shipping"], "post_time": "2022-01-12T11:49:43Z", "salary": {"currency": null, "max": null, "min": null, "period": "monthly", "term": null}, "salary_visible": false, "title_keywords": ["customer service", "shipping coordinator"], "responsibilities": ["communicate with", "provide support", "shipping", "ad hoc", "order management", "customer service", "contact", "inbound and outbound logistics"], "requirements": {"degrees": [], "majors": [], "languages": [], "language_level": [], "hard_skills": ["inbound and outbound logistics"], "soft_skills": ["interested in", "customer service"], "languages_combined": []}, "experience_required": {"duration": ["at least 4 years"], "field": ["management", "customer service", "team"]}}, {"job_id": "100003009056374", "location_code": "hk", "company": "Stryker Pacific Ltd - Accounts", "job_title": "Senior Order Management Specialist", "description": "Stryker is one of the world\u2019s leading medical technology companies and, together with our customers, is driven to make healthcare better. We offer innovative products and services in Orthopedics, Medical and Surgical, and Neurotechnology and Spine that help improve patient and hospital outcomes. We are proud to be named one of the World\u2019s Best Workplaces and a Best Workplace for Diversity by Fortune Magazine. Learn more about our award-winning organization by visiting careers.stryker.com\u00a0\n\nAbout the Role :\u00a0\n\nThe Order Management team acts as a primary interface with both external (i.e., hospitals or distributors) and internal customers (i.e. commercial, customer care, finance and planning teams), and triage/ respond to the sales order related enquiries. This team plays a crucial role towards the customer experience journey, and to the Order-to-Cash (\u201cOTC\u201d) process flow.\nIn this role, you will be the main person in Hong Kong for the Medical business - handling enquiries, processing orders and service billing along the OTC flow with external customers. You will also support internal requests such as master data maintenance, demo or stock transfer as part of the daily routine.\n\nWhat You Will Be Doing :\n\nPrimary point of contact on orders from order processing to order status follow-up within Operations and Planning teams.\nCollaborate with commercial and customer care teams to provide timely responses to customers\u2019 enquiries.\nTriage and/or resolve any problems or customer complaints based on process and data analytics.\nExecute the order management process and integrate with the 3PL management process to complete the entire Order-to-Cash flow.\nWork closely with other functional teams to identify opportunities to standardize and optimize the flow.\nWork with Sales, 3PL and customers to arrange timely deliveries for key orders.\nSupport in relevant master data setup in internal systems.\nCoordinating the dispatch, delivery, and billing of capital products.\nReducing inbound freight costs while keeping high service levels.\nGenerate relevant KPI reports and support the analysis.\u00a0\n\nWho We Are Looking For :\u00a0\n\nBachelor\u2019s degree in Business, Operations, Supply Chain or related fields.\nAbout 3 to 5 years' experience in order processing or sales support in MNC settings. Applicants with less experience will also be considered.\u00a0\nExcellent communications skills in verbal and written English.\nEnjoys the challenge of working in a growing business and playing a key role in building up processes.\nGreat interpersonal skills and able to tactfully influence and persuade stakeholders towards paths of action.\nEffective relationship building skills and ability to collaborate well with internal stakeholders across various functions.\nStrong sense of ownership and problem solving skills.\nProficiency in Microsoft Office tools including, Excel, PowerPoint.\nPrevious experience using an ERP system. (JDE and BI experience or equivalent).", "employment_types": ["Full Time", "Permanent"], "selling_points": ["Fortune 500 Medical Device MNC", "World's Best Workplaces Award 2021", "Career Development Opportunities"], "locations": ["Tai Koo"], "categories": ["Transportation & Logistics", "Fulfillment", "Supply Chain", "Sales, CS & Business Devpt", "Sales Administration"], "post_time": "2022-01-18T04:06:13Z", "salary": {"currency": null, "max": null, "min": null, "period": "monthly", "term": null}, "salary_visible": false, "title_keywords": ["specialist"], "responsibilities": ["collaborate with", "collaborate", "order management", "management", "maintenance", "data", "customer complaints", "operations", "analysis", "teams", "cash flow", "costs", "reports", "contact", "order processing", "internal systems", "setup", "planning"], "requirements": {"degrees": ["degree", "bachelor", "master"], "majors": ["business"], "languages": ["english"], "language_level": ["excellent"], "hard_skills": ["excel", "bi", "sales support", "maintenance", "microsoft office", "data analytics", "analysis", "powerpoint", "make", "erp system", "order processing", "3pl management", "problem solving skills", "processing"], "soft_skills": ["timely", "interpersonal skills", "patient", "problem solving skills", "innovative", "driven"], "languages_combined": [{"language": "english", "language_level": ["excellent"]}]}, "experience_required": {"duration": ["3 to 5 years"], "field": ["erp system", "sales support", "order processing", "team"]}}, {"job_id": "100003009051839", "location_code": "hk", "company": "Stylevana", "job_title": "Assistant Merchandiser \u2013 Beauty", "description": "Join us & Be eCommerce Innovators\n\n\nAre you looking to be part of revolutionizing online shopping behaviour and experience? We are a well-esteemed eCommcere company that operates multiple eCommerce websites internationally. We are now looking for potential talent to help us expand our new business worldwide.\n\nKey Job Responsibilities:\u00a0\n\nResponsible for Korean office purchase order follow up\nPrepare PI and PO, follow up with payment and shipment arrangement\nConsolidate and follow up with Korea Merchandising Team on all orderings from Hong Kong Team\nConsolidation of all Korean purchased goods and prepare paperwork to facilitate the export of goods from Korea\nCommunicate and coordinate with internal or external logistic parties to ensure smooth export process\nPerform other administrative support to Merchandising Team\nOther ad-hoc duties as assigned\n\nDesired Skills and Experience:\u00a0\n\nDiploma of above\u00a0 \u00a0 \u00a0 \u00a0 \u00a0\nMinimum 1-2 years or above working experience in merchandising or logistic experience under trading environment or buying office\nIndependent, well-organized, detailed minded, and able to manage multiple tasks\nGood command of written and spoken English\nImmediate available is highly preferred\n\nWe offer friendly team environment, good career prospect, also attractive remuneration package including commission and discretionary bonus incentive, together with other benefits like five-day work week, flexible working hours, double pay, medical and dental insurance. Interested parties please send full resume with available date, present and expected salary by clicking \u201cApply Now\u201d for an interview.\n\nAll personal data collected will be used for recruitment purpose only.\u00a0", "employment_types": ["Full Time", "Permanent"], "selling_points": ["eCom - Korean Beauty", "Exp in buying beauty products / shipment", "5-day work, Double Pay, flexible working hour"], "locations": ["Kwai Hing"], "categories": ["Transportation & Logistics", "Fulfillment", "Merchandising & Purchasing", "Procurement / Purchasing / Sourcing", "E-commerce", "Marketing - Brand / Product Management"], "post_time": "2022-01-17T01:20:52Z", "salary": {"currency": null, "max": null, "min": null, "period": "monthly", "term": null}, "salary_visible": false, "title_keywords": ["assistant merchandiser"], "responsibilities": ["shipment arrangement", "administrative support", "merchandising", "coordinate with", "purchase", "payment", "ad-hoc duties", "insurance"], "requirements": {"degrees": ["diploma"], "majors": [], "languages": ["english", "korean"], "language_level": ["good command"], "hard_skills": [], "soft_skills": ["flexible", "independent", "responsible", "multiple tasks", "well-organized", "smooth", "friendly", "ad-hoc duties", "detailed"], "languages_combined": [{"language": "english", "language_level": ["good command"]}, {"language": "korean", "language_level": []}]}, "experience_required": {"duration": ["minimum 1-2 years"], "field": ["ecommerce", "merchandising", "trading"]}}, {"job_id": "100003009049592", "location_code": "hk", "company": "Premier by Dead Sea", "job_title": "Senior Logistic Officer", "description": "Responsibilities:\n\nHandle day-to-day logistics operations and workflows including goods receiving, order handling, delivery arrangement, reverse logistics and warranty exchange\nClose collaboration with warehouse to ensure the services meet the business requirements\nWork with various departments to ensure a smooth supply chain system is in place\nInventory control to keep stock record align between WMS and ERP system\nHelp for stock planning, orders replenishment and delivery arrangement with suppliers\nConduct other ad hoc task as assigned\n\n\u00a0Job Requirements:\n\nHigh Diploma in Logistics or related field\n5+ years working experience preferably in cosmetic retail industry\nKnowledge in shipping is an advantage\nGood PC skills in MS Word and Excel, knowledge on POS System\nExcellent communication skill, proactive, multi-task, attention to details, organized and willing to learn\nGood command of both written & spoken Chinese and English\nImmediate availability is preferred.", "employment_types": ["Full Time", "Permanent"], "selling_points": ["5 years logistic experience cosmetic retail", "Proactive and a good communicator", "Work life balance, friendly working environment"], "locations": ["Kwun Tong"], "categories": ["Transportation & Logistics", "Fulfillment", "Inventory / Warehousing"], "post_time": "2022-01-14T08:55:55Z", "salary": {"currency": null, "max": null, "min": null, "period": "monthly", "term": null}, "salary_visible": false, "title_keywords": ["logistic officer"], "responsibilities": ["ad hoc", "operations", "replenishment", "inventory control", "logistics", "wms", "stock planning"], "requirements": {"degrees": ["high diploma"], "majors": [], "languages": ["english", "chinese"], "language_level": ["good command"], "hard_skills": ["excel", "pos system", "pc skills", "ms word"], "soft_skills": ["organized", "multi-task", "communication skill", "willing to learn", "attention to details", "proactive"], "languages_combined": [{"language": "english", "language_level": ["good command"]}, {"language": "chinese", "language_level": ["good command"]}]}, "experience_required": {"duration": ["5+ years"], "field": ["retail industry"]}}, {"job_id": "100003009047836", "location_code": "hk", "company": "PVH Asia Limited", "job_title": "Allocation Analyst, Hong Kong, Macau, Malaysia, Singapore, Taiwan", "description": "POSITION SUMMARY:\n\nDevelop, execute and communicate tactical allocation plans that support the merchandising, marketing and financial objectives of assigned product group.\n\nPRIMARY RESPONSIBILITIES:\n\n\nEnsure the financial success of the product group by meeting or exceeding sales, gross profit and inventory turn goals on an annual basis.\nSet up initial model stock for all replenishable items based on fixture fill plus back stock based on weeks of supply required.\nExecute the release of initial product distributions and in season replenishment to stores.\nAnalyze daily/weekly and monthly selling and adjust model stock where applicable.\nRecap and communicate size selling performance in order to maximize sell through.\nWork with cross functional team on basic styles reorder and in season replenishment to support desired in stock targets.\nWork with cross functional team to ensure timely and accurate execution of new store openings.\nDevelop knowledge of geographic and store attribute performance and trends through data analysis and field feedback.\nDevelop and maintain effective working relationships within cross-functional team (merchandising, planning, marketing, visual, etc.). In particular this will be the allocation analyst, planner, merchant team responsible for the product group.\nCommunicate initial release and replenishment strategies within cross functional team.\nParticipate in cross functional meetings, contributing input on distribution strategies.\nCollaborate with peers to ensure consistency of information, share best practices and develop systems knowledge.\nManage communication regarding inventory/replenishment with field contacts on a store by store basis if required.\nREQUIREMENT:\n2-3 years work experience of Distribution/Allocation Analyst in MNCs preferable in Retail industry.\u00a0 Work experience in an analytical field desired.\nBachelor degree and/or an advance education in logistic/supply chain, Business Administration related disciplines.\u00a0\nStrong analytical and problem solving skills.\nDetail oriented with excellent organizational skills and a self-motivation.\nAble to build and maintain productive relationships within team environment.\nDemonstrates good listening, written and oral communication skills.\nShow ability or aptitude to learn technical applications quickly.\nStrong PC and associated application skills, MS Word and Excel as a requirement.\nJDA Allocation system, GalaxE allocation system. SAP system knowledge.\nWe offer excellent career prospects to the right candidate. Salary will be commensurate with qualifications and experience. Our attractive remuneration package includes variable bonus, retirement benefits with top up contribution to MPF and insurance scheme(s).\n\nPlease send us a full resume including present and expected salary and availability to Human Resources Department via e-mail.\n\nAll information provided by applicants will be used strictly for recruitment purpose. Applicants who are not contacted within one month may consider their applications unsuccessful.\n", "employment_types": ["Full Time", "Permanent"], "selling_points": ["Develop, execute and communicate allocation plan", "Product distributions and replenishment to stores", "JDA, GalaxE, SAP"], "locations": ["Hung Hom"], "categories": ["Sales, CS & Business Devpt", "Customer Service - Supervisor / Officer", "Transportation & Logistics", "Fulfillment", "Inventory / Warehousing"], "post_time": "2022-01-14T04:00:18Z", "salary": {"currency": null, "max": null, "min": null, "period": "monthly", "term": null}, "salary_visible": false, "title_keywords": ["analyst"], "responsibilities": ["collaborate with", "inventory", "systems", "merchandising", "replenishment", "develop", "data analysis", "communication", "maintain", "visual", "working relationships", "planning"], "requirements": {"degrees": ["degree", "bachelor"], "majors": ["related disciplines", "business administration"], "languages": [], "language_level": [], "hard_skills": ["excel", "sap", "pc", "problem solving skills", "ms word"], "soft_skills": ["productive", "organizational skills", "oral", "communication skills", "detail oriented", "analytical and problem solving skills", "self-motivation"], "languages_combined": []}, "experience_required": {"duration": ["2-3 years"], "field": ["retail industry", "analytical"]}}, {"job_id": "100003009039846", "location_code": "hk", "company": "Hays", "job_title": "Shipping Clerk - up to 25K", "description": "Job Duties:\n\n\nFollow up cargoes;\nPrepare purchases & sales contracts;\nCo-ordinate with suppliers, buyers & head office to arrange loading schedules;\nHandle full set shipping documents & issue invoices, etc.\nFulfill other duties related to operations;\n\n\u00a0\nRequirement:\n\n\nUniversity graduate in Shipping Logistics and Global Supply Chain are highly preferred;\n\nProficiency in Mandarin, English and Chinese;\nSelf-motivated, Reliable, Independent, Team work, Detail-minded and able to work under pressure;\n1 to 2 years working experience in operations and logistics;\n\nFresh graduate will be also considered;\nImmediately Available.\n\n*Interested parties, please send full resume with current & expected salary & date available in MS WORD FORMAT ONLY to email: \u00a0jobs@HKETERNITY. com \u00a0\u00a0\u00a0or fax to 3527 0634\n\nHotline: (852) 3542 5082\n\nFor more jobs, please visit our website: www.hketernity.com\n\nWe are welcome applicants resend resumes to us even you have applied jobs in our company before.\n\n(Personal data submitted are for recruitment purpose only.)\u00a0", "employment_types": ["Full Time", "Permanent"], "selling_points": ["Fashion apparel industry", "Double pay", "APAC market"], "locations": ["Not Specified"], "categories": ["Transportation & Logistics", "Others", "Fulfillment", "Shipping"], "post_time": "2022-01-11T11:59:29Z", "salary": {"currency": null, "max": null, "min": null, "period": "monthly", "term": null}, "salary_visible": false, "title_keywords": ["shipping clerk"], "responsibilities": ["shipping documents", "invoices", "other duties", "co-ordinate with", "contracts", "schedules", "operations"], "requirements": {"degrees": ["university graduate", "fresh graduate"], "majors": [], "languages": ["english", "chinese", "mandarin"], "language_level": ["proficiency"], "hard_skills": [], "soft_skills": ["detail-minded", "self-motivated", "independent", "reliable", "work under pressure"], "languages_combined": [{"language": "english", "language_level": ["proficiency"]}, {"language": "chinese", "language_level": ["proficiency"]}, {"language": "mandarin", "language_level": ["proficiency"]}]}, "experience_required": {"duration": ["1 to 2 years"], "field": ["logistics"]}}, {"job_id": "100003009046454", "location_code": "hk", "company": "Page Personnel", "job_title": "Warehouse Supervisor - Freight Forwarding Company", "description": "\u8077\u8cac\uff1a\n\n\u8ca0\u8cac\u5e97\u5167\u5009\u52d9\u904b\u4f5c\uff0c\u5305\u62ec\u6536\u8ca8\u3001\u9ede\u8ca8\u3001\u6574\u7406\u8ca8\u54c1\u3001\u4e0a\u67b6\u3001\u76e4\u9ede\u5eab\u5b58\u53ca\u8655\u7406\u5e97\u8216\u9593\u8ca8\u54c1\u8abf\u914d;\n\u7ba1\u7406\u5e97\u8216\u5009\u5eab\u3001\u66f4\u65b0\u7cfb\u7d71\u5167\u5b58\u8ca8\u8a18\u9304;\n\u6309\u5e97\u8216\u4e3b\u7ba1\u5b89\u6392\uff0c\u8655\u7406\u8207\u5e97\u8216\u5009\u5eab\u53ca\u8ca8\u54c1\u76f8\u95dc\u5de5\u4f5c\n\n\u8981\u6c42\uff1a\n\n\u7121\u9808\u7d93\u9a57\n\u826f\u597d\u6e9d\u901a\u6280\u5de7\uff0c\u61c2\u95b1\u8b80\u53ca\u66f8\u5beb\u4e2d\u6587\n\u5177\u5718\u968a\u5408\u4f5c\u7cbe\u795e\n\u9031\u4e00\u81f3\u9031\u4e94\u8f2a\u73ed\u5de5\u4f5c\uff0c\u6bcf\u5929\u5de5\u4f5c9\u5c0f\u6642 (\u5305\u62ec1\u5c0f\u6642\u4f11\u606f\u6642\u9593)\n\n\u5de5\u4f5c\u5730\u9ede\uff1a\n\n\u6d77\u6e2f\u57ce / \u5713\u65b9 / \u9285\u947c\u7063\u5d07\u5149\u767e\u8ca8\n\n\u6211\u5011\u63d0\u4f9b\u512a\u539a\u798f\u5229:\n\n12-16\u5929\u5e74\u5047\n\u751f\u65e5\u5047\u671f\n\u5168\u52e4\u734e\u91d1\n\u503c\u73ed\u6d25\u8cbc**\n\u91ab\u7642\u6d25\u8cbc\n\u5e74\u7d42\u914c\u60c5\u6027\u82b1\u7d05\n\u4ecb\u7d39\u4eba\u734e\u91d1\n\n** \u9069\u7528\u65bc\u5d07\u5149\u767e\u8ca8\u5206\u5e97\n\n\u6709\u610f\u61c9\u5fb5\u8005\uff0c\u8acb\u6309[via APPLY NOW] \u00a0\u50b3\u9001\u5b8c\u6574\u5c65\u6b77\u3001\u9810\u671f\u85aa\u91d1\u53ca\u53ef\u5230\u8077\u65e5\u671f\u3002\u61c9\u5fb5\u8005\u63d0\u4f9b\u7684\u500b\u4eba\u8cc7\u6599\u5c07\u88ab\u56b4\u683c\u4fdd\u5bc6\u53ca\u53ea\u7531 MARYLING ASIA PACIFIC GROUP LIMITED \u7528\u65bc\u62db\u8058\u7528\u9014\u3002\u4e0d\u6210\u529f\u7533\u8acb\u8005\u500b\u4eba\u8cc7\u6599\u5c07\u5728\u62db\u8058\u5b8c\u6210\u5f8c\u7acb\u5373\u92b7\u6bc0\u3002", "employment_types": ["Full Time", "Permanent"], "selling_points": ["Supervisory level, leading a team of 6-8", "Warehouse operation monitoring", "Medical and dental convered"], "locations": ["Not Specified"], "categories": ["Transportation & Logistics", "Freight Forwarding", "Fulfillment", "Inventory / Warehousing"], "post_time": "2022-01-13T11:19:53Z", "salary": {"currency": null, "max": null, "min": null, "period": "monthly", "term": null}, "salary_visible": false, "title_keywords": ["warehouse supervisor"], "responsibilities": [], "requirements": {"degrees": [], "majors": [], "languages": [], "language_level": [], "hard_skills": [], "soft_skills": [], "languages_combined": []}, "experience_required": {"duration": [], "field": []}}, {"job_id": "100003009041125", "location_code": "hk", "company": "Retail Technology (Hong Kong) Limited", "job_title": "Warehouse Supervisor", "description": "Your new company\nWe are working with an fashion apparel company who is looking for a Shipping Clerk with experience in handling import and export shipment for the APAC market.\n\nYour new role\n\nCommunicate with freight forwarding company on the import and export shipment arrangements\nHandle full set of I/E documents and declaration\nMonitor the logistics performance of the 3PL to ensure they are up to company standard\nTrace order delivery on-time and act as the key contact point for the designated market\n\n\nWhat you'll need to succeed\n\n3+ years of experience in shipping, import and export\nGood language skills\nImmediately available will be highly preferred\n\n\nWhat you need to do now\nIf you're interested in this role, click 'apply now' to forward an up-to-date copy of your CV, or call us now.\nIf this job isn't quite right for you but you are looking for a new position, please contact us for a confidential discussion on your career.", "employment_types": ["Full Time"], "selling_points": ["Warehouse and logistic planning, E-commerce/ O2O", "Proven hand-on frontline experience in warehousing", "Guarantee 13 months salary with performance bonus"], "locations": ["Kwai Fong"], "categories": ["Transportation & Logistics", "Fulfillment"], "post_time": "2022-01-12T03:28:55Z", "salary": {"currency": null, "max": null, "min": null, "period": "monthly", "term": null}, "salary_visible": false, "title_keywords": ["warehouse supervisor"], "responsibilities": ["communicate with", "shipping", "monitor", "import and export shipment", "logistics", "contact"], "requirements": {"degrees": [], "majors": [], "languages": [], "language_level": [], "hard_skills": ["import and export"], "soft_skills": ["interested in"], "languages_combined": []}, "experience_required": {"duration": ["3+ years"], "field": []}}, {"job_id": "100003009036889", "location_code": "hk", "company": "Durabasics LLC", "job_title": "Logistics Analyst", "description": "Excellent opportunity for warehouse experts to work for a leading Freight Forwarding comapny.\n\nClient Details\n\nOur client is one of the most reputable companies within the freight forwarding industry. With over decades of history, they have been delivering the best products and services to the world. With steady and rapid expansion in business in Hong Kong, they are actively looking for a Warehouse Supervisor to join their dynamic company.\n\nDescription\n\nSupervise the warehouse operation team for daily operation\nFormulate the operation procedure to increase the working efficiency and warehouse capacity\nSchedule couriers delivery to satisfy business needs\nWork closely with multiple parties for day-to-day cargo handling operation\nAssisting in ad-hoc duties as per assigned\n\nProfile\n\nDiploma or above\nMinimum 4-year experience in warehouse operation in 3PL, preferably with supervisory experience\nStrong interpersonal and communication skills\nOrganized and detail-oriented individual\nExcellent command in both English and Chinese\n\nJob Offer\n\nGuaranteed double pay\nMedical and Dental covered", "employment_types": ["Full Time", "Contract"], "selling_points": [], "locations": ["Not Specified"], "categories": ["Transportation & Logistics", "Fulfillment", "Inventory / Warehousing", "E-commerce", "Supply Chain"], "post_time": "2022-01-11T16:01:37Z", "salary": {"currency": null, "max": null, "min": null, "period": "monthly", "term": null}, "salary_visible": false, "title_keywords": ["logistics analyst"], "responsibilities": ["communication", "daily operation", "schedule", "ad-hoc duties"], "requirements": {"degrees": ["diploma or above"], "majors": [], "languages": ["english", "chinese"], "language_level": ["excellent"], "hard_skills": ["dynamic", "rapid"], "soft_skills": ["organized", "communication skills", "detail-oriented", "dynamic", "ad-hoc duties", "interpersonal"], "languages_combined": [{"language": "english", "language_level": ["excellent"]}, {"language": "chinese", "language_level": ["excellent"]}]}, "experience_required": {"duration": ["minimum 4-year"], "field": ["operation", "supervisory experience"]}}, {"job_id": "100003009038576", "location_code": "hk", "company": "HK Pick-Up Limited", "job_title": "Operations Manager (Warehouse Fulfilment)", "description": "The Job\n\nLead logistics team to complete all E-commerce daily fulfilment orders\nPlan and manage the allocation of manpower resources based on business needs to ensure efficient operations\nMonitor the availability and reliability of infrastructure and equipment to minimize downtime, and resolve problems/breakdowns immediately\nDevelop and enhance fulfilment strategies, policies and processes to optimize delivery capacity, enhance productivity and minimize costs\nCreate and review SOP and WI to meet high standard for logistics activities\nManage root cause analysis and establish corrective actions on service quality\nCoordinate with internal/external parties to assist daily operations\nSupport KPI, clerical duties, process optimization\nMaintain daily discipline and uphold a positive working mentality across the team\n\nThe Person\n\nMinimum 4 years of experience in logistics and warehouse operations, one of which must be in supervisory position, E-commerce fulfilment experience is preferable\nDemonstrate in-depth understanding of distribution centre, distribution and transportation\nDemonstrate strong appreciation of customer service requirements and commitment\nHolder of valid driving license 1, 2, Valid Hong Kong driving license\nFluent in both spoken and written English, Mandarin and Cantonese\nStrong command in common PC software such as MS Excel / Access / Word\nCandidate with less experience will be considered as Assistant Logistics Supervisor / Planner", "employment_types": ["Full Time"], "selling_points": ["Well-funded Logistic Tech Startup", "Lead warehouse fulfilment operations", "Cover multiple warehouse locations"], "locations": ["Hung Hom"], "categories": ["Transportation & Logistics", "Fulfillment", "Inventory / Warehousing"], "post_time": "2022-01-11T07:25:13Z", "salary": {"currency": null, "max": null, "min": null, "period": "monthly", "term": null}, "salary_visible": false, "title_keywords": ["operations manager"], "responsibilities": ["operations", "policies", "infrastructure", "monitor", "review", "analysis", "develop", "quality", "coordinate with", "external parties", "daily operations", "logistics", "maintain", "plan", "costs"], "requirements": {"degrees": [], "majors": [], "languages": ["cantonese", "english", "mandarin"], "language_level": ["fluent"], "hard_skills": ["planner", "e-commerce", "word", "ms excel", "pc"], "soft_skills": ["customer service"], "languages_combined": [{"language": "cantonese", "language_level": ["fluent"]}, {"language": "english", "language_level": ["fluent"]}, {"language": "mandarin", "language_level": ["fluent"]}]}, "experience_required": {"duration": ["minimum 4 years"], "field": ["supervisory", "logistics", "e-commerce"]}}, {"job_id": "100003009042475", "location_code": "hk", "company": "Intellect Direction Limited", "job_title": "Operations Officer", "description": "Highlights\n\nFull-time 40 hours per week\n\nCompetitive salary\n\nHave a major impact on company performance\n\nRemote position\n\nHealth insurance stipend\n\nPaid vacation\n\n90 Day Objectives\n\nBecome proficient with Durabasics supply chain processes.\n\nWork with Operations Senior Manager to facilitate consistent inventory practices (factory > consolidation > ocean freight > 3PL > Amazon).\n\nProvide feedback on processes and how they might be improved or changed.\n\n\n\n\n\nKey Performance Indicators\n\nMaintain inventory levels as set by the Operations Senior Manager for SKUs at our 3PL warehouse and at Amazon.\n\nEnsure Durabasics has 0 SKUs out of stock at Amazon.\n\nResponse times for actively managing the Supply Chain within 24 hours.\n\nAmazon Inventory Performance Index (IPI) - Greater than 475\n\nWhat\u2019s the Role\n\nAs the Logistics Analyst, you will have a daily impact on helping drive Durabasics\u2019 future growth and profitability. You will work closely with the Operations Senior Manager to ensure our product pipeline is always full so we can meet our annual goals. We are on the lookout for an enthusiastic individual who knows how to take direction but is also able to provide diagnostic feedback with respect to keeping the Supply Chain active and on track.\u00a0 We need a self-starter who is capable of working independently within the framework stipulated by the Operations Senior Manager.\n\n\n\n\nYou\u2019re an ideal fit for this role if you are a person who enjoys being organized, loves small business entrepreneurship, and finds success in the details.\u00a0 You also bring knowledge across multiple supply chain disciplines -- for example, import/export, ocean freight, trucking, warehousing, and demand forecasting.\n\n\n\n\n\nWhat You\u2019ll Do\n\nWork with the Operations Senior Manager to:\n\nReview inventory levels of all SKUs to determine replenishment plan.\n\nMonitor sales trends to assist in determining the seasonality of products.\n\nWork with 3PL to monitor inventory levels and transfer stock to Amazon.\n\nMaintain paperwork and details of transfers to Amazon.\n\nReview PO\u2019s and invoices for accuracy and reconciling.\n\nPartner with factories to ensure timely delivery and the highest quality products to our exact specifications.\n\nReview charges from third-party vendors to ensure we are receiving the best rates and opportunities.\n\nOther duties as assigned by the Operations Senior Manager.\n\n\n\n\n\nWhat Will Make Someone Successful\n\nExperience and knowledge of supply chain and inventory management.\n\nCritical thinking and problem-solving abilities using numbers (e.g. modeling out in Excel different options, comparing costs, identifying the qualitative pros/cons of each, identifying our business need and level of importance, and making a recommendation based on data)\n\nAttention to detail to ensure all data is accurate and correct -- this position requires consistent accuracy.\n\nVery strong organizational skills to manage multiple duties at the same time.\n\nStrong understanding of warehousing, inventory, and records maintenance.\n\nUnderstanding of China logistics operations and manufacturing processes.\n\nYou are thorough and detail-oriented. Please email me at polly at\u00a0durabasics . com with your resume and cover letter. Use the word \u2018jellyfish\u2019 along with the position you\u2019re applying for in the email subject line to be considered for the role.\n\nStrong personal drive and ability to work independently the majority of the time in a fast-paced, urgent environment.\n\n\n\n\n\nWhat You\u2019ll Bring\n\n3+ years experience in logistics, warehousing, or transportation operations\n\n2+ years of experience in inventory management systems\n\n1+ years of experience in remote work\n\nFluent in English \u2013 you will be communicating regularly with both native and non-native English speakers\n\nHighly proficient in Microsoft Office and Google Suite products (specifical spreadsheets)\n\n\n\n\n\nNice to Have\u2019s\n\nFluency in Chinese (Mandarin) a plus - you will be communicating with Chinese factories and forwarders often\n\nPrevious Amazon experience\n\nExperience with procurement, incoterm and negotiations", "employment_types": ["Full Time", "Permanent"], "selling_points": ["Form 5/DSE, 1-3 years\u2019 experience in Sea Shipment", "Customer oriented, willing to learn", "Cross functional , absorbing opportunity"], "locations": ["Tsuen Wan Area"], "categories": ["Transportation & Logistics", "Freight Forwarding", "Fulfillment", "Shipping"], "post_time": "2022-01-12T07:39:23Z", "salary": {"currency": null, "max": null, "min": null, "period": "monthly", "term": null}, "salary_visible": false, "title_keywords": ["operations officer"], "responsibilities": ["data", "operations", "inventory", "quality", "inventory management", "maintain", "plan", "costs", "invoices", "other duties", "monitor", "logistics", "forecasting", "warehousing", "review", "specifications", "maintenance", "systems", "replenishment", "communicating with", "insurance"], "requirements": {"degrees": [], "majors": [], "languages": ["english", "chinese", "mandarin"], "language_level": ["fluency", "native", "fluent"], "hard_skills": ["small", "excel", "plus", "amazon", "maintenance", "microsoft office", "problem-solving", "nice", "word", "make"], "soft_skills": ["organized", "organizational skills", "independently", "work independently", "capable", "exact", "accurate", "timely", "problem-solving", "detail-oriented", "thorough", "attention to detail", "enthusiastic", "active", "ideal"], "languages_combined": [{"language": "english", "language_level": ["fluent", "native"]}, {"language": "chinese", "language_level": ["fluency"]}, {"language": "mandarin", "language_level": ["fluency"]}]}, "experience_required": {"duration": ["1+ years", "2+ years", "3+ years"], "field": ["inventory management systems", "supply chain", "inventory management", "logistics", "procurement"]}}, {"job_id": "100003009039113", "location_code": "hk", "company": "GOGO TECH LTD", "job_title": "Logistics Solutions Manager", "description": "\u5de5\u4f5c\u5167\u5bb9\u00a0Job descriptions :\n\n\u8ca0\u8cac\u57f7\u8ca8\u3001\u5305\u88dd\u00a0To pick & pack goods for daily orders\n\u5b89\u6392\u5165\u5009\u8ca8\u54c1\u5b58\u653e\u5230\u8ca8\u67b6\u00a0To arrange incoming goods on racks / shelves\n\u5b9a\u671f\u76e4\u9ede\u8ca8\u5009\u5b58\u8ca8\u00a0To attend regular stock-take\n\u6574\u7406\u53ca\u6e05\u6f54\u8ca8\u5009\u885b\u751f\u00a0To clean up warehouse\n\n\u5165\u8077\u689d\u4ef6\u00a0Requirements :\n\n\u4e2d\u4e94\u6216\u4ee5\u4e0a\u7a0b\u5ea6\u00a0F. 5 or above\n\u4e8c\u81f3\u4e09\u5e74\u5de5\u4f5c\u7d93\u9a57\u00a02-3 years working experience\n\u80fd\u95b1\u8b80\u7c21\u55ae\u82f1\u8a9e\u00a0Able to read simple English\n\n\u5f85\u9047\u00a0Offer :\n\n\u85aa\u512a\u00a015-17K Attractive Salary : 15-17K\n5\u5929\u534a\u5de5\u4f5c\u00a05\u00a0 1/2 day work per week\n\u9280\u884c\u5047\u671f\u00a0Banking holidays\n\u91ab\u7642\u4fdd\u96aa\u00a0Medical insurance coverage", "employment_types": ["Full Time", "Permanent"], "selling_points": ["Start-Up Work Environment", "Flexible Working Hours", "Good Incentive Schemes"], "locations": ["Kwun Tong"], "categories": ["Transportation & Logistics", "Fulfillment", "Shipping", "Sales, CS & Business Devpt", "Sales - Sales Management"], "post_time": "2022-01-11T08:43:54Z", "salary": {"currency": null, "max": null, "min": null, "period": "monthly", "term": null}, "salary_visible": false, "title_keywords": ["manager", "logistics"], "responsibilities": ["daily orders"], "requirements": {"degrees": [], "majors": [], "languages": ["english"], "language_level": [], "hard_skills": ["simple"], "soft_skills": [], "languages_combined": [{"language": "english", "language_level": []}]}, "experience_required": {"duration": ["2-3 years"], "field": []}}, {"job_id": "100003009044578", "location_code": "hk", "company": "Honour Lane Shipping Ltd", "job_title": "Pricing Coordinator / Senior Pricing Coordinator - Marketing", "description": "Pickupp is hiring an Operations Manager\u00a0(Warehouse Fulfilment) to build and grow our logistics tech business in Hong Kong. This role will focus on the building and operating of our warehouse function and expand our warehousing service complimenting our last mile delivery services.\n[Candidates with the right fit but less experience may be considered for the Assistant Manager / Senior Operations Associate role]\n\nThe right candidate should be comfortable with an \u201call hands on deck\u201d and fast paced startup environment. If you have the passion, innovative and collaborative spirit to build this exciting business, come join us!\n\nAbout The Role:\n\nFulfillment Warehousing Operations: Own and optimize all angles in the fulfillment warehousing operations including inbound, outbound, pick and pack, inventory control etc.\nWarehouse Management System Development: Work closely with our engineering team to build, optimize and iterate our in house warehouse management system.\u00a0\nFront Line Operator Management: Lead a team of front line operator to fulfill all warehousing operations needs.\nWarehouse Network Expansion: Build and expand our warehouse network including location, manpower and resources planning, budget control, streamline operations flow etc.\nWarehousing Consulting: Collaborate with the Sales team to develop, optimize, and automate warehousing processes to increase operational efficiency.\nData Analysis: Utilize data from our systems to better understand our general warehouse operations and inventory trend and deeply automated processes to improve efficiency.\nBe Agile: Expect a rapid changing environment. Prepare to adapt and hustle in a dynamic environment.\n\nRequirements:\n\nBachelor's degree or above in Business, Supply Chain or relevant discipline.\n3+ years of relevant experience. Experience in working with or developing a WMS is preferred.\nProven experience in project management, driving projects from zero to one to deliver results.\nDemonstrated record of positively owning and leading initiatives and projects.\nStrong communications in collaborating with internal and external parties.\nStrong analytical thinking and data-driven decision making mentality; knowledge in SQL is a strong plus.\nFluent in written and spoken Chinese & English is required.\nTop-notch problem solving and hustle skills, plus ability to adapt to thrive in a dynamic work environment.\u00a0\n\nAbout Pickupp:\n\nPickupp is redefining logistics in Asia. We are Asia\u2019s leading logistics technology delivery platform that is dedicated to supporting 10,000+ businesses with same day and next day deliveries. We are headquartered in Hong Kong with offices in Taiwan, Singapore and Malaysia.\u00a0\n\nWe connect businesses to a fleet of independent delivery agents including walkers, scooters, vans, trucks to deliver anything, anytime, anywhere at a fraction of the cost. Our team is entrepreneurial and passionate, with vast experiences including fast growing tech giants (Uber, Deliveroo, etc). Our investors in recent rounds of fundraising include Alibaba, Cyberport, SparkLabs, Swire Properties New Ventures, and more.\n\nIn addition to our core business of last mile delivery, we also recently launched Shop on Pickupp, an e-commerce platform. We provide a seamless one-stop solution for merchants to build e-shop, process payments, manage orders and deliveries. Shoppers can enjoy a wide range of lifestyle and F&B products delivered to their doors at their desired time slots.", "employment_types": ["Full Time", "Permanent"], "selling_points": ["F7 or above & 2 yrs experience in sea freight area", "Familiar with Transpacific trade", "5 day work & Double Pay & Discretionary Bonus"], "locations": ["Tsuen Wan Area"], "categories": ["Transportation & Logistics", "Freight Forwarding", "Fulfillment", "Supply Chain"], "post_time": "2022-01-13T04:38:39Z", "salary": {"currency": null, "max": null, "min": null, "period": "monthly", "term": null}, "salary_visible": false, "title_keywords": ["coordinator"], "responsibilities": ["collaborate with", "consulting", "data", "operations", "fulfillment", "inventory", "internal and external parties", "wms", "budget control", "developing", "develop", "warehouse management system", "logistics", "warehousing", "management", "cost", "data analysis", "inventory control", "systems", "lead a team", "project management", "sales team", "warehouse operations", "e-commerce platform", "planning"], "requirements": {"degrees": ["degree or above", "bachelor"], "majors": ["business"], "languages": ["english", "chinese"], "language_level": ["fluent"], "hard_skills": ["plus", "agile", "e-commerce", "analysis", "sql", "project management", "problem solving", "dynamic", "rapid", "focus"], "soft_skills": ["passionate", "dynamic environment", "independent", "agile", "collaborative", "problem solving", "project management", "hands on", "dynamic", "focus", "innovative", "vast", "driven", "decision making"], "languages_combined": [{"language": "english", "language_level": ["fluent"]}, {"language": "chinese", "language_level": ["fluent"]}]}, "experience_required": {"duration": ["3+ years"], "field": ["tech", "developing", "project management", "relevant experience", "team"]}}, {"job_id": "100003009042595", "location_code": "hk", "company": "Page Personnel", "job_title": "Product Manager - Ocean Freight", "description": "Our client is looking for a suitable Operations Officer.\u00a0\n\nResponsibilities\n\nData Entry, filing, scanning & preparing full set of shipping documents\nInvoicing to customers in compliance with the company guideline and ruel\nCheck and monitor the cargo status\nRequirements\n\n1-3 years related working experience in sea freight forwarding industry\nHave consol. shipment experience is an advantage\nGood communication and interpersonal skills\nCustomer-oriented, self-motivated, able to work under pressure & willing to work overtime when required\nExcellent service manner, patience and problem-solving skills\nGood command of spoken and written English, Mandarin & Cantonese\nFamiliar in MS Office Applications\nWilling to learn and eager for improvement", "employment_types": ["Full Time", "Permanent"], "selling_points": ["Global Procurement Team", "Trans-Pacific Trade", "Competitive Package"], "locations": ["Not Specified"], "categories": ["Transportation & Logistics", "Others", "Freight Forwarding", "Fulfillment"], "post_time": "2022-01-12T08:06:39Z", "salary": {"currency": null, "max": null, "min": null, "period": "monthly", "term": null}, "salary_visible": false, "title_keywords": ["product manager"], "responsibilities": ["scanning", "shipping documents", "data entry", "compliance", "monitor", "invoicing"], "requirements": {"degrees": [], "majors": [], "languages": ["cantonese", "english", "mandarin"], "language_level": ["good command"], "hard_skills": ["problem-solving skills", "ms office"], "soft_skills": ["work overtime", "self-motivated", "willing to learn", "customer-oriented", "communication and interpersonal skills", "patience", "problem-solving skills", "work under pressure"], "languages_combined": [{"language": "cantonese", "language_level": ["good command"]}, {"language": "english", "language_level": ["good command"]}, {"language": "mandarin", "language_level": ["good command"]}]}, "experience_required": {"duration": ["1-3 years"], "field": ["related"]}}, {"job_id": "100003009041958", "location_code": "hk", "company": "VST Computers (HK) Ltd", "job_title": "\u5009\u52d9\u54e1", "description": "For direct application, please click\u00a0here\u00a0\n\n\n\nWhat You Will Be Delivering\n\nAssist General Manager to achieve company sales and profit targets\nPrepare business proposals & reports and update sales kits\nProvide corporate account servicing to company corporate accounts\nAssist tender submission, RFQ, RFI & RFP response\nSOP writing and KPI set for SME & Corporate client\nExplore new marketing collaboration and new business opportunities\nPerform existing corporate client retention and increase existing corporate customer growth\nResponsible for project\u2019s P&L, provide regular performance reports and analytical reports to clients and management team\nMonitor logistics process, ensure timely and accuracy of orders fulfillment to achieve KPIs of the Logistics Service Include , Delivery, Warehouse & Vehicle Rental Service\nCoordinate with customers and internal teams to ensure smooth day to day operation\nHandle any ad-hoc assignments when assigned Requirements\n\nWho You Are\n\nDegree holder in Logistics / Supply Chain Management or related disciplines\nMinimum 6 years\u2019 of experience in parcel delivery, road transportation & warehouse operations; experience in 3PL industry /e-commerce fulfillment / subcontractor management is an advantage\nAble to make sound judgments and decisions, can work in a fast-paced environment and handle complicated issues with flexibility\nDemonstrate strong leaderships with self-motivated, problem solving abilities and a \u201chands on\u201d mentality\nExcellent communication and interpersonal skills\nGood command of both written & spoken English and Chinese, including Mandarin\nCandidate with less experience will be considered as Assistant Manager\u00a0\n\nPerks and Benefits\n\nBirthday Leave\nMedical and Dental insurance\nStart-up Work Environment\u00a0\nFlexible Work Arrangement\nFree flow of snacks and soft drinks\u00a0\nGOGOX New Joiner Kit", "employment_types": ["Full Time"], "selling_points": [], "locations": ["Kowloon Bay"], "categories": ["Transportation & Logistics", "Fulfillment", "Inventory / Warehousing", "Supply Chain"], "post_time": "2022-01-12T04:50:17Z", "salary": {"currency": null, "max": null, "min": null, "period": "monthly", "term": null}, "salary_visible": false, "title_keywords": ["\u5009\u52d9\u54e1"], "responsibilities": ["management team", "performance reports", "ad-hoc assignments", "business opportunities", "fulfillment", "coordinate with", "teams", "p&l", "reports", "logistics", "tender", "sme", "kpis", "monitor logistics"], "requirements": {"degrees": ["degree holder"], "majors": ["related disciplines"], "languages": ["english", "chinese", "mandarin"], "language_level": ["good command"], "hard_skills": ["problem solving", "make", "e-commerce"], "soft_skills": ["self-motivated", "fast-paced environment", "problem solving", "hands on", "communication and interpersonal skills"], "languages_combined": [{"language": "english", "language_level": ["good command"]}, {"language": "chinese", "language_level": ["good command"]}, {"language": "mandarin", "language_level": ["good command"]}]}, "experience_required": {"duration": ["minimum 6 years"], "field": ["management", "e-commerce"]}}, {"job_id": "100003009041161", "location_code": "hk", "company": "Tigers (HK) Co. Limited", "job_title": "Warehouse Operator", "description": "\u8077\u8cac :\n\n- \u8ca0\u8cac\u76e3\u7ba1\u5009\u5eab\u8ca8\u7269\u5b58\u5009\u3001\u51fa\u5009\u670d\u52d9\u6d41\u7a0b\n\n- \u8655\u7406\u5009\u5eab\u7684\u65e5\u5e38\u696d\u52d9\n\n- \u5354\u52a9\u5206\u914d\u5009\u5eab\u4eba\u54e1\u5de5\u4f5c\n\n- \u76e3\u7763\u5916\u5305\u88dd\u5de5\u5e8f\n\n\u8981\u6c42\u8cc7\u6b77 :\n\n- \u4e2d\u5b78/\u5c08\u4e0a\u5b78\u6b77\uff0c\u6709\u5009\u5eab\u53ca\u76e3\u7763\u5305\u88dd\u7d93\u9a57\u512a\u5148\n\n- \u826f\u597d\u7cb5\u8a9e\u512a\u5148; \u4e00\u822c\u666e\u901a\u8a71; \u4e00\u822c\u82f1\u8a9e; \u61c2\u8b80\u5beb\u4e2d\u6587\u82f1\u6587\n\n- \u5177\u6709\u57fa\u672c\u96fb\u8166\u64cd\u4f5c\u77e5\u8b58\n\n\u6709\u610f\u6c42\u8077\u8005\u53ef\u96fb\u90f5 (Apply Now) \u5c65\u6b77\u8868\u7d66\u5eb7\u548c\u91ab\u85e5\u79d1\u6280\u6709\u9650\u516c\u53f8\u3002\u5982\u8981\u7d22\u53d6\u6536\u96c6\u500b\u4eba\u8cc7\u6599\u8072\u660e\uff0c\u8acb\u8207\u674e\u5c0f\u59d0 (Email) \u806f\u7d61\u3002", "employment_types": ["Full Time", "Permanent"], "selling_points": [], "locations": ["Tsing Yi"], "categories": ["Transportation & Logistics", "Fulfillment", "Inventory / Warehousing", "Supply Chain"], "post_time": "2022-01-12T04:01:58Z", "salary": {"currency": null, "max": null, "min": null, "period": null, "term": null}, "salary_visible": false, "title_keywords": ["warehouse operator"], "responsibilities": [], "requirements": {"degrees": [], "majors": [], "languages": [], "language_level": [], "hard_skills": [], "soft_skills": [], "languages_combined": []}, "experience_required": {"duration": [], "field": []}}, {"job_id": "100003009036062", "location_code": "hk", "company": "Ambition", "job_title": "Supply Chain Planner - Consumer / 22k", "description": "Responsibilities:\n\nConsolidate and data analysis the market information of shipping line\nRate quotation\nMaintenance of the company pricing system and database\nCommunicate with overseas agent and offices for market news\nMonitoring SE Asia offices volume and pricing strategy\nCoordinate with trade and local offices for problem solving\n\nRequirements:\n\nF.7/ DSE or above\nAt least 2-year experience in sea freight forwarding field\nFamiliar with Transpacific trade\nGood PC knowledge, English and Mandarin\nAble to work under pressure and overtime\nTeam Spirit is required\nImmediate available is preferred\n\nInterested Parties please submit your resume, present and expected salary at \"Apply Now\" at JobsDB or\u00a0\u00a0hlshrhk @ hlsholding.com\n\nHuman Resources and Administration Department\nHonour Lane Shipping Limited\nRoom 1501, 15/F,, Tower 2, Nina Tower, 8 Yeung Uk Road, Tsuen Wan, N.T., Hong Kong.\nAttention: HR Department\nWebsite: www.hlsholding.com\n(Personal data collected will be used for recruitment purpose only)\u00a0", "employment_types": ["Full Time", "Permanent"], "selling_points": ["Global leading appliance manufacturer", "Regional planning opportunity", "Work life balance culture"], "locations": ["Not Specified"], "categories": ["Transportation & Logistics", "Fulfillment", "Supply Chain"], "post_time": "2022-01-10T09:13:19Z", "salary": {"currency": "HKD", "max": 24999, "min": 17000, "period": "monthly", "term": null}, "salary_visible": true, "title_keywords": ["supply chain planner"], "responsibilities": ["communicate with", "shipping", "market information", "maintenance", "quotation", "monitoring", "coordinate with", "data analysis", "database"], "requirements": {"degrees": ["dse"], "majors": [], "languages": ["english", "mandarin"], "language_level": ["good"], "hard_skills": ["pc knowledge"], "soft_skills": ["team spirit", "work under pressure"], "languages_combined": [{"language": "english", "language_level": ["good"]}, {"language": "mandarin", "language_level": ["good"]}]}, "experience_required": {"duration": ["at least 2-year"], "field": []}}, {"job_id": "100003009037789", "location_code": "hk", "company": "Aacurapid (Hong Kong) Ltd", "job_title": "Logistics Officer (Global 3PL, Circa 20-28K/ month, 5-Day)", "description": "Excellent opportunity for Ocean Freight experts to work for a Global Freight Forwarder.\n\nClient Details\n\nOur client is one of the most reputable companies within the Freight Forwarding industry. With over decades of history, they have been delivering the best products and services to the world. With steady and rapid expansion in business in Hong Kong, they are actively looking for a Product Manager to join their dynamic company.\n\nDescription\n\nConduct freight procurement, price negotiation and relationship building with shipping lines\nWork closely with Trade Lead to develop ocean product for trans-pacific trades\nAnalyze trade performance and setup plans for development\nReview the performance of key shipping lines to ensure identify service level improvement area\nAssist in ad-hoc duties as per assigned\n\nProfile\n\n8 years of experience in Tender/Ocean Freight Management in Freight Forwarding Industry\nKnowledge in Trans-Pacific Trades is a must\nStrong analytical skills with numerical sense\nOrganized and detail-oriented individual\nExcellent command in both English and Chinese\n\nJob Offer\n\nGlobal role\nCompetitive pay\n5-day work", "employment_types": ["Full Time", "Permanent"], "selling_points": ["Warehouse / Logistics Operation/ Order Fulfilment", "Logistics System Enhancement", "Global 3PL, Circa 20-28K/ month, 5-Day"], "locations": ["Not Specified"], "categories": ["Transportation & Logistics", "Fulfillment", "Inventory / Warehousing", "Shipping"], "post_time": "2022-01-11T03:55:07Z", "salary": {"currency": null, "max": null, "min": null, "period": "monthly", "term": null}, "salary_visible": false, "title_keywords": ["logistics officer"], "responsibilities": ["price negotiation", "shipping", "management", "review", "develop", "tender", "ad-hoc duties", "plans", "setup"], "requirements": {"degrees": [], "majors": [], "languages": ["english", "chinese"], "language_level": ["excellent"], "hard_skills": ["dynamic", "analytical skills", "rapid"], "soft_skills": ["organized", "negotiation", "analytical skills", "detail-oriented", "dynamic", "ad-hoc duties"], "languages_combined": [{"language": "english", "language_level": ["excellent"]}, {"language": "chinese", "language_level": ["excellent"]}]}, "experience_required": {"duration": ["8 years"], "field": ["management"]}}, {"job_id": "100003009041116", "location_code": "hk", "company": "Hi-Speed Supply Chain Limited", "job_title": "Logistics Coordinator / Assistant / Officer", "description": "Tigers is a global logistics and e-Commerce company that specializes in bespoke supply chain solutions, e-fulfilment and transportation business. The core of Tigers\u2019 culture centers around freedom, responsibility, performance and people development. The combination of Tigers' logistics expertise, global network and client centric work ethic, provides a truly unique customer experience.\n\n\u00a0We are currently looking for the Warehouse Operator to be based in our Tsing Yi logistics facility.\n\n\u00a0Warehouse Operator\n\nThe incumbent is responsible for routine warehouse operations such as picking and packing and the following duties:\n\nHandle daily order processing, stocks preparation, inbound and outbound shipment\nManage inspection, shipment handling and packaging\nManual labor work and clerical support are required\n\n\u00a0Job requirements:\n\nForm 5 graduate\n1 to 2 years\u2019 relevant experience in the logistics field\nFamiliar with MS Outlook, Word and Excel\nHardworking, responsible and self-motivated\nWilling to work overtime\n\nInterested parties please send full resume with availability and expected salary via email.\n\nPersonal data collected would be used for recruitment purpose only.\u00a0", "employment_types": ["Full Time"], "selling_points": ["Perform clerical support", "Daily customer services support", "Data and information collection and entry"], "locations": ["Fanling"], "categories": ["Sales, CS & Business Devpt", "Customer Service - Supervisor / Officer", "Transportation & Logistics", "Fulfillment", "Inventory / Warehousing"], "post_time": "2022-01-12T03:28:15Z", "salary": {"currency": null, "max": null, "min": null, "period": "monthly", "term": null}, "salary_visible": false, "title_keywords": ["officer", "logistics coordinator", "assistant"], "responsibilities": ["clerical support", "inspection", "logistics", "order processing", "warehouse operations", "shipment handling"], "requirements": {"degrees": ["form 5"], "majors": [], "languages": [], "language_level": [], "hard_skills": ["excel", "e-commerce", "word", "outlook", "order processing"], "soft_skills": ["self-motivated", "work overtime", "responsible", "unique", "work ethic", "hardworking"], "languages_combined": []}, "experience_required": {"duration": ["1 to 2 years"], "field": ["logistics", "relevant experience"]}}, {"job_id": "100003009034391", "location_code": "hk", "company": "Times Express Limited", "job_title": "E-commerce Assistant / Senior Assistant / Assistant Supervisor (Warehouse Operations)", "description": "My client is a global leading consumer appliances manufacturer. With more than 7000 employees, they are a brand of quality. Looking to reinforce their regional supply planning process, they are now in search of a Supply Chain Planner.\n\nYou will support the supply planning and order replenishment process within the APAC region. You will collaborate with suppliers, factories and logistics team to ensure healthy inventory. As a Supply Chain Planner, your responsibilities will include:\n\nSupport the order replenishment process within the APAC region in response to forecast\nHandle the bonded warehouse and u-turn process to ensure health inventory movement\nCollaborate with manufacturers / suppliers to ensure on time production schedule\nCoordinate with logistics team to ensure smooth operation\nMonitor order status and update SAP system accordingly\nMonitor KPI report and trouble shoot any shortage, logistics changes or emergencies\n\nTo qualify, one must possess:\n\nDegree holder with at least 2 years order replenishment and production planning experience\nExperience working / coordinating with manufacturer or factory\nProficient with Excel (Pivot Table, Vlookup) and SAP system\nIndependent, energetic and good communication skills\nGood command in both written and spoken Chinese and English is a MUST\n\nContact Anson Chan on (852) 3103 4334 or email anson.chan@ambition.com.hk\n\nAPPLY NOW by clicking the button below quoting reference number AC 253431.\n\nwww.ambition.com.hk\n\nData provided is for recruitment purposes only.\n\nIf this job isn't quite right for you, but you know someone who would be great at this role, why not take advantage of our referral scheme? We offer HKD1000 in Apple gift cards for every referred candidate who we place in a role. Terms & Conditions Apply. https://www.ambition.com.hk/refer-a-friend", "employment_types": ["Full Time"], "selling_points": ["Fast Growing E-commerce Field", "Cooperate with 100+ Luxury and Wrold-famous Brands", "Energetic Team with Good Career Prospect"], "locations": ["Kwai Fong"], "categories": ["Transportation & Logistics", "Fulfillment", "Inventory / Warehousing", "E-commerce", "Supply Chain"], "post_time": "2022-01-10T03:17:47Z", "salary": {"currency": null, "max": null, "min": null, "period": "monthly", "term": null}, "salary_visible": false, "title_keywords": ["operations", "assistant supervisor", "assistant"], "responsibilities": ["collaborate with", "data", "inventory", "planning process", "quality", "replenishment", "coordinate with", "monitor", "production planning", "communication", "logistics", "schedule", "forecast", "contact", "recruitment", "report", "planning"], "requirements": {"degrees": ["degree holder"], "majors": [], "languages": ["english", "chinese"], "language_level": ["good command"], "hard_skills": ["supply planning", "excel", "planner", "sap", "pivot table", "scheme", "vlookup"], "soft_skills": ["communication skills", "energetic", "independent", "smooth"], "languages_combined": [{"language": "english", "language_level": ["good command"]}, {"language": "chinese", "language_level": ["good command"]}]}, "experience_required": {"duration": ["at least 2 years"], "field": ["planning"]}}, {"job_id": "100003009037343", "location_code": "hk", "company": "Hoper Limited", "job_title": "Associate Logistics/ Supply Chain Director (Multinational company)", "description": "Responsibilities\n\nManage warehouse operation, inbound and outbound shipments\nSupport orders fulfilment and enquiries for customers\nParticipate in designing/implementing operations policy and procedures to enhance the effectiveness\nParticipate in Logistics System Enhancement\n\nRequirements\n\nDegree or above in Logistics / Supply Chain Management or related disciplines with at least 3 years 3PL exposure\nWith working experience in Electronic Products / F&B / Fashion warehouse is definitely an advantage\nExperience in SAP system is a plus", "employment_types": ["Full Time", "Permanent"], "selling_points": ["5 days work week/ Double pay/ Attractive bonus", "Logistics/ Supply Chain/ e-commerce/ Retail", "3PL management/ Customer Service/ Fulfillment"], "locations": ["Not Specified"], "categories": ["Sales, CS & Business Devpt", "Customer Service - Manager", "Transportation & Logistics", "Fulfillment", "Supply Chain"], "post_time": "2022-01-11T02:34:27Z", "salary": {"currency": null, "max": null, "min": null, "period": "monthly", "term": null}, "salary_visible": false, "title_keywords": ["associate", "logistics", "director"], "responsibilities": ["operations", "logistics", "procedures", "designing"], "requirements": {"degrees": ["degree or above"], "majors": ["related disciplines"], "languages": [], "language_level": [], "hard_skills": ["plus", "sap"], "soft_skills": [], "languages_combined": []}, "experience_required": {"duration": [], "field": ["f&b"]}}, {"job_id": "100003009037058", "location_code": "hk", "company": "China Mobile Hong Kong \u4e2d\u570b\u79fb\u52d5\u9999\u6e2f", "job_title": "Procurement Manager", "description": "Job Description\u5de5\u4f5c\u5167\u5bb9\uff1a\n\nResponsible for customer-related issues \u8655\u7406\u8207\u5ba2\u6236\u76f8\u95dc\u4e8b\u5b9c\uff1b\nPerform clerical support such as data collection and data entry \u8ca0\u8cac\u65e5\u5e38\u6587\u66f8\u5de5\u4f5c\uff0c\u5305\u62ec\u4e2d\u3001\u82f1\u6587\u96fb\u8166\u8cc7\u6599\u8f38\u5165\u548c\u5b58\u6a94\uff1b\nRespond calls to coordinate daily picking and delivery orders\u00a0\u63a5\u807d\u96fb\u8a71\u53ca\u8ddf\u55ae\u5165\u55ae\uff1b\nMonitor staff\u2018s attendance\u6838\u5c0d\u54e1\u5de5\u51fa\u52e4\u8cc7\u6599\uff1b\nPrepare reports\u7de8\u5236\u5831\u544a\uff1b\nAssist in other ad hoc projects as assigned \u8655\u7406\u7279\u6d3e\u5de5\u4f5c\u7b49\uff1b\n\nRequirement\u8981\u6c42\uff1a\n\nForm 5 or above \u4e2d\u4e94\u6216\u4ee5\u4e0a\u7a0b\u5ea6\nProficiency in both spoken and written English and Chinese\u826f\u597d\u7cb5\u8a9e; \u826f\u597d\u82f1\u8a9e\uff1b\u61c2\u8b80\u5beb\u4e2d\u6587\uff1b\u61c2\u8b80\u5beb\u82f1\u6587\uff1b\nFamiliar with MS Office applications including Word, PowerPoint & Excel\u61c2\u96fb\u8166\u6587\u66f8\u8655\u7406\uff1b\u61c2\u5009\u9821/\u901f\u6210\uff1b\u8f38\u5165\u6cd5\uff1b\u719f\u6089\u96fb\u8166\u64cd\u4f5c\u77e5\u8b58\uff1b\n\n\nApplicants may be considered for\u00a0other positions\u00a0if matching the requirements of our other openings.\n\n\nWe will offer a competitive salary to suitable candidates. Please apply with full resume by mail to\u00a0Human Resources Department, Hi-Speed Supply Chain Limited, 2/F Smile Centre,\n10-12 On Chuen Street, Fanling\u00a0 or by clicking \"Apply Now.\"\n\nWe will use your data provided by job applicants for recruitment purposes only.\n\n\n", "employment_types": ["Full Time", "Permanent"], "selling_points": ["Network Procurement", "Rationalize procurement needs", "Minimum 8 years\u2019 relevant experience"], "locations": ["Kwai Hing"], "categories": ["Transportation & Logistics", "Fulfillment", "Merchandising & Purchasing", "Electronics", "Procurement / Purchasing / Sourcing"], "post_time": "2022-01-11T01:34:06Z", "salary": {"currency": null, "max": null, "min": null, "period": null, "term": null}, "salary_visible": false, "title_keywords": ["manager"], "responsibilities": ["data entry", "monitor", "clerical support", "coordinate", "ad hoc projects", "data collection"], "requirements": {"degrees": ["form 5 or above"], "majors": [], "languages": ["english"], "language_level": ["proficiency"], "hard_skills": ["word", "powerpoint", "ms office"], "soft_skills": [], "languages_combined": [{"language": "english", "language_level": ["proficiency"]}]}, "experience_required": {"duration": [], "field": []}}, {"job_id": "100003009034399", "location_code": "hk", "company": "Times Express Limited", "job_title": "Supervisor Trainee (E-commerce Warehouse Operations)", "description": "\u4e3b\u8981\u8077\u8cac :\n\n\u8ca0\u8cac\u9032\u884c\u6536\u8ca8, \u7406\u8ca8, \u5206\u8ca8, \u5305\u88dd , \u76e4\u9ede\u53ca\u7279\u5225\u6307\u6d3e\u7b49\u5de5\u4f5c\n\u8ca0\u8cac\u5009\u5eab\u7684\u65e5\u5e38\u4e8b\u52d9\n\u8ca0\u8cac\u7dad\u6301\u5009\u5eab\u7684\u6574\u9f4a\u6e05\u6f54\u72c0\u614b\n\u7dad\u8b77\u5009\u5eab\u5167\u7528\u5177, \u4f8b\u5982:\u5527\u8eca,\u00a0 \u93df\u8eca\n\u5de5\u4f5c\u6642\u9593 9 \u6642\u81f37\u6642\n\n\u6559\u80b2\u53ca\u7d93\u9a57\u8981\u6c42 :\n\n\u4e2d\u5b78\u7a0b\u5ea6\n\u4e00\u5e74\u6216\u4ee5\u4e0a\u5009\u52d9\u5de5\u4f5c\u7d93\u9a57\uff0c\u6709\u76f8\u95dc\u96fb\u5b50\u5009\u8005\u512a\u5148\n\u61c2\u96fb\u8166\u64cd\u4f5c\u8005\u512a\u5148;\n\u826f\u597d\u7cb5\u8a9e,\u61c2\u8b80\u5beb\u4e2d\u6587; \u61c2\u95b1\u8b80\u82f1\u6587\n\u4e3b\u52d5\u7a4d\u6975, \u7368\u7acb\u53ca\u6709\u8cac\u4efb\u611f\u548c\u826f\u597d\u7684\u5718\u968a\u5de5\u4f5c\n\u7acb\u5373\u8005\u512a\u5148\u8003\u616e\n\n\u5de5\u4f5c\u5730\u5340:\u4e5d\u9f8d\u7063\n\n\u6bcf\u5468\u4e94\u5929\u5de5\u4f5c, \u653e\u516c\u773e\u5047\u671f, \u53ca\u4eab\u6709\u5718\u9ad4\u91ab\u7642\u4fdd\u96aa\u798f\u5229\u7b49\n\n\u6709\u610f\u8005\u53ef\u96fb\u90f5\u5c65\u6b77\u8868\u53ca\u8981\u6c42\u85aa\u91d1\uff0c\u6309\u4ee5\u4e0b\u00a0APPLY NOW\u9375\u00a0\u96fb\u90f5\u81f3\u672c\u516c\u53f8\u3002", "employment_types": ["Full Time"], "selling_points": ["Fast Growing E-commerce Field", "Cooperate with 100+ Luxury and Wrold-famous Brands", "Energetic Team with Good Career Prospect"], "locations": ["Kwai Fong"], "categories": ["Transportation & Logistics", "Fulfillment", "Inventory / Warehousing", "E-commerce", "Supply Chain"], "post_time": "2022-01-10T03:18:47Z", "salary": {"currency": null, "max": null, "min": null, "period": "monthly", "term": null}, "salary_visible": false, "title_keywords": ["operations", "supervisor", "trainee"], "responsibilities": [], "requirements": {"degrees": [], "majors": [], "languages": [], "language_level": [], "hard_skills": [], "soft_skills": [], "languages_combined": []}, "experience_required": {"duration": [], "field": []}}, {"job_id": "100003009041218", "location_code": "hk", "company": "RecruitFirst Limited", "job_title": "\u5168\u8077\u5009\u52d9\u54e1 -\u670d\u88dd\u985e (5\u5929\u5de5\u4f5c/\u51b7\u6c23\u5009/13\u5929\u6709\u85aa\u5e74\u5047) @\u9752\u8863", "description": "Responsibilities:\n\nWork closely with Warehouse Operation Team to ensure smooth daily operation\nAssist Manager / Supervisor to maintain key performance indicators\nCo-ordinate with internal and CS team to ensure on-time order fulfilment\nPrepare regular report and data analysis to clients\nProvide administrative support to operations team\nPerform ad-hoc assignment as required\n\nRequirements:\n\nQuicker learner in a fast-paced environment\nSelf-motivated, detail-minded and willing to go extra mile\nWith relevant experience in Warehouse Operations / WMS will be an advantage\nFamiliar with MS Excel applications\nSelf-motivated, independent and willing to work as a team player\nFresh graduates will be considered\nWith relevant experience in Warehouse Operations will be consider as Senior Assistant\nWith relevant experience in Warehouse Management / Costs Control will be consider as Assistant Supervisor\n\nEmployment Terms:\n\nDiscretionary Bonus, Free Lunch Meal, Free Shuttle Bus, Annual Leave, Bank Holiday, Overtime Allowance, 5.5 Days or Alternate Saturday off per week\n\nApplication Information:\n\nJob seekers may click the \"Apply Now\" or whatsapp\u00a0Mr Szeto at 70729297 for further info.", "employment_types": ["Full Time"], "selling_points": [], "locations": ["Tsing Yi"], "categories": ["Transportation & Logistics", "Fulfillment", "Inventory / Warehousing", "Supply Chain"], "post_time": "2022-01-12T03:36:39Z", "salary": {"currency": null, "max": null, "min": null, "period": "monthly", "term": null}, "salary_visible": false, "title_keywords": ["\u5168\u8077\u5009\u52d9\u54e1"], "responsibilities": ["ad-hoc", "co-ordinate with", "operations", "daily operation", "data analysis", "maintain", "provide administrative support", "prepare regular report"], "requirements": {"degrees": [], "majors": [], "languages": [], "language_level": [], "hard_skills": ["whatsapp", "ms excel", "go"], "soft_skills": ["detail-minded", "self-motivated", "independent", "work as a team", "fast-paced environment"], "languages_combined": []}, "experience_required": {"duration": [], "field": ["warehouse management", "relevant experience"]}}, {"job_id": "100003009034516", "location_code": "hk", "company": "JPC Texson Limited", "job_title": "LOGISTICS OPERATION OFFICER (25K-28K) - chemicals trading (Kowloon Bay/5 days work)", "description": "A multinational consumer goods company with global presence is looking for an Associate Director to join their logistics & operations team. The successful candidate will lead a sizable team in customer service, logistics and operation functions.\u00a0\n\nThe Position\nThis position will oversee the company's e-commerce, retail business operations and logistics functions. The successful candidate will partner with major stakeholders within all functional departments to drive business growth and enhance customer experience by offering best platforms from online to offline.\n\n\nManaging the performance of 3PL to ensure all KPIs are met;\nExplore new ways and best practices to reduce costs, improve service quality and reduce operational risk;\nManage the execution and completion of the defined project plans/ roadmaps through effectively coordinating people and resources that support annual business, financial and growth objectives;\nSupport business opportunities in compliance with global operational strategies.\u00a0\n\nRequirement\n\n\nBachelor degree or above in supply chain, operations or any related discipline;\nMinimum 10 years of managerial experience in which 5 years\u2019 experience in logistics and customer service field;\nExperience in O2O operation and leading service team;\nBeing proactive with strong interpersonal skills to communicate with different customers and colleagues;\nStrong leadership with strategical thinking to achieve operational and customer service excellence.\n\n\u00a0(All personal data collected will be kept confidential and is for recruitment purpose only.)", "employment_types": ["Full Time", "Permanent"], "selling_points": ["Degree holder; proficient in English & Mandarin", "3-5 yr logistics or operations in any businesses", "Team = 3 members; report to Logistics Manager"], "locations": ["Kwun Tong Area"], "categories": ["Transportation & Logistics", "Freight Forwarding", "Fulfillment", "Supply Chain"], "post_time": "2022-01-10T03:33:42Z", "salary": {"currency": null, "max": null, "min": null, "period": "monthly", "term": null}, "salary_visible": false, "title_keywords": ["operation officer", "logistics"], "responsibilities": ["communicate with", "operations", "business opportunities", "compliance", "quality", "customer service", "logistics", "recruitment", "plans", "kpis", "personal data", "costs"], "requirements": {"degrees": ["degree or above", "bachelor"], "majors": [], "languages": [], "language_level": [], "hard_skills": ["e-commerce"], "soft_skills": ["customer service", "interpersonal skills", "proactive", "leadership"], "languages_combined": []}, "experience_required": {"duration": ["5 years", "minimum 10 years"], "field": ["managerial", "customer service", "business", "logistics", "operation", "team"]}}, {"job_id": "100003009030590", "location_code": "hk", "company": "Kin Shun Information Technology Limited", "job_title": "Operations Manager, Parcel Delivery", "description": "CHINA MOBILE HONG KONG COMPANY LIMITED (\"CMHK\") is the wholly-owned subsidiary of China Mobile Limited (HKEx: 941) (NYSE: CHL), which ranks 65th on the Fortune Global 500.\n\nOur company strives to offer superior service experience and to become the preferable digital partner for customers. We are preserving an environment with trust, responsibility and caring. At CMHK, we commit to maximizing people\u2019s potential and paving the way toward success for every striver. We are now inviting high caliber professional to join us.\n\nDepartment: Procurement\n\nIn this position, you will:\n\nOversee and supervise procurement activities across different categories of Network Procurement\nHandle tender and ensure procurement activities are conducted in compliance with company standard\nHandle ad-hoc projects on procurement process and systems enhancement\nCollaborate with cross-functional teams, rationalize procurement needs and provide effective sourcing and purchasing support\nMonitor market situation and maintain relationship with major vendors\nIdentify cost saving opportunities and conduct vendor performance evaluation on a continued basis\nFormulate and update policy and work procedures of Procurement\nContribute to the on-going improvement of the procurement function\n\nTo be successful in this position, you should meet the following requirements:\n\nUniversity graduate on Procurement or Engineering\u00a0\nMinimum 8 years of procurement experience, with at least 5 years\u2019 experience on a managerial grade\nExcellent analytical ability and project management skills\nGood Communication, interpersonal and negotiation skill\nStrong supervisory and coaching skills\n\nCandidates with less experience will be considered as \"Procurement Officer\"\u00a0\n\n\u00a0When you work:\n\n5 days work\n8 hours/day\n\n\u00a0What you enjoy:\n\nDouble pay\nDiscretionary bonus\nPerformance bonus\nLife insurance\nMedical insurance\nMeal allowance\nEducation subsidies\nTransportation allowance\nBirthday gift\nMarriage leave\nBirthday leave\nStaff discount\n\nCMHK is committed to be an equal opportunity employer. We offer exceptional benefits package and the opportunity to work in a challenging environment. Personal data provided by applicants will be treated strictly in accordance with our personal data policy and for recruitment purposes only.\n\nPlease submit your application to us by clicking the APPLY NOW button and send your full resume with your availability, current and expected salary to us.", "employment_types": ["Full Time", "Permanent"], "selling_points": [], "locations": ["Lai Chi Kok"], "categories": ["Transportation & Logistics", "Fulfillment", "Supply Chain", "E-commerce", "Supply Chain"], "post_time": "2022-01-07T07:50:30Z", "salary": {"currency": null, "max": null, "min": null, "period": "monthly", "term": null}, "salary_visible": false, "title_keywords": ["operations manager"], "responsibilities": ["collaborate with", "cost", "compliance", "systems", "monitor", "procedures", "communication", "project management", "maintain", "tender", "evaluation", "ad-hoc projects", "insurance", "cross-functional teams"], "requirements": {"degrees": ["university graduate"], "majors": ["engineering"], "languages": [], "language_level": [], "hard_skills": ["mobile", "project management", "vendor"], "soft_skills": ["project management skills", "communication", "committed", "negotiation skill", "interpersonal", "superior"], "languages_combined": []}, "experience_required": {"duration": ["minimum 8 years", "at least 5 years"], "field": ["digital", "procurement", "managerial"]}}, {"job_id": "100003009026790", "location_code": "hk", "company": "CIAO International Limited (Best Mart 360\u00b0)", "job_title": "Demand & Replenishment Specialist", "description": "Responsibilities:\n\nWork closely with Warehouse Operation Team to ensure smooth daily operation\nAssist Manager to maintain key performance indicators\nCo-ordinate with internal and CS team to ensure on-time order fulfilment\nPrepare regular report and data analysis to clients\nDevelop your interpersonal skills and management skills to be a part of the management team in the later stage of your career\nPerform ad-hoc assignment as required\n\nRequirements:\n\nQuicker learner in a fast-paced environment\nSelf-motivated, detail-minded and willing to go extra mile\nWith relevant experience in Warehouse Operations / WMS will be an advantage\nFamiliar with MS Excel applications\nSelf-motivated, independent and willing to work as a team player\nFresh graduates are welcome\n\nEmployment Terms:\n\nDiscretionary Bonus, Free Lunch Meal, Free Shuttle Bus, Annual Leave, Bank Holiday, Overtime Allowance, 5.5 Days or Alternate Saturday off per week\n\nApplication Information:\n\nJob seekers please click the \"Apply Now\".", "employment_types": ["Full Time"], "selling_points": ["Planning, Inventory, Supply Chain experience", "Strong analytical skills & excellent Excel skills", "Immediately available"], "locations": ["Ngau Tau Kok"], "categories": ["Transportation & Logistics", "Fulfillment", "Inventory / Warehousing", "Supply Chain"], "post_time": "2022-01-06T08:38:55Z", "salary": {"currency": null, "max": null, "min": null, "period": "monthly", "term": null}, "salary_visible": false, "title_keywords": ["specialist"], "responsibilities": ["ad-hoc", "management team", "management", "co-ordinate with", "daily operation", "develop", "data analysis", "maintain", "prepare regular report"], "requirements": {"degrees": [], "majors": [], "languages": [], "language_level": [], "hard_skills": ["ms excel", "go"], "soft_skills": ["detail-minded", "self-motivated", "independent", "work as a team", "fast-paced environment"], "languages_combined": []}, "experience_required": {"duration": [], "field": ["relevant experience"]}}, {"job_id": "100003009032998", "location_code": "hk", "company": "PARKnSHOP", "job_title": "Business Analyst", "description": "\u4e0a\u73ed\u6642\u9593\uff1a\u661f\u671f\u4e00\u81f3\u516d (\u5176\u4e2d5\u5929) 8:30am-5:30pm / 9:30am-6:30pm\n\n\u5de5\u4f5c\u5185\u5bb9\uff1a\n\n\u6536\u8ca8\u3001\u9ede\u8ca8\u3001\u4e0a\u67b6\u3001\u4f7f\u7528\u8a2d\u5099\u642c\u904b\u8ca8\u7269\n\u65e5\u5e38\u5009\u52d9\u5de5\u4f5c\uff0c\u78ba\u4fdd\u5009\u5eab\u7684\u6574\u6f54\u548c\u6548\u7387\n\n\u8981\u6c42\uff1a\n\n\u4e00\u5e74\u5009\u52d9\u7d93\u9a57 (\u6709\u4f7f\u7528\u5806\u9ad8\u6a5f\u7d93\u9a57\u512a\u5148)\n\u4e00\u822c\u82f1\u8a9e\uff0c\u61c2\u5f97\u57fa\u672c\u96fb\u8166\u904b\u7528\n\u6709\u8cac\u4efb\u5fc3, \u80fd\u7368\u7acb\u8655\u7406\u5de5\u4f5c\n\n\u798f\u5229:\n\n\u9280\u884c\u5047\u671f\n13\u5929\u6709\u85aa\u5e74\u5047\n\u91ab\u7642\u798f\u5229\n\u6709\u85aa\u5728\u8077\u57f9\u8a13\n\u54e1\u5de5\u8cfc\u7269\u512a\u60e0\n\n\u6709\u610f\u61c9\u5fb5\u8005\u8acb\u7acb\u5373\u6309\u7533\u8acb(Apply Now)\n\n\u5982\u6709\u4efb\u4f55\u7591\u554f\uff0c\u6b61\u8fce\u806f\u7d61Hailey Chan 3702 3826\u67e5\u8a62\u3002", "employment_types": ["Full Time"], "selling_points": [], "locations": ["Shatin Area"], "categories": ["Transportation & Logistics", "Fulfillment", "Inventory / Warehousing"], "post_time": "2022-01-08T05:35:14Z", "salary": {"currency": null, "max": null, "min": null, "period": null, "term": null}, "salary_visible": false, "title_keywords": ["business analyst"], "responsibilities": [], "requirements": {"degrees": [], "majors": [], "languages": [], "language_level": [], "hard_skills": [], "soft_skills": [], "languages_combined": []}, "experience_required": {"duration": [], "field": []}}, {"job_id": "100003009025097", "location_code": "hk", "company": "Airbus China Limited", "job_title": "SATAIR - Order Fulfillment Specialist", "description": "\n\nTHE COMPANY :\n\n\nTrading : industrial chemicals import & export\nMain market : China and Asian countries\nAsian offices : Vietnam, China, Taiwan\nWe are looking for\u00a0\u00a0 LOGISTICS OPERATION OFFICER\u00a0 - with details as follows :\n\u00a0\nTHE JOB :\n\n\nDegree holder\nStudies in Logistics / Supply Chain Management / Trading / Operations / Business is a plus\nProficient in English, Chinese and Mandarin\n3 to 5 years logistics / operations / order processing in trading or manufacturing of any products\nExperience or interest in industrial chemicals is a plus\nReport to the Senior Operations Manager\nWork in Operations team of 3 members\nPerform order processing, handle logistics documents and coordinate shipment activities\nCoordinate with suppliers, clients, China & Asian offices for logistics and operation arrangement\nKnowledge in or willing to learn SAP\n5 days work \u00a0\n13 months salary + performance bonus \u00a0\nAnnual leave : 12 days\nMedical benefits\u00a0\n\u00a0\nTO APPLY for this job or similar jobs :\n\u00a0\n\u00a0\nFor secure and confidential job application, please click the below link to get our email address.\n\u00a0\nhttp://jpc.hk/confidential_apply.htm\n\u00a0\n\u00a0\nWe provide free job hunting services to job seekers.\n\u00a0\nTo speed up our process, please do NOT send us download links.\n\u00a0\nPersonal data provided by job applicants will be used for recruitment purpose only.\n\u00a0\nYour privacy is guaranteed. We will never give out, lease, or sell your personal information.\n\u00a0\nJPC Recruiting Services was established in 1990.\n\u00a0\nhttp://www.facebook.com/pages/JPC-Texson-Ltd/500356593325952\n\u00a0\n\u00a0\n\n", "employment_types": ["Full Time", "Permanent", "Contract"], "selling_points": [], "locations": ["Airport Area"], "categories": ["Transportation & Logistics", "Fulfillment"], "post_time": "2022-01-06T03:27:18Z", "salary": {"currency": null, "max": null, "min": null, "period": "monthly", "term": null}, "salary_visible": false, "title_keywords": ["specialist"], "responsibilities": ["management", "operations", "shipment activities", "coordinate with", "coordinate", "logistics", "order processing", "report"], "requirements": {"degrees": ["degree holder"], "majors": [], "languages": ["english", "chinese", "mandarin"], "language_level": ["proficient"], "hard_skills": ["plus", "sap", "order processing"], "soft_skills": ["willing to learn"], "languages_combined": [{"language": "english", "language_level": ["proficient"]}, {"language": "chinese", "language_level": ["proficient"]}, {"language": "mandarin", "language_level": ["proficient"]}]}, "experience_required": {"duration": [], "field": []}}, {"job_id": "100003009030552", "location_code": "hk", "company": "Puyi Optical Limited", "job_title": "\u5009\u52d9\u52a9\u7406 Warehouse Assistant", "description": "About Zeek\nZeek is the brand name under Kin Shun Information Technology Limited which incorporated in 2019. Zeek aims to provide smart logistics, SaaS solutions and online / offline integrated instant delivery service for Hong Kong and Southeast Asia market, meeting their needs for food & parcel delivery and last-mile logistics.\n\nWe strive for building an excellent delivery experience by adopting big data and artificial intelligence. With existing business in Hong Kong, Singapore, Malaysia, Thailand and Vietnam, we will continue to expand our business to Southeast Asia countries and regions like Taiwan, Philippines and Indonesia in near future.\n\n\nResponsibilities:\n\n\nTo supervise and managing the delivery operations, particularly on workforce management strictly on company regulation to ensure the operations flow is smoothly and efficiency;\nOversees the strategy , planning .and execution of projects to \u00a0ensure accuracy\u00a0 and cost-efficiency;\nExperience with sortation center/ parcel fulfillment center, cost benefit analysis, labor productivity analysis in order to\u00a0effectively plan and scheduling the operations resources in order to meet and exceed internal and external\u00a0services levels at all times with productive and cost efficiency;\nWork with related departments to maintain and enhance the platform of reward system for member activation and engagement;\nMeasure performance, provide a feedback as well as taking proactive steps to ensure the best\u00a0practices are shared across all departments;\nCreate a positive and collaborative team environment by setting and regularly reviewing the\u00a0achievement of team goals;\nDocument and track any failures/error including reporting on failure rates, causes, and preventable\u00a0incidents;\nAssist in training and coaching new and existing team members;\nPerform ad-hoc duties / projects assigned by top management\n\nRequirements:\n\nDiploma holder or above in Logistics, Supply Chain Management or related disciplines;\n5-7 years\u2019 relevant experience of which 2 years were at supervisory level in operations from logistics/supply chain industries;\nExperience in emerging technology in logistics and supply chain, including but not limited to open-platform, dynamic pricing; knowledge of cloud service in logistics is a plus;\nStrong planning and analytical skills. Sensitive to numbers;\nGood people management and presentation skills;\nIndependent, flexible, stress resistant and able to work in a fast pace team-base environment;\nProficiency in MS Excel, Word, PowerPoint and Chinese word processing;\nGood command of both written and spoken English, Chinese and Putonghua\n\nWe offer competitive remuneration, birthday and work anniversary holidays and benefit packages to the right candidate.\n\nPlease send your detailed resume, with last and expected salary to our Human Resources Department by clicking \"Apply Now\u201d.\u00a0\n\n(All information collected will be treated in strict confidence and used solely for recruitment)", "employment_types": ["Full Time", "Permanent"], "selling_points": ["\u8655\u7406\u65e5\u5e38\u5009\u5eab\u76f8\u95dc\u7684\u4e8b\u5b9c", "\u5230\u516c\u53f8\u9580\u5e97\u76e4\u9ede", "\u5354\u52a9\u8ddf\u8eca\u9001\u8ca8\u5230\u9580\u5e97"], "locations": ["Tsim Sha Tsui"], "categories": ["Transportation & Logistics", "Fulfillment", "Inventory / Warehousing", "Supply Chain"], "post_time": "2022-01-07T07:44:30Z", "salary": {"currency": null, "max": null, "min": null, "period": "monthly", "term": null}, "salary_visible": false, "title_keywords": ["warehouse assistant", "\u5009\u52d9\u52a9\u7406"], "responsibilities": ["reporting", "management", "cost", "operations", "fulfillment", "analysis", "scheduling", "maintain", "plan", "ad-hoc duties", "planning"], "requirements": {"degrees": ["diploma holder"], "majors": ["related disciplines"], "languages": ["putonghua", "english", "chinese"], "language_level": ["proficiency", "good command"], "hard_skills": ["plus", "chinese word processing", "word", "powerpoint", "analytical skills", "ms excel", "dynamic"], "soft_skills": ["flexible", "independent", "analytical skills", "presentation skills", "dynamic", "sensitive to numbers"], "languages_combined": [{"language": "putonghua", "language_level": ["good command"]}, {"language": "english", "language_level": ["good command"]}, {"language": "chinese", "language_level": ["proficiency", "good command"]}]}, "experience_required": {"duration": ["5-7 years", "2 years"], "field": ["supervisory level", "logistics", "relevant experience", "supply chain"]}}, {"job_id": "100003009030237", "location_code": "hk", "company": "Delmar International (Hong Kong) Limited", "job_title": "Ocean Freight Operations (5 Day Work)", "description": "Primary responsibilities:\n\nOrder management and administration for all aspects of the material order handling process and facilitating the stock dispatch of material from resources globally.\nUnderstand customer requirements and transform into fulfilment actions.\nPurchasing of parts from Airbus partner companies, which include monitoring and escalation of deliveries.\nInitiating withdrawal process from production lines, external suppliers or Airbus' global warehouses.\nDevelop alternative solutions and make decisions to ensure in-time material delivery to meet customer requirement.\nLaunch and coordinate sourcing process and data loading activities for new part numbers.\nEnsure in-time delivery for all spare parts and related services to all Airbus customers\u2019 worldwide using available technical and commercial data.\nCoordinate clarification of technical and commercial queries utilizing Airbus Technical Documentation and/or liaising with Airbus technical, engineering or commercial departments.\nBe the focal point for the customer for material order related actions.\nManage order book and follow up proactively to ensure no or low backlog and delays.\nInform relevant stakeholders proactively on order status, especially for delays or critical parts.\nHand over relevant tasks and related information to the 24/7 backup organization.\nSecondary responsibilities:\n\nProvide high quality responses related to any customer or internal requests.\nMeasure and utilize key performance indicators (KPIs) in order to manage material order activity and producing order activity reports.\nAssist, coordinate and prepare reports on operational topics and participate in customer meetings as required.\nWork in a team to fulfil overall targets and communicate any relevant information to other team members, especially planning officers to improve forecasting and avoid future critical situations.\nGeneral:\n\nComply with Satair Group\u2019s mission, values and Quality Management procedures\nComply with Satair Group\u2019s guidelines on Ethics & Compliance\nUnderstanding, sharing and living of Satair Group values and rules\nRespect Satair Group processes and procedures agreed per function\nKeep the direct report informed of the status of agreed tasks and of any critical problem areas\nParticipate in optimizing Satair Group\u2019s business procedures by applying existing Satair Group\u2019s IT systems\nComment/advise on unsatisfactory situations within the organization, and propose potential solutions for improvements\nIdentify and offer suggestions to improve efficiency\nBe well informed about and familiar with the latest developments in Satair Group's business\nHave an inter-cultural understanding\nParticipate in occupational safety and health efforts\nContribute towards a positive and inspiring working environment\nPersonal & interpersonal skills:\n\nDiplomatic sense and open/\u2018out-of-silo\u2019 mind-set\nAbility to build successful relations across functions and with all stakeholders\nStrong ability to work in a team to achieve common targets\nPositive, pro-active, and enthusiastic communication and working\nFlexibility in terms of working time, which could include weekend or shift work if required to fulfil targets\nProfessional skills:\n\nMinimum 3 years working experience\nDegree in Business, Supply Chain, Logistics or Production and have relevant work\nWorking knowledge of English, both orally and in writing\nUnderstanding aviation business specifically in the area of spares supply chain management\nTechnical and process oriented background with the ability to understand and interpret technical documentation and drawings\nAbility to understand your customer to develop and propose creative solutions\nFlexible, able to work under pressure with tight deadlines and successfully deal with unexpected situations / issues\nWorking knowledge of MS Office applications (Excel, Power Point...) and SAP R/3", "employment_types": ["Full Time", "Permanent"], "selling_points": ["Immediate available is highly preferred", "Handling inbound/outbound shipment and planning", "5 Day Work Week"], "locations": ["Kwai Fong"], "categories": ["Transportation & Logistics", "Others", "Freight Forwarding", "Fulfillment"], "post_time": "2022-01-07T07:03:15Z", "salary": {"currency": null, "max": null, "min": null, "period": "monthly", "term": null}, "salary_visible": false, "title_keywords": ["operations"], "responsibilities": ["data", "clarification", "quality", "drawings", "communication", "administration", "work under pressure", "compliance", "liaising with", "develop", "reports", "logistics", "kpis", "forecasting", "report", "management", "monitoring", "procedures", "documentation", "order management", "guidelines", "systems", "coordinate", "prepare reports", "planning"], "requirements": {"degrees": ["degree"], "majors": ["business"], "languages": ["english"], "language_level": [], "hard_skills": ["excel", "no", "inform", "focal", "sap", "make", "documentation", "r", "power point", "ms office"], "soft_skills": ["flexible", "diplomatic", "communication", "enthusiastic", "interpersonal skills", "inspiring", "orally", "pro-active", "creative", "positive", "work under pressure"], "languages_combined": [{"language": "english", "language_level": []}]}, "experience_required": {"duration": ["minimum 3 years"], "field": []}}, {"job_id": "100003009030668", "location_code": "hk", "company": "Top Personnel Consultant", "job_title": "Shipping Assistant / Officers (MNC $17-22K)", "description": "Responsibilities:\n\nEvaluate and review forecast by analyzing sales trend and seasonality\nManage routine replenishment with local & overseas suppliers and supply chain activities.\nMaintain a healthy inventory level to meet demand as well as avoid overstocking\nAssist in continuous improvement projects and ad-hoc duties\nWork closely with internal parties (Purchasing / Operations / Logistics) for daily operations \u00a0\nOversee and responsible for inventory control and demand forecast\nNegotiate with suppliers for solving supply chain related issue\nGenerate routine reporting and PO with also follow-up monitoring\n\nRequirement:\n\nFormal qualifications in Supply Chain, Business or equivalent\n2 -5 years in planning, inventory, supply chain experience in Retail or FMCG business\nDetailed oriented and sensitive to figures, well organized and able to work independently\nCompetent to work in a fast-paced and dynamic retail environment that required multi-tasking skills, flexibility and adaptability\nStrong ability to review and identify issues and opportunities in operations\nGood command of both written and spoken English and Chinese\nStrong analytical skills and excellent Excel skills\nAn excellent communication skill at all levels of the organization\nImmediate available is preferred\n\nWe offer\u00a0competitive\u00a0package including 5-day work week, medical insurance and staff discount, etc.\u00a0 Interest parties, please send full resume with\u00a0current and expected salary\u00a0and date of availability by clicking \"Apply Now\".\n\n(Data collected will be used for recruitment purpose only)", "employment_types": ["Full Time", "Permanent"], "selling_points": ["TST / Fortress Hill, MNC, HQ in Europe", "1 yr+ in Import & Export shipping docs exp.", "HK$17-22K X13 +DB +Med+ Dental +Life, Eng & Mand"], "locations": ["Not Specified"], "categories": ["Transportation & Logistics", "Fulfillment", "Shipping", "Supply Chain"], "post_time": "2022-01-07T08:04:26Z", "salary": {"currency": null, "max": null, "min": null, "period": "monthly", "term": null}, "salary_visible": false, "title_keywords": ["shipping", "assistant"], "responsibilities": ["continuous improvement projects", "reporting", "operations", "inventory", "review", "monitoring", "replenishment", "evaluate", "daily operations", "maintain", "logistics", "inventory control", "forecast", "ad-hoc duties", "internal parties"], "requirements": {"degrees": [], "majors": [], "languages": ["english", "chinese"], "language_level": ["good command"], "hard_skills": ["excel", "dynamic", "analytical skills"], "soft_skills": ["work independently", "detailed oriented", "competent", "sensitive to figures", "communication skill", "well organized", "analytical skills", "dynamic", "adaptability", "multi-tasking skills"], "languages_combined": [{"language": "english", "language_level": ["good command"]}, {"language": "chinese", "language_level": ["good command"]}]}, "experience_required": {"duration": ["2 -5 years"], "field": ["fmcg", "supply chain", "business", "retail", "planning"]}}, {"job_id": "100003009027198", "location_code": "hk", "company": "Kerry Logistics", "job_title": "Officer - Logistics Solutions", "description": "\u8077\u8cac :\n\n\u8655\u7406\u65e5\u5e38\u5009\u5eab\u76f8\u95dc\u7684\u4e8b\u5b9c\n\u5305\u62ec\u9032/\u51fa\u8ca8\u8655\u7406,\u7cfb\u7d71\u66f4\u65b0, \u54c1\u8cea\u6aa2\u67e5\u8207\u639b\u50f9\u9322\u724c\u7b49\u3002\n\u5230\u516c\u53f8\u9580\u5e97\u76e4\u9ede(\u6bcf\u6708\u7d04\u4e00\u81f3\u5169\u6b21)\n\u5354\u52a9\u8ddf\u8eca\u9001\u8ca8\u5230\u9580\u5e97(\u6bcf\u661f\u671f\u7d04\u5169\u81f3\u4e09\u6b21)\n\u78ba\u4fdd\u5009\u5eab\u7bc4\u570d\u6574\u9f4a\u6e05\u6f54\n\n\n\u5165\u8077\u689d\u4ef6 :\n\n\u4e2d\u4e94\u6216\u9999\u6e2f\u4e2d\u5b78\u6587\u6191\u8a66\u7a0b\u5ea6\n\u51771-2\u5e74\u6709\u95dc\u5de5\u4f5c\u7d93\u9a57\uff0c\u6b61\u8fce\u61c9\u5c46\u7562\u696d\u751f\u7533\u8acb\n\u61c2\u57fa\u672c\u96fb\u8166\u64cd\u4f5c\n\u8aa0\u5be6\u3001\u7d30\u5fc3\u53ca\u6709\u8cac\u4efb\u611f\n\u9858\u610f\u52a0\u73ed\u5de5\u4f5c\n\u798f\u5229:\n\n\u6bcf\u9031\u4e94\u5929\u5de5\u4f5c\n\u51b7\u6c23\u5009\u5eab\u5de5\u4f5c\u74b0\u5883\n\u653e\u516c\u773e\u5047\u671f\n\u4ea4\u901a\u4fbf\u5229\uff0c\u5de5\u4f5c\u5730\u9ede\u6b65\u884c6\u5206\u9418\u53ef\u5230\u6e2f\u9435\u7ad9\n\u751f\u65e5\u5047\u671f\n12\u5929\u6709\u85aa\u5e74\u5047\n\u91ab\u7642\u798f\u5229\n\u52a0\u73ed\u6d25\u8cbc\n\u5b50\u5973\u95dc\u9867\u5047\n\u6709\u610f\u8005\u8acb\u5c07\u5c65\u6b77\u53ca\u8981\u6c42\u5f85\u9047\u96fb\u90f5\u81f3\"Apply Now\".\u00a0\n\n\u7533\u8acb\u4eba\u6240\u63d0\u4f9b\u7684\u500b\u4eba\u8cc7\u6599\u7d55\u5c0d\u4fdd\u5bc6\uff0c\u4e26\u53ea\u7528\u4f5c\u62db\u8058\u6709\u95dc\u7528\u9014", "employment_types": ["Full Time", "Permanent"], "selling_points": [], "locations": ["Kwai Fong"], "categories": ["Transportation & Logistics", "Others", "Fulfillment", "Supply Chain"], "post_time": "2022-01-06T09:17:05Z", "salary": {"currency": null, "max": null, "min": null, "period": "monthly", "term": null}, "salary_visible": false, "title_keywords": ["officer", "logistics"], "responsibilities": [], "requirements": {"degrees": [], "majors": [], "languages": [], "language_level": [], "hard_skills": [], "soft_skills": [], "languages_combined": []}, "experience_required": {"duration": [], "field": []}}, {"job_id": "100003009032603", "location_code": "hk", "company": "JPC Texson Limited", "job_title": "SHIPPING SPECIALIST (22K-27K) \u2013 French baby garment/toys/sundries buying office (TST/5 days work)", "description": "Job Responsibilities:-\n\nResponse to customer\nHandling inbound/outbound Ocean Freight shipment and planning\nManage Ocean Freight shipment data and ensure data integrity\nCommunicate with other branches/ origin offices\nRequirements:-\n\nFluent in English and Chinese\nMinimum 2 years relevant working experience\nFluent in English and Mandarin, both written and spoken\nImmediate available is\u00a0highly preferred\n\n\nPlease send full resume with present & expected salary for consideration.", "employment_types": ["Full Time", "Permanent"], "selling_points": ["Work in Shipping Team of 5 members", "Handle full set I/E shipping & LC documents", "Exp in garment, toys or sundries is a plus"], "locations": ["Tsim Sha Tsui"], "categories": ["Transportation & Logistics", "Fulfillment", "Shipping", "Supply Chain"], "post_time": "2022-01-07T11:49:21Z", "salary": {"currency": null, "max": null, "min": null, "period": "monthly", "term": null}, "salary_visible": false, "title_keywords": ["specialist", "shipping"], "responsibilities": ["communicate with", "data", "planning"], "requirements": {"degrees": [], "majors": [], "languages": ["english", "chinese", "mandarin"], "language_level": ["fluent"], "hard_skills": [], "soft_skills": [], "languages_combined": [{"language": "english", "language_level": ["fluent", "fluent"]}, {"language": "chinese", "language_level": ["fluent", "fluent"]}, {"language": "mandarin", "language_level": ["fluent", "fluent"]}]}, "experience_required": {"duration": ["minimum 2 years"], "field": ["relevant working experience"]}}, {"job_id": "100003009033860", "location_code": "hk", "company": "Zenit (Hong Kong) Company Limited", "job_title": "\u5009\u52d9\u54e1 (Warehouse Assistant/ Stock keeper/ Store keeper/ Operator)", "description": "Our client is a multinational trading company (HQ in Europe) with offices at TST & Fortress Hill\u00a0 in 5 days\u2019 work urgently looking for\u00a0Shipping Assistant / Officers\u00a0to join their company with details as follows:\u00a0\n\nShipping Assistant ($16-18K) at Fortress Hill / Toys Products\n\nShipping Officer ($19-22K) at TST / Garment Items\n\nResponsibilities:\n\n\u0178\u00a0\u00a0 Follow up all import & export shipping documentation\u00a0\n\n\u0178\u00a0\u00a0 Input shipping data in SAP system\n\n\u0178\u00a0\u00a0 Coordinate and communicate with Suppliers and Buyers, HQ, internal & external depts\n\n\nRequirements:\n\n\u0178\u00a0\u00a0 Diploma\u00a0 or above in any disciplines\n\n\u0178\u00a0\u00a0 At least 1 year up in handling import & export shipping documents\n\n\u0178\u00a0\u00a0 Can communicate in both English and Mandarin\u00a0\n\nSalary negotiable (HK$17-22K) depends on qualifications & experience.\n\nInterested parties, please email detailed resume by Clicking \"Apply Now\"\u00a0or call 2866 1088 (Ms. Yuen) for further inquiries.\n\nFor more information about our\u00a0agency, please visit www.toppersonnel.com.hk\n\nThe information provided by applicants will be used for employment related purpose only.", "employment_types": ["Full Time", "Permanent"], "selling_points": ["5\u5929\u5de5\u4f5c \u65e9\u4e0a9\u6642\u81f3\u4e0b\u53486\u6642", "\u65bc\u6574\u6f54\u53ca\u6709\u51b7\u6c23\u8ca8\u5009\u5de5\u4f5c", "15 \u65e5 \u5927\u5047"], "locations": ["Tsuen Wan Area"], "categories": ["Transportation & Logistics", "Fulfillment", "Inventory / Warehousing"], "post_time": "2022-01-10T01:58:00Z", "salary": {"currency": null, "max": null, "min": null, "period": "monthly", "term": null}, "salary_visible": false, "title_keywords": ["operator", "warehouse assistant", "\u5009\u52d9\u54e1"], "responsibilities": ["communicate with", "shipping", "data", "coordinate", "documentation"], "requirements": {"degrees": ["diploma"], "majors": ["any disciplines"], "languages": ["english", "mandarin"], "language_level": [], "hard_skills": [], "soft_skills": [], "languages_combined": [{"language": "english", "language_level": []}, {"language": "mandarin", "language_level": []}]}, "experience_required": {"duration": [], "field": []}}, {"job_id": "100003009026085", "location_code": "hk", "company": "China Mobile Hong Kong \u4e2d\u570b\u79fb\u52d5\u9999\u6e2f", "job_title": "Procurement Assistant", "description": "You can enjoy:\nComprehensive Medical and Life insurance coverage, including your spouse and children\nExclusive company pension schemes\nMarriage, Maternity and Paternity Leave\nExclusive shopping discount, Bazaar Sales for our people only\nProfessional training and career advancement opportunities\nConvenient office location, less than 5 min. walk from MTR\nContemporary workplace with Onsite Clinic, Lactation Rooms, free drinks and chill out areas\nWell-equipped Gym inside our office building, plus fitness and interest class packages\nFree round-trip lunchtime shuttle bus services to Shatin\nResponsibilities:\nProvide insights on stock management and improve the efficiency of supply chain activities to ensure the Company's KPIs to be met\nReview inventory and stock allocation plans by producing and compiling reports (e.g. Slow Movement, Stock Week Coverage and On-Shelf Availability) regularly\nMaintain the database accuracy and review replenishment system setting periodically\nAssist in various ad hoc projects\nRequirements:\nUniversity graduate in Supply Chain Management, Economic, Statistics or related discipline\n3 years\u2019 working experience, preferably in FMCG or retail industry\nAttentive to details with good problem solving and analytical skills\nHigh proficiency in MS Office applications (Excel, VBA, Access) and statistical/data-mining tools\nSelf-driven, independent and able to meet tight deadlines and work under pressure\nAn attractive salary and benefit package will be offered. Interested parties please forward detailed resume stating expected salary to: People Department, PARKnSHOP (HK) Limited, Watson House, 1-5 Wo Liu Hang Road, Fo Tan, N.T. or email to us.\nWe are an equal opportunity employer and welcome applications from all qualified candidates. The information provided will be treated in strict confidence and be used only for consideration of your application for relevant / similar posts within the A.S. Watson Group. All personal data of unsuccessful applicants will be destroyed within 12 months from the date of application.", "employment_types": ["Full Time", "Permanent"], "selling_points": ["Prepare tender evaluation & issue purchase orders", "Identify effective & reliable sourcing strategies", "0-1 years\u2019 relevant experience"], "locations": ["Kwai Hing"], "categories": ["Transportation & Logistics", "Fulfillment", "Merchandising & Purchasing", "Electronics", "Procurement / Purchasing / Sourcing"], "post_time": "2022-01-06T07:17:52Z", "salary": {"currency": null, "max": null, "min": null, "period": null, "term": null}, "salary_visible": false, "title_keywords": ["procurement assistant"], "responsibilities": ["provide insights", "stock management", "stock allocation", "inventory", "review", "replenishment", "maintain", "reports", "ad hoc projects", "plans", "database", "kpis"], "requirements": {"degrees": ["university graduate"], "majors": ["statistics"], "languages": [], "language_level": [], "hard_skills": ["excel", "vba", "analytical skills", "problem solving", "ms office"], "soft_skills": ["meet tight deadlines", "independent", "attentive to details", "problem solving and analytical skills", "driven", "work under pressure"], "languages_combined": []}, "experience_required": {"duration": ["3 years"], "field": ["retail industry", "fmcg"]}}, {"job_id": "100003009031365", "location_code": "hk", "company": "V-Logic Limited", "job_title": "International Freight - Operations Officer / Clerk (Near Lai King MTR Station)", "description": "Responsibilities\n\nAssist in designing logistics operations policy and procedures to enhance the operational efficiency and effectiveness\nLead a team to support customers\u2019 orders fulfillment and enquiries\nMonitor all inventory and warehouse activities\nPlan and schedule inbound and outbound shipments\nPrepare reports and analysis on order fulfillment for customer\n\nRequirements\n\nDegree or above in Logistics / Supply Chain Management or related disciplines\nMinimum 3 years\u2019 relevant experience, with exposurein 3PL or Electronic Technology & Industrial / Food & Beverage / Fashion & Lifestyle warehouse\nStrong in Logistics System enhancement and with experience in SAP system is a plus\nSelf-motivated, independent, can handle complicated issues with flexibility and able to adopt in a fast paced industry\nGood command of both written & spoken English and Chinese, including Mandarin\nCandidate with more experience will be considered as Assistant Manager\nWorking Location: Sheung Shui / Fanling / Kwai Chung / Tsuen Wan\n\nIf you have the energy and qualifications to add to our velocity,\u00a0Please visit\u00a0Kerry Logistics Network Company Webpage\u00a0to apply or\u00a0send your CV with your present and expected salary to the\u00a0Group Director of\u00a0Human Resources & Administration, Kerry Logistics by clicking APPLY NOW\u00a0or by fax to +852 2614 8517.\n\n(We are an equal opportunity employer and welcomes applications from all qualified candidates.\u00a0All personal data will be kept in the strictest confidence and will be used for recruitment purpose only. All applicants maybe considered for other suitable positions in the Kerry Group and its members. All personal data of unsuccessful candidates will be destroyed.)", "employment_types": ["Full Time", "Permanent"], "selling_points": [], "locations": ["Kwai Tsing Area"], "categories": ["Transportation & Logistics", "Freight Forwarding", "Fulfillment", "Supply Chain"], "post_time": "2022-01-07T09:15:27Z", "salary": {"currency": null, "max": null, "min": null, "period": "monthly", "term": null}, "salary_visible": false, "title_keywords": ["operations officer", "clerk"], "responsibilities": ["operations", "fulfillment", "inventory", "procedures", "monitor", "analysis", "lead a team", "order fulfillment", "logistics", "schedule", "plan", "designing", "prepare reports"], "requirements": {"degrees": ["degree or above"], "majors": ["related disciplines"], "languages": ["english", "chinese", "mandarin"], "language_level": ["good command"], "hard_skills": ["plus", "wan", "sap"], "soft_skills": ["self-motivated", "confidence", "independent"], "languages_combined": [{"language": "english", "language_level": ["good command"]}, {"language": "chinese", "language_level": ["good command"]}, {"language": "mandarin", "language_level": ["good command"]}]}, "experience_required": {"duration": ["minimum 3 years"], "field": ["food", "logistics", "relevant experience"]}}, {"job_id": "100003009030887", "location_code": "hk", "company": "Circle K Convenience Stores (HK) Ltd", "job_title": "\u517c\u8077\u5305\u88dd\u54e1(\u9752\u8863)", "description": "\nTHE COMPANY :\n\n\nFrench multinational company\nBaby garment brand owner and marketer\nHong Kong office : buying office\nMain market : US, Europe, Asia, China and worldwide\nVendor factories : Guangdong\nWe are looking for\u00a0\u00a0 SHIPPING SPECIALIST\u00a0 \u2013 with details as follows :\n\u00a0\nTHE JOB :\n\n\nWork in Shipping team of 5 members\nLiaise with suppliers, forwarders, customers, internal departments, sister companies and Headquarter on shipments to ensure on time delivery.\nHandle full set of I/E shipping documents independently.\nArrange Domestic, Import and Export shipment and prepare related documentations.\nMonitor shipment status to ensure on time delivery.\nAssign appointed Shipping Line & Forwarders to vendors according to instructions from Headquarter Export Department.\nManage booking to catch targeted vessel and urgent shipments.\nMinimum 5 years of shipping experience, familiar in Garment, toys or sundries field at buying office is preferable.\nExperience in handling export shipment to worldwide market.\nExperience in dealing with the factory and forwarding agent.\nFamiliar with L/C stipulations, Tradelink I/E declaration\nGood command of written and spoken English, Chinese and Mandarin.\nGood PC skills and MS Excel; experience in SAP operation is a plus\n5 days work\nAnnual leave : 15 days\nMedical benefit\nDental benefit\nLife insurance benefit\nWork-life balance\nFriendly work environment\nOffice location : TST Harbour City\n\u00a0\n\u00a0\nTO APPLY for this job or similar jobs :\n\u00a0\n\u00a0\nFor secure and confidential job application, please click the below link to get our email address.\n\u00a0\nhttp://jpc.hk/confidential_apply.htm\n\u00a0\n\u00a0\nWe provide free job hunting services to job seekers.\n\u00a0\nTo speed up our process, please do NOT send us download links.\n\u00a0\nPersonal data provided by job applicants will be used for recruitment purpose only.\n\u00a0\nYour privacy is guaranteed. We will never give out, lease, or sell your personal information.\n\u00a0\nJPC Recruiting Services was established in 1990.\n\u00a0\nhttp://www.facebook.com/pages/JPC-Texson-Ltd/500356593325952\n\n", "employment_types": ["Part Time"], "selling_points": [], "locations": ["Tsing Yi"], "categories": ["Transportation & Logistics", "Fulfillment", "Inventory / Warehousing", "Sales, CS & Business Devpt", "Wholesale"], "post_time": "2022-01-07T08:32:03Z", "salary": {"currency": null, "max": null, "min": null, "period": "hourly", "term": null}, "salary_visible": false, "title_keywords": [], "responsibilities": ["shipping documents", "shipping", "tradelink", "ensure on time delivery", "monitor", "import and export shipment", "booking", "insurance", "liaise with suppliers"], "requirements": {"degrees": [], "majors": [], "languages": ["english", "french", "chinese", "mandarin"], "language_level": ["good command"], "hard_skills": ["plus", "harbour", "sap", "vendor", "import and export", "ms excel", "c", "pc skills", "documentations"], "soft_skills": ["independently", "friendly"], "languages_combined": [{"language": "english", "language_level": ["good command"]}, {"language": "french", "language_level": []}, {"language": "chinese", "language_level": ["good command"]}, {"language": "mandarin", "language_level": ["good command"]}]}, "experience_required": {"duration": ["minimum 5 years"], "field": ["garment", "operation", "toys"]}}, {"job_id": "100003009016410", "location_code": "hk", "company": "Flexport Asia Limited", "job_title": "Ocean Freight Fulfilment Associate (Supply Chain Officer)", "description": "CHINA MOBILE HONG KONG COMPANY LIMITED (\"CMHK\") is the wholly-owned subsidiary of China Mobile Limited (HKEx: 941) (NYSE: CHL), which ranks 65th on the Fortune Global 500.\n\nOur company strives to offer superior service experience and to become the preferable digital partner for customers. We are preserving an environment with trust, responsibility and caring. At CMHK, we commit to maximizing people\u2019s potential and paving the way toward success for every striver. We are now inviting high caliber professional to join us.\n\nDepartment: Procurement\n\nIn this position, you will:\n\nAssist in procurement activities including preparation of tender documents, tender evaluation, issue purchase orders and review contract documents in accordance with established policies and procedures\nWork with user departments to analyze and identify business needs and support development of best fit procurement and contracting strategies\nPrepare procurement related report analysis\nMonitor and evaluate vendor performance and internal customer satisfaction\n\nTo be successful in this position, you should meet the following requirements:\n\nDegree holder in Engineering, IT, Procurement or related discipline\u00a0\n0-1 years\u2019 relevant experience\nProficient in MS Office application\nExcellent communication, interpersonal and negotiation skills, with proactive attitude\nGood command in English and Putonghua\n\n\u00a0When you work:\n\n5 days work\n8 hours/day\n\nCMHK is committed to be an equal opportunity employer. We offer exceptional benefits package and the opportunity to work in a challenging environment. Personal data provided by applicants will be treated strictly in accordance with our personal data policy and for recruitment purposes only.\n\nPlease submit your application to us by clicking the APPLY NOW button and send your full resume with your availability, current and expected salary to us.", "employment_types": ["Full Time", "Permanent"], "selling_points": ["Regional exposure in ocean fulfillment/allocation", "Tech-freight forwarder from Silicon Valley", "Cross functions working environment"], "locations": ["Quarry Bay"], "categories": ["Transportation & Logistics", "Freight Forwarding", "Fulfillment", "Shipping"], "post_time": "2022-01-03T09:01:39Z", "salary": {"currency": null, "max": null, "min": null, "period": "monthly", "term": null}, "salary_visible": false, "title_keywords": ["supply chain officer", "associate"], "responsibilities": ["tender documents", "policies", "analysis", "review", "procedures", "monitor", "evaluate", "communication", "purchase", "contracting", "tender", "evaluation", "report"], "requirements": {"degrees": ["degree holder"], "majors": ["it", "engineering"], "languages": ["putonghua", "english"], "language_level": ["good command"], "hard_skills": ["mobile", "analysis", "vendor", "ms office"], "soft_skills": ["communication", "committed", "negotiation skills", "proactive", "interpersonal", "superior"], "languages_combined": [{"language": "putonghua", "language_level": ["good command"]}, {"language": "english", "language_level": ["good command"]}]}, "experience_required": {"duration": ["0-1 years"], "field": ["digital", "relevant experience"]}}, {"job_id": "100003009022671", "location_code": "hk", "company": "ConnectedGroup Limited", "job_title": "Assistant Logistics Manager - FMCG company", "description": "Responsibilities:\n\nHandle freight related documents\nHandle shipments and communication with overseas agents\nDevelop co-loading business\n\nRequirements:\n\nCompleted tertiary or related education\nOne to two years freight operations working experience is preferable\nExperience in working with and managing co-loader\nProactive and highly self-motivated in communicating with various parties\nGood team player\nAnalytical and logical thinking, positive and good working attitude\nProficient in both written and spoken English and Chinese\nHands-on PC knowledge, competent in MS Excel etc. is an advantage\nCandidates without working experience can be considered as Operations Clerk\n\n\nIf you are the one we are looking for, please send your full resume with expected salary by clicking \"Apply Now\".\n\n\nResume without expected salary will not be considered.\n\nJob Location: Kwai Chung (Next to MTR Station)", "employment_types": ["Full Time", "Permanent"], "selling_points": ["Well-established multinational company", "Attractive remuneration package", "Excellent career progression"], "locations": ["Not Specified"], "categories": ["Transportation & Logistics", "Others", "Fulfillment", "Supply Chain"], "post_time": "2022-01-05T06:09:24Z", "salary": {"currency": null, "max": null, "min": null, "period": "monthly", "term": null}, "salary_visible": false, "title_keywords": ["logistics manager", "assistant"], "responsibilities": ["related documents", "communication", "develop"], "requirements": {"degrees": [], "majors": [], "languages": ["english", "chinese"], "language_level": ["proficient"], "hard_skills": ["pc knowledge", "ms excel"], "soft_skills": ["good working attitude", "good team player", "self-motivated", "competent", "hands-on", "proactive", "positive"], "languages_combined": [{"language": "english", "language_level": ["proficient"]}, {"language": "chinese", "language_level": ["proficient"]}]}, "experience_required": {"duration": ["one to two years"], "field": []}}, {"job_id": "100003009024860", "location_code": "hk", "company": "Hays", "job_title": "Logistics & Trade Specialist", "description": "\u8077\u8cac :\n\n\u8ca0\u8cac\u5305\u88dd\uff1b\u65e5\u5e38\u5009\u52d9\u5de5\u4f5c\u5305\u62ec\u642c\u8ca8\u3001\u57f7\u8ca8\u53ca\u5206\u8ca8\u7b49\n\u8cc7\u6b77 :\n\n\u6c92\u6709\u5b78\u6b77\u8981\u6c42; \u826f\u597d\u7cb5\u8a9e; \u7565\u61c2\u8b80\u5beb\u4e2d\u6587\n\u5f85\u9047 :\n\n\u6bcf\u5c0f\u6642$54.00 - $57.00, \u6709\u54e1\u5de5\u8cfc\u7269\u512a\u60e0, \u5728\u8077\u57f9\u8a13, \u91ab\u7642\u798f\u5229\u53ca\u8d85\u6642\u5de5\u4f5c\u6d25\u8cbc, \u4e0a\u53489\u6642\u81f3\u4e0b\u53488\u6642, \u6bcf\u9031\u5de5\u4f5c4\u5929\u81f36\u5929,\u8f2a\u4f11, \u6bcf\u5929\u5de5\u4f5c 5 - 11 \u5c0f\u6642\n\u7533\u8acb\u9808\u77e5 :\u6c42\u8077\u8005\u53ef\u81f4\u96fb29916268\u8207OK\u4fbf\u5229\u5e97\u6709\u9650\u516c\u53f8\u9673\u5c0f\u59d0\u806f\u7d61\u3002\n\n\u6709\u610f\u7533\u8acb\u8005\u8acb \u6309 APPLY NOW\u7533\u8acb\u00a0", "employment_types": ["Full Time", "Permanent"], "selling_points": ["International MNC", "Trade & Logistics Management", "Up to 25K"], "locations": ["Not Specified"], "categories": ["Transportation & Logistics", "Others", "Fulfillment", "Shipping"], "post_time": "2022-01-06T02:45:27Z", "salary": {"currency": null, "max": null, "min": null, "period": "monthly", "term": null}, "salary_visible": false, "title_keywords": ["specialist", "logistics"], "responsibilities": [], "requirements": {"degrees": [], "majors": [], "languages": [], "language_level": [], "hard_skills": [], "soft_skills": [], "languages_combined": []}, "experience_required": {"duration": [], "field": []}}, {"job_id": "100003009030701", "location_code": "hk", "company": "IKEA", "job_title": "\u517c\u8077\u6536\u8ca8\u52a9\u7406 Part Time Goods Flow Co-worker", "description": "Build the Ocean Services to help Flexport grow\nThe opportunity:\nOur Ocean Freight Team is essential to winning new business, supporting all current business, and building out the future of Flexport\u2019s ocean services. As a Ocean Freight Fulfillment Associate, you\u2019ll be an integral part of helping achieve Flexport\u2019s growth goals.\u00a0\nWe\u2019re looking for a team member based in our Hong Kong office, responsible for different trades that we are focusing on. Candidates will need to have a passion for ocean freight and ability to work with parties across different parts of the organization.\n\nWhat you\u2019ll do:\nBe an operational leader:\nYou will help to ensure seamless operation of moving ocean shipments under Flexport contracts\nYou will manage both soft and hard allocation with ocean carriers that match with clients\u2019 demand and minimize allocation shortfall\nYou will support with trial / VIP shipments by providing various ocean carrier options and protect these shipments from roll-overs\nYou will maintain and run the fulfillment management tool for daily operation and support urgent requests from clients / squads\nYou will assist the team leader to closely work with Ocean Freight Procurement Team regarding allocation planning\nYou will support the team leader create strategy and best practices for fulfillment management tool execution\nYou are expected to be process and data driven in your daily activities, ensuring we operate in an efficient and effective way.\nYou can take action to manage exceptions in operations and be proactive in exploring and implementing solutions\nFocus on strategy and development:\nYou will create tools for internal use to build efficiency and share knowledge, both within the team and company\nYou will collaborate with operations, sales, marketing and compliance as needed for new projects\nWe\u2019re still a young company with a lot to learn and build, need people who will be flexible, engaged, and ready to jump into something new\nWhat you\u2019ll need:\nBA/BS degree with a strong track record of success\nMinimum 2 years of experience at a startup, top consulting firm, an NVOCC pricing, procurement or operations team or in a supply-chain role, hands on experience of Transpacific trade is a plus; also open to candidates from other industries as well. We are trying to diversify our team!\nExcellent communication, interpersonal, and organizational skills\nAn obsession with client happiness. You succeed when they succeed\nNext-level attention to detail\nCourage to challenge the status quo when logic and reason require it. See something broken? Fix it!\nThe intellectual horsepower to become an expert on international trade in a matter of weeks\nA mastery of email communication. You keep the inbox at zero", "employment_types": ["Full Time"], "selling_points": [], "locations": ["Not Specified"], "categories": ["Transportation & Logistics", "Others", "Fulfillment", "Inventory / Warehousing"], "post_time": "2022-01-07T08:08:13Z", "salary": {"currency": null, "max": null, "min": null, "period": "hourly", "term": null}, "salary_visible": false, "title_keywords": [], "responsibilities": ["collaborate with", "management", "consulting", "data", "contracts", "fulfillment", "operations", "daily operation", "compliance", "bs", "communication", "maintain", "support the team", "planning"], "requirements": {"degrees": ["degree"], "majors": [], "languages": [], "language_level": [], "hard_skills": ["focus", "reason", "plus"], "soft_skills": ["efficient", "flexible", "organizational skills", "proactive", "responsible", "passion for", "interpersonal", "communication", "hands on", "attention to detail", "focus", "team member", "driven"], "languages_combined": []}, "experience_required": {"duration": ["minimum 2 years"], "field": ["procurement", "consulting", "team"]}}, {"job_id": "100003009023456", "location_code": "hk", "company": "Pernod Ricard Hong Kong Ltd", "job_title": "(Senior) Demand Planner", "description": "Your new company\nThis is a well-known international fashion apparel company with over 100 years of history. As one of the top leaders in the industry, they have established goods reputation and friendly working environment. They are now looking for a Logistics & Trade Specialist to join the Hong Kong office.\n\nYour new role\n\nHandle import and export trading and shipment issues for the APAC market\nManage the trading customs compliance during the shipment process\nContinuously evaluate import and export activities in order to develop and implement better compliance practices for the global market\nKeep up to date in trade requirements which may affect the trade operations\n\n\nWhat you'll need to succeed\n\nAt least 2 year of experience in global import and export trade operations\nLC experience is preferred\nWilling to learn attitude\nGood command of Mandarin and English\n\n\nWhat you'll get in return\n\nMultinational working environment\nAttractive salary\nPromising career path\n\n\nWhat you need to do now\nIf you're interested in this role, click 'apply now' to forward an up-to-date copy of your CV, or call us now.\nIf this job isn't quite right for you but you are looking for a new position, please contact Venice Li at venice.li@hays.com.hk for a confidential discussion on your career.", "employment_types": ["Full Time", "Permanent"], "selling_points": ["demand planning, demand planner", "analysis, supply chain", "Strong Excel skills"], "locations": ["Tsim Sha Tsui"], "categories": ["Transportation & Logistics", "Fulfillment", "Supply Chain"], "post_time": "2022-01-05T08:49:06Z", "salary": {"currency": null, "max": null, "min": null, "period": "monthly", "term": null}, "salary_visible": false, "title_keywords": [], "responsibilities": ["operations", "compliance", "develop", "evaluate", "logistics", "contact"], "requirements": {"degrees": [], "majors": [], "languages": ["english", "mandarin"], "language_level": ["good command"], "hard_skills": ["import and export"], "soft_skills": ["interested in", "willing to learn", "friendly"], "languages_combined": [{"language": "english", "language_level": ["good command"]}, {"language": "mandarin", "language_level": ["good command"]}]}, "experience_required": {"duration": ["at least 2 year"], "field": []}}, {"job_id": "100003009017209", "location_code": "hk", "company": "Aacurapid (Hong Kong) Ltd", "job_title": "Logistics Officer (Global Logistics, TST Area, Up to 30K/month, Bonus)", "description": "\n\u4f60\u5c07\u6703\u611b\u4e0a\u5b9c\u5bb6\u5bb6\u5c45\n\n\u6211\u5011\u662f\u4e00\u7fa4\u52d9\u5be6\u5766\u8aa0\u3001\u71b1\u611b\u5bb6\u5c45\u5e03\u7f6e\u7684\u4eba\uff0c\u4f86\u81ea\u4e16\u754c\u5404\u5730\uff0c\u80cc\u666f\u5404\u6709\u4e0d\u540c\uff0c\u4f46\u537b\u6709\u540c\u4e00\u500b\u76ee\u6a19\uff1a\u70ba\u5927\u773e\u7de0\u9020\u66f4\u7f8e\u597d\u7684\u751f\u6d3b\u3002\u6211\u5011\u4ee5\u5171\u540c\u7684\u50f9\u503c\u89c0\u5be6\u8e10\u76ee\u6a19\u3002\u9019\u4e9b\u50f9\u503c\u89c0\u662f\u6211\u5011\u5de5\u4f5c\u7684\u57fa\u790e\uff0c\u4e5f\u662f\u5171\u878d\u95dc\u611b\u3001\u958b\u660e\u5766\u8aa0\u6587\u5316\u7684\u57fa\u77f3\u3002\u6211\u5011\u63d0\u5021\u5718\u968a\u6587\u5316\uff0c\u71b1\u8aa0\u6a02\u89c0\uff0c\u6b61\u8fce\u8207\u6211\u5011\u614b\u5ea6\u53ca\u50f9\u503c\u89c0\u76f8\u540c\u7684\u4eba\u624d\u52a0\u5165\u3002\n\n\n\n\u9019\u6703\u662f\u4f60\u55ce\n\n\u4f60\u6210\u719f\u4e3b\u52d5\u53ca\u64c1\u6709\u826f\u597d\u9867\u5ba2\u670d\u52d9\u614b\u5ea6\uff0c\u4ee5\u5ba2\u70ba\u5148\n\u4f60\u559c\u6b61\u8207\u4eba\u6e9d\u901a\u53ca\u91cd\u8996\u5718\u968a\u5408\u4f5c\n\u4f60\u5c0d\u5bb6\u98fe\u5bb6\u54c1\u696d\u5145\u6eff\u71b1\u8aa0\n\u4f60\u80fd\u64cd\u6d41\u5229\u7cb5\u8a9e\u53ca\u7c21\u55ae\u82f1\u8a9e\u61c9\u5c0d\n\u4f60\u64c1\u6709\u4e2d\u4e94\u7a0b\u5ea6\u6216\u4ee5\u4e0a\u5b78\u6b77\n\u6b61\u8fce\u5c0d\u96f6\u552e\u696d\u5145\u6eff\u71b1\u8aa0\u7684\u61c9\u5c46\u7562\u696d\u751f\u52a0\u5165\u6211\u5011\n\n\u4f60\u7684\u65e5\u5e38\u5de5\u4f5c\n\n\u8207\u914d\u9001\u4e2d\u5fc3\u5354\u8abf\u53ca\u5b89\u6392\u9001\u8ca8\u548c\u6536\u8ca8\u7b49\u4e8b\u5b9c\n\u63a5\u6536\u3001\u76e4\u9ede\u53ca\u8655\u7406\u6240\u6709\u9032\u51fa\u5206\u5e97\u4e4b\u8ca8\u7269\u53ca\u5176\u6587\u4ef6\n\u5c07\u8ca8\u7269\u5206\u985e\u53ca\u4f7f\u7528\u6b63\u78ba\u5de5\u5177\u5b89\u6392\u4e0a\u67b6\n\u9075\u5b88\u5b9c\u5bb6\u5bb6\u5c45\u7684\u5065\u5eb7\u53ca\u5b89\u5168\u653f\u7b56\uff0c\u9810\u9632\u53d7\u50b7\u4e8b\u6545\u53ca\u8ca8\u7269\u640d\u58de\n\n\u6211\u5011\u5718\u968a\u7684\u4f7f\u547d\n\u6211\u5011\u5718\u968a\u4e3b\u8981\u65bc\u5e55\u5f8c\u652f\u63f4\uff0c\u78ba\u4fdd\u5927\u773e\u80fd\u65bc\u8ca8\u5834\u9078\u8cfc\u6240\u9700\u7684\u5b9c\u5bb6\u7522\u54c1\uff0c\u4e26\u5229\u7528\u6211\u5011\u65bc\u4f9b\u61c9\u6d41\u7a0b\u7684\u5c08\u696d\u77e5\u8b58\u4f86\u9810\u6e2c\u548c\u8a02\u8ca8\uff0c\u5c07\u6210\u672c\u964d\u5230\u6700\u4f4e\n\n\n\u54e1\u5de5\u798f\u5229\n\u96c6\u5718\u8cfc\u7269\u512a\u60e0\u3001\u751f\u65e5\u79ae\u5238\u3001\u4ecb\u7d39\u4eba\u53ca\u65b0\u54e1\u63a8\u85a6\u734e\u91d1\n\n\u5982\u6709\u4efb\u4f55\u67e5\u8a62\uff0c\u6b61\u8fce\u00a0WhatsApp 9438 6523\n\n\u7533\u8acb\u8005\u63d0\u4f9b\u4e4b\u8cc7\u6599\u7d55\u5c0d\u4fdd\u5bc6\uff0c\u7533\u8acb\u4eba\u4e4b\u8cc7\u6599\u53ea\u4f9bDFI\u96f6\u552e\u96c6\u5718\u9644\u5c6c\u6a5f\u69cb\u6216\u6388\u6b0a\u4e4b\u4ee3\u7406\u4eba\u4f5c\u62db\u8058\u53ca\u7504\u9078\u7528\u9014\u3002\u62db\u8058\u904e\u7a0b\u5b8c\u7562\u5f8c\uff0c\u7533\u8acb\u8cc7\u6599\u5c07\u88ab\u4fdd\u7559\u4e8c\u5341\u56db\u500b\u6708\u4f5c\u53c3\u8003\u4e4b\u7528\u3002\u672c\u516c\u53f8\u5df2\u5099\u6709\u4e00\u4efd\u300c\u79c1\u96b1\u653f\u7b56\u8072\u660e\u300d\uff0c\u95a3\u4e0b\u5982\u6709\u9700\u8981\u53ef\u700f\u89bd\u516c\u53f8\u7db2\u9801\u6216\u4ee5\u66f8\u9762\u5f62\u5f0f\u5411\u4eba\u529b\u8cc7\u6e90\u90e8\u7d22\u53d6\u6709\u95dc\u8cc7\u6599\u3002\u7533\u8acb\u4eba\u5982\u5728\u905e\u4ea4\u7533\u8acb\u8868\u5f8c\u516d\u661f\u671f\u5167\u4ecd\u672a\u63a5\u7372\u901a\u77e5\u7d04\u898b\uff0c\u5176\u6709\u95dc\u7533\u8acb\u5c07\u88ab\u5b58\u6a94\uff0c\u4ee5\u4f5c\u65e5\u5f8c\u540c\u985e\u578b\u8077\u4f4d\u7a7a\u7f3a\u8003\u616e\u4e4b\u7528\u3002\n\n\u6b64\u62db\u8058\u5ee3\u544a\u7531\u725b\u5976\u6709\u9650\u516c\u53f8\u767c\u884c\u00a0", "employment_types": ["Full Time", "Permanent"], "selling_points": ["Clients & Carriers Booking", "Quotation / Rate Management", "With Forwarder / NVOCCs Exposure is a MUST"], "locations": ["Tsim Sha Tsui"], "categories": ["Transportation & Logistics", "Others", "Fulfillment", "Shipping"], "post_time": "2022-01-03T11:16:33Z", "salary": {"currency": null, "max": null, "min": null, "period": "monthly", "term": null}, "salary_visible": false, "title_keywords": ["logistics officer", "logistics"], "responsibilities": [], "requirements": {"degrees": [], "majors": [], "languages": [], "language_level": [], "hard_skills": ["whatsapp"], "soft_skills": [], "languages_combined": []}, "experience_required": {"duration": [], "field": []}}, {"job_id": "100003009017038", "location_code": "hk", "company": "Ambition", "job_title": "Logistics Supervisor - 30k", "description": "Position Summary\n\nResponsible for the smooth, on-time and accurate execution of demand planning process and associated S&OP activities in Travel Retail Asia. Key objectives :\n\nEnsure accurate and timely compilation of demand plan incorporating insights from internal/external business stakeholders Ensure prompt and correct communication and execution of S&OP decisions and actions Deliver forecast accuracy and related supply chain KPI target to achieve overall supply chain efficiency.\n\nKey Responsibilities / Accountabilities\n\nDemand Planning and S&OP Execution\n\nExecute the demand planning process to ensure business demands are communicated accurately and timely to stakeholders\n\nWork collaboratively with business stakeholders to align on forecast assumptions and to incorporate business intelligence, commercial strategy and promotion plan into the demand plan as needed\n\nManage statistical forecast in the Demand Planning system with appropriate algorithms or models\n\nConduct Demand Review on a regular basis with Commercial and Finance team\n\nCompile and consolidate monthly demand plan for supply planning, financial budgeting and estimates\n\nProactively manage and coordinate day-to-day demand changes to minimise any detrimental impact on the operation, escalate changes as needed\n\nCoordinate the execution of the demand plan with Commercial and Customer Services teams, effectively managing exceptions\n\nEnsure timely and efficient communication of decisions and follow-ups identified throughout the S&OP processes\u00a0\n\nForecast Analysis and Reporting\n\nPrepare and compile Demand Planning decks to support Demand Review meetings\n\nPrepare and compile forecast analysis and metrics report to measure and track performance, review and interpret data as appropriate\n\nDevelop and prepare regular or ad hoc tracking, risks and scenario analysis reports to support business decisions\n\nOthers\n\nOperate as the Super User of the Demand Planning system, provide training and system support to business users\n\nDrive collaborative partnerships with cross-functional teams to facilitate business delivery\n\nSupport collaboration with key customers to develop joint-forecasting plans to ensure customer insights are articulated\n\nSeek and support continuous improvements in systems and processes to enhance quality, efficiency, cost control and resources optimization\n\nAssist in any ad hoc projects or assignments as required\n\nKey Requirements\n\nDegree holder or above preferably in Business Administration, Management, Logistics, Supply Chain Management or related disciplines\n\n8+ years relevant working experience in business, demand or supply planning, preferably gained in FMCG or retail industry\n\nProven experience in business and demand planning for Asia Pacific markets\n\nSolid understanding and exposure in S&OP processes and tools\n\nDemonstrated strong aptitude in data analysis, root causes identification and problem solving\n\nAbility to comprehend business requirements and translate into tactics to move forward\n\nExceptional written/verbal communication and interpersonal skills\n\nAbility to build strong relationships across different functions and levels\n\nHigh proficiency in MS office applications with advanced Excel knowledge\n\nApplicants with less experience will be consider as Planner", "employment_types": ["Full Time", "Permanent"], "selling_points": ["Global leading collectable grading company", "Stable company with expansion", "Work life balance culture"], "locations": ["Not Specified"], "categories": ["Transportation & Logistics", "Fulfillment", "Inventory / Warehousing"], "post_time": "2022-01-03T10:24:01Z", "salary": {"currency": "HKD", "max": 29999, "min": 25000, "period": "monthly", "term": null}, "salary_visible": true, "title_keywords": ["supervisor", "logistics"], "responsibilities": ["provide training", "data", "analysis reports", "budgeting", "demand planning", "quality", "support business decisions", "communication", "plan", "plans", "ad hoc", "teams", "customer insights", "customer services", "develop", "finance team", "forecast", "forecasting", "report", "continuous improvements", "reporting", "review", "cross-functional teams", "tracking", "analysis", "systems", "coordinate", "ad hoc projects", "cost control", "planning"], "requirements": {"degrees": ["degree holder"], "majors": ["related disciplines", "business administration"], "languages": [], "language_level": [], "hard_skills": ["supply planning", "excel", "planner", "demand planning", "analysis", "problem solving", "ms office"], "soft_skills": ["problem solving", "communication and interpersonal skills", "advanced"], "languages_combined": []}, "experience_required": {"duration": ["8+ years"], "field": ["retail industry", "fmcg", "relevant working experience", "business", "planning"]}}, {"job_id": "100003008952592", "location_code": "hk", "company": "Nestle Hong Kong Ltd", "job_title": "Order Fulfillment Officer", "description": "Responsibilities:\n\nCoordinate bookings with clients and carriers\nHandle daily shipping logistics operation & answer corresponding enquires\nFully responsible for receiving rate requests, sourcing rates as well as quoting rate to clients to maximize the profit for each deal\n\nRequirements\n\nHigh Diploma or above with minimum 4 years relevant experience with Forwarder / NVOCCs Exposure is a MUST\nWith Regional Exposure is definitely an advantage\nGood communication and negotiation skills\nGood at both written and spoken English and Chinese, including Mandarin\nProficiency in MS Offices (Excel, Word, PowerPoint etc)", "employment_types": ["Full Time", "Permanent"], "selling_points": ["Challenge work and strong expectation for success", "Work hard play hard and energetic culture", "Bringing Nutrition, Health and Wellness to HK"], "locations": ["Yuen Long"], "categories": ["Transportation & Logistics", "Fulfillment", "Supply Chain", "E-commerce", "Supply Chain"], "post_time": "2022-01-05T03:46:03Z", "salary": {"currency": null, "max": null, "min": null, "period": "monthly", "term": null}, "salary_visible": false, "title_keywords": ["officer"], "responsibilities": ["coordinate", "shipping", "logistics"], "requirements": {"degrees": ["high diploma or above"], "majors": [], "languages": ["english", "chinese", "mandarin"], "language_level": ["good"], "hard_skills": ["excel", "word", "powerpoint"], "soft_skills": ["communication", "negotiation skills"], "languages_combined": [{"language": "english", "language_level": ["good"]}, {"language": "chinese", "language_level": ["good"]}, {"language": "mandarin", "language_level": []}]}, "experience_required": {"duration": ["minimum 4 years"], "field": ["relevant experience"]}}, {"job_id": "100003009019126", "location_code": "hk", "company": "GOAT Group HK Limited", "job_title": "Fulfillment Support", "description": "\u8077\u8cac :\n\n\u8ca0\u8cac\u6642\u88dd\u5546\u54c1\u5305\u88dd\u5de5\u4f5c, \u5982\u647a\u76d2, \u8cbc\u6a19\u7c64, \u78c5\u91cd, \u5c01\u53e3\u7b49; \u6bcf\u65e5\u9700\u8981\u5b8c\u6210\u516c\u53f8\u6307\u5b9a\u7684\u5de5\u4f5c\u91cf\n\u8cc7\u6b77 :\n\n\u5c0f\u516d\u7a0b\u5ea6; 1\u5e74\u7d93\u9a57; \u826f\u597d\u7cb5\u8a9e; \u4e00\u822c\u666e\u901a\u8a71; \u4e00\u822c\u82f1\u8a9e; \u61c2\u8b80\u5beb\u4e2d\u6587; \u61c2\u95b1\u8b80\u82f1\u6587; \u6709\u5305\u88dd\u7d93\u9a57\u512a\u5148, \u505a\u4e8b\u7d30\u5fc3, \u6709\u8cac\u4efb\u5fc3\n\u5f85\u9047 :\n\n\u6bcf\u5c0f\u6642$50.00, \u661f\u671f\u4e00\u81f3\u516d: \u4e0a\u53489\u6642\u81f3\u4e0b\u53486\u6642, \u6bcf\u9031\u5de5\u4f5c4\u5929\u81f36\u5929, \u6bcf\u5929\u5de5\u4f5c 7.5 \u5c0f\u6642\n\u7533\u8acb\u9808\u77e5 :\u6c42\u8077\u8005\u53ef\u81f4\u96fb66048609\u8207HYPEBEAST HONG KONG LIMITED\u66fe\u5973\u58eb\u806f\u7d61\u3002\n\n\u6709\u610f\u7533\u8acb\u8005\u8acb \u6309 APPLY NOW\u7533\u8acb\u00a0", "employment_types": ["Full Time", "Contract"], "selling_points": ["sneaker", "fulfilment support", "order management"], "locations": ["Shatin Area"], "categories": ["Transportation & Logistics", "Fulfillment", "Inventory / Warehousing"], "post_time": "2022-01-04T06:45:15Z", "salary": {"currency": "HKD", "max": 16999, "min": 14000, "period": "monthly", "term": null}, "salary_visible": true, "title_keywords": [], "responsibilities": [], "requirements": {"degrees": [], "majors": [], "languages": [], "language_level": [], "hard_skills": [], "soft_skills": [], "languages_combined": []}, "experience_required": {"duration": [], "field": []}}, {"job_id": "100003009024276", "location_code": "hk", "company": "OSM HK Limited", "job_title": "Director, Supply Chain", "description": "My client is a global leading luxury / collectable grading service provider. To maintain their logistics operation, they are now in search of an Logistics Supervisor.\n\nYou will support the daily logistics and operation function of the company. You will manage the shipping arrangement, system update, documentation, and packing / unpacking process. You responsibilities will include:\n\nSupport the Operation Supervisor on daily logistics and operation related function\nManage the shipping arrangement from Hong Kong customers to US/China graders and the return process\nLead the order processing function regarding documentation, invoicing and system update\nSupport the operation team on packing and unpacking of inventory prior to shipment arrangement (hands on operation - light weight and non-physical intense)\nProvide updates to internal system to ensure accurate and traceable data of the stocks\nSupport the Assistant manager on other admin task\n\nTo quality, one must possess:\n\nDiploma or associate degree holder with at least 6 years of operation or logistics experience\nExperience with shipping and order processing\nDoesn't mind to support the team on packing / unpacking task (light weight and non-physical intense)\nCandidate with less experience will be considered as Assistant Logistics Supervisor\nFriendly team player with good communication skills\nProficient with both spoken and written English and Mandarin\n\nContact Anson Chan on (852) 3103 4334 or email anson.chan@ambition.com.hk\n\nAPPLY NOW by clicking the button below quoting reference number AC 251581.\n\nwww.ambition.com.hk\n\nData provided is for recruitment purposes only.\n\n\nIf this job isn't quite right for you, but you know someone who would be great at this role, why not take advantage of our referral scheme? We offer HKD1000 in Apple gift cards for every referred candidate who we place in a role. Terms & Conditions Apply. https://www.ambition.com.hk/refer-a-friend", "employment_types": ["Full Time", "Permanent"], "selling_points": [], "locations": ["Kwun Tong"], "categories": ["Transportation & Logistics", "Fulfillment", "Supply Chain", "Manufacturing", "Manufacturing Management"], "post_time": "2022-01-05T12:34:22Z", "salary": {"currency": null, "max": null, "min": null, "period": "monthly", "term": null}, "salary_visible": false, "title_keywords": ["director"], "responsibilities": ["shipping", "shipment arrangement", "data", "system update", "inventory", "quality", "invoicing", "communication", "maintain", "logistics", "contact", "order processing", "recruitment", "documentation", "support the team"], "requirements": {"degrees": ["associate degree", "diploma"], "majors": [], "languages": ["english", "mandarin"], "language_level": ["proficient"], "hard_skills": ["documentation", "scheme", "order processing"], "soft_skills": ["communication skills", "hands on", "friendly", "team player", "accurate"], "languages_combined": [{"language": "english", "language_level": ["proficient"]}, {"language": "mandarin", "language_level": ["proficient"]}]}, "experience_required": {"duration": ["at least 6 years"], "field": ["operation", "logistics", "order processing"]}}, {"job_id": "100003009027282", "location_code": "hk", "company": "Link Profit International Development Limited", "job_title": "E-commerce Warehouse Officer \u96fb\u5546\u5009\u52d9\u54e1", "description": "(Working Location: 5.5 Days work in Yuen Long)\u00a0\n\nPosition Summary\n\nResponsible for effective management of stock allocation process, including proactively reviewing demand & supply simulations and executing customer behavior analysis. Collaborates across market functions to align on actions to mitigate risk and impact, while enhancing the business' ability to provide proactive communication to customers in need for out of stock situations.\n\nA day in the life of...\nResponsible for effective management of stock allocation process\nCollaborates across market functions to align on actions to mitigate OOS risk and impact\nManagement customer demand and ensure on time and in full delivery of physical goods to customers\nWhat will make you successful\n\n- Higher Diploma or above in related\u00a0disciplines\n\n- 1-3 years related experience in order fulfillment/processing, preferable FMCG\n\n-\u00a0Attention to details and\u00a0sensitive of data\n\n- Advanced Use of SAP and Microsoft Excel (Vlookup & Pivot Table)\n\n-\u00a0Fluent in spoken and written Cantonese,\u00a0Mandarin\u00a0and English", "employment_types": ["Full Time", "Temporary"], "selling_points": [], "locations": ["Kwai Hing"], "categories": ["Transportation & Logistics", "Fulfillment", "Inventory / Warehousing", "E-commerce", "Others"], "post_time": "2022-01-06T09:35:18Z", "salary": {"currency": null, "max": null, "min": null, "period": "monthly", "term": null}, "salary_visible": false, "title_keywords": ["officer"], "responsibilities": ["management", "data", "stock allocation", "analysis", "communication", "order fulfillment", "executing"], "requirements": {"degrees": ["higher diploma or above"], "majors": ["related disciplines"], "languages": ["cantonese", "english", "mandarin"], "language_level": ["fluent"], "hard_skills": ["sap", "analysis", "pivot table", "microsoft excel", "make", "vlookup", "processing"], "soft_skills": ["advanced", "responsible", "communication", "attention to details", "sensitive", "proactive"], "languages_combined": [{"language": "cantonese", "language_level": ["fluent"]}, {"language": "english", "language_level": ["fluent"]}, {"language": "mandarin", "language_level": ["fluent"]}]}, "experience_required": {"duration": ["1-3 years"], "field": ["related", "fmcg"]}}, {"job_id": "100003009019464", "location_code": "hk", "company": "Quantium Solutions (Hong Kong) Limited", "job_title": "Assistant Manager, Finance", "description": "Our client is a well-established multinational company with a large presence in Hong Kong, they are now looking for an Assistant Logistics Manager to support the logistics operation.\n\nResponsibilities\n\nSupervise both inbound and outbound logistics operation.\nHandle shipment scheduling and planning\nManage shipment data and ensure data integrity\nEvaluate the SOP and provide suggestion / improvement plan.\nResponsible for 3PL management and ensure their performance meet KPI\nReview logistic cost and explore optimization plan. Negotiate with external third party to improve the cost structure\n\nRequirements:\n\nDegree holder in Business Administration, Supply Chain, or related disciplines\nMinimum of 4 years of experience in Logistic field especially in FMCG industry\nFamiliar with SAP system\nGood command of written and spoken English and Chinese", "employment_types": ["Permanent"], "selling_points": [], "locations": ["Wong Tai Sin Area"], "categories": ["Accounting", "Finance / Accounting Manager", "Transportation & Logistics", "Freight Forwarding", "Fulfillment"], "post_time": "2022-01-04T07:44:22Z", "salary": {"currency": null, "max": null, "min": null, "period": "monthly", "term": null}, "salary_visible": false, "title_keywords": ["assistant manager,"], "responsibilities": ["management", "cost", "data", "review", "shipment scheduling and planning", "manage shipment data", "evaluate", "plan", "third party", "inbound and outbound logistics"], "requirements": {"degrees": ["degree holder"], "majors": ["related disciplines", "business administration"], "languages": ["english", "chinese"], "language_level": ["good command"], "hard_skills": ["fmcg industry", "sap"], "soft_skills": [], "languages_combined": [{"language": "english", "language_level": ["good command"]}, {"language": "chinese", "language_level": ["good command"]}]}, "experience_required": {"duration": ["minimum of 4 years"], "field": ["fmcg"]}}, {"job_id": "100003009024912", "location_code": "hk", "company": "Hays", "job_title": "Logistics Manager", "description": "Company Overview\nOSM makes awesome on-trend retail ready products and engineered soft goods for global brands. Our services include consumer driven design, product development, scalable mass production and supply chain management solutions. Founded in Sweden, our heritage influences our design thinking, aesthetics and ethical conduct. We operate our own factories and have developed an exceptional global supply chain. We have a global presence with regional representation. We conduct global consumer trend research to understand the wants and needs of consumers. Working with world class brands for over 16 years and having made in surplus of 350 million products, we have a refined understanding of what brands week in developing world class products.\n\nJob Highlights\n\u2022 Senior Management role in Supply Chain Function\n\u2022 Regional exposure in electronics and soft goods industries\n\u2022 European MNC, pragmatic work culture, good benefits\n\nJob Overview\nReporting to the CEO based in Hong Kong, the job holder takes total ownership of the Supply Chain management and logistics coordination among our global production plants and towards our global customers. The role ensures customer demand is fulfilled by working very closely with our sales and account management and other functions. The job holder is also expected to identify the right future supply chain model, tools, work processes and procedures to support continued business expansion. It allows the job holder to gain valuable regional exposure in supply chain in manufacturing industry in a European working culture and a pragmatic and friendly work environment.\n\nKey Responsibilities\n\u2022 Lead and take total ownership of the Supply Chain management function\n\u2022 Ensure smooth supply chain process by managing inventories, distribution, delivery, demand and supply planning as well as product end of life management\n\u2022 Work closely with global customers and operations team for a modern customer PO & forecasting model and efficient operational procedures to ensure highest fulfilment rates, OTD, optimized inventory levels while balancing working capital\n\u2022 Ensure delivery targets and KPIs are met\n\u2022 Review current operational standards and processes to identify and implement the right and enhanced future work model, business plan, tools and processes to support continued business growth\n\u2022 Develop and grow the team\u2019s competences and capabilities\n\nJob Requirements\n\u2022 University degree holder with 10-15 years\u2019 experience in supply chain management within China and Southeast Asia coverage\n\u2022 Solid knowledge of end-to-end operations management, in electronics and engineered soft goods industries is highly preferred\n\u2022 Production management knowledge is preferred\n\u2022 Hands on experience in developing and managing ERP business process flows, e.g. MS Dynamics AX, SAP etc.\n\u2022 Experienced in managing SEA Logistics and Customs, 3PL, in-house warehouse, consignment warehouse\n\u2022 Experience in transfer price and inter-company trade\n\u2022 Experienced in implementing, managing and operating a bonded warehouse preferably in China/Hong Kong\n\u2022 Experienced in managing a regional team of 10-20 members\n\u2022 Excellent written and spoken English and Chinese (Cantonese and Mandarin)\n\u2022 Capability to work in a matrix organization with good leadership and influencing skills\n\u2022 High degree of strategic, drive and challenging the status quo mindset\n\u2022 Independent, able to work under pressure in a fast-paced environment\n\u2022 Ready to travel to China and South East Asia and work with a flexible schedule", "employment_types": ["Full Time", "Permanent"], "selling_points": ["Fortune 100 FMCG company", "Lead team", "Promising career progression"], "locations": ["Not Specified"], "categories": ["Transportation & Logistics", "Fulfillment", "Inventory / Warehousing", "Supply Chain"], "post_time": "2022-01-06T02:54:28Z", "salary": {"currency": null, "max": null, "min": null, "period": "monthly", "term": null}, "salary_visible": false, "title_keywords": ["logistics manager"], "responsibilities": [], "requirements": {"degrees": [], "majors": [], "languages": [], "language_level": [], "hard_skills": [], "soft_skills": [], "languages_combined": []}, "experience_required": {"duration": [], "field": []}}, {"job_id": "100003009015969", "location_code": "hk", "company": "L'Occitane (Far East) Limited", "job_title": "Customer Service Representative, Travel Retail", "description": "\u8077\u8cac:\n\n- \u8ca0\u8cac\u65e5\u5e38\u5009\u52d9\u904b\u4f5c\uff0c\u5305\u62ec\u6536\u8ca8\u3001\u51fa\u8ca8\u3001\u7522\u54c1\u6aa2\u67e5\u53ca\u9ede\u5b58;\n- \u8cc7\u6599\u8f38\u5165\u3001\u7ba1\u7406\u5eab\u5b58\u3001\u7dad\u6301\u5eab\u5b58\u7d00\u9304\uff1b\n- \u8655\u7406\u53ca\u56de\u8986\u65e5\u5e38\u5ba2\u6236\u67e5\u8a62\n- \u5411\u5009\u52d9\u90e8\u63d0\u4f9b\u6240\u9700\u8981\u7684\u652f\u63f4\u53ca\u5354\u52a9\n\n\u8981\u6c42:\n-\u00a0\u4e2d\u4e94\u6216\u4ee5\u4e0a\u5b78\u6b77\n- \u5177\u5009\u52d9\u5de5\u4f5c/\u96fb\u5b50\u5546\u52d9\u7d93\u9a57\u512a\u5148\uff0c\u6b61\u8fce\u61c9\u5c46\u7562\u696d\u751f\n- \u826f\u597d\u4e2d\u82f1\u6587\u6c34\u5e73\uff0c\u719f\u6089Microsoft Office\n- \u6709\u5718\u968a\u7cbe\u795e\u3001\u8cac\u4efb\u611f\u3001\u8aa0\u5be6\u3001\u53ca\u826f\u597d\u5de5\u4f5c\u614b\u5ea6\n- \u826f\u597d\u7684\u6e9d\u901a\u6280\u5de7\u53ca\u4eba\u969b\u95dc\u4fc2\n\n\n\u5168\u8077\u54e1\u5de5\u798f\u5229:\n\n- 5\u5929\u5de5\u4f5c\n- \u6709\u85aa\u5e74\u5047\n-\u00a0\u5e74\u7d42\u82b1\u7d05\n-\u00a010\u5929\u6709\u85aa\u5e74\u5047\n\n\n\nJob Description:\n\nResponsible for the day-to-day operations in our warehouse, ranging from inbound\u00a0deliveries\u00a0to picking & packing outbound shipments to our customers, duties include:\n\n- Support warehouse operations on daily order processing\n- Ensure quality and accurate pick and pack\n- Liaise with logistic partners and couriers for order distribution and collection\n- Prepare manifest and data entry for\u00a0reporting\n- Provide other clerical and administrative supports to the team.\n\n\nJob Requirements:\n\n\n- F.5 or above, fresh graduates are also welcomed\n- One-year of working experience (Familiar with e-Commence operations is an advantage)\n- Candidate with less experience will be considered as Warehouse Officer\n- Good knowledge of warehouse operation;\n- Proficiency in Microsoft Office\n- Detail-minded, well-organized and responsible\n\nBenefits:\n- Discretionary Bonus\n- 5 day work week\n- Bank Holidays\n- 10 days annual leave", "employment_types": ["Full Time", "Permanent"], "selling_points": ["3 years' work experience in customer service", "Degree holder/ Diploma in Supply Chain Management", "Hands on experience in SAP"], "locations": ["Quarry Bay"], "categories": ["Sales, CS & Business Devpt", "Customer Service - Supervisor / Officer", "Transportation & Logistics", "Fulfillment"], "post_time": "2022-01-03T08:00:29Z", "salary": {"currency": null, "max": null, "min": null, "period": "monthly", "term": null}, "salary_visible": false, "title_keywords": ["customer service representative"], "responsibilities": ["reporting", "data entry", "day-to-day operations", "quality", "order processing", "liaise with", "warehouse operations"], "requirements": {"degrees": [], "majors": [], "languages": [], "language_level": [], "hard_skills": ["microsoft office"], "soft_skills": ["detail-minded", "well-organized", "responsible"], "languages_combined": []}, "experience_required": {"duration": [], "field": []}}, {"job_id": "100003009020051", "location_code": "hk", "company": "ConnectedGroup Limited", "job_title": "Supply Chain Analyst - Sourcing Office", "description": "Singapore Post Group\u2019s Quantium Solutions is actively expanding in North Asia region. The role\u00a0will drive various workflow in effective and efficient ways to meet business needs.\n\nJob Responsibility:\u00a0\n\n\nHandle full set of management accounts and daily financial function\u00a0\nPerform month end closing & financial analysis, to review various elements of business performance as required by Senior Management\nTackle the financial audits and regulatory reporting\u00a0\nIn charge of billing, A/R, A/P, cash management and handle the day to day job performance of the team members\nPrepare budget & forecast\u00a0\nInvolve in system enhancement, re-engineering and work flow control\nWork with a range of internal and external stakeholders\nAssist in ad hoc projects and assignments\u00a0\n\nRequirements:\n\nDegree in Accounting or related discipline\nAt least 3 years or above relevant experience within MNC organisations\nRelevant experience in ecommerce or logistics industry\u00a0\nAble to work under pressure and fulfill of tight schedules and deadlines\nKnowledge in MS Office, SAP\nProficiency in written and spoken English, Cantonese and Mandarin\n\n\nWe offer 5-day work and\u00a0attractive remuneration package including medical insurance, life insurance, dental and other fringe benefits to the right candidate.\u00a0Interested parties please send your full resume with date of availability, present and expected salaries to us.", "employment_types": ["Full Time", "Permanent"], "selling_points": ["Renowned Sourcing Office", "Attractive remuneration package", "Focus on production management"], "locations": ["Not Specified"], "categories": ["Transportation & Logistics", "Others", "Fulfillment", "Supply Chain"], "post_time": "2022-01-04T09:49:13Z", "salary": {"currency": null, "max": null, "min": null, "period": "monthly", "term": null}, "salary_visible": false, "title_keywords": ["analyst"], "responsibilities": ["reporting", "management", "month end closing", "control", "review", "budget", "financial analysis", "ad hoc projects", "forecast", "audits", "senior management", "re-engineering"], "requirements": {"degrees": ["degree"], "majors": ["accounting"], "languages": ["cantonese", "english", "mandarin"], "language_level": ["proficiency"], "hard_skills": ["sap", "ms office"], "soft_skills": ["work under pressure"], "languages_combined": [{"language": "cantonese", "language_level": ["proficiency"]}, {"language": "english", "language_level": ["proficiency"]}, {"language": "mandarin", "language_level": ["proficiency"]}]}, "experience_required": {"duration": ["at least 3 years"], "field": ["ecommerce", "logistics industry", "relevant experience"]}}, {"job_id": "100003009024095", "location_code": "hk", "company": "NET-A-PORTER", "job_title": "Inbound - Receiving Coordinator", "description": "Your new company\nA fortune 100 company in the FMCG sector is looking for a Logistics Manager in Hong Kong. The are one of the largest consumer goods manufactures and distributor in the global market. They are ranked as the top employer of choice in 2021 and over 80% of the employees gets promoted internally.\n\nYour new role\n\nManage the P&L for the distribution center and repair center\nMonitor the KPI of the operations team as well as 3PL in terms of lead time, fulfilment rate and customer satisfaction rate\nSupervise a team in managing day to day logistics distribution and transportation\nLead monthly meeting with 3PL to ensure the transportation quality and control of delivery performance\nLead process improvement projects and analyse the logistics performance in a group level\n\n\nWhat you'll need to succeed\n\nBachelor Degree holder in supply chain, logistics or other related field\n6+ experience in 3PL management, warehouse and distribution\nP&L experience is essential\nExperience in leading a team is beneficial\nGood command of English, Cantonese and Mandarin\n\n\nWhat you'll get in return\nThey can offer attractive salary and benefit. This company supports employees to develop their career in a stable environment and also opportunities to step up.\n\nWhat you need to do now\nIf you're interested in this role, click 'apply now' to forward an up-to-date copy of your CV, or call us now.\nIf this job isn't quite right for you but you are looking for a new position, please contact us for a confidential discussion on your career.", "employment_types": ["Full Time", "Permanent"], "selling_points": ["\u5e36\u9818\u5718\u968a\u5b8c\u6210Receiving and QC\u7a0b\u5e8f", "\u4e00\u6d41\u7684\u5de5\u4f5c\u74b0\u5883\u6574\u6f54\u7684\u51b7\u6c23\u5009 \u5b8c\u5584\u8a13\u7df4\u53ca\u6649\u5347\u6a5f\u6703", "13\u5929\u5e74\u5047 \u9280\u884c\u5047\u671f"], "locations": ["Tsing Yi"], "categories": ["Transportation & Logistics", "Others", "Fulfillment", "Inventory / Warehousing"], "post_time": "2022-01-05T10:39:29Z", "salary": {"currency": null, "max": null, "min": null, "period": "monthly", "term": null}, "salary_visible": false, "title_keywords": ["coordinator"], "responsibilities": ["control", "management", "operations", "monitor", "quality", "p&l", "develop", "repair", "logistics", "contact", "analyse"], "requirements": {"degrees": ["bachelor degree holder"], "majors": [], "languages": ["cantonese", "english", "mandarin"], "language_level": ["good command"], "hard_skills": ["3pl management"], "soft_skills": ["stable", "interested in"], "languages_combined": [{"language": "cantonese", "language_level": ["good command"]}, {"language": "english", "language_level": ["good command"]}, {"language": "mandarin", "language_level": ["good command"]}]}, "experience_required": {"duration": [], "field": ["management", "team"]}}, {"job_id": "100003009017478", "location_code": "hk", "company": "The Garden Company Limited", "job_title": "Logistics Operations Manager", "description": "About the Job Role:\n\n\nRaise sales orders to third party logistics company, give clear instructions for deliveries and to ensure all required follow up actions can be fulfilled in a timely manner\nCommunicate with sales team on the order fulfillment\nHandle customer enquiries and coordinate within internal sales team\nStrong collaboration with Demand Planning team especially on stock availability and allocation arrangement\nFollow up on sales return deliveries and claims request from customers\nLiaise with third party logistics company for all stock management aspects, e.g. batch management compliance in respect to customers\u2019 requirement\nResponsible for customs declaration, handling full set of shipping and export documents independently\n\nWhat we expect from you:\n\nDegree holder/ Diploma in Supply Chain Management or business related disciplines\u00a0\nMinimum 3 years of related work experience in customer service, sales admin. coordination and shipping, preferably in Travel Retail or Beauty industry\nDetail-oriented, strong analytical and inventory management skills\nA fast learner, able to work independently and in a fast paced and dynamic environment\nGood communication and interpersonal skills\nProficient in Microsoft Office Excel and knowledge in SAP is preferable\nFluency in both written and spoken English is a must\n\n\n\nWe offer an attractive package to the right candidates. Interested parties please send detailed resume, salary history, expected salary and date available to L\u2019Occitane (Far East) Ltd.,\u00a020th\u00a0Floor, K11 ATELIER, 728 King\u2019s Road, Quarry Bay, Hong Kong, or e-mail to HR Department (email address shown in our company profile).\n\n(All personal data collected will be used for recruitment purpose only.)\n\nL\u2019OCCITANE is an Equal Opportunities Employer and is committed to ensuring that factors relating to its employees\u2019 ability to perform workplace responsibilities, and to develop in their employment, are the only ones considered in the decisions about their career with L\u2019OCCITANE.\n\nBuilding a more diverse and inclusive organisational culture is one of the ways we cultivate change.\n\nThis involves building an inclusive workplace that makes our people feel:\n\nsafe from any sort of discrimination or harassment\nrespected and valued for who they are as individuals.\n\nWe recruit competent and positive minded people who share our core values entrepreneurship, team spirit, leading by example and authenticity and our commitment to sustainability.", "employment_types": ["Full Time", "Permanent"], "selling_points": ["Plan and manage the logistics fleet", "Exercise quality control measures", "Review and formulate logistics policies"], "locations": ["Tsuen Wan Area"], "categories": ["Transportation & Logistics", "Others", "Fulfillment", "Supply Chain"], "post_time": "2022-01-04T00:41:21Z", "salary": {"currency": null, "max": null, "min": null, "period": "monthly", "term": null}, "salary_visible": false, "title_keywords": ["logistics", "operations manager"], "responsibilities": ["shipping", "demand planning", "inventory management", "communication", "customer service", "liaise with", "compliance", "order fulfillment", "logistics", "management", "handle customer enquiries", "stock management", "third party", "communicate with", "customs declaration", "a timely manner", "coordinate", "sales team", "coordination"], "requirements": {"degrees": ["diploma", "degree holder"], "majors": ["related disciplines", "business"], "languages": ["english"], "language_level": ["fluency"], "hard_skills": ["excel", "sap", "microsoft office", "demand planning", "batch", "dynamic"], "soft_skills": ["work independently", "independently", "dynamic environment", "responsible", "timely", "detail-oriented", "clear", "customer service", "communication and interpersonal skills", "coordination", "fast learner"], "languages_combined": [{"language": "english", "language_level": ["fluency"]}]}, "experience_required": {"duration": ["minimum 3 years"], "field": ["related", "admin", "customer service"]}}, {"job_id": "100003009024106", "location_code": "hk", "company": "NET-A-PORTER", "job_title": "\u5009\u52d9\u54e1 Picker/Packer", "description": "Job Description:\n\nOur client is a Renowned sourcing office. They are currently looking for a Supply Chain Analyst to join their Hong Kong team.\n\nKey Job Responsibilities include:\n\n\n\nWork closely with internal party and perform daily operation from order processing to shipment delivery\nManage vendor's performance and provide solutions for any production issues\nProvide suggestion and improvement plan in order to improve the supply chain process\nAd-hoc tasks assigned by manager\n\nOther requirements include:\n\nDegree holder in Supply Chain Management/Logistics/Business Administration or other related disciplines\nMinimum of 3 years' experience in or Supply Chain/ demand/inventory/supply planning or other related fields\nExperience in using SAP or ERP system is a plus\nProficient in MS Office, Excel, Access & PowerPoint\nStrong communication and analytic skills\nTravel if necessary", "employment_types": ["Full Time", "Permanent"], "selling_points": ["\u74b0\u5883\u6574\u6f54\u7684\u51b7\u6c23\u5009", "\u57f7\u8ca8\u3001\u5305\u88dd\u8ca8\u54c1", "\u5177\u5099\u57fa\u672c\u82f1\u8a9e\u80fd\u529b \u57fa\u672c\u96fb\u8166\u77e5\u8b58"], "locations": ["Tsing Yi"], "categories": ["Transportation & Logistics", "Others", "Fulfillment", "Inventory / Warehousing"], "post_time": "2022-01-05T10:44:25Z", "salary": {"currency": null, "max": null, "min": null, "period": "monthly", "term": null}, "salary_visible": false, "title_keywords": ["\u5009\u52d9\u54e1"], "responsibilities": ["ad-hoc tasks", "daily operation", "provide solutions", "order processing", "plan", "supply chain process"], "requirements": {"degrees": ["degree holder"], "majors": ["related disciplines", "business administration"], "languages": [], "language_level": [], "hard_skills": ["supply planning", "excel", "plus", "sap", "powerpoint", "analytic skills", "erp system", "ms office"], "soft_skills": ["communication"], "languages_combined": []}, "experience_required": {"duration": ["minimum of 3 years"], "field": ["related", "supply chain", "erp system", "planning"]}}, {"job_id": "100003009015944", "location_code": "hk", "company": "Penavico (Hong Kong) Limited", "job_title": "Logistics Assistant", "description": "YOOX NET-A-PORTER GROUP is the e-commerce leader in online luxury and fashion.\u00a0Operations are now seeking an Inbound Receiving Coordinator to join the Inbound team base in Tsing Yi Warehouse.\n\nJob Duties:\n\nMonitor receiving operation managing book-in, item count, QC check, bag & tag and put away\nMaintain the smooth flow of the Inbound team\nManage the UPH (Unit Per Hour) of different functions\nOther duties assigned by Manager\nRequirements:\n\nExperience in the E-commerce/logistics company is preferred\nProven leadership skills will be an advantage\nProficient in written and spoken Chinese and English\nPossess fair knowledge in MS\nAble to work under pressure and stringent deadlines\n\n\u00a0Working Hours:\n\nMonday to Friday 930am-630pm\n\nLocation:\n\nTsing Yi (10 mins shuttle bus away from Tsing Yi station)\n\nBenefits:\n\nClean and Tidy warehouse\nPerformance bonus schemes\n13 Days Annual Leaves & Bank Holiday\nCareer path & training\nStaff discount along with exclusive staff sales\nPrivate healthcare\nFor Interested parties, please email your CV and expected salary to\u00a0hkrecruitment@ net-a-porter.com\u00a0or WhatsApp 6651 2251 for further enquiries.", "employment_types": ["Full Time", "Permanent"], "selling_points": ["Double pay with Bonus", "Full attendance allowance and Lunch allowance", "Five working days"], "locations": ["Central"], "categories": ["Admin & HR", "Clerical / Admin Staff", "Transportation & Logistics", "Fulfillment", "Shipping"], "post_time": "2022-01-03T07:57:38Z", "salary": {"currency": null, "max": null, "min": null, "period": "monthly", "term": null}, "salary_visible": false, "title_keywords": ["logistics", "assistant"], "responsibilities": ["maintain", "monitor", "other duties"], "requirements": {"degrees": [], "majors": [], "languages": ["english", "chinese"], "language_level": ["proficient"], "hard_skills": ["e-commerce"], "soft_skills": ["leadership skills", "work under pressure"], "languages_combined": [{"language": "english", "language_level": ["proficient"]}, {"language": "chinese", "language_level": ["proficient"]}]}, "experience_required": {"duration": [], "field": ["logistics", "e-commerce"]}}, {"job_id": "100003009016131", "location_code": "hk", "company": "Spring Professional (Hong Kong) Limited", "job_title": "Logistics Manager \u2013 Power Tools", "description": "Responsibilities\n\nPlan and manage the logistics fleet and manpower resources to ensure a timely goods delivery in a professional and efficient manner.\u00a0\nExercise quality control measures to ensure accuracy of goods and prevent damages during delivery to our customers.\nReviewing and formulating logistics management related policies, guidelines and best practices together with setting up of data-base to drive continuous improvement.\nCollaborate with internal departments and external parties to integrate logistics with production, sales and the overall business systems in maximizing customer satisfaction, enhancing service quality and productivity\nPerform other ad-hoc projects as assigned\n\nRequirements\n\n\u00a0Degree holder in Business Management/ Logistics/Supply Chain Management\nWith 15 years related logistics experience in which at least 10 years\u2019 supervisory level,\u00a0 preferably in local logistics / distribution center management / manufacturing operations.\n\u00a0Computer literate and accounting knowledge is a plus\n\u00a0Strong communication, presentation and leadership skills\n\u00a0Mature and able to work independently and under pressure\n\nWorking Location: Sham Tseng\n\nInterested parties please click \"Apply Now\" or send the expected salary and available date, quote the job position and reference number to Human Resources Department, 1-11 Sham Tsz Street, Sham Tseng, New Territories, Hong Kong.\n\nAll the information collected will be used for the purpose of recruitment only.", "employment_types": ["Full Time"], "selling_points": ["Logistics Manager \u2013 Power Tools", "Global Leader in Power Tools industry", "MNC Exposure"], "locations": ["Not Specified"], "categories": ["Transportation & Logistics", "Fulfillment", "Inventory / Warehousing"], "post_time": "2022-01-03T08:22:24Z", "salary": {"currency": null, "max": null, "min": null, "period": "monthly", "term": null}, "salary_visible": false, "title_keywords": ["logistics manager"], "responsibilities": ["collaborate with", "management", "data", "guidelines", "policies", "external parties", "systems", "quality", "logistics", "quality control", "plan", "ad-hoc projects"], "requirements": {"degrees": ["degree holder"], "majors": ["business"], "languages": [], "language_level": [], "hard_skills": ["business management", "plus"], "soft_skills": ["work independently", "under pressure", "leadership skills", "mature", "communication", "presentation"], "languages_combined": []}, "experience_required": {"duration": ["at least 10 years", "15 years"], "field": ["management", "manufacturing", "related", "logistics", "supervisory level"]}}, {"job_id": "100003009017960", "location_code": "hk", "company": "AY Talent Solutions Limited", "job_title": "Airfreight Export (Cargo Planner)", "description": "Language requirement: Fluent in Mandarin and English\n\nLocation: Hongkong\n\nIn this role you will:\n\nlDocument issues and communicate with sellers and buyers to reach an optimal resolution according to marketplace guidelines.\n\nlEnsure orders in the fulfillment flow are solved and returned to the flow for same-day shipment.\n\nlDevelop an understanding of shoe conditions, specifically those that are considered \"issues\" by GOAT standards. Capable of picking shoes from inventory and processing specific returns and orders to buyers and sellers.\n\nlAble to take photos quickly and accurately of sneakers.\n\nlDevelop an understanding of GOATs order statuses to help triage escalated orders\n\nlBe able to work in a fast paced and team environment.\n\nWe are looking for:\n\nl2+ years of warehouse experience preferred.\n\nlHighly organized with demonstrated attention to detail.\n\nlBackground in dealing directly with customers and suppliers.\n\nlWilling and able to operate carts, dollies and other moving equipment to move quantities of merchandise.\n\nlA quick learner, a self-starter, able to work independently, and you're willing (and able) to handle the pressures of an increasing level of responsibility.\n\nlMust be able to stand for long periods of time (up to 12 hours).\n\nlMust be able to lift and move boxes (up to 35 pounds).\n\nlMust be available and willing to work extended hours as occasionally needed (during crunch times) per day or per week, including weekends and holidays, to meet business needs.", "employment_types": ["Full Time", "Permanent"], "selling_points": ["Dealing with airline and co-loader", "Prepare flight planning and loading plan", "Enhance productivity"], "locations": ["Tsuen Wan Area"], "categories": ["Transportation & Logistics", "Freight Forwarding", "Fulfillment", "Shipping"], "post_time": "2022-01-04T02:35:29Z", "salary": {"currency": null, "max": null, "min": null, "period": "monthly", "term": null}, "salary_visible": false, "title_keywords": [], "responsibilities": ["communicate with", "guidelines", "fulfillment", "inventory", "resolution"], "requirements": {"degrees": [], "majors": [], "languages": ["english", "mandarin"], "language_level": ["fluent"], "hard_skills": ["processing"], "soft_skills": ["organized", "work independently", "capable", "quick learner", "attention to detail"], "languages_combined": [{"language": "english", "language_level": ["fluent"]}, {"language": "mandarin", "language_level": ["fluent"]}]}, "experience_required": {"duration": [], "field": []}}, {"job_id": "100003009015506", "location_code": "hk", "company": "SEB Asia Limited", "job_title": "Senior Supply Chain Manager (Flow Management)", "description": "YOOX NET-A-PORTER GROUP\u662f\u5168\u7403\u9818\u5148\u7684\u7db2\u4e0a\u5962\u4f88\u6642\u88dd\u96f6\u552e\u5546\u3002\u6211\u5011\u4f4d\u65bc\u9752\u8863\u7684\u51b7\u6c23\u5009\u5eab\u73fe\u6b63\u62db\u8058\u5009\u52d9\u54e1\n\n\u5de5\u4f5c\u5167\u5bb9:\n\n\n\u65e5\u5e38\u5009\u52d9\u5de5\u4f5c\uff1a\u57f7\u8ca8\u3001\u5305\u88dd\u8ca8\u54c1 \u6216\u5176\u4ed6\u4e0a\u53f8\u5b89\u6392\u4e4b\u5de5\u4f5c\n\n\u5de5\u4f5c\u8981\u6c42:\n\n\n\u5177\u5099\u57fa\u672c\u82f1\u8a9e\u80fd\u529b\u00a0(\u670d\u88dd\u985e\u578b/\u8cea\u6599/\u984f\u8272)\n\u57fa\u672c\u96fb\u8166\u77e5\u8b58\n\u5de5\u4f5c\u7d30\u5fc3\u4ed4\u7d30\n\u6709\u670d\u88dd/\u5009\u52d9\u7d93\u9a57\u512a\u5148\u8003\u616e\n\n\u5de5\u4f5c\u6642\u9593:\n\n\u661f\u671f\u4e00\u81f3\u4e94 9:30am-6:30pm\u00a0\n\n\u5de5\u4f5c\u5730\u9ede:\n\n\u9752\u8863 \u2013 \u514d\u8cbb\u7a7f\u68ad\u5df4\u58eb\u5f80\u8fd4\u9752\u8863\u6e2f\u9435\u7ad9\n\n\u512a\u539a\u798f\u5229:\n\n\u4e00\u6d41\u7684\u5de5\u4f5c\u74b0\u5883\u6574\u6f54\u7684\u51b7\u6c23\u5009\n\n\u61c9\u5fb5\u8005\u8acb\u81f4\u96fb / WHATSAPP 6651 2251\u6216\u96fb\u90f5\u5c65\u6b77\u8868\u5230hkrecruitment @net-a-porter.com(*\u4eba\u529b\u8cc7\u6e90\u90e8*)\u9810\u7d04\u6642\u9593\u9762\u8a66\u3002(*\u7533\u8acb\u8cc7\u6599\u53ea\u4f5c\u62db\u8058\u7528\u9014*,\u4e26\u7d55\u5c0d\u4fdd\u5bc6\u3002)", "employment_types": ["Full Time", "Permanent"], "selling_points": ["Flow Management", "Be part of the global supply chain network", "5-day work, birthday leave, family leave"], "locations": ["Yau Tsim Mong Area"], "categories": ["Transportation & Logistics", "Fulfillment", "Supply Chain", "Merchandising & Purchasing", "Home Appliances"], "post_time": "2022-01-03T06:52:17Z", "salary": {"currency": null, "max": null, "min": null, "period": "monthly", "term": null}, "salary_visible": false, "title_keywords": ["supply chain manager"], "responsibilities": [], "requirements": {"degrees": [], "majors": [], "languages": [], "language_level": [], "hard_skills": ["whatsapp"], "soft_skills": [], "languages_combined": []}, "experience_required": {"duration": [], "field": []}}, {"job_id": "100003009014052", "location_code": "hk", "company": "Beauty Express Limited", "job_title": "Senior Logistic Officer", "description": "Job Responsibilities:\n\n1. Check and manage warehouse accounts, and check with the internal financial department to ensure that the accounts are clear;\n2. Confirm customer requirements and provide the most reasonable air transportation plan;\n3. Maintain good communication with suppliers and customers to ensure smooth cargo transportation;\n4. Prepare quotations, documents, customs declarations and other documents;\n5. Complete the on-site inspection work;\n6. Other tasks assigned by the department.\n\n\n\u00a0Job Requirements:\n\n1. Priority is given to those with experience in logistics operations such as shipping and air transportation;\n2. Those who are interested in freight, welcome fresh graduates;\n3. Good execution, communication skills and teamwork spirit;\n4. Language ability: English/Cantonese/Mandarin. Mastery: good;\n5. Basic computer knowledge, familiar with Microsoft software operation;\n6. Recognize the culture of Chinese-funded companies.\n", "employment_types": ["Full Time", "Permanent"], "selling_points": ["5 years logistic experience cosmetic retail", "Proactive and a good communicator", "Work life balance, friendly working environment"], "locations": ["Kwun Tong"], "categories": ["Transportation & Logistics", "Fulfillment"], "post_time": "2022-01-03T02:58:21Z", "salary": {"currency": null, "max": null, "min": null, "period": "monthly", "term": null}, "salary_visible": false, "title_keywords": ["logistic officer"], "responsibilities": ["other tasks", "maintain good communication", "plan", "site inspection"], "requirements": {"degrees": [], "majors": [], "languages": ["cantonese", "english", "chinese", "mandarin"], "language_level": [], "hard_skills": ["basic"], "soft_skills": ["communication skills", "interested in", "teamwork spirit"], "languages_combined": [{"language": "cantonese", "language_level": []}, {"language": "english", "language_level": []}, {"language": "chinese", "language_level": []}, {"language": "mandarin", "language_level": []}]}, "experience_required": {"duration": [], "field": ["logistics"]}}, {"job_id": "100003009014374", "location_code": "hk", "company": "The Garden Company Limited", "job_title": "Assistant Logistics Planning Manager / Logistics Planning Manager", "description": "Logistics Manager \u2013 Power Tools\n\n\nGlobal Leader in Power Tools industry\nMNC Exposure\n\nAbout Our Client:\nOur client is a leading Power Tools company with an extensive presence across over 120 locations globally. With their rapid growth especially in APAC region, they are now looking for a Logistics Manager in supporting their guaranteed service standard.\n\nMain Duties & Responsibilities:\n\nImplement tool service strategy based on regional roadmap, manage the warehouse to develop the team to a high performing and sustainable service standard for the aftersales service.\nActive driver of lean management principles like \u201cShop-floor management\u201d, \u201cLeadership\u201d, CIP (Continuous Improvement Process) and discipline of implementing standards to achieve operational excellence, to achieve a positive P&L.\nLead and coach an Operations team including customer service (for inbound and outbound), local repair experts, team leads, operations support and technicians towards operational excellence.\nCoordinate the day-to-day activities of the Tool Service Centre warehouse operations with 3PLs and monitor their service level against SLA process\nContinuously review the warehouse operation and drive optimization and reduction of warehousing cost\nChallenge the current standard operating procedures and lead continuous improvement in delivery execution, productivity, system functionality and quality\nManage warehousing KPIs and identify opportunities to improve to align with the productivity targets and report to management on a regular basis\nExecute seamless end to end customer experience through effective service processes for all customers, including complaint handling quotation and quality management.\nAccountable for people and competence development to ensure the organizational sustainability and build an engaging high performing team.\n\n\nCandidate Profile:\n\nBachelor or above in Logistics / Supply Chain Management / Business Administration or related disciplines.\n+ 5 years\u2019 experience in supply chain, 3PLs, distribution & transportation with strong commercial sense and customer orientation, experience to lead a team will be an advantage.\nProficient with ERP system including DRP/MRP\nProficient in any purchasing and inventory modules.\nHigh proficiency in English & Chinese (written & spoken)\nProject management or process improvement experience and able to construct and implement work-plans is an added plus.\n\n\nWhat to Expect:\nOur client offers the benefits of a work environment that is stimulating, challenging and balanced. You will be working in a Highly Visible, People Management Role within an Established Organization; and being part of an Employee Centric Business that provides a large degree of autonomy to their management team and encourage creativity and development of new ideas.\n\nPlease kindly send your CV to Kaela Chau for further information.", "employment_types": ["Full Time", "Permanent"], "selling_points": ["Strategic logistics operations planning", "Enhance service quality and productivity", "Immediate available is highly preferred"], "locations": ["Tsuen Wan Area"], "categories": ["Transportation & Logistics", "Others", "Fulfillment", "Supply Chain"], "post_time": "2022-01-03T03:20:04Z", "salary": {"currency": null, "max": null, "min": null, "period": "monthly", "term": null}, "salary_visible": false, "title_keywords": ["assistant logistics planning manager", "logistics planning manager"], "responsibilities": ["service standard", "operations", "inventory", "quotation", "quality", "customer service", "plans", "administration", "monitor", "p&l", "develop", "logistics", "kpis", "report", "warehousing", "management", "cost", "review", "procedures", "coordinate", "lead a team", "repair", "project management", "warehouse operations"], "requirements": {"degrees": ["bachelor"], "majors": ["related disciplines", "business administration"], "languages": ["english", "chinese"], "language_level": ["proficiency"], "hard_skills": ["lean", "plus", "sla", "erp system", "project management", "rapid"], "soft_skills": ["organizational", "accountable", "project management", "customer service", "leadership", "active", "extensive", "positive"], "languages_combined": [{"language": "english", "language_level": ["proficiency"]}, {"language": "chinese", "language_level": ["proficiency"]}]}, "experience_required": {"duration": ["5 years"], "field": ["supply chain", "quotation", "commercial", "project management", "quality management", "team"]}}, {"job_id": "100003009008497", "location_code": "hk", "company": "Cellarmaster Wines (H.K.) Limited", "job_title": "Sales Coordinator", "description": "\nThis role plays a key part in coordinate with different parties, strengthening operations processes and enhance productivity with good quality / service.\u00a0\n\nJob Description\n\nAssist to monitor the productivity and the daily operation of Air Freight Export Team\nCoordinate with all applicable parties for all air export shipments, including internal parties, customers, operations team, sales team, warehouse and sub-contractors\nHandle customer complaints and enquiries\nCoordinating with airline or co-loader reservation\nPrepare the flight planning and loading plan in cope with the cost & customer requirement\nMonitor document completion process & delivery cargo before the airline cut-off time, ensure documents handed over to terminal accurately and timely\nPerform any other duties as assigned by the Management\nRequirements\n\nDiploma or above in Logistics Management or related disciplines\nComprehensive product knowledge in air freight\n5-8 years relevant experience with at least 2 years in supervisor level\nExperience in handle DG, VAL and special cargo\nFamiliar with full set of air export documentation & cargo planning", "employment_types": ["Full Time"], "selling_points": [], "locations": ["Causeway Bay"], "categories": ["Transportation & Logistics", "Fulfillment", "E-commerce", "Supply Chain", "Sales, CS & Business Devpt", "Sales Administration"], "post_time": "2021-12-30T08:11:40Z", "salary": {"currency": null, "max": null, "min": null, "period": "monthly", "term": null}, "salary_visible": false, "title_keywords": ["sales coordinator"], "responsibilities": ["any other duties", "cost", "management", "air freight", "customer complaints", "operations", "daily operation", "coordinate with", "monitor", "sales team", "plan", "internal parties", "planning"], "requirements": {"degrees": ["diploma or above"], "majors": ["related disciplines"], "languages": [], "language_level": [], "hard_skills": ["documentation"], "soft_skills": ["comprehensive"], "languages_combined": []}, "experience_required": {"duration": ["at least 2 years", "5-8 years"], "field": ["relevant experience"]}}, {"job_id": "100003009008823", "location_code": "hk", "company": "Maxim's Caterers Ltd", "job_title": "Supply Chain Planning Specialist", "description": "Responsibilities:\n\nHandle day-to-day logistics operations and workflows including goods receiving, order handling, delivery arrangement, reverse logistics and warranty exchange\nClose collaboration with warehouse to ensure the services meet the business requirements\nWork with various departments to ensure a smooth supply chain system is in place\nInventory control to keep stock record align between WMS and ERP system\nHelp for stock planning, orders replenishment and delivery arrangement with suppliers\nConduct other ad hoc task as assigned\n\n\u00a0Job Requirements:\n\nHigh Diploma in Logistics or related field\n5+ years working experience preferably in cosmetic retail industry\nKnowledge in shipping is an advantage\nGood PC skills in MS Word and Excel, knowledge on POS System\nExcellent communication skill, proactive, multi-task, attention to details, organized and willing to learn\nGood command of both written & spoken Chinese and English\nImmediate availability is preferred.", "employment_types": ["Full Time"], "selling_points": ["Supply Planning", "Manage Supplier Performance", "Monitor Order Fulfilment"], "locations": ["Lai Chi Kok"], "categories": ["Hospitality / F & B", "Food & Beverage", "Transportation & Logistics", "Fulfillment", "Supply Chain"], "post_time": "2021-12-30T09:19:02Z", "salary": {"currency": null, "max": null, "min": null, "period": null, "term": null}, "salary_visible": false, "title_keywords": ["specialist"], "responsibilities": ["ad hoc", "operations", "replenishment", "inventory control", "logistics", "wms", "stock planning"], "requirements": {"degrees": ["high diploma"], "majors": [], "languages": ["english", "chinese"], "language_level": ["good command"], "hard_skills": ["excel", "pos system", "pc skills", "ms word"], "soft_skills": ["organized", "multi-task", "communication skill", "willing to learn", "attention to details", "proactive"], "languages_combined": [{"language": "english", "language_level": ["good command"]}, {"language": "chinese", "language_level": ["good command"]}]}, "experience_required": {"duration": ["5+ years"], "field": ["retail industry"]}}, {"job_id": "100003009007992", "location_code": "hk", "company": "Page Personnel", "job_title": "Customer Fulfilment Specialist - Raw Material Supplier", "description": "Mission:\nReporting to our Supply Chain Director, you will lead a team of supply chain professional (Supply Chain Managers, Master Production Schedulers, Supply Planners, and Supply Chain Officers, etc.) to contribute and guarantee SEB Customer Satisfaction and Product Availability globally.\nWhat\u2019s in it for you:\n\nManage manufacturing & suppliers\u2019 capacities in a very demanding context\nSecure 100% production schedule reliability and ensure the supply plan is feasible and workable by suppliers to fulfill customers\u2019 requirements\nManage a Global Stock Policy (Components & Sub-assembly)\nMinimize the risk of exposure on components by suppliers according to forecasts and process\nReduce suppliers\u2019 lead time and product MOQ to continuously improve service level to SEB subsidiaries and our customers\nPlay as a project team member to develop products in achieving the optimized schedule, price and quality\nMonitor supplier\u2019s performance to achieve KPI target in terms of SSL\nProvide strategic planning in response to the volatile supply chain environment\nPlay a strong role as a team leader and dedicated to team development\nWhat we are looking for:\nBachelor\u2019s Degree in Supply Chain / Logistics / Business or related field\nAt least 10-year experience in Logistics & Supply Chain Management and 5-year experience in a managerial capacity\nKnowledge in Supply Chain process (MRP II), APICS Training, etc.\nFamiliar with Supply Chain context, process and system\u00a0 (APO SNP & SAP DP)\nKnowledge in Small Domestic Appliances, plastics and electronics components is preferred\nSolid analytic, reporting and problem-solving skills \u00a0\nStrong sense of priorities, autonomy, responsiveness, responsibility, collaboration mindset and self-motivation\nGood communication, negotiation, presentation and interpersonal skills\nGood computer literacy in MS Office and Excel, SAP\nGood command of both spoken and written English as well as Chinese (Mandarin & Cantonese)\nWillingness for frequent travel, supplier visits\nWe offer attractive remuneration package to the right candidate including 5-day work, discretionary bonus,\u00a0family leave & birthday leave,\u00a0medical, dental / life insurance scheme, etc.\nInterested parties please apply with full resume with\u00a0expected salary\u00a0and current salary\u00a0to\u00a0Human Resources\u00a0Department. For company details, please visit our website.\nAll data collected is for recruitment purpose only. Candidates not invited for interview within 8 weeks from the date of this posting may consider their applications unsuccessful. Unsuccessful applications will be destroyed after 6 months.", "employment_types": ["Full Time", "Permanent"], "selling_points": ["Stable working hour", "Competitive salary", "Regional role"], "locations": ["Not Specified"], "categories": ["Transportation & Logistics", "Fulfillment", "Supply Chain", "Sales, CS & Business Devpt", "Sales Administration"], "post_time": "2021-12-30T06:14:16Z", "salary": {"currency": null, "max": null, "min": null, "period": "monthly", "term": null}, "salary_visible": false, "title_keywords": ["specialist"], "responsibilities": ["reporting", "management", "strategic planning", "quality", "monitor", "develop", "communication", "lead a team", "logistics", "schedule", "plan", "insurance", "supply chain process"], "requirements": {"degrees": ["degree", "bachelor", "master"], "majors": ["business"], "languages": ["cantonese", "english", "chinese", "mandarin"], "language_level": ["good command"], "hard_skills": ["small", "excel", "sap", "supply chain context", "scheme", "problem-solving skills", "ms office"], "soft_skills": ["negotiation", "communication", "computer literacy", "self-motivation", "interpersonal skills", "problem-solving skills", "team member", "presentation"], "languages_combined": [{"language": "cantonese", "language_level": ["good command"]}, {"language": "english", "language_level": ["good command"]}, {"language": "chinese", "language_level": ["good command"]}, {"language": "mandarin", "language_level": ["good command"]}]}, "experience_required": {"duration": ["at least 10-year", "5-year"], "field": ["supply chain", "management", "logistics", "managerial"]}}, {"job_id": "100003009008034", "location_code": "hk", "company": "Vitasoy International Holdings Ltd", "job_title": "Fleet Operations Officer", "description": "Daily delivery arrangement and perform orders fulfilment for online platform and warehouse management system;\nCommunicate with Logistics Supervisor, warehouse and delivery team on delivery arrangement and stock issue;\nCoordinate with Customer Service Executive in case of any problems on stock and delivery arrangement;\nPreparation of reports as required, e.g. inventory report, order summary, sales report etc.\nAssist in company events, if necessary\n\n\u00a0Requirements\n\nDiploma or above or with minimum 3 years\u2019 experience in order processing, preferable for online shop\nGood team player and able to work in a fast-paced environment\nGood problem solving, communication and negotiation skills\nProficiency in MS office\nFluent in Mandarin, English and Chinese (both spoken and written)", "employment_types": ["Full Time", "Permanent"], "selling_points": ["Fleet Operations", "Data Processing", "Tuen Mun, Double Pay, Medical Benefits"], "locations": ["Tuen Mun Area"], "categories": ["Transportation & Logistics", "Fulfillment", "Supply Chain"], "post_time": "2021-12-30T06:27:06Z", "salary": {"currency": null, "max": null, "min": null, "period": "monthly", "term": null}, "salary_visible": false, "title_keywords": ["operations officer"], "responsibilities": ["communicate with", "sales report", "inventory", "coordinate with", "warehouse management system", "communication", "customer service", "logistics", "reports", "order processing", "report"], "requirements": {"degrees": ["diploma or above"], "majors": [], "languages": ["english", "chinese", "mandarin"], "language_level": ["fluent"], "hard_skills": ["problem solving", "order processing", "ms office"], "soft_skills": ["good team player", "fast-paced environment", "communication", "problem solving", "negotiation skills", "customer service"], "languages_combined": [{"language": "english", "language_level": ["fluent"]}, {"language": "chinese", "language_level": ["fluent"]}, {"language": "mandarin", "language_level": ["fluent"]}]}, "experience_required": {"duration": ["minimum 3 years"], "field": ["order processing"]}}, {"job_id": "100003009011222", "location_code": "hk", "company": "Hongkong YunExpress Logistics Limited", "job_title": "Project Executive, APAC / Regional Executive Assistant", "description": "Responsibilities:\n\nPlan with different stakeholders to standardize the planning strategy and manage the changes effectively\nInitiate and lead short and long term supply plans to balance the demand forecast with cost, efficiency and capacity constraints\nResolve short term supply issues, identify and resolve any supply constraint to meet the long\u00a0term demand requirement\nServe as primary contact for supplier issues/performance and identify action\nEnsure timeliness of POs / replenishment\nManage the supply risk assessment to ensure order fulfillment\nMaximize inventory turns and optimize the warehouse space utilization to meet order fulfillment\n\nRequirements:\n\nBachelor Degree in Supply Chain, Business Administration, Logistics Management or related disciplines with at least 3 years\u2019 solid experience in demand forecast, supply and inventory\u00a0management, preferably in FMCG and F&B industry\nProgressive knowledge of supply planning or inventory management processes\nStrong analytical, quantitative and problem-solving\u00a0skills\nGood business acumen, with strong ability of multitasking and\u00a0time management\u00a0\nGood team player and able to work with minimum supervision\nProficient in MS office especially in Excel & PowerPoint. Experience in Oracle & SAP is preferred but not a must\nProficient in spoken and written Chinese and English\n\nInterested parties please apply with full resume, state current and expected salaries by clicking \"Apply Now\". All applications and data collected will be treated in strict confidence and used exclusively for recruitment purposes. Only short listed candidates will be invited for interview. The company will retain the applications for a maximum period of 24 months and may refer suitable candidates to other vacancies within the Group.", "employment_types": ["Full Time"], "selling_points": ["warehouse/logistics/airfreight overseas' support", "E-commerce logistics", "Start up, Fresh Graduates will be considered"], "locations": ["Kwai Fong"], "categories": ["Transportation & Logistics", "Freight Forwarding", "Fulfillment", "Supply Chain"], "post_time": "2021-12-31T06:46:22Z", "salary": {"currency": null, "max": null, "min": null, "period": "monthly", "term": null}, "salary_visible": false, "title_keywords": ["project executive", "executive assistant"], "responsibilities": ["cost", "inventory", "replenishment", "order fulfillment", "contact", "forecast", "plan", "plans", "planning"], "requirements": {"degrees": ["degree", "bachelor"], "majors": ["related disciplines", "business administration"], "languages": ["english", "chinese"], "language_level": ["proficient"], "hard_skills": ["supply planning", "excel", "oracle", "sap", "acumen", "powerpoint", "problem-solving skills", "ms office"], "soft_skills": ["good team player", "business acumen", "progressive", "problem-solving skills", "time management"], "languages_combined": [{"language": "english", "language_level": ["proficient"]}, {"language": "chinese", "language_level": ["proficient"]}]}, "experience_required": {"duration": ["at least 3 years"], "field": ["management", "fmcg", "business administration", "related", "supply chain", "inventory management", "f&b", "logistics"]}}, {"job_id": "100003009005248", "location_code": "hk", "company": "Stryker Pacific Ltd - Accounts", "job_title": "Supply Chain Lead Specialist", "description": "Excellent opportunity for order management experts to work for a leading chemical material manufacturer. The chosen candidate will be responsible for order management, logistics operation, supply chain management and customer inquiry handling.\n\nClient Details\n\nOur client is one of the most reputable companies within the chemical material suppliers. With over decades of history, they have been delivering the best products and services to the world. With steady and rapid expansion in business in Hong Kong, they are actively looking for an Order Fulfilment Specialist to join their dynamic company.\n\nDescription\n\nHandle full Bonded Logistics Park (BLP) process and U-Turn orders to ensure smooth logistics operation and delivery arrangement\nMonitor order status and production schedule by coordinating between multiple parties to drive customer satisfaction\nManage whole order processing including sales order documents, following up with customer, and logistics operation monitoring\nAssist in ad-hoc duties as per assigned\n\nProfile\n\nMinimum 5 years of experience in Customer Service/Logistics/Supply Chain/Order Fulfilment\nKnowledge in SAP, BLP process, U-Turn is a must\nStrong analytical skills with numerical sense\nOrganized and detail-oriented individual\nExcellent command in both English and Chinese\n\nJob Offer\n\nMNC Culture\nCompetitive pay\n5-day work", "employment_types": ["Full Time", "Permanent"], "selling_points": ["Fortune \"World's Best Workplaces 2021\" award", "We empower our People to own their career", "Comprehensive total rewards package"], "locations": ["Tai Koo"], "categories": ["Transportation & Logistics", "Fulfillment", "Inventory / Warehousing", "Supply Chain"], "post_time": "2021-12-29T03:39:33Z", "salary": {"currency": null, "max": null, "min": null, "period": "monthly", "term": null}, "salary_visible": false, "title_keywords": ["specialist", "lead"], "responsibilities": ["order management", "management", "monitoring", "monitor", "customer service", "logistics", "schedule", "order processing", "ad-hoc duties"], "requirements": {"degrees": [], "majors": [], "languages": ["english", "chinese"], "language_level": ["excellent"], "hard_skills": ["sap", "analytical skills", "dynamic", "order processing", "rapid"], "soft_skills": ["organized", "responsible", "analytical skills", "detail-oriented", "smooth", "dynamic", "customer service", "ad-hoc duties"], "languages_combined": [{"language": "english", "language_level": ["excellent"]}, {"language": "chinese", "language_level": ["excellent"]}]}, "experience_required": {"duration": ["minimum 5 years"], "field": ["supply chain", "customer service", "logistics"]}}, {"job_id": "100003009011262", "location_code": "hk", "company": "Kin Shun Information Technology Limited", "job_title": "Regional Operations Manager, Food & Quick Commerce", "description": "Why Stryker?\u00a0\n\n\nStryker is one of the world\u2019s leading medical technology companies and, together with our customers, is driven to make healthcare better.\n\nThe company offers innovative products and services in Orthopedics, Medical & Surgical, and Neurotechnology & Spine that help improve patient and hospital outcomes.\n\nWould you like to be part of a stellar organization that has seen 40 consecutive years of sales growth and has won numerous awards for being one of the world's best workplaces? Discover exciting opportunities at careers.stryker.com - we could be your next career destination!\n\n\nAbout the Role\u00a0\n\nThis role will lead the setup and continuous development of a robust 3PL management system in Hong Kong, managing 3PLs and interfacing with commercial and other functional teams with the objective to optimize the utilization of working capital and increase service levels for customers.\nYou will work closely with the Operations Manager and collaborate with the Order Management team to enhance the Order-to-Cash (\u201cOTC\u201d) process flow and ultimately drive the optimal cost-to-serve model. You will also partner with the Planning team to monitor inventory levels for stock allocation and fulfilment, and to provide timely responses to customers\u2019 enquiries.\n\nWhat You Will Be Doing :\n\nBe the change agent in leading & fine-tuning the 3PL management process, achieving this through a close working relationship with Order Management, Commercial and other functional teams.\nBe the primary contact for regular reviews with 3PLs to drive and improve performance quality.\nWork as a team with Order Management to define the relevant master data setup in internal systems to ensure the end-to-end process efficiency.\nOwn and drive functional improvements (kaizen events) through root cause analysis and problem solving.\nWork with IT to deploy systems and tool strategies.\nDefine and analyze operational KPIs, and develop improvement strategies and plans with Operations Manager.\nTriage and resolve any issues or customer complaints based on process and data analytics\nSupport Operations Manager and Supply Chain leaders in driving down the total Variable Manufacturing Cost.\nSupport the implementation of the Corporate and East Asia/HK supply chain structure and objectives.\nWho We Are Looking For :\nBachelor's Degree in Supply Chain Management, Logistics, Business or related fields.\n6 to 8 years\u00a0working experience in 3PL management in MNC commercial settings.\nProven ability in building up process framework(s).\nExperience in demand/supply forecasting and planning is an added advantage.\nExcellent data processing and analytical skills.\nResults-oriented with strong negotiation & influencing skills.\nConfidence and flair in managing stakeholder expectations and lead discussions.\nFluent in\u00a0verbal\u00a0and written English\u00a0and\u00a0Chinese\u00a0required to communicate with different stakeholders in the process.\nStrong project management / lean six sigma (Green-belt) experience.\nJDE / SAP implementation experience a strong plus", "employment_types": ["Full Time", "Permanent"], "selling_points": [], "locations": ["Lai Chi Kok"], "categories": ["Hospitality / F & B", "Food & Beverage", "Transportation & Logistics", "Fulfillment", "E-commerce", "Supply Chain"], "post_time": "2021-12-31T06:51:15Z", "salary": {"currency": null, "max": null, "min": null, "period": "monthly", "term": null}, "salary_visible": false, "title_keywords": ["operations manager"], "responsibilities": ["collaborate with", "data", "operations", "inventory", "quality", "deploy", "plans", "teams", "monitor", "implementation", "develop", "logistics", "kpis", "forecasting", "internal systems", "setup", "management", "cost", "customer complaints", "stock allocation", "contact", "communicate with", "order management", "analysis", "systems", "data processing", "project management", "planning"], "requirements": {"degrees": ["degree", "bachelor", "master"], "majors": ["business"], "languages": ["english", "chinese"], "language_level": ["fluent"], "hard_skills": ["lean", "plus", "sap", "data analytics", "analysis", "analytical skills", "problem solving", "make", "project management", "six sigma", "3pl management", "processing"], "soft_skills": ["confidence", "negotiation", "work as a team", "timely", "robust", "analytical skills", "problem solving", "project management", "patient", "innovative", "driven"], "languages_combined": [{"language": "english", "language_level": ["fluent"]}, {"language": "chinese", "language_level": ["fluent"]}]}, "experience_required": {"duration": ["6 to 8 years"], "field": ["commercial", "management", "project management", "planning"]}}, {"job_id": "100003009009665", "location_code": "hk", "company": "PARKnSHOP", "job_title": "Warehouse Operations Officer", "description": "You can enjoy:\n\nComprehensive Medical and Life insurance coverage, including your spouse and children\nExclusive company pension schemes\nMarriage, Maternity and Paternity Leave\nExclusive shopping discount, Bazaar Sales for our people only\nProfessional training and career advancement opportunities\n\nResponsibilities:\n\nAssist Warehouse Operations Manager in managing daily warehouse operations including but not limited to goods receiving, order picking, loading and transportation\nMonitor stock flow and system information accuracy to maintain warehouse shrinkage in an acceptable level\nMaximize warehouse space utilization by frequently review staff productivity and inventory reports\nUpdate Standard Operations Procedure (SOP) periodically to maintain a smooth and efficient operation flow\n\nRequirements:\n\nTertiary education or above in Supply Chain, Logistics Management or related disciplines\nAt least 2 years\u2019 experience in warehouse operations and with Retail, FMCG or eCommerce exposure is definitely an advantage\nAnalytical, detail-minded and independent\nCompetency in MS Office, especially in Word, Excel and PowerPoint\nGood command of spoken and written English and Chinese\n\nAn attractive salary and benefit package will be offered. Interested parties please forward detailed resume stating expected salary to: People Department, PARKnSHOP (HK) Limited, Watson House, 1-5 Wo Liu Hang Road, Fo Tan, N.T. or email to us.\n\nWe are an equal opportunity employer and welcome applications from all qualified candidates. The information provided will be treated in strict confidence and be used only for consideration of your application for relevant / similar posts within the A.S. Watson Group. All personal data of unsuccessful applicants will be destroyed within 12 months from the date of application.", "employment_types": ["Full Time"], "selling_points": [], "locations": ["Kwai Fong"], "categories": ["Transportation & Logistics", "Fulfillment"], "post_time": "2021-12-31T01:53:09Z", "salary": {"currency": null, "max": null, "min": null, "period": null, "term": null}, "salary_visible": false, "title_keywords": ["operations officer"], "responsibilities": ["operations", "inventory", "review", "monitor", "maintain", "reports", "warehouse operations"], "requirements": {"degrees": [], "majors": [], "languages": ["english", "chinese"], "language_level": ["good command"], "hard_skills": ["excel", "word", "powerpoint", "ms office"], "soft_skills": ["detail-minded", "independent"], "languages_combined": [{"language": "english", "language_level": ["good command"]}, {"language": "chinese", "language_level": ["good command"]}]}, "experience_required": {"duration": ["at least 2 years"], "field": ["ecommerce", "retail", "fmcg"]}}, {"job_id": "100003009013320", "location_code": "hk", "company": "Zenit (Hong Kong) Company Limited", "job_title": "\u5009\u52d9\u54e1 (Warehouse Assistant/ Stock keeper/ Store keeper/ Operator)", "description": "\u4e00\u822c\u8077\u8cac:\n\n\u8ca0\u8cac\u4e00\u822c\u5009\u52d9\u65e5\u5e38\u904b\u4f5c\uff0c\u8ca8\u7269\u9ede\u6536\u3001\u62c6\u8ca8\u3001\u642c\u8ca8\n\u8ddf\u55ae\u57f7\u8ca8\u3001\u8ca8\u7269\u4e0a\u67b6\u53ca\u4e0b\u67b6\n\u8655\u7406\u65e5\u5e38\u8a02\u55ae\u53ca\u66f4\u65b0\u5b58\u8ca8\u8a18\u9304\n\u6839\u64da\u6587\u4ef6\u6d41\u7a0b\u8a18\u9304\u53ca\u6b78\u6a94\n\u5b9a\u671f\u76e4\u9ede\u8ca8\u7269\u9032\u51fa\u4e4b\u6578\u91cf\n\u7dad\u6301\u8ca8\u5009\u4e4b\u79e9\u5e8f\u6574\u9f4a\n\u8ddf\u9032\u9000\u8ca8\u7dad\u4fee\u8ddf\u9032\u500b\u6848\n\u8655\u7406\u5176\u4ed6\u6307\u6d3e\u5de5\u4f5c\n\u6bcf\u661f\u671f\u5de5\u4f5c5\u5929\uff0c\u65e9\u4e0a9\u6642\u81f3\u4e0b\u53486\u6642\n\u65bc\u6574\u6f54\u53ca\u6709\u51b7\u6c23\u8ca8\u5009\u5de5\u4f5c\n\u8077\u4f4d\u8981\u6c42:\n\n\u4e2d\u4e94\u6216\u4ee5\u4e0a\u7a0b\u5ea6\n\u80fd\u95b1\u8b80\u53ca\u66f8\u5beb\u4e2d\u6587\u53ca\u95b1\u8b80\u7c21\u55ae\u82f1\u6587\n\u66fe\u6709\u5009\u52d9\u6216\u5176\u4ed6\u6587\u8077\u5de5\u4f5c\u7d93\u9a57\u5747\u53ef\n\u61c2\u57fa\u672c\u96fb\u8166\u53caMicrosoft Office\u64cd\u4f5c\n\u6709\u8cac\u4efb\u5fc3\uff0c\u505a\u4e8b\u6709\u689d\u7406\uff0c\u52e4\u596e\u597d\u5b78\uff0c\u5b88\u6642\n\u4e3b\u52d5\u7a4d\u6975\uff0c\u7368\u7acb\uff0c\u6709\u8cac\u4efb\u611f\uff0c\u5177\u5718\u968a\u7cbe\u795e\n\n\u672a\u6709\u76f8\u95dc\u5de5\u4f5c\u7d93\u9a57\u8005\u4e5f\u6703\u8003\u616e", "employment_types": ["Full Time", "Permanent"], "selling_points": ["5\u5929\u5de5\u4f5c \u65e9\u4e0a9\u6642\u81f3\u4e0b\u53486\u6642", "\u65bc\u6574\u6f54\u53ca\u6709\u51b7\u6c23\u8ca8\u5009\u5de5\u4f5c", "15 \u65e5 \u5927\u5047"], "locations": ["Tsuen Wan Area"], "categories": ["Transportation & Logistics", "Fulfillment", "Inventory / Warehousing"], "post_time": "2022-01-03T02:03:21Z", "salary": {"currency": null, "max": null, "min": null, "period": "monthly", "term": null}, "salary_visible": false, "title_keywords": ["operator", "warehouse assistant", "\u5009\u52d9\u54e1"], "responsibilities": [], "requirements": {"degrees": [], "majors": [], "languages": [], "language_level": [], "hard_skills": [], "soft_skills": [], "languages_combined": []}, "experience_required": {"duration": [], "field": []}}, {"job_id": "100003009009628", "location_code": "hk", "company": "PARKnSHOP", "job_title": "Production Officer (Fresh Food)", "description": "You can enjoy:\n\nComprehensive Medical and Life insurance coverage, including your spouse and children\nExclusive company pension schemes\nMarriage, Maternity and Paternity Leave\nExclusive shopping discount, Bazaar Sales for our people only\nProfessional training and career advancement opportunities\n\nResponsibilities:\n\nAssist Production Manager in managing daily production including but not limited to materials planning, manpower planning, and managing occupational health & safety standards\nMaximize production capacity and reduce the shrinkage by frequently review staff productivity and work procedure\nUpdate Standard Operations Procedure (SOP) periodically to maintain a smooth and efficient production flow\n\nRequirements:\n\nTertiary education or above in Service Operations Management, Food Safety & Technology or related disciplines\n2 years\u2019 experience in food production environment\nAnalytical, detail-minded and independent\nCompetency in MS Office, especially in Word and Excel\nGood command of spoken and written English and Chinese\n\nAn attractive salary and benefit package will be offered. Interested parties please forward detailed resume stating expected salary to: People Department, PARKnSHOP (HK) Limited, Watson House, 1-5 Wo Liu Hang Road, Fo Tan, N.T. or email to us.\n\nWe are an equal opportunity employer and welcome applications from all qualified candidates. The information provided will be treated in strict confidence and be used only for consideration of your application for relevant / similar posts within the A.S. Watson Group. All personal data of unsuccessful applicants will be destroyed within 12 months from the date of application.", "employment_types": ["Full Time"], "selling_points": [], "locations": ["Sheung Shui"], "categories": ["Transportation & Logistics", "Fulfillment"], "post_time": "2021-12-31T01:49:59Z", "salary": {"currency": null, "max": null, "min": null, "period": null, "term": null}, "salary_visible": false, "title_keywords": ["production officer"], "responsibilities": ["operations", "review", "maintain", "safety standards", "planning"], "requirements": {"degrees": [], "majors": [], "languages": ["english", "chinese"], "language_level": ["good command"], "hard_skills": ["excel", "word", "ms office"], "soft_skills": ["detail-minded", "independent"], "languages_combined": [{"language": "english", "language_level": ["good command"]}, {"language": "chinese", "language_level": ["good command"]}]}, "experience_required": {"duration": ["2 years"], "field": ["food"]}}, {"job_id": "100003009006704", "location_code": "hk", "company": "Gemini Personnel Limited", "job_title": "Senior Operation (5 days per week / HKD20K) PRC-J078075", "description": "Job Scope:\n\n1) Manage the Order Fulfilment Rate compliance include:\nUpkeep order fulfilment (OF) status of all routes of all teams\nPrepare OF report by route and focus area\nUpdate OF report for different format by team\nRouting System parameters update\nRouting System report running\nUpdate Remote Vending System alerts to team\nAssist ad-hoc projects by assignment\n2)\u00a0Assist in data mining from available systems (BO, LSS), information analysis and report drafting\n\n3) Handle any ad-hoc job task assigned by Div. Head or by Dept. Manager.\n\nEducation & Qualification Requirement\n1) Form 5 or above\n2)\u00a0At least 3 to 5 years relevant working experience in logistics, sales administration, engineering or related field preferred.\n3) Proficiency in PC applications such as MS Excel\u00a0\n4) Able to work independently\n\n", "employment_types": ["Full Time", "Permanent"], "selling_points": ["1-2 years sea freight operation exp in USA market", "Good spoken & written in English", "5 days work per week"], "locations": ["Kwun Tong"], "categories": ["Transportation & Logistics", "Freight Forwarding", "Fulfillment", "Shipping"], "post_time": "2021-12-29T09:58:36Z", "salary": {"currency": null, "max": null, "min": null, "period": "monthly", "term": null}, "salary_visible": false, "title_keywords": [], "responsibilities": ["ad-hoc", "sales administration", "analysis", "compliance", "teams", "systems", "logistics", "data mining", "ad-hoc projects", "report"], "requirements": {"degrees": ["form 5 or above"], "majors": [], "languages": [], "language_level": [], "hard_skills": ["analysis", "pc applications", "ms excel", "data mining", "focus"], "soft_skills": ["focus", "work independently"], "languages_combined": []}, "experience_required": {"duration": ["at least 3 to 5 years"], "field": ["sales administration", "engineering", "related", "relevant working experience", "logistics"]}}, {"job_id": "100003009004480", "location_code": "hk", "company": "Page Personnel", "job_title": "Assistant Logistics Manager - FMCG Trading Company", "description": "\u00a0Duties:\n\nSupport warehousing, logistics or airfreight deployment of branch companies in Asia Pacific Region\nProvide regional support on above regions\nIdentify and act on regional problems or else report to general manager\nSupport ad hoc tasks and project delivery\n\nRequirements:\n\nExcellent in Language including Chinese, English and Mandarin (any other Asian languages are a plus)\nExperience/degree in project management or logistics/supply chain is preferred\nDetail minded and strong communication skills\nGood knowledge in MS office and translation application", "employment_types": ["Full Time", "Permanent"], "selling_points": ["3PL Management", "Warehouse relocation project", "5-day work, medical"], "locations": ["Not Specified"], "categories": ["Transportation & Logistics", "Fulfillment", "Inventory / Warehousing", "Supply Chain"], "post_time": "2021-12-29T02:34:02Z", "salary": {"currency": null, "max": null, "min": null, "period": "monthly", "term": null}, "salary_visible": false, "title_keywords": ["logistics manager", "assistant"], "responsibilities": ["warehousing", "ad hoc tasks", "logistics", "report"], "requirements": {"degrees": ["degree"], "majors": ["project management"], "languages": ["english", "chinese", "mandarin"], "language_level": ["excellent"], "hard_skills": ["project management", "plus", "translation", "ms office"], "soft_skills": ["communication skills", "project management"], "languages_combined": [{"language": "english", "language_level": ["excellent"]}, {"language": "chinese", "language_level": ["excellent"]}, {"language": "mandarin", "language_level": ["excellent"]}]}, "experience_required": {"duration": [], "field": ["project management", "logistics", "supply chain"]}}, {"job_id": "100003009002101", "location_code": "hk", "company": "Page Personnel", "job_title": "Warehouse Supervisor - Top Tier Logistics Solution Provider", "description": "About Zeek\nZeek is the brand name under Kin Shun Information Technology Limited which incorporated in 2019. Zeek aims to provide smart logistics, SaaS solutions and online / offline integrated instant delivery service for Hong Kong and Southeast Asia market, meeting their needs for food & parcel delivery and last-mile logistics.\n\nWe strive for building an excellent delivery experience by adopting big data and artificial intelligence. With existing business in Hong Kong, Singapore, Malaysia, Thailand and Vietnam, we will continue to expand our business to Southeast Asia countries and regions like Taiwan, Philippines and Indonesia in near future.\n\nResponsibilities:\u00a0\n\nRepresent headquarter to oversee operational and financial KPIs of Food & Quick Commerce business across multiple SEA markets, and provide executional inputs to local operations teams in optimizing operational efficiency and service level\nTake lead in operational planning for launch of new markets or services in existing markets;\nMaintain right sets of indicators and reports for effective analysis on services and operations, and also identifying improvement opportunities for Hong Kong and overseas markets;\nFacilitate local operations team to diagnose existing issues in operations and the execution of initiatives by cooperating with various internal parties and external partners;\nTake ownership on urgent issues in operations and take timely actions;\nKeep abreast of the market\u2019s leading practices and understand competitors\u2019 operating models to ensure company\u2019s practice has its competitive advantages;\nShare knowledge and leading practices in operations in Headquarter for local operations teams to take reference;\nDevelop standard operating procedures and guidelines for overseas markets;\nDevelop BI report templates for operations management and monitoring across markets;\nPerform ad-hoc duties assigned by Management\n\nRequirements:\n\nDegree holder in any disciplines;\u00a0\nMinimum 4 years of experience in operations management, project management or consulting, with experiences in start-ups, logistic platforms, F&B or e-commerce sectors preferred;\nStrong planning and analytical skills with strong business sense and problem-solving skill;\nSensitive to numbers and capable in scientific analysis, candidates with BI reporting experience have advantage;\nProactive and able to work under pressure with multi-tasking ability;\nIndependent, self-motivated, detail-oriented, good team player and able to work in a fast paced and dynamic working environment;\nGood command of written and spoken English, Cantonese and Mandarin;\nProficient in MS applications, e.g. PowerPoint, Excel and Word\n\nWe offer competitive remuneration, birthday and work anniversary holidays and benefit packages to the right candidate.\n\nPlease send your detailed resume, with last and expected salary to our Human Resources Department by clicking \"Apply Now\u201d.\u00a0\u2028\n\n(All information collected will be treated in strict confidence and used solely for recruitment)", "employment_types": ["Full Time", "Permanent"], "selling_points": ["Supervisory level, leading a team of 6-8", "Warehouse operation monitoring", "Medical and dental convered"], "locations": ["Not Specified"], "categories": ["Transportation & Logistics", "Others", "Fulfillment", "Inventory / Warehousing"], "post_time": "2021-12-28T03:49:49Z", "salary": {"currency": null, "max": null, "min": null, "period": "monthly", "term": null}, "salary_visible": false, "title_keywords": ["logistics", "warehouse supervisor"], "responsibilities": ["management", "guidelines", "operations", "analysis", "monitoring", "teams", "diagnose", "procedures", "develop", "maintain", "reports", "ad-hoc duties", "kpis", "report", "internal parties", "planning"], "requirements": {"degrees": ["degree holder"], "majors": ["any disciplines"], "languages": ["cantonese", "english", "mandarin"], "language_level": ["good command"], "hard_skills": ["excel", "bi", "ms applications", "e-commerce", "problem-solving", "analysis", "word", "powerpoint", "analytical skills", "project management", "dynamic"], "soft_skills": ["self-motivated", "good team player", "independent", "capable", "business sense", "problem-solving", "analytical skills", "detail-oriented", "project management", "multi-tasking", "dynamic", "sensitive to numbers", "proactive", "work under pressure"], "languages_combined": [{"language": "cantonese", "language_level": ["good command"]}, {"language": "english", "language_level": ["good command"]}, {"language": "mandarin", "language_level": ["good command"]}]}, "experience_required": {"duration": ["minimum 4 years"], "field": ["consulting", "e-commerce", "project management", "f&b", "operations management"]}}]