[{"job_id": "100003009055327", "location_code": "hk", "company": "Hongkong United Dockyards Ltd", "job_title": "Commercial Assistant", "description": "Job Duties:\n\nProvide support to the commercial team (documentation, report generation, research,\u00a0analysis)\nMonitor, tack and report on customer performance and market trend\nCoordinate with other departments on the execution of day-to-day commercial operations and activities\nCreate compelling and creative presentations including research, graphics, structure, ect.\nSupport the planning, organizing and implementing marketing materials and activities\nAny other ad-hoc projects or assignments as required\n\nJob Requirements:\n\nDiploma or above. An associate or Bachelor's Degree holder in Business Administration, Economics, Shipping & Logistics, Maritime related would be advantageous\n3 years' experience in sizable organization, preferred in maritime, shipping & logistics business\nGood knowledge in office applications such as MS Word, Excel, Project, PowerPoint and Outlook\nGood communication skills in both spoken and written English and Chinese(Cantonese and Mandarin)\nA good team player, self starter with ability to work independently\n\nWe Offer:\n\n\n5-day work week\nstable working hours\nfree shuttle bus\u00a0\nmedical coverage\nstaff canteen\n\nWork Location: Tsing Yi (Free shuttle bus service provided)\n\nWe offer a competitive pay and benefits package to the right candidate. Interested parties, please email your resume providing details of the present and expected salary to the Manager - Human Resources & Training by clicking 'Apply Now' on JobsDB.\n\nWe are an equal opportunity employer and welcome applications from all qualified candidates. Personal data collected will be treated in the strictest confidence and handled confidentially by authorized personnel for recruitment-related purposes only within the HUD Group. Applicants not having heard from us within six weeks of the date of application may consider their application unsuccessful. The personal data of unsuccessful applicants will be destroyed after the recruitment exercise pursuant to the requirements of the Personal Data (Privacy) Ordinance in Hong Kong.", "employment_types": ["Full Time", "Permanent"], "selling_points": [], "locations": ["Tsing Yi"], "categories": ["Transportation & Logistics", "Others", "Maritime - General"], "post_time": "2022-01-18T02:12:30Z", "salary": {"currency": null, "max": null, "min": null, "period": "monthly", "term": null}, "salary_visible": false, "title_keywords": ["assistant"], "responsibilities": ["graphics", "marketing materials", "provide support", "operations", "analysis", "monitor", "coordinate with", "presentations", "planning", "documentation", "ad-hoc projects", "report"], "requirements": {"degrees": ["bachelor", "diploma or above", "degree holder"], "majors": ["economics", "business administration"], "languages": ["english", "mandarin"], "language_level": ["good"], "hard_skills": ["excel", "office applications", "powerpoint", "outlook", "ms word"], "soft_skills": ["communication skills", "good team player", "work independently"], "languages_combined": [{"language": "english", "language_level": ["good"]}, {"language": "mandarin", "language_level": ["good"]}]}, "experience_required": {"duration": ["3 years"], "field": ["sizable organization", "business", "logistics"]}}, {"job_id": "100003009056176", "location_code": "hk", "company": "Modern Terminals Ltd", "job_title": "Assistant Business Process Analyst  \u52a9\u7406\u696d\u52d9\u6d41\u7a0b\u5206\u6790\u4e3b\u4efb", "description": "The Role\n\nReporting to Manager, Operations Process and System, the job holder\u2019s major responsibilities are to:\n\nAssist in data capturing from system and perform analysis in supporting team operations\nAssist business analysis and stakeholders in developing business process flow\nHandle enquiries and collect user requirements from different units, and follow-up the analysis within team\nSupport manager and superior in daily administration and team operations\nSupport the development, implementation and maintenance of standard operating procedures\n\nThe Person\n\nThe ideal candidate should have / be:\n\nDegree holder in related discipline with 1 year relevant experience; or\nDiploma holder with 4 years relevant experience, or\nForm 5 or above with 6 years relevant experience\nKnowledge of using BI tools, e.g. Power BI, SQL, is an advantage\nAttend to details and able to work independently on multiple tasks\nStrong analytical, interpersonal and presentation skills\nGood command of both written and spoken English and Chinese (including Putonghua)\n\n\n\nWe offer competitive remuneration package to the right candidate(s). Please apply in confidence with full resume, present and expected salary and contact telephone number, by clicking \"APPLY NOW\".\n\nWhatsApp: 62838297\n\nWe are an equal opportunity employer and welcome applications from all qualified candidates. Personal data collected will be treated in the strictest confidence and only be used for recruitment related purpose. Applicants not invited for interview in 6 weeks may consider their application unsuccessful and your personal data will be destroyed after a period of 6 months.", "employment_types": ["Full Time", "Permanent"], "selling_points": [], "locations": ["Kwai Tsing Area"], "categories": ["Admin & HR", "Clerical / Admin Staff", "Professional Services", "Business Analysis / Data Analysis", "Transportation & Logistics", "Maritime - General"], "post_time": "2022-01-18T03:34:27Z", "salary": {"currency": null, "max": null, "min": null, "period": "monthly", "term": null}, "salary_visible": false, "title_keywords": ["analyst", "assistant"], "responsibilities": ["reporting", "power bi", "maintenance", "data", "operations", "analysis", "procedures", "developing", "implementation", "handle enquiries", "business process", "business analysis", "administration"], "requirements": {"degrees": ["diploma holder", "form 5 or above", "degree holder"], "majors": [], "languages": ["putonghua", "english", "chinese"], "language_level": ["good command"], "hard_skills": ["sql", "analysis", "bi", "maintenance"], "soft_skills": ["work independently", "multiple tasks", "presentation skills", "superior", "interpersonal", "ideal"], "languages_combined": [{"language": "putonghua", "language_level": ["good command"]}, {"language": "english", "language_level": ["good command"]}, {"language": "chinese", "language_level": ["good command"]}]}, "experience_required": {"duration": ["4 years", "6 years", "1 year"], "field": ["related", "relevant experience"]}}, {"job_id": "100003009052906", "location_code": "hk", "company": "Mediterranean Shipping Company (Hong Kong) Limited", "job_title": "Operations Assistant", "description": "Responsibilities\n\n-\u00a0Able to handle full set I/E Shipping documents\n\n- Familiar with operating CFS / CY / Consolidation Arrange bookings\n\n- Tradelink declaration\n\n- Direct communicate with clients, and forwarders for shipment arrangement\n\n- Responsible for data inputting, inventory and preparation of invoice\n\nRequirements\n\n-\u00a0At least 3-5 years in related fields (i.e. shipping or forwarder)\n\n- F.5 or DSE above\n\n- Good command of written Chinese and English, and Putonghua\n\n- Good communication and interpersonal skills\n\n- Familiar with PC operations (e.g. MS office, Chinese Word Processing)\n\n- Immediately available is preferred", "employment_types": ["Full Time", "Permanent"], "selling_points": ["Operations Assistant", "PC literate in MS Office", "DSE Graduate or above"], "locations": ["Lai Chi Kok"], "categories": ["Transportation & Logistics", "Shipping", "Maritime - General"], "post_time": "2022-01-17T04:30:00Z", "salary": {"currency": null, "max": null, "min": null, "period": "monthly", "term": null}, "salary_visible": false, "title_keywords": ["operations assistant"], "responsibilities": ["shipping documents", "communicate with", "shipment arrangement", "data", "inventory", "tradelink declaration", "preparation of invoice"], "requirements": {"degrees": ["dse"], "majors": [], "languages": ["putonghua", "english", "chinese"], "language_level": ["good command"], "hard_skills": ["pc operations", "chinese word processing", "ms office"], "soft_skills": ["communication and interpersonal skills"], "languages_combined": [{"language": "putonghua", "language_level": ["good command"]}, {"language": "english", "language_level": ["good command"]}, {"language": "chinese", "language_level": ["good command"]}]}, "experience_required": {"duration": [], "field": []}}, {"job_id": "100003009047840", "location_code": "hk", "company": "Pacific Basin Shipping (HK) Limited", "job_title": "TECHNICAL OFFICER - HONG KONG", "description": "Responsibilities\n\nTo assist in carrying out vessel operations tasks\nPort Formalities include Immigrations & Marine declaration\nBoarding, Stowage planning, Reporting etc\nPerform any other job duties assigned by immediate supervisor and management\n\n\nRequirements\n\nDSE gradate\u00a0or above\nSound PC literate in MS Offices\nGood command in both written and spoken English, Chinese\u00a0& Mandarin\nGood coordination and communication skills\nSelf-initiative, hard working and can work under pressure and independently\nFresh graduate will be considered\n\nThe successful candidates will be rewarded with an attractive salary and benefit package, which is commensurate with experience and qualifications. Please send your application with full resume stating current and expected salary, status of availability to the attention of HR Manager. 20/F, Lee Garden Two,\u00a028\u00a0Yun Ping\u00a0Road, Causeway Bay,\u00a0Hong Kong or\u00a0 click \"Apply Now\". Please mark the position applied.\n\n(All information provided by applications will be treated in strict confidence and used for recruitment purpose only.\u00a0 All personal data of unsuccessful applicants will be retained for 6 months for future recruitment purpose and will then be destroyed.)", "employment_types": ["Full Time", "Permanent"], "selling_points": ["At least 3 years' relevant experience", "Practical knowledge in marine or engineering", "Good command of written and spoken Eng & Mandarin"], "locations": ["Southern Area"], "categories": ["Engineering", "Others", "Transportation & Logistics", "Shipping", "Maritime - General"], "post_time": "2022-01-14T04:02:22Z", "salary": {"currency": null, "max": null, "min": null, "period": "monthly", "term": null}, "salary_visible": false, "title_keywords": ["technical officer"], "responsibilities": ["operations", "management", "reporting", "planning"], "requirements": {"degrees": ["fresh graduate", "dse"], "majors": [], "languages": ["english", "chinese", "mandarin"], "language_level": ["good command"], "hard_skills": ["pc literate"], "soft_skills": ["communication skills", "independently", "confidence", "hard working", "self-initiative", "coordination", "work under pressure"], "languages_combined": [{"language": "english", "language_level": ["good command"]}, {"language": "chinese", "language_level": ["good command"]}, {"language": "mandarin", "language_level": ["good command"]}]}, "experience_required": {"duration": [], "field": []}}, {"job_id": "100003009048850", "location_code": "hk", "company": "Vanguard Logistics Services (HK) Ltd", "job_title": "Senior / Export Operations Clerk", "description": "REQUIREMENTS\n\n\nPractical knowledge in marine or engineering is preferred;\nAt least 3 years\u2019 relevant experience in a ship owning / ship management company;\nGood command of written and spoken English and Mandarin;\nWell versed in computer skills;\nThe candidates who have more experience will be considered as Senior Technical Officer;\nCandidates are eligible to work in Hong Kong.\n\nJOB SCOPE\u00a0\n\n\nReporting to the Ship Managers;\nSupport the Fleet Managers and Ship Managers in the daily operations of vessels;\nMaintain records of vessels\u2019 returns and certification;\nEfficient and cost effective supply of stores and spares to vessels;\nCommunication with vessels\u2019 Class and statutory authorities;\nAnalysing drydocking quotes and preparing cost comparisons;\nDealing with repair work shops and engine makers.\n\nIf you are selected, you will be continuously assessed not only on the basis of your performance, but also on the basis of your behavior. Cultural fit and adherence to Company values is of paramount importance. Attractive remuneration and good benefits will be offered to the chosen candidate. Please apply with a full r\u00e9sum\u00e9, salary expectation and contact details to the Human Resources Department by clicking 'Apply Now'. You may also apply by WhatsApp to +852 6117 6848. WhatsApp is for application only, not for follow up communication. Please make sure there is a covering message and specify the position for which you are applying. (Application deadline:\u00a027 Jan 2022)\n\nAll applications will be treated in strict confidence and used solely for recruitment purposes.\u00a0", "employment_types": ["Full Time", "Permanent"], "selling_points": ["Export Operations Clerk", "Shipping Clerk", "Forwarder"], "locations": ["Sheung Wan"], "categories": ["Transportation & Logistics", "Freight Forwarding", "Shipping", "Maritime - General"], "post_time": "2022-01-14T07:26:53Z", "salary": {"currency": null, "max": null, "min": null, "period": "monthly", "term": null}, "salary_visible": false, "title_keywords": ["operations clerk"], "responsibilities": ["reporting", "management", "cost", "communication", "daily operations", "maintain", "repair"], "requirements": {"degrees": [], "majors": [], "languages": ["english", "mandarin"], "language_level": ["good command"], "hard_skills": ["computer skills"], "soft_skills": ["efficient", "communication"], "languages_combined": [{"language": "english", "language_level": ["good command"]}, {"language": "mandarin", "language_level": ["good command"]}]}, "experience_required": {"duration": ["at least 3 years"], "field": ["management", "relevant experience"]}}, {"job_id": "100003009043974", "location_code": "hk", "company": "Fleet Management Limited", "job_title": "Purchasing Officer", "description": "Job Position Summary\n\nThe Purchasing Officer would be a part of the procurement team based in Hong Kong. The Purchasing Officer is responsible for bulk chases as determined by the Shared Services Lead and assist in vendor/contract management.\nKey Roles and Responsibilities\n\ndentify the key specifications and key suppliers for bulk supplies\nLiaise with Buyers to determine the requirement and groups for delivery\nAssist the Category Manager in preparing the tender document in case required and send the requisition for the quotations\nCompare the cost with previously supplied similar items, to ensure better costing for bulk purchases\nMaintain standard price list for key store and spare items as identified by Purchase Manager\nMaintain contract file for approved vendors. Inform the purchase manager when a contract is lapsing\nVendor data base to be kept up to date. Unapproved vendors being used to be tracked and identified\nMaintenance of feedback on vendor performance\nOverview of the consolidation being done for freight and forwarding companies to be provided to the Purchase Manager\nReview of the freight and forwarding rates being applied to the company by the identified vendors to be compared and submitted to the Purchase Manager\nLiaise with Buyers and accounts department regarding the invoice payment status and update the vendor of the same.\nCollection of all overdue invoices from the technical teams and processing for consolidated payment.\nResponsible for collecting and documenting all technical information from the vessels, workshops, and vendors\nMaintain a record of total Business done by all Fleet offices, with all vendors and update on monthly basis\nFollow up on advance payments, make necessary entries in the cost book and liaise with suppliers, forwarders, vessels agents and the vessel for speedy dispatch\nMonitor and assist the Category Manager towards the pending invoice payment status\nDocuments housekeeping as per company requirements\nAs and when required assist Purchase Manager in collection and compilation of various ship related data from the technical teams\nAd hoc duties or projects as assigned by Superiors\n\n\n\nJob Experience, Functional Knowledge and Qualifications\n\nDegree holder of any faculty with minimum 2 \u2013 3 years of relevant work experience in procurement or Supply Chain\nPreferably 5 years of working experience in Ship Management\nProficient in Microsoft applications\nProficient in both written and spoken Chinese and English is a Must, any other Asian language is a plus\nFresh graduates will also be considered\nWe offer 5-day work, attractive salary and fringe benefits to the right candidate.\u00a0 Interested parties, please forward your full resume with present and expected salaries by clicking \"Apply Now\"\n\n\n(All information provided will be used for recruitment purpose only)", "employment_types": ["Full Time", "Permanent"], "selling_points": ["Fresh graduate will also be considered", "Relevant work experience in logistic/procurement", "Vendor management, contract management"], "locations": ["Aberdeen"], "categories": ["Transportation & Logistics", "Documentary Credit / Bills Processing", "Shipping", "Maritime - General"], "post_time": "2022-01-13T02:39:23Z", "salary": {"currency": null, "max": null, "min": null, "period": "monthly", "term": null}, "salary_visible": false, "title_keywords": ["purchasing officer"], "responsibilities": ["data", "purchase", "maintain", "payment", "liaise with", "tender document", "ad hoc duties", "invoices", "teams", "monitor", "cost", "management", "invoice", "review", "specifications", "maintenance", "housekeeping", "contract management", "payments", "liaise with suppliers"], "requirements": {"degrees": ["degree holder"], "majors": [], "languages": ["english", "chinese"], "language_level": ["proficient"], "hard_skills": ["inform", "plus", "maintenance", "microsoft applications", "vendor", "make", "workshops", "processing"], "soft_skills": ["determined", "responsible"], "languages_combined": [{"language": "english", "language_level": ["proficient"]}, {"language": "chinese", "language_level": ["proficient"]}]}, "experience_required": {"duration": ["3 years", "5 years"], "field": ["supply chain", "management", "procurement"]}}, {"job_id": "100003009043912", "location_code": "hk", "company": "Fleet Management Limited", "job_title": "Buyer", "description": "\n\u8077\u8cac :\u4e00\u822c\u8239\u9577\u5de5\u4f5c\uff0c\u4e3b\u8981\u8ca0\u8cac\u99d5\u99db\u62d6\u8239\uff0c\u78ba\u4fdd\u8239\u96bb\u822a\u884c\u5b89\u5168\uff1b\u57f7\u884c\u516c\u53f8\u5b89\u5168\u5b88\u5247\n\n\u8cc7\u6b77 :\u6c92\u6709\u5b78\u6b77\u8981\u6c42; 10\u5e74\u7d93\u9a57; \u826f\u597d\u7cb5\u8a9e; \u61c2\u8b80\u5beb\u4e2d\u6587; \u6301\u6709\u5e73\u5b89\u54ad; \u6301\u6709\u5efa\u9020\u696d\u5de5\u4eba\u8a3b\u518a\u8b49; \u719f\u7df4\u64cd\u63a7\u8239\u96bb\uff0c\u6301\u6709\u4e00\u7d1a\u8239\u4e3b\u724c\n\n\u5f85\u9047 :\u6bcf\u6708$25,000, \u661f\u671f\u4e00\u81f3\u516d: \u4e0a\u53488\u6642\u81f3\u4e0b\u53486\u6642, \u6bcf\u9031\u5de5\u4f5c6\u5929, \u6bcf\u5929\u5de5\u4f5c 9 \u5c0f\u6642\n\n\u7533\u8acb\u9808\u77e5 :\u6c42\u8077\u8005\u53ef\u81f4\u96fb26990681\u8207\u9999\u6e2f\u6d77\u4e8b\u627f\u5efa\u6709\u9650\u516c\u53f8\u9ec3\u5c0f\u59d0\u806f\u7d61\u3002\n\n", "employment_types": ["Full Time", "Permanent"], "selling_points": ["Fresh graduate will also be considered", "Relevant work experience in logistic/procurement", "Procurement, processing and documenting orders"], "locations": ["Aberdeen"], "categories": ["Transportation & Logistics", "Documentary Credit / Bills Processing", "Shipping", "Maritime - General"], "post_time": "2022-01-13T02:26:26Z", "salary": {"currency": null, "max": null, "min": null, "period": "monthly", "term": null}, "salary_visible": false, "title_keywords": [], "responsibilities": [], "requirements": {"degrees": [], "majors": [], "languages": [], "language_level": [], "hard_skills": [], "soft_skills": [], "languages_combined": []}, "experience_required": {"duration": [], "field": []}}, {"job_id": "100003009047932", "location_code": "hk", "company": "On Time Express Ltd", "job_title": "Import Operation Clerk, Sea Freight", "description": "Job Position Summary\n\nThe Buyer role would be a part of the shared services, based in Hong Kong. The Buyer is responsible for processing, documenting, and communicating the requisitions put in by the assigned vessels, adhering to policies and SOP\u2019s set by the shared services.\nKey Roles and Responsibilities\n\nBuyer performs day to day purchasing related activities to ensure safe and timely delivery of requisitions ordered by the vessel with due consideration to the criticality of the item\nResponds to the requisitions raised by vessels in company\u2019s purchase module which is Oracle Supply Chain\nCommunicates with Category leads regarding prices and deliveries\nAchieves the goal of cost efficient, safe & timely operations of vessels in accordance with company policy & procedures\nRoutine Duties\n\nCheck & analyze requisitions based on the requirement of stakeholders\nComply with available frame agreements prices pre-selected by the vessel\nIssue the Purchase Order (PO) with all the required details (i.e. ETB, agent details) once approved (To be confirmed)\nEnsure that supplier issues Order confirmation\nFollow up on the delivery two days before of ETB\nOver all duties\n\nDeals with category leads for supply of requested items of required on board\nCarefully takes care of the purchase flow to ensure the desired result which includes processing requisitions\nDaily coordination with vessels to ensure prompt information & immediately address queries and/or complaints\nContinuously improve service quality and productivity levels\nProactively share best practices across the teams\nCoordinates with vessel, agents and local ship chandlers for the smooth delivery of orders\nResolves issues regarding supply as raised directly by the vessel\nProvides feedback to Captain and Superintendent regarding local ship chandler for budget control\nProcess invoices for payment\n\nJob Experience, Functional Knowledge and Qualifications\n\nDegree holder of any faculty with minimum\u00a01 \u2013 3 years of relevant work experience in procurement, preferably ship management industry\nIVE or Diploma of any faculty with 3-6 years relevant work experience, preferably ship management industry\nIT literate for working with advanced procurement systems\nGood interpersonal & stakeholder management skills with ability to communicate at all levels\nHigh stress level, being comfortable handling numerous tasks within limited timeframes in a structured manner with eye for the detail\nStrong-minded with robust personality\nProficient in both written and spoken Chinese and English is a Must\nFresh graduates will also be considered\nWe offer 5-day work, attractive salary and fringe benefits to the right candidate.\u00a0 Interested parties, please forward your full resume with present and expected salaries by clicking \"Apply Now\"\n\n\n(All information provided will be used for recruitment purpose only)", "employment_types": ["Full Time", "Permanent"], "selling_points": ["Ocean import operation, handle import doc&booking", "Good team player & Customer-oriented", "Double pay, performance bonus & 5 days work"], "locations": ["Kowloon Bay"], "categories": ["Transportation & Logistics", "Freight Forwarding", "Shipping", "Maritime - General"], "post_time": "2022-01-14T04:18:03Z", "salary": {"currency": null, "max": null, "min": null, "period": "monthly", "term": null}, "salary_visible": false, "title_keywords": ["operation clerk"], "responsibilities": ["cost", "management", "invoices", "policies", "operations", "coordination with", "procedures", "quality", "teams", "systems", "purchase", "payment", "budget control"], "requirements": {"degrees": ["diploma", "degree holder"], "majors": [], "languages": ["english", "chinese"], "language_level": ["proficient"], "hard_skills": ["goal", "safe", "processing", "oracle"], "soft_skills": ["efficient", "advanced", "responsible", "prompt", "timely", "robust", "coordination", "smooth", "structured", "interpersonal"], "languages_combined": [{"language": "english", "language_level": ["proficient"]}, {"language": "chinese", "language_level": ["proficient"]}]}, "experience_required": {"duration": ["3 years", "3-6 years"], "field": ["management", "procurement"]}}, {"job_id": "100003009045164", "location_code": "hk", "company": "Hong Kong Marine Contractors Ltd", "job_title": "\u8239\u9577**", "description": "Role & Responsibilities\n\n\u00a0Responsible for full set Import shipping document\nResponsible for Import Declaration\nCommunicate with internal & overseas customer or vendors to ensure a smooth running of process\nControl the delivery time allocation\nAnswer rate and service inquiry\nCross check and submit job closing file by monthly end\nHandle ad hoc assignments by Supervisor\nEducation, Experience, Certification and Training requirements\n\n\nF.5 or above\nOver 1 years experience in freight forwarding for Sea import\n\nJob Skills and Competencies for this position\n\n\nImport declaration\nComputer- Word, Excel, PowerPoint, Access, FrontPage\nGood Command of spoken / written English & Fluent Mandarin\nGood timing management skill\nTyping \u2013 ENG 57 wpm ; Chinese 33 wpm\n\nWe offer\n\nDouble pay\nPerformance bonus\n5 days work\nFree shuttle bus\n\nIf you have the desire for an exciting and rewarding career, please send us your resume with stating your present and expected salary to Human Resources Department\n\nOnly short-listed candidates will be contacted.\n\nOn Time is an equal opportunity employer and welcomes applications from all qualified candidates. Information provided will be treated in strict confidence and will only be used for recruitment-related purposes. Personal data provided by job applicants will be used strictly in accordance.", "employment_types": ["Full Time"], "selling_points": [], "locations": ["To Kwa Wan"], "categories": ["Others", "Technician", "Transportation & Logistics", "Maritime - General", "Others"], "post_time": "2022-01-13T07:21:22Z", "salary": {"currency": null, "max": null, "min": null, "period": "monthly", "term": null}, "salary_visible": false, "title_keywords": [], "responsibilities": ["communicate with", "control", "management", "ad hoc assignments", "shipping document"], "requirements": {"degrees": [], "majors": [], "languages": ["english", "chinese", "mandarin"], "language_level": ["good command", "fluent"], "hard_skills": ["excel", "word", "powerpoint", "typing", "shipping document"], "soft_skills": ["responsible", "smooth"], "languages_combined": [{"language": "english", "language_level": ["fluent", "good command"]}, {"language": "chinese", "language_level": []}, {"language": "mandarin", "language_level": ["good command"]}]}, "experience_required": {"duration": ["1 years"], "field": ["training", "education"]}}, {"job_id": "100003009041822", "location_code": "hk", "company": "R&F Properties (HK) Company Limited", "job_title": "\u904a\u8247\u6c34\u624b (131\u5c3a\u79c1\u4eba\u904a\u8247)", "description": "Responsibilities :\n\nResponsible for handling customer service and keeping contact with the shippers and consignees\nTo handle orders follow up and work closely with overseas offices to update the cargo status\u00a0\nTo maintain and develop good relationship with external and internal parties so as to ensure good service to customers\nRequirements :\n\nDiploma or above\nAt least\u00a0 3 / 5 years' relevant experience in sea / air freight forwarding industry\nGood command of both spoken and written English and Mandarin\nGood interpersonal and communication skills\nProficiency in MS Office Applications\nPositive working attitude\u00a0\nData collection will be used for recruitment purpose only\n\nPlease send your resume in WORD format to\u00a0 :", "employment_types": ["Full Time", "Permanent"], "selling_points": [], "locations": ["Others"], "categories": ["Transportation & Logistics", "Maritime - General"], "post_time": "2022-01-12T04:26:54Z", "salary": {"currency": null, "max": null, "min": null, "period": "monthly", "term": null}, "salary_visible": false, "title_keywords": [], "responsibilities": ["develop", "good relationship", "maintain", "customer service", "contact", "internal parties"], "requirements": {"degrees": ["diploma or above"], "majors": [], "languages": ["english", "mandarin"], "language_level": ["good command"], "hard_skills": ["word", "ms office"], "soft_skills": ["communication skills", "interpersonal", "positive working attitude"], "languages_combined": [{"language": "english", "language_level": ["good command"]}, {"language": "mandarin", "language_level": ["good command"]}]}, "experience_required": {"duration": ["5 years"], "field": ["relevant experience"]}}, {"job_id": "100003009043008", "location_code": "hk", "company": "M B L Personnel Consultants Co", "job_title": "Executive, Air & Ocean 20-25K", "description": "Job Objective:\n\nSupport the achievement of business growth objective through identification, evaluation, planning and progression of prioritised opportunities with both existing and new clients, and new leads for business.\n\nSupport the effective and consistent implementation of enhanced sales and customer management capabilities, include use the relevant processes, templates and tools\n\nRequirements\n\nEducation & Qualifications:\n\n\u00a0\u00a0\u00a0\u00a0\u00a0\u00a0\u00a0\u00a0 Relevant degree from an accredited University or College\n\nWork Experience:\n\n\u00a0\u00a0\u00a0\u00a0\u00a0\u00a0\u00a0\u00a0 5 years\u2019 experience relevant experience in business development\n\u00a0\u00a0\u00a0\u00a0\u00a0\u00a0\u00a0\u00a0 Knowledge in Maritime industry is a plus\n\n\u00a0Job-Specific Skills:\n\n\u00a0\u00a0\u00a0\u00a0\u00a0\u00a0\u00a0\u00a0 Fluency in English with excellent written and verbal communication skills\n\u00a0\u00a0\u00a0\u00a0\u00a0\u00a0\u00a0\u00a0 Good analytical mind and able to understand business requirements\n\u00a0\u00a0\u00a0\u00a0\u00a0\u00a0\u00a0\u00a0 Proactive, positive, and persistent in achieving result\n\u00a0\u00a0\u00a0\u00a0\u00a0\u00a0\u00a0\u00a0 Good interpersonal and communications skills for relationship management with internal/external customer\n\u00a0\u00a0\u00a0\u00a0\u00a0\u00a0\u00a0\u00a0 Self-motivated, innovative, and keen on learn and develop\n\nWe offer competitive remuneration package to the right candidate. Interested candidates, please send your CV and application letter with information about your notice period, current and expected salary to HR Department, Bernhard Schulte Shipmanagement (Hong Kong) Limited Partnership, 26/F K Wah Center, 191 Java Road, North Point, Hong Kong or fax to 2960-1530 or apply through the \"Apply Now\" function.\u00a0 \u00a0\n\nPersonal data collected will be used for recruitment purpose only and treated in accordance with Personal Data (Privacy) Ordinance.", "employment_types": ["Full Time"], "selling_points": ["Diploma or above", "3  years' exp in sea & air freight industry", "Good benefits and good career path"], "locations": ["Kwun Tong"], "categories": ["Transportation & Logistics", "Freight Forwarding", "Shipping", "Maritime - General"], "post_time": "2022-01-12T09:31:28Z", "salary": {"currency": null, "max": null, "min": null, "period": "monthly", "term": null}, "salary_visible": false, "title_keywords": ["executive"], "responsibilities": ["management", "implementation", "develop", "communication", "evaluation", "planning"], "requirements": {"degrees": ["degree"], "majors": [], "languages": ["english"], "language_level": ["fluency", "excellent"], "hard_skills": ["plus"], "soft_skills": ["communication skills", "self-motivated", "persistent", "keen", "innovative", "analytical mind", "proactive", "interpersonal", "positive"], "languages_combined": [{"language": "english", "language_level": ["fluency", "excellent"]}]}, "experience_required": {"duration": ["5 years"], "field": ["business development", "relevant experience"]}}, {"job_id": "100003009039678", "location_code": "hk", "company": "Bernhard Schulte ShipMgt (HK) Ltd Partnership", "job_title": "Business Development Executive", "description": "\u8077\u8cac:\n\u8f14\u4f50\u8239\u9577\uff0c\u8ca0\u8cac131\u5c3a\u904a\u8247\u822a\u884c\u3001\u64cd\u4f5c\u7b49\u76f8\u95dc\u5de5\u4f5c\uff1b\n\u7de8\u5beb\u904a\u8247\u65e5\u5e38\u64cd\u4f5c\u8a18\u9304\uff1b\n\u78ba\u4fdd\u904a\u8247\u822a\u884c\u53ca\u904b\u4f5c\u5b89\u5168\uff1b\n\u8ca0\u8cac\u6e38\u8247\u6e05\u6f54\u53ca\u4fdd\u990a\u4e8b\u5b9c\uff1b\n\u63a5\u5f85\u8001\u95c6\u548c\u5ba2\u4eba\n\u8077\u4f4d\u8981\u6c42:\n\n\u6301\u6709\u4e8c\u7d1a\u904a\u6a02\u8239\u64cd\u4f5c\u4eba\u8b49\u660e\u66f8\uff1b\n\u64c1\u6709\u904a\u8247\u7684\u64cd\u4f5c\u6280\u8853\u77e5\u8b58\uff1b\n\u5177\u76f8\u95dc\u5de5\u4f5c\u7d93\u9a57\u4e09\u5e74\u6216\u4ee5\u4e0a\uff1b\n\u5f9e\u4e8b\u79c1\u4eba\u904a\u8247\u884c\u696d\u7d93\u9a57\u8005\u3001\u724c\u7167\u9f4a\u5168\u8005\u512a\u5148\u8003\u616e\uff1b\n\u4e2d\u4e09\u7a0b\u5ea6\u3001\u64cd\u826f\u597d\u7cb5\u8a9e\u3001\u80fd\u61c9\u4ed8\u4e00\u822c\u82f1\u8a9e\u6703\u8a71\u3001\u666e\u901a\u8a71\u66f4\u4f73\uff1b\n\u61c2\u6e38\u6cf3\u53ca\u5177\u6025\u6551\u8b49\u66f8\u8005\u512a\u5148\u8003\u616e", "employment_types": ["Full Time", "Permanent"], "selling_points": ["Support strategies of business development & sales", "Review and analyse market intelligence reports", "Prepare presentations and proposals professionally"], "locations": ["North Point"], "categories": ["Sales, CS & Business Devpt", "Business Development", "Transportation & Logistics", "Maritime - General"], "post_time": "2022-01-11T10:27:09Z", "salary": {"currency": null, "max": null, "min": null, "period": null, "term": null}, "salary_visible": false, "title_keywords": ["business development executive"], "responsibilities": [], "requirements": {"degrees": [], "majors": [], "languages": [], "language_level": [], "hard_skills": [], "soft_skills": [], "languages_combined": []}, "experience_required": {"duration": [], "field": []}}, {"job_id": "100003009034518", "location_code": "hk", "company": "Mediterranean Shipping Company (Hong Kong) Limited", "job_title": "Operations Assistant", "description": "Responsibilities\n\nTo assist in carrying out vessel operations tasks\nPort Formalities include Immigrations & Marine declaration\nBoarding, Stowage planning, Reporting etc\nPerform any other job duties assigned by immediate supervisor and management\n\n\nRequirements\n\nDSE gradate\u00a0or above\nSound PC literate in MS Offices\nGood command in both written and spoken English, Chinese\u00a0& Mandarin\nGood coordination and communication skills\nSelf-initiative, hard working and can work under pressure and independently\nFresh graduate will be considered\n\nThe successful candidates will be rewarded with an attractive salary and benefit package, which is commensurate with experience and qualifications. Please send your application with full resume stating current and expected salary, status of availability to the attention of HR Manager. 20/F, Lee Garden Two,\u00a028\u00a0Yun Ping\u00a0Road, Causeway Bay,\u00a0Hong Kong or\u00a0 click \"Apply Now\". Please mark the position applied.\n\n(All information provided by applications will be treated in strict confidence and used for recruitment purpose only.\u00a0 All personal data of unsuccessful applicants will be retained for 6 months for future recruitment purpose and will then be destroyed.)", "employment_types": ["Full Time", "Permanent"], "selling_points": ["Operations Assistant", "PC literate in MS Office", "DSE Graduate or above"], "locations": ["Lai Chi Kok"], "categories": ["Transportation & Logistics", "Shipping", "Maritime - General"], "post_time": "2022-01-10T03:33:50Z", "salary": {"currency": null, "max": null, "min": null, "period": "monthly", "term": null}, "salary_visible": false, "title_keywords": ["operations assistant"], "responsibilities": ["operations", "management", "reporting", "planning"], "requirements": {"degrees": ["fresh graduate", "dse"], "majors": [], "languages": ["english", "chinese", "mandarin"], "language_level": ["good command"], "hard_skills": ["pc literate"], "soft_skills": ["communication skills", "independently", "confidence", "hard working", "self-initiative", "coordination", "work under pressure"], "languages_combined": [{"language": "english", "language_level": ["good command"]}, {"language": "chinese", "language_level": ["good command"]}, {"language": "mandarin", "language_level": ["good command"]}]}, "experience_required": {"duration": [], "field": []}}, {"job_id": "100003009033141", "location_code": "hk", "company": "Marsh (Hong Kong) Limited", "job_title": "Assistant Vice President \u2013 Marine Practice", "description": "Responsibilities:\n\nProvides day-to-day service to clients in Marine/ Cargo industry to ensure that their risk management needs are appropriately met\nManaging and servicing existing portfolio, identifying and pursuing new business opportunities from existing clients and elsewhere\nAssisting in the design of insurance solutions to meet client needs and ensure client satisfaction\nResponsible for the execution of the renewal strategy in accordance with client instructions\nCoaching supporting staff to deliver timely and focused customer service\nObserving, implementing and enforcing operation policies and procedures\nImplementing action plans prepared by supervisors to meet team goals and targets\n\n\u00a0Requirements:\n\nUniversity or college graduate in maritime law, international shipping or transport logistics\nQualification in ANZIIF or ACII is preferable\nPossesses solid insurance brokerage, account management, servicing and sales skills.\nAt least 5-7 years\u2019 relevant experience in insurance with Marine insurance market knowledge is essential\nStrong communication and presentation skills\nAbility to build and forge strong relationship with major market partners\nProficient in written / spoken English and Chinese. Able to understand/ speak Putonghua is of\npreference\nGood PC Skills, including Word, Excel & PowerPoint\nAmbitious, solution focus and with strong skills in client relationship management\n\n\u00a0We offer:\n\nAttractive remuneration and incentives will be offered to the right candidate.\nA flexible work environment with policies and practices that reflect our commitment to Inclusion & Diversity.\nA psychologically safe environment where everyone is invited to share their perspective.\n\nThis is an excellent opportunity for candidates looking to progress their career with Marsh.\n\nJob applications should be sent in confidence with details in education, working history and salary expectation to us by applying below.\n\nWe are an Equal Opportunity Employer. Visit us at www.marsh-asia.com\n\nAll information received will be kept in strict confidence and be used only for employment-related purposes.", "employment_types": ["Full Time", "Permanent"], "selling_points": ["Maritime law, international shipping uni graduate", "At least 5-7 years insurance broking working exp", "Ambitious, solution focus, strong CRM skills"], "locations": ["Quarry Bay"], "categories": ["Insurance", "Insurance Agent / Broker", "Transportation & Logistics", "Maritime - General"], "post_time": "2022-01-08T10:44:41Z", "salary": {"currency": null, "max": null, "min": null, "period": "monthly", "term": null}, "salary_visible": false, "title_keywords": ["assistant vice president"], "responsibilities": ["management", "policies", "business opportunities", "procedures", "design", "customer service", "plans", "insurance"], "requirements": {"degrees": [], "majors": [], "languages": ["putonghua", "english", "chinese"], "language_level": ["proficient"], "hard_skills": ["excel", "word", "powerpoint", "focus", "pc skills"], "soft_skills": ["communication", "presentation skills", "focus"], "languages_combined": [{"language": "putonghua", "language_level": []}, {"language": "english", "language_level": ["proficient"]}, {"language": "chinese", "language_level": ["proficient"]}]}, "experience_required": {"duration": ["at least 5-7 years"], "field": ["insurance", "relevant experience"]}}, {"job_id": "100003009031887", "location_code": "hk", "company": "ZIM Integrated Shipping Services Ltd", "job_title": "Operations Analyst", "description": "Key Responsibilities\n\nPerform data analysis and ensure operation data correctness\nWork with partners and tackle various Operational matters\nPrepare Daily Position Report for Zim vessels also Partner vessels\nMonitor and confirm ship schedule updates\nCreate and update Voyage Schedules in system\nCompile Voyage Fuel Report and Voyage Summary\nMaintain up-to date information of all ship certificates / plans / documents\nMaintain Off-Hire Reports and Stevedores Damages reports\nCreate bunker requisitions\nOther operations matter as requested\n\nWho we are looking for\u00a0\n\nUniversity graduate in Shipping / Logistics related subjects\nFluent spoken and written English and Chinese (Mandarin & Cantonese)\nProficient in MS office (Excel)\nDiligent with strong sense of responsibility\nAble to work independently\nPreference is for person with Merchant Marine Background or already working in Shipping Industry\n\nWe offer\n\nExcellent opportunities for advancement with regional exposure\nCompetitive salary package\n5-Days Work\n15 - 17 days Annual Leave\nDouble Pay\nMedical & Dental Insurance\nLife Insurance\nBirthday Gifts\nMarriage Leave\nPaternity Leave\nWork from home arrangement\n\nInterested parties please share with us your latest resume showing current and expected remuneration package.", "employment_types": ["Full Time", "Permanent"], "selling_points": ["Newly-added headcount due to business expansion", "Data Analyst / Operations", "Intra Asia"], "locations": ["Kwun Tong"], "categories": ["Transportation & Logistics", "Shipping", "Supply Chain", "Maritime - General"], "post_time": "2022-01-07T09:54:01Z", "salary": {"currency": null, "max": null, "min": null, "period": "monthly", "term": null}, "salary_visible": false, "title_keywords": ["operations analyst"], "responsibilities": ["shipping", "data", "schedules", "operations", "monitor", "data analysis", "maintain", "reports", "schedule", "logistics", "plans", "operational matters", "report"], "requirements": {"degrees": ["university graduate"], "majors": [], "languages": ["cantonese", "english", "chinese", "mandarin"], "language_level": ["fluent"], "hard_skills": ["excel", "analysis", "ms office"], "soft_skills": ["work independently", "diligent", "sense of responsibility"], "languages_combined": [{"language": "cantonese", "language_level": ["fluent"]}, {"language": "english", "language_level": ["fluent"]}, {"language": "chinese", "language_level": ["fluent"]}, {"language": "mandarin", "language_level": ["fluent"]}]}, "experience_required": {"duration": [], "field": []}}, {"job_id": "100003009028944", "location_code": "hk", "company": "Pacific Basin Shipping (HK) Limited", "job_title": "OPERATIONS EXECUTIVE - HONG KONG", "description": "REQUIREMENTS\n\n\nUniversity graduate;\nMinimum 3 years\u2019 experience in the Shipping Industry is essential as we are willing to train the right candidate;\nCustomer focused with strong analytical skills;\nReliable team player, who is able to work with energy and creativity across time zones in an international organization;\nGood command of written and spoken English is a must; Mandarin skills is preferable; and\nCandidates must be eligible to work in Hong Kong.\n\nJOB SCOPE\u00a0\n\n\nTo efficiently handle commercial operations for dry bulk ships;\nTo work closely with other departments in the Company to maximize profits on each voyage;\nMaintain close relationships with Owners, Brokers and Service Providers to ensure commercial operations and dispute resolutions are handled efficiently;\nWillingness to work remotely from home if required.\nIf you are selected, you will be continuously assessed not only on the basis of your performance, but also on the basis of your attitude and behavior. Cultural fit and adherence to Company values is of paramount importance. Attractive remuneration and good benefits will be offered to the chosen candidate. Please apply with a full r\u00e9sum\u00e9, salary expectation and contact details to the Human Resources Department by clicking 'Apply Now'. You may also apply by WhatsApp to +852 6117 6848. WhatsApp is for application only, not for follow up communication. Please make sure there is a covering message and specify the position for which you are applying. (Application deadline:\u00a022 Jan 2022)\n\n\nAll applications will be treated in strict confidence and used solely for recruitment purposes.\u00a0\u00a0", "employment_types": ["Full Time", "Permanent"], "selling_points": ["University graduate", "Min. 3 years' experience in Shipping Industry", "Customer focused with strong analytical skills"], "locations": ["Southern Area"], "categories": ["Transportation & Logistics", "Others", "Shipping", "Maritime - General"], "post_time": "2022-01-07T03:39:19Z", "salary": {"currency": null, "max": null, "min": null, "period": "monthly", "term": null}, "salary_visible": false, "title_keywords": ["operations executive"], "responsibilities": ["maintain", "operations", "shipping", "work closely with other departments"], "requirements": {"degrees": ["university graduate"], "majors": [], "languages": ["english", "mandarin"], "language_level": ["good command"], "hard_skills": ["analytical skills"], "soft_skills": ["focused", "analytical skills", "willingness to work", "team player", "reliable"], "languages_combined": [{"language": "english", "language_level": ["good command"]}, {"language": "mandarin", "language_level": []}]}, "experience_required": {"duration": ["minimum 3 years"], "field": ["shipping industry"]}}, {"job_id": "100003009028731", "location_code": "hk", "company": "Wilhelmsen Ships Service Limited", "job_title": "Senior Customer Service & Sales Advisor", "description": "Founded in Norway in 1861, Wilhelmsen is now a comprehensive global maritime group providing over half of the merchant fleet with essential products and services, along with supplying crew and technical management to the largest and most complex vessels ever to sail. Committed to shaping the maritime industry, we also seek to explore and develop new opportunities within the renewables, offshore and energy industries. Supporting a diverse and inclusive workplace, with thousands of colleagues in more than 70 countries, we take competence, sustainability, innovation, and unparalleled customer experiences one step further.\n\nWe are looking for a Senior Customer Service & Sales Advisor to join our Marine Products Division.\n\nThe people at Wilhelmsen don\u2019t just hold jobs here. They make the most innovative ideas a reality \u2013 and in the process, they shape the maritime industry. With one of the largest maritime networks in the world, we do work that makes an impact - if it floats, our products are probably on it.\n\nSupplying marine consumables, products, and solutions to every conceivable vessel type, our Marine Products division includes the Unitor brand of products, Timm ropes, Unicool refrigerants, and Unitor and Nalfleet marine chemicals. Last year we made product deliveries to 27,500 vessels, at over 2,000 ports.\n\nThe position will report to Customer Support Manager and must closely cooperate with Sales, Order Processing Centres and Operation.\n\nRequired experience and skills\n\nBachelor or similar degree in business related studies or relevant work experience\nFluent in English \u2013 both in writing and speaking\nComputer literate, telephone sales skills, analytical skills\nSolid commercial understanding, with professional and proactive attitude and ability to identify business opportunities\nSupporting and co-operating attitude: adapts to the team and builds team spirit; listens, consults and communicates proactively; upholds ethics and vales\n\nMain Responsibilities\n\nAdvise and support customers on what to buy, where to buy, why to buy and how to buy from WSS MP through good commercial and technical guidance.\nProactively follow up enquiries and RFQs and capture sales opportunities through planned quote follow up.\nIdentify and actively pursue sales and order building opportunities through telephone sales expertise.\nActively promote to customers sales campaigns, promotions and initiatives\nWork closely with the customers, understanding their needs and supporting their requirements related to the total WSS customer offer.\nCapture customer specific information and requirements in the system and work proactively with customers to help them standardize their requests.\nAssist Order Processing Coordinators with interpreting the RFQs and POs and with seeking technical advice if appropriate.\nProcess certain high value and pre-defined enquiries and orders from customers as per global process and targets, and keep customers informed of changes in the order delivery status, surcharges and any other relevant information.\nKeep Account Managers, Sales Support and Credit aware of all key issues relating to their customers.\nTo be a member of the sales team for the respective account portfolio.\nResponsible for handling of warranty claims, product return and change in cylinder ownership as per prevailing policies and procedures.\nFollow up complaints/non-compliances through improvement/complaint system in place.\nTo manage the day to day activities in the team and where appropriate take active part in the daily customer handling.\nResponsible for performance assessment, coaching, training and development of the team members\nTo support recruit and manage staff according to company values, rules and regulations.\nActively promote use & review of IP Log, reporting lessons learned, improvements & suggestions\n\nSounds interesting? If you can see yourself in this role, please let us know why you are our new Customer Service and Sales Advisor.\n\nYou can apply online today through our career portal by creating a \"Candidate Home\" account. Here you an upload your resume and a motivational letter.\n\nwww.wilhelmsen.com\n\nApplication Deadline: 21 January 2022\n", "employment_types": ["Permanent"], "selling_points": ["Sell and drive sales of the marine rope offer", "Implementing the company strategy", "Monitor performance & implement corrective action"], "locations": ["Kwun Tong"], "categories": ["Sales, CS & Business Devpt", "Customer Service - Supervisor / Officer", "Transportation & Logistics", "Shipping", "Maritime - General"], "post_time": "2022-01-07T03:00:42Z", "salary": {"currency": null, "max": null, "min": null, "period": "monthly", "term": null}, "salary_visible": false, "title_keywords": ["customer service", "sales advisor"], "responsibilities": ["regulations", "guidance", "management", "reporting", "ideas", "identify business opportunities", "policies", "technical advice", "review", "procedures", "develop", "customer service", "sales team", "order processing", "cooperate with", "report"], "requirements": {"degrees": ["degree", "bachelor"], "majors": ["business"], "languages": ["english"], "language_level": ["fluent"], "hard_skills": ["sales support", "pos", "analytical skills", "make", "ip", "order processing", "sail"], "soft_skills": ["active", "proactive", "team spirit", "responsible", "analytical skills", "committed", "diverse", "comprehensive", "customer service", "innovative"], "languages_combined": [{"language": "english", "language_level": ["fluent"]}]}, "experience_required": {"duration": [], "field": ["related", "business", "sustainability"]}}, {"job_id": "100003009025375", "location_code": "hk", "company": "Anglo-Eastern Ship Management Limited", "job_title": "Fleet Operations Officer", "description": "Responsibilities:\n\nTo monitor the vessels\u2019 position reports, passage routings and voyage progress\nTo verify timely receipt of various reports and follow-up on any overdue reports\nTo issue notices to vessels in sufficient time for them to be acted upon, and maintain a record of these\nTo make port agency appointments, arrange funds to cover port disbursements, and track and monitor the circulation of port agency disbursements accounts to facilitate final settlements.\u00a0\nPopulate various records in office based upon information received from vessels and other sources\nLiaise with insurance companies and internally with other departments in office for opening of insurance cases up to closure.\n\nRequirements:\n\nDiploma or above in maritime studies will be preferred or equivalent qualifications and with at least 1 years working experience\nFresh graduates will be considered\nFluent in spoken and written English\nSound PC knowledge, especially with MS Office\nDynamic & able to work under pressure with excellent time management skills\nWe are an equal opportunity employer and welcome applications from all suitably qualified candidates.\u00a0\u00a0\n\n\nPersonal information collected by us will be treated in strictest confidence according to the Hong Kong Personal Data (Privacy) Ordinance.", "employment_types": ["Full Time", "Permanent"], "selling_points": ["Fresh graduates welcomed", "MNC", "Work-life balance"], "locations": ["Kowloon Bay"], "categories": ["Transportation & Logistics", "Shipping", "Supply Chain", "Maritime - General"], "post_time": "2022-01-06T04:17:16Z", "salary": {"currency": null, "max": null, "min": null, "period": "monthly", "term": null}, "salary_visible": false, "title_keywords": ["operations officer"], "responsibilities": ["monitor", "maintain", "reports", "insurance", "liaise with", "disbursements"], "requirements": {"degrees": ["diploma or above"], "majors": [], "languages": ["english"], "language_level": ["fluent"], "hard_skills": ["pc knowledge", "dynamic", "ms office"], "soft_skills": ["time management skills", "dynamic", "confidence", "work under pressure"], "languages_combined": [{"language": "english", "language_level": ["fluent"]}]}, "experience_required": {"duration": ["at least 1 years"], "field": []}}, {"job_id": "100003009024511", "location_code": "hk", "company": "L&P Global Supply Chain Solutions", "job_title": "Logistics Operations Coordinator", "description": "DUTIES & RESPONSIBILITIES:\n1.\u00a0 Assist Director in Hong Kong\n2.\u00a0 Coordinate E2Open Amber Road on information input.\n3.\u00a0 Maintain close coordination with L&P global offices as needed.\n4.\u00a0 Maintain shipment record report.\n5.\u00a0 Coordinate shipments for all designated L&P branches and provide high quality customer\u00a0\nservice, this would include monitoring costs associated with these shipments & updating systems accordingly.\n6.\u00a0 Coordinate suppliers in Southeast Asia.\n7.\u00a0 Coordinator with be responsible to identify and problems or delays related to the transportation and report in a timely manner.\n8.\u00a0 Coordinate with service providers including ocean carriers and freight forwarders.\n9.\u00a0\u00a0Coordinator will be responsible to initiate, recommend or provide solutions through designated channels and verify the implementation of\u00a0such solutions.\n\nQUALIFICATIONS:\n1.\u00a0 Bachelor degree or equivalent combination of education and experience.\n2.\u00a0 Minimum two years\u2019 experience in logistics/transportation operations, and/or assistant\u00a0function. Freight forwarding\u00a0and shipping line experience is a must.\n3.\u00a0 Verbal and written communication skills in English and Mandarin.\u00a0\u00a0\n4.\u00a0 Proficiency in Microsoft Office, especially Word, Excel and Outlook.\n5.\u00a0 Mathematical aptitude.\n6.\u00a0 Detail oriented.\n7.\u00a0 Ability to manage multiple tasks and projects.\n8.\u00a0 Knowledge of principles and processes required for moving goods via ocean, air, rail, and road including relative costs and benefits.\n\n", "employment_types": ["Full Time"], "selling_points": ["Dental insurance, Medical insurance", "Five-day work week, Double Pay", "Performance bonus"], "locations": ["Kwai Fong"], "categories": ["Transportation & Logistics", "Freight Forwarding", "Supply Chain", "Maritime - General"], "post_time": "2022-01-06T01:30:25Z", "salary": {"currency": "HKD", "max": 24999, "min": 20000, "period": "monthly", "term": null}, "salary_visible": true, "title_keywords": ["operations", "coordinator", "logistics"], "responsibilities": ["shipping", "operations", "coordination with", "quality", "monitoring", "systems", "a timely manner", "coordinate", "coordinate with", "provide solutions", "maintain", "implementation", "logistics", "communication", "costs", "report"], "requirements": {"degrees": ["degree", "bachelor"], "majors": [], "languages": ["english", "mandarin"], "language_level": [], "hard_skills": ["excel", "outlook", "word", "microsoft office"], "soft_skills": ["communication skills", "responsible", "multiple tasks", "timely", "detail oriented", "coordination"], "languages_combined": [{"language": "english", "language_level": []}, {"language": "mandarin", "language_level": []}]}, "experience_required": {"duration": ["minimum two years"], "field": ["logistics", "education"]}}, {"job_id": "100003009031895", "location_code": "hk", "company": "ZIM Integrated Shipping Services Ltd", "job_title": "Assistant / Ship Planner", "description": "Key Responsibilities\n\nPlan and monitor vessel safe condition\nManage suitable loading position for all DG, OOG and special containers\nBe responsible for creating high quality stowage plans for loading and discharge for each vessel\nOptimize trim (TROP), crane split, cargo intake and planning of empty containers\nMinimize shifting, hatch cover operation\nMaximum the crane intensity to reduce port stay and reduce speed / save bunker\n\nWho we are looking for\n\nBachelor's degree or above in shipping / logistics or related disciplines\n2-3 years' experience in Stowage Planning preferred\nAbility to follow through the stowage plan on round-trip basis\nIndependent, proactive, has sense of urgency\nTechnical knowledge of stowage planning systems and stability programs are added advantage\nGood command of written and spoken English\nFresh graduates are also welcome\n\nWe offer\n\nExcellent opportunities for advancement with regional exposure\nCompetitive salary package\n5-Days Work\n15 - 17 days Annual Leave\nDouble Pay\nMedical & Dental Insurance\nLife Insurance\nBirthday Gifts\nMarriage Leave\nPaternity Leave\nWork from home arrangement\n\nInterested parties please share with us your latest resume showing current and expected remuneration package.", "employment_types": ["Full Time", "Permanent"], "selling_points": ["New headcount due to business expansion", "Stowage planning", "Fresh graduates are also welcome"], "locations": ["Kwun Tong"], "categories": ["Transportation & Logistics", "Freight Forwarding", "Shipping", "Maritime - General"], "post_time": "2022-01-07T09:54:41Z", "salary": {"currency": null, "max": null, "min": null, "period": "monthly", "term": null}, "salary_visible": false, "title_keywords": ["assistant"], "responsibilities": ["shipping", "systems", "quality", "monitor", "logistics", "plan", "plans", "planning"], "requirements": {"degrees": ["degree or above", "bachelor"], "majors": ["related disciplines"], "languages": ["english"], "language_level": ["good command"], "hard_skills": ["safe"], "soft_skills": ["urgency", "proactive", "independent", "responsible"], "languages_combined": [{"language": "english", "language_level": ["good command"]}]}, "experience_required": {"duration": ["2-3 years"], "field": ["planning"]}}, {"job_id": "100003009020794", "location_code": "hk", "company": "Wilhelmsen Ships Service Limited", "job_title": "Customer Coordinator (Global Agent, Customer Service Department)", "description": "Customer Coordinator (Global Agent, Customer Service Department)\n\n\nFounded in Norway in 1861, Wilhelmsen is now a comprehensive global maritime group providing over half of the merchant fleet with essential products and services, along with supplying crew and technical management to the largest and most complex vessels ever to sail. Committed to shaping the maritime industry, we also seek to explore and develop new opportunities within the renewables, offshore and energy industries. Supporting a diverse and inclusive workplace, with thousands of colleagues in more than 70 countries, we take competence, sustainability, innovation, and unparalleled customer experiences one step further.\n\nWe are looking for a Global Agent to join our Ships Agency division.\n\nIn Ships Agency, we provide our customers with piece of mind while we handle their cargo, their vessels and their crew. We handle 75,000 port calls per year, which means that every 7 minutes, anywhere around the world, we send a ship safely out to sea again to fulfil its purpose. We match local expertise with strict global standards, making sure we consistently make our customers\u2019 port calls as efficient and safe as possible.\n\nJob Description\n\nMain Responsibilities\n\nManage existing contracts for\u00a0Ships Agency\u00a0customers.\nCollaborate with\u00a0WSS\u00a0local agents\u00a0globally on\u00a0port call\u00a0pre-planning and cost estimates, understand customer needs and\u00a0communicate to local port agents that\u00a0provide the agency services.\nWork closely with operational and administration teams to secure all requirements from the customer in accordance with global operational standards and contract terms in place with customers.\nHandle customer\u00a0complaints and follow up on solutions.\nCollaborate with Sales Managers and Credit team on customer outstanding settlements.\nSupport Sales Managers on business development and business reviews.\nFilter potential business\u00a0opportunities and pass it on to relevant parties in the network.\nSuggest\u00a0process improvements based on efficiency, productivity, or cost effectiveness.\nSupport\u00a0the\u00a0Global Agent\u00a0network\u00a0as a team.\nHandle any ad-hoc assignments from the Supervisor/Manager.\n\nAccountabilities\u00a0\n\nThis position will be measured against:\n\nNumber of port calls handled and average agency fee values.\nAdherence of DAs to agreed agency fees and service scope.\nNumber of leads and opportunities passed to Sales Managers.\nNumber of customer compliments and complaints.\nCompliance to\u00a0all applicable processes.\u00a0\n\nQualifications\u00a0\n\nDegree holders, min. 3 years working experience in any field, experience in shipping industry will be an advantage.\nSelf-motivated and Customer-oriented with commercial mind.\nOrganized and logically thinking, good problem solution skills.\nEnjoy working in dynamic environment with changing requirements and pressure, excellent time management to commit service deadlines.\nStrong interpersonal and communication skills, able to work with people from different cultural backgrounds, both internally and externally.\nProficient in written and spoken English & Chinese, including Mandarin.\nComputer literate.\n\nAdditional Preferences\u00a0\n\nGood negotiating skills.\nGood networking and relation building skills.\n\nSounds interesting? If you can see yourself in this role, please let us know why you are our new Global Agent.\n\n\nYou can apply online today through our career portal by creating a \u2018Candidate Home\u2019 account. Here you can upload your resume and a motivational letter.\n\nwww.wilhelmsen.com\n\nApplication Deadline: 18 January 2022", "employment_types": ["Permanent"], "selling_points": ["Coordinate Ships Agency Husbandry services", "Contract management and Port calls handling", "Collaborate with Sales on business development"], "locations": ["Kwun Tong"], "categories": ["Sales, CS & Business Devpt", "Customer Service - Supervisor / Officer", "Transportation & Logistics", "Maritime - General", "Sales Administration"], "post_time": "2022-01-05T02:05:01Z", "salary": {"currency": null, "max": null, "min": null, "period": "monthly", "term": null}, "salary_visible": false, "title_keywords": ["coordinator", "customer service"], "responsibilities": ["management", "customer service", "develop"], "requirements": {"degrees": [], "majors": [], "languages": [], "language_level": [], "hard_skills": ["sail"], "soft_skills": ["comprehensive", "committed", "customer service", "diverse"], "languages_combined": []}, "experience_required": {"duration": [], "field": ["sustainability"]}}, {"job_id": "100003009018590", "location_code": "hk", "company": "Knight Recruitment Services Limited", "job_title": "International Shipping Logistics Executive/Assistant;5day;Attractive Salary Package (13month+DB)", "description": "Job Duties:\u00a0\n\nAssist in the overall running of the deck operations\nResponsible for the cleanliness and maintenance of the exterior of the yacht\nResponsible for the safety of guests and crew\nAssisting captain with administrative and safety duties\nMaintain deck inventory and deck equipment\nAssist with interior cleaning and service when required\nWatch-keeping of yacht according to duty roster\n\n\u00a0Requirements:\u00a0\n\nMinimum 2 years\u2019 sailor experience\nHolder of HK Pleasure Vessel Operator Grade 2 Certificate\nValid Basic Certificate on Standards of Training, Certification and Watch-keeping for Seafarers (STCW)\nHolder of valid ENG1 medical fitness certificate or equivalent\nExtensive maintenance knowledge and skills; cleaning, rust/corrosion, painting, varnishing, rope splicing, fiberglass, carpentry, outboard motors and maintenance product knowledge\nBasic engineering knowledge\nExperience in driving small boats\nKnowledge of all water sports\nInventory maintenance experience\nMultitasking with ability to prioritize and organize\nGood command of spoken English and Chinese (Cantonese and Mandarin)\nRequire to work on yacht and capable of doing watch\nWorking Location: Sai Kung / Aberdeen\n\nWe offer\u00a0attractive remuneration to successful candidates. To apply, please send your full resume stating date available, present and expected salary by mail to Group Human Resources & Administration Controller, Lai Sun Group, 11/F Lai Sun Commercial Centre, 680 Cheung Sha Wan Road, Kowloon or click the button \"APPLY NOW\" shown below to send your application via email.\n\n\nWebsite: www.laisun.com\n\nPersonal data provided in the employment applications will be treated in strict confidence and used only for recruitment purpose by the Lai Sun Group Companies.\u00a0 All unsuccessful applications will be destroyed upon completion of the process.\n\n\u00a0 \u00a0 \u00a0 \u00a0 \u00a0 \u00a0 \u00a0 \u00a0 \u00a0 \u00a0 \u00a0 \u00a0 \u00a0 \u00a0 \u00a0 \u00a0 \u00a0 \u00a0 \u00a0 \u00a0 \u00a0 \u00a0 \u00a0 \u00a0 \u00a0 \u00a0 \u00a0 \u00a0 \u00a0 A member of the Lai Sun Group", "employment_types": ["Full Time", "Permanent"], "selling_points": ["5 Day; Fresh Graduates Welcome! HK Island!", "13month salary package; Salary negotiable", "Excellent career path & opportunity"], "locations": ["Not Specified"], "categories": ["Accounting", "Financial Analyst", "Transportation & Logistics", "Shipping", "Maritime - General"], "post_time": "2022-01-05T03:04:28Z", "salary": {"currency": null, "max": null, "min": null, "period": "monthly", "term": null}, "salary_visible": false, "title_keywords": ["shipping", "logistics executive"], "responsibilities": ["maintenance", "operations", "inventory", "maintain", "cleaning"], "requirements": {"degrees": ["certificate"], "majors": [], "languages": ["cantonese", "english", "chinese", "mandarin"], "language_level": ["good command"], "hard_skills": ["small", "basic", "rust", "maintenance"], "soft_skills": ["extensive", "capable", "prioritize"], "languages_combined": [{"language": "cantonese", "language_level": ["good command"]}, {"language": "english", "language_level": ["good command"]}, {"language": "chinese", "language_level": ["good command"]}, {"language": "mandarin", "language_level": ["good command"]}]}, "experience_required": {"duration": ["minimum 2 years"], "field": ["maintenance"]}}, {"job_id": "100003009023524", "location_code": "hk", "company": "Lai Sun Group", "job_title": "Yacht Deckhand", "description": "Job Duties:\u00a0\n\nAssist in the overall running of the deck operations\nResponsible for the cleanliness and maintenance of the exterior of the yacht\nResponsible for the safety of guests and crew\nAssisting captain with administrative and safety duties\nMaintain deck inventory and deck equipment\nAssist with interior cleaning and service when required\nWatch-keeping of yacht according to duty roster\n\n\u00a0Requirements:\u00a0\n\nMinimum 2 years\u2019 sailor experience\nHolder of HK Pleasure Vessel Operator Grade 2 Certificate\nValid Basic Certificate on Standards of Training, Certification and Watch-keeping for Seafarers (STCW)\nHolder of valid ENG1 medical fitness certificate or equivalent\nExtensive maintenance knowledge and skills; cleaning, rust/corrosion, painting, varnishing, rope splicing, fiberglass, carpentry, outboard motors and maintenance product knowledge\nBasic engineering knowledge\nExperience in driving small boats\nKnowledge of all water sports\nInventory maintenance experience\nMultitasking with ability to prioritize and organize\nGood command of spoken English and Chinese (Cantonese and Mandarin)\nRequire to work on yacht and capable of doing watch\nWorking Location: Sai Kung / Aberdeen\n\nWe offer\u00a0attractive remuneration to successful candidates. To apply, please send your full resume stating date available, present and expected salary by mail to Group Human Resources & Administration Controller, Lai Sun Group, 11/F Lai Sun Commercial Centre, 680 Cheung Sha Wan Road, Kowloon or click the button \"APPLY NOW\" shown below to send your application via email.\n\n\nWebsite: www.laisun.com\n\nPersonal data provided in the employment applications will be treated in strict confidence and used only for recruitment purpose by the Lai Sun Group Companies.\u00a0 All unsuccessful applications will be destroyed upon completion of the process.\n\n\u00a0 \u00a0 \u00a0 \u00a0 \u00a0 \u00a0 \u00a0 \u00a0 \u00a0 \u00a0 \u00a0 \u00a0 \u00a0 \u00a0 \u00a0 \u00a0 \u00a0 \u00a0 \u00a0 \u00a0 \u00a0 \u00a0 \u00a0 \u00a0 \u00a0 \u00a0 \u00a0 \u00a0 \u00a0 A member of the Lai Sun Group", "employment_types": ["Full Time", "Permanent"], "selling_points": ["Responsible for the running of the deck operations", "Clean & maintain the exterior of the yacht", "Maintain deck inventory & deck equipment"], "locations": ["Sai Kung"], "categories": ["Transportation & Logistics", "Others", "Hospitality / F & B", "Hospitality / Hotel Services", "Maritime - General"], "post_time": "2022-01-05T09:00:45Z", "salary": {"currency": null, "max": null, "min": null, "period": "monthly", "term": null}, "salary_visible": false, "title_keywords": [], "responsibilities": ["maintenance", "operations", "inventory", "maintain", "cleaning"], "requirements": {"degrees": ["certificate"], "majors": [], "languages": ["cantonese", "english", "chinese", "mandarin"], "language_level": ["good command"], "hard_skills": ["small", "basic", "rust", "maintenance"], "soft_skills": ["extensive", "capable", "prioritize"], "languages_combined": [{"language": "cantonese", "language_level": ["good command"]}, {"language": "english", "language_level": ["good command"]}, {"language": "chinese", "language_level": ["good command"]}, {"language": "mandarin", "language_level": ["good command"]}]}, "experience_required": {"duration": ["minimum 2 years"], "field": ["maintenance"]}}, {"job_id": "100003009008470", "location_code": "hk", "company": "Hong Kong Pilots Association Limited", "job_title": "Assistant Operations Controller", "description": "Responsibilities & Duties\n\n\nEnsure vessels safe and efficient operation and environmentally compliant\nSupervise and oversee team and crew members\nOversee the operation of marine vessels\nSet, control budget and cost reduction exercises\nEnsure compliance to legal regulations and company policies\nFirst point of contact for emergencies and contingency situations\nIdentify vessels\u2019 issues and implement solutions in a timely manner\nBuild and maintain professional relationship with relevant internal and external stakeholders\nIncident prevention and review\nMonitor the commissioning of new-built marine vessels\nBoard vessels regularly for periodic inspections and meetings with crew / Technical Manager and repair contractors\nWorking together with the Technical Manager, monitor vessels\u2019 dry-docking and repair programs\nWorking together with all stake-holders to investigate / design / launch programs for process improvement\nCoordinate repairs with our technical manager, shipyard and contractors\nCoordinate with internal departments to complete logistics requirements of clients\nRegular reporting to management\nEngagement with clients\nPerform duties and projects as assigned by the management\n\nRequirements\n\nTertiary education preferable\nHolding a valid of Certificate of Competency as a Deck Officer, Seagoing or River Trade Class 2 or Class 1 recognized by Marine Authorities, or be a member of The Hong Kong Institution of Engineers in the Marine & Naval Architecture Discipline\n5 years\u2019 experience in management and operation of marine vessel fleet\nCandidate with technical knowledge of vessel would be an added advantage\nStrong organizational and problem solving skills\nMust be detail-oriented and possess effective communication skills\nAbility to work independently and under pressure\nGood team work\nProficiency in written and spoken English and Chinese\nGood PC knowledge in MS Excel and Words\n\nInterested parties, please submit your resume with details of qualification, experience, and contact number to the Human Resources Manager by clicking Apply Now. Data collected will be used for recruitment purposes only.", "employment_types": ["Full Time", "Permanent"], "selling_points": [], "locations": ["Sai Wan"], "categories": ["Transportation & Logistics", "Maritime - General"], "post_time": "2021-12-30T08:07:15Z", "salary": {"currency": null, "max": null, "min": null, "period": "monthly", "term": null}, "salary_visible": false, "title_keywords": ["operations", "assistant"], "responsibilities": ["regulations", "budget", "design", "maintain", "control", "monitor", "logistics", "reporting", "cost", "management", "commissioning", "review", "coordinate with", "contact", "policies", "a timely manner", "ensure compliance", "coordinate", "repair"], "requirements": {"degrees": ["certificate"], "majors": ["architecture"], "languages": ["english", "chinese"], "language_level": ["proficiency"], "hard_skills": ["words", "the hong kong institution of engineers", "ms excel", "pc knowledge", "problem solving skills"], "soft_skills": ["good team work", "communication skills", "work independently", "under pressure", "organizational", "detail-oriented", "problem solving skills"], "languages_combined": [{"language": "english", "language_level": ["proficiency"]}, {"language": "chinese", "language_level": ["proficiency"]}]}, "experience_required": {"duration": ["5 years"], "field": ["management", "operation"]}}, {"job_id": "100003009008324", "location_code": "hk", "company": "Fat Kee Stevedores Limited", "job_title": "Manager \u2013 Ship Management", "description": "\u798f\u5229:\n\n\u5e74\u504711\u5929\n\u516c\u773e\u5047\u671f\n\u5ee0\u8eca\u670d\u52d9\n\u98ef\u9910\u512a\u60e0\n\u91ab\u7642\u9580\u8a3a\u53ca\u4f4f\u9662\u4fdd\u96aa (\u5305\u62ec\u76f4\u7cfb\u5bb6\u5c6c)\n\u914c\u60c5\u5e74\u7d42\u82b1\u7d05\n\u52a0\u73ed\u6d25\u8cbc\n\u8f2a\u73ed\u6d25\u8cbc\n\u9032\u4fee\u6d25\u8cbc\n\u6069\u6064\u5047\n\u4eba\u58fd\u4fdd\u96aa\n\u5f37\u7a4d\u91d1\n\u5728\u8077\u57f9\u8a13\n\u54e1\u5de5\u5eb7\u6a02\u6d3b\u52d5\n\u54e1\u5de5\u63a8\u85a6\u734e\u91d1\n\n\u8077\u8cac:\n\n\u64cd\u4f5c\u642c\u571f\u6a5f\u904b\u9001\u53ca\u56de\u6536\u751f\u7522\u7269\u6599\n\u64cd\u4f5c\u5854\u5f0f\u5378\u8ca8\u6a5f\u5f9e\u8239\u4e0a\u8d77\u5378\u751f\u7522\u7269\u6599\n\u64cd\u4f5c\u8f2a\u80ce\u5f0f\u6db2\u58d3\u4f38\u7e2e\u540a\u81c2\u8d77\u91cd\u6a5f\u5354\u52a9\u540a\u904b\u5de5\u5e8f\u53ca\u7dad\u4fee\u9805\u76ee\n\n\u5177\u5099\u689d\u4ef6:\n\n\u4e2d\u4e94\u7a0b\u5ea6\u6216\u4ee5\u4e0a\n\u51771\u5e74\u6216\u4ee5\u4e0a\u78bc\u982d\u4e0a\u8ca8\u53ca\u5378\u8ca8\u7d93\u9a57\n\u6301\u642c\u571f\u6a5f\u3001\u5854\u5f0f\u5378\u8ca8\u6a5f\u6216\u8f2a\u80ce\u5f0f\u6db2\u58d3\u4f38\u7e2e\u540a\u81c2\u8d77\u91cd\u6a5f\u64cd\u4f5c\u8b49\u660e\u66f8\u8005\u5c07\u88ab\u512a\u5148\u8003\u616e\n\u9808\u8f2a\u73ed\u5de5\u4f5c", "employment_types": ["Full Time"], "selling_points": [], "locations": ["Tsuen Wan Area"], "categories": ["Transportation & Logistics", "Others", "Shipping", "Maritime - General"], "post_time": "2021-12-30T07:38:11Z", "salary": {"currency": null, "max": null, "min": null, "period": "monthly", "term": null}, "salary_visible": false, "title_keywords": ["manager"], "responsibilities": [], "requirements": {"degrees": [], "majors": [], "languages": [], "language_level": [], "hard_skills": [], "soft_skills": [], "languages_combined": []}, "experience_required": {"duration": [], "field": []}}, {"job_id": "100003009008640", "location_code": "hk", "company": "Green Island Cement Company, Limited", "job_title": "\u78bc\u982d\u90e8\u64cd\u4f5c\u54e1 Dock Operator", "description": "\u8077\u8cac\uff1a\n\n\u8239\u52d9\u5de5\u4f5c\uff1a\u8655\u7406\u8239\u96bb\u9760\u6cca\u78bc\u982d\u53ca\u7e9c\u7d22\u5de5\u4f5c\u3001\u8d77\u653e\u8df3\u677f\u3001\u5354\u52a9\u7532\u677f\u5de5\u4f5c\u3001\u7167\u9867\u4e58\u5ba2\u4e0a\u843d\u8239\u79e9\u5e8f\u53ca\u6309\u7167\u8239\u9577\u6216\u6a5f\u9577\u6307\u793a\u9032\u884c\u65e5\u5e38\u8239\u96bb\u4fdd\u990a\u4e8b\u5b9c\n\u7968\u52d9\u5de5\u4f5c\uff1a\u8655\u7406\u78bc\u982d\u7968\u52d9\u5de5\u4f5c\u3001\u63a7\u5236\u9598\u6a5f\u53ca\u8655\u7406\u4e58\u5ba2\u67e5\u8a62\n\u8cc7\u6b77\uff1a\n\n\u7121\u9700\u5de5\u4f5c\u7d93\u9a57\u4e26\u63d0\u4f9b\u5728\u8077\u57f9\u8a13\n\u5de5\u4f5c\u52e4\u596e\uff0c\u6709\u8cac\u4efb\u5fc3\n\u826f\u597d\u7cb5\u8a9e\u53ca\u7c21\u6613\u82f1\u8a9e\uff0c\u61c2\u95b1\u8b80\u4e2d\u6587\n\u9700\u8f2a\u73ed\u5de5\u4f5c\n\n\u5de5\u4f5c\u5730\u9ede: \u4e2d\u74b0/\u6109\u666f\u7063\n\n\u516c\u53f8\u514d\u8cbb\u63d0\u4f9b\u524d\u5f80\u6109\u666f\u7063\u4e4b\u4ea4\u901a\u670d\u52d9\u3002\u5f9e\u4e2d\u74b0\u4e58\u5750\u6e21\u8f2a\u524d\u5f80\u6109\u666f\u7063\u53ea\u970025\u5206\u9418\uff0c\u800c\u5f9e\u6b23\u6fb3\u5730\u9435\u7ad9\u4e58\u5750\u5df4\u58eb\u66f4\u53ea\u9700\u898110-15\u5206\u9418\u3002\u5982\u679c\u60a8\u60f3\u9032\u4e00\u6b65\u4e86\u89e3\u6109\u666f\u7063\u7684\u5de5\u4f5c\u751f\u6d3b\uff0c\u8acb\u89c0\u770b\u6b64\u5f71\u7247\uff1ahttps://goo.gl/6LLK75\n\n\u798f\u5229\uff1a\n\n\u6211\u5011\u63d0\u4f9b\u512a\u539a\u7684\u85aa\u916c\u5f85\u9047\uff0c\u5305\u62ec\u81b3\u98df\u3001\u5e74\u5047\u3001\u914c\u60c5\u82b1\u7d05\u3001\u589e\u88dc\u6027\u5f37\u7a4d\u91d1\u3001\u7259\u79d1\u548c\u91ab\u7642\u4fdd\u96aa\u7b49\u3002\u6211\u5011\u91cd\u8996\u54e1\u5de5\u7684\u8077\u696d\u767c\u5c55\uff0c\u4e26\u70ba\u4ed6\u5011\u63d0\u4f9b\u5404\u7a2e\u4e0d\u540c\u57f9\u8a13\u6a5f\u6703\u3002\n\n\u7533\u8acb\u65b9\u6cd5\uff1a\n\n\u7db2\u4e0a\u7533\u8acb - \u516c\u53f8\u7db2\u7ad9http://www.hkri.com (\u5c31\u696d\u6a5f\u6703/\u6109\u666f\u7063\u822a\u904b\u670d\u52d9\u6709\u9650\u516c\u53f8)\uff0c\u586b\u5beb\u5728\u7dda\u7533\u8acb\u8868\n\u96fb\u90f5 - \u9023\u540c\u5c65\u6b77\u548c\u671f\u671b\u85aa\u916c\u767c\u9001\u81f3Apply Now\nWhatsApp - 5603 2198\n\u50b3\u771f - 2987 5057\n\n\u7533\u8acb\u4eba\u5982\u5728\u5169\u500b\u6708\u5167\u672a\u6709\u63a5\u7372\u9762\u8a66\u901a\u77e5\uff0c\u5373\u4ee3\u8868\u5176\u8077\u4f4d\u7533\u8acb\u4e0d\u6210\u529f\u3002\u7533\u8acb\u4eba\u63d0\u4f9b\u4e4b\u5168\u90e8\u8cc7\u6599\u7d55\u5c0d\u4fdd\u5bc6\u53ca\u53ea\u4f5c\u8077\u4f4d\u62db\u8058\u7528\u9014\uff0c\u4e26\u5728\u62db\u8058\u904e\u7a0b\u7d50\u675f\u6642\u92b7\u6bc0\u3002\u5728\u4f7f\u7528\u6c42\u8077\u8005\u6240\u63d0\u4f9b\u7684\u500b\u4eba\u8cc7\u6599\u6642\uff0c\u50f1\u4e3b\u6703\u56b4\u683c\u9075\u5b88\u5176\u500b\u4eba\u8cc7\u6599\u653f\u7b56\u7684\u898f\u5b9a\uff0c\u5728\u6536\u5230\u8981\u6c42\u5f8c\uff0c\u6703\u96a8\u5373\u63d0\u4f9b\u4e00\u4efd\u6709\u95dc\u653f\u7b56\u7684\u8907\u672c\u3002", "employment_types": ["Full Time", "Permanent"], "selling_points": [], "locations": ["Tuen Mun Area"], "categories": ["Manufacturing", "General / Production Workers", "Transportation & Logistics", "Maritime - General"], "post_time": "2021-12-31T16:57:22Z", "salary": {"currency": null, "max": null, "min": null, "period": "monthly", "term": null}, "salary_visible": false, "title_keywords": ["operator"], "responsibilities": [], "requirements": {"degrees": [], "majors": [], "languages": [], "language_level": [], "hard_skills": ["whatsapp"], "soft_skills": [], "languages_combined": []}, "experience_required": {"duration": [], "field": []}}, {"job_id": "100003009008472", "location_code": "hk", "company": "HKR International Ltd", "job_title": "\u6d77\u4e8b\u52a9\u7406 (Ref: TPL/MSA/JDB/28)", "description": "Key Responsibilities\n\nTotal in-charge of vessel operation, plan cargo stowage on vessel and optimize vessel utilization\nMonitor vessel schedule as per weather and provide clear instructions on ETA/Speed and fuel cons to Master for the next port\nCreate vessel schedules/pro-forma in the system and verify daily reports from vessel\nIssue updated coastal schedules/sailing instructions for each vessel on a regular basis\nAssist Line Managers in maximizing the vessel in conjunction with Planning Department Monitoring and control of vessel and port performance (Ship\u2019s voyage performance report)\nManage bunker planning, ordering and cost control\nDetermine the operational requirements for leasing a vessel\nResponsible for pre-fixture vessel evaluations and calculation of estimated round voyage bunker cons; post fixture follow up and arrangements\nMaintain a list of open stevedore/cargo damages and communicate promptly with Agents/owners/vessels/Insurance etc. on case by case basis\n\n\u00a0Who we are looking for\n\nLicensed member of Deck Department as a Master\nExperience with RORO vessels\nThorough knowledge of the rules and regulations of international shipping\nProficiency in Microsoft Office (Excel and PowerPoint in particular)\nFluent in English\n\n\u00a0We offer\n\nExcellent opportunities for advancement with regional exposure\nCompetitive salary package\n5-Days Work\n18 - 20 days Annual Leave\nDouble Pay\nMedical & Dental Insurance\nLife Insurance\nBirthday Gifts\nMarriage Leave\nPaternity Leave\nWork from home arrangement\n\nInterested parties please share with us your latest resume showing current and expected remuneration package.", "employment_types": ["Full Time"], "selling_points": ["\u8655\u7406\u8239\u52d9\u5de5\u4f5c\u53ca\u7968\u52d9\u5de5\u4f5c", "\u7121\u9700\u5de5\u4f5c\u7d93\u9a57\u4e26\u63d0\u4f9b\u5728\u8077\u57f9\u8a13", "\u63d0\u4f9b\u81b3\u98df\u3001\u5e74\u5047\u3001\u914c\u60c5\u82b1\u7d05\u3001\u589e\u88dc\u6027\u5f37\u7a4d\u91d1\u3001\u7259\u79d1\u548c\u91ab\u7642\u4fdd\u96aa"], "locations": ["Not Specified"], "categories": ["Sales, CS & Business Devpt", "Customer Service - Supervisor / Officer", "Transportation & Logistics", "Maritime - General", "Public Transportation"], "post_time": "2021-12-30T08:07:22Z", "salary": {"currency": null, "max": null, "min": null, "period": "monthly", "term": null}, "salary_visible": false, "title_keywords": [], "responsibilities": ["regulations", "control", "shipping", "schedules", "monitoring", "monitor", "maintain", "schedule", "plan", "cost control", "daily reports", "insurance", "report", "planning"], "requirements": {"degrees": ["master"], "majors": [], "languages": ["english"], "language_level": ["fluent"], "hard_skills": ["excel", "powerpoint", "microsoft office"], "soft_skills": ["clear", "thorough", "responsible"], "languages_combined": [{"language": "english", "language_level": ["fluent"]}]}, "experience_required": {"duration": [], "field": []}}, {"job_id": "100003009008541", "location_code": "hk", "company": "HKR International Ltd", "job_title": "\u898b\u7fd2\u8239\u9577 (Ref: TPL/MT/JDB/2)", "description": "\u8077\u8cac\uff1a\n\n\u8ca0\u8cac\u5354\u52a9\u8239\u9577\u53ca\u526f\u8239\u9577\u57f7\u884c\u8239\u4e0a\u822a\u884c\u53ca\u5b89\u5168\u904b\u4f5c\n\u6309\u7167\u8239\u9577\u53ca\u526f\u8239\u9577\u6307\u793a\u7ba1\u7406\u8239\u4e0a\u4e00\u5207\u71df\u904b\uff0c\u7167\u9867\u4e58\u5ba2\u5b89\u5168\uff0c\u4e26\u8655\u7406\u65e5\u5e38\u8239\u4e0a\u4e8b\u52d9\uff0c\u4ee5\u63d0\u5347\u822a\u904b\u670d\u52d9\u7684\u8cea\u7d20\n\n\u8cc7\u6b77\uff1a\n\n\u6301\u6709\u6548\u672c\u5730\u8239\u9577\u4e09\u7d1a\u8b49\u660e\u66f8\n\u5177\u4e00\u5e74\u7684\u672c\u5730\u6d77\u57df\u822a\u884c\u7d93\u9a57\uff0c\u5177\u672c\u5730\u9ad8\u901f\u96d9\u9ad4\u5ba2\u8f2a\u64cd\u4f5c\u7d93\u9a57\u512a\u5148\u8003\u616e\n\u826f\u597d\u4e2d\u82f1\u6587\u66f8\u5beb\u80fd\u529b\n\u9808\u8f2a\u73ed\u5de5\u4f5c\n\n\u5de5\u4f5c\u5730\u9ede: \u4e2d\u74b0/\u6109\u666f\u7063\n\n\u516c\u53f8\u514d\u8cbb\u63d0\u4f9b\u524d\u5f80\u6109\u666f\u7063\u4e4b\u4ea4\u901a\u670d\u52d9\u3002\u5f9e\u4e2d\u74b0\u4e58\u5750\u6e21\u8f2a\u524d\u5f80\u6109\u666f\u7063\u53ea\u970025\u5206\u9418\uff0c\u800c\u5f9e\u6b23\u6fb3\u5730\u9435\u7ad9\u4e58\u5750\u5df4\u58eb\u66f4\u53ea\u9700\u898110-15\u5206\u9418\u3002\u5982\u679c\u60a8\u60f3\u9032\u4e00\u6b65\u4e86\u89e3\u6109\u666f\u7063\u7684\u5de5\u4f5c\u751f\u6d3b\uff0c\u8acb\u89c0\u770b\u6b64\u5f71\u7247\uff1ahttps://goo.gl/6LLK75\n\n\u798f\u5229\uff1a\n\n\u6211\u5011\u63d0\u4f9b\u512a\u539a\u7684\u85aa\u916c\u5f85\u9047\uff0c\u5305\u62ec\u81b3\u98df\u3001\u5e74\u5047\u3001\u914c\u60c5\u82b1\u7d05\u3001\u589e\u88dc\u6027\u5f37\u7a4d\u91d1\u3001\u7259\u79d1\u548c\u91ab\u7642\u4fdd\u96aa\u7b49\u3002\u6211\u5011\u91cd\u8996\u54e1\u5de5\u7684\u8077\u696d\u767c\u5c55\uff0c\u4e26\u70ba\u4ed6\u5011\u63d0\u4f9b\u5404\u7a2e\u4e0d\u540c\u57f9\u8a13\u6a5f\u6703\u3002\n\n\u7533\u8acb\u65b9\u6cd5\uff1a\n\n\u7db2\u4e0a\u7533\u8acb - \u516c\u53f8\u7db2\u7ad9http://www.hkri.com (\u5c31\u696d\u6a5f\u6703/\u6109\u666f\u7063\u822a\u904b\u670d\u52d9\u6709\u9650\u516c\u53f8)\uff0c\u586b\u5beb\u5728\u7dda\u7533\u8acb\u8868\n\u96fb\u90f5 - \u9023\u540c\u5c65\u6b77\u548c\u671f\u671b\u85aa\u916c\u767c\u9001\u81f3Apply Now\nWhatsApp - 5603 2198\n\u50b3\u771f - 2987 5057\n\n\u7533\u8acb\u4eba\u5982\u5728\u5169\u500b\u6708\u5167\u672a\u6709\u63a5\u7372\u9762\u8a66\u901a\u77e5\uff0c\u5373\u4ee3\u8868\u5176\u8077\u4f4d\u7533\u8acb\u4e0d\u6210\u529f\u3002\u7533\u8acb\u4eba\u63d0\u4f9b\u4e4b\u5168\u90e8\u8cc7\u6599\u7d55\u5c0d\u4fdd\u5bc6\u53ca\u53ea\u4f5c\u8077\u4f4d\u62db\u8058\u7528\u9014\uff0c\u4e26\u5728\u62db\u8058\u904e\u7a0b\u7d50\u675f\u6642\u92b7\u6bc0\u3002\u5728\u4f7f\u7528\u6c42\u8077\u8005\u6240\u63d0\u4f9b\u7684\u500b\u4eba\u8cc7\u6599\u6642\uff0c\u50f1\u4e3b\u6703\u56b4\u683c\u9075\u5b88\u5176\u500b\u4eba\u8cc7\u6599\u653f\u7b56\u7684\u898f\u5b9a\uff0c\u5728\u6536\u5230\u8981\u6c42\u5f8c\uff0c\u6703\u96a8\u5373\u63d0\u4f9b\u4e00\u4efd\u6709\u95dc\u653f\u7b56\u7684\u8907\u672c\u3002", "employment_types": ["Full Time"], "selling_points": ["\u6309\u7167\u8239\u9577\u53ca\u526f\u8239\u9577\u6307\u793a\u7ba1\u7406\u8239\u4e0a\u4e00\u5207\u71df\u904b", "\u6301\u6709\u672c\u5730\u8f2a\u6a5f\u64cd\u4f5c\u54e1\u4e00\u7d1a\u8b49\u660e\u66f8\u6216\u672c\u5730\u8f2a\u6a5f\u54e1(150\u5339\u53ca\u4ee5\u4e0a)\u8b49\u66f8", "\u63d0\u4f9b\u81b3\u98df\u3001\u5e74\u5047\u3001\u914c\u60c5\u82b1\u7d05\u3001\u589e\u88dc\u6027\u5f37\u7a4d\u91d1\u3001\u7259\u79d1\u548c\u91ab\u7642\u4fdd\u96aa"], "locations": ["Not Specified"], "categories": ["Transportation & Logistics", "Others", "Maritime - General", "Public Transportation"], "post_time": "2021-12-30T08:14:50Z", "salary": {"currency": null, "max": null, "min": null, "period": "monthly", "term": null}, "salary_visible": false, "title_keywords": [], "responsibilities": [], "requirements": {"degrees": [], "majors": [], "languages": [], "language_level": [], "hard_skills": ["whatsapp"], "soft_skills": [], "languages_combined": []}, "experience_required": {"duration": [], "field": []}}, {"job_id": "100003009003330", "location_code": "hk", "company": "Wilhelmsen Ships Service Limited", "job_title": "Global Agent HK (Ships Agency, Customer Service Department)", "description": "Global Agent HK (Ships Agency, Customer Service Department)\n\n\n\nFounded in Norway in 1861, Wilhelmsen is now a comprehensive global maritime group providing over half of the merchant fleet with essential products and services, along with supplying crew and technical management to the largest and most complex vessels ever to sail. Committed to shaping the maritime industry, we also seek to explore and develop new opportunities within the renewables, offshore and energy industries. Supporting a diverse and inclusive workplace, with thousands of colleagues in more than 70 countries, we take competence, sustainability, innovation, and unparalleled customer experiences one step further.\n\n\nWe are looking for a Global Agent to join our Ships Agency division.\n\nIn Ships Agency, we provide our customers with piece of mind while we handle their cargo, their vessels and their crew. We handle 75,000 port calls per year, which means that every 7 minutes, anywhere around the world, we send a ship safely out to sea again to fulfil its purpose. We match local expertise with strict global standards, making sure we consistently make our customers\u2019 port calls as efficient and safe as possible.\n\n\nJob Description\n\nMain Responsibilities\n\nManage existing contracts for\u00a0Ships Agency\u00a0customers.\nCollaborate with\u00a0WSS\u00a0local agents\u00a0globally on\u00a0port call\u00a0pre-planning and cost estimates, understand customer needs and\u00a0communicate to local port agents that\u00a0provide the agency services.\nWork closely with operational and administration teams to secure all requirements from the customer in accordance with global operational standards and contract terms in place with customers.\nHandle customer\u00a0complaints and follow up on solutions.\nCollaborate with Sales Managers and Credit team on customer outstanding settlements.\nSupport Sales Managers on business development and business reviews.\nFilter potential business\u00a0opportunities and pass it on to relevant parties in the network.\nSuggest\u00a0process improvements based on efficiency, productivity, or cost effectiveness.\nSupport\u00a0the\u00a0Global Agent\u00a0network\u00a0as a team.\nHandle any ad-hoc assignments from the Supervisor/Manager.\n\nAccountabilities\u00a0\n\nThis position will be measured against:\n\nNumber of port calls handled and average agency fee values.\nAdherence of DAs to agreed agency fees and service scope.\nNumber of leads and opportunities passed to Sales Managers.\nNumber of customer compliments and complaints.\nCompliance to\u00a0all applicable processes.\u00a0\n\nQualifications\u00a0\n\nDegree holders, min. 3 years working experience in any field, experience in shipping industry will be an advantage.\nSelf-motivated and Customer-oriented with commercial mind.\nOrganized and logically thinking, good problem solution skills.\nEnjoy working in dynamic environment with changing requirements and pressure, excellent time management to commit service deadlines.\nStrong interpersonal and communication skills, able to work with people from different cultural backgrounds, both internally and externally.\nProficient in written and spoken English & Chinese, including Mandarin.\nComputer literate.\n\nAdditional Preferences\u00a0\n\nGood negotiating skills.\nGood networking and relation building skills.\n\nSounds interesting? If you can see yourself in this role, please let us know why you are our new Global Agent.\n\n\nYou can apply online today through our career portal by creating a \u2018Candidate Home\u2019 account. Here you can upload your resume and a motivational letter.\n\nwww.wilhelmsen.com\n\nApplication Deadline: 7 January 2022", "employment_types": ["Permanent"], "selling_points": ["Coordinate Ships Agency Husbandry services", "Contract management and Port calls handling", "Collaborate with Sales on business development"], "locations": ["Kwun Tong"], "categories": ["Sales, CS & Business Devpt", "Customer Service - Supervisor / Officer", "Transportation & Logistics", "Maritime - General", "Sales Administration"], "post_time": "2021-12-28T08:50:51Z", "salary": {"currency": null, "max": null, "min": null, "period": "monthly", "term": null}, "salary_visible": false, "title_keywords": ["customer service"], "responsibilities": ["management", "customer service", "develop"], "requirements": {"degrees": [], "majors": [], "languages": [], "language_level": [], "hard_skills": ["sail"], "soft_skills": ["comprehensive", "committed", "customer service", "diverse"], "languages_combined": []}, "experience_required": {"duration": [], "field": ["sustainability"]}}, {"job_id": "100003009008397", "location_code": "hk", "company": "HKR International Ltd", "job_title": "\u8f2a\u6a5f\u9577 (Ref: TPL/ENG/JDB/46)", "description": "\u8077\u8cac\uff1a\n\n\u5354\u52a9\u8239\u9577\u7ba1\u7406\u8239\u4e0a\u71df\u904b\u53ca\u8ca0\u8cac\u7ba1\u7406\u8239\u4e0a\u8f2a\u6a5f\u64cd\u4f5c\u53ca\u8239\u6a5f\u4fdd\u990a\u7b49\u5de5\u4f5c\n\n\u8cc7\u6b77\uff1a\n\n\u6301\u6709\u672c\u5730\u8f2a\u6a5f\u64cd\u4f5c\u54e1\u4e00\u7d1a\u8b49\u660e\u66f8\u6216\u672c\u5730\u8f2a\u6a5f\u54e1(150\u5339\u53ca\u4ee5\u4e0a)\u8b49\u66f8\n\u5177\u8f2a\u6a5f\u9577\u7d93\u9a57\u8005\u512a\u5148\n\u80fd\u64cd\u7cb5\u8a9e\u53ca\u57fa\u672c\u82f1\u8a9e\n\n\u5982\u672a\u6301\u76f8\u95dc\u5de5\u4f5c\u7d93\u9a57\u53ca\u8b49\u66f8\u8005\uff0c\u53ef\u8003\u616e\u70ba\u201c\u526f\u8f2a\u6a5f\u9577\u201d\n\n\u5de5\u4f5c\u5730\u9ede: \u4e2d\u74b0/\u6109\u666f\u7063\n\n\u516c\u53f8\u514d\u8cbb\u63d0\u4f9b\u524d\u5f80\u6109\u666f\u7063\u4e4b\u4ea4\u901a\u670d\u52d9\u3002\u5f9e\u4e2d\u74b0\u4e58\u5750\u6e21\u8f2a\u524d\u5f80\u6109\u666f\u7063\u53ea\u970025\u5206\u9418\uff0c\u800c\u5f9e\u6b23\u6fb3\u5730\u9435\u7ad9\u4e58\u5750\u5df4\u58eb\u66f4\u53ea\u9700\u898110-15\u5206\u9418\u3002\u5982\u679c\u60a8\u60f3\u9032\u4e00\u6b65\u4e86\u89e3\u6109\u666f\u7063\u7684\u5de5\u4f5c\u751f\u6d3b\uff0c\u8acb\u89c0\u770b\u6b64\u5f71\u7247\uff1ahttps://goo.gl/6LLK75\n\n\u798f\u5229\uff1a\n\n\u6211\u5011\u63d0\u4f9b\u512a\u539a\u7684\u85aa\u916c\u5f85\u9047\uff0c\u5305\u62ec\u81b3\u98df\u3001\u5e74\u5047\u3001\u914c\u60c5\u82b1\u7d05\u3001\u589e\u88dc\u6027\u5f37\u7a4d\u91d1\u3001\u7259\u79d1\u548c\u91ab\u7642\u4fdd\u96aa\u7b49\u3002\u6211\u5011\u91cd\u8996\u54e1\u5de5\u7684\u8077\u696d\u767c\u5c55\uff0c\u4e26\u70ba\u4ed6\u5011\u63d0\u4f9b\u5404\u7a2e\u4e0d\u540c\u57f9\u8a13\u6a5f\u6703\u3002\n\n\u7533\u8acb\u65b9\u6cd5\uff1a\n\n\u7db2\u4e0a\u7533\u8acb - \u516c\u53f8\u7db2\u7ad9 http://www.hkri.com (\u5c31\u696d\u6a5f\u6703/\u6109\u666f\u7063\u822a\u904b\u670d\u52d9\u6709\u9650\u516c\u53f8)\uff0c\u586b\u5beb\u5728\u7dda\u7533\u8acb\u8868\n\u96fb\u90f5 - \u9023\u540c\u5c65\u6b77\u548c\u671f\u671b\u85aa\u916c\u767c\u9001\u81f3Apply Now\nWhatsApp - 5603 2198\n\u50b3\u771f - 2987 5057\n\n\u7533\u8acb\u4eba\u5982\u5728\u5169\u500b\u6708\u5167\u672a\u6709\u63a5\u7372\u9762\u8a66\u901a\u77e5\uff0c\u5373\u4ee3\u8868\u5176\u8077\u4f4d\u7533\u8acb\u4e0d\u6210\u529f\u3002\u7533\u8acb\u4eba\u63d0\u4f9b\u4e4b\u5168\u90e8\u8cc7\u6599\u7d55\u5c0d\u4fdd\u5bc6\u53ca\u53ea\u4f5c\u8077\u4f4d\u62db\u8058\u7528\u9014\uff0c\u4e26\u5728\u62db\u8058\u904e\u7a0b\u7d50\u675f\u6642\u92b7\u6bc0\u3002\u5728\u4f7f\u7528\u6c42\u8077\u8005\u6240\u63d0\u4f9b\u7684\u500b\u4eba\u8cc7\u6599\u6642\uff0c\u50f1\u4e3b\u6703\u56b4\u683c\u9075\u5b88\u5176\u500b\u4eba\u8cc7\u6599\u653f\u7b56\u7684\u898f\u5b9a\uff0c\u5728\u6536\u5230\u8981\u6c42\u5f8c\uff0c\u6703\u96a8\u5373\u63d0\u4f9b\u4e00\u4efd\u6709\u95dc\u653f\u7b56\u7684\u8907\u672c\u3002", "employment_types": ["Full Time"], "selling_points": ["\u5354\u52a9\u8239\u9577\u7ba1\u7406\u8239\u4e0a\u71df\u904b\u53ca\u8ca0\u8cac\u7ba1\u7406\u8239\u4e0a\u8f2a\u6a5f\u64cd\u4f5c\u53ca\u8239\u6a5f\u4fdd\u990a\u7b49\u5de5\u4f5c", "\u6301\u6709\u672c\u5730\u8f2a\u6a5f\u64cd\u4f5c\u54e1\u4e00\u7d1a\u8b49\u660e\u66f8\u6216\u672c\u5730\u8f2a\u6a5f\u54e1(150\u5339\u53ca\u4ee5\u4e0a)\u8b49\u66f8", "\u63d0\u4f9b\u81b3\u98df\u3001\u5e74\u5047\u3001\u914c\u60c5\u82b1\u7d05\u3001\u589e\u88dc\u6027\u5f37\u7a4d\u91d1\u3001\u7259\u79d1\u548c\u91ab\u7642\u4fdd\u96aa"], "locations": ["Not Specified"], "categories": ["Engineering", "Others", "Transportation & Logistics", "Maritime - General", "Public Transportation"], "post_time": "2021-12-30T07:54:00Z", "salary": {"currency": null, "max": null, "min": null, "period": "monthly", "term": null}, "salary_visible": false, "title_keywords": [], "responsibilities": [], "requirements": {"degrees": [], "majors": [], "languages": [], "language_level": [], "hard_skills": ["whatsapp"], "soft_skills": [], "languages_combined": []}, "experience_required": {"duration": [], "field": []}}, {"job_id": "100003009008431", "location_code": "hk", "company": "HKR International Ltd", "job_title": "\u526f\u8239\u9577 (Ref: TPL/AMAS/JDB/26)", "description": "\u8077\u8cac\uff1a\n\n\u8ca0\u8cac\u5354\u52a9\u8239\u9577\u57f7\u884c\u8239\u4e0a\u822a\u884c\u53ca\u5b89\u5168\u904b\u4f5c\n\u5354\u52a9\u7ba1\u7406\u8239\u4e0a\u4e00\u5207\u71df\u904b\uff0c\u7167\u9867\u4e58\u5ba2\u5b89\u5168\uff0c\u4e26\u8655\u7406\u65e5\u5e38\u8239\u4e0a\u4e8b\u52d9\uff0c\u4ee5\u63d0\u5347\u822a\u904b\u670d\u52d9\u7684\u8cea\u7d20\n\n\u8cc7\u6b77\uff1a\n\n\u6301\u6709\u6548\u672c\u5730\u8239\u9577\u4e8c\u7d1a\u8b49\u660e\u66f8\n\u4e0d\u5c11\u65bc\u5169\u5e74\u7684\u822a\u6d77\u7d93\u9a57\uff0c\u4e26\u64c1\u6709\u6700\u5c11\u4e00\u5e74\u7684\u672c\u5730\u6d77\u57df\u822a\u884c\u7d93\u9a57\uff0c\u5177\u672c\u5730\u9ad8\u901f\u96d9\u9ad4\u5ba2\u8f2a\u64cd\u4f5c\u7d93\u9a57\u512a\u5148\u8003\u616e\n\u826f\u597d\u4e2d\u82f1\u6587\u66f8\u5beb\u80fd\u529b\n\u9808\u8f2a\u73ed\u5de5\u4f5c\n\n\u5de5\u4f5c\u5730\u9ede\uff1a\u4e2d\u74b0/\u6109\u666f\u7063\n\u516c\u53f8\u514d\u8cbb\u63d0\u4f9b\u524d\u5f80\u6109\u666f\u7063\u4e4b\u4ea4\u901a\u670d\u52d9\u3002\u5f9e\u4e2d\u74b0\u4e58\u5750\u6e21\u8f2a\u524d\u5f80\u6109\u666f\u7063\u53ea\u970025\u5206\u9418\uff0c\u800c\u5f9e\u6b23\u6fb3\u5730\u9435\u7ad9\u4e58\u5750\u5df4\u58eb\u66f4\u53ea\u9700\u898110-15\u5206\u9418\u3002\u5982\u679c\u60a8\u60f3\u9032\u4e00\u6b65\u4e86\u89e3\u6109\u666f\u7063\u7684\u5de5\u4f5c\u751f\u6d3b\uff0c\u8acb\u89c0\u770b\u6b64\u5f71\u7247\uff1ahttps://goo.gl/6LLK75\n\n\u798f\u5229\uff1a\n\n\u6211\u5011\u63d0\u4f9b\u512a\u539a\u7684\u85aa\u916c\u5f85\u9047\uff0c\u5305\u62ec\u81b3\u98df\u3001\u5e74\u5047\u3001\u914c\u60c5\u82b1\u7d05\u3001\u589e\u88dc\u6027\u5f37\u7a4d\u91d1\u3001\u7259\u79d1\u548c\u91ab\u7642\u4fdd\u96aa\u7b49\u3002\u6211\u5011\u91cd\u8996\u54e1\u5de5\u7684\u8077\u696d\u767c\u5c55\uff0c\u4e26\u70ba\u4ed6\u5011\u63d0\u4f9b\u5404\u7a2e\u4e0d\u540c\u57f9\u8a13\u6a5f\u6703\u3002\n\n\u7533\u8acb\u65b9\u6cd5\uff1a\n\n\u7db2\u4e0a\u7533\u8acb - \u516c\u53f8\u7db2\u7ad9http://www.hkri.com (\u5c31\u696d\u6a5f\u6703/\u6109\u666f\u7063\u822a\u904b\u670d\u52d9\u6709\u9650\u516c\u53f8)\uff0c\u586b\u5beb\u5728\u7dda\u7533\u8acb\u8868\n\u96fb\u90f5 - \u9023\u540c\u5c65\u6b77\u548c\u671f\u671b\u85aa\u916c\u767c\u9001\u81f3Apply Now\nWhatsApp - 5603 2198\n\u50b3\u771f - 2987 5057\n\n\u7533\u8acb\u4eba\u5982\u5728\u5169\u500b\u6708\u5167\u672a\u6709\u63a5\u7372\u9762\u8a66\u901a\u77e5\uff0c\u5373\u4ee3\u8868\u5176\u8077\u4f4d\u7533\u8acb\u4e0d\u6210\u529f\u3002\u7533\u8acb\u4eba\u63d0\u4f9b\u4e4b\u5168\u90e8\u8cc7\u6599\u7d55\u5c0d\u4fdd\u5bc6\u53ca\u53ea\u4f5c\u8077\u4f4d\u62db\u8058\u7528\u9014\uff0c\u4e26\u5728\u62db\u8058\u904e\u7a0b\u7d50\u675f\u6642\u92b7\u6bc0\u3002\u5728\u4f7f\u7528\u6c42\u8077\u8005\u6240\u63d0\u4f9b\u7684\u500b\u4eba\u8cc7\u6599\u6642\uff0c\u50f1\u4e3b\u6703\u56b4\u683c\u9075\u5b88\u5176\u500b\u4eba\u8cc7\u6599\u653f\u7b56\u7684\u898f\u5b9a\uff0c\u5728\u6536\u5230\u8981\u6c42\u5f8c\uff0c\u6703\u96a8\u5373\u63d0\u4f9b\u4e00\u4efd\u6709\u95dc\u653f\u7b56\u7684\u8907\u672c\u3002", "employment_types": ["Full Time"], "selling_points": ["\u5354\u52a9\u7ba1\u7406\u8239\u4e0a\u4e00\u5207\u71df\u904b", "\u8655\u7406\u65e5\u5e38\u8239\u4e0a\u4e8b\u52d9", "\u6301\u6709\u6548\u672c\u5730\u8239\u9577\u4e8c\u7d1a\u8b49\u660e\u66f8"], "locations": ["Not Specified"], "categories": ["Transportation & Logistics", "Others", "Maritime - General", "Public Transportation"], "post_time": "2021-12-30T08:01:55Z", "salary": {"currency": null, "max": null, "min": null, "period": "monthly", "term": null}, "salary_visible": false, "title_keywords": [], "responsibilities": [], "requirements": {"degrees": [], "majors": [], "languages": [], "language_level": [], "hard_skills": ["whatsapp"], "soft_skills": [], "languages_combined": []}, "experience_required": {"duration": [], "field": []}}, {"job_id": "100003008992049", "location_code": "hk", "company": "Mind Body And Soul International Limited", "job_title": "Shipping Clerk (5 days work)", "description": "Responsibilities:\n\nHandle day-to-day shipping operation for shipments to US market.\nMonitor and provide production & shipment status for US headquarter\nResponsible smooth shipments through monitoring production/shipment schedule with China factory & coordinate with factories, US headquarter and forwarders ensure on time schedule\nHandle full set LC/IE document on back-to-back, issue, negotiate and checking\nPrepare monthly shipping reports & keep data records in proper\n\nRequirements:\n\nDiploma or above with at least 5 years working experience in manufacturing and trading environment\nExperienced in US market is a MUST\nPrevious experience in US buying office will be a great advantage\nHandle full set of shipping documents, L/C and bank documents independently\nStrong shipment coordination skills\nAble to meet tight deadline, flexible personality, strong communication, interpersonal skills and multi-task\nComputer knowledge in Microsoft Excel, Words, Outlook and Chinese Word processing are required\nProficient at written and spoken English, Cantonese and Mandarin required\n\nWe offer attractive remuneration package including 5-day work, 13-month salary, performance-based bonus, and medical scheme to the right candidate. Interested parties, please email your full resume with current salary, expected salary and date of availability by clicking \u201cAPPLY NOW\u201d.\n\nPersonal data collected will be used for recruitment purpose only.", "employment_types": ["Full Time", "Permanent"], "selling_points": [], "locations": ["Kowloon Bay"], "categories": ["Transportation & Logistics", "Shipping", "Supply Chain", "Maritime - General"], "post_time": "2021-12-29T01:44:38Z", "salary": {"currency": null, "max": null, "min": null, "period": "monthly", "term": null}, "salary_visible": false, "title_keywords": ["shipping clerk"], "responsibilities": ["shipping", "data", "monitoring", "monitor", "coordinate with", "checking", "reports", "schedule"], "requirements": {"degrees": ["diploma or above"], "majors": ["manufacturing"], "languages": ["cantonese", "english", "chinese", "mandarin"], "language_level": ["proficient"], "hard_skills": ["chinese word processing", "words", "bank documents", "microsoft excel", "c", "outlook"], "soft_skills": ["flexible", "independently", "multi-task", "coordination skills", "communication", "interpersonal skills", "meet tight deadline"], "languages_combined": [{"language": "cantonese", "language_level": ["proficient"]}, {"language": "english", "language_level": ["proficient"]}, {"language": "chinese", "language_level": []}, {"language": "mandarin", "language_level": ["proficient"]}]}, "experience_required": {"duration": ["at least 5 years"], "field": ["manufacturing", "trading"]}}, {"job_id": "100003009002327", "location_code": "hk", "company": "Anglo-Eastern Ship Management Limited", "job_title": "Technical Officer", "description": "Job Highlights\n\u00a0Guarantee Double Pay\n\u00a0Multi-national Corporation Exposure\n\u00a02 years working experience required\n\n\nJob Responsibilities:\n\nIn coordination with the Technical Superintendent purchasing spare parts and consumables for ships assigned to his team.\nArrange delivery of spares/stores to ships\nScrutinize all invoices from suppliers and maintain an accurate computer record accordingly\nMaintain files for all spare parts inventories received from ship\nResponsible for the document control (e.g. maintain check list of periodic reporting due from vessel)\nReports to the Technical Superintendent (Expatriate)\n\nRequirements:\n\nDiploma or Degree in related discipline, with at least 2 years working experience in similar capacity.\nGood command of written & spoken English.\nSound PC knowledge, experience in purchasing or related software is preferred.\nImmediate available is preferred", "employment_types": ["Full Time", "Permanent"], "selling_points": ["2 years working experience required, MNC", "Work-life balance", "Training tuition sponsorship"], "locations": ["Kowloon Bay"], "categories": ["Transportation & Logistics", "Documentary Credit / Bills Processing", "Shipping", "Maritime - General"], "post_time": "2021-12-28T04:36:14Z", "salary": {"currency": null, "max": null, "min": null, "period": "monthly", "term": null}, "salary_visible": false, "title_keywords": ["technical officer"], "responsibilities": ["reporting", "control", "invoices", "coordination with", "maintain", "reports"], "requirements": {"degrees": ["diploma", "degree"], "majors": [], "languages": ["english"], "language_level": ["good command"], "hard_skills": ["pc knowledge"], "soft_skills": [], "languages_combined": [{"language": "english", "language_level": ["good command"]}]}, "experience_required": {"duration": ["at least 2 years"], "field": ["related", "purchasing"]}}, {"job_id": "100003009007327", "location_code": "hk", "company": "ZIM Integrated Shipping Services Ltd", "job_title": "Line Manager", "description": "We are looking for a Line Manager. The main purpose is to design the product offer of the line, implement, monitor, optimize and constantly improve the performance of the Line.\n\nResponsibilities:\n\nP&L - Ensuring the budgeted volumes, revenues, costs and bottom-line profitability are met Product Management - Optimizing the service design by reviewing rotation and also negotiate with existing/potential partners.\nPricing - Defining overall pricing policies for both BCOs and the spot market in the dedicated trade lanes, special equipment pricing, Key Accounts, as well as origin arbitrariness and destination add-ons\nYield Management - Optimizing the overall yield by deciding allocation between Countries and review cargo mix. Defining the Line\u2019s sales targets\nContingency Planning - Deciding on operational contingencies by balancing operational and commercial needs\nRequirements\u00a0\n\nBusiness degree (MBA is an advantage)\nTrade Expertise and strong business acumen\nStrong communication skills\nProven work experience in a matrix organization and multi-cultural environment Proficiency in MS-Office\nFluent in English\nBusiness acumen, analytical thinking and high level of independence\nAbility to work in a dynamic environment\nTravel required\nWe offer\n\nExcellent opportunities for advancement with regional exposure\nCompetitive salary package\n5-Days Work\n18 - 20 days Annual Leave\nDouble Pay\nMedical & Dental Insurance\nLife Insurance\nBirthday Gifts\nMarriage Leave\nPaternity Leave\nWork from home arrangement\n\nInterested parties please share with us your latest resume showing current and expected remuneration package.", "employment_types": ["Full Time", "Permanent"], "selling_points": ["Experience in Line or Trade Management", "Pacific Business", "International & Dynamic Working Environment"], "locations": ["Kwun Tong"], "categories": ["Transportation & Logistics", "Shipping", "Maritime - General"], "post_time": "2021-12-30T02:25:25Z", "salary": {"currency": null, "max": null, "min": null, "period": "monthly", "term": null}, "salary_visible": false, "title_keywords": ["manager"], "responsibilities": ["management", "policies", "review", "p&l", "design", "costs", "planning"], "requirements": {"degrees": ["degree"], "majors": ["business"], "languages": ["english"], "language_level": ["fluent"], "hard_skills": ["ms-office", "dynamic", "acumen"], "soft_skills": ["business acumen", "communication skills", "dynamic environment"], "languages_combined": [{"language": "english", "language_level": ["fluent"]}]}, "experience_required": {"duration": [], "field": []}}, {"job_id": "100003009007838", "location_code": "hk", "company": "On Time Express Ltd", "job_title": "Operation Clerk, Sea Freight", "description": "Responsibilities\n\n\nHandle full set export docs and daily export bookings\nResponsible for full set export shipping document\nCommunicate with internal & overseas customer or vendors to ensure a smooth running of process\nSend loading instruction to warehouse\nSubmit SI / VGM to Carrier or co-loader\nPrepare shipment pre-alert to overseas agent after departure\nAnswer rate and service inquiry\nCross check and submit job closing file by monthly end\nHandle ad hoc assignments by Supervisor\n\nRequirements\n\nF.5 or above\nOver 1 years experience in freight forwarding for Sea export\nExport declaration (Tradelink system)\nComputer- Word, Excel, PowerPoint, Access, FrontPage\nGood Command of spoken / written English & Fluent Mandarin\nStrong sense on team work and customer-oriented\nGood timing management and communication skill\nTyping \u2013 ENG 57 wpm ; Chinese 33 wpm\n\nWe offer\n\nDouble pay\nPerformance bonus\n5 days work\nFree shuttle bus\n\nIf you have the desire for an exciting and rewarding career, please send us your resume with stating your present and expected salary to Human Resources Department\n\nOnly short-listed candidates will be contacted.\n\nOn Time is an equal opportunity employer and welcomes applications from all qualified candidates. Information provided will be treated in strict confidence and will only be used for recruitment-related purposes. Personal data provided by job applicants will be used strictly in accordance.", "employment_types": ["Full Time", "Permanent"], "selling_points": ["Ocean export operation, handle export doc&booking", "Good team player & Customer-oriented", "Double pay, performance bonus & 5 days work"], "locations": ["Kowloon Bay"], "categories": ["Transportation & Logistics", "Freight Forwarding", "Shipping", "Maritime - General"], "post_time": "2021-12-30T04:42:19Z", "salary": {"currency": null, "max": null, "min": null, "period": "monthly", "term": null}, "salary_visible": false, "title_keywords": ["operation clerk"], "responsibilities": ["communicate with", "shipping document", "ad hoc assignments"], "requirements": {"degrees": [], "majors": [], "languages": ["english", "chinese", "mandarin"], "language_level": ["good command", "fluent"], "hard_skills": ["excel", "word", "powerpoint", "typing"], "soft_skills": ["customer-oriented", "communication skill"], "languages_combined": [{"language": "english", "language_level": ["fluent", "good command"]}, {"language": "chinese", "language_level": []}, {"language": "mandarin", "language_level": ["good command"]}]}, "experience_required": {"duration": ["1 years"], "field": []}}, {"job_id": "100003009000229", "location_code": "hk", "company": "Bernhard Schulte ShipMgt (HK) Ltd Partnership", "job_title": "Insurance & Claims Officer", "description": "Core Responsibilities\n\n\u00a0\u00a0\u00a0\u00a0\u00a0\u00a0\u00a0 Co-ordinate and liaise with the P&I Clubs, Ship owners, surveyors on all related matter to claims\n\u00a0\u00a0\u00a0\u00a0\u00a0\u00a0\u00a0 Ensure all claims are handled and finalized in a timely manner\n\u00a0\u00a0\u00a0\u00a0\u00a0\u00a0\u00a0 Maintain P&I and H&M claims documentations and database\n\u00a0\u00a0\u00a0\u00a0\u00a0\u00a0\u00a0 Co-ordinate with internally parties for accurate booking and charging to owner\n\u00a0\u00a0\u00a0\u00a0\u00a0\u00a0\u00a0 Provide full support in other ad hoc assignments as required\n\nRequirements\n\n\u00a0\u00a0\u00a0\u00a0\u00a0\u00a0\u00a0 Diploma or above\n\u00a0\u00a0\u00a0\u00a0\u00a0\u00a0\u00a0 Around 3 years relevant working experience and preferably with some multinational environment exposure\n\u00a0\u00a0\u00a0\u00a0\u00a0\u00a0\u00a0 Good knowledge of P&I rules, marine insurance industry and claim experience\n\u00a0\u00a0\u00a0\u00a0\u00a0\u00a0\u00a0 Have knowledge in local and international laws relevant to maritime industry\n\u00a0\u00a0\u00a0\u00a0\u00a0\u00a0\u00a0 Good team player, hard working and well-organized\n\u00a0\u00a0\u00a0\u00a0\u00a0\u00a0\u00a0 Self-motivated, independent and detail-minded\n\u00a0\u00a0\u00a0\u00a0\u00a0\u00a0\u00a0 Good command of both spoken and written English\n\u00a0\u00a0\u00a0\u00a0\u00a0\u00a0\u00a0 \u00a0Proficient in MS Office applications, especially in MS Excel\n\n\n\n\nWe offer competitive remuneration package to the right candidate.\u00a0 Interested candidates, please send your CV and application letter to HR Department, Bernhard Schulte Shipmanagement (Hong Kong) Limited Partnership, 26/F K Wah Center, 191 Java Road, North Point, Hong Kong or to our direct fax number 2960-1530 or apply through \u201cApply Now\u201d function.\u00a0 Personal data collected will be used for recruitment purpose only and treated in accordance with Personal Data (Privacy) Ordinance.", "employment_types": ["Full Time", "Permanent"], "selling_points": ["Liaise with various parties for claims", "Maintain P&I & H&M claims documentations &database", "Accurate booking and charging to owner"], "locations": ["North Point"], "categories": ["Insurance", "Claims Officer", "Transportation & Logistics", "Maritime - General"], "post_time": "2021-12-24T15:37:39Z", "salary": {"currency": null, "max": null, "min": null, "period": null, "term": null}, "salary_visible": false, "title_keywords": ["claims officer"], "responsibilities": ["co-ordinate with", "a timely manner", "maintain", "booking", "database", "ad hoc assignments", "liaise with"], "requirements": {"degrees": ["diploma or above"], "majors": [], "languages": ["english"], "language_level": ["good command"], "hard_skills": ["ms excel", "ms office"], "soft_skills": ["detail-minded", "good team player", "self-motivated", "independent", "hard working", "well-organized"], "languages_combined": [{"language": "english", "language_level": ["good command"]}]}, "experience_required": {"duration": ["3 years"], "field": ["insurance industry", "relevant working experience"]}}, {"job_id": "100003008990211", "location_code": "hk", "company": "Bernhard Schulte ShipMgt (HK) Ltd Partnership", "job_title": "Fleet Personnel Officer", "description": "Core Responsibilities:\n\n\n\nTo ensure that all vessels are manned with properly certified seafarers\u00a0\u00a0\u00a0\u00a0\u00a0\u00a0\u00a0\u00a0\u00a0\u00a0\u00a0\u00a0\u00a0\u00a0\u00a0\u00a0\nTo coordinate with various manning agents for recruitment\nMaintain timely and cost effective crew changes\nMaintain an up-to-date and accurate database of crew personnel data\nAssist in following up of Crew P & I claims\nMake travel arrangements and liaise with local port agents\nCheck agents disbursements\nCorrespond with owners on various crewing matters\nPrepare and maintain various reports\nAssist in ad hoc projects and assignments\n\n\u00a0Requirements:\n\nDiploma holder and preferably in the discipline of Maritime or Shipping Logistics\n3- 5 years relevant and solid working experience\nPossess good people skills and be aware of cross-cultural aspects\nGood team player, organized and detail-minded\nSelf-motivated, high integrity and able to cope with work pressure\nGood command of both spoken and written English\n\n\nWe offer competitive remuneration package to the right candidate.\u00a0 Interested candidates, please send your CV and application letter to HR Department, Bernhard Schulte Shipmanagement (Hong Kong) Limited Partnership, 26/F K Wah Center, 191 Java Road, North Point, Hong Kong or apply through the \"Apply Now\" function.\u00a0 Personal data collected will be used for recruitment purpose only and treated in accordance with Personal Data (Privacy) Ordinance.", "employment_types": ["Full Time", "Permanent"], "selling_points": ["Coordinate with various manning agents for recruit", "Maintain timely and cost effective crew changes", "Self-motivated and able to cope with work pressure"], "locations": ["North Point"], "categories": ["Transportation & Logistics", "Others", "Maritime - General"], "post_time": "2021-12-21T07:59:27Z", "salary": {"currency": null, "max": null, "min": null, "period": null, "term": null}, "salary_visible": false, "title_keywords": ["officer"], "responsibilities": ["cost", "travel arrangements", "data", "coordinate with", "maintain", "recruitment", "reports", "database", "ad hoc projects", "liaise with", "disbursements"], "requirements": {"degrees": ["diploma holder"], "majors": [], "languages": ["english"], "language_level": ["good command"], "hard_skills": [], "soft_skills": ["detail-minded", "organized", "good team player", "self-motivated", "integrity"], "languages_combined": [{"language": "english", "language_level": ["good command"]}]}, "experience_required": {"duration": ["3- 5 years"], "field": []}}, {"job_id": "100003008990213", "location_code": "hk", "company": "Bernhard Schulte ShipMgt (HK) Ltd Partnership", "job_title": "Technical Officer / Purchasing Officer", "description": "Core Responsibilities:\n\nProvide administrative support to Technical Superintendent and vessels\nArrange timely supplies and spares to the vessels in a most economical manner\nEnsure a proper documentation of vessels records and correspondences\nEnsure the validity of certificates and surveys\n\nRequirements:\n\nDiploma holder or above, study in the discipline of Marine or Mechanical Engineering will be an advantage\n5 years relevant working experience in purchasing and preferably in ship management industry\nGood team player, organized and detail-minded\nSelf-motivated, high integrity and able to cope with high work pressure\nGood command of both spoken and written English\nProficient in MS Office applications\n\nWe offer competitive remuneration package to the right candidate. Interested candidates, please send your CV and application letter to HR Department, Bernhard Schulte Shipmanagement (Hong Kong) Limited Partnership, 26/F K Wah Center,191 Java Road, North Point,Hong Kong\u00a0 or to our direct fax number 2960-1530 or apply through \"Apply Now\" function.\u00a0 Personal data collected will be used for recruitment purpose only and treated in accordance with Personal Data (Privacy) Ordinance.", "employment_types": ["Full Time", "Permanent"], "selling_points": ["Arrange timely supplies and spares to the vessel", "Ensure a proper documentation", "Ensure the validity of certificates and surveys"], "locations": ["North Point"], "categories": ["Merchandising & Purchasing", "Others", "Transportation & Logistics", "Maritime - General", "Others", "Others"], "post_time": "2021-12-21T08:00:08Z", "salary": {"currency": null, "max": null, "min": null, "period": null, "term": null}, "salary_visible": false, "title_keywords": ["technical officer", "purchasing officer"], "responsibilities": ["provide administrative support", "documentation"], "requirements": {"degrees": ["diploma holder"], "majors": ["mechanical engineering"], "languages": ["english"], "language_level": ["good command"], "hard_skills": ["ms office"], "soft_skills": ["detail-minded", "organized", "good team player", "self-motivated", "integrity"], "languages_combined": [{"language": "english", "language_level": ["good command"]}]}, "experience_required": {"duration": ["5 years"], "field": ["purchasing", "management", "relevant working experience"]}}, {"job_id": "100003008990212", "location_code": "hk", "company": "Bernhard Schulte ShipMgt (HK) Ltd Partnership", "job_title": "Technical Officer / Purchasing Officer", "description": "Core Responsibilities:\n\nProvide administrative support to Technical Superintendent and vessels\nArrange timely supplies and spares to the vessels in a most economical manner\nEnsure a proper documentation of vessels records and correspondences\nEnsure the validity of certificates and surveys\n\nRequirements:\n\nDiploma holder or above, study in the discipline of Marine or Mechanical Engineering will be an advantage\n5 years relevant working experience in purchasing and preferably in ship management industry\nGood team player, organized and detail-minded\nSelf-motivated, high integrity and able to cope with high work pressure\nGood command of both spoken and written English\nProficient in MS Office applications\n\n\u00a0(Candidate with less experience will be considered as an Assistant Technical Officer)\n\nWe offer competitive remuneration package to the right candidate. Interested candidates, please send your CV and application letter to HR Department, Bernhard Schulte Shipmanagement (Hong Kong) Limited Partnership, 26/F K Wah Center,191 Java Road, North Point,Hong Kong\u00a0 or to our direct fax number 2960-1530 or apply through \"Apply Now\" function.\u00a0 Personal data collected will be used for recruitment purpose only and treated in accordance with Personal Data (Privacy) Ordinance.", "employment_types": ["Full Time", "Permanent"], "selling_points": ["Arrange timely supplies and spares to the vessel", "Ensure a proper documentation", "Ensure the validity of certificates and surveys"], "locations": ["North Point"], "categories": ["Merchandising & Purchasing", "Others", "Transportation & Logistics", "Maritime - General", "Others", "Others"], "post_time": "2021-12-21T08:00:08Z", "salary": {"currency": null, "max": null, "min": null, "period": null, "term": null}, "salary_visible": false, "title_keywords": ["technical officer", "purchasing officer"], "responsibilities": ["provide administrative support", "documentation"], "requirements": {"degrees": ["diploma holder"], "majors": ["mechanical engineering"], "languages": ["english"], "language_level": ["good command"], "hard_skills": ["ms office"], "soft_skills": ["detail-minded", "organized", "good team player", "self-motivated", "integrity"], "languages_combined": [{"language": "english", "language_level": ["good command"]}]}, "experience_required": {"duration": ["5 years"], "field": ["purchasing", "management", "relevant working experience"]}}, {"job_id": "100003008988011", "location_code": "hk", "company": "Princess Yachts Greater China Limited", "job_title": "Technical Manager (Luxury Yacht)", "description": "Job Duties:\n\nManage warranty and aftersales service for a range of marine group products\nEnsure all warranty and service repairs are completed at a high level of standard\u00a0\nDeliver prompt technical advice and assistance to yacht owners and their technical staff\nInteract with quality control team in the factory to report defects and improve product quality\nLiaise with the principal on yachts handover and pre-delivery inspection reports\nOrganize training for technical staff, yacht owners, captains and crews\n\nRequirements:\n\nOver 5 years\u2019 relevant experience in the yacht industry\nFamiliar with yacht systems and operations\nFluency in English\nStrong interpersonal and communication skills\n\nAttractive salary package and fringe benefits will be offered to the successful candidate. Interested parties please send your resume stating reference number and expected salary to Human Resources Department\u00a0by email, whatsapp to 9318 2638 or fax to 2798 9562.\u00a0\n\nWe are an equal opportunities employer. Personal data collected will be treated in strict confidence and used for recruitment purposes only. All applications may be considered for other suitable positions with DCH Group / CITIC Pacific Group and the personal data collected will be deleted from our files after 6 months from the date of application.", "employment_types": ["Full Time", "Permanent"], "selling_points": [], "locations": ["Tsing Yi"], "categories": ["Engineering", "Engineering Project Management", "Mechanical", "Transportation & Logistics", "Maritime - General"], "post_time": "2021-12-20T08:55:12Z", "salary": {"currency": null, "max": null, "min": null, "period": "monthly", "term": null}, "salary_visible": false, "title_keywords": ["technical manager"], "responsibilities": ["inspection reports", "technical advice", "quality", "quality control", "liaise with", "report"], "requirements": {"degrees": [], "majors": [], "languages": ["english"], "language_level": ["fluency"], "hard_skills": [], "soft_skills": ["communication skills", "interpersonal"], "languages_combined": [{"language": "english", "language_level": ["fluency"]}]}, "experience_required": {"duration": ["5 years"], "field": ["relevant experience"]}}, {"job_id": "100003008994018", "location_code": "hk", "company": "Orient Overseas Container Line Ltd (OOCL)", "job_title": "Management Trainee (Ref: MT 2022)", "description": "Orient Overseas Container Line Ltd (OOCL) is a leading international container transport and logistics solutions provider, operating from over 120 offices in more than 100 major cities. It offers a global service network encompassing Asia, Europe, Americas, Africa, the Mediterranean, Indian sub-continent, Middle East, and Australia/New Zealand, providing over 190 weekly services and growing. Headquartered in Hong Kong, OOCL employs over 10,000 staff globally.\u00a0\n\nManagement Trainee\u00a0\n\nThe\u202fOOCL Management Trainee Program\u202fwill prepare you for a flourishing career as an executive in our Company:\u00a0\n\n\nA 3-year structured Development Program designed to develop leadership, managerial and functional\u00a0skills;\n\nA series of function-focused job rotations in different Corporate\u00a0and Regional functions across liner and logistics\u00a0business;\n\nAn extensive on-the-job training, coaching, project assignments, and opportunities to organize corporate activities and\u00a0functions;\u00a0\n\nUpon successful completion with fulfillment of predetermined performance criteria, you will be rewarded with a fast-track career development.\u202f At OOCL, performance, potential and attitude count!\u00a0\n\n\nTo succeed in this role, you must meet the following requirements:\u00a0\n\n\nBachelor\u2019s degree or above with outstanding academic results\u00a0\n\nFresh and recent graduates with no more than 2 years of\u00a0full-time\u00a0working experience\u00a0\n\nStrong business acumen, conceptual thinking, analytical ability, and drive to achieve excellence\u00a0\n\nA good, passionate, self-motivated team player and role model with leadership potential, and excellent interpersonal and communication skills\u00a0\n\nPositive to challenges, innovative and capable to identify solutions to problems\u00a0\n\nProficient in Microsoft Office Applications \u202f\u00a0\n\nExcellent command of written and spoken English and Chinese; proficiency in other languages a plus\u00a0\n\nHighly adaptable in a multi-cultural and dynamic environment, and prepared to accept overseas assignments within the Group\u00a0\n\nIf you\u00a0are able to\u00a0produce outstanding results in a challenging environment and are looking for a career which offers exceptional growth possibilities, why not put the power of your work, your advancement, and your career precisely where it belongs \u2013 in your hands!\n\n\nWork Location\u00a0\nWan Chai or Kwun Tong office depending on the job rotation plan.\u202f Excellent performers may be given opportunities of overseas assignments upon business needs. \u202f\u00a0\n\nCompensation & Benefits\u00a0\nWe offer attractive remuneration package with good career prospect to the right candidate.\u00a0\n\nApplication Procedure\u00a0\nPlease\u00a0submit your application\u00a0HERE\u00a0on or before\u00a0December\u00a031, 2021.\u00a0\n\nYou can\u00a0visit our website for more information about our Management Trainee Program.\n\n(Data collected will be used for recruitment purpose only.)\u00a0", "employment_types": ["Full Time", "Permanent"], "selling_points": ["Bachelor\u2019s degree or above in all disciplines", "Promising career path with job rotations", "Develop leadership, managerial & functional skills"], "locations": ["Not Specified"], "categories": ["Transportation & Logistics", "Shipping", "Maritime - General", "Management", "Management Trainee"], "post_time": "2021-12-22T10:16:29Z", "salary": {"currency": null, "max": null, "min": null, "period": "monthly", "term": null}, "salary_visible": false, "title_keywords": ["management trainee"], "responsibilities": ["management", "fulfillment", "develop", "communication", "logistics", "career development"], "requirements": {"degrees": ["degree or above", "bachelor"], "majors": [], "languages": ["english", "chinese"], "language_level": ["excellent"], "hard_skills": ["no", "plus", "microsoft office", "dynamic", "container", "acumen"], "soft_skills": ["passionate", "communication skills", "self-motivated", "dynamic environment", "capable", "focused", "adaptable", "extensive", "innovative", "business acumen", "team player", "structured", "leadership", "interpersonal", "positive"], "languages_combined": [{"language": "english", "language_level": ["excellent"]}, {"language": "chinese", "language_level": ["excellent"]}]}, "experience_required": {"duration": ["2 years"], "field": []}}, {"job_id": "100003008987290", "location_code": "hk", "company": "Honor Information Technology Co., Limited", "job_title": "Logistics Operations Assistant", "description": "\nPosition Description:\n\nHandle customs declaration operations for Hong Kong imports and exports\nHandling Hong Kong trade control license operations\nCoordinate with Hong Kong Customs and Hong Kong Census and Statistics Department to handle other import and export business\nManage supplier's operation quality and exception handling\nStatistical analysis of Hong Kong's import and export business to promote business improvement\u00a0\u00a0\nWork Experience Requirements:\n\nF5 or above;\nAt least 1-2 years of working experience in shipping or logistic field\nAble to handle apply HK import / export liecnse\nGood PC shills (Word, Excel, Outlook & Tradelink) & Chinese Word processing\nGood in spoken & written English, Cantonese & Mandarin\nPersonal Characteristics:\n\n\nCan identify the multiple factors affecting an issue and the various consequences of different actions, capable to find out how complex issues relate to one another\n\n\n\nAdditional Information:\n\nMonday to Friday-office hour\nWork location:\u00a0Tsim Sha Tsui\nmedical Insurance\nWe offer attractive remuneration package and excellent career opportunities to the right candidates.\u00a0 Interested parties please send your full resume with available, current and expected salary to The Human Resources Department,\u00a0Honor Information Technology Co., Limited\nFor enquiry, please contact HR Dept. at +852-3580 1931\n\n\n", "employment_types": ["Full Time", "Contract"], "selling_points": ["Opportunity for career progression", "International exposure", "Stable working environment"], "locations": ["Tsim Sha Tsui"], "categories": ["Transportation & Logistics", "Maritime - General"], "post_time": "2021-12-20T05:52:48Z", "salary": {"currency": "HKD", "max": 19999, "min": 14000, "period": "monthly", "term": null}, "salary_visible": true, "title_keywords": ["operations assistant", "logistics"], "responsibilities": ["control", "shipping", "customs declaration", "tradelink", "operations", "analysis", "quality", "coordinate with"], "requirements": {"degrees": [], "majors": [], "languages": ["cantonese", "english", "chinese", "mandarin"], "language_level": ["good"], "hard_skills": ["excel", "chinese word processing", "statistical analysis", "word", "import and export", "outlook", "pc"], "soft_skills": ["capable"], "languages_combined": [{"language": "cantonese", "language_level": ["good"]}, {"language": "english", "language_level": ["good"]}, {"language": "chinese", "language_level": ["good"]}, {"language": "mandarin", "language_level": ["good"]}]}, "experience_required": {"duration": ["at least 1-2 years"], "field": []}}, {"job_id": "100003008990247", "location_code": "hk", "company": "Bernhard Schulte ShipMgt (HK) Ltd Partnership", "job_title": "Technical Superintendent", "description": "Job Objective:\n\nMonitors and controls the safe and cost efficient technical operation of all assigned vessels using the available resources, within the defined parameters of cost, commercial viability and operational excellence in line with Owners expectations.\n\nCore Responsibilities:\u00a0\u00a0\n\nResponsible for the day to day operation of assigned vessels, to be maintained and operated safely, effectively and reliably within the technical budget\nEnsure that maintenance planning, execution and control is carried out according to company standards and in conformance to the planned maintenance system\nEnsure vessels are operated in full compliance with relevant regulations and requirements\nMonitor survey status of vessels, conduct periodic inspection of assigned vessels, and follow up on identified defects\nPrepare, supervise, attend and follow-up on dry-dockings & repairs, supply of stores and spares\nDemonstrate a strong customer-centric approach to solving problems and have revenue protection as their primary goal.\u00a0\nOther special tasks and projects as per Fleet Manager / Fleet Director / Managing Director\u2019s instruction\n\nRequirements:\n\nEducation & Qualifications\u00a0\n\nB.S. degree in Mechanical, Electrical or Marine Engineering, Naval Architecture or equivalent, or\nChief Engineer\u2019s qualification\n\n\u00a0Work Experience\n\n\u00a03 years of sailing experience as Senior Officer, or\n3 years of shore experience as a technical superintendent with a ship management/owning company\n\n\u00a0Job-Specific Skills\n\n\u00a0Strong knowledge of vessels\u2019 technical requirements and voyage regulations\nExcellent project management skills\nVery good negotiation skills\nVery good people management skills\nTeam work and cooperation\nVery good organisational skills\nGood communication and problem solving skills\u00a0\nHigh integrity and able to work under pressure\u00a0\nWilling to travel on board on a regular basis\u00a0\nFluency in English\nPC literacy\n\n(Candidate with more experience will be considered as a Senior Technical Superintendent)\n\nWe offer competitive remuneration package to the right candidate. Interested candidates, please send your CV and application letter to HR Department, Bernhard Schulte Shipmanagement (Hong Kong) Limited Partnership, 26/F K Wah Center,191 Java Road, North Point,Hong Kong\u00a0 or to our direct fax number 2960-1530 or apply through \"Apply Now\" function.\u00a0 Personal data collected will be used for recruitment purpose only and treated in accordance with Personal Data (Privacy) Ordinance.", "employment_types": ["Full Time", "Permanent"], "selling_points": ["Day to day operation of assigned vessels", "Ensure vessels are operated in full compliance", "Maintenance planning, execution and control"], "locations": ["North Point"], "categories": ["Transportation & Logistics", "Maritime - General"], "post_time": "2021-12-21T08:09:14Z", "salary": {"currency": null, "max": null, "min": null, "period": null, "term": null}, "salary_visible": false, "title_keywords": [], "responsibilities": ["regulations", "control", "maintenance", "compliance", "budget", "monitor", "inspection", "planning"], "requirements": {"degrees": ["degree"], "majors": ["architecture", "engineering"], "languages": ["english"], "language_level": ["fluency"], "hard_skills": ["pc", "project management", "problem solving skills"], "soft_skills": ["project management skills", "integrity", "communication", "negotiation skills", "organisational skills", "problem solving skills", "work under pressure"], "languages_combined": [{"language": "english", "language_level": ["fluency"]}]}, "experience_required": {"duration": ["3 years"], "field": ["management"]}}]