[{"job_id": "100003009053544", "location_code": "hk", "company": "King Easy Telecom Limited", "job_title": "\u5009\u52d9\u54e1", "description": "\n\u8077\u8cac :\u8ca0\u8cac\u5009\u52d9\u5de5\u4f5c, \u5982\u6536\u767c\u8ca8, \u6574\u7406\u8ca8\u5009, \u76e4\u9ede\u8ca8\u5b58, \u642c\u904b\u8ca8\u7bb1, \u5916\u51fa\u9001\u8ca8, \u66f4\u65b0\u5b58\u8ca8\u8a18\u9304\u7b49; \u5354\u52a9\u751f\u7522\u7dda\u5305\u88dd\u7522\u54c1, \u78ba\u4fdd\u51fa\u54c1\u5408\u7b26\u6a19\u6e96\u8981\u6c42\n\n\u8cc7\u6b77 :\u6c92\u6709\u5b78\u6b77\u8981\u6c42; \u4e00\u822c\u7cb5\u8a9e; \u61c2\u8b80\u5beb\u4e2d\u6587; \u61c2\u4f7f\u7528\u5527\u8eca\u512a\u5148; \u6709\u79ae\u8c8c\u3001\u76e1\u8cac\u3001\u52e4\u596e\u5b88\u6642\u3001\u8655\u4e8b\u7d30\u5fc3\u3001\u5de5\u4f5c\u7a4d\u6975\u4e3b\u52d5\u53ca\u5177\u5718\u968a\u5408\u4f5c\u7cbe\u795e\n\n\u5f85\u9047 :\u6bcf\u6708$13,000 - $15,000, \u6709\u8d85\u6642\u5de5\u4f5c\u6d25\u8cbc, \u5e74\u50478\u5929, \u9280\u884c\u5047\u671f, \u914c\u60c5\u6027\u82b1\u7d05, \u54e1\u5de5\u8cfc\u7269\u512a\u60e0 \u53ca\u5728\u8077\u57f9\u8a13, \u661f\u671f\u4e00\u81f3\u516d: \u4e0a\u53489\u6642\u81f3\u4e0b\u53486\u6642, \u6bcf\u9031\u5de5\u4f5c6\u5929, \u6bcf\u5929\u5de5\u4f5c 9 \u5c0f\u6642, 1\u5c0f\u6642\u7528\u81b3\u6642\u9593, \u56e0\u61c9\u516c\u53f8\u5de5\u4f5c\u60c5\u6cc1\u53ef\u80fd\u6709\u9700\u8981\u8d85\u6642\u5de5\u4f5c\n\n\u7533\u8acb\u9808\u77e5 :\u6c42\u8077\u8005\u53ef\u81f4\u96fb31690986\u8207\u7ffa\u76df\u8cc7\u672c\uff08\u9999\u6e2f\uff09\u6709\u9650\u516c\u53f8\u9673\u5c0f\u59d0\u806f\u7d61\u3002\n\n", "employment_types": ["Full Time"], "selling_points": [], "locations": ["Not Specified"], "categories": ["Transportation & Logistics", "Others", "Inventory / Warehousing", "Supply Chain"], "post_time": "2022-01-17T07:08:14Z", "salary": {"currency": null, "max": null, "min": null, "period": "monthly", "term": null}, "salary_visible": false, "title_keywords": ["\u5009\u52d9\u54e1"], "responsibilities": [], "requirements": {"degrees": [], "majors": [], "languages": [], "language_level": [], "hard_skills": [], "soft_skills": [], "languages_combined": []}, "experience_required": {"duration": [], "field": []}}, {"job_id": "100003009053902", "location_code": "hk", "company": "Kallimount Capital (HK) Limited", "job_title": "\u5305\u88dd,\u5009\u7ba1\u517c\u7269\u6d41\u9001\u8ca8\u54e1**", "description": "\n\u8077\u8cac :\u8ddf\u9032\u92b7\u552e\u5718\u968a\u7684\u92b7\u552e\u8a02\u55ae\u4e26\u8207\u5167\u90e8\u548c\u5916\u90e8\u5404\u65b9\u806f\u7d61\u5f8c\u52e4\u5b89\u6392; \u8655\u7406\u3001\u6e96\u5099\u548c\u8a18\u9304\u4ea4\u4ed8\u6587\u4ef6; \u4fdd\u6301\u5eab\u5b58\u5340\u57df\u6574\u6f54; \u8655\u7406\u81e8\u6642\u5206\u914d\u7684\u4efb\u52d9\n\n\u8cc7\u6b77 :\u4e2d\u4e94\u7a0b\u5ea6; 2\u5e74\u7d93\u9a57; \u826f\u597d\u7cb5\u8a9e; \u4e00\u822c\u666e\u901a\u8a71; \u826f\u597d\u82f1\u8a9e; \u61c2\u8b80\u5beb\u4e2d\u6587; \u7565\u61c2\u8b80\u5beb\u82f1\u6587; \u61c2MS Word; \u61c2MS Excel; \u80fd\u7368\u7acb\u5de5\u4f5c\u4e26\u627f\u53d7\u58d3\u529b;\u826f\u597d\u5408\u4f5c\u7cbe\u795e;\u9858\u610f\u5b78\u7fd2;\u5177\u8655\u7406\u91ab\u7642\u7d93\u9a57\u512a\u5148\n\n\u5f85\u9047 :\u6bcf\u6708$17,000 - $18,000, \u6709\u96d9\u7ce7, \u661f\u671f\u4e00\u81f3\u4e94: \u4e0a\u53489\u6642\u81f3\u4e0b\u53486\u6642, \u6bcf\u9031\u5de5\u4f5c5\u5929, \u9700\u8981\u6642\u52a0\u73ed\u5de5\u4f5c\n\n\u7533\u8acb\u9808\u77e5 :\u6c42\u8077\u8005\u53ef\u96fb\u90f5(Apply Now)\u5c65\u6b77\u8868\u7d66\u5c08\u696d\u5eb7\u5065\u8cbf\u6613\u6709\u9650\u516c\u53f8\u3002\u5982\u8981\u7d22\u53d6\u6536\u96c6\u500b\u4eba\u8cc7\u6599\u8072\u660e, \u8acb\u8207\u80e1\u5148\u751f(Email)\u806f\u7d61\u3002\n\n", "employment_types": ["Full Time"], "selling_points": [], "locations": ["Kwun Tong"], "categories": ["Transportation & Logistics", "Others", "Inventory / Warehousing", "Supply Chain"], "post_time": "2022-01-17T07:43:51Z", "salary": {"currency": null, "max": null, "min": null, "period": "monthly", "term": null}, "salary_visible": false, "title_keywords": ["\u5305\u88dd"], "responsibilities": [], "requirements": {"degrees": [], "majors": [], "languages": [], "language_level": [], "hard_skills": ["excel", "word"], "soft_skills": [], "languages_combined": []}, "experience_required": {"duration": [], "field": []}}, {"job_id": "100003009053842", "location_code": "hk", "company": "Professional Health Trading Company Limited", "job_title": "\u7269\u6d41\u5354\u8abf\u54e1", "description": "Job Responsibilities:-\n\nResponse to customer\nHandling inbound/outbound Ocean Freight shipment and planning\nManage Ocean Freight shipment data and ensure data integrity\nCommunicate with other branches/ origin offices\nRequirements:-\n\nFluent in English and Chinese\nMinimum 2 years relevant working experience\nFluent in English and Mandarin, both written and spoken\nImmediate available is\u00a0highly preferred\n\n\nPlease send full resume with present & expected salary for consideration.", "employment_types": ["Full Time"], "selling_points": [], "locations": ["Kwun Tong Area"], "categories": ["Transportation & Logistics", "Others", "Inventory / Warehousing", "Supply Chain"], "post_time": "2022-01-17T07:36:43Z", "salary": {"currency": null, "max": null, "min": null, "period": "monthly", "term": null}, "salary_visible": false, "title_keywords": [], "responsibilities": ["communicate with", "data", "planning"], "requirements": {"degrees": [], "majors": [], "languages": ["english", "chinese", "mandarin"], "language_level": ["fluent"], "hard_skills": [], "soft_skills": [], "languages_combined": [{"language": "english", "language_level": ["fluent", "fluent"]}, {"language": "chinese", "language_level": ["fluent", "fluent"]}, {"language": "mandarin", "language_level": ["fluent", "fluent"]}]}, "experience_required": {"duration": ["minimum 2 years"], "field": ["relevant working experience"]}}, {"job_id": "100003009056866", "location_code": "hk", "company": "Delmar International (Hong Kong) Limited", "job_title": "Ocean Freight Operations (5 Day Work)", "description": "Job Responsibilities:-\n\nResponse to customer\nHandling inbound/outbound Ocean Freight shipment and planning\nManage Ocean Freight shipment data and ensure data integrity\nCommunicate with other branches/ origin offices\nRequirements:-\n\nFluent in English and Chinese\nMinimum 2 years relevant working experience\nFluent in English and Mandarin, both written and spoken\nImmediate available is\u00a0highly preferred\n\n\nPlease send full resume with present & expected salary for consideration.", "employment_types": ["Full Time", "Permanent"], "selling_points": ["Immediate available is highly preferred", "Handling inbound/outbound shipment and planning", "5 Day Work Week"], "locations": ["Kwai Fong"], "categories": ["Transportation & Logistics", "Others", "Freight Forwarding", "Fulfillment"], "post_time": "2022-01-18T06:36:28Z", "salary": {"currency": null, "max": null, "min": null, "period": "monthly", "term": null}, "salary_visible": false, "title_keywords": ["operations"], "responsibilities": ["communicate with", "data", "planning"], "requirements": {"degrees": [], "majors": [], "languages": ["english", "chinese", "mandarin"], "language_level": ["fluent"], "hard_skills": [], "soft_skills": [], "languages_combined": [{"language": "english", "language_level": ["fluent", "fluent"]}, {"language": "chinese", "language_level": ["fluent", "fluent"]}, {"language": "mandarin", "language_level": ["fluent", "fluent"]}]}, "experience_required": {"duration": ["minimum 2 years"], "field": ["relevant working experience"]}}, {"job_id": "100003009055713", "location_code": "hk", "company": "Bun Kee (International) Ltd", "job_title": "\u5e97\u8216\u7406\u8ca8\u54e1", "description": "\u5730\u5340 :\u6d41\u6d6e\u5c71\n\u884c\u696d :\u96f6\u552e\u696d\n\u8077\u8cac :\u4e00\u822c\u5009\u52d9\u54e1/\u7406\u8ca8\u54e1\u5de5\u4f5c, \u8ca0\u8cac\u57f7\u8ca8, \u6536\u8ca8, \u642c\u8ca8, \u7528\u5527\u8eca, \u4e00\u822c\u5009\u52d9\u5de5\u4f5c\n\u8cc7\u6b77 :\u6c92\u6709\u5b78\u6b77\u8981\u6c42; \u826f\u597d\u7cb5\u8a9e; \u61c2\u8b80\u5beb\u4e2d\u6587; \u61c2\u95b1\u8b80\u82f1\u6587; \u61c2\u4f7f\u7528\u624b\u6a5f\u901a\u8a0a\u7a0b\u5f0f\n\u5f85\u9047 :\u6bcf\u6708$13,000 - $16,000, \u6709\u751f\u65e5\u5047,\u91ab\u7642\u798f\u5229,\u6bcf\u6708\u52e4\u5de5\u734e\u91d1$500,\u5a5a\u50471\u5929,\u6bcf\u5c0f\u6642\u8d85\u6642\u5de5\u4f5c\u6d25\u8cbc$45,\u6069\u6064\u50472\u5929, \u661f\u671f\u4e00\u81f3\u516d: \u4e0a\u53488\u6642\u534a\u81f3\u4e0b\u53485\u6642, \u6bcf\u9031\u5de5\u4f5c6\u5929, \u6bcf\u5929\u5de5\u4f5c 8 \u5c0f\u6642\n\u7533\u8acb\u9808\u77e5 :\u6c42\u8077\u8005\u53ef\u81f4\u96fb53360127\u8207\u58eb\u591a\u9999\u6e2f\u6709\u9650\u516c\u53f8\u6881\u5148\u751f\u806f\u7d61\u3002", "employment_types": ["Full Time", "Permanent"], "selling_points": [], "locations": ["Mong Kok"], "categories": ["Transportation & Logistics", "Others", "Sales, CS & Business Devpt", "Retail Sales", "Others"], "post_time": "2022-01-18T02:52:47Z", "salary": {"currency": null, "max": null, "min": null, "period": "monthly", "term": null}, "salary_visible": false, "title_keywords": [], "responsibilities": [], "requirements": {"degrees": [], "majors": [], "languages": [], "language_level": [], "hard_skills": [], "soft_skills": [], "languages_combined": []}, "experience_required": {"duration": [], "field": []}}, {"job_id": "100003009055842", "location_code": "hk", "company": "Ztore HK Limited", "job_title": "\u5009\u52d9\u54e1/\u7406\u8ca8\u54e1", "description": "\n\u8077\u8cac :\u8ca0\u8cac\u8ca8\u6ac3\u904b\u900140\"\u62d6\u67b6, \u65bc\u8475\u82b3\u53d6\u8eca\n\n\u8cc7\u6b77 :\u6c92\u6709\u5b78\u6b77\u8981\u6c42; 2\u5e74\u7d93\u9a57; \u826f\u597d\u7cb5\u8a9e; \u61c2\u8b80\u5beb\u4e2d\u6587; \u6301\u6709\u639b\u63a5\u8eca\u8f1b\u99d5\u99db\u57f7\u7167; \u719f\u6089\u9999\u6e2f\u3001\u4e5d\u9f8d\u53ca\u65b0\u754c\u4e4b\u9053\u8def\n\n\u5f85\u9047 :\u6bcf\u6708$8,775, \u6709\u96d9\u7ce7, \u5e74\u504712\u5929, \u6bcf\u6708\u624b\u63d0\u96fb\u8a71\u6d25\u8cbc$300 \u53ca\u6bcf\u7a0b\u904b\u8cbb\u6d25\u8cbc$240, \u661f\u671f\u4e00\u81f3\u516d: \u4e0a\u53488\u6642\u81f3\u4e0b\u53486\u6642, \u6bcf\u9031\u5de5\u4f5c6\u5929, \u6bcf\u5929\u5de5\u4f5c 9 \u5c0f\u6642\n\n\u7533\u8acb\u9808\u77e5 :\u6c42\u8077\u8005\u53ef\u81f4\u96fb29434412\u8207\u4e09\u904b(\u9999\u6e2f)\u6709\u9650\u516c\u53f8\u6b50\u967d\u5c0f\u59d0\u806f\u7d61\u3002\n", "employment_types": ["Full Time"], "selling_points": ["\u4e00\u822c\u5009\u52d9\u54e1/\u7406\u8ca8\u54e1\u5de5\u4f5c", "\u8ca0\u8cac\u57f7\u8ca8, \u6536\u8ca8, \u642c\u8ca8, \u7528\u5527\u8eca", "\u61c2\u4f7f\u7528\u624b\u6a5f\u901a\u8a0a\u7a0b\u5f0f"], "locations": ["Not Specified"], "categories": ["Transportation & Logistics", "Others", "Inventory / Warehousing"], "post_time": "2022-01-18T03:00:14Z", "salary": {"currency": null, "max": null, "min": null, "period": "monthly", "term": null}, "salary_visible": false, "title_keywords": ["\u7406\u8ca8\u54e1", "\u5009\u52d9\u54e1"], "responsibilities": [], "requirements": {"degrees": [], "majors": [], "languages": [], "language_level": [], "hard_skills": [], "soft_skills": [], "languages_combined": []}, "experience_required": {"duration": [], "field": []}}, {"job_id": "100003009054012", "location_code": "hk", "company": "Mitex International (Hong Kong) Ltd", "job_title": "\u672c\u5730\u62d6\u904b\u53f8\u6a5f  (\u65bc\u8475\u82b3\u53d6\u8eca)", "description": "Job Requirements:\n\nMust be familiar with banking documents shipments such as D/P, D/A, L/C etc.\nDocumentation formalities pertaining to shipments\nArranging shipment and follow up with factories\nCo-coordinating all shipping activities for numerous clients\nEXCELLENT COMMAND IN WRITTEN & SPOKEN ENGLISH, CANTONESE & MANDARIN SKILLS\nGood knowledge of all documentation formalities pertaining to shipments\nMinimum\u00a03 year experience in a manufacturer, trading company, or multinational export company\u2019s shipping department\nExperience in making all relevant shipping documents\nExcellent communication and interpersonal skills\nA team leader who exhibits leadership qualities and is able to work under pressure and within time constraints\nWilling to travel to China and other destinations\nFamiliarity with basic computer programs such as Microsoft Office (Microsoft Word, Excel, Outlook (email) etc)\nA team leader who exhibits leadership qualities and is able to work under pressure and within time constraints.\nPermanent Hong Kong ID card Holder.\nFlexible working times and willing to work after hours if needed.\n\n\nKey requirements:\n\nDegree/Diploma holder, with at least 3 year of relevant experience\nGood understanding on global Markets\nExcellent command in Cantonese, English and Mandarin\nGood communication and interpersonal skills to work with counterparts\nAble to work independently and meet tight deadlines\nProficient in computer skills and MS Office Applications\n\n\nInterested applicants please send your English application along with cover letter and detailed resume with current and expected salary clearly stated to \u201cApply Now\u201d.\n\nAll Personal data collected will be used for recruitment purpose only.", "employment_types": ["Full Time"], "selling_points": ["\u6c92\u6709\u5b78\u6b77\u8981\u6c42", "2\u5e74\u7d93\u9a57", "\u826f\u597d\u7cb5\u8a9e"], "locations": ["Kwai Fong"], "categories": ["Transportation & Logistics", "Others", "Private Transportation", "Public Transportation"], "post_time": "2022-01-17T08:03:03Z", "salary": {"currency": null, "max": null, "min": null, "period": "monthly", "term": null}, "salary_visible": false, "title_keywords": [], "responsibilities": ["shipping documents", "shipping", "communication", "recruitment", "banking", "documentation", "personal data", "work under pressure"], "requirements": {"degrees": ["diploma holder", "degree"], "majors": [], "languages": ["cantonese", "english", "mandarin"], "language_level": ["excellent"], "hard_skills": ["excel", "microsoft word", "basic", "microsoft office", "id", "c", "outlook", "computer skills", "documentation", "ms office"], "soft_skills": ["flexible", "work independently", "meet tight deadlines", "detailed", "communication and interpersonal skills", "leadership", "work under pressure"], "languages_combined": [{"language": "cantonese", "language_level": ["excellent", "excellent"]}, {"language": "english", "language_level": ["excellent", "excellent"]}, {"language": "mandarin", "language_level": ["excellent", "excellent"]}]}, "experience_required": {"duration": ["minimum 3 year", "at least 3 year"], "field": ["trading", "relevant experience"]}}, {"job_id": "100003009029744", "location_code": "hk", "company": "Creative China Creations Limited", "job_title": "Senior Shipping Coordinator (Consumer Products & Sundries)", "description": "\u8077\u8cac :\u8ca0\u8cac\u78bc\u982d\u65e5\u5e38\u5de5\u4f5c\u53ca\u99d5\u99db\u7a7f\u68ad\u5df4\u58eb\u63a5\u8f09\u4e58\u5ba2, \u5354\u52a9\u642c\u904b\u7269\u8cc7, \u65bc\u897f\u8ca2\u6ed8\u897f\u6d32\u53d6/\u4ea4\u8eca, \u4e00\u5e74\u5408\u7d04\n\u8cc7\u6b77 :\u4e2d\u4e09\u7a0b\u5ea6; 1\u5e74\u7d93\u9a57; \u826f\u597d\u7cb5\u8a9e; \u4e00\u822c\u82f1\u8a9e; \u61c2\u8b80\u5beb\u4e2d\u6587; \u7565\u61c2\u8b80\u5beb\u82f1\u6587; \u6301\u6709\u8f15\u578b\u8ca8\u8eca\u99d5\u99db\u57f7\u7167; \u6301\u6709\u79c1\u5bb6\u8eca\u99d5\u99db\u57f7\u7167; \u6301\u79c1\u5bb6\u5df4\u58eb(9\u865f\u724c)\u53ca\u516c\u5171\u5df4\u58eb(10\u865f\u724c)\u99d5\u99db\u57f7\u7167\u512a\u5148\n\u5f85\u9047 :\u6bcf\u6708$15,000 - $18,000(\u8996\u4e4e\u6301\u6709\u4e4b\u99d5\u99db\u57f7\u7167\u7a2e\u985e\u800c\u5b9a), \u6709\u96d9\u7ce7,\u5e74\u504712\u5929,\u7d04\u6eff\u916c\u91d1,\u5728\u8077\u57f9\u8a13,\u91ab\u7642\u4fdd\u96aa,\u4f9b\u81b3\u98df\u53ca\u6649\u5347\u6a5f\u6703, \u4e0a\u53486\u6642\u81f3\u4e0b\u534810\u6642, \u6bcf\u9031\u5de5\u4f5c6\u5929,\u8f2a\u73ed,\u8f2a\u4f11, \u6bcf\u5929\u5de5\u4f5c 8 \u5c0f\u6642\n\u7533\u8acb\u9808\u77e5 :\u6c42\u8077\u8005\u53ef\u81f4\u96fb27913373\u8207THE JOCKEY CLUB KAU SAI CHAU PUBLIC GOLF COURSE LTD\u5f35\u5148\u751f\u806f\u7d61\u3002", "employment_types": ["Full Time", "Permanent"], "selling_points": ["Good understanding on global Markets", "Able to work independently & meet tight deadlines", "With at least 3 year of relevant experience"], "locations": ["Ngau Tau Kok"], "categories": ["Transportation & Logistics", "Others", "Shipping", "Merchandising & Purchasing", "Procurement / Purchasing / Sourcing"], "post_time": "2022-01-17T16:20:53Z", "salary": {"currency": null, "max": null, "min": null, "period": "monthly", "term": null}, "salary_visible": false, "title_keywords": ["shipping coordinator"], "responsibilities": [], "requirements": {"degrees": [], "majors": [], "languages": [], "language_level": [], "hard_skills": [], "soft_skills": [], "languages_combined": []}, "experience_required": {"duration": [], "field": []}}, {"job_id": "100003009056104", "location_code": "hk", "company": "The Jockey Club Kau Sai Chau Public Golf Course Ltd", "job_title": "\u904b\u8f38\u670d\u52d9\u54e1/\u53f8\u6a5f", "description": "Position Summary:\u00a0 Performs duties relating to the loading/unloading of aircraft, flight following, customs and cargo handling to ensure that company meets all company and governmental policies and regulations that customers receive quality service.\n\nMajor Job Accountabilities:\n\nTrack flight with first hand information on Estimated Time of Arrival/ Estimated Time of Delivery (ETA/ETD) and analyze necessary information to determine load plans and handle flight plan request\nCalculate weight and balance and monitor cargo build up/break down in warehouse\nInspect aircraft cargo and identify unsafe and insecure cargo to address any problems and ensure adherence to aircraft, vehicle and employee safety rules and regulations\nLead and coordinate with vendor or handlers of and provide directions on handling required, including supervision of loading and offloading, monitor ramp operations when aircraft on ground, etc.\nEnsure accuracy and completeness of aircraft cargo documentation, HAZMAT loading paperwork, notify crew of location and, if necessary, obtain appropriate approvals prior to take-off\nFinalize meal order and cater for logistics arrangements for crew\nPerform other duties as assigned\n\nQualifications:\u00a0\n\nDiploma or above in any disciplines\nKnowledge in air freight, terminal operations, flight terminology and processes would be preferable\nPrevious airline experience, with good understanding of aircraft positions and heights, aircraft weight limitations, aircraft overhangs, SITA, Unit Load Device (ULD) and flight systems, screens and software is an asset\nAbility to track and coordinate multiple issues simultaneously\nGood computer literacy and logical mindset\nPassion in aviation industry\nProficiency in written and spoken English and Chinese\nAble to attend night shift\n\nPolar Air\u00a0offers attractive remuneration and fringe benefits. Please apply with full resume, current and expected salary.\n\n(The personal data provided with will be treated confidentially and used for recruitment purposes only)", "employment_types": ["Full Time", "Contract"], "selling_points": [], "locations": ["Sai Kung"], "categories": ["Transportation & Logistics", "Others", "Public Transportation"], "post_time": "2022-01-18T03:19:04Z", "salary": {"currency": null, "max": null, "min": null, "period": "monthly", "term": null}, "salary_visible": false, "title_keywords": [], "responsibilities": ["regulations", "perform other duties", "software", "air freight", "policies", "ensure adherence", "operations", "quality", "monitor", "coordinate with", "logistics arrangements", "systems", "coordinate", "plan", "documentation", "plans"], "requirements": {"degrees": ["diploma or above"], "majors": ["any disciplines"], "languages": ["english", "chinese"], "language_level": ["proficiency"], "hard_skills": ["documentation", "vendor", "aircraft", "airline"], "soft_skills": ["computer literacy", "passion in", "logical mindset"], "languages_combined": [{"language": "english", "language_level": ["proficiency"]}, {"language": "chinese", "language_level": ["proficiency"]}]}, "experience_required": {"duration": [], "field": []}}, {"job_id": "100003009053369", "location_code": "hk", "company": "Wealthy Crown Asia Limited", "job_title": "\u517c\u8077\u5e97\u52d9\u52a9\u7406 / \u7406\u8ca8\u54e1", "description": "Working Location:\u00a0Chek Lap Kok\nReporting to the NCG Supervisor, Operations Support, you will liaise and work closely with the operations team in order to provide clerical and documentation support of shipments entering and exiting the Central Asia Hub\nExecute flight movement alerts, transmit shipment information and prepare flight documentations\nRectify and follow up on network on non-conforming shipments.\nConduct and coordinate warehouse searches generated by network trace requests\nPrint shipment manifest for shipment lodgement\nPrepare and handle the documentation for Dangerous Goods and Lithium battery\nRegister, maintain and follow the trace in DHL application to resolve the Lost and Found shipment\nRequirements:\nSecondary education with at least 2 years clerical or operations support experience\nPrevious work experience related to warehousing, distribution center, logistics, freight forwarding and airport operations is an advantage\nFair command of spoken English and Cantonese\nHands-on PC skills\nHardworking, attentive to details, patient with customer service sense\nWilling to work on 24-hour shift duties\nPersonal Information Collection Statement pertaining to Recruitment\nDHL Express (Hong Kong) Limited / DHL Aviation (Hong Kong) Limited (\u201cDHL\u201d) is committed to protecting and respecting your privacy in accordance with the Personal Data (Privacy) Ordinance of Hong Kong (the \u201cOrdinance\u201d) and DHL\u2019s Personal Data Protection Policy (the \u201cPolicy\u201d) at\u00a0https://www.dhl.com/hk-en/home/footer/local-privacy-notice.html\nBy proceeding to respond to this recruitment advertisement, you consent that we may use, retain, process, transfer or otherwise handle the personal data that we collect from you for recruitment,\u00a0 application processing, assessment and communication purposes (including any other purposes directly related thereto) in accordance with the Policy.\nAll personal data of unsuccessful applicants will be retained for future recruitment purposes for a period of not more than two (2) years after which such data will be destroyed.\nYou have the right at any time to make a data access or correction request concerning your personal data held by us. In addition, you may request us to delete your personal data that is no longer required for the relevant purposes which you have given consent. Should you wish to exercise such rights or have any question in relation to your personal data or the Policy, please contact our Human Resources Division in writing.", "employment_types": ["Part Time"], "selling_points": [], "locations": ["Wan Chai"], "categories": ["Transportation & Logistics", "Others", "Inventory / Warehousing", "Supply Chain"], "post_time": "2022-01-17T06:52:41Z", "salary": {"currency": null, "max": null, "min": null, "period": "hourly", "term": null}, "salary_visible": false, "title_keywords": ["\u7406\u8ca8\u54e1"], "responsibilities": ["liaise", "reporting", "warehousing", "data", "operations", "coordinate", "communication", "maintain", "logistics", "customer service", "recruitment", "contact", "documentation", "personal data"], "requirements": {"degrees": ["secondary education"], "majors": [], "languages": ["cantonese", "english"], "language_level": [], "hard_skills": ["no", "processing", "html", "make", "documentation", "pc skills", "documentations"], "soft_skills": ["attentive to details", "communication", "committed", "hands-on", "customer service", "patient", "hardworking"], "languages_combined": [{"language": "cantonese", "language_level": []}, {"language": "english", "language_level": []}]}, "experience_required": {"duration": ["at least 2 years"], "field": ["related", "logistics", "clerical", "education"]}}, {"job_id": "100003009053727", "location_code": "hk", "company": "Polar Air Cargo Worldwide, Inc", "job_title": "Ground Operations Agent", "description": "\n\u8077\u8cac :\u4e00\u822c\u5009\u52d9\u6587\u54e1\u5de5\u4f5c, \u8ca8\u5009\u65e5\u5e38\u904b\u4f5c, \u8ddf\u9032\u6536\u767c\u51fa\u8ca8, \u76e4\u9ede, \u66f4\u65b0\u5009\u5b58\u8a18\u9304, \u8ddf\u9032\u53ca\u8655\u7406\u4e3b\u7ba1\u5206\u914d\u7684\u5176\u4ed6\u5de5\u4f5c\u7b49, \u9700\u5916\u52e4\u53ca\u9ad4\u529b\u52de\u52d5\n\n\u8cc7\u6b77 :\u4e2d\u4e94\u7a0b\u5ea6; 1\u5e74\u7d93\u9a57; \u826f\u597d\u7cb5\u8a9e\u512a\u5148; \u4e00\u822c\u666e\u901a\u8a71; \u4e00\u822c\u82f1\u8a9e; \u61c2\u8b80\u5beb\u4e2d\u6587; \u7565\u61c2\u8b80\u5beb\u82f1\u6587\n\n\u5f85\u9047 :\u6bcf\u6708$12,000 - $14,000, \u6709\u52e4\u5de5\u734e\u91d1, \u91ab\u7642\u798f\u5229 \u53ca\u9280\u884c\u5047\u671f, \u4e0a\u534810\u6642\u534a\u81f3\u4e0b\u53487\u6642\u534a, \u6bcf\u9031\u5de5\u4f5c5\u5929\u81f36\u5929,\u8f2a\u4f11, \u6bcf\u5929\u5de5\u4f5c 9 \u5c0f\u6642, \u6bcf\u67086\u5929\u4f11\u606f\u65e5, \u4f11\u606f\u65e5\u5b9a\u65bc\u975e\u516c\u773e\u5047\u671f\n\n\u7533\u8acb\u9808\u77e5 :\u6c42\u8077\u8005\u53ef\u96fb\u90f5(Apply Now)\u5c65\u6b77\u8868\u7d66\u8fc5\u9054\u96fb\u8a0a\u5de5\u7a0b\u6709\u9650\u516c\u53f8\u3002\u5982\u8981\u7d22\u53d6\u6536\u96c6\u500b\u4eba\u8cc7\u6599\u8072\u660e, \u8acb\u8207\u95dc\u5c0f\u59d0(Fax:24997885)\u806f\u7d61\u3002\n\n", "employment_types": ["Full Time", "Permanent"], "selling_points": ["Loading/unloading of aircraft", "Previous airline experience is a plus", "Attractive remuneration and fringe benefits"], "locations": ["Airport Area"], "categories": ["Transportation & Logistics", "Aviation Services", "Others"], "post_time": "2022-01-17T07:27:31Z", "salary": {"currency": null, "max": null, "min": null, "period": "monthly", "term": null}, "salary_visible": false, "title_keywords": ["operations"], "responsibilities": [], "requirements": {"degrees": [], "majors": [], "languages": [], "language_level": [], "hard_skills": [], "soft_skills": [], "languages_combined": []}, "experience_required": {"duration": [], "field": []}}, {"job_id": "100003009056125", "location_code": "hk", "company": "DHL Aviation (Hong Kong) Limited", "job_title": "Operations Support Agent", "description": "Responsibilities:\n\nResponsible for system administration of AD, VMware, Veeam Backup, monitoring of firewalls, switches, VPN, Internet connectivity, and 2nd level desktop support;\nImplementing system configurations with monitoring, DR, and backup solutions with IT policies with aspects of IT infrastructure;\nPerform routine database administration and maintenance tasks for Application systems;\nProvide technical advice as required for procurement or other projects;\nSupervise vendors to perform infra upgrade;\nContinuously improve effectiveness of security risk control and review IT security risks; and\nPrepare and maintain system management and computer operation documentations\n\nRequirements:\n\nHigher Diploma or above in Computer Engineering / Information Technology or related discipline;\nAt least 5 years\u2019 solid experience in server administration and networking;\nSolid experience of Windows Server platform, Active Directory, Group Policy, VMware, Networking, Firewall;\nHolder of certificate of CCNA or MCSE would be an advantage;\nKnowledge on cloud infrastructure;\nAble to work independently and under pressure; and\nProficient in spoken and written English and Chinese\n\nWorking hours: 5-day work (must include Saturday)\n\nBenefits: End of Year Payment, Annual Leave, Birthday Leave, Bank Holidays, Education Allowance, Medical & Dental Insurance, Free Shuttle Bus (Kowloon / Tuen Mun / Tin Shui Wai)\n\n\n\nWe offer competitive remuneration package for suitable candidates. For interested parties, please send your resume with professional qualifications and expected salary to Human Resources Department by clicking \u201cApply Now\u201d.\u00a0\n\nApplicants not invited for interview within 6 weeks may consider their application unsuccessful. Unsuccessful applications will be kept for 12 months and then destroyed. Personal data collected will be used for recruitment purposes only.", "employment_types": ["Full Time"], "selling_points": ["Print shipment manifest for shipment lodgement", "Secondary education", "2 years clerical or operations support experience"], "locations": ["Not Specified"], "categories": ["Admin & HR", "Clerical / Admin Staff", "Transportation & Logistics", "Others", "Shipping"], "post_time": "2022-01-18T03:21:47Z", "salary": {"currency": null, "max": null, "min": null, "period": null, "term": null}, "salary_visible": false, "title_keywords": ["operations"], "responsibilities": ["control", "management", "it infrastructure", "technical advice", "monitoring", "review", "it policies", "maintenance tasks", "improve effectiveness", "maintain", "database", "application systems", "administration"], "requirements": {"degrees": ["certificate", "higher diploma or above"], "majors": ["computer engineering", "information technology"], "languages": ["english", "chinese"], "language_level": ["proficient"], "hard_skills": ["mcse", "vmware", "active directory", "server administration", "ccna", "firewall", "windows server"], "soft_skills": ["work independently", "active", "under pressure"], "languages_combined": [{"language": "english", "language_level": ["proficient"]}, {"language": "chinese", "language_level": ["proficient"]}]}, "experience_required": {"duration": ["at least 5 years"], "field": ["server administration"]}}, {"job_id": "100003009053699", "location_code": "hk", "company": "Convey Telecom Engineering Limited", "job_title": "\u904b\u4f5c\u52a9\u7406 (\u5009\u52d9)", "description": "\n\u8077\u8cac :\u4e00\u822c\u5009\u52d9\u54e1/\u7406\u8ca8\u54e1\u5de5\u4f5c, \u4e00\u822c\u5009\u52d9\u5de5\u4f5c,\u5982\u6536\u8ca8,\u9ede\u8ca8,\u57f7\u8ca8,\u4e0a\u67b6,\u767c\u8ca8\u7b49\n\n\u8cc7\u6b77 :\u4e2d\u4e09\u7a0b\u5ea6; \u826f\u597d\u7cb5\u8a9e\n\n\u5f85\u9047 :\u6bcf\u6708$13,000 - $15,000, \u6709\u54e1\u5de5\u8cfc\u7269\u512a\u60e0 \u53ca\u4f9b\u81b3\u98df, \u661f\u671f\u4e00\u81f3\u4e94: \u4e0a\u53489\u6642\u81f3\u4e0b\u53486\u6642\u53ca\u661f\u671f\u516d: \u4e0a\u53489\u6642\u81f3\u4e0b\u53483\u6642, \u6bcf\u9031\u5de5\u4f5c5\u5929\u81f36\u5929\n\n\u7533\u8acb\u9808\u77e5 :\u6c42\u8077\u8005\u53ef\u96fb\u90f5(Apply Now)\u5c65\u6b77\u8868\u7d66\u842c\u9806\u660c\u4f01\u696d\u6709\u9650\u516c\u53f8\u3002\u5982\u8981\u7d22\u53d6\u6536\u96c6\u500b\u4eba\u8cc7\u6599\u8072\u660e, \u8acb\u8207\u5468\u5c0f\u59d0(25451190)\u806f\u7d61\u3002\n\n", "employment_types": ["Full Time"], "selling_points": [], "locations": ["Wong Tai Sin Area"], "categories": ["Transportation & Logistics", "Others", "Inventory / Warehousing", "Supply Chain"], "post_time": "2022-01-17T07:22:23Z", "salary": {"currency": null, "max": null, "min": null, "period": "monthly", "term": null}, "salary_visible": false, "title_keywords": ["\u5009\u52d9"], "responsibilities": [], "requirements": {"degrees": [], "majors": [], "languages": [], "language_level": [], "hard_skills": [], "soft_skills": [], "languages_combined": []}, "experience_required": {"duration": [], "field": []}}, {"job_id": "100003009053461", "location_code": "hk", "company": "Feeding Hong Kong Limited", "job_title": "\u5009\u52d9\u517c\u53f8\u6a5f", "description": "Responsibilities:\n\nInput data into Database\nUpdate data file with in Excel\u00a0\nPrepare & co-ordinate with clients for delivery arrangement & documents\nFollow up with clients instruction & provide stock availability & shipping information to stores/warehouse\n\nRequirements:\n\nExcellent in Excel Skills\u00a0\u00a0IS A MUST!\u00a0\nFamiliar with (Pivot Table and V Lookup) IS A MUST!\u00a0\n\nCould read simplified Chinese \u80fd\u95b1\u8b80\u7c21\u9ad4\u5b57\nProficiency in PC operations including Word, Excel, fast accurate input Chinese.\nAble to read English and reply email.\nPassed in Eng. Subject DSE/HKCEE\u00a0\nWith at least 2 years relevant warehouse and logistics clerical experience\nWell-organised and attentive to details; Stable working history\nImmediately available /short notice is preferred.\n\nWORKING LOCATION: TUEN MUN\n5 days work\n12 days AL\n\n\u00a0\u00a0\nSalary \u00a0\u00a0\u00a0\u00a0: \u00a0Negotiable\n\nInterested parties please send your full resume with job description and expected salary to us.", "employment_types": ["Full Time"], "selling_points": ["5\u5929\u5de5\u4f5c, \u661f\u671f\u516d\u65e5\u4f11\u5047", "\u9280\u884c\u5047\u671f, \u91ab\u7642\u4fdd\u96aa", "\u6301\u6709\u6709\u6548\u7684\u4e2d\u578b\u8ca8\u8eca\uff08\u8eca\u8f1b\u985e\u522518\uff09\u99d5\u99db\u57f7\u7167\u6708\u85aa\u9054$17,000"], "locations": ["Kwun Tong Area"], "categories": ["Transportation & Logistics", "Others", "Private Transportation", "Public Transportation"], "post_time": "2022-01-17T07:00:43Z", "salary": {"currency": null, "max": null, "min": null, "period": "monthly", "term": null}, "salary_visible": false, "title_keywords": [], "responsibilities": ["shipping", "co-ordinate with clients", "database", "data"], "requirements": {"degrees": ["dse"], "majors": [], "languages": ["english", "chinese"], "language_level": ["proficiency"], "hard_skills": ["excel", "pivot table", "pc operations", "word"], "soft_skills": ["well-organised", "stable", "accurate", "attentive to details"], "languages_combined": [{"language": "english", "language_level": []}, {"language": "chinese", "language_level": ["proficiency"]}]}, "experience_required": {"duration": ["at least 2 years"], "field": ["logistics", "clerical"]}}, {"job_id": "100003009053924", "location_code": "hk", "company": "Man Shun Cheong Enterprise Limited", "job_title": "\u5009\u52d9\u54e1/\u7406\u8ca8\u54e1", "description": "\u5009\u5eab\u7ba1\u7406\u54e1\n\u516c\u53f8/\u50f1\u4e3b\u540d\u7a31 :\u7063\u85cd(\u9999\u6e2f)\u8cbf\u6613\u6709\u9650\u516c\u53f8\n\u5730\u5340 :\u6c99\u7530\n\u884c\u696d :\u9032\u51fa\u53e3\u8cbf\u6613\n\u8077\u8cac :\u5009\u52d9\u7ba1\u7406, \u5eab\u5b58\u6838\u5c0d, \u51fa\u5165\u5eab\u6838\u5c0d\u7b49\n\u8cc7\u6b77 :\u4e2d\u4e09\u7a0b\u5ea6; 1\u5e74\u7d93\u9a57; \u826f\u597d\u7cb5\u8a9e; \u826f\u597d\u666e\u901a\u8a71; \u4e00\u822c\u82f1\u8a9e; \u61c2\u8b80\u5beb\u4e2d\u6587; \u61c2\u8b80\u5beb\u82f1\u6587\n\u5f85\u9047 :\u6bcf\u6708$12,000 - $14,000, \u6709\u9280\u884c\u5047\u671f, \u54e1\u5de5\u8cfc\u7269\u512a\u60e0\u53ca\u8d85\u6642\u5de5\u4f5c\u6d25\u8cbc, \u4e0a\u53489\u6642\u81f3\u4e0b\u53486\u6642, \u6bcf\u9031\u5de5\u4f5c5\u5929\u81f36\u5929, \u6bcf\u5929\u5de5\u4f5c 8 \u5c0f\u6642, \u661f\u671f\u516d\u9577\u77ed\u9031\n\u7533\u8acb\u9808\u77e5 :\u6c42\u8077\u8005\u53ef\u96fb\u90f5\u5c65\u6b77\u8868\u7d66\u7063\u85cd(\u9999\u6e2f)\u8cbf\u6613\u6709\u9650\u516c\u53f8\u3002\u5982\u8981\u7d22\u53d6\u6536\u96c6\u500b\u4eba\u8cc7\u6599\u8072\u660e, \u8acb\u8207\u6b50\u5c0f\u59d0(Tel:59393656)\u806f\u7d61\u3002", "employment_types": ["Full Time"], "selling_points": [], "locations": ["Sheung Wan"], "categories": ["Transportation & Logistics", "Others", "Inventory / Warehousing", "Supply Chain"], "post_time": "2022-01-17T07:47:15Z", "salary": {"currency": null, "max": null, "min": null, "period": "monthly", "term": null}, "salary_visible": false, "title_keywords": ["\u7406\u8ca8\u54e1", "\u5009\u52d9\u54e1"], "responsibilities": [], "requirements": {"degrees": [], "majors": [], "languages": [], "language_level": [], "hard_skills": [], "soft_skills": [], "languages_combined": []}, "experience_required": {"duration": [], "field": []}}, {"job_id": "100003009053613", "location_code": "hk", "company": "DCH Logistics Co Ltd", "job_title": "Assistant Supervisor (Ref: LOG-AS-RPC)", "description": "Responsibilities:\u00a0\n\nWork closely with other departments to follow up repacking processes;\nLiaise with customers and service providers to ensure smooth operation;\nFollow up invoice billing, chasing outstanding payment;\nPrepare regular inventory reports and analysis;\nResponsible for salary and overtime payment calculation;\nAd-hoc tasks or projects as assigned.\n\n\u00a0Requirements:\u00a0\n\nDiploma holder in Business Administration, Logistics or related discipline;\nAt least 5 years\u2019 relevant experience, preferred in logistics industry;\nStrong communication skills with good command of both spoken and written English, Cantonese and Putonghua;\nMature, initiative, willing to learn & able to work independently;\nProficiency in MS Office application, including Chinese word processing;\nWorking location will be Lau Fau Shan;\nImmediately available is highly preferred.\n\n\u00a0We offer competitive salary to the successful candidate. Interested candidates please send by mail or email your resume together with salary expectation to click \"Apply Now\".\n\nHuman Resources Department, DCH Logistics Company Limited\n67-73 Fuk Hi Street, Yuen Long Industrial Estate, Yuen Long, New Territories.\n\n\nWe are equal opportunities employer. Applicants who are not invited within 2 months may consider their application unsuccessful. All applicants may be considered for other suitable positions with DCH Group / CITIC Pacific Group and will be deleted from our files after 6 months from the date of application.", "employment_types": ["Full Time", "Permanent"], "selling_points": [], "locations": ["Yuen Long"], "categories": ["Transportation & Logistics", "Others", "Inventory / Warehousing"], "post_time": "2022-01-17T07:14:27Z", "salary": {"currency": null, "max": null, "min": null, "period": "monthly", "term": null}, "salary_visible": false, "title_keywords": ["assistant supervisor"], "responsibilities": ["invoice", "inventory", "analysis", "ad-hoc tasks", "work closely with other departments", "payment", "reports", "liaise with"], "requirements": {"degrees": ["diploma holder"], "majors": ["business administration"], "languages": ["cantonese", "putonghua", "english", "chinese"], "language_level": ["proficiency", "good command"], "hard_skills": ["chinese word processing", "ms office"], "soft_skills": ["communication skills", "work independently", "willing to learn", "mature", "initiative"], "languages_combined": [{"language": "cantonese", "language_level": ["good command"]}, {"language": "putonghua", "language_level": ["good command"]}, {"language": "english", "language_level": ["good command"]}, {"language": "chinese", "language_level": ["proficiency"]}]}, "experience_required": {"duration": ["at least 5 years"], "field": ["logistics industry", "relevant experience"]}}, {"job_id": "100003009053543", "location_code": "hk", "company": "Boss Industries Limited", "job_title": "\u5009\u52d9\u54e1/\u7269\u6d41\u54e1", "description": "\u884c\u696d :\u9152\u5e97\u696d\n\u8077\u8cac :\u8ca0\u8cac\u8655\u7406\u9910\u98f2\u98df\u54c1\u5ee2\u7269\u53ca\u6e05\u6f54\u5de5\u4f5c\n\u8cc7\u6b77 :\u6c92\u6709\u5b78\u6b77\u8981\u6c42; \u826f\u597d\u7cb5\u8a9e; \u7565\u61c2\u8b80\u5beb\u4e2d\u6587; \u6709\u79ae\uff0c\u5de5\u4f5c\u6709\u6548\u7387\u53ca\u6709\u8cac\u4efb\u611f\n\u5f85\u9047 :\u6bcf\u6708$14,400 - $14,800, \u6709\u5e74\u504712\u5929, \u914c\u60c5\u6027\u82b1\u7d05, \u7259\u79d1\u798f\u5229, \u91ab\u7642\u798f\u5229, \u4f9b\u81b3\u98df \u53ca\u6649\u5347\u6a5f\u6703, \u4e0a\u53487\u6642\u81f3\u4e0b\u53484\u6642\u6216\u4e0b\u53482\u6642\u534a\u81f3\u4e0b\u534811\u6642\u534a, \u6bcf\u9031\u5de5\u4f5c5\u5929\u81f36\u5929,\u8f2a\u4f11, \u6bcf\u5929\u5de5\u4f5c 9 \u5c0f\u6642\n\u7533\u8acb\u9808\u77e5 :\u6c42\u8077\u8005\u53ef\u81f4\u96fb28662166(Ext.3132)\u8207\u516d\u570b\u9152\u5e97\u6d2a\u5c0f\u59d0\u806f\u7d61\u3002", "employment_types": ["Full Time"], "selling_points": [], "locations": ["Kwun Tong"], "categories": ["Transportation & Logistics", "Others", "Inventory / Warehousing", "Supply Chain"], "post_time": "2022-01-17T07:08:10Z", "salary": {"currency": null, "max": null, "min": null, "period": "monthly", "term": null}, "salary_visible": false, "title_keywords": ["\u5009\u52d9\u54e1"], "responsibilities": [], "requirements": {"degrees": [], "majors": [], "languages": [], "language_level": [], "hard_skills": [], "soft_skills": [], "languages_combined": []}, "experience_required": {"duration": [], "field": []}}, {"job_id": "100003009052734", "location_code": "hk", "company": "China Duty Free International Limited", "job_title": "\u5009\u52d9\u54e1", "description": "\u8077\u8cac :\u4e00\u822c\u5009\u52d9\u5de5\u4f5c, \u5982\u6536\u8ca8, \u9ede\u8ca8, \u57f7\u8ca8, \u4e0a\u67b6, \u767c\u8ca8\u7b49, \u642c\u904b\u8ca8\u7269, \u76e4\u9ede\u5b58\u8ca8, \u66f4\u65b0\u5b58\u8ca8\u8a18\u9304, \u6574\u7406\u8ca8\u5009, \u5b89\u6392\u7269\u6d41\u670d\u52d9, \u5009\u5eab\u7ba1\u7406\n\u8cc7\u6b77 :\u4e2d\u4e94\u7a0b\u5ea6; 3\u5e74\u7d93\u9a57; \u826f\u597d\u7cb5\u8a9e; \u4e00\u822c\u666e\u901a\u8a71\u512a\u5148; \u4e00\u822c\u82f1\u8a9e\u512a\u5148; \u61c2\u8b80\u5beb\u4e2d\u6587; \u7565\u61c2\u8b80\u5beb\u82f1\u6587; \u5177\u6709\u57fa\u672c\u96fb\u8166\u64cd\u4f5c\u77e5\u8b58\n\u5f85\u9047 :\u6bcf\u6708$12,000 - $15,000, \u6709\u96d9\u7ce7, \u9280\u884c\u5047\u671f, \u91ab\u7642\u798f\u5229, \u81b3\u98df\u6d25\u8cbc \u53ca\u914c\u60c5\u6027\u82b1\u7d05, \u661f\u671f\u4e00\u81f3\u516d: \u4e0a\u53489\u6642\u81f3\u4e0b\u53486\u6642, \u6bcf\u9031\u5de5\u4f5c6\u5929, \u6bcf\u5929\u5de5\u4f5c 9 \u5c0f\u6642\n\u7533\u8acb\u9808\u77e5 :\u6c42\u8077\u8005\u53ef\u96fb\u90f5(APPLY NOW)\u5c65\u6b77\u8868\u7d66\u4e2d\u514d\u570b\u969b\u6709\u9650\u516c\u53f8\u3002\u5982\u8981\u7d22\u53d6\u6536\u96c6\u500b\u4eba\u8cc7\u6599\u8072\u660e, \u8acb\u8207\u5442\u5c0f\u59d0(Email)\u806f\u7d61\u3002", "employment_types": ["Full Time"], "selling_points": [], "locations": ["Tuen Mun Area"], "categories": ["Transportation & Logistics", "Others", "Inventory / Warehousing"], "post_time": "2022-01-17T03:52:07Z", "salary": {"currency": null, "max": null, "min": null, "period": "monthly", "term": null}, "salary_visible": false, "title_keywords": ["\u5009\u52d9\u54e1"], "responsibilities": [], "requirements": {"degrees": [], "majors": [], "languages": [], "language_level": [], "hard_skills": [], "soft_skills": [], "languages_combined": []}, "experience_required": {"duration": [], "field": []}}, {"job_id": "100003009056127", "location_code": "hk", "company": "DHL EXPRESS (HONG KONG) LIMITED", "job_title": "Manager, Program Delivery", "description": "Responsibilities:\n\n\nEnsure continuity of IT operations service quality & continuity to IT operations SLAs, ensuring Availability, Capacity, Continuity and Incident\nProject management, audit and disaster recovery activities across the service team, and provide technical advice if required\nManage the development and implementation of the Group IT Application Development\nCollect business initiatives, business cases and requirements from user departments and external users, to deliver digitalize and innovative solutions\nCollaborate with different stakeholders and team members to achieve project objectives in an effective and efficient manner\nEstablish strategies for risk mitigation and contingency planning and resiliency of systems\nDesign, Develop, Implement and coordinate releases, policies and procedures\nProcess review to refresh the workflow regularly\n\nRequirements:\n\n\nExcellent skills in business requirements analysis and business documentation writing\nBachelor Degree or above education, preferably in Computer Science or related disciplines\n8 years IS and business experience, preferably in logistics industry, with 5 years IS management experience\nAnalytical with sound communication skills, able to work effectively with business users and technical staff\nStrong negotiation and organizational skills with possession of the good problem-solving ability\nDemonstrated high proficiency in leading & managing complex IT projects\n\nPersonal Information Collection Statement pertaining to Recruitment\n\nDHL Express (Hong Kong) Limited / DHL Aviation (Hong Kong) Limited (\u201cDHL\u201d) is committed to protecting and respecting your privacy in accordance with the Personal Data (Privacy) Ordinance of Hong Kong (the \u201cOrdinance\u201d) and DHL\u2019s Personal Data Protection Policy (the \u201cPolicy\u201d) at\u00a0https://www.dhl.com/hk-en/home/footer/local-privacy-notice.html\n\nBy proceeding to respond to this recruitment advertisement, you consent that we may use, retain, process, transfer or otherwise handle the personal data that we collect from you for recruitment,\u00a0 application processing, assessment and communication purposes (including any other purposes directly related thereto) in accordance with the Policy.\n\nAll personal data of unsuccessful applicants will be retained for future recruitment purposes for a period of not more than two (2) years after which such data will be destroyed.\n\nYou have the right at any time to make a data access or correction request concerning your personal data held by us. In addition, you may request us to delete your personal data that is no longer required for the relevant purposes which you have given consent. Should you wish to exercise such rights or have any question in relation to your personal data or the Policy, please contact our Human Resources Division in writing.", "employment_types": ["Full Time"], "selling_points": ["Ensure continuity of IT operations service quality", "Bachelor Degree or above education,", "8 years IS and business experience"], "locations": ["Lantau Island"], "categories": ["Admin & HR", "Administration / Operation Manager", "Others", "Transportation & Logistics", "Others"], "post_time": "2022-01-18T03:21:48Z", "salary": {"currency": null, "max": null, "min": null, "period": "monthly", "term": null}, "salary_visible": false, "title_keywords": ["manager"], "responsibilities": ["collaborate with", "policies", "business initiatives", "operations", "technical advice", "systems", "quality", "audit", "implementation", "design", "develop", "project management", "coordinate", "procedures", "review", "application development", "planning"], "requirements": {"degrees": ["degree or above", "bachelor"], "majors": ["related disciplines", "computer science"], "languages": [], "language_level": [], "hard_skills": ["no", "analysis", "problem-solving", "html", "make", "documentation", "processing"], "soft_skills": ["work effectively", "communication skills", "organizational skills", "negotiation", "problem-solving", "communication", "committed"], "languages_combined": []}, "experience_required": {"duration": ["5 years", "8 years"], "field": ["logistics industry", "management", "business"]}}, {"job_id": "100003009053838", "location_code": "hk", "company": "Konew Financial Express Ltd", "job_title": "\u7269\u696d\u8abf\u67e5\u54e1", "description": "\u8077\u8cac\uff1a\n\u5354\u52a9\u516c\u53f8\u9032\u884c\u5ba2\u6236\u7684\u7269\u696d\u67e5\u8a2a\n\u7d00\u9304\u9280\u4e3b\u76e4\u7684\u60c5\u6cc1\u53ca\u6e05\u7406\u7576\u4e2d\u96dc\u7269\n\u76e3\u5bdf\u9280\u4e3b\u76e4\u7684\u7dad\u4fee\u53ca\u7ffb\u65b0\n\u57f7\u884c\u884c\u653f\u90e8\u6307\u6d3e\u7684\u8077\u52d9\n\n\u8981\u6c42\uff1a\n\n\nHKCEE / HKDSE\u7a0b\u5ea6\u6216\u4ee5\u4e0a\n\u61c2\u5e73\u677f\u96fb\u8166\u64cd\u4f5c\n\u826f\u597d\u5ee3\u6771\u8a71\u3001\u7c21\u55ae\u82f1\u6587\n\u4e00\u5e74\u6216\u4ee5\u4e0a\u5ba2\u6236\u670d\u52d9\u7d93\u9a57\n\u614b\u5ea6\u8aa0\u61c7\u89aa\u5207\uff0c\u52e4\u596e\u5b88\u6642\uff0c\u6709\u8cac\u4efb\u611f\n\u6301 1\u30012 \u865f\u724c\u512a\u5148\u8003\u616e\n\n\u5f85\u9047\uff1a\n\n\u661f\u671f\u4e00\u81f3\u4e94\uff0c\u671d\u4e5d\u665a\u516d\n\u52e4\u5de5\u596c\u91d1\n\u914c\u60c5\u6027\u82b1\u7d05\n\u6709\u85aa\u5e74\u5047\n\u751f\u65e5\u5047\n\u5165\u8077\u5468\u5e74\u5047\n\u734e\u52f5\u5047\u671f\n\u91ab\u7642\u4fdd\u96aa\u798f\u5229\u53ca\u7259\u79d1\u798f\n\n\u7533\u8acb\u65b9\u6cd5\uff1a\u6709\u8208\u8da3\u7533\u8acb\u7684\u4eba\u58eb\uff0c\u8acb\u6309 'Apply Now'\u3002\n\n<\u6240\u6536\u96c6\u7684\u500b\u4eba\u8cc7\u6599\u7d55\u5c0d\u4fdd\u5bc6\u53ca\u53ea\u4f5c\u62db\u8058\u7528\u9014>", "employment_types": ["Full Time"], "selling_points": ["\u5354\u52a9\u516c\u53f8\u9032\u884c\u7269\u696d\u67e5\u8a2a", "\u6301 1\u30012 \u865f\u724c\u512a\u5148\u8003\u616e", "\u826f\u597d\u5de5\u4f5c\u798f\u5229"], "locations": ["Central"], "categories": ["Transportation & Logistics", "Others", "Banking / Finance", "Others", "Property / Real Estate", "Others"], "post_time": "2022-01-17T07:36:09Z", "salary": {"currency": null, "max": null, "min": null, "period": "monthly", "term": null}, "salary_visible": false, "title_keywords": [], "responsibilities": [], "requirements": {"degrees": [], "majors": [], "languages": [], "language_level": [], "hard_skills": [], "soft_skills": [], "languages_combined": []}, "experience_required": {"duration": [], "field": []}}, {"job_id": "100003009055121", "location_code": "hk", "company": "Autotoll Limited", "job_title": "\u6280\u8853\u54e1/\u9ad8\u7d1a\u6280\u8853\u54e1", "description": "\u5de5\u4f5c\u7bc4\u570d:\n\n\u5b89\u88dd\u6c7d\u8eca\u5b9a\u4f4d\u53ca\u5176\u4ed6\u8eca\u8f09\u96fb\u5668\u8a2d\u5099\uff0c\u4e94\u5929\u5de5\u4f5c\u5305\u62ec\uff08\u661f\u671f\u516d/\u65e5\uff09\n\n\n\u5165\u8077\u8981\u6c42:\n\n\u4e2d\u4e94\u7a0b\u5ea6\uff0c\u66fe\u4fee\u8b80\u6c7d\u8eca\u76f8\u95dc\u8ab2\u7a0b\n\u6709\u6c7d\u8eca\u7dad\u4fee/\u97f3\u97ff/\u96fb\u5668\u5de5\u4f5c\u7d93\u9a57\u4e00\u5e74\u6216\u4ee5\u4e0a\n\u63011\u53ca2\u985e\u99d5\u99db\u57f7\u7167\n\nWhat you can get from us\n\nOn-the-job training, learning and development\u00a0provided\nExecutive workshops, interest class, corporate purchase discount offered by SHKP\nCompetitive salary and annual leaves\nFlexible working opportunities\n\n\nInterested parties, please send full resume with\u00a0expected salary\u00a0and\u00a0available date\u00a0to Human Resources and Administration Department by e-mail or by fax 2111 9459.\n\n(Data collected will be used for recruitment purpose only.)", "employment_types": ["Full Time"], "selling_points": ["13 days annual leave", "5 day work", "OT Paid"], "locations": ["Not Specified"], "categories": ["Transportation & Logistics", "Others", "Engineering", "Others", "Others", "Others"], "post_time": "2022-01-18T01:15:54Z", "salary": {"currency": null, "max": null, "min": null, "period": "monthly", "term": null}, "salary_visible": false, "title_keywords": ["\u6280\u8853\u54e1"], "responsibilities": ["purchase"], "requirements": {"degrees": [], "majors": [], "languages": [], "language_level": [], "hard_skills": ["workshops"], "soft_skills": ["flexible", "learning"], "languages_combined": []}, "experience_required": {"duration": [], "field": []}}, {"job_id": "100003009053454", "location_code": "hk", "company": "Transport Infrastructure Management Limited", "job_title": "\u9ad8\u7d1a\u53f8\u6a5f(\u591c\u73ed)", "description": "\u8077\u8cac :\u5beb\u5b57\u6a13\u65e5\u5e38\u6e05\u6f54\u3001\u8336\u6c34\u3001\u96dc\u52d9\u53ca\u5354\u52a9\u5916\u52e4\u5de5\u4f5c\n\u8cc7\u6b77 :\u5c0f\u516d\u7a0b\u5ea6; 1\u5e74\u7d93\u9a57; \u826f\u597d\u7cb5\u8a9e; \u7565\u61c2\u8b80\u5beb\u4e2d\u6587\n\u5f85\u9047 :\u6bcf\u6708$9,500 - $10,000, \u6709\u96d9\u7ce7, \u661f\u671f\u4e00\u81f3\u4e94: \u4e0a\u53487\u664245\u5206\u81f3\u4e0b\u53484\u664245\u5206, \u6bcf\u9031\u5de5\u4f5c5\u5929, \u6bcf\u5929\u5de5\u4f5c 9 \u5c0f\u6642\n\u7533\u8acb\u9808\u77e5 :\u6c42\u8077\u8005\u53ef\u81f4\u96fb24312160(Ext.2160)\u8207\u5927\u540c\u6a5f\u68b0\u4f01\u696d\u6709\u9650\u516c\u53f8\u6f58\u5c0f\u59d0\u806f\u7d61\u3002", "employment_types": ["Full Time"], "selling_points": [], "locations": ["Shatin Area"], "categories": ["Transportation & Logistics", "Others", "Supply Chain"], "post_time": "2022-01-17T07:00:06Z", "salary": {"currency": null, "max": null, "min": null, "period": "monthly", "term": null}, "salary_visible": false, "title_keywords": [], "responsibilities": [], "requirements": {"degrees": [], "majors": [], "languages": [], "language_level": [], "hard_skills": [], "soft_skills": [], "languages_combined": []}, "experience_required": {"duration": [], "field": []}}, {"job_id": "100003009056368", "location_code": "hk", "company": "Cosmos Machinery Enterprises Ltd", "job_title": "\u5168\u8077\u6e05\u6f54\u54e1", "description": "Responsibilities\n\nPrepare & Co-ordinate with clients for delivery arrangement & documents\nFollow-up with clients instruction & shipping information to warehouse\nAssist to update Import & Export Declaration\nFollow up on full \u2013set shipping documents, including invoice, good receiving, declaration\nAssist to update the shipment delay reduce impact of delivery\n\nRequirements\n\nPost-secondary or above\n1-2 years relevant logistics clerical experience\nGood command of written and spoken Cantonese, Fair in English and Mandarin.\nStrong in Microsoft Office applications, especially in Excel, Power Point\nDetails and customer service orientated is a must,\nWilling to work under pressure and highly motivated.\nImmediate available is highly preferred.\n\nCandidate with more experience will be considered as Senior Coordinator.\n\nWe offer 5 days work and competitive remuneration package to the right candidate. Interested candidate please send your resume with expected salary through \u201cApply Now\u201d\n\n(Personal data collected will be used for recruitment purpose only)", "employment_types": ["Full Time"], "selling_points": [], "locations": ["Lai Chi Kok"], "categories": ["Transportation & Logistics", "Others", "Others", "Others"], "post_time": "2022-01-18T04:05:54Z", "salary": {"currency": null, "max": null, "min": null, "period": "monthly", "term": null}, "salary_visible": false, "title_keywords": [], "responsibilities": ["shipping documents", "shipping", "invoice", "co-ordinate with clients", "follow-up with clients"], "requirements": {"degrees": [], "majors": [], "languages": ["cantonese", "english", "mandarin"], "language_level": ["good command"], "hard_skills": ["power point", "excel", "microsoft office"], "soft_skills": ["motivated", "customer service", "work under pressure"], "languages_combined": [{"language": "cantonese", "language_level": ["good command"]}, {"language": "english", "language_level": ["good command"]}, {"language": "mandarin", "language_level": ["good command"]}]}, "experience_required": {"duration": ["1-2 years"], "field": ["logistics", "clerical"]}}, {"job_id": "100003009053485", "location_code": "hk", "company": "Vitat Company Limited", "job_title": "\u7269\u696d\u670d\u52d9\u54e1 (\u65e5 / \u591c\u66f4)**", "description": "\u6210\u70baHKTVer,\u60a8\u53ef\u4ee5\u4eab\u6709: * \u5b89\u5168\u99d5\u99db\u6d25\u8cbc * \u5168\u52e4\u6d25\u8cbc * \u512a\u8cea\u670d\u52d9\u6d25\u8cbc * \u7e3e\u6548\u82b1\u7d05 * \u65b0\u4eba\u734e\u91d1 $8,000 * \u6709\u85aa\u5e74\u504716\u5929 * \u54e1\u5de5\u8cfc\u7269\u512a\u60e0 * \u7259\u79d1\u4fdd\u5065\u6d25\u8cbc\u3001\u91ab\u7642\u798f\u5229\n\n\u8077\u8cac: -\u99d5\u99db 3.3-5.5\u5678 \u8ca8\u8eca\u6536\u9001\u7db2\u8cfc\u8ca8\u54c1\n\n\u8077\u4f4d\u8981\u6c42: - \u6301\u67091\u30012\u865f\u99d5\u99db\u57f7\u7167 - \u5169\u5e74\u826f\u597d\u99d5\u99db\u7d93\u9a57 - \u9700\u642c\u904b/\u5354\u52a9\u642c\u904b\u8ca8\u7269 - \u8f2a\u73ed\u8f2a\u4f11\u5236,\u5e73\u5747\u6bcf\u6708\u4f11\u50476\u5929 - \u6bcf\u5929\u7576\u503c10\u5c0f\u6642(08:00-22:00\u5167)\n\n\u5de5\u4f5c\u5730\u9ede ( \u5c07\u8ecd\u6fb3 ): \u5c07\u8ecd\u6fb3\u5de5\u696d\u90a8 \u99ff\u660c\u88571\u865f \u5c07\u8ecd\u6fb3\u7269\u6d41\u4e2d\u5fc3 (\u514d\u8cbb\u7a7f\u68ad\u5df4\u58eb\u5f80\u8fd4\u8abf\u666f\u5dba/\u5eb7\u57ce\u6e2f\u9435\u7ad9\u3002)\n\n\u7533\u8acb\u65b9\u6cd5: \u7531\u65bc\u75ab\u60c5\u95dc\u4fc2,\u6211\u5011\u9700\u8981\u63a7\u5236\u516c\u53f8\u5167\u5605\u4eba\u6d41,\u6211\u5011\u6703\u4e00\u661f\u671f\u5167\u4e3b\u52d5\u806f\u7d61\u5408\u9069\u7533\u8acb\u4eba,\u4ee5\u9810\u7d04\u9762\u8a66\u5f62\u5f0f\u5b89\u6392\u3002\n\n\u5982\u679c\u4f60\u5c0d\u4ee5\u4e0a\u8077\u4f4d\u6709\u8208\u8da3,\u8acb\u63d0\u4f9b\u4f60\u5605\u59d3\u540d\u3001\u7533\u8acb\u8077\u4f4d\u3001\u5de5\u4f5c\u7d93\u9a57\u53ca\u806f\u7d61\u96fb\u8a71 Whatsapp \u81f3:\u00a09752 6762(\u5c07\u8ecd\u6fb3 \u4e4b\u8077\u4f4d)\n\nhttps://api.whatsapp.com/send?phone=85297526762\n\nJob Types: Full-time, Permanent\n\nBenefits:\n\nDental insurance\nEmployee discount\nMedical Insurance\n\nSchedule:\n\nDay shift\nEarly shift\n\nSupplemental Pay:\n\nPerformance bonus", "employment_types": ["Full Time"], "selling_points": [], "locations": ["Wan Chai"], "categories": ["Transportation & Logistics", "Others", "Inventory / Warehousing", "Supply Chain"], "post_time": "2022-01-17T07:02:57Z", "salary": {"currency": null, "max": null, "min": null, "period": "monthly", "term": null}, "salary_visible": false, "title_keywords": [], "responsibilities": [], "requirements": {"degrees": [], "majors": [], "languages": [], "language_level": [], "hard_skills": ["whatsapp"], "soft_skills": [], "languages_combined": []}, "experience_required": {"duration": [], "field": []}}, {"job_id": "100003009052669", "location_code": "hk", "company": "Canon Engineering Hong Kong Co Ltd", "job_title": "Logistics Clerk", "description": "The Role:\u00a0\n\nThe key objectives of the role are including but not limited to administrative support to warehouse operations,\u00a0data input and keeping accurate records of system, proactively communicating inventory and operations issues to\u00a0Manager. You will be also involved in all improvement activities\u00a0and follow through all the procedures within the whole logistics and supply chain processes.\u00a0You will be working closely with internal teams to ensure we have a smooth operation of handling arrival of goods. Other\u00a0logistics\u00a0assignments will be required as part of our improvement projects.\u00a0\u00a0\n\nIf you are\u2026\u202f\u202f\n\n\nAn\u00a0associate degreed graduate\u00a0in\u00a0supply chain or logistics\u00a0related\u00a0disciplines\u00a0\n\nLooking for an opportunity to learn and work in one of the greatest\u00a0brand\u00a0from Hong Kong.\u00a0\n\nHaving previous experience in logistics operations from 3PL or consumer goods manufacturing industry.\u00a0\n\nExcellent in communication, organization, and coordination skills.\u00a0\n\nAble to work under pressure\u00a0with strong sense of responsibility.\u00a0\n\nA positive, independent, creative, energetic and a good team player.\u00a0\n\nGood command in spoken and written English & Chinese.\u00a0\n\nWe will offer you...\u202f\u202f\u00a0\n\nCareer with the market leader in health product sector from Hong Kong.\u202f\nDynamic working culture with great team spirit.\nShuttle to/from Taipo,\u202fTuen\u202fMun, Tin Shui Wai, Tsuen Wan, Kowloon Tong, Yau Tong\u00a0and Causeway Bay.\u00a0\n\nRapid growth opportunities for strong performers.\nAttractive staff purchase\u202fdiscount.\u202f\n\nCasual attire at work.\n\nInterested parties, please send full resume with last & expected salary and date of available by clicking \u2018Apply\u00a0Now\u2019\u00a0\n\nPersonal data collected is for recruitment purpose only. For corporate information, please visit:\u00a0www.vitagreen.com\u00a0", "employment_types": ["Full Time", "Permanent"], "selling_points": [], "locations": ["Kwai Hing"], "categories": ["Transportation & Logistics", "Others", "Freight Forwarding", "Shipping"], "post_time": "2022-01-17T03:40:49Z", "salary": {"currency": null, "max": null, "min": null, "period": "monthly", "term": null}, "salary_visible": false, "title_keywords": ["logistics clerk"], "responsibilities": ["administrative support", "operations", "inventory", "procedures", "data input", "teams", "communication", "purchase", "logistics", "coordination", "warehouse operations", "work under pressure"], "requirements": {"degrees": [], "majors": [], "languages": ["english", "chinese"], "language_level": ["good command"], "hard_skills": ["wan", "dynamic", "rapid"], "soft_skills": ["good team player", "team spirit", "independent", "coordination skills", "creative", "sense of responsibility", "communication", "energetic", "dynamic", "smooth", "accurate", "positive", "work under pressure"], "languages_combined": [{"language": "english", "language_level": ["good command"]}, {"language": "chinese", "language_level": ["good command"]}]}, "experience_required": {"duration": [], "field": ["logistics", "manufacturing industry"]}}, {"job_id": "100003009055385", "location_code": "hk", "company": "Hong Kong Technology Venture Company Limited", "job_title": "[\u5c07\u8ecd\u6fb3.\u9752\u8863.\u5c6f\u9580] \u6d3e\u8ca8\u53f8\u6a5f", "description": "Responsibilities:\nReview and approve credit applications of credit applications within the delegated approval authority; and provide recommendations for requiring higher approval authority;\n\nManage and monitor portfolio of assigned units and ensure credit quality and full compliance with Bank\u2019s credit policies and risk appetites;\n\nHighlight and identify exceptions against the Bank\u2019s lending policies, standard terms and conditions being offered to borrowing clients; and\n\nPerform other ad hoc projects or assignments.\n\nRequirements:\nUniversity graduate in Risk Management, Finance, Accountancy, Business Administration or related disciplines;\n\nCFA, Accountant and/or FRM is a plus; and HKIB ECF-CRM;\n\n5-10 years\u2019 solid experience of large corporate, FIG, SME, and/ or relationship management,\n\nSound knowledge in various corporate lending products, accounting principles and financial statement analysis;\n\nGood understanding in key market and industry dynamics; and\n\nExcellent analytical and quantitative skills with good command of both spoken and written English and Chinese including Putonghua.\n\nInterested candidates, please click APPLY NOW \u00a0to apply.", "employment_types": ["Full Time"], "selling_points": [], "locations": ["Not Specified"], "categories": ["Transportation & Logistics", "Others", "Supply Chain"], "post_time": "2022-01-18T02:24:57Z", "salary": {"currency": null, "max": null, "min": null, "period": "monthly", "term": null}, "salary_visible": false, "title_keywords": [], "responsibilities": ["policies", "review", "quality", "monitor", "compliance", "provide recommendations", "ad hoc projects"], "requirements": {"degrees": ["university graduate"], "majors": ["risk management", "business administration", "finance", "accountancy", "related disciplines"], "languages": ["putonghua", "english", "chinese"], "language_level": ["excellent", "good command"], "hard_skills": ["cfa", "plus", "analysis", "frm"], "soft_skills": [], "languages_combined": [{"language": "putonghua", "language_level": ["excellent", "good command"]}, {"language": "english", "language_level": ["excellent", "good command"]}, {"language": "chinese", "language_level": ["excellent", "good command"]}]}, "experience_required": {"duration": ["5-10 years"], "field": ["management"]}}, {"job_id": "100003009054183", "location_code": "hk", "company": "Vita Green Health Products Company Limited", "job_title": "Logistics Clerk", "description": "\u8077\u8cac :\u8ca0\u8cac\u5305\u88dd\u53ca\u57f7\u6574\u8ca8\u54c1, \u6536\u8ca8, \u88dc\u8ca8, \u4e0a\u67b6\u53ca\u8ca0\u8cac\u4e00\u822c\u8ca8\u5009\u96dc\u52d9\u5de5\u4f5c\n\u8cc7\u6b77 :\u4e2d\u4e09\u7a0b\u5ea6; 2\u5e74\u7d93\u9a57; \u826f\u597d\u7cb5\u8a9e; \u4e00\u822c\u666e\u901a\u8a71; \u4e00\u822c\u82f1\u8a9e; \u61c2\u8b80\u5beb\u4e2d\u6587; \u7565\u61c2\u8b80\u5beb\u82f1\u6587\n\u5f85\u9047 :\u6bcf\u6708$12,000 - $13,000, \u6709\u6bcf\u6708\u52e4\u5de5\u734e\u91d1$500, \u751f\u65e5\u5047, \u54e1\u5de5\u8cfc\u7269\u512a\u60e0, \u5728\u8077\u57f9\u8a13, \u91ab\u7642\u798f\u5229 \u53ca\u7a7f\u68ad\u5df4\u58eb\u670d\u52d9, \u661f\u671f\u4e00\u81f3\u516d: \u4e0a\u53489\u6642\u81f3\u4e0b\u53486\u6642, \u6bcf\u9031\u5de5\u4f5c5\u5929\u81f36\u5929, \u6bcf\u5929\u5de5\u4f5c 8 \u5c0f\u6642, \u6bcf\u6708\u4e00\u6b21\u661f\u671f\u516d\u5de5\u4f5c\n\u7533\u8acb\u9808\u77e5 :\u6c42\u8077\u8005\u53ef\u96fb\u90f5(APPLY NOW)\u5c65\u6b77\u8868\u7d66\u4f59\u4ec1\u751f(\u9999\u6e2f)\u6709\u9650\u516c\u53f8\u3002\u5982\u8981\u7d22\u53d6\u6536\u96c6\u500b\u4eba\u8cc7\u6599\u8072\u660e, \u8acb\u8207\u7f85\u5c0f\u59d0(Email)\u806f\u7d61\u3002", "employment_types": ["Full Time", "Permanent"], "selling_points": ["Logistics support role", "Dynamic working culture", "Rapid growth opportunities for strong performers"], "locations": ["Tai Po Area"], "categories": ["Admin & HR", "Others", "Transportation & Logistics", "Others", "Supply Chain"], "post_time": "2022-01-17T08:41:54Z", "salary": {"currency": null, "max": null, "min": null, "period": "monthly", "term": null}, "salary_visible": false, "title_keywords": ["logistics clerk"], "responsibilities": [], "requirements": {"degrees": [], "majors": [], "languages": [], "language_level": [], "hard_skills": [], "soft_skills": [], "languages_combined": []}, "experience_required": {"duration": [], "field": []}}, {"job_id": "100003009055965", "location_code": "hk", "company": "Chong Hing Bank Ltd", "job_title": "Credit Approval \u2013 Vice President/ Assistant Vice President", "description": "\n\u8077\u8cac :\u9700\u6574\u7406\u8ca8\u7269, \u57f7\u8ca8, \u6253\u5305\u8ca8\u4ef6\u7b49\u5de5\u4f5c\n\n\u8cc7\u6b77 :\u5c0f\u516d\u7a0b\u5ea6; \u826f\u597d\u7cb5\u8a9e; \u4e00\u822c\u666e\u901a\u8a71; \u4e00\u822c\u82f1\u8a9e; \u7565\u61c2\u8b80\u5beb\u4e2d\u6587; \u7565\u61c2\u8b80\u5beb\u82f1\u6587\n\n\u5f85\u9047 :\u6bcf\u5c0f\u6642$65.00, \u661f\u671f\u4e00\u81f3\u4e94: \u4e0a\u53489\u6642\u81f3\u4e0b\u53481\u6642, \u6bcf\u9031\u5de5\u4f5c5\u5929\n\n\u7533\u8acb\u9808\u77e5 :\u6c42\u8077\u8005\u53ef\u81f4\u96fb26081519\u8207\u7da0\u6a44\u6b16\u6709\u9650\u516c\u53f8\u4f55\u5c0f\u59d0\u806f\u7d61\u3002\n\n", "employment_types": ["Full Time"], "selling_points": ["Review and approve credit applications", "Manage and monitor portfolio", "5-10 years\u2019 solid experience"], "locations": ["Not Specified"], "categories": ["Transportation & Logistics", "Others", "Banking / Finance", "Credit Analysis / Approval", "Risk Management"], "post_time": "2022-01-18T03:08:18Z", "salary": {"currency": null, "max": null, "min": null, "period": "monthly", "term": null}, "salary_visible": false, "title_keywords": ["vice president", "assistant vice president"], "responsibilities": [], "requirements": {"degrees": [], "majors": [], "languages": [], "language_level": [], "hard_skills": [], "soft_skills": [], "languages_combined": []}, "experience_required": {"duration": [], "field": []}}, {"job_id": "100003009052297", "location_code": "hk", "company": "Eu Yan Sang (HK) Ltd", "job_title": "\u5009\u52d9\u54e1", "description": "\n\u8077\u8cac :\u8ca0\u8cac\u5546\u54c1\u7684\u9032\u51fa\u5eab\u6aa2\u9a57\u7b49\u65e5\u5e38\u5de5\u4f5c, \u5305\u62ec\u9ede\u8ca8\u3001\u57f7\u8ca8\u5165\u7bb1\u3001\u5305\u88dd\u3001\u6574\u7406\u5009\u5eab, \u904b\u7528\u96fb\u8166\u7cfb\u7d71\u9032\u884c\u8ca8\u7269\u5206\u985e,\u6a19\u7c64\u9ecf\u8cbc,\u6383\u63cf\u53ca\u6210\u54c1\u6574\u7406\u7b49\u5de5\u4f5c, \u8ca0\u8cac\u54c1\u8cea\u76e3\u6e2c\u5de5\u4f5c, \u4f7f\u7528\u5527\u8eca, \u9700\u8981\u61c9\u4ed8\u9ad4\u529b\u52de\u52d5\u5de5\u4f5c, \u9700\u8981\u70ba\u5546\u54c1\u62cd\u7167\u4e26\u5b58\u6a94\n\n\u8cc7\u6b77 :\u4e2d\u4e94\u7a0b\u5ea6; 1\u5e74\u7d93\u9a57; \u4e00\u822c\u7cb5\u8a9e\u512a\u5148; \u4e00\u822c\u666e\u901a\u8a71\u512a\u5148; \u4e00\u822c\u82f1\u8a9e\u512a\u5148; \u61c2\u8b80\u5beb\u4e2d\u6587; \u7565\u61c2\u8b80\u5beb\u82f1\u6587; \u5177\u6709\u4e00\u822c\u4e92\u806f\u7db2\u77e5\u8b58; \u61c2\u4e2d\u82f1\u6587\u96fb\u8166\u64cd\u4f5c; \u5177\u6709\u57fa\u672c\u96fb\u8166\u64cd\u4f5c\u77e5\u8b58\n\n\u5f85\u9047 :\u6bcf\u6708$11,000 - $15,000, \u6709\u52e4\u5de5\u734e\u91d1, \u9280\u884c\u5047\u671f, \u96d9\u7ce7 \u53ca\u5e74\u7d42\u734e\u91d1, \u4e0a\u53489\u6642\u81f3\u4e0b\u53486\u6642, \u6bcf\u9031\u5de5\u4f5c6\u5929,\u8f2a\u4f11, \u6bcf\u5929\u5de5\u4f5c 9 \u5c0f\u6642\n\n\u7533\u8acb\u9808\u77e5 :\u6c42\u8077\u8005\u53ef\u96fb\u90f5(Apply Now)\u5c65\u6b77\u8868\u7d66\u5f97\u7269(\u9999\u6e2f)\u4f9b\u61c9\u93c8\u6709\u9650\u516c\u53f8\u3002\u5982\u8981\u7d22\u53d6\u6536\u96c6\u500b\u4eba\u8cc7\u6599\u8072\u660e, \u8acb\u8207\u56b4 \u5148\u751f(Email)\u806f\u7d61\u3002\n\n", "employment_types": ["Full Time"], "selling_points": [], "locations": ["Yuen Long"], "categories": ["Transportation & Logistics", "Others", "Inventory / Warehousing", "Supply Chain"], "post_time": "2022-01-17T02:40:01Z", "salary": {"currency": null, "max": null, "min": null, "period": "monthly", "term": null}, "salary_visible": false, "title_keywords": ["\u5009\u52d9\u54e1"], "responsibilities": [], "requirements": {"degrees": [], "majors": [], "languages": [], "language_level": [], "hard_skills": [], "soft_skills": [], "languages_combined": []}, "experience_required": {"duration": [], "field": []}}, {"job_id": "100003009053792", "location_code": "hk", "company": "De Wu (HK) Supply Chain Company Limited", "job_title": "\u5009\u52d9\u54e1", "description": "Duties:\u00a0\n\nAssisting in planning design, preparation and implementation of soft landscape works and vegetation maintenance under contract\nConducting site inspection, site supervision and preparing and maintaining site records under contracts\nConducting Tree Risk Assessment\nChecking or auditing Form 1, Form 1.5 and Form 2 records\nAssisting Landscape Architects to vet Tree Preservation and Removal Application including on site checking or auditing\nFollowing up with complaint cases related to vegetation maintenance\nProviding technical support and assistant to the Landscape Term Contract administration and contract document preparation\n\nRequirements:\u00a0\n\nGraduated from one of the arboriculture, horticulture, landscape management or tree management programmes at Level 3 to Level 5 of the Qualifications Framework in Hong Kong\nA diploma or higher certificate in management studies, natural science or related subjects from a Hong Kong university or HKIVE\nAt least 1 year of related practical experience on supervision of soft landscape work, woodland planting and management, or tree inspection and risk management", "employment_types": ["Full Time"], "selling_points": [], "locations": ["Tin Shui Wai"], "categories": ["Transportation & Logistics", "Others", "Inventory / Warehousing", "Supply Chain"], "post_time": "2022-01-17T07:31:11Z", "salary": {"currency": null, "max": null, "min": null, "period": "monthly", "term": null}, "salary_visible": false, "title_keywords": ["\u5009\u52d9\u54e1"], "responsibilities": ["site supervision", "maintenance", "maintaining", "technical support", "contracts", "contract administration", "implementation", "design", "site inspection", "checking", "auditing", "planning"], "requirements": {"degrees": ["diploma", "higher certificate"], "majors": ["science"], "languages": [], "language_level": [], "hard_skills": [], "soft_skills": [], "languages_combined": []}, "experience_required": {"duration": ["at least 1 year"], "field": ["related", "risk management", "management"]}}, {"job_id": "100003009054198", "location_code": "hk", "company": "RecruitFirst Limited", "job_title": "Assistant Arborist Support [20k/ Tree Risk/ Landscape/ 9 months contract/ Kowloon]", "description": "HAECO ITM Limited is a joint venture between HAECO (Hong Kong Aircraft Engineering Co. Ltd) and Cathay Pacific, providing inventory technical management services to different airline customers in Hong Kong and around the world. Customers anticipate to benefit saving from the ITM services through synergy of component pooling, sound technical know-how of component engineering, repair and supplier management.\n\nHXITM is now looking for candidates who are interested in this business for the position of\u00a0Inventory Management Executive.\n\nScope of Duties:\u00a0\n\nAnalyze provisioning parameter, customer fleet data, part reliability and repair time performance to determine the optimum stock level and provisioning policy\nManaging Float module template and incorporating changes as approved\nRecommend changes in inventory level and support model where appropriate based on analysis and simulation on part shortage promptly, by gathering information, interfacing with functional teams, and monitoring shortage recovery continuously\nProduce and deliver regular inventory reports and maintain relevant database to support inventory operations planning and control in an effective and efficient manner\nInteract, communicate, and influence functional teams to action on deficient area based on stock level alert and failed pick analysis\n\nRequirements:\u00a0\n\nA minimum of 3 years of relevant experience, preferably in Inventory Management, Operations, Planning field or Material control\nA recognized Degree in Supply Chain, Business Analysis, or related disciplines\nKnowledge or experience in aviation industry would be an advantage\nGood analytical and problem-solving skills, able to think systematically and holistically\nSkillful in preparing analytical report and presentations with MS Excel, MS Access, MS PowerPoint.\nGood command of English, both spoken and written\n\nHow to Apply:\n\nPlease send your resume with expected salary, quoting the employer's reference no., to: Human Resources Department - Resourcing Team, Hong Kong Aircraft Engineering Company Limited, 80 South Perimeter Road, Hong Kong International Airport, Lantau, Hong Kong OR submit your application via\u00a0https://careers.haeco.com/hkg/job-opening-itm/\n\nCandidates not contacted 4-6 weeks after submission of applications and/or interviews may consider their application unsuccessful.\n\nAll information provided by candidates will be treated in strict confidence and will be used for employment purpose only.", "employment_types": ["Full Time", "Contract"], "selling_points": [], "locations": ["Kwun Tong Area"], "categories": ["Transportation & Logistics", "Others", "Sciences, Lab, R&D", "Environmental Science / Waste Management", "Property / Real Estate", "Others"], "post_time": "2022-01-17T08:46:45Z", "salary": {"currency": null, "max": null, "min": null, "period": "monthly", "term": null}, "salary_visible": false, "title_keywords": ["assistant"], "responsibilities": ["control", "data", "operations", "analysis", "inventory", "teams", "monitoring", "repair", "maintain", "reports", "database", "planning"], "requirements": {"degrees": ["degree"], "majors": ["related disciplines", "business"], "languages": ["english"], "language_level": ["good command"], "hard_skills": ["no", "aircraft", "analysis", "presentations", "ms excel", "problem-solving skills", "ms powerpoint"], "soft_skills": ["problem-solving skills", "confidence"], "languages_combined": [{"language": "english", "language_level": ["good command"]}]}, "experience_required": {"duration": ["minimum of 3 years"], "field": ["inventory management", "relevant experience", "planning"]}}, {"job_id": "100003009053726", "location_code": "hk", "company": "Hong Kong Aircraft Engineering Co Ltd", "job_title": "Inventory Management Executive", "description": "\n\u8077\u8cac :\u8ca0\u8cac\u6bcf\u5929\u4e0a\u8ca8, \u843d\u8ca8, \u62c6\u6ac3, \u57cb\u4f4d, \u5009\u5167\u8ca8\u7269\u6574\u9f4a\u6e05\u6f54\n\n\u8cc7\u6b77 :\u6c92\u6709\u5b78\u6b77\u8981\u6c42; \u826f\u597d\u7cb5\u8a9e; \u61c2\u8b80\u5beb\u4e2d\u6587; \u6709\u8cac\u4efb\u5fc3, \u6709\u5718\u9ad4\u5408\u4f5c\u7cbe\u795e, \u9858\u610f\u914d\u5408\u516c\u53f8\u898f\u5247, \u5b88\u6642, \u6709\u79ae\u8c8c, \u61c2\u64cd\u4f5c\u624b\u5527\u8eca\n\n\u5f85\u9047 :\u6bcf\u6708$14,000, \u6709\u91ab\u7642\u4fdd\u96aa, \u5e74\u7d42\u914c\u60c5\u6027\u82b1\u7d05,\u751f\u65e5\u5047\u53ca\u6301\u6709\u53c9\u8eca\u724c\u6bcf\u6708\u6709$800, \u661f\u671f\u4e00\u81f3\u516d: \u4e0a\u53488\u6642\u81f3\u4e0b\u53485\u664215\u5206, \u6bcf\u9031\u5de5\u4f5c6\u5929\n\n\u7533\u8acb\u9808\u77e5 :\u6c42\u8077\u8005\u53ef\u81f4\u96fb26738388\u8207\u767c\u5229\u884c\u6709\u9650\u516c\u53f8\u9673\u5148\u751f\u806f\u7d61\u3002\n\n", "employment_types": ["Full Time", "Permanent"], "selling_points": ["Analyze provisioning parameter", "Managing Float module template", "A minimum of 3 years of relevant experience"], "locations": ["Airport Area"], "categories": ["Transportation & Logistics", "Others", "Professional Services", "Business Analysis / Data Analysis", "Supply Chain"], "post_time": "2022-01-17T07:25:42Z", "salary": {"currency": null, "max": null, "min": null, "period": "monthly", "term": null}, "salary_visible": false, "title_keywords": ["inventory management", "executive"], "responsibilities": [], "requirements": {"degrees": [], "majors": [], "languages": [], "language_level": [], "hard_skills": [], "soft_skills": [], "languages_combined": []}, "experience_required": {"duration": [], "field": []}}, {"job_id": "100003009053566", "location_code": "hk", "company": "Boxful Limited", "job_title": "\u517c\u8077\u57f7\u8ca8\u54e1(\u6b61\u8fce\u5bb6\u5ead\u4e3b\u5a66)", "description": "\n\u8077\u8cac :\u8ca0\u8cac\u8ca8\u7269\u4e4b\u642c\u904b,\u6574\u7406,\u76e4\u9ede\u7b49\u5de5\u4f5c,\u5076\u723e\u9700\u5916\u52e4\n\n\u8cc7\u6b77 :\u4e2d\u4e09\u7a0b\u5ea6; 1\u5e74\u7d93\u9a57; \u4e00\u822c\u7cb5\u8a9e; \u4e00\u822c\u82f1\u8a9e; \u61c2\u8b80\u5beb\u4e2d\u6587; \u80fd\u7368\u7acb\u5de5\u4f5c\n\n\u5f85\u9047 :\u6bcf\u6708$12,500, \u6709\u82b1\u7d05, \u91ab\u7642\u6d25\u8cbc\u53ca\u5176\u4ed6\u6d25\u8cbc/\u798f\u5229(\u7236\u6bcd\u611f\u8b1d\u91d1,\u5b50\u5973\u6559\u80b2\u6d25\u8cbc,\u7279\u5225\u5047\u671f), \u661f\u671f\u4e00\u81f3\u4e94: \u4e0a\u53488\u6642\u534a\u81f3\u4e0b\u53485\u6642\u534a, \u6bcf\u9031\u5de5\u4f5c5\u5929\n\n\u7533\u8acb\u9808\u77e5 :\u6c42\u8077\u8005\u53ef\u81f4\u96fb27877295\u8207\u5bcc\u5b89\u96c6\u5718\u6709\u9650\u516c\u53f8\u6797\u5148\u751f\u806f\u7d61\u3002\n\n", "employment_types": ["Part Time"], "selling_points": [], "locations": ["Kwai Tsing Area"], "categories": ["Transportation & Logistics", "Others", "Inventory / Warehousing", "Others", "Others"], "post_time": "2022-01-17T07:10:19Z", "salary": {"currency": null, "max": null, "min": null, "period": "hourly", "term": null}, "salary_visible": false, "title_keywords": [], "responsibilities": [], "requirements": {"degrees": [], "majors": [], "languages": [], "language_level": [], "hard_skills": [], "soft_skills": [], "languages_combined": []}, "experience_required": {"duration": [], "field": []}}, {"job_id": "100003009053768", "location_code": "hk", "company": "Richform Holdings Limited", "job_title": "\u5009\u52d9\u54e1", "description": "\nWe are now looking for enthusiastic English speaking teachers in the early childhood educational sector and Bachelor degree holder or higher.\nJob Description:\nTeach English to young learners in a fun and interesting way\nOrganize, conduct and follow the teaching curriculum provided by schools\nMake lesson plan\nTeaching phonics, Trinity GESE, Oral and Cambridge English\nRequirements:\nMust be Native English Speaker\nDegree and/or with teaching qualification such as TEFL, TESOL, QKT and PGDE is preferred.\nPatient, friendly, outgoing, caring and love working with young children\nClean criminal background check\nPast experience in teaching young children in a kindergarten preferred\nBenefits:\nTraining workshops\nTeaching resources and materials support\nWorking visa sponsorship for suitable full-time candidates\nInterested parties please send your CV, availability and expected salary email to us\nFrances Lai\nUnit 2503, 25/F,\nTuen Mun Parklane Square,\n2 Tuen Hi Road,\nTuen Mun\nHong Kong\n\nEmail: Apply Now\nPhone:96894897\nFax:\n\n", "employment_types": ["Full Time"], "selling_points": [], "locations": ["Kwun Tong"], "categories": ["Transportation & Logistics", "Others", "Inventory / Warehousing", "Supply Chain"], "post_time": "2022-01-17T07:29:34Z", "salary": {"currency": null, "max": null, "min": null, "period": "monthly", "term": null}, "salary_visible": false, "title_keywords": ["\u5009\u52d9\u54e1"], "responsibilities": ["plan"], "requirements": {"degrees": ["degree"], "majors": [], "languages": ["english"], "language_level": ["native"], "hard_skills": ["clean"], "soft_skills": ["outgoing", "patient", "friendly"], "languages_combined": [{"language": "english", "language_level": ["native"]}]}, "experience_required": {"duration": [], "field": ["teaching"]}}, {"job_id": "100003009051643", "location_code": "hk", "company": "Emperor Watch & Jewellery (HK) Company Limited", "job_title": "Logistic Clerk", "description": "Responsibilities:\n\nData entry and price tag handling\nHandle goods packaging according to company standards\nLiaise with other department on merchandise transfer and delivery issue\nProvide administrative and clerical support\nHandling ad hoc assignments as required\n\n\nRequirements:\n\nForm 5 graduate or above\nMinimum 1 year of working experience,\u00a0 worked in Jewellery industry would be an advantage\nExperience gained from logistic field is also considered\nFamiliar with SAP system would be an advantage\nWilling to learn, with strong attention to detail\nGood PC application skills\nGood command of both English and Mandarin\nImmediately available is preferred\n\nWe offer 5-day-work week with competitive remuneration and benefit packages to the right candidate. Interested parties please send your application letter, resume, expected salary and availability to Human Resources Department, 25/F, Emperor Group Centre, 288 Hennessy Road, Wanchai, Hong Kong or by\u00a0APPLY NOW\u00a0or by email to ewjrecruitment01 @ emperorgroup . com\u00a0\n\nWe are an equal opportunity employer and welcome applications from all qualified candidates. The information provided will be treated in strict confidence and be used only for consideration of your application for relevant / similar posts within the Emperor Group. Applicants not hearing from us within four weeks from the date of advertisement may consider their applications unsuccessful. We retain the unsuccessful applications for a maximum period of 24 months.", "employment_types": ["Full Time", "Permanent"], "selling_points": ["5-day work", "Data entry and price tag handling", "Administrative and clerical support"], "locations": ["Wan Chai"], "categories": ["Transportation & Logistics", "Others", "Inventory / Warehousing", "Supply Chain"], "post_time": "2022-01-16T17:39:04Z", "salary": {"currency": null, "max": null, "min": null, "period": null, "term": null}, "salary_visible": false, "title_keywords": ["logistic clerk"], "responsibilities": ["liaise with", "ad hoc assignments", "administrative and clerical support", "data entry"], "requirements": {"degrees": ["form 5"], "majors": [], "languages": ["english", "mandarin"], "language_level": ["good command"], "hard_skills": ["pc", "sap"], "soft_skills": ["willing to learn", "attention to detail"], "languages_combined": [{"language": "english", "language_level": ["good command"]}, {"language": "mandarin", "language_level": ["good command"]}]}, "experience_required": {"duration": ["minimum 1 year"], "field": []}}, {"job_id": "100003009055255", "location_code": "hk", "company": "The Hong Kong Ice & Cold Storage Company Limited", "job_title": "\u4e2d\u724c\u53f8\u6a5f(\u6cb9\u5858)", "description": "\u8077\u8cac :\u8ca0\u8cac\u4e0a\u843d\u8ca8, \u9001\u8ca8, \u6536\u9280, \u8eca\u8f1b\u6e05\u6f54\u53ca\u9700\u8207\u5ba2\u6236\u6e9d\u901a; \u53d6\u8eca\u5730\u9ede:\u6cb9\u5858\n\u8cc7\u6b77 :\u6c92\u6709\u5b78\u6b77\u8981\u6c42; 3\u5e74\u7d93\u9a57; \u826f\u597d\u7cb5\u8a9e; \u61c2\u8b80\u5beb\u4e2d\u6587; \u61c2\u95b1\u8b80\u82f1\u6587; \u6301\u6709\u4e2d\u578b\u8ca8\u8eca\u99d5\u99db\u57f7\u7167\n\u5f85\u9047 :\u6bcf\u6708$22,000 - $30,000, \u6709\u96d9\u7ce7, \u5e74\u504711\u5929, \u4f63\u91d1, \u5728\u8077\u57f9\u8a13, \u91ab\u7642\u4fdd\u96aa \u53ca\u6649\u5347\u6a5f\u6703, \u4e0a\u53485\u6642\u534a\u81f3\u4e0b\u53483\u6642\u534a, \u6bcf\u9031\u5de5\u4f5c6\u5929,\u8f2a\u4f11, \u6bcf\u5929\u5de5\u4f5c 9 \u5c0f\u6642\n\u7533\u8acb\u9808\u77e5 :\u6c42\u8077\u8005\u53ef\u6309 APPLY NOW\u7533\u8acb\u6216\u81f4\u96fb92793861\u8207\u9999\u6e2f\u88fd\u51b0\u53ca\u51b7\u85cf\u6709\u9650\u516c\u53f8\u9ec3\u5148\u751f\u806f\u7d61\u3002", "employment_types": ["Full Time"], "selling_points": [], "locations": ["Kwun Tong Area"], "categories": ["Transportation & Logistics", "Others", "Private Transportation"], "post_time": "2022-01-18T01:56:28Z", "salary": {"currency": null, "max": null, "min": null, "period": "monthly", "term": null}, "salary_visible": false, "title_keywords": [], "responsibilities": [], "requirements": {"degrees": [], "majors": [], "languages": [], "language_level": [], "hard_skills": [], "soft_skills": [], "languages_combined": []}, "experience_required": {"duration": [], "field": []}}, {"job_id": "100003009054386", "location_code": "hk", "company": "Superpower Pumping Engineering Co., Ltd.", "job_title": "Purchasing Officer", "description": "\u00a0Job Responsibilities:\nMonitor the overall inventory level and ensure replenishment are stocked within the required time frame\nManage full procurement process starting from vendor sourcing & selection, goods & services delivery, etc.\nManage all processes and procedures involved in warehousing functions, including physical goods receiving, quality and quantity checking, system update and stock take, etc.\nDevelop strong supplier relationship to ensure reliable and quality sources at competitive prices are provided\nReview and enhance the existing purchasing and warehouse system\n\n\u00a0Job Requirements:\n\nDiploma or above (Major in Purchasing, Supply Chain Management or equivalent is preferred)\nAt least 2 years\u2019 working experience in purchasing & warehouse management\nStrong leadership, communication and negotiation skills\nGood command of spoken and written English and Chinese\nHardworking, initiative and able to work under pressure\nImmediate available is highly preferred\n\nInterested parties please send full resume (MS Word Format) with expected salary and date of availability via \"APPLY NOW\" or by post to: The Human Resources and Administration Department \u2013 Recruitment & Selection Section, Superpower Pumping Engineering Co., Ltd, 16/F, World Tech Centre, 95 How Ming Street, Kwun Tong, Kowloon. Please quote reference number on letter.\n\nWe are an Equal Opportunity Employer. Personal data will be kept strict confidence and used for recruitment-related purpose only.", "employment_types": ["Full Time", "Permanent"], "selling_points": ["Diploma or above", "At least 2 years\u2019 working experience in purchasing", "Monitor the overall inventory level"], "locations": ["Cheung Sha Wan"], "categories": ["Transportation & Logistics", "Others", "Inventory / Warehousing", "Supply Chain"], "post_time": "2022-01-17T09:19:51Z", "salary": {"currency": null, "max": null, "min": null, "period": "monthly", "term": null}, "salary_visible": false, "title_keywords": ["purchasing officer"], "responsibilities": ["warehousing", "inventory", "system update", "monitor", "replenishment", "procedures", "quality", "checking", "stock take", "develop", "review"], "requirements": {"degrees": ["diploma or above"], "majors": [], "languages": ["english", "chinese"], "language_level": ["good command"], "hard_skills": [], "soft_skills": ["communication", "negotiation skills", "leadership", "initiative", "hardworking", "work under pressure"], "languages_combined": [{"language": "english", "language_level": ["good command"]}, {"language": "chinese", "language_level": ["good command"]}]}, "experience_required": {"duration": ["at least 2 years"], "field": ["purchasing", "warehouse management"]}}, {"job_id": "100003009053503", "location_code": "hk", "company": "W&Y (Asia) Company Limited", "job_title": "\u4e2d\u6e2f\u516c\u53f8\u53f8\u6a5f \uff08\u4e03\u4eba\u8eca\uff09", "description": "\n\u8077\u8cac :\u8ca0\u8cac\u99d5\u99db\u8eca\u8f1b\u63a5\u9001\u8001\u95c6\u53ca\u516c\u53f8\u8cb4\u8cd3\u5ba2\u6236, \u6bcf\u5929\u4fdd\u6301\u8eca\u8f1b\u5167\u5916\u6e05\u6f54\uff0c\u7dad\u6301\u8eca\u8f1b\u7684\u4fdd\u990a, \u8ddf\u9032\u65e5\u5e38\u7dad\u4fee\u3001\u4fdd\u990a\u3001\u7e8c\u724c\u7b49\u4e8b\u5b9c, \u6709\u6642\u9700\u5f80\u4f86\u4e2d\u6e2f\u5169\u5730, \u65bc\u5c07\u8ecd\u6fb3\u6216\u8475\u6d8c\u53d6\u8eca\n\n\u8cc7\u6b77 :\u4e2d\u4e09\u7a0b\u5ea6; 5\u5e74\u7d93\u9a57; \u826f\u597d\u7cb5\u8a9e; \u4e00\u822c\u666e\u901a\u8a71; \u61c2\u8b80\u5beb\u4e2d\u6587; \u7565\u61c2\u8b80\u5beb\u82f1\u6587; \u6301\u6709\u5167\u5730\u99d5\u99db\u57f7\u7167; \u6301\u6709\u79c1\u5bb6\u8eca\u99d5\u99db\u57f7\u7167; \u51775\u5e74\u516c\u53f8\u53f8\u6a5f\u5de5\u4f5c\u7d93\u9a57\uff0c\u719f\u6089\u9999\u6e2f\u53ca\u5167\u5730\u9053\u8def\u548c\u4ea4\u901a\u689d\u4f8b\uff0c\u826f\u597d\u99d5\u99db\u7d00\u9304\u53ca\u614b\u5ea6\uff0c\u5c45\u65bc\u5c07\u8ecd\u6fb3\u5340\u512a\u5148\n\n\u5f85\u9047 :\u6bcf\u6708$18,000 - $24,000, \u6709\u9280\u884c\u5047\u671f \u53ca\u82b1\u7d05, \u661f\u671f\u4e00\u81f3\u4e94: \u4e0a\u53487\u6642\u81f3\u4e0b\u53487\u6642, \u6bcf\u9031\u5de5\u4f5c5\u5929, \u6bcf\u5929\u5de5\u4f5c 12 \u5c0f\u6642, \u9593\u4e2d\u9700\u8981\u8d85\u6642\u5de5\u4f5c\n\n\u7533\u8acb\u9808\u77e5 :\u6c42\u8077\u8005\u53ef\u81f4\u96fb92510374\u8207\u5fb7\u611b\u4f01\u696d(\u4e9e\u6d32)\u6709\u9650\u516c\u53f8\u5f35\u5973\u58eb\u806f\u7d61\u3002\n\n", "employment_types": ["Full Time"], "selling_points": [], "locations": ["Kwai Tsing Area"], "categories": ["Transportation & Logistics", "Others", "Private Transportation"], "post_time": "2022-01-17T07:04:26Z", "salary": {"currency": null, "max": null, "min": null, "period": "monthly", "term": null}, "salary_visible": false, "title_keywords": [], "responsibilities": [], "requirements": {"degrees": [], "majors": [], "languages": [], "language_level": [], "hard_skills": [], "soft_skills": [], "languages_combined": []}, "experience_required": {"duration": [], "field": []}}, {"job_id": "100003009052835", "location_code": "hk", "company": "Panasonic Hong Kong Co., Limited", "job_title": "Shipping Clerk/ Coordinator (Focus on Logistics)", "description": "Responsibilities:\n\nTo\u00a0handle shipping schedule and arrangement\nTo follow up on sales and purchase orders, shipment booking and scheduling\nTo co-ordinate and arrange with factories and overseas customer for end to end supply chain\nTo compile statistical figures for logistics process improvement\nTo assist in other ad-hoc assignments as required\n\nRequirements:\n\nHKCEE F.5 / DSE graduated or above\n1-2 years relevant logistics experience especially in China export arrangement\nPrevious exposures trading company or MNC are preferred\nProficient in MS Office and previous exposure in shipping software system is preferred\nGood command of written and spoken English and Chinese\nHave good communication, well organized and a fast learner\nWilling to provide ad hoc support\n\nRemuneration will be commensurate with qualification and experience. Interested parties, please send your application with detailed resume indicating both existing & expected salary and date of availability to us.\n\nWe are an equal opportunity employer. All information provided by applicants will be treated in strict confidence and used for recruitment purpose only.", "employment_types": ["Full Time", "Permanent"], "selling_points": ["Handle shipping schedule & shipment booking", "Exposure in trading company & export arrangement", "Stable MNC in-house environment"], "locations": ["Tsim Sha Tsui"], "categories": ["Transportation & Logistics", "Others", "Shipping", "Supply Chain"], "post_time": "2022-01-17T04:13:27Z", "salary": {"currency": null, "max": null, "min": null, "period": "monthly", "term": null}, "salary_visible": false, "title_keywords": ["logistics", "coordinator", "shipping clerk"], "responsibilities": ["shipping schedule", "ad-hoc assignments", "scheduling", "purchase", "logistics", "booking"], "requirements": {"degrees": ["dse"], "majors": [], "languages": ["english", "chinese"], "language_level": ["good command"], "hard_skills": ["ms office"], "soft_skills": ["communication", "fast learner", "well organized"], "languages_combined": [{"language": "english", "language_level": ["good command"]}, {"language": "chinese", "language_level": ["good command"]}]}, "experience_required": {"duration": ["1-2 years"], "field": ["logistics"]}}, {"job_id": "100003009052132", "location_code": "hk", "company": "", "job_title": "Shipping Officer / Senior Shipping Coordinator", "description": "We are a trading company.\u00a0 We invite you to be our Shipping Officer or Senior Shipping Coordinator.\nWe offer you 5 day's work, medical insurance, annual leave and 13th month salary.\u00a0\n\nJobs Description :\u00a0\n\nHandle full set of shipping documents independently\nResponsible for vendor payment\nManage each shipment delivery from factories to customer to ensure all required steps are done and goods are delivered in a timely and cost effective manner\nMaintain shipping records - shipment report for all shipments\nLiaise with suppliers, carriers, transportation company and vendors & check all applicable documentation is in place and fully compliance for Import / Export.\nPreparing weekly reports and keeping them up to date\nAd\u00a0 Ho project as assigned by management\n\nRequirements :\n\nF5 or above or equivalent level\nMinimum 1 - 5 years working exper5ience in shipping field\nGood experience in handling full sets of I/E documents, shipping bookings, SI, shipping arrangements with factories and forwarders\nProficient in both spoken and written in English and Mandarin\u00a0\nSelf motivated, responsible, well organized and able to work independently\nimmediately available will be advantage\nless experience will be consider as senior shipping co-ordinator\nInterested parties, please send your resume, with expected salary and availability\u00a0to our HR email ,\u00a0 or contact number 2330 1647..\nPersonal data collected will be used for recruitment purpose only.\nInterested candidates, please contact us at 23301647 for company details before applying.", "employment_types": ["Full Time"], "selling_points": [], "locations": ["Kowloon City Area"], "categories": ["Transportation & Logistics", "Others", "Shipping", "Supply Chain"], "post_time": "2022-01-17T07:34:09Z", "salary": {"currency": null, "max": null, "min": null, "period": "monthly", "term": null}, "salary_visible": false, "title_keywords": ["shipping coordinator", "shipping officer"], "responsibilities": [], "requirements": {"degrees": [], "majors": [], "languages": [], "language_level": [], "hard_skills": [], "soft_skills": [], "languages_combined": []}, "experience_required": {"duration": [], "field": []}}, {"job_id": "100003009055327", "location_code": "hk", "company": "Hongkong United Dockyards Ltd", "job_title": "Commercial Assistant", "description": "Job Duties:\n\nProvide support to the commercial team (documentation, report generation, research,\u00a0analysis)\nMonitor, tack and report on customer performance and market trend\nCoordinate with other departments on the execution of day-to-day commercial operations and activities\nCreate compelling and creative presentations including research, graphics, structure, ect.\nSupport the planning, organizing and implementing marketing materials and activities\nAny other ad-hoc projects or assignments as required\n\nJob Requirements:\n\nDiploma or above. An associate or Bachelor's Degree holder in Business Administration, Economics, Shipping & Logistics, Maritime related would be advantageous\n3 years' experience in sizable organization, preferred in maritime, shipping & logistics business\nGood knowledge in office applications such as MS Word, Excel, Project, PowerPoint and Outlook\nGood communication skills in both spoken and written English and Chinese(Cantonese and Mandarin)\nA good team player, self starter with ability to work independently\n\nWe Offer:\n\n\n5-day work week\nstable working hours\nfree shuttle bus\u00a0\nmedical coverage\nstaff canteen\n\nWork Location: Tsing Yi (Free shuttle bus service provided)\n\nWe offer a competitive pay and benefits package to the right candidate. Interested parties, please email your resume providing details of the present and expected salary to the Manager - Human Resources & Training by clicking 'Apply Now' on JobsDB.\n\nWe are an equal opportunity employer and welcome applications from all qualified candidates. Personal data collected will be treated in the strictest confidence and handled confidentially by authorized personnel for recruitment-related purposes only within the HUD Group. Applicants not having heard from us within six weeks of the date of application may consider their application unsuccessful. The personal data of unsuccessful applicants will be destroyed after the recruitment exercise pursuant to the requirements of the Personal Data (Privacy) Ordinance in Hong Kong.", "employment_types": ["Full Time", "Permanent"], "selling_points": [], "locations": ["Tsing Yi"], "categories": ["Transportation & Logistics", "Others", "Maritime - General"], "post_time": "2022-01-18T02:12:30Z", "salary": {"currency": null, "max": null, "min": null, "period": "monthly", "term": null}, "salary_visible": false, "title_keywords": ["assistant"], "responsibilities": ["graphics", "marketing materials", "provide support", "operations", "analysis", "monitor", "coordinate with", "presentations", "planning", "documentation", "ad-hoc projects", "report"], "requirements": {"degrees": ["bachelor", "diploma or above", "degree holder"], "majors": ["economics", "business administration"], "languages": ["english", "mandarin"], "language_level": ["good"], "hard_skills": ["excel", "office applications", "powerpoint", "outlook", "ms word"], "soft_skills": ["communication skills", "good team player", "work independently"], "languages_combined": [{"language": "english", "language_level": ["good"]}, {"language": "mandarin", "language_level": ["good"]}]}, "experience_required": {"duration": ["3 years"], "field": ["sizable organization", "business", "logistics"]}}, {"job_id": "100003009053890", "location_code": "hk", "company": "Lucy Sky Logistics Limited", "job_title": "\u8ca8\u6ac3\u8eca\u8abf\u6e21\u54e1**", "description": "\n\u8077\u8cac :\u8eca\u968a\u904b\u8f38\u8abf\u6e21\u8077\u8cac, \u5305\u62ec\u53f8\u6a5f\u7de8\u66f4, \u8eca\u8f1b\u8abf\u914d, \u5b89\u6392\u7dad\u4fee\u4fdd\u990a, \u6587\u4ef6\u8655\u7406\u53ca\u6578\u64da\u8f38\u5165, \u806f\u7e6b\u5ba2\u6236\u63a5\u6d3d\u958b\u8eca\u6578\u91cf, \u8655\u7406\u53f8\u6a5f\u5408\u7d04, \u6d3e\u767c\u53f8\u6a5f\u5de5\u8cc7\u53ca\u596c\u91d1, \u5c0d\u5728\u5de5\u4f5c\u4e2d\u53f8\u6a5f\u63d0\u4f9b\u5354\u52a9 (\u5de5\u4f5c\u7a4d\u6975\u4e3b\u52d5,\u6709\u5718\u968a\u5408\u4f5c\u7cbe\u795e,\u4ee5\u5ba2\u6236\u70ba\u5c0e\u5411)\n\n\u8cc7\u6b77 :\u4e2d\u4e09\u7a0b\u5ea6; 1\u5e74\u7d93\u9a57; \u826f\u597d\u7cb5\u8a9e; \u4e00\u822c\u82f1\u8a9e; \u61c2\u8b80\u5beb\u4e2d\u6587; \u61c2\u95b1\u8b80\u82f1\u6587; \u61c2MS Excel; \u51771\u5e74\u6216\u4ee5\u4e0a\u76f8\u95dc\u5de5\u4f5c\u7d93\u9a57,\u719f\u6089\u8ca8\u6ac3\u78bc\u982d\u64cd\u4f5c\u512a\u5148;\u826f\u597d\u786c\u4ef6\u8a08\u7b97\u6a5f\u6280\u5de7;\u826f\u597d\u6e9d\u901a\u6280\u5de7\n\n\u5f85\u9047 :\u6bcf\u6708$14,000 - $16,000, \u6709\u5e74\u7d42\u82b1\u7d05, \u4e0a\u53489\u6642\u81f3\u4e0b\u53487\u6642, \u6bcf\u9031\u5de5\u4f5c6\u5929,\u8f2a\u4f11, \u6bcf\u5929\u5de5\u4f5c 10 \u5c0f\u6642(\u80fd\u7368\u7acb\u53ca\u5728\u58d3\u529b\u4e0b\u5de5\u4f5c)\n\n\u7533\u8acb\u9808\u77e5 :\u6c42\u8077\u8005\u53ef\u81f4\u96fb92889953\u8207\u88d5\u5929\u7269\u6d41\u6709\u9650\u516c\u53f8\u5b8b\u5c0f\u59d0\u806f\u7d61\u3002\n\n", "employment_types": ["Full Time"], "selling_points": [], "locations": ["Kwai Tsing Area"], "categories": ["Transportation & Logistics", "Others"], "post_time": "2022-01-17T07:42:19Z", "salary": {"currency": null, "max": null, "min": null, "period": "monthly", "term": null}, "salary_visible": false, "title_keywords": [], "responsibilities": [], "requirements": {"degrees": [], "majors": [], "languages": [], "language_level": [], "hard_skills": ["excel"], "soft_skills": [], "languages_combined": []}, "experience_required": {"duration": [], "field": []}}, {"job_id": "100003009053702", "location_code": "hk", "company": "Kenstand Investments Limited", "job_title": "\u516c\u53f8\u517c\u5bb6\u5ead\u53f8\u6a5f (\u4e2d\u6e2f)", "description": "\n\u8077\u8cac :\u8ca0\u8cac\u63a5\u9001\u50f1\u4e3b\u3001\u8ca0\u8cac\u4eba\u4ee5\u53ca\u5176\u5bb6\u5ead\u6210\u54e1\u3001\u5ba2\u6236\u3001\u670b\u53cb\u53ca\u6307\u5b9a\u4eba\u54e1; \u6839\u64da\u50f1\u4e3b\u53ca\u4e0a\u53f8\u9700\u8981\u5b8c\u6210\u65e5\u5e38\u6587\u4ef6\u9001\u9054\u53ca\u4e8b\u52d9\u8655\u7406; \u59a5\u5584\u6253\u7406\u8eca\u8f1b, \u5982\u6709\u9700\u8981\u5fc5\u9808\u901a\u77e5\u50f1\u4e3b\u5b89\u6392\u8eca\u8f1b\u6aa2\u67e5\u7dad\u4fee, \u65bc\u99ac\u978d\u5c71\u53d6\u8eca, \u6709\u9700\u8981\u6642\u9700\u99d5\u99db\u5f80\u5ee3\u6771\u7701 (\u9858\u610f\u63a5\u53d7\u50f1\u4e3b/\u4e0a\u53f8\u6d3e\u9063\u5de5\u4f5c, \u914d\u5408\u6307\u793a\u6216\u898f\u7ae0\u5de5\u4f5c; \u9858\u610f\u63a5\u53d7\u52a0\u73ed\u5de5\u4f5c)\n\n\u8cc7\u6b77 :\u4e2d\u4e09\u7a0b\u5ea6; 3\u5e74\u7d93\u9a57; \u826f\u597d\u7cb5\u8a9e\u512a\u5148; \u826f\u597d\u666e\u901a\u8a71\u512a\u5148; \u4e00\u822c\u82f1\u8a9e; \u61c2\u8b80\u5beb\u4e2d\u6587; \u7565\u61c2\u8b80\u5beb\u82f1\u6587; \u6301\u6709\u5167\u5730\u99d5\u99db\u57f7\u7167; \u6301\u6709\u79c1\u5bb6\u8eca\u99d5\u99db\u57f7\u7167; \u6301\u6709\u826f\u597d\u99d5\u99db\u7d00\u9304; \u719f\u6089\u5168\u6e2f\u5404\u5340\u8857\u9053; \u8aa0\u5be6, \u6709\u79ae, \u5b88\u6642, \u5177\u8cac\u4efb\u5fc3\u53ca\u8010\u6027\n\n\u5f85\u9047 :\u6bcf\u6708$20,000, \u6709\u96d9\u7ce7, \u661f\u671f\u4e00\u81f3\u516d: \u4e0a\u534810\u6642\u81f3\u4e0b\u53488\u6642, \u6bcf\u9031\u5de5\u4f5c6\u5929, \u6bcf\u5929\u5de5\u4f5c 10 \u5c0f\u6642\n\n\u7533\u8acb\u9808\u77e5 :\u6c42\u8077\u8005\u53ef\u96fb\u90f5(Apply Now)\u5c65\u6b77\u8868\u7d66\u69ae\u6607\u6295\u8cc7\u6709\u9650\u516c\u53f8\u3002\u5982\u8981\u7d22\u53d6\u6536\u96c6\u500b\u4eba\u8cc7\u6599\u8072\u660e, \u8acb\u8207\u984f\u5c0f\u59d0(Email)\u806f\u7d61\u3002\n\n", "employment_types": ["Full Time"], "selling_points": [], "locations": ["Not Specified"], "categories": ["Transportation & Logistics", "Others", "Private Transportation", "Others", "Others"], "post_time": "2022-01-17T07:22:49Z", "salary": {"currency": null, "max": null, "min": null, "period": "monthly", "term": null}, "salary_visible": false, "title_keywords": [], "responsibilities": [], "requirements": {"degrees": [], "majors": [], "languages": [], "language_level": [], "hard_skills": [], "soft_skills": [], "languages_combined": []}, "experience_required": {"duration": [], "field": []}}, {"job_id": "100003009051551", "location_code": "hk", "company": "SF Supply Chain (Hong Kong) Limited", "job_title": "\u5009\u52d9\u54e1 (\u5143\u6717, \u65b0\u7530 / \u9022\u5409\u9109) (\u65e5\u73ed) (14K-18K)", "description": "SF Supply Chain\u662f\u9818\u5148\u7684\u4f9b\u61c9\u93c8\u670d\u52d9\u4f01\u696d\uff0c\u696d\u52d9\u8986\u84cb\u4e2d\u570b\u5927\u9678\u3001\u9999\u6e2f\u53ca\u6fb3\u9580\u3002\u7d50\u5408\u4e86\u9806\u8c50\u63a7\u80a1\u5728\u672c\u5730\u5e02\u5834\u7684\u8c50\u5bcc\u57fa\u790e\u8a2d\u65bd\u548c\u5ba2\u6236\u57fa\u790e\u53caDHL\u96c6\u5718\u9818\u5148\u7684\u4f9b\u61c9\u93c8\u7d93\u9a57\uff0cSF Supply Chain\u70ba\u8de8\u884c\u696d\u4f01\u696d\u5ba2\u6236\u63d0\u4f9b\u512a\u8cea\u4e00\u9ad4\u5316\u7684\u4f9b\u61c9\u93c8\u89e3\u6c7a\u65b9\u6848\u3002\n\n\n\n\u8077\u8cac\n\n\u65e5\u5f0f\u8d85\u5e02\u4e7e\u8ca8\u5009\u52d9\u5de5\u4f5c\n\u5de5\u4f5c\u5305\u62ec\u8ddf\u55ae\u6536\u8ca8\u3001\u57f7\u8ca8\u3001\u88dd\u7bb1\u3001\u4e0a/\u4e0b\u67b6\u53ca\u6574\u7406\u8ca8\u67b6\u7b49\n\u9700\u7d30\u5fc3\u6838\u5c0d\u8ca8\u55ae\u53ca\u8ca8\u54c1\n\u9700\u4f7f\u7528\u689d\u78bc\u69cd\u53ca\u5527\u8eca\n\u4fdd\u6301\u5009\u5eab\u6574\u6f54\n\u5b8c\u6210\u4e0a\u53f8\u5206\u914d\u7684\u5de5\u4f5c\n\n\u8981\u6c42\n\n\u4e2d\u4e09\u6216\u4ee5\u4e0a\u7a0b\u5ea6\n\u7121\u7d93\u9a57\u8005\u4ea6\u53ef\u7533\u8acb\n\u6709\u5009\u52d9\u6216\u7269\u6d41\u5de5\u4f5c\u7d93\u9a57\u8005\u512a\u5148\n\u61c2\u57fa\u672c\u4e2d\u82f1\u6587\u95b2\u8b80\u80fd\u529b\u4ee5\u53ca\u57fa\u672c\u96fb\u8166\u64cd\u4f5c\n\n\n\u5de5\u4f5c\u6642\u9593\n\n\u6bcf\u90316\u5929\u5de5\u4f5c\uff0c\u8f2a\u4f11\n09:00 \u2013 18:00\n\n\u00a0\u5de5\u4f5c\u5730\u9ede\n\n\u5143\u6717, \u65b0\u7530 / \u9022\u5409\u9109\n\u9022\u5409\u9109 : \u65bc\u5143\u6717\u897f\u9435\u7ad9\u65c1\u6709\u7a7f\u68ad\u5df4\u58eb\u63a5\u9001\n\u65b0\u7530: \u65bc\u5143\u6717\u958b\u5fc3\u5ee3\u5834\u4e5876\u5c08\u7dda\u5c0f\u5df4\u524d\u5f80\n\n\u00a0\u798f\u5229\u53ca\u85aa\u916c\n\n\u6708\u5165\u53ef\u9054 18K \u4ee5\u4e0a\n\u8d85\u6642\u5de5\u4f5c\u6d25\u8cbc\n12\u5929\u5e74\u5047\n\u751f\u65e5\u5047\n\u96d9\u7ce7\n\u914c\u60c5\u6027\u82b1\u7d05\n\u91ab\u7642\u798f\u5229\n\u4eba\u58fd\u4fdd\u96aa\n\u7259\u79d1\u4fdd\u96aa\n\u9280\u884c\u5047\u671f\n\n\u806f\u7d61\u65b9\u6cd5\n\nWhatsApp: 6740 5879 (\u8acb\u7559\u4e0b\u59d3\u540d\u53ca\u7533\u8acb\u8077\u4f4d)\n\u96fb\u8a71: 35075020 / 6740 5879 \u8207\u8607\u5148\u751f\u806f\u7d61\n\n\u61c9\u5fb5\u8005\u4e4b\u500b\u4eba\u8cc7\u6599\u53ea\u7528\u4f5c\u62db\u8058\u7528\u9014\u3002", "employment_types": ["Full Time"], "selling_points": [], "locations": ["Yuen Long"], "categories": ["Transportation & Logistics", "Others", "Inventory / Warehousing", "Supply Chain"], "post_time": "2022-01-16T10:22:23Z", "salary": {"currency": null, "max": null, "min": null, "period": "monthly", "term": null}, "salary_visible": false, "title_keywords": ["\u5009\u52d9\u54e1"], "responsibilities": [], "requirements": {"degrees": [], "majors": [], "languages": [], "language_level": [], "hard_skills": ["whatsapp"], "soft_skills": [], "languages_combined": []}, "experience_required": {"duration": [], "field": []}}, {"job_id": "100003009053937", "location_code": "hk", "company": "Shopline Limited", "job_title": "Logistics Account Manager", "description": "SHOPLINE is Asia\u2019s largest smart commerce platform. With our customers in mind, we strive to deliver scalable commerce solutions to merchants of all sizes. We\u2019re a full-featured platform with services including online store opening, O2O solution, retail POS systems, advertising placement, business strategy consultation, marketing, and more to empower merchants to succeed in omnichannel retailing and cross-border commerce.\n\nWHAT YOU'LL BE DOING:\n\nDevelops sales plans, strengthens customer relationships and insures market objectives are met.\nAttains or exceeds revenue targets.\nSchedules regular agent and customer visits.\nDevelops new customers, identifies customer needs and presents sales solutions.\nMaintains contact with existing customers to facilitate new sales and repeat contracting for existing business\nDevelops sales presentation and material consistent within business units.\nProvides competitor information to management.\nCollects prioritized product/service requirements and communicates them to Product team\n\nWHO WE ARE LOOKING FOR:\n\nBachelor\u2019s degree or equivalent;\n3+ years of comprehensive technical, direct sales and marketing experience for the E-commence Logistics sector\nConsultative selling experience.\nOutstanding presentation and communication skills.\nAbility to make complex decisions and customer commitments in real-time.\nAbility to build strong relationships with 3PL\nAbility to effectively promote the use of the company\u2019s technology with potential clients\nAbility to both develop and close opportunities\nStrong team player and experience working with all levels of the organization.\nWHY YOU SHOULD JOIN US:\n\n\nWe work in a fun, collaborative open space where we encourage creativity and ideas flow freely.\nYou\u2019ll be able to steer the future roadmap to improve our products, big or small, and see the results of your products reach our customers.\nGet to work with flexible working hours. Our priority is on getting the job done.\nFlat structure environment, you will be able to work independently and make your own choices.\nWe provide guidance and mentorship to polish your business skills and entrepreneurship mindset.\nWe are one of the standout tech startups in Hong Kong, targeting a huge opportunity in Asia.\nShopline is a part of the 500 Startups Accelerator and Incubated by Hong Kong Cyberport, giving us a massive network of advisors and resources globally", "employment_types": ["Full Time", "Permanent"], "selling_points": ["Work in a team to achieve assigned sales target", "Sales/Account management in Logistics field", "Attractive package and benefits"], "locations": ["Sheung Wan"], "categories": ["Transportation & Logistics", "Others", "Supply Chain"], "post_time": "2022-01-17T07:48:05Z", "salary": {"currency": null, "max": null, "min": null, "period": "monthly", "term": null}, "salary_visible": false, "title_keywords": ["logistics account manager"], "responsibilities": ["management", "advertising", "ideas", "schedules", "systems", "develop", "communication", "logistics", "contact", "sales plans", "contracting"], "requirements": {"degrees": ["degree", "bachelor"], "majors": [], "languages": [], "language_level": [], "hard_skills": ["small", "make", "fun", "pos"], "soft_skills": ["flexible", "communication skills", "work independently", "collaborative", "comprehensive", "team player", "presentation"], "languages_combined": []}, "experience_required": {"duration": ["3+ years"], "field": ["marketing", "logistics", "team"]}}, {"job_id": "100003009054989", "location_code": "hk", "company": "Asia Airfreight Terminal Co. Ltd.", "job_title": "Operations Analyst", "description": "Duties\n\n\nPrepare and coordinate new system development, related system change requirements by providing solution to and liaison with user department(s)\nParticipate, lead and manage projects involving process re-engineering, new product development and operations enhancement\nDevelop process improvement procedures and monitor operational performance\nPrepare procedure manual write up\n\nRequirements\n\n\nDegree in Logistics, Industrial Engineering, Operations Management, Transportation or other related disciplines\n3 years relevant experience of project management or process re-engineering management in logistics field\nProficient in MS Office (PowerPoint, Excel, Access and Visio)\nGood command of both written and spoken English and Chinese\nHighly self-motivated with good analytical, interpersonal, presentation and communication skills\nAble to work\u00a0independently and efficiently\u00a0\nCandidates with less academic background or working experience will also be considered\n\nWe offer the right incumbent attractive remuneration package including 13 days annual leave, 5-day week, double pay, performance bonus, medical scheme, life insurance, travel allowance and education subsidy.\u00a0\n\nInterested parties please send your full resume with reference no., recent and expected salary to: Human Resources Department, Asia Airfreight Terminal Co. Ltd., 10 Chun Ping Road, Hong Kong International Airport, Lantau, Hong Kong OR Fax to 2286 0374 OR Please click \u201cApply Now\u201d to submit your application.\n\nWe are an equal opportunity employer and welcome applications from all qualified candidates. We will not be responsible for any disclosure or the loss of personal data during transmission. All personal data collected will be used for recruitment only. Information of unsuccessful candidates will be destroyed after 3 months from the date of application.", "employment_types": ["Full Time", "Permanent"], "selling_points": ["13 days annual leave, 5-day week, double pay", "Prepare and coordinate new system development", "Able to work independently and efficiently"], "locations": ["Airport Area"], "categories": ["Transportation & Logistics", "Others", "Professional Services", "Business Analysis / Data Analysis", "Others", "Student / Fresh Graduate / No Experience"], "post_time": "2022-01-17T16:22:48Z", "salary": {"currency": null, "max": null, "min": null, "period": "monthly", "term": null}, "salary_visible": false, "title_keywords": ["operations analyst"], "responsibilities": ["operations", "procedures", "monitor", "develop", "coordinate", "manage projects", "re-engineering"], "requirements": {"degrees": ["degree"], "majors": ["related disciplines", "engineering"], "languages": ["english", "chinese"], "language_level": ["good command"], "hard_skills": ["excel", "scheme", "powerpoint", "project management", "ms office"], "soft_skills": ["communication skills", "self-motivated", "work independently", "project management", "interpersonal", "presentation"], "languages_combined": [{"language": "english", "language_level": ["good command"]}, {"language": "chinese", "language_level": ["good command"]}]}, "experience_required": {"duration": ["3 years"], "field": ["management", "engineering", "project management", "logistics", "relevant experience"]}}, {"job_id": "100003009055827", "location_code": "hk", "company": "Page Personnel", "job_title": "Assistant Logistics Manager - EU Buying Office", "description": "Excellent opportunity for Logistics experts to work for an EU Retailer.\n\nClient Details\n\nOur client is a leading retailer in the consumer retail industry with over decades of history. With significant business expansion in their local business, they are currently looking to recruit an Assistant Logistics Manager to support future operations.\n\nDescription\n\nWork closely with HQ, Countries, and Freight Forwarders to ensure all shipment bookings are made accurately and timely\nCoordinate with vendors and forwarders to prepare required shipping documents according to Countries instruction\nProvide shipment solutions to Countries according to situation and incoterms\nMonitor stocks level to ensure supply is sufficient for global countries\nBuild Corrective Action Plan for suppliers and internal parties to reduce operational cost and lead time\nAssist in ad-hoc duties as per assigned\n\nProfile\n\n7 years of working experience in trading, buying office, manufacturing, forwarders\nStrong analytical skills with numerical sense\nOrganized and detail-oriented individual\nExcellent command in both English and Chinese\n\nJob Offer\n\nCompetitive pay\n5-day work\nMedical", "employment_types": ["Full Time", "Permanent"], "selling_points": ["Freight forwarder management", "FOB/FCA shipment", "Attractive package"], "locations": ["Kowloon Bay"], "categories": ["Transportation & Logistics", "Others", "Freight Forwarding", "Shipping"], "post_time": "2022-01-18T02:59:22Z", "salary": {"currency": null, "max": null, "min": null, "period": "monthly", "term": null}, "salary_visible": false, "title_keywords": ["logistics manager", "assistant"], "responsibilities": ["shipping documents", "cost", "operations", "monitor", "coordinate with", "logistics", "plan", "ad-hoc duties", "internal parties"], "requirements": {"degrees": [], "majors": [], "languages": ["english", "chinese"], "language_level": ["excellent"], "hard_skills": ["bookings", "analytical skills"], "soft_skills": ["organized", "timely", "detail-oriented", "analytical skills", "ad-hoc duties"], "languages_combined": [{"language": "english", "language_level": ["excellent"]}, {"language": "chinese", "language_level": ["excellent"]}]}, "experience_required": {"duration": ["7 years"], "field": ["manufacturing", "trading"]}}, {"job_id": "100003009055829", "location_code": "hk", "company": "Chong Hing Bank Ltd", "job_title": "\u53f8\u6a5f Driver", "description": "\u8077\u4f4d\u8981\u6c42:\n\n\u6700\u5c115\u5e74\u99d5\u99db\u623f\u8eca\u6216\u4e03\u4eba\u8eca\u7d93\u9a57\uff0c\u4e26\u66fe\u4efb\u516c\u53f8/ \u79c1\u4eba\u53f8\u6a5f ;\n\u826f\u597d\u99d5\u99db\u8a18\u9304\u53ca\u614b\u5ea6\uff0c\u7121\u4e0d\u826f\u55dc\u597d ;\n\u8aa0\u5be6\u6709\u79ae\u3001\u5b88\u6642\u53ca\u8cac\u4efb\u611f ;\n\u9808\u6301\u6709\u6548\u4e2d\u6e2f\u79c1\u5bb6\u8eca\u99d5\u99db\u57f7\u7167\uff0c\u719f\u6089\u9999\u6e2f\u53ca\u570b\u5167\u9053\u8def\u548c\u4ea4\u901a\u689d\u4f8b ;\n\u8b80\u5beb\u7c21\u55ae\u4e2d\u3001\u82f1\u6587; \u7565\u61c2\u666e\u901a\u8a71 ;\n\u6709\u9700\u8981\u6642\u9858\u610f\u8d85\u6642\u5de5\u4f5c\n\n\u5de5\u4f5c\u5167\u5bb9:\n\n\u8ca0\u8cac\u63a5\u8f09\u516c\u53f8\u7ba1\u7406\u5c64\u3001\u9ad8\u7d1a\u884c\u653f\u4eba\u54e1\u53ca\u6307\u5b9a\u4eba\u58eb ;\n\u78ba\u4fdd\u516c\u53f8\u8eca\u8f1b\u6e05\u6f54\u3001\u8ddf\u9032\u7dad\u4fee\u4fdd\u990a\u3001\u9a57\u8eca\u53ca\u8eca\u8f1b\u7e8c\u724c\u4e8b\u5b9c ;\n\u57f7\u884c\u5176\u4ed6\u81e8\u6642\u59d4\u6d3e\u7684\u4efb\u52d9 ;\n\u6309\u5de5\u4f5c\u9700\u8981\u99d5\u99db\u5f80\u4f86\u4e2d\u6e2f\u5169\u5730 ;\n\u51fa\u8eca\u5730\u9ede: \u4e2d\u74b0\n\n\u5de5\u4f5c\u6642\u9593:\n\n\u6bcf\u9031\u5de5\u4f5c\u516d\u5929\u3001\u9808\u8f2a\u4f11\u3001\u6bcf\u5929\u5de5\u4f5c\u7d0410\u5c0f\u6642 ;\n\u56e0\u61c9\u5de5\u4f5c\u5b89\u6392\uff0c\u5076\u723e\u9700\u65bc\u5047\u65e5\u5de5\u4f5c\u6216\u9700\u8d85\u6642\u5de5\u4f5c\n\n\u9280\u884c\u798f\u5229:\n\n\u9280\u884c\u5047\u671f\u3001\u91ab\u7642(\u542b\u5bb6\u5c6c)\u3001\u7259\u91ab\u6d25\u8cbc\u3001\u8868\u73fe\u82b1\u7d05\u3001\u5176\u4ed6\u9280\u884c\u798f\u5229\n\n\u6309 APPLY NOW\u7533\u8acb", "employment_types": ["Full Time"], "selling_points": ["\u6700\u5c115\u5e74\u99d5\u99db\u623f\u8eca\u6216\u4e03\u4eba\u8eca\u7d93\u9a57", "\u826f\u597d\u99d5\u99db\u8a18\u9304\u53ca\u614b\u5ea6", "\u8ca0\u8cac\u63a5\u8f09\u516c\u53f8\u7ba1\u7406\u5c64"], "locations": ["Central"], "categories": ["Transportation & Logistics", "Others", "Private Transportation"], "post_time": "2022-01-18T02:59:32Z", "salary": {"currency": null, "max": null, "min": null, "period": "monthly", "term": null}, "salary_visible": false, "title_keywords": ["driver"], "responsibilities": [], "requirements": {"degrees": [], "majors": [], "languages": [], "language_level": [], "hard_skills": [], "soft_skills": [], "languages_combined": []}, "experience_required": {"duration": [], "field": []}}, {"job_id": "100003009056290", "location_code": "hk", "company": "ConnectedGroup Limited", "job_title": "Logistics Specialist (US Sourcing office)", "description": "Our client is an US leading company for apparel who is now looking for a Logistics Specialist to join their growing team in HK.\n\nResponsibilities:\n\nResponsible for shipment scheduling and container consolidation\nCoordinates with factories, merchandisers and logistics vendor for order delivery\nProvides solutions in logistics issue and exception\nMonitor service provider's performance and KPI to ensure service standard and cost efficiency\nProvide customer service to internal and external stakeholder, act as an information centre for shipping status\nHandle logistics inquiries regarding shipment issues, carrier services and procedures\nProvide solution with internal teams with any customs related delays\nIdentify cost saving opportunities to minimize freight\nImplement process improvement and review result\nPerform ad hoc data collection and basic analysis as needed\n\nRequirements:\n\nBachelor degree preferred\nAt least 4 years of experience in logistics operation, preferrably for EU and US market\nProficient computer skills MS Office, experience in Excel Vlookup and Pivot Table is a big plus.\nStrong interpersonal and communication skill\nStrong analytical thinking and problem solving skills\nAble to provide solution independently\nFluent in spoken and written Chinese (Mandarin / Cantonese) and English", "employment_types": ["Full Time", "Permanent"], "selling_points": ["US market focused", "Forwarder/ 3PL for EU & US market welcomed", "Double pay + Bonus; 5 day; Medical"], "locations": ["Not Specified"], "categories": ["Transportation & Logistics", "Others", "Shipping", "Supply Chain"], "post_time": "2022-01-18T03:51:22Z", "salary": {"currency": null, "max": null, "min": null, "period": "monthly", "term": null}, "salary_visible": false, "title_keywords": ["logistics specialist"], "responsibilities": ["provide customer service", "cost", "shipping", "ad hoc", "service standard", "analysis", "review", "monitor", "procedures", "teams", "scheduling", "logistics", "data collection"], "requirements": {"degrees": ["degree", "bachelor"], "majors": [], "languages": ["cantonese", "english", "chinese", "mandarin"], "language_level": ["fluent"], "hard_skills": ["excel", "plus", "pivot table", "problem solving skills", "computer skills", "vlookup", "ms office"], "soft_skills": ["problem solving skills", "communication skill", "interpersonal", "independently"], "languages_combined": [{"language": "cantonese", "language_level": ["fluent"]}, {"language": "english", "language_level": ["fluent"]}, {"language": "chinese", "language_level": ["fluent"]}, {"language": "mandarin", "language_level": ["fluent"]}]}, "experience_required": {"duration": ["at least 4 years"], "field": ["operation", "logistics"]}}, {"job_id": "100003009052090", "location_code": "hk", "company": "DKSH Hong Kong Limited", "job_title": "Assistant, Sales Order Processing, FMCG", "description": "Job Descriptions:\n\nResponsible for Sales Order Processing and provide sales administrative support to Sales Operations Team\nMaintain and update sales data and ensure all data is recorded in the system timely and accurately\nWork with internal departments for order related & AR issues\nRequirements:\n\nHigher diploma or above\n1 year of working experience is preferred\nFamiliar in using MS Excel, Word\nGood command of written and spoken English and Chinese\nFresh graduate will be considered\nWorking location: Wong Chuk Hang\n\nWe offer performance bonus and attractive benefits including medical insurance to the right candidate.\u00a0 Interested parties please apply in full resume with current and expected salaries to Human Resources Department, DKSH Hong Kong Limited, 23rd Floor, Tower A, Southmark, 11 Yip Hing Street, Wong Chuk Hang, Hong Kong.\n\nAll personal data collected will be used for recruitment purposes only. Candidates will be contacted within 2 weeks if the background and experience are closely relevant to the job requirement.\n\n\nDrive Growth. Be the Difference. Join DKSH.\n\nDKSH\u2019s strength lies in our great diversity of services, industries, clients, products, regions and employees from various nationalities. We are proud of our people: they are the reason we are successful. Our people are the best in the industry. They are passionate about their career growth and about business success. They work as part of an energetic and committed team, positively impacting millions of lives through the products and services we provide.\n\nJoin us today if you are ready to\u00a0\u201cDrive growth. Be the Difference.\u201d\u00a0With DKSH, you will experience a world of learning and development, own your career and take business responsibility and have a positive impact that touches people\u2019s lives.", "employment_types": ["Full Time", "Permanent"], "selling_points": ["Responsible for Sales Order Processing", "Maintain & update data at system", "Work with internal parties for orders issues"], "locations": ["Aberdeen"], "categories": ["Transportation & Logistics", "Others", "Sales, CS & Business Devpt", "Others", "Sales Administration"], "post_time": "2022-01-17T02:04:45Z", "salary": {"currency": null, "max": null, "min": null, "period": "monthly", "term": null}, "salary_visible": false, "title_keywords": ["sales", "assistant"], "responsibilities": ["ar", "data", "operations", "sales administrative support", "maintain", "sales order processing"], "requirements": {"degrees": ["higher diploma or above", "fresh graduate"], "majors": [], "languages": ["english", "chinese"], "language_level": ["good command"], "hard_skills": ["ms excel", "word"], "soft_skills": [], "languages_combined": [{"language": "english", "language_level": ["good command"]}, {"language": "chinese", "language_level": ["good command"]}]}, "experience_required": {"duration": ["1 year"], "field": []}}, {"job_id": "100003009052088", "location_code": "hk", "company": "IEWC SouthEast Asia Limited", "job_title": "Warehouse Supervisor (5 days work)", "description": "IEWC Southeast Asia Limited\n\nShek Mun Area\n\nResponsibilities:\n\nWarehouse Operation (Daily)\n\nTo lead a team of storekeepers to manage daily warehouse operation, including inbound, outbound, inventory management and system transaction.\nTo ensure the daily tasks finished on time by proper manpower and resource planning.\nArrange shipments and handle import/export shipping documents.\nCoordinate with warehouse, forwarders, customers for shipment arrangement\nTo handle the daily email\u00a0communication and maintain good working \u00a0\u00a0relationship with customer service.\nTo prepare regular reports for management review\u00a0\nTo participate warehouse improvement project.\n\nSupplies, Equipment and Plant\n\nEnsure that adequate supplies, materials and parts are on hand to keep the departments operating smoothly.\nEnsure the performance of minor maintenance and repairs on equipment within their designated department.\n\nQuality Assurance\n\nMaintain compliance with our Quality Standards\nUnderstand and ensure Company compliance with UL and C S A product requirements. \u00b7\n\nCustomer Service\n\nWork with all Company departments to ensure customer satisfaction and new opportunities for business and product growth.\n\nSafety\n\nMaintain a safe and secure work environment.\nEnsure safety policies are properly applied and enforced.\n\n\u00a0Requirements:\n\nF.5\u00a0or above\nAt least\u00a03\u00a0years' solid experience in warehouse operation.\nAble to handle email communication in both English and Chinese.\nSelf-motivated and a good team player.\nGood people management skill.\nGood communication and leadership skills.\nImmediately available is highly preferable.", "employment_types": ["Full Time"], "selling_points": [], "locations": ["Shatin Area"], "categories": ["Transportation & Logistics", "Others", "Inventory / Warehousing", "Supply Chain"], "post_time": "2022-01-17T02:04:05Z", "salary": {"currency": null, "max": null, "min": null, "period": "monthly", "term": null}, "salary_visible": false, "title_keywords": ["warehouse supervisor"], "responsibilities": ["shipping documents", "shipment arrangement", "maintenance", "policies", "review", "coordinate with", "quality", "compliance", "inventory management", "lead a team", "communication", "maintain", "customer service", "regular reports for management", "planning"], "requirements": {"degrees": [], "majors": [], "languages": ["english", "chinese"], "language_level": [], "hard_skills": [], "soft_skills": ["communication", "good team player", "self-motivated", "leadership skills"], "languages_combined": [{"language": "english", "language_level": []}, {"language": "chinese", "language_level": []}]}, "experience_required": {"duration": ["at least 3 years"], "field": ["operation"]}}, {"job_id": "100003009055347", "location_code": "hk", "company": "ZIM Integrated Shipping Services Ltd", "job_title": "Claims Deputy Manager", "description": "Key Responsibilities\n\nManage enquiries from agencies and customers in a professional manner\nHandle accident involved and follow up with all related ports and concerned parties for immediate remedial actions\nExamine title of claimant and correspond with overseas agents and claimants to obtain documentary evidence\nAnalyze information gathered from investigation and surveyors\u2019 findings and recommendations\nCollect relevant evidences for substantiating involvement of 3rd party liability\nMonitor unclaimed cargo and compile monthly report to headquarter, and analyze the data for further follow up with local agencies\nOther matter related to claims handling and marine casualties/events, including data management in the system, contracts reviewing, etc.\n\nWho we are looking for\n\n5+ years of experience in claims & insurance with good knowledge in liner shipping industry\nUniversity degree or above in Logistics industry / Shipping / Insurance or Management\nGood command of spoken and written English and Mandarin\nProficient in computer skills (MS Word, Excel & PowerPoint and Chinese word processing)\nA good team player with excellent communication and interpersonal skills\nCandidates with less experience but having high potential would be also considered\n\nWe offer\n\nExcellent opportunities for advancement with regional exposure\nCompetitive salary package\n5-Days Work\n18 - 20 days Annual Leave\nDouble Pay\nPerformance Bonus\nMedical & Dental Insurance\nLife Insurance\nBirthday Gifts\nMarriage Leave\nPaternity Leave\nWork from home arrangement\n\nInterested parties please share with us your latest resume showing current and expected remuneration package.", "employment_types": ["Full Time", "Permanent"], "selling_points": ["Claims handling, marine casualties / events", "Excellent opportunities for advancement", "Work from home arrangement"], "locations": ["Kwun Tong"], "categories": ["Transportation & Logistics", "Others", "Insurance", "Claims Officer"], "post_time": "2022-01-18T02:24:34Z", "salary": {"currency": null, "max": null, "min": null, "period": "monthly", "term": null}, "salary_visible": false, "title_keywords": ["deputy manager"], "responsibilities": ["management", "shipping", "data", "contracts", "monitor", "professional manner", "investigation", "communication", "logistics", "monthly report", "insurance"], "requirements": {"degrees": ["degree or above"], "majors": ["insurance"], "languages": ["english", "chinese", "mandarin"], "language_level": ["good command", "proficient"], "hard_skills": ["excel", "data management", "chinese word processing", "powerpoint", "computer skills", "ms word"], "soft_skills": ["good team player", "communication and interpersonal skills"], "languages_combined": [{"language": "english", "language_level": ["good command"]}, {"language": "chinese", "language_level": ["proficient"]}, {"language": "mandarin", "language_level": ["good command"]}]}, "experience_required": {"duration": ["5+ years"], "field": ["insurance", "shipping industry"]}}, {"job_id": "100003009055372", "location_code": "hk", "company": "Ocean Park Corporation", "job_title": "\u7269\u6d41\u53f8\u6a5f (Logistics Operator) (\u6c34\u4e0a\u6a02\u5712)", "description": "(\u9577\u671f\u5408\u7d04\uff0c\u8868\u73fe\u826f\u597d\u53ef\u7372\u7e8c\u7d04,\u00a0\u6708\u85aa$16,000-$18,000)\n\u5de5\u4f5c\u6027\u8cea- \u8ca0\u8cac\u904b\u9001\u8ca8\u7269/\u98df\u54c1\u5230\u6307\u5b9a\u5730\u9ede\uff0c\u4e26\u5c07\u5df2\u7528\u5668\u6750\u53ca\u7528\u5177\u904b\u56de\u8ca8\u5009\n- \u5354\u52a9\u4e0a\u843d\u8ca8\uff0c\u5c07\u5378\u4e0b\u7684\u8ca8\u7269\u642c\u904b\u81f3\u76ee\u7684\u5730\n- \u4fdd\u6301\u8ca8\u8eca\u6e05\u6f54\n\u5de5\u4f5c\u8981\u6c42- \u5177\u4e09\u5e74\u99d5\u99db\u516c\u53f8\u8ca8\u8eca\u7d93\u9a57\u53ca\u6301\u67091\u30012\u865f\u99d5\u99db\u57f7\u7167\n- \u80fd\u8aaa\u6d41\u5229\u5ee3\u6771\u8a71\u53ca\u4e00\u822c\u82f1\u8a9e\n\n\u61c9\u5fb5\u8005\u53ef\u5f9e\u4ee5\u4e0b\u65b9\u6cd5\u767b\u5165\u6d77\u6d0b\u516c\u5712\u7db2\u9801\u7533\u8acb\u6b64\u8077\u4f4d\uff0chttp://careers.oceanpark.com.hk >>\u00a0\u8077\u4f4d\u7a7a\u7f3a>>\u9577\u671f/\u5168\u8077\uff0c\u4ea6\u53ef\u5c07\u5c65\u6b77\u51fd\u5bc4\u9999\u6e2f\u4ed4\u6d77\u6d0b\u516c\u5712\u4eba\u529b\u8cc7\u6e90\u90e8\u6216\u50b3\u771f\u81f32553 0777\n\n\u5982\u5c0d\u4ee5\u4e0a\u8077\u4f4d\u6709\u4efb\u4f55\u67e5\u8a62,\u6b61\u8fce\u65bc\u8fa6\u516c\u6642\u9593\u5167WhatsApp 5208 3805\u3002\n\n\u61c9\u5fb5\u8005\u5982\u5728\u516d\u661f\u671f\u5167\u672a\u7372\u9080\u8acb\u9762\u8a66\uff0c\u5c07\u4f5c\u843d\u9078\u8ad6\u3002\u6240\u6709\u6536\u96c6\u8cc7\u6599\u53ea\u4f5c\u62db\u8058\u7528\u9014\u3002", "employment_types": ["Full Time", "Contract"], "selling_points": ["\u99d5\u99db\u57f7\u7167", "\u8ca8\u8eca\u7d93\u9a57", "\u904b\u9001\u8ca8\u7269/\u98df\u54c1"], "locations": ["Aberdeen"], "categories": ["Transportation & Logistics", "Others", "Inventory / Warehousing", "Private Transportation"], "post_time": "2022-01-18T02:22:06Z", "salary": {"currency": null, "max": null, "min": null, "period": "monthly", "term": null}, "salary_visible": false, "title_keywords": ["operator", "logistics"], "responsibilities": [], "requirements": {"degrees": [], "majors": [], "languages": [], "language_level": [], "hard_skills": [], "soft_skills": [], "languages_combined": []}, "experience_required": {"duration": [], "field": []}}, {"job_id": "100003009053624", "location_code": "hk", "company": "Gotendo Beauty and Healthcare Group Limited", "job_title": "\u552e\u8ca8\u54e1/\u5e97\u52d9\u54e1(\u5316\u599d/\u7f8e\u5bb9/\u4fdd\u5065)", "description": "\n\u8077\u8cac :\u8ca0\u8cac\u5e97\u8216\u65e5\u5e38\u904b\u4f5c, \u5305\u62ec\u6536\u9280\u3001\u7406\u8ca8\u3001\u92b7\u552e\u8ca8\u54c1\u3001\u63a5\u5f85\u53ca\u89e3\u7b54\u9867\u5ba2\u67e5\u8a62\u7b49, \u5354\u52a9\u5e97\u8216\u71df\u904b\u53ca\u5b58\u8ca8\u76e4\u9ede\n\n\u8cc7\u6b77 :\u6c92\u6709\u5b78\u6b77\u8981\u6c42; \u826f\u597d\u7cb5\u8a9e; \u4e00\u822c\u666e\u901a\u8a71; \u61c2\u8b80\u5beb\u4e2d\u6587; \u6709\u8cac\u4efb\u5fc3, \u53ef\u5373\u6642\u4e0a\u73ed\u512a\u5148\n\n\u5f85\u9047 :\u6bcf\u6708$12,000\u6216\u4ee5\u4e0a, \u6709\u52e4\u5de5\u734e, \u71df\u696d\u734e\u91d1\u53ca\u5e74\u7d42\u734e\u91d1, \u4e0a\u534811\u6642\u81f3\u4e0b\u53488\u6642, \u6bcf\u9031\u5de5\u4f5c6\u5929, \u8f2a\u4f11, \u6bcf\u5929\u5de5\u4f5c 9 \u5c0f\u6642\n\n\u7533\u8acb\u9808\u77e5 :\u6c42\u8077\u8005\u53ef\u81f4\u96fb28891317\u8207\u5fa1\u6bbf\u5802\u85e5\u599d\u6709\u9650\u516c\u53f8\u85cd\u5c0f\u59d0\u806f\u7d61\u3002\n\n", "employment_types": ["Full Time"], "selling_points": [], "locations": ["Kwun Tong"], "categories": ["Transportation & Logistics", "Others", "Inventory / Warehousing", "Supply Chain"], "post_time": "2022-01-17T07:15:36Z", "salary": {"currency": null, "max": null, "min": null, "period": "monthly", "term": null}, "salary_visible": false, "title_keywords": ["\u552e\u8ca8\u54e1"], "responsibilities": [], "requirements": {"degrees": [], "majors": [], "languages": [], "language_level": [], "hard_skills": [], "soft_skills": [], "languages_combined": []}, "experience_required": {"duration": [], "field": []}}, {"job_id": "100003009052931", "location_code": "hk", "company": "Shipco Transport (HK) Ltd", "job_title": "PNL Specialists", "description": "Day-to-day operations to check and verify the freight invoices correctness\nCommunicate (e.g. E-mail) with overseas agent / back office to clarify the freight invoices\nManage, assist for import and export department to allocate the freight cost\nAd-hoc duty as needed\nRequirements\nDSE or above with at least 2 years relevant operations experience in sea freight forwarding company\nPreferred candidates with hands on experience on operations\nFair English and Mandarin\nLearning Opportunity\nCommunication skills with overseas offices, agents and internal department\nTransshipment costing between import & export department\nInterested parties please send full resume with employment history and expected salary to Mr Lee by clicking \"Apply Now\"\u00a0for internal review.", "employment_types": ["Full Time", "Permanent"], "selling_points": ["Manage, assist for import and export department", "DSE or above", "At least 2 years relevant operations experience"], "locations": ["Not Specified"], "categories": ["Transportation & Logistics", "Others", "Freight Forwarding", "Shipping"], "post_time": "2022-01-17T04:34:50Z", "salary": {"currency": null, "max": null, "min": null, "period": "monthly", "term": null}, "salary_visible": false, "title_keywords": [], "responsibilities": ["ad-hoc", "cost", "invoices", "sea freight", "operations", "day-to-day operations", "back office", "communication"], "requirements": {"degrees": ["dse"], "majors": [], "languages": ["english", "mandarin"], "language_level": [], "hard_skills": ["import and export"], "soft_skills": ["communication skills", "hands on", "learning"], "languages_combined": [{"language": "english", "language_level": []}, {"language": "mandarin", "language_level": []}]}, "experience_required": {"duration": ["at least 2 years"], "field": []}}, {"job_id": "100003009052899", "location_code": "hk", "company": "Fly King Transportation Company Ltd", "job_title": "\u8ca8\u904b\u7ad9\u4e3b\u7ba1\u57f9\u8a13\u751f (Supervisor Trainee)", "description": "\u8077\u8cac\n\n\u76e3\u7763\u53ca\u5e36\u9818\u52a9\u7406\u7ba1\u7406\u54e1\uff0c\u57f7\u52e4\u8077\u52d9\n\u78ba\u4fdd\u670d\u52d9\u5728\u627f\u8afe\u7bc4\u570d\u5167\u5b8c\u6210\u5de5\u4f5c\n\u78ba\u4fdd\u53ca\u7dad\u6301\u7a7a\u904b\u7ad9\u5167\u904b\u4f5c\u66a2\u9806\n\u5354\u52a9\u5009\u5167\u5916\u65e5\u5e38\u5de5\u4f5c\n\n\u5165\u8077\u8981\u6c42\n\n\u5b8c\u6210\u4e2d\u5b78\u6703\u8003/\u4e2d\u5b78\u6587\u6191\u8a66(DSE)\u6216\u540c\u7b49\u5b78\u6b77\n\u80fd\u95b1\u8b80\u53ca\u66f8\u5beb\u4e2d\u3001\u82f1\u6587\n\u6210\u719f\uff0c\u81ea\u4fe1\uff0c\u6709\u826f\u597d\u6e9d\u901a\u6280\u5de7\u53ca\u80fd\u627f\u53d7\u5de5\u4f5c\u58d3\u529b\n\u6709\u76f8\u95dc\u5de5\u4f5c\u7d93\u9a57\u6216\u5009\u52d9\u5de5\u4f5c\u7d93\u9a57\u8005\uff0c\u512a\u5148\u8003\u616e\n\n\u85aa\u916c\n\n\u57f9\u8a13\u671f\u6708\u5165\u53ef\u9054\u6e2f\u5e63$16,000 (\u5305\u62ec\u5e95\u85aa\u9023\u6d25\u8cbc\u798f\u5229)\n\u5b8c\u6210\u57f9\u8a13\u5f8c\u6708\u5165\u53ef\u9054\u6e2f\u5e63$18,000 (\u5305\u62ec\u5e95\u85aa\u9023\u6d25\u8cbc\u798f\u5229)\n\n\u798f\u5229\n\n\u5e74\u5047\u3001\u52de\u5de5\u5047\n\u5e74\u7d42\u914c\u60c5\u82b1\u7d05\n\u51fa\u52e4\u734e\u91d1\u6bcf\u6708$1,000\n\u8d85\u6642\u52a0\u73ed\u6d25\u8cbc\u6bcf\u5c0f\u6642$84\n\u901a\u5bb5\u73ed\u6d25\u8cbc\u6bcf\u65e5$50\n\u91ab\u7642\u6d25\u8cbc\u6bcf\u6708$180\n\u5176\u4ed6\u6d25\u8cbc (\u51cc\u6668\u4ea4\u901a\u3001\u98b1\u98a8)\n\u512a\u60e0\u63a5\u99c1\u8eca\u670d\u52d9\n\u5728\u8077\u57f9\u8a13\n\u826f\u597d\u6649\u5347\u6a5f\u6703\n\n\u5de5\u4f5c\u6642\u9593\n\n\u9700\u4e8c\u5341\u56db\u5c0f\u6642\u8f2a\u73ed\u5de5\u4f5c\uff0c\u8f2a\u4f11\n\u6bcf\u9031\u5de5\u4f5c\u516d\u5929\uff0c\u6bcf\u5929\u5de5\u4f5c\u4e5d\u5c0f\u6642\n\n\u5de5\u4f5c\u5730\u9ede\n\n\u8d64\u9c72\u89d2\u570b\u6cf0\u822a\u7a7a\u8ca8\u904b\u7ad9\n\n\u7533\u8acb\u8005\u8acb\u6309\"Apply Now\"\u63d0\u4f9b\u500b\u4eba\u5c65\u6b77\u9023\u540c\u85aa\u91d1\u8981\u6c42\u53ca\u53ef\u5230\u8077\u65e5\u671f\u3002\n\n\u7533\u8acb\u4eba\u6240\u63d0\u4f9b\u7684\u500b\u4eba\u8cc7\u6599\u526f\u672c\u5c07\u56b4\u683c\u6309\u7167\u50f1\u4e3b\u7684\u500b\u4eba\u8cc7\u6599\u653f\u7b56\u4f7f\u7528\u3002", "employment_types": ["Full Time"], "selling_points": [], "locations": ["Airport Area"], "categories": ["Transportation & Logistics", "Others", "Inventory / Warehousing", "Private Transportation"], "post_time": "2022-01-17T04:28:21Z", "salary": {"currency": null, "max": null, "min": null, "period": "monthly", "term": null}, "salary_visible": false, "title_keywords": ["supervisor", "trainee"], "responsibilities": [], "requirements": {"degrees": [], "majors": [], "languages": [], "language_level": [], "hard_skills": [], "soft_skills": [], "languages_combined": []}, "experience_required": {"duration": [], "field": []}}, {"job_id": "100003009056688", "location_code": "hk", "company": "Bay Blue (Hongkong) Trading Co., Limited", "job_title": "Warehouse Manager/ Manageress \u5009\u52d9\u7d93\u7406", "description": "\u5730\u5340 :\u6c99\u7530\n\u8077\u8cac :\u8ca0\u8cac\u5009\u5eab\u7684\u65e5\u5e38\u904b\u71df, \u5009\u5eab\u5de5\u4f5c\u7684\u57f7\u884c\u548c\u76e3\u7763(\u5305\u62ec\u63a5\u6536, \u8a02\u8cfc, \u5378\u8f09)\u5eab\u5b58\u8a18\u9304; \u76e3\u7763\u5009\u5eab\u64cd\u4f5c, \u5009\u5132\u548c\u51fa\u5eab, \u904b\u8f38, \u5009\u5eab\u548c\u5eab\u5b58\u63a7\u5236, \u5206\u985e, \u5b58\u5132, \u5305\u88dd, \u5408\u7406\u5206\u914d\u7269\u6d41\u548c\u904b\u8f38\u4ee5\u53ca\u65e5\u5e38\u6587\u6a94\u64cd\u4f5c; \u8ca0\u8cac\u5009\u5eab\u6578\u64da\u7d71\u8a08, \u5009\u5eab\u904b\u71df\u6210\u672c\u548c\u904b\u8f38\u6210\u672c\u6838\u7b97; \u78ba\u4fdd\u4ea4\u8ca8\u6642\u9593, \u5408\u7406\u7684\u8ca8\u7269\u5b58\u5132, 6S\u7ba1\u7406\u6a19\u6e96\n\u8cc7\u6b77 :\u5c08\u4e0a\u6559\u80b2\uff1a\u6587\u6191/\u8b49\u66f8; 3\u5e74\u7d93\u9a57; \u826f\u597d\u7cb5\u8a9e; \u826f\u597d\u666e\u901a\u8a71; \u826f\u597d\u82f1\u8a9e; \u61c2\u8b80\u5beb\u4e2d\u6587; \u61c2\u8b80\u5beb\u82f1\u6587\n\u5f85\u9047 :\u6bcf\u6708$25,000 - $35,000, \u6709\u9280\u884c\u5047\u671f, \u914c\u60c5\u6027\u82b1\u7d05\u53ca\u8d85\u6642\u5de5\u4f5c\u6d25\u8cbc, \u661f\u671f\u4e00\u81f3\u516d: \u4e0a\u53489\u6642\u81f3\u4e0b\u53486\u6642, \u6bcf\u9031\u5de5\u4f5c5\u5929\u81f36\u5929, \u6bcf\u5929\u5de5\u4f5c 8 \u5c0f\u6642, \u661f\u671f\u516d\u9577\u77ed\u9031\n\u7533\u8acb\u9808\u77e5 :\u6c42\u8077\u8005\u53ef\u96fb\u90f5\u5c65\u6b77\u8868\u7d66\u7063\u85cd(\u9999\u6e2f)\u8cbf\u6613\u6709\u9650\u516c\u53f8\u3002\u5982\u8981\u7d22\u53d6\u6536\u96c6\u500b\u4eba\u8cc7\u6599\u8072\u660e, \u8acb\u8207\u6b50\u5c0f\u59d0(Tel:59393656)\u806f\u7d61\u3002", "employment_types": ["Full Time"], "selling_points": ["\u8ca0\u8cac\u5009\u5eab\u7684\u65e5\u5e38\u904b\u71df, \u5009\u5eab\u5de5\u4f5c\u7684\u57f7\u884c\u548c\u76e3\u7763", "\u6587\u6191/\u8b49\u66f8; 3\u5e74\u7d93\u9a57; \u826f\u597d\u7cb5\u8a9e; \u826f\u597d\u666e\u901a\u8a71", "\u6bcf\u6708$25,000 - $35,000, \u6709\u9280\u884c\u5047\u671f, \u914c\u60c5\u6027\u82b1\u7d05\u53ca\u8d85\u6642\u5de5\u4f5c\u6d25\u8cbc"], "locations": ["Shatin Area"], "categories": ["Transportation & Logistics", "Others", "Inventory / Warehousing", "Supply Chain"], "post_time": "2022-01-18T05:46:01Z", "salary": {"currency": null, "max": null, "min": null, "period": "monthly", "term": null}, "salary_visible": false, "title_keywords": ["warehouse manager", "\u5009\u52d9\u7d93\u7406"], "responsibilities": [], "requirements": {"degrees": [], "majors": [], "languages": [], "language_level": [], "hard_skills": [], "soft_skills": [], "languages_combined": []}, "experience_required": {"duration": [], "field": []}}, {"job_id": "100003009052800", "location_code": "hk", "company": "Lalamove", "job_title": "Corporate Operations Associate", "description": "Lalamove is disrupting the logistics industry by connecting customers and drivers directly through our technology. We offer customers a lightning fast and convenient way to book delivery and moving services whether they are at their home, at work or on the go. People talk about O2O, we live it!\u00a0\n\n\n\n\nOur strength lies in our internal values, namely Passion in serving local communities, empowering SMEs and our driver partners, Execution and Grit because that is how we differentiate ourselves by never giving up and striving for excellence, and Humility - awareness in ourselves to learn from others and never stop improving.\n\n\n\n\nAt Lalamove, we strongly believe in the power of community. Millions of drivers and customers use our technology every day to connect with one another and move things that matter. Delivery is what we do best and we ensure it is always fast and simple. Since 2013, we have tackled the logistics industry head on to find the most innovative solutions for the world\u2019s delivery needs.\u00a0\n\n\n\n\nOur vision is to bring communities closer and make city life easier by allowing fast and convenient circulation of goods. We realize this vision with a \u2018glocal\u2019 approach, building a robust operations team to adapt our product to local networks of businesses and delivery contractors. At the same time, we have ambition to build an international brand by establishing\u00a0 an even more global presence.\u00a0\n\nWhat you'll do:\nDaily client communication with customers to arrange and monitor daily delivery schedules and order volumes to ensure sufficient driver supply, follow up on ad hoc requests.\u00a0\nManage drivers to achieve the highest standard of customer experience and adherence to agreed SOPs and SLAs.\nAssist in Planning, coordinating and implementing different driver motivation and retention campaigns to improve drivers\u2019 loyalty and lifetime value\nSolving daily delivery issues in a most effective and cost-efficient manner, with prompt resolution of customer complaints.\nPrepare monthly delivery statements and invoices to clients, and handle drivers\u2019 payments.\nGather relevant feedback from drivers and customer operations to share with relevant teams for continuous product and service improvement.\nSupport the implementation of new SOPs and product enhancements with customers and drivers in conjunction with other stakeholders.\nWhat we seek:\n\nUniversity degree holder in business or related disciplines\u00a0\nAt least 1 - 2 years in sales and marketing or an operational role with front-facing experience, preferably in a logistics/e-commerce fulfilment environment\nSelf-motivated, passionate, a good team player with positive and a can-do working attitude\nStrong communication skills with proficiency in written and spoken English and Chinese\nProficient in MS Word, Powerpoint and Excel\nLocal travel to customer sites and with drivers performing deliveries will be required. Strong sense of responsibility and detail-oriented with high level of accuracy\nShifts may be required for working during weekends", "employment_types": ["Full Time", "Permanent"], "selling_points": ["5 working days per week", "Medical Plan", "Dental Plan"], "locations": ["Lai Chi Kok"], "categories": ["Transportation & Logistics", "Others", "Sales, CS & Business Devpt", "Account Servicing", "Channel / Distribution"], "post_time": "2022-01-17T04:06:31Z", "salary": {"currency": null, "max": null, "min": null, "period": "monthly", "term": null}, "salary_visible": false, "title_keywords": ["corporate operations associate"], "responsibilities": ["logistics"], "requirements": {"degrees": [], "majors": [], "languages": [], "language_level": [], "hard_skills": [], "soft_skills": [], "languages_combined": []}, "experience_required": {"duration": [], "field": []}}, {"job_id": "100003009056888", "location_code": "hk", "company": "International Automobiles Limited - trading as Swire Motors", "job_title": "Parts Assistant \u96f6\u4ef6\u52a9\u7406", "description": "Responsibilities\n\nPreparing parts quotation, negotiate price with local suppliers\nFollow-up delivery of back-ordered items\nHandle customer inquiries and complaints\nMaintain warehouse condition and responsible for monthly stock take\n\nRequirements\n\nForm 5 or above\n3 years relevant experience, preferably in automotive parts\nPleasant, energetic, and customer-oriented\nGood communication skills in both written and spoken English and Chinese, Mandarin is an advantage\nProficient in MS Office applications\n\nWorking Location: Fanling / Lau Fu Shan\n\nWe offer competitive remuneration package with a wide range of fringe benefits including\n\nIncentive\nDiscretionary Bonus\nComprehensive Medical Coverage\nStaff Shopping Discount\nNon-contributory Retirement Benefits Scheme\n14-week Maternity Leave\nPaternity Leave\n\nWe offer competitive package to the right candidate. Qualified and interested parties please send your full resume by Email or clicking APPLY NOW below. Only short-listed candidates will be contacted.\n\nWe are an equal opportunity employer. All applications received will be used exclusively for selection purpose and handled confidentially by authorized personnel only. Your application may also be considered for other suitable positions within the Swire group. (Please indicate clearly on your application if you would not like to be considered for other positions within the group.) Unsuccessful applications will be destroyed after an appropriate time.", "employment_types": ["Full Time", "Permanent"], "selling_points": ["Preparing parts quotation", "Form 5 or above", "3 years relevant experience"], "locations": ["Others"], "categories": ["Transportation & Logistics", "Others", "Sales, CS & Business Devpt", "Customer Service - Supervisor / Officer", "Retail Sales"], "post_time": "2022-01-18T06:41:43Z", "salary": {"currency": null, "max": null, "min": null, "period": "monthly", "term": null}, "salary_visible": false, "title_keywords": ["assistant"], "responsibilities": ["maintain", "inquiries and complaints", "quotation", "stock take"], "requirements": {"degrees": ["form 5 or above"], "majors": [], "languages": ["english", "chinese", "mandarin"], "language_level": ["advantage", "good"], "hard_skills": ["ms office"], "soft_skills": ["communication skills", "customer-oriented", "energetic", "pleasant"], "languages_combined": [{"language": "english", "language_level": ["good"]}, {"language": "chinese", "language_level": ["good"]}, {"language": "mandarin", "language_level": ["advantage", "good"]}]}, "experience_required": {"duration": ["3 years"], "field": ["relevant experience"]}}, {"job_id": "100003009049614", "location_code": "hk", "company": "Source Well Co Ltd", "job_title": "\u5168\u8077\u5009\u52d9\u54e1**", "description": "A Little About Us\u00a0\n\nIt's an amazing time to be working at\u00a0Li & Fung, especially for Supply Chain Solutions. We are a big enough company to have the ability to execute large-scale deliverables, and small enough that you will play an important role in that\u00a0delivery.\u00a0\u00a0\n\nWe\u00a0are currently looking for\u00a0a Full-time Assistant Manager / Senior Officer - Operations to join our team in Hong Kong.\n\nAbout this role\u2026\n\nSupport business operations and drive continuous improvement in sourcing, merchandising, quality management and compliance\nPrepare business analytics reports, dashboard and presentations with insights and recommendations\nCreate, communicate, and maintain Standard Operating Procedure (SOP) in various aspects of business operations and supplier management\nSupport business manager to identify process improvement opportunities and drive implementation of new processes to enable operations excellence\nSupport business manager to manage projects, monitor project activities and track progress, and coordinate with internal and external stakeholders to resolve issues and achieve project objectives\n\n\u00a0You might be a good fit if you have \u2026\n\nBachelor's degree in business, finance, statistics, engineering or information technology\n3-5 years work experience preferably in sourcing, merchandising, quality management, supply chain, or operations (candidate with less experience but have knowledge of Tableau will also be considered)\nStrong skills in MS Excel and MS Power Point, Knowledge of Tableau is a strong advantage\nExcellent communicator in English, Cantonese and Mandarin is an advantage\nDetail-oriented, well organized, excellent communication skills and data-driven mindset\n\nPerks you will entitled...\n\nCompetitive salary with 13th month salary plus performance bonus\nHealth, dental, life and personal accident insurances\nPaid days off + festival early leave + volunteer leave\nNumerous sample sales and staff discount offer\n\n\n\nIf this sounds like you, Apply Now!\n\nIt\u2019s alright if this is not what you are looking for! You can also join us on LF Talent Network by clicking HERE . We will contact you when the right job opportunity comes up!\n\nAbout Li & FungAs new technologies disrupt the way consumers and businesses interact, Li & Fung is reimagining and creating supply chains for the future. Through our innovative products and end-to-end supply chain solutions, we aim to expand the realm of what\u2019s possible and create more value for more players along the supply chain. With our entrepreneurial spirit, we are using digital technologies to speed collaboration, drive innovation and enhance sustainability. We are dedicated to changing how the world works, and making life better for people everywhere.\nAs an equal opportunity employer, we shall consider all applicants regardless of gender, age, religion, marital status, race, sexual orientation, disability, disease, pregnancy, or trade union and/or political affiliation, and disregard all factors deemed inappropriate by local law and the International Labor Organization\u2019s Declaration on Fundamental Principles and Rights at Work.", "employment_types": ["Full Time"], "selling_points": [], "locations": ["Wong Tai Sin Area"], "categories": ["Transportation & Logistics", "Others", "Inventory / Warehousing", "Supply Chain"], "post_time": "2022-01-14T08:58:19Z", "salary": {"currency": null, "max": null, "min": null, "period": "monthly", "term": null}, "salary_visible": false, "title_keywords": ["\u5168\u8077\u5009\u52d9\u54e1"], "responsibilities": ["management", "data", "operations", "compliance", "merchandising", "quality", "presentations", "implementation", "monitor", "coordinate with", "communication", "maintain", "reports", "manage projects", "contact", "insurances"], "requirements": {"degrees": ["degree", "bachelor"], "majors": ["engineering", "finance", "statistics", "information technology", "business"], "languages": ["cantonese", "english", "mandarin"], "language_level": ["advantage", "excellent"], "hard_skills": ["small", "plus", "tableau", "presentations", "ms excel", "power point"], "soft_skills": ["communication skills", "well organized", "detail-oriented", "communicator", "innovative", "driven"], "languages_combined": [{"language": "cantonese", "language_level": ["advantage", "excellent"]}, {"language": "english", "language_level": ["advantage", "excellent"]}, {"language": "mandarin", "language_level": ["advantage", "excellent"]}]}, "experience_required": {"duration": ["3-5 years"], "field": ["supply chain", "merchandising", "quality management"]}}, {"job_id": "100003009051603", "location_code": "hk", "company": "A.S. Watson Industries", "job_title": "Distribution Manager", "description": "Major Responsibilities: \u00a0\u00a0\n\nThis incumbent will be reporting to the Air Operations Manager and the prime responsibilities will include but not limited to :\n\nHandle full set of Air Export documentation and operation.\nOversee the air export documentation, cargo planning, and other operational related tasks;\nLiaise and build strong relationships with airlines, co-loaders and warehouses;\nCommunicate with CS and sales teams to attain a smooth operations process;\nEnsure shipments and documentation are handed over to terminal timely and accurately;\nEnsure pre-alert are sent to overseas offices and agents timely;\nResponsible for customers\u2019 enquiries and its correspondence;\nResponsible for SOA mapping and credit control on monthly basis;\n\n\u00a0Desired Skills and Experience:\n\nF.5 / DSE or above; \u00a0\n3-5 years\u2019 air export experience in freight forwarding industry; \u00a0\nResponsible, independent and strong personal motivation;\nProficient in PC skills and MS Office; \u00a0\nRequired to work on shift (Day / Noon / Night shift duty) and Alternate Saturday (9am to 6pm) \u2013 Roster to be assigned by the Manager;", "employment_types": ["Full Time"], "selling_points": ["Supervise day-to-day distribution operations", "Lead the tender process", "3PL management and logistics operations"], "locations": ["Tai Po Area"], "categories": ["Transportation & Logistics", "Others", "Inventory / Warehousing", "Supply Chain"], "post_time": "2022-01-16T14:18:19Z", "salary": {"currency": null, "max": null, "min": null, "period": "monthly", "term": null}, "salary_visible": false, "title_keywords": ["manager"], "responsibilities": ["liaise", "reporting", "communicate with", "control", "operations", "teams", "documentation", "planning"], "requirements": {"degrees": ["dse"], "majors": [], "languages": [], "language_level": [], "hard_skills": ["documentation", "pc skills", "airlines", "ms office"], "soft_skills": ["timely", "independent", "responsible", "smooth"], "languages_combined": []}, "experience_required": {"duration": ["3-5 years"], "field": []}}, {"job_id": "100003009053150", "location_code": "hk", "company": "Fly King Transportation Company Ltd", "job_title": "Operation Manager", "description": "Role and Responsibility:\nPlan, organize and manage daily operations\nEvaluate and review the existing warehouse operations\nImplement and execute the standard procedures and policies\nSupport management to meet operational target\nResponsible for operational reporting for management review\nResponsible for daily resources allocation and manpower arrangement\nFollow up the operations irregularities and preclude recurrence\nParticipate in training staff when required\nMotivate subordinate for task accomplishment\nContinuous review on quality in operation and pursue improvement\nProvide an appropriate service standard to our customer\nApply Qualifications:\nDiploma or above in logistic or relevant disciplines is highly recommended\n8 years working experience with 3 years at supervisory level in warehouse\nSolid experience in airlines, air cargo terminal, warehouse or freight forwarding company is preferable.\nGood command of spoken and written Chinese and English.\nGood leadership, planning, organization and decision-making skills.\nPerform shift duty including overnight shift is necessary.", "employment_types": ["Full Time", "Permanent"], "selling_points": [], "locations": ["Airport Area"], "categories": ["Transportation & Logistics", "Others", "Freight Forwarding", "Inventory / Warehousing"], "post_time": "2022-01-17T06:08:20Z", "salary": {"currency": null, "max": null, "min": null, "period": "monthly", "term": null}, "salary_visible": false, "title_keywords": ["operation manager"], "responsibilities": ["reporting", "management", "irregularities", "service standard", "policies", "operations", "review", "procedures", "quality", "evaluate", "plan", "warehouse operations", "manage daily operations", "management review", "planning"], "requirements": {"degrees": ["diploma or above"], "majors": [], "languages": ["english", "chinese"], "language_level": ["good command"], "hard_skills": ["airlines"], "soft_skills": ["leadership", "responsible"], "languages_combined": [{"language": "english", "language_level": ["good command"]}, {"language": "chinese", "language_level": ["good command"]}]}, "experience_required": {"duration": ["3 years", "8 years"], "field": ["supervisory level"]}}, {"job_id": "100003009048957", "location_code": "hk", "company": "AA Choice Personnel Consultancy Limited", "job_title": "Shipping Clerk / Coordinator ( 5 days work plus double pay)", "description": "Requirement:\nHKCEE / DSE\u00a0or above\nAt least 2-3 years solid experience in shipping\u00a0\nGood command of English & Chinese (both Cantonese & Mandarin)\nJob Duties:\nHandle full set of I/E shipping & L/C banking documents\u00a0\nHandle enquiries and requests from internal and external customers and prepare quotations.\nPrepare shipping documents and other operations related documents (invoices, reports) as required.\n\n\n\nIf any inquiries, please contact\u00a0Ms Yip at 2838 8603\n\nOr send your resume in\u00a0WORD\u00a0format, stating current, expected salary and availability and clicking APPLY NOW.", "employment_types": ["Full Time", "Permanent"], "selling_points": ["5 days work", "Double Pay; + Dis Bonus +\uff2dedical", "Location:T.S.T / HK Island"], "locations": ["Tsim Sha Tsui"], "categories": ["Transportation & Logistics", "Others", "Documentary Credit / Bills Processing", "Shipping"], "post_time": "2022-01-14T07:47:41Z", "salary": {"currency": null, "max": null, "min": null, "period": "monthly", "term": null}, "salary_visible": false, "title_keywords": ["coordinator", "shipping clerk"], "responsibilities": ["shipping documents", "internal and external customers", "shipping", "invoices", "related documents", "operations", "handle enquiries", "reports", "contact", "banking"], "requirements": {"degrees": ["dse"], "majors": [], "languages": ["cantonese", "english", "chinese", "mandarin"], "language_level": ["good command"], "hard_skills": [], "soft_skills": [], "languages_combined": [{"language": "cantonese", "language_level": ["good command"]}, {"language": "english", "language_level": ["good command"]}, {"language": "chinese", "language_level": ["good command"]}, {"language": "mandarin", "language_level": ["good command"]}]}, "experience_required": {"duration": ["at least 2-3 years"], "field": []}}, {"job_id": "100003009045489", "location_code": "hk", "company": "DCH Logistics Co Ltd", "job_title": "Clerk  (Ref: LOG-CLK-LFS)", "description": "The incumbent will be responsible for handling customers\u2019 enquires, following up the delivery orders, stock inventory and providing clerical support in Operation.\n\nThe ideal candidate should be:\n\nForm 5 or above;\nAt least 2 years\u2019 relevant experience, preferred in logistics industry;\nProficiency in MS Office application, including Chinese word processing;\nGood communication skills, willing to learn & able to work independently;\nWorking location will be Yuen Long Lau Fau Shan\nImmediately available is highly preferred.\n\n\n\n\u00a0We offer competitive salary, monthly incentive, medical insurance, life and personal accident insurance, annual leave and staff purchase discount to the successful candidate.\u00a0\u00a0\n\nWe are equal opportunities employer. Applicants who are not invited within 2 months may consider their application unsuccessful. All applicants may be considered for other suitable positions with DCH Group / CITIC Pacific Group and will be deleted from our files after 6 months from the date of application.", "employment_types": ["Full Time", "Permanent"], "selling_points": [], "locations": ["Yuen Long"], "categories": ["Transportation & Logistics", "Others", "Inventory / Warehousing"], "post_time": "2022-01-13T07:56:46Z", "salary": {"currency": null, "max": null, "min": null, "period": "monthly", "term": null}, "salary_visible": false, "title_keywords": ["clerk"], "responsibilities": ["inventory", "clerical support", "communication", "purchase", "logistics", "insurance"], "requirements": {"degrees": ["form 5 or above"], "majors": [], "languages": ["chinese"], "language_level": ["proficiency"], "hard_skills": ["chinese word processing", "ms office"], "soft_skills": ["communication skills", "work independently", "responsible", "willing to learn", "ideal"], "languages_combined": [{"language": "chinese", "language_level": ["proficiency"]}]}, "experience_required": {"duration": ["at least 2 years"], "field": ["logistics industry", "relevant experience"]}}, {"job_id": "100003009046903", "location_code": "hk", "company": "John Swire & Sons (HK) Limited", "job_title": "Archive Assistant", "description": "A highly-diversified and global corporation, the Swire Group\u2019s businesses encompass property, aviation, beverages and food chain, as well as marine services and trading & industrial activities. Its core businesses are mainly focused in Asia, with its key operations in Hong Kong and the Chinese Mainland. Within Asia, Swire's activities come under the Group's publicly quoted arm, Swire Pacific Limited, which is the major shareholder in two Hong Kong listed companies: Swire Properties and Cathay Pacific Airways.\n\nJohn Swire & Sons (H.K.) Limited is the holding company of the publicly-listed conglomerate, Swire Pacific Ltd. Our Swire Archives Department is now inviting candidates to apply for the following position:\n\nArchive Assistant\n\nResponsibilities:\n\nSupport the Swire Archives collections management programme, including accessioning and cataloguing of archives in line with international standards\nSupport the location management system, and access and retrieval systems\nUndertake preservation tasks including preservation rehousing, and basic conservation for the archive collections\nEngage in digitization and scanning of archives\nConduct historical research in the archive collections\nRespond to enquirers and users internally and externally\nSupervise and facilitate onsite users in conducting research in archives\nOccasionally support Swire Archives outreach, communication and promotion of its services\nRequirements:\n\n\nBachelor\u2019s degree holder, with at least 1-2 years\u2019 relevant experience in archives or other related fields\nPost-graduate qualification in Archives & Records Management would be an advantage\nExperience of historical research using archives\nExperience in cataloguing and description and using collections management software\nPrepared to occasionally lift and move heavy boxes\nProficient command of verbal and written Chinese and English, proficiency in Putonghua is preferred\n\nApplication:\nAt Swire, we are committed to creating an inclusive and supportive working environment for all our people regardless of their age, gender, gender identity, sexual orientation, relationship, family status, disability, race, ethnicity, nationality, religious or political beliefs. We believe in creating an environment where people feel comfortable at work and are able to realise their full potential.\n\nWe offer a competitive package to the right candidate. If you meet the qualifications and are interested in this position, you can send your application by clicking \u2018Apply Now\u2019. We will contact all shortlisted candidates.\n\nThe Swire group is an equal opportunity employer. All applications will be used exclusively for selection purposes and handled confidentially by authorised personnel only. Your application may also be considered for other suitable positions within the Swire group (please indicate clearly on your application if you would not like to be considered for other positions within the group.) Following the data privacy ordinance, all unsuccessful applications will be destroyed after an appropriate time.", "employment_types": ["Full Time", "Permanent"], "selling_points": ["Bachelor\u2019s degree holder with 1 years\u2019 experience", "Experience of historical research using archives", "Knowledge of collections management software"], "locations": ["Quarry Bay"], "categories": ["Transportation & Logistics", "Others", "Education", "Librarian", "Inventory / Warehousing"], "post_time": "2022-01-14T01:40:44Z", "salary": {"currency": null, "max": null, "min": null, "period": null, "term": null}, "salary_visible": false, "title_keywords": ["assistant"], "responsibilities": ["scanning", "management", "systems", "communication"], "requirements": {"degrees": ["bachelor", "degree holder"], "majors": [], "languages": ["putonghua", "english", "chinese"], "language_level": ["proficiency", "proficient"], "hard_skills": [], "soft_skills": ["committed", "supportive"], "languages_combined": [{"language": "putonghua", "language_level": ["proficiency", "proficient"]}, {"language": "english", "language_level": ["proficient"]}, {"language": "chinese", "language_level": ["proficiency", "proficient"]}]}, "experience_required": {"duration": ["at least 1-2 years"], "field": ["related", "management", "research", "relevant experience"]}}, {"job_id": "100003009052127", "location_code": "hk", "company": "OOCL Logistics Ltd", "job_title": "Business Analyst, Import & Export (Ref: AMSO/OPLUS/OLL)", "description": "Through participation in business projects and on-the-job training, the potential candidate shall gain experience and broaden the global perspectives in logistics business.\u00a0\n\n\u00a0Responsibilities:\u00a0\n\n\nDrive and promote\u202fcompliance\u202fwith\u00a0Government\u00a0rules and regulations in\u00a0NVOCC\u00a0operations\nMonitor\u00a0changes\u00a0in\u00a0NVOCC Customs Filing requirements\u00a0& regulations\u00a0and adapt\u00a0it in\u00a0processes\u00a0and\u00a0systems\n\nFormulate guidelines for internal compliance\u00a0and implement guidelines in business operations\n\nGuide\u00a0team\u00a0and train relevant parties on rules, processes and systems\n\nOrganize and house-keep Import/Export business\u00a0licenses\n\nLiaise with\u00a0agent\u00a0on handling\u00a0shipments and\u00a0to\u00a0ensure\u00a0smooth operation\n\nRequirements:\u00a0\n\n\nBachelor\u2019s Degree in Business Administration\u00a0or related disciplines\n2 years of experience in logistics or freight forwarding industry\n\nStrong analytical and problem-solving skills\nWell-organized and detail-minded\nProficient with MS Office and advanced functions of Excel\nExcellent spoken and written English and Chinese, proficiency in Mandarin will be an advantage\nPromising\u00a0candidate with less experience would be considered\u00a0as Officer\n\nInterested parties, please submit your application letter together with detailed resume and copies of your latest transcript\u00a0by clicking \u201cApply Now\u201d.\n\n(Data collected will be used for recruitment purpose only.)", "employment_types": ["Full Time", "Permanent"], "selling_points": ["Ensure rules and regulations compliance", "2 years\u2019 relevant work experience", "Degree holder (Fresh Graduates also welcome)"], "locations": ["Kwun Tong"], "categories": ["Transportation & Logistics", "Others", "Freight Forwarding", "Shipping"], "post_time": "2022-01-17T02:11:09Z", "salary": {"currency": null, "max": null, "min": null, "period": "monthly", "term": null}, "salary_visible": false, "title_keywords": ["business analyst"], "responsibilities": ["regulations", "guidelines", "operations", "compliance", "monitor", "systems", "liaise with"], "requirements": {"degrees": ["degree", "bachelor"], "majors": ["related disciplines", "business administration"], "languages": ["english", "chinese", "mandarin"], "language_level": ["advantage", "excellent", "proficiency"], "hard_skills": ["problem-solving skills", "excel", "ms office"], "soft_skills": ["detail-minded", "problem-solving skills", "well-organized", "advanced"], "languages_combined": [{"language": "english", "language_level": ["advantage", "excellent"]}, {"language": "chinese", "language_level": ["advantage", "excellent"]}, {"language": "mandarin", "language_level": ["proficiency", "advantage", "excellent"]}]}, "experience_required": {"duration": ["2 years"], "field": ["logistics"]}}, {"job_id": "100003009051024", "location_code": "hk", "company": "HARVEY NICHOLS (HONG KONG) LIMITED", "job_title": "Senior Logistics Officer", "description": "Responsibilities:\n\n\nOrder process and upload PO into MIS system;\nFollow up and ensure shipping schedule to meet the department target;\nPrepare full set of order processing and shipment report;\nAssist buying team on order status and coordinate with the sales team on the delivery requests;\nCommunicate with the internal department for arranging order instruction/payment request form and coordinating with the overseas vendors for the shipment schedule;\nMonitor the order processing with the operation and ensure shipment on schedule;\nEstablish a good leadership with the internal team and well relationship with the internal department for the day to day operation and reporting\nReview\u00a0operation regularly and recommend\u00a0improvement\u00a0and action plan\nSupervise team members to support daily distribution/operations.\n\nRequirements:\u00a0\n\n\nBachelor Degree/\u00a0High Diploma in Logistics, Supply Chain Management, or a related disciplines;\nMinimum 3 years experience in order processing field;\nEnergetic, motivated, full of initiative, shipping and logistics'\u00a0knowledge is required and able to work independently and under pressure;\n\nGood command of both spoken and written English and Chinese;\nProficient in Microsoft Office (e.g. Excel is a must);\nGood command of interpersonal and communication skills;\nCandidate with more experience will be considered as Logistics Supervisor.\u00a0\nWe offer excellent career prospects, competitive salary and fringe benefits to the right candidate.\u00a0 Please apply in strict confidence by sending\u00a0personal resume together with salary expected and date available\n\nby email to:\u00a0h r d _ h n @ h a r v e y n i c h o l s . c o m . h k\nWe are an equal opportunity employer and welcome applications from all qualified candidates. Personal data provided by\u00a0 job applicants will be used strictly in accordance with our personal data policy and for recruitment purposes only. Candidates not notified within eight weeks may consider their application unsuccessful. All related information will be kept in our file for up to 24 months. A copy of our Personal Information Collection Statement will be provided upon request by contacting our Human Resources Division.", "employment_types": ["Full Time", "Permanent"], "selling_points": ["Follow up and ensure shipment on schedule", "Coordinating with the overseas vendors", "Min.3 years\u2019 exp., good in English + excel skill"], "locations": ["Yau Tsim Mong Area"], "categories": ["Transportation & Logistics", "Others", "Documentary Credit / Bills Processing", "Shipping"], "post_time": "2022-01-15T01:16:48Z", "salary": {"currency": null, "max": null, "min": null, "period": "monthly", "term": null}, "salary_visible": false, "title_keywords": ["senior logistics officer"], "responsibilities": ["shipping schedule", "communicate with", "reporting", "operations", "review", "coordinate with", "monitor", "supervise team members", "payment", "sales team", "schedule", "order processing", "plan", "report"], "requirements": {"degrees": ["high diploma", "degree", "bachelor"], "majors": ["related disciplines"], "languages": ["english", "chinese"], "language_level": ["good command"], "hard_skills": ["excel", "order processing", "microsoft office"], "soft_skills": ["communication skills", "work independently", "under pressure", "interpersonal", "motivated", "energetic", "initiative"], "languages_combined": [{"language": "english", "language_level": ["good command"]}, {"language": "chinese", "language_level": ["good command"]}]}, "experience_required": {"duration": ["minimum 3 years"], "field": ["logistics", "order processing"]}}, {"job_id": "100003009049811", "location_code": "hk", "company": "Wing Keung Medicine Co Ltd", "job_title": "\u5009\u52d9\u54e1/\u7406\u8ca8\u54e1", "description": "\n\u8077\u8cac :\u4e00\u822c\u5009\u52d9\u54e1/\u7406\u8ca8\u54e1\u5de5\u4f5c, \u8ca0\u8cac\u5009\u5eab\u65e5\u5e38\u5de5\u4f5c, \u5305\u62ec\u57f7\u8ca8\u3001\u9ede\u8ca8\u4e0a\u67b6\u3001\u8a18\u9304\u5eab\u5b58\u3001\u642c\u904b\u7b49\u4e00\u822c\u5009\u52d9\u5de5\u4f5c, \u4ee5\u78ba\u4fdd\u65e5\u5e38\u904b\u4f5c\u66a2\u9806\n\n\u8cc7\u6b77 :\u5c0f\u516d\u7a0b\u5ea6; \u826f\u597d\u7cb5\u8a9e; \u61c2\u8b80\u5beb\u4e2d\u6587; \u61c2\u95b1\u8b80\u82f1\u6587; \u6709\u8cac\u4efb\u5fc3, \u5b88\u6642, \u80fd\u7368\u7acb\u5de5\u4f5c, \u9700\u9ad4\u529b\u52de\u52d5\u5de5\u4f5c, \u52e4\u596e, \u5de5\u4f5c\u7a4d\u6975\u4e3b\u52d5\n\n\u5f85\u9047 :\u6bcf\u6708$13,000 - $17,000, \u6709\u52e4\u5de5\u734e\u91d1, \u914c\u60c5\u6027\u82b1\u7d05, \u54e1\u5de5\u8cfc\u7269\u512a\u60e0, \u91ab\u7642\u798f\u5229, \u65b0\u4eba\u734e\u53ca\u8868\u73fe\u734e\u91d1, \u661f\u671f\u4e00\u81f3\u516d: \u4e0a\u53489\u6642\u81f3\u4e0b\u53486\u6642, \u6bcf\u9031\u5de5\u4f5c6\u5929, \u6bcf\u5929\u5de5\u4f5c 9 \u5c0f\u6642\n\n\u7533\u8acb\u9808\u77e5 :\u6c42\u8077\u8005\u53ef\u81f4\u96fb31457569\u8207\u6c38\u5f37\u897f\u85e5\u884c\u6709\u9650\u516c\u53f8\u6c88\u5c0f\u59d0\u806f\u7d61\u3002\n\n", "employment_types": ["Full Time"], "selling_points": [], "locations": ["Kwai Tsing Area"], "categories": ["Transportation & Logistics", "Others", "Inventory / Warehousing", "Supply Chain"], "post_time": "2022-01-14T09:16:08Z", "salary": {"currency": null, "max": null, "min": null, "period": "monthly", "term": null}, "salary_visible": false, "title_keywords": ["\u7406\u8ca8\u54e1", "\u5009\u52d9\u54e1"], "responsibilities": [], "requirements": {"degrees": [], "majors": [], "languages": [], "language_level": [], "hard_skills": [], "soft_skills": [], "languages_combined": []}, "experience_required": {"duration": [], "field": []}}, {"job_id": "100003009051983", "location_code": "hk", "company": "Schenker International (H.K.) Limited", "job_title": "Sales Support Executive (Ref No: JD/SKM/034/220117)", "description": "The incumbent is responsible to co-ordinate the shipment and follow up customer enquires for Key Account Team.\n\nYour tasks\n\n\nBeing part of the Key account team as the key window for customer, ensure customer satisfaction and sustainable business relationship.\nSupport Global Key Account Team on Customer Analysis (internal) and Customer Reporting (External)\nRespond to enquiries (general enquires & prepare quotation) in timely manner\nGenerate reports and support Global RFQ process as per Global account team instructions before the deadline\nSupport project management for ongoing account specific projects\n\nYour qualifications, experience & skills\n\nDiploma or above\n3-5 years relevant experience, with experience in Oceanfreight will be an advantage\nAbility to review, analyze performance report\nGood interpersonal and communication skills with positive mindset\nGood knowledge of Microsoft Office Software (Excel, Word, PowerPoint and others)\nPossess core competences including initiative, commitment for quality, planning, organizing, team building and cooperation, customer and services orientation\nInterested? We are looking forward to receiving your online application including availability and salary expectations.\n\n\n(Please quote the Job Reference Number on the subject of your application)\n\n(All information collected will be used for recruitment purpose only)\n\nTo know more about us, please visit\u00a0www.dbschenker.com/cn\u00a0", "employment_types": ["Full Time", "Permanent"], "selling_points": ["Follow up customer enquires for Key Account Team", "Customer Analysis and Customer Reporting", "Double pay, Bonus, 5-day work, Medical Insurance"], "locations": ["Tsing Yi"], "categories": ["Transportation & Logistics", "Others", "Freight Forwarding", "Sales, CS & Business Devpt", "Others"], "post_time": "2022-01-17T01:45:16Z", "salary": {"currency": null, "max": null, "min": null, "period": "monthly", "term": null}, "salary_visible": false, "title_keywords": ["sales support executive"], "responsibilities": ["reporting", "software", "analysis", "quotation", "review", "quality", "communication", "project management", "planning", "reports", "recruitment", "report"], "requirements": {"degrees": ["diploma or above"], "majors": [], "languages": [], "language_level": [], "hard_skills": ["excel", "analysis", "word", "powerpoint", "project management", "microsoft office software"], "soft_skills": ["communication skills", "responsible", "positive mindset", "timely", "project management", "initiative", "interpersonal"], "languages_combined": []}, "experience_required": {"duration": ["3-5 years"], "field": ["relevant experience"]}}, {"job_id": "100003009049838", "location_code": "hk", "company": "Galaxy Electronics (Hongkong) Limited", "job_title": "\u5009\u52d9\u54e1/\u7269\u6d41\u52a9\u7406", "description": "\n\u8077\u8cac :\u8ca0\u8cac\u96fb\u5b50\u5143\u5668\u4ef6\u51b7\u6c23\u5009\u5eab\u64cd\u4f5c\u5de5\u4f5c\uff0c\u8ca8\u54c1\u5305\u88f9\u7684\u7c3d\u6536\u3001\u958b\u7bb1\u3001\u6a19\u7c64\u5217\u5370\u3001\u6383\u63cf\u6536\u8ca8\u3001\u4e0a\u67b6\u5165\u5eab\u7b49\n\n\u8cc7\u6b77 :\u4e2d\u4e09\u7a0b\u5ea6; 1\u5e74\u76f8\u95dc\u7d93\u9a57\u512a\u5148; \u4e00\u822c\u7cb5\u8a9e; \u4e00\u822c\u666e\u901a\u8a71; \u61c2\u8b80\u5beb\u4e2d\u6587\n\n\u5f85\u9047 :\u6bcf\u6708$14,000 - $18,000,\u6709\u6bcf\u5c0f\u6642\u8d85\u6642\u5de5\u4f5c\u6d25\u8cbc$55,\u96d9\u7ce7,\u5e74\u504712\u5929,\u9280\u884c\u5047\u671f,\u6bcf\u6708\u8868\u73fe\u734e\u91d1$800,\u6649\u5347\u6a5f\u6703\u53ca\u5728\u8077\u57f9\u8a13, \u661f\u671f\u4e00\u81f3\u516d: \u4e0a\u53489\u6642\u81f3\u4e0b\u53486\u6642, \u6bcf\u9031\u5de5\u4f5c5\u5929\u81f36\u5929, \u6bcf\u5929\u5de5\u4f5c 8 \u5c0f\u6642, \u661f\u671f\u516d\u9577\u77ed\u9031\n\n", "employment_types": ["Full Time"], "selling_points": [], "locations": ["Shatin Area"], "categories": ["Transportation & Logistics", "Others", "Inventory / Warehousing", "Supply Chain"], "post_time": "2022-01-14T09:18:54Z", "salary": {"currency": "HKD", "max": 16999, "min": 14000, "period": "monthly", "term": null}, "salary_visible": true, "title_keywords": ["\u5009\u52d9\u54e1"], "responsibilities": [], "requirements": {"degrees": [], "majors": [], "languages": [], "language_level": [], "hard_skills": [], "soft_skills": [], "languages_combined": []}, "experience_required": {"duration": [], "field": []}}, {"job_id": "100003009049641", "location_code": "hk", "company": "EDOM Technology Co Ltd", "job_title": "\u5305\u88dd\u5de5\u4eba", "description": "\n\u8077\u8cac :\u4e00\u822c\u5305\u88dd\u5de5\u4eba\u5de5\u4f5c, \u6a19\u8cbc\u8ca8\u7269, \u9ede\u7b97\u8ca8\u7269, \u642c\u904b\u8ca8\u7269, \u6838\u5c0d\u6a19\u7c64, \u6aa2\u67e5\u6578\u91cf, \u5305\u88dd\u5c01\u7bb1, \u642c\u904b\u81f3\u51fa\u8ca8\u5340\n\n\u8cc7\u6b77 :\u4e2d\u4e09\u7a0b\u5ea6; \u4e00\u822c\u7cb5\u8a9e; \u61c2\u8b80\u5beb\u4e2d\u6587; \u6e96\u6642, \u8655\u4e8b\u7d30\u5fc3, \u6709\u8cac\u4efb\u5fc3, \u5718\u968a\u7cbe\u795e\n\n\u5f85\u9047 :\u6bcf\u6708$10,000 - $11,000, \u6709\u96d9\u7ce7, \u82b1\u7d05, \u91ab\u7642\u798f\u5229, \u9580\u8a3a\u4fdd\u96aa, \u8d85\u6642\u5de5\u4f5c\u88dc\u5047, \u5e74\u7d42\u734e\u91d1, \u661f\u671f\u4e00\u81f3\u4e94: \u4e0a\u53489\u6642\u81f3\u4e0b\u53486\u6642\u53ca\u661f\u671f\u516d: \u4e0a\u53489\u6642\u81f3\u4e2d\u534812\u6642, \u6bcf\u9031\u5de5\u4f5c5\u5929\u81f35\u5929\u534a, \u6bcf\u5929\u5de5\u4f5c 8 \u5c0f\u6642, \u661f\u671f\u516d\u9577\u77ed\u9031\n\n\u7533\u8acb\u9808\u77e5 :\u6c42\u8077\u8005\u53ef\u50b3\u771f(34279707)\u6216\u96fb\u90f5(Apply Now)\u5c65\u6b77\u8868\u7d66\u76ca\u767b\u79d1\u6280\u80a1\u4efd\u6709\u9650\u516c\u53f8\u3002\u5982\u8981\u7d22\u53d6\u6536\u96c6\u500b\u4eba\u8cc7\u6599\u8072\u660e, \u8acb\u8207\u621a\u5148\u751f(Email)\u806f\u7d61\u3002\n\n", "employment_types": ["Full Time"], "selling_points": [], "locations": ["Kwai Tsing Area"], "categories": ["Transportation & Logistics", "Others", "Inventory / Warehousing", "Supply Chain"], "post_time": "2022-01-14T09:00:50Z", "salary": {"currency": null, "max": null, "min": null, "period": "monthly", "term": null}, "salary_visible": false, "title_keywords": [], "responsibilities": [], "requirements": {"degrees": [], "majors": [], "languages": [], "language_level": [], "hard_skills": [], "soft_skills": [], "languages_combined": []}, "experience_required": {"duration": [], "field": []}}, {"job_id": "100003009049271", "location_code": "hk", "company": "", "job_title": "Assistant / Project Officer (Kwai Chung)", "description": "Responsibilities:\n\n\nMonitor project status and milestone, and prepare the project progress report\nCo-ordinate and communicate with different internal departments to ensure smooth implementation on scope and schedule\nResponsible for coordinating project meetings as requested and take detailed minutes and actions\nPrepare monthly KPI report and ensure the teams submit the operation recurring reports on time\nPrepare project-related paperwork by ensuring all necessary materials are current, properly filed and stored\nOther ad-hoc tasks as assigned\n\n\u00a0Requirements:\n\n\nHigher Diploma or above in Supply Chain Management / Project Management or related disciplines\nFresh graduates / candidates with less working experience will consider as Assistant Project Officer\n1 year or above working experiences in Project Management is an advantage\nWell-organized, detail minded, self-motivated with strong interpersonal and communication skill\nGood command of written and spoken in Chinese and English\nProficiency in MS office\n5 days per week\nCall Cici T: 2975 2109 for a confidential discussion. All information collected will be kept in confidence and will be used for recruitment purpose only.", "employment_types": ["Full Time"], "selling_points": ["Logistics Officer, Project Management", "Logistics, Supply Chain", "Kwai Chung, Warehouse, high salary"], "locations": ["Kwai Tsing Area"], "categories": ["Transportation & Logistics", "Others", "Inventory / Warehousing", "Supply Chain"], "post_time": "2022-01-14T08:20:41Z", "salary": {"currency": null, "max": null, "min": null, "period": null, "term": null}, "salary_visible": false, "title_keywords": ["assistant", "project officer"], "responsibilities": ["communicate with", "project progress report", "ad-hoc tasks", "monitor", "implementation", "teams", "reports", "schedule", "report"], "requirements": {"degrees": ["higher diploma or above"], "majors": ["related disciplines", "project management"], "languages": ["english", "chinese"], "language_level": ["good command"], "hard_skills": ["project management", "ms office"], "soft_skills": ["self-motivated", "confidence", "communication skill", "well-organized", "project management", "interpersonal"], "languages_combined": [{"language": "english", "language_level": ["good command"]}, {"language": "chinese", "language_level": ["good command"]}]}, "experience_required": {"duration": ["1 year"], "field": ["project management"]}}, {"job_id": "100003009028598", "location_code": "hk", "company": "\u548c\u9ec3\u7269\u6d41\u4e2d\u5fc3\u7ba1\u7406\u6709\u9650\u516c\u53f8", "job_title": "\u4ea4\u901a\u4e3b\u4efb [Ref. TO]", "description": "\u4e2d\u4e09\u6216\u4ee5\u4e0a\u7a0b\u5ea6\n\u5177\u5169\u5e74\u7d00\u5f8b\u90e8\u968a\u6216\u4fdd\u5b89\u5de5\u4f5c\u7d93\u9a57\n\u8ca0\u8cac\u4ea4\u901a\u63a7\u5236\u5de5\u4f5c\n\u64cd\u6d41\u5229\u5ee3\u6771\u8a71\uff0c\u4e2d\u6587\u66f8\u5beb\u6d41\u66a2\n\u6bcf\u5929\u5de5\u4f5c9\u5c0f\u6642\uff0c\u9700\u8f2a\u73ed\u53ca\u8f2a\u4f11\n\n\u672c\u516c\u53f8\u63d0\u4f9b\u512a\u539a\u85aa\u916c\u53ca\u5b8c\u5584\u798f\u5229\uff0c\u5305\u62ec\u6709\u85aa\u5e74\u5047\u3001\u81b3\u98df\u6d25\u8cbc\u3001\u7a7f\u68ad\u5df4\u58eb\u670d\u52d9(\u6307\u5b9a\u6642\u9593\u5167)\u53ca\u6649\u5347\u6a5f\u6703\u7b49\u3002\u6709\u610f\u8005\u8acb\u81f4\u96fb2410 8279\u8207\u6f58\u5c0f\u59d0\u806f\u7d61\u6216\u6309\u201cApply Now\u201d\u905e\u4ea4\u7533\u8acb\u3002\n\n\u00a0\u7533\u8acb\u4eba\u63d0\u4f9b\u4e4b\u5168\u90e8\u8cc7\u6599\u5c0d\u4fdd\u5bc6\u53ca\u53ea\u4f5c\u62db\u8058\u4e4b\u7528", "employment_types": ["Full Time", "Permanent"], "selling_points": ["\u4e2d\u4e09\u6216\u4ee5\u4e0a\u7a0b\u5ea6", "\u5177\u5169\u5e74\u7d00\u5f8b\u90e8\u968a\u6216\u4fdd\u5b89\u5de5\u4f5c\u7d93\u9a57", "\u8ca0\u8cac\u4ea4\u901a\u63a7\u5236\u5de5\u4f5c"], "locations": ["Kwai Tsing Area"], "categories": ["Transportation & Logistics", "Others", "Property / Real Estate", "Property Management", "Others"], "post_time": "2022-01-13T18:54:43Z", "salary": {"currency": null, "max": null, "min": null, "period": null, "term": null}, "salary_visible": false, "title_keywords": [], "responsibilities": [], "requirements": {"degrees": [], "majors": [], "languages": [], "language_level": [], "hard_skills": [], "soft_skills": [], "languages_combined": []}, "experience_required": {"duration": [], "field": []}}, {"job_id": "100003009049990", "location_code": "hk", "company": "FRECO International Co., Limited", "job_title": "Procurement Officer/ Procurement Executive (5 days work)", "description": "Expectation:\n\nYou like seeing things change and evolve and are good at anticipating and embracing change.\nYou prefer to work in a place where you have continual learning and developing opportunities.\nYou take a disciplined approach to your work and are constantly looking for ways to do things better and more efficiently.\nYou're interested in growing with our company over time.\n\nActual work:\n\nManage the assigned product category to drive sales and meet target\nSource and select new and exclusive products to meet customers' needs\nNegotiate with suppliers to achieve competitive price, deals and terms\nAnalyze market trends, sales performance, revenues and current inventory levels to forecast inventory needs and estimate purchase quantities;\nCalculate, place and maintain purchase orders / promotional purchase orders with vendors;\nManage inventory days and stock control\nSupport ad-hoc duties as and when required.\n\nRequirement & Qualification\n\nDiploma or above\nA team player with good interpersonal skills, strong negotiation skills and presentation skills\nStrong in analytical thinking\nProficient in MS Office\nGreat command of both written and spoken English and Chinese; Mandarin is required;", "employment_types": ["Full Time", "Permanent"], "selling_points": [], "locations": ["Kwai Hing"], "categories": ["Transportation & Logistics", "Others", "Sales, CS & Business Devpt", "Business Development"], "post_time": "2022-01-14T09:36:10Z", "salary": {"currency": null, "max": null, "min": null, "period": "monthly", "term": null}, "salary_visible": false, "title_keywords": ["procurement executive", "procurement officer"], "responsibilities": ["control", "customers' needs", "sales performance", "inventory", "developing", "purchase", "maintain", "forecast", "ad-hoc duties", "drive sales"], "requirements": {"degrees": ["diploma or above"], "majors": [], "languages": ["english", "chinese", "mandarin"], "language_level": [], "hard_skills": ["ms office"], "soft_skills": ["interested in", "negotiation skills", "learning", "interpersonal skills", "presentation skills", "ad-hoc duties", "team player"], "languages_combined": [{"language": "english", "language_level": []}, {"language": "chinese", "language_level": []}, {"language": "mandarin", "language_level": []}]}, "experience_required": {"duration": [], "field": []}}, {"job_id": "100003009051999", "location_code": "hk", "company": "Schenker International (H.K.) Limited", "job_title": "Operations Supervisor - Airfreight Import (Ref No: JD/AIR/034/220117)", "description": "The incumbent is responsible to assist the Assistant Manager in leading and managing the overall operations to ensure high quality service in line with department work procedure and customer requirement.\n\nYour task:\n\n\nLiaise with customers on shipment arrangement according to the customers\u2019 instruction\nCoach the operation team on their daily works to meet both department and customers\u2019 standard\nMonitor the team works to ensure the shipments process on the right track\nDirect the team on the understanding of department working procedure and systems, also the understanding of the customer requirements\nSupport and backup to the team and Manager in order to maintain the team works in a stipulated standard\n\nYour qualifications, experience & skills\n\nSecondary school graduated or above\nMinimum 5 years working experience in the freight forwarding industry with minimum 1-2 years supervisory experience\nGood command of written and spoken English\nPossess core competences including leadership, managing change, entrepreneurial responsibility, target and result focus, team steering and punctuality\nProficiency in MS Office including MS Word and Excel\nWork location:\u00a0 Tsing Yi\n\nInterested? We are looking forward to receiving your online application including availability and salary expectations.\n\n(Please quote the Job Reference Number on the subject of your application)\n\n(All information collected will be used for recruitment purpose only)\n\nTo know more about us, please visit\u00a0www.dbschenker.com/cn", "employment_types": ["Full Time", "Permanent"], "selling_points": ["Supervise Airfreight Import operations", "5-year experience,  with 1-2 year in supervision", "Double pay, Bonus, Medical Insurance, Allowances"], "locations": ["Tsing Yi"], "categories": ["Transportation & Logistics", "Others", "Freight Forwarding"], "post_time": "2022-01-17T01:48:01Z", "salary": {"currency": null, "max": null, "min": null, "period": "monthly", "term": null}, "salary_visible": false, "title_keywords": ["operations", "supervisor"], "responsibilities": ["shipment arrangement", "operations", "systems", "monitor", "quality", "maintain", "liaise with"], "requirements": {"degrees": [], "majors": [], "languages": ["english"], "language_level": ["good command"], "hard_skills": ["ms word", "excel", "focus", "ms office"], "soft_skills": ["focus", "leadership", "responsible"], "languages_combined": [{"language": "english", "language_level": ["good command"]}]}, "experience_required": {"duration": ["minimum 5 years", "minimum 1-2 years"], "field": ["supervisory experience"]}}, {"job_id": "100003009047221", "location_code": "hk", "company": "Supergo Company Limited", "job_title": "\u5009\u52d9\u54e1", "description": "\u8077\u8cac :\n\n\u4e00\u822c\u5009\u52d9\u5de5\u4f5c (\u8a2d\u6709\u51b7\u6c23) ;\n\u8ca0\u8cac\u65e5\u5e38\u5009\u52d9\u904b\u4f5c;\n\u5354\u52a9\u6536\u8ca8\u3001\u57f7\u8ca8\u3001\u5206\u8ca8\u3001\u51fa\u8ca8\u53ca\u6574\u7406\u8ca8\u5009;\u00a0\n\n\u8cc7\u6b77 :\n\n\u4e2d\u4e09\u7a0b\u5ea6;\n1\u5e74\u76f8\u95dc\u7d93\u9a57;\n\u826f\u597d\u7cb5\u8a9e\u512a\u5148; \u7565\u61c2\u4e00\u822c\u82f1\u8a9e;\n\u9700\u61c2\u8b80\u5beb\u4e2d\u6587; \u7565\u61c2\u8b80\u5beb\u82f1\u6587;\n\u5177\u6709\u57fa\u672c\u96fb\u8166\u64cd\u4f5c\u77e5\u8b58; \u9700\u61c2\u6383\u7784\u689d\u78bc\u64cd\u4f5c\n\n\u54e1\u5de5\u798f\u5229:\n\n\u52e4\u5de5\u734e\u91d1\n\u9280\u884c\u5047\u671f\n\u734e\u52f5\u6027\u82b1\u7d05\n\u91ab\u7642\u798f\u5229\n\u6649\u5347\u6a5f\u6703\n\u54e1\u5de5\u8cfc\u7269\u512a\u60e0\n\n\u5de5\u4f5c\u6642\u9593:\n\n\u661f\u671f\u4e00\u81f3\u516d: \u4e0a\u53489\u6642\u534a\u81f3\u4e0b\u53486\u6642,\u00a0 \u661f\u671f\u516d\u9577\u77ed\u9031\n\n\u6c42\u8077\u8005\u53ef\u81f4\u96fb25257311\u8207\u5d07\u9ad8\u6709\u9650\u516c\u53f8\u5510\u5c0f\u59d0\u806f\u7d61\u3002", "employment_types": ["Full Time"], "selling_points": [], "locations": ["Kwun Tong Area"], "categories": ["Transportation & Logistics", "Others", "Inventory / Warehousing", "Supply Chain"], "post_time": "2022-01-14T02:38:14Z", "salary": {"currency": null, "max": null, "min": null, "period": "monthly", "term": null}, "salary_visible": false, "title_keywords": ["\u5009\u52d9\u54e1"], "responsibilities": [], "requirements": {"degrees": [], "majors": [], "languages": [], "language_level": [], "hard_skills": [], "soft_skills": [], "languages_combined": []}, "experience_required": {"duration": [], "field": []}}, {"job_id": "100003009054771", "location_code": "hk", "company": "Schenker International (H.K.) Ltd", "job_title": "Assistant Manager - Business Implementation & Development - Airfreight (Ref no.: JD/AIR/052/220117)", "description": "The incumbent is\u00a0responsible for successfully implementing new airfreight business gained by working closely with Operation, Customer Service and corresponding account owners as well as monitoring the progress after implementation.\u00a0 In addition, this position needs to work closely with local sales team to identify and develop new local controlled SME and China MNC airfreight business.\n\n\nWork closely with corresponding Sale Team stakeowner, Airfreight Operation and Customer Service to implement new business as per SOP and customer requirement\nMonitoring\u00a0progress of implementation and identify areas of improvement\nRegular\u00a0review with local sales to identify potential SME and China MNC account and drive corresponding opportunities\nJoint visits to customers with sales teams are required\nYour qualifications, experience & skills:\n\n\nDegree holder or above\nMinimum 5 years of working experience in freight forwarding industry\nStrong operational background in airfreight forwarding industry\nExperience in business implementation is required\nGod command of written and spoken English and Mandarin\nStrong in communication skills\nWork location: Tsing Yi\u00a0\n\nInterested? We are looking forward to receiving your online application including availability and salary expectations.\n\n(Please quote the Job Reference Number on the subject of your application)\n\n(All information collected will be used for recruitment purpose only)\n\nTo know more about us, please visit\u00a0www.dbschenker.com/cn\u00a0", "employment_types": ["Full Time", "Permanent"], "selling_points": ["Airfreight business implementation", "Business implementation & development", "Double pay, bonus, 5-day work, medical"], "locations": ["Tsing Yi"], "categories": ["Transportation & Logistics", "Aviation Services", "Others", "Freight Forwarding"], "post_time": "2022-01-17T11:01:48Z", "salary": {"currency": null, "max": null, "min": null, "period": "monthly", "term": null}, "salary_visible": false, "title_keywords": ["assistant manager"], "responsibilities": ["monitoring", "teams", "implementation", "develop", "regular review", "communication", "customer service", "sales team", "sme"], "requirements": {"degrees": ["degree holder"], "majors": [], "languages": ["english", "mandarin"], "language_level": [], "hard_skills": [], "soft_skills": ["controlled", "communication skills", "customer service", "responsible"], "languages_combined": [{"language": "english", "language_level": []}, {"language": "mandarin", "language_level": []}]}, "experience_required": {"duration": ["minimum 5 years"], "field": ["business"]}}, {"job_id": "100003009052744", "location_code": "hk", "company": "The Hongkong Electric Co., Ltd", "job_title": "Assistant Manager (Inventory Control) (Ref. No.  GCD-GS-AMIC-JD)", "description": "Responsibilities :\n\n\n\nReporting to the Manager (Process & Inventory Control), the appointee will mainly perform the following responsibilities:\n\n\nTo perform inventory analysis, identify the improvement areas, monitor the inventory level and perform stock allocation\nTo work with internal and external parties for the lead time reduction arrangement of bulky stock item\nTo conduct storage space utilisation review, report the utilisation rate, as well as plan and execute inventory cycle count related activities\nTo participate in warehouse utilisation optimisation projects\n\nRequirements:\n\n\nBachelor Degree in Logistics Management, Business Administration, Operations Management, Industrial Engineering or related disciplines\nA minimum of 8 years\u2019 relevant work experience in logistics management or inventory planning and control\nFamiliar with MS Office, MS Project and MS Visio\nHands-on experience in using warehouse management systems or SAP system preferred\nGood command of English and Chinese languages, both spoken and written\n\nCandidate with less relevant experience may also be considered for the position of Senior Officer (Inventory Control).\n\nWorking Location :\u00a0Ap Lei Chau, transportation to be provided\n\nApplication :\n\nIf you are interested in this position, please send your resume\u00a0(in PDF format)\u00a0with details of qualification, experience, present and expected salaries, and contact number \u00a0to the\u00a0Human Resources Division, The Hongkong Electric Co., Ltd. on or before 31\u00a0January 2022\u00a0and quote the reference number in your application. Please also visit our website to know more about our Company http://www.hkelectric.com.\n\nApplicants not invited for interview within one month from the closing date may consider their applications unsuccessful. All unsuccessful applications will be kept for six months after the date of this advertisement.\n\nWe are an equal opportunity employer.\u00a0 Personal data provided by job applicants will be treated in strictest confidence and used only for recruitment-related purposes in accordance with the laws and ordinance of the HKSAR.", "employment_types": ["Full Time", "Permanent"], "selling_points": ["To perform inventory analysis", "To conduct storage space utilisation review", "A minimum of 8 years\u2019 relevant work experience"], "locations": ["Aberdeen"], "categories": ["Transportation & Logistics", "Others", "Inventory / Warehousing", "Supply Chain"], "post_time": "2022-01-17T03:53:57Z", "salary": {"currency": null, "max": null, "min": null, "period": "monthly", "term": null}, "salary_visible": false, "title_keywords": ["assistant manager"], "responsibilities": ["reporting", "stock allocation", "inventory", "analysis", "monitor", "internal and external parties", "review", "cycle count", "inventory control", "plan", "report"], "requirements": {"degrees": ["degree", "bachelor"], "majors": ["related disciplines", "business administration", "engineering"], "languages": ["english", "chinese"], "language_level": ["good command"], "hard_skills": ["ap", "sap", "ms office"], "soft_skills": ["hands-on", "interested in", "confidence"], "languages_combined": [{"language": "english", "language_level": ["good command"]}, {"language": "chinese", "language_level": ["good command"]}]}, "experience_required": {"duration": ["minimum of 8 years"], "field": ["management", "inventory control", "relevant experience", "logistics", "warehouse management", "human resources", "planning"]}}, {"job_id": "100003009049087", "location_code": "hk", "company": "Jebsen Motors Limited", "job_title": "Product Specialist (Ref: PORSCHE F041)", "description": "Responsibilities :\n\nPrepare comprehensive Product analysis and pricing comparison with competitors for management review\u00a0\nAssist in monitoring the overall sales process are in line with internal audit and Principal guideline\nSupport on New Car & Pre-owned car sales administration duties including licensing documents , PRP, inventory and relevant reports\nSupport and assist in various sales events/ promotional activities\nAny ad hoc duties as assigned by supervisor\nRequirements\n\nDegree Holder with major in Electrical / Mechanical Engineering or any related discipline\nPassionate in developing career in automotive industry and a car lover\nPossess at least 1 year working experience especially in Automotive industry will be an advantage\nSelf-initiated and outgoing, with good communication & interpersonal skills\u00a0 \u00a0\u00a0\nStrong analytical skills, able to work under pressure\nGood command of both written and spoken English and Chinese including Putonghua and Cantonese\nProficient in MS office (Word, Excel, Powerpoint)\u00a0\nInterested parties please send your full resume and expected salary\u00a0to our mailbox by clicking \u201cApply now\u201d below.\n\nFor more information about Jebsen Group, please visit www.jebsen.com or follow us on:\n\nSina Weibo\u00a0\u00a0\u00a0\u00a0\u00a0http://weibo.com/jebsengroup\n\nWeChat\u00a0\u00a0\u00a0\u00a0\u00a0\u00a0\u00a0\u00a0\u00a0\u00a0 ID: jebsen1895\n\nLinkedIn\u00a0\u00a0\u00a0\u00a0\u00a0\u00a0\u00a0\u00a0\u00a0\u00a0 Jebsen Group\n\u00a0\n\n\nAll information provided by applicants will\u00a0be used for recruitment purposes only.\n\nAt Jebsen, success breeds success.", "employment_types": ["Full Time", "Permanent"], "selling_points": ["Porsche Centre HK", "Fresh Graduates are welcome", "Passionate in Automotive Industry"], "locations": ["Wan Chai"], "categories": ["Transportation & Logistics", "Others", "Sales, CS & Business Devpt", "Sales Administration"], "post_time": "2022-01-14T08:06:08Z", "salary": {"currency": null, "max": null, "min": null, "period": "monthly", "term": null}, "salary_visible": false, "title_keywords": ["product specialist"], "responsibilities": ["ad hoc duties", "sales administration", "relevant reports", "internal audit", "analysis", "monitoring", "inventory", "promotional activities", "management review"], "requirements": {"degrees": ["degree holder"], "majors": ["mechanical engineering"], "languages": ["cantonese", "putonghua", "english", "chinese"], "language_level": ["good command"], "hard_skills": ["excel", "word", "powerpoint", "analytical skills", "ms office"], "soft_skills": ["passionate", "outgoing", "analytical skills", "communication", "interpersonal skills", "work under pressure"], "languages_combined": [{"language": "cantonese", "language_level": ["good command"]}, {"language": "putonghua", "language_level": ["good command"]}, {"language": "english", "language_level": ["good command"]}, {"language": "chinese", "language_level": ["good command"]}]}, "experience_required": {"duration": ["at least 1 year"], "field": ["automotive industry"]}}, {"job_id": "100003009048584", "location_code": "hk", "company": "Divine Health and Massage Limited", "job_title": "\u524d\u53f0\u670d\u52d9\u54e1**", "description": "\n\u8077\u8cac :\u4e00\u822c\u63a5\u5f85\u54e1\u5de5\u4f5c, \u63a5\u807d\u96fb\u8a71\u53ca\u8655\u7406\u96fb\u8a71\u67e5\u8a62, \u8655\u7406\u9810\u7d04, \u63a5\u5f85\u5ba2\u4eba\uff0c\u89e3\u7b54\u67e5\u8a62\n\n\u8cc7\u6b77 :\u4e2d\u4e94\u7a0b\u5ea6; 1\u5e74\u7d93\u9a57; \u826f\u597d\u7cb5\u8a9e\u512a\u5148; \u4e00\u822c\u666e\u901a\u8a71; \u4e00\u822c\u82f1\u8a9e; \u61c2\u8b80\u5beb\u4e2d\u6587; \u7565\u61c2\u8b80\u5beb\u82f1\u6587; \u61c2\u96fb\u8166\u6587\u66f8\u8655\u7406; \u61c2Microsoft Office; \u61c2\u4e2d\u6587\u6253\u5b57; \u5b88\u6642, \u6709\u8cac\u4efb\u5fc3, \u6709\u79ae\u8c8c\n\n\u5f85\u9047 :\u6bcf\u6708$16,000 - $18,000, \u6709\u751f\u65e5\u50471\u5929, \u5728\u8077\u57f9\u8a13 \u53ca\u6649\u5347\u6a5f\u6703, \u4e0a\u53489\u6642\u81f3\u4e0b\u534811\u6642, \u6bcf\u9031\u5de5\u4f5c6\u5929,\u8f2a\u4f11, \u6bcf\u5929\u5de5\u4f5c 9 \u5c0f\u6642(\u5305\u62ec1\u5c0f\u6642\u5348\u81b3\u6642\u9593)\n\n\u7533\u8acb\u9808\u77e5 :\u6c42\u8077\u8005\u53ef\u96fb\u90f5(Apply Now)\u5c65\u6b77\u8868\u7d66\u6668\u6bbf\u6709\u9650\u516c\u53f8\u3002\u5982\u8981\u7d22\u53d6\u6536\u96c6\u500b\u4eba\u8cc7\u6599\u8072\u660e, \u8acb\u8207\u5f90\u5c0f\u59d0(Email)\u806f\u7d61\u3002\n\n", "employment_types": ["Full Time"], "selling_points": [], "locations": ["Kowloon City"], "categories": ["Transportation & Logistics", "Others", "Inventory / Warehousing", "Supply Chain"], "post_time": "2022-01-14T06:51:47Z", "salary": {"currency": null, "max": null, "min": null, "period": "monthly", "term": null}, "salary_visible": false, "title_keywords": [], "responsibilities": [], "requirements": {"degrees": [], "majors": [], "languages": [], "language_level": [], "hard_skills": [], "soft_skills": [], "languages_combined": []}, "experience_required": {"duration": [], "field": []}}, {"job_id": "100003009045553", "location_code": "hk", "company": "Genuine Treasure Access And Scaffolding Limited", "job_title": "\u5009\u52d9\u6587\u54e1", "description": "\u8077\u8cac :\u4e00\u822c\u5009\u52d9\u6587\u54e1\u5de5\u4f5c\uff1b\u8ca8\u5009\u65e5\u5e38\u904b\u4f5c\uff0c\u5b89\u6392\u6bcf\u65e5\u6536\u9001\u8ca8\u884c\u7a0b\uff1b\u8655\u7406\u5009\u4e3b\u7ba1\u5206\u914d\u7684\u5176\u4ed6\u4efb\u52d9 (\u505a\u6eff\u99966\u500b\u6708\u6709\u4e00\u7b46\u904e\u65b0\u4eba\u734e$6,000)\n\u8cc7\u6b77 :\u4e2d\u4e94\u7a0b\u5ea6; \u826f\u597d\u7cb5\u8a9e\u512a\u5148; \u4e00\u822c\u82f1\u8a9e; \u61c2\u8b80\u5beb\u4e2d\u6587; \u7565\u61c2\u8b80\u5beb\u82f1\u6587; \u61c2\u4e2d\u82f1\u6587\u96fb\u8166\u64cd\u4f5c; \u6b61\u8fce\u61c9\u5c46\u7562\u696d\u751f\u7533\u8acb; \u6709\u5009\u52d9\u6587\u54e1\u7d93\u9a57\u512a\u5148\n\u5f85\u9047 :\u6709\u5728\u8077\u57f9\u8a13, \u6649\u5347\u6a5f\u6703 \u53ca \u6709\u5ee0\u8eca\u63a5\u9001(\u5143\u6717,\u5929\u6c34\u570d,\u4e0a\u6c34,\u7c89\u5dba\u5340),\n\u7533\u8acb\u9808\u77e5 :\u6c42\u8077\u8005\u53ef\u96fb\u90f5(APPLY NOW)\u5c65\u6b77\u8868\u7d66\u4fca\u5ddd\u68da\u67b6\u8a2d\u5099\u6709\u9650\u516c\u53f8\u3002\u5982\u8981\u7d22\u53d6\u6536\u96c6\u500b\u4eba\u8cc7\u6599\u8072\u660e, \u8acb\u8207\u90ed\u5148\u751f(Email)\u806f\u7d61\u3002", "employment_types": ["Full Time"], "selling_points": ["\u4e00\u822c\u5009\u52d9\u6587\u54e1\u5de5\u4f5c", "\u6709\u5009\u52d9\u6587\u54e1\u7d93\u9a57\u512a\u5148; \u6b61\u8fce\u61c9\u5c46\u7562\u696d\u751f\u7533\u8acb;", "\u8475\u9752\u5340 (\u5143\u6717,\u5929\u6c34\u570d,\u4e0a\u6c34,\u7c89\u5dba\uff08\u8fd1\u6e2f\u9435\u7ad9\uff09\u6709\u5ee0\u8eca\u63a5\u9001)"], "locations": ["Kwun Tong Area"], "categories": ["Admin & HR", "Clerical / Admin Staff", "Transportation & Logistics", "Others"], "post_time": "2022-01-13T08:04:08Z", "salary": {"currency": null, "max": null, "min": null, "period": "monthly", "term": null}, "salary_visible": false, "title_keywords": ["\u5009\u52d9\u6587\u54e1"], "responsibilities": [], "requirements": {"degrees": [], "majors": [], "languages": [], "language_level": [], "hard_skills": [], "soft_skills": [], "languages_combined": []}, "experience_required": {"duration": [], "field": []}}, {"job_id": "100003009048574", "location_code": "hk", "company": "Association of Hong Kong Flag-Guards Limited", "job_title": "\u5009\u52d9\u54e1", "description": "\n\u8077\u8cac :\n\u4e00\u822c\u6587\u66f8\u5de5\u4f5c\uff0c\u5305\u62ec\u63a5\u807d\u96fb\u8a71\u3002\n\u8655\u7406\u7279\u6d3e\u5de5\u4f5c\uff0c\u8ca0\u8cac\u6d3b\u52d5\u884c\u653f\u5de5\u4f5c\uff1b\n\u8ca0\u8cac\u884c\u653f\u5de5\u4f5c\uff0c\u5305\u62ec\u63a1\u8cfc\u3001\u6536\u652f\u7ba1\u7406\u53ca\u4e00\u822c\u8fa6\u516c\u5ba4\u96dc\u52d9\uff1b\n\u9700\u8981\u5354\u52a9\u5eab\u5b58\u548c\u57f7\u5236\u670d\u5de5\u4f5c\n\n\u8cc7\u6b77 :\n\u4e2d\u516d\u7a0b\u5ea6;\n\u826f\u597d\u7cb5\u8a9e; \u4e00\u822c\u666e\u901a\u8a71; \u4e00\u822c\u82f1\u8a9e;\n\u61c2\u8b80\u5beb\u4e2d\u6587; \u7565\u61c2\u8b80\u5beb\u82f1\u6587;\n\u61c2Microsoft Office;\n\u5177\u6709\u4e00\u822c\u4e92\u806f\u7db2\u77e5\u8b58;\n\u61c2\u4e2d\u82f1\u6587\u96fb\u8166\u64cd\u4f5c;\n\u61c2\u5009\u9821/\u901f\u6210\u8f38\u5165\u6cd5;\n\u5177\u6709\u57fa\u672c\u96fb\u8166\u64cd\u4f5c\u77e5\u8b58\n\n\u661f\u671f\u4e00\u81f3\u516d: \u4e0a\u53489\u6642\u81f3\u4e0b\u53486\u6642\u53ca\u6bcf\u9031\u5de5\u4f5c5\u5929\u534a, \u6bcf\u5929\u5de5\u4f5c 8 \u5c0f\u6642\n\n\u7533\u8acb\u9808\u77e5 :\u6c42\u8077\u8005\u53ef\u50b3\u771f(24311628)\u6216\u96fb\u90f5(Apply Now)\u5c65\u6b77\u8868\u7d66\u9999\u6e2f\u5347\u65d7\u968a\u7e3d\u6703\u3002\u5982\u8981\u7d22\u53d6\u6536\u96c6\u500b\u4eba\u8cc7\u6599\u8072\u660e, \u8acb\u8207\u7c21\u5c0f\u59d0(Email)\u806f\u7d61\u3002\n", "employment_types": ["Full Time"], "selling_points": ["\u4e2d\u516d\u7a0b\u5ea6", "\u826f\u597d\u7cb5\u8a9e", "\u4e00\u822c\u666e\u901a\u8a71"], "locations": ["Chai Wan"], "categories": ["Transportation & Logistics", "Others", "Inventory / Warehousing", "Supply Chain"], "post_time": "2022-01-15T03:50:01Z", "salary": {"currency": null, "max": null, "min": null, "period": "monthly", "term": null}, "salary_visible": false, "title_keywords": ["\u5009\u52d9\u54e1"], "responsibilities": [], "requirements": {"degrees": [], "majors": [], "languages": [], "language_level": [], "hard_skills": [], "soft_skills": [], "languages_combined": []}, "experience_required": {"duration": [], "field": []}}, {"job_id": "100003009045702", "location_code": "hk", "company": "CommNet Telecom Limited", "job_title": "\u517c\u8077\u5009\u52d9\u54e1", "description": "\n\u8077\u8cac :\u8ca0\u8cac\u65e5\u5e38\u5009\u52d9\u904b\u4f5c, \u5305\u62ec\u62c6\u8ca8\u3001\u57f7\u8ca8\u3001\u6574\u7406\u5b58\u8ca8,\u8ca8\u7269\u76e4\u9ede,\u642c\u904b\u8ca8\u7269,\u4e00\u822c\u8ca8\u5009\u96dc\u52d9\u5de5\u4f5c\n\n\u8cc7\u6b77 :\u4e2d\u4e09\u7a0b\u5ea6; \u826f\u597d\u7cb5\u8a9e; \u61c2\u8b80\u5beb\u4e2d\u6587; \u5177\u6709\u57fa\u672c\u96fb\u8166\u64cd\u4f5c\u77e5\u8b58; \u4e3b\u52d5\u71b1\u8aa0\uff0c\u6709\u8cac\u4efb\u5fc3\uff0c\u523b\u82e6\n\n\u5f85\u9047 :\u6bcf\u5c0f\u6642$80.00, \u661f\u671f\u4e00\u81f3\u4e94: \u4e0a\u534810\u6642\u81f3\u4e0b\u53486\u6642, \u6bcf\u9031\u5de5\u4f5c1\u5929\u81f35\u5929, \u5be6\u969b\u5de5\u4f5c\u65e5\u6578\u6309\u8ca8\u91cf\u800c\u5b9a\n\n\u7533\u8acb\u9808\u77e5 :\u6c42\u8077\u8005\u53ef\u96fb\u90f5(Apply Now)\u5c65\u6b77\u8868\u7d66\u806f\u76c8\u96fb\u8a0a\u79d1\u6280\u6709\u9650\u516c\u53f8\u3002\u5982\u8981\u7d22\u53d6\u6536\u96c6\u500b\u4eba\u8cc7\u6599\u8072\u660e, \u8acb\u8207\u674e\u5c0f\u59d0(Email)\u806f\u7d61\u3002\n\n", "employment_types": ["Part Time"], "selling_points": [], "locations": ["Kwun Tong"], "categories": ["Transportation & Logistics", "Others", "Inventory / Warehousing", "Supply Chain"], "post_time": "2022-01-13T08:24:04Z", "salary": {"currency": null, "max": null, "min": null, "period": "hourly", "term": null}, "salary_visible": false, "title_keywords": [], "responsibilities": [], "requirements": {"degrees": [], "majors": [], "languages": [], "language_level": [], "hard_skills": [], "soft_skills": [], "languages_combined": []}, "experience_required": {"duration": [], "field": []}}, {"job_id": "100003009051060", "location_code": "hk", "company": "Rentokil Initial Hong Kong Ltd", "job_title": "Operation Clerk (Contract 1 year) (Monthly salary up to HK$13,000)", "description": "PRINCIPAL DUTIES & RESPONSIBILITIES\n\n\nPerform general clerical duties\nHandle customers phone and email enquires\nProvide administration support to the department\nAd hoc duties as when required\nPERSON SPECIFICATION\n\nDiploma or above with 1-year working experience, experience in operation in the service industry is an advantage (F.5 or above also welcome)\nGood communication skills, good attitude and willingness to work\nGood command of spoken and written English, Mandarin and Cantonese\n\nAre you interested? Here's what you can expect when you join us\n\nCompetitive salary package\nOffer learning & development and Training program\nExcellent company culture\nExcellent promotion opportunities\n5-day work week\nService leads incentive opportunity\n\nIf you are interested in applying, please enclose your resume with email address & contact number. Thank you.", "employment_types": ["Full Time"], "selling_points": ["Monthly salary up to HK$13,000", "5-day work week", "Service leads incentive opportunity"], "locations": ["Kwun Tong"], "categories": ["Transportation & Logistics", "Others", "Sales, CS & Business Devpt", "Customer Service - Supervisor / Officer", "Marketing / Public Relations", "Public Relations - General / Support"], "post_time": "2022-01-15T01:36:58Z", "salary": {"currency": null, "max": null, "min": null, "period": "monthly", "term": null}, "salary_visible": false, "title_keywords": ["operation clerk"], "responsibilities": ["ad hoc duties", "contact", "communication", "administration"], "requirements": {"degrees": ["diploma or above"], "majors": [], "languages": ["cantonese", "english", "mandarin"], "language_level": ["good command"], "hard_skills": [], "soft_skills": ["interested in", "communication skills", "learning", "willingness to work"], "languages_combined": [{"language": "cantonese", "language_level": ["good command"]}, {"language": "english", "language_level": ["good command"]}, {"language": "mandarin", "language_level": ["good command"]}]}, "experience_required": {"duration": ["1-year"], "field": ["operation", "service industry"]}}, {"job_id": "100003009050344", "location_code": "hk", "company": "Fly King Transportation Company Ltd", "job_title": "Training Supervisor", "description": "Responsibilities\nConduct classroom training courses\nProvide on-site coaching to frontline staff\nMaintain training schedules and keep training record up-to-dated\nPrepare and review training materials and documents\nCooperate with CPSL training team for training related programs\nAny ad hoc duties as assigned by superior\nRequirements\n2-3 years\u2019 relevant experience in air cargo industry is a must\nExcellent presentation and communication skills\nStrong sense of responsibility and good interpersonal skills\nFluency in spoken and written Chinese and English\nProficient in MS applications including Word, Excel and Powerpoint\nInterested parties, please send application with full particulars of qualifications, experience, current and expected salary by email via \"Apply Now\"\nAll information will be kept confidential and used for recruitment purpose only.", "employment_types": ["Full Time", "Permanent"], "selling_points": [], "locations": ["Airport Area"], "categories": ["Transportation & Logistics", "Aerospace", "Others", "Admin & HR", "Training & Development"], "post_time": "2022-01-14T10:10:34Z", "salary": {"currency": null, "max": null, "min": null, "period": "monthly", "term": null}, "salary_visible": false, "title_keywords": ["supervisor"], "responsibilities": ["ad hoc duties", "schedules", "review", "maintain", "cooperate with"], "requirements": {"degrees": [], "majors": [], "languages": ["english", "chinese"], "language_level": ["fluency"], "hard_skills": ["excel", "ms applications", "word", "powerpoint"], "soft_skills": ["communication skills", "interpersonal skills", "presentation", "sense of responsibility"], "languages_combined": [{"language": "english", "language_level": ["fluency"]}, {"language": "chinese", "language_level": ["fluency"]}]}, "experience_required": {"duration": ["2-3 years"], "field": ["relevant experience"]}}, {"job_id": "100003009045615", "location_code": "hk", "company": "Parkview Hotel Services Ltd", "job_title": "\u7ba1\u5bb6\u90e8\u53f8\u6a5f", "description": "\u5de5\u4f5c\u8077\u8cac\uff1a\n\n\u70ba\u7ba1\u5bb6\u90e8\u99d5\u99db\u90e8\u9580\u8eca\u8f1b\u3002\n\n\u4fdd\u6301\u5c08\u696d\u3001\u53cb\u5584\u3001\u6574\u6f54\u53ca\u89aa\u5207\u7684\u5f62\u8c61\u3002\n\n\u5de5\u4f5c\u8981\u6c42\uff1a\n\n\u5b78\u6b77\u4e0d\u62d8\n\n1\u5e74\u76f8\u95dc\u5de5\u4f5c\u7d93\u9a57\u3002\n\n\u6301\u6709\u6709\u6548\u99d5\u99db\u57f7\u71671\u548c2\u3002\n\n\u4e00\u822c\u7cb5\u8a9e\u6216\u82f1\u8a9e\u3002\n\n\u516c\u53f8\u798f\u5229 :\n\n\u4e94\u6708\u5de5\u4f5c\u9031\n\u5e74\u7d42\u4fdd\u8b49\u96d9\u7ce7\u00a0\n\u5bb6\u5ead\u91ab\u7642\u8a08\u5283\n\u751f\u65e5\u5047\n\u54e1\u5de5\u53ef\u4eab\u7528\u6703\u6240\u5065\u8eab\u5ba4\n\u514d\u8cbb\u503c\u73ed\u81b3\u98df\n\u514d\u8cbb\u7a7f\u68ad\u5df4\u58eb\u63a5\u9001\u670d\u52d9 (\u5f80\u8fd4\u4e2d\u74b0 ; \u5f80\u9285\u947c\u7063\uff0c\u7063\u4ed4\uff0c\u91d1\u9418\u53ca\u9999\u6e2f\u4ed4)\n\nPlease send full resume,\u00a0expected salary\u00a0and contact telephone number to\n\nHong Kong Parkview\nHuman Resources Department\n88 Tai Tam Reservoir Road, Hong Kong\n\nWhatsApp: 7071 2186\nConfidential Fax No. 2812 3490\nEmail:\u00a0[via APPLY NOW]\n\n(All data collected will be used for recruitment purpose only)", "employment_types": ["Full Time"], "selling_points": ["\u70ba\u7ba1\u5bb6\u90e8\u99d5\u99db\u90e8\u9580\u8eca\u8f1b", "\u4fdd\u6301\u5c08\u696d\u3001\u53cb\u5584\u3001\u6574\u6f54\u53ca\u89aa\u5207\u7684\u5f62\u8c61", "1\u5e74\u76f8\u95dc\u5de5\u4f5c\u7d93\u9a57"], "locations": ["Wan Chai"], "categories": ["Transportation & Logistics", "Others", "Hospitality / F & B", "Hospitality / Hotel Services", "Private Transportation"], "post_time": "2022-01-13T08:12:38Z", "salary": {"currency": null, "max": null, "min": null, "period": "monthly", "term": null}, "salary_visible": false, "title_keywords": [], "responsibilities": ["recruitment", "contact", "data"], "requirements": {"degrees": [], "majors": [], "languages": [], "language_level": [], "hard_skills": ["no", "whatsapp"], "soft_skills": [], "languages_combined": []}, "experience_required": {"duration": [], "field": []}}, {"job_id": "100003009052563", "location_code": "hk", "company": "Centrix Professionals - Recruitment Agency Division", "job_title": "Logistics Officer / Shipping Officer / Operations Officer (5 Days) 2 Post URGENT", "description": "Our client is a sizable company with attractive benefits is urgently looking for the following positions :\n\nPosition : Logistics Officer / Shipping Officer / Operation Officer (2 Post)\n\nSalary : Negotiable\u00a0\n\nRequirements :\u00a0\n\nBenefits : Medical, Dental, Guarantee Double Pay, Yearly Discretionary Bonus, Annual Leave, 5 Days\n\nRequirements:\n\nDegree holder is a must, major in International Shipping, Logistics Engineering Management, Supply Chain Management or related discipline\nAt least 1-3 yrs relevant experience in Shipping Companies is preferable\u00a0\nGained experience in Demurrage will consider Operation Officer (Demurrage)\nProficiency in English, Cantonese & Mandarin (most important)\nProficient in Microsoft Office (Ms Word, Excel & Chinese Word Processing\nStable, Reliable, Independent, Team Work, Detail-minded and able to work under pressure\nFresh Graduate with related major will consider as Assistant Grade\u00a0\nImmediate Available is highly preferable\n\nResponsibilities for the position of Operation Officer / Assistant\u00a0\n\n\nHandle full set of shipping documents\u00a0\n\nCoordinate with supplier, buyers & head office to arrange loading schedules\nFollow up charter party & handle commercial claims\u00a0\n\nResponsibilities for the position of Operation Officer - Demurrage\u00a0\n\nPrepare demurrage computation for timely submission\nFollow up receivable and collection to counter parties proactively\nNegotiable and settle demurrage claims according to trading contracts and charter parties\nPrepare demurrage claim invoices and check invoices for settlement\nReview of shipping and trading contracts related to lay time calculation and demurrage\nHandle and manage full set of demurrage documents\nKeep outstanding claims record update\nUndertake Department Head relevant assignment whenever required\u00a0\nAttractive salary and fringe benefits will be offered to the right candidates.\n\n\nInterested parties, please send full resume in\u00a0MS WORD FORMAT, stating expected salary by clicking \"Apply Now\"\n\nFor more information, please visit : www.centrix.com.hk\n\n\n(Personal data collected will be used for recruitment purpose only)\u00a0\u00a0", "employment_types": ["Full Time", "Permanent"], "selling_points": ["Degree Int'l shpg Supply Chain 2 post TOP URGENT", "1-3 yrs rel exp in Shpg Co / Demurrage Stable", "Flu Eng & Mandarin Stable Reliable Independent"], "locations": ["Not Specified"], "categories": ["Transportation & Logistics", "Others", "Shipping", "Supply Chain"], "post_time": "2022-01-17T03:25:35Z", "salary": {"currency": null, "max": null, "min": null, "period": "monthly", "term": null}, "salary_visible": false, "title_keywords": ["logistics officer", "operations officer", "shipping officer"], "responsibilities": [], "requirements": {"degrees": [], "majors": [], "languages": [], "language_level": [], "hard_skills": [], "soft_skills": [], "languages_combined": []}, "experience_required": {"duration": [], "field": []}}, {"job_id": "100003009045683", "location_code": "hk", "company": "Sacred Heart of Mary Catholic Primary School", "job_title": "\u6821\u52d9\u54e1", "description": "\n\u8077\u8cac :\u7167\u9867\u5b78\u7ae5, \u6e05\u6f54\u6821\u820d\u3001\u6821\u5167\u8a2d\u65bd\u53ca\u7269\u54c1, \u642c\u904b\u7269\u8cc7\u3001\u5916\u52e4\u53ca\u8655\u7406\u96dc\u52d9, \u8655\u7406\u6821\u65b9\u59d4\u6d3e\u5de5\u4f5c; \u6e96\u50f1\u54e1\u9700\u81ea\u9858\u9032\u884c\u300a\u6027\u7f6a\u884c\u5b9a\u7f6a\u7d00\u9304\u67e5\u6838\u300b\u3002\n\n\u8cc7\u6b77 :\u5c0f\u516d\u7a0b\u5ea6; \u4e00\u822c\u7cb5\u8a9e; \u61c2\u95b1\u8b80\u4e2d\u6587; \u6709\u611b\u5fc3\u53ca\u8010\u6027\u53ca\u5177\u8cac\u4efb\u611f, \u80fd\u7368\u7acb\u5de5\u4f5c\u53ca\u5177\u5718\u9ad4\u7cbe\u795e, \u61c2\u6cb9\u5370, \u7dad\u4fee\u6216\u82b1\u6728\u8b77\u7406\u53ca\u5c45\u4f4f\u5927\u57d4\u5340\u512a\u5148\n\n\u5f85\u9047 :\u6bcf\u6708$11,550 - $13,650, \u661f\u671f\u4e00\u81f3\u4e94: 7:00AM-5:00PM/8:00AM-6:00PM/ 9:00AM-7:00PM\u53ca\u661f\u671f\u516d: 8:00AM-4:00PM,\u6bcf\u9031\u5de5\u4f5c6\u5929, \u6bcf\u5929\u5de5\u4f5c 8-10 \u5c0f\u6642\n\n\u7533\u8acb\u9808\u77e5 :\u6c42\u8077\u8005\u53ef\u50b3\u771f(26667048)\u6216\u81f4\u96fb(26606161)\u5c65\u6b77\u8868\u7d66\u5929\u4e3b\u6559\u8056\u6bcd\u8056\u5fc3\u5c0f\u5b78\u3002\u5982\u8981\u7d22\u53d6\u6536\u96c6\u500b\u4eba\u8cc7\u6599\u8072\u660e, \u8acb\u8207\u76e7\u5c0f\u59d0\u806f\u7d61\u3002\n\n", "employment_types": ["Full Time"], "selling_points": [], "locations": ["Tai Po Area"], "categories": ["Transportation & Logistics", "Others", "Inventory / Warehousing", "Supply Chain"], "post_time": "2022-01-13T08:21:09Z", "salary": {"currency": null, "max": null, "min": null, "period": "monthly", "term": null}, "salary_visible": false, "title_keywords": [], "responsibilities": [], "requirements": {"degrees": [], "majors": [], "languages": [], "language_level": [], "hard_skills": [], "soft_skills": [], "languages_combined": []}, "experience_required": {"duration": [], "field": []}}, {"job_id": "100003009040035", "location_code": "hk", "company": "Sunny Handicraft (HK) Limited", "job_title": "Shipping Officer", "description": "Requirement for Shipping Officer:\nDiploma at least 5 Years working experience in logistic\nCoordinate with factory & customer to ensure daily import & export operations in timely & accurate schedule\nSound Knowledge and experienced in import & export procedures, Trade-link declaration, regulation and L/C Doc. Handling\nKnowledge and experienced in handling office administration and accounting task.\nGood communication and interpersonal skills\nAble to work under pressure and multi-tasking abilities alone.\nWilling to work overtime during peak season\nProficiency in MS office\nFluency in both written and spoken English, Cantonese and Mandarin\nHands-on experience in handling shipment for USA, Canada, European countries.\n\n\nPlease submit your resume with EXPECTED salary and date of availability.", "employment_types": ["Full Time", "Permanent"], "selling_points": ["Flexible working hours", "Coordinate with factory & customer", "Experienced in import & export procedures"], "locations": ["Kowloon Bay"], "categories": ["Transportation & Logistics", "Others", "Shipping", "Supply Chain"], "post_time": "2022-01-12T07:28:05Z", "salary": {"currency": null, "max": null, "min": null, "period": "monthly", "term": null}, "salary_visible": false, "title_keywords": ["shipping officer"], "responsibilities": ["shipping", "operations", "office administration", "coordinate with", "procedures", "communication", "schedule", "work under pressure"], "requirements": {"degrees": ["diploma"], "majors": [], "languages": ["cantonese", "english", "mandarin"], "language_level": ["fluency"], "hard_skills": ["c", "ms office"], "soft_skills": ["work overtime", "timely", "multi-tasking", "communication and interpersonal skills", "hands-on", "accurate", "work under pressure"], "languages_combined": [{"language": "cantonese", "language_level": ["fluency"]}, {"language": "english", "language_level": ["fluency"]}, {"language": "mandarin", "language_level": ["fluency"]}]}, "experience_required": {"duration": ["at least 5 years"], "field": []}}, {"job_id": "100003009046966", "location_code": "hk", "company": "Fat Kee Logistics Limited", "job_title": "Logistics Executive", "description": "Responsibilities\n\nLiaise with clients for inbound and outbound instruction\nCoordinate with warehouses and delivery team to execute clients\u2019 instruction\nMaintain good relationship with clients\nResponsible for maintaining accurate logs of all transportation and goods\nMonitor deliveries and ensure customer satisfaction\nData entry and clerical support\n\n\n\nRequirements\n\n\nDSE graduated or above\nFresh graduate are welcome\nRelevant working experience in distribution centre, logistics warehouse or e-commerce logistics will be an advantage\nWell communication & interpersonal skills\nSelf-motivated with a positive attitude and willing to learn\nGood command of both written & spoken English, Cantonese & Mandarin\nProficient in MS Office applications (Outlook, Word, Excel) and Chinese Word Processing\n\n\n\nWe offer an attractive remuneration package and a traffic arrangement to the right candidate.\u00a0 Interested parties, please submit your resume with details of qualification, experience, and contact number to the Human Resources Manager by\u00a0clicking \"Apply Now\". Data collected will be used for recruitment purposes only.\n\nApplicants not invited for interview within one month may consider their applications unsuccessful.\u00a0 All unsuccessful applications will be kept for six months after the date of this advertisement.", "employment_types": ["Full Time"], "selling_points": [], "locations": ["Kwai Tsing Area"], "categories": ["Transportation & Logistics", "Others", "Freight Forwarding", "Inventory / Warehousing"], "post_time": "2022-01-14T01:53:29Z", "salary": {"currency": null, "max": null, "min": null, "period": "monthly", "term": null}, "salary_visible": false, "title_keywords": ["logistics executive"], "responsibilities": ["liaise with clients", "maintaining", "data entry", "monitor", "coordinate with", "clerical support", "maintain good relationship"], "requirements": {"degrees": ["fresh graduate", "dse"], "majors": [], "languages": ["cantonese", "english", "chinese", "mandarin"], "language_level": ["good command", "proficient"], "hard_skills": ["excel", "chinese word processing", "e-commerce", "word", "outlook", "ms office"], "soft_skills": ["self-motivated", "willing to learn", "communication", "positive attitude", "interpersonal skills"], "languages_combined": [{"language": "cantonese", "language_level": ["good command"]}, {"language": "english", "language_level": ["good command"]}, {"language": "chinese", "language_level": ["proficient"]}, {"language": "mandarin", "language_level": ["good command"]}]}, "experience_required": {"duration": [], "field": ["logistics", "relevant working experience", "e-commerce"]}}, {"job_id": "100003009049958", "location_code": "hk", "company": "Hong Kong Aero Engine Services Ltd", "job_title": "Storekeeper (Ref. No. : SK010122-B)", "description": "Responsibilities :\n\n\nTo perform daily warehouse activities - goods picking/packing and delivery\nTo compile daily reports\nRequirements :\nHKDSE/ HKCEE graduated\nEquipped with warehouse and inventory system knowledge, preferably SAP system\nProficient in MS Office \u2013 Excel, Word\nGood command of both English and Chinese\nHardworking and good communication skills\nMinimum 2 years of relevant working experience in warehouse\nInterested parties please send a full resume with expected salary and quote our reference number to Human Resources Department, Hong Kong Aero Engine Services Ltd., 70 Chun Choi Street, Tseung Kwan O Industrial Estate, Tseung Kwan O, N.T. or alternatively, email us via \"Apply Now\".\n\nPlease feel free to visit our company website at www.haesl.com.\n\nData collected will be used for recruitment purpose only\n\n\"Applicants not invited for interview within three weeks from the date of submitting CV may consider their application unsuccessful\"", "employment_types": ["Full Time", "Permanent"], "selling_points": ["Double Pay, Performance Bonus", "Dental & Medical Insurance", "Transportation Allowance"], "locations": ["Tseung Kwan O"], "categories": ["Transportation & Logistics", "Others", "Inventory / Warehousing"], "post_time": "2022-01-14T09:30:50Z", "salary": {"currency": null, "max": null, "min": null, "period": "monthly", "term": null}, "salary_visible": false, "title_keywords": ["storekeeper"], "responsibilities": ["daily reports"], "requirements": {"degrees": ["hkdse"], "majors": [], "languages": ["english", "chinese"], "language_level": ["good command"], "hard_skills": ["excel", "word", "sap", "ms office"], "soft_skills": ["communication skills", "hardworking"], "languages_combined": [{"language": "english", "language_level": ["good command"]}, {"language": "chinese", "language_level": ["good command"]}]}, "experience_required": {"duration": ["minimum 2 years"], "field": ["relevant working experience"]}}, {"job_id": "100003009050509", "location_code": "hk", "company": "Guardforce Ltd", "job_title": "Sales Executive", "description": "Responsibilities\n\nDevelop sales channels and evaluate customer needs\nTo seek out new sales opportunities through social media, networking, etc.\nSet up meetings with potential\u00a0clients and listening to their needs actively\nSupport reporting manager to execute\u00a0sales strategies or projects\u00a0and achieve sales targets\nAssist in preparing sales presentation/ briefing to customers\nPerform ad-hoc duties as assigned\n\nRequirements\n\n1-2 years of\u00a0\u00a0relevant working experience, preferably with sales experience in courier/ logistics, Fresh graduate will be considered\nA good team player with pleasant and outgoing personality\nAble to work and communicate effectively with internal/ external parties and customers\nWell-organized and self-motivated\nFamiliar with MS Word, Excel and PowerPoint\nGood command of both spoken and written English and Chinese, conversational Mandarin is preferable\n\nCome & Join Us! Attractive remuneration packages will be offered to the right candidate.\n\nInterested parties, please send your application together with a full resume stating your\u00a0present and expected salary & date of availability to:\n\nFax: 2333-3481; or\nMail: 1/F., Guardforce Centre, 3 Hok Yuen Street East, Hung Hom, Kowloon.\n\nPersonal data provided in your application will be kept in the strictest confidence. It will only be used for employment-related purposes by any entity within our Group. Applicants not notified within 1 month will be considered as unsuccessful. Unsuccessful application may be kept for another 3 months for new openings or consideration by another entity within our Group before properly shredded.\n\nSecurity Licence No. : 0092", "employment_types": ["Full Time", "Permanent"], "selling_points": [], "locations": ["Hung Hom"], "categories": ["Transportation & Logistics", "Others", "Inventory / Warehousing", "Private Transportation"], "post_time": "2022-01-14T10:35:09Z", "salary": {"currency": null, "max": null, "min": null, "period": "monthly", "term": null}, "salary_visible": false, "title_keywords": ["sales executive"], "responsibilities": ["social media", "reporting", "develop", "evaluate", "ad-hoc duties"], "requirements": {"degrees": ["fresh graduate"], "majors": [], "languages": ["english", "chinese", "mandarin"], "language_level": ["conversational", "good command"], "hard_skills": ["excel", "powerpoint", "ms word"], "soft_skills": ["outgoing personality", "good team player", "self-motivated", "well-organized", "pleasant"], "languages_combined": [{"language": "english", "language_level": ["good command"]}, {"language": "chinese", "language_level": ["good command"]}, {"language": "mandarin", "language_level": ["conversational", "good command"]}]}, "experience_required": {"duration": ["1-2 years"], "field": ["logistics", "relevant working experience"]}}, {"job_id": "100003009049770", "location_code": "hk", "company": "KSS Technology Limited", "job_title": "\u591c\u66f4\u5009\u52d9\u54e1**", "description": "\n\u8077\u8cac :\u8ca0\u8cac\u5728\u8ca8\u5009\u5167\u642c\u904b,\u62c6\u8ca8,\u4e0a\u8ca8\u53ca\u9ede\u8ca8\n\n\u8cc7\u6b77 :\u5c0f\u516d\u7a0b\u5ea6; \u61c2\u95b1\u8b80\u4e2d\u6587; \u61c2\u95b1\u8b80\u82f1\u6587\n\n\u5f85\u9047 :\u6bcf\u6708$16,000, \u6709\u91ab\u7642\u6d25\u8cbc, \u5e74\u7d42\u82b1\u7d05 \u53ca\u8d85\u6642\u5de5\u4f5c\u6d25\u8cbc, \u4e0b\u534810\u6642\u81f3\u4e0a\u53487\u6642, \u6bcf\u9031\u5de5\u4f5c6\u5929\n\n\u7533\u8acb\u9808\u77e5 :\u6c42\u8077\u8005\u53ef\u81f4\u96fb24620821\u8207KSS TECHNOLOGY LIMITED\u4f55\u5c0f\u59d0\u806f\u7d61\u3002\n\n", "employment_types": ["Full Time"], "selling_points": [], "locations": ["Kwai Tsing Area"], "categories": ["Transportation & Logistics", "Others", "Inventory / Warehousing", "Supply Chain"], "post_time": "2022-01-14T09:13:09Z", "salary": {"currency": null, "max": null, "min": null, "period": "monthly", "term": null}, "salary_visible": false, "title_keywords": [], "responsibilities": [], "requirements": {"degrees": [], "majors": [], "languages": [], "language_level": [], "hard_skills": [], "soft_skills": [], "languages_combined": []}, "experience_required": {"duration": [], "field": []}}, {"job_id": "100003009045269", "location_code": "hk", "company": "Wah Seng Far East Limited", "job_title": "\u5009\u52d9\u54e1/\u7406\u8ca8\u54e1", "description": "\n\u8077\u8cac :\u4e00\u822c\u5009\u52d9\u54e1/\u7406\u8ca8\u54e1\u5de5\u4f5c, \u4e00\u822c\u5009\u52d9\u5de5\u4f5c, \u5982: \u6536\u8ca8, \u9ede\u8ca8, \u57f7\u8ca8, \u4e0a\u67b6, \u767c\u8ca8\u7b49\n\n\u8cc7\u6b77 :\u6c92\u6709\u5b78\u6b77\u8981\u6c42; 2\u5e74\u7d93\u9a57; \u826f\u597d\u7cb5\u8a9e; \u61c2\u95b1\u8b80\u4e2d\u6587; \u6709\u8cac\u4efb\u5fc3, \u5177\u5718\u968a\u5408\u4f5c\u7cbe\u795e\n\n\u5f85\u9047 :\u6bcf\u6708$14,000 - $14,600, \u6709\u96d9\u7ce7, \u52e4\u5de5\u734e\u91d1 \u53ca\u9280\u884c\u5047\u671f, \u661f\u671f\u4e00\u81f3\u516d: \u4e0a\u53489\u6642\u81f3\u4e0b\u53486\u6642, \u6bcf\u9031\u5de5\u4f5c6\u5929, \u6bcf\u5929\u5de5\u4f5c 9 \u5c0f\u6642\n\n\u7533\u8acb\u9808\u77e5 :\u6c42\u8077\u8005\u53ef\u81f4\u96fb24778522\u8207\u83ef\u6210\u9060\u6771\u6709\u9650\u516c\u53f8\u9ea5\u5c0f\u59d0\u806f\u7d61\u3002\n\n", "employment_types": ["Full Time"], "selling_points": [], "locations": ["Yuen Long"], "categories": ["Transportation & Logistics", "Others", "Inventory / Warehousing", "Supply Chain"], "post_time": "2022-01-13T07:31:32Z", "salary": {"currency": null, "max": null, "min": null, "period": "monthly", "term": null}, "salary_visible": false, "title_keywords": ["\u7406\u8ca8\u54e1", "\u5009\u52d9\u54e1"], "responsibilities": [], "requirements": {"degrees": [], "majors": [], "languages": [], "language_level": [], "hard_skills": [], "soft_skills": [], "languages_combined": []}, "experience_required": {"duration": [], "field": []}}, {"job_id": "100003009045310", "location_code": "hk", "company": "S.P.H (Hong Kong) International Trading Co., Limited", "job_title": "\u5009\u52d9\u52a9\u7406", "description": "\n\u8077\u8cac :\u8ca0\u8cac\u5354\u52a9\u8ca8\u5009\u4e3b\u7ba1\u5009\u5eab\u5de5\u4f5c,\u5de5\u4f5c\u9592\u9918\u6642\u9700\u914d\u5408\u524d\u53f0\u92b7\u552e\u540c\u4e8b\u53d6\u8ca8,\u9001\u8ca8\u548c\u7406\u8ca8\u4e8b\u5b9c\n\n\u8cc7\u6b77 :\u4e2d\u4e09\u7a0b\u5ea6; \u4e00\u822c\u7cb5\u8a9e; \u4e00\u822c\u666e\u901a\u8a71; \u4e00\u822c\u82f1\u8a9e; \u61c2\u8b80\u5beb\u4e2d\u6587; \u5de5\u4f5c\u52e4\u596e\u4e0a\u9032,\u6709\u8cac\u4efb\u5fc3,\u5177\u76f8\u95dc\u5de5\u4f5c\u7d93\u9a57\u512a\u5148\n\n\u5f85\u9047 :\u6bcf\u6708$15,000, \u6709\u52e4\u5de5\u53ca\u5348\u98ef\u6d25\u8cbc, \u661f\u671f\u4e00\u81f3\u516d: \u4e0a\u534810\u6642\u81f3\u4e0b\u53487\u6642, \u6bcf\u9031\u5de5\u4f5c6\u5929\n\n\u7533\u8acb\u9808\u77e5 :\u6c42\u8077\u8005\u53ef\u96fb\u90f5(Apply Now)\u5c65\u6b77\u8868\u7d66\u5c1a\u54c1\u6ed9(\u9999\u6e2f)\u63a7\u80a1\u6709\u9650\u516c\u53f8\u3002\u5982\u8981\u7d22\u53d6\u6536\u96c6\u500b\u4eba\u8cc7\u6599\u8072\u660e, \u8acb\u8207\u937e\u5c0f\u59d0(Tel:34272313)\u806f\u7d61\u3002\n\n", "employment_types": ["Full Time"], "selling_points": [], "locations": ["Tsim Sha Tsui"], "categories": ["Transportation & Logistics", "Others", "Inventory / Warehousing", "Supply Chain"], "post_time": "2022-01-13T07:35:59Z", "salary": {"currency": null, "max": null, "min": null, "period": "monthly", "term": null}, "salary_visible": false, "title_keywords": ["\u5009\u52d9\u52a9\u7406"], "responsibilities": [], "requirements": {"degrees": [], "majors": [], "languages": [], "language_level": [], "hard_skills": [], "soft_skills": [], "languages_combined": []}, "experience_required": {"duration": [], "field": []}}, {"job_id": "100003009045342", "location_code": "hk", "company": "Hong Kong Ningxia Unique & Premium Products Centre Co., Limited", "job_title": "\u517c\u8077\u5009\u52d9\u54e1/\u7406\u8ca8\u54e1**", "description": "\n\u8077\u8cac :\u4e00\u822c\u5009\u52d9\u54e1\u5de5\u4f5c\uff0c\u8ca0\u8cac\u5e97\u8216\u53ca\u8ca8\u5009\u7684\u5009\u52d9\u5de5\u4f5c\u5305\u62ec\u642c\u904b\u8ca8\u7269\uff0c\u9ede\u8ca8\uff0c\u57f7\u8ca8\uff0c\u5305\u88dd\uff0c\u51fa\u8ca8\u3002\n\n\u8cc7\u6b77 :\u6c92\u6709\u5b78\u6b77\u8981\u6c42; \u4e00\u822c\u7cb5\u8a9e; \u4e00\u822c\u666e\u901a\u8a71; \u61c2\u8b80\u5beb\u4e2d\u6587\n\n\u5f85\u9047 :\u6bcf\u5c0f\u6642$60.00 - $65.00, \u661f\u671f\u4e00\u81f3\u4e94: \u4e0b\u53482\u6642\u81f3\u4e0b\u53486\u6642\u6216\u661f\u671f\u516d: \u4e0a\u53489\u6642\u81f3\u4e0b\u53481\u6642, \u6bcf\u9031\u5de5\u4f5c3\u5929\u81f35\u5929, \u6bcf\u5929\u5de5\u4f5c 4 \u5c0f\u6642\n\n\u7533\u8acb\u9808\u77e5 :\u6c42\u8077\u8005\u53ef\u81f4\u96fb21857698\u8207\u9999\u6e2f\u5be7\u590f\u540d\u7279\u512a\u7522\u54c1\u4e2d\u5fc3\u6709\u9650\u516c\u53f8\u9ad8\u5148\u751f\u806f\u7d61\u3002\n\n", "employment_types": ["Part Time"], "selling_points": [], "locations": ["Sheung Wan"], "categories": ["Transportation & Logistics", "Others", "Inventory / Warehousing", "Supply Chain"], "post_time": "2022-01-13T07:39:40Z", "salary": {"currency": null, "max": null, "min": null, "period": "hourly", "term": null}, "salary_visible": false, "title_keywords": ["\u7406\u8ca8\u54e1"], "responsibilities": [], "requirements": {"degrees": [], "majors": [], "languages": [], "language_level": [], "hard_skills": [], "soft_skills": [], "languages_combined": []}, "experience_required": {"duration": [], "field": []}}, {"job_id": "100003009047220", "location_code": "hk", "company": "Supergo Company Limited", "job_title": "\u5009\u52d9\u54e1 (\u9700\u8ddf\u8eca\u9001\u8ca8)", "description": "\u8077\u8cac :\n\n\u4e00\u822c\u5009\u52d9\u5de5\u4f5c (\u8a2d\u6709\u51b7\u6c23) ;\n\u8ca0\u8cac\u65e5\u5e38\u5009\u52d9\u904b\u4f5c;\n\u5354\u52a9\u6536\u8ca8\u3001\u57f7\u8ca8\u3001\u5206\u8ca8\u3001\u51fa\u8ca8\u53ca\u6574\u7406\u8ca8\u5009;\u00a0\n\u9700\u8ddf\u8eca\u9001\u8ca8\u5230\u5404\u9023\u9396\u5e97\n\n\u8cc7\u6b77 :\n\n\u4e2d\u4e09\u7a0b\u5ea6;\n1\u5e74\u76f8\u95dc\u7d93\u9a57;\n\u826f\u597d\u7cb5\u8a9e\u512a\u5148;\u00a0\u7565\u61c2\u4e00\u822c\u82f1\u8a9e;\n\u9700\u61c2\u8b80\u5beb\u4e2d\u6587; \u7565\u61c2\u8b80\u5beb\u82f1\u6587;\n\u5177\u6709\u57fa\u672c\u96fb\u8166\u64cd\u4f5c\u77e5\u8b58; \u9700\u61c2\u6383\u7784\u689d\u78bc\u64cd\u4f5c\n\n\u54e1\u5de5\u798f\u5229:\n\n\u52e4\u5de5\u734e\u91d1\n\u9280\u884c\u5047\u671f\n\u734e\u52f5\u6027\u82b1\u7d05\n\u91ab\u7642\u798f\u5229\n\u6649\u5347\u6a5f\u6703\n\u54e1\u5de5\u8cfc\u7269\u512a\u60e0\n\n\u5de5\u4f5c\u6642\u9593:\n\n\u661f\u671f\u4e00\u81f3\u516d: \u4e0a\u53489\u6642\u534a\u81f3\u4e0b\u53486\u6642,\u00a0 \u661f\u671f\u516d\u9577\u77ed\u9031\n\n\u6c42\u8077\u8005\u53ef\u81f4\u96fb25257311\u8207\u5d07\u9ad8\u6709\u9650\u516c\u53f8\u5510\u5c0f\u59d0\u806f\u7d61\u3002", "employment_types": ["Full Time"], "selling_points": [], "locations": ["Kwun Tong Area"], "categories": ["Transportation & Logistics", "Others", "Inventory / Warehousing", "Supply Chain"], "post_time": "2022-01-14T02:38:14Z", "salary": {"currency": null, "max": null, "min": null, "period": "monthly", "term": null}, "salary_visible": false, "title_keywords": ["\u5009\u52d9\u54e1"], "responsibilities": [], "requirements": {"degrees": [], "majors": [], "languages": [], "language_level": [], "hard_skills": [], "soft_skills": [], "languages_combined": []}, "experience_required": {"duration": [], "field": []}}, {"job_id": "100003009050749", "location_code": "hk", "company": "GEODIS Hong Kong Limited", "job_title": "Operation Clerk, Air Import", "description": "Responsibilities:\n\n1. Responsible for handling daily inbound operation, daily report preparing, transportation arrangement, billing and filing.\n2. Communicate with internal & overseas customers to ensure a smooth running of the process;\n3. Assist to solve customers issues.\n4. Handle complaints and develop corrective measurement;\n5. Responsible for effective working practices with the customer.\n6. Import Declaration\n\nRequirements:\n\n1.\u00a0Tertiary education preferred\n2. Minimum 1 years of working experience in airfreight industry\n3. Good command of English & Chinese, good spoken Cantonese and Mandarin\n4. Independent strong personal motivation and well disciplines\n5. Responsible, self-managed and willing to work overtime.\n6. Good computer skill on Excel, Word and PowerPoint etc.\n7. Good analytical mind and commercial sense\n\nWe offer a rewarding package and company benefits including double pay, bonus, 15 days annual leave, medical insurance etc. Interested parties please send your full resume with current and expected salary to us.\n\nPersonal data collected will be used for recruitment purpose only.\n\nOur data processing are compliant with data protection regulations. To learn about GEODIS Privacy Policy or exercise your rights, go to http://geodis.com/dp/recruitment-privacy-policy\n\n", "employment_types": ["Full Time", "Permanent"], "selling_points": ["Handle daily air import shipments", "15 days annual leave", "Medical & Dental Insurance Coverage"], "locations": ["Cheung Sha Wan"], "categories": ["Transportation & Logistics", "Others", "Freight Forwarding", "Supply Chain"], "post_time": "2022-01-14T11:16:03Z", "salary": {"currency": null, "max": null, "min": null, "period": "monthly", "term": null}, "salary_visible": false, "title_keywords": ["operation clerk"], "responsibilities": ["communicate with", "measurement", "develop", "handle complaints", "daily report"], "requirements": {"degrees": [], "majors": [], "languages": ["cantonese", "english", "chinese", "mandarin"], "language_level": ["good command", "good"], "hard_skills": ["excel", "computer skill", "word", "powerpoint"], "soft_skills": ["work overtime", "independent", "responsible", "self-managed", "analytical mind"], "languages_combined": [{"language": "cantonese", "language_level": ["good", "good command"]}, {"language": "english", "language_level": ["good", "good command"]}, {"language": "chinese", "language_level": ["good", "good command"]}, {"language": "mandarin", "language_level": ["good", "good command"]}]}, "experience_required": {"duration": ["minimum 1 years"], "field": []}}, {"job_id": "100003009049858", "location_code": "hk", "company": "Orient Overseas Container Line Ltd (OOCL)", "job_title": "Assistant Manager/ Deputy Manager, Traffic Control Centre (Ref: AMDM/TCC)", "description": "Responsibilities:\nTo implement daily traffic control of vessels, including various service of Traffic flow\nTo handle the disruptions of assigned FND in Asia\nTo identify and resolve ad-hoc traffic problem\nTo coordinate closely with partners on coastal space exchange and oceanic slots buy/sell\nTo maintain and issue regular traffic reports\nRequirements:\nUniversity graduate in Business, Shipping & Logistics or related disciplines\nMinimum 6 years of relevant working experience, preferably in shipping industry\nGood communication, analytical, decision making and problem solving skills\nAble to work under pressure and possess business sense\nProficiency in spoken and written English and Chinese; Putonghua is an added advantage\nAdvanced level of using MS Applications such as Excel\nInterested parties please send your application letter with detailed resume and expected salary by clicking \"Apply Now\" .\n(Data collected will be used for recruitment purpose only.)", "employment_types": ["Full Time", "Permanent"], "selling_points": ["To handle the disruptions of assigned FND in Asia", "To identify and resolve ad-hoc traffic problem", "University graduate in Business, Shipping"], "locations": ["Wan Chai"], "categories": ["Transportation & Logistics", "Others", "Sales, CS & Business Devpt", "Business Development", "Shipping"], "post_time": "2022-01-14T09:19:28Z", "salary": {"currency": null, "max": null, "min": null, "period": "monthly", "term": null}, "salary_visible": false, "title_keywords": ["assistant manager", "deputy manager"], "responsibilities": ["ad-hoc", "control", "coordinate", "maintain", "reports"], "requirements": {"degrees": ["university graduate"], "majors": ["related disciplines", "business"], "languages": ["putonghua", "english", "chinese"], "language_level": ["advantage", "proficiency"], "hard_skills": ["excel", "problem solving skills", "ms applications"], "soft_skills": ["decision making", "advanced", "business sense", "communication", "problem solving skills", "work under pressure"], "languages_combined": [{"language": "putonghua", "language_level": ["advantage"]}, {"language": "english", "language_level": ["proficiency"]}, {"language": "chinese", "language_level": ["proficiency"]}]}, "experience_required": {"duration": ["minimum 6 years"], "field": ["relevant working experience", "shipping industry"]}}, {"job_id": "100003009050417", "location_code": "hk", "company": "Guardforce Ltd", "job_title": "\u4f4f\u5b85\u4fdd\u5b89\u7d93\u7406 / Security Manager (On-site)", "description": "\u8077\u8cac\uff1a\n\u76e3\u7763\u4fdd\u5b89\u5718\u968a\u4e26\u78ba\u4fdd\u63d0\u4f9b\u6700\u4f73\u670d\u52d9\n\u57f9\u8a13\u3001\u76e3\u7763\u53ca\u8a55\u6838\u5c6c\u4e0b\u54e1\u5de5\uff0c\u78ba\u4fdd\u5176\u5de5\u4f5c\u8868\u73fe\u9054\u6a19\n\u9818\u5c0e\u5718\u968a\u9032\u884c\u4e8b\u4ef6\u7ba1\u7406\u548c\u885d\u7a81\u89e3\u6c7a\n\u5236\u5b9a\u4fdd\u5b89\u6307\u5f15\u53ca\u7a0b\u5e8f\n\u8655\u7406\u5ba2\u6236\u67e5\u8a62\u53ca\u6295\u8a34\n\u64b0\u5beb\u4e8b\u4ef6\u5831\u544a\u66f8\u5411\u516c\u53f8\u532f\u5831\n\n\u8981\u6c42\uff1a\n\n\u4e2d\u4e94\u7a0b\u5ea6\u6216\u4ee5\u4e0a\n\u5341\u5e74\u6216\u4ee5\u4e0a\u4fdd\u5b89\u4e3b\u7ba1\u7d93\u9a57\n\u61c2\u8b80\u5beb\u4e2d\u6587\u53ca\u6587\u66f8\u8655\u7406\n\u6301\u6709\u6548QASRS\u57f9\u8a13\u8b49\u66f8\u53ca\u4fdd\u5b89\u4eba\u54e1\u8a31\u53ef\u8b49\n\n\u5de5\u4f5c\u5730\u5340\uff1a\u8343\u7063\n\n\u6709\u8208\u8da3\u8005\u53ef\u5728\u8fa6\u516c\u6642\u9593\u5230\u4ee5\u4e0b\u5730\u5740\u898b\u5de5:\n\n\u8fa6\u516c\u6642\u9593: \u661f\u671f\u4e00\u81f3\u4e9409:00-12:00, 14:00-17:00 (\u516c\u773e\u5047\u671f\u9664\u5916)\n\n\u516c\u53f8\u5730\u5740: \u7d05\u78e1\u9db4\u5712\u6771\u88573\u865f\u885e\u5b89\u4e2d\u5fc32\u6a13206\u5ba4(\u9ec3\u57d4\u6e2f\u9435\u7ad9A\u51fa\u53e3)\n\n\u6216\u8acbwhatsapp 6025 6252/ \u81f4\u96fb 2765 2819\u00a0\u67e5\u8a62\u6709\u95dc\u4fdd\u5b89\u5de5\u4f5c\n\n\n", "employment_types": ["Full Time", "Contract"], "selling_points": [], "locations": ["Tsuen Wan Area"], "categories": ["Transportation & Logistics", "Others", "Inventory / Warehousing", "Private Transportation"], "post_time": "2022-01-14T10:22:20Z", "salary": {"currency": null, "max": null, "min": null, "period": "monthly", "term": null}, "salary_visible": false, "title_keywords": ["manager"], "responsibilities": [], "requirements": {"degrees": [], "majors": [], "languages": [], "language_level": [], "hard_skills": [], "soft_skills": [], "languages_combined": []}, "experience_required": {"duration": [], "field": []}}]