[{"job_id": "100003009050188", "location_code": "hk", "company": "Sunrise Engineering Plastics Co Limited", "job_title": "Shipping Officer", "description": "Job Description:\u00a0Senior / Junior Shipping Clerk\n\n\u00a0Job Duties:\n\n\u00a0\u00a0\u00a0\u00a0\u00a0\u00a0\u00a0Independently handle full set of I/E documents, custom declaration to meet requirements;\n\u00a0\u00a0\u00a0\u00a0\u00a0\u00a0\u00a0Coordination with forwarders, and factories about all transportation issues including ocean and air freight forwarding, Liaise with related parties, shipment arrangement independently;\n\nRequirements:\n\n\u00a0\u00a0\u00a0\u00a0\u00a0\u00a0\u00a0Form 5 or DSE above;\n\u00a0\u00a0\u00a0\u00a0\u00a0\u00a0\u00a01-2 years working experience in shipping department of the trading company dealing in US , UK & Europe market.\n\u00a0\u00a0\u00a0\u00a0\u00a0\u00a0\u00a0Good English, Mandarin (Spoken and Written);\n\u00a0\u00a0\u00a0\u00a0\u00a0\u00a0\u00a0Understand the shipment process and work flow of factory in China;\n\u00a0\u00a0\u00a0\u00a0\u00a0\u00a0\u00a0Responsible for handling import /export documents , shipment and logistics arrangement ,Letter of Credit.\n\u00a0\u00a0\u00a0\u00a0\u00a0\u00a0\u00a0Proficiency in PC skills, such as MS office, Excel and Chinese word processing;\n\u00a0\u00a0\u00a0\u00a0\u00a0\u00a0\u00a0Good problem solving skill;\n\u00a0\u00a0\u00a0\u00a0\u00a0\u00a0\u00a0Independent, initiative and responsible;.\n\u00a0\u00a0\u00a0\u00a0\u00a0\u00a0\u00a0Immediate available is highly preferable\n\nCompany offers attractive remuneration package including\u00a05-day work, 12 days AL + banking holidays, double pay\u00a0to the right candidate.\u00a0\u00a0Interested parties please email us your full resume in MS Word or PDF format including your current and expected salary.\n\nAll information received will be kept in strict confidence and only for employment related purpose.\n\nAdditional Information\n\nCareer Level\n\nEntry Level\n\nQualification\n\nSchool Certificate\n\nYears of Experience\n\nJob Type\n\nFull Time, Permanent\n\nJob Functions\n\nTransportation & Logistics,\u00a0Freight Forwarding,\u00a0Shipping", "employment_types": ["Full Time", "Permanent"], "selling_points": [], "locations": ["Tsim Sha Tsui"], "categories": ["Transportation & Logistics", "Documentary Credit / Bills Processing", "Inventory / Warehousing", "Shipping"], "post_time": "2022-01-17T08:56:49Z", "salary": {"currency": null, "max": null, "min": null, "period": "monthly", "term": null}, "salary_visible": false, "title_keywords": ["shipping officer"], "responsibilities": ["shipping", "shipment arrangement", "air freight", "custom declaration", "coordination with", "liaise with"], "requirements": {"degrees": ["form 5", "dse"], "majors": [], "languages": ["english", "chinese", "mandarin"], "language_level": ["proficiency", "good"], "hard_skills": ["excel", "chinese word processing", "problem solving", "pc skills", "ms office"], "soft_skills": ["problem solving skill", "independent", "initiative", "responsible"], "languages_combined": [{"language": "english", "language_level": ["good"]}, {"language": "chinese", "language_level": ["proficiency"]}, {"language": "mandarin", "language_level": []}]}, "experience_required": {"duration": ["1-2 years"], "field": ["trading"]}}, {"job_id": "100003009053844", "location_code": "hk", "company": "Jakks Pacific (HK) Limited", "job_title": "Senior Shipping Clerk / Shipping Clerk", "description": "Job Responsibilities:\n\nHandle full set of shipping arrangement for import/export include getting freight quotation, PO processing, Packing List, Export Declaration documents e,g. Certificate of Origin (worldwide) and large volume of data entry;\nWork of the preparation, submission, recording & filing of import/export shipping documents;\nPrepare daily & monthly Logistics & Inventory report;\nWell communication skills with forwarders;\nProvide support to ad hoc tasks as assigned.\n\nRequirements:\n\nForm 5 or DSE graduate;\nMinimum 3-4 years in related working experience;\nKnowledge & experience in import/export procedures and custom declaration regulations including CEPA & TradeLink application;\nFactory of plastic field experience is an advantage;\nFamiliar with EXCEL and MS Office;\nTeam player, pro-active, willing to meet challenge and learn attitude;\nGood command in spoken and written English, Chinese and Mandarin;\nImmediate available would be highly preferred.\n\n\u00a0We offer 5-day work with attractive salary and fringe benefits to the right candidate.\n\n\u00a0Please send your full resume with availability, current & expected salary to HR Department:", "employment_types": ["Full Time", "Permanent"], "selling_points": ["5days work / Flexi-hours / 12AL+ / Double Pay", "Medical & Life Insurance / Company Leave", "2yr exp in US Toys / Handle full set I/E Shpg & LC"], "locations": ["Tsim Sha Tsui"], "categories": ["Transportation & Logistics", "Documentary Credit / Bills Processing", "Inventory / Warehousing", "Shipping"], "post_time": "2022-01-17T07:36:47Z", "salary": {"currency": null, "max": null, "min": null, "period": "monthly", "term": null}, "salary_visible": false, "title_keywords": ["shipping clerk"], "responsibilities": ["shipping documents", "provide support", "shipping", "data entry", "inventory", "quotation", "ad hoc tasks", "packing list", "communication", "certificate of origin", "logistics", "report"], "requirements": {"degrees": ["form 5", "dse"], "majors": [], "languages": ["english", "chinese", "mandarin"], "language_level": ["good command"], "hard_skills": ["excel", "ms office"], "soft_skills": ["team player", "pro-active"], "languages_combined": [{"language": "english", "language_level": ["good command"]}, {"language": "chinese", "language_level": ["good command"]}, {"language": "mandarin", "language_level": ["good command"]}]}, "experience_required": {"duration": ["minimum 3-4 years"], "field": ["related"]}}, {"job_id": "100003009054958", "location_code": "hk", "company": "Pearl Lam Galleries Limited", "job_title": "Shipping Supervisor", "description": "Job Description:\n\nCoordinate with factories/forwarder in shipping schedule\nPrepare full set of shipping documentation\nPresent documentation to bank\n\nRequirements:\n\nForm 5 / DSE or above\n2 years or above working experience in shipping field for toys / stationery / garment trading industry (mainly for US market). More experience will be considered as Senior Shipping Clerk\nHandle full set of I/E shipping & L/C banking documents independently\nExperience in JDE system is preferred\nGood computer skills especially in Word, Excel and Tradelink\nGood command of spoken and written English, Cantonese/Chinese and Mandarin\nSelf-motivated, with good interpersonal skill, able to work under pressure and overtime\nImmediately available is preferred\n\nBenefit:\n\nFive-day work week\nFlexible working hours\nMedical insurance\nLife insurance\nDouble pay\nDiscretionary Bonus\n12+ days annual leave\nCompany holiday\n\nInterested parties are invited to send their applications with full employment history, current and expected salary and quoting reference number in the subject and on the envelope to:\n\nHrrecruit@ jakks.com.hk via e-mail or JAKKS Pacific Group, 12/F., Wharf T & T Centre, 7 Canton Road, Tsim Sha Tsui, Kowloon, Hong Kong by post.\u00a0\n\nPlease visit our website for more information about us at:\u00a0www.jakks.com\n\n\u00a0* Personal data collected will be used for recruitment purpose only.\u00a0", "employment_types": ["Full Time"], "selling_points": ["Shipping", "Logistics", "Warehouse"], "locations": ["Chai Wan"], "categories": ["Transportation & Logistics", "Shipping"], "post_time": "2022-01-17T15:07:52Z", "salary": {"currency": "HKD", "max": 19999, "min": 14000, "period": "monthly", "term": null}, "salary_visible": true, "title_keywords": ["shipping supervisor"], "responsibilities": ["shipping schedule", "documentation", "shipping", "coordinate with"], "requirements": {"degrees": ["form 5", "dse"], "majors": [], "languages": ["cantonese", "english", "chinese", "mandarin"], "language_level": ["good command"], "hard_skills": ["excel", "c", "computer skills", "word"], "soft_skills": ["work under pressure", "self-motivated", "independently", "interpersonal skill"], "languages_combined": [{"language": "cantonese", "language_level": ["good command"]}, {"language": "english", "language_level": ["good command"]}, {"language": "chinese", "language_level": ["good command"]}, {"language": "mandarin", "language_level": ["good command"]}]}, "experience_required": {"duration": ["2 years"], "field": ["toys", "garment", "trading"]}}, {"job_id": "100003009056412", "location_code": "hk", "company": "Stack's Bowers and Ponterio, Limited", "job_title": "Consignment and Shipping Assistant", "description": "Pearl Lam Galleries are seeking an experienced Shipping Supervisor. \u00a0Candidate must be accustomed working in an extremely fast-paced environment, must posses excellent communication skills, ability to work in a team environment, and be extremely detail-oriented, courteous and professional.\n\nYou will be responsible for handling full set of import and export shipping documentations, logistics and order management to different clients, select appropriate service providers by obtaining quotes from various shipping companies, prepare proforma invoices and packing lists as well as liaising with international shipping colleagues to ensure smooth deliveries and arrangements.\n\nThe ideal candidate should coordinate all elements and products of global exhibitions to ensure safe and cost effective movements of property, assist on any logistics issues and ensure all legal and compliance regulations are within standard. \u00a0\n\nYou will be working with the Art Handling team assisting installing and de-installing exhibitions / art fairs.\n\nMinimum of one year experience working in logistics/shipping, candidate with contemporary art experience is definitely an advantage. \u00a0Working days: Mon - Sat + (public holidays if required) - to start immediately. \u00a0Working hours: 10:00 - 19:00 (with one hour lunch time). \u00a0Working location: Chaiwan. \u00a0Please send your CV with subject \"Application to the post of Shipping Supervisor\" for interview arrangement. \u00a0No phone calls or in-person visits.", "employment_types": ["Full Time", "Permanent"], "selling_points": [], "locations": ["Tsim Sha Tsui"], "categories": ["Admin & HR", "Clerical / Admin Staff", "Transportation & Logistics", "Shipping", "Sales, CS & Business Devpt", "Sales Administration"], "post_time": "2022-01-18T04:14:27Z", "salary": {"currency": null, "max": null, "min": null, "period": "monthly", "term": null}, "salary_visible": false, "title_keywords": ["shipping", "assistant"], "responsibilities": ["regulations", "sat", "order management", "shipping", "cost", "invoices", "compliance", "liaising with", "communication", "coordinate", "installing", "logistics", "interview arrangement", "phone calls"], "requirements": {"degrees": [], "majors": [], "languages": [], "language_level": [], "hard_skills": ["pearl", "no", "import and export", "safe", "documentations"], "soft_skills": ["communication skills", "courteous", "responsible", "fast-paced environment", "detail-oriented", "smooth", "ideal"], "languages_combined": []}, "experience_required": {"duration": ["minimum of one year"], "field": ["logistics"]}}, {"job_id": "100003009052132", "location_code": "hk", "company": "", "job_title": "Shipping Officer / Senior Shipping Coordinator", "description": "Key responsibilities (Not limited to the following):\n\nCoordinating, monitoring, tracking, and processing incoming consignments\nOpening packages, verifying and labeling contents, creating a record of each item in the database\nKeeping items in database up to date and accurate, auditing contracts and other consignment paperwork for accuracy\nResearching the status of consignments\nProcessing shipping requests\nMonitor the progress of shipments and deliveries, conferring with suppliers to troubleshoot and rectify problems in a timely manner and ensuring that interested parties are apprised of the status of the shipment.\nParticipate in ad-hoc duties as requested, not limited to additional main and mid-season auction based duties which may include, but are not limited to, telephone and online bidding support\n\nQualification Requirements:\n\n\n\nHigh School Diploma is a must (College degree is preferred). Fresh graduate is also considered\nFluent verbal and written English and Chinese (including Mandarin)\nAbility to learn quickly and apply knowledge\nExcellent communication and interpersonal skills; demonstrated ability to communicate with all organizational levels\nAbility to work both independently and as a team member to complete the task at hand\nStrong organizational skills to set priorities, multi task and meet deadlines\nProficiency in Microsoft Offices skills\nDuring auction, flexibility to work overtime and weekend hours when necessary is required", "employment_types": ["Full Time"], "selling_points": [], "locations": ["Kowloon City Area"], "categories": ["Transportation & Logistics", "Others", "Shipping", "Supply Chain"], "post_time": "2022-01-17T07:34:09Z", "salary": {"currency": null, "max": null, "min": null, "period": "monthly", "term": null}, "salary_visible": false, "title_keywords": ["shipping coordinator", "shipping officer"], "responsibilities": ["shipping", "contracts", "monitoring", "database", "contents", "auditing", "tracking"], "requirements": {"degrees": [], "majors": [], "languages": [], "language_level": [], "hard_skills": [], "soft_skills": [], "languages_combined": []}, "experience_required": {"duration": [], "field": []}}, {"job_id": "100003009052825", "location_code": "hk", "company": "Tim Toys Ltd", "job_title": "MERCHANDISING and SHIPPING EXECUTIVE", "description": "We are a trading company.\u00a0 We invite you to be our Shipping Officer or Senior Shipping Coordinator.\nWe offer you 5 day's work, medical insurance, annual leave and 13th month salary.\u00a0\n\nJobs Description :\u00a0\n\nHandle full set of shipping documents independently\nResponsible for vendor payment\nManage each shipment delivery from factories to customer to ensure all required steps are done and goods are delivered in a timely and cost effective manner\nMaintain shipping records - shipment report for all shipments\nLiaise with suppliers, carriers, transportation company and vendors & check all applicable documentation is in place and fully compliance for Import / Export.\nPreparing weekly reports and keeping them up to date\nAd\u00a0 Ho project as assigned by management\n\nRequirements :\n\nF5 or above or equivalent level\nMinimum 1 - 5 years working exper5ience in shipping field\nGood experience in handling full sets of I/E documents, shipping bookings, SI, shipping arrangements with factories and forwarders\nProficient in both spoken and written in English and Mandarin\u00a0\nSelf motivated, responsible, well organized and able to work independently\nimmediately available will be advantage\nless experience will be consider as senior shipping co-ordinator\nInterested parties, please send your resume, with expected salary and availability\u00a0to our HR email ,\u00a0 or contact number 2330 1647..\nPersonal data collected will be used for recruitment purpose only.\nInterested candidates, please contact us at 23301647 for company details before applying.", "employment_types": ["Full Time", "Permanent"], "selling_points": ["5-day work week, 13-month pay, medical benefits", "3 years solid experience in International trading", "Degree holder in Business related disciplines"], "locations": ["Tsim Sha Tsui"], "categories": ["Transportation & Logistics", "Shipping", "Merchandising & Purchasing", "Toy", "Sales, CS & Business Devpt", "Direct Sales"], "post_time": "2022-01-17T04:11:38Z", "salary": {"currency": null, "max": null, "min": null, "period": "monthly", "term": null}, "salary_visible": false, "title_keywords": ["shipping", "merchandising", "executive"], "responsibilities": [], "requirements": {"degrees": [], "majors": [], "languages": [], "language_level": [], "hard_skills": [], "soft_skills": [], "languages_combined": []}, "experience_required": {"duration": [], "field": []}}, {"job_id": "100003009055198", "location_code": "hk", "company": "Tsit Wing Coffee Co Ltd", "job_title": "Shipping clerk", "description": "We are the Asia Pacific Sales branch office for one of the leading toy companies based in Germany.\u00a0\u00a0 We are now looking for a Merchandising and Shipping Executive to join the team.\n\nJob Responsibilities:\n\n-\u00a0\u00a0\u00a0\u00a0\u00a0\u00a0\u00a0\u00a0\u00a0 Coordinate, follow up and process orders from factory to overseas clients independently.\n\n-\u00a0\u00a0\u00a0\u00a0\u00a0\u00a0\u00a0\u00a0\u00a0 Maintain and update order-processing system\n\n-\u00a0\u00a0\u00a0\u00a0\u00a0\u00a0\u00a0\u00a0\u00a0 Handle shipping operation with required documents\n\n-\u00a0\u00a0\u00a0\u00a0\u00a0\u00a0\u00a0\u00a0\u00a0 Frequent communication with both factories and overseas customers\n\n-\u00a0\u00a0\u00a0\u00a0\u00a0\u00a0\u00a0\u00a0\u00a0 Reports generation\n\nRequirements:\n\n-\u00a0\u00a0\u00a0\u00a0\u00a0\u00a0\u00a0\u00a0\u00a0 Degree holder in Business related disciplines with minimum 3 years solid experience in International trading.\u00a0 Toy industry a plus.\n\n-\u00a0\u00a0\u00a0\u00a0\u00a0\u00a0\u00a0\u00a0\u00a0 Fluency in both written and spoken English, Cantonese and Mandarin.\n\n-\u00a0\u00a0\u00a0\u00a0\u00a0\u00a0\u00a0\u00a0\u00a0 Excellent interpersonal and communication skills\n\n-\u00a0\u00a0\u00a0\u00a0\u00a0\u00a0\u00a0\u00a0\u00a0 Open minded to multicultural business\n\n-\u00a0\u00a0\u00a0\u00a0\u00a0\u00a0\u00a0\u00a0\u00a0 Strong analytical skills, detail-minded and able to work in multi-task environment under pressure independently and in a team.\n\n-\u00a0\u00a0\u00a0\u00a0\u00a0\u00a0\u00a0\u00a0\u00a0 Well-versed in MS Office such as Excel, Word and PowerPoint.\n\n-\u00a0\u00a0\u00a0\u00a0\u00a0\u00a0\u00a0\u00a0\u00a0 Occasional travels to China may be required\n\n-\u00a0\u00a0\u00a0\u00a0\u00a0\u00a0\u00a0\u00a0\u00a0 Immediate availability is highly preferred\n\nBenefits and Others:\n\nOur office is located in Tsim Sha Tsui.\u00a0 Attractive remuneration package including 5-day work week, bank holidays, 13-month pay, medical benefits and etc. will be offered to the successful candidate.\n\nInterested parties please send CV with expected salary by clicking APPLY NOW.\n", "employment_types": ["Full Time", "Permanent"], "selling_points": [], "locations": ["Kwai Fong"], "categories": ["Transportation & Logistics", "Fulfillment", "Shipping", "Merchandising & Purchasing", "Procurement / Purchasing / Sourcing"], "post_time": "2022-01-18T01:44:58Z", "salary": {"currency": null, "max": null, "min": null, "period": "monthly", "term": null}, "salary_visible": false, "title_keywords": ["shipping clerk"], "responsibilities": ["shipping", "process orders", "coordinate", "communication", "maintain", "reports"], "requirements": {"degrees": ["degree holder"], "majors": ["related disciplines", "business"], "languages": ["cantonese", "english", "mandarin"], "language_level": ["fluency"], "hard_skills": ["excel", "plus", "word", "powerpoint", "analytical skills", "ms office"], "soft_skills": ["detail-minded", "communication skills", "independently", "multi-task", "under pressure", "analytical skills", "open minded", "interpersonal"], "languages_combined": [{"language": "cantonese", "language_level": ["fluency"]}, {"language": "english", "language_level": ["fluency"]}, {"language": "mandarin", "language_level": ["fluency"]}]}, "experience_required": {"duration": ["minimum 3 years"], "field": ["related", "business", "trading"]}}, {"job_id": "100003009040035", "location_code": "hk", "company": "Sunny Handicraft (HK) Limited", "job_title": "Shipping Officer", "description": "Job Category :Management / ShippingJob Title :Shipping managerNo. of Vacancy :1Job Location :Tsim Sha Tsui\nJob Duties and Requirements :\n\nMinimum 5 years of shipping experience in handling consumer goods preferablr in multinational company. Familiar with U.S. market. Coordinate and arrange shipment schedule with various parties. Handle full set of I/E documents, L/C banking document for US market independently. Occasional travelling to Shenzhen office in handling shipping documents when required. Willing to work overtime. English and Mandarin are musts. PC knowledge on MS Excel & Words. Supervise the junior on shipment schedule, booking, customer requirements and coordinate with factory on ship docs. submit, Daily report to management. (IMMEDIATELY AVAILABLE PREFERRED)\n\nJob Type :Full TimeWorking Days Per Week :5Working Hours :From 0930 to 1730Salary :HKD 19,000 UP (Negotiable)Other Benefits and\nAllowances :Lunch is provided\nTransportation Reimbursement\nDouble Pay\nDiscretionary Bonus\nMedical Allowance\nAnnual LeaveEducation Level :Certificate in Logistics relatedRelated Experience5 years or aboveContact Method :Interested parties, please e-mail full resume by e-mail to:\n(Attn: Mr. Chan)\u00a0\"Personal data collected will be used for recruitment purpase only.\"", "employment_types": ["Full Time", "Permanent"], "selling_points": ["Flexible working hours", "Coordinate with factory & customer", "Experienced in import & export procedures"], "locations": ["Kowloon Bay"], "categories": ["Transportation & Logistics", "Others", "Shipping", "Supply Chain"], "post_time": "2022-01-12T07:28:05Z", "salary": {"currency": null, "max": null, "min": null, "period": "monthly", "term": null}, "salary_visible": false, "title_keywords": ["shipping officer"], "responsibilities": [], "requirements": {"degrees": [], "majors": [], "languages": ["english", "mandarin"], "language_level": [], "hard_skills": ["pc knowledge", "c", "ms excel", "words"], "soft_skills": ["work overtime", "independently"], "languages_combined": [{"language": "english", "language_level": []}, {"language": "mandarin", "language_level": []}]}, "experience_required": {"duration": ["minimum 5 years"], "field": ["multinational company"]}}, {"job_id": "100003009029744", "location_code": "hk", "company": "Creative China Creations Limited", "job_title": "Senior Shipping Coordinator (Consumer Products & Sundries)", "description": "F.7 / DSE or above graduate\u00a0\n2-3 years solid experience in shipping documents\nGeneral clerical support to Accounts Department\u00a0\nGood interpersonal skills, self-motivated, stable\nProficiency in computer applications, e.g. MS Word, Excel and Chinese Word Processing\nGood command in spoken and written English and Chinese\nExperience in Garment Field is preferred\u00a0\nImmediate available is preferred\u00a0\n\nAttractive salary and benefit package will be offered to the right candidates.\u00a0\u00a0\n\nPlease include your expected salary and email by clicking \"Apply Now\" for an applicant form.\n\n\nAttn: Union Apparel International Ltd. - Ms. Cheung\n\n(Location: San Po Kong \u2013 Near Diamond Hill Station)\n\nPersonal data collected will be used for recruitment purpose only.", "employment_types": ["Full Time", "Permanent"], "selling_points": ["Good understanding on global Markets", "Able to work independently & meet tight deadlines", "With at least 3 year of relevant experience"], "locations": ["Ngau Tau Kok"], "categories": ["Transportation & Logistics", "Others", "Shipping", "Merchandising & Purchasing", "Procurement / Purchasing / Sourcing"], "post_time": "2022-01-17T16:20:53Z", "salary": {"currency": null, "max": null, "min": null, "period": "monthly", "term": null}, "salary_visible": false, "title_keywords": ["shipping coordinator"], "responsibilities": ["shipping documents", "clerical support", "recruitment", "computer applications", "personal data"], "requirements": {"degrees": ["dse"], "majors": [], "languages": ["english", "chinese"], "language_level": ["good command"], "hard_skills": ["excel", "chinese word processing", "ms word"], "soft_skills": ["self-motivated", "interpersonal skills", "stable"], "languages_combined": [{"language": "english", "language_level": ["good command"]}, {"language": "chinese", "language_level": ["good command"]}]}, "experience_required": {"duration": ["2-3 years"], "field": ["garment"]}}, {"job_id": "100003009051936", "location_code": "hk", "company": "Madden International Limited", "job_title": "SHIPPING CLERK", "description": "Responsibilities\u00a0\n\nResponsible for I/E Document preparation, declaration\nMonitor shipment status and order follow up\nCoordinate with freight forwarders and shipping companies for shipment and transportation arrangement\nAccurate and timely data input of shipment details to order system\nPerform any ad hoc projects as assigned\n\nRequirements\n\nDegree holder in relevant discipline\u00a0\n2 years\u2019 experiences preferably in shipping\nFresh graduates will be considered\nExcellent communication skills with both internal and exteral parties\nGood command of spoken English, Putonghua and Cantonese\nKnowledge of SAP system is preferred\n\nWorking location:\u00a0Kwai Chung\n\n\n\nStaff Benefit\n\nDiscretionary Bonus\nMedical & Life Insurance\nAnnual Leave\nPayable Sick Leave\nEncourage continuing education and on-job training\nOpen office working environment\nOffer promotion opportunities and long-term career path\u00a0\n\nWe offer a competitive remuneration package to the right candidate.\u00a0Interested parties\u00a0please click\u00a0\"Apply Now\"\u00a0to submit your application\u00a0or by email to\u00a0hr1 @twcoffee.com\n\n\u00a0(All personal data provided by applicants will be treated in strict confidence and used for employment-related purpose only.)", "employment_types": ["Full Time", "Permanent"], "selling_points": ["Handle I/E document, Invoice, Packing list, filing", "Coordinate with factory and forwarder", "Data input and general clerical support"], "locations": ["Not Specified"], "categories": ["Admin & HR", "Clerical / Admin Staff", "Transportation & Logistics", "Documentary Credit / Bills Processing", "Shipping"], "post_time": "2022-01-17T01:32:51Z", "salary": {"currency": null, "max": null, "min": null, "period": "monthly", "term": null}, "salary_visible": false, "title_keywords": ["shipping clerk"], "responsibilities": ["shipping", "monitor", "data input", "coordinate with", "ad hoc projects"], "requirements": {"degrees": ["degree holder"], "majors": [], "languages": ["cantonese", "putonghua", "english"], "language_level": ["good command"], "hard_skills": ["sap"], "soft_skills": ["communication skills"], "languages_combined": [{"language": "cantonese", "language_level": ["good command"]}, {"language": "putonghua", "language_level": ["good command"]}, {"language": "english", "language_level": ["good command"]}]}, "experience_required": {"duration": ["2 years"], "field": []}}, {"job_id": "100003009054006", "location_code": "hk", "company": "DKSH Hong Kong Limited", "job_title": "Supervisor, Supply Chain Management (Shipping)", "description": "Requirement for Shipping Officer:\nDiploma at least 5 Years working experience in logistic\nCoordinate with factory & customer to ensure daily import & export operations in timely & accurate schedule\nSound Knowledge and experienced in import & export procedures, Trade-link declaration, regulation and L/C Doc. Handling\nKnowledge and experienced in handling office administration and accounting task.\nGood communication and interpersonal skills\nAble to work under pressure and multi-tasking abilities alone.\nWilling to work overtime during peak season\nProficiency in MS office\nFluency in both written and spoken English, Cantonese and Mandarin\nHands-on experience in handling shipment for USA, Canada, European countries.\n\n\nPlease submit your resume with EXPECTED salary and date of availability.", "employment_types": ["Full Time", "Permanent"], "selling_points": ["Form 5/ DSE or above", "three years' experience in a similar role", "Prepare billings/invoices"], "locations": ["Kwai Tsing Area"], "categories": ["Transportation & Logistics", "Documentary Credit / Bills Processing", "Freight Forwarding", "Shipping"], "post_time": "2022-01-17T08:01:48Z", "salary": {"currency": null, "max": null, "min": null, "period": "monthly", "term": null}, "salary_visible": false, "title_keywords": ["shipping", "supervisor"], "responsibilities": ["shipping", "operations", "office administration", "coordinate with", "procedures", "communication", "schedule", "work under pressure"], "requirements": {"degrees": ["diploma"], "majors": [], "languages": ["cantonese", "english", "mandarin"], "language_level": ["fluency"], "hard_skills": ["c", "ms office"], "soft_skills": ["work overtime", "timely", "multi-tasking", "communication and interpersonal skills", "hands-on", "accurate", "work under pressure"], "languages_combined": [{"language": "cantonese", "language_level": ["fluency"]}, {"language": "english", "language_level": ["fluency"]}, {"language": "mandarin", "language_level": ["fluency"]}]}, "experience_required": {"duration": ["at least 5 years"], "field": []}}, {"job_id": "100003009052835", "location_code": "hk", "company": "Panasonic Hong Kong Co., Limited", "job_title": "Shipping Clerk/ Coordinator (Focus on Logistics)", "description": "Job Requirements:\n\nMust be familiar with banking documents shipments such as D/P, D/A, L/C etc.\nDocumentation formalities pertaining to shipments\nArranging shipment and follow up with factories\nCo-coordinating all shipping activities for numerous clients\nEXCELLENT COMMAND IN WRITTEN & SPOKEN ENGLISH, CANTONESE & MANDARIN SKILLS\nGood knowledge of all documentation formalities pertaining to shipments\nMinimum\u00a03 year experience in a manufacturer, trading company, or multinational export company\u2019s shipping department\nExperience in making all relevant shipping documents\nExcellent communication and interpersonal skills\nA team leader who exhibits leadership qualities and is able to work under pressure and within time constraints\nWilling to travel to China and other destinations\nFamiliarity with basic computer programs such as Microsoft Office (Microsoft Word, Excel, Outlook (email) etc)\nA team leader who exhibits leadership qualities and is able to work under pressure and within time constraints.\nPermanent Hong Kong ID card Holder.\nFlexible working times and willing to work after hours if needed.\n\n\nKey requirements:\n\nDegree/Diploma holder, with at least 3 year of relevant experience\nGood understanding on global Markets\nExcellent command in Cantonese, English and Mandarin\nGood communication and interpersonal skills to work with counterparts\nAble to work independently and meet tight deadlines\nProficient in computer skills and MS Office Applications\n\n\nInterested applicants please send your English application along with cover letter and detailed resume with current and expected salary clearly stated to \u201cApply Now\u201d.\n\nAll Personal data collected will be used for recruitment purpose only.", "employment_types": ["Full Time", "Permanent"], "selling_points": ["Handle shipping schedule & shipment booking", "Exposure in trading company & export arrangement", "Stable MNC in-house environment"], "locations": ["Tsim Sha Tsui"], "categories": ["Transportation & Logistics", "Others", "Shipping", "Supply Chain"], "post_time": "2022-01-17T04:13:27Z", "salary": {"currency": null, "max": null, "min": null, "period": "monthly", "term": null}, "salary_visible": false, "title_keywords": ["logistics", "coordinator", "shipping clerk"], "responsibilities": ["shipping documents", "shipping", "communication", "recruitment", "banking", "documentation", "personal data", "work under pressure"], "requirements": {"degrees": ["diploma holder", "degree"], "majors": [], "languages": ["cantonese", "english", "mandarin"], "language_level": ["excellent"], "hard_skills": ["excel", "microsoft word", "basic", "microsoft office", "id", "c", "outlook", "computer skills", "documentation", "ms office"], "soft_skills": ["flexible", "work independently", "meet tight deadlines", "detailed", "communication and interpersonal skills", "leadership", "work under pressure"], "languages_combined": [{"language": "cantonese", "language_level": ["excellent", "excellent"]}, {"language": "english", "language_level": ["excellent", "excellent"]}, {"language": "mandarin", "language_level": ["excellent", "excellent"]}]}, "experience_required": {"duration": ["minimum 3 year", "at least 3 year"], "field": ["trading", "relevant experience"]}}, {"job_id": "100003009056504", "location_code": "hk", "company": "DFV Fine Wines Limited", "job_title": "Shipping and Sales Adminstrative Assistant", "description": "Jobs duties\n\nResponsible for handle full set of Export document, L/C and Bank documents, filing, Tradelink Declaration\nCoordinate with customer, factory and forwarder for shipment arrangement\nData input and general clerical support to shipping Department\nExperience in handling EXPORT Shipment to European / US Counties\u00a0 \u00a0\n\nRequirement\n\nOver 3 years relevant experience\nGood communications and interpersonal skills\nGood commend of written and spoken English, Chinese and Putonghua\nAble to work under pressure and independently\nProficient in PC skills, such as Microsoft outlook, Work, Excel\nSelf-motivated, well organized, with strong sense of responsibility\nHardworking, willing to learn\nShort notice or Immediate available is preferable\n\nWe offer 5 day work with competitive remuneration package, benefits and good career prospects to the right candidate.\u00a0 Interested parties, please apply with full resume stating current & expected salary and available date.\u00a0Please quote the reference no. (Ref:\u00a0 SC-JAN 2022) on application\n\nAll personal data collected will be kept in strict confidence and would only be used for recruitment purpose.", "employment_types": ["Full Time"], "selling_points": [], "locations": ["Kwun Tong"], "categories": ["Admin & HR", "Clerical / Admin Staff", "Transportation & Logistics", "Shipping", "Sales, CS & Business Devpt", "Sales Administration"], "post_time": "2022-01-18T04:43:15Z", "salary": {"currency": "HKD", "max": 16999, "min": 11000, "period": "monthly", "term": null}, "salary_visible": true, "title_keywords": ["shipping", "assistant", "sales"], "responsibilities": ["shipping", "shipment arrangement", "coordinate with", "clerical support", "data input", "tradelink declaration"], "requirements": {"degrees": [], "majors": [], "languages": ["putonghua", "english", "chinese"], "language_level": ["good"], "hard_skills": ["excel", "pc skills", "outlook"], "soft_skills": ["self-motivated", "independently", "sense of responsibility", "well organized", "willing to learn", "interpersonal skills", "hardworking", "work under pressure"], "languages_combined": [{"language": "putonghua", "language_level": ["good"]}, {"language": "english", "language_level": ["good"]}, {"language": "chinese", "language_level": ["good"]}]}, "experience_required": {"duration": ["3 years"], "field": ["relevant experience"]}}, {"job_id": "100003009054624", "location_code": "hk", "company": "IKEA", "job_title": "Shipping & Receiving Clerk \u8239\u52d9\u6587\u54e1", "description": "Job Responsibilities:\n\nProvide administration support across Sales Team and Order Management Team\nSupport superior in managing day-to-day operating expenditures, supervise and coach the team to ensure operation runs efficiently\nPerform daily checking and monitoring of contract's shipments\nFile, scan properly and maintain necessary documents\nPrepare billings/invoices (including forwarder invoices, customer's L/C documents)(e.g. I/E shipping documents, customs, freight costs management)\nCoordinate with internal teams (Sales, Order Management, Quality, etc) to gather and verify information\nAnalyze data to monitor KPI performance and plan for improvements, streamline the logistics flow, refine SOP\nHandle ad hoc tasks as assigned\nJob Requirements:\n\nForm 5/DSE or aboveor equivalent level\nMinimum three years' experience in a similar role, with more experience may be considered as senior level post.\nBasic knowledge of machinery sales' shipment from Overseas to China.\nWorking knowledge onISO, full set of L/C document, logistic documents (Airway Bill, Bill of Lading, Insurance, Incoterm, bank guarantee).\nDemonstrate proficiencies in office productivity tools (e.g. Excel, Word and PowerPoint), skill in Chinese input.\nFluent in local language and ideally in English and Mandarin (Traditional & Simplified Chinese), both written and spoken\nExperience in Pharmaceutical field is an advantage\nCandidate with less experience will be considered as Assistant Supervisor\u00a0\n\nWorking Location: Kwai Chung\n\nWe offer performance bonus and attractive benefits including medical insurance.\u00a0Please apply with full particulars, contact number and current/ expected salary to\u00a0People & Organization Department, DKSH Hong Kong Limited, 23rd Floor, Tower A, Southmark, 11 Yip Hing Street, Wong Chuk Hang, Hong Kong or fax:2895 9711.\n\nAll personal data collected will be used for recruitment purpose only.\u00a0Candidates will be contacted within 2 weeks if the background and experience are closely relevant to the job requirement.\n\nDrive Growth. Be the Difference. Join DKSH.\n\nDKSH\u2019s strength lies in our great diversity of services, industries, clients, products, regions, and employees from various cultures. We are proud of our people: they are the best in the industry and the reason for our business success. They are passionate, energetic, and purposeful, positively touching millions of lives through the products and services we provide. Join us today if you are ready to \u201cDrive Growth. Be the Difference.\u201d With DKSH, you will experience a world of learning and development, own your career and take business responsibility, and have a positive impact that touches people\u2019s lives.", "employment_types": ["Full Time", "Permanent"], "selling_points": ["Passionate in Home Furnishing", "Working Location: Kwai Chung", "Responsible for Shipping Activities"], "locations": ["Kwai Tsing Area"], "categories": ["Transportation & Logistics", "Documentary Credit / Bills Processing", "Fulfillment", "Shipping"], "post_time": "2022-01-17T10:17:08Z", "salary": {"currency": null, "max": null, "min": null, "period": "monthly", "term": null}, "salary_visible": false, "title_keywords": ["shipping", "clerk"], "responsibilities": ["shipping documents", "quality", "maintain", "plan", "costs", "administration", "invoices", "billings", "teams", "monitor", "logistics", "analyze data", "management", "monitoring", "coordinate with", "checking", "ad hoc tasks", "order management", "sales team"], "requirements": {"degrees": ["form 5", "dse"], "majors": [], "languages": ["english", "chinese", "mandarin"], "language_level": ["fluent"], "hard_skills": ["chinese input", "excel", "basic", "word", "powerpoint", "c"], "soft_skills": [], "languages_combined": [{"language": "english", "language_level": ["fluent"]}, {"language": "chinese", "language_level": ["fluent"]}, {"language": "mandarin", "language_level": ["fluent"]}]}, "experience_required": {"duration": ["minimum three years"], "field": ["pharmaceutical"]}}, {"job_id": "100003009052615", "location_code": "hk", "company": "Union Duty-Free Limited", "job_title": "Shipping Clerk", "description": "Responsibilities:\n\nTo\u00a0handle shipping schedule and arrangement\nTo follow up on sales and purchase orders, shipment booking and scheduling\nTo co-ordinate and arrange with factories and overseas customer for end to end supply chain\nTo compile statistical figures for logistics process improvement\nTo assist in other ad-hoc assignments as required\n\nRequirements:\n\nHKCEE F.5 / DSE graduated or above\n1-2 years relevant logistics experience especially in China export arrangement\nPrevious exposures trading company or MNC are preferred\nProficient in MS Office and previous exposure in shipping software system is preferred\nGood command of written and spoken English and Chinese\nHave good communication, well organized and a fast learner\nWilling to provide ad hoc support\n\nRemuneration will be commensurate with qualification and experience. Interested parties, please send your application with detailed resume indicating both existing & expected salary and date of availability to us.\n\nWe are an equal opportunity employer. All information provided by applicants will be treated in strict confidence and used for recruitment purpose only.", "employment_types": ["Full Time"], "selling_points": [], "locations": ["Tsuen Wan Area"], "categories": ["Accounting", "Others", "Admin & HR", "Clerical / Admin Staff", "Transportation & Logistics", "Shipping"], "post_time": "2022-01-17T03:33:27Z", "salary": {"currency": null, "max": null, "min": null, "period": "monthly", "term": null}, "salary_visible": false, "title_keywords": ["shipping clerk"], "responsibilities": ["shipping schedule", "ad-hoc assignments", "scheduling", "purchase", "logistics", "booking"], "requirements": {"degrees": ["dse"], "majors": [], "languages": ["english", "chinese"], "language_level": ["good command"], "hard_skills": ["ms office"], "soft_skills": ["communication", "fast learner", "well organized"], "languages_combined": [{"language": "english", "language_level": ["good command"]}, {"language": "chinese", "language_level": ["good command"]}]}, "experience_required": {"duration": ["1-2 years"], "field": ["logistics"]}}, {"job_id": "100003009052618", "location_code": "hk", "company": "", "job_title": "Shipping Clerk / Logistics Clerk  (5-day)", "description": "Handle import and export documents\nHandle stock in&out documents for fine wines warehouse.\nAssist in customers in&out for wine cellars.\nAssist in system maintainence.\nAssist in daily administration work.\nAssist in sales and customer service work.\nDirectly report to Adminstration Manager and Director.\nResponsible and detailed minded.\nSelf-motivated and a team player.\u00a0\nGood communication skills.\nGood writting skills in English and Chinese.\nRelated working experience is preferred.\nWine industry working experience is preferred.", "employment_types": ["Full Time", "Permanent", "Temporary"], "selling_points": ["At least 1 year exp shipping or logistic (Sea/Air)", "With forwarder/logistic/trading company exp prefer", "Garantee Double Pay, Bonus, Medical Insurance, etc"], "locations": ["Lai Chi Kok"], "categories": ["Admin & HR", "Clerical / Admin Staff", "Transportation & Logistics", "Freight Forwarding", "Shipping"], "post_time": "2022-01-17T03:37:38Z", "salary": {"currency": null, "max": null, "min": null, "period": "monthly", "term": null}, "salary_visible": false, "title_keywords": ["logistics clerk", "shipping clerk"], "responsibilities": ["communication", "report", "customer service", "administration"], "requirements": {"degrees": [], "majors": [], "languages": ["english", "chinese"], "language_level": ["good"], "hard_skills": ["import and export"], "soft_skills": ["communication skills", "self-motivated", "responsible", "customer service", "team player", "detailed"], "languages_combined": [{"language": "english", "language_level": ["good"]}, {"language": "chinese", "language_level": ["good"]}]}, "experience_required": {"duration": [], "field": ["related"]}}, {"job_id": "100003009052006", "location_code": "hk", "company": "Giesecke & Devrient Asia Pacific Ltd", "job_title": "Logistics Coordinator (1 Year Contract)", "description": "Responsibilities:\n\nHandle I/E shipping documents, L/C & Customs Clearance procedure, invoice and delivery note, and packing list, Tradelink, etc,\nCoordinate with forwarders, transportation companies or cargo agents for shipment arrangement.\nData input and checking\n\nRequirements:\n\nF.5 / HKDSE or above\n2 years of relevant working experience\nGood in MS office, excel/word\nGood team player and hard working\nWilling to work OT $70/hour\n\nimmediately available is highly preferred\n\nBenefit:\n\nDouble pay and year-end bonus after one year employment\nOT allowance (Max. up to $70/hours)\nMedical provided after probation\nAnnual leave 10 days (Max. 19 days)\nPublic Holiday\n5-days work / Shift to work on Saturday (half day which count as OT allowance)\nFree snack provided\nBirthday Coupon\n\n\u00a0Interest parties please send your application letter & full resume with expected salaries and earliest availability by clicking \"Apply Now\"", "employment_types": ["Full Time", "Contract"], "selling_points": ["Import/Export Control", "Good at SAP (PTP-PUR and OTC)", "Immediate available"], "locations": ["Causeway Bay"], "categories": ["Transportation & Logistics", "Documentary Credit / Bills Processing", "Inventory / Warehousing", "Shipping"], "post_time": "2022-01-17T01:48:39Z", "salary": {"currency": null, "max": null, "min": null, "period": "monthly", "term": null}, "salary_visible": false, "title_keywords": ["logistics coordinator"], "responsibilities": ["shipping documents", "tradelink", "shipment arrangement", "invoice", "coordinate with", "data input", "checking", "packing list"], "requirements": {"degrees": ["hkdse"], "majors": [], "languages": [], "language_level": [], "hard_skills": ["excel", "word", "ms office"], "soft_skills": ["good team player", "hard working"], "languages_combined": []}, "experience_required": {"duration": ["2 years"], "field": ["relevant working experience"]}}, {"job_id": "100003009054046", "location_code": "hk", "company": "Smith & Associates Far East Ltd", "job_title": "Logistics Coordinator/ Operation Admin Support", "description": "Requirements:\n\nHKCEE/HKDSE or above\nAt least 1 year relevant experience in shipping or logistics (Sea / Air)\u00a0 duties\n\nWorking experience in Forwarder / Logistics / Trading company background is preferable\u00a0\nResponsible for handling general shipping / logistics\u00a0 duties, Import/Export\u00a0 document and general operation duties, etc.\nKnowledge of tradelink is preferable\nImmediate available is an advantage\n\n*\u00a0 \u00a0 \u00a0\u00a0Recent graduates are welcome\n\nCompany offers attractive remuneration package including 5-day work, banking holiday, 14 days annual leave, medical & life insurance, grantee double pay, discretionary bonus and overtime allowance\u00a0 to right candidates. Interested parties please send email to\u00a0roco@biznetvigator.com or contact with 23092138\u00a0for more details and to obtain application form.\n\n(Data collected used by recruitment purpose only)", "employment_types": ["Full Time", "Permanent"], "selling_points": ["Well established MNC", "Nice Warehouse Environment", "Stable and friendly work environment"], "locations": ["Kowloon Bay"], "categories": ["Transportation & Logistics", "Shipping", "Supply Chain", "Merchandising & Purchasing", "Others"], "post_time": "2022-01-17T08:12:02Z", "salary": {"currency": null, "max": null, "min": null, "period": "monthly", "term": null}, "salary_visible": false, "title_keywords": ["admin", "logistics coordinator"], "responsibilities": ["shipping", "tradelink", "logistics", "banking", "insurance"], "requirements": {"degrees": ["hkdse"], "majors": [], "languages": [], "language_level": [], "hard_skills": [], "soft_skills": ["responsible"], "languages_combined": []}, "experience_required": {"duration": ["at least 1 year"], "field": ["logistics", "relevant experience", "trading"]}}, {"job_id": "100003009051659", "location_code": "hk", "company": "Tai Chi Solutions Limited", "job_title": "sales administrator / shipping assistant", "description": "Trading\n\n\u00a0\u00a0Requirements:\n\nF.5\nAt least 3 -8 years shipping experience in shipping in Trading or factory\n\nFull set of I/E, L/C documents\nContact with\u00a0vendor, overseas buyer, forwarder\nExperience in USA and Europe market\nGood communication and\n\nGood commend of both English and Mandarin\n\n*Interested parties, please Email full resume with current & expected salary & date available in MS WORD FORMAT ONLY to us\u00a0or fax to 3527 0634*\n\nFor more jobs, please visit our website: www.hketernity.com\n\n(Personal data submitted are for recruitment purpose only.)", "employment_types": ["Full Time"], "selling_points": ["5 day work", "lunch including", "near MTR station"], "locations": ["Chai Wan"], "categories": ["Transportation & Logistics", "Shipping", "Sales, CS & Business Devpt", "Sales Administration"], "post_time": "2022-01-16T21:50:33Z", "salary": {"currency": null, "max": null, "min": null, "period": "monthly", "term": null}, "salary_visible": false, "title_keywords": ["sales administrator", "shipping", "assistant"], "responsibilities": ["communication", "shipping", "contact"], "requirements": {"degrees": [], "majors": [], "languages": ["english", "mandarin"], "language_level": ["good"], "hard_skills": ["c", "vendor"], "soft_skills": ["communication"], "languages_combined": [{"language": "english", "language_level": ["good"]}, {"language": "mandarin", "language_level": ["good"]}]}, "experience_required": {"duration": ["at least 3 -8 years"], "field": ["trading"]}}, {"job_id": "100003009053355", "location_code": "hk", "company": "Alpha Power Solutions Limited", "job_title": "Planning & Logistics Specialist", "description": "MAJOR DUTIES AND RESPONSIBILITIES include the followings. Other duties may be assigned as necessary to fulfill optimum efficiency of this position:\n\nManage purchase order and stock transfer order placement and liaison with internal/external vendors\nCoordinate inbound shipment arrangement with logistics service providers\nBe responsible for handling of monitoring and housekeeping activities (purchasing stream) in the ERP system\nSupport application works in import and export control as well as compliance\nSupport SAP rollout project in Asia\nOther ad hoc duties as assigned\n\nREQUIREMENT:\n\nSchool certification or above with logistics or supply chain disciplines.\u00a0\nTeam player, mature, detail-minded and can work independently\nGood PC knowledge, i.e., MS Office, Chinese word processing\nGood command in speaking and writing in English and Chinese\nGood experience in using SAP (PTP-PUR and OTC) is preferable\u00a0\nImmediate available preferred\u00a0\n\nAn attractive package that is commensurate with successful candidate's qualifications and experience will be offered. Please apply with detailed resume including availability, current & expected salary and contact number to HR Department, Giesecke & Devrient Asia Pacific Limited, Room 2901 Hysan Place, 500 Hennessy Road, Causeway Bay, Hong Kong or apply in JobsDB.com directly.\n\nAll information received will be kept in strict confidence and only for employment-related purpose.", "employment_types": ["Full Time"], "selling_points": [], "locations": ["Shatin Area"], "categories": ["Transportation & Logistics", "Shipping", "Supply Chain", "Manufacturing", "Production Planning / Control"], "post_time": "2022-01-17T06:49:56Z", "salary": {"currency": null, "max": null, "min": null, "period": "monthly", "term": null}, "salary_visible": false, "title_keywords": ["logistics specialist"], "responsibilities": ["monitoring and housekeeping activities", "ad hoc duties", "other duties", "purchasing stream", "sap rollout project", "compliance", "import and export control", "coordinate", "purchase", "logistics", "support application works", "inbound shipment"], "requirements": {"degrees": [], "majors": [], "languages": ["english", "chinese"], "language_level": ["good command"], "hard_skills": ["pc knowledge", "chinese word processing", "sap", "ms office"], "soft_skills": ["detail-minded", "work independently", "confidence", "mature", "team player", "detailed"], "languages_combined": [{"language": "english", "language_level": ["good command"]}, {"language": "chinese", "language_level": ["good command"]}]}, "experience_required": {"duration": [], "field": []}}, {"job_id": "100003009052109", "location_code": "hk", "company": "Associated Maritime Company (Hong Kong) Limited", "job_title": "\u6cd5\u5f8b\u5408\u898f\u5d17\uff08Shipping Law & Marine Insurance\uff09", "description": "Key Responsibilities\n\nUnload all inbound shipments from carriers, open boxes and place shipments in bins\nPerform order verification process. Identify and verify Purchase Order information and determine if there is a Sales Order associated with the product\nTo ensure all shipments coming inbound and going outbound move as quickly as possible and are delivered within their schedule\nTo ensure all shipments are proactively expedited through customs and are imported in accordance with customs compliance\nUtilize delivery systems, i.e. UPS, FEDEX, DHL, TNT, or Freight Forwarders, to ship product worldwide\nTo proactively research missing freight and file claim if needed\nTo provide timely international and domestic quotes for any Smith & Associates or Consignment shipment at a minimum cost where service is not jeopardized\nWhen needed, move shipments as quickly as possible (next flight outs, hot shots, drop shipments, etc.)\nAssist with other projects as necessary.\nProvide office administrative, clerical support when needed\n\nRequirements\n\nForm 7 or above with 2-3 years' working experience\nWritten and spoken Cantonese, Mandarin and English\nCommunication, negotiation, multi-tasking and problem solving skills\nMature, detail-orientated, team player and able to work under pressure", "employment_types": ["Full Time"], "selling_points": ["\u5be9\u95b1\u6cd5\u5f8b\u6027\u6587\u4ef6", "\u6cd5\u5f8b\u98a8\u63a7,\u5408\u898f\u4e8b\u52d9", "\u5168\u65e5\u5236\u5927\u5b78\u822a\u904b\u6216\u6cd5\u5b78\u672c\u79d1\u5b78\u6b77\u6559\u80b2\u80cc\u666f"], "locations": ["Sheung Wan"], "categories": ["Professional Services", "Legal & Compliance", "Transportation & Logistics", "Shipping"], "post_time": "2022-01-17T02:06:53Z", "salary": {"currency": "HKD", "max": 54999, "min": 30000, "period": "monthly", "term": null}, "salary_visible": true, "title_keywords": [], "responsibilities": ["cost", "compliance", "systems", "clerical support", "purchase", "schedule"], "requirements": {"degrees": [], "majors": [], "languages": ["cantonese", "english", "mandarin"], "language_level": [], "hard_skills": ["problem solving skills"], "soft_skills": ["negotiation", "mature", "communication", "multi-tasking", "team player", "problem solving skills", "work under pressure"], "languages_combined": [{"language": "cantonese", "language_level": []}, {"language": "english", "language_level": []}, {"language": "mandarin", "language_level": []}]}, "experience_required": {"duration": ["2-3 years"], "field": []}}, {"job_id": "100003009053052", "location_code": "hk", "company": "Relosmart Limited", "job_title": "Customer Service Representative (Removals/Shipping/Logistics)", "description": "JOB HIGHLIGHTS:\n\nReliable, has initiative and is willing to learn.\nHard working and can handle full set of shipping docs.\nCan handle all logistics duties independently.\nNice, stable and friendly work environment.\n\nJob Description\n\nResponsibilities:\n\nVerify, file and keep records of shipment documentation.\nHandle import shipment as well as I/E customs declaration.\nPrepare shipment documents and export shipment report, etc.\nCoordinate with customers, factory and forwarder for shipment arrangement.\nExperience in handling documents to US Countries. \u00a0\n\nRequirements:\n\nForm 5\u00a0or above;\nCapable in handling import shipment and tradelink system.\nFamiliar with MS Office applications including Word & Excel.\nAble to communicate in Chinese & English.\n\nWe offer 5-day work, bank holidays. Interested candidates please send your full resume with CURRENT/LAST & EXPECTED SALARY.\n\n(Information collected will be used for recruitment purpose only)", "employment_types": ["Full Time", "Permanent", "Contract"], "selling_points": ["Customer Service", "Shipping Moving Logistic", "Relocation Call Center"], "locations": ["Kwun Tong"], "categories": ["Sales, CS & Business Devpt", "Customer Service - Manager", "Transportation & Logistics", "Freight Forwarding", "Shipping"], "post_time": "2022-01-17T16:20:58Z", "salary": {"currency": "HKD", "max": 19999, "min": 14000, "period": "monthly", "term": null}, "salary_visible": true, "title_keywords": ["shipping", "logistics", "customer service representative"], "responsibilities": ["customs declaration", "shipment arrangement", "handling documents", "coordinate with", "documentation", "report"], "requirements": {"degrees": ["form 5 or above"], "majors": [], "languages": ["english", "chinese"], "language_level": [], "hard_skills": ["excel", "word", "ms office"], "soft_skills": ["capable"], "languages_combined": [{"language": "english", "language_level": []}, {"language": "chinese", "language_level": []}]}, "experience_required": {"duration": [], "field": []}}, {"job_id": "100003009051249", "location_code": "hk", "company": "Chu Kong Optical Mfy Ltd", "job_title": "Shipping Assistant / Operations Officer", "description": "- issuing quotation, purchase orders, invoices\n- issuing packing list and delivery note\n- arrange goods delivery\n- printing production and luxury packaging experience is an advantage", "employment_types": ["Full Time"], "selling_points": ["5 days work", "Modern Office Environment", "FREE shuttle bus service provided"], "locations": ["Kwai Tsing Area"], "categories": ["Transportation & Logistics", "Shipping", "Manufacturing", "Manufacturing Management", "Merchandising & Purchasing", "Others"], "post_time": "2022-01-15T06:15:09Z", "salary": {"currency": null, "max": null, "min": null, "period": "monthly", "term": null}, "salary_visible": false, "title_keywords": ["operations officer", "shipping", "assistant"], "responsibilities": ["purchase", "quotation", "invoices", "packing list"], "requirements": {"degrees": [], "majors": [], "languages": [], "language_level": [], "hard_skills": [], "soft_skills": [], "languages_combined": []}, "experience_required": {"duration": [], "field": []}}, {"job_id": "100003009051237", "location_code": "hk", "company": "Lynns Limited", "job_title": "Shipping Executive", "description": "\u5de5\u4f5c\u8077\u8cac\uff1a\n\n1\uff0e\u8655\u7406\u6cd5\u5f8b\u98a8\u63a7,\u5408\u898f\u76f8\u95dc\u4e8b\u52d9\uff1b\n\n2\uff0e\u8349\u64ec\u548c\u5ba1\u9605\u516c\u53f8\u958b\u5c55\u696d\u52d9\u6240\u9700\u7684\u5404\u9805\u898f\u7ae0\u5236\u5ea6\uff1b\n\n3\uff0e\u5be9\u95b1\u5408\u540c\u689d\u6b3e\u4ee5\u53ca\u5176\u4ed6\u6cd5\u5f8b\u6027\u6587\u4ef6\uff1b\u8d1f\u8d23\u5408\u540c\u7ba1\u7406\u5de5\u4f5c\uff1b\n\n4\uff0eKYC;\n\n5\uff0e\u70ba\u516c\u53f8\u65e5\u5e38\u7d93\u71df\u696d\u52d9\u6d3b\u52d5\u63d0\u4f9b\u6cd5\u5f8b\u610f\u898b\u3002\n\n\u4efb\u8077\u8981\u6c42\uff1a\n\n1.\u00a0 \u00a0\u5168\u65e5\u5236\u5927\u5b78\u822a\u904b\u6216\u6cd5\u5b78\u672c\u79d1\u6216\u4ee5\u4e0a\u5b78\u6b77\u6559\u80b2\u80cc\u666f\u8005\u512a\u5148\uff1b\n\n2.\u00a0 \u00a0\u5177\u5099\u4e2d\u570b\u6216\u82f1\u7f8e\u6cd5\u5f8b\u570b\u5bb6(\u6216\u5730\u5340)\u6cd5\u5f8b\u8077\u696d\u8cc7\u683c\u6216\u5f8b\u5e2b\u8cc7\u683c\u512a\u5148\uff1b\n\n3.\u00a0 \u00a0\u5177\u5099\u98a8\u63a7\u3001\u5408\u898f\u5de5\u4f5c\u7d93\u9a57\u4f18\u5148\uff1b\n\n4.\u00a0 \u00a0\u826f\u597d\u7684\u666e\u901a\u8a71\u4ee5\u53ca\u82f1\u8a9e\u53e3\u982d\u8868\u9054\u548c\u66f8\u5beb\u80fd\u529b\uff1b\n\n5.\u00a0 \u00a0\u5de5\u4f5c\u7a4d\u6975\u4e3b\u52d5\uff0c\u6709\u7368\u7acb\u5de5\u4f5c\u80fd\u529b\uff0c\u517c\u5177\u9ad8\u5ea6\u7684\u5718\u968a\u5408\u4f5c\u7cbe\u795e\u548c\u826f\u597d\u7684\u6e9d\u901a\u80fd\u529b\u3002", "employment_types": ["Full Time"], "selling_points": [], "locations": ["Wan Chai"], "categories": ["Transportation & Logistics", "Shipping"], "post_time": "2022-01-15T05:38:47Z", "salary": {"currency": null, "max": null, "min": null, "period": "monthly", "term": null}, "salary_visible": false, "title_keywords": ["shipping", "executive"], "responsibilities": [], "requirements": {"degrees": [], "majors": [], "languages": [], "language_level": [], "hard_skills": [], "soft_skills": [], "languages_combined": []}, "experience_required": {"duration": [], "field": []}}, {"job_id": "100003009048961", "location_code": "hk", "company": "Bestseller United China Limited", "job_title": "Shipping Assistant - URGENT", "description": "Job responsibilities:\n\nHandle all aspects of shipping\nPrepare the shipping documents, I/E declaration and L/C\nFamiliar with European markets\nCoordinate with factory team on shipments\nCommunicate with buyer, merchandiser, HQ, internal & external department\nAd hoc duties as assigned\n\n\u00a0Job requirements:\n\nForm 6 or above\nAt Least 3 year of relevant working experience in shipping\nExcellent command of both spoken and written English, Chinese and Mandarin\nProficient in MS Word, Excel and other computer skill\nSelf-motivated, proactive and well organized\nAble to work under pressure with strong problem solving skills.\nImmediate available is preferred\n\nTo apply for this opportunity, please\u00a0submit your Resume with salary expectation via email directly.", "employment_types": ["Full Time"], "selling_points": ["Five-day work week", "Excellent command of both spoken and written Eng", "Minimum 3 years relevant experiences"], "locations": ["Tsim Sha Tsui"], "categories": ["Transportation & Logistics", "Shipping"], "post_time": "2022-01-14T07:48:22Z", "salary": {"currency": null, "max": null, "min": null, "period": "monthly", "term": null}, "salary_visible": false, "title_keywords": ["shipping", "assistant"], "responsibilities": ["shipping documents", "communicate with", "ad hoc duties", "shipping", "coordinate with"], "requirements": {"degrees": [], "majors": [], "languages": ["english", "chinese", "mandarin"], "language_level": ["excellent"], "hard_skills": ["excel", "problem solving skills", "computer skill", "ms word"], "soft_skills": ["self-motivated", "well organized", "problem solving skills", "proactive", "work under pressure"], "languages_combined": [{"language": "english", "language_level": ["excellent"]}, {"language": "chinese", "language_level": ["excellent"]}, {"language": "mandarin", "language_level": ["excellent"]}]}, "experience_required": {"duration": ["at least 3 year"], "field": ["relevant working experience"]}}, {"job_id": "100003009050823", "location_code": "hk", "company": "Paladone Products Limited", "job_title": "Shipping Clerk", "description": "We are a UK owned gift and health & beauty company located in TST East. Our office is a convenient 10 minute walk from the TST East or Hung Hom MTR station. We offer an interesting and diverse product range to our international retailers and distributors. We are currently looking for an experienced Shipping Clerk to join our team.\n\nJob Description:\n\n\nPrepare invoices, packing lists and other related documents and payment arrangements\nResponsible for online shipment bookings\nLiaise with related parties - Vendors, Forwarders, Customers for shipping arrangements\nFollow-up order status with the customer merchandising team to ensure customer satisfaction and on-time delivery\nHandling full set of shipping documents, bank documents and customs declarations\nMonitor shipment schedules with vendors and forwarders\nData entry in our ERP system\nPerform ad hoc projects as assigned\nYou need to be highly motivated, responsible, well organized, able to work under pressure, proactive, hardworking; with a can-do attitude, willing to work overtime in peak season and able to work in a fast-paced environment.\n\nYou must be fluent in both spoken and written Cantonese, Mandarin and English.\nYou will have shipping experience across different payment conditions and good knowledge on shipping documents and I/E procedures.\nYou will have at least 3 years\u2019 shipping experience in trading companies (Gift/Toys/Seasonal preferred).\nYou must be proficient in Microsoft Excel, Word and Outlook. Experience with an ERP system is highly regarded, but not necessary as full training will be provided.\n\nWe offer flexible working hours, 13th month salary and discretionary bonus. If you are interested in joining our team, please email your cover letter, CV, expected starting salary, and available starting date by clicking \u201cApply Now\u201d \u2013 please note if you don\u2019t include all just listed, your application will be discarded. Attention to detail is a critical requirement for this role.\n\n", "employment_types": ["Full Time", "Permanent"], "selling_points": [], "locations": ["Tsim Sha Tsui"], "categories": ["Transportation & Logistics", "Shipping"], "post_time": "2022-01-15T03:51:15Z", "salary": {"currency": null, "max": null, "min": null, "period": "monthly", "term": null}, "salary_visible": false, "title_keywords": ["shipping clerk"], "responsibilities": [], "requirements": {"degrees": [], "majors": [], "languages": [], "language_level": [], "hard_skills": [], "soft_skills": [], "languages_combined": []}, "experience_required": {"duration": [], "field": []}}, {"job_id": "100003009052669", "location_code": "hk", "company": "Canon Engineering Hong Kong Co Ltd", "job_title": "Logistics Clerk", "description": "We are looking for intelligent, enthusiastic, caring individuals to fill the following vacancy:\u00a0\n\nCustomer Service Representative (Hong Kong)\n\nWorking with our young, multinational team, you will be a primary point of contact for our clients, assisting & coordinating\u00a0 every aspect of the services that we provide to them. This includes handling of shipping documents,\u00a0execute new bookings, communication with existing and new clients.\n\nWhat we seek\n\nBoth English & Cantonese must be spoken to a \u201cmother tongue\u201d level\nOne year of work experience necessary within administration and/or shipping backgroundOverseas graduate a plus\n\nMonthly salary HK$15,000 to HK$19,000\n\nWhat we offer\n\nWe\u2019re wired a bit differently and we pursue ambitious goals in an intriguing environment. We love a dynamic corporate culture with flat hierarchies. We offer a start-up atmosphere with excellent development opportunities. Are you enthusiastic about tackling new challenges that suit your personality and abilities? Perfect! Because as a\u00a0Customer Service Representative\u00a0working full time in our office in Hong Kong, you\u2019re able to actively shape our future success. And it's important to know: We hire for attitude and train for skills!\n\nPlease send your resume, salary expectation and availability to enquiry at relosmart.asia", "employment_types": ["Full Time", "Permanent"], "selling_points": [], "locations": ["Kwai Hing"], "categories": ["Transportation & Logistics", "Others", "Freight Forwarding", "Shipping"], "post_time": "2022-01-17T03:40:49Z", "salary": {"currency": null, "max": null, "min": null, "period": "monthly", "term": null}, "salary_visible": false, "title_keywords": ["logistics clerk"], "responsibilities": ["customer service"], "requirements": {"degrees": [], "majors": [], "languages": [], "language_level": [], "hard_skills": [], "soft_skills": ["customer service", "enthusiastic"], "languages_combined": []}, "experience_required": {"duration": [], "field": []}}, {"job_id": "100003009051222", "location_code": "hk", "company": "Easy Job Centre", "job_title": "Shipping Clerk / Senior Shipping Clerk", "description": "Responsibilities\n\nCoordinate with the logistics team and plan shipments based on product availability and customer requests.\nTrack shipments to ensure timely deliveries.\nPrepare shipping documents on time (like invoices, purchase orders, and bills of lading).\nSchedule shifts with third parties to ensure continuous operation during public holidays.\nMaintain updated and accurate records of shipments, suppliers, and customers in the CTRM.\nProvide information to customers about the status of their orders.\nRaise change requests from the client and shipment issues on time.\nMake document presentations to the bank against the letter of credit or arrange prepayment from the clients.\nConduct any quality or quantity claim.\nInteract with both internal and external clients related to the deliveries, and cover the work while any colleague is on leave or absent.\nUndertake analysis to identify potential logistics issues and collaborate with different departments to take preventive and corrective actions.\nAd hoc projects as assigned.\n\nRequirements\n\nWork experience as a Logistics Administrator, Supply Change, or similar role.\nBasic accounting knowledge.\nExcellent organizational, time-management skills, and able to multi-task effectively.\nGood communication skills, fluent in English and Mandarin, Cantonese is an advantage.\nBSc in Supply chain management, Logistics, or relevant field.\nStrong knowledge of the letter of credit for import/export.\nStrong analytical and quantitative skills.\nExcellent in MS Word, Excel, and PowerPoint. Knowledge of ERP and CTRM is an advantage.\nInterested parties, please send your resume with availability and current and expected salary to jenny.chai@manpowergrc.hk.\u00a0", "employment_types": ["Full Time"], "selling_points": [], "locations": ["Tsim Sha Tsui"], "categories": ["Transportation & Logistics", "Freight Forwarding", "Shipping", "Supply Chain"], "post_time": "2022-01-15T05:19:56Z", "salary": {"currency": null, "max": null, "min": null, "period": "monthly", "term": null}, "salary_visible": false, "title_keywords": ["shipping clerk"], "responsibilities": ["shipping documents", "collaborate with", "invoices", "analysis", "coordinate with", "quality", "presentations", "purchase", "maintain", "logistics", "schedule", "plan", "customer requests", "ad hoc projects"], "requirements": {"degrees": ["bsc"], "majors": [], "languages": ["cantonese", "english", "mandarin"], "language_level": ["advantage", "fluent", "good"], "hard_skills": ["excel", "basic", "erp", "powerpoint", "ms word"], "soft_skills": ["communication skills", "organizational", "multi-task"], "languages_combined": [{"language": "cantonese", "language_level": ["advantage", "good"]}, {"language": "english", "language_level": ["fluent", "good"]}, {"language": "mandarin", "language_level": ["fluent", "good"]}]}, "experience_required": {"duration": [], "field": ["logistics"]}}, {"job_id": "100003009056900", "location_code": "hk", "company": "Philex Hong Kong Limited", "job_title": "Shipping Clerk", "description": "Job Description:\u00a0Senior / Junior Shipping Clerk\n\n\u00a0Job Duties:\n\n\u00a0\u00a0\u00a0\u00a0\u00a0\u00a0\u00a0Independently handle full set of I/E documents, custom declaration to meet requirements;\n\u00a0\u00a0\u00a0\u00a0\u00a0\u00a0\u00a0Coordination with forwarders, and factories about all transportation issues including ocean and air freight forwarding, Liaise with related parties, shipment arrangement independently;\n\nRequirements:\n\n\u00a0\u00a0\u00a0\u00a0\u00a0\u00a0\u00a0Form 5 or DSE above;\n\u00a0\u00a0\u00a0\u00a0\u00a0\u00a0\u00a01-2 years working experience in shipping department of the trading company dealing in US , UK & Europe market.\n\u00a0\u00a0\u00a0\u00a0\u00a0\u00a0\u00a0Good English, Mandarin (Spoken and Written);\n\u00a0\u00a0\u00a0\u00a0\u00a0\u00a0\u00a0Understand the shipment process and work flow of factory in China;\n\u00a0\u00a0\u00a0\u00a0\u00a0\u00a0\u00a0Responsible for handling import /export documents , shipment and logistics arrangement ,Letter of Credit.\n\u00a0\u00a0\u00a0\u00a0\u00a0\u00a0\u00a0Proficiency in PC skills, such as MS office, Excel and Chinese word processing;\n\u00a0\u00a0\u00a0\u00a0\u00a0\u00a0\u00a0Good problem solving skill;\n\u00a0\u00a0\u00a0\u00a0\u00a0\u00a0\u00a0Independent, initiative and responsible;.\n\u00a0\u00a0\u00a0\u00a0\u00a0\u00a0\u00a0Immediate available is highly preferable\n\nCompany offers attractive remuneration package including\u00a05-day work, 12 days AL + banking holidays, double pay\u00a0to the right candidate.\u00a0\u00a0Interested parties please email us your full resume in MS Word or PDF format including your current and expected salary.\n\nAll information received will be kept in strict confidence and only for employment related purpose.\n\nAdditional Information\n\nCareer Level\n\nEntry Level\n\nQualification\n\nSchool Certificate\n\nYears of Experience\n\nJob Type\n\nFull Time, Permanent\n\nJob Functions\n\nTransportation & Logistics,\u00a0Freight Forwarding,\u00a0Shipping", "employment_types": ["Full Time"], "selling_points": [], "locations": ["Tsim Sha Tsui"], "categories": ["Transportation & Logistics", "Shipping"], "post_time": "2022-01-18T06:44:38Z", "salary": {"currency": null, "max": null, "min": null, "period": "monthly", "term": null}, "salary_visible": false, "title_keywords": ["shipping clerk"], "responsibilities": ["shipping", "shipment arrangement", "air freight", "custom declaration", "coordination with", "liaise with"], "requirements": {"degrees": ["form 5", "dse"], "majors": [], "languages": ["english", "chinese", "mandarin"], "language_level": ["proficiency", "good"], "hard_skills": ["excel", "chinese word processing", "problem solving", "pc skills", "ms office"], "soft_skills": ["problem solving skill", "independent", "initiative", "responsible"], "languages_combined": [{"language": "english", "language_level": ["good"]}, {"language": "chinese", "language_level": ["proficiency"]}, {"language": "mandarin", "language_level": []}]}, "experience_required": {"duration": ["1-2 years"], "field": ["trading"]}}, {"job_id": "100003009056620", "location_code": "hk", "company": "Harvest Strong Limited", "job_title": "Shipping Manager", "description": "Job Category :Management / ShippingJob Title :Shipping managerNo. of Vacancy :1Job Location :Tsim Sha Tsui\nJob Duties and Requirements :\n\nMinimum 5 years of shipping experience in handling consumer goods preferablr in multinational company. Familiar with U.S. market. Coordinate and arrange shipment schedule with various parties. Handle full set of I/E documents, L/C banking document for US market independently. Occasional travelling to Shenzhen office in handling shipping documents when required. Willing to work overtime. English and Mandarin are musts. PC knowledge on MS Excel & Words. Supervise the junior on shipment schedule, booking, customer requirements and coordinate with factory on ship docs. submit, Daily report to management. (IMMEDIATELY AVAILABLE PREFERRED)\n\nJob Type :Full TimeWorking Days Per Week :5Working Hours :From 0930 to 1730Salary :HKD 19,000 UP (Negotiable)Other Benefits and\nAllowances :Lunch is provided\nTransportation Reimbursement\nDouble Pay\nDiscretionary Bonus\nMedical Allowance\nAnnual LeaveEducation Level :Certificate in Logistics relatedRelated Experience5 years or aboveContact Method :Interested parties, please e-mail full resume by e-mail to:\n(Attn: Mr. Chan)\u00a0\"Personal data collected will be used for recruitment purpase only.\"", "employment_types": ["Full Time"], "selling_points": [], "locations": ["Tsim Sha Tsui"], "categories": ["Transportation & Logistics", "Others", "Shipping"], "post_time": "2022-01-18T05:11:42Z", "salary": {"currency": "HKD", "max": 34999, "min": 25000, "period": "monthly", "term": null}, "salary_visible": true, "title_keywords": ["shipping", "manager"], "responsibilities": [], "requirements": {"degrees": [], "majors": [], "languages": ["english", "mandarin"], "language_level": [], "hard_skills": ["pc knowledge", "c", "ms excel", "words"], "soft_skills": ["work overtime", "independently"], "languages_combined": [{"language": "english", "language_level": []}, {"language": "mandarin", "language_level": []}]}, "experience_required": {"duration": ["minimum 5 years"], "field": ["multinational company"]}}, {"job_id": "100003009056998", "location_code": "hk", "company": "Union Apparel International Ltd", "job_title": "Shipping Clerk", "description": "F.7 / DSE or above graduate\u00a0\n2-3 years solid experience in shipping documents\nGeneral clerical support to Accounts Department\u00a0\nGood interpersonal skills, self-motivated, stable\nProficiency in computer applications, e.g. MS Word, Excel and Chinese Word Processing\nGood command in spoken and written English and Chinese\nExperience in Garment Field is preferred\u00a0\nImmediate available is preferred\u00a0\n\nAttractive salary and benefit package will be offered to the right candidates.\u00a0\u00a0\n\nPlease include your expected salary and email by clicking \"Apply Now\" for an applicant form.\n\n\nAttn: Union Apparel International Ltd. - Ms. Cheung\n\n(Location: San Po Kong \u2013 Near Diamond Hill Station)\n\nPersonal data collected will be used for recruitment purpose only.", "employment_types": ["Full Time", "Permanent"], "selling_points": ["Attractive Salary & Benefit Package", "Promotion Chance", "Good Career Path"], "locations": ["Wong Tai Sin Area"], "categories": ["Transportation & Logistics", "Shipping"], "post_time": "2022-01-18T07:07:46Z", "salary": {"currency": null, "max": null, "min": null, "period": "monthly", "term": null}, "salary_visible": false, "title_keywords": ["shipping clerk"], "responsibilities": ["shipping documents", "clerical support", "recruitment", "computer applications", "personal data"], "requirements": {"degrees": ["dse"], "majors": [], "languages": ["english", "chinese"], "language_level": ["good command"], "hard_skills": ["excel", "chinese word processing", "ms word"], "soft_skills": ["self-motivated", "interpersonal skills", "stable"], "languages_combined": [{"language": "english", "language_level": ["good command"]}, {"language": "chinese", "language_level": ["good command"]}]}, "experience_required": {"duration": ["2-3 years"], "field": ["garment"]}}, {"job_id": "100003009054923", "location_code": "hk", "company": "Eternity Consultants (HK) Ltd", "job_title": "Shipping Clerk / Operation Clerk", "description": "Trading\n\n\u00a0\u00a0Requirements:\n\nF.5\nAt least 3 -8 years shipping experience in shipping in Trading or factory\n\nFull set of I/E, L/C documents\nContact with\u00a0vendor, overseas buyer, forwarder\nExperience in USA and Europe market\nGood communication and\n\nGood commend of both English and Mandarin\n\n*Interested parties, please Email full resume with current & expected salary & date available in MS WORD FORMAT ONLY to us\u00a0or fax to 3527 0634*\n\nFor more jobs, please visit our website: www.hketernity.com\n\n(Personal data submitted are for recruitment purpose only.)", "employment_types": ["Full Time", "Permanent"], "selling_points": ["5 days, bank holiday, 10 al", "Diploma or above", "3-8 yrs shipping exp in trading, factory"], "locations": ["Not Specified"], "categories": ["Transportation & Logistics", "Freight Forwarding", "Shipping", "Supply Chain"], "post_time": "2022-01-17T14:03:14Z", "salary": {"currency": null, "max": null, "min": null, "period": "monthly", "term": null}, "salary_visible": false, "title_keywords": ["shipping clerk", "operation clerk"], "responsibilities": ["communication", "shipping", "contact"], "requirements": {"degrees": [], "majors": [], "languages": ["english", "mandarin"], "language_level": ["good"], "hard_skills": ["c", "vendor"], "soft_skills": ["communication"], "languages_combined": [{"language": "english", "language_level": ["good"]}, {"language": "mandarin", "language_level": ["good"]}]}, "experience_required": {"duration": ["at least 3 -8 years"], "field": ["trading"]}}, {"job_id": "100003009056727", "location_code": "hk", "company": "Golden Ticket Limited", "job_title": "Shipping Clerk / Shipping Coordinator / Office Admin", "description": "JOB HIGHLIGHTS:\n\nReliable, has initiative and is willing to learn.\nHard working and can handle full set of shipping docs.\nCan handle all logistics duties independently.\nNice, stable and friendly work environment.\n\nJob Description\n\nResponsibilities:\n\nVerify, file and keep records of shipment documentation.\nHandle import shipment as well as I/E customs declaration.\nPrepare shipment documents and export shipment report, etc.\nCoordinate with customers, factory and forwarder for shipment arrangement.\nExperience in handling documents to US Countries. \u00a0\n\nRequirements:\n\nForm 5\u00a0or above;\nCapable in handling import shipment and tradelink system.\nFamiliar with MS Office applications including Word & Excel.\nAble to communicate in Chinese & English.\n\nWe offer 5-day work, bank holidays. Interested candidates please send your full resume with CURRENT/LAST & EXPECTED SALARY.\n\n(Information collected will be used for recruitment purpose only)", "employment_types": ["Full Time"], "selling_points": [], "locations": ["Tsim Sha Tsui"], "categories": ["Transportation & Logistics", "Shipping"], "post_time": "2022-01-18T06:05:00Z", "salary": {"currency": null, "max": null, "min": null, "period": "monthly", "term": null}, "salary_visible": false, "title_keywords": ["admin", "shipping clerk", "shipping coordinator"], "responsibilities": ["customs declaration", "shipment arrangement", "handling documents", "coordinate with", "documentation", "report"], "requirements": {"degrees": ["form 5 or above"], "majors": [], "languages": ["english", "chinese"], "language_level": [], "hard_skills": ["excel", "word", "ms office"], "soft_skills": ["capable"], "languages_combined": [{"language": "english", "language_level": []}, {"language": "chinese", "language_level": []}]}, "experience_required": {"duration": [], "field": []}}, {"job_id": "100003009055691", "location_code": "hk", "company": "Manpower Services (Hong Kong) Limited", "job_title": "Logistics Admin _Natural Resources_ Max 35K", "description": "Responsibilities\n\nCoordinate with the logistics team and plan shipments based on product availability and customer requests.\nTrack shipments to ensure timely deliveries.\nPrepare shipping documents on time (like invoices, purchase orders, and bills of lading).\nSchedule shifts with third parties to ensure continuous operation during public holidays.\nMaintain updated and accurate records of shipments, suppliers, and customers in the CTRM.\nProvide information to customers about the status of their orders.\nRaise change requests from the client and shipment issues on time.\nMake document presentations to the bank against the letter of credit or arrange prepayment from the clients.\nConduct any quality or quantity claim.\nInteract with both internal and external clients related to the deliveries, and cover the work while any colleague is on leave or absent.\nUndertake analysis to identify potential logistics issues and collaborate with different departments to take preventive and corrective actions.\nAd hoc projects as assigned.\n\nRequirements\n\nWork experience as a Logistics Administrator, Supply Change, or similar role.\nBasic accounting knowledge.\nExcellent organizational, time-management skills, and able to multi-task effectively.\nGood communication skills, fluent in English and Mandarin, Cantonese is an advantage.\nBSc in Supply chain management, Logistics, or relevant field.\nStrong knowledge of the letter of credit for import/export.\nStrong analytical and quantitative skills.\nExcellent in MS Word, Excel, and PowerPoint. Knowledge of ERP and CTRM is an advantage.\nInterested parties, please send your resume with availability and current and expected salary to jenny.chai@manpowergrc.hk.\u00a0", "employment_types": ["Permanent"], "selling_points": ["Exp in handling L/C & Supply Chain procedure", "Fluent English & Mandarin", "Immediatly Available"], "locations": ["Central"], "categories": ["Transportation & Logistics", "Fulfillment", "Shipping", "Supply Chain"], "post_time": "2022-01-18T02:51:17Z", "salary": {"currency": null, "max": null, "min": null, "period": "monthly", "term": null}, "salary_visible": false, "title_keywords": ["admin", "logistics"], "responsibilities": ["shipping documents", "collaborate with", "invoices", "analysis", "coordinate with", "quality", "presentations", "purchase", "maintain", "logistics", "schedule", "plan", "customer requests", "ad hoc projects"], "requirements": {"degrees": ["bsc"], "majors": [], "languages": ["cantonese", "english", "mandarin"], "language_level": ["advantage", "fluent", "good"], "hard_skills": ["excel", "basic", "erp", "powerpoint", "ms word"], "soft_skills": ["communication skills", "organizational", "multi-task"], "languages_combined": [{"language": "cantonese", "language_level": ["advantage", "good"]}, {"language": "english", "language_level": ["fluent", "good"]}, {"language": "mandarin", "language_level": ["fluent", "good"]}]}, "experience_required": {"duration": [], "field": ["logistics"]}}, {"job_id": "100003009049888", "location_code": "hk", "company": "Benetton Asia Pacific Limited", "job_title": "Shipping Clerk", "description": "Responsibilities\n\n\nResponsible for general shipping document control and I/E declaration\nCommunicate with internal department, suppliers and Italy headquarter\nFollowing with suppliers as control shipment in all shipping method\nHandling correspondence with external vendors & suppliers\nAssist in daily administrative duties of the department\n\nJob Requirements\n\nHKCEE/HKDSE or above\n2-3 years shipping experience and familiar in Garment field at buying office is preferable\nExperience in dealing with the factory and forwarding agent\nAble to work independent and under pressure\nFamiliar with MS Excel and Word\nProficiency in English and Mandarin, good writing skills is preferred\nResponsible and committed. Details Oriented with good numerical sense\nFresh graduate will also be considered\nImmediate available is highly preferred\n\nWe offer 5-day work week, extended paternity leave, family care leave, birthday leave and good career development opportunities in a young and dynamic environment. Interested parties, please send your resume, quoting the reference no. and stating your current & expected salary to Benetton Asia Pacific Limited by clicking\u00a0 \"Apply Now\".\n\n(Personal data collected will be used for recruitment purpose only)", "employment_types": ["Full Time", "Permanent"], "selling_points": ["5-Day Work Week", "Flexible working hour", "Family care leave"], "locations": ["Kowloon Bay"], "categories": ["Transportation & Logistics", "Shipping", "Supply Chain", "Others", "Trading"], "post_time": "2022-01-14T09:24:00Z", "salary": {"currency": null, "max": null, "min": null, "period": "monthly", "term": null}, "salary_visible": false, "title_keywords": ["shipping clerk"], "responsibilities": ["communicate with", "control", "shipping", "administrative duties", "shipping document"], "requirements": {"degrees": ["hkdse", "fresh graduate"], "majors": [], "languages": ["english", "mandarin"], "language_level": ["proficiency", "good"], "hard_skills": ["ms excel", "dynamic", "word", "writing skills"], "soft_skills": ["dynamic environment", "independent", "under pressure", "responsible", "writing skills", "committed"], "languages_combined": [{"language": "english", "language_level": ["proficiency", "good"]}, {"language": "mandarin", "language_level": ["proficiency", "good"]}]}, "experience_required": {"duration": ["2-3 years"], "field": ["garment"]}}, {"job_id": "100003009052642", "location_code": "hk", "company": "Tai Luen Coffee Co Ltd", "job_title": "Temporary Clerk", "description": "Job Descriptions:\n\nProvide full spectrum of administrative and clerical support in daily operations\nAssist to prepare monthly reports, documents , correspondence and summaries\u00a0\nAssist in ad hoc assignments\n\n\u00a0The ideal candidate should be :\n\nDiploma in Business Administration or related disciplines or above\u00a0\nAble to work independently, well organized, strong sense of responsibility, detail-minded, self-motivated, good communication and interpersonal skills\nGood command in spoken and written English and Chinese\nProficiency in MS Office software application and Chinese word processing\nImmediate available is highly preferred\n\nPlease send your application with resume and expected salary to The HR Manager, Tai Luen Coffee Company Limited, 7/F, DCH Building, 20 Kai Cheung Road, Kowloon Bay or send your application online by clicking\u00a0\"Apply Now\".\n\nInformation provided will be for the purpose of selection within the company and only shortlisted candidates will be contacted. All applications will be retained for a maximum period of 6 months.\u00a0", "employment_types": ["Part Time", "Temporary"], "selling_points": [], "locations": ["Shatin Area"], "categories": ["Admin & HR", "Clerical / Admin Staff", "Transportation & Logistics", "Shipping", "Supply Chain"], "post_time": "2022-01-17T03:37:46Z", "salary": {"currency": null, "max": null, "min": null, "period": "monthly", "term": null}, "salary_visible": false, "title_keywords": ["temporary clerk"], "responsibilities": ["software", "monthly reports", "hr", "communication", "daily operations", "ad hoc assignments", "administrative and clerical support", "administration"], "requirements": {"degrees": ["diploma"], "majors": ["related disciplines", "business administration"], "languages": ["english", "chinese"], "language_level": ["proficiency", "good command"], "hard_skills": ["chinese word processing", "ms office"], "soft_skills": ["detail-minded", "work independently", "self-motivated", "sense of responsibility", "well organized", "communication and interpersonal skills", "ideal"], "languages_combined": [{"language": "english", "language_level": ["good command"]}, {"language": "chinese", "language_level": ["proficiency", "good command"]}]}, "experience_required": {"duration": [], "field": []}}, {"job_id": "100003009056873", "location_code": "hk", "company": "Omnibrand Limited", "job_title": "Accounting Assistant & Logistics Clerk", "description": "General clerical works/duties at those 2 departments;\nWork closely with various internal divisions;\nAssist in any ad hoc tasks assigned by the team supervisor.\n\n\u00a0Requirements:\n\nF.5 or above;\u00a0 \u00a0\n1 year relevant working experience;\nFamiliar with MS Office;\u00a0\u00a0 \u00a0\nProactive and detail-mined, self-motivated and able to work under pressure;\nImmediately available is highly preferred.\u00a0\n\nPlease forward detailed resume stating employment history with expected salary to HR Department.\u00a0\n\nAll information collected for recruitment purpose only.", "employment_types": ["Full Time", "Permanent"], "selling_points": [], "locations": ["Wong Tai Sin Area"], "categories": ["Accounting", "Accounting Clerk / Supervisor", "Transportation & Logistics", "Shipping"], "post_time": "2022-01-18T06:37:33Z", "salary": {"currency": null, "max": null, "min": null, "period": "monthly", "term": null}, "salary_visible": false, "title_keywords": ["accounting assistant", "logistics clerk"], "responsibilities": ["recruitment", "hr", "ad hoc tasks", "work under pressure"], "requirements": {"degrees": [], "majors": [], "languages": [], "language_level": [], "hard_skills": ["ms office"], "soft_skills": ["self-motivated", "proactive", "detailed", "work under pressure"], "languages_combined": []}, "experience_required": {"duration": ["1 year"], "field": ["relevant working experience"]}}, {"job_id": "100003009054690", "location_code": "hk", "company": "Nesta (Hong Kong) Limited", "job_title": "Load Control Officer / Flight Planning Officer / Cargo Service Officer (18-20K, 5days)", "description": "Our client is a world\u2019s premier company specializing in Express Service is now seeking for a high caliber to join their team as Load Control Officer / Flight Planning Officer / Cargo Service Officer.\n\nJOB RESPONSIBILITY\n\nHandle shipment booking enquiries from overseas countries for flight arrangement\nCommunicate with other Hubs and Gateways on real time flight and shipment monitoring\nPerform customer service for network tracing and investigation of shipment\u00a0 issues\nPrepare reports and\u00a0 Unit Load Device (ULD) inventory management\u00a0\n\nJOB REQUIREMENT\n\nDiploma holder or above\n2 years experience in industry of\u00a0transportation, logistics, airlines, airport operations or freight forwarding\u00a0\nGood command of written and spoken English\nGood analytical, telephone manner customer services skills", "employment_types": ["Full Time"], "selling_points": ["MNC Logistic Company with Good Package", "18-20K, 5days", "Airline / Ground Services Experience preferred!!"], "locations": ["Not Specified"], "categories": ["Transportation & Logistics", "Aviation Services", "Freight Forwarding", "Shipping"], "post_time": "2022-01-17T10:35:28Z", "salary": {"currency": null, "max": null, "min": null, "period": "monthly", "term": null}, "salary_visible": false, "title_keywords": ["officer"], "responsibilities": ["communicate with", "monitoring", "investigation", "inventory management", "customer service", "booking", "prepare reports"], "requirements": {"degrees": ["diploma holder"], "majors": [], "languages": ["english"], "language_level": ["good command"], "hard_skills": ["airlines"], "soft_skills": ["telephone manner", "customer services skills"], "languages_combined": [{"language": "english", "language_level": ["good command"]}]}, "experience_required": {"duration": ["2 years"], "field": ["logistics"]}}, {"job_id": "100003009054753", "location_code": "hk", "company": "Powertek Group Co., Limited", "job_title": "Assistant Office Supervisor", "description": "Task & Responsibilities:\n\u2022 Prepare invoice / delivery note / packing list, etc\n\u2022 Handle shipping arrangement and document\n\u2022 Provide clerical support to the Logistic Department\n\u2022 Organize and assign proper manpower\n\u2022 Uphold a positive working mentality across the team\n\u2022 To assist other ad-hoc projects as assigned\n\nQualifications and Experience:\n\u2022 Diploma / Associate Degree or related disciplines\n\u2022 At least 3~5 years solid relevant experience\n\u2022 Familiar with \u201cTradelink\u201d for custom declaration, ERP system, BarTender software\n\u2022 Good command of written and spoken English, Chinese and Putonghua\n\u2022 Proficient in using MS Office (especially in Excel)\n\u2022 Familiar with Chinese typing\n\u2022 Good analytical, decision making and problem solving skills, responsible, well organized and a fast learner\n\u2022 Strong communication and leadership skills\n\u2022 Willing to work overtime when necessary and able to work under pressure\n\u2022 Immediately availability preferred\n\nInterested parties please send full resume with present and expected salary to us.\n(All information collected will be used for recruitment purpose only)", "employment_types": ["Full Time"], "selling_points": [], "locations": ["Kwun Tong"], "categories": ["Transportation & Logistics", "Inventory / Warehousing", "Shipping", "Supply Chain"], "post_time": "2022-01-17T10:53:55Z", "salary": {"currency": null, "max": null, "min": null, "period": "monthly", "term": null}, "salary_visible": false, "title_keywords": ["supervisor", "assistant"], "responsibilities": ["provide clerical support", "shipping", "software", "tradelink", "invoice", "custom declaration", "packing list", "communication", "ad-hoc projects", "work under pressure"], "requirements": {"degrees": ["associate degree", "diploma"], "majors": ["related disciplines"], "languages": ["putonghua", "english", "chinese"], "language_level": ["good command"], "hard_skills": ["excel", "typing", "erp system", "problem solving skills", "ms office"], "soft_skills": ["work overtime", "responsible", "work under pressure", "leadership skills", "well organized", "communication", "problem solving skills", "fast learner", "positive", "decision making"], "languages_combined": [{"language": "putonghua", "language_level": ["good command"]}, {"language": "english", "language_level": ["good command"]}, {"language": "chinese", "language_level": ["good command"]}]}, "experience_required": {"duration": ["at least 3~5 years"], "field": ["relevant experience"]}}, {"job_id": "100003009047897", "location_code": "hk", "company": "Goldlok Holdings (Guangdong) Company Limited", "job_title": "Shipping Clerk (Toys)", "description": "We are the dynamic & fast-growing Toy manufacturer located in TST, it\u2019s now looking for high caliber candidates to fill the following positions, selected candidates will be invited to join our young & dynamic team:\n\n\nResponsibilities:\n\nResponsible for shipment and order follow up\nHandle full set I/E documents independently\nLiaise and coordinate internally and externally on shipping / local transportation\nPrepare packing list, invoice and delivery note\n\u00a0Communicate with overseas headquarter and forwarding company for shipment arrangement\n\nWork aspects:\n\nF.5 or above with full certificate\nAt least 2 years working experience in I/E firm or shipping related company\nGood PC knowledge (MS Office, Word, Excel, English and Chinese word processing)\nFluent command of spoken and written English, Cantonese and Mandarin;\nGood communication & interpersonal skills\nSelf-motivated, reliable and independent\nImmediate available is highly preferable\nAttractive salary package will be offered to right candidates. Please e-mail detailed resume with\n\nWe offer attractive remuneration including MPF, medical insurance, performance bonus and excellent career prospect to the right candidates.\u00a0 Please send email to Apply Now\u00a0for interview arrangement.", "employment_types": ["Full Time"], "selling_points": [], "locations": ["Tsim Sha Tsui"], "categories": ["Transportation & Logistics", "Documentary Credit / Bills Processing", "Freight Forwarding", "Shipping"], "post_time": "2022-01-14T07:40:27Z", "salary": {"currency": null, "max": null, "min": null, "period": "monthly", "term": null}, "salary_visible": false, "title_keywords": ["shipping clerk"], "responsibilities": ["liaise", "communicate with", "shipping", "shipment arrangement", "invoice", "packing list", "coordinate", "communication"], "requirements": {"degrees": ["certificate"], "majors": [], "languages": ["cantonese", "english", "chinese", "mandarin"], "language_level": ["fluent", "good"], "hard_skills": ["excel", "chinese word processing", "word", "dynamic", "pc knowledge", "ms office"], "soft_skills": ["self-motivated", "independently", "independent", "responsible", "communication", "dynamic", "interpersonal skills", "reliable", "detailed"], "languages_combined": [{"language": "cantonese", "language_level": ["fluent"]}, {"language": "english", "language_level": ["fluent", "good"]}, {"language": "chinese", "language_level": ["good"]}, {"language": "mandarin", "language_level": ["fluent"]}]}, "experience_required": {"duration": ["at least 2 years"], "field": ["related"]}}, {"job_id": "100003009055212", "location_code": "hk", "company": "Scan-Shipping Hong Kong Limited", "job_title": "Warehouse Datacenter Coordinator (5 days work)", "description": "Job Description:\n\nResponsible for all aspects of the warehouse functions including the receiving, storing, handling, shipping and preparing of product for customer delivery while maintaining the warehouse in a safe and orderly fashion.\nMaintain all asset inventory records for the site and conduct regular reporting\nIdentify any damages to shipments when received and follow escalation procedures immediately\n\nRequirement:\n\nForm 5 or above\n3-5 years of related industry experience\nCustomer Service experience required\nKnowledge of Dangerous Goods/Restricted Article Regulations Preferred\nSelf-motivated, attention to detail, well organized, independent and able to work under pressure\nFluent in spoken and written of Cantonese\nProficiency in reading, spoken and written of English\nPhysical work is necessary\nMust be able to work flexible schedule (extended hours or evenings, weekends and holidays as required)\n\nBenefits:\n\n40 working hours per week,\u00a0 5 days work, Sunday off\nProvide system training\nMedical plan\n\nJob Location: Tsuen Wan and/or Chai Wan", "employment_types": ["Full Time"], "selling_points": ["40 working hours per week, Sunday off", "3-5 years of related industry experience", "Provide system training, Medical plan"], "locations": ["Tsuen Wan Area"], "categories": ["Sales, CS & Business Devpt", "Customer Service - Supervisor / Officer", "Transportation & Logistics", "Inventory / Warehousing", "Shipping"], "post_time": "2022-01-18T01:46:56Z", "salary": {"currency": null, "max": null, "min": null, "period": "monthly", "term": null}, "salary_visible": false, "title_keywords": ["coordinator"], "responsibilities": ["reporting", "shipping", "maintaining", "procedures", "maintain", "asset inventory"], "requirements": {"degrees": ["form 5 or above"], "majors": [], "languages": ["cantonese", "english"], "language_level": ["proficiency", "fluent"], "hard_skills": [], "soft_skills": ["flexible", "self-motivated", "independent", "well organized", "customer service", "attention to detail", "work under pressure"], "languages_combined": [{"language": "cantonese", "language_level": ["fluent"]}, {"language": "english", "language_level": ["proficiency"]}]}, "experience_required": {"duration": ["3-5 years"], "field": ["related", "customer service"]}}, {"job_id": "100003009054339", "location_code": "hk", "company": "YKK Hong Kong Limited", "job_title": "Associate Planning & Operation Executive", "description": "Job Descriptions:\n\nResponsible for purchasing & operation activities from business contracts, sourcing, price negotiation, orders, shipment;\n\nCollaborate with sales team and liaise with suppliers to drive on time shipment delivery;\nLiaise and support post-contract management activities like handling deliveries discrepancies and monitoring supplier performance;\nHandle full set of shipping I/E documents, liaise with supplier and forwarders for shipment schedule and arrangement;\nPrepare regular reporting and conduct analysis to support business decisions;\nAssist in other ad-hoc assignment as required.\n\nJob Requirements:\n\nDegree holder majoring in Purchasing, Supply Chain Management or other related subjects with at least 2 years related working experience, with background in purchasing field or manufacturing industry will be a plus;\n\nFluent in spoken and written English & Chinese (Cantonese and Mandarin);\nWell versed with PC applications, i.e. MS Word, Excel, PowerPoint & Chinese Word Processing;\nPatient, detailed-mind, willing to learn, able to work under pressure;\nWell-organized with good interpersonal and communication skills;\nCandidates with more experience will be considered as Planning & Operation Executive.\n\nBenefits:\n\n5-day work\u00a0(staggered working hours)\nDouble pay\nDiscretionary bonus\nGroup medical\nOT pay\nStatutory Annual Leave with extra\u00a07 days Company Annual Leave\nBank Holiday\nOther Special Leave i.e. Marriage Leave, etc.\n\nWe offer competitive remuneration and benefits, holidays, stable working environment to the right candidates. Interested parties please click \"Apply Now\" and send your full resume with expected salary in MS Word Format to us (Please quote Position Name & Reference No.)\n\n*All personal data collected will be kept strictly confidential and used for recruitment-related purpose only.", "employment_types": ["Full Time", "Permanent"], "selling_points": ["Degree in Purchasing / Supply Chain Management", "2 years exp.,Good command of English & Chinese", "5-day, 13-mth, discretionary bonus, extra leave"], "locations": ["Tsim Sha Tsui"], "categories": ["Transportation & Logistics", "Shipping", "Supply Chain", "Merchandising & Purchasing", "Textiles"], "post_time": "2022-01-17T09:12:06Z", "salary": {"currency": null, "max": null, "min": null, "period": "monthly", "term": null}, "salary_visible": false, "title_keywords": ["associate", "operation executive"], "responsibilities": ["collaborate with", "liaise", "price negotiation", "shipping", "reporting", "ad-hoc", "contracts", "analysis", "monitoring", "contract management", "support business decisions", "sales team", "schedule", "liaise with", "liaise with suppliers"], "requirements": {"degrees": ["degree holder"], "majors": ["manufacturing"], "languages": ["cantonese", "english", "chinese", "mandarin"], "language_level": ["fluent"], "hard_skills": ["excel", "plus", "chinese word processing", "powerpoint", "pc applications", "ms word"], "soft_skills": ["communication skills", "willing to learn", "well-organized", "detailed", "patient", "interpersonal", "work under pressure"], "languages_combined": [{"language": "cantonese", "language_level": ["fluent"]}, {"language": "english", "language_level": ["fluent"]}, {"language": "chinese", "language_level": ["fluent"]}, {"language": "mandarin", "language_level": ["fluent"]}]}, "experience_required": {"duration": ["at least 2 years"], "field": ["management", "purchasing", "supply chain", "related", "operation", "manufacturing industry", "planning"]}}, {"job_id": "100003009056125", "location_code": "hk", "company": "DHL Aviation (Hong Kong) Limited", "job_title": "Operations Support Agent", "description": "Working Location:\u00a0Chek Lap Kok\nReporting to the NCG Supervisor, Operations Support, you will liaise and work closely with the operations team in order to provide clerical and documentation support of shipments entering and exiting the Central Asia Hub\nExecute flight movement alerts, transmit shipment information and prepare flight documentations\nRectify and follow up on network on non-conforming shipments.\nConduct and coordinate warehouse searches generated by network trace requests\nPrint shipment manifest for shipment lodgement\nPrepare and handle the documentation for Dangerous Goods and Lithium battery\nRegister, maintain and follow the trace in DHL application to resolve the Lost and Found shipment\nRequirements:\nSecondary education with at least 2 years clerical or operations support experience\nPrevious work experience related to warehousing, distribution center, logistics, freight forwarding and airport operations is an advantage\nFair command of spoken English and Cantonese\nHands-on PC skills\nHardworking, attentive to details, patient with customer service sense\nWilling to work on 24-hour shift duties\nPersonal Information Collection Statement pertaining to Recruitment\nDHL Express (Hong Kong) Limited / DHL Aviation (Hong Kong) Limited (\u201cDHL\u201d) is committed to protecting and respecting your privacy in accordance with the Personal Data (Privacy) Ordinance of Hong Kong (the \u201cOrdinance\u201d) and DHL\u2019s Personal Data Protection Policy (the \u201cPolicy\u201d) at\u00a0https://www.dhl.com/hk-en/home/footer/local-privacy-notice.html\nBy proceeding to respond to this recruitment advertisement, you consent that we may use, retain, process, transfer or otherwise handle the personal data that we collect from you for recruitment,\u00a0 application processing, assessment and communication purposes (including any other purposes directly related thereto) in accordance with the Policy.\nAll personal data of unsuccessful applicants will be retained for future recruitment purposes for a period of not more than two (2) years after which such data will be destroyed.\nYou have the right at any time to make a data access or correction request concerning your personal data held by us. In addition, you may request us to delete your personal data that is no longer required for the relevant purposes which you have given consent. Should you wish to exercise such rights or have any question in relation to your personal data or the Policy, please contact our Human Resources Division in writing.", "employment_types": ["Full Time"], "selling_points": ["Print shipment manifest for shipment lodgement", "Secondary education", "2 years clerical or operations support experience"], "locations": ["Not Specified"], "categories": ["Admin & HR", "Clerical / Admin Staff", "Transportation & Logistics", "Others", "Shipping"], "post_time": "2022-01-18T03:21:47Z", "salary": {"currency": null, "max": null, "min": null, "period": null, "term": null}, "salary_visible": false, "title_keywords": ["operations"], "responsibilities": ["liaise", "reporting", "warehousing", "data", "operations", "coordinate", "communication", "maintain", "logistics", "customer service", "recruitment", "contact", "documentation", "personal data"], "requirements": {"degrees": ["secondary education"], "majors": [], "languages": ["cantonese", "english"], "language_level": [], "hard_skills": ["no", "processing", "html", "make", "documentation", "pc skills", "documentations"], "soft_skills": ["attentive to details", "communication", "committed", "hands-on", "customer service", "patient", "hardworking"], "languages_combined": [{"language": "cantonese", "language_level": []}, {"language": "english", "language_level": []}]}, "experience_required": {"duration": ["at least 2 years"], "field": ["related", "logistics", "clerical", "education"]}}, {"job_id": "100003009048041", "location_code": "hk", "company": "Abdoolally Ebrahim Housewares Limited", "job_title": "Shipping Executive", "description": "Responsibilities:\n\n\n\nMonitor and handle daily shipment operation\nHandle full set of I/E documents, shipping procedures and custom declaration\nCoordinate with different parties (i.e. suppliers, customers, and colleagues) for on time shipments and necessary documentations\u00a0\u00a0\u00a0\u00a0\u00a0\n\u00a0Liaise with shipping forwarders to request & compare rates\nAnticipate delays & arrange necessary timely action to ensure on time shipment.\nPrepare various reports for management use, if any.\nAssist in merchandising duties, when required.\nSales Contract and Purchase Contract Preparation\n\n\u00a0Requirements:\n\n\nDiploma or above in logistics, shipping or related discipline\nAt least 3 years solid experience in logistic & shipping in trading environment.\nKnowledge of L/C\nMerchandising experience is definitely an advantage.\nFamiliar with logistic & customs requirements.\nProficiency in PC skills,\u00a0such as MS\u00a0Office, Excel, ERP and\u00a0Chinese word\u00a0processing\nProactive, independent, detail-minded and responsible\nGood communication and interpersonal skills\nGood command of spoken and written English, Cantonese and Mandarin", "employment_types": ["Full Time", "Permanent"], "selling_points": ["5 days work", "Double Pay", "Medical Benefits"], "locations": ["Kwun Tong"], "categories": ["Transportation & Logistics", "Shipping"], "post_time": "2022-01-14T04:36:05Z", "salary": {"currency": null, "max": null, "min": null, "period": "monthly", "term": null}, "salary_visible": false, "title_keywords": ["shipping", "executive"], "responsibilities": ["management", "shipping", "custom declaration", "coordinate with", "monitor", "procedures", "merchandising", "purchase", "reports", "liaise with"], "requirements": {"degrees": ["diploma or above"], "majors": [], "languages": ["cantonese", "english", "chinese", "mandarin"], "language_level": ["proficiency", "good command"], "hard_skills": ["excel", "chinese word processing", "erp", "c", "pc skills", "ms office"], "soft_skills": ["detail-minded", "independent", "responsible", "communication and interpersonal skills", "proactive"], "languages_combined": [{"language": "cantonese", "language_level": ["good command"]}, {"language": "english", "language_level": ["good command"]}, {"language": "chinese", "language_level": ["proficiency"]}, {"language": "mandarin", "language_level": ["good command"]}]}, "experience_required": {"duration": ["at least 3 years"], "field": ["merchandising", "trading"]}}, {"job_id": "100003009055146", "location_code": "hk", "company": "Ocean Network Express (East Asia) Limited", "job_title": "Manager - CRM Training (East Asia Region)", "description": "Responsibilities:\n\nSupport and deliver the Training Delivery Guide in Customer Relationship Management (CRM) Training;\nCollaborate with Regional, Country Sales, and Customer Service teams to determine and evaluate their training requirements and effectiveness, as well as generate and distribute reports;\nParticipate in the User Acceptance Testing (UAT) for Customer Relationship Management (CRM) and assist in guiding designated users among the region.\n\n\u00a0Requirements:\n\nBachelor Degree in any discipline, major in shipping, logistics or business management is highly preferred;\nMinimum 10 years of relevant experience;\nStrong interpersonal skills such as communication and listening;\nTechnical skills including a competent understanding of customer service department workflows;\nExperience in training or teaching is a must;\nWillingness to learn and keep improving the knowledge;\nKnowledge in CRM system (preferably Salesforce) is an advantage but not a mandatory requirement;\nFamiliar with Microsoft Office or Google suite, e.g. Word, Excel, PowerPoint, G-sheets, G-Docs, G-Slides;\nGood command in spoken and written English and Chinese, Mandarin is a plus.", "employment_types": ["Full Time", "Permanent"], "selling_points": ["Responsible for CRM Training", "Regional exposure\u00a0in East Asia", "Agility workplace, collaborative & fun activities"], "locations": ["Kwun Tong"], "categories": ["Admin & HR", "Training & Development", "Transportation & Logistics", "Shipping", "Sales, CS & Business Devpt", "Others"], "post_time": "2022-01-18T01:27:39Z", "salary": {"currency": null, "max": null, "min": null, "period": "monthly", "term": null}, "salary_visible": false, "title_keywords": ["manager"], "responsibilities": ["collaborate with", "management", "uat", "teams", "testing", "evaluate", "customer service", "reports"], "requirements": {"degrees": ["degree", "bachelor"], "majors": ["business"], "languages": ["english", "chinese", "mandarin"], "language_level": ["good command"], "hard_skills": ["business management", "excel", "plus", "salesforce", "microsoft office", "word", "powerpoint"], "soft_skills": ["competent", "communication", "customer service", "interpersonal skills", "technical skills"], "languages_combined": [{"language": "english", "language_level": ["good command"]}, {"language": "chinese", "language_level": ["good command"]}, {"language": "mandarin", "language_level": ["good command"]}]}, "experience_required": {"duration": ["minimum 10 years"], "field": ["teaching", "relevant experience", "training"]}}, {"job_id": "100003009045306", "location_code": "hk", "company": "Medikonia Limited", "job_title": "Shipping & Operations Officer", "description": "Follow up shipment booking and handle all logistics activities with internal and external parties to ensure smooth delivery.\nPurchasing orders and monitoring the inventory.\nInventory management to determine when new purchases should be scheduled.\nAble to handle full set of shipping documents, Tradelink system, custom declaration and all related issues.\nOperate storeroom activities of dispatching, receiving, sorting, and distributing deliveries.\nSupport sales team to deliver the goods to local customers.\nPrepare sales reports & analysis for inventory management purposes.\nVarious office administrative duties such as local and international courier to support office daily operations.\nOther ad-hoc job duties if necessary.\nJob Requirements\n\nDiploma graduated or above.\n2-3 years of experience in shipping and logistic is preferred or familiar with international trade.\nGood command of both written and spoken English and Chinese.\nAdvanced computer skills including MS Word and excel.\nAble to work independently with a high sense of responsibility, reliable, detail-minded and team player.\n\u00a0", "employment_types": ["Full Time", "Permanent"], "selling_points": [], "locations": ["Mong Kok"], "categories": ["Admin & HR", "Clerical / Admin Staff", "Sciences, Lab, R&D", "Life Science", "Transportation & Logistics", "Shipping"], "post_time": "2022-01-13T18:55:07Z", "salary": {"currency": null, "max": null, "min": null, "period": "monthly", "term": null}, "salary_visible": false, "title_keywords": ["operations officer", "shipping"], "responsibilities": ["ad-hoc"], "requirements": {"degrees": ["diploma graduated"], "majors": [], "languages": ["english", "chinese"], "language_level": ["good command"], "hard_skills": ["excel", "computer skills", "ms word"], "soft_skills": ["detail-minded", "work independently", "advanced", "high sense of responsibility", "team player", "reliable"], "languages_combined": [{"language": "english", "language_level": ["good command"]}, {"language": "chinese", "language_level": ["good command"]}]}, "experience_required": {"duration": ["2-3 years"], "field": []}}, {"job_id": "100003009043362", "location_code": "hk", "company": "Narmah (HK) Limited", "job_title": "Senior Shipping Clerk", "description": "Requirements:-\n\n\nHKCEE/HKDSE or above / Higher Diploma\n3 years plus relevant working experience\u00a0in shipping department of a trading company;\nLiaise with factories, shipping companies and Internal teams to arrange shipment and documents;\nResponsible for handling import/export documents, shipment and logistics arrangement, Letter of Credit, CTN Application, COC, Inspections, etc;\nExperience in managing independently documents for Nigeria is an Advantage;\nGood Command of both English and Mandarin is a MUST;\nProficiency in PC application and MS office;\nGood communication and interpersonal skills;\nImmediate available is preferred.\n\nCompany offers attractive remuneration package including 5-day work, 12 days AL + Banking holidays, Medical benefit,\u00a0Double pay\u00a0to the right candidate.\u00a0\u00a0Interested parties please email us your full resume in MS Word or PDF format including the date of availability, current/last & expected salary.\n\n\nAll information received will be kept in strict confidence and only for employment related purpose.", "employment_types": ["Full Time", "Permanent"], "selling_points": [], "locations": ["Sheung Wan"], "categories": ["Transportation & Logistics", "Freight Forwarding", "Shipping", "Supply Chain"], "post_time": "2022-01-12T11:02:57Z", "salary": {"currency": null, "max": null, "min": null, "period": "monthly", "term": null}, "salary_visible": false, "title_keywords": ["shipping clerk"], "responsibilities": ["shipping", "logistics arrangement", "teams", "communication", "banking", "liaise with"], "requirements": {"degrees": ["diploma", "hkdse"], "majors": [], "languages": ["english", "mandarin"], "language_level": ["good command"], "hard_skills": ["pc", "plus", "ms office"], "soft_skills": ["independently", "communication and interpersonal skills", "responsible"], "languages_combined": [{"language": "english", "language_level": ["good command"]}, {"language": "mandarin", "language_level": ["good command"]}]}, "experience_required": {"duration": ["3 years"], "field": ["trading", "relevant working experience"]}}, {"job_id": "100003009051273", "location_code": "hk", "company": "ZIM Integrated Shipping Services Ltd", "job_title": "Capacity Management Officer (Shipping)", "description": "Key Responsibilities\n\nConsolidate, check and monitor countries forecast, booking and loading capacity\nCapacity planning by controlling country and vessel allocations / capacity\nFollow up closely with pricing team to optimize the utilization and communicate with countries/ transshipment hub / partners for cargo arrangement\n\nWho we are looking for\n\nDiploma or above\nGood command of both spoken and written English\nA good team player with excellent interpersonal skills\nProficient in Microsoft Excel\n\nWe offer\n\nExcellent opportunities for advancement with regional exposure\nCompetitive salary package\n5-Days Work\n15 - 17 days Annual Leave\nDouble Pay\nMedical & Dental Insurance\nLife Insurance\nBirthday Gifts\nMarriage Leave\nPaternity Leave\nWork from home arrangement\n\nInterested parties please share with us your latest resume showing current and expected remuneration package.", "employment_types": ["Full Time", "Permanent"], "selling_points": ["Familiar in Excel and Spread Sheet Operations", "New headcount due to business expansion", "Work from home arrangement"], "locations": ["Kwun Tong"], "categories": ["Transportation & Logistics", "Freight Forwarding", "Shipping", "Others", "Student / Fresh Graduate / No Experience"], "post_time": "2022-01-15T07:02:54Z", "salary": {"currency": null, "max": null, "min": null, "period": "monthly", "term": null}, "salary_visible": false, "title_keywords": ["officer", "shipping"], "responsibilities": ["communicate with", "monitor", "booking", "forecast", "planning"], "requirements": {"degrees": ["diploma or above"], "majors": [], "languages": ["english"], "language_level": ["good command"], "hard_skills": ["microsoft excel"], "soft_skills": ["good team player", "interpersonal skills"], "languages_combined": [{"language": "english", "language_level": ["good command"]}]}, "experience_required": {"duration": [], "field": []}}, {"job_id": "100003009054969", "location_code": "hk", "company": "SJS Products HK Ltd", "job_title": "Warehouse Keeper - Hong Kong", "description": "The Hong Kong Warehouse Keeper is responsible for ensuring proper receiving of product and documentation thereof.\u00a0 Ensures that all orders are properly prepared for shipment as required.\u00a0 Accountable for all transfers, paperwork and system functions.\u00a0 Responsible for maintaining the overall appearance and housekeeping of warehouse, and periodic maintenance of warehouse and office at the Hong Kong facility.\nYou must be motivated, organized, professional and timely.\u00a0 The hours for this position are generally 9:00 AM to 6:00 PM, Monday through Friday, but will be dependent on the department and customers\u2019 needs and ensuring that customer needs are fulfilled.Receive incoming material, process paperwork, inspection, disposition to stock/shipping\n\nNotify Loomis QC of incoming shipment for immediate receipt to SAP\nPull stock for orders\nPrint/prepare shippers for daily orders\nPackage orders for delivery\nComplete information required on shipping paperwork and place with the packaged order i.e. bill of lading, international invoices, shippers, security endorsements, etc.\nMeet \u201cOn-time\u201d delivery.\nBag and re-bag stock as needed.\nRecord all inventory movement on inventory cards, and logs, as necessary. (Shipments, receipts, samples, returns, transfers, reworks and MRB)\nComplete all receiving documentation with appropriate information i.e.: date received, qty. received, scale used, sample used, sample weight and initials.\nComplete any other documents necessary. i.e. Overage/Shortage, or rejection.\nAbility to repetitively lift, move and process packages weighing up to 19 kg.\n\n\u00a0JOB REQUIREMENTS\n\n\nThe hours for this position are generally 9:00 AM to 6:00 PM, Monday through Friday, but will be dependent on the department and customers\u2019 needs and ensuring that customer needs are fulfilled.\nBe motivated, organized, professional and timely.\nAbility to repetitively lift, move and process packages weighing up to 19 kg.\nClear telephone and email communication skills. Must be able to speak English clearly and be able to be understood clearly over the telephone and email. Be fluent in Cantonese.\nTyping skills and alpha/numeric data entry skills required.\nOne (1) year minimum warehouse experience.\nOne (1) year minimum of computer experience.\nCustomer Service or Sale Administration Officer experience preferred.", "employment_types": ["Full Time", "Contract"], "selling_points": ["5 days work", "Performance Bonus", "No Special Educational Requirement"], "locations": ["Kwun Tong"], "categories": ["Transportation & Logistics", "Inventory / Warehousing", "Shipping", "Sales, CS & Business Devpt", "Sales Administration"], "post_time": "2022-01-17T16:14:23Z", "salary": {"currency": null, "max": null, "min": null, "period": "monthly", "term": null}, "salary_visible": false, "title_keywords": ["warehouse keeper"], "responsibilities": ["shipping", "invoices", "maintenance", "maintaining", "housekeeping", "receipts", "inventory", "data entry", "inspection", "communication", "daily orders", "customer service", "documentation", "administration"], "requirements": {"degrees": [], "majors": [], "languages": ["cantonese", "english"], "language_level": ["fluent"], "hard_skills": ["documentation", "sap", "typing", "maintenance"], "soft_skills": ["organized", "communication skills", "responsible", "timely", "accountable", "clear", "motivated", "customer service"], "languages_combined": [{"language": "cantonese", "language_level": ["fluent"]}, {"language": "english", "language_level": []}]}, "experience_required": {"duration": [], "field": ["sale", "customer service", "administration"]}}, {"job_id": "100003009056817", "location_code": "hk", "company": "Marae Limited", "job_title": "Procurement Officer (Frozen Meat)", "description": "Job descriptions and responsibilities:\u00a0\n\nExplore reliable suppliers and organization partner, negotiate with vendors to secure advantageous terms\u00a0\nAnalyze market prices and trends in order to provide the up-to-date market information and seek for innovative solutions.\u00a0\nPerform risk management and mitigation for key purchases, supply contracts and agreements\u00a0\nFormulate effective contingency plan on the supply of core materials to guarantee production continuity, provide professional suggestions to management\u00a0 \u00a0 \u00a0 \u00a0\u00a0\nAchieve healthy stock turnover to minimize cost of carry-over stocks\u00a0\nRequirements:\u00a0\n\nDegree in Purchasing & Supply Chain Management or related disciplines\nMinimum 3 years working experience, preferable in fresh food / supermarket industry\nPassionate, efficient and flexible\nGood communication, analytical and negotiation skills\nProficient in MS Word, Excel and Chinese Word Processing\nExcellent in spoken and written in Cantonese & English\n\nWe offer:\n\n5-Day Work Week\nCompetitive Salary Package\n13 months' Guaranteed Salary\nPerformance Incentives\nGroup Medical Scheme\nBirthday Leave\nFree Lunch Provided\nEnergetic & Dynamic Culture\n\nWe offer an attractive remuneration package and good career opportunities to the right candidate.\u00a0\n\nInterested parties, please click \u201cApply Now\u201d\u00a0\n\nAll personal data collected will be used for recruitment purpose only.", "employment_types": ["Full Time", "Permanent"], "selling_points": ["Experience in fresh food / supermarket industry", "organized, detail-minded, initiative & innovative", "Discover and develop reliable suppliers"], "locations": ["Lai Chi Kok"], "categories": ["Transportation & Logistics", "Shipping", "Merchandising & Purchasing", "Procurement / Purchasing / Sourcing"], "post_time": "2022-01-18T06:27:55Z", "salary": {"currency": null, "max": null, "min": null, "period": "monthly", "term": null}, "salary_visible": false, "title_keywords": ["procurement officer"], "responsibilities": ["management", "market information", "cost", "contracts", "plan"], "requirements": {"degrees": ["degree"], "majors": ["related disciplines"], "languages": ["cantonese", "english", "chinese"], "language_level": ["excellent", "proficient"], "hard_skills": ["excel", "chinese word processing", "ms word"], "soft_skills": ["passionate", "flexible", "efficient", "communication", "negotiation skills"], "languages_combined": [{"language": "cantonese", "language_level": ["excellent"]}, {"language": "english", "language_level": ["excellent"]}, {"language": "chinese", "language_level": ["proficient"]}]}, "experience_required": {"duration": ["minimum 3 years"], "field": ["food"]}}, {"job_id": "100003009052474", "location_code": "hk", "company": "Foodgears Industrial International Limited", "job_title": "Import & Export Officer", "description": "Job Duties:\n\nHandle full set of import & export shipping documents (e.g. L/C, D/P, D/A, T/T)\nCommunicate and liaise with forwarder / logistic company / warehouse\nHandle order processing and shipment schedule\nApply import permit from Government (FEHD) / Trade and Industry Dept.\nData entry by using the company system\n\n\u00a0Requirements:\n\nDiploma or above with 3 years relevant experience in supply chain / logistics / shipping field\nGood command of Cantonese, English, and Mandarin\nProficiency in MS Word, Excel & Chinese Word Processing\nContributes to the development of processes & procedures\nStrong communication & coordinating capability\nGood knowledge of L/C and banking document, Tradelink system\n\n\n\nRemuneration:\n\n5 working days\nBank holidays\nDouble pay\nDental & medical coverage\n\n\n\nWe offer attractive remuneration package to the right candidate.\u00a0 Interested parties please send full resume with present & expected salary and available date by clicking \"Apply Now\"\n\n\n\nAll personal data collected will be used for recruitment purpose only.", "employment_types": ["Full Time", "Permanent"], "selling_points": [], "locations": ["Wong Tai Sin Area"], "categories": ["Transportation & Logistics", "Freight Forwarding", "Shipping", "Supply Chain"], "post_time": "2022-01-17T03:07:20Z", "salary": {"currency": null, "max": null, "min": null, "period": "monthly", "term": null}, "salary_visible": false, "title_keywords": ["officer"], "responsibilities": ["data entry", "import & export shipping documents", "schedule", "order processing", "liaise with"], "requirements": {"degrees": ["diploma or above"], "majors": [], "languages": ["cantonese", "english", "chinese", "mandarin"], "language_level": ["proficiency", "good command"], "hard_skills": ["excel", "c", "chinese word processing", "ms word"], "soft_skills": ["communication"], "languages_combined": [{"language": "cantonese", "language_level": ["good command"]}, {"language": "english", "language_level": ["good command"]}, {"language": "chinese", "language_level": ["proficiency"]}, {"language": "mandarin", "language_level": ["good command"]}]}, "experience_required": {"duration": ["3 years"], "field": ["supply chain", "logistics", "relevant experience"]}}, {"job_id": "100003009052657", "location_code": "hk", "company": "NET-A-PORTER", "job_title": "Logistic Assistant/ Advisor (Online Fashion Retailer, Fresh Graduates are welcome)", "description": "NET-A-PORTER are now seeking a talented Logistic Assistant/ Advisor join the team. Some of the essentials for you to know are:\n\nLocation:\u00a0Tsing Yi Office\n\nReporting into:\u00a0Trade & Transport Manager\n\nHere is a breakdown of what you\u2019ll be doing:\n\n\n\nInbound :\u00a0\n\nChecks all applicable documentations are in place and ensuring Government/Customs compliance is adhered to for all markets prior to ship\nProvides Shipping Instructions to the 3PL Carriers/Courier & prepare necessary shipping docs (if need)\nLiaises with vendors / internal business partners to resolve problem that could delay the release or movement of shipments\nFollow up shipment status and ensure the goods receiving is completed in WMS\u00a0\nOutbound :\n\nCustomer services support on all B2B courier shipping arrangement & inquiries\nGeneral Admin :\nObtain 3 PL quotation with comparison\nEnsure system data & daily operation log files are accurate and updated in timely manner\n3PL Billing validation & payment application to Finance\nAssist management for any ad hoc reporting and analysis tasks\n\n\u00a0The type of person we are looking for:\n\nPositive Thinking, Passionate in work, Paying Attention to Details, also a Team-Player\nExcellent communication and computer skills, especially Excel in advance level\nAn understanding of I/E shipping documentations and procedures\nFamiliar the Tradelink, DHL / UPS booking system\nSound working knowledge of International Customs laws/Regulations and Trade Compliance policies, is a definite plus\nCandidate with 1-2 experience is a plus, but fresh graduate will be considered\nBesides a competitive salary, we can offer you:\n\nPerformance bonus schemes\u00a0dependent\u00a0on the type of role you are in\nOur famous staff discount along with exclusive staff sales\nMPF plus voluntary contribution from the company\nMulti-purpose insurance\nRental Reimbursement Program\nFlexible working\nA chance to be part of a fun and caring team that support each other", "employment_types": ["Full Time", "Permanent"], "selling_points": ["Fresh graduates are welcome to apply", "Progressive career path; Good learning opportunity", "Advanced in MS Excel is ideal"], "locations": ["Tsing Yi"], "categories": ["Transportation & Logistics", "Freight Forwarding", "Shipping", "Supply Chain"], "post_time": "2022-01-17T03:39:23Z", "salary": {"currency": null, "max": null, "min": null, "period": "monthly", "term": null}, "salary_visible": false, "title_keywords": ["advisor", "assistant"], "responsibilities": ["regulations", "shipping", "quotation", "communication", "payment", "wms", "ad hoc", "tradelink", "compliance", "customer services", "reporting", "management", "mpf", "procedures", "system data", "booking", "policies", "analysis", "daily operation", "insurance"], "requirements": {"degrees": ["fresh graduate"], "majors": [], "languages": [], "language_level": [], "hard_skills": ["excel", "plus", "fun", "analysis", "computer skills", "pl", "documentations"], "soft_skills": ["passionate", "flexible", "team-player", "timely", "positive thinking", "communication", "attention to details", "accurate"], "languages_combined": []}, "experience_required": {"duration": [], "field": []}}, {"job_id": "100003009045455", "location_code": "hk", "company": "DCH Logistics Co Ltd", "job_title": "I/E/ Shipping/ Receiving Clerk", "description": "Responsibilities:General shipping paperwork, handling shipping, air transportation, transit vehicle documents, seamless customs clearance, liaising with customers and internal transportation colleagues, following up domestic and overseas customer orders, responding to customer progress, delivery dates, shipping schedules, etc.\nRequirements :\n\nSecondary 5;\n2 Year(s) Experience Required;\nFluent Cantonese\u00a0;Fair Putonghua ; Fair English ;\nAble to read & write Chinese ;Able to read & write English ;\nMS Word; MS Outlook; MS Excel; Basic Computer Operation Knowledge\nEmployment Terms:\u00a0\u00a0Annual Leave 12 days, Overtime Allowance, Performance Award, Medical Benefits and Bank Holiday, Mon to Fri: 8:45AM-5:15PM and Sat: 8:45AM-12:45PM, 5 - 5.5 working days per week\nApplication Information:Interested candidates, please click APPLY NOW to apply job.\n", "employment_types": ["Full Time"], "selling_points": [], "locations": ["Yuen Long"], "categories": ["Transportation & Logistics", "Others", "Shipping", "Others", "Others"], "post_time": "2022-01-13T07:53:24Z", "salary": {"currency": null, "max": null, "min": null, "period": "monthly", "term": null}, "salary_visible": false, "title_keywords": ["shipping", "clerk"], "responsibilities": ["schedules", "sat", "shipping", "liaising with"], "requirements": {"degrees": [], "majors": [], "languages": ["cantonese", "putonghua", "english", "chinese"], "language_level": ["fluent"], "hard_skills": ["basic", "ms excel", "outlook", "computer operation knowledge", "ms word"], "soft_skills": [], "languages_combined": [{"language": "cantonese", "language_level": ["fluent"]}, {"language": "putonghua", "language_level": []}, {"language": "english", "language_level": []}, {"language": "chinese", "language_level": []}]}, "experience_required": {"duration": [], "field": []}}, {"job_id": "100003009056156", "location_code": "hk", "company": "Cathay Pacific Catering Services (H.K.) Limited", "job_title": "Assistant Logistics Manager (Ramp Services)", "description": "Responsibilities\n\nMaintains a high standard of loading & unloading procedures and ensures an on-time performance of all flights\nEnsures efficient aircraft handling and smoothen daily operations\nMonitor and enhances subordinates\u2019 working performance\nEnsures the Company\u2019s regulations are followed strictly\nReviews the existing procedures/resources and plans for a better development\nMaintains a harmonic working atmosphere and executes fair-minded measures at all times\nMaintains a good relationship with the customers and provides satisfactory services to minimize complaints\nPerforms ad hoc duties as directed by Loading Services Manager\nRequirements\n\nTertiary Education in Operations Management or related disciplines\nMinimum 5 years of relevant working experience in a supervisory level\nHolder of a valid driving license (No. 1 and 2) is an advantage\nGood communication skills, leadership and interpersonal skills\nAble to work independently under pressure and follow tight schedules\nProficient in PC applications, including MS Word, PowerPoint and Excel\nGood command of English and Chinese, both written and spoken\nShift duty is required\nWe offer a competitive remuneration package and a full range of benefits. Interested parties please send your resume with your current and expected salary to Head of People,11 Catering Road East, Hong Kong International Airport, Lantau, Hong Kong or by clicking the \"Apply Now\" button\u00a0on or before 10 February 2022.\nPersonal data collected will be treated in the strictest confidence and only be used for recruitment-related purposes. Applicants who do not receive notification for an interview within six weeks may consider their application unsuccessful.", "employment_types": ["Full Time", "Permanent"], "selling_points": ["Logistics Management", "Operations Services Enhancement", "Career advancement opportunities"], "locations": ["Airport Area"], "categories": ["Transportation & Logistics", "Aviation Services", "Shipping", "Manufacturing", "Manufacturing Management"], "post_time": "2022-01-18T03:26:29Z", "salary": {"currency": null, "max": null, "min": null, "period": "monthly", "term": null}, "salary_visible": false, "title_keywords": ["logistics manager", "assistant"], "responsibilities": ["regulations", "ad hoc duties", "procedures", "monitor", "good relationship", "daily operations", "plans"], "requirements": {"degrees": [], "majors": [], "languages": ["english", "chinese"], "language_level": ["good command"], "hard_skills": ["excel", "no", "powerpoint", "pc applications", "ms word"], "soft_skills": ["communication skills", "work independently", "under pressure", "interpersonal skills", "leadership"], "languages_combined": [{"language": "english", "language_level": ["good command"]}, {"language": "chinese", "language_level": ["good command"]}]}, "experience_required": {"duration": ["minimum 5 years"], "field": ["supervisory level", "relevant working experience"]}}, {"job_id": "100003009050376", "location_code": "hk", "company": "Find Asia Limited", "job_title": "Shipping Clerk (5 days work)", "description": "Our client, an electronics manufacturing and trading company ,is now looking for a candidate with the following details:\n\nDuties:\n\nHandle Shipping documents support, contact with suppliers, factories and liaise with the forwarders for delivery arrangement\u00a0\nPrepare invoice, packing list, delivery documents and reports\nHandle goods delivery, support the team manager to solve the delivery issue\n\n\u00a0Requirement\u00a0\n\nExperience as Sales Admin/ Shipping/ Procurement/ Purchasing\u00a0in trading company, preferable in electronics industry\nGood Excel skills\u00a0\nIndependent and good team player\ndetail-minded and self-motivated", "employment_types": ["Full Time", "Permanent"], "selling_points": ["Shipping, I/E, delivery", "electronics components", "5 days, Double Pay, Bonus"], "locations": ["Tsim Sha Tsui"], "categories": ["Transportation & Logistics", "Shipping", "Supply Chain", "Manufacturing", "Production Planning / Control"], "post_time": "2022-01-15T19:11:42Z", "salary": {"currency": null, "max": null, "min": null, "period": "monthly", "term": null}, "salary_visible": false, "title_keywords": ["shipping clerk"], "responsibilities": ["shipping documents", "invoice", "packing list", "reports", "contact", "liaise with", "support the team"], "requirements": {"degrees": [], "majors": [], "languages": [], "language_level": [], "hard_skills": ["excel"], "soft_skills": ["detail-minded", "good team player", "independent", "self-motivated"], "languages_combined": []}, "experience_required": {"duration": [], "field": ["purchasing", "admin", "trading", "procurement"]}}, {"job_id": "100003009056290", "location_code": "hk", "company": "ConnectedGroup Limited", "job_title": "Logistics Specialist (US Sourcing office)", "description": "Our client is an US leading company for apparel who is now looking for a Logistics Specialist to join their growing team in HK.\n\nResponsibilities:\n\nResponsible for shipment scheduling and container consolidation\nCoordinates with factories, merchandisers and logistics vendor for order delivery\nProvides solutions in logistics issue and exception\nMonitor service provider's performance and KPI to ensure service standard and cost efficiency\nProvide customer service to internal and external stakeholder, act as an information centre for shipping status\nHandle logistics inquiries regarding shipment issues, carrier services and procedures\nProvide solution with internal teams with any customs related delays\nIdentify cost saving opportunities to minimize freight\nImplement process improvement and review result\nPerform ad hoc data collection and basic analysis as needed\n\nRequirements:\n\nBachelor degree preferred\nAt least 4 years of experience in logistics operation, preferrably for EU and US market\nProficient computer skills MS Office, experience in Excel Vlookup and Pivot Table is a big plus.\nStrong interpersonal and communication skill\nStrong analytical thinking and problem solving skills\nAble to provide solution independently\nFluent in spoken and written Chinese (Mandarin / Cantonese) and English", "employment_types": ["Full Time", "Permanent"], "selling_points": ["US market focused", "Forwarder/ 3PL for EU & US market welcomed", "Double pay + Bonus; 5 day; Medical"], "locations": ["Not Specified"], "categories": ["Transportation & Logistics", "Others", "Shipping", "Supply Chain"], "post_time": "2022-01-18T03:51:22Z", "salary": {"currency": null, "max": null, "min": null, "period": "monthly", "term": null}, "salary_visible": false, "title_keywords": ["logistics specialist"], "responsibilities": ["provide customer service", "cost", "shipping", "ad hoc", "service standard", "analysis", "review", "monitor", "procedures", "teams", "scheduling", "logistics", "data collection"], "requirements": {"degrees": ["degree", "bachelor"], "majors": [], "languages": ["cantonese", "english", "chinese", "mandarin"], "language_level": ["fluent"], "hard_skills": ["excel", "plus", "pivot table", "problem solving skills", "computer skills", "vlookup", "ms office"], "soft_skills": ["problem solving skills", "communication skill", "interpersonal", "independently"], "languages_combined": [{"language": "cantonese", "language_level": ["fluent"]}, {"language": "english", "language_level": ["fluent"]}, {"language": "chinese", "language_level": ["fluent"]}, {"language": "mandarin", "language_level": ["fluent"]}]}, "experience_required": {"duration": ["at least 4 years"], "field": ["operation", "logistics"]}}, {"job_id": "100003009046917", "location_code": "hk", "company": "Hung Hing Printing Group Ltd", "job_title": "Assistant Shipping Manager", "description": "As the Assistant Shipping Manager, you are responsible for\nLead 3 Hong Kong and China logistics teams for all inbound and outbound logistics (coordination of overseas supplier, freight forwarder and inward local logistic company, warehouse and customers).\nDesign and develop effective & efficient SOPs.\nTimely settlement and report of any troubles, unexpected issues and irregularities.\nLiaise with Freight Forwarders for best rate/terms.\nEnsure the S&OP process reflects the market needs & deadlines are being met as per agreed schedules.\nOther ad-hoc duties assigned.\nSkills & experiences required.\nTo succeed in this position, you need \u2013\nBachelor/Diploma or above in Supply Chain/Logistics Management or related disciplines.\nMinimum 8 years of related Shipping/Logistics experience (supervisory level), preferably in Listed Company or printing field.\nSelf-motivated, positive and meticulous; able to perform independently & proactively.\nGood team work with sound negotiation and problem-solving skills.\nProficient in MS Office & ERP system.\nGood command of spoken and written English, Cantonese and Mandarin.\nExperience in digital transformation is a plus.z\nInterested individuals can apply now for more information, only relevant candidates will be contacted.", "employment_types": ["Full Time", "Permanent"], "selling_points": ["Design and develop effective & efficient SOPs.", "Liaise with Freight Forwarders for best rate/terms", "Experience in digital transformation is a plus."], "locations": ["Tai Po Area"], "categories": ["Transportation & Logistics", "Freight Forwarding", "Shipping", "Supply Chain"], "post_time": "2022-01-14T05:56:27Z", "salary": {"currency": null, "max": null, "min": null, "period": "monthly", "term": null}, "salary_visible": false, "title_keywords": ["shipping", "manager", "assistant"], "responsibilities": ["management", "shipping", "irregularities", "ad-hoc duties", "schedules", "teams", "design and develop", "timely settlement", "logistics", "coordination", "sops", "liaise with", "report of any troubles", "unexpected issues", "all inbound and outbound logistics"], "requirements": {"degrees": ["bachelor", "diploma or above"], "majors": ["related disciplines"], "languages": ["cantonese", "english", "mandarin"], "language_level": ["good command"], "hard_skills": ["plus", "inbound and outbound logistics", "erp system", "problem-solving skills", "ms office"], "soft_skills": ["efficient", "meticulous", "self-motivated", "good team work", "responsible", "problem-solving skills", "timely", "coordination", "ad-hoc duties", "sound negotiation", "perform independently & proactively", "positive"], "languages_combined": [{"language": "cantonese", "language_level": ["good command"]}, {"language": "english", "language_level": ["good command"]}, {"language": "mandarin", "language_level": ["good command"]}]}, "experience_required": {"duration": ["minimum 8 years"], "field": ["related", "supervisory level", "logistics", "digital"]}}, {"job_id": "100003009052563", "location_code": "hk", "company": "Centrix Professionals - Recruitment Agency Division", "job_title": "Logistics Officer / Shipping Officer / Operations Officer (5 Days) 2 Post URGENT", "description": "Our client is a sizable company with attractive benefits is urgently looking for the following positions :\n\nPosition : Logistics Officer / Shipping Officer / Operation Officer (2 Post)\n\nSalary : Negotiable\u00a0\n\nRequirements :\u00a0\n\nBenefits : Medical, Dental, Guarantee Double Pay, Yearly Discretionary Bonus, Annual Leave, 5 Days\n\nRequirements:\n\nDegree holder is a must, major in International Shipping, Logistics Engineering Management, Supply Chain Management or related discipline\nAt least 1-3 yrs relevant experience in Shipping Companies is preferable\u00a0\nGained experience in Demurrage will consider Operation Officer (Demurrage)\nProficiency in English, Cantonese & Mandarin (most important)\nProficient in Microsoft Office (Ms Word, Excel & Chinese Word Processing\nStable, Reliable, Independent, Team Work, Detail-minded and able to work under pressure\nFresh Graduate with related major will consider as Assistant Grade\u00a0\nImmediate Available is highly preferable\n\nResponsibilities for the position of Operation Officer / Assistant\u00a0\n\n\nHandle full set of shipping documents\u00a0\n\nCoordinate with supplier, buyers & head office to arrange loading schedules\nFollow up charter party & handle commercial claims\u00a0\n\nResponsibilities for the position of Operation Officer - Demurrage\u00a0\n\nPrepare demurrage computation for timely submission\nFollow up receivable and collection to counter parties proactively\nNegotiable and settle demurrage claims according to trading contracts and charter parties\nPrepare demurrage claim invoices and check invoices for settlement\nReview of shipping and trading contracts related to lay time calculation and demurrage\nHandle and manage full set of demurrage documents\nKeep outstanding claims record update\nUndertake Department Head relevant assignment whenever required\u00a0\nAttractive salary and fringe benefits will be offered to the right candidates.\n\n\nInterested parties, please send full resume in\u00a0MS WORD FORMAT, stating expected salary by clicking \"Apply Now\"\n\nFor more information, please visit : www.centrix.com.hk\n\n\n(Personal data collected will be used for recruitment purpose only)\u00a0\u00a0", "employment_types": ["Full Time", "Permanent"], "selling_points": ["Degree Int'l shpg Supply Chain 2 post TOP URGENT", "1-3 yrs rel exp in Shpg Co / Demurrage Stable", "Flu Eng & Mandarin Stable Reliable Independent"], "locations": ["Not Specified"], "categories": ["Transportation & Logistics", "Others", "Shipping", "Supply Chain"], "post_time": "2022-01-17T03:25:35Z", "salary": {"currency": null, "max": null, "min": null, "period": "monthly", "term": null}, "salary_visible": false, "title_keywords": ["logistics officer", "operations officer", "shipping officer"], "responsibilities": [], "requirements": {"degrees": [], "majors": [], "languages": [], "language_level": [], "hard_skills": [], "soft_skills": [], "languages_combined": []}, "experience_required": {"duration": [], "field": []}}, {"job_id": "100003009052702", "location_code": "hk", "company": "Headsearch21 Consultancy Ltd", "job_title": "Logistic CS Supervisor (MNC)", "description": "To cope with the expansion of the Company, our client is now looking for high caliber candidate to join the Customer Services Team in Hong Kong:\n\nResponsibilities:\n\nWork closely with overseas agents, carriers, co-loaders, customers, suppliers and warehouse team\nResponsible for arranging inbound & outbound shipment for customers\nAnswer customers' enquiries and handle complaints\nFollow up shipment and achieve on-time delivery\nMaintain up-to-date record\nHandle pre-alert and general correspondence\n\nRequirements:\n\nAt least 4 years CS experience in\u00a0Logistic Co. / Freight-Forwarder / 3PL\nForm 5 or above\nGood knowledge of general procedures of I/E documentation and custom declaration\nProficiency in MS Office or SAP / WMS system\nGood command\u00a0of English and Mandarin\nCandidate with less experience will also be considered as \"Logistic CS Officer\"\n\nInterested parties, please click the \"Apply Now\" or send\u00a0 your updated resume with\u00a0 Current\u00a0and\u00a0Expected salary\u00a0in MS word format to cv @headsearch21.com\u00a0\n\nFor more information please contact Ms. Leung at 3188 3072.\n\nRef #: SD01005\n\nAll information collected will be treated in strict confidence and be used for recruitment purpose only\n\nCompany Web-Site:\u00a0www.headsearch21.com", "employment_types": ["Full Time", "Permanent"], "selling_points": ["4 years CS exp in Logistic Co. / Forwarder / 3PL", "SAP / WMS system (Prefer)", "Near MTR / Modern Office Design"], "locations": ["Not Specified"], "categories": ["Sales, CS & Business Devpt", "Customer Service - Supervisor / Officer", "Transportation & Logistics", "Freight Forwarding", "Shipping"], "post_time": "2022-01-17T03:45:08Z", "salary": {"currency": "HKD", "max": 19999, "min": 14000, "period": "monthly", "term": null}, "salary_visible": true, "title_keywords": ["supervisor"], "responsibilities": ["maintain", "inbound & outbound", "handle complaints"], "requirements": {"degrees": ["form 5 or above"], "majors": [], "languages": ["english", "mandarin"], "language_level": ["good command"], "hard_skills": ["documentation", "sap", "ms office"], "soft_skills": [], "languages_combined": [{"language": "english", "language_level": ["good command"]}, {"language": "mandarin", "language_level": ["good command"]}]}, "experience_required": {"duration": ["at least 4 years"], "field": ["cs"]}}, {"job_id": "100003009053051", "location_code": "hk", "company": "Relosmart Limited", "job_title": "SALES CONSULTANT / RELOCATION CONSULTANT", "description": "\u00a0Relosmart - Smart Relocations\n\nDo you keep on going in spite of opposition, obstacles, and discouragement?\n\nDo you have strong belief and full assurance in yourself?\n\nDo you have a strong desire to succeed and outperform your competition?\n\nAre you capable of delivering quality results to your team time and time again?\n\nWe are looking for intelligent, enthusiastic, caring individuals to fill the following vacancy:\n\nSALES CONSULTANT / RELOCATION CONSULTANT\n\nYou will be responsible for growing our sales, by nurturing existing clients, developing new relationships (cold calling), showing imagination in marketing, & initiative in promoting our businesses.\n\nRelevant work experience, & sales track record is a must\n\nOverseas graduate a plus\n\nExperience in Insurance, Banking, Airline industry or similar an advantage\n\nEnglish must be spoken to a mother tongue level. Other language skills an advantage.\n\nHigh base salary plus performance bonus.\n\nPlease email resumes, with a cover letter and salary expectation to enquiry at relosmart.asia\n\nFor further information please visit www.relosmart.asia", "employment_types": ["Full Time"], "selling_points": ["Are you the best sales person in the world?", "Confident and love interacting with people?", "Looking for a stepping stone into a career?"], "locations": ["Kwun Tong"], "categories": ["Sales, CS & Business Devpt", "Business Development", "Transportation & Logistics", "Shipping", "Tele-sales (Telemarketing)"], "post_time": "2022-01-17T16:20:58Z", "salary": {"currency": "HKD", "max": 24999, "min": 17000, "period": "monthly", "term": null}, "salary_visible": true, "title_keywords": ["sales consultant", "consultant"], "responsibilities": ["insurance", "quality", "developing", "banking"], "requirements": {"degrees": [], "majors": [], "languages": ["english"], "language_level": [], "hard_skills": ["plus", "airline"], "soft_skills": ["initiative", "capable", "responsible", "enthusiastic"], "languages_combined": [{"language": "english", "language_level": []}]}, "experience_required": {"duration": [], "field": ["insurance", "banking"]}}, {"job_id": "100003008952060", "location_code": "hk", "company": "LIP ON TRADING LIMITED", "job_title": "Officer, Shipping Department", "description": "Responsibilities:\n\n\nOrder process and upload PO into MIS system;\nFollow up and ensure shipping schedule to meet the department target;\nPrepare full set of order processing and shipment report;\nAssist buying team on order status and coordinate with the sales team on the delivery requests;\nCommunicate with the internal department for arranging order instruction/payment request form and coordinating with the overseas vendors for the shipment schedule;\nMonitor the order processing with the operation and ensure shipment on schedule;\nEstablish a good leadership with the internal team and well relationship with the internal department for the day to day operation and reporting\nReview\u00a0operation regularly and recommend\u00a0improvement\u00a0and action plan\nSupervise team members to support daily distribution/operations.\n\nRequirements:\u00a0\n\n\nBachelor Degree/\u00a0High Diploma in Logistics, Supply Chain Management, or a related disciplines;\nMinimum 3 years experience in order processing field;\nEnergetic, motivated, full of initiative, shipping and logistics'\u00a0knowledge is required and able to work independently and under pressure;\n\nGood command of both spoken and written English and Chinese;\nProficient in Microsoft Office (e.g. Excel is a must);\nGood command of interpersonal and communication skills;\nCandidate with more experience will be considered as Logistics Supervisor.\u00a0\nWe offer excellent career prospects, competitive salary and fringe benefits to the right candidate.\u00a0 Please apply in strict confidence by sending\u00a0personal resume together with salary expected and date available\n\nby email to:\u00a0h r d _ h n @ h a r v e y n i c h o l s . c o m . h k\nWe are an equal opportunity employer and welcome applications from all qualified candidates. Personal data provided by\u00a0 job applicants will be used strictly in accordance with our personal data policy and for recruitment purposes only. Candidates not notified within eight weeks may consider their application unsuccessful. All related information will be kept in our file for up to 24 months. A copy of our Personal Information Collection Statement will be provided upon request by contacting our Human Resources Division.", "employment_types": ["Full Time", "Permanent"], "selling_points": [], "locations": ["Tsuen Wan Area"], "categories": ["Transportation & Logistics", "Shipping"], "post_time": "2022-01-13T04:06:58Z", "salary": {"currency": "HKD", "max": 24999, "min": 17000, "period": "monthly", "term": null}, "salary_visible": true, "title_keywords": ["officer", "shipping"], "responsibilities": ["shipping schedule", "communicate with", "reporting", "operations", "review", "coordinate with", "monitor", "supervise team members", "payment", "sales team", "schedule", "order processing", "plan", "report"], "requirements": {"degrees": ["high diploma", "degree", "bachelor"], "majors": ["related disciplines"], "languages": ["english", "chinese"], "language_level": ["good command"], "hard_skills": ["excel", "order processing", "microsoft office"], "soft_skills": ["communication skills", "work independently", "under pressure", "interpersonal", "motivated", "energetic", "initiative"], "languages_combined": [{"language": "english", "language_level": ["good command"]}, {"language": "chinese", "language_level": ["good command"]}]}, "experience_required": {"duration": ["minimum 3 years"], "field": ["logistics", "order processing"]}}, {"job_id": "100003009048850", "location_code": "hk", "company": "Vanguard Logistics Services (HK) Ltd", "job_title": "Senior / Export Operations Clerk", "description": "Requirement:\n\na) A Hong Kong bachelor's degree, or equivalent;\n(b) Good command of written Chinese and English, met the language proficiency requirements of Level 3^ or above in Chinese Language and English Language in the Hong Kong Diploma of Secondary Education Examination (HKDSEE) or in the Hong Kong Certificate of Education Examination (HKCEE), or equivalent, and be fluent in English and Cantonese;\n(c) Have at least 5 years of post-qualification full-time work experience in executive and/or anagement duties. Working experience and/or knowledge in the operations of the shipping industry is highly preferred;\n(d) Good understanding of government measures against COVID-19 will be an asset;\n(e) Sound knowledge in common computer applications and operations including Microsoft Word, Excel Spreadsheet and mail merge as well as Chinese word processing (Candidates may be required to take computer proficiency test and/or written test);\n(f) Good organisation, communication and interpersonal skills, and ability to work independently and effectively under tight schedule; and\n(g) Candidates must be permanent residents of the Hong Kong Special Administrative Region at the time of appointment.\n^For appointment purpose, 'Grade C' and 'Grade E' in Chinese Language and English Language (Syllabus B) in the HKCEE before 2007 are accepted administratively as comparable to 'Level 3' and 'Level 2' respectively in Chinese Language and English Language in the 2007 HKCEE and henceforth.\n\n\nDuties:\n\nreport to Senior Manager (Port)\nTo handle workload incurred in the implementation of the latest anti-epidemic measures for the maritime industry, particularly COVID-19 testing for high-risk and high-exposure groups relating to the staff of designated container terminals and ship services sector.\n\nMainly deployed for duties relating to COVID-19 testing, duties include \u2013\n(a) collect and compile information and data;\n(b) maintain databases, registration lists and distribution lists, etc.;\n(c) liaise with service providers, industry stakeholders and government departments, etc. for returns and reports;\n(d) handle enquiries from the industry and the public through phone, email, etc.;\n(e) provide general administrative support; and\n(f) undertake any other duties as assigned.\n\n\nInterested parties, please send your resume in WORD format, stating HKCEE/HKALE/DSE result and availability and clicking APPLY NOW\n\n\u00a0(All personal data provided by applicants will be used for recruitment purpose only.)", "employment_types": ["Full Time", "Permanent"], "selling_points": ["Export Operations Clerk", "Shipping Clerk", "Forwarder"], "locations": ["Sheung Wan"], "categories": ["Transportation & Logistics", "Freight Forwarding", "Shipping", "Maritime - General"], "post_time": "2022-01-14T07:26:53Z", "salary": {"currency": null, "max": null, "min": null, "period": "monthly", "term": null}, "salary_visible": false, "title_keywords": ["operations clerk"], "responsibilities": ["any other duties", "data", "general administrative support", "implementation", "testing", "handle enquiries", "maintain", "reports", "databases", "liaise with", "report"], "requirements": {"degrees": ["secondary education", "certificate", "bachelor", "diploma", "degree"], "majors": [], "languages": ["cantonese", "english", "chinese"], "language_level": ["proficiency", "good command", "fluent"], "hard_skills": ["excel", "microsoft word", "chinese word processing", "c", "spreadsheet"], "soft_skills": ["work independently", "communication and interpersonal skills", "organisation"], "languages_combined": [{"language": "cantonese", "language_level": ["proficiency", "good command", "fluent"]}, {"language": "english", "language_level": ["proficiency", "good command", "fluent"]}, {"language": "chinese", "language_level": ["proficiency", "proficiency", "good command", "fluent"]}]}, "experience_required": {"duration": ["at least 5 years"], "field": ["post-qualification", "shipping industry"]}}, {"job_id": "100003009055827", "location_code": "hk", "company": "Page Personnel", "job_title": "Assistant Logistics Manager - EU Buying Office", "description": "~Degree / Diploma or above\n~3 years customer service service experience\n~Shipping / Forwarder / Service Company experience pref\n~Good English, Cantonese and Mandarin", "employment_types": ["Full Time", "Permanent"], "selling_points": ["Freight forwarder management", "FOB/FCA shipment", "Attractive package"], "locations": ["Kowloon Bay"], "categories": ["Transportation & Logistics", "Others", "Freight Forwarding", "Shipping"], "post_time": "2022-01-18T02:59:22Z", "salary": {"currency": null, "max": null, "min": null, "period": "monthly", "term": null}, "salary_visible": false, "title_keywords": ["logistics manager", "assistant"], "responsibilities": ["customer service"], "requirements": {"degrees": ["diploma or above"], "majors": [], "languages": ["cantonese", "english", "mandarin"], "language_level": [], "hard_skills": [], "soft_skills": ["customer service"], "languages_combined": [{"language": "cantonese", "language_level": []}, {"language": "english", "language_level": []}, {"language": "mandarin", "language_level": []}]}, "experience_required": {"duration": [], "field": ["customer service"]}}, {"job_id": "100003009055002", "location_code": "hk", "company": "Finder Technology Limited", "job_title": "Warehouse Clerk  (5 Days Work)", "description": "~ Diploma or above\n~ 3 years relevant experience (Toys)\u00a0\n~ English, Cantonese and Mandarin\u00a0\u00a0", "employment_types": ["Full Time", "Permanent"], "selling_points": [], "locations": ["Chai Wan"], "categories": ["Transportation & Logistics", "Inventory / Warehousing", "Shipping", "Supply Chain"], "post_time": "2022-01-17T16:22:55Z", "salary": {"currency": null, "max": null, "min": null, "period": "monthly", "term": null}, "salary_visible": false, "title_keywords": ["warehouse clerk"], "responsibilities": [], "requirements": {"degrees": ["diploma or above"], "majors": [], "languages": ["cantonese", "english", "mandarin"], "language_level": [], "hard_skills": [], "soft_skills": [], "languages_combined": [{"language": "cantonese", "language_level": []}, {"language": "english", "language_level": []}, {"language": "mandarin", "language_level": []}]}, "experience_required": {"duration": ["3 years"], "field": ["toys", "relevant experience"]}}, {"job_id": "100003009050173", "location_code": "hk", "company": "RGF HR Agent Hong Kong Limited", "job_title": "Shipping Assistant /(Trading company) ( up to 19K )", "description": "- Diploma or above\n- 1-5 years working experience\n- Good English, Mandarin and Japanese (N2)\n- Immediate available is preferred\n\nInterested parties, please click \"apply now\" to submit your application.", "employment_types": ["Full Time", "Permanent"], "selling_points": ["3 yrs shipping exp/Trading Company", "Handle Chinese suppliers/Fluent Chi&Eng", "Stable Working Hour"], "locations": ["Others"], "categories": ["Transportation & Logistics", "Shipping", "Sales, CS & Business Devpt", "Sales Administration"], "post_time": "2022-01-14T09:54:09Z", "salary": {"currency": null, "max": null, "min": null, "period": "monthly", "term": null}, "salary_visible": false, "title_keywords": ["shipping", "assistant"], "responsibilities": [], "requirements": {"degrees": ["diploma or above"], "majors": [], "languages": ["japanese", "english", "mandarin"], "language_level": ["good"], "hard_skills": [], "soft_skills": [], "languages_combined": [{"language": "japanese", "language_level": ["good"]}, {"language": "english", "language_level": ["good"]}, {"language": "mandarin", "language_level": ["good"]}]}, "experience_required": {"duration": ["1-5 years"], "field": []}}, {"job_id": "100003009051778", "location_code": "hk", "company": "Sinoway Shipping Limited", "job_title": "Project Officer", "description": "Requirement:\n\nFive subjects, including Chinese Language and English Language (\u201cSyllabus B\u201d before 2007), at Level 2 / Grade E or above in the Hong Kong Certificate of Education Examination, or at Level 2 or equivalent or above in the Hong Kong Diploma of Secondary Education Examination\nAt least 1 year of work experience preferably in settlement / back office operations / correspondent banking services for a wide range of financial products and markets\nBasic knowledge of settlement practices and SWIFT message standards\nHands-on experience/ knowledge of settlement and other operating systems such as SWIFT, RTGS, RIS, EasyWay, confirmation matching system and reconciliation system, and conversant with MS Excel an advantage\nGood command of written and spoken English\nDuties:\n\nSupport daily settlement operations such as cash transfer, fixed income, foreign exchange, interest rate swaps, and futures and options\nWork closely with stakeholders and external parties (e.g. counterparties, custodians and Nostro banks etc.) to ensure smooth settlement\nPerform other trade processing and settlement functions such as corporate actions, trade confirmation matching, reconciliation and static data maintenance, etc.\nSupport system and process improvement initiatives by participating in User Acceptance Test, production rollout, etc.\nAssist in the preparation of Management Information System reports and monthly statistic reports\nParticipate in regular Business Continuity Planning drills\nPerform other back office operational and administrative tasks", "employment_types": ["Full Time", "Contract"], "selling_points": ["Good benefits", "Free shuttle", "Medical & life insurance"], "locations": ["Tsing Yi"], "categories": ["Transportation & Logistics", "Shipping"], "post_time": "2022-01-17T01:03:47Z", "salary": {"currency": null, "max": null, "min": null, "period": "monthly", "term": null}, "salary_visible": false, "title_keywords": ["project officer"], "responsibilities": ["business continuity", "management", "maintenance", "data", "operations", "external parties", "back office", "reports", "trade confirmation", "administrative tasks", "planning"], "requirements": {"degrees": ["certificate", "diploma", "secondary education"], "majors": [], "languages": ["english", "chinese"], "language_level": ["good command"], "hard_skills": ["swift", "ms excel", "basic"], "soft_skills": ["hands-on"], "languages_combined": [{"language": "english", "language_level": ["good command"]}, {"language": "chinese", "language_level": []}]}, "experience_required": {"duration": ["at least 1 year"], "field": ["financial", "banking services"]}}, {"job_id": "100003009052931", "location_code": "hk", "company": "Shipco Transport (HK) Ltd", "job_title": "PNL Specialists", "description": "Requirement:\n\nFive subjects, including Chinese Language and English Language (\u201cSyllabus B\u201d before 2007), at Level 2 / Grade E or above in the Hong Kong Certificate of Education Examination, or at Level 2 or equivalent or above in the Hong Kong Diploma of Secondary Education Examination\n1 year\u2019s relevant work experience preferred\nWell versed in MS Word, Excel, Powerpoint and Chinese word-processing\nGood command of spoken and written English and Chinese\nDuties:\n\nProvide administrative and clerical support for the office, as well as to perform other ad hoc tasks as assigned\nHandle written public enquiries\nAssist in arranging the logistics of office's meetings and industry events held internally or externally\nAssist in preparing office' s promotional materials\nArrange all procurement and related activities", "employment_types": ["Full Time", "Permanent"], "selling_points": ["Manage, assist for import and export department", "DSE or above", "At least 2 years relevant operations experience"], "locations": ["Not Specified"], "categories": ["Transportation & Logistics", "Others", "Freight Forwarding", "Shipping"], "post_time": "2022-01-17T04:34:50Z", "salary": {"currency": null, "max": null, "min": null, "period": "monthly", "term": null}, "salary_visible": false, "title_keywords": [], "responsibilities": ["logistics", "promotional materials", "ad hoc tasks", "administrative and clerical support"], "requirements": {"degrees": ["certificate", "diploma", "secondary education"], "majors": [], "languages": ["english", "chinese"], "language_level": ["good command"], "hard_skills": ["excel", "chinese word-processing", "powerpoint", "ms word"], "soft_skills": [], "languages_combined": [{"language": "english", "language_level": ["good command"]}, {"language": "chinese", "language_level": ["good command"]}]}, "experience_required": {"duration": ["1 year"], "field": []}}, {"job_id": "100003009053944", "location_code": "hk", "company": "Lee Kum Kee (Hong Kong) Foods Ltd", "job_title": "\u9ad8\u7d1a\u5009\u52d9\u54e1", "description": "\u00a0MUST meet below requirements\n\n(a)\u00a0\u00a0 (1) possess a Bachelor\u2019s degree from a Hong Kong university with accountancy or law as a major subject, or equivalent; or\u00a0 \u00a0\n\u00a0 \u00a0 \u00a0 \u00a0(2)\u00a0 be a registered student of the Hong Kong Institute of Certified Public Accountants\u2019 Qualification Programme (QP) and have completed the\nAssociate Level of QP, or equivalent; or\u00a0 \u00a0\n\u00a0 \u00a0 \u00a0 \u00a0(3)\u00a0 have a pass in the International Qualifying Scheme of the Hong Kong Institute of Chartered Secretaries, or equivalent;\n(b)\u00a0 have met the language\u00a0 proficiency\u00a0 requirements of Level 3 or above in Chinese Language and English Language in the Hong Kong Diploma of\nSecondary Education Examination (HKDSEE) or Hong Kong Certificate of Education Examination (HKCEE), or equivalent [Note];\n(c)\u00a0 have relevant post-graduation or post-qualification working experience for two years; and\n(d)\u00a0 be fluent in Cantonese and spoken English.\n\n\nNote: \u201cGrade C\u201d in Chinese Language and English Language (Syllabus B) in the HKCEE held before 2007 are accepted administratively as comparable to \u201cLevel 3\u201d in Chinese Language and English Language in the 2007 HKCEE and henceforth.\n\nDuties:\n\nAdministering bankruptcy and compulsory winding-up cases which generally includes seizure\u00a0 of\u00a0 assets and\u00a0 records,\u00a0 realization of assets, investigation, adjudication of claims of creditors,\u00a0 distribution of dividends, checking trustees\u2019 and liquidators\u2019 accounts, reviewing cases\u00a0 regularly\u00a0 until\u00a0 close\u00a0 and\u00a0 administering ordinances relating to bankruptcy and compulsory winding-up;\nProviding\u00a0 attestation services to the debtors who present bankruptcy petitions against themselves; and\u00a0\nUndertaking any other duties as required.\u00a0\n\n\u00a0Interested parties, please send your resume in\u00a0WORD\u00a0format, stating your HKCEE/HKALE/DSE result, current & expected salary and availability by clicking APPLY NOW.\n\n(All personal data provided by applicants will be used for recruitment purpose only.)", "employment_types": ["Full Time"], "selling_points": [], "locations": ["Tai Po Area"], "categories": ["Transportation & Logistics", "Freight Forwarding", "Inventory / Warehousing", "Shipping"], "post_time": "2022-01-17T07:48:46Z", "salary": {"currency": null, "max": null, "min": null, "period": "monthly", "term": null}, "salary_visible": false, "title_keywords": [], "responsibilities": ["any other duties", "checking", "investigation"], "requirements": {"degrees": ["secondary education", "certificate", "bachelor", "diploma", "degree"], "majors": ["law", "accountancy"], "languages": ["cantonese", "english", "chinese"], "language_level": ["proficiency", "fluent"], "hard_skills": ["hong kong institute of certified public accountants", "c", "scheme"], "soft_skills": [], "languages_combined": [{"language": "cantonese", "language_level": ["fluent"]}, {"language": "english", "language_level": ["fluent", "proficiency"]}, {"language": "chinese", "language_level": ["proficiency"]}]}, "experience_required": {"duration": ["two years"], "field": ["post-qualification"]}}, {"job_id": "100003009044794", "location_code": "hk", "company": "Yusen Logistics (Hong Kong) Limited", "job_title": "Logistics Executive/Shipping Coordinator  - 3PL Ocean Freight Key Account", "description": "- Degree holder\n- Min 5 years solid accounting experience\n- Fluent in English, Mandarin and Japanese N1\n- Immediate available is preferred\n\nInterested parties, please click \"apply now\" to submit your application.", "employment_types": ["Full Time", "Permanent"], "selling_points": ["5 days work, key account. 3PL ocean shipment", "Control tower, Comm. with overseas,monitor vendors", "Manage daily export/ import, Fresh grad. welcome"], "locations": ["Kwai Hing"], "categories": ["Transportation & Logistics", "Freight Forwarding", "Shipping", "Supply Chain"], "post_time": "2022-01-13T06:17:50Z", "salary": {"currency": null, "max": null, "min": null, "period": "monthly", "term": null}, "salary_visible": false, "title_keywords": ["shipping coordinator", "logistics executive"], "responsibilities": [], "requirements": {"degrees": ["degree holder"], "majors": [], "languages": ["japanese", "english", "mandarin"], "language_level": ["fluent"], "hard_skills": [], "soft_skills": [], "languages_combined": [{"language": "japanese", "language_level": ["fluent"]}, {"language": "english", "language_level": ["fluent"]}, {"language": "mandarin", "language_level": ["fluent"]}]}, "experience_required": {"duration": ["min 5 years"], "field": ["accounting experience"]}}, {"job_id": "100003009056061", "location_code": "hk", "company": "Yusen Logistics (Hong Kong) Limited", "job_title": "Assistant Supervisor / Indoor Sales", "description": "~Diploma or above, Shipping Certificates or Business studies pref\u00a0\n~3-5 years experience in shipping field and trading industry\u00a0\n~Good English, Mandarin and Cantonese\n~Strong computer skills, e.g. Excel\u00a0\u00a0", "employment_types": ["Full Time", "Permanent"], "selling_points": ["Degree holder", "Relevant freight forwarding experience is required", "Proactive, good interpersonal & analytical skills"], "locations": ["Kwai Hing"], "categories": ["Transportation & Logistics", "Freight Forwarding", "Shipping", "Supply Chain"], "post_time": "2022-01-18T03:14:31Z", "salary": {"currency": null, "max": null, "min": null, "period": "monthly", "term": null}, "salary_visible": false, "title_keywords": ["assistant supervisor", "sales"], "responsibilities": ["shipping"], "requirements": {"degrees": [], "majors": [], "languages": ["cantonese", "english", "mandarin"], "language_level": [], "hard_skills": ["excel", "computer skills"], "soft_skills": [], "languages_combined": [{"language": "cantonese", "language_level": []}, {"language": "english", "language_level": []}, {"language": "mandarin", "language_level": []}]}, "experience_required": {"duration": ["5 years"], "field": ["trading"]}}, {"job_id": "100003009054926", "location_code": "hk", "company": "Apass International Hong Kong Company Limited", "job_title": "(Assistant) Merchandising Officer - FMCG / Food", "description": "~Diploma or above\n~Min 2 years Sales and Marketing experience, Sundries, Gift and Premium, Jewelry experience\u00a0\u00a0\n~Good English must\u00a0\u00a0\n~Excellent communication skill", "employment_types": ["Full Time", "Permanent"], "selling_points": ["Established food discributor of many famous brands", "Great exposure-purchase, marketing & merchandising", "Dynamic Japanese culture & utilise language skill"], "locations": ["Others"], "categories": ["Transportation & Logistics", "Shipping", "Marketing / Public Relations", "Marketing - General / Support", "Merchandising & Purchasing", "Procurement / Purchasing / Sourcing"], "post_time": "2022-01-17T14:06:55Z", "salary": {"currency": null, "max": null, "min": null, "period": "monthly", "term": null}, "salary_visible": false, "title_keywords": ["officer", "merchandising", "assistant"], "responsibilities": ["communication"], "requirements": {"degrees": [], "majors": [], "languages": ["english"], "language_level": [], "hard_skills": [], "soft_skills": ["communication skill"], "languages_combined": [{"language": "english", "language_level": []}]}, "experience_required": {"duration": ["2 years"], "field": ["marketing"]}}, {"job_id": "100003009043991", "location_code": "hk", "company": "Biotronik Hong Kong Limited", "job_title": "Logistics and Admin Coordinator", "description": "~Form 5 or above\n~5 years Woven / Knit / Sweater garment experience\n~Good English, Cantonese and fair Mandarin\n", "employment_types": ["Full Time", "Permanent"], "selling_points": ["Sales Coordination", "Diploma or above", "2-3 years working experience in MNC"], "locations": ["Sheung Wan"], "categories": ["Sales, CS & Business Devpt", "Customer Service - Supervisor / Officer", "Transportation & Logistics", "Documentary Credit / Bills Processing", "Shipping"], "post_time": "2022-01-13T18:54:31Z", "salary": {"currency": null, "max": null, "min": null, "period": "monthly", "term": null}, "salary_visible": false, "title_keywords": ["coordinator", "admin", "logistics"], "responsibilities": [], "requirements": {"degrees": [], "majors": [], "languages": ["cantonese", "english", "mandarin"], "language_level": [], "hard_skills": [], "soft_skills": [], "languages_combined": [{"language": "cantonese", "language_level": []}, {"language": "english", "language_level": []}, {"language": "mandarin", "language_level": []}]}, "experience_required": {"duration": [], "field": ["garment"]}}, {"job_id": "100003009038369", "location_code": "hk", "company": "K. C. Dat Limited", "job_title": "Shipping Officer (1-year contract)", "description": "~ Diploma or above\n~ 5 years relevant experience in Garment Trims / Packaging industry\n~ Good English and Mandarin\n~ Immediate available is preferred\n\nInterested parties, please click \"apply now\" to submit your application.\n\n", "employment_types": ["Contract"], "selling_points": ["responsible for data entry and filing", "handle  import and export shipment", "able to work from 9:00 am to 5:30 pm (Mon - Fri)"], "locations": ["Wan Chai"], "categories": ["Transportation & Logistics", "Freight Forwarding", "Shipping", "Sales, CS & Business Devpt", "Sales Administration"], "post_time": "2022-01-11T06:41:51Z", "salary": {"currency": null, "max": null, "min": null, "period": "hourly", "term": null}, "salary_visible": false, "title_keywords": ["shipping officer"], "responsibilities": [], "requirements": {"degrees": ["diploma or above"], "majors": [], "languages": ["english", "mandarin"], "language_level": ["good"], "hard_skills": [], "soft_skills": [], "languages_combined": [{"language": "english", "language_level": ["good"]}, {"language": "mandarin", "language_level": ["good"]}]}, "experience_required": {"duration": ["5 years"], "field": ["garment", "relevant experience"]}}, {"job_id": "100003009055187", "location_code": "hk", "company": "FedEx Trade Networks Transport & Brokerage (Hong Kong) Limited", "job_title": "Operations Analyst, Ocean / Associate Operations Analyst, Ocean", "description": "~ Diploma or above in Supply Chain, Textile, Purchasing or related disciplines\n~ 5 years relevant experience in procurement and strategic sourcing.\n~ Strong sourcing network including Vietnam, USA, South America, South China, etc.\n~ Good interpersonal skills and ability to network and utilize internal and external resources.\n~ Good English and Mandarin\n~ Willing to travel.\n\nInterested parties, please click \"apply now\" to submit your application.", "employment_types": ["Full Time", "Permanent"], "selling_points": ["Guarantee 14 months paid with attractive benefits", "Freight fowarding industry & Ocean Operations", "Immediately available is highly preferred"], "locations": ["Kwai Fong"], "categories": ["Transportation & Logistics", "Freight Forwarding", "Shipping", "Supply Chain"], "post_time": "2022-01-18T01:42:19Z", "salary": {"currency": null, "max": null, "min": null, "period": "monthly", "term": null}, "salary_visible": false, "title_keywords": ["associate", "operations analyst"], "responsibilities": [], "requirements": {"degrees": ["diploma or above"], "majors": ["related disciplines"], "languages": ["english", "mandarin"], "language_level": ["good"], "hard_skills": [], "soft_skills": ["interpersonal skills"], "languages_combined": [{"language": "english", "language_level": ["good"]}, {"language": "mandarin", "language_level": ["good"]}]}, "experience_required": {"duration": ["5 years"], "field": ["relevant experience", "procurement"]}}, {"job_id": "100003009053486", "location_code": "hk", "company": "City Super Ltd", "job_title": "\u4e2d\u73ed\u8ca8\u8eca\u53f8\u6a5f", "description": "1 to 3 yrs in electrical / mechanical technical maintenance\nREW grade A holder\nKnowledge in conveyor / sorter system\nLocation : HK airport\nShift: morning and night from MON \u2013 SUN w/ 2 day off after 2 shifts\n1 \u81f33 \u5e74\u6a5f\u96fb\u7dad\u4fee / \u8abf\u6a5f\u7d93\u9a57\n\u6301\u6709\u96fb\u5de5A\u724c\n\u5c0d\u904b\u8f38\u5e36\u7cfb\u7d71\u6709\u8a8d\u8b58\n\u5de5\u4f5c\u5730\u9ede: \u9999\u6e2f\u6a5f\u5834\n\u65e9\u665a\u66f4\uff0c\u8fd4\uff12\u65e5\u653e\uff12\u65e5\n\nBenefit: Public Holiday, guaranteed annual bonus, Medical, Transportation\u00a0allowance\u00a0and mobile allowance, OT pay\n\nFor enquiries, please contact Ms. Jade KO at 2838 8603 (Office), 64841771 (Whatsapp)", "employment_types": ["Full Time"], "selling_points": [], "locations": ["Kwai Tsing Area"], "categories": ["Transportation & Logistics", "Documentary Credit / Bills Processing", "Inventory / Warehousing", "Shipping"], "post_time": "2022-01-17T07:02:46Z", "salary": {"currency": null, "max": null, "min": null, "period": "monthly", "term": null}, "salary_visible": false, "title_keywords": [], "responsibilities": ["contact", "maintenance"], "requirements": {"degrees": [], "majors": [], "languages": [], "language_level": [], "hard_skills": ["mobile", "whatsapp", "jade", "maintenance"], "soft_skills": [], "languages_combined": []}, "experience_required": {"duration": [], "field": []}}, {"job_id": "100003009052762", "location_code": "hk", "company": "G3 Worldwide Hong Kong Limited", "job_title": "Business Development Manager / Assistant Business Development Manager", "description": "Job description:\nMaintain inventory records on timely basic Process warehouse documentation including data input, labelling printing for boxes and items, and daily inventory reports\nLiaise with customers and vendors for transportation issues and price negotiation\nPerform clerical duties and prepare regular report\nSalary: 13,000-14,000 per month\nWork hour: Mon to Fri (alt. Sat) 9am to 5:30pm\nWork Location: Kwai Chung\nWhy you?\nDSE or above in education\n1 - 3 years of relevant experience in supply chain, logistics or shipping field, with solid knowledge in shipping documentation and customs declaration\nProficient in MS Office Applications and Chinese word processing", "employment_types": ["Full Time"], "selling_points": [], "locations": ["Ngau Tau Kok"], "categories": ["Transportation & Logistics", "Shipping", "E-commerce", "Business Development", "Supply Chain"], "post_time": "2022-01-17T03:58:17Z", "salary": {"currency": null, "max": null, "min": null, "period": "monthly", "term": null}, "salary_visible": false, "title_keywords": ["business development manager", "assistant business development manager"], "responsibilities": ["sat", "price negotiation", "inventory", "data input", "liaise with", "maintain", "reports", "documentation", "prepare regular report"], "requirements": {"degrees": [], "majors": [], "languages": [], "language_level": [], "hard_skills": ["documentation", "basic"], "soft_skills": ["timely", "negotiation"], "languages_combined": []}, "experience_required": {"duration": [], "field": []}}, {"job_id": "100003009053435", "location_code": "hk", "company": "Johnson Electric Industrial Manufactory Limited", "job_title": "\u4e2d\u6e2f\u8ca8\u6ac3\u8eca\u53f8\u6a5f", "description": "To prospect, analyze, and recommend business solutions to major accounts from e-platforms, consolidators and direct e-sellers.\nTo make sales plan and meet the sales targets given by the company, ensuring continuous growth and maximizing returns.\nTo obtain information of market trends and customer needs, therefore providing insights to the management, with recommendations.\nTo establish business pipeline in parallel with sales plan, ensuring sales force efficiency and healthy new business development in line with sales and strategic plans.\nTo maintain regular contact and follow up with existing accounts, for maximum retention and sustainable business relationship.\nTo analyze trading portfolio and identify threat and opportunity.\u00a0\nProvide weekly sales updates and report.\u00a0\nHandle ad hoc projects as assigned.\nRequirements\nDegree holder in any disciplines.\nMin. 5 years of B2B sales / account servicing experience preferably in logistics industry\nKnowledgeable in e-platform / supply chain management is desirable.\nProficient in both English and Chinese.\nExcellent negotiation and interpersonal skills.\nAggressive, flexible and can-do attitude preferred.\u00a0\nFrequently travel to China or Asia Pacific region is envisaged.\u00a0\nImmediately availability is preferred\n\nG3 Worldwide Hong Kong Limited\u00a0is an equal opportunity employer and welcomes applications from all qualified candidates. Information provided will be treated in strict confidence and only be used for recruitment related purposes. Applicants who are not contacted within 6 weeks may consider their application unsuccessful. Unsuccessful applications may be kept for another 3 months for being considered for other suitable positions available in our Company. The unsuccessful applications will be destroyed after the said period of retention.\n", "employment_types": ["Full Time"], "selling_points": [], "locations": ["Not Specified"], "categories": ["Transportation & Logistics", "Shipping", "Others", "Technician", "Private Transportation"], "post_time": "2022-01-17T06:58:59Z", "salary": {"currency": null, "max": null, "min": null, "period": "monthly", "term": null}, "salary_visible": false, "title_keywords": [], "responsibilities": ["management", "strategic plans", "maintain", "ad hoc projects", "contact", "plan", "logistics", "recruitment", "report"], "requirements": {"degrees": ["degree holder"], "majors": ["any disciplines"], "languages": ["english", "chinese"], "language_level": ["proficient"], "hard_skills": ["make"], "soft_skills": ["flexible", "confidence", "negotiation", "can-do attitude", "interpersonal skills"], "languages_combined": [{"language": "english", "language_level": ["proficient"]}, {"language": "chinese", "language_level": ["proficient"]}]}, "experience_required": {"duration": ["5 years"], "field": ["logistics industry", "account servicing"]}}, {"job_id": "100003009044108", "location_code": "hk", "company": "Classic Fine Foods (Hong Kong) Limited", "job_title": "Procurement and Shipping Officer (5 Months Contract)", "description": "Role & Responsibilities:\nSupport Sales team to prepare quotation and Routing order\nFollow up shipping progress and keep customer informed for shipping status\nCollaborate with internal staff to deliver good and efficient customer services Maintain good support with customers and keep abreast of market & industry development\nAggressive, self-motivated, customer oriented\nAttend sales meeting with reporting and share in markets where that is desired\nRequirements\n1-2 years working experience\nCustomer oriented, proactive in client management and development\nProficient in Excel\nGood oral and written communication skills in English and Chinese language\nLearning opportunities\nBusiness development and intelligence\nCommercial awareness\nNegotiation skills\nAny candidate who is interested in 1 position is requested to send email to Mr. Matchy Yuen\u00a0 (email by clicking \"Apply Now\"\u00a0for internal review)", "employment_types": ["Temporary", "Contract"], "selling_points": ["Maternity Cover", "5 days working", "Under Procurement & Shipping Team"], "locations": ["Kwai Tsing Area"], "categories": ["Hospitality / F & B", "Food & Beverage", "Transportation & Logistics", "Shipping", "Merchandising & Purchasing", "Procurement / Purchasing / Sourcing"], "post_time": "2022-01-13T03:05:15Z", "salary": {"currency": null, "max": null, "min": null, "period": "monthly", "term": null}, "salary_visible": false, "title_keywords": ["shipping officer"], "responsibilities": ["collaborate with", "reporting", "shipping", "quotation", "customer services", "maintain", "sales team"], "requirements": {"degrees": [], "majors": [], "languages": ["english", "chinese"], "language_level": ["good"], "hard_skills": ["excel"], "soft_skills": ["communication skills", "oral", "interested in", "negotiation skills", "learning", "proactive"], "languages_combined": [{"language": "english", "language_level": ["good"]}, {"language": "chinese", "language_level": ["good"]}]}, "experience_required": {"duration": ["1-2 years"], "field": []}}, {"job_id": "100003009043082", "location_code": "hk", "company": "Asia Pacific Offset Limited", "job_title": "Temporary Shipping Clerk", "description": "\u8077\u8cac\n\n\u8ca0\u8cac\u64cd\u4f5c\u689d\u78bc(Bar Code)\u548c\u6578\u64da\u8f38\u5165\u7cfb\u7d71,\n\u70ba\u7ba1\u7406\u5c64\u6e96\u5099\u6bcf\u65e5\u5831\u544a,\n\u8207\u5ba2\u6236\u548c\u92b7\u552e\u5354\u8abf\u5236\u5b9a\u767c\u8ca8\u8a08\u5283,\n\u76e3\u63a7\u5eab\u5b58\u6c34\u5e73,\n\u65bc\u96fb\u5b50\u7cfb\u7d71\u8655\u7406\u51fa\u5165\u53e3\u5831\u7a05\n\u8981\u6c42\n\n\u4e2d\u4e94\u6216\u4e2d\u516d\uff0c\u81f3\u5c113\u5e74\u96fb\u5b50\u5de5\u4f5c\u7d93\u9a57\n\u80fd\u7368\u7acb\u5de5\u4f5c\uff0c\u5c0d\u5de5\u4f5c\u6709\u7a4d\u6975\u7684\u614b\u5ea6\n\u826f\u597d\u7684\u96fb\u8a71\u79ae\u8c8c\uff0c\u6e96\u6642\uff0c\u5718\u968a\u7cbe\u795e\uff0c\u6709\u8cac\u4efb\u5fc3\uff0c\u6a02\u65bc\u5b78\u7fd2\uff0c\u80fd\u627f\u53d7\u5de5\u4f5c\u58d3\u529b\nMS word\u3001Excel\u3001Windows\u7b49 PC\u64cd\u4f5c\n\u7cbe\u901a\u7cb5\u8a9e\u548c\u666e\u901a\u8a71\n\u7acb\u5373\u4e0a\u73ed", "employment_types": ["Temporary", "Contract"], "selling_points": ["Immediately available is preferred", "Higher diploma or above", "1-3 years of relevant experience"], "locations": ["Kowloon Bay"], "categories": ["Transportation & Logistics", "Others", "Shipping", "Supply Chain"], "post_time": "2022-01-12T09:45:24Z", "salary": {"currency": null, "max": null, "min": null, "period": "monthly", "term": null}, "salary_visible": false, "title_keywords": ["shipping clerk"], "responsibilities": [], "requirements": {"degrees": [], "majors": [], "languages": [], "language_level": [], "hard_skills": [], "soft_skills": [], "languages_combined": []}, "experience_required": {"duration": [], "field": []}}, {"job_id": "100003009040285", "location_code": "hk", "company": "Starkford Limited", "job_title": "Shipping Clerk", "description": "Job Description\nPrepare full set of I/E documents & L/C documents\nHandle custom declaration and import shipments\nLiaise with customers and vendors for transportation issues and price negotiation\nPerform clerical duties and prepare regular reports\nKeep track and ensure shipping schedule\nAssist in coordinating and solving shipment issues\nRequirements\nHigher Diploma or above in logistics, supply chain or related disciplines\n1 - 3 years of relevant experience in supply chain, logistics or shipping field, with solid knowledge in shipping documentation and customs declaration\nProficient in MS Office Applications and Chinese word processing, knowledge of ERP systems and e-system of Tradelink and HK Customs is preferred\nStrong numerical sense, detail-oriented, and able to make good judgments based on different scenarios\nGood interpersonal, communication and organization skills\nGood command of both spoken & written English and Chinese\nImmediately available is highly preferred\nWe offer an attractive remuneration package to the right candidate. Interested parties please send\u00a0the\u00a0detailed resume with current and expected salary by clicking \"Apply Now\".\nInformation provided will be treated in strict confidence and only be used for consideration of your application for the relevant or similar post(s) within our Group only.\u00a0", "employment_types": ["Full Time", "Permanent"], "selling_points": ["Diploma or above", "Monitor shipments, prepare invoice & shipping doc", "5-day work, Double Pay, flexible working hour"], "locations": ["Kwai Hing"], "categories": ["Transportation & Logistics", "Others", "Shipping", "E-commerce", "Supply Chain"], "post_time": "2022-01-12T02:08:16Z", "salary": {"currency": null, "max": null, "min": null, "period": "monthly", "term": null}, "salary_visible": false, "title_keywords": ["shipping clerk"], "responsibilities": ["shipping schedule", "price negotiation", "custom declaration", "reports", "liaise with"], "requirements": {"degrees": ["higher diploma or above"], "majors": ["related disciplines"], "languages": ["english", "chinese"], "language_level": ["good command", "proficient"], "hard_skills": ["erp systems", "chinese word processing", "make", "documentation", "ms office"], "soft_skills": ["communication", "organization skills", "interpersonal", "detail-oriented"], "languages_combined": [{"language": "english", "language_level": ["good command"]}, {"language": "chinese", "language_level": ["good command", "proficient"]}]}, "experience_required": {"duration": ["1 - 3 years"], "field": ["supply chain", "logistics", "relevant experience"]}}, {"job_id": "100003009053683", "location_code": "hk", "company": "Atlantx Partners Limited", "job_title": "LCL Product Manager", "description": "Job Responsibilities:\u00a0\u00a0\n\nMonitor import/export shipments with courier/logistics service provider\nPrepare invoice, shipping documents\u00a0and clerical duties\nWork closely with Procurement team and Operation team\nGenerate monthly reports\nPerform ad-hoc duties as assigned\u00a0\n\n\u00a0Job Requirements:\n\nDiploma or above, preferably in Logistics or Supply Chain related fields\n1-3 years\u00a0relevant working experience, fresh graduate will also be considered\nGood Cantonese, Mandarin and English written and verbal communication skills\nFamiliar with MS Office application, including Word, Excel & Chinese Word Processing\nMust be flexible, independent, challenging and able to work under pressure\nImmediately available preferred\n\nWe offer friendly team environment, good career prospect, also attractive remuneration package including discretionary bonus incentive, together with other benefits like five-day work week, flexible working hours, double pay, medical and dental insurance. Interested parties please send full resume with available date, present and expected salary by clicking \u201cApply Now\u201d for an interview.\n\n\n\nAll personal data collected will be used for recruitment purpose only.\n\n%MCEPASTEBIN%", "employment_types": ["Full Time"], "selling_points": ["LCL Products & Strategies Initiatives", "Implementation of Sales Strategy", "Dynamic & Stable Environment"], "locations": ["Central & Western Area"], "categories": ["Transportation & Logistics", "Freight Forwarding", "Shipping", "Supply Chain"], "post_time": "2022-01-17T07:45:06Z", "salary": {"currency": null, "max": null, "min": null, "period": "monthly", "term": null}, "salary_visible": false, "title_keywords": ["product manager"], "responsibilities": ["shipping documents", "monthly reports", "invoice", "monitor", "logistics", "ad-hoc duties"], "requirements": {"degrees": ["fresh graduate", "diploma or above"], "majors": [], "languages": ["cantonese", "english", "chinese", "mandarin"], "language_level": ["good"], "hard_skills": ["excel", "chinese word processing", "word", "ms office"], "soft_skills": ["flexible", "communication skills", "independent", "friendly", "work under pressure"], "languages_combined": [{"language": "cantonese", "language_level": ["good"]}, {"language": "english", "language_level": ["good"]}, {"language": "chinese", "language_level": []}, {"language": "mandarin", "language_level": ["good"]}]}, "experience_required": {"duration": ["1-3 years"], "field": ["relevant working experience"]}}, {"job_id": "100003009056089", "location_code": "hk", "company": "The Jockey Club Kau Sai Chau Public Golf Course Ltd", "job_title": "\u6c34\u624b", "description": "Our client, a Hong Kong based freight forwarding company with global offices is now seeking for a LCL product specialist to join their dynamic team\u00a0\n\n\n\nJob Responsibilities\n\nIdentify LCL Product opportunities and deliver Strategy for Group LCL Product\nAnalyze market opportunities and develop new product solutions and market entry opportunities aligned with Corporate LCL Strategy\nProduct set-up and execution of SOP\nBuild bridges between Product Development, Operations and Sales and Customer Experience Management\nNegotiate and benchmark vendor rates, participate in RFQs, work closely on procurement of LCL service from globally approved partners.\n\nRequirements\n\nBachelor or higher diploma in any discipline (Logistic/Supply Chain) would be a plus\nMinimum 8 years of of shipping industry experience and LCL product\nSolid experiences in Ocean Freights operations and customer service in NVOCC business, solution design & PL ownership\nWell written and spoken English is a\u00a0MUST, also fluent in Mandarin and Cantonese\nCompetent communicator who could work well under-pressure, meet deadline, be proactive and attention to details\nPlease email CV to\u00a0cs @ atlantxpartners.com", "employment_types": ["Full Time", "Contract"], "selling_points": [], "locations": ["Sai Kung"], "categories": ["Transportation & Logistics", "Freight Forwarding", "Shipping"], "post_time": "2022-01-18T03:15:52Z", "salary": {"currency": null, "max": null, "min": null, "period": "monthly", "term": null}, "salary_visible": false, "title_keywords": [], "responsibilities": ["operations", "management", "develop"], "requirements": {"degrees": ["diploma", "bachelor"], "majors": [], "languages": ["cantonese", "english", "mandarin"], "language_level": ["fluent"], "hard_skills": ["plus", "pl"], "soft_skills": ["competent", "customer service", "attention to details", "communicator", "proactive"], "languages_combined": [{"language": "cantonese", "language_level": ["fluent"]}, {"language": "english", "language_level": ["fluent"]}, {"language": "mandarin", "language_level": ["fluent"]}]}, "experience_required": {"duration": ["minimum 8 years"], "field": ["business", "customer service", "shipping industry", "design"]}}, {"job_id": "100003009048363", "location_code": "hk", "company": "Kingsway Personnel Ltd", "job_title": "Japanese Speaking Sales & Shipping Coordinator (Japanese trading co.) ~17K", "description": "\u8077\u8cac :\u5354\u52a9\u8239\u9577\u548c\u8f2a\u6a5f\u64cd\u4f5c\u54e1\u9032\u884c\u5ba2\u8259\u5167\u5916\u7684\u5404\u9805\u5de5\u4f5c\uff0c\u5354\u52a9\u63a5\u5f85\u4e58\u5ba2\u5b89\u5168\u5730\u4e0a\u843d\u8239\u96bb\uff0c\u4e00\u5e74\u5408\u7d04\n\u8cc7\u6b77 :\u6c92\u6709\u5b78\u6b77\u8981\u6c42; 1\u5e74\u7d93\u9a57; \u826f\u597d\u7cb5\u8a9e; \u4e00\u822c\u82f1\u8a9e; \u61c2\u8b80\u5beb\u4e2d\u6587; \u7565\u61c2\u8b80\u5beb\u82f1\u6587; \u9808\u5177\u5099\u57fa\u672c\u8239\u85dd\u53ca\u8239\u8236\u5b89\u5168\u77e5\u8b58\uff0c\u6709\u76f8\u95dc\u5de5\u4f5c\u7d93\u9a57\u512a\u5148\n\u5f85\u9047 :\u6bcf\u6708$13,000, \u6709\u5e74\u504712\u5929, \u5728\u8077\u57f9\u8a13, \u91ab\u7642\u4fdd\u96aa, \u6649\u5347\u6a5f\u6703, \u4f9b\u81b3\u98df \u53ca\u7d04\u6eff\u916c\u91d1, 24\u5c0f\u6642\u5de5\u4f5c\u53ca24\u5c0f\u6642\u4f11\u606f\u4e4b\u8f2a\u73ed\u4ea4\u66ff, \u6bcf\u9031\u5de5\u4f5c3\u5929\n\u7533\u8acb\u9808\u77e5 :\u6c42\u8077\u8005\u53ef\u81f4\u96fb27913373\u8207THE JOCKEY CLUB KAU SAI CHAU PUBLIC GOLF COURSE LTD\u5f35\u5148\u751f\u806f\u7d61\u3002", "employment_types": ["Full Time", "Permanent"], "selling_points": ["Japanese speaking, full set shipping", "Min. 2yrs sales co. exp. in Japanese co.", "~17K, double pay, bonus, transportation fee"], "locations": ["Shatin Area"], "categories": ["Transportation & Logistics", "Shipping", "Sales, CS & Business Devpt", "Others", "Sales Administration"], "post_time": "2022-01-16T21:50:21Z", "salary": {"currency": null, "max": null, "min": null, "period": "monthly", "term": null}, "salary_visible": false, "title_keywords": ["shipping coordinator", "sales"], "responsibilities": [], "requirements": {"degrees": [], "majors": [], "languages": [], "language_level": [], "hard_skills": [], "soft_skills": [], "languages_combined": []}, "experience_required": {"duration": [], "field": []}}, {"job_id": "100003009054384", "location_code": "hk", "company": "Mannings", "job_title": "\u5277\u8eca\u53f8\u6a5f (\u65e9\u73ed/\u4e2d\u73ed/\u901a\u5bb5\u73ed)", "description": "Ref: NR09555\nNature of Business: Japanese Trading co.\nLocation: Shatin Area\nWorking Days: 5 Days\n\nBenefit:\n- Double pay\n- Discretionary Bonus\n- Medical insurance\n- Transportation allowance\n\nRequirement:\n- Min. 2yrs full set shipping and sales co. exp.\n- Good command of Japanese, Mandarin and English\n- Working exp. in Japanese company, familiar with MS Excel\n\nDuties:\n- Handle order SO, PO follow up, full set shipping documents\n- Handle delivery control and payment collection\n- Liaise and negotiate with supplier\n\nInterested in the above vacancy?\u00a0 Send your resume to us NOW!\nOnly short-listed candidates will be notified. Personal data collected will be used for recruitment purpose only", "employment_types": ["Full Time"], "selling_points": [], "locations": ["Others"], "categories": ["Transportation & Logistics", "Freight Forwarding", "Inventory / Warehousing", "Shipping"], "post_time": "2022-01-17T09:19:29Z", "salary": {"currency": null, "max": null, "min": null, "period": "monthly", "term": null}, "salary_visible": false, "title_keywords": [], "responsibilities": [], "requirements": {"degrees": [], "majors": [], "languages": [], "language_level": [], "hard_skills": [], "soft_skills": [], "languages_combined": []}, "experience_required": {"duration": [], "field": []}}, {"job_id": "100003009045969", "location_code": "hk", "company": "Avnet Technology Hong Kong Limited", "job_title": "Logistics Clerk / Customer Service Representative", "description": "\u8077\u8cac :\u8ca0\u8cac\u99d5\u99db\u5277\u8eca\u88dd\u5378\u8ca8\u7269\u53ca\u5354\u52a9\u4e00\u822c\u5009\u52d9\u5de5\u4f5c (\u9700\u6301\u6709\u6709\u6548\u5277\u8eca\u724c, \u4f38\u5c55\u578b \u6216 \u6297\u8861\u578b \u5277\u8eca\u724c\u512a\u5148)(\u6bcf\u5929\u5de5\u4f5c 8 \u5c0f\u6642)\n\u8cc7\u6b77 :\u6c92\u6709\u5b78\u6b77\u8981\u6c42; 1\u5e74\u7d93\u9a57; \u4e00\u822c\u7cb5\u8a9e; \u61c2\u95b1\u8b80\u4e2d\u6587; \u61c2\u95b1\u8b80\u82f1\u6587; \u6301\u6709\u64cd\u4f5c\u53c9\u5f0f\u8d77\u91cd\u8eca(\u93df\u8eca)\u8b49\u66f8; \u9762\u8a66\u6642\u9593: \u661f\u671f\u4e00\u81f3\u661f\u671f\u4e94(\u516c\u773e\u5047\u671f\u9664\u5916) \u4e0a\u53489:30\u81f3\u4e2d\u534812:30 \u6216 \u4e0b\u53481:30\u81f35:00\n\u5f85\u9047 :\u6bcf\u6708$16,500 - $18,500, \u6709\u96d9\u7ce7, \u5e74\u504712\u5929, \u9280\u884c\u5047\u671f, \u54e1\u5de5\u8cfc\u7269\u512a\u60e0, \u91ab\u7642\u798f\u5229, \u5a5a\u5047 \u53ca\u4ea4\u901a\u6d25\u8cbc, \u4e0a\u53487\u6642\u81f3\u4e0b\u53484\u6642,\u4e0a\u53488\u6642\u81f3\u4e0b\u53485\u6642,\u4e0a\u53489\u6642\u81f3\u4e0b\u53486\u6642,\u4e0b\u53481\u6642\u81f3\u4e0b\u534810\u6642\u6216\u4e0b\u534810\u6642\u81f3\u4e0a\u53487\u6642, \u6bcf\u9031\u5de5\u4f5c6\u5929,\u8f2a\u4f11,\u56fa\u5b9a\u66f4\n\u7533\u8acb\u9808\u77e5 :\u6c42\u8077\u8005\u8acb\u89aa\u81e8\u4e5d\u9f8d\u8354\u679d\u89d2\u9577\u9806\u8857\u4e03\u865f\u897f\u9813\u4e2d\u5fc3\u516b\u6a13\u842c\u5be7\u9762\u8a66\u3002\u67e5\u8a62\u8acb\u81f4\u96fb22998150\u8207\u4f55\u5c0f\u59d0\u806f\u7d61\u3002", "employment_types": ["Full Time", "Permanent"], "selling_points": ["Double Pay, Discretionary Incentive (Quarterly)", "At least 1 yr exp in warehouse/logistics industry", "Good command of spoken Eng., Mandarin & Cantonese"], "locations": ["Tsuen Wan Area"], "categories": ["Transportation & Logistics", "Inventory / Warehousing", "Shipping", "Merchandising & Purchasing", "Electronics"], "post_time": "2022-01-13T09:15:40Z", "salary": {"currency": null, "max": null, "min": null, "period": "monthly", "term": null}, "salary_visible": false, "title_keywords": ["logistics clerk", "customer service representative"], "responsibilities": [], "requirements": {"degrees": [], "majors": [], "languages": [], "language_level": [], "hard_skills": [], "soft_skills": [], "languages_combined": []}, "experience_required": {"duration": [], "field": []}}, {"job_id": "100003009039780", "location_code": "hk", "company": "Able Choice Personnel Consultancy", "job_title": "Shipping and Sales Administrator", "description": "Job Description :\n\nTo handle ocean shipment to US, EU and Intra Asia markets;\nTo coordinate with suppliers, carriers, factories on day to day operation, which includes:-\nHandle and follow up booking with vendors;\nPrepare forecast to carriers;\nSubmit booking to related carriers;\nPrepare SI, dispatch ASN data;\nExecute SOP & Logistics related tasks;\nWork with origin teams closely\nJob Requirement :\n\nDegree or above in any discipline;\nWith 1 years' experience in international logistics (air / ocean freight) operations;\nAble to act as a team player to execute the operation;\nProficiency in written and verbal English , Cantonese and Mandarin;\nFresh Graduate is also welcome\nInterested parties please send full resume with employment history and expected salary to HRA Division, Yusen Logistics (Hong Kong) Limited at Level 31, Tower 1, Kowloon Commerce Centre, 51 Kwai Cheong Road, Kwai Chung, N.T. or by email to\u00a0hr.ylhk\u00a0@ hk.yusen-logistics.com\u00a0 \u00a0 \u00a0\n\n\nYusen Logistics (Hong Kong) is an equal opportunity employer. All information collected will be used for recruitment purpose only.", "employment_types": ["Full Time", "Permanent"], "selling_points": ["trading / manufacturing", "Shipping I/E document, Order follow up", "Mature and independent"], "locations": ["Tsim Sha Tsui"], "categories": ["Transportation & Logistics", "Shipping", "Sales, CS & Business Devpt", "Others", "Sales Administration"], "post_time": "2022-01-11T11:13:30Z", "salary": {"currency": null, "max": null, "min": null, "period": "monthly", "term": null}, "salary_visible": false, "title_keywords": ["sales administrator", "shipping"], "responsibilities": ["data", "coordinate with", "teams", "logistics", "booking", "forecast"], "requirements": {"degrees": ["degree or above", "fresh graduate"], "majors": [], "languages": ["cantonese", "english", "mandarin"], "language_level": ["proficiency"], "hard_skills": [], "soft_skills": ["team player"], "languages_combined": [{"language": "cantonese", "language_level": ["proficiency"]}, {"language": "english", "language_level": ["proficiency"]}, {"language": "mandarin", "language_level": ["proficiency"]}]}, "experience_required": {"duration": ["1 years"], "field": ["logistics"]}}, {"job_id": "100003009039698", "location_code": "hk", "company": "Hilpop Fashion Ltd", "job_title": "Shipping and General Clerk - Knitwear Manufacturing (\u8239\u52d9\u6587\u54e1 -\u91dd\u7e54\u6642\u88dd)", "description": "Job Duties:\n\nResponds to customer inquiries, expedites critical orders, communicates dispositions, researches and resolves issues, and researches orders\nCoordinate with internal and external customers\nDaily shipment coordination\nHandle system transactions\nPrepare shipping documentations, filing and reports\nTo follow up daily operation to comply with the KPI\nAny ad-hoc support upon requested\n\nJob Requirements:\n\n\nHigh School / Diploma or above\nAt least 1 year related experience in warehouse or logistics industry\nBasic computer, email, phone and communication skills\nMust be able to multi-task and work in a fast paced environment\nGood command of spoken and written in English, Cantonese and Mandarin\nWith SAP knowledge will be an advantage\n\nInterested parties please submit your application together with details CV (including salary history and expected salary) to the HR Department via\u00a0our career website (Click Here)\u00a0or by email at hkrecruitment @avnet.com. Please quote clearly the position your apply for in the email subject.\n\n\nAll applications will be treated in strict confidence and personal data provided with be used solely for recruitment purpose. Unsuccessful candidates may be considered for other vacancies. Applicants who are not contacted within one month should consider their applications filed for future reference. All unsuccessful applications will be destroyed within six months.", "employment_types": ["Full Time", "Permanent"], "selling_points": [], "locations": ["Kwun Tong"], "categories": ["Transportation & Logistics", "Shipping"], "post_time": "2022-01-11T10:34:12Z", "salary": {"currency": null, "max": null, "min": null, "period": "monthly", "term": null}, "salary_visible": false, "title_keywords": ["general clerk", "shipping"], "responsibilities": ["ad-hoc", "internal and external customers", "shipping", "customer inquiries", "coordinate with", "daily operation", "transactions", "reports", "coordination"], "requirements": {"degrees": ["diploma or above", "high school"], "majors": [], "languages": ["cantonese", "english", "mandarin"], "language_level": ["good command"], "hard_skills": ["basic", "sap"], "soft_skills": ["communication skills", "multi-task", "work in a fast paced environment"], "languages_combined": [{"language": "cantonese", "language_level": ["good command"]}, {"language": "english", "language_level": ["good command"]}, {"language": "mandarin", "language_level": ["good command"]}]}, "experience_required": {"duration": ["at least 1 year"], "field": ["related", "logistics industry"]}}, {"job_id": "100003009054354", "location_code": "hk", "company": "Wellcome", "job_title": "\u8ca8\u8eca\u53f8\u6a5f(\u8475\u6d8c\u8ca8\u6ac3\u78bc\u982d\u8ca8\u5009) (\u591c\u73ed)", "description": "~ Diploma or above\u00a0\n~ 6-8 years of relevant experience in trading/manufacturing industry\n~ Solid experience in I/E shipping document and order follow up in EU/US market.\u00a0\n~ Good English, Mandarin and Cantonese.\n\nInterested parties please send your detailed CV with expected salary by email to felix@ablechoice. com for interview.", "employment_types": ["Full Time"], "selling_points": [], "locations": ["Kwai Tsing Area"], "categories": ["Transportation & Logistics", "Freight Forwarding", "Inventory / Warehousing", "Shipping"], "post_time": "2022-01-17T09:15:12Z", "salary": {"currency": null, "max": null, "min": null, "period": "monthly", "term": null}, "salary_visible": false, "title_keywords": [], "responsibilities": ["shipping document"], "requirements": {"degrees": ["diploma or above"], "majors": [], "languages": ["cantonese", "english", "mandarin"], "language_level": ["good"], "hard_skills": ["shipping document"], "soft_skills": [], "languages_combined": [{"language": "cantonese", "language_level": ["good"]}, {"language": "english", "language_level": ["good"]}, {"language": "mandarin", "language_level": ["good"]}]}, "experience_required": {"duration": ["6-8 years"], "field": ["manufacturing industry", "relevant experience", "trading"]}}, {"job_id": "100003009049240", "location_code": "hk", "company": "GEODIS Hong Kong Limited", "job_title": "Logistics Supervisor (Tin Shui Wai 5.5 days)", "description": "We\u2019re looking for a passionate and dynamic individual to join our expanding teams. You have to be good natured and willing to learn, in return we\u2019ll guide you to the best career path we can provide.\n\nFor who we are it\u2019s all on our website: www.hilpop.com\n\nJob Responsibilities\n\n-\u00a0Assist in all shipment related jobs, including local/international courier services, cargo shipment\n\n-\u00a0General clerical work\n\n- Provide assistance to Merchandising\n\n\nJob Requirements\n\n-\u00a0F.5/IVE or equivalent\n\n-\u00a01-2 years\u2019 experience in Shipping\n\n- Fresh grads are also considered\n\nApart from the usual fringe benefits, our office has free coffee, in addition to having a fun and open working environment. In the fashion industry everything is seasonal so some periods may be busier than others.\u00a0\n\nInterested parties please send in your cover letter, CV and expected salary and we'll get back to you if we feel that you're someone we want!", "employment_types": ["Full Time", "Permanent"], "selling_points": ["Maintain operations performance and security", "15 Days Annual Leave with Medical Insurance", "5 years relevant experience in shipping/logistics"], "locations": ["Tin Shui Wai"], "categories": ["Transportation & Logistics", "Freight Forwarding", "Inventory / Warehousing", "Shipping"], "post_time": "2022-01-14T08:18:02Z", "salary": {"currency": null, "max": null, "min": null, "period": "monthly", "term": null}, "salary_visible": false, "title_keywords": ["supervisor", "logistics"], "responsibilities": ["provide assistance", "merchandising"], "requirements": {"degrees": [], "majors": [], "languages": [], "language_level": [], "hard_skills": [], "soft_skills": [], "languages_combined": []}, "experience_required": {"duration": ["1-2 years"], "field": []}}, {"job_id": "100003009043440", "location_code": "hk", "company": "Hays", "job_title": "Customer Service/ Shipping Coordinator", "description": "\u8077\u8cac :\u8ca0\u8cac\u99d5\u99db18\u985e\u724c\u7167\u8ca8\u8eca\u904b\u9001\u8ca8\u5230\u5404\u5340\u5206\u5e97(\u8475\u6d8c\u4e09\u865f\u8ca8\u6ac3\u78bc\u982d\u53d6\u8eca)\n\u8cc7\u6b77 :\u6c92\u6709\u5b78\u6b77\u8981\u6c42; 2\u5e74\u7d93\u9a57; \u4e00\u822c\u7cb5\u8a9e; \u61c2\u95b1\u8b80\u4e2d\u6587; \u61c2\u95b1\u8b80\u82f1\u6587; \u6301\u6709\u4e2d\u578b\u8ca8\u8eca\u99d5\u99db\u57f7\u7167\n\u5f85\u9047 :\u6bcf\u6708$17,000 - $25,000, \u6709\u96d9\u7ce7, \u5e74\u504712\u5929, \u9280\u884c\u5047\u671f, \u4ea4\u901a\u6d25\u8cbc, \u54e1\u5de5\u8cfc\u7269\u512a\u60e0, \u91ab\u7642\u798f\u5229 \u53ca\u65b0\u4eba\u734e$6000, \u4e0b\u53485\u6642\u534a\u81f3\u51cc\u66682\u6642\u534a, \u6bcf\u9031\u5de5\u4f5c6\u5929,\u8f2a\u4f11, \u6bcf\u5929\u5de5\u4f5c 8 \u5c0f\u6642\n\u7533\u8acb\u9808\u77e5 :\u6c42\u8077\u8005\u8acb\u89aa\u81e8\u4e5d\u9f8d\u8354\u679d\u89d2\u9577\u9806\u8857\u4e03\u865f\u897f\u9813\u4e2d\u5fc3\u516b\u6a13\u60e0\u5eb7\u9762\u8a66\u3002\u67e5\u8a62\u8acb\u81f4\u96fb22998150\u8207\u4f55 \u5c0f\u59d0\u806f\u7d61\u3002", "employment_types": ["Full Time", "Permanent"], "selling_points": ["MNC opportunity", "Work from home arrangements", "Competitive salary"], "locations": ["Not Specified"], "categories": ["Sales, CS & Business Devpt", "Customer Service - Supervisor / Officer", "Transportation & Logistics", "Fulfillment", "Shipping"], "post_time": "2022-01-12T11:49:43Z", "salary": {"currency": null, "max": null, "min": null, "period": "monthly", "term": null}, "salary_visible": false, "title_keywords": ["customer service", "shipping coordinator"], "responsibilities": [], "requirements": {"degrees": [], "majors": [], "languages": [], "language_level": [], "hard_skills": [], "soft_skills": [], "languages_combined": []}, "experience_required": {"duration": [], "field": []}}, {"job_id": "100003009054138", "location_code": "hk", "company": "Wellcome", "job_title": "\u8ca8\u8eca\u53f8\u6a5f (\u65b0\u9bae\u98df\u54c1\u5009)", "description": "The applicant is responsible to handle full set inbound and outbound shipping documents (air & sea) independently; coordinate with local,\u00a0\u00a0oversea agents\u00a0and internal parties to ensure timely shipping document delivery arrangements to customers; maintain updated shipment information and good filing system.\n\n\u00a0Requirements:\u00a0\n\nresponsible for data entry and filing\u00a0\ncommunicate and liaise with forwarder, logistic company and warehouse\n3-5 years working experience in handling full set inbound and outbound shipping document (air & sea) independently\u00a0\n\u00a0fluency in spoken and written English and good command of spoken Cantonese\nhands-on PC skills in MS-Word and Excel\ncustomer oriented, proactive and strong sense of responsibility\nable to work from 9:00 am to 5:30 pm (Mondays - Fridays) is preferable\nwilling to work overtime and learn\u00a0\nhandle other ad-hoc assignments as required\n\nOffice Location: Wanchai\n\nOffice Hours: 9:00 am - 5:30\u00a0pm (Mondays - Fridays)\n\nFringe\u00a0benefits: 5-day\u00a0work, public holidays and\u00a0MPF scheme.\n\nInterested candidates, please send your application with a detailed resume stating your expected salary and date of availability to Personnel Department, 17th Floor, 3 Lockhart Road, Wanchai, H.K. or by Apply Now.\n\n\u00a0(Personal data collection is strictly used for recruitment purpose)", "employment_types": ["Full Time"], "selling_points": [], "locations": ["Tseung Kwan O"], "categories": ["Transportation & Logistics", "Others", "Shipping"], "post_time": "2022-01-17T08:32:47Z", "salary": {"currency": null, "max": null, "min": null, "period": "monthly", "term": null}, "salary_visible": false, "title_keywords": [], "responsibilities": ["shipping documents", "data entry and filing", "ad-hoc assignments", "coordinate with", "maintain", "liaise with", "shipping document", "internal parties"], "requirements": {"degrees": [], "majors": [], "languages": ["cantonese", "english"], "language_level": ["fluency", "good command"], "hard_skills": ["ms-word", "pc skills", "shipping document", "excel"], "soft_skills": ["work overtime", "independently", "responsible", "sense of responsibility", "timely", "hands-on", "proactive"], "languages_combined": [{"language": "cantonese", "language_level": ["fluency", "good command"]}, {"language": "english", "language_level": ["fluency", "good command"]}]}, "experience_required": {"duration": ["3-5 years"], "field": []}}, {"job_id": "100003009050816", "location_code": "hk", "company": "Health and Happiness (H&H) Hong Kong Limited", "job_title": "Senior Procurement Specialist (FMCG)", "description": "Responsibilities:\n\nAssist\u00a0manager to enhance logistics operations standards\nEnsure proper manpower utilization and improve effectiveness and efficiency of operations of the department\nCoordinate the loading, unloading & storage of Logistics Centre\nEnsure all inventory transactions are properly recorded and maintain warehouse management system (WMS) for administration and automated material storage and retrieval\nStrict control\u00a0of productivity performances\nEnsure logistics operations\u00a0met the required KPI\u00a0& ISO standard\nReview internal SOP, develop strategies, policies, guidelines and procedures to improve operational efficiency\u00a0and streamline daily operation flow\nImplement and execute logistics strategies, include\u00a0forecast on budget and cost control\nReview\u00a0daily operational reports and make record for further analysis\nReview\u00a0operation regularly and recommend\u00a0improvement\u00a0and action plan\n\nRequirement:\u00a0\n\nF.7\u00a0or above, preferably with\u00a05 years relevant experience in shipping/logistics industry with at least 2 years in supervisory level\nExperience in maintaining and monitoring the daily productivity and operation output\nExperience in warehouse operation and operation development is preferred\nProficiency in WMS, SCM system and MS Office (including Word, Excel, Outlook)\u00a0\nGood command\u00a0of Chinese and English\nWorking location:\u00a0 Tin Shui Wai 5.5 days work\n\nIf you are interested in the career opportunity stated above, please send your application letter and resume stating full details of your background, references and expected salary to us.\n\nPersonal data collected will be used for recruitment purpose only.\n\nOur data processing are compliant with data protection regulations. To learn about GEODIS Privacy Policy or exercise your rights, go to http://geodis.com/dp/recruitment-privacy-policy", "employment_types": ["Full Time", "Permanent"], "selling_points": ["International Procurement (FMCG)", "Manage Purchase Orders (Adult/Baby Nutrition)", "Excellent Excel & Good Language Skills"], "locations": ["Quarry Bay"], "categories": ["Transportation & Logistics", "Documentary Credit / Bills Processing", "Shipping", "Merchandising & Purchasing", "Procurement / Purchasing / Sourcing"], "post_time": "2022-01-15T03:51:14Z", "salary": {"currency": null, "max": null, "min": null, "period": "monthly", "term": null}, "salary_visible": false, "title_keywords": ["specialist"], "responsibilities": ["operations", "budget", "inventory transactions", "improve effectiveness", "administration and automated material storage and retrieval", "maintain", "wms", "plan", "control", "warehouse management system", "logistics", "reports", "forecast", "proper manpower utilization", "efficiency of operations", "review", "procedures", "develop strategies", "guidelines", "policies", "analysis", "daily operation", "coordinate", "cost control"], "requirements": {"degrees": [], "majors": [], "languages": ["english", "chinese"], "language_level": ["good command"], "hard_skills": ["excel", "word", "go", "outlook", "processing", "ms office"], "soft_skills": ["interested in"], "languages_combined": [{"language": "english", "language_level": ["good command"]}, {"language": "chinese", "language_level": ["good command"]}]}, "experience_required": {"duration": ["5 years", "at least 2 years"], "field": ["development", "logistics industry", "operation", "relevant experience", "supervisory level"]}}, {"job_id": "100003009048702", "location_code": "hk", "company": "UAG Hong Kong Limited", "job_title": "Supply Chain Specialist", "description": "Your new company\nOur client is looking for a candidate with customer service and shipping experience to join their Hong Kong Team\n\nYour new role\n\nCommunicate with freight forwarders and internal stakeholders on shipping arrangement\nProvide support on inbound and outbound logistics queries for APAC market\nFollow up with customers enquiries\nHandle ad hoc issues\n\nWhat you'll need to succeed\n\nAt least 4 years of experience in shipping and order management, welcome candidates from 3PL background\nExperience in handling different markets\n\nWhat you'll get in return\n\nup to 25K\n5 days of work\nBenefit from work from home policy\n\nWhat you need to do now\nIf you're interested in this role, click 'apply now' to forward an up-to-date copy of your CV, or call us now.\nIf this job isn't quite right for you but you are looking for a new position, please contact us for a confidential discussion on your career.", "employment_types": ["Full Time", "Permanent"], "selling_points": ["End to end supply chain role", "Global market exposure", "Fast-Paced Work Environments"], "locations": ["Kowloon Bay"], "categories": ["Transportation & Logistics", "Fulfillment", "Shipping", "Supply Chain"], "post_time": "2022-01-14T07:04:36Z", "salary": {"currency": null, "max": null, "min": null, "period": "monthly", "term": null}, "salary_visible": false, "title_keywords": ["specialist"], "responsibilities": ["communicate with", "provide support", "shipping", "ad hoc", "order management", "customer service", "contact", "inbound and outbound logistics"], "requirements": {"degrees": [], "majors": [], "languages": [], "language_level": [], "hard_skills": ["inbound and outbound logistics"], "soft_skills": ["interested in", "customer service"], "languages_combined": []}, "experience_required": {"duration": ["at least 4 years"], "field": ["management", "customer service", "team"]}}, {"job_id": "100003009046195", "location_code": "hk", "company": "Otis Elevator Co (HK) Limited", "job_title": "Logistics Officer, Supply Chain", "description": "\u5de5\u4f5c\u5167\u5bb9: \u8ca0\u8cac\u99d5\u99db18\u985e\u724c\u7167\u8ca8\u8eca\u904b\u9001\u8ca8\u5230\u5404\u5340\u5206\u5e97\n\n\u5de5\u4f5c\u5730\u9ede: \u5c07\u8ecd\u6fb3\u5de5\u696d\u90a8\u65b0\u9bae\u98df\u54c1\u4e2d\u5fc3 (\u9700\u5728\u51cd\u5009\u5de5\u4f5c)\n\n\u5de5\u4f5c\u6642\u9593: \u4e0a\u53487\u6642\u81f3\u4e0b\u53483\u664245\u5206 \uff0c\u6bcf\u9031\u5de5\u4f5c6\u5929\uff0c\u8f2a\u4f11\n\n\u5de5\u4f5c\u8981\u6c42: \u5b78\u6b77\u4e0d\u62d8\uff0c\u9700\u6301\u670918\u724c\uff0c\u5169\u5e74\u6709\u95dc\u5de5\u4f5c\u7d93\u9a57\uff0c\u4e00\u822c\u7cb5\u8a9e\uff0c\u61c2\u8b80\u5beb\u4e2d\u6587\n\n\u5f85\u9047: \u65b0\u4eba\u734e\u91d1$6,000\uff0c\u63d0\u4f9b\u514d\u8cbb\u7a7f\u68ad\u5df4\u58eb\uff0c\u5e74\u7d42\u96d9\u7ce7\uff0c12\u5929\u6709\u85aa\u5e74\u5047\u300117\u5929\u516c\u773e\u5047\u671f\u3001\u96c6\u5718\u8cfc\u7269\u512a\u60e0\u3001\u8d85\u6642\u5de5\u4f5c\u6d25\u8cbc\u3001\u54e1\u5de5\u53ca\u5bb6\u5c6c\u91ab\u7642\u512a\u60e0\uff08\u4e2d\u897f\u91ab\u3001\u8dcc\u6253\u53ca\u7259\u91ab\uff09\u3001\u6709\u85aa\u5a5a\u5047\u53ca\u514d\u4f9b\u6b3e\u9000\u4f11\u8a08\u5283\n\n\u85aa\u916c\uff1a $19,000-$30,000\n\u00a0\n\n\u6709\u610f\u61c9\u5fb5\u8005\u53ef\u89aa\u81e8\u62db\u8058\u4e2d\u5fc3\u9762\u8a66 \u3010\u7121\u9808\u9810\u7d04\u3011\uff1a\n\n\u65e5\u671f\uff1a\u661f\u671f\u4e00\u81f3\u4e94 (\u516c\u773e\u5047\u671f\u9664\u5916)\n\n\u6642\u9593\uff1a9:00-12:30 / 13:30-17:00\n\n\u5730\u9ede\uff1a\u4e5d\u9f8d\u8354\u679d\u89d2\u9577\u9806\u88577\u865f\u897f\u9813\u4e2d\u5fc38\u6a13 (\u6e2f\u9435\u8354\u679d\u89d2\u7ad9A\u51fa\u53e3)", "employment_types": ["Full Time", "Permanent"], "selling_points": ["Exposure to MNC Environment", "Family-Friendly Employer", "Employee Scholar Program up to $160,000/ Degree"], "locations": ["Kowloon Bay"], "categories": ["Transportation & Logistics", "Shipping", "Supply Chain"], "post_time": "2022-01-13T09:54:29Z", "salary": {"currency": null, "max": null, "min": null, "period": "monthly", "term": null}, "salary_visible": false, "title_keywords": ["logistics officer"], "responsibilities": [], "requirements": {"degrees": [], "majors": [], "languages": [], "language_level": [], "hard_skills": [], "soft_skills": [], "languages_combined": []}, "experience_required": {"duration": [], "field": []}}, {"job_id": "100003009049524", "location_code": "hk", "company": "Brother Machinery (Asia) Limited", "job_title": "Customer Service Officer / After Sales Coordinator / Sales Associate / Sales Assistant", "description": "\u8077\u8cac :\n\n\u8ca0\u8cac\u8655\u7406\u4e00\u822c\u8ca8\u5009\u4e8b\u52d9\uff0c\u5305\u62ec\u57f7\u8ca8\u3001\u62c6\u8ca8\u3001\u9001\u8ca8\u53ca\u76e4\u9ede; \u8655\u7406\u65e5\u5e38\u9032\u51fa\u5009\u52d9\u6587\u4ef6\u53ca\u8ca8\u5b58\u8a18\u9304\uff0c\u5c07\u8cc7\u6599\u8f38\u5165\u65bc\u96fb\u8166\u7cfb\u7d71\u5167; \u5176\u4ed6\u7531\u90e8\u9580\u7d93\u7406\u6216\u4e3b\u7ba1\u5b89\u6392\u4e4b\u5de5\u4f5c; \u65bc\u8475\u6d8c\u53d6\u8eca\n\u8cc7\u6b77 :\n\n\u4e2d\u4e09\u7a0b\u5ea6; \u4e00\u822c\u7cb5\u8a9e; \u7565\u61c2\u8b80\u5beb\u4e2d\u6587; \u61c2\u95b1\u8b80\u82f1\u6587; \u6301\u6709\u4e2d\u578b\u8ca8\u8eca\u99d5\u99db\u57f7\u7167; \u53ef\u5373\u6642\u4e0a\u73ed\u512a\u5148\n\u5f85\u9047 :\n\n\u6bcf\u6708$16,780, \u6709\u5e74\u504710\u5929, \u9280\u884c\u5047\u671f, \u914c\u60c5\u6027\u82b1\u7d05 \u53ca\u91ab\u7642\u798f\u5229, \u4e0a\u53489\u6642\u534a\u81f3\u4e0b\u53487\u6642, \u6bcf\u9031\u5de5\u4f5c5\u5929\u81f36\u5929,\u8f2a\u73ed,\u8f2a\u4f11, \u6bcf\u5929\u5de5\u4f5c 8.5 \u5c0f\u6642, \u6bcf\u67087\u5929\u4f11\u606f\u65e5\n\u7533\u8acb\u9808\u77e5 :\u6c42\u8077\u8005\u53ef\u81f4\u96fb63053856\u8207CITY SUPER LIMITED\u856d\u5c0f\u59d0\u806f\u7d61\u3002", "employment_types": ["Full Time", "Permanent"], "selling_points": [], "locations": ["Kwai Hing"], "categories": ["Sales, CS & Business Devpt", "Customer Service - Supervisor / Officer", "Transportation & Logistics", "Shipping", "Others", "Trading"], "post_time": "2022-01-15T03:50:29Z", "salary": {"currency": null, "max": null, "min": null, "period": "monthly", "term": null}, "salary_visible": false, "title_keywords": ["sales coordinator", "sales assistant", "customer service officer", "sales associate"], "responsibilities": [], "requirements": {"degrees": [], "majors": [], "languages": [], "language_level": [], "hard_skills": [], "soft_skills": [], "languages_combined": []}, "experience_required": {"duration": [], "field": []}}, {"job_id": "100003009050507", "location_code": "hk", "company": "Expeditors Hong Kong Limited", "job_title": "Logistics Coordinator (Freight Forwarding/ Attractive Bonus/ Fresh Graduates are welcome)", "description": "Key Responsibilities\n\nSupport business unit by supplying adequate equipment without shortage\nEvacuate the surplus equipment to right locations that need the equipment\nImprove the cargo mapping for over / under balance locations to reduce the balancing cost\nMonitor equipment turnaround time\nUpdate and manage the system information, avoid the discrepancy of expense between actual and system\nMonitor the container tracing system for customers\n\nWho we are looking for\n\nBachelor's degree in shipping, logistics engineering, transport, or related disciplines\n2-year experience in shipping or / and logistics is highly preferred\nGood command of written and spoken in English and Mandarin\nProficiency in MS Office\nStrong analytical skills\nFresh graduates are also welcome\n\nWe offer\n\nExcellent opportunities for advancement with regional exposure\nCompetitive salary package\n5-Days Work\n15 - 17 days Annual Leave\nDouble Pay\nMedical & Dental Insurance\nLife Insurance\nBirthday Gifts\nMarriage Leave\nPaternity Leave\nWork from home arrangement\n\nInterested parties please share with us your latest resume showing current and expected remuneration package.", "employment_types": ["Full Time", "Permanent"], "selling_points": [], "locations": ["Kowloon Bay"], "categories": ["Transportation & Logistics", "Freight Forwarding", "Shipping", "Supply Chain"], "post_time": "2022-01-14T10:35:04Z", "salary": {"currency": null, "max": null, "min": null, "period": "monthly", "term": null}, "salary_visible": false, "title_keywords": ["logistics coordinator"], "responsibilities": ["cost", "shipping", "monitor", "logistics"], "requirements": {"degrees": ["degree", "bachelor"], "majors": ["related disciplines", "engineering"], "languages": ["english", "mandarin"], "language_level": ["good command"], "hard_skills": ["container", "analytical skills", "ms office"], "soft_skills": ["analytical skills"], "languages_combined": [{"language": "english", "language_level": ["good command"]}, {"language": "mandarin", "language_level": ["good command"]}]}, "experience_required": {"duration": ["2-year"], "field": ["logistics"]}}, {"job_id": "100003009042534", "location_code": "hk", "company": "Bravo Personnel Consultancy Limited", "job_title": "Shipping / Quality Control Assistant ($18K)", "description": "A bit about us\n\nHealth & Happiness (H&H) Group is a publicly traded company out of Hong Kong, with offices worldwide. Our vision is focused on premium nutrition and lifetime wellness. We have three business segments \u2013 Baby, Adult and Pet Nutrition and Care \u2013 supporting whole-family health and happiness across seven international brands. We care passionately about our customers and community and are looking for similar-minded people to join us!\n\nOn our journey to making a positive difference across the world, you will work with passionate people in an innovative and collaborative organisation as we inspire wellness through #PurposeLedCareers!\n\nAs an equal opportunity employer, we care deeply about creating an inclusive workplace where our team members feel valued, respected, and empowered.\n\nYour role within the team\n\nReporting to Associate Director - Procurement, the incumbent will have to manage Purchase Orders (POs) for global markets.\n\nKey responsibilities include:\n\nPrepare and issue purchase orders to overseas factories as well as managing each order shipment plans from creation to payment.\nEnsure execution of all regular procurement duties and administrative work.\nPrepare all the IC documents.\nManage all product and supplier data setup and updates in system.\nFollow up and analyze purchase order execution & completion.\nCheck supplier shipping documents and prepare related internal documents.\nLiaise with internal parties to make sure all specifications are communicated and received by Supplier.\nRegularly review supplier costing.\nPrepare and analyze supplier KPIs.\nDesired Skills and Experience\n\n\nTo make sure we are setting new starters up for success, we ask that you meet a few criteria relevant to the role to be considered for this opportunity:\n\n\u00a0Bachelor Degree in Supply Chain/Purchasing or equivalent.\n\u00a0At least 2-3 years relevant experience from FMCG industry.\n\u00a0Familiar with international trading\n\u00a0Detail minded, strong analytical and organizational skills\n\u00a0Excellent knowledge of MS Excel, preferably knowledge of Oracle and AX order processing\n\u00a0Good presentation and report writing skills\u00a0\n\u00a0Ability to work in a diversified culture environment.\n\u00a0Fluent in spoken English and Mandarin.\n\nH&H Group believes in the benefits of a diverse and inclusive workplace and aims to reflect the varied cultures within which we exist. We are committed to providing a working environment that is free from discrimination and harassment, creating a safe and inclusive environment for all.\n\nWe encourage applications from people of all ages, nationalities, religions, racial and gender identities, sexual orientations, abilities and cultures, and our hiring decisions will be based on business needs, position requirements, and the qualifications and experience of individuals.\u00a0 If you require support or assistance during the application process, please notify us at the time of application and we will be sure to enable reasonable adjustments where suitable.\n\nIf you have what it takes, please apply via the online portal and we will be in touch soon. We move quickly and may fill the role prior to the application close date, so we suggest you get in touch today!\n\nSalary and benefits will be competitive and commensurate with experience.\u00a0 All personal data collected is for recruitment purposes only.", "employment_types": ["Full Time", "Permanent"], "selling_points": [], "locations": ["Tsuen Wan Area"], "categories": ["Transportation & Logistics", "Others", "Shipping", "Manufacturing", "Quality Assurance, Control & Testing / ISO"], "post_time": "2022-01-12T08:35:29Z", "salary": {"currency": null, "max": null, "min": null, "period": "monthly", "term": null}, "salary_visible": false, "title_keywords": ["shipping", "assistant"], "responsibilities": ["shipping documents", "reporting", "administrative work", "data", "review", "purchase", "payment", "specifications", "internal parties", "kpis", "liaise with", "plans", "order processing", "setup", "report"], "requirements": {"degrees": ["degree", "bachelor"], "majors": [], "languages": ["english", "mandarin"], "language_level": ["fluent"], "hard_skills": ["pos", "fmcg industry", "writing skills", "make", "ms excel", "order processing", "oracle"], "soft_skills": ["passionate", "organizational skills", "focused", "collaborative", "writing skills", "organisation", "innovative", "presentation", "positive"], "languages_combined": [{"language": "english", "language_level": ["fluent"]}, {"language": "mandarin", "language_level": ["fluent"]}]}, "experience_required": {"duration": ["at least 2-3 years"], "field": ["fmcg", "relevant experience"]}}, {"job_id": "100003009049239", "location_code": "hk", "company": "GEODIS Hong Kong Limited", "job_title": "Logistics Clerk (Tuen Mun)", "description": "Responsibility\nResolve shipping & logistics issues independently\nMonitor shipping & logistics arrangement to ensure on-time shipments independently\nEnsure invoice/Customs documentation meets the requirement of destination countries\nMaintain KPI service level to uphold customer satisfaction\nPrepare monthly reports with operation data for business analysis\nKnowledgeable in handling I/E shipping documents and L/C if required\nAble to work under tight schedule and dynamic environment, and proactively seek solutions when issues arose\nSupport ad hoc projects and assignments when required\nLiaise with end user on goods return, damaged and claims\nRequirements\nHigh Diploma or above in related disciplines\n5 years of relevant experience and able to handle full sets independently\nExperience in warehouse operation and operation development is preferable\nGood command of spoken and written of English, Cantonese and Mandarin\nProficient with MS Office including Excel, Outlook and Word and Power point\nExperience in using SAP/Oracle ERP system is preferable\nGood customer service with internal and external parties will be a merit\nWe offer remuneration package including attractive salary, comprehensive fringe benefits and excellent opportunities for the right candidate.\u00a0(*** Employee Scholar Program\u00a0up to $160,000/ person for each degree***)\nWebsite:\u00a0http://www.otis.com/\u00a0\nInformation provided by applicants will be treated in strict confidence and will only be used for recruitment related purposes. All information on unsuccessful candidates will be deleted from our files within 24 months.", "employment_types": ["Full Time", "Permanent"], "selling_points": ["Coordinate and monitor daily operation", "Form 5 or above", "15 days annual leave"], "locations": ["Tuen Mun Area"], "categories": ["Admin & HR", "Clerical / Admin Staff", "Transportation & Logistics", "Inventory / Warehousing", "Shipping"], "post_time": "2022-01-14T08:18:01Z", "salary": {"currency": null, "max": null, "min": null, "period": "monthly", "term": null}, "salary_visible": false, "title_keywords": ["logistics clerk"], "responsibilities": ["shipping documents", "shipping", "business analysis", "logistics arrangement", "invoice", "monthly reports", "data", "monitor", "liaise with", "maintain", "logistics", "schedule", "ad hoc projects", "documentation"], "requirements": {"degrees": ["high diploma or above"], "majors": ["related disciplines"], "languages": ["cantonese", "english", "mandarin"], "language_level": ["good command"], "hard_skills": ["excel", "sap", "word", "oracle erp", "outlook", "power point", "ms office"], "soft_skills": ["independently", "customer service"], "languages_combined": [{"language": "cantonese", "language_level": ["good command"]}, {"language": "english", "language_level": ["good command"]}, {"language": "mandarin", "language_level": ["good command"]}]}, "experience_required": {"duration": ["5 years"], "field": ["development", "erp system", "operation", "relevant experience"]}}, {"job_id": "100003009036593", "location_code": "hk", "company": "China Resources Vanguard (Hong Kong) Co Ltd", "job_title": "Shipping Clerk / Assistant / Officer", "description": "Build and maintain strong relationship with clients to provide excellence after sales service and support\nDaily operations including customer enquiries follow up, and orders in ERP system, etc.\nCo-ordinate closely with internal suppliers to meet delivery schedule and quality sales services.\nParts inventory control for maintain a stable supply within reasonable stock level.\nArrange logistics (delivery, shipping, import and export declarations)\nProvide administration and secretarial support\nAssist in ad hoc duties assigned by manager\n\nTraining & Development\nProvide in house E-learning platform and study subsidy for job related topics\n\nOur Ideal Candidate\n\n\n3 years or above sales associate / coordinator experience / fresh graduate with potential will also be considered\nGood command of written and spoken English\u00a0\nAttention to details, self-motivated, sensible in problem solving and able to work independently\nGood PC skills (Excel and Outlook) with Chinese types & MS Office\nExperience of ERP system (SAP, Salesforce etc) will be advantage\nImmediate availability is preferred\n\nStaff Benefits\n\n5 days work\nBank Holiday\nFlexible Working Hours\nWork From Home\nTransportation Allowance\nMedical & Dental Insurance\nBody check\n\nInterested?\nIf you are interested please send your\u00a0full resume,\u00a0current\u00a0and\u00a0expected salary\u00a0and\u00a0availability\u00a0by clicking \"APPLY NOW\".\n\n*Personal data provided are treated in strictest confidence and for recruitment purposes only.\u00a0 All information will be destroyed after the process completed.*", "employment_types": ["Full Time", "Permanent"], "selling_points": ["Form 6 or above", "Immediate available is preferable", "Retail industry"], "locations": ["Shatin Area"], "categories": ["Transportation & Logistics", "Others", "Shipping", "Supply Chain"], "post_time": "2022-01-10T11:16:14Z", "salary": {"currency": null, "max": null, "min": null, "period": "monthly", "term": null}, "salary_visible": false, "title_keywords": ["officer", "shipping clerk", "assistant"], "responsibilities": ["ad hoc duties", "shipping", "customer enquiries", "quality", "delivery schedule", "daily operations", "maintain", "inventory control", "logistics", "secretarial support", "administration"], "requirements": {"degrees": ["fresh graduate"], "majors": [], "languages": ["english", "chinese"], "language_level": ["good command", "good"], "hard_skills": ["excel", "salesforce", "sap", "import and export", "problem solving", "erp system", "outlook", "pc skills", "ms office"], "soft_skills": ["self-motivated", "work independently", "problem solving", "learning", "attention to details", "stable", "ideal"], "languages_combined": [{"language": "english", "language_level": ["good command", "good"]}, {"language": "chinese", "language_level": ["good"]}]}, "experience_required": {"duration": ["3 years"], "field": ["erp system"]}}, {"job_id": "100003009037767", "location_code": "hk", "company": "Ample Solutions Co., Limited", "job_title": "Shipping clerk /Logistic Officer/Assistant", "description": "The Job (Ocean/ Air Export Team):\n\nTo contact vendors for bookings and validating bookings against consignee\u2019s instruction\u00a0\nTo arrange cargo, document pick-up\u00a0and distribution in accordance with our operations procedure and customers\u2019 requirements\nTo file all shipment record correctly and timely, and monitor the computerized database\nTo answer general telephone enquiries\nTeams and working location(Please state the preferred team in CV):\n\u00a0Ocean Team: Kowloon Bay\nAir Export Team**: Chek Lap Kok\u00a0(**Shift duty is required, including overnight shift ; Shift allowance is provided).\u00a0 \u00a0\u00a0\u00a0 \u00a0\u00a0 \u00a0\n\nThe Qualifications:\n\nTertiary education graduate with 1-2 years\u2019 experience in freight forwarding or shipping industry\nFresh graduates with less experience will also be considered\nPossess strong interest to pursue long term career in the logistic solutions industry\nProficient PC knowledge\nGood communication skills and able to communicate in English and Chinese (Cantonese and Mandarin)\n\nThe Future:\n\nCandidate for supervisory position\n\nAttractive remuneration package with good career prospect will be offered to the right candidates. Interested parties, please send your full resume and expecting salary to the Manager-Administration, 36/F-37/F, Enterprise Square Three, 39 Wang Chiu Road, Kowloon Bay, Hong Kong or fax to 2721 9734\u00a0or by clicking \"Apply Now\" button below. Please quote the reference on your application. Further information about the Company can be obtained at Expeditors\u2019 website: http://www.expeditors.com. Shortlisted candidates will be notified within 6 weeks.\n\n\u00a0All information provided by candidates will be used solely for recruitment purposes. Unsuccessful application will be destroyed in strict confidence upon completion of recruitment process.\n\nExpeditors is an equal opportunities employer and works towards a smoke free environment.", "employment_types": ["Full Time"], "selling_points": ["Immediate available is highly preferred", "Double pay\uff1bBonus\uff1bMedical insurance\uff1bFestive Gift", "Bank Holiday\uff1bChinese holiday;high tea"], "locations": ["Shatin Area"], "categories": ["Transportation & Logistics", "Documentary Credit / Bills Processing", "Shipping", "Supply Chain"], "post_time": "2022-01-11T03:46:27Z", "salary": {"currency": "HKD", "max": 19999, "min": 14000, "period": "monthly", "term": null}, "salary_visible": true, "title_keywords": ["logistic officer", "shipping clerk", "assistant"], "responsibilities": ["shipping", "operations", "teams", "monitor", "communication", "contact", "database"], "requirements": {"degrees": [], "majors": [], "languages": ["cantonese", "english", "chinese", "mandarin"], "language_level": ["good"], "hard_skills": ["bookings", "pc knowledge"], "soft_skills": ["communication skills", "timely"], "languages_combined": [{"language": "cantonese", "language_level": ["good"]}, {"language": "english", "language_level": ["good"]}, {"language": "chinese", "language_level": ["good"]}, {"language": "mandarin", "language_level": ["good"]}]}, "experience_required": {"duration": ["1-2 years"], "field": ["shipping industry", "education"]}}]