[{"job_id": "100003009053219", "location_code": "hk", "company": "Eternity Commerce Limited", "job_title": "E-Commerce Supply Chain Assistant/Officer (Logistics&Procurement/Sourcing/Merchandising/Purchasing)", "description": "The Job\n\nResponsible for inventory planning at Stores and Warehouse levels based on sales trends, promotion schedule and requirements\nAnalyze actual product demand, research demand drivers, refine the forecast to reflect updated sales momentum, and adjust inventory plans accordingly\nIssue PO and ensure smooth delivery from Supplier\nOrder placement and Evaluate stock availability to fulfill the demand\nLiaise with suppliers on delivery management to ensure smooth delivery operation.\nExecute allocation to optimize sales and meet the demand of Stores and Customers\nMaintain and timely update the auto replenishment system for Stores\nResolve out of stocks and overstock issue in Warehouse and Stores\nPrepare the performance figures, which includes maintaining the KPI for the team in terms of order fulfillment rate to stores and analyzing the performance details and identify improvement areas\n\nThe Person\n\nDiploma holder or above, preferably in Supply Chain management or relevant discipline.;\nMinimum 2 years of experience in Supply Chain or inventory planning. Experience in Retail or FMCG will be an advantage\nDetailed oriented and sensitive to figures, well organized and able to work independently\nFamiliar with MS Excel and Outlook\nFluent in Cantonese and English\nImmediate availability is preferable\nShipping knowledge is a Plus\nCandidate with more experience can be considered for Senior Demand and Supply Planning Officer\n\n\n\n\nDFI Retail Group is responsible for ensuring that all personal information collected from each Candidate presented to DFI Retail Group is used for recruitment purposes only and the data collection process is in accordance with all applicable laws and compliant with the Code of Practice on Human Resource Management.\n\nTo find out more about Our Businesses and Our People, please visit our website:\u00a0https://www.DFIretailgroup.com\n\nWe are an equal opportunity employer. Personal data collected will be kept and handled confidentially by authorised personnel for recruitment purposes only. We will retain the applications of candidates not selected for a period of no more than 24 months. A copy of our Privacy Policy can be accessed by visiting our Company website.\u201d\n\nIssued by The Dairy Farm Company, Limited", "employment_types": ["Full Time"], "selling_points": ["Logistics/Procurement/Purchasing/Merchandising", "Fresh Graduates are Welcome", "Young & Energetic Working Environment"], "locations": ["Quarry Bay"], "categories": ["Transportation & Logistics", "Supply Chain", "Merchandising & Purchasing", "Procurement / Purchasing / Sourcing", "E-commerce", "Supply Chain"], "post_time": "2022-01-17T06:27:59Z", "salary": {"currency": null, "max": null, "min": null, "period": "monthly", "term": null}, "salary_visible": false, "title_keywords": ["officer", "merchandising", "supply chain assistant"], "responsibilities": ["inventory planning", "management", "maintaining", "inventory", "replenishment", "evaluate", "maintain", "order fulfillment", "schedule", "forecast", "plans", "liaise with suppliers"], "requirements": {"degrees": ["diploma holder"], "majors": [], "languages": ["cantonese", "english"], "language_level": ["fluent"], "hard_skills": ["supply planning", "plus", "no", "ms excel", "outlook", "code"], "soft_skills": ["work independently", "detailed oriented", "responsible", "sensitive to figures", "well organized"], "languages_combined": [{"language": "cantonese", "language_level": ["fluent"]}, {"language": "english", "language_level": ["fluent"]}]}, "experience_required": {"duration": ["minimum 2 years"], "field": ["supply chain", "retail", "fmcg", "planning"]}}, {"job_id": "100003009051964", "location_code": "hk", "company": "Mannings", "job_title": "Senior/ Demand and Supply Planning Officer", "description": "We are now seeking a high caliber candidate for the following position:\n\n\n\u00a0Logistics / Supply Chain Manager\n\n\u00a0Job Responsibilities:\n\nSupervise the logistics team for all our orders, either our internal orders or direct shipments to customers\nMake sure that our ERP system is up to date and draw action plan whenever there is a delay\nCommunicate with our Sales Support in Holland all delays and promotions we have with key clients\nLiaise with the existing team all bookings with carriers and make sure allocations are used to their maximum capacity\nReview processes in communication but also within our ERP\nTake charge of some of the key clients understanding their process and workflow and coordinate with the merchandising team and Sales support\nReview on a weekly base all Quality planning for our team based in mainland China and arrange their schedule\n\nJob Requirements:\n\nExcellent in communication in English, Cantonese and Mandarin\nStrong logistics background preferred, review the daily operations and force of proposal to streamline the process\nGood knowledge of ERP system - preferably Microsoft Dynamics\nExcellent in excel functionalities and reporting\nGood knowledge of Hong Kong / China business practices\nPragmatic personality and hands on the job", "employment_types": ["Full Time", "Permanent"], "selling_points": ["Experience in Supply Chain or inventory planning", "Detailed oriented and sensitive to figures", "Responsible for inventory planning"], "locations": ["Quarry Bay"], "categories": ["Transportation & Logistics", "Supply Chain"], "post_time": "2022-01-17T01:39:33Z", "salary": {"currency": null, "max": null, "min": null, "period": "monthly", "term": null}, "salary_visible": false, "title_keywords": ["officer"], "responsibilities": ["communicate with", "review", "coordinate with", "merchandising", "quality", "communication", "logistics", "schedule", "plan", "liaise with", "planning"], "requirements": {"degrees": [], "majors": [], "languages": ["cantonese", "english", "mandarin"], "language_level": ["excellent"], "hard_skills": ["excel", "erp system"], "soft_skills": ["communication", "hands on"], "languages_combined": [{"language": "cantonese", "language_level": ["excellent"]}, {"language": "english", "language_level": ["excellent"]}, {"language": "mandarin", "language_level": ["excellent"]}]}, "experience_required": {"duration": [], "field": []}}, {"job_id": "100003009054132", "location_code": "hk", "company": "Edelman Asia Limited", "job_title": "Logistics / Supply Chain Manager", "description": "Responsibilities\n\nResponsible for strategic logistics operations planning\nReview on the implementation of operational initiatives in maximizing customer satisfaction, enhancing service quality and productivity\nStreamline the logistics flow\nEnhance the efficiency, cost control and resource optimization\nPerform other ad-hoc projects as assigned\n\nRequirements\n\nDegree holder in Business Management/ Logistics/Supply Chain Management\nWith 5 years related logistics experience in which at least 3 years supervisory level, preferably in local logistics / distribution center management\nComputer literate and accounting knowledge is a plus\nHaving driving license is preferable\nStrong communication, presentation and leadership skills\nMature and able to work independently and under pressure\n\nWorking Location: Sham Tseng\n\nInterested parties please click \"Apply Now\" or send the expected salary and available date, quote the job position and reference number to Human Resources Department, 1-11 Sham Tsz Street, Sham Tseng, New Territories, Hong Kong.\n\nAll the information collected will be used for the purpose of recruitment only.", "employment_types": ["Full Time"], "selling_points": [], "locations": ["Hung Hom"], "categories": ["Transportation & Logistics", "Supply Chain"], "post_time": "2022-01-17T08:43:10Z", "salary": {"currency": null, "max": null, "min": null, "period": "monthly", "term": null}, "salary_visible": false, "title_keywords": ["logistics", "supply chain manager"], "responsibilities": ["operations", "review", "quality", "implementation", "logistics", "cost control", "ad-hoc projects", "planning"], "requirements": {"degrees": ["degree holder"], "majors": ["business"], "languages": [], "language_level": [], "hard_skills": ["business management", "plus"], "soft_skills": ["work independently", "under pressure", "leadership skills", "mature", "communication", "presentation"], "languages_combined": []}, "experience_required": {"duration": ["5 years", "at least 3 years"], "field": ["related", "supervisory level", "management", "logistics"]}}, {"job_id": "100003009053355", "location_code": "hk", "company": "Alpha Power Solutions Limited", "job_title": "Planning & Logistics Specialist", "description": "Job Responsibilities:\n\nCollaborate with sales team and warehouse for delivery schedule arrangement and issue delivery note\nAssist in sourcing and purchasing raw materials\nLiaise with suppliers to drive on- time shipment delivery\nHandle order processing, inventory control and coordinate all transportation including ocean and air freight forwarding\nHandle purchase orders and shipping documents. Freight rate checking and transit time analysis\nMonitor supply availability, quality standards, cost & contracts and ensure deliverables are achieved to project site\nAssist in handling product quality issue and quality control\nAd hoc tasks as assigned\n\nRequirement:\n\nHigher Diploma or above, major in Supply Chain Management/Logistics, Mathematics, Science, Business or equivalent\nFresh graduates with passion and willing to learn are welcomed\nGood knowledge of PC and Excel is essential\nGood command of both spoken and written English and Chinese\nSelf-motivated, well organized, able to work independently and strong compliance with ability to meet deadlines\nCandidate with more experience will be consider as Supply Chain Officer\nImmediately available is preferred\u00a0\n\nOur attractive remuneration includes:\n\nMedical Insurance\nDouble Pay\nDiscretionary Bonus\nBirthday Leave\nPaid Sick Leave\nGym Membership\nFive Days Work Week\nFlexible working hours\nEducation Allowance", "employment_types": ["Full Time"], "selling_points": [], "locations": ["Shatin Area"], "categories": ["Transportation & Logistics", "Shipping", "Supply Chain", "Manufacturing", "Production Planning / Control"], "post_time": "2022-01-17T06:49:56Z", "salary": {"currency": null, "max": null, "min": null, "period": "monthly", "term": null}, "salary_visible": false, "title_keywords": ["logistics specialist"], "responsibilities": ["collaborate with", "shipping documents", "quality", "product quality issue", "purchase", "contracts", "monitor", "cost", "air freight", "ad hoc tasks", "checking", "delivery schedule", "inventory control", "analysis", "coordinate", "sales team", "order processing", "quality control", "liaise with suppliers"], "requirements": {"degrees": ["higher diploma or above"], "majors": ["mathematics", "business", "science"], "languages": ["english", "chinese"], "language_level": ["good command"], "hard_skills": ["pc", "excel"], "soft_skills": ["flexible", "self-motivated", "work independently", "willing to learn", "well organized", "meet deadlines"], "languages_combined": [{"language": "english", "language_level": ["good command"]}, {"language": "chinese", "language_level": ["good command"]}]}, "experience_required": {"duration": [], "field": ["supply chain"]}}, {"job_id": "100003009054083", "location_code": "hk", "company": "Vita Green Pharmaceutical (H.K.) Limited", "job_title": "Purchasing & Material Control Manager", "description": "Jobs responsibilities\n\nProvide PC installation, network setup, and administration, including firewall, VPN, and Wireless router\nPerform daily support and maintenance to the application systems, including all the updates and upgrades of software and hardware\nProvide end-users technical support and conduct troubleshooting on hardware, software, and other computer services\nPrepare documents such as user guidelines, system and application operation procedures\nEnsure the technical problems are resolved and follow-up actions are completed in a timely manner\n\nJobs requirements\n\nDegree holder in IT/ Computer Sciences or related disciplines\nMinimum 2 years of hands-on experience in IT helpdesk or enterprise support, including network devices, hardware and software setup\nProficient in different technologies and platforms, such as Windows 2008 Server or above, Linux, MYSQL\nProficient in both written and spoken English, Cantonese and Mandarin\n\nIf you are interested in the above position, please feel free to send your updated CV to cindy.wong@manpowergrc.hk", "employment_types": ["Full Time", "Permanent"], "selling_points": ["Newly created role", "Material Control & Purchasing focus", "Team leader role"], "locations": ["Tai Po Area"], "categories": ["Transportation & Logistics", "Supply Chain", "Manufacturing", "Production Planning / Control", "Merchandising & Purchasing", "Procurement / Purchasing / Sourcing"], "post_time": "2022-01-17T08:20:43Z", "salary": {"currency": null, "max": null, "min": null, "period": "monthly", "term": null}, "salary_visible": false, "title_keywords": ["manager"], "responsibilities": ["installation", "software", "upgrades", "technical support", "guidelines", "computer services", "procedures", "troubleshooting", "daily support and maintenance", "a timely manner", "hardware", "application systems", "prepare documents", "setup", "administration"], "requirements": {"degrees": ["degree holder"], "majors": ["related disciplines", "it"], "languages": ["cantonese", "english", "mandarin"], "language_level": ["proficient"], "hard_skills": ["server", "hardware", "linux"], "soft_skills": ["hands-on", "interested in"], "languages_combined": [{"language": "cantonese", "language_level": ["proficient"]}, {"language": "english", "language_level": ["proficient"]}, {"language": "mandarin", "language_level": ["proficient"]}]}, "experience_required": {"duration": ["minimum 2 years"], "field": ["it helpdesk"]}}, {"job_id": "100003009056631", "location_code": "hk", "company": "The Garden Company Limited", "job_title": "Assistant Logistics Planning Manager / Logistics Planning Manager", "description": "Responsibilities\n\nResponsible for strategic logistics operations planning\nReview on the implementation of operational initiatives in maximizing customer satisfaction, enhancing service quality and productivity\nStreamline the logistics flow\nEnhance the efficiency, cost control and resource optimization\nPerform other ad-hoc projects as assigned\n\nRequirements\n\nDegree holder in Business Management/ Logistics/Supply Chain Management\nWith 5 years related logistics experience in which at least 3 years supervisory level, preferably in local logistics / distribution center management\nComputer literate and accounting knowledge is a plus\nHaving driving license is preferable\nStrong communication, presentation and leadership skills\nMature and able to work independently and under pressure\n\nWorking Location: Sham Tseng\n\nInterested parties please click \"Apply Now\" or send the expected salary and available date, quote the job position and reference number to Human Resources Department, 1-11 Sham Tsz Street, Sham Tseng, New Territories, Hong Kong.\n\nAll the information collected will be used for the purpose of recruitment only.", "employment_types": ["Full Time", "Permanent"], "selling_points": ["Strategic logistics operations planning", "Enhance service quality and productivity", "Immediate available is highly preferred"], "locations": ["Tsuen Wan Area"], "categories": ["Transportation & Logistics", "Others", "Fulfillment", "Supply Chain"], "post_time": "2022-01-18T05:15:52Z", "salary": {"currency": null, "max": null, "min": null, "period": "monthly", "term": null}, "salary_visible": false, "title_keywords": ["assistant logistics planning manager", "logistics planning manager"], "responsibilities": ["operations", "review", "quality", "implementation", "logistics", "cost control", "ad-hoc projects", "planning"], "requirements": {"degrees": ["degree holder"], "majors": ["business"], "languages": [], "language_level": [], "hard_skills": ["business management", "plus"], "soft_skills": ["work independently", "under pressure", "leadership skills", "mature", "communication", "presentation"], "languages_combined": []}, "experience_required": {"duration": ["5 years", "at least 3 years"], "field": ["related", "supervisory level", "management", "logistics"]}}, {"job_id": "100003009054386", "location_code": "hk", "company": "Superpower Pumping Engineering Co., Ltd.", "job_title": "Purchasing Officer", "description": "Job Duties:\n\nHandling all relevant IP matters such as trademark and copyright\nPrepare, edit, format, and proof-read correspondences and documents\nCommunicating with external agents and relevant stakeholders\nAssist in any ad hoc project as required\n\nRequirements:\n\nBachelor's Degree or above in Law/IP (intellectual property) or relevant disciplines\nExperience in IP field preferred\nNQ is also considered\nProficient in English and Chinese (Cantonese & Mandarin), other language is a plus\nExcellent communication skills and team player\nAble to work under pressure\nFamiliar with online procurement tools as well as major IT tools, advanced user of Excel and Power Point, or database tools is a plus", "employment_types": ["Full Time", "Permanent"], "selling_points": ["Diploma or above", "At least 2 years\u2019 working experience in purchasing", "Monitor the overall inventory level"], "locations": ["Cheung Sha Wan"], "categories": ["Transportation & Logistics", "Others", "Inventory / Warehousing", "Supply Chain"], "post_time": "2022-01-17T09:19:51Z", "salary": {"currency": null, "max": null, "min": null, "period": "monthly", "term": null}, "salary_visible": false, "title_keywords": ["purchasing officer"], "responsibilities": ["communicating with", "ad hoc"], "requirements": {"degrees": ["degree or above", "bachelor"], "majors": ["law"], "languages": ["cantonese", "english", "chinese", "mandarin"], "language_level": ["proficient"], "hard_skills": ["power point", "ip", "plus", "excel"], "soft_skills": ["communication skills", "team player", "advanced", "work under pressure"], "languages_combined": [{"language": "cantonese", "language_level": ["proficient"]}, {"language": "english", "language_level": ["proficient"]}, {"language": "chinese", "language_level": ["proficient"]}, {"language": "mandarin", "language_level": ["proficient"]}]}, "experience_required": {"duration": [], "field": []}}, {"job_id": "100003009056290", "location_code": "hk", "company": "ConnectedGroup Limited", "job_title": "Logistics Specialist (US Sourcing office)", "description": "Responsibilities:\n\nAssist in the project management, system implementation, as well as other IT projects\nPerform data analyses and extraction using different analytical tools.\nParticipate in the new project initiatives, such as business intelligence and data analytics projects\nProvide application support and perform testing in various IT systems\nPerform tasks as assigned by the supervisors\n\nRequirements:\n\nDegree Holder in Information System / Computer Science / Data Science or related disciplines\n1 years of solid experience in project development and implementation, data modelling, using relational database, data warehouse, data lakes, SQL and reporting tools\nStrong analytical, problem-solving, interpersonal and communication skills\nGood command in English, and Chinese\n\nAny interested parties, please click \u201cApply Now\u201d or send your resume to carrie.yim@manpowergrc.hk", "employment_types": ["Full Time", "Permanent"], "selling_points": ["US market focused", "Forwarder/ 3PL for EU & US market welcomed", "Double pay + Bonus; 5 day; Medical"], "locations": ["Not Specified"], "categories": ["Transportation & Logistics", "Others", "Shipping", "Supply Chain"], "post_time": "2022-01-18T03:51:22Z", "salary": {"currency": null, "max": null, "min": null, "period": "monthly", "term": null}, "salary_visible": false, "title_keywords": ["logistics specialist"], "responsibilities": ["data", "systems", "implementation", "testing", "project management"], "requirements": {"degrees": ["degree holder"], "majors": ["related disciplines", "data science", "computer science"], "languages": ["english", "chinese"], "language_level": ["good command"], "hard_skills": ["data warehouse", "problem-solving", "sql", "information system"], "soft_skills": ["communication skills", "problem-solving", "interpersonal"], "languages_combined": [{"language": "english", "language_level": ["good command"]}, {"language": "chinese", "language_level": ["good command"]}]}, "experience_required": {"duration": ["1 years"], "field": ["sql", "development", "database"]}}, {"job_id": "100003009053225", "location_code": "hk", "company": "DKSH Hong Kong Limited", "job_title": "Specialist, Supply Chain Management (Fresh Graduates are welcome)", "description": "Job Duties:\n\nHands on source-to-pay procurement process with multiple categories focus (mainly in IT & Telcom, Facility Services & Marketing Services), mainly operates in company's in-house group procurement platform.\nProvides full process support with internal stakeholders and external suppliers in order to achieve business targets by implementing sourcing & procurement execution within the group procurement policy and procedures.\u00a0\nEnhance user experience both internal & external by sound project planning & correspondence, as well as timely reactions in addressing queries & problem solving.\nKeep constant collaboration with central Group Procurement team in Hangzhou, as well as other regional teams, to maintain the synergy of category strategies, process improvement, and best practice sharing of overseas procurement operation.\nCollaborates with other functions such as Finance, Legal, HR in maintaining overall process control and mutual key performance metrics.\nExecuting project-based sourcing with guidance of the line manager. Develop local category strategy and expand local supply base.\nData reporting on a regular basis.\n\nRequirements:\n\nBachelor's Degree or above\nWorking experience in procurement or similar scope is an advantage\nFast learning in a very dynamic and fast pace environment\nPatient with sense of customer care, open-minded and willing to pro-actively communicate with others\nProficient in English and Mandarin, other language is a plus\nFamiliar with online procurement tools as well as major IT tools, advanced user of Excel and Power Point, or database tools is a plus\nCandidate with no experiences or fresh graduate will also be considered", "employment_types": ["Full Time", "Permanent"], "selling_points": ["Certificate or Diploma graduate", "Immediate available is highly preferred", "Fresh Graduates are welcome"], "locations": ["Kwai Tsing Area"], "categories": ["Transportation & Logistics", "Others", "Supply Chain", "Manufacturing", "Others"], "post_time": "2022-01-17T06:29:13Z", "salary": {"currency": null, "max": null, "min": null, "period": "monthly", "term": null}, "salary_visible": false, "title_keywords": ["specialist"], "responsibilities": ["guidance", "project planning", "control", "reporting", "maintaining", "data", "hr", "procedures", "user experience", "teams", "performance metrics", "develop", "maintain", "executing"], "requirements": {"degrees": ["degree or above", "bachelor", "fresh graduate"], "majors": [], "languages": ["english", "mandarin"], "language_level": ["proficient"], "hard_skills": ["excel", "plus", "no", "dynamic", "power point"], "soft_skills": ["advanced", "open-minded", "dynamic", "learning", "patient"], "languages_combined": [{"language": "english", "language_level": ["proficient"]}, {"language": "mandarin", "language_level": ["proficient"]}]}, "experience_required": {"duration": [], "field": ["procurement"]}}, {"job_id": "100003009055691", "location_code": "hk", "company": "Manpower Services (Hong Kong) Limited", "job_title": "Logistics Admin _Natural Resources_ Max 35K", "description": "Job Duties:\n\nDesign and prepare Test Plan\nTest Scenarios and Test Cases according to user requirements\nPerform functional test and user scenario test on a non-Production system\nFind out and bug fixing\nProvide clear and detailed test reports\nPerform any ad hoc project/tasks\n\nRequirements:\n\nDiploma or above in Information System, Computer Science, or related diploma\nAt least 1 year of relevant experience in the IT industry\nExperience in Quality Assurance is preferred\nKnowledge of any test management tools (Zephyr, XRay, PractiTest, Testlink, Testrail, Testflow)\nDetail oriented and well organized and able to work under pressure.\nGood command of both written and spoken English and Chinese (Cantonese & Mandarin)\nFresh Graduates are also welcome", "employment_types": ["Permanent"], "selling_points": ["Exp in handling L/C & Supply Chain procedure", "Fluent English & Mandarin", "Immediatly Available"], "locations": ["Central"], "categories": ["Transportation & Logistics", "Fulfillment", "Shipping", "Supply Chain"], "post_time": "2022-01-18T02:51:17Z", "salary": {"currency": null, "max": null, "min": null, "period": "monthly", "term": null}, "salary_visible": false, "title_keywords": ["admin", "logistics"], "responsibilities": ["ad hoc", "reports", "design", "plan"], "requirements": {"degrees": ["diploma", "diploma or above"], "majors": ["computer science"], "languages": ["cantonese", "english", "chinese", "mandarin"], "language_level": ["good command"], "hard_skills": ["information system"], "soft_skills": ["detail oriented", "well organized", "work under pressure"], "languages_combined": [{"language": "cantonese", "language_level": ["good command"]}, {"language": "english", "language_level": ["good command"]}, {"language": "chinese", "language_level": ["good command"]}, {"language": "mandarin", "language_level": ["good command"]}]}, "experience_required": {"duration": ["at least 1 year"], "field": ["it", "relevant experience", "quality assurance"]}}, {"job_id": "100003009051016", "location_code": "hk", "company": "Watson's Wine", "job_title": "Senior Supply Chain Officer", "description": "Responsibilities:\n\nProofreading and manage the quality process of mobile apps project.\nConduct compliance awareness for the content review process and normalization.\nManage the accuracy and timely delivery of production and projects.\n\nRequirements:\n\nUniversity graduate in any discipline.\n1 year or above relevant experience.\nNative Chinese & English Speaker\nHong Kong PR; No remote working is allowed. It is a full-time job in Hong Kong", "employment_types": ["Full Time"], "selling_points": [], "locations": ["Shatin Area"], "categories": ["Transportation & Logistics", "Inventory / Warehousing", "Supply Chain"], "post_time": "2022-01-15T01:04:53Z", "salary": {"currency": null, "max": null, "min": null, "period": null, "term": null}, "salary_visible": false, "title_keywords": ["supply chain officer"], "responsibilities": ["compliance", "review", "proofreading", "quality"], "requirements": {"degrees": ["university graduate"], "majors": [], "languages": ["english", "chinese"], "language_level": ["native"], "hard_skills": ["no"], "soft_skills": [], "languages_combined": [{"language": "english", "language_level": ["native"]}, {"language": "chinese", "language_level": ["native"]}]}, "experience_required": {"duration": ["1 year"], "field": ["relevant experience"]}}, {"job_id": "100003009050177", "location_code": "hk", "company": "Everlink HR Consulting Limited", "job_title": "Senior Supply Chain Planner, APAC (Beauty Brand)", "description": "At Swarovski, where innovation meets inspiration, our people desire to explore, experience, and create. We are looking for a Procurement Excellence Manager where you will get a chance to work in a rewarding role within a diverse team that is pushing boundaries. Be part of a truly iconic global brand, learn and grow with us. We\u2019re bold and inventive, revealing astonishing things like no one else can. A world of wonder awaits you.\n\nAbout the job\n\nEnable SCB strategic procurement functions in strategic aspects of category management, supplier and risk management\n\nSupport Head of Procurement Excellence in defining the harmonized ways of working in strategic areas for entire function\n\nDefine the ways of working and framework for Supplier and Risk management using the market best practice approach\n\nSupport and guide on strategy definition within category management, monitor category strategy execution, manage tools for category strategy\n\nRepresent the voice of strategic procurement \u00a0and gather new functional requirements from strategic procurement functions towards tools and processes in given areas\n\nMonitor market procurement trends and best practice solutions available to optimize the ways of working and procurement strategy in given areas\n\nStrong alignment with leadership of procurement functions to support the strategy development\n\nAbout you\n\nWe are looking for a unique and amazing talent, who brings along the following:\n\nUniversity degree/ Education\n\nMinimum 5 years of professional experience in a similar role within an international setting\n\nKnowledge in strategic procurement processes, techniques, and approaches\n\nExperience in supplier and risk management\n\nStrong stakeholder management - ability to work effectively with all levels of the organization\n\nIndependent and strategic mindset\n\nExcellent English proficiency, presentation, and communication skills\n\nInnovative and creative approach whenever possible and can-do attitude\n\nBy applying this job, I understand and accept the principles of personal data protection, please visit the following link to find out more about Data Protection Consent Statement.\u00a0https://www.swarovskigroup.com/S/careers/data_protection_consent_statement.en.html\n\n\n\n\nAbout Swarovski\n\nSwarovski is a Wonderlab where magic and science meet.\n\nSwarovski unifies all parts of its organization under one spellbinding idea and brings forward a wondrous new world of crystal craftsmanship. Founded in 1895 in Austria, the company designs, manufactures and sells the world\u2019s highest quality crystal, genuine gemstones, Swarovski Created Diamonds and zirconia, jewelry, and accessories, as well as crystal objects and home accessories. Together with its sister companies Swarovski Optik (optical devices) and Tyrolit (abrasives), Swarovski Crystal Business forms the Swarovski Group.\n\nA responsible relationship with people and the planet has always been an integral part of Swarovski\u2019s heritage. This manifests today in the company\u2019s well-established sustainability agenda with youth-focused education programs and foundations to promote human empowerment and conserve natural resources to achieve positive social impact.", "employment_types": ["Full Time", "Permanent"], "selling_points": ["Supply Chain", "Regional Explorsure", "stock replenishment"], "locations": ["Not Specified"], "categories": ["Transportation & Logistics", "Others", "Fulfillment", "Supply Chain"], "post_time": "2022-01-14T09:54:32Z", "salary": {"currency": null, "max": null, "min": null, "period": "monthly", "term": null}, "salary_visible": false, "title_keywords": ["supply chain planner"], "responsibilities": ["management", "data", "procurement processes", "monitor", "quality", "communication", "personal data"], "requirements": {"degrees": ["university degree"], "majors": [], "languages": ["english"], "language_level": ["excellent", "proficiency"], "hard_skills": ["no", "html"], "soft_skills": ["work effectively", "communication skills", "independent", "creative", "responsible", "can-do attitude", "focused", "bold", "unique", "genuine", "diverse", "innovative", "leadership", "presentation", "positive"], "languages_combined": [{"language": "english", "language_level": ["proficiency", "excellent"]}]}, "experience_required": {"duration": ["minimum 5 years"], "field": ["risk management"]}}, {"job_id": "100003009054238", "location_code": "hk", "company": "Swarovski Hong Kong Ltd", "job_title": "Procurement Excellence Manager", "description": "Responsibilities\n\nCoordinate the entire order and delivery cycle as well as SOP processes include but not limited to order handling, delivery, inventory control, etc\nMaintain an accurate and up-to-date stock & inventory records in the system\nLiaise with internal and external stakeholders to handle incoming enquiries as well as logistics process\nAssist in ad hoc projects / tasks as required\nRequirements\n\nF.5 or above with minimum 4 years of working experience in logistics or warehouse. Preferably in FMCG industry\nEnergetic, well-organized, self-motivated, proactive, able to work independently & capable of working under pressure and meeting deadline\nGood command of written and spoken English and Chinese\nPC Knowledge in MS Excel, Word & PowerPoint and Chinese Processing\nFamiliar with SAP is highly preferred", "employment_types": ["Full Time", "Permanent"], "selling_points": ["Knowledge in strategic procurement processes", "Experience in supplier and risk management", "Strong stakeholder management"], "locations": ["Kowloon City"], "categories": ["Transportation & Logistics", "Supply Chain", "Merchandising & Purchasing", "Procurement / Purchasing / Sourcing"], "post_time": "2022-01-17T08:53:09Z", "salary": {"currency": null, "max": null, "min": null, "period": "monthly", "term": null}, "salary_visible": false, "title_keywords": ["manager"], "responsibilities": ["inventory", "coordinate", "inventory control", "maintain", "logistics", "ad hoc projects", "liaise with"], "requirements": {"degrees": [], "majors": [], "languages": ["english", "chinese"], "language_level": ["good command"], "hard_skills": ["sap", "fmcg industry", "word", "powerpoint", "ms excel", "pc knowledge", "processing"], "soft_skills": ["self-motivated", "proactive", "work independently", "capable", "under pressure", "well-organized", "energetic"], "languages_combined": [{"language": "english", "language_level": ["good command"]}, {"language": "chinese", "language_level": ["good command"]}]}, "experience_required": {"duration": ["minimum 4 years"], "field": ["logistics"]}}, {"job_id": "100003009053507", "location_code": "hk", "company": "The French Chamber of Commerce and Industry in HK", "job_title": "Functional Consultant", "description": "Responsibilities:\n\nInput data into Database\nUpdate data file with in Excel\u00a0\nPrepare & co-ordinate with clients for delivery arrangement & documents\nFollow up with clients instruction & provide stock availability & shipping information to stores/warehouse\n\nRequirements:\n\nExcellent in Excel Skills\u00a0\u00a0IS A MUST!\u00a0\nFamiliar with (Pivot Table and V Lookup) IS A MUST!\u00a0\n\nCould read simplified Chinese \u80fd\u95b1\u8b80\u7c21\u9ad4\u5b57\nProficiency in PC operations including Word, Excel, fast accurate input Chinese.\nAble to read English and reply email.\nPassed in Eng. Subject DSE/HKCEE\u00a0\nWith at least 2 years relevant warehouse and logistics clerical experience\nWell-organised and attentive to details; Stable working history\nImmediately available /short notice is preferred.\n\nWORKING LOCATION: TUEN MUN\n5 days work\n12 days AL\n\n\u00a0\u00a0\nSalary \u00a0\u00a0\u00a0\u00a0: \u00a0Negotiable\n\nInterested parties please send your full resume with job description and expected salary to us.", "employment_types": ["Full Time", "Permanent"], "selling_points": ["Logistics solution platform", "Customer Service", "Friendly working environment"], "locations": ["Central"], "categories": ["Information Technology (IT)", "Technical / Functional Consulting", "Transportation & Logistics", "Freight Forwarding", "Supply Chain"], "post_time": "2022-01-17T07:04:28Z", "salary": {"currency": null, "max": null, "min": null, "period": "monthly", "term": null}, "salary_visible": false, "title_keywords": ["consultant"], "responsibilities": ["shipping", "co-ordinate with clients", "database", "data"], "requirements": {"degrees": ["dse"], "majors": [], "languages": ["english", "chinese"], "language_level": ["proficiency"], "hard_skills": ["excel", "pivot table", "pc operations", "word"], "soft_skills": ["well-organised", "stable", "accurate", "attentive to details"], "languages_combined": [{"language": "english", "language_level": []}, {"language": "chinese", "language_level": ["proficiency"]}]}, "experience_required": {"duration": ["at least 2 years"], "field": ["logistics", "clerical"]}}, {"job_id": "100003009054753", "location_code": "hk", "company": "Powertek Group Co., Limited", "job_title": "Assistant Office Supervisor", "description": "Task & Responsibilities:\n\u2022 Prepare invoice / delivery note / packing list, etc\n\u2022 Handle shipping arrangement and document\n\u2022 Provide clerical support to the Logistic Department\n\u2022 Organize and assign proper manpower\n\u2022 Uphold a positive working mentality across the team\n\u2022 To assist other ad-hoc projects as assigned\n\nQualifications and Experience:\n\u2022 Diploma / Associate Degree or related disciplines\n\u2022 At least 3~5 years solid relevant experience\n\u2022 Familiar with \u201cTradelink\u201d for custom declaration, ERP system, BarTender software\n\u2022 Good command of written and spoken English, Chinese and Putonghua\n\u2022 Proficient in using MS Office (especially in Excel)\n\u2022 Familiar with Chinese typing\n\u2022 Good analytical, decision making and problem solving skills, responsible, well organized and a fast learner\n\u2022 Strong communication and leadership skills\n\u2022 Willing to work overtime when necessary and able to work under pressure\n\u2022 Immediately availability preferred\n\nInterested parties please send full resume with present and expected salary to us.\n(All information collected will be used for recruitment purpose only)", "employment_types": ["Full Time"], "selling_points": [], "locations": ["Kwun Tong"], "categories": ["Transportation & Logistics", "Inventory / Warehousing", "Shipping", "Supply Chain"], "post_time": "2022-01-17T10:53:55Z", "salary": {"currency": null, "max": null, "min": null, "period": "monthly", "term": null}, "salary_visible": false, "title_keywords": ["supervisor", "assistant"], "responsibilities": ["provide clerical support", "shipping", "software", "tradelink", "invoice", "custom declaration", "packing list", "communication", "ad-hoc projects", "work under pressure"], "requirements": {"degrees": ["associate degree", "diploma"], "majors": ["related disciplines"], "languages": ["putonghua", "english", "chinese"], "language_level": ["good command"], "hard_skills": ["excel", "typing", "erp system", "problem solving skills", "ms office"], "soft_skills": ["work overtime", "responsible", "work under pressure", "leadership skills", "well organized", "communication", "problem solving skills", "fast learner", "positive", "decision making"], "languages_combined": [{"language": "putonghua", "language_level": ["good command"]}, {"language": "english", "language_level": ["good command"]}, {"language": "chinese", "language_level": ["good command"]}]}, "experience_required": {"duration": ["at least 3~5 years"], "field": ["relevant experience"]}}, {"job_id": "100003009052474", "location_code": "hk", "company": "Foodgears Industrial International Limited", "job_title": "Import & Export Officer", "description": "Job Duties:\n\nHandle full set of import & export shipping documents (e.g. L/C, D/P, D/A, T/T)\nCommunicate and liaise with forwarder / logistic company / warehouse\nHandle order processing and shipment schedule\nApply import permit from Government (FEHD) / Trade and Industry Dept.\nData entry by using the company system\n\n\u00a0Requirements:\n\nDiploma or above with 3 years relevant experience in supply chain / logistics / shipping field\nGood command of Cantonese, English, and Mandarin\nProficiency in MS Word, Excel & Chinese Word Processing\nContributes to the development of processes & procedures\nStrong communication & coordinating capability\nGood knowledge of L/C and banking document, Tradelink system\n\n\n\nRemuneration:\n\n5 working days\nBank holidays\nDouble pay\nDental & medical coverage\n\n\n\nWe offer attractive remuneration package to the right candidate.\u00a0 Interested parties please send full resume with present & expected salary and available date by clicking \"Apply Now\"\n\n\n\nAll personal data collected will be used for recruitment purpose only.", "employment_types": ["Full Time", "Permanent"], "selling_points": [], "locations": ["Wong Tai Sin Area"], "categories": ["Transportation & Logistics", "Freight Forwarding", "Shipping", "Supply Chain"], "post_time": "2022-01-17T03:07:20Z", "salary": {"currency": null, "max": null, "min": null, "period": "monthly", "term": null}, "salary_visible": false, "title_keywords": ["officer"], "responsibilities": ["data entry", "import & export shipping documents", "schedule", "order processing", "liaise with"], "requirements": {"degrees": ["diploma or above"], "majors": [], "languages": ["cantonese", "english", "chinese", "mandarin"], "language_level": ["proficiency", "good command"], "hard_skills": ["excel", "c", "chinese word processing", "ms word"], "soft_skills": ["communication"], "languages_combined": [{"language": "cantonese", "language_level": ["good command"]}, {"language": "english", "language_level": ["good command"]}, {"language": "chinese", "language_level": ["proficiency"]}, {"language": "mandarin", "language_level": ["good command"]}]}, "experience_required": {"duration": ["3 years"], "field": ["supply chain", "logistics", "relevant experience"]}}, {"job_id": "100003009056303", "location_code": "hk", "company": "CEVA Logistics (Hong Kong) Limited", "job_title": "Ocean Freight Coordinator", "description": "Job Responsibilities\n\nResponsible for Handle full set of import customer service and documentation\nContact co-loader and carrier to obtain shipment arrival and payment\nPrepare documents and payment to exchange the delivery order with co-loader and carrier before the vessel arrives\nResponsible to provide arrival notice, invoice, delivery order to consignee in timely manner\nPrepare monthly customer report and achieve customer KPI\nCoordinate with co-loader and subcontractor for door delivery\nComplete the company and customer KPI within timeframe\n\nJob Requirements\n\nF.5 or DSE or\u00a0 above\nRelevant working experience in sea freight forwarding industry is an advantage\nExperience in handling full set of Ocean Import flow and Cargowise is an advantage\nCandidates with less working experience would also be considered\nGood communication skills and able to work independently under pressure\nGood command in written and spoken English and Mandarin\nProficient in the use of Microsoft Word and Excel\nSelf-motivated and Responsible\u00a0\n\nWe offer attractive remuneration packages to the right candidates. Interested parties, please send your FULL resume with CURRENT and EXPECTED SALARY by clicking \"APPLY NOW\". For further information of our company, please visit our website: http://www.cevalogistics.com.\u00a0\u00a0", "employment_types": ["Full Time", "Permanent"], "selling_points": ["Ocean Freight", "Fresh graduate will be considered", "Self-motivated and Responsible"], "locations": ["Kowloon Bay"], "categories": ["Sales, CS & Business Devpt", "Customer Service - Supervisor / Officer", "Transportation & Logistics", "Freight Forwarding", "Supply Chain"], "post_time": "2022-01-18T03:53:19Z", "salary": {"currency": null, "max": null, "min": null, "period": null, "term": null}, "salary_visible": false, "title_keywords": ["coordinator"], "responsibilities": ["invoice", "coordinate with", "payment", "customer service", "contact", "documentation", "prepare documents", "report"], "requirements": {"degrees": ["dse"], "majors": [], "languages": ["english", "mandarin"], "language_level": ["good command"], "hard_skills": ["excel", "microsoft word"], "soft_skills": ["communication skills", "work independently", "self-motivated", "under pressure", "responsible"], "languages_combined": [{"language": "english", "language_level": ["good command"]}, {"language": "mandarin", "language_level": ["good command"]}]}, "experience_required": {"duration": [], "field": ["relevant working experience"]}}, {"job_id": "100003009052744", "location_code": "hk", "company": "The Hongkong Electric Co., Ltd", "job_title": "Assistant Manager (Inventory Control) (Ref. No.  GCD-GS-AMIC-JD)", "description": "Responsibilities :\n\n\n\nReporting to the Manager (Process & Inventory Control), the appointee will mainly perform the following responsibilities:\n\n\nTo perform inventory analysis, identify the improvement areas, monitor the inventory level and perform stock allocation\nTo work with internal and external parties for the lead time reduction arrangement of bulky stock item\nTo conduct storage space utilisation review, report the utilisation rate, as well as plan and execute inventory cycle count related activities\nTo participate in warehouse utilisation optimisation projects\n\nRequirements:\n\n\nBachelor Degree in Logistics Management, Business Administration, Operations Management, Industrial Engineering or related disciplines\nA minimum of 8 years\u2019 relevant work experience in logistics management or inventory planning and control\nFamiliar with MS Office, MS Project and MS Visio\nHands-on experience in using warehouse management systems or SAP system preferred\nGood command of English and Chinese languages, both spoken and written\n\nCandidate with less relevant experience may also be considered for the position of Senior Officer (Inventory Control).\n\nWorking Location :\u00a0Ap Lei Chau, transportation to be provided\n\nApplication :\n\nIf you are interested in this position, please send your resume\u00a0(in PDF format)\u00a0with details of qualification, experience, present and expected salaries, and contact number \u00a0to the\u00a0Human Resources Division, The Hongkong Electric Co., Ltd. on or before 31\u00a0January 2022\u00a0and quote the reference number in your application. Please also visit our website to know more about our Company http://www.hkelectric.com.\n\nApplicants not invited for interview within one month from the closing date may consider their applications unsuccessful. All unsuccessful applications will be kept for six months after the date of this advertisement.\n\nWe are an equal opportunity employer.\u00a0 Personal data provided by job applicants will be treated in strictest confidence and used only for recruitment-related purposes in accordance with the laws and ordinance of the HKSAR.", "employment_types": ["Full Time", "Permanent"], "selling_points": ["To perform inventory analysis", "To conduct storage space utilisation review", "A minimum of 8 years\u2019 relevant work experience"], "locations": ["Aberdeen"], "categories": ["Transportation & Logistics", "Others", "Inventory / Warehousing", "Supply Chain"], "post_time": "2022-01-17T03:53:57Z", "salary": {"currency": null, "max": null, "min": null, "period": "monthly", "term": null}, "salary_visible": false, "title_keywords": ["assistant manager"], "responsibilities": ["reporting", "stock allocation", "inventory", "analysis", "monitor", "internal and external parties", "review", "cycle count", "inventory control", "plan", "report"], "requirements": {"degrees": ["degree", "bachelor"], "majors": ["related disciplines", "business administration", "engineering"], "languages": ["english", "chinese"], "language_level": ["good command"], "hard_skills": ["ap", "sap", "ms office"], "soft_skills": ["hands-on", "interested in", "confidence"], "languages_combined": [{"language": "english", "language_level": ["good command"]}, {"language": "chinese", "language_level": ["good command"]}]}, "experience_required": {"duration": ["minimum of 8 years"], "field": ["management", "inventory control", "relevant experience", "logistics", "warehouse management", "human resources", "planning"]}}, {"job_id": "100003009052163", "location_code": "hk", "company": "Arvato Services Hong Kong Limited", "job_title": "Key Account Management Manger (Supply Chain/ Logistics Industry)", "description": "YOU are invited to our team!\n\nWhat we offer?\nWell-developed Oversea and Local Training program\nInternational Exposure\nWork-life balance with friendly working environment\nPromotion Opportunities\nGreat benefit scheme: Flexible Benefit, Birthday, Exam and Child Care Leave\nDo not hesitate! Join Us Now!\n\nPosition Summary\n\nSupport ongoing contractual relationships and the operational delivery of services to a defined customer base or a group of accounts and serve as the primary point of contact with clients to ensure client satisfaction.\u00a0 Directly report to our Head of HK.\n\n\nJob Responsibilities:\n\nTake full ownership\u00a0of Company or customer initiated projects;\u00a0Communicate with global colleagues, global customers, manage customer escalations and drive initiative for continuous process improvement and maintain a good relationship with them.\nMaximize revenue, Review and Optimize cost base (cost driver analysis and close feedback loop to local teams);\u00a0Account P&L ownership including Invoicing/Forecasting/Budgeting.\nResponsible for KPI & SLA monitoring and performance reporting (MBR/QBR);\u00a0Support in any RFQ and RFP as assigned.\nEscalation handling with root cause, corrective action & status updates and\u00a0Ensure common standards / SOPs across sites throughout the region.\nMulti-task across different customers/programs and work with cross functional teams on deliverable and\u00a0Responsible for Account Audits / Reviews / Development Plan.\nCoordination of ad hoc requests, problem resolution and improvement initiatives with functional departments in all relevant sites.\n\nJob Requirements:\n\nDegree holder in Supply Chain Management, Business Administration or related discipline.\nAt least 7 years work experience in Logistics and Supply Chain Management.\nGood communication and interpersonal skills in both English and Chinese.\nExcellent command of PC knowledge including Excel and PowerPoint.\nExperience in SAP is a plus\nAble to work multi-task in a tight deadline.\n\nCompetitive remuneration package will be offered to the right candidate. It is also an excellent career opportunity to lean the end-to-end business and operation processes of a modern distribution center in a fast pace international environment.\n\nInterested parties please apply by submitting resume with career details, expected salary and contact information to HR Department.\u00a0We are an equal opportunities employer; all personal data will be treated in strict confidential and for recruitment purpose only.", "employment_types": ["Full Time"], "selling_points": ["MNC with regional setup", "Exciting development opportunities", "Excellent team culture"], "locations": ["Tuen Mun Area"], "categories": ["Sales, CS & Business Devpt", "Business Development", "Transportation & Logistics", "Supply Chain", "Account Servicing"], "post_time": "2022-01-17T02:18:16Z", "salary": {"currency": null, "max": null, "min": null, "period": "monthly", "term": null}, "salary_visible": false, "title_keywords": ["logistics"], "responsibilities": [], "requirements": {"degrees": [], "majors": [], "languages": [], "language_level": [], "hard_skills": [], "soft_skills": [], "languages_combined": []}, "experience_required": {"duration": [], "field": []}}, {"job_id": "100003009055911", "location_code": "hk", "company": "Randstad Hong Kong Limited", "job_title": "Order Management Specialist", "description": "about the company.\nOur client is an electronics company with a great reputation around the globe. They are the market leader in the industry and serve the most well-known corporate clients. In the meantime, they are constantly reinventing and challenging themselves to keep ahead of consumer demands and remain competitive. Currently they are hiring an Order Management Specialist in the team.\n\nabout the job.\nAs an Order Management Specialist in the team, you will be responsible for\n-Performing order fulfilment related tasks\n-Liaising with factories, customers and freight forwarders for order-to-cash process\n-Monitoring order status and delivery performance\n-Planning and managing logistics activities from factories to China market\n-Preparing and analysing data to achieve quality and efficiency\n-Performing other ad-hoc duties as assigned\n\nskills & experiences required.\n-Diploma from logistics/supply chain or any relevant discipline\n-Minimum 3 years of working experience in logistics/shipping/supply chain\n-Candidates from electronics/FMCG industry are highly preferred\n-Fluent mandarin is a must\n-Flexible, logical thinking, hands-on\n\nabout the benefits.\nOur client offers an attractive salary package. They also offer\n-5 day work; 9-6\n-Double Pay\n-Bonus (Up to 2-3 Months)\n-Convenient location\n-Work life balance\n-Career Progression\n\nIf you're interested in this role, click 'apply now' to forward an up-to-date copy of your CV, or call Sally LO at 2232 3496.\nIf this is not your ideal job but you are looking out, please contact us for a discussion on your career preferences.", "employment_types": ["Full Time", "Permanent"], "selling_points": ["Market leader in the industry", "Regional office in Hong Kong", "Young and dynamic working culture"], "locations": ["Not Specified"], "categories": ["Transportation & Logistics", "Inventory / Warehousing", "Supply Chain", "Public Transportation"], "post_time": "2022-01-18T03:04:43Z", "salary": {"currency": null, "max": null, "min": null, "period": "monthly", "term": null}, "salary_visible": false, "title_keywords": ["specialist"], "responsibilities": ["order management", "shipping", "data", "quality", "logistics", "ad-hoc duties"], "requirements": {"degrees": [], "majors": [], "languages": ["mandarin"], "language_level": [], "hard_skills": ["fmcg industry"], "soft_skills": ["hands-on", "responsible", "ad-hoc duties"], "languages_combined": [{"language": "mandarin", "language_level": []}]}, "experience_required": {"duration": ["3 years"], "field": ["supply chain", "logistics"]}}, {"job_id": "100003009055708", "location_code": "hk", "company": "Michael Page", "job_title": "Business Development Manager- Logistics / 3PL", "description": "Our client is a world leading 3PL. They are looking for a Business Development Manager (Logistics) to join their young and dynamic team.\n\nClient Details\n\nOur client is a world leading 3PL. It provides diverse supply chain and logistics products and services. They are looking for a Business Development Manager to join their young and dynamic team.\n\nDescription\n\nResponsible for account management for the company.\nCommunicate with new and existing customers, understand market needs and therefore able to provide the best fit solutions and services to the customers.\nEstablish excellent relationships with internal stakeholders and top management to improve efficiency.\n\nProfile\n\n6 -8 years of sales experience in the logistics, 3PL or freight forwarding industry.\nYou must have a proven sales track record of business growth.\nYou must have a great business mindset and the ability to develop long-term partnerships with clients and partners.\nThis candidate needs to have strong connection with clients.\nExcellent communication in both Cantonese, Mandarin and English is mandatory.\n\nJob Offer\n\nThe company offers attractive remuneration package. Also the company has dynamic culture and great opportunities for career development.\n\nTo apply online please click the 'Apply' button below. For a confidential discussion about this role please contact Phoebe Leung on +852 3412 4853.", "employment_types": ["Full Time", "Permanent"], "selling_points": ["A well known logistics company", "Business Development", "Logistics industry"], "locations": ["Not Specified"], "categories": ["Transportation & Logistics", "Freight Forwarding", "Supply Chain", "Sales, CS & Business Devpt", "Account Servicing"], "post_time": "2022-01-18T02:52:22Z", "salary": {"currency": null, "max": null, "min": null, "period": "monthly", "term": null}, "salary_visible": false, "title_keywords": ["business development manager", "logistics"], "responsibilities": ["communicate with", "management", "develop", "communication", "logistics", "contact", "career development"], "requirements": {"degrees": [], "majors": [], "languages": ["cantonese", "english", "mandarin"], "language_level": ["excellent"], "hard_skills": ["dynamic"], "soft_skills": ["communication", "diverse", "dynamic", "responsible"], "languages_combined": [{"language": "cantonese", "language_level": ["excellent"]}, {"language": "english", "language_level": ["excellent"]}, {"language": "mandarin", "language_level": ["excellent"]}]}, "experience_required": {"duration": ["6 -8 years"], "field": ["logistics"]}}, {"job_id": "100003009056364", "location_code": "hk", "company": "IKEA", "job_title": "Fulfilment Development & Multichannel Network Manager, North Asia", "description": "WHY YOU WILL LOVE US\n\nWe\u2019re a diverse group of down-to-earth, straightforward people with a passion for home furnishing. We come from all over the world, but we share an inspiring vision: \u201cto create a better everyday life for the many people\u201d. How we realize this vision is based on our shared humanistic values. These values guide our work and build our inclusive, open and honest culture. It\u2019s all based on a spirit of togetherness and enthusiasm. We work hard, but we have fun doing it. We\u2019re always looking for people who share our positive attitude and values.\n\nWHY WE WILL LOVE YOU\n\nYou have a University degree (Economics, Logistics, Supply Chain Management) or proven performance in logistics/commercial/supply chain management 4-6 years working experience in a management position (preferable in distribution, retail, logistics or similar)\nYou have proven successful leadership in a big organisation, delivering both business result and people development\nYou have the interest and experience in retail/ home furnishing/ supply chain/ customer service\nYou have experience of working as a management team member with proven ability to make a difference by positively influencing the business directly as well as through good collaboration\nYou have experience in securing the implementation of mid-term and long-term strategies and plans and set/follow up goals\nYou have proven ability to have a high level of influence in a matrix organisation\nYou have successfully led projects or processes on country/market/national level\n\nWHAT YOU WILL BE DOING DAY TO DAY\n\nContribute to the development of tools, processes and ways of working in co-creation with the groups function and take accountability for the market implementation of globally developed of tools, processes and ways of working to enable the design, establishment and continuous development of an efficient, effective and end to end multichannel distribution network on the market\nAccountable for defining the Fulfilment Development Roadmap on the market in tune with the evolving market benchmarks to enable IKEA results and succeed in a multichannel environment\nAccountable for organising communication and reporting of progress towards all relevant stakeholders through all stages of the multichannel network and development project(s) and taking needed actions to secure the readiness\nAccountable for preparing the investment request connected to Customer Fulfilment investments and the investment budget on the market level including securing all required support to market counterparts\nAccountable for providing business cases and enabling the implementation of development and innovation solutions\nAccountable for the testing of new technical/automated solutions in the fulfilment units and service fulfilment\nAccountable for keeping the total picture of fulfilment development and multichannel network together and synchronised on the market including capturing ideas from within the company\nAccountable for securing development and innovation of fulfilment units and service fulfilment through identifying, evaluating and scaling best practices within IKEA and through setting the right priorities based on input from market and group level, industry intelligence and benchmarking\nResponsible for the cooperation with key partners on within and outside of retail while contributing with both knowledge and resources to optimal operational and multichannel development, sourcing activities as well as to all matrices, global and market initiatives and competence networks\nAccountable to lead, coach and develop the Market Development and Multichannel Network\u00a0organisation\n\nTOGETHER AS A TEAM\n\nCustomer Fulfilment (CFF) is a fundamental part in making IKEA multichannel retailing in reality. CFF acts as a fully integrated, process-oriented organization with an end-to-end approach to develop our business and deliver results across functions together with our partners. We are focusing on providing seamless shopping experience with great quality in all touchpoints for the many.\n\nSTAFF BENEFITS\n\nAnnual Fixed Bonus, 5-Day Work Week, 17 days Public Holiday, Paid Leave (Paid Annual Leave, 14 weeks Maternity Leave, 5 days Paternity Leave, 1 week Marriage Leave), Employee Medical Coverage, Non-Contributory Retirement Plan, Staff Purchase Discount, Birthday Coupon, Referral Bonus, Excellent Career Path\n\nPersonal data collected will be kept and handled confidentially by authorized personnel for recruitment purposes only. It might also be disclosed to our subsidiaries, associates and agencies authorized to process the information for appointment. The Company will retain the applications of candidates not selected for a maximum period of 24 months after the selection process is finalized. Our Personal Information Collection Statement (PICS) is available at our career site and can be provided upon request by contacting our Human Resources Department. Applicants not heard from us within six weeks may consider their applications filed for future reference.\n\nIssued by The Dairy Farm Company, Limited\n\n\n", "employment_types": ["Full Time", "Permanent"], "selling_points": ["Report to Head of Customer Fulfilment, North Asia", "Defining the Fulfilment Development Roadmap", "Multichannel network and development projects"], "locations": ["Shatin Area"], "categories": ["Transportation & Logistics", "Others", "Fulfillment", "Supply Chain"], "post_time": "2022-01-18T04:05:49Z", "salary": {"currency": null, "max": null, "min": null, "period": "monthly", "term": null}, "salary_visible": false, "title_keywords": ["manager"], "responsibilities": ["management team", "management", "reporting", "ideas", "budget", "quality", "implementation", "design", "testing", "communication", "develop", "customer service", "logistics", "plans"], "requirements": {"degrees": ["university degree"], "majors": ["economics"], "languages": [], "language_level": [], "hard_skills": ["make", "fun"], "soft_skills": ["efficient", "accountability", "passion for", "responsible", "accountable", "positive attitude", "diverse", "communication", "customer service", "inspiring", "honest", "organisation", "team member", "leadership"], "languages_combined": []}, "experience_required": {"duration": ["4-6 years"], "field": ["management", "supply chain", "management position", "commercial", "customer service", "logistics", "business", "retail", "team"]}}, {"job_id": "100003009052152", "location_code": "hk", "company": "Arvato Services Hong Kong Limited", "job_title": "Business Development Manager (Logistics/ Supply Chain Industry)", "description": "YOU are invited to our team!\n\nWhat we offer?\nWell-developed Oversea and Local Training program\nInternational Exposure\nWork-life balance with friendly working environment\nPromotion Opportunities\nGreat benefit scheme: Flexible Benefit, Birthday, Exam and Child Care Leave\nDo not hesitate! Join Us Now!\n\nHunt for new business with primary focus on value added logistics, warehousing, retail distribution and end-to-end supply chain solutions. Support regional clients global inquiries by cooperating with global colleagues.\u00a0\nWork with Business Development, Marketing, Solution Design and Logistics Engineering on creation of competitive concept proposals and develop new service offerings based on detailed and documented insight of market and client needs.\nManage and maintain a structured analysis of target clients and documentation in CRM system.\u00a0\nProvide market intelligence and feedback to the Global and Regional teams on market & industry developments and competitors\u2019 developments\nJob Requirement:\n\nBachelor degree holder, specialized in SCM related disciplines will be advantageous\nFluent in written and spoken Cantonese, Mandarin & English\u00a0\nHighly self-motivated and success-driven professional with 10+years of experience in solution selling & new business development (logistics / supply chain management)\nVery good understanding of logistics requirements and logistics solutions incl. warehouse design and according commercial experiences\nExperience with working in multicultural teams and willingness to constantly learn\nExcellent communication, interpersonal and team leadership skills\nAbility to develop \u201crapport\u201d with both internal and external customers\n\nCompetitive remuneration package will be offered to the right candidate. It is also an excellent career opportunity to lean the end-to-end business and operation processes of a modern distribution center in a fast pace international environment.\n\nInterested parties please apply by submitting resume with career details, expected salary and contact information to HR Department.\u00a0We are an equal opportunities employer; all personal data will be treated in strict confidential and for recruitment purpose only.\n\n\n\n", "employment_types": ["Full Time"], "selling_points": ["Hunt and acquire new business with new accounts.", "Support in expanding sales", "Manage and maintain a structured analysis"], "locations": ["Tuen Mun Area"], "categories": ["Transportation & Logistics", "Others", "Sales, CS & Business Devpt", "Business Development", "Supply Chain"], "post_time": "2022-01-17T02:16:39Z", "salary": {"currency": null, "max": null, "min": null, "period": "monthly", "term": null}, "salary_visible": false, "title_keywords": ["business development manager", "logistics"], "responsibilities": [], "requirements": {"degrees": [], "majors": [], "languages": [], "language_level": [], "hard_skills": [], "soft_skills": [], "languages_combined": []}, "experience_required": {"duration": [], "field": []}}, {"job_id": "100003009055002", "location_code": "hk", "company": "Finder Technology Limited", "job_title": "Warehouse Clerk  (5 Days Work)", "description": "TQM Consultants Co. Limited, a well-established top-tier management consulting firm based in Hong Kong, provides a wide spectrum of consultancy services with extensive experience in various business and industrial sectors.\n\nWe are the market leader of management systems in Hong Kong, sharing 70% of the HKSAR Government/ Public Sector\u2019s Management System Consultancy and Training assignments.\n\nhttp://www.tqm.com.hk\n\nJob Detail\n\nParticipate in process improvement, quality improvement and safety/environmental/energy management project\nPrepare work proposal and project documentation\nCoordinate with various teams in the company to achieve project goals\nRegularly and timely follow up with the customer needs and objectives\nHandle ad hoc projects as assigned\nEnsure high-quality customer services are provided at all times\n\nRequirements\u00a0\n\nGraduates\u00a0(years 2020\u00a0onwards)\u00a0with good honour Degree in\u00a0Logistics and Transportation Engineering Discipline\nHolders\u00a0of Hong Kong identity card\nGood interpersonal, communication & presentation skills\nGood command of English and Chinese, both spoken and written\n\nWhy us?\n\nOfferthe\u00a0HKIE Graduate Training Scheme 'A'\u00a0in\u00a0Logistics and Transportation Discipline(LTE)\n2-year Scheme \u2018A\u2019 trainee + 2-year working to become a registered professional engineer! (6 YEARS for Non-scheme A)\nMarket-leading remuneration package (13-month pay with annual bonus and Medical, Telecom, and Training allowance)\nWork-life Balance (5-day workweek (09:00-17:30) and 2 weeks of paid ALs)\nRegular Team Building Activities\nProfessional advice and coaching regularly\n\nHow to apply? Learn more at https://www.tqm.com.hk/scheme-a", "employment_types": ["Full Time", "Permanent"], "selling_points": [], "locations": ["Chai Wan"], "categories": ["Transportation & Logistics", "Inventory / Warehousing", "Shipping", "Supply Chain"], "post_time": "2022-01-17T16:22:55Z", "salary": {"currency": null, "max": null, "min": null, "period": "monthly", "term": null}, "salary_visible": false, "title_keywords": ["warehouse clerk"], "responsibilities": ["management", "consulting", "systems", "quality", "coordinate with", "teams", "customer services", "communication", "ad hoc projects", "logistics", "project documentation"], "requirements": {"degrees": ["degree"], "majors": ["engineering"], "languages": ["english", "chinese"], "language_level": ["good command"], "hard_skills": ["documentation", "hkie", "scheme"], "soft_skills": ["timely", "communication", "presentation skills", "extensive", "interpersonal"], "languages_combined": [{"language": "english", "language_level": ["good command"]}, {"language": "chinese", "language_level": ["good command"]}]}, "experience_required": {"duration": [], "field": ["management", "business", "consulting"]}}, {"job_id": "100003009046892", "location_code": "hk", "company": "Avalon Steritech Limited", "job_title": "Senior Supply Chain Officer", "description": "Company,\u00a0E/I agent situated in Chai Wan, with business mainly in the field of electronic components parts is looking for\u00a0a suitable candidate with good potential\u00a0to\u00a0fill the following vacancy:\n\n\u00a0Responsibilities:\n- Visual inspection and incoming handling of inbound goods\n- Input and manage relevant goods information in the company software system\n- Outbound cargo shipments preparation\n- Communication with courier services, forwarders and cargo agents\n- Able to handle I/E documentation when it is required\n\nRequirements:\n- Form 5 or higher\n- At least 2 years of overall working experience\n- Job experience with handling of electronic parts and components is an advantage\n- Responsible and stable, willing to work overtime, when it is required\n-\u00a0Acceptable command in English to communicate with colleagues and agents\n- It is preferred an immediately available candidate\n\nCandidate please send full resume and salary expectation\n\n", "employment_types": ["Full Time"], "selling_points": ["Supply chain, Logistics, Business Development", "15AL, Flexible working hours, 5 day work week", "Group Medical, Dental"], "locations": ["Tuen Mun Area"], "categories": ["Transportation & Logistics", "Inventory / Warehousing", "Shipping", "Supply Chain"], "post_time": "2022-01-14T01:38:20Z", "salary": {"currency": null, "max": null, "min": null, "period": "monthly", "term": null}, "salary_visible": false, "title_keywords": ["supply chain officer"], "responsibilities": ["software", "inspection", "communication", "visual", "documentation"], "requirements": {"degrees": ["form 5"], "majors": [], "languages": ["english"], "language_level": [], "hard_skills": [], "soft_skills": ["stable", "work overtime", "responsible"], "languages_combined": [{"language": "english", "language_level": []}]}, "experience_required": {"duration": ["at least 2 years"], "field": []}}, {"job_id": "100003009053937", "location_code": "hk", "company": "Shopline Limited", "job_title": "Logistics Account Manager", "description": "Avalon SteriTech strives to provide next-generation cleaning, disinfection and sterilization technology infrastructure for public spaces.Led by a diverse team of world-class scientists, medical doctors, academic advisors and business professionals, we are able to use our knowledge and market insights to deliver customized solutions that address unmet public health needs.\n\nResponsibilities:\n\nResolve shipping and logistics issues independently to achieve on-time delivery at a reasonable cost\nMonitor shipping and logistics arrangement and keep track of shipment status\nEnsure invoice/Customs documentation meets the requirement of destination countries\nResponsible for handling orders, processing and preparing relevant documents e.g. delivery note, invoice, and arranging delivery\nCoordinate with internal parties for inventory planning, stock control, goods allocation and logistics arrangement\nManage the stock movement, maintain up-to-date stock record in the system, and provide regular report for management\nWork closely with Finance Team for billing administration\nLiaise with end user on goods return, damaged and claims\nIdentify and work with logistics partners in different countries\nSupport ad hoc projects and assignments when required\n\nRequirements:\n\nBachelor degree holder or above in logistics management, business management or supply chain management related disciplines\nMinimum 5 years of relevant experience, preferably in manufacturing industry\nKnowledgeable in handling I/E shipping documents and L/C if required\nSolid experience in handling dangerous goods DG packaging and shipment\nProactive team player with good communication, problem solving skills\nProficient with MS Office including Excel, Outlook, Word, Powerpoint\nExperience in SAP system will be an advantage\nGood command of spoken and written English, Cantonese and Mandarin", "employment_types": ["Full Time", "Permanent"], "selling_points": ["Work in a team to achieve assigned sales target", "Sales/Account management in Logistics field", "Attractive package and benefits"], "locations": ["Sheung Wan"], "categories": ["Transportation & Logistics", "Others", "Supply Chain"], "post_time": "2022-01-17T07:48:05Z", "salary": {"currency": null, "max": null, "min": null, "period": "monthly", "term": null}, "salary_visible": false, "title_keywords": ["logistics account manager"], "responsibilities": ["administration", "cost", "shipping", "inventory planning", "control", "management", "logistics arrangement", "invoice", "monitor", "coordinate with", "liaise with", "maintain", "logistics", "finance team", "ad hoc projects", "documentation", "internal parties", "report"], "requirements": {"degrees": ["bachelor degree holder"], "majors": ["related disciplines", "business"], "languages": ["cantonese", "english", "mandarin"], "language_level": ["good command"], "hard_skills": ["business management", "excel", "sap", "word", "powerpoint", "c", "outlook", "problem solving skills", "ms office"], "soft_skills": ["communication", "team player", "proactive", "problem solving skills"], "languages_combined": [{"language": "cantonese", "language_level": ["good command"]}, {"language": "english", "language_level": ["good command"]}, {"language": "mandarin", "language_level": ["good command"]}]}, "experience_required": {"duration": ["minimum 5 years"], "field": ["relevant experience", "manufacturing industry"]}}, {"job_id": "100003009053739", "location_code": "hk", "company": "HelloKids Education Limited", "job_title": "Native English Teacher (Full-time) - Tuen Mun", "description": "SHOPLINE is Asia\u2019s largest smart commerce platform. With our customers in mind, we strive to deliver scalable commerce solutions to merchants of all sizes. We\u2019re a full-featured platform with services including online store opening, O2O solution, retail POS systems, advertising placement, business strategy consultation, marketing, and more to empower merchants to succeed in omnichannel retailing and cross-border commerce.\n\nWHAT YOU'LL BE DOING:\n\nDevelops sales plans, strengthens customer relationships and insures market objectives are met.\nAttains or exceeds revenue targets.\nSchedules regular agent and customer visits.\nDevelops new customers, identifies customer needs and presents sales solutions.\nMaintains contact with existing customers to facilitate new sales and repeat contracting for existing business\nDevelops sales presentation and material consistent within business units.\nProvides competitor information to management.\nCollects prioritized product/service requirements and communicates them to Product team\n\nWHO WE ARE LOOKING FOR:\n\nBachelor\u2019s degree or equivalent;\n3+ years of comprehensive technical, direct sales and marketing experience for the E-commence Logistics sector\nConsultative selling experience.\nOutstanding presentation and communication skills.\nAbility to make complex decisions and customer commitments in real-time.\nAbility to build strong relationships with 3PL\nAbility to effectively promote the use of the company\u2019s technology with potential clients\nAbility to both develop and close opportunities\nStrong team player and experience working with all levels of the organization.\nWHY YOU SHOULD JOIN US:\n\n\nWe work in a fun, collaborative open space where we encourage creativity and ideas flow freely.\nYou\u2019ll be able to steer the future roadmap to improve our products, big or small, and see the results of your products reach our customers.\nGet to work with flexible working hours. Our priority is on getting the job done.\nFlat structure environment, you will be able to work independently and make your own choices.\nWe provide guidance and mentorship to polish your business skills and entrepreneurship mindset.\nWe are one of the standout tech startups in Hong Kong, targeting a huge opportunity in Asia.\nShopline is a part of the 500 Startups Accelerator and Incubated by Hong Kong Cyberport, giving us a massive network of advisors and resources globally", "employment_types": ["Full Time"], "selling_points": [], "locations": ["Tuen Mun Area"], "categories": ["Transportation & Logistics", "Others", "Inventory / Warehousing", "Supply Chain"], "post_time": "2022-01-17T07:26:16Z", "salary": {"currency": null, "max": null, "min": null, "period": "monthly", "term": null}, "salary_visible": false, "title_keywords": ["native english teacher"], "responsibilities": ["management", "advertising", "ideas", "schedules", "systems", "develop", "communication", "logistics", "contact", "sales plans", "contracting"], "requirements": {"degrees": ["degree", "bachelor"], "majors": [], "languages": [], "language_level": [], "hard_skills": ["small", "make", "fun", "pos"], "soft_skills": ["flexible", "communication skills", "work independently", "collaborative", "comprehensive", "team player", "presentation"], "languages_combined": []}, "experience_required": {"duration": ["3+ years"], "field": ["marketing", "logistics", "team"]}}, {"job_id": "100003009055341", "location_code": "hk", "company": "Possehl Electronics Hong Kong Ltd", "job_title": "Order Fulfillment Manager", "description": "\nWe are now looking for enthusiastic English speaking teachers in the early childhood educational sector and Bachelor degree holder or higher.\nJob Description:\nTeach English to young learners in a fun and interesting way\nOrganize, conduct and follow the teaching curriculum provided by schools\nMake lesson plan\nTeaching phonics, Trinity GESE, Oral and Cambridge English\nRequirements:\nMust be Native English Speaker\nDegree and/or with teaching qualification such as TEFL, TESOL, QKT and PGDE is preferred.\nPatient, friendly, outgoing, caring and love working with young children\nClean criminal background check\nPast experience in teaching young children in a kindergarten preferred\nBenefits:\nTraining workshops\nTeaching resources and materials support\nWorking visa sponsorship for suitable full-time candidates\nInterested parties please send your CV, availability and expected salary email to us\nFrances Lai\nUnit 2503, 25/F,\nTuen Mun Parklane Square,\n2 Tuen Hi Road,\nTuen Mun\nHong Kong\n\nEmail: Apply Now\nPhone:96894897\nFax:\n\n", "employment_types": ["Full Time", "Permanent"], "selling_points": ["5 days per week", "Work in Hong Kong", "Medical Insurance & Year End Bonus"], "locations": ["Tsuen Wan Area"], "categories": ["Transportation & Logistics", "Fulfillment", "Supply Chain", "Manufacturing", "Production Planning / Control"], "post_time": "2022-01-18T02:15:02Z", "salary": {"currency": null, "max": null, "min": null, "period": "monthly", "term": null}, "salary_visible": false, "title_keywords": ["manager"], "responsibilities": ["plan"], "requirements": {"degrees": ["degree"], "majors": [], "languages": ["english"], "language_level": ["native"], "hard_skills": ["clean"], "soft_skills": ["outgoing", "patient", "friendly"], "languages_combined": [{"language": "english", "language_level": ["native"]}]}, "experience_required": {"duration": [], "field": ["teaching"]}}, {"job_id": "100003009048683", "location_code": "hk", "company": "UAG Hong Kong Limited", "job_title": "Supply Planning & Logistic Manager", "description": "Responsibilities:\n\nManage routine order fulfillment communication with all related parties.\nIn charge of procurement, Customer Service and PMC function of the Supply Chain.\nMonitor Production capacity and resources allocations\nManage and supervise the team on material planning and forecasts, production schedules, and shipment schedules.\nHands on experience to lead and support daily warehouse operation.\n\nRequirements:\n\nDegree holder of Supply Management or relevant disciplines.\nMinimum of 5 years experience in managerial position (previous exposure in Semi-con Industry would be an advantage)\nDetail-minded with ability to work under pressure and independently\nTeam Player with Excellent Communication and Interpersonal skills\nGood command of written and spoken English and Cantonese\nProficiency in MS Office\nImmediate Availability is highly preferred.\n\nAttractive remuneration package is provided to the right candidate, including 5 days work, Year End bonus, incentive bonus & medical insurance. Interested parties please send your full resume with CURRENT and EXPECTED salary and reference number (JD008) via email to \"Apply Now\"\n\n\u00a0You are welcome to visit our website : www.possehlelectronics.com\n\n\u00a0(The resume without expected salary will not be considered.)\n\nAll information received will be kept in strict confidence and only for employment-related purpose.", "employment_types": ["Full Time"], "selling_points": ["All rounded Supply Chain Role", "Minimal Supervision", "Global Exposure"], "locations": ["Kowloon Bay"], "categories": ["Transportation & Logistics", "Fulfillment", "Inventory / Warehousing", "Supply Chain"], "post_time": "2022-01-14T07:02:35Z", "salary": {"currency": null, "max": null, "min": null, "period": "monthly", "term": null}, "salary_visible": false, "title_keywords": ["manager"], "responsibilities": ["schedules", "monitor", "communication", "order fulfillment", "customer service", "shipment schedules", "planning"], "requirements": {"degrees": ["degree holder"], "majors": [], "languages": ["cantonese", "english"], "language_level": ["good command"], "hard_skills": ["ms office"], "soft_skills": ["detail-minded", "independently", "communication and interpersonal skills", "team player", "work under pressure"], "languages_combined": [{"language": "cantonese", "language_level": ["good command"]}, {"language": "english", "language_level": ["good command"]}]}, "experience_required": {"duration": ["minimum of 5 years"], "field": ["managerial"]}}, {"job_id": "100003009052835", "location_code": "hk", "company": "Panasonic Hong Kong Co., Limited", "job_title": "Shipping Clerk/ Coordinator (Focus on Logistics)", "description": "Responsibilities:\n\nTo\u00a0handle shipping schedule and arrangement\nTo follow up on sales and purchase orders, shipment booking and scheduling\nTo co-ordinate and arrange with factories and overseas customer for end to end supply chain\nTo compile statistical figures for logistics process improvement\nTo assist in other ad-hoc assignments as required\n\nRequirements:\n\nHKCEE F.5 / DSE graduated or above\n1-2 years relevant logistics experience especially in China export arrangement\nPrevious exposures trading company or MNC are preferred\nProficient in MS Office and previous exposure in shipping software system is preferred\nGood command of written and spoken English and Chinese\nHave good communication, well organized and a fast learner\nWilling to provide ad hoc support\n\nRemuneration will be commensurate with qualification and experience. Interested parties, please send your application with detailed resume indicating both existing & expected salary and date of availability to us.\n\nWe are an equal opportunity employer. All information provided by applicants will be treated in strict confidence and used for recruitment purpose only.", "employment_types": ["Full Time", "Permanent"], "selling_points": ["Handle shipping schedule & shipment booking", "Exposure in trading company & export arrangement", "Stable MNC in-house environment"], "locations": ["Tsim Sha Tsui"], "categories": ["Transportation & Logistics", "Others", "Shipping", "Supply Chain"], "post_time": "2022-01-17T04:13:27Z", "salary": {"currency": null, "max": null, "min": null, "period": "monthly", "term": null}, "salary_visible": false, "title_keywords": ["logistics", "coordinator", "shipping clerk"], "responsibilities": ["shipping schedule", "ad-hoc assignments", "scheduling", "purchase", "logistics", "booking"], "requirements": {"degrees": ["dse"], "majors": [], "languages": ["english", "chinese"], "language_level": ["good command"], "hard_skills": ["ms office"], "soft_skills": ["communication", "fast learner", "well organized"], "languages_combined": [{"language": "english", "language_level": ["good command"]}, {"language": "chinese", "language_level": ["good command"]}]}, "experience_required": {"duration": ["1-2 years"], "field": ["logistics"]}}, {"job_id": "100003009053792", "location_code": "hk", "company": "De Wu (HK) Supply Chain Company Limited", "job_title": "\u5009\u52d9\u54e1", "description": "\n\u8077\u8cac :\u8ca0\u8cac\u5546\u54c1\u7684\u9032\u51fa\u5eab\u6aa2\u9a57\u7b49\u65e5\u5e38\u5de5\u4f5c, \u5305\u62ec\u9ede\u8ca8\u3001\u57f7\u8ca8\u5165\u7bb1\u3001\u5305\u88dd\u3001\u6574\u7406\u5009\u5eab, \u904b\u7528\u96fb\u8166\u7cfb\u7d71\u9032\u884c\u8ca8\u7269\u5206\u985e,\u6a19\u7c64\u9ecf\u8cbc,\u6383\u63cf\u53ca\u6210\u54c1\u6574\u7406\u7b49\u5de5\u4f5c, \u8ca0\u8cac\u54c1\u8cea\u76e3\u6e2c\u5de5\u4f5c, \u4f7f\u7528\u5527\u8eca, \u9700\u8981\u61c9\u4ed8\u9ad4\u529b\u52de\u52d5\u5de5\u4f5c, \u9700\u8981\u70ba\u5546\u54c1\u62cd\u7167\u4e26\u5b58\u6a94\n\n\u8cc7\u6b77 :\u4e2d\u4e94\u7a0b\u5ea6; 1\u5e74\u7d93\u9a57; \u4e00\u822c\u7cb5\u8a9e\u512a\u5148; \u4e00\u822c\u666e\u901a\u8a71\u512a\u5148; \u4e00\u822c\u82f1\u8a9e\u512a\u5148; \u61c2\u8b80\u5beb\u4e2d\u6587; \u7565\u61c2\u8b80\u5beb\u82f1\u6587; \u5177\u6709\u4e00\u822c\u4e92\u806f\u7db2\u77e5\u8b58; \u61c2\u4e2d\u82f1\u6587\u96fb\u8166\u64cd\u4f5c; \u5177\u6709\u57fa\u672c\u96fb\u8166\u64cd\u4f5c\u77e5\u8b58\n\n\u5f85\u9047 :\u6bcf\u6708$11,000 - $15,000, \u6709\u52e4\u5de5\u734e\u91d1, \u9280\u884c\u5047\u671f, \u96d9\u7ce7 \u53ca\u5e74\u7d42\u734e\u91d1, \u4e0a\u53489\u6642\u81f3\u4e0b\u53486\u6642, \u6bcf\u9031\u5de5\u4f5c6\u5929,\u8f2a\u4f11, \u6bcf\u5929\u5de5\u4f5c 9 \u5c0f\u6642\n\n\u7533\u8acb\u9808\u77e5 :\u6c42\u8077\u8005\u53ef\u96fb\u90f5(Apply Now)\u5c65\u6b77\u8868\u7d66\u5f97\u7269(\u9999\u6e2f)\u4f9b\u61c9\u93c8\u6709\u9650\u516c\u53f8\u3002\u5982\u8981\u7d22\u53d6\u6536\u96c6\u500b\u4eba\u8cc7\u6599\u8072\u660e, \u8acb\u8207\u56b4 \u5148\u751f(Email)\u806f\u7d61\u3002\n\n", "employment_types": ["Full Time"], "selling_points": [], "locations": ["Tin Shui Wai"], "categories": ["Transportation & Logistics", "Others", "Inventory / Warehousing", "Supply Chain"], "post_time": "2022-01-17T07:31:11Z", "salary": {"currency": null, "max": null, "min": null, "period": "monthly", "term": null}, "salary_visible": false, "title_keywords": ["\u5009\u52d9\u54e1"], "responsibilities": [], "requirements": {"degrees": [], "majors": [], "languages": [], "language_level": [], "hard_skills": [], "soft_skills": [], "languages_combined": []}, "experience_required": {"duration": [], "field": []}}, {"job_id": "100003009048736", "location_code": "hk", "company": "Market Hong Kong Limited", "job_title": "Logistics Officer (5-day work)", "description": "Practical experience in Construction industry;\nTo plan, source and negotiate with new/existing supplier, in order to reduce the total cost of inventory;\nSupply contract management and periodical review supplier performance;\nHighly motivated and quality driven;\nHigher Diploma in Logistic Management;\nLess experience will be considered as Purchasing Clerk.\u00a0\n\nWe offer attractive remuneration package. Interested parties, please send full resume with present and expected salary to HR & Admin Dept.\n\nAll information collected will be kept in strictly confidential and used for recruitment purpose only.", "employment_types": ["Full Time", "Permanent"], "selling_points": [], "locations": ["Tsim Sha Tsui"], "categories": ["Transportation & Logistics", "Inventory / Warehousing", "Supply Chain", "E-commerce", "Supply Chain"], "post_time": "2022-01-14T07:10:59Z", "salary": {"currency": null, "max": null, "min": null, "period": "monthly", "term": null}, "salary_visible": false, "title_keywords": ["logistics officer"], "responsibilities": ["cost", "management", "inventory", "review", "quality", "contract management", "plan"], "requirements": {"degrees": ["diploma"], "majors": [], "languages": [], "language_level": [], "hard_skills": [], "soft_skills": ["motivated", "driven"], "languages_combined": []}, "experience_required": {"duration": [], "field": ["purchasing", "construction industry"]}}, {"job_id": "100003009054545", "location_code": "hk", "company": "Tactful Building Co Ltd", "job_title": "Purchasing Officer/ Clerk", "description": "Responsibilities:\nHandle daily rate request and related pricing inquiries (preferably Oceania/Intra Asia/Import trade lanes)\nRegular rate sheet and pricing database update and distribution to relevant stake holders\nSpace / allocation coordination / arrangement with local offices and carriers\nStatistics and reports, market information update (e.g. FAK/NAC/Spot Rate Update, Utilization Levels, Blank Sailings etc.)\nCoordination between carriers, sales & operation team\nInvoice / billing management\nRequirements:\nDiploma or above\nPreferred 1-3 years experience in Logistics Service Providers / Carriers\nBasic knowledge in shipping industry knowledge\nKnowledge or experience in pricing / ocean product will be an advantage\nGood command of spoken and written English and Mandarin\nProficient in MS office, especially Excel\nStrong sense of responsibility and team player\nPleasant and cooperative\nCandidate with\u00a0less experience will also be considered\nBenefits:\nDouble Pay\nFive-day work week\nBirthday Leave\nMedical Insurance\nFree Shuttle Bus\nTraining Allowance\nAttractive remuneration package and excellent career development opportunities will be offered to the successful candidate.\u00a0 For Interested parties, please apply with a detailed resume stating present and stating present and expected salary by clicking \"Apply Now\".\u00a0 You are welcome to visit our website at http://www.cargofe.com.\nPersonal data collected will be used for recruitment purposes only and be treated in strict confidence.\u00a0 Cargo Services treats all applicants for employment in the same way, regardless of age, sex, marriage and civil partnership, race, disability, religion or belief.", "employment_types": ["Full Time", "Permanent"], "selling_points": [], "locations": ["Kwun Tong"], "categories": ["Engineering", "Engineering Project Management", "Transportation & Logistics", "Supply Chain", "Building & Construction", "Others"], "post_time": "2022-01-17T09:57:20Z", "salary": {"currency": null, "max": null, "min": null, "period": "monthly", "term": null}, "salary_visible": false, "title_keywords": ["clerk", "purchasing officer"], "responsibilities": ["management", "market information", "invoice", "reports", "coordination", "database"], "requirements": {"degrees": ["diploma or above"], "majors": [], "languages": ["english", "mandarin"], "language_level": ["good command"], "hard_skills": ["excel", "basic", "ms office"], "soft_skills": ["cooperative", "pleasant", "team player", "sense of responsibility"], "languages_combined": [{"language": "english", "language_level": ["good command"]}, {"language": "mandarin", "language_level": ["good command"]}]}, "experience_required": {"duration": ["1-3 years"], "field": ["logistics"]}}, {"job_id": "100003009053636", "location_code": "hk", "company": "Cargo Services Far East Ltd", "job_title": "Executive - Ocean Freight Pricing", "description": "Supervise day-to-day logistics/distribution operations with 3PL\nMaintain the Company's standard delivery service records\nLead the tender process during contract renewal in compliance with company\u2019s policies.\nReview and analyze company's logistics performance and provide suggestion for process improvement\nAssist in preparing weekly and monthly reports for management review\nMaintain and enhance the logistics SOP in order to fulfill IMS requirement\nHandle ad hoc projects assigned by Supervisor\n\nJob Requirements\n\nDegree holder in Supply Chain, Logistics, Transportation or other related disciplines\n8+ years related experience of inbound and outbound logistics mangaement which in F&B industry is preferred\nExperience\u00a0in 3PL management will be an advantages\u00a0\nEnergetic, well-organized, self-motivated, initiative, able to work independently & capable of working under pressure and meet deadline\nGood communication, presentation and interpersonal skill\nGood command of written and spoken English and Chinese\nPC Knowledge in MS Excel, Word & PowerPoint and Chinese Processing\n\nWe offer competitive salary, discretionary performance bonus, medical and retirement benefits, free company coach services and excellent career prospects. Please send your resume together with salary expectation via\u00a0[via APPLY NOW]\n\nFor more information, please visit our website at\u00a0www.aswatson.com\n\nAll information provided will be used for recruitment other employment-related purposes by A.S. Watson & Company Limited (for and on behalf of the A.S. Watson Group of companies). It may be provided to companies/parties authorized to process the information for purposes relating to recruitment, e.g. qualifications assessment.\n\nWith the consent of applicant, all personal data of unsuccessful applicants will be retained for future consideration for two years. Otherwise, all personal data of unsuccessful applicants will be retained for twelve months.\n\nApplication will not be considered if the applicant does not provide all information as requested.\n\nAll information provided will be held in strict confidence.\n\nIf applicant request access to, and to request correction of personal data in relation to the application, please contact our People Department at 2660 1880.", "employment_types": ["Full Time", "Permanent"], "selling_points": ["Seafreight pricing - Oceania/Intra Asia/Import", "1-3 years relevant experiences", "Double Pay; 5-day week; Birthday Leave"], "locations": ["Kwai Tsing Area"], "categories": ["Transportation & Logistics", "Freight Forwarding", "Shipping", "Supply Chain"], "post_time": "2022-01-17T07:16:11Z", "salary": {"currency": null, "max": null, "min": null, "period": "monthly", "term": null}, "salary_visible": false, "title_keywords": ["executive"], "responsibilities": ["management", "operations", "policies", "compliance", "review", "website", "communication", "maintain", "logistics", "ad hoc projects", "tender", "recruitment", "contact", "personal data", "weekly and monthly reports", "management review", "inbound and outbound logistics"], "requirements": {"degrees": ["degree holder"], "majors": ["related disciplines"], "languages": ["english", "chinese"], "language_level": ["good command"], "hard_skills": ["word", "powerpoint", "ms excel", "3pl management", "pc knowledge", "processing", "inbound and outbound logistics"], "soft_skills": ["self-motivated", "work independently", "under pressure", "capable", "confidence", "presentation", "well-organized", "interpersonal skill", "communication", "energetic", "initiative"], "languages_combined": [{"language": "english", "language_level": ["good command"]}, {"language": "chinese", "language_level": ["good command"]}]}, "experience_required": {"duration": ["8+ years"], "field": ["related", "f&b", "logistics", "management"]}}, {"job_id": "100003009051603", "location_code": "hk", "company": "A.S. Watson Industries", "job_title": "Distribution Manager", "description": "Job Highlights\n\nPrepare accurate purchase order\nFollow up shipment and relevant documents\nLiaise with local vendor and supplier\n\nJob Responsibilities:\n\n\u00a0\u00a0\u00a0\u00a0\u00a0\u00a0\u00a0\u00a0 To prepare accurate purchase order\n\u00a0\u00a0\u00a0\u00a0\u00a0\u00a0\u00a0\u00a0 To follow up shipment and relevant documents\n\u00a0\u00a0\u00a0\u00a0\u00a0\u00a0\u00a0\u00a0 Issue invoice and packing list\n\u00a0\u00a0\u00a0\u00a0\u00a0\u00a0\u00a0\u00a0 Handle import documents\n\u00a0\u00a0\u00a0\u00a0\u00a0\u00a0\u00a0\u00a0 To maintain shipment record for updating internal system\n\u00a0\u00a0\u00a0\u00a0\u00a0\u00a0\u00a0\u00a0 Work closely with third party logistics to ensure logistics are arranged timely and cost effectively\n\u00a0\u00a0\u00a0\u00a0\u00a0\u00a0\u00a0\u00a0 Analyze and manage inventory; execute any expansion plan if needed\u00a0\n\u00a0\u00a0\u00a0\u00a0\u00a0\u00a0\u00a0\u00a0 Prepare weekly and monthly reports to analysis warehouse operation activities and all cost reduction projects\u00a0 \u00a0\n\nRequirements:\n\n\u00a0\u00a0\u00a0\u00a0\u00a0\u00a0\u00a0\u00a0 At least 2-3 years of shipping, purchasing or supply chain experience\n\u00a0\u00a0\u00a0\u00a0\u00a0\u00a0\u00a0\u00a0 Ability to multi-task, good time management, and prioritize deadlines.\n\u00a0\u00a0\u00a0\u00a0\u00a0\u00a0\u00a0\u00a0 Excellent interpersonal skill, able to communicate well with all levels\n\u00a0\u00a0\u00a0\u00a0\u00a0\u00a0\u00a0\u00a0 Strong planning,\u00a0implementation\u00a0and negotiation skills;\u00a0good problem solving\n\u00a0\u00a0\u00a0\u00a0\u00a0\u00a0\u00a0\u00a0 Good command of spoken and written English and Chinese. Knowledgeable in Japanese is preferred\u00a0\u00a0", "employment_types": ["Full Time"], "selling_points": ["Supervise day-to-day distribution operations", "Lead the tender process", "3PL management and logistics operations"], "locations": ["Tai Po Area"], "categories": ["Transportation & Logistics", "Others", "Inventory / Warehousing", "Supply Chain"], "post_time": "2022-01-16T14:18:19Z", "salary": {"currency": null, "max": null, "min": null, "period": "monthly", "term": null}, "salary_visible": false, "title_keywords": ["manager"], "responsibilities": ["cost", "invoice", "inventory", "analysis", "packing list", "purchase", "maintain", "logistics", "plan", "weekly and monthly reports", "third party"], "requirements": {"degrees": [], "majors": [], "languages": ["japanese", "english", "chinese"], "language_level": ["good command"], "hard_skills": ["problem solving"], "soft_skills": ["multi-task", "prioritize", "interpersonal skill", "problem solving", "negotiation skills", "time management"], "languages_combined": [{"language": "japanese", "language_level": []}, {"language": "english", "language_level": ["good command"]}, {"language": "chinese", "language_level": ["good command"]}]}, "experience_required": {"duration": ["at least 2-3 years"], "field": ["purchasing", "supply chain"]}}, {"job_id": "100003009047882", "location_code": "hk", "company": "En Group Limited", "job_title": "Supply Chain Officer/ Executive (Japanese F &B)", "description": "Job Descriptions:\n\nResponsible for purchasing & operation activities from business contracts, sourcing, price negotiation, orders, shipment;\n\nCollaborate with sales team and liaise with suppliers to drive on time shipment delivery;\nLiaise and support post-contract management activities like handling deliveries discrepancies and monitoring supplier performance;\nHandle full set of shipping I/E documents, liaise with supplier and forwarders for shipment schedule and arrangement;\nPrepare regular reporting and conduct analysis to support business decisions;\nAssist in other ad-hoc assignment as required.\n\nJob Requirements:\n\nDegree holder majoring in Purchasing, Supply Chain Management or other related subjects with at least 2 years related working experience, with background in purchasing field or manufacturing industry will be a plus;\n\nFluent in spoken and written English & Chinese (Cantonese and Mandarin);\nWell versed with PC applications, i.e. MS Word, Excel, PowerPoint & Chinese Word Processing;\nPatient, detailed-mind, willing to learn, able to work under pressure;\nWell-organized with good interpersonal and communication skills;\nCandidates with more experience will be considered as Planning & Operation Executive.\n\nBenefits:\n\n5-day work\u00a0(staggered working hours)\nDouble pay\nDiscretionary bonus\nGroup medical\nOT pay\nStatutory Annual Leave with extra\u00a07 days Company Annual Leave\nBank Holiday\nOther Special Leave i.e. Marriage Leave, etc.\n\nWe offer competitive remuneration and benefits, holidays, stable working environment to the right candidates. Interested parties please click \"Apply Now\" and send your full resume with expected salary in MS Word Format to us (Please quote Position Name & Reference No.)\n\n*All personal data collected will be kept strictly confidential and used for recruitment-related purpose only.", "employment_types": ["Full Time"], "selling_points": ["logistic", "shipment", "F&B industry"], "locations": ["To Kwa Wan"], "categories": ["Transportation & Logistics", "Supply Chain"], "post_time": "2022-01-14T04:07:24Z", "salary": {"currency": null, "max": null, "min": null, "period": "monthly", "term": null}, "salary_visible": false, "title_keywords": ["supply chain officer", "executive"], "responsibilities": ["collaborate with", "liaise", "price negotiation", "shipping", "reporting", "ad-hoc", "contracts", "analysis", "monitoring", "contract management", "support business decisions", "sales team", "schedule", "liaise with", "liaise with suppliers"], "requirements": {"degrees": ["degree holder"], "majors": ["manufacturing"], "languages": ["cantonese", "english", "chinese", "mandarin"], "language_level": ["fluent"], "hard_skills": ["excel", "plus", "chinese word processing", "powerpoint", "pc applications", "ms word"], "soft_skills": ["communication skills", "willing to learn", "well-organized", "detailed", "patient", "interpersonal", "work under pressure"], "languages_combined": [{"language": "cantonese", "language_level": ["fluent"]}, {"language": "english", "language_level": ["fluent"]}, {"language": "chinese", "language_level": ["fluent"]}, {"language": "mandarin", "language_level": ["fluent"]}]}, "experience_required": {"duration": ["at least 2 years"], "field": ["management", "purchasing", "supply chain", "related", "operation", "manufacturing industry", "planning"]}}, {"job_id": "100003009054339", "location_code": "hk", "company": "YKK Hong Kong Limited", "job_title": "Associate Planning & Operation Executive", "description": "Supply Chain Manager\n\nSky is seeking to appoint a Supply Chain Manager to support the Group Supply Chain Planning team in the UK to coordinate with the suppliers based in Asia. The primary focus for this role is to support production plans and resolve all planning related issues for our major products.\n\nResponsibilities\n\nCoordinate with key suppliers to review the latest Sky related Product Forecasts, Production and Shipping Schedules, Performance vs Plan.\nReview supplier safety stock buffer levels and identify potential material risks (shortages and overstock) that may impact production plans and future changes\nBuild credible business relationships with key internal and external stakeholders to represent Sky Supply Chain Planning in the Asia Pac region\nAssist in resolving any planning related queries relating to production output, inbound delivery planning and coordination with members of the Sky Freight Management team / 3PL Control Tower, as required\nIdentify and drive performance improvement initiatives, including the development and implementation of production visibility and reporting tools\nLiaise with colleagues in Sky Group Supply Chain Planning Team and provide additional insight and support, as required, to build and develop supplier production and shipping plans\n\nExperience, Skills & Knowledge\n\nTertiary Education or above in Supply Chain Management, Business Administration, Procurement or other related disciplines\nKnowledge of production planning, shipping, and inventory management.\nExcellent communication skills verbal & written attention to detail and strong organizational skills\nProficiency in MS Office: Outlook, PowerPoint, Excel, & Word\nFluency in English and Chinese (Mandarin and Cantonese) both written and verbal is essential.", "employment_types": ["Full Time", "Permanent"], "selling_points": ["Degree in Purchasing / Supply Chain Management", "2 years exp.,Good command of English & Chinese", "5-day, 13-mth, discretionary bonus, extra leave"], "locations": ["Tsim Sha Tsui"], "categories": ["Transportation & Logistics", "Shipping", "Supply Chain", "Merchandising & Purchasing", "Textiles"], "post_time": "2022-01-17T09:12:06Z", "salary": {"currency": null, "max": null, "min": null, "period": "monthly", "term": null}, "salary_visible": false, "title_keywords": ["associate", "operation executive"], "responsibilities": ["shipping", "schedules", "coordination with", "inventory management", "communication", "plan", "liaise with", "plans", "administration", "management team", "control", "implementation", "develop", "reporting", "management", "review", "coordinate with", "production planning", "planning"], "requirements": {"degrees": [], "majors": [], "languages": ["cantonese", "english", "chinese", "mandarin"], "language_level": ["fluency"], "hard_skills": ["excel", "word", "powerpoint", "outlook", "vs", "focus", "ms office"], "soft_skills": ["communication skills", "organizational skills", "attention to detail", "coordination", "focus"], "languages_combined": [{"language": "cantonese", "language_level": []}, {"language": "english", "language_level": ["fluency"]}, {"language": "chinese", "language_level": ["fluency"]}, {"language": "mandarin", "language_level": []}]}, "experience_required": {"duration": [], "field": []}}, {"job_id": "100003009050897", "location_code": "hk", "company": "Sky Manufacturing Services Limited", "job_title": "Supply Chain Manager", "description": "Responsibilities:\n\n\nManage all round demand and supply planning from group level to keep the optimal inventory and able to meet sales target\nTake Lead on the monthly S&OP process and coordinate\u00a0 any changes\u00a0 with respect of the planning process\nEvaluate and follow up on demand and supply status on phase in/out, promotional, sales event items to make sure planning on track\nDrive regular strategic and operational review meetings with key vendors for product supply and inventory planning\nMaintain good data quality for Purchase Order generation, relevant documentation required and for logistics team to follow up on shipments.\nManage new store, festive, bulk stock and store closure stock arrangement and logistics\nPrepare work plan and schedule over all kinds of periodic inventory movement and control on each promotional and seasonal activities\nPerform any ad-hoc tasks as assigned by Management\nRequirements\n\nDegree in Supply Chain management or related discipline\nMinimum 10 years in Supply Chain Planning, preferably from FMCG & manufacturing experience\u00a0\nSelf-motivated, independent and able to perform multitasks under pressure\nWell organized with strong numerical sense and business acumen\nStrong leadership, problem solving and decision making skills\nExcellent communication and presentation skills\n\nInterested parties please send\u00a0full resume with present and expected salary\u00a0to Human Resources Department by clicking\u00a0\"APPLY NOW\".\n\n(Information provided will be treated in strict confidence and will only be used for recruitment-related purposes.)\n\n\n\n", "employment_types": ["Full Time", "Permanent"], "selling_points": ["Supply Chain Management", "Proactive, self-motivated, communication skills", "5 days, Bank holiday, Medical"], "locations": ["Wong Tai Sin Area"], "categories": ["Transportation & Logistics", "Inventory / Warehousing", "Supply Chain", "Manufacturing", "Production Planning / Control"], "post_time": "2022-01-15T03:51:16Z", "salary": {"currency": null, "max": null, "min": null, "period": "monthly", "term": null}, "salary_visible": false, "title_keywords": ["supply chain manager"], "responsibilities": ["data", "inventory", "planning process", "quality", "purchase", "maintain", "plan", "control", "sales target", "logistics", "schedule", "management", "review", "documentation", "seasonal activities", "inventory planning", "ad-hoc tasks", "coordinate", "evaluate", "planning"], "requirements": {"degrees": ["degree"], "majors": [], "languages": [], "language_level": [], "hard_skills": ["problem solving", "acumen"], "soft_skills": ["self-motivated", "decision making skills", "independent", "under pressure", "well organized", "problem solving", "communication", "presentation skills", "business acumen", "leadership"], "languages_combined": []}, "experience_required": {"duration": ["minimum 10 years"], "field": ["manufacturing", "fmcg", "supply chain planning"]}}, {"job_id": "100003009052563", "location_code": "hk", "company": "Centrix Professionals - Recruitment Agency Division", "job_title": "Logistics Officer / Shipping Officer / Operations Officer (5 Days) 2 Post URGENT", "description": "Our client is a sizable company with attractive benefits is urgently looking for the following positions :\n\nPosition : Logistics Officer / Shipping Officer / Operation Officer (2 Post)\n\nSalary : Negotiable\u00a0\n\nRequirements :\u00a0\n\nBenefits : Medical, Dental, Guarantee Double Pay, Yearly Discretionary Bonus, Annual Leave, 5 Days\n\nRequirements:\n\nDegree holder is a must, major in International Shipping, Logistics Engineering Management, Supply Chain Management or related discipline\nAt least 1-3 yrs relevant experience in Shipping Companies is preferable\u00a0\nGained experience in Demurrage will consider Operation Officer (Demurrage)\nProficiency in English, Cantonese & Mandarin (most important)\nProficient in Microsoft Office (Ms Word, Excel & Chinese Word Processing\nStable, Reliable, Independent, Team Work, Detail-minded and able to work under pressure\nFresh Graduate with related major will consider as Assistant Grade\u00a0\nImmediate Available is highly preferable\n\nResponsibilities for the position of Operation Officer / Assistant\u00a0\n\n\nHandle full set of shipping documents\u00a0\n\nCoordinate with supplier, buyers & head office to arrange loading schedules\nFollow up charter party & handle commercial claims\u00a0\n\nResponsibilities for the position of Operation Officer - Demurrage\u00a0\n\nPrepare demurrage computation for timely submission\nFollow up receivable and collection to counter parties proactively\nNegotiable and settle demurrage claims according to trading contracts and charter parties\nPrepare demurrage claim invoices and check invoices for settlement\nReview of shipping and trading contracts related to lay time calculation and demurrage\nHandle and manage full set of demurrage documents\nKeep outstanding claims record update\nUndertake Department Head relevant assignment whenever required\u00a0\nAttractive salary and fringe benefits will be offered to the right candidates.\n\n\nInterested parties, please send full resume in\u00a0MS WORD FORMAT, stating expected salary by clicking \"Apply Now\"\n\nFor more information, please visit : www.centrix.com.hk\n\n\n(Personal data collected will be used for recruitment purpose only)\u00a0\u00a0", "employment_types": ["Full Time", "Permanent"], "selling_points": ["Degree Int'l shpg Supply Chain 2 post TOP URGENT", "1-3 yrs rel exp in Shpg Co / Demurrage Stable", "Flu Eng & Mandarin Stable Reliable Independent"], "locations": ["Not Specified"], "categories": ["Transportation & Logistics", "Others", "Shipping", "Supply Chain"], "post_time": "2022-01-17T03:25:35Z", "salary": {"currency": null, "max": null, "min": null, "period": "monthly", "term": null}, "salary_visible": false, "title_keywords": ["logistics officer", "operations officer", "shipping officer"], "responsibilities": [], "requirements": {"degrees": [], "majors": [], "languages": [], "language_level": [], "hard_skills": [], "soft_skills": [], "languages_combined": []}, "experience_required": {"duration": [], "field": []}}, {"job_id": "100003009053902", "location_code": "hk", "company": "Kallimount Capital (HK) Limited", "job_title": "\u5305\u88dd,\u5009\u7ba1\u517c\u7269\u6d41\u9001\u8ca8\u54e1**", "description": "\n\u8077\u8cac :\u8ca0\u8cac\u5009\u52d9\u5de5\u4f5c, \u5982\u6536\u767c\u8ca8, \u6574\u7406\u8ca8\u5009, \u76e4\u9ede\u8ca8\u5b58, \u642c\u904b\u8ca8\u7bb1, \u5916\u51fa\u9001\u8ca8, \u66f4\u65b0\u5b58\u8ca8\u8a18\u9304\u7b49; \u5354\u52a9\u751f\u7522\u7dda\u5305\u88dd\u7522\u54c1, \u78ba\u4fdd\u51fa\u54c1\u5408\u7b26\u6a19\u6e96\u8981\u6c42\n\n\u8cc7\u6b77 :\u6c92\u6709\u5b78\u6b77\u8981\u6c42; \u4e00\u822c\u7cb5\u8a9e; \u61c2\u8b80\u5beb\u4e2d\u6587; \u61c2\u4f7f\u7528\u5527\u8eca\u512a\u5148; \u6709\u79ae\u8c8c\u3001\u76e1\u8cac\u3001\u52e4\u596e\u5b88\u6642\u3001\u8655\u4e8b\u7d30\u5fc3\u3001\u5de5\u4f5c\u7a4d\u6975\u4e3b\u52d5\u53ca\u5177\u5718\u968a\u5408\u4f5c\u7cbe\u795e\n\n\u5f85\u9047 :\u6bcf\u6708$13,000 - $15,000, \u6709\u8d85\u6642\u5de5\u4f5c\u6d25\u8cbc, \u5e74\u50478\u5929, \u9280\u884c\u5047\u671f, \u914c\u60c5\u6027\u82b1\u7d05, \u54e1\u5de5\u8cfc\u7269\u512a\u60e0 \u53ca\u5728\u8077\u57f9\u8a13, \u661f\u671f\u4e00\u81f3\u516d: \u4e0a\u53489\u6642\u81f3\u4e0b\u53486\u6642, \u6bcf\u9031\u5de5\u4f5c6\u5929, \u6bcf\u5929\u5de5\u4f5c 9 \u5c0f\u6642, 1\u5c0f\u6642\u7528\u81b3\u6642\u9593, \u56e0\u61c9\u516c\u53f8\u5de5\u4f5c\u60c5\u6cc1\u53ef\u80fd\u6709\u9700\u8981\u8d85\u6642\u5de5\u4f5c\n\n\u7533\u8acb\u9808\u77e5 :\u6c42\u8077\u8005\u53ef\u81f4\u96fb31690986\u8207\u7ffa\u76df\u8cc7\u672c\uff08\u9999\u6e2f\uff09\u6709\u9650\u516c\u53f8\u9673\u5c0f\u59d0\u806f\u7d61\u3002\n\n", "employment_types": ["Full Time"], "selling_points": [], "locations": ["Kwun Tong"], "categories": ["Transportation & Logistics", "Others", "Inventory / Warehousing", "Supply Chain"], "post_time": "2022-01-17T07:43:51Z", "salary": {"currency": null, "max": null, "min": null, "period": "monthly", "term": null}, "salary_visible": false, "title_keywords": ["\u5305\u88dd"], "responsibilities": [], "requirements": {"degrees": [], "majors": [], "languages": [], "language_level": [], "hard_skills": [], "soft_skills": [], "languages_combined": []}, "experience_required": {"duration": [], "field": []}}, {"job_id": "100003009052290", "location_code": "hk", "company": "Kerry Logistics", "job_title": "Graduate Trainee", "description": "Our Graduate Trainee (GT) Programme\u00a0is a comprehensive career development programme providing invaluable opportunities to enter the gate of logistics field. Experience different aspects of the industry & to apply innovative & technology elements into value-adding solutions.\n\nFeatures of Graduate Trainee Programme\n\nThrough intensive action-learning projects in Hong Kong, the programme prepares high potential graduates to take on early responsibility and shape their project leadership with industrial knowledge and hands-on experience.\n\n12-month programme\nAttach to 2 operation / business projects\nOn-job training supported with senior management guidance and coaching programme\nWide exposures from operations to key accounts management and business development\nRegular talent review and presentation to the management on business ideas and project improvement\nLearning curriculums to forge successful and sustainable career\n\n\u00a0Requirements\n\n2022 university graduates from any disciplines\nLogistics related study or work experience is an added advantage\u00a0\nPassionate\u00a0in taking leadership in 3PL project\nReady to take early responsibility and drive results\nProactive, adaptive, solution-focused\nProficiency in both English and Chinese\n\nApplication Period:\u00a0 3 January 2022 - 6 February 2022 (HK Intake)\n\n\nHow to apply\n\nSubmit your application only through\u00a0Kerry Logistics Job Application System\u00a0(yea.kerrylogistics.com). We do NOT accept email or other means of application.\n\nVirtual Information Session\n\nDate & time:\u00a0\u00a0\u00a0\u00a0\u00a028 January, 3pm via ZOOM\n\nRegistration:\u00a0 \u00a0 \u00a0Sign up\u00a0at\u00a0bit.ly/GT22info\u00a0by 25 January.\n\nA confirmation email with an access link will be sent on 26 January.\u00a0\n\n(We are an equal opportunity employer and welcomes applications from all qualified candidates.\u00a0All personal data will be kept in the strictest confidence and will be used for recruitment purpose only. All applicants maybe considered for other suitable positions in the Kerry Group and its members. All personal data of unsuccessful candidates will be destroyed.)", "employment_types": ["Full Time", "Permanent"], "selling_points": [], "locations": ["Kwai Fong"], "categories": ["Transportation & Logistics", "Others", "Fulfillment", "Supply Chain"], "post_time": "2022-01-17T02:39:29Z", "salary": {"currency": null, "max": null, "min": null, "period": "monthly", "term": null}, "salary_visible": false, "title_keywords": ["graduate trainee"], "responsibilities": ["recruitment", "personal data", "logistics", "application system"], "requirements": {"degrees": [], "majors": [], "languages": [], "language_level": [], "hard_skills": [], "soft_skills": ["passionate", "leadership"], "languages_combined": []}, "experience_required": {"duration": [], "field": ["related", "logistics"]}}, {"job_id": "100003009056859", "location_code": "hk", "company": "HK JEBN Limited", "job_title": "Purchasing officer/Purchaser ( Greater China Food Sourcing)", "description": "[Steam A:\u00a0Native Mandarin + Senior China-market Trader]\n\n[Steam B:\u00a0Good Mandarin + 5 years or above stated/lived in China]\n\n[Steam C:\u00a0Native Mandarin + Chinese Medicine / Food Science / industry calibre]\n\nMain Duties:\nPurchaser's duties:\nAct as a sourcing officer in purchasing department;\n\nHandle sourcing, price negotiation, payment terms, PO, Shipping Documents, order follow up as well as payment arrangement, etc;\n\nCommunicate between with suppliers and production teams;\n\nLiaise with factories for production schedule & quality checking;\n\nInternal communication with warehouse for stock management, food quality control, etc;\n\nOccasionally travel to Greater China region.\n\nCandidates with relative trading / sourcing experience in Greater China Region will be considered as Purchasing Officer / Sourcing Officer, in addition providing following duties:\n\nMeet with Ethnic Chinese (Mainland China / Taiwan / Hong Kong) vendors;\n\nSource and audit new suppliers;\n\nMaintain current product supply and ensure in stable quality;\n\nTravel to China / Taiwan, source and audit new suppliers;\n\nHandle price negotiation, cost comparison & analysis;\n\nImportant:\u00a0Instead of related experience in the field, good intuitive and common senses are overwhelmingly important requirements for the above position. Candidate with following knowledge is preferred: Chinese Medicine, Food and Nutrition, Food Science, Biological Science, Logistics, Supply Chain\n\nRequirements:\nDegree holder, preferably in Chinese Medicine , Food and Nutrition, Food Science, Biological Science, Logistics, Supply Chain, Accounting & Finance, Linguistics , Business administration disciplines;\n\nGood command in both written and spoken Mandarin plus Native Cantonese Speaking;\n\n2-6 years' working experience, preferably in sales or trading, purchasing office, retail industry;\n\nGood understanding of China's business environment / culture is preferred;\n\nGood Knowledge of Chinese culinary, supply chain, food science, etc is an advantage;\n\nHolder of driving license (Hong Kong and China);\n\nAble to work multi-tasks under pressure and deliver on schedule;\n\nSelf-motivated, positive, energetic and keen on learning;\n\nGood numerical sense plus proficiency in usage of EXCEL tool is definite advantage;\n\nStrong team player and communicator;\n\nDisciplinary, punctual.\n\nWe offer 5-day work, Free lunch, Monthly incentive, 12 days annual leave, Birthday leave, 10 days paternity leave, Employee purchase discount, Medical insurance and Annual body check to the above position.\n\nInterested parties please send Full resume to HK JEBN LIMITED, including the following details:\n\n1) Availability\n\n2) Expected salary\n\n3) Present salary\n\n\nHK JEBN Group policies on non-recruitment of smokers or other tobacco users.\nAll personal data collected will be treated in strict confidential and be used for recruitment purpose solely.", "employment_types": ["Full Time"], "selling_points": [], "locations": ["Not Specified"], "categories": ["Beauty Care / Health", "Others", "Transportation & Logistics", "Supply Chain"], "post_time": "2022-01-18T06:34:41Z", "salary": {"currency": null, "max": null, "min": null, "period": "monthly", "term": null}, "salary_visible": false, "title_keywords": ["purchasing officer"], "responsibilities": ["shipping documents", "price negotiation", "quality checking", "stock management", "cost", "analysis", "teams", "audit", "quality", "communication", "payment", "maintain", "logistics", "schedule", "quality control", "liaise with"], "requirements": {"degrees": ["degree holder"], "majors": ["business administration", "biological science", "finance", "accounting", "food science"], "languages": ["cantonese", "chinese", "mandarin"], "language_level": ["native", "good command", "good", "advantage"], "hard_skills": ["excel", "plus"], "soft_skills": ["self-motivated", "under pressure", "multi-tasks", "keen", "learning", "business environment", "team player", "energetic", "positive", "communicator"], "languages_combined": [{"language": "cantonese", "language_level": ["good command"]}, {"language": "chinese", "language_level": ["advantage"]}, {"language": "mandarin", "language_level": ["native", "good", "native", "good command"]}]}, "experience_required": {"duration": ["2-6 years"], "field": ["purchasing", "retail industry", "trading"]}}, {"job_id": "100003009053842", "location_code": "hk", "company": "Professional Health Trading Company Limited", "job_title": "\u7269\u6d41\u5354\u8abf\u54e1", "description": "\n\u8077\u8cac :\u8ddf\u9032\u92b7\u552e\u5718\u968a\u7684\u92b7\u552e\u8a02\u55ae\u4e26\u8207\u5167\u90e8\u548c\u5916\u90e8\u5404\u65b9\u806f\u7d61\u5f8c\u52e4\u5b89\u6392; \u8655\u7406\u3001\u6e96\u5099\u548c\u8a18\u9304\u4ea4\u4ed8\u6587\u4ef6; \u4fdd\u6301\u5eab\u5b58\u5340\u57df\u6574\u6f54; \u8655\u7406\u81e8\u6642\u5206\u914d\u7684\u4efb\u52d9\n\n\u8cc7\u6b77 :\u4e2d\u4e94\u7a0b\u5ea6; 2\u5e74\u7d93\u9a57; \u826f\u597d\u7cb5\u8a9e; \u4e00\u822c\u666e\u901a\u8a71; \u826f\u597d\u82f1\u8a9e; \u61c2\u8b80\u5beb\u4e2d\u6587; \u7565\u61c2\u8b80\u5beb\u82f1\u6587; \u61c2MS Word; \u61c2MS Excel; \u80fd\u7368\u7acb\u5de5\u4f5c\u4e26\u627f\u53d7\u58d3\u529b;\u826f\u597d\u5408\u4f5c\u7cbe\u795e;\u9858\u610f\u5b78\u7fd2;\u5177\u8655\u7406\u91ab\u7642\u7d93\u9a57\u512a\u5148\n\n\u5f85\u9047 :\u6bcf\u6708$17,000 - $18,000, \u6709\u96d9\u7ce7, \u661f\u671f\u4e00\u81f3\u4e94: \u4e0a\u53489\u6642\u81f3\u4e0b\u53486\u6642, \u6bcf\u9031\u5de5\u4f5c5\u5929, \u9700\u8981\u6642\u52a0\u73ed\u5de5\u4f5c\n\n\u7533\u8acb\u9808\u77e5 :\u6c42\u8077\u8005\u53ef\u96fb\u90f5(Apply Now)\u5c65\u6b77\u8868\u7d66\u5c08\u696d\u5eb7\u5065\u8cbf\u6613\u6709\u9650\u516c\u53f8\u3002\u5982\u8981\u7d22\u53d6\u6536\u96c6\u500b\u4eba\u8cc7\u6599\u8072\u660e, \u8acb\u8207\u80e1\u5148\u751f(Email)\u806f\u7d61\u3002\n\n", "employment_types": ["Full Time"], "selling_points": [], "locations": ["Kwun Tong Area"], "categories": ["Transportation & Logistics", "Others", "Inventory / Warehousing", "Supply Chain"], "post_time": "2022-01-17T07:36:43Z", "salary": {"currency": null, "max": null, "min": null, "period": "monthly", "term": null}, "salary_visible": false, "title_keywords": [], "responsibilities": [], "requirements": {"degrees": [], "majors": [], "languages": [], "language_level": [], "hard_skills": ["excel", "word"], "soft_skills": [], "languages_combined": []}, "experience_required": {"duration": [], "field": []}}, {"job_id": "100003009052833", "location_code": "hk", "company": "Panasonic Hong Kong Co., Limited", "job_title": "Officer (Operation Planning)", "description": "Responsibilities:\n\nPrepare schedule and coordinate Electronic Data Interchange with users, business partners, IT Dept and monitor the overall performance\nPrepare monthly reports and ad-hoc management reports for management analysis purpose\nCoordinate Global Freight Cost and container space issue with GFC Team and Operation team\nSupport improvement projects in system, operation and logistics aspects\nSupport in-house system login management\nPerform in-house training within Division\nPerform other ad-hoc projects as assigned\n\nRequirements:\n\nBachelor Degree or above in Business, Supply Chain Management, Computer Science or related discipline\n3 years relevant experience in international trading\nProficient in MS Office (Word, Excel, PowerPoint)\nGood command of English and Mandarin. Japanese is preferable\nGood analytical skills on reporting\nGood communication skills, well organized\n\nRemuneration will be commensurate with qualification and experience. Interested parties, please send your application with detailed resume indicating both existing & expected salary and date of availability to us.\n\nWe are an equal opportunity employer. All information provided by applicants will be treated in strict confidence and used for recruitment purpose only.", "employment_types": ["Full Time", "Permanent"], "selling_points": ["Knowledge in System & Operation Planning", "3 yrs relevant exp. in international trading", "Stable MNC in-house environment"], "locations": ["Tsim Sha Tsui"], "categories": ["Information Technology (IT)", "Product Management / Business Analyst", "Transportation & Logistics", "Supply Chain", "Merchandising & Purchasing", "Procurement / Purchasing / Sourcing"], "post_time": "2022-01-17T04:13:26Z", "salary": {"currency": null, "max": null, "min": null, "period": "monthly", "term": null}, "salary_visible": false, "title_keywords": ["officer"], "responsibilities": ["ad-hoc", "management", "cost", "monthly reports", "data", "analysis", "monitor", "coordinate", "management reports", "logistics", "schedule", "ad-hoc projects"], "requirements": {"degrees": ["degree or above", "bachelor"], "majors": ["business", "computer science"], "languages": ["japanese", "english", "mandarin"], "language_level": ["good command"], "hard_skills": ["excel", "word", "powerpoint", "analytical skills", "ms office"], "soft_skills": ["communication skills", "well organized", "analytical skills"], "languages_combined": [{"language": "japanese", "language_level": []}, {"language": "english", "language_level": ["good command"]}, {"language": "mandarin", "language_level": ["good command"]}]}, "experience_required": {"duration": ["3 years"], "field": ["relevant experience", "trading"]}}, {"job_id": "100003009056110", "location_code": "hk", "company": "DHL EXPRESS (HONG KONG) LIMITED", "job_title": "Customer Service Representative (Tracing Team)", "description": "Working Location: Ngau Tau Kok\nWorking Hours: Monday - Sunday, including public holidays 07:30-22:30 (5 days, average 42.5 hours per week)\nResponsibilities:\nYou will be responsible for providing quality customer services to both local and overseas clients through 24-hours hotline. You are required to handle shipment tracing and customer complaints, as well as to resolve customer enquiries and problems.\nRequirements:\nPost-secondary education (English & Chinese passed in HKCEE / HKDSE or equivalent)\nMore than 1 year customer service experience, preferably in logistic industry (Candidate with more than 3 years customer service experience will be considered as Customer Service Executive)\nGood command of spoken & written English and Chinese, proficiency in Mandarin is an advantage\nGood PC knowledge and typing skill with 40 wpm\nEffective interpersonal, communications, problem solving and telephone handling skills\nCustomer oriented, flexible, initiative and able to work under pressure\nFresh graduates of Degree/ Associate Degree with experiences in direct customer interfaces will also be considered\nApplication:\nClick \"Apply Now\" or apply on line via the following link:https://dhlexpress.taleo.net/careersection/ex/jobdetail.ftl?job=2100ATJ&iniurl.src=CWS-10001&tz=GMT%2B08%3A00&tzname=Asia%2FShanghai\nalso indicating your current and expected salary, and availability.\u00a0 For more job opportunities, please visit our website at https://www.dpdhl.jobs/\nPersonal Information Collection Statement pertaining to Recruitment\nDHL Express (Hong Kong) Limited / DHL Aviation (Hong Kong) Limited (\u201cDHL\u201d) is committed to protecting and respecting your privacy in accordance with the Personal Data (Privacy) Ordinance of Hong Kong (the \u201cOrdinance\u201d) and DHL\u2019s Personal Data Protection Policy (the \u201cPolicy\u201d) at https://www.dhl.com/hk-en/home/footer/local-privacy-notice.html\nBy proceeding to respond to this recruitment advertisement, you consent that we may use, retain, process, transfer or otherwise handle the personal data that we collect from you for recruitment,\u00a0 application processing, assessment and communication purposes (including any other purposes directly related thereto) in accordance with the Policy.\nAll personal data of unsuccessful applicants will be retained for future recruitment purposes for a period of not more than two (2) years after which such data will be destroyed.\nYou have the right at any time to make a data access or correction request concerning your personal data held by us. In addition, you may request us to delete your personal data that is no longer required for the relevant purposes which you have given consent. Should you wish to exercise such rights or have any question in relation to your personal data or the Policy, please contact our Human Resources Division in writing via \"Apply Now\"", "employment_types": ["Full Time", "Permanent"], "selling_points": ["Responsible for providing quality customer service", "More than 1 year customer service experience", "Post-secondary education"], "locations": ["Ngau Tau Kok"], "categories": ["Sales, CS & Business Devpt", "Customer Service - Supervisor / Officer", "Transportation & Logistics", "Supply Chain"], "post_time": "2022-01-18T03:19:57Z", "salary": {"currency": null, "max": null, "min": null, "period": null, "term": null}, "salary_visible": false, "title_keywords": ["customer service representative"], "responsibilities": ["customer enquiries", "customer complaints", "quality", "customer services"], "requirements": {"degrees": ["associate degree", "degree", "hkdse", "secondary education"], "majors": [], "languages": ["english", "chinese", "mandarin"], "language_level": ["advantage", "proficiency", "good command"], "hard_skills": ["no", "typing", "html", "problem solving", "make", "pc knowledge", "processing"], "soft_skills": ["flexible", "problem solving", "committed", "communication", "customer service", "interpersonal", "initiative", "work under pressure"], "languages_combined": [{"language": "english", "language_level": ["proficiency", "advantage", "good command"]}, {"language": "chinese", "language_level": ["proficiency", "advantage", "good command"]}, {"language": "mandarin", "language_level": ["proficiency", "advantage", "good command"]}]}, "experience_required": {"duration": ["3 years", "1 year"], "field": ["customer service"]}}, {"job_id": "100003009053969", "location_code": "hk", "company": "Global Airlift Solutions (Asia) Limited", "job_title": "Charter & Emergency Manager / Executive, Asia Pacific", "description": "Job description and responsibilities:\n\n\nSales & Marketing Activities\u00a0:\u00a0\u00a0\nMaintain active business relationship with potential and existing carriers and service providers\nIntroduce our service (Cargo Charter / On Board Courier / Critical Care Solutions - Express Airfreight) to customers / freight forwarders\nReceive visitors\u00a0\nProcess Air Cargo Charter and Emergency Requests :\nCharter quotations to GAS customers and GAS stations,\u00a0Issue contracts and perform customer order until completion\nResponsible to negotiate best possible terms and conditions with the suppliers to provide best in class emergency transport solutions (On Board Couriers and Critical Care Solutions, Express Airfreight)\nCommunicates new business opportunities\u00a0internally and externally, and the cooperation with (new) service providers.\nArrange cargo charter flight / Express Airfreight / On Board Courier operation and billing invoices / documentation\u00a0\n\u00a0Administration:\nResponsible for the invoicing of the handled jobs and accruals of the incoming jobs. Has the financial responsibility for own files.\n\u00a0Team Work:\nAssure the best possible team spirit within the team.\nFollow the procedures set on the team and effectively communication at all times with all parties involved during the charter and OBC operations.\n\nJob requirements:\nTeam player, Results-driven work style,\u00a0Be Fearless, Aggressive, Ambitious\nCreative problem solving skills / quick thinking / Multi-Tasking /\u00a0negotiation, communication & decision making skills\u00a0\nAbility to work with a flexible schedule, including morning / night shift and weekends, to adapt and grow in a changing, fast-paced work environment.\nGood verbal and written knowledge of English and one or more local language(s), fluent in Korean or Japanese Speaking is an advantage\nSeveral years of Airfreight Forwarding experience with an Airlines, Broker or Freight Forwarder is required\u00a0\nBasic knowledge of MS Office (Word, Excel, Outlook) and flair for IT systems as a user\n\nInterested parties please send full resume with experience, qualification with expected salary to Unit 10, 17/F, Grand City Plaza, Tsuen Wan, Hong Kong, fax via +852 3188 9719, or click \"Apply Now\" to apply\n\nPersonal data collected will be treated as strictly confidential and used for recruitment purpose only.\u00a0\n\nCandidate\u00a0with less experience will be considered as Charter & Emergency Executive, Asia Pacific\u00a0", "employment_types": ["Full Time"], "selling_points": ["Salary negotiable, depends on experience", "Flexible, ready to work in shifts and weekends", "Good in English, Teamwork"], "locations": ["Tsuen Wan Area"], "categories": ["Transportation & Logistics", "Aviation Services", "Freight Forwarding", "Supply Chain"], "post_time": "2022-01-17T07:52:30Z", "salary": {"currency": null, "max": null, "min": null, "period": "monthly", "term": null}, "salary_visible": false, "title_keywords": ["manager", "executive"], "responsibilities": ["issue contracts", "invoices", "operations", "business opportunities", "procedures", "invoicing", "communication", "maintain", "sales & marketing activities", "documentation", "administration"], "requirements": {"degrees": [], "majors": [], "languages": ["japanese", "english", "korean"], "language_level": ["advantage", "fluent", "good"], "hard_skills": ["excel", "basic", "word", "outlook", "airlines", "problem solving skills", "ms office"], "soft_skills": ["flexible", "decision making skills", "negotiation", "communication", "multi-tasking", "problem solving skills", "team player", "creative", "driven"], "languages_combined": [{"language": "japanese", "language_level": ["advantage", "good"]}, {"language": "english", "language_level": ["advantage", "good"]}, {"language": "korean", "language_level": ["fluent", "advantage", "good"]}]}, "experience_required": {"duration": [], "field": []}}, {"job_id": "100003009055187", "location_code": "hk", "company": "FedEx Trade Networks Transport & Brokerage (Hong Kong) Limited", "job_title": "Operations Analyst, Ocean / Associate Operations Analyst, Ocean", "description": "Responsibilities :\n\nAssist manager and team lead in handling day-to-day customer service, operations and documentation activities\nDesign internal SOP, guideline & work process to the team ensuring smooth operation & regulatory compliance\n\nDevelop and maintain various reports on performance measure\n\nMonitor KPI/SQI to achieve corporate target\n\nMonitor P&L accuracy\n\nRate quotation and RFQ\n\nCoordinate development, testing and implementation of system enhancement and new process\n\nAttend non-office hour calls and meetings\n\nOther ad hoc duties\n\nRequirements :\n\n44 working hours per week (Monday to Friday)\n\n\nAcademic:\n\nDiploma or Degree in Logistics or equivalent\nExperience & knowledge:\n\nMinimum of six (6) years professional experience in Ocean Freight Forwarding industry\nGood understanding of ocean cost and pricing structure\n\nStrong analytical, logical thinking and communications skills\n\nAttentive to details\n\nProficient in MS Office Application (e.g. MS Excel and Macro, MS Access, Powerpoint, Visio)\n\nExperience in handling massive database data is a plus\n\nFluent spoken & written in English & Chinese (Mandarin)\nLess experience candidate will consider as Associate Operations Analyst, Ocean\nImmediately available is highly preferred\n\n\nJoin FedEx and you'll be rewarded with an excellent salary and benefits package including guarantee two months' year-end bonus, medical and dental benefits, life insurance, provident fund, extra annual leave, and attractive promotional prospects.\n\nOur company addresses:\nUnit 801, 8/F, Metroplaza Tower 1\n223 Hing Fong Road, Kwai Fong\nN.T.\u00a0\n\nAll information provided by applicants will be treated in strict confidence and used only for recruitment purpose in accordance with the employer's personal data policies. A copy of Personal Information Collection Statement (PICS) will be provided upon request. Please write to the Human Resources Department. Applicants who are not invited to an interview within four weeks may consider their applications unsuccessful. All personal data of unsuccessful applicants will be destroyed after one year.\u00a0\n\nLess experience candidate will consider as\u00a0Associate Operations Analyst, Ocean", "employment_types": ["Full Time", "Permanent"], "selling_points": ["Guarantee 14 months paid with attractive benefits", "Freight fowarding industry & Ocean Operations", "Immediately available is highly preferred"], "locations": ["Kwai Fong"], "categories": ["Transportation & Logistics", "Freight Forwarding", "Shipping", "Supply Chain"], "post_time": "2022-01-18T01:42:19Z", "salary": {"currency": null, "max": null, "min": null, "period": "monthly", "term": null}, "salary_visible": false, "title_keywords": ["associate", "operations analyst"], "responsibilities": ["ad hoc duties", "operations", "compliance", "monitor", "quotation", "design", "develop", "p&l", "coordinate", "testing", "customer service", "maintain", "reports", "implementation", "documentation"], "requirements": {"degrees": ["diploma", "degree"], "majors": [], "languages": ["english", "chinese", "mandarin"], "language_level": ["fluent"], "hard_skills": ["plus", "macro", "powerpoint", "ms excel", "ms office"], "soft_skills": ["confidence", "attentive to details"], "languages_combined": [{"language": "english", "language_level": ["fluent"]}, {"language": "chinese", "language_level": ["fluent"]}, {"language": "mandarin", "language_level": ["fluent"]}]}, "experience_required": {"duration": [], "field": ["database"]}}, {"job_id": "100003009049637", "location_code": "hk", "company": "Phase Scientific International Limited", "job_title": "Senior Logistics officer", "description": "Responsibilities:\u00a0\n\nResponsible for handling full set of Import/Export documents, operation, booking and consolidation\n\nLiaise, communicate and co-ordinate with oversea office, agents, forwarders, carrier and customers\u00a0to ensure on-time delivery and maintain KPI\nResponsible for the daily operations of in/outbound shipment\nPrepare monthly report and KPI record\nManage freight and prepare shipping documents & conduct system update\nPrepare I/E customs declaration export from Hong Kong / China\nAssist in ad-hoc tasks as assigned by manager.\n\n\u00a0Knowledge and Skill Requirements:\u00a0\n\nDegree / Diploma holder from HK or Overseas in supply chain, logistics or related subjects\u00a0\u00a0\nAt least 8+ years working experiences in logistics, international freight, US import is a MUST\nExcellent working knowledge of Microsoft Office and Powerpoint\nAble to work independently and under pressure\u00a0\nProficiency in both spoken and written English, Chinese and Mandarin, knowing other languages would be an advantage\nProactive and mature team-mate willing to learn\nMedical Device experience is preferable\n\nWe offer an attractive basic salary, on-the-job training and career advancement opportunity to the right candidates.\u00a0 Please send full resume with availability, current and expected salary by clicking \"Apply Now\"\u00a0\n\n\u00a0\u00a0Benefits\n\n\u00a0\u00a0\u00a0\u00a0\u00a0\u00a0\u00a0\u00a0 Five-day work\n\u00a0\u00a0\u00a0\u00a0\u00a0\u00a0\u00a0\u00a0 Bank Holidays\n\u00a0\u00a0\u00a0\u00a0\u00a0\u00a0\u00a0\u00a0 Medical Insurance\n\u00a0\u00a0\u00a0\u00a0\u00a0\u00a0\u00a0\u00a0 12+ Days Annual leave\n\u00a0\u00a0\u00a0\u00a0\u00a0\u00a0\u00a0\u00a0 Paid Marriage Leave\n\u00a0\u00a0\u00a0\u00a0\u00a0\u00a0\u00a0\u00a0 Birthday Leave\n\n\u00a0(Personal data collected will be used for recruitment purpose only.)", "employment_types": ["Full Time"], "selling_points": ["Responsible for all logistics needs", "Handle full set of shipping documents", "Logistic arrangement"], "locations": ["Kwun Tong"], "categories": ["Transportation & Logistics", "Supply Chain"], "post_time": "2022-01-14T09:00:30Z", "salary": {"currency": null, "max": null, "min": null, "period": "monthly", "term": null}, "salary_visible": false, "title_keywords": ["senior logistics officer"], "responsibilities": ["liaise", "shipping documents", "customs declaration", "co-ordinate with", "system update", "ad-hoc tasks", "daily operations", "maintain", "booking", "monthly report"], "requirements": {"degrees": ["diploma holder", "degree"], "majors": [], "languages": ["english", "chinese", "mandarin"], "language_level": ["advantage", "proficiency"], "hard_skills": ["powerpoint", "microsoft office"], "soft_skills": ["work independently", "under pressure", "willing to learn", "mature", "proactive"], "languages_combined": [{"language": "english", "language_level": ["advantage", "proficiency"]}, {"language": "chinese", "language_level": ["advantage", "proficiency"]}, {"language": "mandarin", "language_level": ["advantage", "proficiency"]}]}, "experience_required": {"duration": ["at least 8+ years"], "field": ["logistics", "medical device"]}}, {"job_id": "100003009049973", "location_code": "hk", "company": "Hays", "job_title": "Supply Chain Project Specialist", "description": "Your new company\nThis is one of the largest chemical group in the world which operates in over 120 countries. They are rapidly expanding the APAC office and is now inviting Supply Chain professional who base in Hong Kong.\n\nYour new role\n\nDrive improvements on the supply chain process in the group level to make significant performance improvements\nImplement and roll out projects for SAP supply chain management, planning or transportation modules\nLead the SAP implementation project from user requirement identification, analysis, testing to training.\nCoordinate with business stakeholders including Super Users, IT, Supply Chain Operations team\n\n\nWhat you'll need to succeed\n\nSolid understanding of Supply Chain Process from forecasting to delivery\nExperience in supporting SAP implementation such as APO, IBP, WM, TM etc\nGood analytic skills and able to communicate with cross team departments\nGood command of English and Mandarin\n\nWhat you need to do now\nIf you're interested in this role, click 'apply now' to forward an up-to-date copy of your CV, or call us now.\nIf this job isn't quite right for you but you are looking for a new position, please contact us for a confidential discussion on your career.", "employment_types": ["Full Time", "Permanent"], "selling_points": ["Largest chemical group", "SAP supply chain modules", "Up to 45K"], "locations": ["Not Specified"], "categories": ["Information Technology (IT)", "Product Management / Business Analyst", "Transportation & Logistics", "Supply Chain", "Manufacturing", "Product Development / Management"], "post_time": "2022-01-14T09:34:01Z", "salary": {"currency": null, "max": null, "min": null, "period": "monthly", "term": null}, "salary_visible": false, "title_keywords": ["specialist"], "responsibilities": ["communicate with", "user requirement", "management", "operations", "analysis", "coordinate with", "implementation", "testing", "contact", "forecasting", "supply chain process", "planning"], "requirements": {"degrees": [], "majors": [], "languages": ["english", "mandarin"], "language_level": ["good command"], "hard_skills": ["make", "analysis", "analytic skills", "sap"], "soft_skills": ["interested in"], "languages_combined": [{"language": "english", "language_level": ["good command"]}, {"language": "mandarin", "language_level": ["good command"]}]}, "experience_required": {"duration": [], "field": []}}, {"job_id": "100003009052657", "location_code": "hk", "company": "NET-A-PORTER", "job_title": "Logistic Assistant/ Advisor (Online Fashion Retailer, Fresh Graduates are welcome)", "description": "NET-A-PORTER are now seeking a talented Logistic Assistant/ Advisor join the team. Some of the essentials for you to know are:\n\nLocation:\u00a0Tsing Yi Office\n\nReporting into:\u00a0Trade & Transport Manager\n\nHere is a breakdown of what you\u2019ll be doing:\n\n\n\nInbound :\u00a0\n\nChecks all applicable documentations are in place and ensuring Government/Customs compliance is adhered to for all markets prior to ship\nProvides Shipping Instructions to the 3PL Carriers/Courier & prepare necessary shipping docs (if need)\nLiaises with vendors / internal business partners to resolve problem that could delay the release or movement of shipments\nFollow up shipment status and ensure the goods receiving is completed in WMS\u00a0\nOutbound :\n\nCustomer services support on all B2B courier shipping arrangement & inquiries\nGeneral Admin :\nObtain 3 PL quotation with comparison\nEnsure system data & daily operation log files are accurate and updated in timely manner\n3PL Billing validation & payment application to Finance\nAssist management for any ad hoc reporting and analysis tasks\n\n\u00a0The type of person we are looking for:\n\nPositive Thinking, Passionate in work, Paying Attention to Details, also a Team-Player\nExcellent communication and computer skills, especially Excel in advance level\nAn understanding of I/E shipping documentations and procedures\nFamiliar the Tradelink, DHL / UPS booking system\nSound working knowledge of International Customs laws/Regulations and Trade Compliance policies, is a definite plus\nCandidate with 1-2 experience is a plus, but fresh graduate will be considered\nBesides a competitive salary, we can offer you:\n\nPerformance bonus schemes\u00a0dependent\u00a0on the type of role you are in\nOur famous staff discount along with exclusive staff sales\nMPF plus voluntary contribution from the company\nMulti-purpose insurance\nRental Reimbursement Program\nFlexible working\nA chance to be part of a fun and caring team that support each other", "employment_types": ["Full Time", "Permanent"], "selling_points": ["Fresh graduates are welcome to apply", "Progressive career path; Good learning opportunity", "Advanced in MS Excel is ideal"], "locations": ["Tsing Yi"], "categories": ["Transportation & Logistics", "Freight Forwarding", "Shipping", "Supply Chain"], "post_time": "2022-01-17T03:39:23Z", "salary": {"currency": null, "max": null, "min": null, "period": "monthly", "term": null}, "salary_visible": false, "title_keywords": ["advisor", "assistant"], "responsibilities": ["regulations", "shipping", "quotation", "communication", "payment", "wms", "ad hoc", "tradelink", "compliance", "customer services", "reporting", "management", "mpf", "procedures", "system data", "booking", "policies", "analysis", "daily operation", "insurance"], "requirements": {"degrees": ["fresh graduate"], "majors": [], "languages": [], "language_level": [], "hard_skills": ["excel", "plus", "fun", "analysis", "computer skills", "pl", "documentations"], "soft_skills": ["passionate", "flexible", "team-player", "timely", "positive thinking", "communication", "attention to details", "accurate"], "languages_combined": []}, "experience_required": {"duration": [], "field": []}}, {"job_id": "100003009046448", "location_code": "hk", "company": "FRED Paris", "job_title": "Regional Supply Chain Executive", "description": "Reporting to the Regional Supply Chain Manager of Asia Pacific, you will be responsible to drive and support the supply chain and product distribution of the region:\n\n1. Supply Planning\n\nRegular review the stock situation in APAC to maximize the product availability based on the assortment and Model Stock defined.\nAssist in managing the regular update of model stock of APAC to maximize the product availability and control overstock.\n2. Product Supply Chain and Distribution\nSupport Daily stock request from markets, coordinate stock transfers between markets and HQ.\nCoordinate with HQ and markets on medium / high jewellery product flow management, rotation plan and drive stock balance within the region.\nMonitor the interfaces for proper communication between systems. Liaise and report the issues to HQ/ IT.\nManage the logistics of novelties according to launch plan, coordinate together with HQ and markets on the product arrival\nDrive stock re-balancing within the region.\nCoordinate with markets on quality control action/ correction to put in place.\nSupport the product arrangement of different events including but not limited to boutique opening, events etc.\n3. Logistics Management of TR:\nCo-ordination with HQ on the Travel Retail replenishment arrival for merchandise and the non-merchandise\nPlacing Sales Order, closely follow up on the replenishment order and monitor the stock/ non-merchandise status\nCo-ordination between 3rd party logistics and business partner for shipment to Travel Retailer business, providing visibility on the shipment arrival, taking care the documentation ensure the physical stock/ documentation is aligned\nJob requirements\n\nUniversity degree in business administration / logistic related\nAt least 5 years\u2019 experience in Supply Chain and Operations\nExcellent PC skill, especially MS Excel. Knowledge ERP system, SAP would be a plus.\nStrong analytical and numerical skills, attentive to details\nStrong interpersonal skills, communication skills and negotiation skills\nStrong self-motivation and able to work under pressure\nCustomer oriented, Experience of luxury industry is an advantage\nProblem solving skills and result-oriented\n\nInterested parties please\u00a0send us a detailed resume stating present and expected salary\u00a0by clicking \"Apply Now\" to proceed with your application. We regret only short-listed candidates will be notified. The personal data collected will be used for recruitment purposes only.", "employment_types": ["Full Time", "Permanent"], "selling_points": ["Brand with unconditional love of stones and pearls", "Drive and explore in jewellery business", "Min. 5 years relevant experience in Supply Chain"], "locations": ["Quarry Bay"], "categories": ["Transportation & Logistics", "Inventory / Warehousing", "Supply Chain"], "post_time": "2022-01-13T11:15:14Z", "salary": {"currency": null, "max": null, "min": null, "period": "monthly", "term": null}, "salary_visible": false, "title_keywords": ["supply chain executive"], "responsibilities": ["liaise", "operations", "regular review", "communication", "plan", "administration", "work under pressure", "control", "stock balance", "monitor", "logistics", "product arrangement", "report", "reporting", "management", "coordinate with", "documentation", "systems", "replenishment", "coordinate", "quality control", "planning"], "requirements": {"degrees": ["university degree"], "majors": ["business administration"], "languages": [], "language_level": [], "hard_skills": ["supply planning", "plus", "sap", "pc skill", "ms excel", "erp system", "numerical skills", "luxury industry", "documentation", "problem solving skills"], "soft_skills": ["communication skills", "attentive to details", "responsible", "communication", "negotiation skills", "self-motivation", "interpersonal skills", "problem solving skills", "result-oriented", "work under pressure"], "languages_combined": []}, "experience_required": {"duration": ["at least 5 years"], "field": ["supply chain"]}}, {"job_id": "100003009056735", "location_code": "hk", "company": "PCC Asia Limited", "job_title": "Customer Service Coordinator", "description": "Responsibilities:\nProvide the best services to customer\nWork closely with the sales, purchasing, shipping and warehouse teams\nAssist sample arrangement for customer\nKeep track of delivery and ensure on time delivery to the customer\nHandle daily customer correspondence through phone call and email\nMaintain data accuracy in the system\nOther ad-hoc tasks designated by the supervisor\nRequirements:\n\u00a0F.5 or above\n2 years or more work experience in garment trims or related industry is preferable\nExperience in customer support or related industry is a plus\nExcellent communication and interpersonal skill\nProficiency in computer knowledge\nGood communication in English and Chinese\nWe offer an attractive remuneration package including 5-days work, medical scheme and bank holidays to the right candidate. If you aspired to an exciting and rewarding career, please send a full resume with expected salary and available starting date by clicking \u201cAPPLY NOW\u201d to the Human Resources Department.\n\nTo know more about us, please visit our website at\u00a0www.chargeurs-pcc.com\n\n\n(Personal data collected will be kept confidential and used for recruitment purpose only.)", "employment_types": ["Full Time", "Permanent"], "selling_points": [], "locations": ["Kwun Tong"], "categories": ["Transportation & Logistics", "Documentary Credit / Bills Processing", "Supply Chain", "Sales, CS & Business Devpt", "Account Servicing"], "post_time": "2022-01-18T06:06:37Z", "salary": {"currency": null, "max": null, "min": null, "period": "monthly", "term": null}, "salary_visible": false, "title_keywords": ["customer service coordinator"], "responsibilities": ["shipping", "ad-hoc tasks", "ensure on time delivery", "teams", "maintain data"], "requirements": {"degrees": [], "majors": [], "languages": ["english", "chinese"], "language_level": ["good"], "hard_skills": ["plus"], "soft_skills": ["communication", "interpersonal skill"], "languages_combined": [{"language": "english", "language_level": ["good"]}, {"language": "chinese", "language_level": ["good"]}]}, "experience_required": {"duration": ["2 years"], "field": ["garment", "related"]}}, {"job_id": "100003009049213", "location_code": "hk", "company": "BOA Technology Hong Kong Limited", "job_title": "Supply Chain Specialist", "description": "WORK WITH US.\n\nPursue your passion for adventure and innovation at BOA.\n\nLIFE AT BOA.\n\nWe are a team of innovators, disruptors, creators, and so much more. We know the importance of actively pursuing goals and the excitement of taking calculated risks to push what\u2019s possible and create what\u2019s next.\n\nDoes life as a pioneer at BOA sound like the place for you? If so, check out our open position below and submit your application today!\n\nOVERVIEW OF THE ROLE\n\nReporting to the Assistant Supply Chain Manager \u2013 this role is to lead and drive end to end supply chain activities concentrate on developing and implementing integrated supply and demand planning strategies that improve cost efficiency, increase business effectiveness, and create synergies and collaboration across companies. You will be able to drive continuous improvement initiatives throughout the extended supply chain.\n\nCORE RESPONSIBILITIES\n\nRegularly role model the Core Operating Principles to your team and others\u00a0\nAssist manager to develop and execute long term supply chain strategy roadmap to support company business growth\nIntegrated supply chain planning that links from customer demand to operations planning/scheduling to enhance customers satisfaction and shipment reliability\nDevelop and compile analytical reports to facilitate decision making of management under tight timeline\nBuild systematic process in the entire supply chain to proactively alert the potential risks, ensuring timely escalating to key stakeholders\nManage Product Phase in/Out timeline such as Production, capacity, and inventory planning\nProactively conduct global data collection, research, studies that facilitates the process of supply chain strategy development\nRe-engineering and simplification on process, workflow, and report to improve supply chain speed and agility (e.g. S&OP activities, volume forecasting, etc.)\nLead, participate and support supply chain or other projects as appropriate\n\n\u00a0REQUIRED QUALIFICATIONS\n\nTertiary education\nOccasional travelling is required\n8+ years supply chain planning experience\nStrong interpersonal (verbal and written) communication and presentation skills\nStrong cross functional skills to work with different departments, and companies\nFluent in written and spoken English and Cantonese, with Mandarin is a plus\nHigh proficient in MS excel, PowerPoint is a Must\nExcellent analytical skills with the ability to collect, organize and turn data into information and insights\nProactive, solution driven and self-motivated. Ability to identify problems, demonstrate use of initiative and implement appropriate solutions.\nAbility to work sensitively with confidential material\n\n\u00a0DESIRED QUALIFICATIONS\n\nExperience with shoes manufacturing or international trading industry is preferred\nExperience with Microsoft NAV is preferred\nExperience on project, and process improvement are advantage\nFamiliar with VBA, Power BI,\u00a0and programming tools to build customized report\n\nBENEFITS\n\nWe\u2019re committed to helping our people be themselves, be well, and grow. We\u2019re proud to offer a creative work environment with a range of benefits no matter where you are around the world.\u00a0\n\nFun, friendly workplace with social adventures and activities\nHealth and Wellness program\nSupport for local communities\nLearning and development opportunities\nCompetitive remuneration package\n\nWe are an equal opportunity employer.\u00a0 We offer competitive remuneration package to the right candidates.\u00a0 Interested parties please send full resume with current and expected salary and availability by clicking the \"Apply Now\" button. All Personal data collected will be kept in strict confidence and will be used for recruitment related purpose only.", "employment_types": ["Full Time", "Permanent"], "selling_points": ["VBA, Power BI", "Learning and development opportunities", "Friendly workplace"], "locations": ["Shatin Area"], "categories": ["Transportation & Logistics", "Supply Chain", "Manufacturing", "Production Planning / Control"], "post_time": "2022-01-14T08:16:24Z", "salary": {"currency": null, "max": null, "min": null, "period": "monthly", "term": null}, "salary_visible": false, "title_keywords": ["specialist"], "responsibilities": ["reporting", "cost", "management", "inventory planning", "power bi", "data", "operations", "demand planning", "developing", "develop", "communication", "scheduling", "reports", "data collection", "report", "forecasting", "re-engineering", "planning"], "requirements": {"degrees": [], "majors": [], "languages": ["cantonese", "english", "mandarin"], "language_level": ["fluent"], "hard_skills": ["vba", "plus", "bi", "demand planning", "powerpoint", "analytical skills", "ms excel", "programming"], "soft_skills": ["solution driven", "initiative", "self-motivated", "passion for", "timely", "systematic", "analytical skills", "communication", "presentation skills", "proactive", "interpersonal", "decision making"], "languages_combined": [{"language": "cantonese", "language_level": ["fluent"]}, {"language": "english", "language_level": ["fluent"]}, {"language": "mandarin", "language_level": ["fluent"]}]}, "experience_required": {"duration": ["8+ years"], "field": ["manufacturing", "trading", "supply chain planning"]}}, {"job_id": "100003009053750", "location_code": "hk", "company": "Tronic Technology International (Hong Kong) Limited", "job_title": "\u5009\u52d9\u54e1/\u7406\u8ca8\u54e1", "description": "\n\u8077\u8cac :\u4e00\u822c\u5009\u52d9\u5de5\u4f5c, \u5982\u6536\u8ca8, \u9ede\u8ca8, \u57f7\u8ca8, \u4e0a\u67b6, \u767c\u8ca8\u7b49\n\n\u8cc7\u6b77 :\u5c0f\u516d\u7a0b\u5ea6; \u826f\u597d\u7cb5\u8a9e; \u61c2\u8b80\u5beb\u4e2d\u6587; \u7565\u61c2\u8b80\u5beb\u82f1\u6587; \u6301\u6709\u4f01\u93df\u724c\u512a\u5148\n\n\u5f85\u9047 :\u6bcf\u6708$11,000 - $14,000, \u6709\u8d85\u6642\u5de5\u4f5c\u6d25\u8cbc, \u96d9\u7ce7, \u52e4\u5de5\u734e\u91d1, \u5e74\u504710\u5929, \u9280\u884c\u5047\u671f \u53ca\u7a7f\u68ad\u5df4\u58eb\u670d\u52d9, \u661f\u671f\u4e00\u81f3\u4e94: \u4e0a\u53489\u6642\u81f3\u4e0b\u53486\u6642\u53ca\u661f\u671f\u516d: \u4e0a\u53489\u6642\u81f3\u4e0b\u53481\u6642, \u6bcf\u9031\u5de5\u4f5c5\u5929\u534a, \u6bcf\u5929\u5de5\u4f5c 8 \u5c0f\u6642\n\n\u7533\u8acb\u9808\u77e5 :\u6c42\u8077\u8005\u53ef\u96fb\u90f5(Apply Now)\u5c65\u6b77\u8868\u7d66\u5275\u9818\u79d1\u6280\u570b\u969b(\u9999\u6e2f)\u6709\u9650\u516c\u53f8\u3002\u5982\u8981\u7d22\u53d6\u6536\u96c6\u500b\u4eba\u8cc7\u6599\u8072\u660e, \u8acb\u8207\u9f94\u5148\u751f(Email)\u806f\u7d61\u3002\n\n", "employment_types": ["Full Time"], "selling_points": [], "locations": ["Yuen Long"], "categories": ["Transportation & Logistics", "Others", "Inventory / Warehousing", "Supply Chain"], "post_time": "2022-01-17T07:27:35Z", "salary": {"currency": null, "max": null, "min": null, "period": "monthly", "term": null}, "salary_visible": false, "title_keywords": ["\u7406\u8ca8\u54e1", "\u5009\u52d9\u54e1"], "responsibilities": [], "requirements": {"degrees": [], "majors": [], "languages": [], "language_level": [], "hard_skills": [], "soft_skills": [], "languages_combined": []}, "experience_required": {"duration": [], "field": []}}, {"job_id": "100003009049025", "location_code": "hk", "company": "Shun Hing Logistics Company Limited", "job_title": "Logistics Assistant", "description": "Responsibilities\n\nResponsible for local delivery scheduling and customer enquiries\nAssist in departmental workflow and system development\nCoordinate and liaise with cross-functional departments towards the aims of sustaining highest customer satisfactory level\nWork closely with internal and external parties for handling delivery orders arrangement\nMaximize fleet utilization\nPerform other related duties as assigned\n\n\nRequirements\n\nHigher Diploma in Logistics Management or related discipline\n2 years' working experience in logistics or vehicle management\nGood interpersonal skills with customer oriented\nProficiency in MS Office application\nFluent in English and Chinese\nKnowledge of WMS or TMS system is an advantage\nLess experience with tertiary education level will also be considered\n\n\nAttractive package and fringe benefits will be offered to the right candidate. Please send your application together with your full resume, present and expected salary to Human Resources Manager of Shun Hing Logistics Co. Ltd.:\u00a0\u00a0\n\nBy post: 9/F, Shun Hing Centre, 2 Shing Yiu Street, Kwai Chung, N.T.; or\nBy email: acheung @ shunhinggroup.com\u00a0\n\nData collected will be used for recruitment purpose only. It may be transferred to other companies of the Group to see if suitable vacancies arise. Applicants not contacted within 6 weeks may consider their application unsuccessful. The information will be destroyed.", "employment_types": ["Full Time", "Permanent"], "selling_points": [], "locations": ["Kwai Fong"], "categories": ["Sales, CS & Business Devpt", "Customer Service - Supervisor / Officer", "Transportation & Logistics", "Inventory / Warehousing", "Supply Chain"], "post_time": "2022-01-14T07:56:57Z", "salary": {"currency": null, "max": null, "min": null, "period": "monthly", "term": null}, "salary_visible": false, "title_keywords": ["logistics", "assistant"], "responsibilities": ["customer enquiries", "internal and external parties", "coordinate", "scheduling", "liaise with"], "requirements": {"degrees": ["diploma"], "majors": [], "languages": ["english", "chinese"], "language_level": ["fluent"], "hard_skills": ["ms office"], "soft_skills": ["interpersonal skills"], "languages_combined": [{"language": "english", "language_level": ["fluent"]}, {"language": "chinese", "language_level": ["fluent"]}]}, "experience_required": {"duration": ["2 years"], "field": ["management", "logistics", "education"]}}, {"job_id": "100003009047493", "location_code": "hk", "company": "Unicorn Stores (HK) Limited", "job_title": "Logistic Assistant / Officer", "description": "Job Description\n\nMonitor import/export shipments with courier/logistics service provider\nPrepare invoice, shipping documents\u00a0and clerical duties\nWork closely with Merchandising team and Operations team\nGenerate monthly reports\nCoordinate with different parties for on-time shipments and necessary documentations\nAssist in handling\u00a0all aspects of logistic\u00a0and necessary documents\nCooperate with team members and others to achieve desired results and support business needs\nLiaise with shipping forwarders\u00a0\nAll export procedures with shipping forwarder and third-party shipping system\nAble to handle L/C banking documents independently\nHandle full set of I/E documents, Tradelink customs declaration\nPerform ad-hoc duties as assigned\u00a0\n\n\u00a0Requirement & Qualification\n\nDiploma or above, preferably in Logistics or Supply Chain related fields\n1-3 years\u00a0relevant working experience,\u00a0fresh graduatewill also be considered\nGood Cantonese, Mandarin and English written and verbal communication skills\nFamiliar with MS Office application, including Word, Excel & Chinese Word Processing (Familiar with SAP or ERP)\nMust be detailed-mind, flexible, independent, challenging and able to work under pressure\nImmediately available preferred", "employment_types": ["Full Time", "Permanent"], "selling_points": ["FMCG / Retail Industry", "Double Pay, Discretionary Bonus", "Immediate availability is preferred"], "locations": ["Tai Koo"], "categories": ["Transportation & Logistics", "Freight Forwarding", "Inventory / Warehousing", "Supply Chain"], "post_time": "2022-01-14T03:19:47Z", "salary": {"currency": null, "max": null, "min": null, "period": "monthly", "term": null}, "salary_visible": false, "title_keywords": ["officer", "assistant"], "responsibilities": ["shipping documents", "shipping", "customs declaration", "tradelink", "monthly reports", "invoice", "operations", "ad-hoc duties", "monitor", "merchandising", "coordinate with", "achieve desired results", "procedures", "logistics", "support business needs", "banking", "liaise with", "cooperate with"], "requirements": {"degrees": ["diploma or above"], "majors": [], "languages": ["cantonese", "english", "chinese", "mandarin"], "language_level": ["good"], "hard_skills": ["excel", "chinese word processing", "sap", "word", "erp", "ms office"], "soft_skills": ["flexible", "communication skills", "independent", "detailed", "work under pressure"], "languages_combined": [{"language": "cantonese", "language_level": ["good"]}, {"language": "english", "language_level": ["good"]}, {"language": "chinese", "language_level": []}, {"language": "mandarin", "language_level": ["good"]}]}, "experience_required": {"duration": ["1-3 years"], "field": ["relevant working experience"]}}, {"job_id": "100003009053701", "location_code": "hk", "company": "Hong Kong Aircraft Engineering Co Ltd", "job_title": "Coordinator (Inventory Management)", "description": "HAECO ITM Limited is a joint venture between HAECO (Hong Kong Aircraft Engineering Co. Ltd) and Cathay Pacific, providing inventory technical management services to different airline customers in Hong Kong and around the world. Customers anticipate to benefit saving from the ITM services through synergy of component pooling, sound technical know-how of component engineering, repair and supplier management.\n\nHXITM is now looking for candidates who are interested in this business for the position of\u00a0Coordinator (Inventory Management).\n\nScope of Duties:\u00a0\n\nAnalyze provisioning parameter, customer fleet data, part reliability and repair time performance to determine the optimum stock level and provisioning policy\nManaging Float module template and incorporating changes as approved\nRecommend changes in inventory level and support model where appropriate based on analysis and simulation on part shortage promptly, by gathering information, interfacing with functional teams, and monitoring shortage recovery continuously\nProduce and deliver regular inventory reports and maintain relevant database to support inventory operations planning and control in an effective and efficient manner\nInteract, communicate, and influence functional teams for appropriate action based on stock level alert and failed pick analysis\n\nRequirements:\u00a0\n\nA minimum of 1 year of relevant experience, preferably in Inventory Management, Operations, Planning field or Material control.\nFresh graduates are welcome\nA recognized Degree in Supply Chain, Business Analysis, or related disciplines\nKnowledge or experience in aviation industry would be an advantage\nGood analytical and problem-solving skills, able to think systematically and holistically\nSkillful in preparing analytical report and presentations with MS Excel, MS Access, MS PowerPoint\nGood command of English, both spoken and written\n\nHow to Apply:\n\nPlease send your resume with expected salary, quoting the employer's reference no., to: Human Resources Department - Talent & Partnership Team, Hong Kong Aircraft Engineering Company Limited, 80 South Perimeter Road, Hong Kong International Airport, Lantau, Hong Kong OR submit your application via\u00a0https://careers.haeco.com/hkg/job-opening-itm/\n\nCandidates not contacted 4-6 weeks after submission of applications and/or interviews may consider their application unsuccessful.\n\nAll information provided by candidates will be treated in strict confidence and will be used for employment purpose only.", "employment_types": ["Full Time", "Permanent"], "selling_points": ["A minimum of 1 year of relevant experience", "Fresh graduates are welcome", "Good analytical and problem-solving skills"], "locations": ["Airport Area"], "categories": ["Professional Services", "Business Analysis / Data Analysis", "Transportation & Logistics", "Inventory / Warehousing", "Supply Chain"], "post_time": "2022-01-17T07:23:08Z", "salary": {"currency": null, "max": null, "min": null, "period": "monthly", "term": null}, "salary_visible": false, "title_keywords": ["inventory management", "coordinator"], "responsibilities": ["control", "data", "operations", "analysis", "inventory", "teams", "monitoring", "repair", "maintain", "reports", "database", "planning"], "requirements": {"degrees": ["degree"], "majors": ["related disciplines", "business"], "languages": ["english"], "language_level": ["good command"], "hard_skills": ["no", "aircraft", "analysis", "presentations", "ms excel", "problem-solving skills", "ms powerpoint"], "soft_skills": ["problem-solving skills", "confidence"], "languages_combined": [{"language": "english", "language_level": ["good command"]}]}, "experience_required": {"duration": ["minimum of 1 year"], "field": ["inventory management", "relevant experience", "planning"]}}, {"job_id": "100003009053628", "location_code": "hk", "company": "Cargo Services Far East Limited", "job_title": "Key Account Executive (Ocean Freight)", "description": "Take responsibility of the customer experience by managing the customers\u2019 international supply chain in coordination with relevant stakeholders;\nBuild strong customer relationships, solve customer query about operations and be curious around their business needs and drivers, to better serve them and identify new business opportunities;\nEnsure smooth execution of the end-to-end shipment lifecycle, monitor agreed service level and build operational knowledge\n\n\u00a0\nRequirements:\nUniversity graduate with a Bachelor's degree from a recognised institution\nOr holder of Higher Diploma / Associate Degree with minimum 2 years working experience in logistics industry\nStrong communication and inter-personal skills\nHigh willingness to accept responsibility and drive results\nAbility to work with a high number of teams internationally and internal stakeholders on various projects\nGood command of both written and spoken English and Chinese\nProficient with Microsoft Office applications\nWilling to learn and work under pressure\nCandidates will more experienes will also be considered senior role\nBenefits:\nDouble Pay\n\nFive-day Work Week\n\nBirthday Leave\n\nMedical Insurance\n\nFree Shuttle Bus\u00a0\n\nTraining Allowance\nAttractive remuneration package and excellent career development opportunities will be offered to the right candidates. For Interested parties, please apply with a detailed resume stating present and expected salary by clicking \"Apply Now\". You are welcome to visit our website at http://www.cargofe.com.\n\nPersonal data collected will be used for recruitment purposes only and be treated in strict confidence.\u00a0 Cargo Services treats all applicants for employment in the same way, regardless of age, sex, marriage and civil partnership, race, disability, religion or belief.", "employment_types": ["Full Time", "Permanent"], "selling_points": ["Account Management in Freight Forwarder", "Five-day work week; Double Pay; Flexi-Office-Hours", "2+ years relevant experiences or Fresh graduates"], "locations": ["Kwai Tsing Area"], "categories": ["Transportation & Logistics", "Freight Forwarding", "Supply Chain", "Sales, CS & Business Devpt", "Account Servicing"], "post_time": "2022-01-17T07:15:41Z", "salary": {"currency": null, "max": null, "min": null, "period": "monthly", "term": null}, "salary_visible": false, "title_keywords": ["key account executive"], "responsibilities": ["operations", "business opportunities", "coordination with", "monitor", "teams", "communication", "logistics", "work under pressure"], "requirements": {"degrees": ["associate degree", "university graduate", "bachelor", "diploma", "degree"], "majors": [], "languages": ["english", "chinese"], "language_level": ["good command"], "hard_skills": ["microsoft office"], "soft_skills": ["willing to learn", "inter-personal skills", "communication", "coordination", "smooth", "work under pressure"], "languages_combined": [{"language": "english", "language_level": ["good command"]}, {"language": "chinese", "language_level": ["good command"]}]}, "experience_required": {"duration": ["minimum 2 years"], "field": ["logistics industry", "supply chain"]}}, {"job_id": "100003009051643", "location_code": "hk", "company": "Emperor Watch & Jewellery (HK) Company Limited", "job_title": "Logistic Clerk", "description": "Responsibilities:\n\nData entry and price tag handling\nHandle goods packaging according to company standards\nLiaise with other department on merchandise transfer and delivery issue\nProvide administrative and clerical support\nHandling ad hoc assignments as required\n\n\nRequirements:\n\nForm 5 graduate or above\nMinimum 1 year of working experience,\u00a0 worked in Jewellery industry would be an advantage\nExperience gained from logistic field is also considered\nFamiliar with SAP system would be an advantage\nWilling to learn, with strong attention to detail\nGood PC application skills\nGood command of both English and Mandarin\nImmediately available is preferred\n\nWe offer 5-day-work week with competitive remuneration and benefit packages to the right candidate. Interested parties please send your application letter, resume, expected salary and availability to Human Resources Department, 25/F, Emperor Group Centre, 288 Hennessy Road, Wanchai, Hong Kong or by\u00a0APPLY NOW\u00a0or by email to ewjrecruitment01 @ emperorgroup . com\u00a0\n\nWe are an equal opportunity employer and welcome applications from all qualified candidates. The information provided will be treated in strict confidence and be used only for consideration of your application for relevant / similar posts within the Emperor Group. Applicants not hearing from us within four weeks from the date of advertisement may consider their applications unsuccessful. We retain the unsuccessful applications for a maximum period of 24 months.", "employment_types": ["Full Time", "Permanent"], "selling_points": ["5-day work", "Data entry and price tag handling", "Administrative and clerical support"], "locations": ["Wan Chai"], "categories": ["Transportation & Logistics", "Others", "Inventory / Warehousing", "Supply Chain"], "post_time": "2022-01-16T17:39:04Z", "salary": {"currency": null, "max": null, "min": null, "period": null, "term": null}, "salary_visible": false, "title_keywords": ["logistic clerk"], "responsibilities": ["liaise with", "ad hoc assignments", "administrative and clerical support", "data entry"], "requirements": {"degrees": ["form 5"], "majors": [], "languages": ["english", "mandarin"], "language_level": ["good command"], "hard_skills": ["pc", "sap"], "soft_skills": ["willing to learn", "attention to detail"], "languages_combined": [{"language": "english", "language_level": ["good command"]}, {"language": "mandarin", "language_level": ["good command"]}]}, "experience_required": {"duration": ["minimum 1 year"], "field": []}}, {"job_id": "100003009048702", "location_code": "hk", "company": "UAG Hong Kong Limited", "job_title": "Supply Chain Specialist", "description": "Company Overview\n\nAt Urban Armor Gear (UAG), our mission is to provide high quality mobile solutions combined with unparalleled customer service and industry leading warranties. We believe in empowering mobile users with highly valued products giving them complete peace of mind.\n\nUAG products are designed by adventure seekers for adventure seekers.\n\nAt UAG we work hard and play hard; channeling our inspiration into hard work and pushing the limits of conventional ideas to create superior products. We are a platoon of talented designers, engineers, and marketers corralled by unparalleled leadership. UAG products are sold worldwide through premium e-commerce channels including Amazon.com, eBay, and Rakuten Shopping and specialty retailers in the U.S.\n\nMission\n\nWe are looking for an energetic Supply Chain professional to help us move the company to the next stages of its evolution and growth. Your new role will work across the global SCM team to be accountable for analyze all activities associated with supply planning, logistic, demand planning, and inventory management.\u00a0 You will support 1) avoid the business interruptions and ensure continuity of supply; 2) minimize the logistic cost while maintain the efficient order fulfillment; 3) leverage cross-functions efforts in the global team to continually improve performance and deliver on supply, demand, and logistic KPIs.\n\nEssential Job Functions\n\nSupport the analysis work for weekly purchase decision\nMaintain and track logistical costs for reporting and efficiency\nManage the freight schedule to align the inventory availability and goods delivery to worldwide with the lowest possible cost.\nAssist in preparation of supply chain report to facilitate the decision making\nAssist in the inventory planning and stock control\n\nRequired Skills and Experience\n\n3 - 5 years of experience in supply chain role in short life cycle consumer goods/electronics\nBachelor\u2019s degree in Business Administration, Supply Chain Management or equivalent experience\nExperience using MS Office, ERP, data warehouse, and planning tools\nExcellent communication skills (written & oral)\nKnowledge of sophisticated supply chain concepts and processes, having manufacturing concept is a plus\nAbility to thrive in multi-tasking and fast-paced working environment\nStrong interest in the market trend of consumer electronic device\nEager in working with other teams across the world.", "employment_types": ["Full Time", "Permanent"], "selling_points": ["End to end supply chain role", "Global market exposure", "Fast-Paced Work Environments"], "locations": ["Kowloon Bay"], "categories": ["Transportation & Logistics", "Fulfillment", "Shipping", "Supply Chain"], "post_time": "2022-01-14T07:04:36Z", "salary": {"currency": null, "max": null, "min": null, "period": "monthly", "term": null}, "salary_visible": false, "title_keywords": ["specialist"], "responsibilities": ["ideas", "data", "demand planning", "quality", "inventory management", "communication", "purchase", "customer service", "maintain", "costs", "administration", "control", "inventory availability", "teams", "order fulfillment", "schedule", "kpis", "report", "reporting", "cost", "management", "inventory planning", "analysis", "planning"], "requirements": {"degrees": ["degree", "bachelor"], "majors": ["business administration"], "languages": [], "language_level": [], "hard_skills": ["supply planning", "plus", "amazon", "e-commerce", "data warehouse", "demand planning", "analysis", "erp", "mobile", "ms office"], "soft_skills": ["efficient", "communication skills", "oral", "sophisticated", "decision making", "accountable", "multi-tasking", "customer service", "energetic", "leadership", "superior"], "languages_combined": []}, "experience_required": {"duration": ["3 - 5 years"], "field": ["supply chain", "management", "business administration", "planning"]}}, {"job_id": "100003009051981", "location_code": "hk", "company": "HCT GROUP", "job_title": "Order Fulfillment Coordinator", "description": "Responsibilities:\n\n\u00a0\u00a0\u00a0\u00a0\u00a0 Manage the team for internally and externally regarding orders and transportation needs.\n\u00a0\u00a0\u00a0\u00a0\u00a0 Daily monitoring of client\u2019s EDI or web-based systems for PO\u2019s, updates and shipment details.\n\u00a0\u00a0\u00a0\u00a0\u00a0 Achieve timely dispatches with domestics and overseas vendors.\n\u00a0\u00a0\u00a0\u00a0\u00a0 Utilize various functions in SAP, including but not limited to item setup, creating orders, goods receipt, delivery, etc.\n\u00a0\u00a0\u00a0\u00a0\u00a0 Initiate timely invoicing and work closely with accounting department to ensure billing accuracy.\n\u00a0\u00a0\u00a0\u00a0\u00a0 Various SAP projects or other duties as they arise.\n\nRequirements:\n\n\u00a0\u00a0\u00a0\u00a0\u00a0 Hong Kong permanent resident\n\u00a0\u00a0\u00a0\u00a0\u00a0 1-2 years of experience in the field of purchasing or logistics\n\u00a0\u00a0\u00a0\u00a0\u00a0 Quick learner, detail oriented with proven ability to work efficiently with high accuracy\n\u00a0\u00a0\u00a0\u00a0\u00a0 Exceptional organization and time management skills with the ability to work effectively independently and in a team environment\n\u00a0\u00a0\u00a0\u00a0\u00a0 Strong knowledge of import/export documentation and solid understanding of Inco terms\n\u00a0\u00a0\u00a0\u00a0\u00a0 Proficiency in SAP (or other operating systems) Outlook, Excel and Word is required\n\u00a0\u00a0\u00a0\u00a0\u00a0 Strong verbal/written communication skills (English and Chinese) are essential\n\u00a0\u00a0\u00a0\u00a0\u00a0 Fluent in both spoken and written English, Mandarin and Cantonese.\n\u00a0\u00a0\u00a0\u00a0\u00a0 Ability to gather and analyze data and work with figures communicate effectively both narration and in writing\n\nWe offer 5 days work, attractive salary, medical insurance, harmony and excellent working environment to right candidate. Interested parties please send full resume in\u00a0MS Word\u00a0format, present and expected salary with full confidence attention to Ms. Mak.\n\nYou are welcome to visit our HCT Group website: https://hctgroup.com\n\n* ALL PERSONAL DATA RECEIVED WILL BE TREATED CONFIDENTIALLY AND USED FOR RECRUITMENT PURPOSE ONLY.*", "employment_types": ["Full Time"], "selling_points": [], "locations": ["Sheung Wan"], "categories": ["Transportation & Logistics", "Freight Forwarding", "Fulfillment", "Supply Chain"], "post_time": "2022-01-17T01:44:54Z", "salary": {"currency": null, "max": null, "min": null, "period": "monthly", "term": null}, "salary_visible": false, "title_keywords": ["coordinator"], "responsibilities": ["other duties", "systems", "invoicing", "daily monitoring", "setup"], "requirements": {"degrees": [], "majors": [], "languages": ["cantonese", "english", "chinese", "mandarin"], "language_level": ["fluent"], "hard_skills": ["excel", "sap", "word", "outlook", "documentation"], "soft_skills": ["work effectively", "communication skills", "independently", "time management skills", "detail oriented", "quick learner"], "languages_combined": [{"language": "cantonese", "language_level": ["fluent"]}, {"language": "english", "language_level": ["fluent"]}, {"language": "chinese", "language_level": []}, {"language": "mandarin", "language_level": ["fluent"]}]}, "experience_required": {"duration": ["1-2 years"], "field": ["purchasing", "logistics"]}}, {"job_id": "100003009049267", "location_code": "hk", "company": "Sa Sa Cosmetic Company Limited", "job_title": "Logistics Officer (Kwai Chung)", "description": "Responsibilities:\n\nAssist in stock management, stock replenishment and order fulfillment\nPlan for delivery schedule and courier delivery to mainland China or overseas\nAnalyze data and prepare reports on warehouse operations, stock management and stock transactions to support company growth\nProvide clerical support to operation team\nWork closely with other departments to follow up logistics processes\nAd hoc project as assigned\n\u00a0\nRequirements:\n\nHigher Diploma or above in Logistics, Supply Chain or related disciplines\n3 years or above logistics working experiences\nFresh graduates from Bachelor's degree in supply chain or related disciplines will also be considered\nIndependent, self-motivated and good team player\nGood communication skills in both English and Chinese\nProficient in PC skills, Word and Excel, acknowledge of SAP is preferable\nCandidates with less working experience would also be considered as Assistant Logistics Officer\nImmediate available is an advantage\u00a0\n\nAlternative work 6 or 5 days per week", "employment_types": ["Full Time"], "selling_points": ["Clerk, clerical support, data entry", "Diploma, Logistics, Warehouse", "Kwai Chung, warehouse, high salary"], "locations": ["Kwai Tsing Area"], "categories": ["Transportation & Logistics", "Supply Chain"], "post_time": "2022-01-14T08:20:40Z", "salary": {"currency": null, "max": null, "min": null, "period": null, "term": null}, "salary_visible": false, "title_keywords": ["logistics officer"], "responsibilities": ["provide clerical support", "stock replenishment", "stock management", "prepare reports", "follow up logistics processes", "ad hoc", "stock transactions", "work closely with other departments", "delivery schedule", "order fulfillment", "plan", "analyze data", "warehouse operations", "courier delivery"], "requirements": {"degrees": ["degree", "higher diploma or above", "bachelor"], "majors": ["related disciplines"], "languages": ["english", "chinese"], "language_level": ["good"], "hard_skills": ["excel", "pc skills", "word", "sap"], "soft_skills": ["communication skills", "good team player", "self-motivated", "independent"], "languages_combined": [{"language": "english", "language_level": ["good"]}, {"language": "chinese", "language_level": ["good"]}]}, "experience_required": {"duration": ["3 years"], "field": ["logistics"]}}, {"job_id": "100003009056061", "location_code": "hk", "company": "Yusen Logistics (Hong Kong) Limited", "job_title": "Assistant Supervisor / Indoor Sales", "description": "Job Descriptions:\n\nDaily works include, but not limited to:\n\nSupport outdoor sales and teammates for sales related issues, not limited to rate inquiries or prepare quotations;\nPrepare tailor-made shipments and invoices reports;\nShipment coordination and problem solving for the stakeholders;\nFollow up invoice billing, chasing outstanding payment, and credit control.\nRequirements:\n\nDegree or above in any discipline;\nRelevant freight forwarding experience is required;\nFluent in written and spoken English and Mandarin;\nProactive, good interpersonal and analytical skills.\nInterested parties please send full resume with employment history and expected salary to HRA Division, Yusen Logistics (Hong Kong) Limited at Level 31, Tower 1, Kowloon Commerce Centre, 51 Kwai Cheong Road, Kwai Chung or by email to hr.ylhk@ hk.yusen-logistics.com .\n\n\n\nYusen Logistics (Hong Kong) is an equal opportunity employer. All information collected will be used for recruitment purpose only.", "employment_types": ["Full Time", "Permanent"], "selling_points": ["Degree holder", "Relevant freight forwarding experience is required", "Proactive, good interpersonal & analytical skills"], "locations": ["Kwai Hing"], "categories": ["Transportation & Logistics", "Freight Forwarding", "Shipping", "Supply Chain"], "post_time": "2022-01-18T03:14:31Z", "salary": {"currency": null, "max": null, "min": null, "period": "monthly", "term": null}, "salary_visible": false, "title_keywords": ["assistant supervisor", "sales"], "responsibilities": ["control", "invoices", "invoice", "payment", "reports", "coordination"], "requirements": {"degrees": ["degree or above"], "majors": [], "languages": ["english", "mandarin"], "language_level": ["fluent"], "hard_skills": ["analytical skills"], "soft_skills": ["proactive", "interpersonal", "analytical skills"], "languages_combined": [{"language": "english", "language_level": ["fluent"]}, {"language": "mandarin", "language_level": ["fluent"]}]}, "experience_required": {"duration": [], "field": []}}, {"job_id": "100003009049555", "location_code": "hk", "company": "Migros (Hong Kong) Ltd", "job_title": "Logistics Officer", "description": "Responsibilities:\n\nMonitor the outsource Forwarders operations by supervising the team members performing on a timely manner\nPlan and co-ordinate the delivery schedule (Inbound) and (Outbound) with outsourced logistics service providers\nManage the Logistics Assistant who is in charge of daily operation and all system / application\nAssure excellent accuracy of inventory in warehouse as well as respect of lead times\nValidated all the logistics cost from 3rd party logistics\nHandling APAC countries logistics experience (Include understand the countries customs rule and logistics flow)\nMaintain daily operation control and in transit report\nPrepare monthly logistics report for HK and Asia and monitoring forwarders KPI report\nProvide internal logistics and IT system training\nMaintain partnership and liaise all logistics related issues with headquarter, departments, forwarders, suppliers and factories in Asia\nCarry out ad-hoc project as assigned by the management\nRequirements:\n\nDegree holder in Supply Chain Management, Transport and Logistics Management\nExperience in sourcing industry is an advantage\u00a0\nMin. 5 years of relevant logistics experience\nGood knowledge of trade declaration, air, ocean, cross border trucking, shipping procedure, customs\nFluent in spoken and written English, Cantonese and Mandarin\nHard working and able to handle pressure and multiple projects\nGood interpersonal, problem solving and strong negotiation skills\u00a0\nOpen and polite communicator with internal and external customers and partners\nA good team player, able to work independently, self-motivated, proactive and willing to learn more\nProficient in Microsoft office applications (Excel, Word, Outlook Etc.) and Internet\nWe offer right candidate with competitive salary, 13th month salary, 5-day work per week, flexible working hours, 15 days annual leave, birthday leave, family leave, education sponsorship, MPF voluntary contribution, medical & dental insurance, business travel insurance.\nInterested parties please send us your full resume with last/current and expected salary by clicking \u201cApply Now\u201d\n\u00a0Please visit our website for more information: https://www.migros.com.hk/\n\u00a0All data collected will be used for recruitment purpose only.", "employment_types": ["Full Time", "Permanent"], "selling_points": [], "locations": ["Kowloon Bay"], "categories": ["Transportation & Logistics", "Supply Chain", "Merchandising & Purchasing", "Procurement / Purchasing / Sourcing"], "post_time": "2022-01-14T08:52:28Z", "salary": {"currency": null, "max": null, "min": null, "period": "monthly", "term": null}, "salary_visible": false, "title_keywords": ["logistics officer"], "responsibilities": ["liaise", "ad-hoc", "supervising", "operations", "logistics assistant", "maintain", "monthly logistics report", "plan", "control", "monitor", "logistics", "report", "cost", "management", "monitoring", "delivery schedule", "a timely manner", "daily operation", "assure excellent accuracy of inventory"], "requirements": {"degrees": ["degree holder"], "majors": [], "languages": ["cantonese", "english", "mandarin"], "language_level": ["fluent"], "hard_skills": ["excel", "microsoft office", "word", "problem solving", "outlook"], "soft_skills": ["flexible", "good team player", "work independently", "self-motivated", "polite", "hard working", "willing to learn", "problem solving", "negotiation skills", "communicator", "proactive", "interpersonal"], "languages_combined": [{"language": "cantonese", "language_level": ["fluent"]}, {"language": "english", "language_level": ["fluent"]}, {"language": "mandarin", "language_level": ["fluent"]}]}, "experience_required": {"duration": ["5 years"], "field": ["logistics"]}}, {"job_id": "100003009052088", "location_code": "hk", "company": "IEWC SouthEast Asia Limited", "job_title": "Warehouse Supervisor (5 days work)", "description": "IEWC Southeast Asia Limited\n\nShek Mun Area\n\nResponsibilities:\n\nWarehouse Operation (Daily)\n\nTo lead a team of storekeepers to manage daily warehouse operation, including inbound, outbound, inventory management and system transaction.\nTo ensure the daily tasks finished on time by proper manpower and resource planning.\nArrange shipments and handle import/export shipping documents.\nCoordinate with warehouse, forwarders, customers for shipment arrangement\nTo handle the daily email\u00a0communication and maintain good working \u00a0\u00a0relationship with customer service.\nTo prepare regular reports for management review\u00a0\nTo participate warehouse improvement project.\n\nSupplies, Equipment and Plant\n\nEnsure that adequate supplies, materials and parts are on hand to keep the departments operating smoothly.\nEnsure the performance of minor maintenance and repairs on equipment within their designated department.\n\nQuality Assurance\n\nMaintain compliance with our Quality Standards\nUnderstand and ensure Company compliance with UL and C S A product requirements. \u00b7\n\nCustomer Service\n\nWork with all Company departments to ensure customer satisfaction and new opportunities for business and product growth.\n\nSafety\n\nMaintain a safe and secure work environment.\nEnsure safety policies are properly applied and enforced.\n\n\u00a0Requirements:\n\nF.5\u00a0or above\nAt least\u00a03\u00a0years' solid experience in warehouse operation.\nAble to handle email communication in both English and Chinese.\nSelf-motivated and a good team player.\nGood people management skill.\nGood communication and leadership skills.\nImmediately available is highly preferable.", "employment_types": ["Full Time"], "selling_points": [], "locations": ["Shatin Area"], "categories": ["Transportation & Logistics", "Others", "Inventory / Warehousing", "Supply Chain"], "post_time": "2022-01-17T02:04:05Z", "salary": {"currency": null, "max": null, "min": null, "period": "monthly", "term": null}, "salary_visible": false, "title_keywords": ["warehouse supervisor"], "responsibilities": ["shipping documents", "shipment arrangement", "maintenance", "policies", "review", "coordinate with", "quality", "compliance", "inventory management", "lead a team", "communication", "maintain", "customer service", "regular reports for management", "planning"], "requirements": {"degrees": [], "majors": [], "languages": ["english", "chinese"], "language_level": [], "hard_skills": [], "soft_skills": ["communication", "good team player", "self-motivated", "leadership skills"], "languages_combined": [{"language": "english", "language_level": []}, {"language": "chinese", "language_level": []}]}, "experience_required": {"duration": ["at least 3 years"], "field": ["operation"]}}, {"job_id": "100003009056685", "location_code": "hk", "company": "Bay Blue (Hongkong) Trading Co., Limited", "job_title": "Warehouse Assistant \u5009\u52d9\u54e1", "description": "\u5730\u5340 :\u6c99\u7530\n\u8077\u8cac :\u8ca0\u8cac\u65e5\u5e38\u8ca8\u7269\u7684\u63a5\u6536\uff0c\u88dd\u5378\u9ede\u8ca8\uff0c\u57f7\u8ca8\uff0c\u4e0a\u67b6\uff0c\u767c\u8ca8\u7b49\u3002\u642c\u904b\u8ca8\u7269\uff0c\u6574\u7406\u8ca8\u5009\uff0c\u4e00\u822c\u7406\u8ca8\u54e1\u5de5\u4f5c\u3002\u5354\u52a9\u7ba1\u7406\u5eab\u5b58\u72c0\u6cc1\uff08\u4f8b\u5982\uff1a\u7ba1\u7406\u8ca8\u54c1\u5230\u671f\u65e5\uff0c\u8ca8\u54c1\u5305\u88dd\u72c0\u614b\uff09\u3002\u6838\u5c0d\u8ca8\u7269\u7684\u54c1\u724c\uff0c\u9644\u52a0\u865f\uff0c\u5305\u88dd\u662f\u5426\u640d\u58de\u7b49\u8a18\u9304\uff1b\u6839\u64da\u92b7\u552e\u55ae\u9032\u884c\u8ca8\u7269\u6311\u9078\u53ca\u5305\u88dd\u3001\u5b9a\u671f\u9032\u884c\u5eab\u5b58\u76e4\u9ede\u4e26\u4fdd\u6301\u6e96\u78ba\u7684\u5eab\u5b58\u3002\u4fdd\u6301\u63c0\u8ca8\u5340\u6709\u689d\u7406\u3002\n\u8cc7\u6b77 :\u4e2d\u4e09\u7a0b\u5ea6; 1\u5e74\u7d93\u9a57; \u826f\u597d\u7cb5\u8a9e; \u826f\u597d\u666e\u901a\u8a71; \u61c2\u8b80\u5beb\u4e2d\u6587; \u61c2\u8b80\u5beb\u82f1\u6587\n\u5f85\u9047 :\u6bcf\u6708$12,000 - $15,000, \u6709\u8d85\u6642\u5de5\u4f5c\u88dc\u5047, \u9280\u884c\u5047\u671f, \u54e1\u5de5\u8cfc\u7269\u512a\u60e0, \u5728\u8077\u57f9\u8a13 \u53ca\u6649\u5347\u6a5f\u6703, \u661f\u671f\u4e00\u81f3\u516d: \u4e0a\u53489\u6642\u81f3\u4e0b\u53486\u6642, \u6bcf\u9031\u5de5\u4f5c5\u5929\u81f36\u5929, \u6bcf\u5929\u5de5\u4f5c 8 \u5c0f\u6642, \u661f\u671f\u516d\u9577\u77ed\u9031\n\u7533\u8acb\u9808\u77e5 :\u6c42\u8077\u8005\u53ef\u96fb\u90f5\u5c65\u6b77\u8868\u7d66\u7063\u85cd(\u9999\u6e2f)\u8cbf\u6613\u6709\u9650\u516c\u53f8\u3002\u5982\u8981\u7d22\u53d6\u6536\u96c6\u500b\u4eba\u8cc7\u6599\u8072\u660e, \u8acb\u8207\u6b50\u5c0f\u59d0(Email)\u806f\u7d61", "employment_types": ["Full Time"], "selling_points": ["\u8ca0\u8cac\u65e5\u5e38\u8ca8\u7269\u7684\u63a5\u6536\uff0c\u88dd\u5378\u9ede\u8ca8", "\u5354\u52a9\u7ba1\u7406\u5eab\u5b58\u72c0\u6cc1", "\u4e2d\u4e09\u7a0b\u5ea6; 1\u5e74\u7d93\u9a57; \u826f\u597d\u7cb5\u8a9e"], "locations": ["Shatin Area"], "categories": ["Transportation & Logistics", "Others", "Inventory / Warehousing", "Supply Chain"], "post_time": "2022-01-18T05:43:50Z", "salary": {"currency": null, "max": null, "min": null, "period": "monthly", "term": null}, "salary_visible": false, "title_keywords": ["warehouse assistant", "\u5009\u52d9\u54e1"], "responsibilities": [], "requirements": {"degrees": [], "majors": [], "languages": [], "language_level": [], "hard_skills": [], "soft_skills": [], "languages_combined": []}, "experience_required": {"duration": [], "field": []}}, {"job_id": "100003009055185", "location_code": "hk", "company": "FedEx Trade Networks Transport & Brokerage (Hong Kong) Limited", "job_title": "Hong Kong Management Trainee 2022", "description": "FedEx Management Trainee Program is designed to groom and develop young talents of high caliber as future leaders of FedEx.\u00a0 The 36-month program provides an excellent opportunity for a Management Trainee (MT) to gain an exposure and development in FTN.\u00a0 MT will go through on-the-job trainings, job rotation and get practical work experience including the chances of assuming an overseas assignment in APAC region. Upon completion of the 36-month training, it is expected that the Management Trainee will be assigned a permanent position at FTN.\n\n\u00a0What are the benefits for you?\n\n3-Year Program\nJob Rotation\nOverseas Assignment Opportunities\nOn-the-job Training\nCoaching & Buddy Support\nSenior Management Mentoring\n\nWhat do we offer?\u00a0\n\n14-month Pay\nDiscretionary Bonus\nMedical & Dental Benefits\nSpecial Leave\nFamily-friendly Leave\n\nResponsibilities :\n\nReceive training, and perform duties in several departments, in operations, products, and support functions in order to attain functional and departmental perspective on objectives by following the FedEx philosophy of People-Service-Profit and Purple Promise\nLearn various staff functions, operations workflow, management viewpoints and company policies and practices affecting each phase of FTN business development\nMeet performance goals and objectives set by management\nReport to management regularly on progress made in attaining goals and objectives\nObserve experienced talents in FTN to acquire knowledge of methods, procedures, and standards required for performance of departmental duties\nProvide support as needed by management in the various departments, including reporting, data-entry, presentation creation, strategic planning, and ad-hoc project work\n\nRequirements :\n\nUniversity graduates in all disciplines.\u00a0Degree in logistics, supply chain management, or industrial engineering is preferred but not essential\nKeen interest in Supply Chain Management & Freight Forwarder Industry\nSelf-motivated, passionate and energetic\nHighly committed, hardworking and consistently self-disciplined\nGood team player\nAble to work under pressure\nExcellent spoken and written English with strong interpersonal and presentation skills. Fluent Mandarin and Chinese are preferable.\nBe willing to relocate to Mainland China or other countries for short-term assignments.\n\nApplication deadline : February 28, 2022 (Monday)\n\nJoin FedEx and you'll be rewarded with an excellent salary and benefits package including guarantee two months' year-end bonus, medical and dental benefits, life insurance, provident fund, extra annual leave, and attractive promotional prospects.\n\nIf you are interested in joining us, please send us your resume, highlight graduation year, faculty, outstanding achievements, internship experience, etc.\n\nFor any inquiries regarding the MT programme, please contact us through whatsapp at +852 65801399.\n\nOur company addresses:\nUnit 801, 8/F, Metroplaza Tower 1\n223 Hing Fong Road, Kwai Fong\nN.T.\u00a0\n\nAll information provided by applicants will be treated in strict confidence and used only for recruitment purpose in accordance with the employer's personal data policies. A copy of Personal Information Collection Statement (PICS) will be provided upon request. Please write to the Human Resources Department. Applicants who are not invited to an interview within four weeks may consider their applications unsuccessful. All personal data of unsuccessful applicants will be destroyed after one year.", "employment_types": ["Full Time", "Permanent"], "selling_points": ["Guarantee 14 months paid with attractive benefits", "Management Trainee", "Fresh Graduates"], "locations": ["Kwai Fong"], "categories": ["Transportation & Logistics", "Freight Forwarding", "Supply Chain", "Others", "Student / Fresh Graduate / No Experience"], "post_time": "2022-01-18T01:42:18Z", "salary": {"currency": null, "max": null, "min": null, "period": "monthly", "term": null}, "salary_visible": false, "title_keywords": ["management trainee"], "responsibilities": [], "requirements": {"degrees": [], "majors": [], "languages": [], "language_level": [], "hard_skills": [], "soft_skills": [], "languages_combined": []}, "experience_required": {"duration": [], "field": []}}, {"job_id": "100003009050191", "location_code": "hk", "company": "Alliance Construction Materials Limited", "job_title": "Logistics  Engineer", "description": "Alliance Construction Materials Limited\n\nWhen you choose Alliance, it means you'll be working alongside some of our industry's best people while making a real contribution to most exciting construction projects in Hong Kong. Because we hire people as employees with a view to training and educating them for their long-term career development to management, our employees have been able to develop their skills and thrive in a fast-paced and entrepreneurial environment. Alliance's business culture is performance-based and customer-driven. So, we are looking for an individual who is motivated, a real team player and who shares our commitment to making it happen for our customers.\n\nLogistics Engineer\u00a0\u00a0\n\nThis position is suitable for a highly motivated individual, who has the aspiration to develop long term career in the field of logistics management. \u00a0\n\nDuties :\n\n\nCoordinate the delivery schedules undertaken by the truck drivers and marine barges\nPlan for and monitor the training of new truck drivers\nManage the fleet of drivers and marine barges and resolve their operational issues\nManage the remuneration records for the fleet of drivers\nPrepare monthly reports on logistics operations for management\nEnsure compliance with operational procedures and legal requirements\nManage health and safety issues of drivers to continuously improve the Company\u2019s health and safety performance\nUndertake any tasks as assigned\n\nWhat you will need for this role\n\nThe successful candidate will possess the following key skills and attributes:\n\n\nBachelor Degree in Logistics Management or related disciplines\nAt least 1-2 years\u2019 relevant working experience\nBasic knowledge of ERP preferred\nSelf-motivated, problem-solving capability with analytical mind\nPleasant and outgoing personality with strong sense of responsibility\nGood presentation, communication and negotiation skills\nA good team player\nAble to work independently and under pressure\nGood command of written and spoken English and Chinese\n\nRemarks : Those with less experience will be considered for the post of Assistant Engineer\n\nA competitive package will be offered to the successful candidate who is willing to develop and grow with us.\u00a0\u00a0 If you wish to be considered for this opportunity, please apply now with your full resume and present & expected salaries to\u00a0HR team.", "employment_types": ["Full Time", "Permanent"], "selling_points": ["Logistics Management", "ERP knowledge", "Manage health and safety issues"], "locations": ["Yau Tsim Mong Area"], "categories": ["Transportation & Logistics", "Others", "Engineering", "Others", "Supply Chain"], "post_time": "2022-01-14T09:56:57Z", "salary": {"currency": null, "max": null, "min": null, "period": "monthly", "term": null}, "salary_visible": false, "title_keywords": ["logistics", "engineer"], "responsibilities": ["management", "monthly reports", "schedules", "operations", "hr", "monitor", "develop", "coordinate", "ensure compliance", "communication", "operational procedures", "logistics", "plan", "career development"], "requirements": {"degrees": ["degree", "bachelor"], "majors": ["related disciplines"], "languages": ["english", "chinese"], "language_level": ["good command"], "hard_skills": ["problem-solving", "basic", "erp"], "soft_skills": ["outgoing personality", "self-motivated", "good team player", "work independently", "under pressure", "sense of responsibility", "problem-solving", "presentation", "pleasant", "communication", "motivated individual", "negotiation skills", "motivated", "analytical mind", "team player", "driven"], "languages_combined": [{"language": "english", "language_level": ["good command"]}, {"language": "chinese", "language_level": ["good command"]}]}, "experience_required": {"duration": ["at least 1-2 years"], "field": ["relevant working experience"]}}, {"job_id": "100003009056300", "location_code": "hk", "company": "CEVA Logistics (Hong Kong) Limited", "job_title": "Air Export Senior Coordinator / Coordinator", "description": "Job Description\u00a0\n\nHandle full set of Air Export documents\nSystem data entry\nFollow up shipment status\nResponsible for daily inquiry related to external and internal parties\nAd-hoc projects as assigned by supervisor\n\nJob Requirements\n\n\n\u00a0F.5 or DSE or above with 1-2 years working experience in Air Freight Forwarding Industry\n\u00a0CargoWise One experience is highly preferred\n\u00a0Responsible, mature, detailed mind and good team player\n\u00a0Alternate week day/night shift duty\u00a0is required\n\u00a0Fresh graduate will also be considered\n\n\u00a0\u00a0Company Benefits and Allowance\u00a0\n\n\u00a05 days work\n\u00a0Guaranteed Double Pay\n\u00a0Performance Bonus\n\u00a0Medical and life and dental Insurance\n\u00a0OT and night shift allowance\u00a0\n\nWe offer attractive remuneration packages to the right candidates. Interested parties please send your FULL resume with CURRENT & EXPECTED SALARY by clicking \"APPLY NOW\". For further information of our company, please visit our website: http://www.cevalogistics.com.\n\nInformation provided will be kept confidential and only be used for the recruitment related purpose only.", "employment_types": ["Full Time", "Permanent", "Contract"], "selling_points": ["Handle full set of Air Export documents", "1-2 years relevant experience", "5 day work, 13th mth guarantee pay and incentive"], "locations": ["Kwai Fong"], "categories": ["Transportation & Logistics", "Aviation Services", "Shipping", "Supply Chain"], "post_time": "2022-01-18T03:53:18Z", "salary": {"currency": null, "max": null, "min": null, "period": null, "term": null}, "salary_visible": false, "title_keywords": ["coordinator"], "responsibilities": ["ad-hoc projects", "internal parties", "system data"], "requirements": {"degrees": ["fresh graduate", "dse"], "majors": [], "languages": [], "language_level": [], "hard_skills": [], "soft_skills": ["mature", "good team player", "detailed mind", "responsible"], "languages_combined": []}, "experience_required": {"duration": ["1-2 years"], "field": []}}, {"job_id": "100003009056519", "location_code": "hk", "company": "Cathay Pacific Services Limited", "job_title": "Cargo Services Officer - Escort \u7a7a\u904b\u670d\u52d9\u4e3b\u4efb - \u62bc\u9001\u53f8\u6a5f", "description": "Responsibilities:\nTo be conversant with Warehouse Operating System (WOS) operations and its fallback procedures\nTo perform escorting services for special cargo, safe-handed item and valuable cargo to/from cargo terminal and aircraft parking bay\nTo handle shipside release and perform cargo release procedures for import cargo at aircraft parking bay\nTo drive and comply with HKIA driving regulations and speed limits\nTo report for traffic accident or company property damage to supervisor instantly\nTo liaise with parties such as government parties, ramp handling operators, customer airlines, air mail center, ULD repair center and other cargo terminal operators in day-to-day cargo handling matters\nTo perform duties as assigned by supervisor\nTo maintain company vehicles tidiness\n\u00a0Requirements:\nHolder of HKCEE/HKDSE with passes in English and Chinese Language\nPossessing of valid Hong Kong Driving License (class 1 and 2) with good driving record\nWillingness to work shift duty and overnight as necessary\n\nRecruitment Days (Walk-in Interview)\n\nDate: 24 January 2022 (Monday)\nTime: 14:00 \u2013 17:00\u00a0\nVenue: Desk One, 23/F, Chung Kiu Commercial Building, 47-51 Shantung Street, Mong Kok, Kowloon\u00a0(Mong Kok MTR Station Exit E2)\n\nDate: 27 January 2022 (Thursday)\u00a0\nTime: 14:00 \u2013 16:30\u00a0\nVenue: 9/F, High Block, Queensway Government Offices, 66 Queensway, Hong Kong (Admiralty MTR Station Exit C1)\n\nDate: 11 February 2022 (Friday)\u00a0\nTime: 14:00 \u2013 17:00\u00a0\nVenue: Desk One, 21/F, Hang Seng Tsuen Wan Building, 289 Sha Tsui Road, Tsuen Wan\u00a0(Tsuen Wan MTR Station Exit B1)\n\nDate: 17 February 2022 (Thursday)\u00a0\nTime: 14:00 \u2013 17:00\u00a0\nVenue: Desk One, 20/F, 2004-06, Tower 1, Grand Central Plaza, 138 Sha Tin Rural Committee Road, Sha Tin\u00a0(Sha Tin MTR Station Exit B)\n\nDate: 23 \u00a0February 2022 (Wednesday)\u00a0\nTime: 14:00 \u2013 17:00\u00a0\nVenue: YMCA of Hong Kong Beacon Centre \u2013 Lifelong Learning Institute, No. 373, Po On Road, Kowloon\u00a0(Cheung Sha Wan MTR station Exit C2)\n\nDate: 3 March 2022 (Wednesday)\nTime: 14:00 \u2013 17:00\u00a0\nVenue: Desk One, 23/F, Chung Kiu Commercial Building, 47-51 Shantung Street, Mong Kok, Kowloon\u00a0(Mong Kok MTR Station Exit E2)\n\n* please bring along your 1) HKID Card, 2) Resume, 3) Original Copies of School & Work Certificates, 4) Original Driving License (if applicable)\n\n\nIf you are interested, please\u00a0call 2767-9375 during office hours as well as by WeChat/Whatsapp at 5599-2177 for interview appointment. For application, you may simply click Apply Online\u00a0on our website or email your confidential resume with date of availability, current and expected salary to recruitment @cpsl.com.hk. Applicants not contacted within 6 weeks may consider their applications unsuccessful.\n\nCathay Pacific Services Limited is an Equal Opportunities Employer. Personal data provided by job applicants will be used strictly in accordance with our personal data policy and for recruitment purposes only. Candidates not notified within six weeks may consider their application unsuccessful. All related information will be kept in our file for up to 24 months.\n\u00a0\n\n\n\n\u7acb\u5373\u52a0\u5165CPSL \u6210\u70ba\u6211\u5011\u7684\u4e00\u4efd\u5b50\n\n\u7a7a\u904b\u670d\u52d9\u4e3b\u4efb (\u62bc\u9001\u53f8\u6a5f)\n\n\u8077\u8cac\uff1a\n\n\u8b77\u9001\u53ca\u78ba\u4fdd\u7279\u6b8a\u6216\u8cb4\u91cd\u8ca8\u7269\u5b89\u5168\u5f80\u8fd4\u8ca8\u904b\u7ad9\u53ca\u822a\u6a5f\n\u5354\u52a9\u8655\u7406\u505c\u6a5f\u576a\u51fa\u5165\u53e3\u8ca8\u7269\u4ea4\u6536\u5de5\u4f5c\n\n\u5165\u8077\u689d\u4ef6\uff1a\n\n\u4e2d\u4e94\u7a0b\u5ea6\u6216\u9999\u6e2f\u4e2d\u5b78\u6587\u6191\u8a66\u540c\u7b49\u5b78\u6b74\u00a0\n\u6301\u6709\u9999\u6e2f\u99d5\u99db\u57f7\u71671\u53ca2\u985e\u5225\u4e26\u5177\u826f\u597d\u99d5\u99db\u7d00\u9304\n24\u5c0f\u6642\u8f2a\u73ed\u5236\uff0c\u9700\u591c\u73ed\u5de5\u4f5c\u00a0\u00a0 \u00a0 \u00a0\n\n\u62db\u8058\u65e5\u00a0(\u5373\u5834\u9762\u8a66)\n\n\u65e5\u671f\uff1a2022\u5e741\u670824\u65e5\uff08\u661f\u671f\u4e00\uff09\n\u6642\u9593\uff1a14:00\u00a0\u2013 17:00\n\u5730\u9ede\uff1a\u65fa\u89d2\u5c71\u6771\u885747-51\u865f\u4e2d\u50d1\u5546\u696d\u5927\u5ec823\u6a13Desk One\u00a0(\u65fa\u89d2\u7ad9E2\u51fa\u53e3)\n\n\n\u65e5\u671f\uff1a2022\u5e741\u670827\u65e5\uff08\u661f\u671f\u56db)\n\u6642\u9593\uff1a14:00\u00a0\u2013 16:30\n\u5730\u9ede\uff1a\u9999\u6e2f\u91d1\u9418\u905366\u865f\u91d1\u9418\u9053\u653f\u5e9c\u5408\u7f72\u9ad8\u5ea79\u6a13 (\u91d1\u9418\u7ad9C1\u51fa\u53e3)\n\n\u65e5\u671f\uff1a2022\u5e742\u670811\u65e5\uff08\u661f\u671f\u4e94)\n\u6642\u9593\uff1a14:00\u00a0\u2013 17:00\n\u5730\u9ede\uff1a\u8343\u7063\u6c99\u5480\u9053289\u865f\u6052\u751f\u8343\u7063\u5927\u5ec821\u6a13Desk One(\u8343\u7063\u7ad9B1\u51fa\u53e3)\n\n\u65e5\u671f\uff1a2022\u5e742\u670817\u65e5\uff08\u661f\u671f\u56db)\n\u6642\u9593\uff1a14:00\u00a0\u2013 17:00\n\u5730\u9ede\uff1a\u6c99\u7530\u5a1c\u4e8b\u6703\u8def138\u865f\u65b0\u57ce\u5e02\u4e2d\u592e\u5ee3\u58341\u5ea720\u6a1304-06\u5ba4Desk One (\u6c99\u7530\u7ad9B\u51fa\u53e3)\n\n\u65e5\u671f\uff1a2022\u5e742\u670823\u65e5\uff08\u661f\u671f\u4e09)\n\u6642\u9593\uff1a14:00\u00a0\u2013 17:00\n\u5730\u9ede\uff1a\u4e5d\u9f8d\u4fdd\u5b89\u9053373\u865f\u897f\u4e5d\u9f8d\u8000\u4fe1\u767c\u5c55\u5b78\u7fd2\u4e2d\u5fc3\u00a0(\u9577\u6c99\u7063\u7ad9C2\u51fa\u53e3)\n\n\u65e5\u671f\uff1a2022\u5e743\u67083\u65e5\uff08\u661f\u671f\u4e09\uff09\n\u6642\u9593\uff1a14:00\u00a0\u2013 17:00\n\u5730\u9ede\uff1a\u65fa\u89d2\u5c71\u6771\u885747-51\u865f\u4e2d\u50d1\u5546\u696d\u5927\u5ec823\u6a13Desk One\u00a0(\u65fa\u89d2\u7ad9E2\u51fa\u53e3)\n\n*\u00a0\u8acb\u5e36\u540c\u60a8\u7684\u00a01)\u00a0\u8eab\u4efd\u8b49, 2)\u00a0\u5c65\u6b77\u8868, 3)\u00a0\u5b78\u6b77\u53ca\u5de5\u4f5c\u200b\u8b49\u660e\u6587\u4ef6\u6b63\u672c, 4)\u00a0\u8eca\u724c\u00a0(\u5982\u9069\u7528)\n\n\u6709\u610f\u61c9\u5fb5\u8005\u53ef\u65bc\u8fa6\u516c\u6642\u9593\u5167\u81f4\u96fb2767-9375\u6216Whatsapp 5599-2177\u5b89\u6392\u9762\u8a66\u3002\u60a8\u4ea6\u53ef\u6309\"\u7db2\u4e0a\u7533\u8acb\"\u6216\u5c07\u500b\u4eba\u5c65\u6b77\u8868\u9023\u540c\u53ef\u5230\u8077\u65e5\u671f\u3001\u73fe\u6642\u53ca\u8981\u6c42\u5f85\u9047\u96fb\u90f5\u81f3recruitment @cpsl.com.hk\u3002\u82e5\u7533\u8acb\u8005\u65bc\u516d\u661f\u671f\u5167\u672a\u80fd\u63a5\u7372\u9762\u8a66\u901a\u77e5\uff0c\u5176\u7533\u8acb\u5c07\u5217\u70ba\u4e0d\u7372\u8003\u616e\u3002", "employment_types": ["Full Time", "Permanent"], "selling_points": ["Work in a world-class design cargo terminal", "Provide professional services to customers", "Work in a dynamic environment with opportunities"], "locations": ["Airport Area"], "categories": ["Transportation & Logistics", "Aviation Services", "Inventory / Warehousing", "Supply Chain"], "post_time": "2022-01-18T04:38:02Z", "salary": {"currency": null, "max": null, "min": null, "period": "monthly", "term": null}, "salary_visible": false, "title_keywords": ["officer"], "responsibilities": ["regulations", "operations", "procedures", "repair", "maintain", "liaise with", "report"], "requirements": {"degrees": ["hkdse"], "majors": [], "languages": ["english", "chinese"], "language_level": [], "hard_skills": ["whatsapp", "no", "wan", "wechat"], "soft_skills": ["learning", "willingness to work"], "languages_combined": [{"language": "english", "language_level": []}, {"language": "chinese", "language_level": []}]}, "experience_required": {"duration": [], "field": []}}, {"job_id": "100003009046195", "location_code": "hk", "company": "Otis Elevator Co (HK) Limited", "job_title": "Logistics Officer, Supply Chain", "description": "Responsibility\nResolve shipping & logistics issues independently\nMonitor shipping & logistics arrangement to ensure on-time shipments independently\nEnsure invoice/Customs documentation meets the requirement of destination countries\nMaintain KPI service level to uphold customer satisfaction\nPrepare monthly reports with operation data for business analysis\nKnowledgeable in handling I/E shipping documents and L/C if required\nAble to work under tight schedule and dynamic environment, and proactively seek solutions when issues arose\nSupport ad hoc projects and assignments when required\nLiaise with end user on goods return, damaged and claims\nRequirements\nHigh Diploma or above in related disciplines\n5 years of relevant experience and able to handle full sets independently\nExperience in warehouse operation and operation development is preferable\nGood command of spoken and written of English, Cantonese and Mandarin\nProficient with MS Office including Excel, Outlook and Word and Power point\nExperience in using SAP/Oracle ERP system is preferable\nGood customer service with internal and external parties will be a merit\nWe offer remuneration package including attractive salary, comprehensive fringe benefits and excellent opportunities for the right candidate.\u00a0(*** Employee Scholar Program\u00a0up to $160,000/ person for each degree***)\nWebsite:\u00a0http://www.otis.com/\u00a0\nInformation provided by applicants will be treated in strict confidence and will only be used for recruitment related purposes. All information on unsuccessful candidates will be deleted from our files within 24 months.", "employment_types": ["Full Time", "Permanent"], "selling_points": ["Exposure to MNC Environment", "Family-Friendly Employer", "Employee Scholar Program up to $160,000/ Degree"], "locations": ["Kowloon Bay"], "categories": ["Transportation & Logistics", "Shipping", "Supply Chain"], "post_time": "2022-01-13T09:54:29Z", "salary": {"currency": null, "max": null, "min": null, "period": "monthly", "term": null}, "salary_visible": false, "title_keywords": ["logistics officer"], "responsibilities": ["shipping documents", "shipping", "business analysis", "logistics arrangement", "invoice", "monthly reports", "data", "monitor", "liaise with", "maintain", "logistics", "schedule", "ad hoc projects", "documentation"], "requirements": {"degrees": ["high diploma or above"], "majors": ["related disciplines"], "languages": ["cantonese", "english", "mandarin"], "language_level": ["good command"], "hard_skills": ["excel", "sap", "word", "oracle erp", "outlook", "power point", "ms office"], "soft_skills": ["independently", "customer service"], "languages_combined": [{"language": "cantonese", "language_level": ["good command"]}, {"language": "english", "language_level": ["good command"]}, {"language": "mandarin", "language_level": ["good command"]}]}, "experience_required": {"duration": ["5 years"], "field": ["development", "erp system", "operation", "relevant experience"]}}, {"job_id": "100003009053740", "location_code": "hk", "company": "Tronic Technology International (Hong Kong) Limited", "job_title": "\u5009\u52d9(\u526f)\u4e3b\u7ba1", "description": "\n\u8077\u8cac :\u8ca0\u8cac\u9032\u51fa\u5eab\u8655\u7406; \u5b89\u6392\u54e1\u5de5\u5de5\u4f5c\n\n\u8cc7\u6b77 :\u4e2d\u4e09\u7a0b\u5ea6; 5\u5e74\u7d93\u9a57; \u4e00\u822c\u7cb5\u8a9e\u512a\u5148; \u61c2\u8b80\u5beb\u4e2d\u6587; \u7565\u61c2\u8b80\u5beb\u82f1\u6587; \u6301\u6709\u6297\u8861\u5f0f\u93df\u8eca\u724c\u6216\u4f38\u5c55\u5f0f\u93df\u8eca\u724c\n\n\u5f85\u9047 :\u6bcf\u6708$16,000 - $18,000, \u6709\u8d85\u6642\u5de5\u4f5c\u6d25\u8cbc, \u96d9\u7ce7, \u52e4\u5de5\u734e\u91d1, \u5e74\u504710\u5929, \u9280\u884c\u5047\u671f \u53ca\u7a7f\u68ad\u5df4\u58eb\u670d\u52d9, \u661f\u671f\u4e00\u81f3\u4e94: \u4e0a\u53489\u6642\u81f3\u4e0b\u53486\u6642\u53ca\u661f\u671f\u516d: \u4e0a\u53489\u6642\u81f3\u4e0b\u53481\u6642, \u6bcf\u9031\u5de5\u4f5c5\u5929\u534a, \u6bcf\u5929\u5de5\u4f5c 8 \u5c0f\u6642\n\n\u7533\u8acb\u9808\u77e5 :\u6c42\u8077\u8005\u53ef\u96fb\u90f5(Apply Now)\u5c65\u6b77\u8868\u7d66\u5275\u9818\u79d1\u6280\u570b\u969b(\u9999\u6e2f)\u6709\u9650\u516c\u53f8\u3002\u5982\u8981\u7d22\u53d6\u6536\u96c6\u500b\u4eba\u8cc7\u6599\u8072\u660e, \u8acb\u8207\u9f94\u5148\u751f(Email)\u806f\u7d61\u3002\n\n", "employment_types": ["Full Time"], "selling_points": [], "locations": ["Yuen Long"], "categories": ["Transportation & Logistics", "Others", "Inventory / Warehousing", "Supply Chain"], "post_time": "2022-01-17T07:26:27Z", "salary": {"currency": null, "max": null, "min": null, "period": "monthly", "term": null}, "salary_visible": false, "title_keywords": [], "responsibilities": [], "requirements": {"degrees": [], "majors": [], "languages": [], "language_level": [], "hard_skills": [], "soft_skills": [], "languages_combined": []}, "experience_required": {"duration": [], "field": []}}, {"job_id": "100003009053973", "location_code": "hk", "company": "Wing Hang Medical Supplies Limited", "job_title": "\u5009\u52d9\u517c\u8ddf\u8eca\u9001\u8ca8\u54e1", "description": "\n\u8077\u8cac :\u8ca0\u8cac\u9001\u8ca8\u53ca\u5009\u5eab\u65e5\u5e38\u5de5\u4f5c(\u90f5\u5bc4:\u7c89\u5dba\u5b89\u6a02\u6751\u6a02\u696d\u8def11\u865f\u6c38\u6052\u4f01\u696d\u5927\u5ec8)\n\n\u8cc7\u6b77 :\u4e2d\u4e09\u7a0b\u5ea6; 1\u5e74\u7d93\u9a57; \u826f\u597d\u7cb5\u8a9e; \u4e00\u822c\u666e\u901a\u8a71; \u4e00\u822c\u82f1\u8a9e; \u61c2\u8b80\u5beb\u4e2d\u6587; \u7565\u61c2\u8b80\u5beb\u82f1\u6587\n\n\u5f85\u9047 :\u6bcf\u6708$12,500, \u6709\u96d9\u7ce7, \u9280\u884c\u5047\u671f \u53ca\u6bcf\u6708\u52e4\u5de5\u734e\u91d1$300, \u661f\u671f\u4e00\u81f3\u4e94: \u4e0a\u53488\u6642\u81f3\u4e0b\u53485\u6642\u534a\u53ca\u661f\u671f\u516d: \u4e0a\u53488\u6642\u81f3\u4e0b\u53481\u6642, \u6bcf\u9031\u5de5\u4f5c5\u5929\u81f35\u5929\u534a, \u661f\u671f\u516d\u9577\u77ed\u9031\n\n\u7533\u8acb\u9808\u77e5 :\u50b3\u771f(26026263)/\u96fb\u90f5(Apply Now)/\u90f5\u5bc4\u5c65\u6b77\u8868\u7d66\u6c38\u6052\u6d0b\u884c\u91ab\u7642\u7528\u54c1\u6709\u9650\u516c\u53f8\u3002\u5982\u8981\u7d22\u53d6\u6536\u96c6\u500b\u4eba\u8cc7\u6599\u8072\u660e, \u8acb\u8207\u9673/\u6c88\u5c0f\u59d0(Fax/Email/Post)\u806f\u7d61\n\n", "employment_types": ["Full Time"], "selling_points": [], "locations": ["Fanling"], "categories": ["Transportation & Logistics", "Freight Forwarding", "Inventory / Warehousing", "Supply Chain"], "post_time": "2022-01-17T07:52:56Z", "salary": {"currency": null, "max": null, "min": null, "period": "monthly", "term": null}, "salary_visible": false, "title_keywords": [], "responsibilities": [], "requirements": {"degrees": [], "majors": [], "languages": [], "language_level": [], "hard_skills": [], "soft_skills": [], "languages_combined": []}, "experience_required": {"duration": [], "field": []}}, {"job_id": "100003009052642", "location_code": "hk", "company": "Tai Luen Coffee Co Ltd", "job_title": "Temporary Clerk", "description": "Job Descriptions:\n\nProvide full spectrum of administrative and clerical support in daily operations\nAssist to prepare monthly reports, documents , correspondence and summaries\u00a0\nAssist in ad hoc assignments\n\n\u00a0The ideal candidate should be :\n\nDiploma in Business Administration or related disciplines or above\u00a0\nAble to work independently, well organized, strong sense of responsibility, detail-minded, self-motivated, good communication and interpersonal skills\nGood command in spoken and written English and Chinese\nProficiency in MS Office software application and Chinese word processing\nImmediate available is highly preferred\n\nPlease send your application with resume and expected salary to The HR Manager, Tai Luen Coffee Company Limited, 7/F, DCH Building, 20 Kai Cheung Road, Kowloon Bay or send your application online by clicking\u00a0\"Apply Now\".\n\nInformation provided will be for the purpose of selection within the company and only shortlisted candidates will be contacted. All applications will be retained for a maximum period of 6 months.\u00a0", "employment_types": ["Part Time", "Temporary"], "selling_points": [], "locations": ["Shatin Area"], "categories": ["Admin & HR", "Clerical / Admin Staff", "Transportation & Logistics", "Shipping", "Supply Chain"], "post_time": "2022-01-17T03:37:46Z", "salary": {"currency": null, "max": null, "min": null, "period": "monthly", "term": null}, "salary_visible": false, "title_keywords": ["temporary clerk"], "responsibilities": ["software", "monthly reports", "hr", "communication", "daily operations", "ad hoc assignments", "administrative and clerical support", "administration"], "requirements": {"degrees": ["diploma"], "majors": ["related disciplines", "business administration"], "languages": ["english", "chinese"], "language_level": ["proficiency", "good command"], "hard_skills": ["chinese word processing", "ms office"], "soft_skills": ["detail-minded", "work independently", "self-motivated", "sense of responsibility", "well organized", "communication and interpersonal skills", "ideal"], "languages_combined": [{"language": "english", "language_level": ["good command"]}, {"language": "chinese", "language_level": ["proficiency", "good command"]}]}, "experience_required": {"duration": [], "field": []}}, {"job_id": "100003009046079", "location_code": "hk", "company": "Shopkyo Limited", "job_title": "Operations Specialist (2 vacancies)", "description": "About this role:\nThis role is designed to facilitate the movement of shipments while discovering and driving efficiencies that smoothen and improve operations. You will serve as a liaison for our 3PLs, Customers, Sales Team, Customer Service Team, IT team, and other internal functions to ensure operational efficiency and excellent customer experience.\n\nYou will be responsible for ensuring that our 3PLs are executed according to plan, on time, and within budget.\nYou will have the opportunity to spot opportunities to improve customer experience, streamline processes, and introduce innovative ways of managing a supply chain.\nYou will gain experience in operation management, effective communication, relationship building, creative solution design, and deep industry knowledge with this role.\n\nYour day to day jobs (RESPONSIBILITIES):\n\nImplement operational procedures in the day-to-day workflow, and constantly identify and execute on opportunities to realize optimal efficiency and productivity.\nCoordinate day-to-day operations with internal and external partners such as vendor warehouse, express delivery carriers, domestic delivery carriers, the sales team, the customer representative team, and IT teams.\nDevelop and implement guidelines/ procedures to control and improve the operation efficiency and quality\nTimely shipment troubleshooting and exception escalation\n\nREQUIREMENTS:\n\nDiploma Graduate or above in any disciplines, preferred in Operations Management, Logistics, Supply Chain or related discipline\nAt least 1 year or above experience\nAbility to work independently and collaborate with a team\nPositive, optimistic, and confident person able to continue moving forward when faced with adversity\nProcess-oriented, structured thinking with strong problem-solving capabilities Excellent communication, interpersonal and organizational skills\nOperations Strong analytical and problem-solving skills with a good sense of risk management\nFluent spoken and written in English and Chinese including Mandarin\nLogistics/freight forwarding/e-commerce experience preferred but not required\nHolder of Dangerous Goods Awareness or Dangerous Goods Regulations would be an advantage\nImmediately Available is an advantage\n\nOur offer\n\nWe will give you the best support we possibly could for you to produce your best work. This includes providing you with:\n\nDiverse career advancement opportunity\nAllowance for self-learning (udemy, coursea, skillshare, etc)\nResult Driven Work Environment\n\nAdditional perks\n\n-Medical Insurance\n-Free Drinks, Snacks\n-Gym membership at Science Park\n\nMore info about Spaceship on\n\nLinkedIn:\u00a0https://hk.linkedin.com/company/spaceshiphk\nFacebook:\u00a0https://www.facebook.com/spaceshiphongkong\nWebsite:\u00a0https://spaceship.hk/", "employment_types": ["Full Time", "Permanent"], "selling_points": ["Market leading all-in-one smart logistic solution", "Start-up and energetic environment", "Great learning opportunity"], "locations": ["Tseung Kwan O"], "categories": ["Transportation & Logistics", "Fulfillment", "Shipping", "Supply Chain"], "post_time": "2022-01-13T09:33:26Z", "salary": {"currency": null, "max": null, "min": null, "period": "monthly", "term": null}, "salary_visible": false, "title_keywords": ["specialist", "operations"], "responsibilities": ["control", "guidelines", "teams", "day-to-day operations", "procedures", "develop", "coordinate", "quality", "troubleshooting", "operational procedures", "sales team"], "requirements": {"degrees": ["diploma"], "majors": ["any disciplines"], "languages": ["english", "chinese", "mandarin"], "language_level": ["fluent"], "hard_skills": ["problem-solving skills", "problem-solving", "facebook", "e-commerce"], "soft_skills": ["confident", "organizational skills", "work independently", "problem-solving", "driven", "communication", "diverse", "learning", "problem-solving skills", "structured", "interpersonal", "positive"], "languages_combined": [{"language": "english", "language_level": ["fluent"]}, {"language": "chinese", "language_level": ["fluent"]}, {"language": "mandarin", "language_level": ["fluent"]}]}, "experience_required": {"duration": ["at least 1 year"], "field": ["logistics", "e-commerce"]}}, {"job_id": "100003009050403", "location_code": "hk", "company": "Links International", "job_title": "Logistic Operation & CS Manager", "description": "Logistic Operation & CS Manager - Fashion Retailer\n\nOur client is a large international fashion retailer, looking for a Logistic Operation & CS Manager to join their organization. Oversee and manage the operation of 3PL warehouses and all trade logistics for Hong Kong and Macau Market.\n\nResponsibilities:\n\n\nLead and coach a team of specialists, coordinate with vendors in handling logistic operations such as inventory aging, sales orders pick-pack-ship process and shipment arrangement.\nMonitor all processes for receiving, processing, pick and pack and returns handling.\nWork closely with NBIL to manage local market IAS processes.\nCreate operations strategies and solutions based on global / regional strategic priorities.\nManage and refine warehouse operations, ensuring smooth and efficient operation.\nOversees and reports weekly, monthly, quarterly, and annual metrics.\nPerform regular audit of the local warehouse.\nIdentify cost savings opportunities, identify logistic trends and assesses opportunities to improve operational procedures and execution.\nWorks closely with regional operations team and Hong Kong finance team on other special planning and various new developing projects.\n\nQualifications:\n\n\nA strong educational background in Logistics, Supply Chain Management or related discipline is preferably\n10 years in supply chain and warehouse operation years in a multinational company is preferred. At least 5 years of working experience in operation management.\nKnowledge and experiences in supply chain optimization, warehouse operation, systems, inventory planning, shipping, order management, replenishment, CS\nBeing entrepreneurial; gets things done and constantly looking for ways to improve.\nExcellent command in both English and Chinese\nHigh motivation and self-discipline to work independently", "employment_types": ["Full Time", "Permanent"], "selling_points": ["Retail experience preferred", "HK & Macau Coverage, lead team", "Logistic and CS Management"], "locations": ["Not Specified"], "categories": ["Transportation & Logistics", "Fulfillment", "Inventory / Warehousing", "Supply Chain"], "post_time": "2022-01-14T10:19:05Z", "salary": {"currency": "HKD", "max": 54999, "min": 45000, "period": "monthly", "term": null}, "salary_visible": true, "title_keywords": ["manager"], "responsibilities": ["shipping", "operations", "inventory", "audit", "monitor", "developing", "operational procedures", "logistics", "reports", "finance team", "cost", "management", "shipment arrangement", "coordinate with", "inventory planning", "order management", "systems", "replenishment", "3pl warehouses", "warehouse operations", "planning"], "requirements": {"degrees": [], "majors": [], "languages": ["english", "chinese"], "language_level": ["excellent"], "hard_skills": ["processing"], "soft_skills": ["efficient", "work independently", "smooth"], "languages_combined": [{"language": "english", "language_level": ["excellent"]}, {"language": "chinese", "language_level": ["excellent"]}]}, "experience_required": {"duration": ["at least 5 years"], "field": ["management", "supply chain", "operation management", "operation", "cs", "planning"]}}, {"job_id": "100003009053915", "location_code": "hk", "company": "TUV Rheinland Hong Kong Limited", "job_title": "\u5009\u52d9\u52a9\u7406 (Warehouse Assistant)", "description": "Job Responsibilities:\n\n\u8ca0\u8cac\u65e5\u5e38\u5009\u52d9\u904b\u4f5c\u53ca\u5009\u5eab\u6574\u7406\n\u8655\u7406\u8ca8\u7269\u5eab\u5b58\uff0c\u5305\u62ec\u5206\u985e\u3001\u9ede\u7b97\u53ca\u8a18\u9304\n\u4fdd\u6301\u8ca8\u5009\u5b89\u5168\u3001\u6e05\u6f54\u3001\u6574\u9f4a\u53ca\u6709\u7cfb\u7d71\u904b\u4f5c\n\u8207\u5167\u90e8\u90e8\u9580\uff0c\u4f9b\u61c9\u5546\u53ca\u5feb\u905e\u516c\u53f8\u5354\u8abf\u767c\u8ca8\u53ca\u51fa\u8ca8\n\u5354\u52a9\u5b8c\u6210\u516c\u53f8\u6307\u6d3e\u7684\u8077\u52d9\n\nJob Requirements:\n\n1\u5e74\u6216\u4ee5\u4e0a\u5009\u52d9\u7d93\u9a57\n\u57fa\u672c\u96fb\u8166\u64cd\u4f5c\n\u5de5\u4f5c\u614b\u5ea6\u826f\u597d\uff0c\u505a\u4e8b\u6709\u689d\u7406\u53ca\u6709\u8010\u6027\uff0c\u80fd\u7368\u7acb\u8655\u7406\u4e8b\u60c5\n\u9808\u642c\u904b\u8ca8\u7269\u53ca\u9ad4\u529b\u52de\u52d5\n\nOther benefits:\n\n\u9280\u884c\u5047\n\u96d9\u7ce7\n12\u5929\u6709\u85aa\u5e74\u5047\n\u91ab\u7642\u6d25\u8cbc\n\u7259\u79d1\u6d25\u8cbc\n\nAll information received will be kept in strict confidence and used for employment purpose only. Applicants who are not invited for interview within\u00a05 weeks may assume their applications unsuccessful and their data will be retained for 6 months for other suitable vacancies in our organization and thereafter destroyed.", "employment_types": ["Full Time", "Permanent"], "selling_points": ["\u8212\u9069\u51b7\u6c23\u8ca8\u5009", "\u7a69\u5b9a\u5de5\u4f5c\u74b0\u5883", "\u57fa\u672c\u96fb\u8166\u64cd\u4f5c"], "locations": ["Tsuen Wan Area"], "categories": ["Admin & HR", "Clerical / Admin Staff", "Transportation & Logistics", "Inventory / Warehousing", "Supply Chain"], "post_time": "2022-01-17T07:45:15Z", "salary": {"currency": null, "max": null, "min": null, "period": "monthly", "term": null}, "salary_visible": false, "title_keywords": ["warehouse assistant", "\u5009\u52d9\u52a9\u7406"], "responsibilities": [], "requirements": {"degrees": [], "majors": [], "languages": [], "language_level": [], "hard_skills": [], "soft_skills": [], "languages_combined": []}, "experience_required": {"duration": [], "field": []}}, {"job_id": "100003009051947", "location_code": "hk", "company": "Quantium Solutions (Hong Kong) Limited", "job_title": "Customer Service Supervisor/Executive", "description": "Quantium Solutions\n\nQS is an established eCommerce logistics services provider in the Asia Pacific Region. Headquartered in Singapore, we are ideally positioned to be the best gateway to Asia.\n\nOur serviced offices now serve the needs of enterprises and entrepreneurs across major 200 countries and 18 markets.\n\nAt QS, creating a workplace that provides opportunities for each of you and we believe in you and know you\u2019ll do great things. As an employer, our role is to empower you by bringing your true talents and best self to this dynamic digital world and people we serve.\n\n\n\n\nJob Description\n\nResponsibilities:\n\nProcess customer requests fast and efficiently.\nTake ownership of customer issues and follow through problems to solutions.\nResponsible for customer retention and relationship building with customers.\nAssess customers\u2019 needs and collaborate with other counterpart to provide quality service.\nClosely work with Operations, Sales and other counterpart for service enhancement.\nAssist in ad-hoc project when required.\n\nRequirements:\n\nBachelor\u2019s degree or equivalent in business, logistics or related disciplines;\nAt least 1 year working experience in customer services;\nProactive, customer-oriented with strong interpersonal and problem-solving skills;\nProficiency in MS Word, Excel and Power Point;\nGood communication in both written and verbal English, Chinese and Mandarin;\nImmediately available is highly preferred.\u00a0\u00a0\nCandidates with less experience will be considered as Customer Service Executive\n\nWe offer attractive remuneration package including medical insurance, life insurance, dental and other fringe benefits to the right candidate. Interested parties please send your full resume with date of availability, present and expected salaries to us\n\n\n", "employment_types": ["Full Time", "Permanent"], "selling_points": [], "locations": ["Wong Tai Sin Area"], "categories": ["Sales, CS & Business Devpt", "Call Centre", "Customer Service - Supervisor / Officer", "Transportation & Logistics", "Supply Chain"], "post_time": "2022-01-17T01:36:24Z", "salary": {"currency": null, "max": null, "min": null, "period": "monthly", "term": null}, "salary_visible": false, "title_keywords": ["customer service supervisor", "executive"], "responsibilities": ["collaborate with", "ad-hoc", "operations", "quality", "customer requests", "customer issues"], "requirements": {"degrees": ["degree", "bachelor"], "majors": ["related disciplines", "business"], "languages": ["english", "chinese", "mandarin"], "language_level": ["good"], "hard_skills": ["power point", "problem-solving skills", "excel", "ms word"], "soft_skills": ["communication", "customer-oriented", "customer service", "problem-solving skills", "proactive", "interpersonal"], "languages_combined": [{"language": "english", "language_level": ["good"]}, {"language": "chinese", "language_level": ["good"]}, {"language": "mandarin", "language_level": ["good"]}]}, "experience_required": {"duration": ["at least 1 year"], "field": ["customer service", "customer services"]}}, {"job_id": "100003009053855", "location_code": "hk", "company": "Drake Overload Ltd", "job_title": "Logistics Associate (1-year contract)/ (1 \u5e74\u5408\u7d04\uff09", "description": "Job responsibility \u8077\u8cac:\n\n\u8ca0\u8cac\u65e5\u5e38\u7269\u6d41\u71df\u904b\uff0c\u4f8b\u5982\uff1a\u63a5\u6536\u53ca\u4fdd\u5b58\u8a02\u55ae\u548c\u904b\u8f38\u8a18\u9304\uff1b\u7ba1\u7406\u53ca\u66f4\u65b0\u5eab\u5b58(Responsible on daily logistic operation, including receiving order, updating shipping record, and inventory management.)\n\u8207\u5ba2\u6236\u5bc6\u5207\u5408\u4f5c\uff0c\u8ddf\u9032\u8a02\u55ae\u00a0 \u00a0(Cooperating with clients in shipping orders.)\n\u6e96\u5099\u5b9a\u671f\u5831\u544a\u00a0 \u00a0(Preparing periodic reports for senior manager.)\n\u8207\u5ba2\u6236\u3001\u5916\u90e8\u548c\u5167\u90e8\u5404\u65b9\u5354\u8abf\u00a0 \u00a0(Communicating with clients, internal and external staff on logistics and shipping matters.)\n\u57f7\u884c\u7ba1\u7406\u5c64\u5206\u914d\u7684\u5176\u4ed6\u8077\u8cac\u00a0 \u00a0(Perform ad hoc task organized by manager.)\n\u63d0\u4f9b2-3\u500b\u6708\u5728\u8077\u57f9\u8a13\uff0c\u57f9\u8a13\u5f8c\u9700\u5230\u5ba2\u6236\u516c\u53f8\u5de5\u4f5c\u00a0(2-3 months on-job training are provide and candidates are required to support client\u2019s company on client\u2019s site after training.)\n\nRequirement \u8981\u6c42:\n\n\u526f\u5b78\u58eb\u6216\u5b78\u58eb\u5b78\u4f4d\u6216\u4ee5\u4e0a\u00a0 \u00a0(Associate degree or Bachelor\u2019s Degree above candidates are welcomed.)\n\u6b61\u8fce\u73fe\u5c46\u5927\u5b78\u7562\u696d\u751f\u00a0(Fresh Graduates are welcomed.)\n1\u5e74\u6216\u4ee5\u4e0a\u7269\u6d41/\u5009\u52d9\u6587\u54e1\u53ca\u76f8\u95dc\u5ba2\u670d\u7d93\u9a57\u00a0 \u00a0(Minimum 1 year of related experience in logistics or warehousing experience are preferred)\n\u7121\u76f8\u95dc\u7d93\u9a57\u8005\u4ea6\u6703\u8003\u616e\u00a0(Candidates with non-related experience will also be considered\n\u826f\u597d\u7684\u82f1\u8a9e\u3001\u5ee3\u6771\u8a71\u548c\u666e\u901a\u8a71\u00a0 \u00a0(Good in English, Cantonese and Mandarin speaking and writing skills are required.)\n\u6709\u8cac\u4efb\u5fc3\u3001\u80fd\u7368\u7acb\u5de5\u4f5c\u00a0 \u00a0(Candidates with responsible and are available in working independently.)\n\u7cbe\u901a MS \u8fa6\u516c\u61c9\u7528\u7a0b\u5e8f\uff0c\u5305\u62ec Excel\u3001Word\u00a0(Good computer skills, for instance, basic skills in Microsoft Excel and Word.)", "employment_types": ["Full Time", "Contract"], "selling_points": ["1-year contract 1\u5e74\u5408\u7d04", "Fresh Graduates are welcomed \u6b61\u8fce\u73fe\u5c46\u5927\u5b78\u7562\u696d\u751f", "2-3 months on-job training 2-3\u500b\u6708\u5728\u8077\u57f9\u8a13"], "locations": ["Central"], "categories": ["Transportation & Logistics", "Supply Chain"], "post_time": "2022-01-17T07:37:47Z", "salary": {"currency": "HKD", "max": 16999, "min": 14000, "period": "monthly", "term": null}, "salary_visible": true, "title_keywords": ["associate", "logistics"], "responsibilities": ["shipping", "ad hoc", "inventory management", "communicating with", "logistics", "reports"], "requirements": {"degrees": ["associate degree", "degree", "bachelor"], "majors": [], "languages": ["cantonese", "english", "mandarin"], "language_level": ["good"], "hard_skills": ["basic", "word", "writing skills", "microsoft excel", "computer skills"], "soft_skills": ["independently", "writing skills", "responsible"], "languages_combined": [{"language": "cantonese", "language_level": ["good"]}, {"language": "english", "language_level": ["good"]}, {"language": "mandarin", "language_level": ["good"]}]}, "experience_required": {"duration": ["minimum 1 year"], "field": ["related", "logistics"]}}, {"job_id": "100003009053699", "location_code": "hk", "company": "Convey Telecom Engineering Limited", "job_title": "\u904b\u4f5c\u52a9\u7406 (\u5009\u52d9)", "description": "\n\u8077\u8cac :\u4e00\u822c\u5009\u52d9\u6587\u54e1\u5de5\u4f5c, \u8ca8\u5009\u65e5\u5e38\u904b\u4f5c, \u8ddf\u9032\u6536\u767c\u51fa\u8ca8, \u76e4\u9ede, \u66f4\u65b0\u5009\u5b58\u8a18\u9304, \u8ddf\u9032\u53ca\u8655\u7406\u4e3b\u7ba1\u5206\u914d\u7684\u5176\u4ed6\u5de5\u4f5c\u7b49, \u9700\u5916\u52e4\u53ca\u9ad4\u529b\u52de\u52d5\n\n\u8cc7\u6b77 :\u4e2d\u4e94\u7a0b\u5ea6; 1\u5e74\u7d93\u9a57; \u826f\u597d\u7cb5\u8a9e\u512a\u5148; \u4e00\u822c\u666e\u901a\u8a71; \u4e00\u822c\u82f1\u8a9e; \u61c2\u8b80\u5beb\u4e2d\u6587; \u7565\u61c2\u8b80\u5beb\u82f1\u6587\n\n\u5f85\u9047 :\u6bcf\u6708$12,000 - $14,000, \u6709\u52e4\u5de5\u734e\u91d1, \u91ab\u7642\u798f\u5229 \u53ca\u9280\u884c\u5047\u671f, \u4e0a\u534810\u6642\u534a\u81f3\u4e0b\u53487\u6642\u534a, \u6bcf\u9031\u5de5\u4f5c5\u5929\u81f36\u5929,\u8f2a\u4f11, \u6bcf\u5929\u5de5\u4f5c 9 \u5c0f\u6642, \u6bcf\u67086\u5929\u4f11\u606f\u65e5, \u4f11\u606f\u65e5\u5b9a\u65bc\u975e\u516c\u773e\u5047\u671f\n\n\u7533\u8acb\u9808\u77e5 :\u6c42\u8077\u8005\u53ef\u96fb\u90f5(Apply Now)\u5c65\u6b77\u8868\u7d66\u8fc5\u9054\u96fb\u8a0a\u5de5\u7a0b\u6709\u9650\u516c\u53f8\u3002\u5982\u8981\u7d22\u53d6\u6536\u96c6\u500b\u4eba\u8cc7\u6599\u8072\u660e, \u8acb\u8207\u95dc\u5c0f\u59d0(Fax:24997885)\u806f\u7d61\u3002\n\n", "employment_types": ["Full Time"], "selling_points": [], "locations": ["Wong Tai Sin Area"], "categories": ["Transportation & Logistics", "Others", "Inventory / Warehousing", "Supply Chain"], "post_time": "2022-01-17T07:22:23Z", "salary": {"currency": null, "max": null, "min": null, "period": "monthly", "term": null}, "salary_visible": false, "title_keywords": ["\u5009\u52d9"], "responsibilities": [], "requirements": {"degrees": [], "majors": [], "languages": [], "language_level": [], "hard_skills": [], "soft_skills": [], "languages_combined": []}, "experience_required": {"duration": [], "field": []}}, {"job_id": "100003009056689", "location_code": "hk", "company": "Bay Blue (Hongkong) Trading Co., Limited", "job_title": "\u5009\u5eab\u7ba1\u7406\u54e1 Storekeeper/ Stock keeper", "description": "\u5009\u5eab\u7ba1\u7406\u54e1\n\u516c\u53f8/\u50f1\u4e3b\u540d\u7a31 :\u7063\u85cd(\u9999\u6e2f)\u8cbf\u6613\u6709\u9650\u516c\u53f8\n\u5730\u5340 :\u6c99\u7530\n\u884c\u696d :\u9032\u51fa\u53e3\u8cbf\u6613\n\u8077\u8cac :\u5009\u52d9\u7ba1\u7406, \u5eab\u5b58\u6838\u5c0d, \u51fa\u5165\u5eab\u6838\u5c0d\u7b49\n\u8cc7\u6b77 :\u4e2d\u4e09\u7a0b\u5ea6; 1\u5e74\u7d93\u9a57; \u826f\u597d\u7cb5\u8a9e; \u826f\u597d\u666e\u901a\u8a71; \u4e00\u822c\u82f1\u8a9e; \u61c2\u8b80\u5beb\u4e2d\u6587; \u61c2\u8b80\u5beb\u82f1\u6587\n\u5f85\u9047 :\u6bcf\u6708$12,000 - $14,000, \u6709\u9280\u884c\u5047\u671f, \u54e1\u5de5\u8cfc\u7269\u512a\u60e0\u53ca\u8d85\u6642\u5de5\u4f5c\u6d25\u8cbc, \u4e0a\u53489\u6642\u81f3\u4e0b\u53486\u6642, \u6bcf\u9031\u5de5\u4f5c5\u5929\u81f36\u5929, \u6bcf\u5929\u5de5\u4f5c 8 \u5c0f\u6642, \u661f\u671f\u516d\u9577\u77ed\u9031\n\u7533\u8acb\u9808\u77e5 :\u6c42\u8077\u8005\u53ef\u96fb\u90f5\u5c65\u6b77\u8868\u7d66\u7063\u85cd(\u9999\u6e2f)\u8cbf\u6613\u6709\u9650\u516c\u53f8\u3002\u5982\u8981\u7d22\u53d6\u6536\u96c6\u500b\u4eba\u8cc7\u6599\u8072\u660e, \u8acb\u8207\u6b50\u5c0f\u59d0(Tel:59393656)\u806f\u7d61\u3002", "employment_types": ["Full Time"], "selling_points": ["\u4e2d\u4e09\u7a0b\u5ea6", "1\u5e74\u7d93\u9a57", "\u826f\u597d\u7cb5\u8a9e"], "locations": ["Shatin Area"], "categories": ["Transportation & Logistics", "Others", "Inventory / Warehousing", "Supply Chain"], "post_time": "2022-01-18T05:47:47Z", "salary": {"currency": null, "max": null, "min": null, "period": "monthly", "term": null}, "salary_visible": false, "title_keywords": ["storekeeper"], "responsibilities": [], "requirements": {"degrees": [], "majors": [], "languages": [], "language_level": [], "hard_skills": [], "soft_skills": [], "languages_combined": []}, "experience_required": {"duration": [], "field": []}}, {"job_id": "100003009052061", "location_code": "hk", "company": "OOCL Logistics Ltd", "job_title": "Manager/Assistant Manager, Pricing, Import & Export (Ref: M/AM/OPLUS)", "description": "At global level to develop and drive procurement strategy, defining guidelines and processes for responsibilities diversification between Corporate and Regions.\u00a0Drive to generate freight volumes across regions to support expansion and optimization of\u00a0carriers\u00a0portfolio and cost.\u00a0\n\n\u00a0Responsibilities:\u00a0\n\n\nDrive the volume growth while developing, and executing plans to enable future growth of assigned accounts\u00a0\nHandle daily rate and tender / RQF enquiry\u00a0\nParticipate in market research and prepare regular rate analysis\u00a0\nAchieve full renewals of agreement\u00a0\nDevelop the customers into strategic name account tier\u00a0\nAnalyze customers\u2019 support of our products and services, promote focused trade lanes and products including core\u00a0carriers\u00a0undertakings.\u00a0\nCollaborate with sales teams in selling cycles to achieve the business deals\nAssist support teams to onboard new customers\u00a0\nParticipate to generate and define business development plans and opportunities in line with carrier procurement direction\n\nRequirements:\u00a0\n\nUniversity graduate with minimum 5 years of proven ocean freight experience in Shipping, NVOCC or Freight Forwarding industries, pricing or sales/customer service experiences in sea-freight products would be an advantage\u00a0\nAccount management skills and experience, with high proficiency in MS Word, Excel and Power-point\u00a0\nStrong sales partner development skills and the ability to build and execute plans to increase sales partner performance\u00a0\u00a0\nExcellent interpersonal, communication, teamwork, and project management skills required\u00a0\nStrong analytical, negotiation, presentation and writing skills\u00a0\nProactive, detailed-minded\u00a0\u00a0\nGood command of English and Chinese\u00a0\nInterested parties, please submit your application letter together with detailed resume and copies of your latest transcript\u00a0by clicking \u201cApply Now\u201d.\n\n(Data collected will be used for recruitment purpose only.)", "employment_types": ["Full Time"], "selling_points": ["sea freight/freight fordwarding", "procurement & sales", "pricing, tender/RQF handling"], "locations": ["Kwun Tong"], "categories": ["Transportation & Logistics", "Freight Forwarding", "Shipping", "Supply Chain"], "post_time": "2022-01-17T02:00:18Z", "salary": {"currency": null, "max": null, "min": null, "period": "monthly", "term": null}, "salary_visible": false, "title_keywords": ["manager", "assistant manager,"], "responsibilities": ["collaborate with", "analysis", "teams", "developing", "market research", "develop", "executing", "tender", "plans"], "requirements": {"degrees": ["university graduate"], "majors": [], "languages": ["english", "chinese"], "language_level": ["good command"], "hard_skills": ["excel", "project management", "writing skills", "ms word"], "soft_skills": ["negotiation", "project management skills", "teamwork", "presentation", "writing skills", "communication", "customer service", "proactive", "interpersonal", "detailed"], "languages_combined": [{"language": "english", "language_level": ["good command"]}, {"language": "chinese", "language_level": ["good command"]}]}, "experience_required": {"duration": ["minimum 5 years"], "field": ["customer service", "account management"]}}, {"job_id": "100003009051011", "location_code": "hk", "company": "PARKnSHOP", "job_title": "Inventory Planning Executive", "description": "You can enjoy:\n\nComprehensive Medical and Life insurance coverage, including your spouse and children\nExclusive company pension schemes\nMarriage, Maternity and Paternity Leave\nExclusive shopping discount, Bazaar Sales for our people only\nProfessional training and career advancement opportunities\nConvenient office location, less than 5 min. walk from MTR\nContemporary workplace with Onsite Clinic, Lactation Rooms, free drinks and chill out areas\nWell-equipped Gym inside our office building, plus fitness and interest class packages\nFree round-trip lunchtime shuttle bus services to Shatin\nResponsibilities:\n\nCollect and analyse data in monitoring inventory level in optimal level\nAct as a first-screener to check stores request and draft a stock allocation plan and replenishment schedule in a timely manner\nLiaise with suppliers and buying team for order management and monitor the order fulfillment\nCoordinate with different internal departments and warehouse to ensure replenishment activities are properly implemented and executed\nRequirements:\n\nDiploma holder or above in Supply Chain Management, Operations Management, Logistics or related discipline\n1-2 years' relevant experience in logistics operations and supply chain, from Retail / FMCG are highly preferred\nGood command of English & Chinese with strong interpersonal, communication and negotiation skills\nCompetency in Excel (Vlookup & Pivot-table)\nExperience with ERP and POS system is an advantage\nAble to work under pressure and complexity\nAn attractive salary and benefit package will be offered. Interested parties please forward detailed resume stating expected salary to: People Department, PARKnSHOP (HK) Limited, Watson House, 1-5 Wo Liu Hang Road, Fo Tan, N.T. or email to us.\n\nWe are an equal opportunity employer and welcome applications from all qualified candidates. The information provided will be treated in strict confidence and be used only for consideration of your application for relevant / similar posts within the A.S. Watson Group. All personal data of unsuccessful applicants will be destroyed within 12 months from the date of application.", "employment_types": ["Full Time"], "selling_points": [], "locations": ["Shatin Area"], "categories": ["Transportation & Logistics", "Others", "Inventory / Warehousing", "Supply Chain"], "post_time": "2022-01-15T00:47:51Z", "salary": {"currency": null, "max": null, "min": null, "period": null, "term": null}, "salary_visible": false, "title_keywords": ["executive"], "responsibilities": ["order management", "data", "stock allocation", "inventory", "monitoring", "a timely manner", "replenishment", "monitor", "coordinate with", "order fulfillment", "schedule", "plan", "liaise with suppliers", "analyse"], "requirements": {"degrees": ["diploma holder"], "majors": [], "languages": ["english", "chinese"], "language_level": ["good command"], "hard_skills": ["excel", "vlookup", "pos system", "erp"], "soft_skills": ["communication", "negotiation skills", "interpersonal", "work under pressure"], "languages_combined": [{"language": "english", "language_level": ["good command"]}, {"language": "chinese", "language_level": ["good command"]}]}, "experience_required": {"duration": ["1-2 years"], "field": ["fmcg", "supply chain", "logistics", "relevant experience", "retail"]}}, {"job_id": "100003009053924", "location_code": "hk", "company": "Man Shun Cheong Enterprise Limited", "job_title": "\u5009\u52d9\u54e1/\u7406\u8ca8\u54e1", "description": "\n\u8077\u8cac :\u4e00\u822c\u5009\u52d9\u54e1/\u7406\u8ca8\u54e1\u5de5\u4f5c, \u4e00\u822c\u5009\u52d9\u5de5\u4f5c,\u5982\u6536\u8ca8,\u9ede\u8ca8,\u57f7\u8ca8,\u4e0a\u67b6,\u767c\u8ca8\u7b49\n\n\u8cc7\u6b77 :\u4e2d\u4e09\u7a0b\u5ea6; \u826f\u597d\u7cb5\u8a9e\n\n\u5f85\u9047 :\u6bcf\u6708$13,000 - $15,000, \u6709\u54e1\u5de5\u8cfc\u7269\u512a\u60e0 \u53ca\u4f9b\u81b3\u98df, \u661f\u671f\u4e00\u81f3\u4e94: \u4e0a\u53489\u6642\u81f3\u4e0b\u53486\u6642\u53ca\u661f\u671f\u516d: \u4e0a\u53489\u6642\u81f3\u4e0b\u53483\u6642, \u6bcf\u9031\u5de5\u4f5c5\u5929\u81f36\u5929\n\n\u7533\u8acb\u9808\u77e5 :\u6c42\u8077\u8005\u53ef\u96fb\u90f5(Apply Now)\u5c65\u6b77\u8868\u7d66\u842c\u9806\u660c\u4f01\u696d\u6709\u9650\u516c\u53f8\u3002\u5982\u8981\u7d22\u53d6\u6536\u96c6\u500b\u4eba\u8cc7\u6599\u8072\u660e, \u8acb\u8207\u5468\u5c0f\u59d0(25451190)\u806f\u7d61\u3002\n\n", "employment_types": ["Full Time"], "selling_points": [], "locations": ["Sheung Wan"], "categories": ["Transportation & Logistics", "Others", "Inventory / Warehousing", "Supply Chain"], "post_time": "2022-01-17T07:47:15Z", "salary": {"currency": null, "max": null, "min": null, "period": "monthly", "term": null}, "salary_visible": false, "title_keywords": ["\u7406\u8ca8\u54e1", "\u5009\u52d9\u54e1"], "responsibilities": [], "requirements": {"degrees": [], "majors": [], "languages": [], "language_level": [], "hard_skills": [], "soft_skills": [], "languages_combined": []}, "experience_required": {"duration": [], "field": []}}, {"job_id": "100003009053159", "location_code": "hk", "company": "", "job_title": "Shipping clerk", "description": "Global companies' (Europe/USA) Hong Kong office\n\nPosition : Shipping clerk\n\nWorking: Tsimshatsui\n\nRequirements :\n\nRelevant experience in food additives, chemicals or pharmaceuticals is advantage\nKnowledge in logistic/shipping system & checking of the export documents are essential. (Preparation of full set shipping documents is NOT required).\nCommunication with Chinese producers in Mandarin is a must\nFluent in spoken English & Mandarin and reading & writing in English are most important.\nFamiliar with Ms Word, Outlook, Excel & Chinese Word Processing\nImmediate available is highly preferable\n\nOffer attractive salary & 5 days work to the right candidate\n\nInterested candidates, please contact us at 62122989 for company details before applying.", "employment_types": ["Full Time"], "selling_points": ["Passion, careful, attentive are essential", "Good working environment", "Immediate available is highly preferable"], "locations": ["Tsim Sha Tsui"], "categories": ["Transportation & Logistics", "Documentary Credit / Bills Processing", "Supply Chain", "Merchandising & Purchasing", "Procurement / Purchasing / Sourcing"], "post_time": "2022-01-17T06:10:06Z", "salary": {"currency": null, "max": null, "min": null, "period": "monthly", "term": null}, "salary_visible": false, "title_keywords": ["shipping clerk"], "responsibilities": ["shipping documents", "communication", "shipping", "checking"], "requirements": {"degrees": [], "majors": [], "languages": ["english", "chinese", "mandarin"], "language_level": ["fluent"], "hard_skills": ["excel", "chinese word processing", "outlook", "ms word"], "soft_skills": ["communication"], "languages_combined": [{"language": "english", "language_level": ["fluent"]}, {"language": "chinese", "language_level": []}, {"language": "mandarin", "language_level": ["fluent"]}]}, "experience_required": {"duration": [], "field": ["food", "relevant experience"]}}, {"job_id": "100003009053745", "location_code": "hk", "company": "Tronic Technology International (Hong Kong) Limited", "job_title": "\u5009\u52d9\u54e1", "description": "\n\u8077\u8cac :\u4e00\u822c\u5009\u52d9\u54e1/\u7406\u8ca8\u54e1\u5de5\u4f5c\n\n\u8cc7\u6b77 :\u4e2d\u4e09\u7a0b\u5ea6; 2\u5e74\u7d93\u9a57; \u826f\u597d\u7cb5\u8a9e; \u61c2\u8b80\u5beb\u4e2d\u6587; \u7565\u61c2\u8b80\u5beb\u82f1\u6587; \u6301\u6709\u4f38\u5c55\u5f0f\u93df\u8eca\u724c\n\n\u5f85\u9047 :\u6bcf\u6708$14,000 - $15,000, \u6709\u8d85\u6642\u5de5\u4f5c\u6d25\u8cbc, \u96d9\u7ce7, \u52e4\u5de5\u734e\u91d1, \u5e74\u504710\u5929, \u9280\u884c\u5047\u671f \u53ca\u7a7f\u68ad\u5df4\u58eb\u670d\u52d9, \u661f\u671f\u4e00\u81f3\u4e94: \u4e0a\u53489\u6642\u81f3\u4e0b\u53486\u6642\u53ca\u661f\u671f\u516d: \u4e0a\u53489\u6642\u81f3\u4e0b\u53481\u6642, \u6bcf\u9031\u5de5\u4f5c5\u5929\u534a, \u6bcf\u5929\u5de5\u4f5c 8 \u5c0f\u6642\n\n\u7533\u8acb\u9808\u77e5 :\u6c42\u8077\u8005\u53ef\u96fb\u90f5(Apply Now)\u5c65\u6b77\u8868\u7d66\u5275\u9818\u79d1\u6280\u570b\u969b(\u9999\u6e2f)\u6709\u9650\u516c\u53f8\u3002\u5982\u8981\u7d22\u53d6\u6536\u96c6\u500b\u4eba\u8cc7\u6599\u8072\u660e, \u8acb\u8207\u9f94\u5148\u751f(Email)\u806f\u7d61\u3002\n\n", "employment_types": ["Full Time"], "selling_points": [], "locations": ["Yuen Long"], "categories": ["Transportation & Logistics", "Others", "Inventory / Warehousing", "Supply Chain"], "post_time": "2022-01-17T07:26:59Z", "salary": {"currency": null, "max": null, "min": null, "period": "monthly", "term": null}, "salary_visible": false, "title_keywords": ["\u5009\u52d9\u54e1"], "responsibilities": [], "requirements": {"degrees": [], "majors": [], "languages": [], "language_level": [], "hard_skills": [], "soft_skills": [], "languages_combined": []}, "experience_required": {"duration": [], "field": []}}, {"job_id": "100003009051034", "location_code": "hk", "company": "Aeon Stores (Hong Kong) Co Ltd", "job_title": "Inventory Control Officer (Ref: JDB/LO)", "description": "Job Descriptions:\n\n\nManage cycle counts process on a regular basis;\nInvestigate discrepancies in reported quantities and locations of all inventory;\nPrepare weekly inventory report;\nPerform stock reconciliation to minimize variance\u00a0 & loss;\nAssist in company stock take preparation, arrangement and follow-up actions;\nSupport to system development; and\nPerform other duties and responsibilities as assigned.\n\n\u00a0Job Requirements:\n\nDegree holder with a major in Supply Chain Management or Logistics Management;\nAt least 5 years of relevant experience in supply chain management and in retail industry is preferred;\nIndependent, analytical, self-motivated with strong numerical sense and logical thinking;\nHardworking, organized and with a strong sense of responsibility, able to work independently under pressure and meet deadline with high accuracy;\nExcellent command of both written and spoken English and Chinese (Cantonese and Mandarin); and\nFamiliar with Microsoft Excel, Word, power point and Chinese Word Processing.\nCandidate with more experience will be considered as Senior Officer\n\n\nWe offer attractive remuneration package, commensurate with experience to the successful applicant. Interested parties please \"APPLY NOW\" by using full resume with current and expected salaries or send to\u00a0The Human Resources Manager, AEON Stores (Hong Kong) Co., Limited,\u00a0Units 7-11, 26 Floor, CDW Building, 388 Castle Peak Road, Tsuen Wan, New Territories, Hong Kong\n\n\u00a0\u00a0\u00a0\u201cAll application received will be kept strictly confidential and used exclusively for employment purpose only\u201d\n\n(Please quote our reference no. for the position applied on the envelope)", "employment_types": ["Full Time", "Permanent"], "selling_points": ["Inventory planning", "Double Pay", "Discretionary Bonus"], "locations": ["Tsuen Wan Area"], "categories": ["Transportation & Logistics", "Inventory / Warehousing", "Supply Chain"], "post_time": "2022-01-15T01:20:35Z", "salary": {"currency": null, "max": null, "min": null, "period": "monthly", "term": null}, "salary_visible": false, "title_keywords": ["officer"], "responsibilities": ["stock take", "inventory", "perform other duties", "report"], "requirements": {"degrees": ["degree holder"], "majors": [], "languages": ["cantonese", "english", "chinese", "mandarin"], "language_level": ["excellent"], "hard_skills": ["power point", "chinese word processing", "word", "microsoft excel"], "soft_skills": ["organized", "self-motivated", "work independently", "independent", "under pressure", "sense of responsibility", "hardworking"], "languages_combined": [{"language": "cantonese", "language_level": ["excellent"]}, {"language": "english", "language_level": ["excellent"]}, {"language": "chinese", "language_level": ["excellent"]}, {"language": "mandarin", "language_level": ["excellent"]}]}, "experience_required": {"duration": ["at least 5 years"], "field": ["retail industry", "supply chain", "management", "relevant experience"]}}, {"job_id": "100003009052882", "location_code": "hk", "company": "Sensory Artisan Group Limited", "job_title": "Storekeeper \u5009\u52d9\u54e1", "description": "\u8077\u8cac\uff1a\n\n\u8ca0\u8cac\u642c\u904b\u8ca8\u7269\u53ca\u8ca0\u8cac\u5009\u52d9\u904b\u4f5c, \u5305\u62ec\u9ede\u6536\u8ca8\u7269\u3001\u8ca8\u54c1\u5206\u985e\u3001\u57f7\u8ca8\u3001\u6574\u7406\u8ca8\u5009\u7684\u6b63\u5e38\u7a0b\u5e8f\n\u6aa2\u67e5\u8ca8\u54c1\u7684\u8cea\u7d20\u53ca\u6578\u91cf\n\u8207\u4f9b\u61c9\u5546\u8ddf\u9032\u8ca8\u54c1\u6bcf\u65e5\u7684\u4ea4\u6536\n\u78ba\u4fdd\u904b\u8f38\u8ca8\u54c1\u7684\u7a0b\u5e8f\u7b26\u5408\u516c\u53f8\u8981\u6c42\uff0c\u5305\u62ec\u4f9b\u61c9\u5546\u767c\u7968\uff0c\u8655\u7406\u8ca8\u54c1\u7684\u8cea\u7d20\u53ca\u6578\u91cf\n\u8655\u7406\u8ca8\u54c1\u51fa\u5009\uff0f\u5165\u5009\u3001\u9ede\u6536\u8ca8\u7269\uff0c\u7ba1\u7406\u5009\u5b58\u8a18\u9304\uff0c\u78ba\u4fdd\u5eab\u5b58\u6578\u64da\u7684\u6e96\u78ba\u6027\u548c\u5b8c\u6574\u6027\n\u6574\u7406\u5b58\u8ca8\u8a18\u9304\u53ca\u76e4\u9ede\u5b58\u8ca8\n\u4fdd\u6301\u8ca8\u5009\u74b0\u5883\u5b89\u5168\u53ca\u885b\u751f\u6574\u6f54\n\n\u00a0\u00a0 \u5165\u8077\u8981\u6c42\uff1a\n\n\u4e2d\u5b78\u6216\u4ee5\u4e0a\u7a0b\u5ea6\n\u6700\u5c11\u4e00\u5e74\u76f8\u95dc\u5de5\u4f5c\u7d93\u9a57\uff0c\u64c1\u6709\u98f2\u98df\u53ca\u670d\u52d9\u696d\u8005\u7d93\u9a57\u512a\u5148\n\u5c0d\u98df\u7269\u5b89\u5168\u885b\u751f\u6a19\u6e96\u6709\u76f8\u7576\u8a8d\u8b58\n\u61c2\u5f97\u96fb\u8166\u61c9\u7528\n\u5177\u8cac\u4efb\u611f\uff0c\u80fd\u7368\u7acb\u5de5\u4f5c\u53ca\u64c1\u6709\u826f\u597d\u6e9d\u901a\u6280\u5de7\n\n.\u5168\u8077\u798f\u5229\uff1a\n\n\u6bcf\u9031\u5de5\u4f5c5\u5929\u534a, \u6bcf\u5929\u5de5\u4f5c 9\u5c0f\u6642\n\u9280\u884c\u5047\u671f\u53ca10\u5929\u6709\u85aa\u5e74\u5047\n\u54e1\u5de5\u8cfc\u7269\u53ca\u9910\u98f2\u6298\u6263\u512a\u60e0\n\n\u5982\u6709\u8208\u8da3\u53ef\u4ee5\u5c07\u7c21\u55ae\u300c\u500b\u4eba\u5c65\u6b77\u300d\u53ca\u300c\u8981\u6c42\u5f85\u9047\u300d\u96fb\u90f5\u6216 WhatsApp 2511 6021 \u67e5\u8a62\u3002", "employment_types": ["Full Time"], "selling_points": ["\u78ba\u4fdd\u6536\u8ca8\u3001\u57f7\u8ca8\u3001\u6574\u7406\u8ca8\u5009\u7684\u6b63\u5e38\u7a0b\u5e8f", "\u6700\u5c11\u4e00\u5e74\u76f8\u95dc\u5de5\u4f5c\u7d93\u9a57", "\u64c1\u6709\u98f2\u98df\u53ca\u670d\u52d9\u696d\u8005\u7d93\u9a57\u512a\u5148"], "locations": ["Not Specified"], "categories": ["Transportation & Logistics", "Documentary Credit / Bills Processing", "Inventory / Warehousing", "Supply Chain"], "post_time": "2022-01-17T04:24:36Z", "salary": {"currency": "HKD", "max": 16999, "min": 14000, "period": "monthly", "term": null}, "salary_visible": true, "title_keywords": ["storekeeper", "\u5009\u52d9\u54e1"], "responsibilities": [], "requirements": {"degrees": [], "majors": [], "languages": [], "language_level": [], "hard_skills": ["whatsapp"], "soft_skills": [], "languages_combined": []}, "experience_required": {"duration": [], "field": []}}, {"job_id": "100003009053825", "location_code": "hk", "company": "Nutrilink Limited", "job_title": "\u9ad8\u7d1a\u5009\u52d9\u54e1", "description": "\n\u8077\u8cac :\u8ca0\u8cac\u5009\u52d9\u7269\u6d41\u5de5\u4f5c\n\n\u8cc7\u6b77 :\u4e2d\u4e94\u7a0b\u5ea6; \u826f\u597d\u7cb5\u8a9e; \u4e00\u822c\u82f1\u8a9e; \u61c2\u8b80\u5beb\u4e2d\u6587; \u7565\u61c2\u8b80\u5beb\u82f1\u6587; \u6709\u7d93\u9a57\u512a\u5148\n\n\u5f85\u9047 :\u6bcf\u6708$16,000, \u6709\u5168\u5e74\u734e\u91d1\u7d041-2\u500b\u6708\u6708\u85aa, \u661f\u671f\u4e00\u81f3\u516d: \u4e0a\u53488\u6642\u534a\u81f3\u4e0b\u53485\u6642\u534a, \u6bcf\u9031\u5de5\u4f5c6\u5929\n\n\u7533\u8acb\u9808\u77e5 :\u6c42\u8077\u8005\u53ef\u81f4\u96fb98878846\u8207\u71df\u532f\u98df\u54c1\u6709\u9650\u516c\u53f8\u5433\u5148\u751f\u806f\u7d61\u3002\n\n", "employment_types": ["Full Time"], "selling_points": [], "locations": ["Not Specified"], "categories": ["Transportation & Logistics", "Others", "Inventory / Warehousing", "Supply Chain"], "post_time": "2022-01-17T07:35:22Z", "salary": {"currency": null, "max": null, "min": null, "period": "monthly", "term": null}, "salary_visible": false, "title_keywords": [], "responsibilities": [], "requirements": {"degrees": [], "majors": [], "languages": [], "language_level": [], "hard_skills": [], "soft_skills": [], "languages_combined": []}, "experience_required": {"duration": [], "field": []}}, {"job_id": "100003009050520", "location_code": "hk", "company": "Rohlig Hong Kong Limited", "job_title": "Logistics Coordinator", "description": "Specific duties including, but not restricted to\u00a0:\n\nResponse to customer's needs in timely manner in effective communication\nEnsure timely invoicing, internal expense report and month-end closing\nInventory Management for responsible Customer\u2019s\nAdminister the in and out records\nControl stock distribution with internal and external parties\n\n\nRequirement\n\n1 - 2 year(s) 3rd parties logistics firm experiences, customer services and PRC coordination. (Fresh graduates will also be considered)\nKnowledge in warehouse operation is an advantage\nF.5 / DSE or above. Diploma in Logistics Management or Inventory Management is an advantage.\nHands-on computer skills (Proficiency in MS Office Application)\nA good team player (Initiative, independent & willing to work under pressure & overtime)\nGood command of written and spoken English, Chinese and Mandarin\nMore experienced will be considered as Senior Logistics Coordinator\n\nWorking Location:\u00a0 Tsing Yi\u00a0\n\nInterested parties please send FULL resume with CURRENT & EXPECTED SALARY to us:\na p p l y . h k g @ r o h l i g . c o m\n\nFor further information of our company, please visit our website: \u00a0www.rohlig.com\n\nAll information received will be kept in strict confidence and only for employment-related purpose.\n", "employment_types": ["Full Time", "Permanent"], "selling_points": ["Inventory Management for responsible Customer\u2019s", "F.5 / DSE or above", "Administer the in and out records"], "locations": ["Tsing Yi"], "categories": ["Transportation & Logistics", "Inventory / Warehousing", "Supply Chain", "Others", "Student / Fresh Graduate / No Experience"], "post_time": "2022-01-14T10:36:37Z", "salary": {"currency": null, "max": null, "min": null, "period": "monthly", "term": null}, "salary_visible": false, "title_keywords": ["logistics coordinator"], "responsibilities": ["control", "management", "work under pressure", "internal and external parties", "customer services", "communication", "invoicing", "inventory management", "month-end closing", "logistics", "coordination", "report"], "requirements": {"degrees": ["diploma", "dse"], "majors": [], "languages": ["english", "chinese", "mandarin"], "language_level": ["good command"], "hard_skills": ["computer skills", "ms office"], "soft_skills": ["good team player", "independent", "responsible", "timely", "communication", "hands-on", "coordination", "initiative", "work under pressure"], "languages_combined": [{"language": "english", "language_level": ["good command"]}, {"language": "chinese", "language_level": ["good command"]}, {"language": "mandarin", "language_level": ["good command"]}]}, "experience_required": {"duration": [], "field": ["logistics", "customer services"]}}, {"job_id": "100003009056599", "location_code": "hk", "company": "Cathay Pacific Services Limited", "job_title": "Cargo Services Officer - Tractor \u7a7a\u904b\u670d\u52d9\u4e3b\u4efb - \u62d6\u982d\u64cd\u4f5c\u54e1", "description": "\u00a0Responsibilities:\nTo operate equipment vehicles, including tractor and pusher for ULD towing and ULD transfer\nTo complete all assignment allocated by superior; to perform ULD towing to/from CPCT, and ULD transfer\nHands-on experience in apron driving related to ramp operation is preferable\nRequirements:\nForm 3 standard or above\nHolder of valid Hong Kong Driving License (class 1 and 2) and clean driving record\nShift duty including overnight duty is required\n\nRecruitment Days (Walk-in Interview)\n\nDate: 24 January 2022 (Monday)\nTime: 14:00 \u2013 17:00\u00a0\nVenue: Desk One, 23/F, Chung Kiu Commercial Building, 47-51 Shantung Street, Mong Kok, Kowloon\u00a0(Mong Kok MTR Station Exit E2)\n\nDate: 27 January 2022 (Thursday)\u00a0\nTime: 14:00 \u2013 16:30\u00a0\nVenue: 9/F, High Block, Queensway Government Offices, 66 Queensway, Hong Kong (Admiralty MTR Station Exit C1)\n\nDate: 11 February 2022 (Friday)\u00a0\nTime: 14:00 \u2013 17:00\u00a0\nVenue: Desk One, 21/F, Hang Seng Tsuen Wan Building, 289 Sha Tsui Road, Tsuen Wan\u00a0(Tsuen Wan MTR Station Exit B1)\n\nDate: 17 February 2022 (Thursday)\u00a0\nTime: 14:00 \u2013 17:00\u00a0\nVenue: Desk One, 20/F, 2004-06, Tower 1, Grand Central Plaza, 138 Sha Tin Rural Committee Road, Sha Tin\u00a0(Sha Tin MTR Station Exit B)\n\nDate: 23 \u00a0February 2022 (Wednesday)\u00a0\nTime: 14:00 \u2013 17:00\u00a0\nVenue: YMCA of Hong Kong Beacon Centre \u2013 Lifelong Learning Institute, No. 373, Po On Road, Kowloon\u00a0(Cheung Sha Wan MTR station Exit C2)\n\nDate: 3 March 2022 (Wednesday)\nTime: 14:00 \u2013 17:00\u00a0\nVenue: Desk One, 23/F, Chung Kiu Commercial Building, 47-51 Shantung Street, Mong Kok, Kowloon\u00a0(Mong Kok MTR Station Exit E2)\n\n* please bring along your 1) HKID Card, 2) Resume, 3) Original Copies of School & Work Certificates, 4) Original Driving License (if applicable)\n\n\nIf you are interested, please\u00a0call 2767-9375 during office hours as well as by WeChat/Whatsapp at 5599-2177 for interview appointment. For application, you may simply click Apply Online\u00a0on our website or email your confidential resume with date of availability, current and expected salary to recruitment @cpsl.com.hk. Applicants not contacted within 6 weeks may consider their applications unsuccessful.\n\nCathay Pacific Services Limited is an Equal Opportunities Employer. Personal data provided by job applicants will be used strictly in accordance with our personal data policy and for recruitment purposes only. Candidates not notified within six weeks may consider their application unsuccessful. All related information will be kept in our file for up to 24 months.\n\u00a0\n\n\u8077\u8cac\uff1a\n\n\u8ca0\u8cac\u64cd\u4f5c\u516c\u53f8\u5404\u985e\u578b\u6a5f\u68b0\u8a2d\u65bd\u3001\u8eca\u8f1b\u53ca\u62d6\u982d\n\u4f9d\u7167\u7763\u5c0e\u54e1\u6307\u793a\uff0c\u8ca0\u8cac\u8655\u7406\u96c6\u88dd\u5668\u62d6\u5e36\u53ca\u8ca8\u904b\u7ad9\u4e4b\u9593\u96c6\u88dd\u5668\u4ea4\u6536\u8655\u7406\n\u5177\u6709\u76f8\u95dc\u8ca8\u904b\u8655\u7406\u53ca\u505c\u6a5f\u576a\u99d5\u99db\u8005\u512a\u5148\n\u5165\u8077\u689d\u4ef6\uff1a\n\u4e2d\u4e09\u7a0b\u5ea6\u6216\u4ee5\u4e0a\n\u9808\u6301\u6709\u6548\u9999\u6e2f\u99d5\u99db\u57f7\u71671\u53ca2\u985e\u53ca\u826f\u597d\u99d5\u99db\u8a18\u9304\n\u9700\u8f2a\u73ed\u53ca\u591c\u73ed\u5de5\u4f5c\n\n\u62db\u8058\u65e5\u00a0(\u5373\u5834\u9762\u8a66)\n\n\u65e5\u671f\uff1a2022\u5e741\u670824\u65e5\uff08\u661f\u671f\u4e00\uff09\n\u6642\u9593\uff1a14:00\u00a0\u2013 17:00\n\u5730\u9ede\uff1a\u65fa\u89d2\u5c71\u6771\u885747-51\u865f\u4e2d\u50d1\u5546\u696d\u5927\u5ec823\u6a13Desk One\u00a0(\u65fa\u89d2\u7ad9E2\u51fa\u53e3)\n\n\u65e5\u671f\uff1a2022\u5e741\u670827\u65e5\uff08\u661f\u671f\u56db)\n\u6642\u9593\uff1a14:00\u00a0\u2013 16:30\n\u5730\u9ede\uff1a\u9999\u6e2f\u91d1\u9418\u905366\u865f\u91d1\u9418\u9053\u653f\u5e9c\u5408\u7f72\u9ad8\u5ea79\u6a13 (\u91d1\u9418\u7ad9C1\u51fa\u53e3)\n\n\u65e5\u671f\uff1a2022\u5e742\u670811\u65e5\uff08\u661f\u671f\u4e94)\n\u6642\u9593\uff1a14:00\u00a0\u2013 17:00\n\u5730\u9ede\uff1a\u8343\u7063\u6c99\u5480\u9053289\u865f\u6052\u751f\u8343\u7063\u5927\u5ec821\u6a13Desk One(\u8343\u7063\u7ad9B1\u51fa\u53e3)\n\n\u65e5\u671f\uff1a2022\u5e742\u670817\u65e5\uff08\u661f\u671f\u56db)\n\u6642\u9593\uff1a14:00\u00a0\u2013 17:00\n\u5730\u9ede\uff1a\u6c99\u7530\u5a1c\u4e8b\u6703\u8def138\u865f\u65b0\u57ce\u5e02\u4e2d\u592e\u5ee3\u58341\u5ea720\u6a1304-06\u5ba4Desk One (\u6c99\u7530\u7ad9B\u51fa\u53e3)\n\n\u65e5\u671f\uff1a2022\u5e742\u670823\u65e5\uff08\u661f\u671f\u4e09)\n\u6642\u9593\uff1a14:00\u00a0\u2013 17:00\n\u5730\u9ede\uff1a\u4e5d\u9f8d\u4fdd\u5b89\u9053373\u865f\u897f\u4e5d\u9f8d\u8000\u4fe1\u767c\u5c55\u5b78\u7fd2\u4e2d\u5fc3\u00a0(\u9577\u6c99\u7063\u7ad9C2\u51fa\u53e3)\n\n\u65e5\u671f\uff1a2022\u5e743\u67083\u65e5\uff08\u661f\u671f\u4e09\uff09\n\u6642\u9593\uff1a14:00\u00a0\u2013 17:00\n\u5730\u9ede\uff1a\u65fa\u89d2\u5c71\u6771\u885747-51\u865f\u4e2d\u50d1\u5546\u696d\u5927\u5ec823\u6a13Desk One\u00a0(\u65fa\u89d2\u7ad9E2\u51fa\u53e3)\n\n*\u00a0\u8acb\u5e36\u540c\u60a8\u7684\u00a01)\u00a0\u8eab\u4efd\u8b49, 2)\u00a0\u5c65\u6b77\u8868, 3)\u00a0\u5b78\u6b77\u53ca\u5de5\u4f5c\u200b\u8b49\u660e\u6587\u4ef6\u6b63\u672c, 4)\u00a0\u8eca\u724c\u00a0(\u5982\u9069\u7528)\n\n\u6709\u610f\u61c9\u5fb5\u8005\u53ef\u65bc\u8fa6\u516c\u6642\u9593\u5167\u81f4\u96fb2767-9375\u6216Whatsapp 5599-2177\u5b89\u6392\u9762\u8a66\u3002\u60a8\u4ea6\u53ef\u6309\"\u7db2\u4e0a\u7533\u8acb\"\u6216\u5c07\u500b\u4eba\u5c65\u6b77\u8868\u9023\u540c\u53ef\u5230\u8077\u65e5\u671f\u3001\u73fe\u6642\u53ca\u8981\u6c42\u5f85\u9047\u96fb\u90f5\u81f3recruitment @cpsl.com.hk\u3002\u82e5\u7533\u8acb\u8005\u65bc\u516d\u661f\u671f\u5167\u672a\u80fd\u63a5\u7372\u9762\u8a66\u901a\u77e5\uff0c\u5176\u7533\u8acb\u5c07\u5217\u70ba\u4e0d\u7372\u8003\u616e\u3002\n\n\n\u6709\u610f\u61c9\u5fb5\u8005\uff0c\u53ef\u65bc\u8fa6\u516c\u6642\u9593\u5167\u81f4\u96fb2767-9375\u6216 WeChat / Whatsapp 5599-2177\u5b89\u6392\u9762\u8a66\u3002\u60a8\u4ea6\u53ef\u6309\u7db2\u4e0a\u7533\u8acb\u6216\u5c07\u500b\u4eba\u5c65\u6b77\u8868\u9023\u540c\u53ef\u5230\u8077\u65e5\u671f\u3001\u73fe\u6642\u53ca\u8981\u6c42\u5f85\u9047\u96fb\u90f5\u81f3recruitment @cpsl.com.hk\u3002\u82e5\u7533\u8acb\u8005\u65bc\u516d\u661f\u671f\u5167\u672a\u80fd\u63a5\u7372\u9762\u8a66\u901a\u77e5\uff0c\u5176\u7533\u8acb\u5c07\u5217\u70ba\u4e0d\u7372\u8003\u616e\u3002\u00a0\n\n\u7533\u8acb\u4eba\u63d0\u4f9b\u4e4b\u5168\u90e8\u8cc7\u6599\u7d55\u5c0d\u4fdd\u5bc6\u53ca\u53ea\u4f5c\u62db\u8058\u7528\u9014\u3002\u82e5\u7533\u8acb\u8005\u65bc\u516d\u661f\u671f\u5167\u672a\u80fd\u63a5\u7372\u9762\u8a66\u901a\u77e5\uff0c\u5176\u7533\u8acb\u5c07\u5217\u70ba\u4e0d\u7372\u8003\u616e\uff0c\u672c\u516c\u53f8\u6055\u4e0d\u53e6\u884c\u901a\u77e5\u3002", "employment_types": ["Full Time", "Permanent"], "selling_points": ["Work in a world-class design cargo terminal", "Provide professional services to customers", "Work in a dynamic environment with opportunities"], "locations": ["Airport Area"], "categories": ["Transportation & Logistics", "Aviation Services", "Inventory / Warehousing", "Supply Chain"], "post_time": "2022-01-18T04:59:20Z", "salary": {"currency": null, "max": null, "min": null, "period": "monthly", "term": null}, "salary_visible": false, "title_keywords": ["officer"], "responsibilities": [], "requirements": {"degrees": [], "majors": [], "languages": [], "language_level": [], "hard_skills": ["clean", "no", "wechat", "whatsapp", "wan"], "soft_skills": ["learning"], "languages_combined": []}, "experience_required": {"duration": [], "field": []}}, {"job_id": "100003009049268", "location_code": "hk", "company": "Sa Sa Cosmetic Company Limited", "job_title": "Assistant Logistics Officer (Kwai Chung)", "description": "Responsibilities:\n\nProvide clerical support to operation team\nWork closely with other departments to follow up logistics processes\nPlan for delivery schedule and courier delivery to mainland China or overseas\nAnalyze operation data and prepare reports\nAd hoc project as assigned\n\nRequirements:\n\nForm 5 and DSE or above\n1 year or above logistics working experiences is preferable, fresh graduates will also be considered\nWilling to learn, work smart and good team player\nGood communication skills in Chinese\nProficient PC skills, Word and Excel, acknowledge of SAP is preferable\nImmediate available is an advantage\nAlternative work 6 or 5 days per week", "employment_types": ["Full Time"], "selling_points": ["Clerk, clerical support, data entry", "Diploma, Logistics, Warehouse", "Kwai Chung, warehouse, high salary"], "locations": ["Kwai Tsing Area"], "categories": ["Transportation & Logistics", "Supply Chain"], "post_time": "2022-01-14T08:20:40Z", "salary": {"currency": null, "max": null, "min": null, "period": null, "term": null}, "salary_visible": false, "title_keywords": ["assistant logistics officer"], "responsibilities": ["provide clerical support", "ad hoc", "follow up logistics processes", "data", "work closely with other departments", "delivery schedule", "plan", "prepare reports", "courier delivery"], "requirements": {"degrees": ["form 5", "dse"], "majors": [], "languages": ["chinese"], "language_level": ["good"], "hard_skills": ["excel", "pc skills", "word", "sap"], "soft_skills": ["communication skills", "good team player", "work smart", "willing to learn"], "languages_combined": [{"language": "chinese", "language_level": ["good"]}]}, "experience_required": {"duration": ["1 year"], "field": ["logistics"]}}, {"job_id": "100003009053617", "location_code": "hk", "company": "Gate Way Valve & Fitting Limited", "job_title": "\u5009\u52d9\u54e1/\u7406\u8ca8\u54e1", "description": "\n\u8077\u8cac :\u4e00\u822c\u5009\u52d9\u54e1/\u7406\u8ca8\u54e1\u5de5\u4f5c, \u4e00\u822c\u5009\u52d9\u5de5\u4f5c,\u5982\u6536\u8ca8,\u9ede\u8ca8,\u57f7\u8ca8,\u4e0a\u67b6,\u767c\u8ca8\u7b49, \u642c\u904b\u8ca8\u7269, \u76e4\u9ede\u5b58\u8ca8, \u5b89\u6392\u7269\u6d41\u670d\u52d9\n\n\u8cc7\u6b77 :\u4e2d\u4e09\u7a0b\u5ea6; \u826f\u597d\u7cb5\u8a9e; \u61c2\u8b80\u5beb\u4e2d\u6587; \u7565\u61c2\u8b80\u5beb\u82f1\u6587; \u5177\u6c34\u5589\u5009\u52d9\u5de5\u4f5c\u7d93\u9a57\u512a\u5148\n\n\u5f85\u9047 :\u6bcf\u6708$13,000 - $15,000, \u6709\u96d9\u7ce7, \u9280\u884c\u5047\u671f \u53ca\u914c\u60c5\u6027\u82b1\u7d05, \u661f\u671f\u4e00\u81f3\u4e94: \u4e0a\u53488\u6642\u81f3\u4e0b\u53485\u6642\u534a\u53ca\u661f\u671f\u516d: \u4e0a\u53488\u6642\u81f3\u4e0b\u53484\u6642, \u6bcf\u9031\u5de5\u4f5c5\u5929\u81f36\u5929, \u661f\u671f\u516d\u9577\u77ed\u9031\n\n\u7533\u8acb\u9808\u77e5 :\u6c42\u8077\u8005\u53ef\u81f4\u96fb63544088\u8207\u57fa\u6cd5\u6c34\u7ba1\u914d\u4ef6\u6709\u9650\u516c\u53f8\u6797\u5148\u751f\u806f\u7d61\u3002\n\n", "employment_types": ["Full Time"], "selling_points": [], "locations": ["Yuen Long"], "categories": ["Transportation & Logistics", "Others", "Inventory / Warehousing", "Supply Chain"], "post_time": "2022-01-17T07:15:00Z", "salary": {"currency": null, "max": null, "min": null, "period": "monthly", "term": null}, "salary_visible": false, "title_keywords": ["\u7406\u8ca8\u54e1", "\u5009\u52d9\u54e1"], "responsibilities": [], "requirements": {"degrees": [], "majors": [], "languages": [], "language_level": [], "hard_skills": [], "soft_skills": [], "languages_combined": []}, "experience_required": {"duration": [], "field": []}}, {"job_id": "100003009053308", "location_code": "hk", "company": "DHL Global Forwarding (Hong Kong) Limited", "job_title": "Executive, Business Solution, Asia Pacific (with less experience will be considered)", "description": "Working Location : Kwai Hing\n\nResponsibilities:\n\nTo support Solution improvements for existing accounts\nTo support new business development by building creative solutions to meet customer needs\nTo support the implementation of new business and existing clients\nTo strive for positive feedback from global / region network\nTo support senior management in developing knowledge and skill sets that differentiate DHL from the competition in meeting the needs of Key customers in AP and Globally\nTo identify areas of improvement and provide suggestions for advanced solutions\nTo support Global Business Solutions teams\n\nRequirements:\n\nDegree qualified or higher in supply chain discipline\nExperience in exporting from Asia, consolidation, and ideally ocean & air freight in logistics industry\nKnowledge of Asia-Pacific freight forwarding, warehousing and logistics business practices\nKnowledge in basic EDI and API setup, ISC systems in particular (Infor Nexus, MicroStratagies) is an advantage\nStrong planning and analytical skills\nStrong problem solving-skills, with ability to think outside of the box\nStrong communication and interpersonal skills\nDetail oriented, self-motivated and good team player\nAble to work independently\nFluent in both written and spoken English and Chinese, knowledge in Mandarin is an advantage\nRemarks: Less experience or Fresh Graduate who is willing to learn and grow with DHL\u00a0will be also considered as Senior Coordinator\n5 days work, career development, attractive remuneration and benefits package will be offered to the right candidate.\nApplications will be treated in strict confidence. Please send application with full particulars of qualifications, experience, current and expected salary\u00a0by clicking the\u00a0Apply now\u00a0button\u00a0or\u00a0by post to Human Resources Department, 4/F, EDGE, Nos. 30 \u2013 34 Kwai Wing Road, Kwai Chung, New Territories, Hong Kong.\u00a0\u00a0\nApplicants not contacted within six weeks may consider their applications unsuccessful.\u00a0\nPersonal Information Collection Statement pertaining to Recruitment\nDHL ISC (Hong Kong) Limited (\u201cDHL\u201d) is committed to protecting and respecting your privacy in accordance with the Personal Data (Privacy) Ordinance of Hong Kong (the \u201cOrdinance\u201d) and DHL\u2019s Personal Data Protection Policy (the \u201cPolicy\u201d) at\u00a0http://www.dhl.com.hk/en/legal.html#pdpp\nBy proceeding to respond to this recruitment advertisement you consent that we may use, retain, process, transfer or otherwise handle the personal data that we collect from you for recruitment purposes (including any other purposes directly related thereto) in accordance with the Policy.\nAll personal data of unsuccessful applicants will be retained for future recruitment purposes for a period of not more than six (6) months, after which such data will be destroyed.\nYou have the right at any time to make a data access or correction request concerning your personal data held by us. In addition, you may request us to delete your personal data that is no longer required for the relevant purposes which you have given consent. Should you wish to exercise such rights or have any question in relation to your personal data or the Policy, please contact our Human Resources Department.\nWhat is International Supply Chain (ISC)\nAn International Supply Chain Management service providing end-to-end order management, visibility and reporting for customers\u2019 international shipment flows across all transportation modes.\nThe solution links the origin supply chain with the destination requirements, resulting in a more cost effective and efficient supply chain with complete visibility and control.", "employment_types": ["Full Time", "Permanent"], "selling_points": [], "locations": ["Kwai Hing"], "categories": ["Transportation & Logistics", "Freight Forwarding", "Shipping", "Supply Chain"], "post_time": "2022-01-17T06:44:16Z", "salary": {"currency": null, "max": null, "min": null, "period": "monthly", "term": null}, "salary_visible": false, "title_keywords": ["executive"], "responsibilities": ["ap", "teams", "implementation", "developing", "senior management"], "requirements": {"degrees": ["degree", "fresh graduate"], "majors": [], "languages": ["english", "chinese", "mandarin"], "language_level": ["advantage", "fluent"], "hard_skills": ["problem solving", "basic", "analytical skills"], "soft_skills": ["self-motivated", "good team player", "work independently", "detail oriented", "willing to learn", "analytical skills", "problem solving", "communication and interpersonal skills"], "languages_combined": [{"language": "english", "language_level": ["advantage", "fluent"]}, {"language": "chinese", "language_level": ["advantage", "fluent"]}, {"language": "mandarin", "language_level": ["advantage", "fluent"]}]}, "experience_required": {"duration": [], "field": ["logistics industry", "consolidation"]}}, {"job_id": "100003009048088", "location_code": "hk", "company": "Active Components (HK) Ltd", "job_title": "Senior Logistics Officer", "description": "Responsibilities\n\n\u00a0\u00a0\u00a0\u00a0\u00a0\u00a0\u00a0\u00a0 Setting up freight pattern/freight guideline for suppliers and customers\n\u00a0\u00a0\u00a0\u00a0\u00a0\u00a0\u00a0\u00a0 Cost control/negotiation on freight with 3PL\n\u00a0\u00a0\u00a0\u00a0\u00a0\u00a0\u00a0\u00a0 Overseeing incoming and outgoing shipments\n\u00a0\u00a0\u00a0\u00a0\u00a0\u00a0\u00a0\u00a0 Organizing regular container shipment from HK\n\u00a0\u00a0\u00a0\u00a0\u00a0\u00a0\u00a0\u00a0 Overseeing warehouse in HK\n\u00a0\u00a0\u00a0\u00a0\u00a0\u00a0\u00a0\u00a0 Generating freight related reports\n\u00a0\u00a0\u00a0\u00a0\u00a0\u00a0\u00a0\u00a0 Liaising with factories, forwarders and internal departments (HK and oversea)\n\nRequirements\n\n\nDegree or above\nExperience in related field and ERP system is highly preferred\nProficient in MS Office\nGood command of written and spoken English, Cantonese and Mandarin\nAble to work independently, proactive and being a good team player\nImmediate availability/Short-notice is preferred\n\nPlease submit your resume with expected salary and availability by clicking \"Apply now\".", "employment_types": ["Full Time", "Permanent"], "selling_points": [], "locations": ["Kwun Tong"], "categories": ["Transportation & Logistics", "Inventory / Warehousing", "Supply Chain", "Others", "Trading"], "post_time": "2022-01-14T04:49:22Z", "salary": {"currency": null, "max": null, "min": null, "period": "monthly", "term": null}, "salary_visible": false, "title_keywords": ["senior logistics officer"], "responsibilities": ["reports", "liaising with", "cost control"], "requirements": {"degrees": ["degree or above"], "majors": [], "languages": ["cantonese", "english", "mandarin"], "language_level": ["good command"], "hard_skills": ["erp system", "ms office"], "soft_skills": ["good team player", "work independently", "proactive"], "languages_combined": [{"language": "cantonese", "language_level": ["good command"]}, {"language": "english", "language_level": ["good command"]}, {"language": "mandarin", "language_level": ["good command"]}]}, "experience_required": {"duration": [], "field": ["related", "erp system"]}}, {"job_id": "100003009053543", "location_code": "hk", "company": "Boss Industries Limited", "job_title": "\u5009\u52d9\u54e1/\u7269\u6d41\u54e1", "description": "\n\u8077\u8cac :\u4e00\u822c\u5009\u52d9\u5de5\u4f5c,\u5982\u6536\u8ca8,\u9ede\u8ca8,\u57f7\u8ca8,\u4e0a\u67b6,\u767c\u8ca8,\u6392\u8ca8,\u642c\u904b\u8ca8\u7269\u7b49;\u4e00\u822c\u5009\u52d9\u54e1/\u7406\u8ca8\u54e1\u5de5\u4f5c,\u66f4\u65b0\u5b58\u8ca8\u8a18\u9304,\u5b89\u6392\u7269\u6d41\u670d\u52d9,\u5b89\u6392\u904b\u9001\u8ca8\u7269,\u6aa2\u67e5\u4ea4\u8ca8\u662f\u5426\u6709\u640d\u58de\u6216\u5dee\u7570\uff0c\u78ba\u4fdd\u51fa\u8ca8\u6d41\u7a0b\u66a2\u9806\uff1b\u7ba1\u7406\u8ca8\u5009\u548c\u652f\u63f4\u5916\u51fa\u5de5\u4f5c\u7684\u540c\u4e8b\uff1b\u6574\u7406\u8ca8\u5009\uff0c\u6838\u5c0d\u5009\u5b58\u6578\u91cf\uff0c\u51fa\u5165\u7406\u8ca8\u5de5\u4f5c\uff0c\u66f4\u65b0\u5b58\u8ca8\u8a18\u9304, \u5009\u5b58\u7cfb\u7d71\u6578\u64da\u8f38\u5165\u548c\u8655\u7406\u4e00\u822c\u5009\u52d9\u6587\u4ef6\uff1b\u5176\u4ed6\u4e3b\u7ba1\u6307\u6d3e\u7684\u5de5\u4f5c\u3002\n\n\u8cc7\u6b77 :\u4e2d\u4e09\u7a0b\u5ea6; \u826f\u597d\u7cb5\u8a9e; \u4e00\u822c\u666e\u901a\u8a71; \u7565\u61c2\u8b80\u5beb\u4e2d\u6587; \u61c2\u96fb\u8166\u6587\u66f8\u8655\u7406\n\n\u5f85\u9047 :\u6bcf\u6708$12,000 - $15,000, \u6709\u734e\u52f5\u6027\u82b1\u7d05, \u661f\u671f\u4e00\u81f3\u516d: \u4e0a\u53489\u6642\u534a\u81f3\u4e0b\u53486\u6642\u534a, \u6bcf\u9031\u5de5\u4f5c5\u5929\u81f36\u5929, \u6bcf\u5929\u5de5\u4f5c 7 - 8 \u5c0f\u6642\n\n\u7533\u8acb\u9808\u77e5 :\u6c42\u8077\u8005\u53ef\u81f4\u96fb93139183\u8207\u535a\u601d\u4f01\u696d\u6709\u9650\u516c\u53f8\u912d\u5148\u751f\u806f\u7d61\u3002\n\n", "employment_types": ["Full Time"], "selling_points": [], "locations": ["Kwun Tong"], "categories": ["Transportation & Logistics", "Others", "Inventory / Warehousing", "Supply Chain"], "post_time": "2022-01-17T07:08:10Z", "salary": {"currency": null, "max": null, "min": null, "period": "monthly", "term": null}, "salary_visible": false, "title_keywords": ["\u5009\u52d9\u54e1"], "responsibilities": [], "requirements": {"degrees": [], "majors": [], "languages": [], "language_level": [], "hard_skills": [], "soft_skills": [], "languages_combined": []}, "experience_required": {"duration": [], "field": []}}, {"job_id": "100003009050754", "location_code": "hk", "company": "JAC Recruitment Hong Kong Co., Limited", "job_title": "Logistics Manager", "description": "OVERVIEW\nOur client is looking for a Logistics Manager for our client to work in Supply Chain & Operations team Main duties would include monitoring, improving the logistics workflows, driving projects, communicate with different parties including global customers, 3PLs, suppliers and our internal multi-functional teams. This role will be reporting to Supply Chain Director.\n\nJob Highlights\n>10 years working experience\nIn-house logistics experience preferred\n\nJOB RESPONSIBILITIES\nLead daily operational, ensure smooth order fulfilment, logistics planning, sales & purchase order creation, invoicing and import/export handling.\nOversees logistics workflows, cost improvements and benchmarking, lead a team in shipment planning & execution, import/export procedures & documentation,\u00a0\nManage and liaise with 3PLs\u00a0\nConstantly review existing workflows and provide improvement recommendations to enhance efficiency\n\nJOB REQUIREMENTS\nDegree holder, preferably in Business Administration, Supply Chain, Merchandising or related disciplines\n>10 years working experience in logistics sector, covering shipment planning & execution, as well as hands-on 3PLs management is preferable\nLead with strong sense of responsibility and ownership\nFluent command of spoken and written English, Cantonese and Mandarin is a MUST\nExcellent command of computer literacy in Word, Excel and PowerPoint\nA good team player, pro-active and with a mature mindset, outgoing, and self-motivated\nPositive, Confident and Smart\nImmediate availability is preferred\nPersonal data collected will be used for employment-related purpose only.\u00a0We\u00a0regret to inform that only shortlisted candidates will be notified, thank you.\n#LI-JACHK\n#countryhongkong", "employment_types": ["Full Time"], "selling_points": ["10 years+ Logistics Experience", "5 days work, 15 days AL, WFH, Insurance", "Multinational, dynamic culture"], "locations": ["Not Specified"], "categories": ["Transportation & Logistics", "Supply Chain"], "post_time": "2022-01-14T11:16:53Z", "salary": {"currency": null, "max": null, "min": null, "period": "monthly", "term": null}, "salary_visible": false, "title_keywords": ["logistics manager"], "responsibilities": ["cost", "review", "procedures", "invoicing", "lead a team", "purchase", "liaise with", "logistics", "documentation", "planning"], "requirements": {"degrees": ["degree holder"], "majors": ["related disciplines", "business administration"], "languages": ["cantonese", "english", "mandarin"], "language_level": ["fluent"], "hard_skills": ["excel", "inform", "word", "powerpoint"], "soft_skills": ["outgoing", "confident", "good team player", "self-motivated", "sense of responsibility", "mature", "computer literacy", "hands-on", "pro-active", "positive"], "languages_combined": [{"language": "cantonese", "language_level": ["fluent"]}, {"language": "english", "language_level": ["fluent"]}, {"language": "mandarin", "language_level": ["fluent"]}]}, "experience_required": {"duration": ["10 years"], "field": ["management", "logistics", "planning"]}}, {"job_id": "100003009054923", "location_code": "hk", "company": "Eternity Consultants (HK) Ltd", "job_title": "Shipping Clerk / Operation Clerk", "description": "Trading\n\n\u00a0\u00a0Requirements:\n\nF.5\nAt least 3 -8 years shipping experience in shipping in Trading or factory\n\nFull set of I/E, L/C documents\nContact with\u00a0vendor, overseas buyer, forwarder\nExperience in USA and Europe market\nGood communication and\n\nGood commend of both English and Mandarin\n\n*Interested parties, please Email full resume with current & expected salary & date available in MS WORD FORMAT ONLY to us\u00a0or fax to 3527 0634*\n\nFor more jobs, please visit our website: www.hketernity.com\n\n(Personal data submitted are for recruitment purpose only.)", "employment_types": ["Full Time", "Permanent"], "selling_points": ["5 days, bank holiday, 10 al", "Diploma or above", "3-8 yrs shipping exp in trading, factory"], "locations": ["Not Specified"], "categories": ["Transportation & Logistics", "Freight Forwarding", "Shipping", "Supply Chain"], "post_time": "2022-01-17T14:03:14Z", "salary": {"currency": null, "max": null, "min": null, "period": "monthly", "term": null}, "salary_visible": false, "title_keywords": ["shipping clerk", "operation clerk"], "responsibilities": ["communication", "shipping", "contact"], "requirements": {"degrees": [], "majors": [], "languages": ["english", "mandarin"], "language_level": ["good"], "hard_skills": ["c", "vendor"], "soft_skills": ["communication"], "languages_combined": [{"language": "english", "language_level": ["good"]}, {"language": "mandarin", "language_level": ["good"]}]}, "experience_required": {"duration": ["at least 3 -8 years"], "field": ["trading"]}}, {"job_id": "100003009050376", "location_code": "hk", "company": "Find Asia Limited", "job_title": "Shipping Clerk (5 days work)", "description": "Our client, an electronics manufacturing and trading company ,is now looking for a candidate with the following details:\n\nDuties:\n\nHandle Shipping documents support, contact with suppliers, factories and liaise with the forwarders for delivery arrangement\u00a0\nPrepare invoice, packing list, delivery documents and reports\nHandle goods delivery, support the team manager to solve the delivery issue\n\n\u00a0Requirement\u00a0\n\nExperience as Sales Admin/ Shipping/ Procurement/ Purchasing\u00a0in trading company, preferable in electronics industry\nGood Excel skills\u00a0\nIndependent and good team player\ndetail-minded and self-motivated", "employment_types": ["Full Time", "Permanent"], "selling_points": ["Shipping, I/E, delivery", "electronics components", "5 days, Double Pay, Bonus"], "locations": ["Tsim Sha Tsui"], "categories": ["Transportation & Logistics", "Shipping", "Supply Chain", "Manufacturing", "Production Planning / Control"], "post_time": "2022-01-15T19:11:42Z", "salary": {"currency": null, "max": null, "min": null, "period": "monthly", "term": null}, "salary_visible": false, "title_keywords": ["shipping clerk"], "responsibilities": ["shipping documents", "invoice", "packing list", "reports", "contact", "liaise with", "support the team"], "requirements": {"degrees": [], "majors": [], "languages": [], "language_level": [], "hard_skills": ["excel"], "soft_skills": ["detail-minded", "good team player", "independent", "self-motivated"], "languages_combined": []}, "experience_required": {"duration": [], "field": ["purchasing", "admin", "trading", "procurement"]}}, {"job_id": "100003009054391", "location_code": "hk", "company": "S.F. Express (Hong Kong) Limited", "job_title": "\u8eca\u8f1b\u7ba1\u7406\u52a9\u7406 - \u5b89\u5168", "description": "\u8077\u8cac:\n\n\u5354\u52a9\u8655\u7406\u4ea4\u901a\u610f\u5916\u5f8c\u7e8c\u7684\u8ddf\u9032\u5de5\u4f5c\n\u5354\u52a9\u8ddf\u9032\u8eca\u8f1b\u6295\u8a34\n\u5236\u4f5c\u6708\u5ea6\u5831\u8868\n\u5de5\u4f5c\u6642\u9593 : \u661f\u671f\u4e00\u81f3\u661f\u671f\u4e94 (09:00-18:00)\n\u5de5\u4f5c\u5730\u9ede : \u9752\u8863\u9806\u8c50\u5927\u6a13\u8fa8\u516c\u5ba4\n\n\u8981\u6c42:\n\n\u5927\u5c08\u6216\u4ee5\u4e0a\u5b78\u6b77\n\u6301\u67091, 2\u8eca\u724c\n\u5177\u5099\u826f\u597d\u7684\u6e9d\u901a\u80fd\u529b\u3001\u9748\u6d3b\u7684\u61c9\u8b8a\u80fd\u529b\u548c\u5718\u968a\u5408\u4f5c\u7cbe\u795e\n\u5177\u5099\u4f7f\u7528MS Office\u80fd\u529b\n\u53ef\u5373\u6642\u4e0a\u73ed\u512a\u5148\n\nWe offer attractive remuneration package and fringe benefits to the right candidates. Interested parties please submit your application to us.\u00a0\n\nYou are welcome to visit our website at\u00a0https://htm.sf-express.com/hk/tc/\u00a0for more information about us.\n\nCandidates who are not invited for interview within 1-month may consider their applications unsuccessful.\n\nAll personal data provided by job applicants will be used only for recruitment purpose and will be treated strictly confidential. Unsuccessful applications will be retained for a maximum period of 24-month.", "employment_types": ["Full Time", "Permanent"], "selling_points": ["Free shuttle bus coverage", "2 months or above performance bonus", "Attractive basic salary"], "locations": ["Tsing Yi"], "categories": ["Transportation & Logistics", "Supply Chain", "Private Transportation", "Public Transportation"], "post_time": "2022-01-17T09:20:33Z", "salary": {"currency": null, "max": null, "min": null, "period": "monthly", "term": null}, "salary_visible": false, "title_keywords": [], "responsibilities": [], "requirements": {"degrees": [], "majors": [], "languages": [], "language_level": [], "hard_skills": [], "soft_skills": [], "languages_combined": []}, "experience_required": {"duration": [], "field": []}}]