[{"job_id": "100003009054705", "location_code": "hk", "company": "Tricor Staffing Solutions Limited", "job_title": "Digital Marketing Executive - Fast-growing Technology Company", "description": "Our client is one of Fast-growing Technology company in Hong Kong. They are now looking for a\u00a0Digital Marketing Executive to support the business operations.\u00a0\n\nJob Description:\n\nKeep track of the daily performance of all online marketing and social media platforms\nBoost sales on in-house website and marketplaces by designing and implementing relevant marketing strategies\nOversee competitive offerings analysis, product listings and pricing\nReview and evaluate the effectives of marketing campaigns / activities to achieve sales targets\nPlan and monitor all online marketing strategies\n\nQualifications:\n\nHigher Diploma or above in Marketing, Digital, e-Commerce, or other relevant disciplines\n1-3 years of e-Commerce experience in a digital marketing\nFamiliar with Google Sheet, Excel, and other analytical tools\nKnowledge of javascript / python / development of Shopify is a plus\nPrevious exposure in operating e-commerce platforms (such as Amazon, Ebay, TMall, HKTVmall, etc.)\nPassionate in Internet industry\nStrong interpersonal and communication skills\nProficient in both written and spoken English and Chinese (Cantonese and Mandarin)", "employment_types": ["Full Time", "Part Time", "Permanent", "Temporary", "Contract", "Internship", "Freelance"], "selling_points": ["1-3 yrs of Digital Mkt or e-Commerce experience", "Regional exposure", "Google Sheet & Excel knowledge"], "locations": ["Lai Chi Kok"], "categories": ["Marketing / Public Relations", "Digital Marketing", "E-commerce", "Business Development", "Marketing - Brand / Product Management"], "post_time": "2022-01-17T10:41:22Z", "salary": {"currency": null, "max": null, "min": null, "period": "monthly", "term": null}, "salary_visible": false, "title_keywords": ["digital marketing executive"], "responsibilities": ["marketing strategies", "operations", "analysis", "social media platforms", "product listings", "website", "review", "monitor", "evaluate", "e-commerce platforms", "communication", "digital marketing", "marketing campaigns", "designing", "plan"], "requirements": {"degrees": ["higher diploma or above"], "majors": ["marketing", "e-commerce"], "languages": ["cantonese", "english", "chinese", "mandarin"], "language_level": ["proficient"], "hard_skills": ["excel", "plus", "amazon", "e-commerce", "shopify", "analysis", "javascript", "python"], "soft_skills": ["passionate", "communication skills", "interpersonal"], "languages_combined": [{"language": "cantonese", "language_level": []}, {"language": "english", "language_level": ["proficient"]}, {"language": "chinese", "language_level": ["proficient"]}, {"language": "mandarin", "language_level": []}]}, "experience_required": {"duration": ["1-3 years"], "field": ["digital marketing", "e-commerce"]}}, {"job_id": "100003009052847", "location_code": "hk", "company": "Chase Jewellery Manufactory Limited", "job_title": "eCommerce Executive", "description": "\u00a0eCommerce Executive\n- Coordinate and manage eCommerce funds among internal and external stakeholders\n- Responsible for driving eCommerce strategy for online platforms\n- Build brand awareness and across websites and online platforms\n- Monitor channels\u2019 effectiveness and report insightful analysis to optimize eCommerce performance\n\nRequirement:\n- Marketing or digital marketing experience preferred\n- Proficiency in MS Office applications\n- Good communication skills\n- Curious and eager to learn\n- Attractive remuneration package with 5-days work week, year-end bonus, commission upon reaching sales target\n\n\u00a0\u7db2\u7d61\u5546\u52d9\u96f6\u552e\n- \u8207\u5167\u5916\u76f8\u95dc\u8005\u8ddf\u9032\u4e26\u7ba1\u7406\u5df2\u6279\u7db2\u7d61\u5546\u52d9\u8cc7\u91d1\n- \u8ca0\u8cac\u898f\u5283\u4e26\u767c\u5c55\u6709\u6548\u7684\u7db2\u7d61\u5546\u52d9\u92b7\u552e\u7b56\u7565\n- \u5728\u7db2\u7d61\u5e73\u53f0\u767c\u5c55\u54c1\u724c\u77e5\u540d\u5ea6\n- \u7559\u610f\u4e26\u532f\u5831\u7db2\u7d61\u5e73\u53f0\u76f8\u95dc\u92b7\u552e\u53ca\u71df\u92b7\u6210\u6548\n\n\u8981\u6c42\uff1a\n- \u5177\u71df\u92b7\u6216\u96fb\u5b50\u71df\u92b7\u7d93\u9a57\u66f4\u4f73\n- \u719f\u6089\u96fb\u8166\u53ca MS Office \u57fa\u672c\u4f7f\u7528\u77e5\u8b58\u53ca\u6280\u80fd\n- \u826f\u597d\u6e9d\u901a\u80fd\u529b\n- \u6709\u597d\u5947\u5fc3\u4e26\u8b19\u865b\u5b78\u7fd2\n- \u512a\u8d8a\u5f85\u9047\uff0c5\u5929\u5de5\u4f5c\u5929\u3001\u5e74\u7d42\u82b1\u7d05\u3001\u96a8\u8868\u73fe\u767c\u653e\u4f63\u91d1\uff08\u53ef\u9762\u8ac7\uff09", "employment_types": ["Full Time"], "selling_points": [], "locations": ["Hung Hom"], "categories": ["E-commerce", "Business Development", "Marketing - Brand / Product Management", "Product Management / Business Analyst"], "post_time": "2022-01-17T04:16:26Z", "salary": {"currency": "HKD", "max": 19999, "min": 14000, "period": "monthly", "term": null}, "salary_visible": true, "title_keywords": ["ecommerce executive"], "responsibilities": ["year-end", "analysis", "sales target", "monitor", "coordinate", "communication", "digital marketing", "report"], "requirements": {"degrees": [], "majors": [], "languages": [], "language_level": [], "hard_skills": ["analysis", "ms office"], "soft_skills": ["communication skills", "responsible", "eager to learn"], "languages_combined": []}, "experience_required": {"duration": [], "field": ["marketing", "digital marketing"]}}, {"job_id": "100003009053632", "location_code": "hk", "company": "ASH (HK) Limited", "job_title": "E-commerce Executive", "description": "Job Responsibilities\n\nCoordinate with vendors on user requirements, website development and UAT\nManage products and contents includes product listing, conduct market research, product photo editing, compose product description and pricing\nManage the operation of marketplaces includes Amazon and Zalora\nDevelop creative ideas, mechanics flow, concepts and art direction for websites\nDrive online marketing initiatives, including SEO, CRM, affiliate / database / social marketing\nCoordinate and build relationships with affiliate partners, portals and websites to gain exposure / visibility\nPrepare monthly performance reports\n\n\u00a0Job Requirements\u00a0\n\nBachelor\u2019s Degree holder or equivalent in e-commerce, Marketing, IT or related discipline\nMinimum 2 years of experience in e-commerce business.\nKnowledge in Google Analytics, Google Merchant Center and Magento system would be an advantage\nIT or Fashion Company background is a plus.\nBe familiar with webpage skills like HTML, CSS and Photoshop\nWell organized, self-motivated and multi-tasking mindset\nStrong verbal and written English, Cantonese and Mandarin is a plus\nImmediate available is highly preferred", "employment_types": ["Full Time"], "selling_points": [], "locations": ["Tsim Sha Tsui"], "categories": ["E-commerce", "Marketing - Brand / Product Management"], "post_time": "2022-01-17T07:15:56Z", "salary": {"currency": null, "max": null, "min": null, "period": "monthly", "term": null}, "salary_visible": false, "title_keywords": ["executive"], "responsibilities": ["seo", "product listing", "uat", "performance reports", "conduct market research", "coordinate with", "website", "coordinate", "database", "contents", "editing", "develop creative ideas"], "requirements": {"degrees": ["bachelor", "degree holder"], "majors": ["marketing", "it", "e-commerce"], "languages": ["cantonese", "english", "mandarin"], "language_level": [], "hard_skills": ["google analytics", "plus", "e-commerce", "html", "css", "photoshop"], "soft_skills": ["self-motivated", "well organized", "multi-tasking"], "languages_combined": [{"language": "cantonese", "language_level": []}, {"language": "english", "language_level": []}, {"language": "mandarin", "language_level": []}]}, "experience_required": {"duration": ["minimum 2 years"], "field": ["business", "e-commerce"]}}, {"job_id": "100003009050326", "location_code": "hk", "company": "iGoodies Holdings Company Limited", "job_title": "E-commerce & Social Media Officer", "description": "Job Highlights\u00a0\n\nSolid exp in e-Commerce & Social Media 2-3 years\nWork independently for operating an online shop\nKnowledge use of web page, photoshop & AI design marketing materials\n\nJob Description\n\nA newly set up on-line shop is looking for a competent, reliable and agile candidate to fill up a position of E-Commence Officer to manage and boost the sales of our \u00a0e-Commerce platforms including but not limited to our online shops, to design and prepare marketing materials for both the online shops and showroom.\n\nDuties and Responsibilities\n\nFully responsible to operate this\u00a0online shop and showroom independently;\nResponsibilities including but not limited to online sales, marketing and daily\u00a0Operation of this online shop;\nPerform & manage operation of this online shop and on different selling channels and\u00a0 E-Commerce portals;\u00a0\nManage daily operations of online shop including generate & update website content (product listing, data entry, promotions, etc);\nEffective use of SEO, social media and KOLs to promote our products, e.g. through Facebook, Instagram, Google AD, WeChat group and \u5c0f\u7d05\u66f8 etc;\nKnowledge of video shooting, editing and daily video production;\nAnalyze and monitor online shop statistics and daily sales data to optimize\u00a0channel traffic performance and sales;\u00a0\nModify weekly product arrangements and make suggestions to change online shop layouts;\u00a0\nCreate & implement tactical offers to support specific products and target specific market;\nOther ad-hoc assignments.\n\nRequirements\n\nDegree in Journalism & Communication\u00a0or related discipline;\n2+ year relevant experience in E-commerce platform related, (fresh graduated will be considered);\nPossess well-developed design skills and marketing knowledge \u2013 capable to use photoshops, AI for design and preparing marketing materials;\nGood knowledge of SEO, SEM, Goggle analytics and adwords;\nExperience with logistic arrangement and warehouse management is advantage;\nProficient in MS Office (MS Word, Excel, Powerpoint, Outlook);\nCapable to work independently;\nGood command of written and spoken English and Chinese (include Mandarin).\n\nAvailability commencement :\n\nAround February, 2022 (after CNY holiday)\n\nWorking days :\n\n5 days per week\n\nTue\u2013Sat (09:30~18:30); Sun & Mon Rest day", "employment_types": ["Full Time", "Permanent"], "selling_points": [], "locations": ["Kwun Tong"], "categories": ["Media & Advertising", "Photography / Video", "Marketing / Public Relations", "Digital Marketing", "E-commerce", "Marketing - Brand / Product Management"], "post_time": "2022-01-17T09:16:23Z", "salary": {"currency": null, "max": null, "min": null, "period": "monthly", "term": null}, "salary_visible": false, "title_keywords": ["officer"], "responsibilities": ["social media", "seo", "product listing", "boost the sales", "data entry", "video production", "data", "ad-hoc assignments", "daily operation", "e-commerce platforms", "design", "website", "monitor", "video shooting", "facebook", "editing", "manage daily operations", "prepare marketing materials"], "requirements": {"degrees": ["degree"], "majors": ["journalism"], "languages": ["english", "chinese", "mandarin"], "language_level": ["good command"], "hard_skills": ["excel", "seo", "ai", "e-commerce", "adwords", "ms word", "powerpoint", "outlook", "sem", "ms office"], "soft_skills": ["communication", "work independently", "capable"], "languages_combined": [{"language": "english", "language_level": ["good command"]}, {"language": "chinese", "language_level": ["good command"]}, {"language": "mandarin", "language_level": ["good command"]}]}, "experience_required": {"duration": ["2+ year"], "field": ["related", "warehouse management", "relevant experience", "e-commerce"]}}, {"job_id": "100003009051949", "location_code": "hk", "company": "OSIM (HK) Co. Limited", "job_title": "Digital Marketing Executive ( 5 Days Work)", "description": "Join Us and Start your eCommerce Journey\n\nAre you looking to be part of a fast growing eCommerce business focused on bringing world class customer experiences to people across the globe? Join our energetic team as we grow our ideas into reality. We are looking for talent to help continue expand our beauty business, driving brand awareness to interested people.\n\nKey Job Responsibilities:\u00a0\u00a0\n\n\nResponsible for developing strategic influencer marketing strategies to enhance brand awareness\nResponsible for identifying and recruiting new potential KOLs and influencers that align with our company goals and values\nDevelop long-term relationship with KOLs and influencers\nMonitor traffic and marketing KPI as well as ensuring ROAS from KOL marketing, in close collaboration with Business team\nConduct regular ad hoc market search and analysis to keep up with latest market trend and competitor activities in influencer marketing\nPerform other duties as assigned by Management\n\n\u00a0Desired Skills and Experience:\u00a0\u00a0\n\nDegree holder or above in Marketing/ Business/ eCommerce or related disciplines\nMinimum 2-3 years or above working experience in eCommerce, preferably in beauty and fast-fashion industry\nStrong interest in Korean and Asian branded beauty products\nSolid experience in online digital marketing, preferably in social media, influencer marketing and affiliate marketing\nStrong analytical skills to drive marketing results, transforming data to actionable insight and recommendations\nWell-organized, detailed minded and able to manage multiple tasks\nAble to work independently and under pressure, as well as cooperate well with team and stakeholders to achieve company goals\nExcellent command of written and spoken English\nWe offer friendly team environment, good career prospect, also attractive remuneration package, together with other benefits like five-day work week, flexible working hour, double pay, medical and dental insurance. Interested parties please send full resume with available date, present and expected salary by clicking \u201cApply Now\u201d for an interview.\u00a0\n\n\nAll personal data collected will be used for recruitment purpose only.", "employment_types": ["Full Time", "Permanent"], "selling_points": [], "locations": ["Shatin Area"], "categories": ["Marketing / Public Relations", "Marketing - Direct Marketing", "Others", "E-commerce", "Marketing - Brand / Product Management"], "post_time": "2022-01-17T01:36:24Z", "salary": {"currency": null, "max": null, "min": null, "period": "monthly", "term": null}, "salary_visible": false, "title_keywords": ["digital marketing executive"], "responsibilities": ["social media", "perform other duties", "management", "marketing strategies", "ideas", "ad hoc", "data", "analysis", "monitor", "developing", "develop", "digital marketing", "insurance"], "requirements": {"degrees": ["degree holder"], "majors": ["business", "related disciplines", "ecommerce", "marketing"], "languages": ["english", "korean"], "language_level": ["excellent"], "hard_skills": ["analysis", "analytical skills"], "soft_skills": ["flexible", "work independently", "under pressure", "focused", "responsible", "multiple tasks", "well-organized", "analytical skills", "friendly", "energetic", "detailed"], "languages_combined": [{"language": "english", "language_level": ["excellent"]}, {"language": "korean", "language_level": []}]}, "experience_required": {"duration": ["minimum 2-3 years"], "field": ["ecommerce", "social media", "business", "digital marketing", "beauty", "marketing", "team"]}}, {"job_id": "100003009051841", "location_code": "hk", "company": "Stylevana", "job_title": "Digital Marketing Executive (Influencer Marketing) \u2013 Fashion & Beauty", "description": "Accountabilities \u2013 Key Result Areas\n\nHandle and manage the daily operations of the company\u2019s E-Commerce platform including but not limited to preparing eDM, content management, product listing, pricing, promotion, inventory update, customer service and order related issues\nDrive sales, define and implement online sales strategy and traffic optimization\nWork closely with various internal and external parties, including agency, marketing, graphic designers, system development team etc\nLiaise with internal and external parties for regular promotions\n\nExperience / Qualification Requirements\n\nDegree in Marketing or related disciplines\n2 years or above relevant experience in E-Commerce\nMicrosoft Office, Good knowledge of website analytics tools, e.g. Google Analytics\nGood command of both spoken and written Cantonese and English\nAbility to work in a fast paced environment, multi task and works well under pressure\nYou may visit www.gcr.com.hk for our company details", "employment_types": ["Full Time", "Permanent"], "selling_points": ["eCommerce, preferably in beauty and fast-fashion", "Experience in influencer marketing", "5-day work, Flex working hour, friendly team"], "locations": ["Kwai Hing"], "categories": ["Media & Advertising", "Editorial / Journalism", "Marketing / Public Relations", "Digital Marketing", "E-commerce", "Marketing - Brand / Product Management"], "post_time": "2022-01-17T01:20:53Z", "salary": {"currency": null, "max": null, "min": null, "period": "monthly", "term": null}, "salary_visible": false, "title_keywords": ["digital marketing executive"], "responsibilities": ["analytics tools", "management", "product listing", "edm", "inventory", "internal and external parties", "website", "daily operations", "customer service", "liaise with", "drive sales", "e-commerce platform"], "requirements": {"degrees": ["degree"], "majors": ["related disciplines", "marketing"], "languages": ["cantonese", "english"], "language_level": ["good command"], "hard_skills": ["microsoft office", "analytics tools", "google analytics", "e-commerce"], "soft_skills": ["work in a fast paced environment", "customer service", "under pressure"], "languages_combined": [{"language": "cantonese", "language_level": ["good command"]}, {"language": "english", "language_level": ["good command"]}]}, "experience_required": {"duration": ["2 years"], "field": ["relevant experience", "e-commerce"]}}, {"job_id": "100003009052852", "location_code": "hk", "company": "Global Technology Integrator Ltd", "job_title": "E-commerce Executive", "description": "Responsibilities:\u00a0\n\nInteract with customers and address their needs on digital platform in a professional manner\nIntroduce brands and products to customers as well as provide high quality customer services\nReview\u00a0and identify customer journey and formulate strategy to uplift customer experience\nDevelop FAQ, product sales talk and sales tools to drive sales conversions and meet the KPIs defined by the company\nConduct market research on latest trend of e-Commerce platforms and provide recommendations\nWork closely with internal teams including CRM, Marketing, Sales and Aftersales\nPerform other ad hoc duties as assigned\n\nTogether with integrity and passion, our ideal staff should meet the following requirements:\n\nDiploma holder or above in Business / Hospitality related disciplines\nAt least 3 years of working experience, preferably in the service industry\nProfessional negotiation skills, problem solving and complaint handling skills\nPassionate in automotive industry with appetite to drive innovative ideas and changes in matrix environment\nCustomer oriented, cheerful, self-motivated and outgoing personality\nExcellent communication and interpersonal skills, independent and able to work under pressure\nGood command of spoken and written English, Mandarin and Cantonese\nProficient in MS Office and Chinese word processing\n\n\nInterested parties, please send your application with detailed resume stating expected salary and date of availability by clicking \"APPLY NOW'.\n\nAll information will be used solely for recruitment purpose and will be destroyed when the recruitment process is finished.", "employment_types": ["Full Time"], "selling_points": ["Degree in Marketing or related disciplines", "2 years E-commerce experience", "5 days 9:00-5:30"], "locations": ["Ngau Tau Kok"], "categories": ["Marketing / Public Relations", "Digital Marketing", "E-commerce", "Business Development", "Marketing - Brand / Product Management"], "post_time": "2022-01-17T04:16:51Z", "salary": {"currency": null, "max": null, "min": null, "period": "monthly", "term": null}, "salary_visible": false, "title_keywords": ["executive"], "responsibilities": ["ad hoc duties", "ideas", "conduct market research", "review", "quality", "professional manner", "digital platform", "customer services", "develop", "e-commerce platforms", "teams", "communication", "provide recommendations", "kpis", "drive sales", "work under pressure"], "requirements": {"degrees": ["diploma holder"], "majors": ["related disciplines", "hospitality", "business"], "languages": ["cantonese", "english", "chinese", "mandarin"], "language_level": ["good command", "proficient"], "hard_skills": ["problem solving", "chinese word processing", "ms office", "e-commerce"], "soft_skills": ["passionate", "outgoing personality", "self-motivated", "cheerful", "independent", "work under pressure", "integrity", "problem solving", "negotiation skills", "communication and interpersonal skills", "innovative", "ideal"], "languages_combined": [{"language": "cantonese", "language_level": ["good command"]}, {"language": "english", "language_level": ["good command"]}, {"language": "chinese", "language_level": ["proficient"]}, {"language": "mandarin", "language_level": ["good command"]}]}, "experience_required": {"duration": ["at least 3 years"], "field": ["service industry"]}}, {"job_id": "100003009055056", "location_code": "hk", "company": "Kam Lung Motor Group Limited", "job_title": "Customer Digital Experience Specialist", "description": "Our Client\n\nOur client, an movie distributor and animation agent in Asia, who is looking for a Marketing Executive and a\u00a0 Licensing Officer to join the expanding team in Hong Kong.\n\nMarketing Executive\u00a0\n\nJob Responsibilities\n\nAssist in designing, planning, organizing and participating in marketing activities\nManage websites and IG and Facebook page\nHandle inquiry regarding our brands and update relevant materials on a regular basis\nProvide assistant in expanding licensing portfolio, source and negotiate with potential new licensees (Local & Asia Markets)\n\nJob Requirements\n\nDiploma or above\u00a0\n1 years\u2019 of\u00a0 related work experience,\u00a0\u00a0experience in\u00a0 Agency/Media/Animation/Entertainment industry is definitely an advantage\nWell organized and attention to details\nGood command of both spoken and written English and Chinese\nExcellent interpersonal and communication skills\nGood team spirit\n\n\n** Candidate with LESS experience will be considered as Marketing Assistant\n\n\n\nLicensing Officer\u00a0\n\nJob Responsibilities\n\nWork with licensing teammate for animation IP distribution\nDevelop and explore new customers and expand animation licensing business in Asia\nResponsible for market research of animation industry and animation IP\u00a0\nAssist in the preparation of regular reports\nProvide general support to the team\nResponsible for consolidation of license agreements.\nTravel to Asia Market is required\n\nJob Requirements\n\nDiploma or above, preferably in Media, Communications or related disciplines\n1 year relevant experience, prior experience in TV/Media/Animation industry is preferred\nAble to work independently and under pressure with tight schedule\nFamiliar with MS Word, Excel and PowerPoint\nGood command in both written and spoken of English and Mandarin\u00a0\n\n\n\nInterested applicants, please send your detailed resume quoting position title, reference number, current and expected salary.\n\nPersonal data provided by job applicants will be used\u00a0strictly in accordance with the employer's personal data policies and for recruitment purposes only.", "employment_types": ["Full Time", "Permanent"], "selling_points": ["Leading Automotive Group", "Handle daily operation of Digital platform", "Excellent customer service"], "locations": ["Tsuen Wan Area"], "categories": ["Sales, CS & Business Devpt", "Customer Service - Supervisor / Officer", "E-commerce", "Business Development", "Marketing - Brand / Product Management"], "post_time": "2022-01-18T01:03:24Z", "salary": {"currency": null, "max": null, "min": null, "period": "monthly", "term": null}, "salary_visible": false, "title_keywords": ["specialist"], "responsibilities": ["facebook", "planning", "designing"], "requirements": {"degrees": ["diploma or above"], "majors": ["related disciplines", "communications"], "languages": ["english", "chinese", "mandarin"], "language_level": ["good command"], "hard_skills": ["powerpoint", "ip", "excel", "ms word"], "soft_skills": ["communication skills", "work independently", "team spirit", "under pressure", "responsible", "well organized", "attention to details", "interpersonal", "detailed"], "languages_combined": [{"language": "english", "language_level": ["good command", "good command"]}, {"language": "chinese", "language_level": ["good command"]}, {"language": "mandarin", "language_level": ["good command"]}]}, "experience_required": {"duration": ["1 years", "1 year"], "field": ["related", "agency", "marketing", "relevant experience", "media"]}}, {"job_id": "100003009054868", "location_code": "hk", "company": "JPC Texson Limited", "job_title": "eCommerce Manager (30K-40K) - FMCG/health supplement brand (Kwun Tong/5 days work)", "description": "\n\n\nTHE COMPANY :\n\nHealth supplement / FMCG brand owner target China market like Taobao, JD, Tmall....etc\nWe are looking for\u00a0 E-COMMERCE MANAGER - with details as follows :\n\nTHE JOB :\n\nJob summary : build and manage this new e-Commerce business of a US health supplement brand target China market\nAll round operate this e-Commerce business including but not limited to sales, customer service, branding, marketing, daily operation (monitor China e-Commerce agency)\nOversee e-commerce platforms to achieve sales goals, raise brand awareness and ensure high standard of customer service.\nLead and collaborate with different stakeholders, including internal teammates and external vendors for various e-commerce projects\nManage day-to-day operation and update content materials of e-commerce platforms (such as online marketing campaigns, new product launch and demonstrations, product catalogue, price change and other sales and marketing events).\nMonitor and analyze online sales performance, traffic, user behavior, conversion funnels and goals by using different analytic tools, and provide suggestion to key stakeholders.\nWork independently in the early stage, will develop a small e-commerce team in later stage\nReport to MD directly\nDegree holder\nSolid working experience in e-commerce for China market\nExperience in health supplements or FMCG brands is a plus\nExperience in China e-Commerce market like Tmall, JD, Taobao is a big plus\nAble to work independently for all round operating this e-Commerce business including both sales, digital marketing and operation management\n5 days work\nTO APPLY for this job or similar jobs :\n\n\u00a0\nFor secure and confidential job application, please click the below link to get our email address.\n\u00a0\nhttp://jpc.hk/confidential_apply.htm\n\u00a0\n\u00a0\nWe provide free job hunting services to job seekers.\n\u00a0\nTo speed up our process, please do NOT send us download links.\n\u00a0\nPersonal data provided by job applicants will be used for recruitment purpose only.\n\u00a0\nYour privacy is guaranteed. We will never give out, lease, or sell your personal information.\n\u00a0\nJPC Recruiting Services was established in 1990.\n\u00a0\nhttp://www.facebook.com/pages/JPC-Texson-Ltd/500356593325952\n\n", "employment_types": ["Full Time", "Permanent"], "selling_points": ["Solid e-commerce exp for China market", "Exp in JD, Tmall, Taobao.... is a plus", "Exp in health supplement or FMCG brands a plus"], "locations": ["Kwun Tong Area"], "categories": ["Marketing / Public Relations", "Digital Marketing", "E-commerce", "Business Development", "Marketing - Brand / Product Management"], "post_time": "2022-01-17T12:12:57Z", "salary": {"currency": null, "max": null, "min": null, "period": "monthly", "term": null}, "salary_visible": false, "title_keywords": ["manager"], "responsibilities": ["collaborate with", "marketing events", "management", "raise brand awareness", "sales performance", "monitor", "daily operation", "e-commerce platforms", "develop", "customer service", "digital marketing", "marketing campaigns", "update content materials", "catalogue", "day-to-day operation", "report"], "requirements": {"degrees": ["degree holder"], "majors": [], "languages": [], "language_level": [], "hard_skills": ["small", "plus", "e-commerce"], "soft_skills": ["work independently", "customer service"], "languages_combined": []}, "experience_required": {"duration": [], "field": ["fmcg", "e-commerce"]}}, {"job_id": "100003009054239", "location_code": "hk", "company": "PERSOLKELLY Hong Kong Limited", "job_title": "Digital Marketing Executive (E-commerce) (Renewable Contract)", "description": "Our a\u00a0Chinese\u00a0multinational\u00a0e-commerce, retail, Internet, AI and technology, is seeking a Digital Marketing Executive to support their operation.\n\nResponsibilities\n\nPlan and execute B2B sales & marketing activities\nConduct data analysis to identify business opportunities; provide actionable insights;\nPlan and execute digital marketing strategies to promote the company\u2019s products & content; Perform in-depth analysis of the campaigns to constantly improve the ad performance;\nInitiate, plan and implement online and offline marketing programs to generate sales leads, drive the performance of campaigns, and to enhance brand awareness;\nOptimize content for the website and social networking channels such as Facebook, WeChat, Youtube etc. Support any ad hoc project assigned.\nRequirements\u00a0\n\nDiploma or Degree Holder in Marketing, Communication or other related discipline\nMinimum 2 years\u2019 experience in Digital Marketing or E-Commerce industry will be an advantage\nProficiency in Google Ads, Facebook Ads Manager, Google Analytics or equivalent tools; Experiences in Digital Marketing Project Management such as website promotion, email advertisement, Facebook advertising is preferred\nBe an excellent team player, self-motivated, proactive, creative and detail-minded;\nWilling to take up challenges, independent, proactive and can work under pressure\nHave good command of both written & spoken English & Chinese; Good Chinese copywriting is a definite advantage\nTo apply for this position, please click on \u201cApply Now\u201d bottom.\u00a0 All applications will be treated in strict confidence, and used for recruitment purposes only in accordance with PERSOLKELLY Hong Kong Limited\u2019s Privacy Notice.\u00a0\u00a0", "employment_types": ["Full Time", "Contract"], "selling_points": ["Innovative Culture", "12 months renewable contract", "Genuine Development Opportunity"], "locations": ["Causeway Bay"], "categories": ["Marketing / Public Relations", "Digital Marketing", "E-commerce", "Marketing - Brand / Product Management"], "post_time": "2022-01-17T08:53:43Z", "salary": {"currency": null, "max": null, "min": null, "period": "monthly", "term": null}, "salary_visible": false, "title_keywords": ["digital marketing executive"], "responsibilities": ["digital marketing strategies", "identify business opportunities", "ad hoc", "analysis", "website", "data analysis", "generate sales leads", "plan", "sales & marketing activities", "facebook"], "requirements": {"degrees": ["diploma", "degree holder"], "majors": ["marketing"], "languages": ["english", "chinese"], "language_level": ["advantage", "good command", "good"], "hard_skills": ["facebook", "project management", "google analytics", "e-commerce"], "soft_skills": ["detail-minded", "self-motivated", "confidence", "independent", "creative", "communication", "project management", "team player", "proactive", "work under pressure"], "languages_combined": [{"language": "english", "language_level": ["good command", "good"]}, {"language": "chinese", "language_level": ["advantage", "good command", "good", "good"]}]}, "experience_required": {"duration": ["minimum 2 years"], "field": ["advertising", "e-commerce", "project management", "digital marketing", "advertisement"]}}, {"job_id": "100003009051666", "location_code": "hk", "company": "Genfortune Pharmaceuticals Limited", "job_title": "Digital Marketing Executive (5 days)", "description": "Requirements:\n\nDiploma / Associate Degree/ Degree in IT / Web / Graphic / Multimedia Design or related disciplines, better with e-commerce knowledge.\nHands-on experience in Adobe AI and Photoshop proficiently.\nFamiliar with social platforms like: Facebook, Instagram, Wechat and TikTok etc. with strategical mindset.\n\nResponsibilities:\n\nPlanning, designing and executing marketing strategies and create product catalogs.\nResponsible for social platform content (copywriting, photos and videos) via Facebook, Instagram, Wechat and TikTok etc.\nGood at data collection, self-solving ability, able to w\nWork independently.\nExperience in editing videos, familiar with social media advertising and operation is a plus.\u00a0\n\nWe offered benefits to staff:\n\nMedical Insurance\nAnnual Leave\n5-days work\nBank holidays\nDouble Pay\nPerformance bonus\nStaff discount\u00a0\n\nInterested parties please send us your full resume, expected salary and applied position to HR Dept. through APPLY NOW\u00a0\n\nAll information collected is for recruitment purpose only.", "employment_types": ["Full Time", "Permanent"], "selling_points": ["E-commerce knowledge", "Familiar with social platforms", "Staff discount/Medical Insurance/Performance bonus"], "locations": ["Quarry Bay"], "categories": ["Marketing / Public Relations", "Marketing - Brand / Product Management", "Marketing - Direct Marketing", "E-commerce", "Marketing - Brand / Product Management"], "post_time": "2022-01-16T21:50:37Z", "salary": {"currency": null, "max": null, "min": null, "period": "monthly", "term": null}, "salary_visible": false, "title_keywords": ["digital marketing executive"], "responsibilities": ["social media", "marketing strategies", "advertising", "executing", "data collection", "designing", "facebook", "editing", "planning"], "requirements": {"degrees": ["associate degree", "diploma", "degree"], "majors": ["multimedia design", "related disciplines", "it", "e-commerce"], "languages": [], "language_level": [], "hard_skills": ["web", "ai", "e-commerce", "wechat", "adobe", "multimedia", "facebook", "photoshop"], "soft_skills": ["hands-on"], "languages_combined": []}, "experience_required": {"duration": [], "field": []}}, {"job_id": "100003009052266", "location_code": "hk", "company": "6C Technology Limited", "job_title": "Sales & Marketing Officer", "description": "Responsibilities:\n\nManage daily operations of online shop including generate & update website content\u00a0including product information, promotion, events and etc.\nMaking promotion plan each month based on data analysis (Mainly E-Commerce and assistant for retail shop)\nTrack online sales progress, traffic and click-through rate etc and provide analysis for management review and strategic planning\nMonitor the functionality of the online shops and to assure the timely logistic operation and delivery arrangement.\nPrepare analysis report on sales performance, inventory control and e-Commerce operation efficiency.\nResponsible for online shop stock controlling.\nCreating eCommer banner and product information visual by own\nMaintaining direct online platform (specially HKTV Mall) and WTC eStore\nHandling official WeChat account for branding.\nRequirements:\n\nNot less than 2 year\u00a0experiences\u00a0in digital and eCommerce solution, preferably in FMCG and retail industries.\nGood Knowledge in\u00a0online shop and e-marketplaces operation\nProficient with MS Office; Knowledge of Photoshop/ Illustrator/ Google Analytics/ Internet Technology\nGood Project management skill and independent handle multi-tasks to hit tight deadlines\nProficiency in English and Cantonese\nImmediate available is preferred\nFamiliar with\u00a0popular\u00a0social media\u00a0platform including WeChat\nWe offer competitive remuneration and attractive compensation package to the right candidate.\u00a0\n\n", "employment_types": ["Full Time", "Part Time", "Permanent", "Temporary", "Contract", "Internship", "Freelance"], "selling_points": [], "locations": ["Tai Po Area"], "categories": ["Marketing / Public Relations", "Marketing - General / Support", "Sales, CS & Business Devpt", "Sales - Sales Management", "E-commerce", "Marketing - Brand / Product Management"], "post_time": "2022-01-17T02:36:38Z", "salary": {"currency": null, "max": null, "min": null, "period": "monthly", "term": null}, "salary_visible": false, "title_keywords": ["sales", "marketing officer"], "responsibilities": ["strategic planning", "maintaining", "analysis report", "sales performance", "analysis", "monitor", "website", "data analysis", "inventory control", "plan", "visual", "manage daily operations", "management review"], "requirements": {"degrees": [], "majors": [], "languages": ["cantonese", "english"], "language_level": ["proficiency"], "hard_skills": ["google analytics", "illustrator", "wechat", "project management", "ms office", "photoshop"], "soft_skills": ["independent", "multi-tasks", "project management skill"], "languages_combined": [{"language": "cantonese", "language_level": ["proficiency"]}, {"language": "english", "language_level": ["proficiency"]}]}, "experience_required": {"duration": ["2 year"], "field": ["ecommerce", "digital", "fmcg", "retail"]}}, {"job_id": "100003009046179", "location_code": "hk", "company": "Texpo International Limited", "job_title": "Social Media & Marketing Executive", "description": "Requirements\n\nHigher Diploma/Diploma in e-Commerce, Marketing or equivalent\n1-2 years experience in e-Commerce and online sales operation\nKnowledge of operating social media platforms e.g. Facebook, IG, website\nWell-versed in using MS Word, Excel, PowerPoint, Chinese WP\nSelf-motivated, energetic, flexible and sense of responsibilities\nGood command of English and fair in spoken Mandarin\nImmediate available is a definite advantage\n\nResponsibilities\n\nHandle the daily smooth operation of e-Commerce sales platforms\nUpdate content of online platforms such as new products posting and promotion\nLiaise with e-Commerce partners such as HKTV Mall, Shopify on sales operation\nPerform sales enquiries & logistics issues and ad hoc tasks as assigned\n\nWe offer attractive remuneration package and promising career prospect to the right candidates. Interested parties please send full resume with expected/last salary and date of available by clicking \u2018Apply Now\u2019", "employment_types": ["Full Time"], "selling_points": ["Marketing strategy", "Assist to track & record inventories", "High organization & project management skill"], "locations": ["Central"], "categories": ["Marketing / Public Relations", "Marketing - Brand / Product Management", "Marketing - General / Support", "E-commerce", "Marketing - Brand / Product Management"], "post_time": "2022-01-14T02:23:41Z", "salary": {"currency": null, "max": null, "min": null, "period": "monthly", "term": null}, "salary_visible": false, "title_keywords": ["marketing executive"], "responsibilities": ["liaise with", "ad hoc tasks", "logistics"], "requirements": {"degrees": ["diploma"], "majors": ["marketing", "e-commerce"], "languages": ["english", "chinese", "mandarin"], "language_level": ["good command"], "hard_skills": ["excel", "chinese wp", "e-commerce", "powerpoint", "facebook", "ms word"], "soft_skills": ["flexible", "self-motivated", "energetic", "sense of responsibilities"], "languages_combined": [{"language": "english", "language_level": ["good command"]}, {"language": "chinese", "language_level": []}, {"language": "mandarin", "language_level": ["good command"]}]}, "experience_required": {"duration": ["1-2 years"], "field": ["online sales", "operation", "e-commerce"]}}, {"job_id": "100003009051752", "location_code": "hk", "company": "Amorepacific Global Operations Limited", "job_title": "Ecommerce Officer (Retail Skincare)", "description": "Join us & Be eCommerce Innovators\nAre you looking to be part of revolutionizing online shopping behaviour and experience? We are a well-esteemed eCommerce company that operates multiple eCommerce websites internationally. We are now looking for potential talent to help us expand our new beauty and fashion business worldwide and to build brand awareness and sales revenue.\n\nKey Job Responsibilities:\u00a0\n\nResponsible for daily eCommerce operations include managing website, banner update, promotion rules update, website content update etc.\nResponsible for update reporting on weekly basis to monitor sales performance of marketing channels and program, including newsletter, affiliate marketing, CRM etc.\nEnsure website efficient operation and consumer experience on website content in good UX basis\nAssist other ad hoc projects and operations of website and other online activities in eCommerce backend system\nAssist in website enhancements and resolving any website issues on timely basis\nWork closely with different function units including eCommerce Business, Digital Marketing and Merchandizing to ensure smooth consumer experiences on website\nPerform other duties as assigned by Supervisor and Manager\u00a0\n\n\u00a0Desired Skills and Experience:\u00a0\n\nDiploma or above in Marketing/ Business/ eCommerce or related disciplines\nExperience in any eCommerce backend system is an advantage\nWell-organized, detailed minded and able to manage multiple tasks\nAble to work independently and under pressure, as well as cooperate well with team and stakeholders to achieve company goals\nExcellent command of written and spoken English, Cantonese\nFresh graduate is welcome\n\nWe offer a friendly team environment, good career prospect. We also offer attractive remuneration package including discretionary bonus incentive. We also offer other benefits such as five-day work week, flexible working hours, double pay, medical and dental insurance. Interested parties please send full resume with available date, present and expected salary to our email or clicking \u201cApply Now\u201d for an interview.\n\nAll personal data collected will be used for recruitment purpose only.\u00a0", "employment_types": ["Full Time", "Contract"], "selling_points": [], "locations": ["Causeway Bay"], "categories": ["Marketing / Public Relations", "Marketing - Brand / Product Management", "E-commerce", "Business Development", "Marketing - Brand / Product Management"], "post_time": "2022-01-17T00:24:47Z", "salary": {"currency": null, "max": null, "min": null, "period": "monthly", "term": null}, "salary_visible": false, "title_keywords": ["ecommerce officer"], "responsibilities": ["reporting", "perform other duties", "operations", "sales performance", "monitor", "website", "ad hoc projects", "operations of website", "digital marketing"], "requirements": {"degrees": ["fresh graduate", "diploma or above"], "majors": ["business", "related disciplines", "ecommerce", "marketing"], "languages": ["cantonese", "english"], "language_level": ["excellent"], "hard_skills": ["merchandizing"], "soft_skills": ["efficient", "work independently", "under pressure", "responsible", "multiple tasks", "timely", "well-organized", "smooth", "detailed"], "languages_combined": [{"language": "cantonese", "language_level": ["excellent"]}, {"language": "english", "language_level": ["excellent"]}]}, "experience_required": {"duration": [], "field": ["ecommerce", "operation", "digital marketing", "business"]}}, {"job_id": "100003009051844", "location_code": "hk", "company": "Stylevana", "job_title": "eCommerce Assistant / Executive - Fashion & Beauty", "description": "Responsibilities:\n\nResponsible for content management of the brand website and other e-commerce channels\nAssist the team to plan and execute online promotion campaigns\n\nManage social media channels in order to meet the targeted KPI\nPlan and monitor company\u2019s SEO and SEM management\n\nParticipate and communicate with headquarters in website enhancement\nAssist in performance analysis in all digital channels\nAssist in any ad hoc duties as requested\n\nRequirements:\n\nDegree holder in Marketing / Communications e-commerce or related disciplines\nWith 1 - 2 years of solid experience in online marketing\n\nExperience in Google analytics is an advantage\nProactive, results-oriented with a strong sense of responsibility\nFast-paced with excellent communication and interpersonal skills\nCreative and attention to details\nGood command of spoken and written English, Cantonese, and Mandarin\n\n\nInterested parties, please send your full resume with\u00a0current salary,\u00a0expected salary,\u00a0and\u00a0available date\u00a0either by direct application from JobsDB (Please quote the job title on the subject ) or by WhatsApp:69298297 or by post to Human Resources Department, Unit 8-14 & 22-28, 11/F, Topsail Plaza, 11 On Sum Street, Shek Mun.\n\"Personal data collected will be used for recruitment purposes only.\"", "employment_types": ["Full Time", "Permanent"], "selling_points": ["eCom - Asian Fashion & Beauty", "daily eCom operations & monitor mkting channels", "5-day work, Double Pay, friendly team"], "locations": ["Kwai Hing"], "categories": ["Marketing / Public Relations", "Digital Marketing", "E-commerce", "Business Development", "Marketing - Brand / Product Management"], "post_time": "2022-01-17T01:20:54Z", "salary": {"currency": null, "max": null, "min": null, "period": "monthly", "term": null}, "salary_visible": false, "title_keywords": ["executive", "assistant"], "responsibilities": ["communicate with", "social media", "management", "ad hoc duties", "seo", "analysis", "monitor", "website", "plan", "sem", "online promotion"], "requirements": {"degrees": ["degree holder"], "majors": ["related disciplines", "marketing", "communications", "e-commerce"], "languages": ["cantonese", "english", "mandarin"], "language_level": ["good command"], "hard_skills": ["google analytics", "e-commerce"], "soft_skills": ["creative", "sense of responsibility", "communication and interpersonal skills", "attention to details", "proactive"], "languages_combined": [{"language": "cantonese", "language_level": ["good command"]}, {"language": "english", "language_level": ["good command"]}, {"language": "mandarin", "language_level": ["good command"]}]}, "experience_required": {"duration": ["1 - 2 years"], "field": ["marketing"]}}, {"job_id": "100003009054417", "location_code": "hk", "company": "Chow Sang Sang Holdings International Limited", "job_title": "Senior Executive - Digital Marketing", "description": "Our client is\u00a0a e-commerce cooperation is seeking for a Merchant Marketing Specialist to support their daily operations.\n\nResponsibilities\n\n\nBuild the regional marketing how to engage merchant users to drive awareness that the company is now open for business\nDrive integrated marketing campaigns for focus categories with high impact outcomes, in alignment with the overall business strategy\nBe a strong strategic partner to key business stakeholders across regional marketing teams, country teams, category managers and sales teams\nWork closely with media and creative agencies for integrated marketing campaigns (both online and o\ufb04ine activities) and own the project from planning until execution\nMeasure the e\ufb00ectiveness of each communication touch point and work to improve awareness and engagement and at each step of the user journey\nManage multiple, competing priorities simultaneously and deliver results\nRequirements\n\nExperience in working for B2B companies, preferably for 3-5 years\nStrategic and problem solving skills\nExcellent English and Cantonese communication skills\nExcellent project management skills\nExcellent collaboration and stakeholder management skills\nSpecialize in engagements, social media marketing, content marketing, and paid partnerships\n\nTo apply for this position, please click on \u201cApply Now\u201d bottom.\u00a0 All applications will be treated in strict confidence, and used for recruitment purposes only in accordance with PERSOLKELLY Hong Kong Limited\u2019s Privacy Notice.\u00a0\u00a0", "employment_types": ["Full Time", "Permanent"], "selling_points": ["Plan&execute strategies across digital touchpoints", "Work with UX team on customer journey", "Min 5 years exp in digital project management"], "locations": ["Cheung Sha Wan"], "categories": ["Marketing / Public Relations", "Others", "Digital Marketing", "E-commerce", "Marketing - Brand / Product Management"], "post_time": "2022-01-17T09:27:05Z", "salary": {"currency": null, "max": null, "min": null, "period": "monthly", "term": null}, "salary_visible": false, "title_keywords": ["senior executive", "digital marketing"], "responsibilities": ["communication", "teams", "marketing campaigns", "planning"], "requirements": {"degrees": [], "majors": [], "languages": ["cantonese", "english"], "language_level": ["excellent"], "hard_skills": ["project management", "problem solving skills"], "soft_skills": ["communication skills", "problem solving skills", "confidence", "project management skills"], "languages_combined": [{"language": "cantonese", "language_level": ["excellent"]}, {"language": "english", "language_level": ["excellent"]}]}, "experience_required": {"duration": ["3-5 years"], "field": []}}, {"job_id": "100003009053977", "location_code": "hk", "company": "PERSOLKELLY Hong Kong Limited", "job_title": "Merchant Marketing Specialist (12 months contract) (E-commerce)", "description": "Responsibilities:\u00a0\u00a0\u00a0\u00a0\u00a0\u00a0\u00a0\u00a0\u00a0\u00a0\u00a0\u00a0\u00a0\u00a0\u00a0\n\nManage daily E-shop and online platform order arrangement.\nOur E-shop: www.Kormawo.com\nTo assist to formulate and execute e-commerce strategies, including digital marketing, advertising activities and promotion campaigns to drive the sales and revenue.\nExecute all social and online advertising campaigns and updates, including create appealing and well-structured digital content and feeds\nAssist in overseeing assigned event and communicate with internal departments and external parties for the operation execution\nSupport event planning and ensure successful delivery of all venue services on time with quality and customer satisfaction\nAssist in managing budget planning and monitor event timeline\nProvide support on event planning provisions and general administration support\nCoordinate with sourcing and other internal teams regarding product availability, pricing, and stock levels\nPrepare regular analysis & reports for management review\n\nRequirements:\u00a0\n\nDSE or above with diploma in Business, E-Commerce, Marketing, IT or related discipline\nMinimum 5 years of solid experience with proven record in e-Commerce and/or digital marketing\n\u00a0Experience in membership recruitment and event management an advantage\n\u00a0Experience in HKTV, Carosell, Google Analytics, Google Adv, SEO/ SEM, FB/ IG ad placement\n\u00a0Experience in skincare/beauty product is an advantage\n\u00a0Proficient with graphic design tools, Adobe Illustrator and Photoshop & all MS Office Usage (esp. excel, word and powerpoint)\n\nBenefits:\n\n\n5 days work week\nbanking holidays\n12 days annual leave\nmonthly commission\nmedical insurance\nstaff purchase discount\nbirthday gift\u00a0\nfridge benefits\u00a0\nInterested parties please send your full resume and expected salary to our mailbox by clicking \"Apply Now\" below", "employment_types": ["Full Time", "Contract"], "selling_points": ["5 days working", "Competitive Salary", "Innovative Culture"], "locations": ["Tai Koo"], "categories": ["E-commerce", "Business Development", "Marketing - Brand / Product Management"], "post_time": "2022-01-17T07:54:04Z", "salary": {"currency": null, "max": null, "min": null, "period": "monthly", "term": null}, "salary_visible": false, "title_keywords": ["marketing specialist"], "responsibilities": ["e-shop", "external parties", "quality", "promotion campaigns", "online advertising", "management review", "administration", "budget planning", "advertising", "monitor", "e-commerce strategies", "teams", "reports", "provide support", "coordinate with", "digital marketing", "communicate with", "analysis", "planning"], "requirements": {"degrees": ["diploma", "dse"], "majors": ["business", "marketing", "it", "e-commerce"], "languages": [], "language_level": [], "hard_skills": ["google analytics", "excel", "seo", "e-commerce", "word", "powerpoint", "adobe illustrator", "sem", "ms office", "photoshop"], "soft_skills": [], "languages_combined": []}, "experience_required": {"duration": ["minimum 5 years"], "field": ["management", "e-commerce", "recruitment", "digital marketing", "beauty"]}}, {"job_id": "100003008966987", "location_code": "hk", "company": "Hong Kong QingHe Management Service Limited", "job_title": "Assistant Marketing Manager (Event & eCommerce)", "description": "Job Duties:\n\nPerform clerical and administrative support\nHandle customs declaration procedures and price comparison of product\nOR\nPerform operational duties include product uploading and information checking\nPhoto retouching\nOther ad hoc assignments as required\n\nJob Requirements:\n\nHigher Diploma or above\nProficient in MS Office Application, especially Excel\nFamiliar with Photoshop skill is an advantage\nReasonable level of fluency in Chinese and English\nImmediate availability is preferred\n\nWorking pattern: 3-4 full days per week (Mon - Fri, 9 am - 6 pm)\n\nSalary: HK$55/hour\n\n\n\n\nInterested parties please click \"APPLY NOW\" and attach with your full resume and expected salary in the application\n\n(Personal data collected is for recruitment purpose only.)", "employment_types": ["Full Time", "Permanent"], "selling_points": ["Manage social media platform-Kormawo.com", "Experience in handle exhibition, events", "5 days work and monthly commission"], "locations": ["Tsuen Wan Area"], "categories": ["Design", "Multi-media", "E-commerce", "Business Development", "Marketing - Brand / Product Management"], "post_time": "2022-01-17T06:52:05Z", "salary": {"currency": null, "max": null, "min": null, "period": "monthly", "term": null}, "salary_visible": false, "title_keywords": ["assistant marketing manager"], "responsibilities": ["photo retouching", "customs declaration", "administrative support", "procedures", "checking", "ad hoc assignments", "operational duties"], "requirements": {"degrees": ["higher diploma or above"], "majors": [], "languages": ["english", "chinese"], "language_level": ["fluency"], "hard_skills": ["excel", "photoshop", "ms office"], "soft_skills": [], "languages_combined": [{"language": "english", "language_level": ["fluency"]}, {"language": "chinese", "language_level": ["fluency"]}]}, "experience_required": {"duration": [], "field": []}}, {"job_id": "100003009054352", "location_code": "hk", "company": "Strawberry Cosmetics (Services) Limited", "job_title": "Part Time Clerk", "description": "Responsibilities:\n\nFormulate marketing strategies and implement marketing plan to drive business and build corporate and brand image\nResponsible for translation and interpretation between Japanese, English and Chinese\nPlan, execute & evaluate the effectiveness of marketing campaigns that fully integrate above- and below-the-line activities and PR initiative\nSales presentation of marketing materials for various social media channels and other relevant media formats\nWork closely with internal departments and external agencies to ensure the smooth execution of marketing programs\n\nRequirements:\n\nDegree or or above in\u00a0 Japanese\u00a0translation related disciplines\nAt least 2 years marketing or translation & interpretation experience, relevant in beauty service or retail industry is definitely an advantage\nGood command of both spoken and written English, Chinese, Japanese.\u00a0 Business level in Japanese (JLPT N1 or above).\u00a0\nHighly committed and eager to drive forward initiatives and achieving results\nSelf-motivated, detail-oriented and ability to work under pressure\nGood team player with excellent communication and interpersonal skills\n\nBenefits:\n\n5-day work week(half day work on Saturday once per month)\nMarriage and Compassionate Leave\nFree hair cut & chemical service\nStaff discount\u00a0\u00a0", "employment_types": ["Part Time", "Temporary", "Contract"], "selling_points": [], "locations": ["Shau Kei Wan"], "categories": ["Others", "Student / Fresh Graduate / No Experience", "E-commerce", "Marketing - Brand / Product Management"], "post_time": "2022-01-17T09:14:51Z", "salary": {"currency": null, "max": null, "min": null, "period": "monthly", "term": null}, "salary_visible": false, "title_keywords": ["part time clerk"], "responsibilities": ["social media", "marketing strategies", "evaluate", "marketing plan", "plan", "marketing campaigns", "marketing materials"], "requirements": {"degrees": ["degree"], "majors": ["related disciplines"], "languages": ["japanese", "english", "chinese"], "language_level": ["good command"], "hard_skills": ["translation"], "soft_skills": ["self-motivated", "good team player", "detail-oriented", "committed", "communication and interpersonal skills", "work under pressure"], "languages_combined": [{"language": "japanese", "language_level": ["good command"]}, {"language": "english", "language_level": ["good command"]}, {"language": "chinese", "language_level": ["good command"]}]}, "experience_required": {"duration": ["at least 2 years"], "field": ["retail industry", "marketing", "beauty"]}}, {"job_id": "100003009053033", "location_code": "hk", "company": "PS Group International Ltd", "job_title": "Japanese Translator **URGENT**", "description": "Responsibilities:\n\nManage e-Business operations, including released new product, content management, pricing and digital marketing strategy\nCoordinate the development of promotion material and activities such as exhibition\nWork closely with team members to ensure the smooth daily business operation on procurement, order placement, fulfillment and shipping, pre-sale and post sales customer service work etc.\nReview competitors on regular basis to understand best practices\nHunt down prospects creatively\nHandle ad hoc tasks\u00a0\n\nRequirements:\n\nDegree in related discipline in Business, e-Commerce, Marketing, Communication, Journalism or other related disciplines\u00a0\nGood written and verbal communication skills in English, Cantonese, and Mandarin\nStrong presentation, communication and interpersonal skills.\u00a0\nWork experience in sales & marketing, preferrable related to equipment or\u00a0jewellery industry\u00a0\nFamiliar with WordPress (WooCommerce) or similar ecommerce platforms is an advantage\u00a0\nFamiliar with design software is an advantage", "employment_types": ["Full Time"], "selling_points": ["Hair/Beauty Group", "5 Day Week", "Stable Working Environment"], "locations": ["North Point"], "categories": ["Others", "Trading", "Professional Services", "Translation", "E-commerce", "Marketing - Brand / Product Management"], "post_time": "2022-01-17T05:16:00Z", "salary": {"currency": null, "max": null, "min": null, "period": "monthly", "term": null}, "salary_visible": false, "title_keywords": ["translator"], "responsibilities": ["business operation", "management", "shipping", "operations", "fulfillment", "review", "ad hoc tasks", "coordinate", "customer service", "digital marketing"], "requirements": {"degrees": ["degree"], "majors": ["e-commerce", "journalism", "related disciplines", "business", "marketing"], "languages": ["cantonese", "english", "mandarin"], "language_level": ["good"], "hard_skills": ["wordpress", "e-commerce"], "soft_skills": ["communication", "communication skills", "communication and interpersonal skills", "presentation"], "languages_combined": [{"language": "cantonese", "language_level": ["good"]}, {"language": "english", "language_level": ["good"]}, {"language": "mandarin", "language_level": ["good"]}]}, "experience_required": {"duration": [], "field": ["related", "marketing"]}}, {"job_id": "100003009051756", "location_code": "hk", "company": "E-Teklon Company Limited", "job_title": "Sales & Marketing Assistant", "description": "Job description -\n\nMarketing Responsibilities:\n\nCreating promotional information to drive business\nCoordinating multiple channels of marketing strategies\nManaging budgets for marketing campaigns\nTesting new marketing opportunities\nBuilding relationships with media outlets\nDirecting social media strategies\nEvaluating performances of marketing campaigns\nTroubleshooting marketing campaigns that are not performing well\nManaging employees and third-party vendors\nAddressing customer service problems\nComing up with new ways to promote new products\nAnalyzing customer feedback from social media platforms\nAnalyzing advertising returns\nAssist in the following accounting procedures\n\nBasic Sales handling\nWeekly budgeting\nPop-Up budgeting\nInventory & Sales\nAssist to track & record inventories and sale\nHandle of order shipping\nRequirements:\n\nBachelor degree/ Diploma in business/ marketing disciplines or equivalent (Fresh graduates are welcome to apply)\nSkill in Adobe Creative Cloud (e.g. Photoshop, Illustrator\u2026etc) is preferred\nThe sophisticated user of popular social media platforms (e.g. Facebook, Instagram, Linkedin) is preferred\nStrong communications skills and interpersonal skills\nLogical, self-motivated and diligent\nGood command of written and spoken English and Chinese is a must\nImmediate availability is preferred\nFull time - 9am to 6pm, Monday to Friday\nInterested parties please send full resume giving details of expected salaries and availability by clicking \"Apply Now\u201d\n\nPersonal data collected will be used for recruitment only.\n", "employment_types": ["Full Time"], "selling_points": ["Good skills in social media platforms", "Experience in Web sales and Marketing", "Team Player"], "locations": ["Kowloon Bay"], "categories": ["Marketing / Public Relations", "Marketing - General / Support", "E-commerce", "Marketing - Brand / Product Management", "Others"], "post_time": "2022-01-17T00:39:46Z", "salary": {"currency": null, "max": null, "min": null, "period": "monthly", "term": null}, "salary_visible": false, "title_keywords": ["marketing assistant", "sales"], "responsibilities": ["budgets", "shipping", "marketing strategies", "advertising", "budgeting", "inventory", "social media platforms", "procedures", "troubleshooting", "testing", "customer service", "marketing campaigns", "social media strategies"], "requirements": {"degrees": ["diploma", "degree", "bachelor"], "majors": ["business", "marketing"], "languages": ["english", "chinese"], "language_level": ["good command"], "hard_skills": ["facebook", "adobe", "illustrator", "photoshop"], "soft_skills": ["sophisticated", "self-motivated", "diligent", "interpersonal skills", "creative"], "languages_combined": [{"language": "english", "language_level": ["good command"]}, {"language": "chinese", "language_level": ["good command"]}]}, "experience_required": {"duration": [], "field": []}}, {"job_id": "100003009054686", "location_code": "hk", "company": "505 United Limited", "job_title": "Account Executive (E-commerce & Sports Project)", "description": "Daily posts for the social media (including photography, wordings, and interaction with our TA)\nHandling customer service\nProduct Upload on different platforms\nArranging shipment & packaging for web sales orders\nAssist in running all different platforms and adopted our brand smoothly into the market\nAssist in product sourcing\u00a0\nHave good computer knowledge, such as PowerPoint, Photoshop, etc.\nRequire to report to work after CNY\n\nData collected will be used for recruitment purposes only.", "employment_types": ["Full Time", "Permanent"], "selling_points": ["E-commerce project for Global famous fashion brand", "Sports Lovers are preferable", "Project,Event & PR work with famous football team"], "locations": ["Mong Kok"], "categories": ["Marketing / Public Relations", "Public Relations - Event Management", "Digital Marketing", "E-commerce", "Marketing - Brand / Product Management"], "post_time": "2022-01-17T10:33:42Z", "salary": {"currency": null, "max": null, "min": null, "period": "monthly", "term": null}, "salary_visible": false, "title_keywords": ["account executive"], "responsibilities": ["social media", "data", "customer service", "recruitment", "product upload", "report"], "requirements": {"degrees": [], "majors": [], "languages": [], "language_level": [], "hard_skills": ["web sales", "powerpoint", "photoshop"], "soft_skills": ["customer service"], "languages_combined": []}, "experience_required": {"duration": [], "field": []}}, {"job_id": "100003009054361", "location_code": "hk", "company": "eCargo Enterprise Limited", "job_title": "E-commerce Operations Assistant Manager / Manager", "description": "Job Responsibilities:\n-\u00a0 E-commerce platform daily operation and handling.\u00a0Write, edit and proof-read all copy for e-commerce platform, marketing communication material. Handle new product launch & other ad-hoc projects assignment;\u00a0\n-\u00a0 Sports project planning, coordinating, executing on various marketing campaigns, including events, video production, advertising, public relation and social media.\u00a0To develop and implement marketing activities & prepare presentation materials\n-\u00a0 Social media on\u00a0exploring, researching and creating shareable content in different formats e.g. articles, graphics, videos...etc in social media platforms. Monitor and analyse the performance of marketing campaigns and provide regular report\n-\u00a0 To forge positive relationship with clients.\u00a0To develop and implement growth opportunity in existing and new clients, strong customer development and negotiation skills\n\nRequirements:\n-\u00a0 Sports Lovers,\u00a0self-motivated, proactive and hands-on approach\n-\u00a0 Degree holder or above, proficiency in sports knowledge\n-\u00a0 2 years exp in in PR agency / event / account service experience.\u00a0 More experience will be considered as Senior Account Executive (\u00a0Fresh Graduates are welcome to apply )\n-\u00a0 Creative mindset and familiar with social media and experience in research / media / digital agency is an advantage\n-\u00a0 Attentive to details and able to\u00a0prioritise multiple assignments ; Able to work under pressure & towards deadline\n-\u00a0 A Team Player with\u00a0verbal and written\u00a0communications skills, work within a team and be able to communicate with staff at all levels\n-\u00a0 Proficiency in computer skills such as PowerPoint, Excel, Chinese Word Processing, Photoshop and AI.\u00a0 Photo and Video editing skill is a plus\n-\u00a0 Irregular shift will be required", "employment_types": ["Full Time", "Permanent"], "selling_points": ["Support sales and marketing when necessary", "With wine knowledge will be a plus", "Five-day Work Week, Double Pay, Birthday Leave"], "locations": ["Kwai Tsing Area"], "categories": ["Marketing / Public Relations", "Public Relations - Event Management", "Digital Marketing", "E-commerce", "Marketing - Brand / Product Management"], "post_time": "2022-01-17T09:16:31Z", "salary": {"currency": null, "max": null, "min": null, "period": "monthly", "term": null}, "salary_visible": false, "title_keywords": ["manager", "operations assistant"], "responsibilities": ["graphics", "social media", "project planning", "ad-hoc projects", "advertising", "video production", "social media platforms", "daily operation", "monitor", "develop", "communication", "executing", "marketing campaigns", "report", "e-commerce platform", "analyse"], "requirements": {"degrees": ["degree holder"], "majors": [], "languages": ["chinese"], "language_level": ["proficiency"], "hard_skills": ["excel", "plus", "chinese word processing", "ai", "powerpoint", "video editing", "computer skills", "photoshop"], "soft_skills": ["self-motivated", "attentive to details", "creative mindset", "prioritise", "hands-on", "team player", "proactive", "work under pressure"], "languages_combined": [{"language": "chinese", "language_level": ["proficiency"]}]}, "experience_required": {"duration": ["2 years"], "field": ["social media", "pr", "research", "agency", "digital", "media"]}}, {"job_id": "100003009051839", "location_code": "hk", "company": "Stylevana", "job_title": "Assistant Merchandiser \u2013 Beauty", "description": "Responsibilities:\n\nManage and handle wine merchant on-boarding formalities. Facilitate wine product selection for online sales\nManage and handle cross-border logistics flow & operations, online product listing, stock management in timely and accurate manner\nVendor management, as well as liaise and coordinate with internal stake-holder departments on day to day business operation\nResponsible for eCommerce operations including but not limited to product listing, contents preparation and promotion/event planning/executions\nResponsible for overall order flow management, including collecting wines and arranging cross-border delivery\nResponsible for performance reports and analysis to maximize ROI from various activities\nCollect market intelligence and analyze\nSupport sales and marketing when necessary\nPerform ad hoc assignments by management\nEducation and Experience required:\n\nHigher Diploma / Associate Degree in eCommerce or relevant disciplines\nWith hands-on experience in eCommerce operation will be a plus\nWith wine knowledge will be a plus\nEffective and creative problem solving and decision-making skills\nExcellent organizational and analytical skills\nIndependent, sell motivated, detail-oriented; ability of multitasking in fast-tracking project\nBenefits:\n\nDouble Pay\nFive-day Work Week\nBirthday Leave\nMedical Insurance\nFree Shuttle Bus\u00a0\n\nAttractive remuneration package and excellent career development opportunities will be offered to the successful candidate.\u00a0 For Interested parties, please apply with a detailed resume stating present and stating present and expected salary by clicking \"Apply Now\".\u00a0 You are welcome to visit our website at http://www.ecargo.com.\nPersonal data collected will be used for recruitment purposes only and be treated in strict confidence.\u00a0 We treat all applicants for employment in the same way, regardless of age, sex, marriage and civil partnership, race, disability, religion or belief.", "employment_types": ["Full Time", "Permanent"], "selling_points": ["eCom - Korean Beauty", "Exp in buying beauty products / shipment", "5-day work, Double Pay, flexible working hour"], "locations": ["Kwai Hing"], "categories": ["Transportation & Logistics", "Fulfillment", "Merchandising & Purchasing", "Procurement / Purchasing / Sourcing", "E-commerce", "Marketing - Brand / Product Management"], "post_time": "2022-01-17T01:20:52Z", "salary": {"currency": null, "max": null, "min": null, "period": "monthly", "term": null}, "salary_visible": false, "title_keywords": ["assistant merchandiser"], "responsibilities": ["liaise", "management", "tracking", "stock management", "product listing", "performance reports", "operations", "analysis", "coordinate with", "logistics", "ad hoc assignments", "maximize roi", "contents", "day to day business operation", "planning"], "requirements": {"degrees": ["associate degree", "diploma"], "majors": ["ecommerce"], "languages": [], "language_level": [], "hard_skills": ["plus", "analysis", "vendor", "analytical skills", "problem solving"], "soft_skills": ["independent", "creative", "responsible", "organizational", "timely", "analytical skills", "problem solving", "detail-oriented", "hands-on", "motivated", "accurate"], "languages_combined": []}, "experience_required": {"duration": [], "field": ["ecommerce", "operation", "education"]}}, {"job_id": "100003009047546", "location_code": "hk", "company": "Motiva Consulting Limited", "job_title": "Digital Marketing Executive", "description": "Reporting to the Marketing & Business Development Manager, this role is based in Hong Kong and the candidate will be responsible for the business growth of ZALORA and its brand partners.\n\nThis is a unique, exciting opportunity to influence minds and make a positive difference to ZALORA, and to your career. \u00a0\n\nRESPONSIBILITIES\n\nBuild relationships with the assigned brands by being the go-to person when it comes to supporting their needs at ZALORA.\nMonitor and drive the growth of the brands: create and execute on strategic plans that delivers on business opportunities both for ZALORA and the Brand.\nLiaise with brands on campaign objectives and work with Marketing to incorporate Sellers promotions into ZALORA\u2019s marketing calendar.\nWork with the external brand partners & internal teams to continuously improve operational aspects of their business which directly impact customer experience.\nConstantly review brands catalog to ensure the content meets ZALORA guidelines and co-ordinate with internal teams to fix the issues for an improved customer experience.\nHandle various sets of daily, weekly and monthly business reports to improve visibility of brands performance to senior management.\nSupport the team on the management of exciting strategic cross-market campaigns for which you will plan, coordinate (internally and externally) and execute the marketing initiatives.\nUpdate the yearly trade marketing campaign calendar and you manage cross-market brand launches.\nCollaborate with all relevant Zalora stakeholders and ensure all work jointly to put in place the most impactful campaigns possible.\nFoster innovation to always bring the campaigns one step forward compared to the competition.\nParticipate to the evaluation and analysis of the campaigns and brand launches.\n\nREQUIRED SKILLS AND EXPERIENCE\n\nDigital Media/ Marketing & Account Servicing experience is a must.\nStrong communication, interpersonal and negotiations skills.\n1-2 years of working experience.\nAble to deliver results and meet targets with a strong will to get things done.\nWilling to work in a fast-paced and collaborative start-up environment.\nPrevious experience in organizing 360 marketing campaigns is a plus.\nGreat project management skills and can work under pressure.\nStrong analytical and reporting skills.\nWork easily and confidently in an international environment.\nFluent in English, Mandarin, Cantonese.\nStrong Microsoft Office skills (Excel, Word and PowerPoint).\n\nWHAT WE OFFER\n\nA versatile and responsible role, your contribution will have concrete and tangible results.\nInvolvement hands-on in the development of our platform.\nSignificant global career growth opportunities in a fast-growing business.\nFun and casual working atmosphere.\nOpen to new impulses and ideas.\nInternational mindset, close collaboration with management.", "employment_types": ["Full Time"], "selling_points": ["E-commerce", "Digital Marketing", "Product management"], "locations": ["Tsuen Wan Area"], "categories": ["Media & Advertising", "Media Buying", "Marketing / Public Relations", "Digital Marketing", "E-commerce", "Marketing - Brand / Product Management"], "post_time": "2022-01-14T03:25:44Z", "salary": {"currency": null, "max": null, "min": null, "period": "monthly", "term": null}, "salary_visible": false, "title_keywords": ["digital marketing executive"], "responsibilities": ["collaborate with", "co-ordinate with", "communication", "plan", "evaluation", "liaise with", "senior management", "work under pressure", "monitor", "teams", "reports", "marketing campaigns", "reporting", "management", "business opportunities", "review", "support the team", "trade marketing", "strategic plans", "guidelines", "analysis", "coordinate", "project management"], "requirements": {"degrees": [], "majors": [], "languages": ["cantonese", "english", "mandarin"], "language_level": ["fluent"], "hard_skills": ["excel", "plus", "microsoft office", "analysis", "word", "powerpoint", "make", "project management", "go"], "soft_skills": ["responsible", "project management skills", "collaborative", "unique", "communication", "interpersonal", "positive", "work under pressure"], "languages_combined": [{"language": "cantonese", "language_level": []}, {"language": "english", "language_level": ["fluent"]}, {"language": "mandarin", "language_level": ["fluent"]}]}, "experience_required": {"duration": ["1-2 years"], "field": ["brand", "account servicing", "digital media", "business", "marketing"]}}, {"job_id": "100003009048153", "location_code": "hk", "company": "Learning Time Limited", "job_title": "Customer Service Executive - Children's Products (5-day work week)", "description": "- Young and energetic team\n- Excellent office environment in Wanchai\n- Stable working hours\n\nResponsibilities\n- Prospect and qualify new sales leads\n- Handle all inbound and outbound communications with customers and prospects via different channels\u00a0\n- Nurture leads and follow-up to convert leads into sales\n- Use our CRM tools to develop and maintain pipelines and workflows\u00a0\n- Provide suggestions on how to optimise workflows related to sales and customer service\n- Develop strong, ongoing relationships with prospects, customers and ex-customers\n- Respond to customer inquiries and requests via telephone, email, and chat in a timely fashion, including during off work hours\n- Document all inquiries, requests, resolutions, and follow-up tasks\n- Perform research about the products to answer customer inquiries and requests\n- Grow existing customer accounts through exceptional customer service and effective sales techniques\n\nQualifications\u00a0\n- 2 years of customer service and/or sales and/or admin experience\n- Excellent interpersonal and communication skills\u00a0\n- Basic computer skills in various softwares and web-based applications\u00a0\n- Ability to prioritise tasks and manage time efficiently\u00a0\n- Highly self-motivated\u00a0\n- Fluent in both English and Chinese, written and spoken\n\nWhat you enjoy\n-5-day work week\u00a0\n\n-12 days annual leave\n-Start-up culture with room to learn and grow\n-Great platform to learn and develop new skills in an encouraging environment\n-Clinical and hospital coverage\n\nAdditional information:\u00a0\n- Full time position\n\nJob function: Administration, customer service, sales representative", "employment_types": ["Full Time"], "selling_points": ["startup culture with plenty of rooms to grow", "great platform to learn and develop new skills", "5 days work week"], "locations": ["Wan Chai Area"], "categories": ["Admin & HR", "Clerical / Admin Staff", "Sales, CS & Business Devpt", "Customer Service - Supervisor / Officer", "E-commerce", "Marketing - Brand / Product Management"], "post_time": "2022-01-14T05:24:26Z", "salary": {"currency": null, "max": null, "min": null, "period": "monthly", "term": null}, "salary_visible": false, "title_keywords": ["customer service executive"], "responsibilities": ["communications with", "customer inquiries", "develop", "communication", "maintain", "customer service", "administration"], "requirements": {"degrees": [], "majors": [], "languages": ["english", "chinese"], "language_level": ["fluent"], "hard_skills": ["pipelines", "computer skills", "web-based applications", "basic"], "soft_skills": ["communication skills", "self-motivated", "timely", "prioritise", "customer service", "stable", "energetic", "interpersonal"], "languages_combined": [{"language": "english", "language_level": ["fluent"]}, {"language": "chinese", "language_level": ["fluent"]}]}, "experience_required": {"duration": ["2 years"], "field": ["admin", "customer service"]}}, {"job_id": "100003009053200", "location_code": "hk", "company": "ADECCO", "job_title": "Ecommerce Manager", "description": "Join us & Be eCommerce Innovators\n\n\nAre you looking to be part of revolutionizing online shopping behaviour and experience? We are a well-esteemed eCommcere company that operates multiple eCommerce websites internationally. We are now looking for potential talent to help us expand our new business worldwide.\n\nKey Job Responsibilities:\u00a0\n\nResponsible for Korean office purchase order follow up\nPrepare PI and PO, follow up with payment and shipment arrangement\nConsolidate and follow up with Korea Merchandising Team on all orderings from Hong Kong Team\nConsolidation of all Korean purchased goods and prepare paperwork to facilitate the export of goods from Korea\nCommunicate and coordinate with internal or external logistic parties to ensure smooth export process\nPerform other administrative support to Merchandising Team\nOther ad-hoc duties as assigned\n\nDesired Skills and Experience:\u00a0\n\nDiploma of above\u00a0 \u00a0 \u00a0 \u00a0 \u00a0\nMinimum 1-2 years or above working experience in merchandising or logistic experience under trading environment or buying office\nIndependent, well-organized, detailed minded, and able to manage multiple tasks\nGood command of written and spoken English\nImmediate available is highly preferred\n\nWe offer friendly team environment, good career prospect, also attractive remuneration package including commission and discretionary bonus incentive, together with other benefits like five-day work week, flexible working hours, double pay, medical and dental insurance. Interested parties please send full resume with available date, present and expected salary by clicking \u201cApply Now\u201d for an interview.\n\nAll personal data collected will be used for recruitment purpose only.\u00a0", "employment_types": ["Full Time", "Permanent"], "selling_points": [], "locations": ["Others"], "categories": ["Sales, CS & Business Devpt", "Sales - Sales Management", "E-commerce", "Marketing - Brand / Product Management", "Product Management / Business Analyst"], "post_time": "2022-01-17T06:25:34Z", "salary": {"currency": null, "max": null, "min": null, "period": "monthly", "term": null}, "salary_visible": false, "title_keywords": ["manager"], "responsibilities": ["shipment arrangement", "administrative support", "merchandising", "coordinate with", "purchase", "payment", "ad-hoc duties", "insurance"], "requirements": {"degrees": ["diploma"], "majors": [], "languages": ["english", "korean"], "language_level": ["good command"], "hard_skills": [], "soft_skills": ["flexible", "independent", "responsible", "multiple tasks", "well-organized", "smooth", "friendly", "ad-hoc duties", "detailed"], "languages_combined": [{"language": "english", "language_level": ["good command"]}, {"language": "korean", "language_level": []}]}, "experience_required": {"duration": ["minimum 1-2 years"], "field": ["ecommerce", "merchandising", "trading"]}}, {"job_id": "100003009050419", "location_code": "hk", "company": "The Nuance Group (HK) Limited", "job_title": "Digital eCommerce Specialist, APAC", "description": "Responsibilities:\n\nResponsible for supporting all business activities of assigned brand with focus on ecommerce business.\nManage the daily operations of the website and e-commerce platform functions including but not limited to product listing & upload, promotion launch, campaign management, daily report, inventory planning & logistics, content preparation and after-sales service support.\nAnalyze the online sales performance and roll out effective digital marketing activities and promotion to reach sales target.\nDrive content creation including banners, copyrighting, layout design to promote brand on website and different social media platforms.\nResearch and identify new potential partnerships and e-commerce opportunities.\nCoordinate marketplace partnership and build relationship.\nPrepare sales, traffic, promotion reports and competitor analysis regularly.\nPerform ad-hoc duties as assigned.\n\nRequirements:\n\nDegree or above in E-commerce, marketing or related discipline.\n3-4 years' relevant experience preferably in retail/ fashion industry.\nProficient PC skills in MS Excel, Word, PowerPoint and Chinese work processing.\nKnowledge in design software such as AI, PS is preferred.\nFluent in spoken and written English and Mandarin.", "employment_types": ["Full Time", "Permanent"], "selling_points": [], "locations": ["Hung Hom"], "categories": ["Marketing / Public Relations", "Digital Marketing", "E-commerce", "Marketing - Brand / Product Management"], "post_time": "2022-01-14T10:22:19Z", "salary": {"currency": null, "max": null, "min": null, "period": "monthly", "term": null}, "salary_visible": false, "title_keywords": ["ecommerce specialist"], "responsibilities": ["layout design", "social media platforms", "website", "banners", "content preparation", "sales performance", "sales target", "prepare sales", "reports", "business activities", "inventory planning & logistics", "promotion launch", "daily operations", "digital marketing", "ad-hoc duties", "campaign management", "product listing & upload", "analysis", "coordinate", "after-sales service", "daily report", "e-commerce platform"], "requirements": {"degrees": ["degree or above"], "majors": ["marketing", "e-commerce"], "languages": ["english", "chinese", "mandarin"], "language_level": ["fluent", "proficient"], "hard_skills": ["e-commerce", "processing", "ai", "word", "powerpoint", "ms excel", "pc skills"], "soft_skills": [], "languages_combined": [{"language": "english", "language_level": ["fluent"]}, {"language": "chinese", "language_level": ["proficient"]}, {"language": "mandarin", "language_level": ["fluent"]}]}, "experience_required": {"duration": ["3-4 years"], "field": ["retail", "relevant experience"]}}, {"job_id": "100003009055523", "location_code": "hk", "company": "Classy Wheeler Limited", "job_title": "Marketing Executive / Licensing Officer (Entertainment Business / Media) - 2 Positions", "description": "Our Client\n\nOur client, an movie distributor and animation agent in Asia, who is looking for a Marketing Executive and a\u00a0 Licensing Officer to join the expanding team in Hong Kong.\n\nMarketing Executive\u00a0\n\nJob Responsibilities\n\nAssist in designing, planning, organizing and participating in marketing activities\nManage websites and IG and Facebook page\nHandle inquiry regarding our brands and update relevant materials on a regular basis\nProvide assistant in expanding licensing portfolio, source and negotiate with potential new licensees (Local & Asia Markets)\n\nJob Requirements\n\nDiploma or above\u00a0\n1 years\u2019 of\u00a0 related work experience,\u00a0\u00a0experience in\u00a0 Agency/Media/Animation/Entertainment industry is definitely an advantage\nWell organized and attention to details\nGood command of both spoken and written English and Chinese\nExcellent interpersonal and communication skills\nGood team spirit\n\n\n** Candidate with LESS experience will be considered as Marketing Assistant\n\n\n\nLicensing Officer\u00a0\n\nJob Responsibilities\n\nWork with licensing teammate for animation IP distribution\nDevelop and explore new customers and expand animation licensing business in Asia\nResponsible for market research of animation industry and animation IP\u00a0\nAssist in the preparation of regular reports\nProvide general support to the team\nResponsible for consolidation of license agreements.\nTravel to Asia Market is required\n\nJob Requirements\n\nDiploma or above, preferably in Media, Communications or related disciplines\n1 year relevant experience, prior experience in TV/Media/Animation industry is preferred\nAble to work independently and under pressure with tight schedule\nFamiliar with MS Word, Excel and PowerPoint\nGood command in both written and spoken of English and Mandarin\u00a0\n\n\n\nInterested applicants, please send your detailed resume quoting position title, reference number, current and expected salary.\n\nPersonal data provided by job applicants will be used\u00a0strictly in accordance with the employer's personal data policies and for recruitment purposes only.", "employment_types": ["Full Time", "Permanent"], "selling_points": ["Long term career growth", "A leader in Asian animation industry", "5 days work"], "locations": ["Central & Western Area"], "categories": ["Marketing / Public Relations", "Others", "Others", "Others", "E-commerce", "Marketing - Brand / Product Management"], "post_time": "2022-01-18T02:40:40Z", "salary": {"currency": null, "max": null, "min": null, "period": "monthly", "term": null}, "salary_visible": false, "title_keywords": ["officer", "marketing executive"], "responsibilities": ["facebook", "planning", "designing"], "requirements": {"degrees": ["diploma or above"], "majors": ["related disciplines", "communications"], "languages": ["english", "chinese", "mandarin"], "language_level": ["good command"], "hard_skills": ["powerpoint", "ip", "excel", "ms word"], "soft_skills": ["communication skills", "work independently", "team spirit", "under pressure", "responsible", "well organized", "attention to details", "interpersonal", "detailed"], "languages_combined": [{"language": "english", "language_level": ["good command", "good command"]}, {"language": "chinese", "language_level": ["good command"]}, {"language": "mandarin", "language_level": ["good command"]}]}, "experience_required": {"duration": ["1 years", "1 year"], "field": ["related", "agency", "marketing", "relevant experience", "media"]}}, {"job_id": "100003009055665", "location_code": "hk", "company": "BDO Financial Services Limited", "job_title": "Senior Manager, Marketing", "description": "Our client is engaged in the selling of wellness products and is looking for a seasoned Marketing professional to lead a team to drive the business forward\n\nKey Responsibilities\u00a0\n\nManage a team and to formulate marketing strategies to support the firm\u2019s future business growth\nDevelop marketing strategies to promote the firm\u2019s product and brand\nPrepare budgets and forecasts and assist in the development of new initiatives\nDrive monthly, quarterly, and annual promotion and campaign strategy\nSet project priorities, define and rollout market\u2019s marketing plans and provide strategic leadership\nCreation of compelling propositions that are segment and industry-relevant and highlight the company's points of differentiation\nIdentify market-specific growth opportunities and evaluate progress towards goals and timelines\nEnhance, monitor, and evaluate existing marketing initiatives and results\nPerform data analysis on market, competitors, and customer to establish marketing direction\nConduct review and evaluate marketing programs from time to time and make recommendations on program modifications, where necessary\n\n\u00a0Key Requirements:\u00a0\u00a0\n\nBachelor degree in business management, marketing or related disciplines\n\nSolid 8-12 years experience in marketing & communication with a multinational company\nFamiliar with MLM Marketing / Beauty/Health Care/Pharmaceutical Marketing\nProven track record of successfully developing and executing integrated marketing initiatives, particularly promotions/campaigns\nDemonstrates business plan development skills and experience including competitive analysis, SWAT analysis, value proposition, break-even analysis, forecasting, etc.\nStrong data analysis, reporting, research, and problem-solving skills\n\nInterested parties please send your application\u00a0with full career history, current and expected salary by\u00a0clicking\u00a0Apply Now\u00a0button below. Applications will be treated in strict confidence. Personal data collected will be used for recruitment purposes only.", "employment_types": ["Full Time", "Permanent"], "selling_points": ["Team Leadership", "A Highly Visible Role", "Stable Work Hours"], "locations": ["Not Specified"], "categories": ["Media & Advertising", "Others", "Marketing / Public Relations", "Marketing - Brand / Product Management", "E-commerce", "Marketing - Brand / Product Management"], "post_time": "2022-01-18T02:50:28Z", "salary": {"currency": null, "max": null, "min": null, "period": "monthly", "term": null}, "salary_visible": false, "title_keywords": ["senior manager"], "responsibilities": ["make recommendations", "budgets", "marketing strategies", "marketing plans", "review", "monitor", "develop", "evaluate", "data analysis"], "requirements": {"degrees": ["degree", "bachelor"], "majors": ["related disciplines", "business", "marketing"], "languages": [], "language_level": [], "hard_skills": ["business management", "problem-solving skills", "analysis"], "soft_skills": ["communication", "problem-solving skills"], "languages_combined": []}, "experience_required": {"duration": ["8-12 years"], "field": ["business", "development", "marketing", "multinational company"]}}, {"job_id": "100003009051598", "location_code": "hk", "company": "Zalora (Hong Kong) Limited", "job_title": "Brand Partnerships Executive", "description": "- Young and energetic team\n- Excellent office environment in Wanchai\n- Stable working hours\n\nResponsibilities\n- Prospect and qualify new sales leads\n- Handle all inbound and outbound communications with customers and prospects via different channels\u00a0\n- Nurture leads and follow-up to convert leads into sales\n- Use our CRM tools to develop and maintain pipelines and workflows\u00a0\n- Provide suggestions on how to optimise workflows related to sales and customer service\n- Develop strong, ongoing relationships with prospects, customers and ex-customers\n- Respond to customer inquiries and requests via telephone, email, and chat in a timely fashion, including during off work hours\n- Document all inquiries, requests, resolutions, and follow-up tasks\n- Perform research about the products to answer customer inquiries and requests\n- Grow existing customer accounts through exceptional customer service and effective sales techniques\n\nQualifications\u00a0\n- 2 years of customer service and/or sales and/or admin experience\n- Excellent interpersonal and communication skills\u00a0\n- Basic computer skills in various softwares and web-based applications\u00a0\n- Ability to prioritise tasks and manage time efficiently\u00a0\n- Highly self-motivated\u00a0\n- Fluent in both English and Chinese, written and spoken\n\nWhat you enjoy\n-5-day work week\u00a0\n\n-12 days annual leave\n-Start-up culture with room to learn and grow\n-Great platform to learn and develop new skills in an encouraging environment\n-Clinical and hospital coverage\n\nAdditional information:\u00a0\n- Full time position\n\nJob function: Administration, customer service, sales representative", "employment_types": ["Full Time", "Permanent"], "selling_points": [], "locations": ["Causeway Bay"], "categories": ["Sales, CS & Business Devpt", "Account Servicing", "E-commerce", "Business Development", "Marketing - Brand / Product Management"], "post_time": "2022-01-16T21:50:30Z", "salary": {"currency": null, "max": null, "min": null, "period": "monthly", "term": null}, "salary_visible": false, "title_keywords": ["executive"], "responsibilities": ["communications with", "customer inquiries", "develop", "communication", "maintain", "customer service", "administration"], "requirements": {"degrees": [], "majors": [], "languages": ["english", "chinese"], "language_level": ["fluent"], "hard_skills": ["pipelines", "computer skills", "web-based applications", "basic"], "soft_skills": ["communication skills", "self-motivated", "timely", "prioritise", "customer service", "stable", "energetic", "interpersonal"], "languages_combined": [{"language": "english", "language_level": ["fluent"]}, {"language": "chinese", "language_level": ["fluent"]}]}, "experience_required": {"duration": ["2 years"], "field": ["admin", "customer service"]}}, {"job_id": "100003009047466", "location_code": "hk", "company": "ASICS HongKong Limited", "job_title": "Sr. Marketing Executive, Onitsuka Tiger Hong Kong", "description": "Our client is an international FMCG Company, they are now looking for a high caliber to join their Ecommerce team in HK.\n\nJob Responsibilities\n\nResponsible for the sales performance, operations of Ecommerce platforms (Own website, marketplaces, mobile apps) across APAC markets\nWork with Marketing, Merchandising, Digital, Logistics, IT and Finance for the execution of e-commerce business launch\nOversee the operations, maintenance and performance of the Ecommerce platform effectiveness\nImplement growth strategy (SEO, SEA, CRM and content optimization) and commercial strategy in line with the marketing plan to optimize the sales potential\nUtilize web analytics tools to provide timely review of all promotional activities, including SEO, SEM, display advertising, eDM, paid social, affiliate\nInitiate and lead projects between different departments that aim to enhance online customer journey and drive business sales growth\u00a0\nIn charge of daily/ weekly/ monthly/ quarterly sales and profit reporting, as well as marketing KPI goals and generate actionable insights to Management\nFull respond to revamp the global ecommerce website with additional enhancement on UI/UX to drive website organic result\n\nJob Requirements\n\nBachelor Degree in E-commerce or related disciplines\nAt least 4 years Ecommerce experience in fashion and FMCG industries\nExposure in\u00a0international markets\u00a0and\u00a0mobile apps development\u00a0are highly preferable\nExcellent understanding of web design and web analysis\nDemonstrable track record of devising sales-enhancing strategies and project management skills\nGood in both spoken and written English and Chinese\n\nInterested parties, please\u00a0CLICK HERE\u00a0to apply the position via Adecco website with your CV, or if you would like to have a further discussion about this role, please contact Alex Tsoi at 852-28996161.", "employment_types": ["Full Time", "Permanent"], "selling_points": ["Marketing, Visual Merchandising, VM", "Trade Marketing, Design, e-commerce", "Fashion, Retail, Wholesales"], "locations": ["Kwun Tong"], "categories": ["Design", "Visual Merchandising", "Marketing / Public Relations", "Others", "E-commerce", "Marketing - Brand / Product Management"], "post_time": "2022-01-14T03:12:27Z", "salary": {"currency": null, "max": null, "min": null, "period": "monthly", "term": null}, "salary_visible": false, "title_keywords": ["marketing executive"], "responsibilities": ["analytics tools", "reporting", "management", "seo", "advertising", "maintenance", "edm", "revamp", "sales performance", "operations", "review", "merchandising", "website", "marketing plan", "logistics", "promotional activities", "sem", "ui"], "requirements": {"degrees": ["degree", "bachelor"], "majors": ["related disciplines", "e-commerce"], "languages": ["english", "chinese"], "language_level": ["good"], "hard_skills": ["web design", "web", "e-commerce", "analysis", "mobile", "project management"], "soft_skills": ["project management skills"], "languages_combined": [{"language": "english", "language_level": ["good"]}, {"language": "chinese", "language_level": ["good"]}]}, "experience_required": {"duration": ["at least 4 years"], "field": ["ecommerce", "fmcg"]}}, {"job_id": "100003009050914", "location_code": "hk", "company": "Besteam Personnel Consultancy Limited", "job_title": "Senior Manager, E-Commerce (Regional role)  - up to $70K", "description": "Reporting to Digital Manager, APAC, the position will support the formulation of eCommerce strategies for APAC region.\u00a0 He/she will be responsible for the execution of local digital marketing campaigns to generate traffic, the identification and coordination of local promotions, and the enrichment and optimization of local product descriptions in digital channels, to strategically grow online sales in a specific location.\n\nKey Accountabilities:\n\nSupport Digital Manager, APAC and Global teams to implement vision, roadmaps and program backlog of the local eCommerce strategy;\nStrategically grow eCommerce ahead of the market in specific location;\nIdentify and coordinate local promotions and launch of new products within the eCommerce area;\nTailor portfolio of opportunities in eCommerce to local market to make it a platform for growth \u2013 including through partnerships with brands and communication initiatives;\nWork with global Product Owners and Product Managers to implement the local digital strategy to improve traffic acquisition, sales and conversion of the eCommerce site (including SEO/SEM, A/B testing initiatives);\nOptimize end-to-end region-specific customer journeys by devising new solutions, services, products or propositions; and\nIdentify and implement new opportunities throughout the customer journey to deliver high performing, agile customer interactions and touchpoints.\nRequirements\n\nDegree in Business Management, Marketing, E-commerce or relevant disciplines;\n3-5 years of digital marketing / eCommerce experience; China exposure is a must;\nProven knowledge of standard concepts, practices, and procedures within the retail and/or travel industry (with a strong focus on eCommerce);\nStrong background in digital marketing principles such as funnel optimization UX, SEO & Landing Page optimization & Display expertise in customer journey management, digital and communications;\nExperience in working with UX/UI designers to define customer experiences;\nExperience in Adobe tools (e.g., Magento, marketing tools) and Google Analytics desirable;\nExperience in running A/B tests for campaigns and deriving customer insights a major plus;\nDemonstrable experience coordinating SEO/SEM, marketing database, email, social media and/or display advertising campaigns;\nDeep understanding in all the commercial levers to drive performance (range, price, experience, marketing);\nCommercial yet customer-first mindset with the ability to identify customer needs; and\nProficiency in both English and Chinese, especially Mandarin and written Chinese.\u00a0\nInterested parties, please send full CV with availability, current and expected salary to us by clicking below button \u201cApply Now\u201d.\n\n\n\nWe are an equal opportunity employer and welcome applications from all qualified candidates. Personal data collected will be treated in strict confidence and handled confidentially by authorised personnel for recruitment-related purposes only within Dufry Group of companies.", "employment_types": ["Full Time", "Permanent"], "selling_points": ["in-house e-commerce leading role", "able to handle a small team", "familiar with marketplace in HK & China or APAC"], "locations": ["Not Specified"], "categories": ["E-commerce", "Business Development", "Marketing - Brand / Product Management", "Others"], "post_time": "2022-01-15T03:51:16Z", "salary": {"currency": null, "max": null, "min": null, "period": "monthly", "term": null}, "salary_visible": false, "title_keywords": ["senior manager"], "responsibilities": ["reporting", "management", "product descriptions", "seo", "social media", "digital marketing campaigns", "teams", "procedures", "customer insights", "testing", "coordinate", "communication", "digital marketing", "coordination", "sem", "database", "advertising campaigns", "ui"], "requirements": {"degrees": ["degree"], "majors": ["business", "e-commerce", "marketing"], "languages": ["english", "chinese", "mandarin"], "language_level": ["proficiency"], "hard_skills": ["business management", "google analytics", "plus", "seo", "agile", "e-commerce", "customer journeys", "make", "adobe", "sem", "focus"], "soft_skills": ["agile", "responsible", "deep", "communication", "coordination", "focus"], "languages_combined": [{"language": "english", "language_level": ["proficiency"]}, {"language": "chinese", "language_level": ["proficiency"]}, {"language": "mandarin", "language_level": ["proficiency"]}]}, "experience_required": {"duration": ["3-5 years"], "field": ["ecommerce", "social media", "advertising", "commercial", "marketing", "digital marketing", "database"]}}, {"job_id": "100003009051597", "location_code": "hk", "company": "Zalora (Hong Kong) Limited", "job_title": "Associate Manager - Marketplace", "description": "\uff1cSCOPE OF POSITION\uff1e\nThe position aims to support the development and execution for press and communication strategies around brand initiatives, special projects, and trade marketing activities.\n\n\uff1cReport to\uff1e\nHead of Onitsuka Tiger Hong Kong\n\n\uff1cDUTIES AND RESPONSIBILITIES\uff1e\n\nCo-ordinate and prepare in-store/marketing materials to maximize retail presence e.g. POP, leaflets etc.\nResponsible for compiling reports of retail marketing programs to keep track on results and evaluate the effectiveness\nSupport the development and execution of all in-store promotions and marketing activities/events at retail level to enhance brand image, product awareness and drive sales/traffic\nManage VIP data for easy analysis. CRM implementation and maintenance of CRM system and activation\nWork closely with different departments and external parties for all trade marketing issues\nManage budget and targets for retention activities and report against ROI\nTranslation and blasting of press release. Arrange delivery of seeding products\nHandle customer complaints\nPrepare visual merchandising guideline and presentation to front line staff. Assist in coordinating and implementing new shop opening and retail promotions.\nDevelop and implement all visual merchandising and promotional displays for seasonal changeover, promotional programs and ad-hoc events under the direction of Onitsuka Tiger Headquarter Japan.\nSource and liaison with suppliers for the ordering, delivering and producing of materials relating to all visual merchandising.\nFollow up VM fixtures and replenishment works such as quotation, delivery schedule, quality control, etc.\nResponsible for the graphic design for various marketing campaigns and functions.\nPerform quality checks and shop visits to ensure complete implementation of visual merchandising materials according to the guideline and standard.\nOther ad hoc duties as assigned\n\uff1cDESIRED SKILLS & EXPERIENCE\uff1e\n\nUniversity graduate in Marketing, Digital Marketing or related disciplines\n3-5 years related hands-on experience of Marketing, preferable in fashion retail industry\nGood command of written and spoken English and Chinese is essential\nGood interpersonal skills, hardworking, creative, self-motivated and willing to learn\nAbility to work in fast-paced environment\nWord, Excel, Power Point skill is a must\nKnowledge in AI and Photoshop is preferable\n\nWe offer attractive remuneration package to the right candidate. If you are interested in this exciting opportunity, please click \u201cApply Now\u201d to submit applications with detailed resume stating career history, present & expected salary and date available.\n\nPersonal data collected will be used for recruitment purpose only. Applicants not hearing from us within 6 weeks may consider their applications unsuccessful and all related information will be destroyed after 6 months.", "employment_types": ["Full Time"], "selling_points": [], "locations": ["Causeway Bay"], "categories": ["Sales, CS & Business Devpt", "Business Development", "E-commerce", "Business Development", "Marketing - Brand / Product Management"], "post_time": "2022-01-16T21:50:30Z", "salary": {"currency": null, "max": null, "min": null, "period": "monthly", "term": null}, "salary_visible": false, "title_keywords": ["associate manager"], "responsibilities": ["data", "external parties", "budget", "merchandising", "quotation", "quality", "communication", "ad-hoc events", "ad hoc duties", "implementation", "develop", "reports", "marketing campaigns", "visual", "report", "customer complaints", "leaflets", "delivery schedule", "digital marketing", "drive sales", "trade marketing", "maintenance", "graphic design", "analysis", "replenishment", "evaluate", "quality control", "marketing materials"], "requirements": {"degrees": ["university graduate"], "majors": ["related disciplines", "marketing", "digital marketing"], "languages": ["english", "chinese"], "language_level": ["good command"], "hard_skills": ["excel", "maintenance", "ai", "analysis", "visual merchandising", "word", "power point", "translation", "photoshop"], "soft_skills": ["self-motivated", "responsible", "willing to learn", "communication", "hands-on", "interpersonal skills", "work in fast-paced environment", "creative", "presentation", "hardworking"], "languages_combined": [{"language": "english", "language_level": ["good command"]}, {"language": "chinese", "language_level": ["good command"]}]}, "experience_required": {"duration": ["3-5 years"], "field": ["related", "marketing", "retail industry"]}}, {"job_id": "100003009050059", "location_code": "hk", "company": "Mani Limited", "job_title": "E-COMMERCE EXECUTIVE", "description": "Job Duties:\n\nBusiness development on new marketplace\nManage the e-commerce team in APAC regions\n\nRequirements:\n\nMin 6 years of experience in online marketplace in HK & China and also have supervisory experience\nKnowledge in social media (e.g. Facebook, Instagram, WeChat, etc.)\nExperience in managing in-house e-business is an advantage\nGood in English and Chinese (including Mandarin)\nExcellent communication, presentation and interpersonal skills\n\nOur client will offer attractive salary to the right candidate. All information received will be kept in strict confidence and only for employment-related purpose.", "employment_types": ["Full Time", "Permanent"], "selling_points": [], "locations": ["Lai Chi Kok"], "categories": ["E-commerce", "Marketing - Brand / Product Management", "Product Management / Business Analyst", "Software Development"], "post_time": "2022-01-14T09:42:13Z", "salary": {"currency": null, "max": null, "min": null, "period": "monthly", "term": null}, "salary_visible": false, "title_keywords": ["executive"], "responsibilities": [], "requirements": {"degrees": [], "majors": [], "languages": ["english", "chinese", "mandarin"], "language_level": ["good"], "hard_skills": ["facebook", "wechat"], "soft_skills": ["communication", "confidence", "interpersonal skills", "presentation"], "languages_combined": [{"language": "english", "language_level": ["good"]}, {"language": "chinese", "language_level": ["good"]}, {"language": "mandarin", "language_level": []}]}, "experience_required": {"duration": ["min 6 years"], "field": ["supervisory experience", "business", "online marketplace"]}}, {"job_id": "100003009047455", "location_code": "hk", "company": "Wellesley Associates Limited", "job_title": "Senior Ecommerce Manager - FMCG Industry / MNC", "description": "Responsibilities\n\nTo drive Global eCommerce agenda across Asia markets and execute plans to maximize profitable revenues opportunities\nCo-creating, implementing and monitoring annual account plans to ensure sales targets and objectives are reached\nWork closely with internal and external parties to drive operational excellence for eCommerce and ensure optimization of digital investments\u00a0\nAnalyse sales data to track performance and identify insight to derive action plan\nCreating comprehensive country eCommerce business plans\nSupporting strategic planning meetings with online retailers and distributors to develop long term partnerships\nUnderstanding consumer behavior and making investment recommendations in line with consumer insights\nCoaching and developing indirect team members to ensure the channel strategy is properly organized, resourced, skilled and directed\n\nRequirement:\n\nBachelor's Degree holder in Marketing or any other related field\nAt least 8 years of relevant working experiences in Ecommerce Management\nPositive attitude, proactive, fast paced and a good team player\nDetail-minded with strong problem-solving and analytical skills\nExcellent verbal and written communication in Cantonese, Mandarin and English\n\nIf you would like to apply for this role or find out more, please apply online with your latest CV in word format and expected salary. Kindly note only shortlisted candidates will be notified.", "employment_types": ["Full Time", "Permanent"], "selling_points": ["Senior Ecommerce Manager - FMCG Industry / MNC", "Regional Exposure / Team-leading role", "8+ years related working experience"], "locations": ["Not Specified"], "categories": ["E-commerce", "Business Development", "Marketing - Brand / Product Management", "Product Management / Business Analyst"], "post_time": "2022-01-14T03:08:17Z", "salary": {"currency": null, "max": null, "min": null, "period": "monthly", "term": null}, "salary_visible": false, "title_keywords": ["manager"], "responsibilities": ["consumer insights", "strategic planning", "data", "monitoring", "internal and external parties", "developing", "business plans", "develop", "plan", "plans", "analyse"], "requirements": {"degrees": ["bachelor", "degree holder"], "majors": ["marketing"], "languages": ["cantonese", "english", "mandarin"], "language_level": ["excellent"], "hard_skills": ["problem-solving", "word", "analytical skills"], "soft_skills": ["detail-minded", "good team player", "problem-solving", "analytical skills", "positive attitude", "communication", "proactive"], "languages_combined": [{"language": "cantonese", "language_level": ["excellent"]}, {"language": "english", "language_level": ["excellent"]}, {"language": "mandarin", "language_level": ["excellent"]}]}, "experience_required": {"duration": ["at least 8 years"], "field": ["ecommerce", "management"]}}, {"job_id": "100003009043173", "location_code": "hk", "company": "OSIM (HK) Co. Limited", "job_title": "Digital Marketing Executive ( 5 Days Work)", "description": "Responsibilities:\n\nResponsible for content management of the brand website and other e-commerce channels\nAssist the team to plan and execute online promotion campaigns\n\nManage social media channels in order to meet the targeted KPI\nPlan and monitor company\u2019s SEO and SEM management\n\nParticipate and communicate with headquarters in website enhancement\nAssist in performance analysis in all digital channels\nAssist in any ad hoc duties as requested\n\nRequirements:\n\nDegree holder in Marketing / Communications e-commerce or related disciplines\nWith 1 - 2 years of solid experience in online marketing\n\nExperience in Google analytics is an advantage\nProactive, results-oriented with a strong sense of responsibility\nFast-paced with excellent communication and interpersonal skills\nCreative and attention to details\nGood command of spoken and written English, Cantonese, and Mandarin\n\n\nInterested parties, please send your full resume with\u00a0current salary,\u00a0expected salary,\u00a0and\u00a0available date\u00a0either by direct application from JobsDB (Please quote the job title on the subject ) or by WhatsApp:69298297 or by post to Human Resources Department, Unit 8-14 & 22-28, 11/F, Topsail Plaza, 11 On Sum Street, Shek Mun.\n\"Personal data collected will be used for recruitment purposes only.\"", "employment_types": ["Full Time", "Permanent"], "selling_points": [], "locations": ["Shatin Area"], "categories": ["Marketing / Public Relations", "Marketing - Direct Marketing", "Others", "E-commerce", "Marketing - Brand / Product Management"], "post_time": "2022-01-12T10:00:42Z", "salary": {"currency": null, "max": null, "min": null, "period": "monthly", "term": null}, "salary_visible": false, "title_keywords": ["digital marketing executive"], "responsibilities": ["communicate with", "social media", "management", "ad hoc duties", "seo", "analysis", "monitor", "website", "plan", "sem", "online promotion"], "requirements": {"degrees": ["degree holder"], "majors": ["related disciplines", "marketing", "communications", "e-commerce"], "languages": ["cantonese", "english", "mandarin"], "language_level": ["good command"], "hard_skills": ["google analytics", "e-commerce"], "soft_skills": ["creative", "sense of responsibility", "communication and interpersonal skills", "attention to details", "proactive"], "languages_combined": [{"language": "cantonese", "language_level": ["good command"]}, {"language": "english", "language_level": ["good command"]}, {"language": "mandarin", "language_level": ["good command"]}]}, "experience_required": {"duration": ["1 - 2 years"], "field": ["marketing"]}}, {"job_id": "100003009041834", "location_code": "hk", "company": "", "job_title": "Marketing and Operations Assistant (Health Products)", "description": "\n- Handle daily orders and stock management of online store (Website: www.gogoherbs.com )\n- Answer customer\u2019s inquiry about health supplements\n- Involve in content preparation for Facebook feeds and product highlights\n- Involve in formulating and reviewing social media and marketing plans periodically\n- Handle ad-hoc duties as assigned\n\nRequirement:\n- Higher Diploma or Above\n- Welcome fresh graduates; experience in Marketing / Ecommerce / Nutrition / Sports / Health-related industry will be an advantage\n- Proficiency in command of written and spoken English & Chinese\n- Good knowledge of MS Office\n- Positive, out-going with strong communication and interpersonal skills\n- Able to work both independently and as a part of a team\n- Immediate availability is preferred\n\nWorking Hours: 9am - 6pm Mon - Fri, Public Holidays\n\nInterested parties, please contact Joanne at\u00a054830695\u00a0\n\n\u5de5\u4f5c\u5167\u5bb9\uff1a\n- \u4fdd\u5065\u54c1\u7db2\u5e97\u71df\u904b\uff0c\u8ddf\u9032\u8a02\u55ae\u548c\u7ba1\u7406\u8ca8\u5b58 (\u7db2\u7ad9\uff1awww.gogoherbs.com)\n- \u89e3\u7b54\u9867\u5ba2\u6709\u95dc\u5065\u5eb7\u7522\u54c1\u7684\u67e5\u8a62\n- \u5354\u52a9\u793e\u4ea4\u5a92\u9ad4\u66f4\u65b0\u5167\u5bb9\n- \u5354\u52a9\u5206\u6790\u5e02\u5834\u8da8\u52e2\n- \u8ddf\u9032\u5176\u4ed6\u8207\u7db2\u5e97\u71df\u904b\u7684\u76f8\u95dc\u5de5\u4f5c\n\n\u5de5\u4f5c\u8981\u6c42\uff1a\n- \u5927\u5c08\u6216\u4ee5\u4e0a\u7a0b\u5ea6\u5b78\u6b77\n- \u6b61\u8fce\u61c9\u5c46\u7562\u696d\u751f\uff0c\u64c1\u5e02\u5834/\u71df\u990a/\u5065\u5eb7\u7522\u54c1\u884c\u696d\u76f8\u95dc\u7d93\u9a57\u8005\u512a\u5148\n- \u826f\u597d\u4e2d\u82f1\u6587\u6c34\u5e73\n- \u7a4d\u6975\u4e3b\u52d5\uff0c\u826f\u597d\u6e9d\u901a\u6280\u5de7\n- \u826f\u597d\u7368\u7acb\u53ca\u5718\u968a\u5de5\u4f5c\u80fd\u529b\n- \u53ef\u5373\u6642\u4e0a\u73ed\u8005\u512a\u5148\u8003\u616e\n\n\u4e0a\u73ed\u6642\u9593\uff1a\u661f\u671f\u4e00\u81f3\u4e94 9am - 6pm\uff0c\u516c\u773e\u5047\u671f\u4f11\u606f\n\n\u5982\u6709\u8208\u8da3\u61c9\u5fb5\uff0c\u8acb\u806f\u7d61Joanne\u00a0\u00a054830695\n\n\nInterested candidates, please contact us at 54830695 for company details before applying.", "employment_types": ["Full Time"], "selling_points": [], "locations": ["Mong Kok"], "categories": ["Marketing / Public Relations", "Marketing - General / Support", "E-commerce", "Marketing - Brand / Product Management"], "post_time": "2022-01-12T05:03:10Z", "salary": {"currency": null, "max": null, "min": null, "period": "monthly", "term": null}, "salary_visible": false, "title_keywords": ["operations assistant"], "responsibilities": ["social media", "stock management", "marketing plans", "website", "communication", "ad-hoc duties", "facebook", "handle daily orders", "content preparation"], "requirements": {"degrees": ["higher diploma or above"], "majors": [], "languages": ["english", "chinese"], "language_level": ["proficiency"], "hard_skills": ["facebook", "ms office"], "soft_skills": ["independently", "communication and interpersonal skills", "positive", "ad-hoc duties"], "languages_combined": [{"language": "english", "language_level": ["proficiency"]}, {"language": "chinese", "language_level": ["proficiency"]}]}, "experience_required": {"duration": [], "field": ["ecommerce", "marketing", "related"]}}, {"job_id": "100003009046475", "location_code": "hk", "company": "Bape Hong Kong Limited", "job_title": "Senior E-commerce Executive", "description": "Accountabilities \u2013 Key Result Areas\n\n\n\nHandle and manage the daily operations of the company\u2019s E-Commerce platform including but not limited to preparing eDM, content management, product listing, pricing, promotion, inventory update, customer service and order related issues\nDrive sales, define and implement online sales strategy and traffic optimization\nWork closely with various internal and external parties, including agency, marketing, graphic designers, system development team etc\nEnrich UX and optimize websites\u2019 structure, content and image\nAssisting in ad hoc projects\u00a0\nExperience / Qualification Requirements\n\n\nDegree holder in E-commerce / Business / Marketing related disciplines\n5 years or above relevant experience in E-Commerce\nMicrosoft Office, Good knowledge of website analytics tools, e.g. Google Analytics\nGood command of both spoken and written Cantonese, English and Mandarin\u00a0\u00a0\nAbility to work in a fast paced environment, multi task and works well under pressure\nExplores opportunities by being resourceful and self-motivating\nCompetitive remuneration and benefit package will be offered to the right candidate. Please submit your application by clicking \"Apply Now\" below.\n\n\n\nAll data collected is for recruitment purpose only.", "employment_types": ["Full Time"], "selling_points": ["5 years or above relevant experience in E-Commerce", "Daily operations of E-Commerce platform", "Good knowledge of website analytics tools"], "locations": ["Southern Area"], "categories": ["Marketing / Public Relations", "Digital Marketing", "E-commerce", "Business Development", "Marketing - Brand / Product Management"], "post_time": "2022-01-13T11:41:53Z", "salary": {"currency": null, "max": null, "min": null, "period": "monthly", "term": null}, "salary_visible": false, "title_keywords": ["executive"], "responsibilities": ["analytics tools", "management", "product listing", "edm", "data", "inventory", "internal and external parties", "website", "daily operations", "customer service", "ad hoc projects", "recruitment", "drive sales", "e-commerce platform"], "requirements": {"degrees": ["degree holder"], "majors": ["related disciplines", "business", "marketing", "e-commerce"], "languages": ["cantonese", "english", "mandarin"], "language_level": ["good command"], "hard_skills": ["microsoft office", "analytics tools", "google analytics", "e-commerce"], "soft_skills": ["work in a fast paced environment", "customer service", "under pressure", "resourceful"], "languages_combined": [{"language": "cantonese", "language_level": ["good command"]}, {"language": "english", "language_level": ["good command"]}, {"language": "mandarin", "language_level": ["good command"]}]}, "experience_required": {"duration": ["5 years"], "field": ["relevant experience", "e-commerce"]}}, {"job_id": "100003009041271", "location_code": "hk", "company": "I.T Apparels Limited", "job_title": "E-commerce Assistant (REF: JDB-IT-ECA)", "description": "Accountabilities \u2013 Key Result Areas\n\nManage ITeShop.com platform interface updates effectively with latest product collections news and information, pricing updates, published meeting promotion plans and digital marketing campaigns, etc.\nEnsure accuracy in gathering relevant updates smooth coordination with relevant stakeholders in timely manner\nSupport other e-commerce operation and other ad-hoc tasks as required\n\nExperience / Qualification Requirements\n\nDegree holder in Business or other disciplines\nWith 1 \u2013 2 years\u2019 administration or project coordination experience in e-commerce/ digital platform environment\nProficient in both English and Chinese communication\nProficiency in\u00a0Photoshop and Adobe Illustrator\nOutstanding interpersonal and communication skills, with ability to work with multiple international stakeholders\nAble to perform multi-tasks and work under pressure in fast paced environment\nPositive attitude, detailed minded, good organization and problem solving skills\n\nCompetitive remuneration and benefit package will be offered to the right candidate. Please submit your application by clicking \"Apply Now\" below.\n\nAll data collected is for recruitment purpose only.\n\nSure you want to know more about our company and brands, simply follow our\n\nWEBSITE at http://www.ithk.com \u00a0 \u00a0 \u00a0 \u00a0 \u00a0 \u00a0 \u00a0 \u00a0 \u00a0 \u00a0 \u00a0 \u00a0 \u00a0 \u00a0 \u00a0 \u00a0 \u00a0 \u00a0 \u00a0 \u00a0 \u00a0 \u00a0 \u00a0 \u00a0 \u00a0 \u00a0 \u00a0 \u00a0 \u00a0 \u00a0 \u00a0 \u00a0 \u00a0 \u00a0\n\nFACEBOOK at\u00a0http://www.facebook.com/I.Ttheofficialpage \u00a0 \u00a0 \u00a0 \u00a0 \u00a0 \u00a0 \u00a0 \u00a0 \u00a0 \u00a0 \u00a0 \u00a0 \u00a0 \u00a0\n\nINSTAGRAM at http://instagram.com/ithk\u00a0 \u00a0 \u00a0 \u00a0 \u00a0 \u00a0 \u00a0 \u00a0 \u00a0 \u00a0 \u00a0 \u00a0 \u00a0 \u00a0 \u00a0 \u00a0 \u00a0 \u00a0 \u00a0 \u00a0 \u00a0 \u00a0 \u00a0 \u00a0 \u00a0 \u00a0 \u00a0 \u00a0\n\nWEIBO at\u00a0http://e.weibo.com/ithongkong", "employment_types": ["Full Time", "Permanent"], "selling_points": ["Support e-commerce operation", "Manage ITeShop.com platform", "Proficiency in Photoshop and Adobe Illustrator"], "locations": ["Southern Area"], "categories": ["Sales, CS & Business Devpt", "Retail Sales", "E-commerce", "Marketing - Brand / Product Management", "Product Management / Business Analyst"], "post_time": "2022-01-12T03:40:38Z", "salary": {"currency": null, "max": null, "min": null, "period": "monthly", "term": null}, "salary_visible": false, "title_keywords": ["assistant"], "responsibilities": ["project coordination", "data", "work under pressure", "digital marketing campaigns", "ad-hoc tasks", "coordination with", "website", "digital platform", "communication", "recruitment", "plans", "facebook", "administration"], "requirements": {"degrees": ["degree holder"], "majors": ["business"], "languages": ["english", "chinese"], "language_level": ["proficient"], "hard_skills": ["e-commerce", "adobe illustrator", "facebook", "problem solving skills", "photoshop"], "soft_skills": ["communication skills", "multi-tasks", "timely", "detailed", "communication", "positive attitude", "coordination", "smooth", "problem solving skills", "interpersonal", "work under pressure"], "languages_combined": [{"language": "english", "language_level": ["proficient"]}, {"language": "chinese", "language_level": ["proficient"]}]}, "experience_required": {"duration": ["2 years"], "field": ["digital", "e-commerce", "administration"]}}, {"job_id": "100003009043476", "location_code": "hk", "company": "Agora Advertising Limited", "job_title": "Digital Marketing Executive", "description": "Key Responsibility\n\u2022 Conduct comprehensive market research for internal and external projects\n\u2022 Good knowledge of digital marketing products for preparation of strategic digital media plans\n\u2022 Formula and execute digital campaigns across social media, Google Ads, Yahoo & Bing Ads, media placement and KOLs alignment\n\u2022 Copywriting of social media marketing materials, search & display campaigns, internal branding posts and website\n\u2022 Analyse performance metrics and conduct evaluation reports in use of analytical tools\n\nRequirements\n\u2022 Degree in Digital Marketing / Marketing / Communications / Journalism / Business / Multimedia or related disciplines\n\u2022 Minimum 1 year relevant experience is preferred (Fresh Graduates are also welcome)\n\u2022 Proficient in Microsoft suite\n\u2022 Good command in Chinese, English and Mandarin\n\u2022 Creative and conceptual, with interest in the latest digital trends\n\u2022 Motivated, positive and adaptive with strong team spirit\n\u2022 Immediate available is preferred\n\nBenefits\n\u2022 Five-day work\n\u2022 Public holiday\n\u2022 12 days annual leave\n\u2022 Birthday leave\n\nInterested parties please apply with your CV & Expected Salary.", "employment_types": ["Full Time"], "selling_points": [], "locations": ["Kwai Hing"], "categories": ["Media & Advertising", "Strategic Planning", "Marketing / Public Relations", "Digital Marketing", "E-commerce", "Marketing - Brand / Product Management"], "post_time": "2022-01-12T13:24:25Z", "salary": {"currency": null, "max": null, "min": null, "period": "monthly", "term": null}, "salary_visible": false, "title_keywords": ["digital marketing executive"], "responsibilities": ["social media", "market research", "website", "performance metrics", "digital marketing", "reports", "digital campaigns", "evaluation", "marketing materials", "plans", "analyse"], "requirements": {"degrees": ["degree"], "majors": ["journalism", "related disciplines", "marketing", "digital marketing", "business", "communications"], "languages": ["english", "chinese", "mandarin"], "language_level": ["good command"], "hard_skills": ["multimedia"], "soft_skills": ["motivated", "creative", "team spirit", "positive"], "languages_combined": [{"language": "english", "language_level": ["good command"]}, {"language": "chinese", "language_level": ["good command"]}, {"language": "mandarin", "language_level": ["good command"]}]}, "experience_required": {"duration": ["minimum 1 year"], "field": ["relevant experience"]}}, {"job_id": "100003009045587", "location_code": "hk", "company": "Silenus (Hong Kong) Limited", "job_title": "E-Commerce Inventory & Logistic Executive", "description": "Our client, a global E-Commerce business branding company, is now looking for an experienced candidate to join them.\n\nResponsibilities:\n\nMake the optimal inventory forecast and planning for each client and their own E-commerce business\nRegularly review and track the existing sales and inventory data\nDevelop a model for inventory data analysis, for better forecasting and planning\nWork closely with existing logistic vendor for product delivery\nHandle and record customer\u2019s inquire for improvement\n\nRequirements:\n\nDegree or Diploma in the relevant discipline\nMore than 2 years in E-Commerce inventory planning and execution, preferably with cross border handlings\nSolid achievement for improving inventory performance\nStrong analytical and communication skills\nFluent in English and Mandarin\n\nFor a confidential discussion about this role please contact Clarence at 2185 6309.", "employment_types": ["Full Time", "Permanent"], "selling_points": ["Strong technical support for data tracking", "CEO with solid experience in E-Commerce sector", "Adaptive and flexible working environment"], "locations": ["Kwun Tong"], "categories": ["E-commerce", "Marketing - Brand / Product Management", "Product Management / Business Analyst", "Supply Chain"], "post_time": "2022-01-13T08:08:23Z", "salary": {"currency": "HKD", "max": 29999, "min": 20000, "period": "monthly", "term": null}, "salary_visible": true, "title_keywords": ["executive"], "responsibilities": ["data", "inventory", "review", "develop", "data analysis", "forecast", "forecasting", "planning"], "requirements": {"degrees": ["diploma", "degree"], "majors": [], "languages": ["english", "mandarin"], "language_level": ["fluent"], "hard_skills": ["e-commerce"], "soft_skills": ["communication skills"], "languages_combined": [{"language": "english", "language_level": ["fluent"]}, {"language": "mandarin", "language_level": ["fluent"]}]}, "experience_required": {"duration": [], "field": []}}, {"job_id": "100003009042300", "location_code": "hk", "company": "Eco Art Limited", "job_title": "E-Commerce executive", "description": "Job Responsibilities:\n\nMap out detailed execution plans and critical timelines; and follow through to ensure smooth operation and launch of marketing programs & regular promotions\nExplore and develop effective online & offline channels to strengthen the company business. Prepare sales data analysis to evaluate brand performance\nWork closely with both internal and external parties in implementing promotion cycles and enhance business performance\nPrepare various kinds of online & offline marketing materials and assist in photo and video shooting and editing for products\nDevelop, maintain, and update content & copywriting in various digital & social media channels by creative ideas\nCarry out ad-hoc tasks as assigned by the supervisor\n\n\nJob Requirements:\n\n\nBachelor\u2019s Degree in marketing, Information Technology, Communications and Business, Retail Management or other related disciplines\nWith at least 3-4 years\u2019 experience in managing digital marketing project, previous experience in managing large scale digital projects is preferable\nInnovative, Creative, fast-paced, independent, self-initiative, energetic, able to work under pressure and to meet tight schedule\nGood written and verbal communication skills in both English and Chinese", "employment_types": ["Full Time"], "selling_points": ["Manage day-to-day operation of e-commerce platform", "Detail-oriented and passionate with baby products", "Good team player"], "locations": ["Kowloon Bay"], "categories": ["E-commerce", "Business Development", "Marketing - Brand / Product Management"], "post_time": "2022-01-12T06:56:34Z", "salary": {"currency": null, "max": null, "min": null, "period": "monthly", "term": null}, "salary_visible": false, "title_keywords": ["executive"], "responsibilities": ["social media", "creative ideas", "ad-hoc tasks", "internal and external parties", "prepare sales", "develop", "data analysis", "evaluate", "video shooting", "maintain", "marketing materials", "plans", "editing"], "requirements": {"degrees": ["degree", "bachelor"], "majors": ["information technology", "related disciplines", "business", "marketing", "communications"], "languages": ["english", "chinese"], "language_level": ["good"], "hard_skills": [], "soft_skills": ["communication skills", "independent", "creative", "innovative", "self-initiative", "energetic", "work under pressure"], "languages_combined": [{"language": "english", "language_level": ["good"]}, {"language": "chinese", "language_level": ["good"]}]}, "experience_required": {"duration": ["at least 3-4 years"], "field": ["digital", "digital marketing"]}}, {"job_id": "100003009051840", "location_code": "hk", "company": "Stylevana", "job_title": "Business Development Manager \u2013 Beauty", "description": "Provide Online Customer Service, Online eshops Operation.\nHandle e-commerce logistic and orders issues.\nWork closely with the product buying team to prepare for key retail seasonal cycles \u2013 season launches, sale and promotions.\nLiaise with warehouse and 3rd party partner to ensure the delivery standard is met.\nSet up e-commerce platforms (e-shop, website, mobile app\u2026.).\nParticipate in ad-hoc projects when require.\nResponsible for sourcing products for selling on E Shop which matches existing company direction.\nProvide full aspect of operational and administrative support to all retail spots.\nUpdate daily sales data of each sales spot for management review.\nRequirements:\n\nFamiliarity with website analytics tools such as Google Analytics is an advantage.\nProficient in using MS Office such as Word and Excel.\nGood working attitude and communication skill.\nCustomer oriented, responsible, well-organized, work with minimum supervision & able to work under pressure.\nProficient in both written and spoken Chinese and English.\nAble to work independently and under pressure to meet tight deadlines.", "employment_types": ["Full Time", "Permanent"], "selling_points": ["eCom - Asian Beauty Products (Japan/ Korea)", "Negotiate and work with vendors", "5-day work, Double Pay, friendly team"], "locations": ["Kwai Hing"], "categories": ["Marketing / Public Relations", "Marketing - Brand / Product Management", "Merchandising & Purchasing", "Procurement / Purchasing / Sourcing", "E-commerce", "Marketing - Brand / Product Management"], "post_time": "2022-01-17T01:20:53Z", "salary": {"currency": null, "max": null, "min": null, "period": "monthly", "term": null}, "salary_visible": false, "title_keywords": ["business development manager"], "responsibilities": ["analytics tools", "e-shop", "mobile app", "online eshops operation", "administrative support", "data", "e-commerce platforms", "website", "communication", "online customer service", "liaise with", "sourcing products", "ad-hoc projects", "management review", "work under pressure"], "requirements": {"degrees": [], "majors": [], "languages": ["english", "chinese"], "language_level": ["proficient"], "hard_skills": ["analytics tools", "google analytics", "excel", "e-commerce", "word", "mobile", "ms office"], "soft_skills": ["good working attitude", "work independently", "meet tight deadlines", "under pressure", "responsible", "communication skill", "well-organized", "customer service", "work under pressure"], "languages_combined": [{"language": "english", "language_level": ["proficient"]}, {"language": "chinese", "language_level": ["proficient"]}]}, "experience_required": {"duration": [], "field": []}}, {"job_id": "100003009045874", "location_code": "hk", "company": "I.T Apparels Limited", "job_title": "CRM Assistant (REF : JDB-IT-CRMA)", "description": "Join us & Be eCommerce Innovators\nAre you looking to be part of revolutionizing online shopping behaviour and experience? We are a well-esteemed eCommcere company that operates multiple eCommerce websites internationally. We are now looking for potential talent to help us expand our new business worldwide and to manage the merchandising process of beauty products.\n\n\n\nKey Job Responsibilities:\u00a0\n\nResponsible and manage the sourcing activities and vendor management for Korean and Japanese beauty and cosmetics category\nNegotiate and work with vendors in Korea, Japan or other regions to build and maintain mutually beneficial relationships to ensure long term strategic partnership\nMaximize Korean and Japanese beauty brands/products sales performance through continuous effort in identifying new vendors in Korea, Japan or other regions\nDrive and implement business strategies to build the categories for the company\nManage merchandising process from souring, product development to vendor management\nProvide strategic sourcing planning and coordinate within merchandising team and sales team for implementation\nAny ad-hoc tasks as assigned\n\n\u00a0Desired Skills and Experience:\u00a0\n\nMinimum 3 years or above working experience in relevant merchandise category or business development experience under trading environment or buying office\nExperience in Korea and Japan branded beauty products\nGood supplier networks with sound vendor development experience and skillsets will be an advantage\nWell-organized, detailed minded, result oriented and able to manage multiple tasks environment\nAble to work independently and under pressure, as well as cooperate well with team and stakeholders to achieve company goals\nExcellent command of written and spoken English, proficiency in Korean or Japanese will be an advantage\nFrequent oversea travel is needed\n\nWe offer friendly team environment, good career prospect, also attractive remuneration package including discretionary bonus incentive, together with other benefits like five-day work week, flexible working hours, double pay, medical and dental insurance. Interested parties please send full resume with available date, present and expected salary by clicking \u201cApply Now\u201d for an interview.\n\nAll personal data collected will be used for recruitment purpose only.\u00a0", "employment_types": ["Full Time", "Permanent"], "selling_points": ["Minimum 1 year of experience in CRM Analytics", "Responsible for customer database management", "Fresh Graduate will also be considered"], "locations": ["Southern Area"], "categories": ["Marketing / Public Relations", "Marketing - Market Research", "Digital Marketing", "E-commerce", "Marketing - Brand / Product Management"], "post_time": "2022-01-13T09:00:21Z", "salary": {"currency": null, "max": null, "min": null, "period": "monthly", "term": null}, "salary_visible": false, "title_keywords": ["crm assistant"], "responsibilities": ["management", "sales performance", "ad-hoc tasks", "merchandising", "implementation", "coordinate", "maintain", "sales team", "insurance", "planning"], "requirements": {"degrees": [], "majors": [], "languages": ["japanese", "english", "korean"], "language_level": ["advantage", "excellent", "proficiency"], "hard_skills": ["vendor"], "soft_skills": ["flexible", "work independently", "under pressure", "responsible", "multiple tasks", "well-organized", "result oriented", "friendly", "detailed"], "languages_combined": [{"language": "japanese", "language_level": ["excellent"]}, {"language": "english", "language_level": ["advantage", "proficiency", "excellent"]}, {"language": "korean", "language_level": ["excellent"]}]}, "experience_required": {"duration": ["minimum 3 years"], "field": ["ecommerce", "development", "business development", "beauty", "trading"]}}, {"job_id": "100003009041597", "location_code": "hk", "company": "Maryling Asia Pacific Group Limited", "job_title": "Social Media Specialist", "description": "Responsibilities\n\n\nManage and create content for various social media platforms, including copywriting, product descriptions translation, and photos / videos editing;\nAssist in planning and implementing online and offline marketing campaigns and events;\nAffiliate marketing coordination. To grow the number of influencers and followers for the brands;\nLiaise with the operations team and design team;\nPerform ad-hoc tasks as assigned.\nRequirements\n\nDiploma holder or above in Communication, Business, Marketing or related field;\n2 years of solid experience in marketing, e-commerce, or retail is highly preferred;\nProficiency in managing social media platforms, Adobe Photoshop, Illustrator, and video editing;\nIndependent, self-motivated, detail-minded, and a good team player;\nGood command of written & spoken English, Mandarin, and Cantonese;\nImmediately available is a definite advantage\n\n\nInterest parties, please send full resume with current and expected salary and date of availability by clicking \"Apply Now\".\u00a0Personal data provided in application will be treated as strictly confidential and used for recruitment purpose by\u00a0MARYLING\u00a0only.\u00a0All unsuccessful applications will be destroyed upon completion of the process.\n\n", "employment_types": ["Full Time", "Permanent"], "selling_points": ["Manage social media platforms", "Plan & execute online/offline marketing campaigns", "Grow the no. of influencers and followers"], "locations": ["Tsim Sha Tsui"], "categories": ["Marketing / Public Relations", "Marketing - Brand / Product Management", "Marketing - General / Support", "E-commerce", "Marketing - Brand / Product Management"], "post_time": "2022-01-12T04:05:08Z", "salary": {"currency": null, "max": null, "min": null, "period": "monthly", "term": null}, "salary_visible": false, "title_keywords": ["social media specialist"], "responsibilities": ["product descriptions", "operations", "ad-hoc tasks", "social media platforms", "design", "marketing campaigns", "coordination", "liaise with", "editing", "planning"], "requirements": {"degrees": ["diploma holder"], "majors": ["business", "marketing"], "languages": ["cantonese", "english", "mandarin"], "language_level": ["good command"], "hard_skills": ["video editing", "adobe photoshop", "illustrator", "e-commerce"], "soft_skills": ["detail-minded", "good team player", "self-motivated", "independent", "communication"], "languages_combined": [{"language": "cantonese", "language_level": ["good command"]}, {"language": "english", "language_level": ["good command"]}, {"language": "mandarin", "language_level": ["good command"]}]}, "experience_required": {"duration": ["2 years"], "field": ["marketing", "retail", "e-commerce"]}}, {"job_id": "100003009037311", "location_code": "hk", "company": "Scents Limited", "job_title": "Marketing Executive", "description": "Responsibilities:\n\nSupport and execute the marketing strategies and planning set by the company in order to drive business growth.\nInitiate new marketing ideas and implement creative marketing & communications programs, CRM activities and other tactical campaigns.\nCoordinate digital marketing activities; monitor and enhance the brand\u2019s social media and digital presence.\nDevelop media plan, creative digital marketing ideas, contents and press materials as well as manage media liaison.\nEvaluating the campaign performance and providing insights to optimize the traffic and conversion\nCo-ordinating with creative team and product team on all marketing communications development, ensuring all promotions are planned and executed on schedule\u2002\nPerform other ad hoc tasks as assigned\u2002\n\nRequired Education:\n\nDegree holder in marketing /\u00a0communication\u00a0/\u00a0business or related discipline\nMinimum 3 years relevant marketing experiences. Experience in food tech / e-commerce / start-up / digital agency is definitely a plus.\nExcellent command of written and spoken English and Cantonese\nCreative, detail-minded, self-motivated , passionate and good at multitasking\nCandidates with more experience will be considered as Assistant Marketing Manager\nBe willing to work hard in a start-up company with can-do spirit\nBe able to work under pressure and meet tight deadline\n\nCompetitive Remuneration Package:\n\n5-day Work Week (Mon - Fri :10:00 \u2013 19:00)\nPublic Holidays\nMinimum 15 days of Paid Annual Leave\nBirthday Leave\nMedical Allowances\nDiscretionary Performance Bonus\n\nInterested parties please submit your CV and expected salary by clicking \"Apply Now\".\n\nVisit us on: https://www.readycook.hk/\n\nWe are an equal opportunity employer and welcome applications from all qualified candidates. The personal data collected will be treated in strict confidence and used for recruitment-related purposes only. All personal data of unsuccessful candidates will be destroyed after 6 months.", "employment_types": ["Full Time", "Permanent"], "selling_points": [], "locations": ["Kwun Tong"], "categories": ["Marketing / Public Relations", "Marketing - Brand / Product Management", "Marketing - General / Support", "E-commerce", "Marketing - Brand / Product Management"], "post_time": "2022-01-11T02:37:45Z", "salary": {"currency": null, "max": null, "min": null, "period": "monthly", "term": null}, "salary_visible": false, "title_keywords": ["marketing executive"], "responsibilities": ["social media", "marketing strategies", "ideas", "work under pressure", "monitor", "ad hoc tasks", "develop", "coordinate", "communication", "digital marketing", "schedule", "plan", "contents", "planning"], "requirements": {"degrees": ["degree holder"], "majors": ["business", "marketing"], "languages": ["cantonese", "english"], "language_level": ["excellent"], "hard_skills": ["plus", "e-commerce"], "soft_skills": ["detail-minded", "passionate", "self-motivated", "communication", "can-do", "meet tight deadline", "creative", "work under pressure"], "languages_combined": [{"language": "cantonese", "language_level": ["excellent"]}, {"language": "english", "language_level": ["excellent"]}]}, "experience_required": {"duration": ["minimum 3 years"], "field": ["e-commerce", "agency", "digital", "tech", "marketing", "food"]}}, {"job_id": "100003009043345", "location_code": "hk", "company": "Hero Star Group Co Limited", "job_title": "Senior Marketing Executive / Assistant Marketing Manager", "description": "Responsibilities:\n\nManage online shop and update website content (product listing, Sales report, translate product description from English to Chinese)\nMake ongoing recommendations on keywords discovery, expansion and optimization in order to improve the keywords ranking\nPerform data analysis and to review the effectiveness of the promotion and the optimization of SEO, SEM and Google Ads\nPerform SEO for onsite product pages and blog articles\nDesign, creates contents and manage promotions in print and on social media platforms (Facebook, Instagram, YouTube and others)\nImplementation & creation of promotion material, print ad banner, EDM.\nWork with internal teams to follow up customers\u2019 online order inquires and after-sales support services\n\nJob Requirement:\u00a0\u00a0\n\nDegree or above in Business, Marketing, Advertising, Communications, E-commerce, management, or related discipline\nMinimum of 3 years of experience in e-commerce\nProficient in\u00a0computer skills,\u00a0MS Office (Word, Excel, PowerPoint etc.)\nProficient in Adobe CS, including Adobe Illustrator, Photoshop, Video production. or other graphic design tools preferred\nGood communication skill in spoken and written English, Chinese\nOutgoing personality, aggressive, independent and able to work under pressure\nImmediate available is a definite advantage\n\nBenefits:\n\n\n5 working days, annual leave, bank holiday, medical benefits and education allowance, etc.\n\nWorking Hours: Monday to Friday (9:00am - 6:00pm)\nInterested parties please click \u201cApply Now\u201d to submit your resume w/expected salary.", "employment_types": ["Full Time"], "selling_points": [], "locations": ["Kwun Tong"], "categories": ["E-commerce", "Marketing - Brand / Product Management"], "post_time": "2022-01-12T11:00:07Z", "salary": {"currency": null, "max": null, "min": null, "period": "monthly", "term": null}, "salary_visible": false, "title_keywords": ["assistant marketing manager", "senior marketing executive"], "responsibilities": ["sales report", "seo", "product listing", "edm", "review", "social media platforms", "website", "design", "implementation", "data analysis", "teams", "support services", "sem", "contents", "facebook"], "requirements": {"degrees": ["degree or above"], "majors": ["business", "e-commerce", "communications", "marketing"], "languages": ["english", "chinese"], "language_level": ["good"], "hard_skills": ["excel", "e-commerce", "word", "powerpoint", "adobe illustrator", "computer skills", "photoshop", "adobe cs", "ms office"], "soft_skills": ["outgoing personality", "communication skill", "independent", "work under pressure"], "languages_combined": [{"language": "english", "language_level": ["good"]}, {"language": "chinese", "language_level": ["good"]}]}, "experience_required": {"duration": ["minimum of 3 years"], "field": ["e-commerce"]}}, {"job_id": "100003009036170", "location_code": "hk", "company": "Scents Limited", "job_title": "Digital Marketing Executive", "description": "Job Description\n\nLead the e-commerce team to drive business development\nAchieve sales target and manage spending within budget\nAnalyze customer insights, consumer trends, market analysis, marketing best practices in order to build business strategies\nResponsible for providing strategic sales and promotion plans to key retailers and drive e-commerce business\nEstablish partnership with e-commerce customers and agencies in order to develop and maintain strategic collaboration with major customers of all channels\nProvide continuous improvement plans to uplift key performance index\nExplore new channels / platforms to maximize sales opportunities and enhance brand awareness\nHandle any other ad-hoc company projects as assigned\u00a0\n\n\u00a0Job Requirements\n\nDegree holder in Marketing, E-commerce or Information Technology\n7 years of relevant experience in FMCG industry in which 3 years of hands-on e-commerce planning and sales management\nExperience in managing promotional calendars/ digital campaigns\nShopify operation experience is a must\nOnline Marketplace operation experience is an advantage\nEnergetic, result-oriented, well-organized, self-motivated, able to work independently and under pressure\nGood communication, presentation, interpersonal & analytical skills\nGood command of written and spoken English and Chinese\n\u00a0\n\n\nWe offer competitive remuneration package and good prospects to the right candidates. Interested parties please send your full resume with expected salary to our email.\n\n*Data collected will be kept confidential and used for recruitment purposes only.", "employment_types": ["Full Time", "Permanent"], "selling_points": [], "locations": ["Kwun Tong Area"], "categories": ["Marketing / Public Relations", "Marketing - General / Support", "Digital Marketing", "E-commerce", "Marketing - Brand / Product Management"], "post_time": "2022-01-11T01:32:35Z", "salary": {"currency": null, "max": null, "min": null, "period": "monthly", "term": null}, "salary_visible": false, "title_keywords": ["digital marketing executive"], "responsibilities": ["consumer trends", "ad-hoc", "sales target", "budget", "customer insights", "develop", "market analysis", "maintain", "plans"], "requirements": {"degrees": ["degree holder"], "majors": ["marketing", "information technology", "e-commerce"], "languages": ["english", "chinese"], "language_level": ["good command"], "hard_skills": ["shopify", "fmcg industry", "analytical skills", "e-commerce"], "soft_skills": ["self-motivated", "work independently", "under pressure", "interpersonal", "presentation", "well-organized", "analytical skills", "communication", "hands-on", "energetic", "result-oriented"], "languages_combined": [{"language": "english", "language_level": ["good command"]}, {"language": "chinese", "language_level": ["good command"]}]}, "experience_required": {"duration": ["7 years", "3 years"], "field": ["management", "fmcg", "e-commerce", "online marketplace", "operation", "relevant experience", "digital", "planning"]}}, {"job_id": "100003009046122", "location_code": "hk", "company": "City Super Ltd", "job_title": "E-Commerce Manager", "description": "Responsibilities:\n\nAssist in the formulation of strategies to build a lasting digital connection with consumers\nPlan and monitor our brands on social media\nLaunch optimized online adverts through Google Adwords, Facebook etc. to increase company and brand awarenes\nMeasure performance of digital marketing efforts using a variety of Web analytics tools (Google Analytics)\nRequirements\n\nProven experience as a Digital Marketing Officer or similar role\nExperience with social media, Google Adwords and email campaigns.\nAnalytical mindset and critical thinking\nExcellent communication and interpersonal skills\nMinimum 2 years in digital marketing experience.\nStrong Chinese copywriting skills. Intermediate English accepted.\nCandidate who is immediately available is preferred.\nWe offer an attractive remuneration package to the right candidates. Interested parties please apply in full resume including current salary, expected salary and earliest availability by clicking\u00a0APPLY NOW.\u00a0\n\nApplications without\u00a0expected salary will not be considered.\nPersonal data collected will be used for recruitment purpose only.", "employment_types": ["Full Time", "Permanent"], "selling_points": ["Lead the e-commerce team to drive business", "Hands-on e-commerce planning and sales mgt.", "Shopify operation experience"], "locations": ["Tsim Sha Tsui"], "categories": ["E-commerce", "Business Development", "Marketing - Brand / Product Management", "Supply Chain"], "post_time": "2022-01-13T09:39:57Z", "salary": {"currency": null, "max": null, "min": null, "period": "monthly", "term": null}, "salary_visible": false, "title_keywords": ["manager"], "responsibilities": ["social media", "analytics tools", "monitor", "digital marketing", "plan", "facebook"], "requirements": {"degrees": [], "majors": [], "languages": ["english", "chinese"], "language_level": ["intermediate"], "hard_skills": ["adwords"], "soft_skills": ["communication and interpersonal skills"], "languages_combined": [{"language": "english", "language_level": ["intermediate"]}, {"language": "chinese", "language_level": []}]}, "experience_required": {"duration": ["minimum 2 years"], "field": ["social media", "digital marketing"]}}, {"job_id": "100003009038072", "location_code": "hk", "company": "Tsui Wah Restaurant", "job_title": "Marketing Officer (Digital marketing)", "description": "JOIN OpenRice\u2026\u2026if you want to service our\n\n\u00a05 million App users with\n\n\u00a09 million pageviews per day in Hong Kong!\u00a0\n\n\nOpenRice\u00a0is seeking an energetic and passionate individual to join a dynamic and collaborative environment as part of marketing\u00a0team.\n\nYou will be responsible for:\n\n\nSupport and execute the marketing strategies and planning set by the company in order to drive business growth.\nInitiate new marketing ideas and implement creative marketing & communications programs, CRM activities and other tactical campaigns.\nCoordinate digital marketing activities; monitor and enhance the brand\u2019s social media and digital presence.\nDevelop media plan and press materials as well as manage media liaison.\nDrive the loyalty program to engage and reward our loyal customers.\nConduct market research and analytical reports to identify opportunities and trends in the market.\n\nYou should possess:\n\n\n\nDegree holder in marketing / communication / business or related discipline\nMinimum 5 years relevant marketing experiences. Experience in food tech / e-commerce / consumer app / digital agency is definitely a plus.\nExcellent command of written and spoken English and Cantonese\nCreative, detail-minded, outgoing and self-motivated\nCandidates with more experience will be considered as Assistant Marketing Manager\n\nWe offer a competitive remuneration package including excellent career prospects to the right candidate. Interested parties please submit your detailed resume with expected salary and available date by clicking the Quick Apply button.\n\nAll personal information submitted by job applicants will be used for recruitment purposes and we reserve the rights to consider the applications for other positions in our Group.", "employment_types": ["Full Time"], "selling_points": ["Social media", "Digital marketing", "Immediately available is preferred"], "locations": ["Kwai Hing"], "categories": ["Marketing / Public Relations", "Marketing - Brand / Product Management", "Digital Marketing", "E-commerce", "Marketing - Brand / Product Management"], "post_time": "2022-01-11T04:52:42Z", "salary": {"currency": null, "max": null, "min": null, "period": "monthly", "term": null}, "salary_visible": false, "title_keywords": ["digital marketing", "marketing officer"], "responsibilities": ["social media", "marketing strategies", "ideas", "conduct market research", "monitor", "develop", "coordinate", "communication", "digital marketing", "reports", "plan", "planning"], "requirements": {"degrees": ["degree holder"], "majors": ["business", "marketing"], "languages": ["cantonese", "english"], "language_level": ["excellent"], "hard_skills": ["plus", "dynamic", "e-commerce"], "soft_skills": ["passionate", "detail-minded", "outgoing", "self-motivated", "creative", "responsible", "collaborative", "communication", "dynamic", "loyal", "energetic"], "languages_combined": [{"language": "cantonese", "language_level": ["excellent"]}, {"language": "english", "language_level": ["excellent"]}]}, "experience_required": {"duration": ["minimum 5 years"], "field": ["e-commerce", "agency", "digital", "tech", "marketing", "food"]}}, {"job_id": "100003009042639", "location_code": "hk", "company": "Openrice Limited", "job_title": "Senior Marketing Executive / Assistant Marketing Manager", "description": "Resourceful Brand Principal\nFast-paced FMCG environment\nCommercial focused role\nThe Role\n\nResponsible for Online Sales strategies and achieve business and brand targets of via different E-Commerce market places\nSupport the development of e-commerce business best practices for the business unit\nPartner closely with Trade Marketing Manager and Brand Managers on campaigns development to increase traffic, recruit new users, and reward loyal customers\nPrepare data analysis reports, manage the budget, and identify business opportunities\nRequirements\n\nDegree holder with at least 8 years working experience in e-commerce business management\nStrong marketing acumen and business development orientation.\nExposure in FMCG industry in Hong Kong essential\nStrong professional business acumen and influencing skills\nWell versed in English and Chinese\n\nInterested candidates, please email your update resume (in MS WORD format) with current and expected salary to us soonest.\n\nAlso come visit www.ProJob21.com to discover other exciting career opportunities!\n\nAll information received will be kept in strict confidence and used for employment-related purposes only.", "employment_types": ["Full Time", "Permanent"], "selling_points": ["Stable and fast growing business", "Flexible working hours", "Immediate availability is preferred"], "locations": ["Quarry Bay"], "categories": ["Media & Advertising", "Others", "Marketing / Public Relations", "Digital Marketing", "E-commerce", "Marketing - Brand / Product Management"], "post_time": "2022-01-12T08:15:00Z", "salary": {"currency": null, "max": null, "min": null, "period": "monthly", "term": null}, "salary_visible": false, "title_keywords": ["assistant marketing manager", "senior marketing executive"], "responsibilities": ["trade marketing", "management", "identify business opportunities", "budget", "data analysis", "reports"], "requirements": {"degrees": ["degree holder"], "majors": ["business", "e-commerce"], "languages": ["english", "chinese"], "language_level": [], "hard_skills": ["business management", "e-commerce", "analysis", "fmcg industry", "acumen"], "soft_skills": ["focused", "resourceful", "responsible", "loyal", "business acumen"], "languages_combined": [{"language": "english", "language_level": []}, {"language": "chinese", "language_level": []}]}, "experience_required": {"duration": ["at least 8 years"], "field": ["management", "business", "e-commerce"]}}, {"job_id": "100003009048189", "location_code": "hk", "company": "ProJob21.com Limited", "job_title": "E-Commerce Manager, FMCG", "description": "Job Highlights\n\nFinTech + FreightTech solution - Pioneer in Asia\nMedical Benefits, Performance Bonus, 5-days work\nCreate our new era, create our culture together\n\nJob Description\n\nFreightAmigo- FreightTech + FinTech eMarketPlace\nEnergetic, Willing to Work with Technology\n\nJob Responsibilities:\n\n\nAnalysing customer\u2019s needs and suggest solutions before Implementing the agreed solutions (configuration & development);\nProject management - assists team leader to manage projects to ensure successful completion of project deliverables within the timeline;\nProvide external and internal users with functional assistance, e.g. deliver tailor-made trainings, system quality review and testing;\nCollaborate with \u00a0developers to execute specific customers' business requirements, as well as working with sales team in pre & post-sales;\nSupport the growth of our partner network;\u00a0\nPerform other ad-hoc projects and tasks as assigned; &\nLess experience will be considered as Assistant Business Analyst.\n\nJob Requirements:\n\nBachelor\u2019s Degree or above in any discipline is welcomed.\u00a0Candidates with Degree in Computer Science / Information Technology or equivalent will be an advantage;\n1 year or above related experience in software development related area, fresh grads are also welcome;\nStrong analytical skills and ability to use data to drive strategy;\nKnowledge in software development life cycle (SDLC) and agile development method;\nQA experience is an asset;\nGood knowledge and interested in mobile application and web page;\nGood communication and reporting skills in English and Chinese\nEnergetic, good team player, proactive and self-motivated; &\nEffective interpersonal, communications and problem solving skills\u00a0 \u00a0 \u00a0 \u00a0 \u00a0\u00a0\n\nLocation: Innocenter, Kowloon Tong (Next to Festival Walk)\n\nBenefits:\n\n5-day work week\nMedical Benefits\nPerformance Bonus\nFree flow of snacks and drinks\nEarly leave on festive days\nStaff Recreation Activity\n\nMore about\u00a0FreightAmigo:\n\n\nWebsite: www.freightamigo.com\nFacebook:\u00a0https://www.facebook.com/yourfreightamigo/\nTwitter:\u00a0https://twitter.com/freightamigo\nLinkedIn:\u00a0https://www.linkedin.com/company/freightamigo-services-limited\n\nInterested parties please send full resume with followings by clicking 'Apply Now'.\n\nExpected Salary\nDate of Availability\nAll Personal data collected will be used for recruitment purpose only.\n", "employment_types": ["Permanent"], "selling_points": [], "locations": ["Not Specified"], "categories": ["E-commerce", "Business Development", "Marketing - Brand / Product Management", "Product Management / Business Analyst"], "post_time": "2022-01-14T05:48:36Z", "salary": {"currency": null, "max": null, "min": null, "period": "monthly", "term": null}, "salary_visible": false, "title_keywords": ["manager"], "responsibilities": [], "requirements": {"degrees": [], "majors": [], "languages": [], "language_level": [], "hard_skills": [], "soft_skills": [], "languages_combined": []}, "experience_required": {"duration": [], "field": []}}, {"job_id": "100003009049952", "location_code": "hk", "company": "Merec Consulting", "job_title": "Assistant / Ecommerce Marketing Manager", "description": "Our client, a global E-Commerce business branding company, is now looking for an experienced candidate to join them.\n\nResponsibilities:\n\nHandle new product sourcing and new product launching\nAnalyze the market trend for hot products that is suitable on the E-Commerce platform\nWork with the product owner or manufacturers for product development including price, packing, layout\nCreate new product launching plan for each product and regularly review on engagement and conversion rate for improvement plan\nAdvise for the product owner or manufacturers for the launch and promotion schedules and details\n\nRequirements:\n\nDegree or Diploma in the relevant discipline\nMore than 2 years in E-Commerce sourcing and product launching experiences, preferably worked with manufacturer or product owner from different countries\nSolid achievement for sourcing and launching new product online\nStrong analytical and communication skills\nFluent in English and Mandarin\n\nFor a confidential discussion about this role please contact Clarence at 2185 6309.", "employment_types": ["Full Time"], "selling_points": ["New headcount", "360 Ecommerce Marketing exposure", "Attractive compensation with Performance bonus"], "locations": ["Not Specified"], "categories": ["Marketing / Public Relations", "Digital Marketing", "E-commerce", "Marketing - Brand / Product Management"], "post_time": "2022-01-14T09:29:34Z", "salary": {"currency": null, "max": null, "min": null, "period": "monthly", "term": null}, "salary_visible": false, "title_keywords": ["marketing manager", "assistant"], "responsibilities": ["schedules", "e-commerce platform", "review", "plan"], "requirements": {"degrees": ["diploma", "degree"], "majors": [], "languages": ["english", "mandarin"], "language_level": ["fluent"], "hard_skills": ["e-commerce"], "soft_skills": ["communication skills"], "languages_combined": [{"language": "english", "language_level": ["fluent"]}, {"language": "mandarin", "language_level": ["fluent"]}]}, "experience_required": {"duration": ["2 years"], "field": ["e-commerce"]}}, {"job_id": "100003009045586", "location_code": "hk", "company": "Silenus (Hong Kong) Limited", "job_title": "E-Commerce Sourcing Specialist / Buyer", "description": "We are looking for a Site Operations Specialist who will be a core member of the team and will work closely with different stakeholders to drive the entire consumer-facing e-commerce site experience, and ensure that the key KPIs for site operations are met and exceeded. This person will report to the Site Operations Manager.\n\nThe Job\n\nManage day-to-day operations of customer-facing O2O channels.\nCapable to gather data from platform dashboard, Google Analytics and the other areas that have an impact on the mobile app and using this information to understand the trends and the shift in consumers\u2019 behavior to make data-driven decisions that will drive more online sales.\nWork closely with commercial team and design team to prepare UX/UI design and materials including wireframing, mockup and rapid prototyping for mobile app\nAnalyze current user journey to understand motivation, expose pain points, issues and improvement opportunities.\nPartner with the internal stakeholders to implement periodical and seasonality campaigns.\nMonitor and report KPI achievements and post-campaign analysis for data-driven decision-making.\nThe Person\n\nMinimum 2 years of solid experience of e-commerce on the mobile app, preferably in Hong Kong\nCulture fit with the company is very important - must be able to embrace change, strive for innovation, and be results-driven\nComfortable working in a fast-paced, agile, collaborative and competitive team environment\nComfortable working cross cultures, especially with local HK, mainland Chinese culture, and MNC\u2019s in HK\nStrong analytical and problem-solving skills, is performance-driven and is well organized, hands-on and details oriented\nFamiliarity with UX/ UI management on apps\nHave experience and expertise in managing digital content (description) with local HK insight, best to have local market experience", "employment_types": ["Full Time", "Permanent"], "selling_points": ["Strong technical support for data tracking", "CEO with solid experience in E-Commerce sector", "Adaptive and flexible working environment"], "locations": ["Not Specified"], "categories": ["E-commerce", "Business Development", "Marketing - Brand / Product Management", "Product Management / Business Analyst"], "post_time": "2022-01-13T08:08:23Z", "salary": {"currency": "HKD", "max": 29999, "min": 20000, "period": "monthly", "term": null}, "salary_visible": true, "title_keywords": ["specialist"], "responsibilities": ["mobile app", "data", "analysis", "day-to-day operations", "monitor", "design", "ui", "report"], "requirements": {"degrees": [], "majors": [], "languages": ["chinese"], "language_level": [], "hard_skills": ["problem-solving skills", "mobile", "agile", "e-commerce"], "soft_skills": ["agile", "well organized", "collaborative", "hands-on", "problem-solving skills", "driven"], "languages_combined": [{"language": "chinese", "language_level": []}]}, "experience_required": {"duration": ["minimum 2 years"], "field": ["digital content", "e-commerce"]}}, {"job_id": "100003009042507", "location_code": "hk", "company": "Retail Technology (Hong Kong) Limited", "job_title": "Site Operations Specialist (E-commerce)", "description": "Our client is an International Crypto Exchange looking for a creative director to develop the best\u00a0campaign strategies to boost its image in the market.\n\nResponsibilities:\n\nDevelop an innovative and compelling brand voice and image strategy for new products\nWork cross-functionally in developing the best campaign strategy with peers\nContinuously improve the quality, craft, and standards of graphic design\nCommunicate and collaborate with cross-departmental staff on strategy direction\nSupervise the overall design process and provide guidance to designers when necessary\n\nRequirements:\n\nMinimum of 7 years of relevant experience in the Financial Technology Industry\nCandidates with less than 7 years of experience are considered as Senior Brand Designer\nBachelor\u2019s degree in Graphic Design, or any related disciplines\nExtensive portfolio with a track of previous work\u00a0(Compulsory upon application)\nStrong understanding of digital design, design software, motion graphics, and animation\nExperiences in leading and working with design, product, and creative departments\nExcellent command of English, Cantonese, and Mandarin\n_________________________________________________________________\nAll job openings are available on our website website:\u00a0www.matchtalent.com.hk", "employment_types": ["Full Time"], "selling_points": ["E-Commerce, O2O", "Site Operation", "Guarantee 13 months salary with performance bonus"], "locations": ["Tai Koo"], "categories": ["E-commerce", "Business Development", "Marketing - Brand / Product Management", "Others"], "post_time": "2022-01-12T07:49:00Z", "salary": {"currency": null, "max": null, "min": null, "period": "monthly", "term": null}, "salary_visible": false, "title_keywords": ["specialist", "operations"], "responsibilities": ["collaborate with", "graphic design", "quality", "developing", "design", "develop", "provide guidance"], "requirements": {"degrees": ["degree", "bachelor"], "majors": ["related disciplines", "graphic design"], "languages": ["cantonese", "english", "mandarin"], "language_level": ["excellent"], "hard_skills": ["graphics"], "soft_skills": ["creative", "extensive"], "languages_combined": [{"language": "cantonese", "language_level": ["excellent"]}, {"language": "english", "language_level": ["excellent"]}, {"language": "mandarin", "language_level": ["excellent"]}]}, "experience_required": {"duration": ["7 years", "minimum of 7 years"], "field": ["designer", "brand", "design", "relevant experience", "financial"]}}, {"job_id": "100003009044589", "location_code": "hk", "company": "Match Talent Limited", "job_title": "Head of Creative", "description": "What You Will Be Doing:\n\nWork with internal design team in the production of promotional materials including in-store POSM, print/digital ads, product catalogue, leaflets etc.\nFormulate a comprehensive marketing plan to increase awareness to drive penetration into our O2O shops and the conversion of customers through shops' promotional activities\nMeasure and analyze sales performance including actual sales through in each channel and identify key learning\nCollect market information to develop strategic plan\nGeneral/ad-hoc supports to new projects\n\nWho is our Right Fit:\n\nBachelor Degree in Marketing/ Communications/ e-Commence / e-Marketing or a related discipline\n0-3 years relevant experience in the field of CRM, digital advertising, or social media editing\nFresh Graduates are welcome\nFamiliar with data structure or data analysis is an advantage\nProactive, independent with excellent time management skills and ability to work under pressure\nStrong numerical sense, analytical and problem-solving skills\nCreative with strong marketing sense and business acumen\nProficient of both written and spoken English and Chinese\nGood command of MS PowerPoint & MS Excel\nCandidates with more experience will be considered as Marketing Officer\nImmediately available or short notice is an advantage", "employment_types": ["Full Time", "Permanent"], "selling_points": ["Creating innovative and compelling brand voice", "5-days working hours with WFH", "Strong creativity and managing design team"], "locations": ["Causeway Bay"], "categories": ["Design", "Graphics", "Web Designer", "E-commerce", "Marketing - Brand / Product Management"], "post_time": "2022-01-13T04:42:12Z", "salary": {"currency": null, "max": null, "min": null, "period": "monthly", "term": null}, "salary_visible": false, "title_keywords": ["creative"], "responsibilities": ["ad-hoc", "management", "market information", "advertising", "data", "leaflets", "sales performance", "design", "develop", "data analysis", "marketing plan", "promotional materials", "promotional activities", "plan", "social media editing", "catalogue", "work under pressure"], "requirements": {"degrees": ["degree", "bachelor"], "majors": ["marketing", "communications"], "languages": ["english", "chinese"], "language_level": ["proficient"], "hard_skills": ["analysis", "ms excel", "problem-solving skills", "ms powerpoint", "acumen"], "soft_skills": ["independent", "creative", "marketing sense", "time management skills", "comprehensive", "learning", "business acumen", "problem-solving skills", "proactive", "work under pressure"], "languages_combined": [{"language": "english", "language_level": ["proficient"]}, {"language": "chinese", "language_level": ["proficient"]}]}, "experience_required": {"duration": ["0-3 years"], "field": ["social media", "advertising", "marketing", "relevant experience", "digital", "editing"]}}, {"job_id": "100003009047272", "location_code": "hk", "company": "\u8a8c\u6717\u570b\u969b\u6709\u9650\u516c\u53f8", "job_title": "Sales Officer/ Purchase / Manager", "description": "JOIN OpenRice\u2026\u2026if you want to service our\n\n\u00a05 million App users with\n\n\u00a09 million pageviews per day in Hong Kong! \u00a0\n\nOpenRice\u00a0is seeking an energetic and passionate individual to join a dynamic and collaborative environment as part of sales\u00a0team.\n\nYou will be responsible for:\n\nPlan, formulate, pitch and implement promotion strategies to drive traffic, increase Voucher transactions and revenue\nExplore new digital channels for campaign, promotion and partnership opportunities\nBuild and maintain marketing partnership and network\nCollaborate with different stakeholders for optimization marketing campaigns, and support the execution of various marketing activities\nScan and content edit E-Commerce offer in order to optimize the revenue and profit\nTrack, review and analyze effectiveness of each campaign\u00a0\nClosely monitor daily, weekly voucher transactions, reactive tactic promotion immediately\nPerform ad-hoc tasks and projects as assigned\n\nYou should possess:\n\nUniversity graduate in E-Commerce, Marketing, Business Management or related disciplines\nAt least 3 years working experience in F&B e-commerce industry\nMature, self-motivated, aggressive, creative and good interpersonal skills\nFluent in both written and spoken Cantonese, English & Mandarin\nCandidates with less experience will be considered as Marketing Executive\n\nWe offer a competitive remuneration package including excellent career prospects to the right candidate. Interested parties please submit your detailed resume with expected salary and available date by clicking the Quick Apply button.\n\nAll personal information submitted by job applicants will be used for recruitment purposes and we reserve the rights to consider the applications for other positions in our Group.", "employment_types": ["Full Time"], "selling_points": ["5 day work", "Working location: Kwai Chung", "Minimum 3 years of relevant experience"], "locations": ["Kwai Hing"], "categories": ["E-commerce", "Marketing - Brand / Product Management"], "post_time": "2022-01-14T02:43:05Z", "salary": {"currency": null, "max": null, "min": null, "period": "monthly", "term": null}, "salary_visible": false, "title_keywords": ["sales officer", "manager"], "responsibilities": ["collaborate with", "management", "ad-hoc tasks", "review", "monitor", "transactions", "maintain", "sales team", "plan", "marketing campaigns"], "requirements": {"degrees": ["university graduate"], "majors": ["business", "related disciplines", "marketing", "e-commerce"], "languages": ["cantonese", "english", "mandarin"], "language_level": ["fluent"], "hard_skills": ["business management", "dynamic", "e-commerce"], "soft_skills": ["passionate", "self-motivated", "creative", "responsible", "collaborative", "mature", "dynamic", "interpersonal skills", "energetic"], "languages_combined": [{"language": "cantonese", "language_level": ["fluent"]}, {"language": "english", "language_level": ["fluent"]}, {"language": "mandarin", "language_level": ["fluent"]}]}, "experience_required": {"duration": ["at least 3 years"], "field": ["f&b", "marketing", "e-commerce"]}}, {"job_id": "100003009040545", "location_code": "hk", "company": "Soon Doong Yi (H.K.) Co. Limited", "job_title": "Senior/Digital Marketing Executive", "description": "Responsibilities:\n\nManage daily operations of online shop including generate & update website content\u00a0including product information, promotion, events and etc.\nMaking promotion plan each month based on data analysis (Mainly E-Commerce and assistant for retail shop)\nTrack online sales progress, traffic and click-through rate etc and provide analysis for management review and strategic planning\nMonitor the functionality of the online shops and to assure the timely logistic operation and delivery arrangement.\nPrepare analysis report on sales performance, inventory control and e-Commerce operation efficiency.\nResponsible for online shop stock controlling.\nCreating eCommer banner and product information visual by own\nMaintaining direct online platform (specially HKTV Mall) and WTC eStore\nHandling official WeChat account for branding.\nRequirements:\n\nNot less than 2 year\u00a0experiences\u00a0in digital and eCommerce solution, preferably in FMCG and retail industries.\nGood Knowledge in\u00a0online shop and e-marketplaces operation\nProficient with MS Office; Knowledge of Photoshop/ Illustrator/ Google Analytics/ Internet Technology\nGood Project management skill and independent handle multi-tasks to hit tight deadlines\nProficiency in English and Cantonese\nImmediate available is preferred\nFamiliar with\u00a0popular\u00a0social media\u00a0platform including WeChat\nWe offer competitive remuneration and attractive compensation package to the right candidate.\u00a0\n\n", "employment_types": ["Full Time"], "selling_points": ["New head count", "Formulate & execute digital marketing strategies", "Knowledge in social media & ditigal platforms"], "locations": ["Sheung Wan"], "categories": ["E-commerce", "Marketing - Brand / Product Management"], "post_time": "2022-01-12T02:45:05Z", "salary": {"currency": null, "max": null, "min": null, "period": "monthly", "term": null}, "salary_visible": false, "title_keywords": ["digital marketing executive"], "responsibilities": ["strategic planning", "maintaining", "analysis report", "sales performance", "analysis", "monitor", "website", "data analysis", "inventory control", "plan", "visual", "manage daily operations", "management review"], "requirements": {"degrees": [], "majors": [], "languages": ["cantonese", "english"], "language_level": ["proficiency"], "hard_skills": ["google analytics", "illustrator", "wechat", "project management", "ms office", "photoshop"], "soft_skills": ["independent", "multi-tasks", "project management skill"], "languages_combined": [{"language": "cantonese", "language_level": ["proficiency"]}, {"language": "english", "language_level": ["proficiency"]}]}, "experience_required": {"duration": ["2 year"], "field": ["ecommerce", "digital", "fmcg", "retail"]}}, {"job_id": "100003009040053", "location_code": "hk", "company": "Hong Kong Technology Venture Company Limited", "job_title": "Assistant Marketing Officer (O2O Shop)", "description": "The Job\n\nWe are looking for a\u00a0Senior Category Executive who will be a core member within the RTA team, will work closely with the Teams to drive the sales and competitiveness of item offerings on the site, and ensure that the key KPI\u2019s for sales and performance are met and exceeded. This person will report to the Merchandising Manager.\u00a0\n\nDrives and owns the sales & performance of certain categories on the platform, ensuring that the daily sales, repeat purchase, item competitiveness of the site are as excellent\nMonitor the real-time performance and make timely decisions to switch items/ price features to drive the best performance possible\nAble to pick and drive star hero products based on customer profile, seasonality, and other factors.\nDrive data-driven decisions, especially with leveraging analysis from past campaigns, data, and other factors to make the best decisions\nWorks closely with Ops team to do item forecasting & proper e-commerce packaging\nWorks hand in hand with the Site Operations team till ensure the site(s) operate excellently and look good\nKey KPI\u2019s owned: sales, the performance of promotions, customer ratings by product.\n\nThe Person\u00a0\n\nStrong analytical and problem-solving skills, performance-driven, and well-organized\nHands-on and details oriented. Knows how to read sales dashboards to make timely decisions to drive performance.\nExtremely results oriented and drive the team to get the best possible topline results at all times.\nVery strong familiarity with\u00a0HK local retail market and competitor pulse\nAnalytical and able to leverage data to make decisions, pre/ during/ post-campaign\nE-commerce experience is not a must, should have a passion and strong interest in the e-commerce field.\u00a0\nComfortable working in fast-paced, agile, collaborative, and competitive team environment.\nHas a good grasp of HK grocery market, the strong familiarity of local competitor offers (on and off)\nComfortable working across cultures (local HK, mainland Chinese, MNC\u2019s in HK).\nTeam player and able to manage different stakeholders well\nUniversity degree with at least 5 years of relevant experience in grocery retail in HK.", "employment_types": ["Full Time", "Permanent"], "selling_points": ["Fresh Graduates are welcome", "O2O shops marketing", "Young & Energetic team; Great career exposure"], "locations": ["Tseung Kwan O"], "categories": ["Marketing / Public Relations", "Marketing - General / Support", "E-commerce", "Marketing - Brand / Product Management"], "post_time": "2022-01-12T01:05:31Z", "salary": {"currency": null, "max": null, "min": null, "period": "monthly", "term": null}, "salary_visible": false, "title_keywords": ["assistant marketing officer"], "responsibilities": ["data", "operations", "analysis", "merchandising", "teams", "monitor", "purchase", "forecasting", "report"], "requirements": {"degrees": ["university degree"], "majors": [], "languages": ["chinese"], "language_level": [], "hard_skills": ["problem-solving skills", "make", "agile", "e-commerce"], "soft_skills": ["agile", "timely", "well-organized", "collaborative", "hands-on", "problem-solving skills", "team player", "driven"], "languages_combined": [{"language": "chinese", "language_level": []}]}, "experience_required": {"duration": ["at least 5 years"], "field": ["retail", "relevant experience", "e-commerce"]}}, {"job_id": "100003009042642", "location_code": "hk", "company": "Openrice Limited", "job_title": "Senior Marketing Executive", "description": "You can enjoy:\n\nYoung and energetic, happy\u00a0working environment\nCompetitive compensation and benefits!\nContemporary workplace, free drinks and chill out areas!\nProfessional training and career advancement opportunities!\nConvenient office location, around 10-15min. walk from Tsuen Wan MTR!\nFaster IT equipped workflow and passionate culture!\nCasual wear every Friday, TGIF!\nMarriage, Maternity and Birthday Leave!\nYear around staff events - hiking, BBQ, annual dinner, incentive etc.\nExclusive shopping discount! Red Wine / sparkling Sales for our people only!\n\nResponsibilities:\n\n-\u00a0Write Website Content, SEO, Blogs, and Ad Copy\n\n- Digital online marketing planning and execution for Internal Projects\n\n-\u00a0Develop content strategy across different channels\n\n- Manage major B2C e-commerce online platforms, e.g. list and update product listings, update price\n\n- Update the information of sales platform, social media platforms\n\nRequirements:\n\n- Academic qualification: diploma or above preferably in Marketing, Business Study / Business Administrative, English Language Studies or other related disciplines\n\n- Excellent reading and writing in Chinese & English\u00a0(DSE at least B or above),\u00a0Must be comfortable writing long-form content\n\n- Fresh Graduate with good academic background OR 2-3 year experience in eCommerce/IT/Marketing would be preferable\n\n- Proficient with MS Excel, Word & PowerPoint\n\n- Immediately available is preferred", "employment_types": ["Full Time", "Permanent"], "selling_points": ["Explore new digital channels for campaign", "Build and maintain marketing partnership", "3 years\u2019 relevant marketing experiences"], "locations": ["Quarry Bay"], "categories": ["Hospitality / F & B", "Food & Beverage", "Marketing / Public Relations", "Marketing - Marketing Communication", "E-commerce", "Marketing - Brand / Product Management"], "post_time": "2022-01-12T08:15:01Z", "salary": {"currency": null, "max": null, "min": null, "period": "monthly", "term": null}, "salary_visible": false, "title_keywords": ["senior marketing executive"], "responsibilities": [], "requirements": {"degrees": [], "majors": [], "languages": [], "language_level": [], "hard_skills": [], "soft_skills": [], "languages_combined": []}, "experience_required": {"duration": [], "field": []}}, {"job_id": "100003009040018", "location_code": "hk", "company": "Innisfree", "job_title": "Senior Ecommerce Officer (FMCG / Retail)", "description": "Responsibilities:\n\n\u00a0 \u00a0 \u00a0 \u00a0 \u00a0Handle and manage the daily operations of the company's e-commerce platform (own e-shop, HKTV mall, Big Big Shop etc) including but not limited to preparing eDM, content management, product listing, pricing, promotion, inventory update, customer service and order related issues\n\u00a0 \u00a0 \u00a0 \u00a0 \u00a0Drive sales, define and implement online sales strategy and traffic optimization\n\u00a0 \u00a0 \u00a0 \u00a0 \u00a0Analyze the online sales performance and roll out effective digital marketing activities and promotions to reach sales target\n\u00a0 \u00a0 \u00a0 \u00a0 \u00a0Manage e-commerce quality control and quality assurance initiatives\n\u00a0 \u00a0 \u00a0 \u00a0 \u00a0Work closely with various internal and external parties, including agency, marketing, graphic designers, system development team etc\n\u00a0 \u00a0 \u00a0 \u00a0 \u00a0Prepare sales, traffic, promotion reports and competitor analysis regularly\n\u00a0 \u00a0 \u00a0 \u00a0 \u00a0Ad hoc projects as required\u00a0\n\nRequirements:\n\n\u00a0 \u00a0 \u00a0 \u00a0 \u00a0Bachelor in e-Business/Digital Marketing / Communication or related disciplines;\n\u00a0 \u00a0 \u00a0 \u00a0 \u00a03 years or above in E-Commerce working experience\n\u00a0 \u00a0 \u00a0 \u00a0 \u00a0Creative, detail-oriented with creative and good analytical/reporting skills\n\u00a0 \u00a0 \u00a0 \u00a0 \u00a0Flexible with good communications skills\n\u00a0 \u00a0 \u00a0 \u00a0 \u00a0Good team player with strong sense of responsibility\n\u00a0 \u00a0 \u00a0 \u00a0 \u00a0Energetic, proactive, self-motivated, think out of the box and able to work fast-paced working environment\nGood command in English and Chinese\n\n\n\nA competitive package and promising career prospect will be offered to the right candidate. Interested parties please send detailed resume with expected salary and availability by clicking \"Apply Now\" to submit your application.\n\nThe personal data collected will be treated in strict confidence and used for recruitment-related purpose only. Applicants who are not invited for interview within\u00a04 weeks may consider their applications unsuccessful.\u00a0 All personal data of unsuccessful candidates will be destroyed after 6 months.", "employment_types": ["Full Time", "Contract"], "selling_points": [], "locations": ["Causeway Bay"], "categories": ["Marketing / Public Relations", "Marketing - Brand / Product Management", "E-commerce", "Business Development", "Marketing - Brand / Product Management"], "post_time": "2022-01-12T00:28:06Z", "salary": {"currency": null, "max": null, "min": null, "period": "monthly", "term": null}, "salary_visible": false, "title_keywords": ["ecommerce officer"], "responsibilities": ["e-shop", "inventory", "internal and external parties", "quality", "customer service", "product listing", "sales performance", "sales target", "prepare sales", "reports", "management", "edm", "daily operations", "digital marketing", "drive sales", "analysis", "ad hoc projects", "quality control", "e-commerce platform"], "requirements": {"degrees": ["bachelor"], "majors": ["related disciplines", "business", "digital marketing"], "languages": ["english", "chinese"], "language_level": ["good command"], "hard_skills": ["e-commerce"], "soft_skills": ["flexible", "good team player", "proactive", "self-motivated", "sense of responsibility", "detail-oriented", "communication", "energetic", "creative"], "languages_combined": [{"language": "english", "language_level": ["good command"]}, {"language": "chinese", "language_level": ["good command"]}]}, "experience_required": {"duration": ["3 years"], "field": ["e-commerce"]}}, {"job_id": "100003009041051", "location_code": "hk", "company": "Retail Technology (Hong Kong) Limited", "job_title": "Senior Buyer", "description": "My client is an international well-known beauty skincare brand. They are now looking for an Assistant Digital Marketing Manager to join their HK team.\n\nResponsibility\n\nAssist on the overall digital marketing strategy and plan the digital marketing initiative\nManage, develop digital and social media campaign and content to drive the online performance and achieve business targets\nManage marketing plan with omnichannel platform including own ecommerce site and marketplace platform\nExecute digital marketing activities including but not limited online paid media planning, content creation, social media campaign etc.\nAnalyze digital & social media data to provide strategic & actionable insights and optimize ROAS / ROI\n\nRequirement\n\nDegree holder in Marketing or related disciplines\nAt least 6 years of relevant experience in digital marketing, preferable in beauty / retail\nHands-on experience and digital marketing campaign management\nTeam player with excellent communication skill and\u00a0strong business acumen\nSpeaks fluent in English, Cantonese and Mandarin", "employment_types": ["Full Time"], "selling_points": ["Minimum 3 years of buying experience", "Experience in FMCG or grocery", "Guarantee 13 months salary with performance bonus"], "locations": ["Tai Koo"], "categories": ["Merchandising & Purchasing", "Procurement / Purchasing / Sourcing", "E-commerce", "Marketing - Brand / Product Management", "Supply Chain"], "post_time": "2022-01-12T03:22:59Z", "salary": {"currency": "HKD", "max": 34999, "min": 25000, "period": "monthly", "term": null}, "salary_visible": true, "title_keywords": [], "responsibilities": ["social media", "data", "develop", "marketing plan", "digital marketing", "plan", "planning"], "requirements": {"degrees": ["degree holder"], "majors": ["related disciplines", "marketing"], "languages": ["cantonese", "english", "mandarin"], "language_level": ["fluent"], "hard_skills": ["acumen"], "soft_skills": ["communication skill", "hands-on", "team player", "business acumen"], "languages_combined": [{"language": "cantonese", "language_level": ["fluent"]}, {"language": "english", "language_level": ["fluent"]}, {"language": "mandarin", "language_level": ["fluent"]}]}, "experience_required": {"duration": ["at least 6 years"], "field": ["management", "relevant experience", "beauty", "digital marketing", "retail"]}}, {"job_id": "100003009039825", "location_code": "hk", "company": "Brand Story Asia Limited", "job_title": "Marketing Project Executive (Digital Online Media, Content Copywriter)", "description": "Main Responsibilities:\n\nl Assist to manage the company online website and marketplaces\n\nl Create and manage social media content and help build online branding\n\nl Manage influencer marketing across multiple channels\n\nl Provide online customer service and manage communications with customers by responding to customer product and order inquiry\n\nl Responsible for daily ecommerce operation including product listing, pricing updates, websites content updates etc\n\nl Handle ad hoc tasks and provide regular reports.\n\nRequirements:\n\nDiploma or above in Marketing/Business/eCommerce or related disciplines;\n\nAt least 2 years experience in eCcommerce & social media platforms\n\nProficient in MS Office & internet skills\n\nStrong verbal & written communications skills.\n\nGood command of English and Chinese\n\nWilling to learn, proactive, result-driven and strong analytical skills\n\nWill start work\u00a0 after CNY 2022", "employment_types": ["Full Time", "Permanent"], "selling_points": ["Young and Energetic Working Environment", "Passionate and Visionary in Digital Marketing", "Attractive Package | Career Development"], "locations": ["Tsuen Wan Area"], "categories": ["Marketing / Public Relations", "Public Relations - Copy-writing", "E-commerce", "Marketing - Brand / Product Management", "Management", "Management Trainee"], "post_time": "2022-01-11T11:41:24Z", "salary": {"currency": null, "max": null, "min": null, "period": "monthly", "term": null}, "salary_visible": false, "title_keywords": ["copywriter", "project executive"], "responsibilities": ["communications with", "product listing", "ad hoc tasks", "website", "social media content", "reports", "online customer service"], "requirements": {"degrees": ["diploma or above"], "majors": ["business", "related disciplines", "ecommerce", "marketing"], "languages": ["english", "chinese"], "language_level": ["good command"], "hard_skills": ["analytical skills", "ms office"], "soft_skills": ["proactive", "willing to learn", "driven", "analytical skills"], "languages_combined": [{"language": "english", "language_level": ["good command"]}, {"language": "chinese", "language_level": ["good command"]}]}, "experience_required": {"duration": ["at least 2 years"], "field": ["social media"]}}, {"job_id": "100003009044815", "location_code": "hk", "company": "WilliamSELECT", "job_title": "Assistant Digital Marketing Manager - Retail / Beauty", "description": "This is an exciting opportunity for people passionate about sports, and looking to grow their career within a fast paced, dynamic and high growth company.\u00a0Along with the exposure, you will also closely be working with the Ecommerce, Marketing & Data teams, to guarantee users satisfaction and retention.\u00a0\n\n\nResponsibilities\nDefine the CRM strategy for the sports businesses in Decathlon Hong Kong, benchmark new channels and competitors\nDefine the action plan and execute with attention to details and efficiency, optimise CRM performance through testing\nIntroduce new CRM channels (SMS and Push notifications)\nWatch over the use of CRM and the 360 degrees marketing plan with all other channel owners (Website, Social Media, Offline) and raise the bar from planning to execution\nCoordinate with the Global Team the launch of new features and programs released locally (product recommendations, dynamic emails..)\nResponsible for all transactional & marketing emails\u00a0\nSupport the Ecommerce Team in building sport journeys and building CRM campaign strategies\nCollaborate with Data Team to improve segmentation and targeting strategies\nWork with Marketing and Sports Teams on brand interest building programs\nExperience & Requirements\nEnergetic and passionate about email marketing, user experience and sports\nSelf-starter, responsible and reliable with high standards and attention to details\nAddicted to challenges & learning and a great team player\nExperience: 3+ years\u2019 experience as a CRM Specialist management\u00a0\nCreative & Entrepreneurial Mindset: Aim to build the most attractive online sports retail platform to attract all sport lovers in Hong Kong and self-motivated to continuous improvement\nSalesforce knowledge is a plus\nWhat we offer\nCompetitive Salary Package including Monthly Bonus\nShareholding Plan\n15 days paid annual leaves\nSports Allowance and monthly sport outings\nMedical and Dental benefits\nEmployee Discount\nInternational Network", "employment_types": ["Full Time"], "selling_points": ["Digital Marketing, social media, communications", "Young & Friendly Culture", "13 Months + bonus"], "locations": ["Not Specified"], "categories": ["Media & Advertising", "Others", "Marketing / Public Relations", "Digital Marketing", "E-commerce", "Marketing - Brand / Product Management"], "post_time": "2022-01-13T06:23:52Z", "salary": {"currency": null, "max": null, "min": null, "period": "monthly", "term": null}, "salary_visible": false, "title_keywords": ["assistant digital marketing manager"], "responsibilities": ["collaborate with", "social media", "data", "coordinate with", "website", "teams", "testing", "marketing plan", "plan", "planning"], "requirements": {"degrees": [], "majors": [], "languages": [], "language_level": [], "hard_skills": ["plus", "salesforce"], "soft_skills": ["self-motivated", "creative", "responsible", "learning", "reliable", "attention to details", "team player", "energetic", "passionate about"], "languages_combined": []}, "experience_required": {"duration": ["3+ years"], "field": ["management", "marketing"]}}, {"job_id": "100003009035074", "location_code": "hk", "company": "Lifetrons International Limited", "job_title": "Marketing & Ecommerce Executive", "description": "Are you interested to join a team of eco- conscious and positive people working hard to make a change in the beauty industry?\u00a0\n\nAre you interested to be exposed to the Behind the scene marketing of the rising beauty and cosmetic industry and work for a sustainable brand that sell in Sephora, Amazon and all around the world?\n\nIf you are independent, proactive, highly motivated, willing to roll up your sleeves to get the job done then we have the perfect opportunity for you!\n\nWe are looking for an awesome full time marketing executive to work closely with our management, design and merchandising and\u00a0be fully part of our team to get things done, be creative, learn, and grow.\n\nJob Duties:\n\nCoordinate Marketing campaigns for abyssian\nLiaise with online/offline retail partners (Sephora, Lookfantastic, etc...)\nManage social media content creators\nMonitor our social media platforms\nHelp to plan and maintain Marketing budget\nWork with design team to produce visuals / packshots\n\nJob Requirements:\n\nDiploma or Degree holder preferably in marketing or business discipline\nAt least 2 years working experience\u00a0in Marketing in the Beauty industry is an advantage\nProficiency in MS Office Application, Word, Excel, PowerPoint and all social media platform\nExperience working in a foreign country or with foreign management is a plus.\nVery Good command of written and spoken English is a must , Cantonese or Mandarin is a plus.\nA Good personality, Positive attitude, able to work independently and under pressure with minimal supervision\nimmediately available is a plus\u00a0\n\nWe offer :\n\n- A fun working environment,\n- 5-days work,\n- flexible working hours,\n- MPF,\n- 13 month\n- Performance Bonus\n- 12 days annual leave,\n- All hongkong bank Holiday,\n- Free product incentive,\u00a0\n- Staff-Discount\n- A Good salary package to the right candidate.\u00a0\n-\u00a0And a job in a company who truly care about the planet.\n\nIf you wish to learn, grow and you're up for a challenge ...\nPlease send your full resume with expected salary\u00a0and availability via\u00a0the \u201cAPPLY\u201d button\u00a0", "employment_types": ["Full Time"], "selling_points": [], "locations": ["Tuen Mun Area"], "categories": ["E-commerce", "Marketing - Brand / Product Management"], "post_time": "2022-01-10T05:50:39Z", "salary": {"currency": null, "max": null, "min": null, "period": "monthly", "term": null}, "salary_visible": false, "title_keywords": ["ecommerce executive"], "responsibilities": ["social media platforms", "monitor", "budget", "design", "coordinate", "maintain", "social media content", "marketing campaigns", "plan", "liaise with"], "requirements": {"degrees": ["diploma", "degree holder"], "majors": ["business", "marketing"], "languages": ["cantonese", "english", "mandarin"], "language_level": ["good command"], "hard_skills": ["excel", "plus", "word", "powerpoint", "ms office"], "soft_skills": ["positive attitude", "work independently", "under pressure"], "languages_combined": [{"language": "cantonese", "language_level": ["good command"]}, {"language": "english", "language_level": ["good command"]}, {"language": "mandarin", "language_level": ["good command"]}]}, "experience_required": {"duration": ["at least 2 years"], "field": ["beauty industry", "marketing", "management"]}}, {"job_id": "100003009042006", "location_code": "hk", "company": "Decathlon Hong Kong Company Limited", "job_title": "CRM Specialist", "description": "Job Description\n\nResponsibilities:\n\n\u00a0\u00a0\u00a0\u00a0\u00a0\u00a0\u00a0\u00a0\u00a0Build and manage the new brand own e-shop and e-commerce activities for local market;\n\u00a0\u00a0\u00a0\u00a0\u00a0\u00a0\u00a0\u00a0\u00a0Oversee e-commerce platforms to achieve sales targets, enhance brand awareness and ensure high standard of customer services;\n\u00a0\u00a0\u00a0\u00a0\u00a0\u00a0\u00a0\u00a0\u00a0Manage daily operations of brand own e-shop, sales order monitoring, sales forecast, inventory planning, promotional arrangement and reports;\n\u00a0\u00a0\u00a0\u00a0\u00a0\u00a0\u00a0\u00a0\u00a0Formulate digital marketing plan to improve traffic and conversion rate;\n\u00a0\u00a0\u00a0\u00a0\u00a0\u00a0\u00a0\u00a0\u00a0Set the strategic direction, oversee and co-ordinate all e-commerce activities through different media;\n\u00a0\u00a0\u00a0\u00a0\u00a0\u00a0\u00a0\u00a0\u00a0Conduct market & competitor research to understand customer needs for enhancing customer shopping experience;\n\u00a0\u00a0\u00a0\u00a0\u00a0\u00a0\u00a0\u00a0\u00a0Collaborate with management team on corporate e-commerce strategies;\n\nRequirements:\n\n\u00a0\u00a0\u00a0\u00a0\u00a0\u00a0\u00a0\u00a0\u00a0Diploma or above in e-Commerce, Digital Marketing, Marketing, Business, IT or related disciplines;\n\u00a0\u00a0\u00a0\u00a0\u00a0\u00a0\u00a0\u00a0\u00a03 years relevant experience in retail e-Commerce / digital marketing portals;\n\u00a0\u00a0\u00a0\u00a0\u00a0\u00a0\u00a0\u00a0\u00a0Solid experience in building & managing on-line shop portals, digital campaigns and advertisement;\n\u00a0\u00a0\u00a0\u00a0\u00a0\u00a0\u00a0\u00a0\u00a0Experience in FMCG e-commerce and online channels is an advantage;\n\u00a0\u00a0\u00a0\u00a0\u00a0\u00a0\u00a0\u00a0\u00a0Strong business sense and analytical skills;\n\u00a0\u00a0\u00a0\u00a0\u00a0\u00a0\u00a0\u00a0\u00a0Excellent presentation and communication skills and able to work fast-paced working environment;\n\u00a0\u00a0\u00a0\u00a0\u00a0\u00a0\u00a0\u00a0\u00a0Well organized, positive and energetic, strong team player and ability to work independently;\n\u00a0\u00a0\u00a0\u00a0\u00a0\u00a0\u00a0\u00a0\u00a0Good command of both written and spoken English and Chinese;\n\u00a0\u00a0\u00a0\u00a0\u00a0\u00a0\u00a0\u00a0\u00a0More experience will be considered as Supervisor\nInterested candidates, please contact us at 28919882 for company details before applying.", "employment_types": ["Full Time", "Permanent"], "selling_points": ["Passionate about CRM & sports", "Amazing work culture!", "Monthly bonus, medical & dental benefits"], "locations": ["Mong Kok"], "categories": ["Marketing / Public Relations", "Marketing - Marketing Communication", "Digital Marketing", "E-commerce", "Marketing - Brand / Product Management"], "post_time": "2022-01-12T05:10:27Z", "salary": {"currency": null, "max": null, "min": null, "period": "monthly", "term": null}, "salary_visible": false, "title_keywords": ["specialist"], "responsibilities": ["understand customer needs", "collaborate with", "inventory planning", "management team", "e-shop", "monitoring", "e-commerce platforms", "e-commerce strategies", "customer services", "reports", "digital marketing", "forecast", "plan", "manage daily operations"], "requirements": {"degrees": ["diploma or above"], "majors": ["e-commerce", "related disciplines", "business", "marketing", "digital marketing", "it"], "languages": ["english", "chinese"], "language_level": ["good command"], "hard_skills": ["analytical skills", "e-commerce"], "soft_skills": ["communication skills", "work independently", "business sense", "well organized", "analytical skills", "team player", "energetic", "presentation", "positive"], "languages_combined": [{"language": "english", "language_level": ["good command"]}, {"language": "chinese", "language_level": ["good command"]}]}, "experience_required": {"duration": ["3 years"], "field": ["fmcg", "e-commerce", "digital marketing", "relevant experience", "digital", "advertisement", "retail"]}}, {"job_id": "100003009038717", "location_code": "hk", "company": "", "job_title": "E-Commerce Specialist/Supervisor", "description": "The Department\nThe Customer and International Business Development Division (C&I) is responsible for providing quality wagering experience to local and overseas customers of The Hong Kong Jockey Club. It operates 88 Race Meetings a year, 37 Simulcasts days, a thrice-weekly Mark 6 Draw, 7X24 Digital Channels, 7X24 Football Betting Services on over 11,000 different leagues per year. The ultimate aim is to provide an impressive total customer experience leading to sustainable turnover growth in a responsible manner.\nWith around 100 off-course betting branches (OCBB) and 2 racecourses, Retail and Telebet Services Department is committed to provide quality and efficient service to our customers throughout Hong Kong.\nGift at Races team (GAR) aims to be the premier retail in its field targeting both local and international Hong Kong racing fans.\u00a0\nThe Job\nYou will:\nPromote Gift at Races (GAR) as a branding vehicle and customer engagement tool to enhance public interest in racing and enhance experience of customers at Racecourse or other Jockey Club venues.\nDevise and implement effective marketing strategies to generate brand awareness, product sales, ROI and generate appropriate traffic.\nResponsible for Eshop business and operation to deliver the assigned KPIs and desirable user shopping experience on GaR eShop.\nWorks alongside all internal and external marketing channels to deliver consistent and relevant campaigns of our affiliate programs in GaR physical and online channels.\nRedesign the Digital Channel to optimize the opportunities through 020 strategy. Analyzing site traffic including click navigation, shopping patterns, and purchase conversion to drive sales in GaR online shop.\nEvaluate, create and update GaR online shop web content that include re-designing home and product pages to optimize campaign effectiveness and product sell-through.\nIdentifying the latest trends within the industry. Devise effective Omni-channel marketing strategy to attract and appeal to new customers; & retain loyal customers via effective eDM, joint promotion, PR, digital and social marketing strategy.\nOversee online store marketing communication and daily system operations. Administer online marketing campaign through proper coordination with management and outside agencies.\nDevelop press releases, message documents, prepare briefing materials and reports to support sales promotion through public relationships.\nCreates campaign objectives with Merchandising and Sales Operations and ensure these are met, evaluated and budgeted.\nEnsures that campaign calendars are kept up-to-date, reviewed regularly and optimized. Monitor progress of campaigns using various metrics; submits reports of performance reporting.\nPlans and works with designer, photographer and printer to prepare marketing materials (POSM, props, posters) for all GAR's POS.\nMaintain & co-ordinate visual marketing guidelines for shops to comply. Communicate with Sales & Operations team about upcoming POS drops, campaign launches and events.\nEnsures compliance with Responsible Gambling Policy and all stipulated legal requirements pertaining to wagering, thereby protecting the integrity of the Club's businesses.\nCoordinate with vendor for event booth set-up. Support on-course sales activities during major event meetings.\nUndertake other duties as assigned by line manager.\nAbout You\nYou should have:\nBachelor in Marketing or have managed sales/ marketing functions for online shops\nA minimum of 6 years' marketing experience, either in-house or agency\nAbility to work under pressure in a fast-paced environment\nExceptional personal time management\nExcellent communication and interpersonal skills\nGood command of both written and spoken English and Chinese\nStrong knowledge of both offline and online marketing strategies\nAbility to create socially-driven retail campaigns\nKnowledge in A.I. / Photoshop a plus\nBe agile and market/ online savvy to understand customer behavior and latest online sales trend to adopt best practices for GAR web shop.\nOccasionally working on race day as required\nTerms of employment\nThe level of appointment will be commensurate with qualification and experience.\n\n\nHow to Apply\nPlease send your resume, complete with expected salary and job reference by clicking the Apply Now button\n\n\nWe are an equal opportunity employer. Personal data provided by job applicants will be used strictly in accordance with the Club's notice to employees and prospective employees relating to the Personal Data (Privacy) Ordinance. A copy of which will be provided immediately upon request.", "employment_types": ["Full Time"], "selling_points": ["Digital Marketing", "Energetic team", "Good Collaboration"], "locations": ["Quarry Bay"], "categories": ["E-commerce", "Marketing - Brand / Product Management"], "post_time": "2022-01-11T07:43:24Z", "salary": {"currency": null, "max": null, "min": null, "period": "monthly", "term": null}, "salary_visible": false, "title_keywords": ["specialist", "supervisor"], "responsibilities": ["monitor progress", "operations", "coordination with", "quality", "merchandising", "communication", "purchase", "maintain", "designing", "plans", "personal data", "work under pressure", "other duties", "compliance", "develop", "reports", "visual", "kpis", "reporting", "management", "marketing strategies", "edm", "coordinate with", "drive sales", "prepare marketing materials", "communicate with", "sales activities", "online channels", "guidelines", "evaluate"], "requirements": {"degrees": ["bachelor"], "majors": ["marketing"], "languages": ["english", "chinese"], "language_level": ["good command"], "hard_skills": ["plus", "agile", "web", "pos", "vendor", "photoshop"], "soft_skills": ["efficient", "agile", "responsible", "fast-paced environment", "integrity", "communication", "committed", "communication and interpersonal skills", "coordination", "loyal", "time management", "driven", "work under pressure"], "languages_combined": [{"language": "english", "language_level": ["good command"]}, {"language": "chinese", "language_level": ["good command"]}]}, "experience_required": {"duration": ["minimum of 6 years"], "field": ["agency", "business development", "business", "operation", "marketing"]}}, {"job_id": "100003009044784", "location_code": "hk", "company": "The Hong Kong Jockey Club", "job_title": "Assistant eCommerce and Marketing Manager", "description": "The candidate will be working closely with our Dedicated Digital Team in one of the biggest e-Commerce service units for a top-tier enterprise client.\n\nTake your place in a top interactive agency where your input & ideas will always be treasured and start your entry into the exciting digital industry.\n\nResponsibilities\n\n\nRequired to work onsite at client office full time\nMaintain and update business portal\nMonitor and optimize the traffic performance of the website (e.g. SEO, SEM, eDM, keywords)\nSupport the planning, implementation and monitoring of corporate digital marketing campaigns\nAnalyse and track digital campaigns\u2019 performance and communicate with agencies to refine tactics to generate business results and outcomes\nKeep abreast of digital marketing and industry trend\nResponsible for monthly performance analytics and drawing insights\nSupport team manager in daily website operation and development\nRequirements\n\nBachelor\u2019s degree in marketing, digital or any relevant disciplines\nA minimum of 2 years\u2019 experience in digital marketing, website development, website tracking and data analysis or social media management (agency experience is a plus)\nProven experience in managing social media, SEO/SEM, and other performance campaigns\nGoogle Analytics, Google Ads, SEM/SEO, CRM experience will be an advantage\nGood understanding of the digital landscape of Hong Kong and China market\nStrategic mind-set and creative thinking\nProficient in Cantonese and English, verbal and written communications\nAbility to manage multiple priorities and meet deadlines in a fast-paced environment\nImmediately available is highly preferred\nApplicant is required to provide employment and salary record/expectation\nInterested parties click \"APPLY NOW\" to submit your application.\n\n\nPersonal data collected will be used for recruitment purpose only.", "employment_types": ["Full Time"], "selling_points": ["Responsible for Eshop business and operation", "A minimum of 6 years' marketing experience", "Knowledge in A.I. / Photoshop is a plus"], "locations": ["Causeway Bay"], "categories": ["Marketing / Public Relations", "Digital Marketing", "E-commerce", "Marketing - Brand / Product Management", "Others"], "post_time": "2022-01-13T06:15:30Z", "salary": {"currency": null, "max": null, "min": null, "period": null, "term": null}, "salary_visible": false, "title_keywords": ["marketing manager", "assistant"], "responsibilities": ["communicate with", "seo", "edm", "digital marketing campaigns", "monitoring", "monitor", "website", "implementation", "maintain", "digital marketing", "website operation", "sem", "analyse", "digital campaigns", "planning"], "requirements": {"degrees": ["degree", "bachelor"], "majors": ["marketing"], "languages": ["cantonese", "english"], "language_level": ["proficient"], "hard_skills": ["google analytics", "plus", "seo", "analysis", "sem"], "soft_skills": ["fast-paced environment", "meet deadlines", "creative"], "languages_combined": [{"language": "cantonese", "language_level": ["proficient"]}, {"language": "english", "language_level": ["proficient"]}]}, "experience_required": {"duration": ["minimum of 2 years"], "field": ["social media", "management", "agency", "development", "data analysis", "digital marketing"]}}, {"job_id": "100003009037906", "location_code": "hk", "company": "Mirum Hong Kong", "job_title": "Digital Marketing Executive", "description": "Are you interested to join a team of eco-conscious and positive people working hard to make a change in the beauty industry?\u00a0\nAre you interested to be exposed to the Behind the scene marketing of the rising beauty and cosmetic industry and work for a sustainable brand that sell in Sephora, LookFantastic.com and all around the world?\n\nIf you are independent, proactive, highly motivated, willing to roll up your sleeves to get the job done then we have the perfect opportunity for you!\nWe are looking for an awesome full time digital marketing executive to work closely with our management, design and merchandising and\u00a0be fully part of our team to get things done, be creative, learn, and grow.\n\n\n\nResponsibilities:\n\n\nExecute Facebook / IG paid ads campaigns for abyssian\nLiaise with influencers for collabs and content\nManage email marketing campaigns\nCoordinate with partner agency for SEO and Google ads\nMonitor campaigns efficacy\n\nRequirements:\n\n\nDiploma or Degree holder in Marketing or Business discipline\n2 years experience\u00a0in Digital Marketing. Beauty sector is a plus\nPositive attitude, sense of initiative, analytic skills\nEnglish is a must, Cantonese or Mandarin is a plus.\nForeign country or foreign manager experience is a plus\nWord, Excel, PowerPoint and social media platforms\nFast Availability preferred\n\n\nWe offer :\n- A fun working environment :)\n- 5-days work\n- flexible working hours\n- MPF\n- 13 month\n- Performance Bonus\n- 12 days annual leave\n- All hongkong bank Holiday\n- Free product incentive\n- Staff-Discount\n- A Good salary package to the right candidate\n-\u00a0And a meaningful job in a company who truly care about the planet.\n\nIf you want to grow,\u00a0 learn and you're up for a challenge ...\nPlease send your full resume with expected salary\u00a0and availability via\u00a0the \u201cAPPLY\u201d button\u00a0", "employment_types": ["Full Time", "Contract"], "selling_points": ["Digital performance marketing role", "Join a top Digital Agency & enterprise client team", "Great opportunity for career growth"], "locations": ["Wan Chai"], "categories": ["Professional Services", "Business Analysis / Data Analysis", "Marketing / Public Relations", "Digital Marketing", "E-commerce", "Marketing - Brand / Product Management"], "post_time": "2022-01-11T04:12:29Z", "salary": {"currency": null, "max": null, "min": null, "period": "monthly", "term": null}, "salary_visible": false, "title_keywords": ["digital marketing executive"], "responsibilities": ["seo", "coordinate with", "monitor", "marketing campaigns", "liaise with", "facebook"], "requirements": {"degrees": ["diploma", "degree holder"], "majors": ["business", "marketing"], "languages": ["cantonese", "english", "mandarin"], "language_level": [], "hard_skills": ["excel", "plus", "word", "powerpoint", "analytic skills"], "soft_skills": ["positive attitude", "initiative"], "languages_combined": [{"language": "cantonese", "language_level": []}, {"language": "english", "language_level": []}, {"language": "mandarin", "language_level": []}]}, "experience_required": {"duration": ["2 years"], "field": ["digital marketing"]}}, {"job_id": "100003009042971", "location_code": "hk", "company": "SIM Design Ltd", "job_title": "Assistant Marketing & Sales Executive (Retail & Wholesale)", "description": "Responsibilities:\n\nTo develop and implement a marketing plan to achieve the business objectives.\u00a0\nTo plan and control the annual marketing budget.\nTo drive brand growth through different marketing programs by management, maintenance and execution.\nTo maintain effective communications with overseas business partners to implement local advertising and promotion activities.\nTo create and prepare a wide range of the marketing collaterals and work closely with design team and production agencies.\nTo develop the eCommerce and digital marketing strategies.\nTo liaise with PR and media agency.\nTo organize the overseas and local trade show.\nOccasional travelling will be required.\n\nRequirements:\n\nUniversity graduate preferably in marketing, business or related disciplines\nMinimum 5 years of marketing experience with at least 1 year at supervisory or managerial level, preferably with exposure in fashion brands or FMCG industry.\nExtensive network in PR & marketing support, sound skills in both traditional marketing and e-marketing strategies and tactics\nEffective interpersonal and communication skills and a good team player\nCreative, self-motivated with high degree of ownership and able to work under high pressure\nHands-on marketing campaign skills and experience\nGood command of written and spoken English, Chinese and Mandarin\nGood presentation and computer skills\n\nWe offer attractive remuneration and excellent career prospects to the right candidates. Interested and qualified parties please send\u00a0full resume including current salary, expected salary and availability\u00a0to The Group Human Resources Department via\u00a0JobsDB:\"Apply Now\".\n\nThe information provided will be kept confidential and used for recruitment purposes only. Applicants not contacted within three months may consider their applications unsuccessful. The company will retain all applications for a maximum of six months.", "employment_types": ["Full Time", "Permanent"], "selling_points": ["Up and coming concept brand for stylish moms", "Startup project team in an established corporation", "Disruptor culture"], "locations": ["Sheung Wan"], "categories": ["E-commerce", "Business Development", "Marketing - Brand / Product Management", "Supply Chain"], "post_time": "2022-01-12T09:21:38Z", "salary": {"currency": null, "max": null, "min": null, "period": "monthly", "term": null}, "salary_visible": false, "title_keywords": ["marketing & sales executive", "assistant"], "responsibilities": ["control", "management", "communications with", "advertising", "maintenance", "digital marketing strategies", "budget", "marketing collaterals", "design", "develop", "marketing plan", "maintain", "plan", "liaise with"], "requirements": {"degrees": ["university graduate", "degree"], "majors": ["business", "related disciplines", "marketing"], "languages": ["english", "chinese", "mandarin"], "language_level": ["good command"], "hard_skills": ["fmcg industry", "computer skills"], "soft_skills": ["communication skills", "good team player", "self-motivated", "presentation", "hands-on", "work under high pressure", "creative", "extensive", "interpersonal"], "languages_combined": [{"language": "english", "language_level": ["good command"]}, {"language": "chinese", "language_level": ["good command"]}, {"language": "mandarin", "language_level": ["good command"]}]}, "experience_required": {"duration": ["at least 1 year", "minimum 5 years"], "field": ["managerial", "supervisory", "marketing", "fmcg"]}}, {"job_id": "100003009040855", "location_code": "hk", "company": "101 Studio Limited", "job_title": "Marketing Manager", "description": "Job Responsibility:\u00a0\n\nAssist in executive of all digital marketing and social media projects, display advertising Facebook, Instagram, YouTube, Linkedin etc. and arising channels\nAssist in the new product introduction into market for dedicated products\nComplete marketing affairs independently like online and offline marketing event organization, product registration, marketing material preparation, etc.\nObserve and share latest market information and trends\nCollect market information in the field independently\n\nRequirements:\n\nDiploma or above\u00a0is required. Business or science background is preferred.\nKnowledge in Photoshop or Illustrator is preferred\u00a0\nKnowledge in media and internet marketing experience\n\u00a0Ability to work independently and under pressure\n\u00a0Good technical skills and communication skills, customer oriented\n\u00a0Result-oriented, aggressive and good presentation\n\u00a0Fluent conversational and written English & Cantonese\nOrganize and attend local and oversea exhibition and workshops\n1-2 year related work experience is required.\n\nInterested parties, please send detailed resume with expected salary to HR Department, Medisource Supply (Asia) Co. Ltd.\u00a0", "employment_types": ["Full Time", "Permanent"], "selling_points": ["5-day work, HK listed Co., luxury eyewear brands", "Min. 5 ys of mkt exp. (at least 1 yr at mgt lv)", "Traditional marketing and e-marketing"], "locations": ["Kwun Tong"], "categories": ["Marketing / Public Relations", "Management", "Marketing - Brand / Product Management", "E-commerce", "Marketing - Brand / Product Management"], "post_time": "2022-01-12T03:09:15Z", "salary": {"currency": null, "max": null, "min": null, "period": "monthly", "term": null}, "salary_visible": false, "title_keywords": ["marketing manager"], "responsibilities": ["social media", "market information", "advertising", "digital marketing", "facebook", "marketing material"], "requirements": {"degrees": ["diploma or above"], "majors": [], "languages": ["cantonese", "english"], "language_level": ["conversational", "fluent"], "hard_skills": ["workshops", "illustrator", "photoshop"], "soft_skills": ["communication skills", "work independently", "under pressure", "presentation", "technical skills", "result-oriented"], "languages_combined": [{"language": "cantonese", "language_level": ["conversational", "fluent"]}, {"language": "english", "language_level": ["conversational", "fluent"]}]}, "experience_required": {"duration": ["1-2 year"], "field": ["related", "marketing", "media"]}}, {"job_id": "100003009042590", "location_code": "hk", "company": "ESD Services Limited (ESDlife)", "job_title": "eCommerce Executive", "description": "Responsibilities:\n- Follow-up quotation and handle customer enquiries\n- To maintain relationship with existing customers for local and overseas.\n- Solid experience in liaise with wholesale overseas customers would be an advantage\n- Knowledge\u00a0of Mobile phone and Branded Goods wholesale trading oversea and local in Hong Kong\n- Able to manage the operation with E-commerce client for their Daily business.\n- Develop new business and the potential channel growth with strong Business sense\n\nRequirements:\n- DSE or above and Must have 3 years or above of working experience in wholesale trading or E-commerce Industry consumer branded electronic industry dealing (Smartphone, Camera, Speaker, Bluetooth, consumer product, IT hardware product, knowledge in FMGC Brand will be consider\n- Develop Business with online seller Around the world and develop with marketplace in Asia & Europe\n- Strong communication, interpersonal and problem solving skills\n- Proficient in MS Word, Excel and Chinese Word Processing is a MUST - Fluency in both written and spoken English and Mandarin Chinese is essential\n\nBasic format:\n- Bank Holiday\n- 5 days work\n- Double Pay\n- Year End Bonus\n- Basic Salary + Commission Plan\n- We offer high motivate plan for individual to grow in personal level & business level\n- 10 Days Annual Leave maximum 18 days\n\nCompany Overview:\nBrandSky International Limited is Hong Kong based Company. BrandSky Management had Experience in Electronic Industry more than 10 years in Business and Add up with Partner knowledge of FMGC Business Also 8 years. Brandsky working with Small Team with crore Business development skills. Key trade in product are brands from Apple, Asus, Beats, Bose, Braun, Canon, Casio, Dji, Garmin, GoPro, HTC, Huawei, Jawbone, JBL, Lenovo, LG, Meizu, Microsoft, Motorola, Nikon, Nestle, Rolex, Samsung, Sony, Xaiomi, ZTE\u2026..\n\n\n\n", "employment_types": ["Full Time", "Permanent"], "selling_points": [], "locations": ["Hung Hom"], "categories": ["Marketing / Public Relations", "Marketing - Direct Marketing", "E-commerce", "Marketing - Brand / Product Management", "Sales, CS & Business Devpt", "Sales Administration"], "post_time": "2022-01-12T08:06:02Z", "salary": {"currency": null, "max": null, "min": null, "period": "monthly", "term": null}, "salary_visible": false, "title_keywords": ["ecommerce executive"], "responsibilities": ["develop new business", "handle customer enquiries", "quotation", "maintain", "liaise with"], "requirements": {"degrees": ["dse"], "majors": ["it", "e-commerce"], "languages": ["mandarin chinese", "english", "chinese"], "language_level": ["fluency", "proficient"], "hard_skills": ["excel", "chinese word processing", "basic", "e-commerce", "hardware", "problem solving skills", "ms word"], "soft_skills": ["communication", "problem solving skills", "interpersonal"], "languages_combined": [{"language": "mandarin chinese", "language_level": ["fluency", "proficient"]}, {"language": "english", "language_level": ["fluency", "proficient"]}, {"language": "chinese", "language_level": ["fluency", "proficient"]}]}, "experience_required": {"duration": ["3 years"], "field": ["brand", "consumer product", "e-commerce", "it", "trading"]}}, {"job_id": "100003009038190", "location_code": "hk", "company": "Lauris Walton International Limited", "job_title": "Social Media Executive", "description": "Job Description:\nManage engaging, creative, innovative content for regularly scheduled digital posts including corporate website, social media platforms (i.e. Facebook, IG, etc)\nBe responsible for handling Google Ads / Facebook Ads / Instagram Ads.\nDevelop and execute digital marketing strategies to improve campaign performance and achieve campaign goals\nHandle marketing CRM tools and develop loyalty marketing campaign\u00a0\nHandle and follow up online customer service\n\n\u00a0Requirements\n\nDegree holder in Marketing, e-Commerce, Business Administration or any related discipline\nGood knowledge in digital marketing technology and platforms, including analytics, social and advertising technology; with hands-on exposure in SEM, SEO and data analytics;\nKnowledge in other web analytics tools (eg, Google Ads, Google Analytics, etc) will be a plus;\nSelf-motivated, adaptive and flexible, and able to work independently\nFluent in written and spoken English & Chinese", "employment_types": ["Full Time", "Permanent"], "selling_points": [], "locations": ["Not Specified"], "categories": ["Media & Advertising", "Strategic Planning", "Marketing / Public Relations", "Digital Marketing", "E-commerce", "Marketing - Brand / Product Management"], "post_time": "2022-01-11T05:58:25Z", "salary": {"currency": null, "max": null, "min": null, "period": "monthly", "term": null}, "salary_visible": false, "title_keywords": ["social media executive"], "responsibilities": ["digital marketing strategies", "social media platforms", "website", "develop", "online customer service", "facebook"], "requirements": {"degrees": ["degree holder"], "majors": ["marketing", "business administration", "e-commerce"], "languages": ["english", "chinese"], "language_level": ["fluent"], "hard_skills": ["google analytics", "plus", "seo", "e-commerce", "data analytics", "sem", "web analytics"], "soft_skills": ["flexible", "work independently", "self-motivated", "hands-on", "web analytics"], "languages_combined": [{"language": "english", "language_level": ["fluent"]}, {"language": "chinese", "language_level": ["fluent"]}]}, "experience_required": {"duration": [], "field": []}}, {"job_id": "100003009040508", "location_code": "hk", "company": "101 Studio Limited", "job_title": "Brand Officer", "description": "Lauris Walton\u00ae is a global recruitment specialist in the digital marketing & e-commerce industry. We\u2019re currently partnering with a fast-growing global online platform to seek a Social Media Executive for their online e-commerce platform. This position will play a key role in driving Digital Marketing campaign strategy and performing analysis to continuously refine and achieve maximum business results.\n\nKey Responsibilities:\n\n\nManage the day-to-day handling of all social media channels such as Facebook, Instagram, and LinkedIn\nDevelop, plan, and deliver content across different platforms\nMonitor, track, analyze performance on social media platforms\nCollaborate with the team to ideate and execute design projects\nIncorporate current trends in developing social media content that will result in increased traffic on social media platforms\nCarry out a high level of organization, professionalism, and attention to detail\n\nRequirements:\n\n\nDiploma holder or above in Communication, Business, Marketing or related field\n1-2 years of solid experience in marketing, e-commerce, or retail is highly preferred\nExcellent written and verbal skills in English and Chinese\nKnowledge of Photoshop, Illustrator, InDesign, Canva, and Premiere\nExperience in online marketing and has a good understanding of major marketing channels\nWell organized, detail-minded, tech-savvy, positive attitude, and willing to learn\nInterested candidates, please get in touch with us for a confidential discussion. For more job openings in Digital Marketing & E-commerce industry, please visit our website at www.lauriswalton.com.\n", "employment_types": ["Full Time", "Permanent"], "selling_points": ["Product development strategies and execution", "Formulating luxury eyewear brand strategies", "5-day work, HK listed Co., with regional exposure"], "locations": ["Kwun Tong"], "categories": ["Marketing / Public Relations", "Marketing - Brand / Product Management", "Marketing - Market Research", "E-commerce", "Marketing - Brand / Product Management"], "post_time": "2022-01-12T02:41:50Z", "salary": {"currency": null, "max": null, "min": null, "period": "monthly", "term": null}, "salary_visible": false, "title_keywords": ["officer"], "responsibilities": ["collaborate with", "social media", "social media platforms", "monitor", "developing", "design", "develop", "social media content", "plan", "facebook"], "requirements": {"degrees": ["diploma holder"], "majors": ["business", "marketing"], "languages": ["english", "chinese"], "language_level": ["excellent"], "hard_skills": ["e-commerce", "indesign", "illustrator", "premiere", "photoshop"], "soft_skills": ["detail-minded", "willing to learn", "well organized", "communication", "positive attitude"], "languages_combined": [{"language": "english", "language_level": ["excellent"]}, {"language": "chinese", "language_level": ["excellent"]}]}, "experience_required": {"duration": ["1-2 years"], "field": ["marketing", "retail", "e-commerce"]}}, {"job_id": "100003009035859", "location_code": "hk", "company": "VTech Telecommunications Limited", "job_title": "Digital Marketing Officer (VTT265/J06)", "description": "Responsibilities:\n\nDevelop and execute digital marketing promotion & campaign in website and other digital platforms according to company\u2019s guidelines;\nPropose and develop creative ideas that resonate with the target audience for different products & campaigns;\nPrepare creative and write-up for content marketing/ online promotion/ digital campaign;\nManage all information and product description in website and of the US wholesalers or any promotional channels;\nImplement and coordinate with team members in copy-writing and video production projects and script-writing;\nHandle customer enquiries via digital/eCommerce platforms;\nManage and Monitor project progress, from planning to execution, from copywriting to creating visual assets;\nAssist in ad-hoc marketing project\n\nRequirements:\n\nBachelor Degree holder or above in Communications, Marketing or other related disciplines;\nMinimum 3 years relevant experience in digital marketing;\u00a0\nExperience in eCommerce platform operations and website maintenance is preferable;\nPrevious experience with eCommerce marketing such as Amazon is desirable;\nSharp marketing sense, able to multi-tasking and good time-management;\nStrong interpersonal and communication skills and attentive to details;\n\nSelf motivated with ability to undertake independent initiatives;\nExcellent writing and communication skills and good command of both spoken and written English and Chinese (including Cantonese and Mandarin);\nImmediately available is preferred", "employment_types": ["Full Time", "Permanent"], "selling_points": ["Prepare creative & write-up content mkg/ campaign", "3+ yrs experiences in digital marketing, eCommerce", "5-day work, flexible working hour, double pay"], "locations": ["Tai Po Area"], "categories": ["Marketing / Public Relations", "Digital Marketing", "E-commerce", "Marketing - Brand / Product Management"], "post_time": "2022-01-10T08:34:28Z", "salary": {"currency": null, "max": null, "min": null, "period": "monthly", "term": null}, "salary_visible": false, "title_keywords": ["digital marketing officer"], "responsibilities": ["ad-hoc", "handle customer enquiries", "monitor project progress", "guidelines", "video production", "coordinate with", "website", "develop", "planning", "digital marketing", "visual", "develop creative ideas", "online promotion"], "requirements": {"degrees": ["bachelor degree holder"], "majors": ["related disciplines", "marketing", "communications"], "languages": ["cantonese", "english", "chinese", "mandarin"], "language_level": ["excellent", "good command"], "hard_skills": ["amazon", "maintenance"], "soft_skills": ["communication skills", "marketing sense", "independent", "attentive to details", "self motivated", "multi-tasking", "interpersonal"], "languages_combined": [{"language": "cantonese", "language_level": ["excellent", "good command"]}, {"language": "english", "language_level": ["excellent", "good command"]}, {"language": "chinese", "language_level": ["excellent", "good command"]}, {"language": "mandarin", "language_level": ["excellent", "good command"]}]}, "experience_required": {"duration": ["minimum 3 years"], "field": ["ecommerce", "maintenance", "marketing", "relevant experience", "digital marketing"]}}, {"job_id": "100003009034072", "location_code": "hk", "company": "Stylevana", "job_title": "Online Business Executive /  Assistant -  Fashion & Beauty", "description": "Hi there, thanks for your interest in Manta Lab Limited.\u00a0\n\nOur company started out producing collectible physical media products for studios like Warner Brothers, DCcomics, Fox Studio and Marvel Studio in 2015 and our company became the Exclusive Licensee for Warner Brothers Home Video in 2019.\u00a0\u00a0\n\nIn 2022 Jan, we are waiting to sign the final contract for the consumer product license with\u00a0Warner Brothers/DC comics\u00a0and we are looking for more staff to help to build our company.\n\nAt the moment, our company is needs a hard working eCommerce executive who has basic knowledge and skills of eCommerce.\u00a0\n\nBelow are the skills and traits we look from an eCommerce Executive\n\n- Enjoys watching movies and have good knowledge of movies\n- Speaks fluent English,and Cantonese\n- Knowledge of managing eCommerce platforms.\u00a0\n- Knowledge of managing Social Media\u00a0\n- Hard working and want to develop career quickly\n\nBelow are what you will do as an eCommerce Executive in the beginning\n\n- Customer service via emails and chats\n- Assist with packing daily orders\u00a0\n- Manage social media and websites\u00a0\n- Light inventory management\n\nIf you have above qualities, don't hesitate to contact us and show us what you have done and what you could do for our company. We are hoping to receive portfolio with your Resume at the same time. We will not consider any application without portfolio.\u00a0\n\nAgain, thank you for your interest in this position at Manta Lab.\u00a0\n\nWe are an equal opportunity employer and welcome applications from all qualified candidates. The information provided will be treated in strictly confidential and used only for consideration of application for relevant/similar post(s) within the Company.\n\n\nIf you are interested in this position, please Click \"Apply Now\" below and submit your CV with\u00a0portfolio and\u00a0expected salary to us.\n\n\nPersonal data collected will be used for recruitment purpose only.", "employment_types": ["Full Time", "Permanent"], "selling_points": ["eCom - Korean Beauty (sales, website traffic)", "eCommerce operations, Google Adwords", "5-day work, Double Pay, friendly team"], "locations": ["Kwai Hing"], "categories": ["Sales, CS & Business Devpt", "Sales - Sales Management", "Marketing / Public Relations", "Digital Marketing", "E-commerce", "Marketing - Brand / Product Management"], "post_time": "2022-01-10T02:35:31Z", "salary": {"currency": null, "max": null, "min": null, "period": "monthly", "term": null}, "salary_visible": false, "title_keywords": ["business executive", "assistant"], "responsibilities": ["social media", "develop", "inventory management", "daily orders", "customer service", "recruitment", "contact", "personal data"], "requirements": {"degrees": [], "majors": [], "languages": ["cantonese", "english"], "language_level": ["fluent"], "hard_skills": ["dc", "basic"], "soft_skills": ["interested in", "hard working", "customer service"], "languages_combined": [{"language": "cantonese", "language_level": ["fluent"]}, {"language": "english", "language_level": ["fluent"]}]}, "experience_required": {"duration": [], "field": []}}, {"job_id": "100003009036417", "location_code": "hk", "company": "Manta Lab Limited", "job_title": "eCommerce Executive", "description": "MARKETING & CREATIVE EXECUTIVE\n\nCreative and Marketing Executive is expected to support the e-commerce and marketing activities of the Company.\n\nKey Responsibilities\nConceptualize creative based on requirements and create artworks for brand collaterals and marketing campaigns\nDevelop interesting social media feed visuals to encourage engagement\nAdhere to brand guidelines, best practices and standards and complete projects according to the deadline\nProofread and align localized content for different markets\nScreen and identify targeted channels for Online marketing opportunities\nAbility to shoot and edit video is a plus\nRequirements\nHong Kong permanent resident status\nHolder of a higher Diploma or above in Graphic/Multimedia or related discipline\nMinimum 2 years working experience in e-Commerce, Graphic, Multimedia with in-house corporate\nExperience in campaign development, digital marketing and social content development\nExperience working in the travel industry is also a plus\nProficient in oral and written English and Chinese\nProficient in MS Office applications and Chinese word processing\nExcellent organisational and multi-tasking ability\nA team player with strong interpersonal and communication skills\nIndependent, self-motivated and able to work under pressure\nFully COVID-19 vaccinated, consideration will be given to those who are unable to get vaccinated for valid medical reasons\nCandidates with less experience may be considered as Assistant Officer\n\u00a0\nWe offer a competitive compensation package to the successful candidate. Interested parties, please click \u201cApply Now\u201d to submit your application\u00a0no later than 25 January 2022.\n\u00a0\n\nGreater Bay Airlines is an Equal Opportunities employer. Personal data provided by job applicants will be used strictly in accordance with our personal data policy and for recruitment purposes only. Our Personal Information Collection Statement will be available upon your online application. Applicants not being notified within 8 weeks may consider their application unsuccessful. Their personal data will be retained for a period of 12 months from the application date and will be destroyed thereafter.", "employment_types": ["Full Time", "Permanent"], "selling_points": [], "locations": ["Kwun Tong"], "categories": ["E-commerce", "Business Development", "Marketing - Brand / Product Management", "Supply Chain"], "post_time": "2022-01-10T10:22:17Z", "salary": {"currency": null, "max": null, "min": null, "period": "monthly", "term": null}, "salary_visible": false, "title_keywords": ["ecommerce executive"], "responsibilities": ["social media", "brand guidelines", "marketing campaigns", "develop"], "requirements": {"degrees": ["higher diploma or above"], "majors": [], "languages": ["english", "chinese"], "language_level": ["proficient"], "hard_skills": ["plus", "chinese word processing", "e-commerce", "multimedia", "ms office"], "soft_skills": ["communication skills", "oral", "self-motivated", "independent", "multi-tasking", "team player", "interpersonal", "work under pressure"], "languages_combined": [{"language": "english", "language_level": ["proficient"]}, {"language": "chinese", "language_level": ["proficient"]}]}, "experience_required": {"duration": ["minimum 2 years"], "field": ["content development", "e-commerce", "development", "graphic", "digital marketing"]}}, {"job_id": "100003009036086", "location_code": "hk", "company": "Greater Bay Airlines Company Limited", "job_title": "MARKETING & CREATIVE EXECUTIVE", "description": "\"Thanks\" from Friends and Cash from Us\nInspire your friend for career breakthrough and reward yourself with HK$ 3,000 or up cash incentive. Talent referral can never be more easier than simply clicking the \"sharing\" button and spread it out via social media channel. Visit our\u00a0candidate referral page\u00a0for further details.\n\n\nMNC Company\nFlexible Working hours\nCollaborate with a strong, dynamic team\n\nAbout Our Client\nOur client is a MNC by using technologies to help their clients to boost up performances. They share a believe on growing with their clients. Due to their upcoming aggressive expansion plan, they are now looking for a strategic and passionate Digital Marketing - Assistant Manager to join them.\n\nJob Description\nBe on the cutting edge of SEO, finding new strategies to implement on behalf of our clients to drive their organic traffic\nDeveloping and implementing effective SEO strategies for the improvement of organic traffic and search ranking and the maximization of ROI\nWell versed in preparing SEO reports on a fortnightly and monthly basis to be shared with client and identifying areas for improvement\nMonitor and analyze SEO statistics such as redirects, click rate, bounce rate, and more.\nCollaborate with other stakeholders including Content team to ensure smooth execution.\nWork with web developers, content strategists, and web designers, to build a scalable and SEO-friendly website.\nRequirement\n3-5+ years working experience in Search Engine Optimization or online marketing or digital agency.\nMinimum of 2-3 years relevant, hands-on SEO experience \u2013 not just creating documentation for developers to implement\nExperience using SEO tools such as SEMRush, Ahrefs, Google Search Console, Botify or Search Metrics.\nFamiliar with Google algorithm, search ranking technology and principles\nExperiences in Technical SEO and Link buildling is a must\n\nRemuneration\nThis is an excellent opportunity to join a company with interest in new technology and multicultural environment. Our client offers an attractive salary and excellent career progression path.\n\nInterested parties please send your full resume to cv @mclarenconsultancy.com. Successful applicants will be contacted within 2 working days.", "employment_types": ["Full Time", "Permanent"], "selling_points": ["Create artwork for branding/marketing campaigns", "Develop social media feed visuals", "2 years\u2019 working experience in e-Commerce"], "locations": ["Lantau Island"], "categories": ["Marketing / Public Relations", "Marketing - Marketing Communication", "Digital Marketing", "E-commerce", "Marketing - Brand / Product Management"], "post_time": "2022-01-10T16:52:45Z", "salary": {"currency": null, "max": null, "min": null, "period": "monthly", "term": null}, "salary_visible": false, "title_keywords": ["creative", "executive"], "responsibilities": ["collaborate with", "seo", "monitor", "developing", "website", "reports"], "requirements": {"degrees": [], "majors": [], "languages": [], "language_level": [], "hard_skills": ["documentation", "seo"], "soft_skills": ["hands-on"], "languages_combined": []}, "experience_required": {"duration": ["minimum of 2-3 years", "5+ years"], "field": ["agency", "digital", "marketing"]}}, {"job_id": "100003009041627", "location_code": "hk", "company": "Mclaren Consultancy Limited", "job_title": "SEO Specialist (Senior) -", "description": "Job Description\n\n\nProvide full support on marketing events and campaigns, promotion, and online materials update etc\nConduct market research and identify market opportunities\nManage and update the contents on company website and social media platforms, e.g. facebook,\u00a0instagram, edm etc\nCoordinate with internal designer to produce new creatives with innovative ideas and formats, and direct report to director\nPerform ad-hoc project as required\n\nRequirements\n\nDiploma or above in marketing or related subjects;\nMinimum 3 years working experience in marketing field;\nSolid hands-on experience on Photoshop, Microsoft;\nExcellent command in spoken and written English.\nWe offer\n\nMedical insurance\nDouble pay\nOvertime pay", "employment_types": ["Full Time", "Permanent"], "selling_points": ["MNC Company", "Flexible Working hours", "Collaborate with a strong, dynamic team"], "locations": ["Not Specified"], "categories": ["Marketing / Public Relations", "Digital Marketing", "E-commerce", "Marketing - Brand / Product Management", "Product Management / Business Analyst"], "post_time": "2022-01-12T04:07:39Z", "salary": {"currency": null, "max": null, "min": null, "period": "monthly", "term": null}, "salary_visible": false, "title_keywords": ["specialist"], "responsibilities": ["ad-hoc", "marketing events", "ideas", "edm", "conduct market research", "social media platforms", "coordinate with", "contents", "facebook", "company website", "report"], "requirements": {"degrees": ["diploma or above"], "majors": ["marketing"], "languages": ["english"], "language_level": ["excellent"], "hard_skills": ["photoshop"], "soft_skills": ["hands-on"], "languages_combined": [{"language": "english", "language_level": ["excellent"]}]}, "experience_required": {"duration": ["minimum 3 years"], "field": ["marketing"]}}, {"job_id": "100003009034211", "location_code": "hk", "company": "ArtsNow.com Limited", "job_title": "Marketing Executive", "description": "JOIN OpenRice\u2026\u2026if you want to service our\n\n\u00a05 million App users with\n\n\u00a09 million pageviews per day in Hong Kong! \u00a0\n\nOpenRice\u00a0is seeking an energetic and passionate individual to join a dynamic and collaborative environment as part of sales\u00a0team.\n\nYou will be responsible for:\n\n\n\nBuild OpenRice Online Booking Service branding and awareness to target audience\nDrive effective usage and increase conversion rate to improve sales performance\nPlan and implement overall partnerships and affiliate strategies to boost user acquisition and drive sales\nAnalyze sales and usage data to identity opportunities for business growth\u00a0 \u00a0\u00a0\u00a0 \u00a0\n\n\nYou should possess:\n\n\n\nBachelor degree or above in business or marketing related discipline\n5 years\u2019 working experience in marketing,\u00a0preferably with B2B experience\nStrong analytical, problem solving and project management skills\u00a0\nGood written and spoken Chinese and English, with strong communication and\u00a0negotiation skill\nPossess strong business networks and customer loyalty related experience are preferred\nImmediately available would be an advantage\n\nWe offer a competitive remuneration package including excellent career prospects to the right candidate. Interested parties please submit your detailed resume with expected salary and available date by clicking the Quick Apply button.\n\nAll personal information submitted by job applicants will be used for recruitment purposes and we reserve the rights to consider the applications for other positions in our Group.", "employment_types": ["Full Time"], "selling_points": ["Double pay, Medical insurance, Overtime pay", "update contents on company website/social media", "Solid hands-on experience on Photoshop, Microsoft"], "locations": ["Kwun Tong"], "categories": ["Marketing / Public Relations", "Public Relations - Event Management", "Digital Marketing", "E-commerce", "Marketing - Brand / Product Management"], "post_time": "2022-01-10T16:52:40Z", "salary": {"currency": null, "max": null, "min": null, "period": "monthly", "term": null}, "salary_visible": false, "title_keywords": ["marketing executive"], "responsibilities": ["sales and usage data", "affiliate strategies", "improve sales performance", "online booking service", "communication", "project management", "sales team", "plan", "drive sales"], "requirements": {"degrees": ["degree or above", "bachelor"], "majors": ["business", "marketing"], "languages": ["english", "chinese"], "language_level": ["good"], "hard_skills": ["problem solving", "project management", "dynamic"], "soft_skills": ["passionate", "responsible", "project management skills", "collaborative", "problem solving", "communication", "dynamic", "negotiation skill", "energetic"], "languages_combined": [{"language": "english", "language_level": ["good"]}, {"language": "chinese", "language_level": ["good"]}]}, "experience_required": {"duration": ["5 years"], "field": ["business", "marketing", "related"]}}, {"job_id": "100003009042643", "location_code": "hk", "company": "Openrice Limited", "job_title": "Partnership Manager, Booking Service (B2B)", "description": "We are seeking to hire a highly skilled marketer to lead product development and marketing to build and maintain Peninsula Merchandising brand proposition in luxury market in all regions that celebrate our heritage and drive business objectives. You will also strive product innovation and quality to drive company growth plan with product diversification and localization.\u00a0\n\nExceptional market leading benefits such as comprehensive family medical insurance (including dependents), 17 paid statutory holidays,\u00a020 vacation days and\u00a03 days paid carers leave.\u00a0\n\nKey Responsibilities:\n\n\nAlign product strategies with overall company business and financial objectives, and lead product development cycle.\nGain customer\u2019s and market\u2019s insight to support product strategies by developing robust market research tools and processes.\nDefine pricing and competitive position of each product with supporting from market intelligence and research.\nDevelop and drive vendor review process and assessment measures to ensure vendor\u2019s performance.\nLead vendor sourcing and selection cycle to identify qualified vendors and ensure it complies with Group\u2019s procurement policy.\nLead and support product and packaging design to deliver a luxury product experience and meets the highest quality standards.\nSet up business review tools with analysis on product performance to present business insight and develop action plan.\u00a0\nEnsure brand integrity across all regions by driving brand policy and building resources including standard of procedures, contents, imagines etc.\nFormulate marketing and communications strategies and overseeing marketing campaigns rollout to contribute to the overall company business and financial objectives.\nDrive brand awareness through social and digital media to build and maintain brand presence in all markets and ensure brand standards are delivered.\nBuild and maintain professional relationship with agencies, vendors, press and influencers to support overall marketing & communications initiatives.\nSet and monitor budget for all teams underneath as per the Group\u2019s guidelines and Company\u2019s objectives.\nBuild and develop teams with nurturing an innovative culture.\n\nRequirements:\n\nMinimum of 12 years of related experience gained in retail or FMCG, with at least 5 years in functional head position with regional responsibility.\nExperience in confectionery or food retail will be an advantage.\nDegree holder in marketing or any related disciplines.\nGreat presentation skill, innovative, strong business acumen.\nIn-depth marketing knowledge in luxury industry, business network with press/influencers.\nStrong command in both written and oral Chinese and English.\nProficient in MS Office.\n\nWe are delighted to receive your application for further consideration. Click apply now with your latest CV and salary information.", "employment_types": ["Full Time", "Permanent"], "selling_points": ["Manage MKT partnerships and affiliate strategies", "Boost user acquisition and drive sales growth", "Attractive salary + high commission"], "locations": ["Quarry Bay"], "categories": ["Sales, CS & Business Devpt", "Account Servicing", "Others", "E-commerce", "Marketing - Brand / Product Management"], "post_time": "2022-01-12T08:15:01Z", "salary": {"currency": null, "max": null, "min": null, "period": "monthly", "term": null}, "salary_visible": false, "title_keywords": ["manager"], "responsibilities": ["packaging design", "guidelines", "analysis", "review", "quality", "developing", "market research", "develop", "procedures", "monitor", "budget", "maintain", "teams", "plan", "contents", "marketing campaigns"], "requirements": {"degrees": ["degree holder"], "majors": ["related disciplines", "marketing"], "languages": ["english", "chinese"], "language_level": [], "hard_skills": ["presentation skill", "luxury industry", "ms office", "acumen"], "soft_skills": ["presentation skill", "oral", "innovative", "business acumen"], "languages_combined": [{"language": "english", "language_level": []}, {"language": "chinese", "language_level": []}]}, "experience_required": {"duration": ["at least 5 years", "minimum of 12 years"], "field": ["related", "food", "retail", "fmcg"]}}, {"job_id": "100003009036115", "location_code": "hk", "company": "CHOW TAI FOOK JEWELLERY CO LTD", "job_title": "Associate, eCommerce Centre", "description": "What You Do\n\nResponsible for daily operations of Vending Machine, including liaise with vendors and departments, arrange venues and select potential products etc.\nParticipate in planning and executing e-Commerce marketing and promotion initiatives to reach company\u2019s sales strategies\nNegotiate and handle contract issue, review product design and execute the marketing initiatives for IP projects through omni-channels\nAssist in e-Commerce business and daily operations including product development, logistics arrangement, inventory replenishment, customer service enquiry, payment settlements and follow up sales orders\nPerform other ad-hoc projects as assigned\nWho Will Thrive\n\nDegree holder in Marketing / Business / Communication / Journalism or related disciplines\nAt least 2 years\u2019 e-Commerce / digital marketing experience with experience in jewelry / luxury industry is an advantage\nGood team player, proactive, multi-tasking, fast-paced with strong communication and problem solving skills\nGood command of written and spoken English, Cantonese & Mandarin\nProficient in MS Word, Excel, PowerPoint and Chinese Word Processing\nFamiliar with Photoshop is an advantage\nBenefits\n5-day work\nCompetitive salary, staff meal, medical and dental insurance,\u00a0life insurance\nVarious types of leave, e.g.\u00a0Family-friendly leave, self-development leave,\u00a0Examination leave, marriage leave, birthday leave, volunteer service leave, etc\nWe offer excellent career opportunities, attractive remuneration package & benefits to the right candidate. Interested parties please click\u00a0\"Apply Now\"\u00a0below or apply with full resume with portfolio by stating latest and expected salaries to 22/F, Chow Tai Fook Centre, 580A-580F Nathan Road, Mongkok, Kowloon, Hong Kong.\n\n\nAll information collected will be used for recruitment purposes only.", "employment_types": ["Full Time", "Permanent"], "selling_points": ["Assist in daily operations of Vending Machine", "1-3 years\u2019 e-Commerce/digital marketing experience", "5-day work, staff meal, medical & dental insurance"], "locations": ["Mong Kok"], "categories": ["E-commerce", "Business Development", "Marketing - Brand / Product Management", "Product Management / Business Analyst"], "post_time": "2022-01-10T09:23:45Z", "salary": {"currency": null, "max": null, "min": null, "period": "monthly", "term": null}, "salary_visible": false, "title_keywords": ["associate"], "responsibilities": ["logistics arrangement", "review", "communication", "daily operations", "product design", "executing", "customer service", "payment", "digital marketing", "liaise with", "ad-hoc projects", "inventory replenishment", "planning"], "requirements": {"degrees": ["degree holder"], "majors": ["business", "related disciplines", "marketing", "journalism"], "languages": ["cantonese", "english", "chinese", "mandarin"], "language_level": ["good command", "proficient"], "hard_skills": ["excel", "chinese word processing", "e-commerce", "powerpoint", "ip", "luxury industry", "photoshop", "problem solving skills", "ms word"], "soft_skills": ["good team player", "responsible", "communication", "multi-tasking", "customer service", "problem solving skills", "proactive"], "languages_combined": [{"language": "cantonese", "language_level": ["good command"]}, {"language": "english", "language_level": ["good command"]}, {"language": "chinese", "language_level": ["proficient"]}, {"language": "mandarin", "language_level": ["good command"]}]}, "experience_required": {"duration": ["at least 2 years"], "field": ["digital marketing", "e-commerce"]}}, {"job_id": "100003009042549", "location_code": "hk", "company": "Asco General Supplies (Far East) Ltd", "job_title": "Business Development Manager - Active", "description": "The role:\n\nTo deliver Market / Key Account business plans (sales, profit, distribution) through implementation of partner business plans & Key Account strategies that contribute to the overall Customer Function Vision \u201cDrive the growth of our brands globally through the execution of market, customer & shopper led opportunities, operating as One Pentland and using commercial capability as a competitive advantage\u201d. This role covers Pentland\u2019s Active (sport) brands, the biggest of which is Speedo.\n\nResponsibilities\n\nDevelop and execute partner/market business plans and budgets to deliver our brand propositions and therefore market growth.\nContinuously improve our go to market model strategies and plans to ensure we are executing our propositions better through partners and in the leading retailers in the region.\nExecute our Fix, Build, Inspire & Hybrid Key Account Strategies to ensure effective business building plans are in place with partners and for agreed Key Account targets in the region.\nDevelop and execute country marketing/trade marketing plans in keeping with Pentland Brand strategies\nLeverage the Pentland matrix organisation to align resources to key opportunities - be an ambassador of \u2018Stronger Together behaviour\u2019\nRegularly review market/partner/key account performance and develop & execute corrective actions where necessary\nSet challenging POP performance standards.\u00a0 Champion execution effectiveness through FBI with consistent evaluation and applying cross category learnings. Ensuring there are steps & processes in place to maximize performance.\nManage sell in, sell out, stock turn, payment, and order book management including managing overdue orderbook and delivering assigned KPIs.\nManage customer marketing budget to invest behind long term business drivers and ensure maximum ROI.\nWork with regional marketing / go-to-market team to provide partners and key accounts with information, materials, support and advice including regular market visits, feedback, and review meetings.\nProvide regular situational analysis and insight to the Business Development Director / Commercial Director Asia and Global Brand Directors and teams\u00a0\n\no\u00a0 Local mkt activity, intelligence, sell in & sell out data\n\no\u00a0 Distributor / Licensee / Retailer Performance\n\no\u00a0 Sales, Marketing, Retail, and Retail Marketing activity\n\no\u00a0 Financial comparisons to budgets, contractual minimums, YOY performance etc\n\nWork closely with Supply Chain and Customer Operations to ensure efficient service to mkts/partners\n\nNeeds to have\n\n5 years experience successfully managing partners / retailers across geographies and in different cultures. Can consider candidates with regional marketing, product, digital or retail experience looking to stretch into a wider commercial and sales role.\nExperience in and potential to manage complex partner relationships and effect change in partner\u2019s performance, growth rate and alignment to strategy.\nExperience in the footwear, apparel & sport industries would be beneficial.\nLeadership potential.\nProven energy and tenacity to deliver results.\nGood analytical skills, able to use diverse data streams to get to root cause & develop alternative/corrective actions. Financial understanding (margins, discounts, debtors, royalties etc)\nExcellent interpersonal and influencing skills, able to work across retailers, distributors & licensees as well as internal stakeholder.\nGood negotiation skills training, comfortable negotiating at multiple levels.\u00a0\nStrong planning & organising skills, able to multi task.\nStrong presentation skills and a persuasive style.\nProficiency in PC skills including Word, Excel, Powerpoint.\nThe role requires fluent English and other Asian languages would be advantageous.\n\nNeeds to be\n\nAn emerging sales and commercial talent seeking career growth.\nPassionate and confident, with the ambition to achieve great things at a high standard of behaviours and execution.\nWilling to dig in, work hard, be persistent, learn fast and learn lots.\nA team player able to motivate others through persuasion, relationship building and influence.\nAn influencer, comfortable working in the matrix environment.\nDiplomatic and culturally aware.\nFlexible to travel extensively in the defined markets.\n\nInterested parties please send your detail resume with expected salary to the Human Resources Department by clicking \"Apply Now\" or applying via the link:\u00a0apply here\n\nPersonal data collected will be used for recruitment-related purposes only.", "employment_types": ["Full Time", "Permanent"], "selling_points": ["Business Development", "Implementation of business plans & strategies", "Analysis and insight"], "locations": ["Tsim Sha Tsui"], "categories": ["E-commerce", "Business Development", "Marketing - Brand / Product Management", "Product Management / Business Analyst"], "post_time": "2022-01-12T08:08:08Z", "salary": {"currency": null, "max": null, "min": null, "period": "monthly", "term": null}, "salary_visible": false, "title_keywords": ["business development manager"], "responsibilities": ["data", "operations", "brand strategies", "budget", "business plans", "payment", "evaluation", "plans", "teams", "implementation", "develop", "kpis", "management", "review", "executing", "budgets", "trade marketing", "analysis", "planning"], "requirements": {"degrees": [], "majors": [], "languages": ["english"], "language_level": ["fluent"], "hard_skills": ["excel", "analysis", "word", "powerpoint", "analytical skills", "go", "pc skills"], "soft_skills": ["efficient", "passionate", "confident", "flexible", "persuasive", "persistent", "diplomatic", "analytical skills", "diverse", "negotiation skills", "presentation skills", "organisation", "team player", "active", "leadership", "interpersonal"], "languages_combined": [{"language": "english", "language_level": ["fluent"]}]}, "experience_required": {"duration": ["5 years"], "field": ["digital", "marketing", "commercial", "retail"]}}, {"job_id": "100003009036259", "location_code": "hk", "company": "HomePlus (Hong Kong) Limited (HOME+)", "job_title": "Data Analyst - Digital Transformation (HOME+ E-Commerce Platform)", "description": "To be part of our mission, we are looking for a Data Analyst (Marketing Focus) with\u2026\n\nEffective negotiating, time-management and communication skills\nConfident, assertive yet collaborative approach, organized, ability to motivate team members\nArticulate with the ability to clearly explain business topics\nTech savvy with good understanding of digital, technology terms and mechanisms to manage digital platform developments\nAbility to work under pressure and prioritize workload\nSelf-motivated, self-managing and target driven\nHigh integrity and ethical standard\n\nWhat efforts you need to make?\n\nResponsible for digital data and customer behavior analysis, web/app platform performance analysis and digital journey optimization.\nApply the market trends and best practices such as App Indexing, Web & App Analysis\nWork closely with business divisions and IT to manage digital platform developments\nWork closely with cross-functional teams and manage marketing support such as gather market intelligence, program logistics formulation, etc\nExecute digital-related strategies devised by business divisions to support business goals and support project management\nConstantly strive for new/innovated ideas and solutions for the business and marketing campaigns\n\nLet's check if you are\u2026\n\n\nDegree in Marketing / Business Management / Statistics / Data Science / Information System or related discipline preferred\nMinimum 3 years of work experience in Consulting / Digital Marketing / Data Analysis related experience\nKnowledge in Google Analytic, Firebase, BigQuery, Omniture is preferred\nTechnically Proficient in data analysis using SQL, SAS, VBA, R is preferred\nSolid consultancy experience is preferred\nPossessed enterprising mindset with the ability to handle multiple priorities.\nFocus and organized with the ability to optimize business initiatives\nProfessional in spoken and written English and Cantonese\nCandidates with more experience will be considered as Senior Data Analyst\n\nWhat you get in return\u2026\n\nApart from competitive salary package and benefits, in HKBN, you will work flexibly under our Talent-first\u00a0culture\u00a0and we uphold Life-Work Priority. Examples of our flexible initiatives:\n\nFive-day work week and shorten working hours (8 hours including 1 hour 15 mins meal break)\nHalf Day Off Friday once a month (compensation leave for Talents who work on shift)\nHalf Day Off on Festival Eve (compensation leave for Talents who work on shift)\nUnique leaves arrangement: Family-care leave, Anniversary leave, Bonus leave, Volunteer leave, Sabbatical leave, etc.\nComprehensive medical and life insurance coverage\nUpgraded maternity leave and paternity leave\nDiscounted Talent plan offers including broadband and mobile plans and other promoted products\nEducation subsidies and Examination leave\nYear-end discretionary bonus", "employment_types": ["Full Time", "Permanent"], "selling_points": ["digital data and customer behavior analysis", "App Indexing, Web & App Analysis", "Google Analytic/Firebase/BigQuery/Omniture"], "locations": ["Kwai Hing"], "categories": ["Marketing / Public Relations", "Marketing - Market Research", "Digital Marketing", "E-commerce", "Marketing - Brand / Product Management"], "post_time": "2022-01-10T09:50:24Z", "salary": {"currency": null, "max": null, "min": null, "period": "monthly", "term": null}, "salary_visible": false, "title_keywords": ["data analyst"], "responsibilities": ["management", "business goals", "ideas", "business initiatives", "consulting", "data", "analysis", "digital platform", "communication", "project management", "data analysis", "logistics", "digital marketing", "marketing campaigns", "cross-functional teams", "work under pressure"], "requirements": {"degrees": ["degree"], "majors": ["business", "data science", "marketing", "statistics"], "languages": ["cantonese", "english"], "language_level": [], "hard_skills": ["business management", "vba", "web", "sas", "analysis", "information system", "sql", "make", "project management", "r", "focus"], "soft_skills": ["confident", "communication skills", "organized", "self-motivated", "responsible", "assertive", "integrity", "collaborative", "prioritize", "project management", "ethical", "enterprising", "articulate", "focus", "driven", "work under pressure"], "languages_combined": [{"language": "cantonese", "language_level": []}, {"language": "english", "language_level": []}]}, "experience_required": {"duration": ["minimum 3 years"], "field": ["data analysis", "related", "digital marketing", "consulting"]}}, {"job_id": "100003009045822", "location_code": "hk", "company": "Michael Page", "job_title": "Assistant eCommerce and Marketing Manager (Entertainment)", "description": "The Assistant Manager will be part of the team that designs the company's omnichannel marketing strategy, which includes a loyalty program, CRM, and online-to-offline promotions.\n\nClient Details\n\nOur client is a world-leading entertainment company.\n\nDescription\n\nThe Assistant Manager will be part of the team that designs the company's omnichannel marketing strategy, which includes a loyalty program, CRM, and online-to-offline promotions. The main duty of this position is to manage and promote the customer loyalty program to boost engagement and customer satisfaction. The main duty of this position is to manage and promote the customer loyalty program to boost engagement and customer satisfaction. Specific tasks include the development of market research and digital marketing campaigns, as well as the preparation of reports and presentations to support management decisions. In doing so, the new teammate will ensure marketing campaigns meet KPIs and enhance sales growth. The Assistant Manager will also oversee, evaluate, and analyze the performance of marketing programs.\n\nProfile\n\nThe qualified candidate should come from at least 6 years of marketing experience, particularly in the eCommerce digital marketing market. A good understanding of B2C (particularly in Retails and eCommerce) businesses is important. Knowledge in O2O marketing and experience in events management would be advantageous. Experienced in driving sales through social media marketing campaigns. Basic knowledge in graphic design (i.e. proficiency in Adobe Photoshop & Illustrator) is a strong advantage. Good command of both written and spoken English and Chinese is required.\n\nJob Offer\n\nThe company also offers a competitive salary package and a promising career path for high potential candidates who are passionate about eCommerce and digital marketing.\n\nTo apply online please click the 'Apply' button below. For a confidential discussion about this role please contact Kenny Lo on +852 3412 4859", "employment_types": ["Full Time", "Permanent"], "selling_points": ["Working in a world-leading entertainment company", "Promote the customer loyalty program", "Drive the online to offline promotions"], "locations": ["Not Specified"], "categories": ["Marketing / Public Relations", "Public Relations - Event Management", "Public Relations - General / Support", "E-commerce", "Marketing - Brand / Product Management"], "post_time": "2022-01-13T08:48:50Z", "salary": {"currency": null, "max": null, "min": null, "period": "monthly", "term": null}, "salary_visible": false, "title_keywords": ["marketing manager", "assistant"], "responsibilities": ["social media", "management", "digital marketing campaigns", "graphic design", "market research", "presentations", "evaluate", "reports", "digital marketing", "marketing campaigns", "contact", "kpis"], "requirements": {"degrees": [], "majors": [], "languages": ["english", "chinese"], "language_level": ["good command"], "hard_skills": ["adobe photoshop", "basic", "illustrator", "presentations"], "soft_skills": ["passionate about"], "languages_combined": [{"language": "english", "language_level": ["good command"]}, {"language": "chinese", "language_level": ["good command"]}]}, "experience_required": {"duration": ["at least 6 years"], "field": ["ecommerce", "management", "marketing", "digital marketing"]}}, {"job_id": "100003009036280", "location_code": "hk", "company": "I.T Apparels Limited", "job_title": "CRM Executive (REF : JDB-IT-CRME)", "description": "Responsibilities:\u00a0\n\nBe a Brand Management role for different eyewear brands.\nAssist in formulating brand strategies.\nBe responsible for product development strategies and execution.\nMonitor the product releasing schedule.\nLiaise with brand principles / licensors for all product management issues.\nClosely collaborating with Marketing Team, Business Development Team, Design Team, and Production Team.\nPerform ad-hoc projects as assigned.\n\n\u00a0Requirements\n\nDegree or above in Marketing related discipline.\nAt least 1 year\u2019s solid experience in Brand Management, preferably in fashion accessories or FMCG.\nFluency in spoken and written English and Chinese.\nExperience on e-commerce would be an advantage.\nStrong marketing sense and attentive to details.\nPresentable, self-motivated with excellent interpersonal skills.\nOccasional travel is required.\n\nWe offer attractive remuneration and excellent career prospects to the right candidates. Interested and qualified parties please send\u00a0full resume including current salary, expected salary and availability\u00a0to The Group Human Resources Department via JobsDB:\"Apply Now\".\n\nThe information provided will be kept confidential and used for recruitment purposes only. Applicants not contacted within three months may consider their applications unsuccessful. The company will retain all applications for a maximum of six months.", "employment_types": ["Full Time", "Permanent"], "selling_points": ["Minimum 3 year of experience in CRM Analytics", "Responsible for customer database management", "E-commerce or online CRM management exposure"], "locations": ["Southern Area"], "categories": ["Sales, CS & Business Devpt", "Account Servicing", "Marketing / Public Relations", "Digital Marketing", "E-commerce", "Marketing - Brand / Product Management"], "post_time": "2022-01-10T09:53:43Z", "salary": {"currency": null, "max": null, "min": null, "period": "monthly", "term": null}, "salary_visible": false, "title_keywords": ["crm executive"], "responsibilities": ["management", "brand strategies", "monitor", "design", "schedule", "liaise with", "ad-hoc projects"], "requirements": {"degrees": ["degree or above"], "majors": ["marketing"], "languages": ["english", "chinese"], "language_level": ["fluency"], "hard_skills": ["e-commerce"], "soft_skills": ["self-motivated", "marketing sense", "attentive to details", "presentable", "interpersonal skills"], "languages_combined": [{"language": "english", "language_level": ["fluency"]}, {"language": "chinese", "language_level": ["fluency"]}]}, "experience_required": {"duration": ["at least 1 year"], "field": ["management", "fmcg", "brand", "e-commerce"]}}, {"job_id": "100003009025318", "location_code": "hk", "company": "Money Plaza Hong Kong Limited", "job_title": "Marketing Executive/ Account Executive", "description": "Join us & Be eCommerce Innovators\nAre you looking to be part of revolutionizing online shopping behaviour and experience? We are a well-esteemed eCommerce company that operates multiple eCommerce websites internationally. We are now looking for potential talent to help us expand our new beauty and fashion business worldwide and to build brand awareness and sales revenue.\n\nKey Job Responsibilities:\u00a0\n\nWebsite Operations\n\n\nManage and monitor website sales performance on daily basis\nConduct and present KPI report on weekly basis\nResponsible for weekly operations include promotion rules set up on backend system and Google Promotion set up\n\nProduct & Pricing\n\n\nAnalyze and review product performance with regular reporting\nMonitor competitors\u2019 pricing strategy closely and review price of products\n\nMarketing Channel\n\n\nReview and monitor overall sales performance and optimize marketing cost usage\nFocus on utilizing Google Adwords to maximize sales performance efficiently, including Google Shopping, Display ad, Video Ad and Search Ad\nAdapt and test new functions on Google to maximize customer base\n\n\nGeneral\n\n\nPerform other duties as assigned by Supervisor and Manager\nAssist other ad hoc projects and operations to improve efficiency of tasks\nWork closely with your team and different function units including Business Analytics & Strategy team, Marketing team, Merchandizing team, Logistic team and Customer Service team to ensure smooth consumer experiences on website\u00a0\n\n\u00a0Desired Skills and Experience:\u00a0\n\nDiploma or above in Marketing/ Business/ eCommerce or related disciplines\nExperience in any eCommerce backend system is an advantage\nWell-organized, detailed minded and able to manage multiple tasks\nAble to work independently and under pressure, as well as cooperate well with team and stakeholders to achieve company goals\nExcellent command of written and spoken English, Cantonese\nFresh graduate is welcome\n\nWe offer friendly team environment, good career prospect, also attractive remuneration package including discretionary bonus incentive, together with other benefits like five-day work week, flexible working hours, double pay, medical and dental insurance. Interested parties please send full resume with available date, present and expected salary by clicking \u201cApply Now\u201d for an interview.\n\nAll personal data collected will be used for recruitment purpose only.\u00a0", "employment_types": ["Full Time", "Permanent", "Contract"], "selling_points": ["Great Exposure in Fintech and digital marketing", "Dynamic and Friendly Work Environment", "5 work days and preformance bonus"], "locations": ["Tsuen Wan Area"], "categories": ["Media & Advertising", "Account Servicing", "Marketing / Public Relations", "Digital Marketing", "E-commerce", "Marketing - Brand / Product Management"], "post_time": "2022-01-10T02:51:15Z", "salary": {"currency": null, "max": null, "min": null, "period": "monthly", "term": null}, "salary_visible": false, "title_keywords": ["account executive", "marketing executive"], "responsibilities": ["reporting", "cost", "perform other duties", "operations", "sales performance", "review", "monitor", "website", "customer service", "ad hoc projects", "insurance", "report"], "requirements": {"degrees": ["fresh graduate", "diploma or above"], "majors": ["business", "related disciplines", "ecommerce", "marketing"], "languages": ["cantonese", "english"], "language_level": ["excellent"], "hard_skills": ["adwords", "focus", "merchandizing"], "soft_skills": ["flexible", "work independently", "under pressure", "responsible", "multiple tasks", "well-organized", "customer service", "friendly", "smooth", "focus", "detailed"], "languages_combined": [{"language": "cantonese", "language_level": ["excellent"]}, {"language": "english", "language_level": ["excellent"]}]}, "experience_required": {"duration": [], "field": ["ecommerce", "customer service", "business", "marketing", "team"]}}, {"job_id": "100003009033395", "location_code": "hk", "company": "Bannershop Hong Kong Limited", "job_title": "Digital Marketing Executive/ Senior Digital Marketing Executive", "description": "Accountabilities \u2013 Key Result Areas\n\n\nSupport in developing and implementing digital marketing and thematic campaigns to support e-commerce business goals and development\nUnderstand e-commerce competitiveness and customer behavior in respective markets via data analytics to maximize digital marketing efficiency\nResponsible for customer database management, delivering report analysis on a regular basis on digital marketing performance results, customer segmentation and online purchase behavior to support e-commerce digital marketing strategy and CRM enhancement\nSupport in execution and end-to end logistics of various digital CRM plans and programs by coordinating with internal departments on digital marketing communication composition such as eDM, SMS, social media communication, etc.\nSupport on other ad-hoc duties as assigned\n\nExperience / Qualification Requirements\n\n\nDegree holder in E-commerce/ Marketing/ Marketing Analytics/ Statistics and other related discipline\nMinimum 3 year of experience in Marketing/ CRM Analytics, with e-commerce or online CRM management exposure is highly preferred\nWith outstanding spoken and written communication skills in English and Chinese (Cantonese and Mandarin)\nWith experience working in MNC or international business environment will be advantageous\nWith passion and interest in e-commerce and fashion business\nAnalytical minded, logical, and adaptable to fast paced environment and meeting tight deadlines\n\nCompetitive remuneration and benefit package will be offered to the right candidate. Please submit your application by clicking \"Apply Now\" below.\n\nAll data collected is for recruitment purpose only.\n\nSure you want to know more about our company and brands, simply follow our\n\nWEBSITE at http://www.ithk.com\u00a0 \u00a0 \u00a0 \u00a0 \u00a0 \u00a0\n\u00a0 \u00a0 \u00a0 \u00a0 \u00a0 \u00a0 \u00a0 \u00a0 \u00a0 \u00a0 \u00a0 \u00a0 \u00a0 \u00a0 \u00a0 \u00a0 \u00a0 \u00a0 \u00a0 \u00a0 \u00a0 \u00a0 \u00a0 \u00a0 \u00a0 \u00a0 \u00a0 \u00a0\u00a0\nFACEBOOK at\u00a0http://www.facebook.com/I.Ttheofficialpage\u00a0 \u00a0 \u00a0 \u00a0\n\u00a0 \u00a0 \u00a0 \u00a0 \u00a0 \u00a0 \u00a0 \u00a0 \u00a0 \u00a0\u00a0\nINSTAGRAM at http://instagram.com/ithk\u00a0 \u00a0 \u00a0 \u00a0 \u00a0\n\u00a0 \u00a0 \u00a0 \u00a0 \u00a0 \u00a0 \u00a0 \u00a0 \u00a0 \u00a0 \u00a0 \u00a0 \u00a0 \u00a0 \u00a0 \u00a0 \u00a0 \u00a0 \u00a0 \u00a0 \u00a0 \u00a0 \u00a0\nWEIBO at\u00a0http://e.weibo.com/ithongkong", "employment_types": ["Full Time"], "selling_points": ["At least 1 yr exp in e-commerce or digital agency", "Exp in content marketing and digital market", "5 days work"], "locations": ["Kwun Tong"], "categories": ["Marketing / Public Relations", "Marketing - Direct Marketing", "Marketing - General / Support", "E-commerce", "Marketing - Brand / Product Management"], "post_time": "2022-01-09T16:25:53Z", "salary": {"currency": null, "max": null, "min": null, "period": "monthly", "term": null}, "salary_visible": false, "title_keywords": ["senior digital marketing executive", "digital marketing executive"], "responsibilities": ["social media", "business goals", "management", "data", "edm", "analysis", "developing", "website", "communication", "purchase", "digital marketing", "logistics", "database", "ad-hoc duties", "recruitment", "plans", "facebook", "report"], "requirements": {"degrees": ["degree holder"], "majors": ["marketing", "statistics", "e-commerce"], "languages": ["cantonese", "english", "chinese", "mandarin"], "language_level": [], "hard_skills": ["data analytics", "analysis", "facebook", "e-commerce"], "soft_skills": ["communication skills", "meeting tight deadlines", "responsible", "adaptable", "communication", "ad-hoc duties", "business environment"], "languages_combined": [{"language": "cantonese", "language_level": []}, {"language": "english", "language_level": []}, {"language": "chinese", "language_level": []}, {"language": "mandarin", "language_level": []}]}, "experience_required": {"duration": ["minimum 3 year"], "field": ["business", "management", "marketing", "e-commerce"]}}, {"job_id": "100003009037216", "location_code": "hk", "company": "WilliamSELECT", "job_title": "Senior Digital / Multimedia Designer - Retail", "description": "Job duties\n\nMonitor and manage daily eCommerce operations\nPlan and execute digital marketing campaign, including advertising, eDM, SEO, website content, social media etc.\nCreating a wide range of different marketing materials\nWorking closely with sales and production team and assisting with new product launches\nMonitor, research and identify market trends and competitor activities, provide monthly analysis report\nAssist in executing\u00a0loyalty programs\u00a0to achieve company goal\nExplore new business opportunity, including brand cooperation\n\nRequirements\n\nAt least 1yr working experience in e-commerce or digital agency\nExperience in content marketing and digital marketing\nKnowledge in search engine marketing, social ad, Google Analytic, etc\nGood tracking and data analytic skill\nGood command of written and spoken English and Chinese\nKnowledge of AI is a plus\nExperience in CRM campaign is a plus\nMore experience will be considered as Senior Marketing Executive", "employment_types": ["Full Time"], "selling_points": ["International Retail Brand- Young & Energetic team", "Graphic & Multimedia Design for ecom / online", "Knowledge in 3D Max will be a plus, Welcome Agency"], "locations": ["Not Specified"], "categories": ["Design", "Graphics", "Multi-media", "E-commerce", "Marketing - Brand / Product Management"], "post_time": "2022-01-11T02:06:20Z", "salary": {"currency": "HKD", "max": 44999, "min": 30000, "period": "monthly", "term": null}, "salary_visible": true, "title_keywords": ["multimedia designer"], "responsibilities": ["social media", "advertising", "seo", "edm", "analysis report", "operations", "monitor", "website", "digital marketing", "executing", "plan", "marketing materials"], "requirements": {"degrees": [], "majors": [], "languages": ["english", "chinese"], "language_level": ["good command"], "hard_skills": ["ai", "plus", "e-commerce"], "soft_skills": [], "languages_combined": [{"language": "english", "language_level": ["good command"]}, {"language": "chinese", "language_level": ["good command"]}]}, "experience_required": {"duration": [], "field": ["e-commerce", "agency", "marketing", "digital marketing", "digital"]}}, {"job_id": "100003009033822", "location_code": "hk", "company": "Konew Financial Express Limited \u5eb7\u696d\u4fe1\u8cb8\u5feb\u905e", "job_title": "Digital Marketing Manager", "description": "Our client is a reputable online platform with presence in Hong Kong and South East Asia. They are now seeking high\u00a0caliber\u00a0professional to join the team as Marketing Manager for the B2B side partners development.\u00a0\n\nResponsibilities:\nBuild company branding and awareness to target audience\nDrive effective usage and increase conversion rate to improve sales performance\nPlan and implement overall partnerships and affiliate strategies to boost user acquisition and drive sales\nAnalyze sales and usage data to identity opportunities for business growth\nQualifications:\n\nBachelor degree or above in business or marketing related discipline\n5 years\u2019 working experience in marketing,\u00a0preferably with B2B experience\nStrong analytical, problem solving and project management skills\u00a0\nGood written and spoken Chinese and English, with strong communication and negotiation skill\nPossess strong business networks and experience in formulating customer loyalty programme are preferred\nAn attractive remuneration package will be offered to the right candidates. Please send your updated resume with expected salary via\u00a0Apply Now\u00a0or send your application to the email address showing in the Company Description.\n\nPersonal data collected will be used for recruitment purpose only.", "employment_types": ["Full Time", "Permanent"], "selling_points": ["Lead a team in developing marketing strategies", "Digital marketing experience is a must", "Highly analytical, structured thinker"], "locations": ["Central"], "categories": ["Media & Advertising", "Strategic Planning", "Marketing / Public Relations", "Digital Marketing", "E-commerce", "Marketing - Brand / Product Management"], "post_time": "2022-01-10T01:51:06Z", "salary": {"currency": null, "max": null, "min": null, "period": "monthly", "term": null}, "salary_visible": false, "title_keywords": ["digital marketing manager"], "responsibilities": ["sales and usage data", "affiliate strategies", "improve sales performance", "communication", "project management", "recruitment", "plan", "drive sales", "personal data"], "requirements": {"degrees": ["degree or above", "bachelor"], "majors": ["business", "marketing"], "languages": ["english", "chinese"], "language_level": ["good"], "hard_skills": ["problem solving", "project management"], "soft_skills": ["problem solving", "project management skills", "communication", "negotiation skill"], "languages_combined": [{"language": "english", "language_level": ["good"]}, {"language": "chinese", "language_level": ["good"]}]}, "experience_required": {"duration": ["5 years"], "field": ["business", "marketing"]}}, {"job_id": "100003009042683", "location_code": "hk", "company": "Seeds Talent Solution Limited", "job_title": "Marketing Manager, B2B Partnership", "description": "The Senior UX/UI Designer will oversee a team to develop and deliver UX/UI solutions for designated client projects, ensuring quality experiences consistently.\n\nResponsibilities:\n\n- Build and foster relationships with designated clients, ensuring their understanding of the role of User Experience\n\n- Work with Account and Production team to enhance quality, productivity, and profitability of designated account\n\n- Participate in workshops alongside Strategy to help define user needs, gather clients' requirements and input to prioritise functionality and content to address client and user needs\n\n- Collaborate with multidiscipline team members including design, copy and tech to provide creative solutions that address the client and user needs\n\n- Create written and visual documentation outlining user experience requirements for client and internal teams, including user journeys, site maps, user-flows, wireframes, functional specifications and prototypes\n\n- Communicate user requirements to clients and internal team\n\n- Work with Account & Production team to define the user experience approach and timings for account projects and ensure all deliverables and deadlines are met within budget\n\n- Validate assumptions by conducting user testing where appropriate\n\n- Keep up-to-date with user experience trends and share this knowledge with the team\n\nRequirements:\n\n- At least 4 years previous experience in a User Experience role\n\n- Experience overseeing junior team members\n\n- Proven experience of developing User Experience deliverables for a range of projects from discrete Campaigns and apps through to large-scale ongoing platform projects\n\n- Extensive proven knowledge of user-centred design methodologies and tools\n\n- Extensive proven knowledge of user experience visualization and prototyping tools such as Omnigraffle\n\n- Ability to define and employ user-centred methodology definition on small to large-scale projects\n\n- Ability to accurately provide timings for deliverables\n\n- Hands-on ability to visualise and document User Experience concepts and detailed specifications\n\n- Excellent communication and presentation skills, with ability to communicate user experience recommendations in a clear, concise manner.\n\nApplication:\n\nDon't miss out on this great opportunity to work in a world-class digital agency! To apply, click 'Apply Now' to submit your resume to us.\n\nAny questions, please feel free to contact Yvonne Hung at +852 3907 3977 or email your inquiry to yhung@morganmckinley.com.", "employment_types": ["Full Time", "Permanent"], "selling_points": ["B2B Marketing experience", "Formulating strategies for partnership programme", "Good numerical sense"], "locations": ["Not Specified"], "categories": ["Marketing / Public Relations", "Management", "Marketing - Brand / Product Management", "E-commerce", "Marketing - Brand / Product Management"], "post_time": "2022-01-12T08:21:50Z", "salary": {"currency": null, "max": null, "min": null, "period": "monthly", "term": null}, "salary_visible": false, "title_keywords": ["marketing manager"], "responsibilities": ["collaborate with", "budget", "quality", "user experience", "design", "teams", "testing", "specifications", "visual", "documentation"], "requirements": {"degrees": [], "majors": [], "languages": [], "language_level": [], "hard_skills": ["small"], "soft_skills": ["world-class", "communication", "clear", "hands-on", "presentation skills", "extensive", "detailed"], "languages_combined": []}, "experience_required": {"duration": ["at least 4 years"], "field": ["developing", "team"]}}, {"job_id": "100003009037475", "location_code": "hk", "company": "DFS Hong Kong Limited", "job_title": "Assistant Manager, Digital Production Partnership - DFS91121322", "description": "Responsibilities\n\nResponsible for executing strategic plans to achieve sales targets and expand the customer base in eCommerce channel specialize in overseas marketplace;\nTo develop and execute full spectrum of marketing and sales plans including budget, brand management, product pricing and trade marketing programs;\nWork close with different teams to monitor and improve operations including but not limited to order management, fulfillment, order forecast, inventory management, preparing business analysis reports;\nManage product mix and assortment planning on assigned platforms;\nAnalyze business trends and consumer insights and evaluate existing product categories on choices;\nSuggest appropriate go-to-market strategies and plans;\nWork closely with 3rd party platforms, agencies & in-house designers for marketing service support and ad hoc projects;\nLead a team to ensure smooth operation in various channels and drive sales to support a fast growing businesses.\nRequirements\n\nUniversity graduate with at least 5 years\u2019 experience in eCommerce/ retail management preferred;\nKnowledge across SEM, Social Media and Affiliates;\nExperienced in cross-border marketplaces and eCommerce operations is absolutely advantage;\nGood in numerical sense;\nHard-working with positive attitude;\nAble to work under pressure and meet the deadlines;\nDetail-oriented, with a high level of accuracy and ability to process and analyze data;\nFast learner and willing to face challenges;\nStrong communication in written and spoken English, Cantonese, with Putonghua is an advantage;\nProficiency in MS Office including MS Excel.\n\n\nWe offer\n\n5 - day work week\nMedical Benefits\nAnnual Merit Bonus\nStaff Purchase Discounts\nStaff Recreation Activity\nShuttle Bus Service\nEducation Sponsorship\n\nInterested parties please send a full resume with current and expected salary by email by clicking\u00a0APPLY NOW:\n\nPlease visit our corporate website at\u00a0http://corp.sasa.com/en/home\u00a0to know more about us.\n\n(Sa Sa is an Equal Opportunity Employer and all qualified applicants will receive consideration for employment. Personal data collected will be kept confidential and used for recruitment purpose only.)", "employment_types": ["Full Time", "Permanent"], "selling_points": ["World's Leading Luxury Travel Retailer", "Work Life Balance, Five-day Work Week", "International & Dynamic Working Environment"], "locations": ["Quarry Bay"], "categories": ["Information Technology (IT)", "Product Management / Business Analyst", "E-commerce", "Marketing - Brand / Product Management", "Product Management / Business Analyst"], "post_time": "2022-01-11T02:55:06Z", "salary": {"currency": null, "max": null, "min": null, "period": "monthly", "term": null}, "salary_visible": false, "title_keywords": ["assistant manager,"], "responsibilities": ["operations", "fulfillment", "budget", "inventory management", "analyze business trends", "plans", "product categories", "teams", "monitor", "develop", "management", "consumer insights", "executing", "order forecast", "drive sales", "trade marketing", "order management", "strategic plans", "product mix and assortment planning", "preparing business analysis reports", "evaluate", "lead a team", "ad hoc projects", "sales plans"], "requirements": {"degrees": ["university graduate"], "majors": ["ecommerce"], "languages": ["cantonese", "putonghua", "english"], "language_level": ["advantage"], "hard_skills": ["ms excel", "sem", "ms office"], "soft_skills": ["detail-oriented", "positive attitude", "communication", "hard-working", "fast learner", "work under pressure"], "languages_combined": [{"language": "cantonese", "language_level": ["advantage"]}, {"language": "putonghua", "language_level": ["advantage"]}, {"language": "english", "language_level": ["advantage"]}]}, "experience_required": {"duration": ["at least 5 years"], "field": ["ecommerce", "management", "retail"]}}, {"job_id": "100003009039446", "location_code": "hk", "company": "Morgan McKinley", "job_title": "Senior UX/UI Manager", "description": "Assist Senior E-Commerce Manager to manage, develop and operate multiple E-commerce platforms for the company\n\nJob Duties and Responsibilities\n\nLiaise with different parties to ensure the delivery of accurate web content in a timely manner including storefront design, product shots, product information, promotion, stock levels\nHandle program and campaign launches to include but not limited to, Banner, Web-page design, EDM campaigns, Search engine, Social Media Marketing, and other leads\u00a0\nPlan out the website update schedule and prepare design briefs for graphic designer to produce on-brand graphics\u00a0\nWork closely with the product buying team to prepare for key retail seasonal cycles \u2013 season launches, sale and promotions\nFormulate digital marketing plan to improve website traffic and conversion rate\nLiaise with warehouse and 3rd party partner to ensure the delivery standard is met\nAssist customer service team to provide and maintain excellent customer and after-sales service\nUtilize site metrics tracking tools and dashboard to generate business intelligence reports for performance evaluation\nRequirements\n\nDegree holder preferably in MIS / E-Business / Marketing or other related disciplines\n3 years of relevant experience in E-commerce business management\nKnowledge in Facebook, Instagram, search engine marketing and Google tools, including Google Search Console, Google Analytics, Google AdWords etc. would be an advantage\nWell organized, efficient and ability to work independently\nExcellent communication skills, analytical and problem solving skills\nAble to work multi-tasks under pressure and deliver on schedule\nExperience in using Magento Community version is an advantage\nCandidate with less experience will be considered as E-Commerce Executive\n\n\u00a0We offer competitive remuneration package with\u00a0a wide range of fringe benefits including\n\n5-day work week\nDiscretionary Bonus\nComprehensive Medical Coverage\nStaff Shopping Discount\nNon-contributory Retirement Benefits Scheme\nBirthday Leave\nInterested parties please send resume with present and expected salary to Human Resources Department, Swire Resources Limited,\u00a012/F Kingston International Centre, 19 Wang Chiu Road Kowloon Bay, Hong Kong or by\u00a0clicking the below \"Apply Now\" button.\n\nSwire Resources Limited is Equal Opportunity Employer\n", "employment_types": ["Full Time", "Permanent"], "selling_points": ["International award-winning digital agency", "Supervise junior staff members", "Excellent communications & presentation skills"], "locations": ["Not Specified"], "categories": ["Marketing / Public Relations", "Marketing - Market Research", "E-commerce", "Marketing - Brand / Product Management", "Information Technology (IT)", "UI/UX Designer"], "post_time": "2022-01-11T09:47:27Z", "salary": {"currency": null, "max": null, "min": null, "period": "monthly", "term": null}, "salary_visible": false, "title_keywords": ["manager"], "responsibilities": ["graphics", "social media", "evaluation", "edm", "a timely manner", "website", "design", "design briefs", "customer service", "digital marketing", "schedule", "plan", "maintain", "liaise with", "after-sales service", "reports", "tracking"], "requirements": {"degrees": ["degree holder"], "majors": ["related disciplines", "business", "marketing"], "languages": [], "language_level": [], "hard_skills": ["business management", "google analytics", "e-commerce", "adwords", "facebook", "problem solving skills"], "soft_skills": ["efficient", "communication skills", "work independently", "under pressure", "multi-tasks", "well organized", "analytical and problem solving skills"], "languages_combined": []}, "experience_required": {"duration": ["3 years"], "field": ["management", "business", "relevant experience", "e-commerce"]}}, {"job_id": "100003009039245", "location_code": "hk", "company": "Sa Sa Dot Com Limited", "job_title": "Assistant eCommerce Manager", "description": "About Calioo\n\nCalioo is transforming the way people discover and experience food.\u00a0\n\nFounded by some of the most prominent leaders within the food tech industry in Asia, Calioo is Hong Kong\u2019s first and only online platform for specialty handcrafted foods. On our mobile app, customers can shop from 500+ (and growing!) small shops and local vendors.\u00a0\n\nJoin us in our mission of empowering our small business community and helping customers discover the latest and tastiest artisanal food!\u00a0\n\nThe Role\u00a0\n\nWe are now looking for a seasoned Senior Marketing Executive (minimum 3 years of work experience) to join our small, but fast-growing team to help take Calioo to the next level in Hong Kong, and eventually broader Southeast Asia. This is a fast-paced role with a lot of autonomy and one that requires strategic thinking and thoughtful execution.\u00a0\n\nYou will be responsible for ideating and executing marketing strategies that fuel growth for the business. You will need to quickly understand the target customer of Calioo, the various customer segments we have, and how to optimize every step of the customer funnel to drive awareness to acquisition to conversion to retention. Ultimately, your performance will be evaluated by your ability to drive performance metrics, including but not limited to: sales, orders, conversions, traffic, acquired customers, retention rate, app downloads, follower counts, and marketing ad KPIs.\n\nPotential Responsibilities\n\nMarketing Campaign Planning\u00a0\u2013 Ideate monthly marketing campaigns and events that will drive customer engagement and sales conversion, including promotional traffic-driving tactics (e.g., discounts, giveaways, sponsorships, collaborations, etc.)\u00a0\nSocial Media Management\u00a0\u2013 Plan social media marketing calendar and produce a diverse range of creative content that is relevant, educational, and / or engaging for our customer base, using visually appealing mediums (e.g., graphics, videos, etc.)\nMedia Coordination\u00a0\u2013 Manage communications and nurture relationships with PR, digital media, and influencer partners who help to showcase the value proposition of Calioo, ultimately amplifying brand awareness via earned media exposure\u00a0\nPaid Ad Strategy\u00a0\u2013 Create and execute a paid social ad strategy that generates the highest results (e.g., clicks, conversions, engagements, follows) at the lowest cost, and constantly A/B test and assess campaign analytics to improve results\nMarketing Analytics\u00a0\u2013 Understand key marketing ad KPIs (e.g., CTR, ROAS, CPA, CPC, etc.), effectively and comfortably analyze performance numbers, and use the insights to adjust ad strategies and budgets\nStrategic Partnerships\u00a0\u2013 Ideate and pitch to potential strategic and affiliate partners (within and outside of the F&B industry) and collaboratively develop co-marketing campaigns or initiatives that boost Calioo brand awareness and app downloads\nEmail Marketing \u2013 Build a repeatable email marketing sequence that retains existing customers and conduct A/B testing to increase eDM open rates (via engaging content and communication of marketing campaigns and promotions)\nOffline Marketing \u2013 Innovate new ways of attracting customers via out-of-home, traditional, and other offline methods (e.g., brick-and-mortar product placement, posters, direct mail, roadshows, flyering, etc.)\nMarketplace Events \u2013 Work collaboratively with internal teams (e.g., merchant team, events team, design team) to strategize and execute monthly physical marketplace selling events, with the goal of driving as much traffic as possible\nMarket Research\u00a0\u2013 Conduct research on trends, consumer preferences, and industry best practices (i.e., via online search, Google analytics and other free data tools, consumer surveys, etc.) to guide all marketing strategies listed above\n\nMust-Have Qualifications\n\nMinimum 3 years of work experience in a marketing-related role\nFamiliarity with any of the following sectors: F&B, startups, online marketplaces\u00a0\nAbility to work in a fast-paced and hard working environment\nSelf-motivated, takes initiative, ambitious, and embraces new challenges\nPassionate about solving problems and coming up with solutions every day\nExtremely creative and filled with big and bold ideas (an eye for design a plus)\nResourceful and can independently execute with minimal direction\nPositive attitude and high eagerness to learn quickly\nWorks collaboratively with team members and external partners\nHigh attention to detail, with logical reasoning and communication\nAnalytical, understands marketing KPIs, and comfortable with analyzing data\u00a0\u00a0\nResults-driven and constantly looking for ways to improve the business\nExcellent multi-tasking skills with flexibility to adapt to changing priorities\nKeeps up-to-date with consumer trends, industry news, and marketing strategies\nExcitement for being part of a fast-growing, early-stage startup\nWritten and verbal fluency in both English and Chinese", "employment_types": ["Full Time"], "selling_points": ["eCommerce channel in overseas marketplace", "Full spectrum of marketing and sales plans", "Free shuttle bus service"], "locations": ["Siu Sai Wan"], "categories": ["E-commerce", "Business Development", "Marketing - Brand / Product Management", "Product Management / Business Analyst"], "post_time": "2022-01-11T09:09:20Z", "salary": {"currency": null, "max": null, "min": null, "period": null, "term": null}, "salary_visible": false, "title_keywords": ["assistant ecommerce manager"], "responsibilities": ["ideas", "data", "design", "communication", "plan", "conduct research", "graphics", "mobile app", "creative content", "teams", "develop", "testing", "marketing campaigns", "kpis", "social media", "management", "cost", "marketing strategies", "edm", "executing", "consumer trends", "budgets", "performance metrics", "market research", "coordination", "planning"], "requirements": {"degrees": [], "majors": [], "languages": ["english", "chinese"], "language_level": ["fluency"], "hard_skills": ["small", "graphics", "google analytics", "plus", "mobile", "goal", "cpa"], "soft_skills": ["self-motivated", "independently", "strategic thinking", "responsible", "resourceful", "hard working", "driven", "bold", "communication", "diverse", "positive attitude", "coordination", "attention to detail", "multi-tasking skills", "creative", "initiative", "passionate about"], "languages_combined": [{"language": "english", "language_level": ["fluency"]}, {"language": "chinese", "language_level": ["fluency"]}]}, "experience_required": {"duration": ["minimum 3 years"], "field": ["related", "food", "marketing", "team"]}}, {"job_id": "100003009032602", "location_code": "hk", "company": "Swire Resources Ltd", "job_title": "E-Commerce Executive", "description": "The Omnichannel Project Manager will provide management, guidance and judgment on new project initiatives, with a focus on experience across stores and ecommerce. The position requires an understanding of all direct-to-consumer business functions; focused on ecommerce, retail, contact center operations and related systems. The ideal candidate will have experience in working across functions, instigating and coordinating project delivery, and possessing knowledge of standard business processes and related systems as well as order fulfillment processes.\n\nThis individual will manage the project work acting on variances from the plan as well as bringing the projects to closure, documenting project execution by creating a body of knowledge, and suggesting process improvements for future projects.\n\nUpon the completion of the initial connected retail infrastructure setup, the Omnichannel Manager will work closely with the retail, ecommerce, and contact center teams to develop on-going plans and business forecasts, driving optimization & growth initiatives based on data-driven performance insights.\n\n\n\nResponsibilities\n\nSupport in identifying new opportunities for Omni channel services, future digital in-store experiences and innovation to maximize customer retention and sales productivity.\nCoordinate Idea gathering, requirements, project deliverables, and targets\nDemonstrate broad knowledge of direct to consumer Customer Contact and ecommerce business processes, with working knowledge of retail and ecommerce systems\nPerforms the overall day-to-day management of the project to ensure that project objectives are achieved within time/cost/quality constraints\nResponsible for project documentation including project plan, status reports.\nWork with IT to ensure that project business and IT requirements are captured and documented via partnership with channel and function stakeholders.\nPerforms management of the risks of the project, including the development of contingency plans\nManage project scope and change control and escalate issues where necessary to remove team impediments\nSupport as needed Quality Assurance team to ensure that project is tested and that test plans are aligned with project requirements\nFacilitate project and update meetings\nAccountable for overall progress.\nEnsure project objectives are understood and met, ensuring that the Project Team members understand the requirements\nEnsure all groups are adequately consulted and are satisfied with each deliverable as it effects their specialist area\nTrack and report project actual expenditures as compared to the budget and effectively manage the project to successful completion within tolerances.\nManage multiple complex projects simultaneously\nEstablish new SOPs, algin roles & responsibilities across various functions\nOwn connected retail KPI and daily, weekly, monthly, quarterly reporting responsibilities\nManage omni channel order related business rules in the OMS and other internal systems\nEstablish strong partnerships with Retail Operations, Planning, and Contact Center teams to effectively plan and manage omni channel fulfillment volumes and customer experiences\n\nRequirements:\u00a0\n\nExperience managing, cross-functional digital commerce projects from inception to successful implementation\nAt minimum 5 years Direct to Consumer experience including retail stores, concessions, ecommerce with an understanding of order fulfillment processes preferred\nKnowledge of one or more: D365, SalesForce Commerce Cloud, IBM Sterling, MadMobile, plus.\nBachelors Degree or higher\nTrack record of project delivery and benefits realization\nBe able to demonstrate a proven track record managing multiple projects\nConversant in the nuances of the retail commerce landscape, with an ability to serve as a product expert when communicating project status to executive stakeholders and peers\nStrong interpersonal communication skills and problem-solving skills\nExcellent presentation and meeting leader skills\nStrong negotiation, organizational, and facilitation skills\nSelf-starter / self-motivated, capable of staying on track and pursuing solutions without supervision\nAble to prepare and present information in business terms\nAble to work under pressure, meet deadlines and handle multiple projects simultaneously.\nAdvanced Excel skills required\nAdvanced PowerPoint skills required\nMust be detail-oriented\nSkilled in developing effective partnership relationships with portfolio stakeholders\nExperience in the identification, assessment, and management of risks; able to manage the risks, not just the risk list\nExperience in strategic planning and analysis\nExceptional interpersonal and negotiation skills. Committed to providing excellent customer service\nDetermined to deliver outcomes and able to overcome obstacles in order to move forward. Accountable for the delivery of outcomes, strives to meet and exceed expectations\nHas a flexible approach to change, is able to work effectively in a variety of situations, constantly seeks improvements and is forward looking\nFluency in Japanese, Korean, or Mandarin highly valued\n\n\n", "employment_types": ["Full Time", "Permanent"], "selling_points": ["3 years of relevant experience in E-com management", "Experience in using Magento is an advantage", "Able to work multi-tasks under pressure"], "locations": ["Kowloon Bay"], "categories": ["Sales, CS & Business Devpt", "Retail Sales", "E-commerce", "Business Development", "Marketing - Brand / Product Management"], "post_time": "2022-01-07T11:48:27Z", "salary": {"currency": null, "max": null, "min": null, "period": "monthly", "term": null}, "salary_visible": false, "title_keywords": ["executive"], "responsibilities": ["project requirements", "actual expenditures", "operations", "fulfillment", "budget", "quality", "plan", "plans", "project documentation", "control", "teams", "day-to-day management", "reports", "internal systems", "report", "reporting", "cost", "management", "contact", "sops", "project deliverables", "systems", "project plan", "coordinate", "planning"], "requirements": {"degrees": ["degree"], "majors": [], "languages": [], "language_level": [], "hard_skills": ["plus", "salesforce"], "soft_skills": [], "languages_combined": []}, "experience_required": {"duration": ["minimum 5 years"], "field": ["ecommerce", "digital", "retail"]}}, {"job_id": "100003009033424", "location_code": "hk", "company": "Calioo Technologies", "job_title": "Senior Marketing Executive", "description": "Associate/assistant manager\n\nThe Hong Kong Investment Funds Association (\u201cHKIFA\u201d) is a non-profit-making organization that represents the fund management industry in Hong Kong.\u00a0 www.hkifa.org.hk.\u00a0 We aim to recruit a high caliber candidate who will play a key role in the following areas.\n\nThe main responsibilities include, amongst others:\n\nlCo-ordinating meetings for committees/working groups;\n\nlPreparing minutes/notes; and providing support to the committees/working groups to implement the resolutions;\u00a0\u00a0\n\nlWorking with vendors to support the maintenance of the website, social media, apps and other relevant communication channels;\n\nlPreparing, managing and updating educational and communication materials (e.g. press releases, investor education materials, communications with members/other stakeholder groups) for distribution and posting on/via various channels; and\n\nlHandling co-ordination and administrative tasks.\n\nAttributes and qualities:\n\nl\u00a0\u00a0 University graduate;\n\nl\u00a0 Solid experience in managing website, social media, apps as well as other communications channels (experience in mainland related ones a plus);\u00a0 \u00a0\n\nl\u00a0\u00a0 Strong writing skills \u2013 both English and Chinese; and\n\nl\u00a0\u00a0 Meticulous and have excellent PC skills.\n\nInterested parties please email to Hong Kong Investment Funds Association\n\n\u00a0(Personal data collected will be used for recruitment purpose only.)", "employment_types": ["Full Time"], "selling_points": [], "locations": ["Causeway Bay"], "categories": ["Hospitality / F & B", "Food & Beverage", "Marketing / Public Relations", "Digital Marketing", "E-commerce", "Marketing - Brand / Product Management"], "post_time": "2022-01-09T15:28:19Z", "salary": {"currency": null, "max": null, "min": null, "period": null, "term": null}, "salary_visible": false, "title_keywords": ["senior marketing executive"], "responsibilities": ["social media", "management", "communications with", "maintenance", "website", "communication", "providing support", "administrative tasks"], "requirements": {"degrees": ["university graduate"], "majors": [], "languages": ["english", "chinese"], "language_level": [], "hard_skills": ["plus", "pc skills", "maintenance", "writing skills"], "soft_skills": ["communication", "meticulous", "writing skills"], "languages_combined": [{"language": "english", "language_level": []}, {"language": "chinese", "language_level": []}]}, "experience_required": {"duration": [], "field": ["related", "social media"]}}, {"job_id": "100003009038769", "location_code": "hk", "company": "Ralph Lauren", "job_title": "Omnichannel Project Manager", "description": "\u00a0**Professional development\n\nEducate clients mindset on investment and insurance products\nRecommend the right product to the right customers to fulfill Risk & Wealth Management\nRegular Review with clients including Claims and goals setting\n\nMPF Consulting & Integration\nGeneral Insurance Service\nIn-depth\u00a0understanding of current Socioeconomic Environment\n\n**Profitable return\n\nHongKongerTeam\n\n24 months financial support (Monthly support from 15,000 to 40,000) + Unlimited Commission\n9 bonus every year\nAll-rounded on-Job Training\nGroup Medical & MPF\nCompany convention to an overseas trip\nBuild up Team and Leadership\n\n**Requirements\n\nHKID holder\nUniversity Degree Holder/ Associate-Degree Holder/ High-Diploma\u00a0Holder\nTeam Spirit, Sincere on learning, hard-working, Positive thinking & attitude\nGood communication skill\n\n**If you wanna join us, please click \u201c Apply \u201d and work with us, you will never get alone.\n[All personal information collected would be used for recruitment purpose only.]\n\n", "employment_types": ["Full Time", "Permanent"], "selling_points": ["APAC Focus", "E-commerce/ Omni-channel", "Project management"], "locations": ["Tsim Sha Tsui"], "categories": ["E-commerce", "Business Development", "Marketing - Brand / Product Management", "Product Management / Business Analyst"], "post_time": "2022-01-11T07:46:33Z", "salary": {"currency": null, "max": null, "min": null, "period": "monthly", "term": null}, "salary_visible": false, "title_keywords": ["project manager"], "responsibilities": ["management", "mpf", "consulting", "regular review", "communication", "recruitment", "insurance"], "requirements": {"degrees": ["diploma holder", "university degree", "degree holder"], "majors": [], "languages": [], "language_level": [], "hard_skills": ["integration"], "soft_skills": ["team spirit", "sincere", "communication skill", "positive thinking", "learning", "hard-working", "leadership"], "languages_combined": []}, "experience_required": {"duration": [], "field": []}}, {"job_id": "100003009036908", "location_code": "hk", "company": "Hong Kong Investment Funds Association", "job_title": "Associate/assistant manager", "description": "Responsibilities:\n\n\n\nPlan on marketing strategy, from idea generation to campaign execution to drive growth.\nWork closely with the creative team in delivering marketing material, provide strategic social media advice and guidance.\nSupport partners\u2019 marketing campaigns in a timely and professional manner\nMonitor marketing performance to identify new business opportunities.\u00a0\nBuild strong client relationships with partners for customer success and satisfaction\nSupport on ad hoc projects\n\n\n\n\nRequirements:\n\nPassionate in digital marketing and FinTech\nMin. of 3 years experience in digital marketing, agency background with account servicing experience will be preferred\nGood understanding in digital marketing and keep abreast of the trend\nExperience in content marketing and copywriting is highly desirable\nKnowledge on and good communication in campaign management\nAggressive, self-motivated and result oriented\nAble to multi-tasks with excellent time management skills\nFluent in Cantonese and English\nCandidate with more experience will be considered for Senior Marketing Executive\n\n\n", "employment_types": ["Full Time"], "selling_points": ["excellent writing skills - Eng/Chin", "solid experience in website/social media", "excellent PC skills"], "locations": ["Central"], "categories": ["Marketing / Public Relations", "Public Relations - General / Support", "Sales, CS & Business Devpt", "Channel / Distribution", "E-commerce", "Marketing - Brand / Product Management"], "post_time": "2022-01-10T23:11:58Z", "salary": {"currency": null, "max": null, "min": null, "period": "monthly", "term": null}, "salary_visible": false, "title_keywords": ["assistant manager", "associate"], "responsibilities": ["guidance", "social media", "business opportunities", "professional manner", "monitor", "ad hoc projects", "plan", "marketing campaigns", "marketing material"], "requirements": {"degrees": [], "majors": [], "languages": ["cantonese", "english"], "language_level": ["fluent"], "hard_skills": [], "soft_skills": ["passionate", "self-motivated", "multi-tasks", "time management skills", "communication", "result oriented"], "languages_combined": [{"language": "cantonese", "language_level": ["fluent"]}, {"language": "english", "language_level": ["fluent"]}]}, "experience_required": {"duration": ["of 3 years"], "field": ["agency", "account servicing", "marketing", "digital marketing", "copywriting"]}}, {"job_id": "100003009035691", "location_code": "hk", "company": "AXA China Region Insurance Company Limited", "job_title": "AXA Prime Program Trainee", "description": "My client is an international retail brand with focus on technolody and they are looking for a Senior Multimedia Designer to join their team.\n\nResponsibilities:\n\nExecute creative solutions that meet the brand goals by translating concepts into exciting visuals.\nProduce sophisticated design aesthetic that lends well to online platforms, ecommerce &digital marketing media including, but not limited to site content, direct email marketing and social media, social media advertising and video / multimedia, across the brands\u2019 online presence\nResponsible for visual effects, editing and video production.\nMaintain strict personal and group goals and deadlines to ensure that the entire marketing development workflow is on schedule and brand standards\nRetouch product images achieved directly through agency or global images when needed\n\nRequirements:\n\nBachelor\u2019s Degree in Design / Graphic / Arts\nGood interpersonal and communication abilities\nKnowledge of design-related applications and software (eg Adobe Creative Suite, Final Cut Pro, Adobe After Effects, Adobe Premiere Pro, 3D Max, Cinema 4D etc.)\n3D Max knowledge would be a huge plus.\nKnowledge in Front-End Programming HTML, JavaScript, GIF Animation, Digital Banner etc. will be a plus\nProficient in English and Chinese", "employment_types": ["Full Time"], "selling_points": ["You seek for Work - Life balance here", "We will teach the skill when you start up here", "Office in Kwun Tong. Fluent in English or Canton"], "locations": ["Kwun Tong"], "categories": ["Sales, CS & Business Devpt", "Business Development", "Others", "Student / Fresh Graduate / No Experience", "E-commerce", "Marketing - Brand / Product Management"], "post_time": "2022-01-11T04:06:55Z", "salary": {"currency": null, "max": null, "min": null, "period": "monthly", "term": null}, "salary_visible": false, "title_keywords": ["trainee"], "responsibilities": ["social media", "advertising", "video production", "design", "maintain", "digital marketing", "schedule", "visual", "editing"], "requirements": {"degrees": ["degree", "bachelor"], "majors": ["design"], "languages": ["english", "chinese"], "language_level": ["proficient"], "hard_skills": ["final cut pro", "plus", "html", "adobe premiere pro", "adobe after effects", "javascript", "programming", "max", "adobe creative suite"], "soft_skills": ["communication", "creative", "interpersonal"], "languages_combined": [{"language": "english", "language_level": ["proficient"]}, {"language": "chinese", "language_level": ["proficient"]}]}, "experience_required": {"duration": [], "field": []}}]