[{"job_id": "100003009052350", "location_code": "hk", "company": "RPT International Limited", "job_title": "Ecommerce Assistant", "description": "Job description and responsibilities\n- Handle daily ecommerce operation such as online customer service and order fulfillment.\u00a0\n- Update information in our online shop backend.\n- Some product research.\n\nJob requirements\n- Form 6 graduate or above.\n- Good command in written and spoken Cantonese and English.\n- Proactive, ability to multi-task and work under pressure.\n- Good interpersonal, communication skills.\n\n", "employment_types": ["Full Time"], "selling_points": [], "locations": ["Kwun Tong"], "categories": ["Sales, CS & Business Devpt", "Customer Service - Supervisor / Officer", "Merchandising & Purchasing", "Others", "E-commerce", "Others"], "post_time": "2022-01-17T02:53:04Z", "salary": {"currency": null, "max": null, "min": null, "period": "monthly", "term": null}, "salary_visible": false, "title_keywords": ["assistant"], "responsibilities": ["order fulfillment", "online customer service"], "requirements": {"degrees": [], "majors": [], "languages": ["cantonese", "english"], "language_level": ["good command"], "hard_skills": [], "soft_skills": ["communication skills", "multi-task", "proactive", "interpersonal", "work under pressure"], "languages_combined": [{"language": "cantonese", "language_level": ["good command"]}, {"language": "english", "language_level": ["good command"]}]}, "experience_required": {"duration": [], "field": []}}, {"job_id": "100003009051842", "location_code": "hk", "company": "Stylevana", "job_title": "Part-time eCommerce Customer Service Officer (English Speaking)", "description": "Job Responsibilities:\n\nProvide excellent customer service to e-commerce customers\nUse phone, instant messaging and email to provide fast response to customer enquiries on products, order status and after sales services\nManage order processing cycle with other departments\nHelping customers in the online buying journey\nHelping customers to resolve any post-sales issues\u00a0\n\nJob Requirements:\n\nExcellent customer services experience using phone, instant messaging and email\nMust be proficient in written and verbal English.\nAsian Beauty and Skincare products knowledge or experience is a benefit\nMust have strong attention to details and customer focus\nWilling to work in between 16 \u2013 24 hours per week (Monday to Friday)\nAble to work independently, autonomously as well as multi-task working\nImmediately available preferred\nFresh graduates will also be considered\nKnowledge of any European language would be an advantage, but not necessary\nWe offered a fun and friendly team environment. Our standard working hour is five (5) days with flexible working hour.\u00a0The right candidates or interested parties should send full resume with available date, present and expected salary to our email\u00a0or clicking \u201cApply Now\u201d for an interview.", "employment_types": ["Part Time"], "selling_points": ["eCommerce Customer Services", "Asian Beauty and Skincare products", "Knowledge of any European language is a plus"], "locations": ["Kwai Hing"], "categories": ["Sales, CS & Business Devpt", "Customer Service - Supervisor / Officer", "Beauty Care / Health", "Others", "E-commerce", "Others"], "post_time": "2022-01-17T01:20:54Z", "salary": {"currency": null, "max": null, "min": null, "period": "hourly", "term": null}, "salary_visible": false, "title_keywords": ["customer service officer"], "responsibilities": ["customer enquiries", "customer service", "order processing"], "requirements": {"degrees": [], "majors": [], "languages": ["english"], "language_level": ["proficient"], "hard_skills": ["focus"], "soft_skills": ["customer focus", "work independently", "multi-task", "attention to details"], "languages_combined": [{"language": "english", "language_level": ["proficient"]}]}, "experience_required": {"duration": [], "field": ["beauty", "customer services"]}}, {"job_id": "100003009052754", "location_code": "hk", "company": "Taste of Asia Group Limited", "job_title": "E-commerce Specialist", "description": "E-commerce SpecialistJob Highlights\nFive-day work week\nMedical & dental allowance\nPerformance bonus\n\nJob Description\n\n\u00b7 To build a B2B E-commerce platform from zero, ensure it is deliverable. Must be knowledgeable and multitask in sales, marketing, operation, logistics...etc. across different field\n\n\u00b7 To support development and implementation of a new-built B2B E-commerce platform towards company\u2019s vision, roadmap and strategy\u00a0\n\n\u00b7 To develop standard operation procedures, deliver user training and launch new e-Commerce channels and logistics\u00a0\n\n\u00b7 To work with internal and external stakeholders on the new E-commerce platform delivery, knowledge transfer workshop, and KPI monitoring\n\n\u00b7 To act as an ambassador and coordinate internal/external stakeholders with a strong sense of communication, and off-site visit is required whenever necessary\u00a0\n\n\u00b7 To optimize the group\u2019s end-to-end E-commerce journey by devising a new solution, service, or proposition\u00a0\n\n\u00b7 To identify and implement new opportunities throughout the E-commerce journey to deliver high-performing, agile stakeholder interactions and touchpoints.\u00a0\n\n\u00b7 To collaborate with the management team on the next wave of company\u2019s E-commerce strategies\u00a0\n\nJob Requirement\n\n\u00b7 Degree in Business Management / E-commerce / Computer Science / I.T. or related disciplines\n\n\u00b7 Minimum 2-3 years working experience in E-commerce, IT background is an advantage\n\n\u00b7 Experience in working with system UAT / UX / UI is preferable\u00a0\n\n\u00b7 Analytical with excellent business and market sense\n\n\u00b7 Confident in approaching new products / business model / concepts / solutions\u00a0\n\n\u00b7 Good command of spoken and written English and Chinese\n\n\u00b7 Independent, good interpersonal communication skills, able to work with critical timelines and challenges\u00a0\n\n\u00b7 Deep understanding of commercial levers in driving performance and growth\u00a0\n\nJob location: San Po Kong\n\nCompetitive remuneration package and benefits as below:\n\nFive-day work week / Marriage leave / Staff discount / Medical & dental allowance / Performance bonus / In-service training course / 5 days paternity leave / Compassionate Leave / Promotion opportunities", "employment_types": ["Full Time"], "selling_points": ["Five-day work week", "Medical & dental allowance", "Performance bonus"], "locations": ["Wong Tai Sin Area"], "categories": ["Information Technology (IT)", "Software Development", "E-commerce", "Supply Chain", "Others"], "post_time": "2022-01-17T03:55:55Z", "salary": {"currency": null, "max": null, "min": null, "period": "monthly", "term": null}, "salary_visible": false, "title_keywords": ["specialist"], "responsibilities": ["collaborate with", "management team", "workshop", "monitoring", "procedures", "implementation", "e-commerce strategies", "develop", "coordinate", "communication", "logistics", "e-commerce platform"], "requirements": {"degrees": ["degree"], "majors": ["business", "computer science", "e-commerce"], "languages": ["english", "chinese"], "language_level": ["good command"], "hard_skills": ["business management", "e-commerce"], "soft_skills": ["confident", "communication skills", "independent", "deep", "interpersonal"], "languages_combined": [{"language": "english", "language_level": ["good command"]}, {"language": "chinese", "language_level": ["good command"]}]}, "experience_required": {"duration": ["minimum 2-3 years"], "field": ["it", "e-commerce"]}}, {"job_id": "100003009044797", "location_code": "hk", "company": "\u9304\u665f\u7db2\u7d61\u79d1\u6280(\u6df1\u5733)\u6709\u9650\u516c\u53f8", "job_title": "E-commerce operation", "description": "Requirements\n\n\u2022 Proven work track record as a E-commerce operation executive or similar role; experience in international sales would be preferred\n\u2022 \u5177\u6709\u96fb\u5b50\u5546\u52d9\u904b\u71df\u6216\u985e\u4f3c\u89d2\u8272\u7684\u7d93\u8b49\u5be6\u7684\u5de5\u4f5c\u8a18\u9304\uff1b\u6709\u570b\u969b\u92b7\u552e\u7d93\u9a57\u8005\u512a\u5148\n\n\u2022 Able to handle and manage data entries\n\u2022 \u80fd\u5920\u8655\u7406\u548c\u7ba1\u7406\u6578\u64da\u689d\u76ee\n\n\u2022 Analytical mindset and critical thinking\n\u2022 \u5177\u6709\u5206\u6790\u601d\u7dad\u548c\u6279\u5224\u6027\u601d\u7dad\n\n\u2022 Excellent communication and interpersonal skills\n\u2022 \u5177\u6709\u512a\u79c0\u7684\u6e9d\u901a\u548c\u4eba\u969b\u4ea4\u5f80\u80fd\u529b\n\n\u2022 Required language (s): English, Mandarin and Cantonese\n\u2022 \u6240\u9700\u8a9e\u8a00\uff1a\u82f1\u8a9e\u3001\u666e\u901a\u8a71\u548c\u7cb5\u8a9e\n\n\u2022 Able to multi-task using computer and mobile\n\u2022 \u80fd\u5920\u9032\u884c\u591a\u4efb\u52d9\u8655\u7406\n\n\u2022 Responsible, hardworking, detail-oriented attitude\n\u2022 \u6709\u8cac\u4efb\u5fc3,\u52e4\u596e,\u7d30\u5fc3,\u8b39\u614e\n\nJob Responsibilities\n\n\u2022 Manage daily e-commerce operations: order processing and shipment fulfilment\n\u2022 \u8ca0\u8cac\u96fb\u5546\u7684\u65e5\u5e38\u904b\u4f5c\uff1a\u8a02\u55ae\u8655\u7406\u548c\u7269\u6d41\u5b89\u6392\n\n\u2022 Manage e-commerce related RMA process, from physical stock inspection to repair coordination\n\u2022 \u8ca0\u8cac\u5ba2\u6236\u9000\u8ca8\u548c\u7dad\u4fee\uff1a\u7522\u54c1\u6aa2\u9a57\uff0c\u5be9\u6838\u9000\u8ca8\uff0c\u4e0e\u7269\u6d41\u914d\u5408\u9000\u8ca8\u6d41\u7a0b\n\n\u2022 Perform before and after-sales customer service\n\u2022 \u8ca0\u8cac\u5ba2\u6236\u552e\u524d\u548c\u552e\u5f8c\u670d\u52d9\n\n\u2022 Manage, cross-check and follow-up on sales and purchase orders, deliveries, returns, warranty requirements and general enquiries\n\u2022 \u8ca0\u8cac\u8a02\u55ae\u5be9\u6838\uff0c\u8a02\u55ae\u8655\u7406\u767c\u8ca8\uff0c\u8ca8\u54c1\u8a02\u55ae\u548c\u7269\u6d41\u914d\u5c0d\n\n\u2022 To work closely and harmoniously with internal colleagues to ensure an effective and efficient operation\n\u2022 \u8207\u5167\u90e8\u540c\u4e8b\u7dca\u5bc6\u548c\u8ae7\u5730\u5408\u4f5c\uff0c\u4ee5\u78ba\u4fdd\u6709\u6548\u548c\u9ad8\u6548\u7684\u904b\u4f5c\n\n\u2022 Co-manage in other part of operations related to e-commerce\n\u2022 \u5354\u52a9\u4e00\u5207\u96fb\u5546\u76f8\u95dc\u7684\u6587\u4ef6\u5de5\u4f5c\n\n\u2022 Assist in other administrative work in office\n\u2022 \u8ca0\u8cac\u4e00\u822c\u6587\u8077\u5de5\u4f5c\u5305\u62ec\u6587\u66f8\u8655\u7406\u4ee5\u53ca\u8fa6\u516c\u5ba4\u65e5\u5e38\u4e8b\u52d9\n\n", "employment_types": ["Full Time", "Contract"], "selling_points": ["Big data, AI, blockchain", "International team", "Stage for young people"], "locations": ["Tsim Sha Tsui"], "categories": ["E-commerce", "Others"], "post_time": "2022-01-13T18:55:03Z", "salary": {"currency": null, "max": null, "min": null, "period": "monthly", "term": null}, "salary_visible": false, "title_keywords": [], "responsibilities": ["administrative work", "operations", "inspection", "repair", "customer service", "purchase", "coordination", "order processing"], "requirements": {"degrees": [], "majors": [], "languages": ["cantonese", "english", "mandarin"], "language_level": [], "hard_skills": ["mobile", "e-commerce"], "soft_skills": ["multi-task", "responsible", "detail-oriented", "communication and interpersonal skills", "hardworking"], "languages_combined": [{"language": "cantonese", "language_level": []}, {"language": "english", "language_level": []}, {"language": "mandarin", "language_level": []}]}, "experience_required": {"duration": [], "field": []}}, {"job_id": "100003009052336", "location_code": "hk", "company": "KW-Commerce Asia Limited", "job_title": "Supply Chain Planner", "description": "Responsibilities:\u4e00\u822c\u6587\u8077\u5de5\u4f5c,\u5ba2\u6236\u67e5\u8a62,\u5831\u8868\u88fd\u4f5c,\u6574\u7406\u5009\u5b58,\u8ca8\u54c1\u6536\u767c,\u5354\u52a9\u5b9a\u671f\u76e4\u9ede\n\nRequirements :Secondary 5; 2 Year(s) Experience Required; Fluent Cantonese ; Fair English ; Able to read & write Chinese ; Able to read & write English ; Microsoft Office; \u52e4\u596e,\u6709\u8cac\u4efb\u5fc3\n\nEmployment Terms:Bank Holiday, Birthday Leave and Overtime Allowance, Mon to Fri: 9:00AM-6:00PM and Sat: 9:00AM-1:00PM, 5.5 working days per week\n\nApplication Information:Job seekers may e-mail(Apply Now) resume to TIMES EXPRESS LIMITED. To obtain a copy of Personal Information Collection Statement, please contact MS LEUNG by Email.", "employment_types": ["Full Time", "Permanent"], "selling_points": ["Talented Fresh Graduates would be considered", "Flexible working hours and work-from-home option", "Work with people who are friendly and supportive"], "locations": ["Kwai Fong"], "categories": ["E-commerce", "Supply Chain", "Others"], "post_time": "2022-01-17T02:48:13Z", "salary": {"currency": null, "max": null, "min": null, "period": "monthly", "term": null}, "salary_visible": false, "title_keywords": ["supply chain planner"], "responsibilities": [], "requirements": {"degrees": [], "majors": [], "languages": ["cantonese", "english", "chinese"], "language_level": ["fluent"], "hard_skills": ["microsoft office"], "soft_skills": [], "languages_combined": [{"language": "cantonese", "language_level": ["fluent"]}, {"language": "english", "language_level": []}, {"language": "chinese", "language_level": []}]}, "experience_required": {"duration": [], "field": []}}, {"job_id": "100003009052805", "location_code": "hk", "company": "Times Express Limited", "job_title": "Senior Assistant - Operations", "description": "DCH is an integrated motor and consumer products company that brings quality products to Hong Kong, PRC and the South East Asia markets. With a strong commitment to deliver exceptional OMO (online-merge-offline) experience to consumers, a new e-commerce team is setup to lead and orchestrate the OMO strategy for the Group. We are now inviting talented candidates who have an entrepreneurial mindset and passion in e-commerce to join our digital transformation journey.\u00a0\n\nResponsibilities:\n\nPlan and manage marketing campaigns on e-marketplaces within budget and on schedule to achieve target metrics/KPIs\nAnalyze and report on the performance of campaigns including actionable insights for enhancement and optimization of communication.\nCollaborate with various internal and external teams to implement marketing campaigns\nPlan and prepare digital marketing content in various formats (web, social media, app, etc.)\nPrepare regular reports to analyze campaign performance\nConduct competitive analysis and provide recommendations based on competitive reviews, learnings, and industry best practice\nLead and develop eCommerce initiatives, partnership, and execute quality content for eCommerce platform\nPerform ad-hoc marketing projects and duties as assigned\nWork closely with e-marketplaces like HKTV mall, Zstore, Foodpanda, etc.\n\nRequirements:\n\nUniversity undergraduate in Marketing, Journalism, Multi-media, Business or related disciplines\nMinimum 4 years of relevant experience with proven record in e-commerce marketing especially in e-marketplaces campaign planning\nExperience in HK e-marketplaces like HKTV mall, Zstore, etc. are highly preferred\nCreative, energetic, self-motivated, able to work in a fast-paced and dynamic environment\nCan-do attitude, good at problem-solving\nOrganized with good project management skills\nAttention to detail with good interpersonal and communication skills\nExperience in social media, digital marketing, and/or e-commerce highly preferred\nProficient in written and spoken English and Chinese including Putonghua\nProficient in MS Office including Word, Excel, PowerPoint and Chinese Word Processing\n\nWe offer competitive salary, discretionary bonus, medical insurance, life and personal accident insurance, annual leave and staff purchase discount. Interested candidates please send your resume with salary expectation by email or clicking \u201cApply Now\u201d.\n\nWe are equal opportunities employer. Applicants who are not invited within 2 months may consider their application unsuccessful. All applicants may be considered for other suitable positions with DCH Group / CITIC Pacific Group and will be deleted from our files after 6 months from the date of application.", "employment_types": ["Full Time"], "selling_points": ["Secondary 5 or above", "2 Years Experience Required", "Bank Holiday"], "locations": ["Shatin Area"], "categories": ["E-commerce", "Others"], "post_time": "2022-01-17T04:07:03Z", "salary": {"currency": null, "max": null, "min": null, "period": "monthly", "term": null}, "salary_visible": false, "title_keywords": ["operations", "assistant"], "responsibilities": ["collaborate with", "social media", "ad-hoc", "analysis", "budget", "teams", "quality", "marketing projects", "develop", "communication", "digital marketing", "schedule", "marketing campaigns", "plan", "reports", "kpis", "provide recommendations", "report"], "requirements": {"degrees": [], "majors": [], "languages": ["putonghua", "english", "chinese"], "language_level": ["proficient"], "hard_skills": ["excel", "chinese word processing", "e-commerce", "problem-solving", "word", "powerpoint", "project management", "dynamic", "ms office"], "soft_skills": ["organized", "self-motivated", "dynamic environment", "communication skills", "creative", "can-do attitude", "project management skills", "problem-solving", "attention to detail", "energetic", "interpersonal"], "languages_combined": [{"language": "putonghua", "language_level": ["proficient"]}, {"language": "english", "language_level": ["proficient"]}, {"language": "chinese", "language_level": ["proficient", "proficient"]}]}, "experience_required": {"duration": ["minimum 4 years"], "field": ["social media", "e-commerce", "marketing", "relevant experience", "digital marketing", "planning"]}}, {"job_id": "100003009051756", "location_code": "hk", "company": "E-Teklon Company Limited", "job_title": "Sales & Marketing Assistant", "description": "Daily posts for the social media (including photography, wordings, and interaction with our TA)\nHandling customer service\nProduct Upload on different platforms\nArranging shipment & packaging for web sales orders\nAssist in running all different platforms and adopted our brand smoothly into the market\nAssist in product sourcing\u00a0\nHave good computer knowledge, such as PowerPoint, Photoshop, etc.\nRequire to report to work after CNY\n\nData collected will be used for recruitment purposes only.", "employment_types": ["Full Time"], "selling_points": ["Good skills in social media platforms", "Experience in Web sales and Marketing", "Team Player"], "locations": ["Kowloon Bay"], "categories": ["Marketing / Public Relations", "Marketing - General / Support", "E-commerce", "Marketing - Brand / Product Management", "Others"], "post_time": "2022-01-17T00:39:46Z", "salary": {"currency": null, "max": null, "min": null, "period": "monthly", "term": null}, "salary_visible": false, "title_keywords": ["marketing assistant", "sales"], "responsibilities": ["social media", "data", "customer service", "recruitment", "product upload", "report"], "requirements": {"degrees": [], "majors": [], "languages": [], "language_level": [], "hard_skills": ["web sales", "powerpoint", "photoshop"], "soft_skills": ["customer service"], "languages_combined": []}, "experience_required": {"duration": [], "field": []}}, {"job_id": "100003009051642", "location_code": "hk", "company": "Hong Kong Trade Development Council", "job_title": "Project Executive", "description": "Ref. No.: 318/PJE/MTI2/HKTDC\n\nResponsibilities:\n\nTo provide clerical and administrative support to the Project Managers in high-level bilateral meetings and events related to Consulate relations\nTo assist Project Managers in overall planning and execution of local and overseas trade promotional events related to merchandise trade\nTo provide logistic support and recruit participants for trade promotional projects\nTo handle enquiries from event participants and undertake on-site duties\nTo liaise and maintain good relations with relevant industry and trade associations\n\nRequirements:\n\nProactive, self-initiated and very attentive to details\nMature, creative, with team work spirits\nMeticulous and detail-minded\nWillingness to work long hours to meet tight deadlines\nStrong command of spoken and written English and Chinese. Fluent in Putonghua\nProficiency in MS applications and Chinese word-processing\nCustomer-oriented with good communication and interpersonal skills in dealing with people from all levels\nSolid prior experience in event management will be an advantage\n\nRemuneration and Benefits:\nThe successful candidate will be appointed on a fixed-term contract basis, renewable subject to operational needs. Salary will be commensurate with qualifications and experience.\u00a0\u00a0\n\nApplication Procedure:\n\nInterested candidates are invited to complete the application form on our website at http://www.hktdc.com/careers.html\u00a0on or before 4 February 2022. Those who do not hear from us within EIGHT WEEKS after the closing date may assume their applications unsuccessful.\n\nAll information provided by applicants will be treated in strict confidence and used only for recruitment purposes. Applicants may be considered for other suitable positions within the Council. Their personal data will be destroyed six months after the selection is finalised.\n\n\n%MCEPASTEBIN%", "employment_types": ["Full Time", "Contract"], "selling_points": ["Clerical & Admin Support", "event participants and undertake on-site duties", "Good interpersonal and communication skills"], "locations": ["Wan Chai"], "categories": ["E-commerce", "Business Development", "Product Management / Business Analyst", "Others"], "post_time": "2022-01-16T17:27:50Z", "salary": {"currency": null, "max": null, "min": null, "period": "monthly", "term": null}, "salary_visible": false, "title_keywords": ["project executive"], "responsibilities": ["liaise", "administrative support", "logistic support", "handle enquiries", "maintain", "planning"], "requirements": {"degrees": [], "majors": [], "languages": ["putonghua", "english", "chinese"], "language_level": ["proficiency", "fluent"], "hard_skills": ["ms applications", "chinese word-processing"], "soft_skills": ["detail-minded", "meticulous", "meet tight deadlines", "creative", "attentive to details", "mature", "customer-oriented", "communication and interpersonal skills", "willingness to work", "proactive"], "languages_combined": [{"language": "putonghua", "language_level": ["fluent"]}, {"language": "english", "language_level": []}, {"language": "chinese", "language_level": ["proficiency"]}]}, "experience_required": {"duration": [], "field": ["management"]}}, {"job_id": "100003009054616", "location_code": "hk", "company": "Klook Travel Technology Limited", "job_title": "Manager, Corporate Finance", "description": "At Klook, we love creating moments of joy. Our platform connects people around the world with experiences that bring a smile to their faces, at a touch of a button. We are a global team of diverse Klookers who push boundaries every day, learn fast with feedback and take ownership to drive the change we want to see. Together, we help each other make the world a more joyful place. Up for the challenge? Join us today!\n\n\nWhat you'll do\n\nYou will be an integral part of the corporate finance team in formulating Klook\u2019s corporate strategy\nLead investment, financing, corporate development, and investor relations related projects\nWork closely with various business units and operations teams to analyze business performance and operational data\nAlign and manage strategic objectives with internal stakeholders including senior management\nIdentify and evaluate new business initiatives (including investment), and manage project teams during the execution\u00a0\nConduct market intelligence research to deliver impactful and actionable insights;\nDevelop models, tools, and processes to support our fast-growing business as it evolves\n\nWhat you\u2019ll need\n\n3-5 years of experience preferably in corporate development, investment banking, or management consulting for tech or consumer businesses.\nGood business / data analytical and problem-solving abilities.\nSophisticated project management skills\nIntellectual curiosity and ready to learn new skills.\nStrong communication and coordination skills.\nGlobally-minded and comfortable working with people from different cultural backgrounds and in different time zones.\nA start-up attitude - highly collaborative with an entrepreneurial, \u2018roll-up-your sleeves' attitude", "employment_types": ["Full Time"], "selling_points": ["Friendly & flexible working culture", "Global organization", "Corporate Finance"], "locations": ["Central"], "categories": ["Banking / Finance", "Analyst", "Corporate Finance", "E-commerce", "Others"], "post_time": "2022-01-17T10:17:09Z", "salary": {"currency": null, "max": null, "min": null, "period": "monthly", "term": null}, "salary_visible": false, "title_keywords": ["manager", "corporate finance"], "responsibilities": ["management", "business initiatives", "consulting", "data", "operations", "teams", "develop", "evaluate", "project management", "communication", "finance team", "coordination", "banking", "senior management"], "requirements": {"degrees": [], "majors": [], "languages": [], "language_level": [], "hard_skills": ["make", "problem-solving", "joy", "project management"], "soft_skills": ["sophisticated", "coordination skills", "project management skills", "problem-solving", "collaborative", "communication", "diverse"], "languages_combined": []}, "experience_required": {"duration": ["3-5 years"], "field": ["management", "consulting", "development", "tech", "investment", "banking"]}}, {"job_id": "100003009055257", "location_code": "hk", "company": "Dah Chong Hong Holdings Limited", "job_title": "Senior Digital Marketing Executive (Marketplaces) (Ref: ECom-MKP)", "description": "DCH is an integrated motor and consumer products company that brings quality products to Hong Kong, PRC and the South East Asia markets. With a strong commitment to deliver exceptional OMO (online-merge-offline) experience to consumers, a new e-commerce team is setup to lead and orchestrate the OMO strategy for the Group. We are now inviting talented candidates who have an entrepreneurial mindset and passion in e-commerce to join our digital transformation journey.\u00a0\n\nResponsibilities:\n\nPlan and manage marketing campaigns on e-marketplaces within budget and on schedule to achieve target metrics/KPIs\nAnalyze and report on the performance of campaigns including actionable insights for enhancement and optimization of communication.\nCollaborate with various internal and external teams to implement marketing campaigns\nPlan and prepare digital marketing content in various formats (web, social media, app, etc.)\nPrepare regular reports to analyze campaign performance\nConduct competitive analysis and provide recommendations based on competitive reviews, learnings, and industry best practice\nLead and develop eCommerce initiatives, partnership, and execute quality content for eCommerce platform\nPerform ad-hoc marketing projects and duties as assigned\nWork closely with e-marketplaces like HKTV mall, Zstore, Foodpanda, etc.\n\nRequirements:\n\nUniversity undergraduate in Marketing, Journalism, Multi-media, Business or related disciplines\nMinimum 4 years of relevant experience with proven record in e-commerce marketing especially in e-marketplaces campaign planning\nExperience in HK e-marketplaces like HKTV mall, Zstore, etc. are highly preferred\nCreative, energetic, self-motivated, able to work in a fast-paced and dynamic environment\nCan-do attitude, good at problem-solving\nOrganized with good project management skills\nAttention to detail with good interpersonal and communication skills\nExperience in social media, digital marketing, and/or e-commerce highly preferred\nProficient in written and spoken English and Chinese including Putonghua\nProficient in MS Office including Word, Excel, PowerPoint and Chinese Word Processing\n\nWe offer competitive salary, discretionary bonus, medical insurance, life and personal accident insurance, annual leave and staff purchase discount. Interested candidates please send your resume with salary expectation by email or clicking \u201cApply Now\u201d.\n\nWe are equal opportunities employer. Applicants who are not invited within 2 months may consider their application unsuccessful. All applicants may be considered for other suitable positions with DCH Group / CITIC Pacific Group and will be deleted from our files after 6 months from the date of application.", "employment_types": ["Full Time", "Permanent"], "selling_points": [], "locations": ["Kowloon Bay"], "categories": ["Marketing / Public Relations", "Others", "E-commerce", "Marketing - Brand / Product Management", "Others"], "post_time": "2022-01-18T03:03:27Z", "salary": {"currency": null, "max": null, "min": null, "period": "monthly", "term": null}, "salary_visible": false, "title_keywords": ["senior digital marketing executive"], "responsibilities": ["collaborate with", "social media", "ad-hoc", "analysis", "budget", "teams", "quality", "marketing projects", "develop", "communication", "digital marketing", "schedule", "marketing campaigns", "plan", "reports", "kpis", "provide recommendations", "report"], "requirements": {"degrees": [], "majors": [], "languages": ["putonghua", "english", "chinese"], "language_level": ["proficient"], "hard_skills": ["excel", "chinese word processing", "e-commerce", "problem-solving", "word", "powerpoint", "project management", "dynamic", "ms office"], "soft_skills": ["organized", "self-motivated", "dynamic environment", "communication skills", "creative", "can-do attitude", "project management skills", "problem-solving", "attention to detail", "energetic", "interpersonal"], "languages_combined": [{"language": "putonghua", "language_level": ["proficient"]}, {"language": "english", "language_level": ["proficient"]}, {"language": "chinese", "language_level": ["proficient", "proficient"]}]}, "experience_required": {"duration": ["minimum 4 years"], "field": ["social media", "e-commerce", "marketing", "relevant experience", "digital marketing", "planning"]}}, {"job_id": "100003009036040", "location_code": "hk", "company": "TDCX Hong Kong", "job_title": "Consumer Care Agent ~ Int'l Beauty Brand, 5-day work, Attractive Remuneration", "description": "Why Deliveroo?\n\nWhen you first think about Deliveroo, you probably think of getting great food to your house in less than half an hour. Awesome right? But behind the scenes is the real story. This story is one of high growth, huge challenges and an enormous opportunity ahead of us.\n\nWe want to be the definitive food company - the app you go to any time you have a hunger pang. We are transforming the way people think about food. We\u2019re a technology driven company at the forefront of the most rapidly expanding industry in the world, so come and join us for the ride.\n\nWhat you\u2019ll be doing\n\nAssist our restaurants\u2019 partners by answering their enquiries through the hotline and email\nCreate and amend menus for our restaurants\u2019 partners in an efficient manner\nEnsure data accuracy when maintaining restaurants\u2019 records\nProviding feedback to relevant teams to help improve our restaurants\u2019 experience\u00a0\nWork closely with the wider Commercial Team and the Customer Care team in ensuring service levels are met\n\nREQUIREMENTS\n\nExcellent skills in English and Cantonese, proficiency in English and Chinese word-processing\nAbility to use multiple systems and multitask in a fast-paced environment\nAbility to quickly assess a situation and problem solve to point of resolution\nCheerful personality, good team player and ability to work under pressure in a fast-paced environment\nWorking experience in customer service sector is an advantage\n\nBenefits:\n\nBecome one of the key employees of a fast-growing, exciting startup changing the food delivery landscape\nOpen, respectful and fun company culture\nMonthly gym allowance\nMeal allowance if you are required to work late\nMonthly Monday breakfast & Friday lunches \u2013 Deliveroo'd to the office of course!\nSnacks and drinks provided (although not unlimited, you will never go thirsty or hungry)\nAdditional leave days for years of service\u00a0\nFree Deliveroo Plus - Free delivery and access to special offers\n\nBenefits and Diversity\n\nAt Deliveroo we know that people are the heart of the business and we prioritise their welfare. We offer a wide range of competitive benefits in areas including health, family, finance, community, convenience, growth, time away and relocation.\n\nWe believe a great workplace is one that represents the world we live in and how beautifully diverse it can be. That means we have no judgement when it comes to any one of the things that make you who you are - your gender, race, sexuality, religion or a secret aversion to coriander. All you need is a passion for (most) food and a desire to be part of one of the fastest growing startups in an incredibly exciting space.", "employment_types": ["Full Time", "Permanent"], "selling_points": ["Mon-Fri 5-day work; Day Off on Sat, Sun & PH", "Support Multi-national Beauty Brands;", "Excellent in spoken & written Chinese & English"], "locations": ["Tin Hau"], "categories": ["Sales, CS & Business Devpt", "Call Centre", "Beauty Care / Health", "Others", "E-commerce", "Others"], "post_time": "2022-01-10T09:10:35Z", "salary": {"currency": "HKD", "max": 16999, "min": 14000, "period": "monthly", "term": null}, "salary_visible": true, "title_keywords": [], "responsibilities": [], "requirements": {"degrees": [], "majors": [], "languages": [], "language_level": [], "hard_skills": ["go"], "soft_skills": [], "languages_combined": []}, "experience_required": {"duration": [], "field": []}}, {"job_id": "100003009042700", "location_code": "hk", "company": "Deliveroo Hong Kong Limited", "job_title": "Partner Service Associate (Corporate Services)", "description": "Station on site\nA cheerful & energetic working place need a new member to join us\nAttractive bonus scheme, out-patient medical benefit, travelling & mobile allowance accelerate & accumulated annual leave, birthday leave\n\nDuties:\n\u00a0\u00a0\u00a0\u00a0\u00a0\u00a0\u00a0\u00a0 Coordinate design, drawing and material, submission\n\u00a0\u00a0\u00a0\u00a0\u00a0\u00a0\u00a0\u00a0 Coordinate project schedule and monitor site activates.\n\n\n\nRequirements:\n\nHigh Cert/Diploma holder or above in Building Services related subject.\nMinimum 3 years full time site supervision/ project management experience in Building Services works.\nProficiency in both written and spoken English and Chinese.\nGood knowledge of PC skill in MS Office, Project and Auto (AI).\nPrefer in Hotel renovation experiences.\u00a0\n\nWe offer attractive remuneration packages & excellent career path to the right candidates.\u00a0 Interested candidates please send your full resume with expected salary by clicking \"Apply Now\".\n\n\n(Personal data collected will be used for recruitment purpose only.)", "employment_types": ["Full Time", "Permanent"], "selling_points": ["Answer restaurants' enquiries by hotline and email", "Working experience in customer service sector", "Handle the on boarding process of restaurants"], "locations": ["Central"], "categories": ["Sales, CS & Business Devpt", "Call Centre", "Customer Service - Supervisor / Officer", "E-commerce", "Others"], "post_time": "2022-01-12T08:26:13Z", "salary": {"currency": null, "max": null, "min": null, "period": "monthly", "term": null}, "salary_visible": false, "title_keywords": ["associate"], "responsibilities": ["coordinate", "monitor", "schedule", "design"], "requirements": {"degrees": ["diploma holder"], "majors": ["building services"], "languages": ["english", "chinese"], "language_level": ["proficiency"], "hard_skills": ["ai", "project management", "pc skill", "ms office"], "soft_skills": ["project management"], "languages_combined": [{"language": "english", "language_level": ["proficiency"]}, {"language": "chinese", "language_level": ["proficiency"]}]}, "experience_required": {"duration": ["minimum 3 years"], "field": ["project management", "building services"]}}, {"job_id": "100003009044379", "location_code": "hk", "company": "PHM Contracting Co. Limited", "job_title": "Building Services Coordinator (Interior Fit Out)", "description": "\u00a0 \u00a0 \u00a0 \u00a0 \u00a0 \u00a0 \u00a0 \u00a0 \u00a0 \u00a0 \u00a0 \u00a0 \u00a0 \u00a0 \u00a0 \u00a0 \u00a0 \u00a0 \u00a0 \u00a0 \u00a0 \u00a0 \u00a0 \u00a0 \u00a0Strategy and Transformation Department\n\nKey responsibilities\nTo work with different business units across the organization to map and assess the current processes and ways of working, and to identify the enhancement opportunities through employing process improvement methodologies in line with best practice, regulatory and legal standards\nTo identify industry trends and variations through the application of innovative thinking\nTo form the better value and greater efficiency strategy through the elimination of unnecessary complexity of the current working processes and through the identification of better ways of working\nTo manage relationships and communications with key stakeholders across the organisation to build trust and maintain buy-in\nTo collaborate with system developers to ensure the business and technical feasibility and suitability\nTo assist in the development and implementation of continuous improvement strategy, and be accountable for the process control, monitoring and optimisation\nTo engage all related parties and team members through training and coaching, and to complete post implementation reviews to ensure successful delivery\nTo actively contribute to developing a positive culture of continuous improvement across the organisation\nCompetencies\u00a0\n\nExcellent understanding of continuous improvement concepts including Six Sigma, Lean, value stream mapping; accredited Lean Six Sigma Black Belt preferred\n3-5 years proven continuous improvement analytical experience from a similar role, including project management and business analysis\nAbility to set-up, facilitate and lead process improvement sessions with a range of business stakeholders\nA \u201ccompleter-finisher\u201d taking accountability for ideas from inception to delivery, in an environment that requires robust metrics to confirm success\nExperience of designing and implementing a framework of continuous improvement in a sizable organisation\nExperience of hands-on implementation of continuous improvement programs and Lean solutions\nExperience of designing remediation plans to address productivity and efficiency issues, and track record of following through to ensure closure\nExcellent verbal and written communication skills and the ability to interact professionally with a diverse group of leaders and colleagues\nStrong analytical, project and product management skills, including a thorough understanding of how to interpret business needs and translate them into operational requirements\nProficient in the use of Microsoft Office, including Project, Visio, Word, Excel, Outlook, and PowerPoint\n\nWe offer 5-day work week, competitive remuneration packages and advancement opportunities. Interested parties, please write with full resume to Director, Human Resources, Human Resources Department, i-CABLE Communications Limited, 4/F Cable TV Tower, 9 Hoi Shing Road Tsuen Wan, N.T. or fax to 2112 7841 or via Apply Now (Please quote reference number and position applied for). For other information, please visit our website http://www.i-cable.com.\n\nYour application may be forwarded to any affiliate companies and successful applicant may be seconded to work at any office as assigned.\u00a0 The information received will be used for consideration of employment only and all personal data supplied will be destroyed within 3 months.\n\nWe are an equal opportunity employer.", "employment_types": ["Full Time", "Permanent"], "selling_points": ["Monitoring site progress coordination work for BS", "Certificate or above in Building Services related", "Medical benefit, private hospital insurance scheme"], "locations": ["Kwun Tong"], "categories": ["Building & Construction", "Architectural Services", "Building / Construction / QS", "E-commerce", "Others"], "post_time": "2022-01-13T06:53:27Z", "salary": {"currency": null, "max": null, "min": null, "period": "monthly", "term": null}, "salary_visible": false, "title_keywords": ["coordinator"], "responsibilities": ["collaborate with", "communications with", "control", "ideas", "management", "monitoring", "implementation", "developing", "communication", "project management", "maintain", "designing", "business analysis", "plans"], "requirements": {"degrees": [], "majors": [], "languages": [], "language_level": [], "hard_skills": ["excel", "lean", "microsoft office", "analysis", "word", "powerpoint", "project management", "six sigma", "outlook"], "soft_skills": ["communication skills", "accountability", "accountable", "robust", "project management", "hands-on", "diverse", "thorough", "organisation", "innovative", "positive"], "languages_combined": []}, "experience_required": {"duration": ["3-5 years"], "field": ["business analysis", "project management", "analytical"]}}, {"job_id": "100003009046201", "location_code": "hk", "company": "Hong Kong Trade Development Council", "job_title": "Senior Project Executive, Platform Development (Contract)", "description": "Ref. No.: 318/PJE-PD/EDB/HKTDC\n\nResponsibilities:\n\n\nAssist project managers in the overall planning, development and implementation of new online initiatives for hktdc.com\nWork closely with IT team, internal departments and external vendors on the development and user requirement collection, prototype design, data migration, test plan preparation and system testing\nParticipate in the full project life cycle and prepare related documentation\nPerform business and data analysis, and identify business opportunities\nCoordinate the changes to ensure the vendor\u2019s deliverables are conformed to business requirements\n\nRequirements:\n\n\nUniversity degree, preferably in Information Systems, Business Administration, E-Commerce or related disciplines\nA minimum of 3 years' working experience in online business environment\nFamiliar with project management lifecycles\nGood understanding of the latest Internet, mobile and social media development trends\nGood command of written and spoken English and Chinese, including Putonghua\nUnderstanding in User Experience design\nA good team player with strong communication and interpersonal skills\nProactive, self-motivated and independent\nHighly analytical and well-structured in problem solving and presentation\nWell organized and meticulous with the ability to multi-task and work under pressure\nFresh graduates will also be considered\nCandidates with less experience would be considered as Project Exeuctive\n\nRemuneration and Benefits:\n\nThe successful candidate will be appointed on a fixed-term contract basis, renewable subject to operational needs. Salary will be commensurate with qualifications and experience.\u00a0\u00a0\n\nApplication Procedure:\n\nInterested candidates are invited to complete the application form on our website at http://www.hktdc.com/careers.html. Those who do not hear from us within EIGHT WEEKS after the closing date may assume their applications unsuccessful.\n\nAll information provided by applicants will be treated in strict confidence and used only for recruitment purposes. Applicants may be considered for other suitable positions within the Council. Their personal data will be destroyed six months after the selection is finalised.\n", "employment_types": ["Full Time", "Contract"], "selling_points": ["Mobile Apps Development Support", "Product management & development", "User Experience design"], "locations": ["Wan Chai"], "categories": ["Information Technology (IT)", "Application Specialist - Software", "E-commerce", "Product Management / Business Analyst", "Others"], "post_time": "2022-01-13T09:55:28Z", "salary": {"currency": null, "max": null, "min": null, "period": "monthly", "term": null}, "salary_visible": false, "title_keywords": ["senior project executive"], "responsibilities": ["user requirement", "related documentation", "identify business opportunities", "data", "implementation", "design", "testing", "data analysis", "coordinate", "plan", "migration", "planning"], "requirements": {"degrees": ["university degree"], "majors": ["related disciplines", "business administration", "e-commerce"], "languages": ["putonghua", "english", "chinese"], "language_level": ["good command"], "hard_skills": ["problem solving", "project management", "mobile", "e-commerce"], "soft_skills": ["meticulous", "good team player", "self-motivated", "independent", "multi-task", "well organized", "problem solving", "project management", "communication and interpersonal skills", "structured", "business environment", "proactive", "presentation", "work under pressure"], "languages_combined": [{"language": "putonghua", "language_level": ["good command"]}, {"language": "english", "language_level": ["good command"]}, {"language": "chinese", "language_level": ["good command"]}]}, "experience_required": {"duration": ["minimum of 3 years"], "field": ["business", "design"]}}, {"job_id": "100003009049542", "location_code": "hk", "company": "Cathay Pacific Airways Ltd", "job_title": "Assistant Manager Digital, Performance Analytics", "description": "Reports to:\u00a0Digital Manager - Omni-Channel Orchestration\nDepartment: Digital (DGT)\n\nRole Introduction\n\n\nThis position will be responsible to :\n\nAct as the platform owner of Adobe Analytics and lead the function of performance analytics in the areas of customer online behavior, commercial performance, digital campaign performance, marketing ROI) by customer, segment, market, product, channel and ensure customer data is enriched and available for cross channel usage\nDesign, drive and recommend measurement framework based on customer journey and business needs\nDrive integrated usage of online and offline data to enrich understanding of customer and generate commercial insight\nCoach and groom development of team members\n\nKey Responsibilities\n\nEnsure best practices in digital analytical tool use, performance tracking, and eco-system development in a cookie-less world\u00a0\nAccountable for recommendation and implementation of appropriate metrics and dimension in tracking customer behavior and commercial performance\u00a0\nLead reports/dashboards design with the use of digital analytics, leveraging quantitative and qualitative data to generate insights for customer experience delivery and campaign optimization\nDevelop and deliver training curriculum and user support as required for head office business units and regional sales teams for digital analytics tools such as\nAdobe Analytics and Campaign Repository\nCollaborate with DGT Analytics and Data Scientist to drive experimental and personalization across customer travel and customer lifestyle areas, as well as to ensure data feedback loop\u00a0\nDrive integrated data usage with both online and offline data\u00a0\nCoach and groom team development team members\n\nRequirements\n\nUniversity degree in an analytical discipline, such as Business, Finance, Statistics, Economics, or Marketing\nMinimum 5 years of experience in digital or e-Commerce with minimum 3 years in analytics and tracking area\nMinimum 2 years hands on experience on Adobe Analytics or Google Analytics with strong understanding of data layers, tagging, cookies, variables and custom metric set up\nSolid understanding of digital marketing channels, such as web, SEO, SEM, display ads etc. and attribution models\nSavvy with respect to technical concepts and workflows that underpin digital analytics, such as site load performance tools, first- vs third-party cookies and data integration\u00a0\nPassion in latest digital and data trends, knowledge of marketing technology tools across web analytics, campaign management across all digital touch points\nDetail-oriented, with proven ability to demonstrate data interpretation capabilities including both online and offline data\nStrong in communication, flexible and comfortable working with internal and external stakeholders from different teams and levels\nAble to stay focused under pressure, prioritizing and managing multiple projects in a fast paced environment\nPrior experience in conducting training for analytics tools is an advantage\nApplication Deadline: 28 January 2022\n\nPersonal & Application Information\n\nCathay Pacific is an Equal Opportunities Employer. Personal data provided by job applicants will be used strictly in accordance with our personal data policy and for recruitment purposes only. Candidates not notified within eight weeks may consider their application unsuccessful. All related information will be kept in our file for up to 24 months. A copy of our Personal Information Collection Statement will be provided upon request by contacting our Data Protection Officer.\n\nPlease note that with effect from 1 December 2021, all employees must be vaccinated in order to access Cathay City and all other Cathay Group Company premises in Hong Kong. Consideration will be given to those who are unable to get vaccinated for valid medical reasons.\n\n", "employment_types": ["Full Time", "Permanent"], "selling_points": ["Min 5 years of experience in digital or e-Commerce", "Lead reports/dashboards design", "Travel Benefits, 5-day work, Medical Benefits"], "locations": ["Lantau Island"], "categories": ["Marketing / Public Relations", "Digital Marketing", "E-commerce", "Business Development", "Others"], "post_time": "2022-01-14T08:51:27Z", "salary": {"currency": null, "max": null, "min": null, "period": "monthly", "term": null}, "salary_visible": false, "title_keywords": ["assistant manager"], "responsibilities": ["collaborate with", "analytics tools", "data", "teams", "implementation", "design", "develop", "reports", "tracking"], "requirements": {"degrees": ["university degree"], "majors": ["finance", "economics", "statistics", "business", "marketing"], "languages": [], "language_level": [], "hard_skills": ["google analytics", "analytics tools", "seo", "web", "e-commerce", "integration", "web analytics", "adobe", "sem", "vs"], "soft_skills": ["flexible", "under pressure", "focused", "passion in", "detail-oriented", "communication", "hands on", "web analytics", "prioritizing"], "languages_combined": []}, "experience_required": {"duration": ["minimum 2 years", "minimum 5 years", "minimum 3 years"], "field": ["digital", "training", "e-commerce"]}}, {"job_id": "100003009042592", "location_code": "hk", "company": "ESD Services Limited (ESDlife)", "job_title": "eCommerce Operations Administrator", "description": "You will:\u00a0\n\nProvide sales administrative support including finance reporting, invoice payment & handling eshop sales operation task\n\nProvide post-sales customer services and admin support including post-sales inquiry, follow up with merchants and receipt handling etc.\nProvide admin support on sales and promotion campaign\nYou should have:\n\n\nDiploma or above\n\nFamiliar with MS applications (Excel, Word & PowerPoint) and Chinese Word Processing\nGood command of spoken and written English and Chinese\nSelf-motivated, hardworking, pleasant and detail-minded\nFresh graduate is welcomed\n\n\u00a0\u00a0In addition, you will be able to:\n\nEnjoy an attractive and competitive remuneration package\nReceive training and development opportunities\n\nSalary and benefit will commensurate with qualifications and experience.\u00a0\u00a0Interested party, please send in your\u00a0full resume and expected salary\u00a0by clicking the button\u00a0\u2018APPLY NOW\u2019.\n\nTo know more about us, please visit our website at\u00a0https://corporate.esdlife.com/\n\nWe are an equal opportunity employer and welcome applications from all qualified candidates. The information provided will be treated in strict confidence and used only for consideration of application for relevant/similar post(s) within the Hutchison Group of Companies. Applicants not having heard from us within four weeks from the date of this advertisement may consider their application unsuccessful. All personal data of unsuccessful applicants will be destroyed after the recruitment exercise when no longer required.", "employment_types": ["Full Time", "Permanent"], "selling_points": [], "locations": ["Hung Hom"], "categories": ["Admin & HR", "Clerical / Admin Staff", "E-commerce", "Others", "Sales, CS & Business Devpt", "Sales Administration"], "post_time": "2022-01-12T08:06:03Z", "salary": {"currency": null, "max": null, "min": null, "period": "monthly", "term": null}, "salary_visible": false, "title_keywords": ["operations", "administrator"], "responsibilities": ["reporting", "invoice", "website", "customer services", "sales administrative support", "payment", "admin support", "recruitment", "personal data"], "requirements": {"degrees": ["fresh graduate", "diploma or above"], "majors": [], "languages": ["english", "chinese"], "language_level": ["good command"], "hard_skills": ["excel", "no", "chinese word processing", "ms applications", "word", "powerpoint"], "soft_skills": ["detail-minded", "self-motivated", "confidence", "pleasant", "hardworking"], "languages_combined": [{"language": "english", "language_level": ["good command"]}, {"language": "chinese", "language_level": ["good command"]}]}, "experience_required": {"duration": [], "field": []}}, {"job_id": "100003009031515", "location_code": "hk", "company": "Chow Sang Sang Holdings International Limited", "job_title": "Associate Executive/Executive, E-Commerce", "description": "Jobs Description:\n\nWork closely with customer service department in delivering quality service to customers\nManage day-to-day operation and update content materials of e-commerce platforms\nHandle e-commerce logistic and orders issues\nLiaise and coordinate with business partners and related departments on day-to-day business operations\nSupport daily operations, preparing and updating daily/monthly reports\nSupport E-commerce team on departmental administration\nAssist in ad-hoc duties as assigned by the supervisor\nRequirements:\n\nDegree in e-commerce/Communication or related discipline\nMinimum 3 years\u2019 experience working in online business or e-commerce operation\nPatient, detail-minded, well-organized, multi-tasking and able to work under pressure\nProficiency in MS Word, Excel, PowerPoint and Chinese Word Processing\u00a0\nExcellent in both written and spoken Chinese and English\nWe offer 5-day-work week with competitive remuneration packages to the right candidate.\u00a0 Interested parties please send your CV with EXPECTED SALARY through the below application procedure.\n(Personal data will be used by Chow Sang Sang (CSS) for recruitment only.\u00a0 CSS may refer suitable applications to other vacancies within CSS and its associated companies.\u00a0 We will retain unsuccessful applications for a maximum period of 24 months.)", "employment_types": ["Full Time", "Permanent"], "selling_points": ["Deliver quality service to customers", "Manage day-to-day operation of e-commerce platform", "3 yrs exp in e-commerce operation"], "locations": ["Cheung Sha Wan"], "categories": ["Sales, CS & Business Devpt", "Others", "E-commerce", "Supply Chain", "Others"], "post_time": "2022-01-07T09:24:19Z", "salary": {"currency": null, "max": null, "min": null, "period": "monthly", "term": null}, "salary_visible": false, "title_keywords": ["associate", "executive"], "responsibilities": ["liaise", "monthly reports", "operations", "support e-commerce team", "quality", "e-commerce platforms", "coordinate with", "daily operations", "customer service", "ad-hoc duties", "update content materials", "day-to-day operation", "administration"], "requirements": {"degrees": ["degree"], "majors": ["e-commerce"], "languages": ["english", "chinese"], "language_level": ["proficiency", "excellent"], "hard_skills": ["excel", "chinese word processing", "e-commerce", "powerpoint", "ms word"], "soft_skills": ["detail-minded", "well-organized", "communication", "multi-tasking", "patient", "work under pressure"], "languages_combined": [{"language": "english", "language_level": ["excellent"]}, {"language": "chinese", "language_level": ["proficiency", "excellent"]}]}, "experience_required": {"duration": ["minimum 3 years"], "field": ["operation", "business", "e-commerce"]}}, {"job_id": "100003009045547", "location_code": "hk", "company": "Sun Television Cybernetworks Enterprise Limited", "job_title": "Designer", "description": "Description:\n\nAssist with content creation for social media (company website, Facebook, Instagram, YouTube, etc.)\nDesign and develop marketing collateral e.g. PPT, Brochures, Newsletters & Website content\nInterested in new things such as NFT, e-commerce platforms, and the ability to learn new things;\nManage other ad-hoc brand / marketing projects as assigned\n\nRequirements:\n\n1 to 2+ years\u2019 experience in design;\nCurious, sensitive to new technology and market trend;\nProficient in Photoshop, Illustrator, After Effects and other relevant design programs\nKnowledge in web/app UX/UI design will be an extra bonus\nResume with portfolio\nFluent in both English and Chinese (Cantonese & Mandarin)\nGood team player with strong organizational, communication and interpersonal skills", "employment_types": ["Full Time", "Permanent"], "selling_points": [], "locations": ["Siu Sai Wan"], "categories": ["Media & Advertising", "Creative / Design", "Banking / Finance", "Others", "E-commerce", "Others"], "post_time": "2022-01-13T08:03:31Z", "salary": {"currency": null, "max": null, "min": null, "period": "monthly", "term": null}, "salary_visible": false, "title_keywords": ["designer"], "responsibilities": ["ad-hoc", "social media", "design and develop", "website", "e-commerce platforms", "marketing projects", "facebook", "company website"], "requirements": {"degrees": [], "majors": [], "languages": ["cantonese", "english", "chinese", "mandarin"], "language_level": ["fluent"], "hard_skills": ["after effects", "illustrator", "web", "photoshop"], "soft_skills": ["good team player", "sensitive to", "communication and interpersonal skills", "organizational"], "languages_combined": [{"language": "cantonese", "language_level": []}, {"language": "english", "language_level": ["fluent"]}, {"language": "chinese", "language_level": ["fluent"]}, {"language": "mandarin", "language_level": []}]}, "experience_required": {"duration": ["2+ years"], "field": ["design"]}}, {"job_id": "100003009027282", "location_code": "hk", "company": "Link Profit International Development Limited", "job_title": "E-commerce Warehouse Officer \u96fb\u5546\u5009\u52d9\u54e1", "description": "We are looking for a passionate and enthusiastic\u00a0Digital\u00a0Marketing Specialist\u00a0to join our team. This role will be suitable for someone who is eager to develop his/her talents through a fast-paced start-up environment.\n\n\nResponsibilities:\n\nSupport the team\u2019s development of digital marketing strategy, with focus on company\u2019s main website, eDM, social media accounts, google business accounts, SEO, SEM\nAnalyze online user behavior, conversion data, and customer journeys, funnel analysis, and customer segments to develop effective strategies and action plans;\nProvide SEM/ SEO strategy and eDM or A/B testing to drive online sales by increasing website traffic and optimizing site conversion;\nManage and monitor KPIs including annual, monthly, or weekly performance targets, traffic targets, and conversion rate targets;\nImplement media strategies via multiple online and offline platforms; monitor advertising metrics to optimize campaign performance;\nBuild and maintain a good relationship with media and business partners;\nLead all CRM projects and loyalty programs, data analysis, and insight\nDevelop of creative writing (by bilingual if needed), promotion and marketing concepts for all media channels\nDesign and proofread marketing collaterals\nProvide project planning, program calendar and management\nRequirements:\n\nUniversity Degree in Marketing or related discipline\nAt least 2 -3 years of Digital Marketing experience.\u00a0\nGood knowledge and experience with digital marketing tools and best practices such as Facebook ad manager, Google ad words, Google analytics, and CRM\nResult-driven, highly flexible, positive attitude towards new challenges in a fast-growing business and strong organizational\nPassionate team player, open-minded, willing to try new ideas and scopes to and inspire others\nSelf-sufficient learner and critical thinker with problem-solving skills\nStrong communication skills with proficiency in written and spoken English and Chinese", "employment_types": ["Full Time", "Temporary"], "selling_points": [], "locations": ["Kwai Hing"], "categories": ["Transportation & Logistics", "Fulfillment", "Inventory / Warehousing", "E-commerce", "Others"], "post_time": "2022-01-06T09:35:18Z", "salary": {"currency": null, "max": null, "min": null, "period": "monthly", "term": null}, "salary_visible": false, "title_keywords": ["officer"], "responsibilities": ["data", "marketing collaterals", "website", "design", "media channels", "maintain", "plans", "advertising", "monitor", "develop", "testing", "good relationship", "kpis", "social media", "management", "seo", "edm", "data analysis", "digital marketing", "support the team", "project planning", "analysis", "sem"], "requirements": {"degrees": ["university degree"], "majors": ["marketing"], "languages": ["english", "chinese"], "language_level": ["proficiency"], "hard_skills": ["problem-solving skills", "facebook", "google analytics", "words"], "soft_skills": ["flexible", "passionate", "communication skills", "organizational", "open-minded", "positive attitude", "problem-solving skills", "team player", "driven"], "languages_combined": [{"language": "english", "language_level": ["proficiency"]}, {"language": "chinese", "language_level": ["proficiency"]}]}, "experience_required": {"duration": ["at least 2 -3 years"], "field": ["digital marketing"]}}, {"job_id": "100003009037957", "location_code": "hk", "company": "Kerry Ecommerce Limited", "job_title": "Business Analyst / Assistant Business Analyst (eCommerce)", "description": "To cope with the rapid growth of our retail and salon business, we are looking for talent\u00a0with the following background to join our vibrant and inspiring marketing team.\u00a0\n\nResponsibilities:\n\nAssist in planning and implementing marketing strategies for HK market including ATL, BTL, online & social media, CRM & PR\nPlan and execute New Product Launches, in-store promotions and GWP to enhance the brand awareness\nLiaison with agencies on development of marketing collaterals, promotional materials, POSM, POPs etc\u00a0\nConduct sales & marketing data analysis and prepare report\nAssist in ad-hoc project assigned\n\nRequirements:\n\nDegree holder in Marketing or related disciplines\nMinimum 3-4 years experience in product marketing, background from FMCG / Beauty industry definitely an advantage\u00a0\nProactive, strategic thinking, attention to details and able to work in fast-paced working environment\nDigital savvy\nFluent in spoken and written English, Cantonese and Mandarin\u00a0\nA good team player with strong communication, interpersonal skills and a can-do attitude\n\n\u00a0We offer\u00a0attractive remuneration package to the right candidates:\n\n5 days work\nBank holidays\nAnnual leave\nStaff discounts and free goods\nEducation allowance\u00a0\n\nPlease visit our website at\u00a0www.marierskincare.com to understand more about our brand.\u00a0\n\nInterested parties, please send\u00a0your CV with Cover Letter, and state your\u00a0current & expected salary, availability\u00a0to our Human Resources Department\u00a0by clicking\u00a0\"Apply Now\" button.\n\nPersonal data collected\u00a0will be used for recruitment purpose only. All applicants will be treated in strict confidence and used exclusively for recruitment purposes. The company will retain the applicants for a maximum period of 6 months.", "employment_types": ["Full Time", "Permanent"], "selling_points": [], "locations": ["Kwai Fong"], "categories": ["E-commerce", "Business Development", "Product Management / Business Analyst", "Others"], "post_time": "2022-01-11T04:26:00Z", "salary": {"currency": null, "max": null, "min": null, "period": "monthly", "term": null}, "salary_visible": false, "title_keywords": ["business analyst", "assistant"], "responsibilities": ["ad-hoc", "social media", "prepare report", "marketing strategies", "marketing collaterals", "data analysis", "promotional materials", "plan", "planning"], "requirements": {"degrees": ["degree holder"], "majors": ["related disciplines", "marketing"], "languages": ["cantonese", "english", "mandarin"], "language_level": ["fluent"], "hard_skills": [], "soft_skills": ["good team player", "strategic thinking", "can-do attitude", "communication", "interpersonal skills", "attention to details", "proactive"], "languages_combined": [{"language": "cantonese", "language_level": ["fluent"]}, {"language": "english", "language_level": ["fluent"]}, {"language": "mandarin", "language_level": ["fluent"]}]}, "experience_required": {"duration": ["minimum 3-4 years"], "field": ["beauty industry", "marketing", "fmcg"]}}, {"job_id": "100003009035148", "location_code": "hk", "company": "Delivery Hero Food Hong Kong Limited", "job_title": "Procurement Coordinator (Part Time)", "description": "\u8077\u8cac:\n\n- \u8ca0\u8cac\u65e5\u5e38\u5009\u52d9\u904b\u4f5c\uff0c\u5305\u62ec\u6536\u8ca8\u3001\u51fa\u8ca8\u3001\u7522\u54c1\u6aa2\u67e5\u53ca\u9ede\u5b58;\n- \u8cc7\u6599\u8f38\u5165\u3001\u7ba1\u7406\u5eab\u5b58\u3001\u7dad\u6301\u5eab\u5b58\u7d00\u9304\uff1b\n- \u8655\u7406\u53ca\u56de\u8986\u65e5\u5e38\u5ba2\u6236\u67e5\u8a62\n- \u5411\u5009\u52d9\u90e8\u63d0\u4f9b\u6240\u9700\u8981\u7684\u652f\u63f4\u53ca\u5354\u52a9\n\n\u8981\u6c42:\n-\u00a0\u4e2d\u4e94\u6216\u4ee5\u4e0a\u5b78\u6b77\n- \u5177\u5009\u52d9\u5de5\u4f5c/\u96fb\u5b50\u5546\u52d9\u7d93\u9a57\u512a\u5148\uff0c\u6b61\u8fce\u61c9\u5c46\u7562\u696d\u751f\n- \u826f\u597d\u4e2d\u82f1\u6587\u6c34\u5e73\uff0c\u719f\u6089Microsoft Office\n- \u6709\u5718\u968a\u7cbe\u795e\u3001\u8cac\u4efb\u611f\u3001\u8aa0\u5be6\u3001\u53ca\u826f\u597d\u5de5\u4f5c\u614b\u5ea6\n- \u826f\u597d\u7684\u6e9d\u901a\u6280\u5de7\u53ca\u4eba\u969b\u95dc\u4fc2\n\n\n\u5168\u8077\u54e1\u5de5\u798f\u5229:\n\n- 5\u5929\u5de5\u4f5c\n- \u6709\u85aa\u5e74\u5047\n-\u00a0\u5e74\u7d42\u82b1\u7d05\n-\u00a010\u5929\u6709\u85aa\u5e74\u5047\n\n\n\nJob Description:\n\nResponsible for the day-to-day operations in our warehouse, ranging from inbound\u00a0deliveries\u00a0to picking & packing outbound shipments to our customers, duties include:\n\n- Support warehouse operations on daily order processing\n- Ensure quality and accurate pick and pack\n- Liaise with logistic partners and couriers for order distribution and collection\n- Prepare manifest and data entry for\u00a0reporting\n- Provide other clerical and administrative supports to the team.\n\n\nJob Requirements:\n\n\n- F.5 or above, fresh graduates are also welcomed\n- One-year of working experience (Familiar with e-Commence operations is an advantage)\n- Candidate with less experience will be considered as Warehouse Officer\n- Good knowledge of warehouse operation;\n- Proficiency in Microsoft Office\n- Detail-minded, well-organized and responsible\n\nBenefits:\n- Discretionary Bonus\n- 5 day work week\n- Bank Holidays\n- 10 days annual leave", "employment_types": ["Part Time"], "selling_points": ["International organizational culture", "Great exposure to fast-paced e-commerce workplace", "Welcome undergraduate or junior candidate"], "locations": ["Sheung Wan"], "categories": ["E-commerce", "Others"], "post_time": "2022-01-10T06:10:55Z", "salary": {"currency": null, "max": null, "min": null, "period": "hourly", "term": null}, "salary_visible": false, "title_keywords": ["coordinator"], "responsibilities": ["reporting", "data entry", "day-to-day operations", "quality", "order processing", "liaise with", "warehouse operations"], "requirements": {"degrees": [], "majors": [], "languages": [], "language_level": [], "hard_skills": ["microsoft office"], "soft_skills": ["detail-minded", "well-organized", "responsible"], "languages_combined": []}, "experience_required": {"duration": [], "field": []}}, {"job_id": "100003009041339", "location_code": "hk", "company": "Postlogistics (Hong Kong) PTE Limited", "job_title": "Onboarding and Implementation Manager (Ecommerce Logistics)", "description": "Responsibilities:\n\nWork closely with business and operation users to deliver new technology solutions to e-commerce industry\nCommunicate with customers, mainly international enterprises & start-ups, for project requirements\nPerform gap analysis to check the compatibility of the existing system infrastructure with the new business requirements\nProvide UAT and product training to customer and internal parties\n\nRequirements:\u00a0\n\nDegree holder in Information Technology, Computer Science, Business Administration or related disciplines\nAt least 2 years\u2019 experience in business analysis, solution design, project coordination, and vendor management\nGood knowledge in e-commerce or logistic IT services is a plus\nStrong communication, presentational and analytical skills\nGood command of spoken and written English and Chinese\nCandidates with less experience or fresh graduate will be considered as Assistant Business Analyst\nImmediately available is highly preferred\nIf you have the energy and qualifications to add to our velocity,\u00a0Please visit\u00a0Kerry Logistics Network Company Webpage\u00a0to apply or\u00a0send your CV with your present and expected salary to the\u00a0Group Director of\u00a0Human Resources & Administration, Kerry Logistics by clicking APPLY NOW\u00a0or by fax to +852 2614 8517\u00a0.\n\n(We are an equal opportunity employer and welcomes applications from all qualified candidates.\u00a0All personal data will be kept in the strictest confidence and will be used for recruitment purpose only. All applicants maybe considered for other suitable positions in the Kerry Group and its members. All personal data of unsuccessful candidates will be destroyed.)", "employment_types": ["Full Time"], "selling_points": ["eCommerce experience", "Good Project Management, Time Management skill", "Fluent in English both written & verbal"], "locations": ["Ngau Tau Kok"], "categories": ["Transportation & Logistics", "Freight Forwarding", "E-commerce", "Others"], "post_time": "2022-01-12T03:45:50Z", "salary": {"currency": null, "max": null, "min": null, "period": "monthly", "term": null}, "salary_visible": false, "title_keywords": ["manager", "logistics"], "responsibilities": ["communicate with", "project requirements", "uat", "analysis", "infrastructure", "internal parties"], "requirements": {"degrees": ["fresh graduate", "degree holder"], "majors": ["business administration", "information technology", "related disciplines", "business", "computer science"], "languages": ["english", "chinese"], "language_level": ["good command"], "hard_skills": ["plus", "e-commerce", "analysis", "vendor", "analytical skills"], "soft_skills": ["communication", "confidence", "coordination", "analytical skills"], "languages_combined": [{"language": "english", "language_level": ["good command"]}, {"language": "chinese", "language_level": ["good command"]}]}, "experience_required": {"duration": ["at least 2 years"], "field": ["business analysis", "management", "business", "design"]}}, {"job_id": "100003009036386", "location_code": "hk", "company": "HomePlus (Hong Kong) Limited (HOME+)", "job_title": "Sales Support Executive", "description": "Job Description\n\nJOBTITLE: \u00a0 \u00a0 \u00a0 Onboarding and Implementation Manager (Ecommerce Logistics)\u00a0\n\nRESPONSIBLETO: \u00a0 \u00a0 \u00a0 \u00a0 Head of Operations - APAC\n\nMAINLOCATION: \u00a0\u00a0\u00a0\u00a0\u00a0\u00a0\u00a0\u00a0\u00a0\u00a0\u00a0\u00a0 Kowloon, Hong Kong\n\nProject Engagement\n\nLeading the solutions design for new business opportunities, key interface between operations team and sales team to ensure quality proposal/solution is delivered\nParticipate in client\u2019s project walkthrough, business requirements gathering, design, trial run plan and implementation session\nLead and manage the implementation of any new client in collaboration with the appropriate cross functional teams within schedule\n\nClient Relationship Engagement\n\nEstablish, maintain and develop strong relationships with new clients at strategic and operational levels.\nEngage with the customer at onboarding stage and maintain contact until handover to Key Account Manager at business-as-usual stage, from collection of information until sign-off of the onboarding\nStrictly manage services scope with clients and ensure solution implemented stays in line with the solution sold\nOperational Engagement\nCreate, distribute, and maintain Standard Operational Procedures (SOPs) in collaboration with cross functional teams (Sales, Operations, Finance,\u00a0IT)\nEnsure operations are optimized and products are delivered under the highest service quality possible.\nRequirement:\nBachelor\u2019s Degree in related field\nMinimum 5 years of working experience in courier/ecommerce\u2019s logistics\nGood experience in ecommerce solution design/ implementations at global environment\nGood understanding of the global ecommerce logistics requirements and solutions across all logistics modes\nGood Project Management, Time Management skill\nFluent in English both written and verbal communication\nCommercial minded and strong engagement exposures with clients in the area of solution design\nExcellent Microsoft Office and SOP writing skills\nDetail oriented, able to multitask and meet deadlines\nSelf-motivated, able to work in a team and independently\n\n\u00a0Desirable Skills:\n\neCommerce experience\n\n\u00a0Additional Requirements:\n\nThe responsibilities associated with this job will change from time to time in accordance with the Company\u2019s business needs.\u00a0 More specifically, the incumbent may be required to perform additional and/or different responsibilities from those set forth above. The above declarations are not intended to be an all-inclusive list of the duties and responsibilities of the job described, nor are they intended to be such a listing of the skills and abilities required to do the job. Rather, they are intended only to describe the general nature of the job.\n\n\u00a0 \u00a0 \u00a0 \u00a0 \u00a0 \u00a0 \u00a0 \u00a0 \u00a0 \u00a0 \u00a0 \u00a0 \u00a0 \u00a0 EQUALITY OF OPPORTUNITY IS COMPANY POLICY", "employment_types": ["Full Time", "Permanent"], "selling_points": ["Sales Administration/Administrative support", "Stationary & Supplies products", "invoicing, order delivery & after sales service"], "locations": ["Kwai Hing"], "categories": ["E-commerce", "Supply Chain", "Others", "Sales, CS & Business Devpt", "Sales Administration"], "post_time": "2022-01-10T10:13:18Z", "salary": {"currency": null, "max": null, "min": null, "period": "monthly", "term": null}, "salary_visible": false, "title_keywords": ["sales support executive"], "responsibilities": ["operations", "business opportunities", "quality", "implementation", "design", "teams", "develop", "maintain", "logistics", "sales team", "plan", "schedule", "contact", "operational procedures", "sops"], "requirements": {"degrees": ["degree", "bachelor"], "majors": [], "languages": ["english"], "language_level": ["fluent"], "hard_skills": ["project management", "forth", "writing skills", "microsoft office"], "soft_skills": ["self-motivated", "independently", "detail oriented", "writing skills", "communication", "project management", "multitask", "time management skill", "meet deadlines"], "languages_combined": [{"language": "english", "language_level": ["fluent"]}]}, "experience_required": {"duration": ["minimum 5 years"], "field": ["ecommerce", "logistics", "design"]}}, {"job_id": "100003009031267", "location_code": "hk", "company": "Silver Talent Corporation Limited", "job_title": "Clerical Officer (FRESH GRADS / 5 DAY /13 months)", "description": "The E-Commerce Coordinator executes website content initiatives to maintain and grow the eCommerce channel, optimize the user experience and supply chain, ensure cross-channel consistency and support online strategies. This role closely collaborates cross functionally to support Marketing, and Operational business goals.\n\nWHAT WE WILL TRUST YOU WITH\nOptimize the website layout and organization of products based on customer and competitive insights, Brand strategy and overall OnTheList online strategy.\nCreate and design online store images and banners\nIdentify opportunities and seek new initiatives to maximize sales (product bundle offers, improvements to navigation, site search and filtering to improve ease of product discovery)\nCreate product content (product names, descriptions and visuals) for the online flash sales, ensure the website reflects correct detail and prices, proactively amending any errors.\nEnsure cross-channel consistency with external actors, from brand partners to the offline operations team and marketing team.\nClose management of the supply chain, including warehouse and courier partners, to ensure smooth operations in all aspects of the customer journey.\nPrepare daily sales reports and reporting materials for brand partners and internal stakeholders.\nWork closely with the Customer Service team to rectify any product or delivery issues to assure excellent customer service.\nContribute to creative ideas that support and generate excitement around each online flash sale to increase visitation.\nWHAT IT TAKES\n1+ years of experience in e-commerce role\nMust have experience using Shopify or other retail e-commerce platform\nSome experience of supply chain or operations\nExcellent excel skills, copy writing and back office skills\nGood knowledge of design tools\nResponsible, well-organized and attention to details\nDegree holder in E-Commerce, Logistics or any related discipline\nExcellent written and spoken Chinese and English\nFresh graduates are welcome", "employment_types": ["Full Time"], "selling_points": ["Fresh graduates welcome", "double pay", "5 days"], "locations": ["Tsim Sha Tsui"], "categories": ["Banking / Finance", "Financial Services", "E-commerce", "Others"], "post_time": "2022-01-07T09:06:45Z", "salary": {"currency": null, "max": null, "min": null, "period": "monthly", "term": null}, "salary_visible": false, "title_keywords": ["officer"], "responsibilities": ["reporting", "business goals", "management", "creative ideas", "sales reports", "delivery issues", "operations", "website", "design", "user experience", "e-commerce platform", "banners", "back office", "maintain", "customer service", "ensure smooth operations", "logistics", "product content"], "requirements": {"degrees": ["degree holder"], "majors": ["e-commerce"], "languages": ["english", "chinese"], "language_level": ["excellent"], "hard_skills": ["ease", "excel", "e-commerce", "shopify", "flash"], "soft_skills": ["responsible", "well-organized", "customer service", "attention to details", "smooth", "creative"], "languages_combined": [{"language": "english", "language_level": ["excellent"]}, {"language": "chinese", "language_level": ["excellent"]}]}, "experience_required": {"duration": ["1+ years"], "field": ["ecommerce", "supply chain", "retail", "e-commerce"]}}, {"job_id": "100003009035602", "location_code": "hk", "company": "Delivery Hero Food Hong Kong Limited", "job_title": "Content Quality Executive", "description": "This\u00a0position will be under HOME+ e-commerce platform.\n\nOur Vision of Home+ is to set up a merchant ecosystem of merchants with shared value, covering different aspects of our customers\u2019 daily household purchases. The mission is to provide customers with the best value for money for the promotional products and services offered, from time to time. For more information, please feel free to visit our website at\u00a0https://home-plus.hk/\n\n\n\nWhat efforts you need to make?\n\nProviding administrative support to daily sales related activities\nResponse customer enquiry, ordering input, invoicing, order delivery & after sales service\nPerform the general administrative works for document printing, scanning, copying, mailing, filing and report generation\nCoordination and communication with different departments\u00a0\nLet's check if you are /have\u2026\n\nF.5 or above\nAt least 1-2 years sales/contract administration experience, experience in handling Stationary & Supplies products is preferable\nCustomer oriented, responsible, well-organized, work with minimum supervision & able to work under pressure\nGood working attitude and communication skill\nProficient in using MS Office such as Word and Excel\nImmediate available is\u00a0highly preferred\n\n", "employment_types": ["Full Time", "Permanent"], "selling_points": ["Great exposure to commercial e-commerce setting", "International organizational culture", "Welcome junior with 1 year content experience"], "locations": ["Sheung Wan"], "categories": ["E-commerce", "Others"], "post_time": "2022-01-10T07:50:02Z", "salary": {"currency": null, "max": null, "min": null, "period": "monthly", "term": null}, "salary_visible": false, "title_keywords": ["executive"], "responsibilities": ["scanning", "copying", "administrative support", "work under pressure", "contract administration", "website", "invoicing", "communication", "coordination", "e-commerce platform", "report"], "requirements": {"degrees": [], "majors": [], "languages": [], "language_level": [], "hard_skills": ["excel", "plus", "e-commerce", "word", "make", "ms office"], "soft_skills": ["good working attitude", "responsible", "communication skill", "well-organized", "communication", "coordination", "work under pressure"], "languages_combined": []}, "experience_required": {"duration": ["at least 1-2 years"], "field": ["administration"]}}, {"job_id": "100003009035812", "location_code": "hk", "company": "Macroview Telecom Limited", "job_title": "Business Analyst Trainee / Junior Business Analyst", "description": "REQUIREMENTS\n\nCandidates with 1-2 years working experience from any industries and or potential FRESH GRADS who are interesting in FINANCIAL FIELDS are considered;\nSkillful knowledge in Excel;\nWilling to learn and to do attitude, sedate under pressure, ATTENTIVE, reliable, and self-disciplined;\n9.5 hours daily SHIFT between 08:00-23:30 required, Mondays to Fridays only.\nPublic Holidays SHIFT required with compensation.\nNO NEED TO WORK OVERTIME.\n\nJOB DESCRIPTION\n\nTo consolidate and settle clients\u2019 account info to internal departments;\nTo sort and e-file clients\u2019 account data;\nNON-SALES role, no outbound duties required.\u00a0\n\nWe offer attractive benefits and remuneration package including first-tier working environment, 13 months salary, free lunch, performance and discretionary bonus, 5 day work, full medical and dental insurance coverage scheme, prospective career promotion, education allowance, birthday allowance, free overseas sight-seeing trip etc. Interested parities please send your CV with current and expected salary by clicking \u201cAPPLY NOW\u201d.", "employment_types": ["Full Time"], "selling_points": ["Participate in JIT delivery of Digital solution", "Thrive as 'all-round' Business Analyst", "Fresh graduates are also welcome"], "locations": ["Others"], "categories": ["Others", "Others", "E-commerce", "Product Management / Business Analyst", "Others"], "post_time": "2022-01-10T08:27:09Z", "salary": {"currency": null, "max": null, "min": null, "period": "monthly", "term": null}, "salary_visible": false, "title_keywords": ["business analyst", "trainee", "junior"], "responsibilities": ["insurance", "data"], "requirements": {"degrees": [], "majors": [], "languages": [], "language_level": [], "hard_skills": ["excel", "no"], "soft_skills": ["attentive", "work overtime", "under pressure", "willing to learn", "reliable"], "languages_combined": []}, "experience_required": {"duration": ["1-2 years"], "field": ["financial"]}}, {"job_id": "100003009020915", "location_code": "hk", "company": "Harvey Nichols (Hong Kong) Limited", "job_title": "E-Commerce Stylist (Frontline In-store position)", "description": "'Hungry to make a difference? Then foodpanda may be the place for you!'\n\nAt foodpanda, we\u2019re on a mission to redefine customers\u2019 food and shopping experience as a multifaceted online platform across the 14 countries we operate in. We\u2019re all about bringing on the smartest and brightest minds as we continue to grow in a fast-moving and agile environment, and hiring those who can thrive in an energetic and hardworking start-up culture. We strive to become everybody\u2019s most loved delivery platform, however, this won't happen without some really awesome people!\n\nWe are looking for a highly-driven and motivated\u00a0Content Quality Executive\u00a0to join our fun, professional and dedicated Commercial Department based here in Hong Kong. Our Commercial Department oversees the end-to-end restaurant partners\u2019 operations and businesses, from partners identification & signing to onboarding & account management, as well as new venture developments. If you are a food lover, join us now to make a direct impact and contribute to large-scale success!\u00a0\u00a0\n\nKnow more about the team\n\nOur Partner Operations team operates under the Commercial Department. Our team is responsible for onboarding restaurant partners, including their \u201cstore-front\u201d such as menus, prices, and dish photos. We also ensure our partners are well taken care of when they have operational enquiries. As a part of this team, you will be an integral component to the success of our platform\u2019s operations!\n\nRoles and Responsibilities\n\nOwns content quality tasks, focusing on vendors\u2019 menus translations (from English to Traditional Chinese, and vice versa) and its\u2019 maintenance\nDeploy the translation results to our back-end tools\nProofread and perform quality check of the translation results\nParticipate in strategizing for menu content enhancements and automation\nExecute related ad-hoc tasks\n\nQualifications and Requirements\n\nAt least 1 full year of working experience\nComfortable in operating basic functions of Excel (lookup, pivot, IFs), Word, Power Point (and Google Suite's equivalent)\nAble to type English and Traditional Chinese at business standard speed\nAble to translate from English to Traditional Chinese, and vice versa, with high accuracy\nAble to execute assigned tasks and complete it in a timely manner, with high degree of quality and accuracy. Strong attention to details\nAble to identify problems quickly and flag to the managers\nRespect GRC (Governance, Risk Management, and Compliance) and Legality matters\nDemonstrates professional, positive, resilience and can-do attitude\nResourceful, full of ideas and aim for sustainable and scalable long term solutions\nEager to constantly improve and overcome challenges. Adapt and embrace changes\nClear, concise, structured verbal and written communications. Full understanding in choosing appropriate communication tools and channels\nTranslation or Language major/minor is a plus\n\nWhat We Offer\n\nA dynamic, fast paced environment\nA vibrant and international team with diverse background\nSteep learning curve in e-commerce & entrepreneurship\nLearning & development programs and skills trainings\nFlexible working hours and agile company with a flat hierarchical structure\nMonthly staff allowance and corporate discounts including at restaurants, gyms and many more\nAgile office environment with a fully-stocked beverage fridge and self-serve beer\nUnlimited paid leave policy", "employment_types": ["Full Time", "Permanent"], "selling_points": ["Ecommerce Stylist", "Fashion enthusiast", "Online sales experience"], "locations": ["Admiralty"], "categories": ["Sales, CS & Business Devpt", "Retail Sales", "Others", "E-commerce", "Others"], "post_time": "2022-01-05T02:32:10Z", "salary": {"currency": null, "max": null, "min": null, "period": "monthly", "term": null}, "salary_visible": false, "title_keywords": [], "responsibilities": ["quality check", "maintenance", "ad-hoc tasks", "quality", "deploy"], "requirements": {"degrees": ["degree"], "majors": ["it"], "languages": ["english", "chinese"], "language_level": [], "hard_skills": ["excel", "plus", "basic", "word", "power point", "translation"], "soft_skills": ["resourceful", "can-do attitude", "timely", "clear", "communication", "attention to details", "structured", "positive"], "languages_combined": [{"language": "english", "language_level": []}, {"language": "chinese", "language_level": []}]}, "experience_required": {"duration": [], "field": []}}, {"job_id": "100003009032105", "location_code": "hk", "company": "SEB Asia Limited", "job_title": "Regional E-Commerce Executive", "description": "Job Responsibilities:\n\nOrganize activities to engage business stakeholders in business requirements elicitation & analysis for new transformation initiatives\nAssist direct supervisor to do Project Monitoring and Control\nUsing UML to illustrate as-is/to-be Business Process Flows\nCollaborate with technical teams in implementation and maintenance of business solutions (Web, Mobile, etc.)\nHandle UAT planning, execution and follow-up\nPrepare and conduct system demo/training for business users\nPerform other ad-hoc projects and tasks as assigned by direct supervisor\nJob Requirement:\n\n\nApplicants should be Degree holders in Business Administration, Information System or Computer Science related disciplines\n0 - 1 year working experience in business analysis, solution development or data analysis.\nCandidates with less experience will be considered as Business Analyst Trainee\nKnowledge/Experience in Project Management is preferred\nKnowledge/Experience in Software Development/Programming is preferred\nKnowledge/Experience in Scrum/Agile is preferred\nKnowledge/Experience in UML is preferred\nKnowledge/Experience in latest technologies is an advantage\nKnowledge/Experience in ERP, HCM & CRM systems is an advantage\nStrong documentation and presentation skill\nStrong communication & inter-personal skills\nIndependent, proactive, innovative, detail-minded and able to work under pressure", "employment_types": ["Full Time", "Permanent"], "selling_points": ["Acceleration of E-Commerce across APAC", "Regional initiatives, APAC DTC", "An exciting opportunity to join our growing team"], "locations": ["Yau Tsim Mong Area"], "categories": ["E-commerce", "Marketing - Brand / Product Management", "Product Management / Business Analyst", "Others"], "post_time": "2022-01-07T10:14:54Z", "salary": {"currency": null, "max": null, "min": null, "period": "monthly", "term": null}, "salary_visible": false, "title_keywords": ["executive"], "responsibilities": ["collaborate with", "control", "uat", "maintenance", "analysis", "monitoring", "teams", "implementation", "business process", "ad-hoc projects", "planning"], "requirements": {"degrees": ["degree"], "majors": ["related disciplines", "business administration", "computer science"], "languages": [], "language_level": [], "hard_skills": ["presentation skill", "agile", "analysis", "information system", "erp", "project management", "programming", "documentation"], "soft_skills": ["presentation skill", "detail-minded", "independent", "agile", "inter-personal skills", "innovative", "communication", "project management", "proactive", "work under pressure"], "languages_combined": []}, "experience_required": {"duration": ["0 - 1 year"], "field": ["development", "data analysis", "project management", "business", "programming", "software development", "business analysis"]}}, {"job_id": "100003009031157", "location_code": "hk", "company": "Ztore HK Limited", "job_title": "[TVB E-commerce] Assistant Administration Manager", "description": "Mission:\nGroupe SEB is pursuing digital transformation and acceleration with a view to provide each consumer with the best, personalized brand and product experience all along the buying and usage journey. In order to fuel our sustainable growth and long-term strategy, we are inviting talented and energetic individual to join our professional team.\n\nThe incumbent will be supporting the deployment and acceleration of E-Commerce across APAC in alignment with the strategic direction.\nWhat\u2019s in it for you:\nWithin the framework, in charge of activating roadmaps for APAC, support the Senior Manager liaising between Corporate, Business Units and Continent, accompany markets in their implementation & identify and share best practices\nSupport and drive APAC markets in their acceleration plans on E-Commerce strategies, in particular, Direct to Customer and eRetailers perimeters\nPartner with Corporate team to strengthen the content localization for APAC\nSupport regional initiatives (e.g. JBP, Brand Days etc)\nEstablish clear data measurement, leverage all E-Commerce dashboard metrics to provide insights and actions\nFacilitate APAC best practice and sharing portal to provide market support and inspiration\nBe the key user on E-Commerce tools and platforms and provide training to APAC stakeholders\nWho we are looking for:\nPossess a real passion E-Commerce\n1 to 3 years\u2019 working experience within E-Commerce environment\nProven experience on project management\nStrong ability to influence, with both assertiveness and teamwork spirit\nStrong communication skills\nStrong analytical skills\nFluent English\nProactive, positive and open minded\nWe offer attractive remuneration package to the right candidate including 5-day work, double pay, discretionary bonus, family leave & birthday leave, medical, dental / life insurance scheme, etc. Interested parties please apply with full resume with expected salary and current salary to Human Resources Department. For company details, please visit our\u00a0website.", "employment_types": ["Full Time"], "selling_points": ["Manage general office administration work", "Review and maintain office administration policies", "Reporting to HR & Admin Manager, TVB e-Commerce"], "locations": ["Lai Chi Kok"], "categories": ["E-commerce", "Others"], "post_time": "2022-01-07T09:01:17Z", "salary": {"currency": null, "max": null, "min": null, "period": "monthly", "term": null}, "salary_visible": false, "title_keywords": ["assistant administration manager"], "responsibilities": ["provide training", "provide insights", "data", "measurement", "implementation", "e-commerce strategies", "communication", "project management", "plans", "insurance"], "requirements": {"degrees": [], "majors": [], "languages": ["english"], "language_level": ["fluent"], "hard_skills": ["e-commerce", "scheme", "analytical skills", "project management", "deployment"], "soft_skills": ["communication skills", "proactive", "analytical skills", "clear", "project management", "teamwork spirit", "open minded", "energetic", "positive"], "languages_combined": [{"language": "english", "language_level": ["fluent"]}]}, "experience_required": {"duration": ["1 to 3 years"], "field": ["digital", "project management", "brand", "e-commerce"]}}, {"job_id": "100003009034627", "location_code": "hk", "company": "Bluebell (Asia) Limited", "job_title": "Digital & IT Internship (Part Time / Full Time)", "description": "WHYare we looking for this position?\n\nAs a fast growing e-Commerce group, aiming to shape a new online shopping paradigm and experience in Hong Kong, we need an Assistant Administration Manager, who will consistently and proactively deliver a better livelihood and environment to our colleagues.\n\n\n\nWHAT duties will you be responsible for?\n\nReporting to HR & Admin Manager of TVB E-commerce group, you will supervise a team of administrative staff to provide administrative and clerical general office support to the company, in multiple office sites. Your duties will include:\n\nServe as an office manager, setting up SOPs to constantly maintain and improve office\u2019s environment, such as ensuring the equipment readiness, supplies in meeting rooms, and replenishment for our snacks and beverage (very important!)\nManage and ensure general administration services including reception services and deliverables\nResponsible for managing general office administration, office renovation and relocation projects, reinstatement work and office improvement works\nHandle the procurement of office supplies, furniture and equipment and maintain an up-to date inventory record\nPerform sourcing, analyze and exercise cost control on all purchases to optimize the pricing and product quality\nLiaise with building management offices and/or relevant parties in the areas of maintenance, building facilities and general services\nAny other administrative and ad-hoc tasks assigned by management\n\nRequirements\n\nBachelor degree holder or above\nMinimum 5 years' experience in secretarial / administrative work\nProactive, detail-oriented, empathetic with everyone\nDemonstrate good organization skills\nExcellent command of written Chinese and English\nKnowledge in MS PowerPoint, Excel, Word and other MS Office software\nCandidate with less experience may be considered for a more junior position", "employment_types": ["Full Time", "Part Time", "Temporary", "Internship"], "selling_points": ["Part Time / Full Time Internship", "Undergraduate students in eCommerce, Digital or IT", "Hands-on experience on digital & IT projects"], "locations": ["Quarry Bay"], "categories": ["Information Technology (IT)", "Others", "E-commerce", "Product Management / Business Analyst", "Others"], "post_time": "2022-01-10T03:49:40Z", "salary": {"currency": null, "max": null, "min": null, "period": "hourly", "term": null}, "salary_visible": false, "title_keywords": ["internship"], "responsibilities": ["software", "renovation", "quality", "building management", "maintain", "liaise with", "administration", "reception services", "administrative work", "office administration", "office support", "reporting", "management", "office supplies", "inventory record", "sops", "maintenance", "hr", "ad-hoc tasks", "replenishment", "cost control"], "requirements": {"degrees": ["bachelor degree holder"], "majors": [], "languages": ["english", "chinese"], "language_level": ["excellent"], "hard_skills": ["excel", "maintenance", "e-commerce", "word", "ms powerpoint", "ms office"], "soft_skills": ["organization skills", "proactive", "responsible", "detail-oriented"], "languages_combined": [{"language": "english", "language_level": ["excellent"]}, {"language": "chinese", "language_level": ["excellent"]}]}, "experience_required": {"duration": ["minimum 5 years"], "field": ["administration", "secretarial", "administrative", "e-commerce"]}}, {"job_id": "100003009032146", "location_code": "hk", "company": "Kicks-Crew Company Limited", "job_title": "E-commerce Operations Assistant", "description": "An exciting opportunity is available for Fashion Enthusiast and E-Commerce savvy persons to showcase your fashion sense and styling professionalism!\u00a0\n\nResponsibilities:\n\nTo build and expand the customer base through exceptional customer service and fashion knowledge\nTo maximize online and in-store sales opportunities for the achievement of sales target\nTo initiate customer\u2019s interest on fashion trends and Personal Styling Services based on our website (www.harveynichols.com.hk) and in-store products\nAssisting customers to build their wardrobe and management of customer online /offline\u00a0enquiries\u00a0\nCustomer data maintenance and reporting\n\nRequirements:\n\nA fashion enthusiast with 1-2 years fashion retail sales experience\nGood fashion sense with an eye for details on online products to recommend fashion styles to target customers\nExcellent interpersonal & communication skill which can drive sales effectively\nGood command of spoken English and Chinese (Cantonese and Mandarin)\nUnderstanding of luxury services and social networking tools\n\nWe offer:\n\nExcellent career prospects\nCompetitive pay\n8 days off per month\n17 Public Holidays\n11 Annual Leave\nVarious allowances\nAttendance bonus\nMedical benefits\nComprehensive training\n\nPlease send your application with detailed resume quoting\u00a0Position Title, with date available, current and expected salary via email\u00a0:\n\nc a r e e r s @ h a r v e y n i c h o l s . c o m . h k\u00a0or clicking \"Apply Now\"\n\nWe are an equal opportunity employer and welcome applications from all qualified candidates. Personal data provided by job applicants will be used strictly in accordance with our personal data policy and for recruitment purposes only. Candidates not notified within eight weeks may consider their application unsuccessful. All related information will be kept in our file for up to 24 months. A copy of our Personal Information Collection Statement will be provided upon request by contacting our Human Resources Division.", "employment_types": ["Full Time"], "selling_points": [], "locations": ["Tsuen Wan Area"], "categories": ["E-commerce", "Others"], "post_time": "2022-01-07T10:19:21Z", "salary": {"currency": "HKD", "max": 16999, "min": 14000, "period": "monthly", "term": null}, "salary_visible": true, "title_keywords": ["operations assistant"], "responsibilities": ["reporting", "management", "maintenance", "sales target", "website", "customer service", "customer data"], "requirements": {"degrees": [], "majors": [], "languages": ["cantonese", "english", "chinese", "mandarin"], "language_level": ["good command"], "hard_skills": [], "soft_skills": ["communication skill", "interpersonal"], "languages_combined": [{"language": "cantonese", "language_level": ["good command"]}, {"language": "english", "language_level": ["good command"]}, {"language": "chinese", "language_level": ["good command"]}, {"language": "mandarin", "language_level": ["good command"]}]}, "experience_required": {"duration": ["1-2 years"], "field": ["retail"]}}, {"job_id": "100003009029434", "location_code": "hk", "company": "Manulife (International) Limited", "job_title": "\u8ca1\u52d9\u7b56\u5283\u7d93\u7406 Financial Planning Manager", "description": "JOIN OpenRice\u2026\u2026if you want to service our\n\n\u00a05 million App users with\n\n\u00a09 million pageviews per day in Hong Kong! \u00a0\n\nOpenRice\u00a0is seeking an energetic and passionate individual to join a dynamic and collaborative environment as part of\u00a0marketing\u00a0team.\n\nYou will be responsible for:\n\nProduce food and beverage related content for OpenRice voucher service\nCopies writing and photo editing\nData input\nMerchant support and follow up\nSupport OpenRice's projects and campaigns\n\nYou should possess:\n\n\nDiploma or above in any disciplines\nGood command of both spoken and written English and Chinese\nGood interpersonal skill and telephone manner in order to maintain high quality service standard to merchants\nIndependent, attentive to details and self-motivated\nStrong writing and editorial skills\nKnowledge of Photoshop\n\nWe offer a competitive remuneration package including excellent career prospects to the right candidate. Interested parties please submit your detailed resume with expected salary and available date by clicking the Quick Apply button.\n\nAll personal information submitted by job applicants will be used for recruitment purposes and we reserve the rights to consider the applications for other positions in our Group.", "employment_types": ["Full Time", "Permanent", "Contract", "Internship"], "selling_points": ["\u4f60\u559c\u6b61\u91d1\u878d\u4e36\u6295\u8cc7\u53ca\u7406\u8ca1\u4e09\u65b9\u9762\u7684\u767c\u5c55\u55ce\uff1f", "\u4f60\u60f3\u300c\u5de5\u4f5c\u8207\u751f\u6d3b\u300d\u4f86\u904e\u5b8c\u7f8e\u5e73\u8861\u55ce\uff1f", "\u4f60\u5e0c\u671b\u300c\u52e4\u529b+\u300d\u53ef\u7a81\u7834\u50b3\u7d71\u6649\u5347\u968e\u68af\u55ce\uff1f"], "locations": ["Kwun Tong"], "categories": ["Beauty Care / Health", "Athletics / Fitness / Sports & Recreation", "Hospitality / F & B", "Tourism / Travel Agency", "E-commerce", "Others"], "post_time": "2022-01-07T05:14:43Z", "salary": {"currency": "HKD", "max": 54999, "min": 20000, "period": "monthly", "term": null}, "salary_visible": true, "title_keywords": ["manager"], "responsibilities": ["service standard", "quality", "data input", "maintain", "editing"], "requirements": {"degrees": ["diploma or above"], "majors": ["any disciplines"], "languages": ["english", "chinese"], "language_level": ["good command"], "hard_skills": ["dynamic", "photoshop"], "soft_skills": ["passionate", "self-motivated", "independent", "responsible", "attentive to details", "collaborative", "interpersonal skill", "dynamic", "energetic", "telephone manner"], "languages_combined": [{"language": "english", "language_level": ["good command"]}, {"language": "chinese", "language_level": ["good command"]}]}, "experience_required": {"duration": [], "field": []}}, {"job_id": "100003009028635", "location_code": "hk", "company": "Profit Sail Int'l Express (H.K.) Ltd", "job_title": "Accountant", "description": "Operational excellence is critical to our business. For every product sold, every new platform sold and new market entered, it is Operations that enable business to flow.\n\nThe Operations team sits at the center of business, coordinating across teams and multi-disciplinary functions. Reflecting KicksCrew\u2019s core values of constant improvement and innovation, you will join a growing team that solves problems with mutual trust, empathy and speed.\u00a0\n\nThe E-commerce Operations Assistant is a crucial role in our company, you will be serving as the coordinator across different teams. The ideal candidate has an understanding of e-commerce and technology with an eagerness to provide the best customer experience possible.\u00a0\n\nWe will teach you the nuts and bolts of E-commerce and show you behind-the-scenes. With this opportunity, you will have a clear career path in the fastest growing world of E-commerce.\n\nIn this role you will:\n\nBe our champion of operations excellence and coordinate across teams\nAssist Omni-channel E-commerce platforms operations and order fulfillment\nAssist on scheduling inbound shipments and logistics to ensure that there is sufficient storage space and manpower for the shipments\nAssist evaluates and manages deliveries and shipments to improve inventory control procedures\nHandle issues arising in shipping or inventory handling\nAid in the feedback/design of our systems, the information flows and the processes that make it all work\nCoordinate with Customer Service, Warehouse, Logistics/Shipping, Engineering teams\u00a0\n\nWe are looking for:\n\nStrong passion for obsessive customer service and interest in E-commerce\nWillingness to learn and ability to handle a steep learning curve\nHighly organized with demonstrated attention to detail\nPreferably 1 year experience in the e-commerce industry / sneakers space\nDiploma/ bachelor\u2019s degree in related discipline\nProficiency in English and Cantonese (Fluent Mandarin will be a plus)\nProficiency in using MS Word, Excel and Chinese word processing\nSelf-motivated, adaptive and flexible, and able to work independently\nImmediate availability is preferable", "employment_types": ["Full Time"], "selling_points": ["Full Set Account", "Maintain and administrate the financial accounts", "Handle daily accounting works"], "locations": ["Kwai Fong"], "categories": ["Accounting", "Accountant", "Transportation & Logistics", "Freight Forwarding", "E-commerce", "Others"], "post_time": "2022-01-07T02:43:03Z", "salary": {"currency": null, "max": null, "min": null, "period": "monthly", "term": null}, "salary_visible": false, "title_keywords": ["accountant"], "responsibilities": ["shipping", "operations", "inventory", "systems", "teams", "e-commerce platforms", "procedures", "design", "coordinate", "scheduling", "coordinate with", "order fulfillment", "logistics", "inventory control", "customer service"], "requirements": {"degrees": ["diploma", "degree", "bachelor"], "majors": [], "languages": ["cantonese", "english", "chinese", "mandarin"], "language_level": ["proficiency", "fluent"], "hard_skills": ["excel", "plus", "chinese word processing", "e-commerce", "make", "ms word"], "soft_skills": ["flexible", "organized", "self-motivated", "work independently", "passion for", "clear", "customer service", "learning", "attention to detail", "empathy", "ideal"], "languages_combined": [{"language": "cantonese", "language_level": ["proficiency"]}, {"language": "english", "language_level": ["proficiency"]}, {"language": "chinese", "language_level": ["proficiency"]}, {"language": "mandarin", "language_level": ["fluent", "proficiency"]}]}, "experience_required": {"duration": ["1 year"], "field": ["e-commerce"]}}, {"job_id": "100003009027579", "location_code": "hk", "company": "Ho Wa Sporting Goods Company Limited", "job_title": "Full Time\u9580\u5e02\u7db2\u5e97\u71df\u904b\u52a9\u7406(\u6236\u5916\u7528\u54c1)-\u516c\u773e\u5047\u671f\u4f11\u606f  Sales Associate (Outdoor Sports)", "description": "\u00a0\u300c\u60f3\u7a81\u7834\u300d\u4e36\u300c\u8df3\u51fa\u8212\u9069\u5708\u300d\u4e36\u300c\u4e0d\u7518\u65bc\u5faa\u898f\u8e48\u77e9\u300d\u2026\n\u6211\u5011\u63d0\u4f9b\u300c\u5728\u8077\u57f9\u8a13\u4e36\u5feb\u901f\u6649\u5347\u300d\u4e26\u4ee5\u300c\u501f\u529b\u6253\u529b\u4e36\u5171\u4eab\u8cc7\u6e90\u300d\u7684\u7cbe\u795e\uff0c\u4f86\u6253\u9020\u4f60\u7684\u672a\u4f86\n\n\u767e\u842c\u5e74\u85aa\u4e0d\u662f\u5922\n\n\u798f\u5229\uff1a\n\u6bcf\u2f49\u71df\u696d\u6d25\u8cbc($14,000 - $30,000) +\u4f63\u91d1 + \u82b1\u7d05 + \u5e74\u7d42\u734e\u91d1\n\u7279\u5feb\u6649\u5347\u5236\u5ea6\uff0c\u52a9\u4f60\u5efa\u2f74\u5718\u968a\uff0c\u92b7\u552e\u53ca\u7ba1\u7406\u540c\u6b65\u767c\u5c55\n\n\u5c08\u696d\u5728\u8077\u57f9\u8a13\uff0c\u63d0\u5347\u92b7\u552e\u6280\u5de7\u53ca\u7522\u54c1\u8cc7\u8a0a\n\u8457\u91cd\u5de5\u4f5c\u8207\u751f\u6d3b\u5e73\u8861\uff0c\u771f\u6b63\u81ea\u4e3b\u81ea\u7531\n\u696d\u7e3e\u734e\u8cde\u5305\u62ec\u6bcf\u6708\u3001\u6bcf\u5b63\u53ca\u5e74\u5ea6\u5609\u8a31\u665a\u5bb4\u4ee5\u53ca\u51fa\u5e2d\u6d77\u5916\u696d\u52d9\u6703\u8b70\n\u900f\u904e\u6301\u7e8c\u5c08\u696d\u57f9\u8a13\uff0c\u914d\u5408\u5718\u968a\u7d93\u7406\u63d0\u4f9b\u500b\u2f08\u6307\u5c0e\uff0c\u52a9\u60a8\u6649\u8eab\u6210\u2f8f\u696d\u5167\u6700\u9802\u5c16\u7684\u767e\u842c\u5713\u684c\u6703\uff08MDRT\uff09\n\u5de5\u4f5c\u7bc4\u570d\n\u7b56\u5283\u53ca\u53c3\u8207\u4e0d\u540c\u985e\u578b\u7684\u5e02\u5834\u63a8\u5ee3\u6d3b\u52d5\n\u5354\u52a9\u50f1\u4e3b\u958b\u7acb\u5f37\u7a4d\u91d1\u5e33\u6236\uff0c\u4e26\u6574\u5408\u500b\u4eba\u8cc7\u7522\u81f3\u5b8f\u5229\n\u914d\u5408\u653f\u5e9c\u653f\u7b56\uff0c\u5b89\u6392\u9000\u4f11\u65b9\u6848 (\u9000\u7a05\u5e74\u91d1\u4e36\u53ef\u6263\u7a05\u81ea\u9858\u6027\u4f9b\u6b3e\u53ca\u81ea\u9858\u91ab\u4fdd)\n\u63d0\u4f9b\u9069\u5408\u4f01\u696d\u53ca\u500b\u4eba\u4e4b\u300c\u4fdd\u8cbb\u878d\u8cc7\u65b9\u6848\u300d\n\u4e00\u822c\u4fdd\u96aa\u53ca\u5718\u9ad4\u91ab\u7642\u65b9\u6848\n\u57fa\u91d1\u6295\u8cc7\u898f\u5283\u53ca\u7ba1\u7406\n\u5c0d\u8c61\u8981\u6c42 :\n\u4e2d\u4e94\u7562\u696d\u3001\u9999\u6e2f\u4e2d\u5b78\u2f42\u6191\uff08\u4e2d / \u82f1\u53ca\u6578\u5b78\u4e94\u79d1\u53ca\u683c\uff09\u6216\u6301\u540c\u7b49\u5b78\u6b77\u4ee5\u4e0a\n1\u5e74\u6216\u4ee5\u4e0a\u5de5\u4f5c\u7d93\u9a57\uff0c\u5177\u5ba2\u6236\u670d\u52d9\u6216\u92b7\u552e\u5de5\u4f5c\u7d93\u9a57\u66f4\u4f73\n\u6210\u719f\u7a69\u91cd\u3001\u6027\u683c\u958b\u6717\u3001\u7a4d\u6975\u9032\u53d6\u3001\u2f83\u5f8b\u53ca\u826f\u597d\u6e9d\u901a\u6280\u5de7\n\u6709\u8cac\u4efb\u611f\uff0c\u5c0d\u751f\u6d3b\u6709\u8981\u6c42\u548c\u671f\u671b\n\u559c\u6b61\u5b78\u7fd2\u65b0\u4e8b\u7269\uff0c\u6bcf\u5929\u767c\u653e\u6b63\u80fd\u91cf\n\u5f48\u6027\u4e0a\u73ed\u6642\u9593\u00a0\uff0c\u6b61\u8fce\u00a0\u7a7a\u4e2d\u670d\u52d9\u54e1 / \u65c5\u904a\u696d\u5f9e\u696d\u54e1 / \u5168\u8077\u5abd\u5abd\u00a0 \u52a0\u5165\n\u6211\u5011\u7684\u512a\u52e2\uff1a\n\n\u00a0\u70ba\u5ba2\u6236\u63d0\u4f9b\u6700\u5c08\u696d\u4e36\u6700\u5408\u9069\u7684\u5206\u6790\u670d\u52d9, \u8207\u5ba2\u6236\u4fdd\u6301\u9577\u9060\u800c\u53c8\u6301\u4e45\u7684\u95dc\u4fc2\uff0c\u5c07\u4e00\u5207\u6a5f\u6703\u5316\u6210\u300c\u5546\u6a5f\u300d\uff0c\u6642\u4ee3\u4e0d\u65b7\u8f49\u8b8a\uff0c\u8981\u8fce\u5408\u5e02\u5834\u9700\u8981\uff0c\u5c31\u8981\u53ca\u65e9\u638c\u63e1\u2f8f\u696d\u5546\u6a5f !\n\u5b8f\u5229\u662f\u5168\u6e2f\u6700\u4ee4\u5ba2\u6236\u6eff\u610f\u7684\u4fdd\u96aa\u54c1\u724c\u4e4b\u4e00\uff0c\u5f37\u7a4d\u91d1\u5e02\u5834\u4f54\u6709\u7387\u6392\u884cNO.1\n\u75ab\u60c5\u6f38\u8da8\u7a69\u5b9a\uff0c\u65b0\u6210\u2f74\u7684\u516c\u53f8\u5c07\u6703\u9678\u7e8c\u51fa\u73fe\uff0c\u50f1\u4e3b\u5fc5\u9808\u70ba\u54e1\u2f2f\u8a2d\u2f74\u5f37\u7a4d\u2fa6\u8a08\u5283\u53ca\u8cfc\u8cb7\u52de\u2f2f\u4fdd\u96aa (\u6cd5\u4f8b\u898f\u5b9a)\n\u91ab\u7642\u901a\u8139\u9a5a\u2f08\uff0c\u7a4d\u84c4\u6613\u88ab\u84b8\u767c\uff0c\u75ab\u60c5\u4e0b\u5371\u75be\u53ca\u4f4f\u9662\u4fdd\u96aa\u66f4\u4ee4\u2f08\u95dc\u6ce8\n\u53ef\u9000\u7a05\u5e74\u2fa6\u3001\u53ef\u6263\u7a05\u81ea\u9858\u6027\u4f9b\u6b3e\u53ca\u2f83\u9858\u91ab\u4fdd\u8cfc\u8cb7\u71b1\u6f6e\u5347\u6eab\uff0c\u5207\u8eab\u7684\u7406\u8ca1\u6aa2\u8996\u670d\u52d9\u9700\u6c42\u2f24\u589e\u3002\n\u2fb9\u6e2f\u87ec\u806f\u5168\u7403\u6700\u2ed1\u58fd\u5730\u5340\uff0c\u2faf\u5c0d\u6f2b\u2ed1\u7684\u9000\u4f11\u2f63\u6d3b\uff0c\u9000\u4f11\u898f\u5283\u624d\u662f\u61c9\u5c0d\u2ed1\u58fd\u2fb5\u96aa\u7684\u89e3\u6c7a\u65b9\u6cd5\u3002\n\n\u4ee5\u4e0a\u7a2e\u7a2e\u90fd\u70ba\u7406\u8ca1\u7b56\u5283\u2f8f\u696d\u5e36\u4f86\u7121\u9650\u5546\u6a5f\uff0c\u8aa0\u9080\u95a3\u4e0b\u52a0\u2f0a\u6211\u5011\u5718\u968a\uff0c\u5171\u540c\u5275\u5bcc!\n\n\u2f74\u5373\u7533\u8acb \u201cApply now\u201d\u00a0\u00a0\u5c07\u5c65\u6b77\u96fb\u90f5\u7d66\u6211\u5011\uff0c\u8e0f\u51fa\u6210\u529f\u7684\u7b2c\u2f00\u6b65!", "employment_types": ["Full Time"], "selling_points": ["\u7db2\u5e97; \u9580\u5e02; \u92b7\u552e; E COMMERCE", "SALES; CUSTOMER SERVICE; ONLINE SHOP", "\u92b7\u552e\u54e1; \u7406\u8ca8\u54e1; \u5ba2\u6236\u670d\u52d9"], "locations": ["Yau Tsim Mong Area"], "categories": ["Sales, CS & Business Devpt", "Retail Sales", "Others", "E-commerce", "Others"], "post_time": "2022-01-06T10:25:50Z", "salary": {"currency": null, "max": null, "min": null, "period": "monthly", "term": null}, "salary_visible": false, "title_keywords": ["sales associate"], "responsibilities": [], "requirements": {"degrees": [], "majors": [], "languages": [], "language_level": [], "hard_skills": [], "soft_skills": [], "languages_combined": []}, "experience_required": {"duration": [], "field": []}}, {"job_id": "100003009024484", "location_code": "hk", "company": "Riverfield Life Limited", "job_title": "\u5009\u52d9\u54e1 (\u5c6f\u9580)", "description": "Responsibilities:\n\nBe a responsible and careful planner to deliver quality e-commerce service at a good product service level to our customers\nBe a collaborator to communicate with different parties\nMonitor inventory level and perform replenishment activities to maintain a healthy inventory control\nMaintain reporting documents\n\nRequirements:\n\n\nResponsible, detail minded and able to work independently\nStrong communication skills\n\nGood command of Chinese and written English\nGood computer skills including Excel, Chinese and English typing\nFresh graduates are welcome", "employment_types": ["Full Time"], "selling_points": [], "locations": ["Tuen Mun Area"], "categories": ["E-commerce", "Others"], "post_time": "2022-01-06T01:27:41Z", "salary": {"currency": null, "max": null, "min": null, "period": "monthly", "term": null}, "salary_visible": false, "title_keywords": ["\u5009\u52d9\u54e1"], "responsibilities": ["communicate with", "reporting", "inventory", "monitor", "quality", "replenishment", "maintain", "inventory control"], "requirements": {"degrees": [], "majors": [], "languages": ["english", "chinese"], "language_level": ["good command", "good"], "hard_skills": ["excel", "computer skills", "typing"], "soft_skills": ["communication skills", "work independently", "responsible"], "languages_combined": [{"language": "english", "language_level": ["good command", "good", "good"]}, {"language": "chinese", "language_level": ["good command", "good", "good"]}]}, "experience_required": {"duration": [], "field": []}}, {"job_id": "100003009039754", "location_code": "hk", "company": "Factory 55 Holdings Limited", "job_title": "Assistant/ Junior Photographer", "description": "Looking for Photographer \u00a0for LUXURY clothing brands in their Studio. This role requires candidates who are creative with a keen attention for detail. Candidates for this position must be highly adaptable and capable of working in a fast paced, stressful environment.\n\nTheir main responsibilities will include;\n\n\u2022 Choosing and co-ordinating outfits for mannequins & models in photo shoots\n\n\u2022 Choosing props and accessories and preparing them for shoots\n\n\u2022 Keeping up to date with current and changing trends in fashion and design\n\n\u2022 Advising clients on fashion styling for visuals\n\n\u2022 Selecting the most appropriate pieces from collections and ranges for the shoot\n\n\u2022 Purchasing props for shoots\n\n\u2022 Supervising photo shoots\n\n\u2022 Steaming garmentsMUST have previous experience in fashion styling & MUST be flexible!", "employment_types": ["Full Time"], "selling_points": [], "locations": ["Wong Tai Sin Area"], "categories": ["E-commerce", "Others"], "post_time": "2022-01-11T10:56:31Z", "salary": {"currency": null, "max": null, "min": null, "period": "monthly", "term": null}, "salary_visible": false, "title_keywords": ["photographer", "assistant", "junior"], "responsibilities": ["supervising", "design"], "requirements": {"degrees": [], "majors": [], "languages": [], "language_level": [], "hard_skills": [], "soft_skills": ["flexible", "capable", "adaptable", "keen", "creative"], "languages_combined": []}, "experience_required": {"duration": [], "field": []}}, {"job_id": "100003009027597", "location_code": "hk", "company": "Casetagram Limited", "job_title": "eCommerce Marketplace Executive (Amazon)", "description": "Your role\n\nExplore new partnership opportunity in Hong Kong and Worldwide for online community project\nMaintain good relationship with strategic merchant partners\nAssist in implementing strategic marketing plan and work closely with internal departments to ensure smooth operation process\nEnsure overall online product presentation, including photography, copy content is cohesive with the overall merchandising strategy\nManagement of return logistics and other merchandising topics with merchant partners\nConduct market research, competitor analysis and trends; Analyze sales performance through sell-through analysis and proposed action plan\u00a0\n\nTo succeed in this role\n\nDegree holder with minimum of 4 year experience in e-commerce and merchandising field\nAbility to handle autonomously projects and deal with sourcing, cost analysis, purchasing, production control and logistics\nGood in price negotiation and trading terms negotiation\u00a0\nHands-on experience in managing SKUs an Categories through various online channels\nGood command of English, Mandarin and Cantonese and excellent skills in communication, presentation and negotiation\n\n\u00a0HKT is an equal opportunity employer and welcomes applications from all qualified candidates. Information provided will be treated in strict confidence and will only be used for recruitment-related purposes.\nPersonal data provided by job applicants will be used strictly in accordance with the employer's privacy statement (www.hkt.com/privacy-statement), a copy of which will be provided immediately upon request.", "employment_types": ["Full Time", "Permanent"], "selling_points": ["eCommerce and Amazon experience is a must", "Good presentation & communication", "Familiar with eCommerce platforms and functions"], "locations": ["Kwun Tong"], "categories": ["Sales, CS & Business Devpt", "Business Development", "E-commerce", "Product Management / Business Analyst", "Others"], "post_time": "2022-01-06T10:33:39Z", "salary": {"currency": null, "max": null, "min": null, "period": "monthly", "term": null}, "salary_visible": false, "title_keywords": ["executive"], "responsibilities": ["management", "control", "price negotiation", "online channels", "terms negotiation", "sales performance", "conduct market research", "analysis", "merchandising", "maintain good relationship", "communication", "marketing plan", "logistics", "recruitment", "plan", "personal data", "cost analysis"], "requirements": {"degrees": ["degree holder"], "majors": ["e-commerce"], "languages": ["cantonese", "english", "mandarin"], "language_level": ["excellent", "good command"], "hard_skills": ["analysis", "e-commerce"], "soft_skills": ["confidence", "negotiation", "cohesive", "communication", "hands-on", "smooth", "presentation"], "languages_combined": [{"language": "cantonese", "language_level": ["good command"]}, {"language": "english", "language_level": ["excellent", "good command"]}, {"language": "mandarin", "language_level": ["excellent", "good command"]}]}, "experience_required": {"duration": ["minimum of 4 year"], "field": ["merchandising", "e-commerce"]}}, {"job_id": "100003008585140", "location_code": "hk", "company": "EAT FRESH ORGANIC E-GREENGROCERY", "job_title": "E-Commerce Operations Logistics", "description": "Hey! We\u2019re CASETiFY,\u00a0a start-up based in Hong Kong and Los Angeles known for our customizable tech accessories that champion self-expression. Our mission is to help people express their personal style through our fun, creative and innovative products. Since our launch in 2011, we started with a simple idea- to turn Instagram photos into custom phone cases. Now nine years later, we're the world's #1 choice for custom tech accessories.\n\nJob Description\nDefine and implement marketplace (Amazon) sales strategy and content optimization\nManage the daily operations of the e-commerce platform (Amazon) functions\nManage e-commerce quality control and quality assurance\nWork closely with various internal and external parties, including agency, marketing, graphic designers, system development team, fulfilment, 3PL etc\nAnalyze the online sales performance and roll out effective advertising campaigns on Amazon and promotion to reach sales targets\nPrepare sales, traffic, promotion reports and competitor analysis regularly\nHandle eCommerce logistic issue and communicate with production, fulfilment\u00a0and warehouse\nResponsible for manage overall logistics, customer service, stock planning and dashboard of activities\nQualifications:\n\nBachelor in e-commerce / Digital Marketing / Communication or related disciplines;\n2 years e-commerce working experience, Amazon experience is a must\nWilling to learn, detail-oriented with good analytical and reporting skills\nGood presentation, communication and influencing skills\nGood team player with strong sense of responsibility\nEnergetic, proactive, self-motivated, and able to work fast-paced working environment\nGood command in English and Chinese\nWe offer an attractive salary + benefits package including occasional outing with teams. Ready to join the team? Email your\u00a0resume and expected salary to us!\nAny personal data provided will be used for recruitment related purposes only and will be treated in strict confidence.", "employment_types": ["Permanent", "Contract"], "selling_points": [], "locations": ["Tuen Mun Area"], "categories": ["Transportation & Logistics", "Others", "E-commerce", "Others"], "post_time": "2022-01-04T02:46:00Z", "salary": {"currency": null, "max": null, "min": null, "period": "hourly", "term": null}, "salary_visible": false, "title_keywords": ["operations", "logistics"], "responsibilities": ["communicate with", "reporting", "sales performance", "analysis", "internal and external parties", "quality", "prepare sales", "communication", "daily operations", "customer service", "reports", "logistics", "quality control", "digital marketing", "stock planning", "e-commerce platform", "advertising campaigns"], "requirements": {"degrees": ["bachelor"], "majors": ["related disciplines", "digital marketing", "e-commerce"], "languages": ["english", "chinese"], "language_level": ["good command"], "hard_skills": ["simple", "amazon", "fun", "e-commerce", "analysis"], "soft_skills": ["good team player", "proactive", "self-motivated", "responsible", "sense of responsibility", "willing to learn", "innovative", "communication", "detail-oriented", "energetic", "customer service", "creative", "presentation"], "languages_combined": [{"language": "english", "language_level": ["good command"]}, {"language": "chinese", "language_level": ["good command"]}]}, "experience_required": {"duration": ["2 years"], "field": ["e-commerce"]}}, {"job_id": "100003009028462", "location_code": "hk", "company": "Sa Sa Dot Com Limited", "job_title": "Senior Customer Service Officer (eCommerce / 5-Day Work)", "description": "Responsibilities:\n\nInterpret data, analyze results using statistical techniques and provide ongoing reports\nProvide advanced analysis and knowledge-based reports to help track customer behavior and campaign performance\nMonitor, analyze and interpret data from internal data source and analytic tools\nConduct analysis including sales performance, traffic flows, customer segmentation, customer journey analysis, and marketing effectiveness/strategy\nExplore opportunities from digital marketing channels Provide marketing insights which is useful to maximize conversion rate\n\nRequirements:\n\nHigh School Diploma or above in Business Administration, Information Technology, Computer Science, Statistics or any related\n2 years of experience in data analysis and/or CRM\nUnderstand e-commerce data in order to conduct evaluations of patterns and trends and provide operational reporting, forecasting, and marketing action plans\nExcellent written and verbal communication skills\nExceptional interpersonal skills\nStrong Adobe Analytics, Google Analytics and spreadsheet skills\nHands-on experience in Adobe Analytics is an advantage\nProven experience in e-commerce is a plus\nWorking Location: Tseung Kwan O Industrial Estate\n\nInterested parties please click \u201cApply Now\" to submit your complete resume with\u00a0compensation history, expected salary and REFERENCE NUMBER or by\u00a0post to\u00a0Human Resources Department,\u00a03/F,\u00a0Sing Tao News Corporation Building, 7 Chun Cheong Street, Tseung Kwan O Industrial Estate, Tseung Kwan O, New Territories, Hong Kong\n\nWe are an equal opportunity employer and welcome applications from all qualified candidates. Information provided will be treated in strict confidence and only be used for recruitment related purpose. Applicant who is not invited for an interview within 6 weeks may consider their application not successful. All personal data of unsuccessful applicants will be destroyed within 6 months.\n\nwww.singtaonewscorp.com\n\n\n", "employment_types": ["Full Time"], "selling_points": ["Assist Mgr in leading & managing CS team", "2 years supervisory CS experience in eCom field", "Work on Sat, Sun & Public Holiday"], "locations": ["Siu Sai Wan"], "categories": ["Sales, CS & Business Devpt", "Customer Service - Supervisor / Officer", "Beauty Care / Health", "Others", "E-commerce", "Others"], "post_time": "2022-01-07T02:21:46Z", "salary": {"currency": null, "max": null, "min": null, "period": null, "term": null}, "salary_visible": false, "title_keywords": ["senior customer service officer"], "responsibilities": ["data", "sales performance", "analysis", "monitor", "reports", "digital marketing"], "requirements": {"degrees": ["high school diploma"], "majors": ["statistics", "business administration", "computer science", "information technology"], "languages": [], "language_level": [], "hard_skills": ["google analytics", "plus", "e-commerce", "analysis", "adobe", "spreadsheet"], "soft_skills": ["communication skills", "hands-on", "interpersonal skills"], "languages_combined": []}, "experience_required": {"duration": ["2 years"], "field": ["data analysis", "e-commerce"]}}, {"job_id": "100003009030000", "location_code": "hk", "company": "Sing Tao Management Services Limited", "job_title": "Data Analyst (New Media Business)", "description": "THE ROLE\n\nReporting to the Assistant Studio Manager, you will prepare the outfit rails each day ready for the shoot and ensure they achieve their daily targets. Using your fashion and brand knowledge, you will develop the Farfetch visual aesthetic and image quality.\n\nWHAT YOU'LL DO\nYou'll style and shoot inspiring on brand, on trend looks daily\nYou'll work with photographer on set to direct model and select best poses/imagery\nYou'll work with the Studio coordinator to try and find ways to improve the process and make it more efficient whilst ensuring the quality is maintained\nYou'll ensure all 'crucial' new brands are researched before being shot\nWHO YOU ARE\n2 +years of experience as a Stylist, either in-house or as a freelancer\nExtensive knowledge of styling luxury brands\nAbility to maintain a calm and composed temperament in a frenetic environment, and ensure issues are deflected from the studio\nFlexible 'can-do', up-beat attitude\nRunway, trend and brand knowledge\nUnderstanding of needs from both a creative and production perspective\nEQUAL OPPORTUNITIES STATEMENT\nFARFETCH is an equal opportunities employer ensuring that all applicants are treated equally and fairly throughout our recruitment process. We are determined that no applicant experiences discrimination on the basis of sex, race, ethnicity, religion or belief, disability, age, gender identity, ancestry, sexual orientation, veteran status, marriage and civil partnership, pregnancy and maternity, or any other basis prohibited by applicable law. We continue to build our consciously inclusive culture as part of our Positively FARFETCH strategy throughout our business, partnerships and communities.", "employment_types": ["Full Time", "Permanent"], "selling_points": [], "locations": ["Tseung Kwan O"], "categories": ["Information Technology (IT)", "Network & System", "E-commerce", "Others", "Data Scientist"], "post_time": "2022-01-07T06:35:09Z", "salary": {"currency": null, "max": null, "min": null, "period": "monthly", "term": null}, "salary_visible": false, "title_keywords": ["data analyst"], "responsibilities": ["reporting", "quality", "develop", "maintain", "visual", "recruitment process"], "requirements": {"degrees": [], "majors": [], "languages": [], "language_level": [], "hard_skills": ["make", "no"], "soft_skills": ["efficient", "flexible", "determined", "calm", "inspiring", "can-do", "creative", "extensive"], "languages_combined": []}, "experience_required": {"duration": ["2 +years"], "field": []}}, {"job_id": "100003009026208", "location_code": "hk", "company": "Farfetch HK Production Limited", "job_title": "Fashion Stylist (Full Time/Freelance)", "description": "Job Description:\n\n- Answer customer enquiries via emails and phone calls in a professional manner\n- Provide after sales service such as delivery status follow up, product warranty service, etc.\u00a0\n- Process administrative works on daily orders processing\n- Take on\u00a0ad-hoc duties as assigned by supervisor\n\nJob Requirements:\n-\u00a0One-year of working experience, fresh graduates are also welcomed\n-\u00a0Familiar with e-Commence operations is an advantage\n- Strong\u00a0communications\u00a0and problem solving skills\n- Excellent writings in both English and Chinese\n-\u00a0Confident and able to work independently,\u00a0detailed-mind, well-organized and responsible\n- Willingness to learn quickly and grow within the position\n- Proficiency in Microsoft Office\n\nBenefits:\n- Discretionary Bonus\n- 5 day work week\n- Bank Holidays\n- 10 days annual leave", "employment_types": ["Full Time", "Permanent"], "selling_points": ["High Volume In-House Product Shooting- Model&Still", "Collaboration & Exchange w/ International Studios", "Vibrant, Energetic Start-Up Team Environment"], "locations": ["Ngau Tau Kok"], "categories": ["Media & Advertising", "Production", "Design", "Fashion", "E-commerce", "Others"], "post_time": "2022-01-07T13:41:53Z", "salary": {"currency": null, "max": null, "min": null, "period": "monthly", "term": null}, "salary_visible": false, "title_keywords": [], "responsibilities": ["customer enquiries", "professional manner", "daily orders", "ad-hoc duties", "phone calls"], "requirements": {"degrees": [], "majors": [], "languages": ["english", "chinese"], "language_level": ["excellent"], "hard_skills": ["problem solving skills", "microsoft office"], "soft_skills": ["confident", "work independently", "responsible", "well-organized", "problem solving skills", "detailed"], "languages_combined": [{"language": "english", "language_level": ["excellent"]}, {"language": "chinese", "language_level": ["excellent"]}]}, "experience_required": {"duration": [], "field": []}}, {"job_id": "100003009025671", "location_code": "hk", "company": "Link Profit International Development Limited", "job_title": "Customer Service and Administrative Executive", "description": "Responsibilities\n\nl\u00a0\u00a0 Support online platform interface update and manage daily operations of cross brand owe e-stores, including but not limited to content management, product listing, pricing, promotion and inventory update, handling order fulfilment and providing\n\nl\u00a0\u00a0 Maintain and update product description, product placement and other logistic arrangement in 3rd party platform such as HKTV Mall\n\nl\u00a0\u00a0 Liaise with warehouse and 3rd party partner to ensure the delivery standard is met\n\nl\u00a0\u00a0 Monitor and control marketing campaign timelines\n\nl\u00a0\u00a0 Conduct market & competitor research to understand customer needs and marketing trends for enhancing customer shopping experience\n\nl\u00a0\u00a0 Assist in preparing business analysis report on sales and promotion performance of cross brand eCommerce marketplace\n\nl\u00a0\u00a0 Assist any other ad-hoc projects as assigned", "employment_types": ["Full Time"], "selling_points": [], "locations": ["Kwai Hing"], "categories": ["Admin & HR", "Clerical / Admin Staff", "Sales, CS & Business Devpt", "Customer Service - Supervisor / Officer", "E-commerce", "Others"], "post_time": "2022-01-06T06:19:38Z", "salary": {"currency": null, "max": null, "min": null, "period": "monthly", "term": null}, "salary_visible": false, "title_keywords": ["administrative executive", "customer service"], "responsibilities": ["understand customer needs", "management", "control", "business analysis", "product listing", "3rd party platform", "inventory", "monitor", "logistic arrangement", "maintain", "liaise with", "ad-hoc projects", "manage daily operations", "report"], "requirements": {"degrees": [], "majors": [], "languages": [], "language_level": [], "hard_skills": ["analysis"], "soft_skills": [], "languages_combined": []}, "experience_required": {"duration": [], "field": ["research", "marketing"]}}, {"job_id": "100003009023402", "location_code": "hk", "company": "Take Action Limited", "job_title": "E-Commerce / Digital Marketing Assistant", "description": "We are seeking a talented Multimedia Designer to join our design team. As a Multimedia Designer, you will be working closely with our Marketing Team to design and produce high-end visual, textual, and animated content for our website.\n\nTo ensure success, you should have a background in digital design, excellent communication skills, and the ability to collaborate on projects.\n\nMain Responsibilities:\n\nTo\u00a0align\u00a0the multimedia and graphic design with the brand image\nIntroduce creative ideas to multiple categories including artwork in various social media platforms, EDM, printed promotional materials, and videos\nAble to maintain Crudo Leather Brand image under corporate guidelines but also put into new visual graphic trends\nDesign both offline and online marketing content and graphics\nMarket research, concept development, artwork, and the graphic making of projects\nResponsible for photo retouching, banner design, video editing\nWork closely with the marketing team to support events and new product launches\nPerform ad-hoc projects as assigned\n\nRequirements:\u00a0\n\nDegree in multimedia design / graphic design or other relative disciplines\nGood verbal and written communications in English and Mandarin\nAdvanced users of Photoshop, illustrator, and video editing tools\n5 years or above in graphic design\nStrong sense in\u00a0aesthetics\u00a0design\n\nInterested parties please email\u00a0portfolio,\u00a0full resume including covering letter, and expected salary to us.\u00a0 Shortlisted candidates will be contacted via phone for the interview.\n\nPersonal data will be used for recruitment purposes only.\u00a0", "employment_types": ["Full Time"], "selling_points": ["5.5-day work week (Sat. half day & off on weekday)", "Staff shopping discount", "10 Days Annual Leave"], "locations": ["Yuen Long"], "categories": ["E-commerce", "Others"], "post_time": "2022-01-05T08:34:13Z", "salary": {"currency": null, "max": null, "min": null, "period": "monthly", "term": null}, "salary_visible": false, "title_keywords": ["digital marketing", "assistant"], "responsibilities": ["graphics", "creative ideas", "photo retouching", "edm", "guidelines", "graphic design", "social media platforms", "market research", "design", "video editing", "promotional materials", "maintain", "visual", "ad-hoc projects"], "requirements": {"degrees": ["degree"], "majors": ["multimedia design", "graphic design"], "languages": ["english", "mandarin"], "language_level": ["good"], "hard_skills": ["video editing", "illustrator", "multimedia", "photoshop"], "soft_skills": ["advanced"], "languages_combined": [{"language": "english", "language_level": ["good"]}, {"language": "mandarin", "language_level": ["good"]}]}, "experience_required": {"duration": [], "field": []}}, {"job_id": "100003009021079", "location_code": "hk", "company": "Crudo International Limited", "job_title": "Art Director", "description": "Highlight of Benefits\uff1a\n\n12 Days annual leave\nPleasant Working Environment\nPerformance Bonus\nGreat Career Exposure\nComprehensive medical Coverage\n\n\u00a0\u00a0Who is our Right Fit\uff1a\n\nTertiary education, major in Accounting, with experience in e-commerce platforms/Freight forwarding industry will be advantage\nSelf-Motivated, energetic, well-organized and able to work under pressure\n3 \u2013 5 years full set of books experience\nProficiency in Excel (e.g. Pivot & Vlookup) and Word processing\nGood command of written and spoken Chinese and English\n\n\u00a0What you will be doing\uff1a\n\nMaintain and administrate the financial accounts in such a way that provide accurate, complete, and timely information to the management\nHandle daily accounting works, including payment checking, accounts receivable and payable, etc.\nPerform clerical support on data entry, vouchers and filing\nPerform or assist in any ad-hoc assignments as required\n\nRemarks:\n\nWe are an equal opportunity employer and we offer the rewarding package plus fringe benefit to the right team player. For interested candidates, please email your full resume with current and expected salary by email to HR\u00a0Dept.", "employment_types": ["Full Time"], "selling_points": ["Graphic design", "Digital marketing", "Fast growing jewellrey brand"], "locations": ["Kwun Tong"], "categories": ["Design", "Graphics", "Multi-media", "E-commerce", "Others"], "post_time": "2022-01-10T16:52:40Z", "salary": {"currency": null, "max": null, "min": null, "period": "monthly", "term": null}, "salary_visible": false, "title_keywords": ["art director"], "responsibilities": [], "requirements": {"degrees": [], "majors": [], "languages": [], "language_level": [], "hard_skills": [], "soft_skills": [], "languages_combined": []}, "experience_required": {"duration": [], "field": []}}, {"job_id": "100003009016007", "location_code": "hk", "company": "eGateway Global Limited", "job_title": "E-commerce Officer (Entry Level)", "description": "Coordinating new product & existing\nManage the operations of online platforms to meet or exceed launch goal\nDesigning and implementing process to effectively launch products onto HKTVmall\nRequirement\n\nFresh Grad are welcomed\nIndependent, self-motivated\nInterested in e-commerce industry\nGood command of written English and Chinese\nBasic Photoshop skills\nBenefits\n\nAttractive Remuneration Package\nBank Holiday\nMedical Allowance", "employment_types": ["Full Time"], "selling_points": ["E-commerce", "5-day work week", "Household product"], "locations": ["Lai Chi Kok"], "categories": ["E-commerce", "Others"], "post_time": "2022-01-03T08:05:46Z", "salary": {"currency": null, "max": null, "min": null, "period": "monthly", "term": null}, "salary_visible": false, "title_keywords": ["officer"], "responsibilities": ["operations", "designing"], "requirements": {"degrees": [], "majors": [], "languages": ["english", "chinese"], "language_level": ["good command"], "hard_skills": ["goal", "basic", "photoshop", "e-commerce"], "soft_skills": ["self-motivated", "interested in", "independent"], "languages_combined": [{"language": "english", "language_level": ["good command"]}, {"language": "chinese", "language_level": ["good command"]}]}, "experience_required": {"duration": [], "field": []}}, {"job_id": "100003009032052", "location_code": "hk", "company": "Khan Industries Limited", "job_title": "Web & Graphic Designer", "description": "Job Duties\n\nResponsible for new development & maintenance to the websites and eCommerce sites\nCreate graphic design for corporate websites, social media and any online advertising materials\nApply best practices to increase page speed & ratings, and SEO ranking\nProvide documentation and administrative support as assigned\n\nRequirements\n\nAt least 1 year experience in related field\nDiploma or above in design or related disciplines\nKnowledge in HTML and CSS\nProficient in Adobe Photoshop, Illustrator, SEO and Wordpress\nGood art sense, detail-oriented, good communication skills\nGood command of Chinese & English\nPortfolio attachment is a MUST\n\nWe will offer\n\n5 days work\n12 days annual leave\nWedding leave\nOvertime pay\nSmall team, Friendly work environment\nInterested parties, please send your resume stating expected salary, portfolio and click \"Apply Now' to submit your application.\n\nAll personal data provided by job applicants will be used for recruitment purpose only. Applicants who are not invited for interview within six weeks might consider their applications unsuccessful.", "employment_types": ["Full Time", "Permanent"], "selling_points": ["HKD16,000 - 18,000 /month", "5 days work, Overtime Pay", "Small team, Friendly work environment"], "locations": ["Ngau Tau Kok"], "categories": ["Design", "Graphics", "Web Designer", "E-commerce", "Others"], "post_time": "2022-01-07T10:09:33Z", "salary": {"currency": null, "max": null, "min": null, "period": "monthly", "term": null}, "salary_visible": false, "title_keywords": ["graphic designer"], "responsibilities": ["social media", "seo", "maintenance", "administrative support", "graphic design", "documentation", "online advertising"], "requirements": {"degrees": ["diploma or above"], "majors": ["related disciplines", "design"], "languages": ["english", "chinese"], "language_level": ["good command"], "hard_skills": ["small", "seo", "adobe photoshop", "illustrator", "html", "wordpress", "css"], "soft_skills": ["communication skills", "friendly", "detail-oriented"], "languages_combined": [{"language": "english", "language_level": ["good command"]}, {"language": "chinese", "language_level": ["good command"]}]}, "experience_required": {"duration": ["at least 1 year"], "field": ["related"]}}, {"job_id": "100003009022927", "location_code": "hk", "company": "eCargo Enterprise Limited", "job_title": "E-commerce Operations Executive", "description": "Responsibilities:\n\n\nManage and handle wine merchant on-boarding formalities. Facilitate wine product selection for online sales\nManage and handle cross-border logistics flow & operations, online product listing, stock management in timely and accurate manner\nVendor management, as well as liaise and coordinate with internal stake-holder departments on day to day business operation\nResponsible for eCommerce operations including but not limited to product listing, contents preparation and promotion/event planning/executions\nResponsible for overall order flow management, including collecting wines and arranging cross-border delivery\nResponsible for performance reports and analysis to maximize ROI from various activities\nCollect market intelligence and analyze\nSupport sales and marketing when necessary\nPerform ad hoc assignments by management\n\nEducation and Experience required:\n\n\nDegree in eCommerce or relevant disciplines\nWith hands-on experience in eCommerce operation will be a plus\nWith wine knowledge will be a plus\nEffective and creative problem solving and decision-making skills\nExcellent organizational and analytical skills\nIndependent, sell motivated, detail-oriented; ability of multitasking in fast-tracking project\nCandidates with more experiences will be considered as Senior Executive role\nBenefits:\nDouble Pay\nFive-day work week\nBirthday Leave\nMedical Insurance\nFree Shuttle Bus\nAttractive remuneration package and excellent career development opportunities will be offered to the successful candidate. \u00a0For Interested parties, please apply with a detailed resume stating present and stating present and expected salary by clicking \"Apply Now\".\u00a0 \u00a0\u00a0You are welcome to visit our website at http://www.ecargo.com.\n\nPersonal data collected will be used for recruitment purposes only and be treated in strict confidence.\u00a0 Cargo Services treats all applicants for employment in the same way, regardless of age, sex, marriage and civil partnership, race, disability, religion or belief.", "employment_types": ["Full Time", "Permanent"], "selling_points": ["eCommerce Operations; Marketing", "Degree in eCommerce, w/ Wine knowledge is a plus", "5-day work; Double Pay, Excellent career exposure"], "locations": ["Kwai Tsing Area"], "categories": ["E-commerce", "Marketing - Brand / Product Management", "Product Management / Business Analyst", "Others"], "post_time": "2022-01-05T06:57:26Z", "salary": {"currency": null, "max": null, "min": null, "period": "monthly", "term": null}, "salary_visible": false, "title_keywords": ["operations executive"], "responsibilities": ["liaise", "management", "tracking", "stock management", "product listing", "performance reports", "operations", "analysis", "coordinate with", "logistics", "ad hoc assignments", "maximize roi", "contents", "day to day business operation", "planning"], "requirements": {"degrees": ["degree"], "majors": ["ecommerce"], "languages": [], "language_level": [], "hard_skills": ["plus", "analysis", "vendor", "analytical skills", "problem solving"], "soft_skills": ["independent", "creative", "responsible", "organizational", "timely", "analytical skills", "problem solving", "detail-oriented", "hands-on", "motivated", "accurate"], "languages_combined": []}, "experience_required": {"duration": [], "field": ["ecommerce", "operation", "education"]}}, {"job_id": "100003009017720", "location_code": "hk", "company": "Fila Marketing (Hong Kong) Limited", "job_title": "E-Commerce Executive", "description": "E-Commerce Operation Logistics\u00a0\n\nWORK ONSITE AND REMOTELY.\nLanguage:\u00a0Cantonese & English speaking\nContract Period:\u00a0long term\nLocation: Tuen Mun\nSalary\u00a0- in the market\nRequirement of\u00a0staff\u00a0(experience & qualification):\u00a0Operations: supervise packing team, communicate with logistics team; create reports, manage customers' orders' workflow and internal order procedure for logistic team; report to directors; simple admin; although preferred,\u00a0no previous qualification/experience required\nMUST pay attention to detail, be a fast learner, pro-active, good character, able to work well in a team as well as independently. Customer service: reply emails, Whatsapp, phone calls;\nThe ideal candidate will have English & Cantonese language skills, computer skills.\nWe welcome entry level as well as returning to work force people, we require committed and enthusiasitic individuals", "employment_types": ["Full Time", "Permanent"], "selling_points": ["2 years e-commerce working experience", "Bachelor Degree holder", "able to work fast-paced working environment"], "locations": ["Kowloon Bay"], "categories": ["E-commerce", "Business Development", "Product Management / Business Analyst", "Others"], "post_time": "2022-01-04T01:48:59Z", "salary": {"currency": null, "max": null, "min": null, "period": "monthly", "term": null}, "salary_visible": false, "title_keywords": ["executive"], "responsibilities": ["communicate with", "operations", "customer service", "logistics", "reports", "phone calls", "report"], "requirements": {"degrees": [], "majors": [], "languages": ["cantonese", "english"], "language_level": [], "hard_skills": ["simple", "no", "e-commerce", "whatsapp", "computer skills"], "soft_skills": ["independently", "committed", "customer service", "attention to detail", "pro-active", "fast learner", "ideal"], "languages_combined": [{"language": "cantonese", "language_level": []}, {"language": "english", "language_level": []}]}, "experience_required": {"duration": [], "field": ["logistics", "team"]}}, {"job_id": "100003009030715", "location_code": "hk", "company": "Hong Kong Trade Development Council", "job_title": "Senior Project Executive, Platform Development (Contract)", "description": "Responsibilities\u00a0\nAssist Manager in leading and managing a team of CSOs in delivering quality service to internal & external customers;\nIntroduce best practices to enhance customer experience and satisfaction, drive and track service quality on service-related initiatives;\nConduct field coaching and call quality assessments to ensure daily operations are in compliance with company & department standards;\nParticipate to review current processes and procedures, liaise and co-ordinate with cross-functional teams leader on continued improvement of fulfillment tasks;\nProvide second line phone and email supporting to the team, ensure to meet key performance indicator (KPI) targets as set by management;\nProvide premier service to difficult people, be tactful and assertive with professional sense in tackling customer requirements or complaints.\nRequirements\u00a0\nDegree holder or equivalent with 4 years experience in customer service and call centre environment;\n1-2 years experience in supervisory level of which in e-Commerce is highly preferred;\nKnowledge in developing of a call centre operations, workflow and procedure preferable;\nProficient in PC applications including MS Words, Excel and Chinese word processing, good writing and presentation skills is an advantage;\nGood command of spoken and written Chinese and English, proficient in Mandarin speaking is a must;\nCustomer centric and attention to detail, precise and thorough; able to manage a range of tasks, people and projects;\nExcellent supervisory skills with problem-solving capability and result-oriented potential;\nTo work on shifts, weekends and public holiday.\n\nWe offer\n\n5 - day work week\nMedical Benefits\nAnnual Merit Bonus\nStaff Purchase Discounts\nStaff Recreation Activity\nShuttle Bus Service\nEducation Sponsorship\n\nInterested parties please send a full resume with current and expected salary by clicking APPLY NOW:\n\nHuman Resources Department\nSa Sa Cosmetic Co Ltd\n14/F, Block B, MP Industrial Centre\n18 Ka Yip Street\nChai Wan\nHong Kong\n\nPlease visit our corporate website at\u00a0http://corp.sasa.com/en/home\u00a0to know more about us.\n\n(Sa Sa is an Equal Opportunity Employer and all qualified applicants will receive consideration for employment. Personal data collected will be kept confidential and used for recruitment purpose only)", "employment_types": ["Full Time", "Contract"], "selling_points": ["Mobile Apps Development Support", "Product management & development", "Digital Management & E-commerce"], "locations": ["Wan Chai"], "categories": ["Information Technology (IT)", "Application Specialist - Software", "E-commerce", "Product Management / Business Analyst", "Others"], "post_time": "2022-01-07T08:09:43Z", "salary": {"currency": null, "max": null, "min": null, "period": "monthly", "term": null}, "salary_visible": false, "title_keywords": ["senior project executive"], "responsibilities": ["liaise", "management", "co-ordinate with", "fulfillment", "review", "compliance", "quality", "procedures", "daily operations", "managing a team", "cross-functional teams"], "requirements": {"degrees": ["degree holder"], "majors": [], "languages": ["english", "chinese", "mandarin"], "language_level": ["good", "good command", "proficient", "advantage"], "hard_skills": ["excel", "chinese word processing", "ms words", "e-commerce", "problem-solving", "pc applications"], "soft_skills": ["problem-solving", "presentation skills", "customer service", "thorough", "attention to detail", "precise", "result-oriented"], "languages_combined": [{"language": "english", "language_level": ["good", "good command"]}, {"language": "chinese", "language_level": ["proficient", "good", "good", "good command", "advantage"]}, {"language": "mandarin", "language_level": ["good", "good command"]}]}, "experience_required": {"duration": ["4 years", "1-2 years"], "field": ["supervisory level", "customer service", "e-commerce"]}}, {"job_id": "100003009020428", "location_code": "hk", "company": "Earthy Kiss", "job_title": "Assistant Operation Officer", "description": "Ref. No.: 318/PJE-PD/DGB/HKTDC\n\nResponsibilities:\n\n\nAssist Project manager in collecting & preparing user requirements specifications and preparing functional specifications for business systems development\nLiaise with vendors, users and internal/cross-functional teams on all product-related issues\nFacilitate and conduct acceptance test (UAT), log defects and follow up on bug/defect fixing\nSupport the full product development lifecycle, system rollout and deployment, and work closely with the technical team to configure and optimize the customer experience\nAnalyze and research on market B2B & B2C products and assist in providing valuable insights to facilitate management decision making\nMonitor the progress of project deliverables\nUpdate documentation such as but not limited to operational workflows and meeting notes\nOther ad-hoc project assignments\n\nRequirements:\n\n\nUniversity degree, preferably in Computer Science, Digital Management, Information System or related disciplines\nWorking experience in product management, product development or project management is preferrable\nAble to work independently and under pressure when issues may escalate or timelines demand\nStrong problem-solving, research, analytical and presentation skills with well-organized, process oriented and positive approach\nGood team player with interpersonal and relationship building skills, able to collaborate with different stakeholders, both internal and external\nGood in written and spoken English and Chinese\nFresh graduates would be considered\n\nRemuneration and Benefits:\n\nThe successful candidate will be appointed on a fixed-term contract basis, renewable subject to operational needs. Salary will be commensurate with qualifications and experience.\u00a0\u00a0\n\nApplication Procedure:\n\nInterested candidates are invited to complete the application form on our website at http://www.hktdc.com/careers.html. Those who do not hear from us within EIGHT WEEKS after the closing date may assume their applications unsuccessful.\n\nAll information provided by applicants will be treated in strict confidence and used only for recruitment purposes. Applicants may be considered for other suitable positions within the Council. Their personal data will be destroyed six months after the selection is finalised.\n", "employment_types": ["Part Time"], "selling_points": ["On the job training, Caring environment", "Fast-growing start-up business", "Friendly work environment, close to metro station"], "locations": ["Chai Wan"], "categories": ["Admin & HR", "Clerical / Admin Staff", "Personal / Executive Assistant", "E-commerce", "Others"], "post_time": "2022-01-04T16:20:23Z", "salary": {"currency": null, "max": null, "min": null, "period": "monthly", "term": null}, "salary_visible": false, "title_keywords": ["operation officer", "assistant"], "responsibilities": ["ad-hoc", "management", "documentation", "uat", "project deliverables", "systems", "monitor", "specifications", "liaise with", "cross-functional teams"], "requirements": {"degrees": ["university degree"], "majors": ["related disciplines", "computer science"], "languages": ["english", "chinese"], "language_level": ["good"], "hard_skills": ["project management", "problem-solving", "information system"], "soft_skills": ["work independently", "good team player", "under pressure", "problem-solving", "well-organized", "project management", "presentation skills", "interpersonal", "positive"], "languages_combined": [{"language": "english", "language_level": ["good"]}, {"language": "chinese", "language_level": ["good"]}]}, "experience_required": {"duration": [], "field": ["product management", "project management", "product development"]}}, {"job_id": "100003009020392", "location_code": "hk", "company": "Watson's Wine", "job_title": "eCommerce Officer (Customer Service)", "description": "Requirements:\n- Higher Diploma or above\n- Independent, detail-minded and self-motivated\n- Optimistic, good communication and interpersonal skills\n- Proficient in both spoken and written English and Chinese\n- Attention to details, mature and able to work under pressure and tight deadlines\n- Proficient computer application skills (Microsoft applications, Chinese word processing) and understand iOS system (we provide Mac book)\n- Knowledge of Adobe Creative is an advantage\n\nJob description:\n- Assist to support daily online shop operation, including inventory management\n- Assist to manage office administration work\n- To work closely with direct managers\n- Assist to handle queries from customers\n\nWe offer:\n- 3 days' work\u00a0\n- Fun, young and joyful work environment\n- Performance bonus\n- An opportunity to convert into full-time contract if your performance is satisfactory.\n\n\n(Negotiable salary)\n\n(Able to work from January/ February is highly preferred)\n\nInterested candidates, please email full resume with 1.) EXPECTED DAILY WAGE\n2.) AVAILABILITY 3.)\u00a0WORK REFERENCE\u00a0 to us by clicking 'Apply Now'.\n\nFor company information, please refer to the website https://www.earthykiss.com\n\nAll information received will be kept in strict confidence and only for employment-related purposes.", "employment_types": ["Full Time", "Permanent"], "selling_points": [], "locations": ["Shatin Area"], "categories": ["Sales, CS & Business Devpt", "Customer Service - Supervisor / Officer", "Others", "E-commerce", "Others"], "post_time": "2022-01-05T05:53:54Z", "salary": {"currency": null, "max": null, "min": null, "period": null, "term": null}, "salary_visible": false, "title_keywords": ["customer service", "ecommerce officer"], "responsibilities": [], "requirements": {"degrees": ["higher diploma or above"], "majors": [], "languages": ["english", "chinese"], "language_level": ["proficient"], "hard_skills": [], "soft_skills": ["detail-minded", "self-motivated", "independent", "mature", "communication and interpersonal skills", "attention to details", "work under pressure"], "languages_combined": [{"language": "english", "language_level": ["proficient"]}, {"language": "chinese", "language_level": ["proficient"]}]}, "experience_required": {"duration": [], "field": []}}, {"job_id": "100003009018827", "location_code": "hk", "company": "Profit Link Holdings Limited", "job_title": "\u63a1\u8cfc/\u8ddf\u55ae\u6587\u54e1\uff08\u7db2\u8cfc\uff09", "description": "You can enjoy:\u00a0\n\nComprehensive Medical and Life Insurance coverage, including your spouse and children\nExclusive company pension schemes\nMarriage, Maternity and Paternity Leave\nExclusive shopping discount, Bazaar Sales for our people only\nProfessional training and career advancement opportunities\nConvenient office location, less than 5 min. walk from MTR\nContemporary workplace with Onsite Clinic, Lactation Rooms, free drinks and chill out areas\nWell-equipped Gym inside our office building, plus fitness and interest class packages\nFree round-trip lunchtime shuttle bus services to Shatin\n\nResponsibilities:\n\nAssist in operating and developing the eCommerce & digital front-end platform (including eCommerce Store, desktop & mobile website, mobile apps etc)\nHandle customers\u2019 enquiries & complaints regarding the eStore on pre-sales & post sales issues through email and phone in a professional manner\nFollow up after sales service issues include but not limited to delivery, order cancellation, return order and refund arrangement\nWork with eCommerce and Distribution teams to ensure timely and quality delivery service\nResponsible for ad hoc assignment if required\n\nRequirements:\n\nUniversity graduate\nMinimum 2 years\u2019 working experience in related to customer servicing, with eStore experience is an advantage\nStrong customer service mind and result-oriented towards customer service delivery\nGood command of both written and spoken Chinese/Mandarin and English\nSelf-driven in problem solving and proactive team player\n\nAn attractive salary and benefit package will be offered. Interested parties please forward detailed resume stating expected salary to: People Department, A.S Watson Retail (HK) Ltd, Watson House, 1-5 Wo Liu Hang Road, Fo Tan, N.T. or email to us or click \u201cApply Now\u201d.\n\nWe are an equal opportunity employer and welcome applications from all qualified candidates. The information provided will be treated in strict confidence and be used only for consideration of your application for relevant / similar posts within the A.S. Watson Group. All personal data of unsuccessful applicants will be destroyed within 12 months from the date of application.", "employment_types": ["Full Time"], "selling_points": [], "locations": ["Kwun Tong"], "categories": ["Admin & HR", "Clerical / Admin Staff", "Merchandising & Purchasing", "Others", "E-commerce", "Others"], "post_time": "2022-01-04T05:09:54Z", "salary": {"currency": null, "max": null, "min": null, "period": "monthly", "term": null}, "salary_visible": false, "title_keywords": [], "responsibilities": ["ad hoc assignment", "quality", "teams", "professional manner", "developing", "website"], "requirements": {"degrees": ["university graduate"], "majors": [], "languages": ["english", "chinese", "mandarin"], "language_level": ["good command"], "hard_skills": ["problem solving"], "soft_skills": ["result-oriented", "problem solving", "customer service", "team player", "proactive", "driven"], "languages_combined": [{"language": "english", "language_level": ["good command"]}, {"language": "chinese", "language_level": ["good command"]}, {"language": "mandarin", "language_level": ["good command"]}]}, "experience_required": {"duration": ["minimum 2 years"], "field": ["related"]}}, {"job_id": "100003009030761", "location_code": "hk", "company": "Yunfeng Financial Group Limited", "job_title": "Client Services Officer, Associate (CS-21-10-2)", "description": "\u8ca0\u8cac\u7db2\u8cfc\u5e73\u53f0\n\u8ddf\u9032\u5ba2\u6236\u8a02\u55ae\u00a0\n\u5b89\u6392\u53ca\u8ddf\u9032\u51fa\u8ca8\u4e8b\u5b9c\n\u5c0b\u627e\u53ca\u806f\u7d61\u4f9b\u61c9\u5546\n\u7cfb\u7d71\u8cc7\u6599\u8f38\u5165/\u66f4\u65b0\n\u4e2d\u4e94\u7a0b\u5ea6\uff0c3\u5e74\u7d93\u9a57\uff0c\u7db2\u8cfc\u7d93\u9a57\u512a\u5148\uff0c\u5177\u6709\u57fa\u672c\u96fb\u8166\u64cd\u4f5c\u77e5\u8b58\n\u9700\u5916\u51fa\u5de5\u4f5c\n\u516c\u53f8\u59d4\u6d3e\u4e4b\u5176\u4ed6\u5de5\u4f5c\n\u5de5\u4f5c\u5730\u9ede\u53ca\u6642\u9593\uff1a\u89c0\u5858\uff0c\u661f\u671f\u4e00\u81f3\u4e94\uff0c9:00am - 5:00pm", "employment_types": ["Full Time", "Permanent"], "selling_points": ["2+  years working experience", "Experience in KYC/AML areas", "SFC type 1 license holder"], "locations": ["Wan Chai"], "categories": ["Banking / Finance", "Financial Services", "Sales, CS & Business Devpt", "Customer Service - Supervisor / Officer", "E-commerce", "Others"], "post_time": "2022-01-07T08:16:49Z", "salary": {"currency": null, "max": null, "min": null, "period": "monthly", "term": null}, "salary_visible": false, "title_keywords": ["client services officer", "associate"], "responsibilities": [], "requirements": {"degrees": [], "majors": [], "languages": [], "language_level": [], "hard_skills": [], "soft_skills": [], "languages_combined": []}, "experience_required": {"duration": [], "field": []}}, {"job_id": "100003009030546", "location_code": "hk", "company": "Peoplus Recruitment", "job_title": "Sales & Customer Service Consultant (Ref: CC220107-01)", "description": "Responsibilities\n\nProvide full range of account services proactively to clients\nHandle account opening and client onboarding processes, including data collection, KYC and record keeping\nProvide and promote quality client solutions by working closely with all business lines\n\nRequirements\n\n2+ years working experience in related field such as relationship management, onboarding, client services etc\nExperience in KYC/AML areas within Finance industry is strongly preferred\nExcellent in client service mindset and interpersonal communication skill\nSFC type 1 license holder / pass of relevant papers is strongly preferred\nFluent in Mandarin and English is a must\nTitle would adjust based on the relevant experience\n\nWe provide a very competitive and open career path for our star performers. Interested candidates please kindly include the current and expected salary in the application. Information provided will be treated in strict confidence and will only be used for recruitment-related purposes. Only short-listed candidates will be notified.", "employment_types": ["Full Time", "Permanent"], "selling_points": ["Fashion KOL, E-commerce Fashion group", "Excellent working environment, Self-motivation", "Immediately available is highly preferred"], "locations": ["Not Specified"], "categories": ["Sales, CS & Business Devpt", "Customer Service - Supervisor / Officer", "Design", "Fashion", "E-commerce", "Others"], "post_time": "2022-01-07T19:21:16Z", "salary": {"currency": null, "max": null, "min": null, "period": "monthly", "term": null}, "salary_visible": false, "title_keywords": ["customer service", "consultant", "sales"], "responsibilities": ["account opening", "quality", "data collection", "kyc"], "requirements": {"degrees": [], "majors": [], "languages": ["english", "mandarin"], "language_level": ["fluent"], "hard_skills": ["aml", "kyc"], "soft_skills": ["communication skill", "interpersonal"], "languages_combined": [{"language": "english", "language_level": ["fluent"]}, {"language": "mandarin", "language_level": ["fluent"]}]}, "experience_required": {"duration": ["2+ years"], "field": ["related", "management", "relevant experience", "finance industry"]}}, {"job_id": "100003009026200", "location_code": "hk", "company": "Farfetch HK Production Limited", "job_title": "Part Time Fitting Assistant", "description": "Our client is\u00a0one of the leading online\u00a0Luxury Fashion Group, they are currently looking for\u00a0a high caliber to fill up above positions for their HK subsidiary company.\n\n\nSales & Customer Service Consultant\n\n\nResponsibilities\n\nBe the first point of contact, you will consistently deliver an exceptional customer experience\nAddress customer enquiries through a number of channels including phone, email, chat and social, working within brand guidelines\nConfidently sell through service in offering styling advice to meet customer needs and effective questioning through positive engagement\nAnswer a wide variety of customer enquiries including; product enquiries, styling advice, returns or repairs, pricing questions, order delivery timescales and conveying a solution focused message to the customer at all times\nLiaise with internal departments such as operational and commercial teams to expedite issues that are raised by the customer\n\nRequirements\n\nStrong ability to communicate effectively in English, Mandarin and Cantonese\nExperience in working in a customer care environment, preferably in the luxury retail sector\nExperience in ecommerce industry will be an advantage\nExcellent written and verbal communication skills; including attention to detail and use of excellent spelling and grammar as well as the ability to build relationships with customers\nAbility to speak and write in native level English\n\nAttractive remuneration package and excellent career prospects will be provided to the right candidate.\n\nInterested parties please send full resume with followings to jobs5@ peoplus.com.hk\n1. Current & Expected Salary\n2. Availability\n3. Date of Achievement : Academic Result\n4. Quoting the Emp. Ref. No. : CC220107-01\n\nAll personal data provided by job applicants will be used for recruitment purpose only", "employment_types": ["Full Time", "Permanent"], "selling_points": ["Leading online luxury fashion retail platform", "Collaboration & Exchange w/ International Studios", "Vibrant, Energetic Start-Up Team Environment"], "locations": ["Ngau Tau Kok"], "categories": ["Design", "Fashion", "E-commerce", "Others"], "post_time": "2022-01-07T13:42:22Z", "salary": {"currency": null, "max": null, "min": null, "period": "monthly", "term": null}, "salary_visible": false, "title_keywords": ["assistant"], "responsibilities": ["customer enquiries", "teams", "brand guidelines", "contact", "liaise with"], "requirements": {"degrees": [], "majors": [], "languages": ["cantonese", "english", "mandarin"], "language_level": ["native"], "hard_skills": [], "soft_skills": ["communication skills", "attention to detail"], "languages_combined": [{"language": "cantonese", "language_level": []}, {"language": "english", "language_level": ["native"]}, {"language": "mandarin", "language_level": []}]}, "experience_required": {"duration": [], "field": ["ecommerce", "luxury retail", "customer care"]}}, {"job_id": "100003009016249", "location_code": "hk", "company": "TDCX Hong Kong", "job_title": "Consumer Care Agent ~ Int'l Beauty Brand, 5-day work, Attractive Remuneration", "description": "THE ROLE\n\nReport to Assistant Studio Manager, you will work with stylists, photographers, and models in the studios to provide accurate and appropriate fit information to the customer. By providing the best fitting advice, customers will make online purchases easier and reducing the returns which are caused by the wrong fitting.\nWHAT YOU'LL DO\nYou'll provide accurate fit information to the customer through the Size and Fit copy.\nYou'll meet daily studio targets while maintaining a high-level of consistency.\nYou'll share any relevant brand, category or model fit advice necessary with the team leader so it can be shared with the team.\nYou'll work with stylists and photographers to keep a smooth workflow.\nYou'll ensure the correct size is being shot on the model while balancing the stylist's creative direction.\nYou'll attend global fitting team meetings and supporting global project, contribute to the team's growth and awareness through brand and competitor analysis.\nYou'll update the potential fitting phrases will increase the customer shopping experience\nYou'll provide weekly report to align the team quality and for training purpose\nYou'll work with the Model and support the model coating process.\nWHO YOU ARE\nHigher Diploma or above in Fashion Design or related discipline\nUnderstand Women and Menswear international sizing.\nA sound knowledge of Women and Menswear brands, trends, technical terms and fabric knowledge for both RTW and accessories.\nHave experience in a studio environment, in retail, customer service, garment technology, fashion design or similar areas would be advantage\nA proven ability to work quickly and efficiently with accuracy and attention to detail.\nYou must be dedicated, proactive, have a can-do attitude and happy being hands-on.\nExcellent sense of prioritization and timing\nEQUAL OPPORTUNITIES STATEMENT\nFARFETCH is an equal opportunities employer ensuring that all applicants are treated equally and fairly throughout our recruitment process. We are determined that no applicant experiences discrimination on the basis of sex, race, ethnicity, religion or belief, disability, age, gender identity, ancestry, sexual orientation, veteran status, marriage and civil partnership, pregnancy and maternity, or any other basis prohibited by applicable law. We continue to build our consciously inclusive culture as part of our Positively FARFETCH strategy throughout our business, partnerships and communities.", "employment_types": ["Full Time", "Permanent"], "selling_points": ["Mon-Fri 5-day work; Day Off on Sat, Sun & PH", "Support Multi-national Beauty Brands;", "Excellent in spoken & written Chinese & English"], "locations": ["Tin Hau"], "categories": ["Sales, CS & Business Devpt", "Call Centre", "Beauty Care / Health", "Others", "E-commerce", "Others"], "post_time": "2022-01-03T08:42:22Z", "salary": {"currency": "HKD", "max": 16999, "min": 14000, "period": "monthly", "term": null}, "salary_visible": true, "title_keywords": [], "responsibilities": ["maintaining", "analysis", "quality", "design", "customer service", "recruitment process", "report"], "requirements": {"degrees": ["higher diploma or above"], "majors": ["design"], "languages": [], "language_level": [], "hard_skills": ["no", "make", "analysis"], "soft_skills": ["proactive", "creative", "determined", "can-do attitude", "hands-on", "customer service", "attention to detail", "smooth", "accurate"], "languages_combined": []}, "experience_required": {"duration": [], "field": ["garment", "retail", "customer service", "fashion design"]}}, {"job_id": "100003009015093", "location_code": "hk", "company": "Homeless Limited", "job_title": "Customer Service Assistant / Officer", "description": "We are looking for\u00a0Consumer Care Agent\u00a0to join our growing family. Come home and start your #BeMore journey with TDCX today!\n\nTop reasons to work here:\n\nAttractive Remuneration.\nComprehensive Medical Care and Insurance Coverage.\nPremium & Instagrammable workspaces\nGet engaged and recognized with our Engagement & Recognition Program.\nGet coached and mentored by experts in your field.\nFun and flexible working arrangements.\nEasy to locate area with direct access to public transport.\nIncredible opportunities for you to develop your personal and professional skillsets.\n25 years of experience and more than 310+ industry awards\nOur culture believes in the power of teamwork, initiative, courage, innovation, and trust, for you to #BeMore at work.\n\nWhat is your mission?\n\nYou are also required to perform these job functions:\n\nSupport Multi-national Beauty Brands\nMonitor online community trends\nLoyalty program management, track record of managing loyalty programs and/or online communities\u00a0\nProvide online customer service and manage all communications with customers by responding to customer product and order inquiry; Co-ordinate with different department\n\nWho are we looking for?\n\nA data-sensitive observer\nExcellent command in spoken and written Cantonese and English\nExperiences in complex issues\nAttentive to details, multi-tasking with good organizational skills, able to work independently to meet a tight deadline\nImmediate available is highly preferred\nFamiliar with the beauty industry is a plus", "employment_types": ["Full Time"], "selling_points": ["Customer Service experience", "Fresh graduate will also be considered", "Proficiency in using Microsoft Office"], "locations": ["Southern Area"], "categories": ["Sales, CS & Business Devpt", "Customer Service - Supervisor / Officer", "Marketing / Public Relations", "Digital Marketing", "E-commerce", "Others"], "post_time": "2022-01-03T05:30:55Z", "salary": {"currency": null, "max": null, "min": null, "period": "monthly", "term": null}, "salary_visible": false, "title_keywords": ["officer", "customer service assistant"], "responsibilities": ["management", "communications with", "data", "co-ordinate with", "monitor", "develop", "online customer service", "insurance"], "requirements": {"degrees": [], "majors": [], "languages": ["cantonese", "english"], "language_level": ["excellent"], "hard_skills": ["plus", "fun"], "soft_skills": ["flexible", "organizational skills", "work independently", "attentive to details", "teamwork", "multi-tasking", "comprehensive", "customer service", "sensitive", "initiative"], "languages_combined": [{"language": "cantonese", "language_level": ["excellent"]}, {"language": "english", "language_level": ["excellent"]}]}, "experience_required": {"duration": ["25 years"], "field": []}}, {"job_id": "100003009026057", "location_code": "hk", "company": "Deliveroo Hong Kong Limited", "job_title": "Part-time Partner Service Agent (Central, Hourly Rate: $67)", "description": "Job Description\n\nHandles customer inquiries from different incoming channels in timely manner in effective communication e.g. phone, email, digital media etc;\nManages and resolves customer complaints and assist escalated complex cases;\nProvides immediate support to team members when they encounter difficulties in handling inquiries;\nPerforms ad hoc tasks as required by supervisor being a team player to back up other functions for service continuity;\nRequirements:\n\nAt least 1 years of customer service and/or digital retail and/or digital entertainment industry experience, Fresh graduate will also be considered;\nDetailed-minded, well-organized, independent, responsible, multi-tasking, ability to work under pressure and with tight deadlines;\nExcellent communication and interpersonal skills and ability to collaborate with different organizations and teams;\nProficiency in using Microsoft Office (Word, Excel, PowerPoint, Outlook) & Chinese typing;\nWork in Wong Chuk Hang;", "employment_types": ["Part Time"], "selling_points": ["Part-time agent to support our restaurant partners", "Admin duties with data entry and email handling", "University students are welcomed"], "locations": ["Central"], "categories": ["Admin & HR", "Clerical / Admin Staff", "Hospitality / F & B", "Food & Beverage", "E-commerce", "Others"], "post_time": "2022-01-06T07:10:37Z", "salary": {"currency": null, "max": null, "min": null, "period": "hourly", "term": null}, "salary_visible": false, "title_keywords": [], "responsibilities": ["communication", "ad hoc tasks", "customer inquiries", "customer complaints"], "requirements": {"degrees": ["fresh graduate"], "majors": [], "languages": ["chinese"], "language_level": ["proficiency"], "hard_skills": ["excel", "microsoft office", "word", "powerpoint", "typing", "outlook"], "soft_skills": ["independent", "responsible", "work under pressure", "well-organized", "multi-tasking", "customer service", "communication and interpersonal skills", "detailed"], "languages_combined": [{"language": "chinese", "language_level": ["proficiency"]}]}, "experience_required": {"duration": ["at least 1 years"], "field": ["digital", "customer service", "retail"]}}, {"job_id": "100003009026271", "location_code": "hk", "company": "Sagawa Express (H.K.) Company Limited", "job_title": "Sales Manager/Asst Sales Manager  - Express/Courier & Freight Forwarding (5 days work)", "description": "We are looking for someone to help our restaurant partners with their day-to-day inquiries as a part of our Partner Service team. You will be responsible to answer inquiries by our restaurant partners over the phone and through email. The job is predominantly admin-focused duties with a lot of data entry and email handling involved. This role is for any individual looking for hands-on experience in back-office operations for partner support.\n\nYour job duties will include:\n\nMaintain restaurant records by updating account information\nWork closely with the Partner Service Associates in ensuring service levels are met\nDeal with the creation and updating of our restaurant menus\nHandling restaurant inquiries through email\nProvide technical support to restaurant partner staff\nRequirements:\n\nExcellent written and spoken Cantonese and English\nAbility to work under pressure in a fast-paced environment\nAble to communicate across different teams and resolve any issues that might arise\nExperience with Salesforce would be beneficial\nUniversity students are welcomed\nAble to effectively communicate to a wide range of people via telephone or email", "employment_types": ["Full Time", "Permanent"], "selling_points": ["Sales in Express / Courier and Freight Forwarding", "Provide one stop solution to client and ecommerce", "2-5 yrs of exp in regional and global forwarding"], "locations": ["Lai Chi Kok"], "categories": ["Sales, CS & Business Devpt", "Others", "E-commerce", "Supply Chain", "Others"], "post_time": "2022-01-06T07:49:43Z", "salary": {"currency": null, "max": null, "min": null, "period": "monthly", "term": null}, "salary_visible": false, "title_keywords": ["sales manager"], "responsibilities": ["technical support", "maintain"], "requirements": {"degrees": [], "majors": [], "languages": ["cantonese", "english"], "language_level": ["excellent"], "hard_skills": ["salesforce"], "soft_skills": ["fast-paced environment", "work under pressure"], "languages_combined": [{"language": "cantonese", "language_level": ["excellent"]}, {"language": "english", "language_level": ["excellent"]}]}, "experience_required": {"duration": [], "field": []}}, {"job_id": "100003008988090", "location_code": "hk", "company": "Cafune Limited", "job_title": "E-COMMERCE EXECUTIVE", "description": "Responsibilities:\n\nDefine and implement online sales strategy and traffic optimization\nManage the daily operations of the e-commerce platform functions\nAnalyze the online sales performance and roll out effective digital marketing activities and promotion to reach sales target\nManage e-commerce quality control and quality assurance initiatives\nWork closely with various internal and external parties, including agency, marketing, graphic designers, system development team, 3PL etc\nCoordinate marketplace partnership and build relationship\nPrepare sales, traffic, promotion reports and competitor analysis regularly\nHandle eCommerce logistic issue and communicate with warehouse\nResponsible for manage overall logistics, customer service, stock and dashboard of activities\nAd hoc projects as required\u00a0\n\nRequirements:\n\nBachelor in e-Business/Digital Marketing / Communication or related disciplines;\n2 years e-commerce working experience\nHigh Adversity Quotient (AQ)\nGood fashion sense, detail-oriented with good analytical and reporting skills\nGood presentation, communication and influencing skills\nGood team player with strong sense of responsibility\nEnergetic, proactive, self-motivated, think out of the box and able to work fast-paced working environment\nGood command in English and Chinese", "employment_types": ["Full Time"], "selling_points": [], "locations": ["Kwai Hing"], "categories": ["Design", "Fashion", "E-commerce", "Others"], "post_time": "2022-01-04T03:43:15Z", "salary": {"currency": null, "max": null, "min": null, "period": "monthly", "term": null}, "salary_visible": false, "title_keywords": ["executive"], "responsibilities": ["communicate with", "sales performance", "sales target", "internal and external parties", "quality", "prepare sales", "analysis", "coordinate", "daily operations", "customer service", "digital marketing", "reports", "quality control", "logistics", "ad hoc projects", "e-commerce platform"], "requirements": {"degrees": ["bachelor"], "majors": ["related disciplines", "business", "digital marketing"], "languages": ["english", "chinese"], "language_level": ["good command"], "hard_skills": ["e-commerce"], "soft_skills": ["good team player", "proactive", "self-motivated", "sense of responsibility", "detail-oriented", "communication", "energetic", "presentation"], "languages_combined": [{"language": "english", "language_level": ["good command"]}, {"language": "chinese", "language_level": ["good command"]}]}, "experience_required": {"duration": ["2 years"], "field": ["e-commerce"]}}, {"job_id": "100003009019252", "location_code": "hk", "company": "Wall E-Commerce Limited", "job_title": "E-Commerce Sales Coordinator", "description": "We are looking for a highly motivated and organised individual to join our E-commerce team. This is an exciting opportunity for people passionate about fashion, and looking to grow their career within a dynamic brand. The candidate will be responsible to manage, develop and operate our sales channels.\n\nResponsibilities include but not limited to:\n\nResponsible for daily operations of our sales channels - logistics, customer service and inventory control\u00a0\nMonitor and optimise performance of sales channels via design updates, campaigns, content\u00a0\nCarry out market research on e-commerce trends, features, customer behaviour in order to optimise sales channels for conversions\u00a0\nAnalyse and report on channels performance; provide enhancement suggestions\u00a0\nWork closely with product team and marketing team on brand growth strategy\u00a0\n\nRequirements:\u00a0\n\n1+ years working experience \u00a0 \u00a0\nEnergetic and passionate about fashion\nAbility to work in a small team and work independently in a fast-paced environment\nExcellent organisational skills, detail oriented, analytical\u00a0\nStrong communicator; Fluent in Chinese and English\u00a0\nExperience in using Shopify or similar e-commerce providers is an advantage\nBachelor degree holder\u00a0", "employment_types": ["Full Time", "Permanent"], "selling_points": ["Handling & follow up sales & customers' enquiries", "Responding to order follow up & shipment status", "Manage company e-commerce websites"], "locations": ["Kowloon Bay"], "categories": ["E-commerce", "Marketing - Brand / Product Management", "Others"], "post_time": "2022-01-04T07:06:38Z", "salary": {"currency": null, "max": null, "min": null, "period": "monthly", "term": null}, "salary_visible": false, "title_keywords": ["sales coordinator"], "responsibilities": ["monitor", "market research", "design", "daily operations", "customer service", "logistics", "inventory control", "report", "analyse"], "requirements": {"degrees": ["bachelor degree holder"], "majors": [], "languages": ["english", "chinese"], "language_level": ["fluent"], "hard_skills": ["small", "shopify", "e-commerce"], "soft_skills": ["work independently", "fast-paced environment", "detail oriented", "organisational skills", "communicator", "energetic", "passionate about"], "languages_combined": [{"language": "english", "language_level": ["fluent"]}, {"language": "chinese", "language_level": ["fluent"]}]}, "experience_required": {"duration": ["1+ years"], "field": ["e-commerce"]}}, {"job_id": "100003009022684", "location_code": "hk", "company": "Hong Kong Trade Development Council", "job_title": "Senior Project Executive, Platform Development (Contract)", "description": "Ref. No.: 318/PJE-PD/EDB/HKTDC\n\nResponsibilities:\n\n\nAssist Project manager in collecting & preparing user requirements specifications and preparing functional specifications for business systems development\nLiaise with vendors, users and internal/cross-functional teams on all product-related issues\nFacilitate and conduct acceptance test (UAT), log defects and follow up on bug/defect fixing\nSupport the full product development lifecycle, system rollout and deployment, and work closely with the technical team to configure and optimize the customer experience\nAnalyze and research on market B2B & B2C products and assist in providing valuable insights to facilitate management decision making\nMonitor the progress of project deliverables\nUpdate documentation such as but not limited to operational workflows and meeting notes\nOther ad-hoc project assignments\n\nRequirements:\n\n\nUniversity degree, preferably in Computer Science, Digital Management, Information System or related disciplines\nWorking experience in product management, product development or project management is preferrable\nAble to work independently and under pressure when issues may escalate or timelines demand\nStrong problem-solving, research, analytical and presentation skills with well-organized, process oriented and positive approach\nGood team player with interpersonal and relationship building skills, able to collaborate with different stakeholders, both internal and external\nGood in written and spoken English and Chinese\nCandidate with less experience would be considered as Project Executive\nFresh graduates would be considered\n\nRemuneration and Benefits:\n\nThe successful candidate will be appointed on a fixed-term contract basis, renewable subject to operational needs. Salary will be commensurate with qualifications and experience.\u00a0\u00a0\n\nApplication Procedure:\n\nInterested candidates are invited to complete the application form on our website at http://www.hktdc.com/careers.html. Those who do not hear from us within EIGHT WEEKS after the closing date may assume their applications unsuccessful.\n\nAll information provided by applicants will be treated in strict confidence and used only for recruitment purposes. Applicants may be considered for other suitable positions within the Council. Their personal data will be destroyed six months after the selection is finalised.\n", "employment_types": ["Full Time", "Contract"], "selling_points": ["Mobile Apps Development Support", "Product management & development", "Digital Management & E-commerce"], "locations": ["Wan Chai"], "categories": ["Information Technology (IT)", "Application Specialist - Software", "E-commerce", "Product Management / Business Analyst", "Others"], "post_time": "2022-01-05T06:13:39Z", "salary": {"currency": null, "max": null, "min": null, "period": "monthly", "term": null}, "salary_visible": false, "title_keywords": ["senior project executive"], "responsibilities": ["ad-hoc", "management", "documentation", "uat", "project deliverables", "systems", "monitor", "specifications", "liaise with", "cross-functional teams"], "requirements": {"degrees": ["university degree"], "majors": ["related disciplines", "computer science"], "languages": ["english", "chinese"], "language_level": ["good"], "hard_skills": ["project management", "problem-solving", "information system"], "soft_skills": ["work independently", "good team player", "under pressure", "problem-solving", "well-organized", "project management", "presentation skills", "interpersonal", "positive"], "languages_combined": [{"language": "english", "language_level": ["good"]}, {"language": "chinese", "language_level": ["good"]}]}, "experience_required": {"duration": [], "field": ["product management", "project management", "product development"]}}, {"job_id": "100003009012137", "location_code": "hk", "company": "Daniel & Co", "job_title": "E-Commerce Assistant", "description": "Responsibilities:\n\nHandle daily operations of the e-commerce platform, including customer support, order fulfillment and product delivery arrangement\nProvide clerical and administration support to the team\nExecute E-commerce marketing promotions\nPrepare regular reports for promotion evaluation and sales performance\nHandle ad hoc assignments as assigned\n\n\u00a0Requirements:\n\nHigher Diploma\nAt least one year solid working experience (Fresh graduate will also be considered)\nExperience in E-commerce platform operations and website maintenance is preferably\nSelf-initiated individual with good team spirit, analytical mindset, attentive details and problem solving skill. Ability to work independently and under pressure\nFamiliar with social media culture and media tools such as Facebook and Instagram\nProficient in MS Word, MS Excel and Chinese word processing is a MUST;\nGood command of spoken and written English, Cantonese\nImmediately available is preferable\u00a0", "employment_types": ["Full Time", "Permanent"], "selling_points": ["daily operations of the e-commerce platform", "At least one year solid working experience", "website maintenance"], "locations": ["Kwai Tsing Area"], "categories": ["E-commerce", "Business Development", "Marketing - Brand / Product Management", "Others"], "post_time": "2021-12-31T09:14:18Z", "salary": {"currency": null, "max": null, "min": null, "period": "monthly", "term": null}, "salary_visible": false, "title_keywords": ["assistant"], "responsibilities": ["sales performance", "daily operations", "order fulfillment", "reports", "marketing promotions", "ad hoc assignments", "evaluation", "e-commerce platform", "administration"], "requirements": {"degrees": ["diploma", "fresh graduate"], "majors": [], "languages": ["cantonese", "english", "chinese"], "language_level": ["good command", "proficient"], "hard_skills": ["chinese word processing", "maintenance", "e-commerce", "problem solving", "ms excel", "facebook", "ms word"], "soft_skills": ["attentive", "work independently", "team spirit", "under pressure", "problem solving skill"], "languages_combined": [{"language": "cantonese", "language_level": ["good command"]}, {"language": "english", "language_level": ["good command"]}, {"language": "chinese", "language_level": ["proficient"]}]}, "experience_required": {"duration": ["at least one year"], "field": ["maintenance", "e-commerce"]}}, {"job_id": "100003009015311", "location_code": "hk", "company": "Taste of Asia Group Limited", "job_title": "E-commerce Specialist", "description": "Responsibilities:\n\nResponsible for daily key account management to ensure deliverables and KPIs are well achieved\nWork closely with in-house operation teams to deliver consistent and excellent performances\nTaking obligations to conduct internal & external business reviews on potential growth/ operation enhancement/ cost optimization\nEstablish long-term relationships with clients and identify potential business growth\nHandle any ad hoc duties as assigned\n\nRequirements:\n\nDegree in Business Management, Supply Chain, Logistics, eCommerce or related disciplines is preferred\nMinimum 3 years of key account/ project management experience, preferably in the field of 3PL & eCommerce industry\nPossess business acumen and able to perform multi-tasking\nExcellent communication and negotiation skills with strong sense of responsibility\nProficient in Microsoft Office (Word, Excel, PowerPoint)\nGood command of both written and spoken English and Chinese, Including Mandarin\nImmediate available is preferred\n\nIf you have the energy and qualifications to add to our velocity,\u00a0Please visit\u00a0Kerry Logistics Network Company Webpage\u00a0to apply or\u00a0send your CV with your present and expected salary to the\u00a0Group Director of\u00a0Human Resources & Administration, Kerry Logistics by clicking APPLY NOW\u00a0or by fax to +852 2614 8517\u00a0.\n\n(We are an equal opportunity employer and welcomes applications from all qualified candidates.\u00a0All personal data will be kept in the strictest confidence and will be used for recruitment purpose only. All applicants maybe considered for other suitable positions in the Kerry Group and its members. All personal data of unsuccessful candidates will be destroyed.)", "employment_types": ["Full Time"], "selling_points": ["Five-day work week", "Medical & dental allowance", "Performance bonus"], "locations": ["Wong Tai Sin Area"], "categories": ["Information Technology (IT)", "Software Development", "E-commerce", "Supply Chain", "Others"], "post_time": "2022-01-03T06:30:18Z", "salary": {"currency": null, "max": null, "min": null, "period": "monthly", "term": null}, "salary_visible": false, "title_keywords": ["specialist"], "responsibilities": ["ad hoc duties", "management", "cost optimization", "teams", "kpis"], "requirements": {"degrees": ["degree"], "majors": ["ecommerce", "related disciplines", "business"], "languages": ["english", "chinese", "mandarin"], "language_level": ["good command"], "hard_skills": ["business management", "excel", "microsoft office", "word", "powerpoint", "project management", "acumen"], "soft_skills": ["confidence", "sense of responsibility", "communication", "project management", "multi-tasking", "negotiation skills", "business acumen"], "languages_combined": [{"language": "english", "language_level": ["good command"]}, {"language": "chinese", "language_level": ["good command"]}, {"language": "mandarin", "language_level": ["good command"]}]}, "experience_required": {"duration": ["minimum 3 years"], "field": ["ecommerce", "project management"]}}, {"job_id": "100003009030760", "location_code": "hk", "company": "Yunfeng Financial Group Limited", "job_title": "Client Services Manager, Corporate Team (Vice President) (CS-21-08)", "description": "Job Description\n\nTo build a B2B E-commerce platform from zero, make sure it is profitable. Must be knowledgeable and multitask in sales, marketing, operation, logistics...etc. different field\nDevelop and implement B2B warehouse\u00a0standard operation\u00a0procedures in e-Commerce channels and logistics\nManage the existing logistic channel and explore new channels of E-commerce platform\nResearch and identify new potential partnerships and e-commerce opportunities\nSet the strategic direction, oversee and co-ordinate all e-commerce activity through different media\nFacilitate and monitor the KPIs of the warehouse, ensure timely and accuracy of orders fulfillment\n\nJob Requirement\n\nDegree in E-commerce / Computer Science / I.T. or related disciplines\nMinimum 2-3 years working experience in E-commerce, IT background is an advantage\nAnalytical with excellent business and market sense\nConfident in selling products/ business model/ concepts\nGood command of spoken and written English and Chinese\nIndependent and able to work under pressure\n\nJob location: San Po Kong\n\nCompetitive remuneration package and benefits as below:\nFive-day work week\nMarriage leave\nStaff discount\nMedical & dental allowance\nPerformance bonus\nIn-service training course\n5 days paternity leave\nCompassionate Leave\nPromotion opportunitie", "employment_types": ["Full Time", "Permanent"], "selling_points": ["5+  years working experience", "Experience in KYC/AML areas", "Experience in fund and trustee client onboarding"], "locations": ["Wan Chai"], "categories": ["Banking / Finance", "Investment", "Sales, CS & Business Devpt", "Customer Service - Manager", "E-commerce", "Others"], "post_time": "2022-01-07T08:16:48Z", "salary": {"currency": null, "max": null, "min": null, "period": "monthly", "term": null}, "salary_visible": false, "title_keywords": ["vice president", "client services manager"], "responsibilities": ["fulfillment", "monitor", "procedures", "develop", "logistics", "kpis", "e-commerce platform"], "requirements": {"degrees": ["degree"], "majors": ["computer science", "e-commerce"], "languages": ["english", "chinese"], "language_level": ["good command"], "hard_skills": ["e-commerce"], "soft_skills": ["confident", "independent", "work under pressure"], "languages_combined": [{"language": "english", "language_level": ["good command"]}, {"language": "chinese", "language_level": ["good command"]}]}, "experience_required": {"duration": ["minimum 2-3 years"], "field": ["it", "e-commerce"]}}, {"job_id": "100003009021026", "location_code": "hk", "company": "Postlogistics (Hong Kong) PTE Limited", "job_title": "Key Account Manager", "description": "Responsibilities\n\nProvide full range of account services proactively to premium corporate clients\nHandle account opening and corporate client onboarding processes, including data collection, KYC and record keeping\nProvide and promote quality client solutions by working closely with all business lines\nAssist the department head to establish and enforce service procedures, policies and standards\nParticipate in the coaching and training process of less experienced associates when necessary\n\nRequirements\n\n6+ \u00a0years working experience in related field such as relationship management, onboarding, client services etc\nExperience in fund and trustee client onboarding is preferable\nExperience in KYC/AML areas within Finance industry is strongly preferred\nFamiliar with SFC regulation on KYC and AML requirements\nExperience of providing service to all type of clients including Institutional, Corporate and Individual is highly preferred\nSFC type 1 license holder / pass of relevant papers is strongly preferred\nFluent in Mandarin and English is a must\nTitle would adjust based on the relevant experience\n\nWe provide a very competitive and open career path for our star performers. Interested candidates please kindly include the current and expected salary in the application. Information provided will be treated in strict confidence and will only be used for recruitment-related purposes. Only short-listed candidates will be notified.", "employment_types": ["Full Time"], "selling_points": ["Minimum 5 years KAM exp", "12 AL, double pay", "Degree holder in Business, Logistics"], "locations": ["Ngau Tau Kok"], "categories": ["Transportation & Logistics", "Private Transportation", "E-commerce", "Others"], "post_time": "2022-01-05T02:55:29Z", "salary": {"currency": null, "max": null, "min": null, "period": "monthly", "term": null}, "salary_visible": false, "title_keywords": ["account manager"], "responsibilities": ["account opening", "policies", "quality", "procedures", "data collection", "kyc"], "requirements": {"degrees": [], "majors": [], "languages": ["english", "mandarin"], "language_level": ["fluent"], "hard_skills": ["aml", "kyc"], "soft_skills": [], "languages_combined": [{"language": "english", "language_level": ["fluent"]}, {"language": "mandarin", "language_level": ["fluent"]}]}, "experience_required": {"duration": [], "field": ["related", "management", "relevant experience", "finance industry"]}}, {"job_id": "100003009016341", "location_code": "hk", "company": "Pear & Carrot Limited", "job_title": "Trade & Operations Assistant / Clerk (F&B)", "description": "We are a SME, with an international team of about 15 people.We are a responsible and sincere employer who is looking for candidates with the same thought and long-term commitment. Please read the salary range below to ensure it is within your expectation. Please DO state your Last Salary, Expected Salary and Notice Period in your CV.\n\nMain responsibilities:\n- General business support for our different business units\n- Food trading related tasks\n- Document preparation\n- Food labelling administration\n- Delivery booking and communication with our suppliers, shipping partners, local warehouses, retail locations and wholesale customers\n- Ad hoc duties as required\n\nRemuneration Package:\n- Nordic-style working environment\n- 9:00 am to 6:00 pm, 5-day work\n- Standard HK statutory bank holidays plus 12 days of paid annual leave + BIRTHDAY LEAVE\n- Medical Insurance\n- Staff Discount\n\nApplication requirements:\n-\u00a0 Over 1 year\u2019 relevant all-round office administration, secretariat, clerk, e-commerce or project management experience\u00a0\n- Strong sense of responsibility, ownership and common sense\n- Organized, detailed, able to handle multi-tasks effectively and prioritize works to meet schedules/ deadlines\n- Excellent communication, interpersonal and supervisory skills\n- Willing to work beyond office hours and on weekends/holidays to handle/ monitor emergency or ad hoc projects\n- Proficient in written English and Chinese\n\nAlways a Bonus,\n- Any experience from Scandinavia will be considered as an advantage\n- Any experience from F&B will be considered as an advantage\n- Computer savvy, proficiency in MS Office\n\nFresh graduates are welcome!\n\nWorking Location: FOTAN", "employment_types": ["Full Time"], "selling_points": ["Work Life Balance", "5 working days per week", "Fresh graduates welcome!"], "locations": ["Shatin Area"], "categories": ["Admin & HR", "Clerical / Admin Staff", "E-commerce", "Others"], "post_time": "2022-01-04T16:20:11Z", "salary": {"currency": "HKD", "max": 16999, "min": 14000, "period": "monthly", "term": null}, "salary_visible": true, "title_keywords": ["clerk", "operations assistant"], "responsibilities": ["ad hoc duties", "shipping", "communication", "booking", "insurance", "administration"], "requirements": {"degrees": [], "majors": [], "languages": ["english", "chinese"], "language_level": ["proficient"], "hard_skills": ["project management", "ms office", "e-commerce"], "soft_skills": ["organized", "multi-tasks", "sense of responsibility", "prioritize", "communication", "project management", "interpersonal", "detailed"], "languages_combined": [{"language": "english", "language_level": ["proficient"]}, {"language": "chinese", "language_level": ["proficient"]}]}, "experience_required": {"duration": ["1 year"], "field": ["office administration", "project management", "f&b", "e-commerce"]}}, {"job_id": "100003009023757", "location_code": "hk", "company": "The Cookware Company Limited", "job_title": "Digital Marketing Specialist", "description": "Inspired by the healthy kitchen? Looking for a tasteful challenge in an international company? Look no further!\n\nThe Cookware Company is a global company with a high expertise in innovative cookware. Our organization is vertically integrated, allowing us to manage both the production and distribution of our products. We have sales offices in Europe, the United States and Asia as well as state-of-the-art production facilities in Korea, China and Europe. We have high quality standards (e.g. ISO-certificates) and work hard to reduce our environmental impact.\n\nThe Cookware Company has always been a pioneer in healthy ceramic non-stick cookware. Over the years we have extended our scope in order to offer smart cookware solutions for everyone. Innovation, flexibility, creativity and social responsibility are our main focus. However, our most important asset are our people. They\u2019re the heart of our company.\n\nDue to significant business growth, we are currently seeking an Digital Marketing Specialist\u00a0to join our dynamic team in our Hong Kong Office.\n\nDigital Marketing Specialist\n\nESSENTIAL FUNCTIONS AND DUTIES:\n\nDesign digital media campaigns aligned with business goals\nExecution of campaign schedules and budgets\nManage end-to-end digital projects\nBoost brand awareness, engagement and conversion rate\nUnderstand the workings of Social Media and AdWords\u2019 programs, and search engine optimization towards promoting appropriately the profit goal of the organization\nManage the digital agency relationships of the organisation\nMaintain a strong online company voice through social media\nLiaise with Marketing, Sales, and Product development teams to ensure brand consistency\nCoordinate the creation of digital content (e.g. website, social media, eDM, influencers, online advertising)\nMaintain campaign reporting ROI and KPIs, metrics, and prepare reports\nPresent insights and workable recommendations to reporting manager\u00a0 \u00a0 \u00a0 \u00a0 \u00a0 \u00a0 \u00a0 \u00a0 \u00a0 \u00a0 \u00a0 \u00a0 \u00a0 \u00a0 \u00a0 \u00a0 \u00a0 \u00a0 \u00a0 \u00a0 \u00a0 \u00a0 \u00a0 \u00a0 \u00a0 \u00a0 \u00a0 \u00a0 \u00a0 \u00a0 \u00a0 \u00a0 \u00a0 \u00a0 \u00a0\n\nQUALIFICATIONS:\n\nBusiness savvy and data driven\nProven experience and knowledge in key areas (SEO, Social Media advertising, SEM, email marketing)\nFamiliar with Facebook Ad Manager, Google Analytics, Google Adwords, Facebook Merchant Center\n5+ years in marketing / digital marketing field\nD2C work experience\nBachelor\u2019s Degree Related to Marketing, or Business", "employment_types": ["Full Time", "Permanent"], "selling_points": ["Fast Growing MNC", "Regional Exposure", "Cross-cultural Working Environment"], "locations": ["Kowloon Bay"], "categories": ["Marketing / Public Relations", "Digital Marketing", "E-commerce", "Marketing - Brand / Product Management", "Others"], "post_time": "2022-01-05T09:43:04Z", "salary": {"currency": null, "max": null, "min": null, "period": "monthly", "term": null}, "salary_visible": false, "title_keywords": ["digital marketing specialist"], "responsibilities": ["business goals", "data", "schedules", "quality", "website", "design", "maintain", "liaise with", "facebook", "online advertising", "advertising", "teams", "kpis", "social media", "reporting", "seo", "edm", "digital marketing", "budgets", "coordinate", "sem", "prepare reports", "brand consistency"], "requirements": {"degrees": ["degree", "bachelor"], "majors": ["business", "marketing"], "languages": [], "language_level": [], "hard_skills": ["google analytics", "no", "seo", "adwords", "goal", "dynamic", "sem", "facebook", "focus"], "soft_skills": ["dynamic", "organisation", "focus", "innovative", "driven"], "languages_combined": []}, "experience_required": {"duration": [], "field": ["social media", "marketing", "advertising"]}}, {"job_id": "100003009017836", "location_code": "hk", "company": "Shopee Hong Kong Limited", "job_title": "Account Executive (Electronics Category)", "description": "Job Highlights\n\u5e74\u504710-12\u65e5\n\u5177\u76f8\u95dc\u96f6\u552e\u7d93\u9a57\u8005\u512a\u5148\u8003\u616e\n\u7121\u96f6\u552e\u7d93\u9a57\u8005\u4e5f\u8003\u616e\u517c\u8077\u7533\u8acb, \u8868\u73fe\u826f\u597d\u53ef\u8f49\u5168\u8077\n\nKey Responsibilities \u5de5\u4f5c\u7bc4\u570d\uff1a\n\n1.Responsible for product selling and relevant customer service\n\u00a0 \u00a0\u92b7\u552e\u7522\u54c1\u53ca\u5ba2\u6236\u670d\u52d9.\n\n2.Support retail store daily operations, including visual merchandising, stock keeping and cashiering and logistics arrangement\n\u00a0 \u5354\u52a9\u5e97\u8216\u65e5\u5e38\u904b\u4f5c\uff0c\u5305\u62ec\u7522\u54c1\u9673\u5217\u3001\u5009\u5b58\u6574\u7406\u3001\u6536\u9280\u5de5\u4f5c\u7b49\n\n3.Support online and offline shop daily opertaion.\n\u00a0 \u00a0\u5354\u52a9\u53ca\u652f\u63f4\u7db2\u5e97\u53ca\u5be6\u9ad4\u5e97\u76f8\u95dc\u71df\u904b\u5de5\u4f5c\n\n\u00a0\u8077\u4f4d\u8981\u6c42\uff1a\n-\u00a0\u71b1\u611b\u6236\u5916\u6d3b\u52d5\u5982\u9732\u71df\u884c\u5c71, \u6d6e\u6f5b\u6f5b\u6c34\u7b49\u6d3b\u52d5\n-\u00a0\u6700\u5c112 \u5e74\u5168\u8077\u5de5\u4f5c\u7d93\u9a57\uff0c\u6700\u5c11\u6709\u4e00\u4efd\u5de5\u4f5c\u505a\u8d85\u904e2\u5e74\u6216\u4ee5\u4e0a\n- \u4e2d\u5b78\u6216\u4ee5\u4e0a\u7a0b\u5ea6\n- \u6d41\u5229\u7cb5\u8a9e\u3001\u7c21\u55ae\u82f1\u8a9e\u53ca\u666e\u901a\u8a71\n-\u00a0\u8aa0\u61c7\u6709\u79ae\u3001\u4e3b\u52d5\u7a4d\u6975\u3001\u5177\u8cac\u4efb\u611f\u3001\u5177\u5718\u968a\u7cbe\u795e\n- \u826f\u597d\u6e9d\u901a\u53ca\u92b7\u552e\u6280\u5de7\n\n\u5f85\u9047\uff1a\u52e4\u5de5\u734e\u91d1, \u96d9\u7ce7\u53ca\u5e74\u7d42\u734e\u91d1, \u9280\u884c\u5047\u671f, \u54e1\u5de5\u8cfc\u7269\u512a\u60e0\u53ca\u5728\u8077\u57f9\u8a13\u5e73\u5747\u6bcf\u67086 \u5929\u5047\u671f\uff0c\u9022\u516c\u773e\u5047\u671f\u4f11\u606f\n\n\u7533\u8acb\u65b9\u6cd5\uff1a\n\n\u8acb\u6309\u00a0Apply Now\u00a0\u7533\u8acb\u00a0\u6216\u00a0WhatsApp\u81f361100341 \u5433\u5c0f\u59d0\n\n", "employment_types": ["Full Time"], "selling_points": ["Young and energetic working environment", "Key account management", "Attractive and competitive package and benefits"], "locations": ["Mong Kok"], "categories": ["E-commerce", "Others"], "post_time": "2022-01-04T02:13:40Z", "salary": {"currency": null, "max": null, "min": null, "period": "monthly", "term": null}, "salary_visible": false, "title_keywords": ["account executive"], "responsibilities": ["logistics arrangement", "merchandising", "daily operations", "customer service", "visual"], "requirements": {"degrees": [], "majors": [], "languages": [], "language_level": [], "hard_skills": ["visual merchandising"], "soft_skills": ["customer service", "responsible"], "languages_combined": []}, "experience_required": {"duration": [], "field": []}}, {"job_id": "100003009012746", "location_code": "hk", "company": "DKSH Hong Kong Limited", "job_title": "Senior Executive, Online Sales & Marketing, FMCG", "description": "JOB TITLE: Key Account Manager\nRESPONSIBLE TO: Head of Sales - APAC\nMAIN LOCATION: Kwun Tong, Hong Kong\n\nResponsibilities:\n\n\u2022 Build and maintain business relationship with assigned key accounts for long term partnership and revenue growth\n\u2022 Coordinate with key stakeholders to drive new business development and implementation.\n\u2022 Conduct regular business review meeting to ensure operation excellence and customer experience.\n\u2022 Upsell / cross-sell to expand the revenue profile and share of wallet.\n\u2022 Regular update pipeline status and market intelligence.\n\u2022 Perform any other ad-hoc tasks assigned by the manager.\n\nEssential Skills:\n\n\u2022 Degree holder in Business, Logistics or related discipline.\n\u2022 Minimum 5 years key account management and development, preferably in logistics / transportation industry.\n\u2022 Familiar with the cross border eCommerce industry is an added advantage.\n\u2022 Self-motivated with strong sense of tasks ownership.\n\u2022 Good command of spoken & written English and Chinese/Mandarin.\n\nAdditional Requirements:\n\n1. In addition to the duties and responsibilities listed, the postholder may be required to perform other duties assigned by the Company from time to time. Subject to adequate experience and/or training.\n2. To participate in the annual performance appraisal and objective setting scheme.\n3. To work in accordance with all company policies including Health and Safety, Employment, Staff, Quality and Environmental.\n4. It is important that during the employment with the Company and any time thereafter, that any information relating to the affairs of the Company is treated with the highest level of confidentiality.\n5. To have a detailed knowledge of and apply the Company's Business Plan in all aspects of development.\n\n\u00a0 \u00a0 \u00a0 \u00a0 \u00a0 \u00a0 \u00a0 \u00a0 \u00a0 \u00a0\u00a0 EQUALITY OF OPPORTUNITY IS COMPANY POLICY", "employment_types": ["Full Time"], "selling_points": ["E-Commerce business (China focus)", "Support Online Sales & Marketing Operations", "Familiar with Tmall, VIP, Kaola, JD, Redbook etc"], "locations": ["Aberdeen"], "categories": ["E-commerce", "Marketing - Brand / Product Management", "Others", "Sales, CS & Business Devpt", "Sales Administration"], "post_time": "2022-01-02T02:29:58Z", "salary": {"currency": null, "max": null, "min": null, "period": "monthly", "term": null}, "salary_visible": false, "title_keywords": ["senior executive", "sales"], "responsibilities": ["management", "ad-hoc tasks", "review", "coordinate with", "implementation", "maintain", "revenue growth", "logistics"], "requirements": {"degrees": [], "majors": [], "languages": [], "language_level": [], "hard_skills": ["scheme"], "soft_skills": ["detailed"], "languages_combined": []}, "experience_required": {"duration": [], "field": ["training"]}}, {"job_id": "100003009006940", "location_code": "hk", "company": "Samsonite Asia Limited", "job_title": "E-commerce Assistant (Part-Time)", "description": "Job Responsibilities\nExperience in account management with online marketplace are highly preferred\nManagement of the partners on a daily basis, responsible for the aspect of planning and execution including promotion, new brands and new products launches etc\u00a0\u00a0\nAbility to act as a consolidation/consultation role between internal and external parties such as standardize procedures with cross functional teams\nIdentify potential opportunities with key partners to develop and grow market share\nAnalyze and monitor the sales achievement and propose/initiate/take action to meet quarterly and yearly target\nBuild and sustain great business relationship with partners\nHandle admin work as required including on-boarding new potential partners\nCoachable and motivated amongst team members, take positive action and accountability for their assigned work.\nFamiliar with the Customer Electronics trend\nAssist and participate in other ad-hoc projects\n\nJob Requirements\n\nPreferably 1 year account management experience\nSelf-driven with strategic mind to explore new opportunities and generate sales with strong marketing sense\nGood analytical and numerical skills\nProficiency in MS office\nFluent in English, Cantonese and good in Mandarin\nProactive, positive and ready for challenges are highly preferred", "employment_types": ["Part Time"], "selling_points": ["eCommerce exposure", "Attentive to details and accuracy", "Part-Time can work at least 4 days per week"], "locations": ["Tsim Sha Tsui"], "categories": ["Admin & HR", "Clerical / Admin Staff", "E-commerce", "Others"], "post_time": "2021-12-29T13:24:37Z", "salary": {"currency": null, "max": null, "min": null, "period": "hourly", "term": null}, "salary_visible": false, "title_keywords": ["assistant"], "responsibilities": ["management", "internal and external parties", "procedures", "teams", "monitor", "develop", "ad-hoc projects", "planning"], "requirements": {"degrees": [], "majors": [], "languages": ["cantonese", "english", "mandarin"], "language_level": ["good", "fluent"], "hard_skills": ["numerical skills", "ms office"], "soft_skills": ["proactive", "marketing sense", "driven", "positive"], "languages_combined": [{"language": "cantonese", "language_level": ["fluent"]}, {"language": "english", "language_level": ["good", "fluent"]}, {"language": "mandarin", "language_level": ["fluent"]}]}, "experience_required": {"duration": ["1 year"], "field": ["account management"]}}, {"job_id": "100003009016786", "location_code": "hk", "company": "Links International", "job_title": "Key Account Manager - B2B2C", "description": "The job holder\u2019s key responsibilities are to:\n\nManage daily operation for official E-Shop and other e-Commerce platforms\nAssist the product assortment on website and marketplaces\nResponsible for managing overall logistics, inventory, customer services issues\nPerform administrative tasks and operational support for the team\nWork closely with internal departments to ensure smooth operation\nOther tasks as assigned by supervisors\u00a0\n\nRequirements:\n\nHigher Diploma or above in Marketing, eCommerce, or related disciplines\nExperience in e-Commerce operation and administrative tasks would be a plus\nPassionate, creative, and open minded\nGood communication skills, self-motivated, attentive to details and accuracy\nHigh proficiency in both written and spoken English & Cantonese\nAble to work at least 4 days per week\n\nWe offer competitive package, benefits and remuneration.\u00a0 Please apply with full resume by stating the latest and expected salaries and availability date to the Human Resources Manager, 25/F Tower 2, The Gateway, Harbour City, 25 Canton Road, Tsim Sha Tsui, Kowloon or by clicking \u2018APPLY NOW\u2019, please visit our website at http://www.samsonite.com.hk. \u00a0All personal data collected is for recruitment purposes only.\n\nSamsonite is an equal opportunity employer and welcome applications from all qualified candidates. All information provided by candidates will be used solely for recruitment purposes. Unsuccessful applications will be destroyed in strict confidence upon completion of recruitment process.", "employment_types": ["Full Time", "Permanent"], "selling_points": ["Global leading internet firm", "5+ yrs exp in account management", "Data driven, strategic"], "locations": ["Not Specified"], "categories": ["Hospitality / F & B", "Others", "Sales, CS & Business Devpt", "Account Servicing", "E-commerce", "Others"], "post_time": "2022-01-03T09:49:59Z", "salary": {"currency": null, "max": null, "min": null, "period": "monthly", "term": null}, "salary_visible": false, "title_keywords": ["account manager"], "responsibilities": ["operational support", "e-shop", "inventory", "daily operation", "e-commerce platforms", "website", "customer services", "other tasks", "logistics", "administrative tasks"], "requirements": {"degrees": ["higher diploma or above"], "majors": ["ecommerce", "related disciplines", "marketing"], "languages": ["cantonese", "english"], "language_level": ["proficiency"], "hard_skills": ["plus", "e-commerce"], "soft_skills": ["passionate", "communication skills", "self-motivated", "attentive to details", "open minded", "creative"], "languages_combined": [{"language": "cantonese", "language_level": ["proficiency"]}, {"language": "english", "language_level": ["proficiency"]}]}, "experience_required": {"duration": [], "field": ["operation", "administrative", "e-commerce"]}}, {"job_id": "100003009006166", "location_code": "hk", "company": "HongKong Suning Commerce Co., Limited", "job_title": "Administration Assistant", "description": "Job responsibilities:\n\nResponsible for day-to-day management across E-Commerce\nManage cross border E-Commerce business via own and 3rd party platform\nIdentify appropriate new 3rd party sites\nEnsure new sites are aligned with overall digital strategies and objectives; maintain strong working relationships with 3rd party partners (Tmall, VIP, Kaola, JD, Redbook etc)\nCollect and analyze customer business performance data (e.g. shipment sales, public agency data and online channels) and make recommendations to utilize the business opportunities\nResearch and report on market / competitor / customer data and other relevant data to provide insights and support for negotiation processes\nEvaluate promotional plans (pre and post) with supporting qualitative commentary and their impact on customer and brand strategies\nDevelop effective relationships with external stakeholders (e.g. data providers and contacts) throughout the customers' organizations in order to gather relevant data for analysis\nWork closely with the cross-functional teams (e.g. Trade Marketing, Retail and Supply Chain Management) to ensure efficient and effective execution.\nJob requirements:\n\nUniversity graduate in any discipline\nMinimum of 2 years' experience in e-Commerce, Candidate with China cross border key account exposure is preferred\nSound knowledge and understanding of China 3rd party e-Commerce sites/competitors/key trends\nAdvanced research and analytical skills\nGeneral understanding in all aspects of supplier and customer relationship management including supply chain, marketing and branding\nStrong coordination and organization skills in collecting business-related data\nProficiency in office productivity tools (e.g. Excel, Word and PowerPoint)\nExcellent written and spoken English and Mandarin\nWorking location: Wong Chuk Hang\n\nWe offer performance bonus and attractive benefits to the right candidate.\u00a0 Interested parties please apply in full resume with current and expected salaries by clicking \"Apply Now\".\n\nAll personal data collected will be used for recruitment purpose only.\u00a0 Candidates will be contacted within 2 weeks if the background and experience are closely relevant to the job requirement.\n\nDrive Growth.\u00a0 Be the Difference.\u00a0 Join DKSH.\n\nDKSH's strength lies in our great diversity of services, industries, clients, products, regions and employees from various nationalities.\u00a0 We are proud of our people: they are the reason we are successful.\u00a0 Our people are the best in the industry.\u00a0 They are passionate about their career growth and about business success.\u00a0 They work as part of an energetic and committed team, positively impacting millions of lives through the products and services we provide.\n\nJoin us today if you are ready to \"Drive growth.\u00a0 Be the Difference.\"\u00a0 With DKSH, you will experience a world of learning and development, own your career and take business responsibility and have a positive impact that touches people's lives.", "employment_types": ["Full Time"], "selling_points": ["High diploma or degree holder", "Immediate available is preferred", "Fresh graduate are welcome"], "locations": ["Kwun Tong"], "categories": ["Admin & HR", "Personal / Executive Assistant", "Secretary", "E-commerce", "Others"], "post_time": "2022-01-02T22:53:38Z", "salary": {"currency": null, "max": null, "min": null, "period": "monthly", "term": null}, "salary_visible": false, "title_keywords": ["administration assistant"], "responsibilities": ["provide insights", "customer business performance data", "data", "brand strategies", "negotiation processes", "maintain", "cross border e-commerce business", "gather relevant data", "digital strategies and objectives", "make recommendations", "develop effective relationships", "day-to-day management", "3rd party sites", "customer data", "utilize the business opportunities", "management", "3rd party platform", "research and report", "promotional plans", "cross-functional teams", "online channels", "trade marketing", "shipment sales", "analysis", "public agency data", "evaluate", "working relationships"], "requirements": {"degrees": ["university graduate"], "majors": [], "languages": ["english", "mandarin"], "language_level": ["excellent"], "hard_skills": ["excel", "e-commerce", "word", "powerpoint", "analytical skills"], "soft_skills": ["organization skills", "advanced", "coordination", "analytical skills"], "languages_combined": [{"language": "english", "language_level": ["excellent"]}, {"language": "mandarin", "language_level": ["excellent"]}]}, "experience_required": {"duration": ["minimum of 2 years"], "field": ["e-commerce"]}}, {"job_id": "100003009016896", "location_code": "hk", "company": "Hong Kong Technology Venture Company Limited", "job_title": "Marketing Officer (O2O Shop)", "description": "Our client is UK Listed Internet Company. They are now expanding the Key Account team and looking for Key Account Manager to join.\n\nJob Responsibilities\n\n\nBuild and manage existing key client relationship, consistently improve business performance and identify potential business opportunities\nConduct performance analysis to identify growth opportunities and drive improvement projects\nCoordinate among various internal stakeholders on marketing promotion planning for sales generation\nDevelop and build consumer value proposition, including promotions, pricing, selections, service levels, etc.\n\nRequirements\n\n\nBachelor degree holder\n4+ years of related experience in B2B or B2B2C account management\nProven account management on key clients for project management and sales generation\nData-driven to analyze performance and provide insights for improvement\nFlexible and a good team player with great problem-solving skills and creativity", "employment_types": ["Full Time"], "selling_points": ["Fresh graduates are welcome", "Measure and analyze sales performance", "Young and energetic team"], "locations": ["Tseung Kwan O"], "categories": ["Marketing / Public Relations", "Marketing - General / Support", "E-commerce", "Others"], "post_time": "2022-01-03T10:03:45Z", "salary": {"currency": null, "max": null, "min": null, "period": "monthly", "term": null}, "salary_visible": false, "title_keywords": ["marketing officer"], "responsibilities": ["business opportunities", "analysis", "develop", "coordinate", "planning"], "requirements": {"degrees": ["bachelor degree holder"], "majors": [], "languages": [], "language_level": [], "hard_skills": ["problem-solving skills", "project management"], "soft_skills": ["flexible", "good team player", "project management", "problem-solving skills", "driven"], "languages_combined": []}, "experience_required": {"duration": ["4+ years"], "field": ["related", "account management"]}}, {"job_id": "100003009007723", "location_code": "hk", "company": "Take Action Limited", "job_title": "E-Commerce / Digital Marketing Assistant", "description": "Responsibilities:\n\nResponsible for daily paper work, maintain confidential information and document management\nCoordinate, monitor and follow up all business matters and documentation as assigned\nCoordinate and attend team meetings, events and conferences\nCapable to handle all enquires and correspondence independently\nTo works closely with the e-commerce and marketing team\nProvide secretarial support to director\nAssist in clerical and various tasks assigned and ad hoc projects\n\nQualifications:\n\nHigh diploma or degree holder\nStrong communication and interpersonal skills\nFluency in Putonghua is an advantage\nGood computer skills (MS Office, Excel, Powerpoint) and proficient in Chinese typing\nIndependent, proactive, mature and multitasking, work under pressure and with a can do attitude\nFresh graduate are welcome.\nImmediate available is preferred.\n\nRemarks:\n\nWe offer attractive remuneration package including\u00a0Meal\u00a0allowance, medical\u00a0benefits and\u00a0year-end\u00a0bonus.\n\nInformation collected will be kept confidential and to be used for recruitment purpose.", "employment_types": ["Full Time"], "selling_points": ["5.5-day work week (Sat. half day & off on weekday)", "Staff shopping discount", "10 Days Annual Leave"], "locations": ["Yuen Long"], "categories": ["E-commerce", "Others"], "post_time": "2021-12-30T04:02:06Z", "salary": {"currency": null, "max": null, "min": null, "period": "monthly", "term": null}, "salary_visible": false, "title_keywords": ["digital marketing", "assistant"], "responsibilities": ["management", "monitor", "coordinate", "communication", "conferences", "maintain", "ad hoc projects", "secretarial support", "documentation", "work under pressure"], "requirements": {"degrees": ["high diploma", "fresh graduate", "degree holder"], "majors": [], "languages": ["putonghua", "chinese"], "language_level": ["fluency", "advantage", "proficient", "good"], "hard_skills": ["excel", "e-commerce", "typing", "powerpoint", "computer skills", "documentation", "ms office"], "soft_skills": ["independently", "independent", "capable", "responsible", "mature", "communication and interpersonal skills", "proactive", "work under pressure"], "languages_combined": [{"language": "putonghua", "language_level": ["fluency", "advantage"]}, {"language": "chinese", "language_level": ["proficient", "good"]}]}, "experience_required": {"duration": [], "field": []}}, {"job_id": "100003009001316", "location_code": "hk", "company": "Pricerite Home Ltd", "job_title": "Assistant Officer / Officer, E-Commerce", "description": "What Will You Be Doing:\n\n\nWork with internal design team in the production of promotional materials including in-store POSM, print/digital ads, product catalogue, leaflets etc.\nFormulate a comprehensive marketing plan to increase awareness to drive penetration into our O2O shops and the conversion of customers through shops' promotional activities\nMeasure and analyze sales performance including actual sales through in each channel and identify key learning\nCollect market information to develop strategic plan\nGeneral/ad-hoc supports to new projects\n\nWho is our Right Fit:\n\n\nBachelor Degree in Marketing/ Communications/ e-Commence / e-Marketing or a related discipline\n0-3 years relevant experience in the field of CRM, digital advertising, or social media editing\nFresh Graduates are welcome\nFamiliar with data structure or data analysis is an advantage\nProactive, independent with excellent time management skills and ability to work under pressure\nStrong numerical sense, analytical and problem-solving skills\nCreative with strong marketing sense and business acumen\nProficient of both written and spoken English and Chinese\nGood command of MS PowerPoint & MS Excel\nImmediately available or short notice is an advantage", "employment_types": ["Full Time", "Permanent"], "selling_points": ["Birthday Leave", "Friendly working environment", "Assist in various E-commerce project developments"], "locations": ["Kowloon Bay"], "categories": ["Sales, CS & Business Devpt", "Retail Sales", "E-commerce", "Supply Chain", "Others"], "post_time": "2021-12-28T02:12:24Z", "salary": {"currency": null, "max": null, "min": null, "period": "monthly", "term": null}, "salary_visible": false, "title_keywords": ["assistant officer", "officer"], "responsibilities": ["ad-hoc", "management", "market information", "advertising", "data", "leaflets", "sales performance", "design", "develop", "data analysis", "marketing plan", "promotional materials", "promotional activities", "plan", "social media editing", "catalogue", "work under pressure"], "requirements": {"degrees": ["degree", "bachelor"], "majors": ["marketing", "communications"], "languages": ["english", "chinese"], "language_level": ["proficient"], "hard_skills": ["analysis", "ms excel", "problem-solving skills", "ms powerpoint", "acumen"], "soft_skills": ["independent", "creative", "marketing sense", "time management skills", "comprehensive", "learning", "business acumen", "problem-solving skills", "proactive", "work under pressure"], "languages_combined": [{"language": "english", "language_level": ["proficient"]}, {"language": "chinese", "language_level": ["proficient"]}]}, "experience_required": {"duration": ["0-3 years"], "field": ["social media", "advertising", "relevant experience", "digital", "editing"]}}, {"job_id": "100003009017551", "location_code": "hk", "company": "PARKnSHOP", "job_title": "Web Designer (3-month Contract)", "description": "Responsibilities\n\nl\u00a0\u00a0 Support online platform interface update and manage daily operations of cross brand owe e-stores, including but not limited to content management, product listing, pricing, promotion and inventory update, handling order fulfilment and providing\n\nl\u00a0\u00a0 Maintain and update product description, product placement and other logistic arrangement in 3rd party platform such as HKTV Mall\n\nl\u00a0\u00a0 Liaise with warehouse and 3rd party partner to ensure the delivery standard is met\n\nl\u00a0\u00a0 Monitor and control marketing campaign timelines\n\nl\u00a0\u00a0 Conduct market & competitor research to understand customer needs and marketing trends for enhancing customer shopping experience\n\nl\u00a0\u00a0 Assist in preparing business analysis report on sales and promotion performance of cross brand eCommerce marketplace\n\nl\u00a0\u00a0 Assist any other ad-hoc projects as assigned", "employment_types": ["Temporary", "Contract"], "selling_points": [], "locations": ["Shatin Area"], "categories": ["Design", "Multi-media", "Web Designer", "E-commerce", "Others"], "post_time": "2022-01-04T01:11:06Z", "salary": {"currency": null, "max": null, "min": null, "period": null, "term": null}, "salary_visible": false, "title_keywords": ["designer"], "responsibilities": ["understand customer needs", "management", "control", "business analysis", "product listing", "3rd party platform", "inventory", "monitor", "logistic arrangement", "maintain", "liaise with", "ad-hoc projects", "manage daily operations", "report"], "requirements": {"degrees": [], "majors": [], "languages": [], "language_level": [], "hard_skills": ["analysis"], "soft_skills": [], "languages_combined": []}, "experience_required": {"duration": [], "field": ["research", "marketing"]}}, {"job_id": "100003009004343", "location_code": "hk", "company": "Travel Expert Ltd", "job_title": "Operations Officer - eCommerce", "description": "Responsibilities:\n\nPrepare eShop promotion landing page, CMS management and maintain website content\nPrepare artworks for web interface including web design, page layout, banner, animation etc.\nSupport the production of online campaign including online/mobile shopping\nDesign promotional materials including web banner, eDM, catalogues, brochure, and poster advertisement.\n\nRequirements:\n\nDiploma or above in Graphic, Multimedia Design, or related disciplines\nKnowledge of design applications (DreamWeaver, Photoshop, Illustrator)\nFamiliar with HTML5, UX & UI, CSS, JS\nGood communication skills in both Chinese & English\nA good team player with good time management skill\n\nAn attractive salary and benefit package will be offered. Interested parties please forward detailed resume stating expected salary to: People\u00a0Department, PARKnSHOP (HK) Limited, Watson House, 1-5 Wo Liu Hang Road, Fo Tan, N.T. or email to us.\n\nWe are an equal opportunity employer and welcome applications from all qualified candidates. The information provided will be treated in strict confidence and be used only for consideration of your application for relevant / similar posts within the A.S. Watson Group. All personal data of unsuccessful applicants will be destroyed within 12 months from the date of application.", "employment_types": ["Full Time"], "selling_points": [], "locations": ["Lai Chi Kok"], "categories": ["E-commerce", "Others"], "post_time": "2021-12-29T02:07:35Z", "salary": {"currency": null, "max": null, "min": null, "period": "monthly", "term": null}, "salary_visible": false, "title_keywords": ["operations officer"], "responsibilities": ["management", "edm", "website", "design", "maintain", "promotional materials", "animation"], "requirements": {"degrees": ["diploma or above"], "majors": ["multimedia design", "related disciplines"], "languages": ["english", "chinese"], "language_level": ["good"], "hard_skills": ["illustrator", "multimedia", "dreamweaver", "css", "photoshop"], "soft_skills": ["communication skills", "good team player", "time management skill"], "languages_combined": [{"language": "english", "language_level": ["good"]}, {"language": "chinese", "language_level": ["good"]}]}, "experience_required": {"duration": [], "field": []}}, {"job_id": "100003009008323", "location_code": "hk", "company": "Francfranc HONG KONG LIMITED", "job_title": "Customer Service & Operation Officer", "description": "RESPONSIBILITIES\n\n\nAnswer customer enquiry and handle customer complaints on products, orders and after sale service in a professional manner\nHandle e-commerce logistics issue with internal & external parties\nDaily Order Processing\nSupport daily operation\nAssist in optimizing operation workflow projects\nReflect customer feedback and suggest service improvement in terms of products, system and daily workflow\nPrepare various reports such as case report, refund reports etc\n\n\u00a0REQUIREMENTS\n\nDiploma or Degree holder in Customers Service or any related discipline\n\n1-2 years e-Commerce experience from retail industry\nFluent in spoken and written in English, Mandarin and Cantonese\nGood PC skill including MS office, Chinese and English word typing\nAbility to work independently, service-oriented approach with a positive and good attitude in helping customers\n\nJOB OFFER\n\nDouble Pay\nMedical Benefit\nBirthday Leave\nMarriage Leave\nStudy Sponsorship\nStaff Discounts\n5 Days work\nLocation : Kwun Tong\n\n\u00a0Interested applicants, please send your application letter with FULL RESUME, PRESENT AND EXPECTED SALARY and DATE OF AVAILABLE to Francfranc Hong Kong Ltd by clicking APPLY NOW\n\n(Please quote Job Ref.: Customer Service & Operation Officer)\n\nAll information provided by applicants will be used for recruitment related purpose only and will be handled in strict confidence by authorized personnel. Only short-listed candidates will be notified.", "employment_types": ["Full Time", "Permanent"], "selling_points": ["Answer customer enquiry and handle customer", "Handle e-commerce logistics issue", "Daily Order Processing"], "locations": ["Kwun Tong"], "categories": ["E-commerce", "Others"], "post_time": "2021-12-30T07:37:48Z", "salary": {"currency": null, "max": null, "min": null, "period": "monthly", "term": null}, "salary_visible": false, "title_keywords": ["operation officer", "customer service"], "responsibilities": ["customer complaints", "external parties", "professional manner", "daily operation", "logistics", "reports", "order processing", "report"], "requirements": {"degrees": ["diploma", "degree holder"], "majors": [], "languages": ["cantonese", "english", "chinese", "mandarin"], "language_level": ["good", "fluent"], "hard_skills": ["e-commerce", "typing", "word", "pc skill", "ms office"], "soft_skills": ["work independently", "confidence", "service-oriented", "customer service", "positive"], "languages_combined": [{"language": "cantonese", "language_level": ["fluent"]}, {"language": "english", "language_level": ["good", "fluent"]}, {"language": "chinese", "language_level": ["good"]}, {"language": "mandarin", "language_level": ["fluent"]}]}, "experience_required": {"duration": ["1-2 years"], "field": ["retail industry", "e-commerce"]}}, {"job_id": "100003009008282", "location_code": "hk", "company": "Ultimate PC & MAC Gallery Limited", "job_title": "Operation Officer", "description": "Job Highlights\n\nBe very responsible and detail-minded\nSupport daily operations\nRapid growing E-Commerce\n\u00a0Job Description\n\nResponsibilities:\n\nPrepare documents processing and ensure punctual shipment schedule\nWork in close collaboration with warehouse team on shipment arrangements\nHandle daily routine operation work to ensure all deliveries are properly handled\nProvide administration/operations support\nData Entry and product research\nCode and deal creation\nAssist team members on general operations\n\nRequirements:\n\nHigher Diploma or above\nExcellent in written and spoken Chinese, well in written English\nGood interpersonal, organizing and communication skills\nAble to work in high pressure and fast-paced environment\nExperience in Retail or other Order Support role is an advantage\nRelevant working experience is an advantage\nHardworking, independent and self-motivated with excellent communication skills\nProficiency in MSOffice (Word, Excel)\nImmediate availability is preferred", "employment_types": ["Full Time"], "selling_points": ["1-2 or above years of experience", "Rapid growing E-Commerce", "Immediate availability is preferred"], "locations": ["Kwun Tong"], "categories": ["E-commerce", "Others"], "post_time": "2021-12-30T07:25:08Z", "salary": {"currency": null, "max": null, "min": null, "period": "monthly", "term": null}, "salary_visible": false, "title_keywords": ["operation officer"], "responsibilities": ["data entry", "operations", "schedule", "prepare documents", "administration"], "requirements": {"degrees": ["higher diploma or above"], "majors": [], "languages": ["english", "chinese"], "language_level": ["excellent"], "hard_skills": ["excel", "msoffice", "word"], "soft_skills": ["communication skills", "self-motivated", "independent", "fast-paced environment", "interpersonal", "hardworking"], "languages_combined": [{"language": "english", "language_level": ["excellent"]}, {"language": "chinese", "language_level": ["excellent"]}]}, "experience_required": {"duration": [], "field": ["retail", "relevant working experience"]}}, {"job_id": "100003009015242", "location_code": "hk", "company": "Morgan McKinley", "job_title": "Investigator, Very Large Company", "description": "Job Responsibilities:\n\nManage daily operations\u00a0of website\nParticipate in the development of Omni-channel strategies\nUpdate various project progress on daily/weekly basis with reporting and logging duties\nCommunicate with 3rd\u00a0party vendors for project updates\nAssist in various E-commerce project developments and perform quality check on testing environment\nMaintain, update and publish 3rd party marketplace content including products description and image\nGenerate sales report and perform marketing research for management review\nSupport E-commerce team on departmental administration\nAssist in ad hoc duties as assigned\u00a0by the supervisor\n\nJob Requirements:\n\nUniversity graduate in E-commerce, Business or related discipline\n2 years solid E-commerce experience, preferably from retail industry\nFundamental knowledge and experience in Magento\u00a0will be an advantage along with web analytical tools, E-commerce platforms and payment gateways, i.e. Google Analytics & PayPal\nProficiency in MS Office applications (Excel, Word, PowerPoint and Chinese Word Processing)\nSelf-motivated and able to work under pressure\nCustomer-oriented, Good team spirit and good communication skill\nGood level of spoken and written English, Chinese and Mandarin\nCandidate with more experience will be considered as Officer\n\nWe offer an attractive package commensurate with your qualifications and experience. Please apply with full resume, present and expected salary, quoting the ref. no. to the Human Resources Department, Pricerite Home Limited, 28/F Manhattan Place, 23 Wang Tai Road, Kowloon Bay, Kowloon, HK; or fax to 2820 0651 or press \"APPLY NOW\"\n\nAll information provided by applicants will be treated in strict confidentiality and used for recruitment purpose only. We will retain your application for a maximum period of 6 months and may refer it to other vacancies within the Group.", "employment_types": ["Full Time", "Permanent"], "selling_points": ["Very Large Company", "Exposure to Various Large Projects", "Great Exposure"], "locations": ["Not Specified"], "categories": ["Professional Services", "Business Consultancy", "Banking / Finance", "Risk Management", "E-commerce", "Others"], "post_time": "2022-01-03T06:15:55Z", "salary": {"currency": null, "max": null, "min": null, "period": "monthly", "term": null}, "salary_visible": false, "title_keywords": [], "responsibilities": ["website", "marketing research", "maintain", "e-commerce project", "management review", "administration", "ad hoc duties", "sales report", "support e-commerce team", "project progress", "testing environment", "manage daily operations", "3rd party vendors", "quality check", "products description and image", "3rd party marketplace content", "reporting and logging duties", "communicate with", "project updates", "omni-channel strategies"], "requirements": {"degrees": ["university graduate"], "majors": ["business", "e-commerce"], "languages": ["english", "chinese", "mandarin"], "language_level": ["proficiency", "good"], "hard_skills": ["google analytics", "excel", "chinese word processing", "web", "e-commerce", "word", "powerpoint", "ms office"], "soft_skills": ["self-motivated", "team spirit", "communication skill", "customer-oriented", "work under pressure"], "languages_combined": [{"language": "english", "language_level": ["good"]}, {"language": "chinese", "language_level": ["proficiency", "good"]}, {"language": "mandarin", "language_level": ["good"]}]}, "experience_required": {"duration": ["2 years"], "field": ["retail industry", "analytical", "e-commerce"]}}, {"job_id": "100003009006311", "location_code": "hk", "company": "AM730 Media Limited", "job_title": "\u591a\u5a92\u9ad4\u7de8\u8f2f", "description": "This company is a leading company with a strong presence and growth. They are looking for an Investigator to join their team.\n\nResponsibilities\n\nBe responsible for different types of investigations including but not limited to employee misconduct, integrity, fraud, bribery and corruption\nCarry out investigations through reviewing evidence and interviewing potential witnesses and suspects\nWrite investigation reports\nLiaise with Law Enforcement Agencies on requests for information\nAssist in the identifying integrity threats from patterns, trends, and criminal organisations that may pose financial crime risks to the company\nCollect and analyse relevant information/data and compile relevant reports in summarising the findings of threats to integrity with sound recommendations\n\nRequirements\n\nBachelor's degree holder\nA minimum of 4-6 years of experience in investigation\nPreviously experience in law enforcement agencies/government is preferred\nFluency in spoken and written English and Cantonese\n\nTo apply online, please click the \"Apply\" button below. For a confidential discussion about this role, please contact David Yung on +3907 3932 or dyung@morganmckinley.com", "employment_types": ["Full Time", "Permanent"], "selling_points": ["\u591a\u5a92\u9ad4\u5e73\u53f0\u7de8\u63a1\u5de5\u4f5c", "\u63a1\u8a2a;\u5beb\u7a3f", "\u7de8\u8f2f;\u6821\u5c0d"], "locations": ["Wan Chai"], "categories": ["Media & Advertising", "Editorial / Journalism", "Print Media", "E-commerce", "Others"], "post_time": "2021-12-29T08:06:45Z", "salary": {"currency": null, "max": null, "min": null, "period": "monthly", "term": null}, "salary_visible": false, "title_keywords": [], "responsibilities": ["relevant reports", "data", "investigation", "reports", "liaise with", "analyse"], "requirements": {"degrees": ["bachelor", "degree holder"], "majors": [], "languages": ["cantonese", "english"], "language_level": ["fluency"], "hard_skills": [], "soft_skills": [], "languages_combined": [{"language": "cantonese", "language_level": ["fluency"]}, {"language": "english", "language_level": ["fluency"]}]}, "experience_required": {"duration": ["minimum of 4-6 years"], "field": []}}, {"job_id": "100003009001219", "location_code": "hk", "company": "91App HK Limited", "job_title": "Customer Service and Operation Officer (Ecommerce) (2 Positions Open)", "description": "\u7368\u7acb\u8ca0\u8cac\u591a\u5a92\u9ad4\u5e73\u53f0\u7de8\u63a1\u5de5\u4f5c\uff0c\u5305\u62ec\u63a1\u8a2a\u3001\u5beb\u7a3f\u3001\u7de8\u8f2f\u53ca\u6821\u5c0d\u7b49\u5de5\u4f5c\n\n\u5165\u8077\u8981\u6c42\n\n\n\n\u5927\u5b78\u7a0b\u5ea6\uff0c\u4e3b\u4fee\u8a9e\u6587\u6216\u65b0\u805e\u7cfb\u512a\u5148\u8003\u616e\n\u4e2d\u82f1\u6587\u826f\u597d\n2-3\u5e74\u7de8\u63a1\u7d93\u9a57\n\u5177\u63a1\u8a2a\u5de5\u4f5c\u7d93\u9a57\u512a\u5148\u8003\u616e\n\u61c2\u651d\u5f71\u3001\u6709\u5a92\u9ad4\u77ed\u7247\u6216\u5177\u5099\u57fa\u672cPhotoshop\u6280\u5de7\u512a\u5148\u8003\u616e\n\u9700\u5047\u671f\u8f2a\u73ed\u5de5\u4f5c\n\u826f\u597d\u6e9d\u901a\u53ca\u7368\u7acb\u8655\u4e8b\u80fd\u529b\n\u4e3b\u52d5\u7a4d\u6975\uff0c\u5177\u8cac\u4efb\u611f\u53ca\u80fd\u5728\u58d3\u529b\u4e0b\u5de5\u4f5c\n\n\u6211\u5011\u63d0\u4f9b\u6bcf\u5468\u4e94\u5929\u5de5\u4f5c\u53ca\u512a\u539a\u5f85\u9047\uff0c\u6709\u610f\u8005\u8acb\u5c07\u500b\u4eba\u5c65\u6b77\u8868\u3001\u8981\u6c42\u5f85\u9047\u53ca\u53ef\u5230\u8077\u65e5\u671f\u96fb\u90f5\u81f3\u672c\u516c\u53f8\u4eba\u529b\u8cc7\u6e90\u90e8\n\n\u7533\u8acb\u4eba\u6240\u63d0\u4f9b\u7684\u5168\u90e8\u8cc7\u6599\u7d55\u5c0d\u4fdd\u5bc6\u53ca\u53ea\u4f5c\u62db\u8058\u7528\u9014\u3002", "employment_types": ["Full Time"], "selling_points": [], "locations": ["Kwun Tong Area"], "categories": ["Sales, CS & Business Devpt", "Customer Service - Supervisor / Officer", "Others", "E-commerce", "Others"], "post_time": "2021-12-28T01:53:09Z", "salary": {"currency": null, "max": null, "min": null, "period": "monthly", "term": null}, "salary_visible": false, "title_keywords": ["operation officer", "customer service"], "responsibilities": [], "requirements": {"degrees": [], "majors": [], "languages": [], "language_level": [], "hard_skills": [], "soft_skills": [], "languages_combined": []}, "experience_required": {"duration": [], "field": []}}, {"job_id": "100003009006308", "location_code": "hk", "company": "AM730 Media Limited", "job_title": "\u6e2f\u805e\u8a18\u8005", "description": "At Texpert.com, we target to improve individual abilities and grow the business at the same time as a team. We are looking for motivated people, who are comfortable to work in a flexible early start-up environment. If you enjoy working with a young and energetic team, you are welcome to join us and be a core member of our digital team.\n\nResponsibilities:\n\nManage daily operation, price update, order processing support, operation tasks, invoices, and reports follow-up\n\nResponsible for uploading & maintenance of all listed products;\n\nWork closely with business developing department including product listings, verifying contracts and orders\n\nLiaise both internal and external parties day-to-day business operations to enhance workflow efficiency\n\nPerform ad-hoc operation tasks and projects as assigned\n\nSkills and Requirements:\n\nDiploma or above in E-Commerce, Business Administration & Marketing would be a big advantage\n\n1 year or above relevant working experience\n\nGood organization, attention to detail, good time management, and self-initiative\n\nBasic knowledge in Excel, Word or related tools\n\nProficient in both written and spoken English and Chinese\n\nHigh level of flexibility and adaptability with good problem-solving skills.\n\nFresh graduates will also be considered", "employment_types": ["Full Time", "Permanent"], "selling_points": ["\u63a1\u8a2a\u3001\u5beb\u7a3f\u3001\u7de8\u8f2f\u53ca\u6821\u5c0d", "\u6709\u8208\u8da3\u7de8\u63a1\u672c\u5730\u65b0\u805e", "\u61c2\u651d\u5f71"], "locations": ["Wan Chai"], "categories": ["Media & Advertising", "Editorial / Journalism", "Print Media", "E-commerce", "Others"], "post_time": "2021-12-29T08:06:25Z", "salary": {"currency": null, "max": null, "min": null, "period": "monthly", "term": null}, "salary_visible": false, "title_keywords": [], "responsibilities": ["liaise", "ad-hoc", "invoices", "maintenance", "contracts", "operations", "internal and external parties", "daily operation", "developing", "product listings", "reports", "order processing"], "requirements": {"degrees": ["diploma or above"], "majors": ["marketing", "business administration", "e-commerce"], "languages": ["english", "chinese"], "language_level": ["proficient"], "hard_skills": ["excel", "basic", "e-commerce", "word", "problem-solving skills"], "soft_skills": ["self-initiative", "adaptability", "attention to detail", "problem-solving skills", "time management"], "languages_combined": [{"language": "english", "language_level": ["proficient"]}, {"language": "chinese", "language_level": ["proficient"]}]}, "experience_required": {"duration": ["1 year"], "field": ["relevant working experience"]}}, {"job_id": "100003009014163", "location_code": "hk", "company": "Newide Trading Limited", "job_title": "\u96fb\u5668\u92b7\u552e\u54e1**", "description": "\u5165\u8077\u8981\u6c42:\u00a0 \u00a0\n\n\n\u00a0\u00a0\u00a0 \u5927\u5b78\u7a0b\u5ea6\uff0c\u4e3b\u4fee\u8a9e\u6587\u6216\u65b0\u805e\u7cfb\u512a\u5148\u8003\u616e\n\u00a0\u00a0\u00a0 \u4e2d\u82f1\u6587\u826f\u597d\n\u00a0\u00a0\u00a0 \u6709\u8208\u8da3\u7de8\u63a1\u672c\u5730\u65b0\u805e\n\u00a0\u00a0\u00a0 \u5177\u63a1\u8a2a\u5de5\u4f5c\u7d93\u9a57\u512a\u5148\u8003\u616e\n\u00a0\u00a0\u00a0 \u61c2\u651d\u5f71\u70ba\u4f73\n\u00a0\u00a0\u00a0 \u826f\u597d\u6e9d\u901a\u53ca\u7368\u7acb\u8655\u4e8b\u80fd\u529b\n\u00a0\u00a0\u00a0 \u4e3b\u52d5\u7a4d\u6975\uff0c\u5177\u8cac\u4efb\u611f\u53ca\u80fd\u5728\u58d3\u529b\u4e0b\u5de5\u4f5c\n\n\u6211\u5011\u63d0\u4f9b\u6bcf\u5468\u4e94\u5929\u5de5\u4f5c\u53ca\u512a\u539a\u5f85\u9047\uff0c\u6709\u610f\u8005\u8acb\u6309\u201cAPPLY NOW\u201d\u63d0\u4ea4\u7533\u8acb\uff0c\u4e26\u5c07\u500b\u4eba\u5c65\u6b77\u8868\u3001\u8981\u6c42\u5f85\u9047\u53ca\u53ef\u5230\u8077\u65e5\u671f\u50b3\u81f3\u672c\u516c\u53f8\u4eba\u529b\u8cc7\u6e90\u90e8\u6536\u3002\u00a0\n\n\u7533\u8acb\u4eba\u6240\u63d0\u4f9b\u7684\u5168\u90e8\u8cc7\u6599\u7d55\u5c0d\u4fdd\u5bc6\u53ca\u53ea\u4f5c\u62db\u8058\u7528\u9014\u3002", "employment_types": ["Full Time"], "selling_points": [], "locations": ["Tuen Mun Area"], "categories": ["Admin & HR", "Clerical / Admin Staff", "Sales, CS & Business Devpt", "Retail Sales", "E-commerce", "Others"], "post_time": "2022-01-03T03:06:28Z", "salary": {"currency": null, "max": null, "min": null, "period": "monthly", "term": null}, "salary_visible": false, "title_keywords": [], "responsibilities": [], "requirements": {"degrees": [], "majors": [], "languages": [], "language_level": [], "hard_skills": [], "soft_skills": [], "languages_combined": []}, "experience_required": {"duration": [], "field": []}}, {"job_id": "100003008999939", "location_code": "hk", "company": "Yue Hwa Chinese Products Emporium Ltd", "job_title": "\u7db2\u8cfc\u8ddf\u55ae\u5009\u52d9\u54e1", "description": "What you do:\n- Manage customers delivery and ensure correctness in inventory\n- Support product enquiry and suggestion from sales team\n- Provide monthly sales and inventory reports to partnered suppliers\n- Manage product data in system\nWhat you need:\n- Loved to explore different wine and spirits products\n- Well structured and sophisticated in Microsoft Suite especially Excel\n- Motivated,\u00a0independent,\u00a0good\u00a0team\u00a0player and good interpersonal skill\n- Proficiency\u00a0in\u00a0written\u00a0and\u00a0spoken\u00a0English\u00a0and\u00a0Chinese\nWhat you get:\n- Experience to work with a broad portfolio of wine and spirits importers both in Hong Kong and Oversea\n- Train your palate and explore a variety of wine and spirits with in-house and customer tastings\n- Work in a cozy team with a dynamic environment\nInterested candidate please send your resume to talent @ myicellar.com with expected salary", "employment_types": ["Full Time"], "selling_points": ["\u7db2\u8cfc", "\u5009\u52d9", "\u7db2\u5e97"], "locations": ["Yau Ma Tei"], "categories": ["Sales, CS & Business Devpt", "Retail Sales", "E-commerce", "Supply Chain", "Others"], "post_time": "2021-12-29T01:44:42Z", "salary": {"currency": null, "max": null, "min": null, "period": "monthly", "term": null}, "salary_visible": false, "title_keywords": [], "responsibilities": ["inventory", "sales team", "reports", "data"], "requirements": {"degrees": [], "majors": [], "languages": ["english", "chinese"], "language_level": ["proficiency"], "hard_skills": ["excel", "dynamic"], "soft_skills": ["sophisticated", "good team player", "dynamic environment", "independent", "interpersonal skill", "motivated", "structured"], "languages_combined": [{"language": "english", "language_level": ["proficiency"]}, {"language": "chinese", "language_level": ["proficiency"]}]}, "experience_required": {"duration": [], "field": []}}, {"job_id": "100003009003925", "location_code": "hk", "company": "MyiCellar Limited", "job_title": "Operation Executive", "description": "We would like to invite high calibre, capable, energetic individuals to join our office in Tsim Sha Tsui:\n\nRequirements and preferred attributes:\n\nSkillful computer appliance\nReasonable communication skills\nSmart with good common sense\nGood analytical and observation skills\nQuick learner\nActive team player\nGood sense of computer hardware will be an advantage but not essential\nCandidates with good sense on photography will be an advantage but not essential\n\nHK$15,000 - 20,000 /month\nSalary will commensurate with qualifications and experience.\n5-Day work week\n\nGreat opportunity for freshers or experienced individuals to start or restart their career in Diamond Industry. Interested party please click the \"Apply-Now\".", "employment_types": ["Full Time", "Part Time"], "selling_points": ["Latest trend with e-commerce", "Cozy team with dynamic environment", "Broad exposure of wine and spirits products"], "locations": ["Quarry Bay"], "categories": ["Hospitality / F & B", "Food & Beverage", "Sales, CS & Business Devpt", "Retail Sales", "E-commerce", "Others"], "post_time": "2021-12-28T12:15:26Z", "salary": {"currency": null, "max": null, "min": null, "period": "monthly", "term": null}, "salary_visible": false, "title_keywords": ["operation executive"], "responsibilities": ["communication", "hardware"], "requirements": {"degrees": [], "majors": [], "languages": [], "language_level": [], "hard_skills": ["hardware"], "soft_skills": ["communication skills", "capable", "quick learner", "energetic", "team player", "active"], "languages_combined": []}, "experience_required": {"duration": [], "field": []}}, {"job_id": "100003009005530", "location_code": "hk", "company": "SIT Imaging Technologies Limited", "job_title": "Operation Executive", "description": "\u5165\u8077\u8981\u6c42:\u00a0 \u00a0\n\n\n\u00a0\u00a0\u00a0 \u5927\u5b78\u7a0b\u5ea6\uff0c\u4e3b\u4fee\u8a9e\u6587\u6216\u65b0\u805e\u7cfb\u512a\u5148\u8003\u616e\n\u00a0\u00a0\u00a0 \u4e2d\u82f1\u6587\u826f\u597d\n\u00a0\u00a0\u00a0 \u6709\u8208\u8da3\u7de8\u63a1\u8ca1\u7d93\u53ca\u5730\u7522\u65b0\u805e\n\u00a0\u00a0\u00a0 \u5177\u63a1\u8a2a\u5de5\u4f5c\u7d93\u9a57\u512a\u5148\u8003\u616e\n\u00a0\u00a0\u00a0 \u61c2\u651d\u5f71\u70ba\u4f73\n\u00a0\u00a0\u00a0 \u826f\u597d\u6e9d\u901a\u53ca\u7368\u7acb\u8655\u4e8b\u80fd\u529b\n\u00a0\u00a0\u00a0 \u4e3b\u52d5\u7a4d\u6975\uff0c\u5177\u8cac\u4efb\u611f\u53ca\u80fd\u5728\u58d3\u529b\u4e0b\u5de5\u4f5c\n\n\u6211\u5011\u63d0\u4f9b\u6bcf\u5468\u4e94\u5929\u5de5\u4f5c\u53ca\u512a\u539a\u5f85\u9047\uff0c\u6709\u610f\u8005\u8acb\u6309\u201cAPPLY NOW\u201d\u63d0\u4ea4\u7533\u8acb\uff0c\u4e26\u5c07\u500b\u4eba\u5c65\u6b77\u8868\u3001\u8981\u6c42\u5f85\u9047\u53ca\u53ef\u5230\u8077\u65e5\u671f\u50b3\u81f3\u672c\u516c\u53f8\u4eba\u529b\u8cc7\u6e90\u90e8\u6536\u3002\u00a0\n\n\u7533\u8acb\u4eba\u6240\u63d0\u4f9b\u7684\u5168\u90e8\u8cc7\u6599\u7d55\u5c0d\u4fdd\u5bc6\u53ca\u53ea\u4f5c\u62db\u8058\u7528\u9014\u3002", "employment_types": ["Full Time", "Permanent"], "selling_points": ["Operation Executive", "HKD $15,000 - HKD $20,000", "5 days work"], "locations": ["Tsim Sha Tsui"], "categories": ["Information Technology (IT)", "Others", "Media & Advertising", "Photography / Video", "E-commerce", "Others"], "post_time": "2021-12-29T03:59:58Z", "salary": {"currency": "HKD", "max": 19999, "min": 14000, "period": "monthly", "term": null}, "salary_visible": true, "title_keywords": ["operation executive"], "responsibilities": [], "requirements": {"degrees": [], "majors": [], "languages": [], "language_level": [], "hard_skills": [], "soft_skills": [], "languages_combined": []}, "experience_required": {"duration": [], "field": []}}, {"job_id": "100003009006317", "location_code": "hk", "company": "AM730 Media Limited", "job_title": "\u8ca1\u7d93\u53ca\u5730\u7522\u8a18\u8005", "description": "Job\u00a0Duties:\u00a0\n\nLiaison with auditors and banks for overall finance & accounting operations, including daily accounting work, internal control, budgeting\nPrepare the accounting functions of the\u00a0Group's SEA companies\nAssist financial costing and variance analysis and provide\u00a0advice to management\nAdvise management on policies, procedures and internal controls\u00a0over business processes\nPerform ad hoc assignments as required\n\nJob Requirements:\u00a0\u00a0\n\nDegree holder in Accounting or related disciplines\nQualified Accountant or equivalent would be an advantage\nAt least 5 years\u2019 or above work experience in accounting and financial reporting\n\u00a0 (relevant work experience in e-commerce is an advantage)\nGood command of English, Chinese and Mandarin\nProficient in MS Office including Word, Excel and PowerPoint\nSelf-motivated, detail-oriented and with good communication skills\n\nWe offer attractive remuneration with excellent career opportunities to the right candidate. Interested parties please apply with\u00a0detailed resume stating present and expected salaries\u00a0to the Human Resources Department by email.\n\nPersonal data will be used for recruitment purpose only.\u00a0", "employment_types": ["Full Time", "Permanent"], "selling_points": ["\u63a1\u8a2a\u3001\u5beb\u7a3f\u3001\u7de8\u8f2f\u53ca\u6821\u5c0d", "\u6709\u8208\u8da3\u7de8\u63a1\u8ca1\u7d93\u53ca\u5730\u7522\u65b0\u805e", "\u61c2\u651d\u5f71"], "locations": ["Wan Chai"], "categories": ["Media & Advertising", "Editorial / Journalism", "Print Media", "E-commerce", "Others"], "post_time": "2021-12-29T08:08:14Z", "salary": {"currency": null, "max": null, "min": null, "period": "monthly", "term": null}, "salary_visible": false, "title_keywords": [], "responsibilities": ["management", "operations", "daily accounting work", "budgeting", "policies", "procedures", "variance analysis", "provide advice", "ad hoc assignments", "internal control"], "requirements": {"degrees": ["degree holder"], "majors": ["related disciplines", "accounting"], "languages": ["english", "chinese", "mandarin"], "language_level": ["good command"], "hard_skills": ["excel", "e-commerce", "word", "powerpoint", "ms office"], "soft_skills": ["communication skills", "self-motivated", "detail-oriented"], "languages_combined": [{"language": "english", "language_level": ["good command"]}, {"language": "chinese", "language_level": ["good command"]}, {"language": "mandarin", "language_level": ["good command"]}]}, "experience_required": {"duration": ["at least 5 years"], "field": ["accounting", "e-commerce", "financial"]}}, {"job_id": "100003009008072", "location_code": "hk", "company": "BAOZUN HONGKONG LIMITED", "job_title": "Finance BP (e-Commerce)", "description": "We are fast-growing company. To facilitate our increasing customer base, we are looking for a professional and customer-centric individual to join our growing team.\n\nResponsibilities\n\nHandle general service enquiry and complaints from customers via phone, email and other platforms\nProvide excellent user experience for our customers\nFollow up after-sales service including but not limited to delivery, order cancel and refund, etc\nResponsible for ad hoc assignment if required\n\nRequirements\n\nAt least 1 years experience in customer service\nEcommerce operation experience will be an advantage\nGood command in both English and Chinese\nProficient in Chinese word processing\nGood telephone manner, customer-oriented and pleasant personality\nCan work independently\nImmediately available preferred\n\nWe offer\n\n5-day work week\nPerformance bonus\nMedical coverage\nBirthday leave\nStaff purchase discount\nFree food and snacks\nA fun working environment!\n\nInterested candidates please email your resume, expected salary and availability to bobowong[at]91app.com (or click \"Apply Now\" button)\n\n\nWe offer equal opportunity.\u00a0Personal information submitted by job applicants will only be used for recruitment purposes.", "employment_types": ["Full Time", "Permanent"], "selling_points": [], "locations": ["Kwun Tong"], "categories": ["Banking / Finance", "Corporate Finance", "E-commerce", "Others"], "post_time": "2021-12-30T06:37:58Z", "salary": {"currency": null, "max": null, "min": null, "period": "monthly", "term": null}, "salary_visible": false, "title_keywords": [], "responsibilities": ["general service enquiry", "after-sales service", "ad hoc assignment", "user experience"], "requirements": {"degrees": [], "majors": [], "languages": ["english", "chinese"], "language_level": ["good command", "proficient"], "hard_skills": ["chinese word processing"], "soft_skills": ["work independently", "pleasant", "customer-oriented", "customer service", "telephone manner"], "languages_combined": [{"language": "english", "language_level": ["good command"]}, {"language": "chinese", "language_level": ["good command", "proficient"]}]}, "experience_required": {"duration": ["at least 1 years"], "field": ["ecommerce", "operation", "customer service"]}}, {"job_id": "100003009003950", "location_code": "hk", "company": "The Floristry", "job_title": "Customer Service & Operations Assistant", "description": "\n\u8077\u8cac :\u8ca0\u8cac\u92b7\u552e\u5bb6\u5ead\u96fb\u5668\n\n\u8cc7\u6b77 :\u4e2d\u4e09\u7a0b\u5ea6; \u826f\u597d\u7cb5\u8a9e; \u4e00\u822c\u666e\u901a\u8a71; \u4e00\u822c\u82f1\u8a9e; \u61c2\u95b1\u8b80\u4e2d\u6587\n\n\u5f85\u9047 :\u6bcf\u6708$10,000 - $12,000, \u6709\u52e4\u5de5\u734e\u91d1 \u53ca\u4f63\u91d1, \u661f\u671f\u4e00\u81f3\u516d: \u4e0a\u53489\u6642\u81f3\u4e0b\u53485\u6642\u534a, \u6bcf\u9031\u5de5\u4f5c5\u5929\u81f36\u5929, \u9577\u77ed\u9031\n\n\u7533\u8acb\u9808\u77e5 :\u6c42\u8077\u8005\u53ef\u96fb\u90f5(Apply Now)\u5c65\u6b77\u8868\u7d66\u65b0\u5eb7\u8cbf\u6613\u6709\u9650\u516c\u53f8\u3002\u5982\u8981\u7d22\u53d6\u6536\u96c6\u500b\u4eba\u8cc7\u6599\u8072\u660e, \u8acb\u8207\u5468\u5c0f\u59d0(Email)\u806f\u7d61\u3002\n\n", "employment_types": ["Full Time"], "selling_points": ["Friendly & able to work under pressure", "1+ year customer service experience", "5 days work week (including weekends)"], "locations": ["Sheung Wan"], "categories": ["Admin & HR", "Clerical / Admin Staff", "Sales, CS & Business Devpt", "Customer Service - Supervisor / Officer", "E-commerce", "Others"], "post_time": "2021-12-28T12:51:09Z", "salary": {"currency": null, "max": null, "min": null, "period": "monthly", "term": null}, "salary_visible": false, "title_keywords": ["customer service", "operations assistant"], "responsibilities": [], "requirements": {"degrees": [], "majors": [], "languages": [], "language_level": [], "hard_skills": [], "soft_skills": [], "languages_combined": []}, "experience_required": {"duration": [], "field": []}}, {"job_id": "100003009006356", "location_code": "hk", "company": "Kicks-Crew Company Limited", "job_title": "Data entry", "description": "The Floristry is Hong Kong's leading floral lifestyle brand. We celebrate wild-inspired living and offer a curated assortment of flowers, homeware and lifestyle objects with a newly opened store and coffee bar in central.\n\nWe're currently on the look out for a friendly and organised customer service & operations assistant to help chat with our customers and ensure smooth operations.\u00a0We are expanding rapidly and in exchange for your passion for the brand we offer excellent career progression.\n\n\nRESPONSIBILITIES\n\nCustomer Service\n\nOversee customer queries and complaints via all touch points including email, social media, phone, chat and WhatsApp.\nEnsure high standards of customer service are delivered at all times.\nHandle customer complaints, provide appropriate solutions and alternatives within the time limits; follow up to ensure resolution.\nFollow communication procedures, guidelines and policies.\nTake the extra mile to engage customers.\n\nOperations\n\nBook and track couriers to ensure timely delivery of all our products to customers.\nDevelop a strong relationship with courier company to ensure smooth delivery of all orders.\nWork closely with the florist team to ensure smooth running.\nEnsure daily operations run smoothly and continue to improve daily processes.\nOversee cash balances ensuring petty cash is balanced and receipts submitted monthly.\nContribute to the company\u2019s growth by constantly thinking of ways to improve operations and customer satisfaction.\n\nREQUIRMENTS\n\nHave excellent verbal and written English and Chinese.\n\n+1 years experience in a customer facing role.\nOrganised and able to working in a fast paced environment.\nExcellent communication and presentation skills.\nAbility to multi-task, prioritize, and manage time effectively.\nNeed to work on Saturdays and Sundays.\nThere will be overtime during peak seasons.\nInterested candidates please submit your CV with expected salary by clicking Apply Now!", "employment_types": ["Full Time"], "selling_points": [], "locations": ["Tsuen Wan Area"], "categories": ["E-commerce", "Others"], "post_time": "2021-12-29T08:19:56Z", "salary": {"currency": "HKD", "max": 13999, "min": 11000, "period": "monthly", "term": null}, "salary_visible": true, "title_keywords": [], "responsibilities": [], "requirements": {"degrees": [], "majors": [], "languages": [], "language_level": [], "hard_skills": [], "soft_skills": [], "languages_combined": []}, "experience_required": {"duration": [], "field": []}}, {"job_id": "100003009006111", "location_code": "hk", "company": "Pear & Carrot Limited", "job_title": "Trade & Operations Assistant / Clerk (F&B)", "description": "\u8077\u8cac\uff1a\n\n\u4e00\u822c\u5009\u52d9\u5de5\u4f5c\uff0c\u5982\u6536\u8ca8\u3001\u9ede\u8ca8\u3001\u4e0a\u67b6\u3001\u57f7\u8ca8\u3001\u5305\u88dd\u3001\u76e4\u9ede\u5b58\u8ca8\u7b49\uff1b\n\u4e00\u822c\u96fb\u8166\u6587\u66f8\u8655\u7406\u53ca\u8cc7\u6599\u8f38\u5165\u3002\n\n\u00a0\u8981\u6c42\uff1a\n\n\u52e4\u5feb\u3001\u8a8d\u771f\u3001\u7d30\u5fc3\uff1b\n\u6709\u7db2\u8cfc\u6216\u8ca8\u5009\u7d93\u9a57\uff1b\n\u53ef\u5373\u6642\u4e0a\u73ed\u8005\u512a\u5148\u3002\u00a0\n\u2022\u00a0\u5de5\u4f5c\u6642\u9593\uff1a\u661f\u671f\u4e00\u81f3\u516d 9:30am\u00a0\u2013\u00a06:30pm;\u00a0\u661f\u671f\u65e5\u4f11\u606f;\u53e6\u6bcf\u6708\u984d\u5916\u4e00\u5929\u8f2a\u4f11;\n\u2022 \u4f50\u6566\u5340\u5de5\u4f5c;\u5ba4\u5167\u6709\u51b7\u6c23;\n\u2022 \u6709\u610f\u53ef\u9023\u540c\u5c65\u6b77\u8868\u6309APPLY NOW\u7533\u8acb, \u67e5\u8a62\u96fb\u8a71: 3511 2222;\n\u2022\u00a0\u54e1\u5de5\u8cfc\u7269\u512a\u60e0\u3001\u91ab\u7642\u798f\u5229\u3001\u5728\u8077\u57f9\u8a13\u3001\u5347\u8077\u6a5f\u6703\u3001\u6709\u85aa\u5047\u671f\u53ca\u52de\u5de5\u5047\u3002\n\n\nYue Hwa Online Shop:\u00a0https://zh.shop.yuehwa.com/", "employment_types": ["Full Time"], "selling_points": ["Work Life Balance", "5 working days per week", "Fresh graduates welcome!"], "locations": ["Shatin Area"], "categories": ["Admin & HR", "Clerical / Admin Staff", "E-commerce", "Others"], "post_time": "2021-12-29T07:06:07Z", "salary": {"currency": "HKD", "max": 16999, "min": 14000, "period": "monthly", "term": null}, "salary_visible": true, "title_keywords": ["clerk", "operations assistant"], "responsibilities": [], "requirements": {"degrees": [], "majors": [], "languages": [], "language_level": [], "hard_skills": [], "soft_skills": [], "languages_combined": []}, "experience_required": {"duration": [], "field": []}}, {"job_id": "100003009003948", "location_code": "hk", "company": "The Floristry", "job_title": "Full-time Florist", "description": "Responsibilities:\n\nHandle data entries\nReport to supervisor if necessary\nAssist in ad-hoc assignments as required\n\nRequirements:\n\nHKDSE, undergraduates and fresh graduates are all welcomed\nResponsible, detail-minded and self-motivated\nProficient in MS Office including MS Word, MS Excel and Chinese word processing\nWPM 40-60", "employment_types": ["Full Time"], "selling_points": ["Creative Florist", "Excellent career progression opportunities", "Creative environment"], "locations": ["Sheung Wan"], "categories": ["Others", "Agriculture / Forestry / Fishing", "Design", "Others", "E-commerce", "Others"], "post_time": "2021-12-28T12:50:24Z", "salary": {"currency": null, "max": null, "min": null, "period": "monthly", "term": null}, "salary_visible": false, "title_keywords": [], "responsibilities": ["report", "ad-hoc assignments", "data"], "requirements": {"degrees": ["hkdse"], "majors": [], "languages": ["chinese"], "language_level": ["proficient"], "hard_skills": ["ms word", "ms excel", "chinese word processing", "ms office"], "soft_skills": ["detail-minded", "self-motivated", "responsible"], "languages_combined": [{"language": "chinese", "language_level": ["proficient"]}]}, "experience_required": {"duration": [], "field": []}}, {"job_id": "100003008997758", "location_code": "hk", "company": "Aware & Trustful (HK) Co., Limited", "job_title": "e-Commerce Executive", "description": "We are a SME, with an international team of about 15 people.We are a responsible and sincere employer who is looking for candidates with the same thought and long-term commitment. Please read the salary range below to ensure it is within your expectation. Please DO state your Last Salary, Expected Salary and Notice Period in your CV.\n\nMain responsibilities:\n- General business support for our different business units\n- Food trading related tasks\n- Document preparation\n- Food labelling administration\n- Delivery booking and communication with our suppliers, shipping partners, local warehouses, retail locations and wholesale customers\n- Ad hoc duties as required\n\nRemuneration Package:\n- Nordic-style working environment\n- 9:00 am to 6:00 pm, 5-day work\n- Standard HK statutory bank holidays plus 12 days of paid annual leave + BIRTHDAY LEAVE\n- Medical Insurance\n- Staff Discount\n\nApplication requirements:\n-\u00a0 Over 1 year\u2019 relevant all-round office administration, secretariat, clerk, e-commerce or project management experience\u00a0\n- Strong sense of responsibility, ownership and common sense\n- Organized, detailed, able to handle multi-tasks effectively and prioritize works to meet schedules/ deadlines\n- Excellent communication, interpersonal and supervisory skills\n- Willing to work beyond office hours and on weekends/holidays to handle/ monitor emergency or ad hoc projects\n- Proficient in written English and Chinese\n\nAlways a Bonus,\n- Any experience from Scandinavia will be considered as an advantage\n- Any experience from F&B will be considered as an advantage\n- Computer savvy, proficiency in MS Office\n\nFresh graduates are welcome!\n\nWorking Location: FOTAN", "employment_types": ["Full Time"], "selling_points": ["e-Commerce", "Know how daily operation", "Know how to draw audiences"], "locations": ["Tsuen Wan Area"], "categories": ["E-commerce", "Others"], "post_time": "2021-12-24T01:29:37Z", "salary": {"currency": null, "max": null, "min": null, "period": "monthly", "term": null}, "salary_visible": false, "title_keywords": ["executive"], "responsibilities": ["ad hoc duties", "shipping", "communication", "booking", "insurance", "administration"], "requirements": {"degrees": [], "majors": [], "languages": ["english", "chinese"], "language_level": ["proficient"], "hard_skills": ["project management", "ms office", "e-commerce"], "soft_skills": ["organized", "multi-tasks", "sense of responsibility", "prioritize", "communication", "project management", "interpersonal", "detailed"], "languages_combined": [{"language": "english", "language_level": ["proficient"]}, {"language": "chinese", "language_level": ["proficient"]}]}, "experience_required": {"duration": ["1 year"], "field": ["office administration", "project management", "f&b", "e-commerce"]}}, {"job_id": "100003009005044", "location_code": "hk", "company": "Aesop", "job_title": "Regional Digital Content Producer", "description": "About Us\nThe Floristry is Hong Kong's leading floral lifestyle brand. We celebrate wild-inspired living and offer a curated assortment of flowers, homeware and lifestyle objects with a newly opened store and coffee bar in central.\n\nWe're currently on the look out for florist to assist with daily operations and seasonal flower designs.\u00a0We are expanding rapidly and in exchange for your passion for the brand we offer excellent career progression.\n\n\n\n\nDaily Operations\n\nAssisting in making bouquets, flower jars and general day-to-day florist duties.\nFloral Design\n\nAssist in designing and creating seasonal floral designs and products in line with The Floristry brand.\nEnsure all products are being made correctly.\nWork with buying team to ensure seasonal flower varieties are ordered and high quality of stock is maintained.\nStyling\n\nAssist in styling flowers on set during video and photoshoots in various locations.\nEnsure all shoot flowers are delivered on time and ready on set.\nStyle monthly product photography in our studio.\nAssist in creating seasonal installations and displays\nREQUIREMENTS\n\n1+ years experience\nStrong\u00a0floral design skills & creative eye.\n\nGood team player and enjoy mentoring junior members of the team.\nCreative and passionate about The Floristry brand.\nHighly organised.\nEnjoy a fast paced start-up environment.\nInterested candidates please submit your CV with expected salary by clicking Apply Now!\n\u00a0", "employment_types": ["Full Time", "Permanent"], "selling_points": ["Site Merchandising and Content Management", "Global and growing retail organisation", "Attractive Benefits"], "locations": ["Central & Western Area"], "categories": ["Design", "Multi-media", "Web Designer", "E-commerce", "Others"], "post_time": "2021-12-29T03:22:37Z", "salary": {"currency": null, "max": null, "min": null, "period": "monthly", "term": null}, "salary_visible": false, "title_keywords": ["producer"], "responsibilities": ["daily operations"], "requirements": {"degrees": [], "majors": [], "languages": [], "language_level": [], "hard_skills": [], "soft_skills": [], "languages_combined": []}, "experience_required": {"duration": [], "field": []}}, {"job_id": "100003009000141", "location_code": "hk", "company": "Hong Kong ECMS International Logistics Co., Limited", "job_title": "Key Account Executive", "description": "e-Commerce executive\nMain Responsibility:\n\u00a0Operating a new start up online shopping platform for premium home\u00a0products.\n\u00a0Execute and implement all online marketing activities and promotions to target consumers.\n\u00a0Define and implement online sales strategy and traffic optimization.\n\u00a0Manage the daily operations of the e-commerce platform functions.\n\u00a0Evaluate customer research, marketing activities, and market information.\n\u00a0Familiar with social media\n\u00a0Work\u00a0with internal and external team\u00a0on digital marketing campaign, including\u00a0SEO/SEM, landing page development\n\u00a0Establish and cultivate strong relationships with key influences\n\u00a0Work with the\u00a0third party\u00a0team ensuring that their work and production maintain a relevant relationship with the brand guidelines.\n\u00a0Handle\u00a0customers\u2019 online orders\u00a0and after-sales support services.\nResponsibilities:\n\u00a0Diploma or Degree in e-commerce/ Digital Marketing/ Communication or related discipline.\n\u00a0Minimum 3 years\u2019 experience working in online business or e-commerce operation\n\u00a0Familiar with current social media trends\n\u00a0Strong interpersonal and negotiation skills, and good attitude for\u00a0customer services.\n\u00a0Driven, self-motivated, result-oriented\n\n", "employment_types": ["Full Time", "Permanent"], "selling_points": [], "locations": ["Lai Chi Kok"], "categories": ["Transportation & Logistics", "Others", "Sales, CS & Business Devpt", "Business Development", "E-commerce", "Others"], "post_time": "2021-12-24T10:05:45Z", "salary": {"currency": null, "max": null, "min": null, "period": "monthly", "term": null}, "salary_visible": false, "title_keywords": ["key account executive"], "responsibilities": ["social media", "market information", "seo", "support services", "customer services", "evaluate", "communication", "daily operations", "maintain", "digital marketing", "brand guidelines", "sem", "e-commerce platform", "third party"], "requirements": {"degrees": ["diploma", "degree"], "majors": ["digital marketing", "e-commerce"], "languages": [], "language_level": [], "hard_skills": ["sales support", "seo", "sem", "e-commerce"], "soft_skills": ["result-oriented", "self-motivated", "communication", "negotiation skills", "interpersonal", "driven"], "languages_combined": []}, "experience_required": {"duration": ["minimum 3 years"], "field": ["operation", "business", "e-commerce"]}}, {"job_id": "100003008995347", "location_code": "hk", "company": "Synergy Marketing (Asia) Limited", "job_title": "E-Commerce Executive", "description": "Job Description Responsibilities:\n\u2022 Responsible for designing promotional materials, such as website and banners\n\u2022 Maintain and update contents at eShop\n\u2022 Prepare contents for eShop and store promotions\n\u2022 Provide eCommerce operations support including system backend management and eShop promotion setup\n\u2022 Develop creative concepts and art designs for marketing collateral, eCommerce & social media content, photo/video production projects, and other communication materials\n\u2022 Align design creation with company/ product identity and needs\n\u2022 Undertake the creation and production of multimedia graphics and videos\n\u2022 Support photo shooting and retouching for online and offline use\nRequirements:\n\u2022 Higher Diploma/Associate Degree or above in Graphic Design, Arts, Visual Arts or related disciplines\n\u2022 Minimum 2 years of relevant working experience\n\u2022 Proficiency in Adobe Photoshop and Illustrator\n\u2022 Knowledge in Adobe Premiere Pro is a plus\n\u2022 Hand-on experience in content management system\n\u2022 Experience in editing or copy writing is an advantage\n\u2022 Immediate available is highly preferred", "employment_types": ["Full Time"], "selling_points": [], "locations": ["Tuen Mun Area"], "categories": ["E-commerce", "Others"], "post_time": "2021-12-23T03:50:33Z", "salary": {"currency": null, "max": null, "min": null, "period": "monthly", "term": null}, "salary_visible": false, "title_keywords": ["executive"], "responsibilities": ["retouching", "management", "video production", "operations", "multimedia graphics and videos", "website", "design", "communication", "banners", "contents", "maintain", "promotional materials", "social media content", "designing", "develop creative concepts", "setup"], "requirements": {"degrees": ["diploma", "degree or above"], "majors": ["related disciplines", "graphic design"], "languages": [], "language_level": [], "hard_skills": ["plus", "adobe photoshop", "illustrator", "adobe premiere pro"], "soft_skills": [], "languages_combined": []}, "experience_required": {"duration": ["minimum 2 years"], "field": ["management", "relevant working experience", "writing", "editing"]}}, {"job_id": "100003008996838", "location_code": "hk", "company": "Delivery Hero Food Hong Kong Limited", "job_title": "Account Management Coordinator", "description": "Job Responsibilities:\n\nHandle different back-end supports on our E-Commerce business.\nProduce different on-line and off-line marketing materials such as graphic/video materials, social media post, web design and photo retouching.\nCreate, design and refine beautiful, elegant, meaningful and high-quality user interfaces, scalable UI components and related interactions.\n\n\u00a0Job Requirements:\n\nFluent in English, Cantonese and Mandarin.\nProficiency in graphic and interactive design tools such as Adobe Creative Suite with AI & Photoshop.\nProficiency in video editing such as Adobe After Effect, Premiere, Finial Cut Pro.\nFamiliar with output and printing, web-site maintenance knowledge in HTML and CSS and software such as wordpress.\nUnderstanding on online and social media is an advantage.\nHardworking, self-motivated, independent, result-oriented and detail minded.\nAble to work under pressure in a fast-paced environment.\nGood analytical skills, strong business acumen, communication and interpersonal skills.", "employment_types": ["Full Time", "Permanent"], "selling_points": ["Great exposure to account management/ e-commerce", "International organizational culture", "Welcome junior candidates"], "locations": ["Sheung Wan"], "categories": ["E-commerce", "Others"], "post_time": "2021-12-23T08:56:32Z", "salary": {"currency": null, "max": null, "min": null, "period": "monthly", "term": null}, "salary_visible": false, "title_keywords": ["coordinator"], "responsibilities": ["social media", "photo retouching", "quality", "design", "marketing materials", "ui"], "requirements": {"degrees": [], "majors": [], "languages": ["cantonese", "english", "mandarin"], "language_level": ["fluent"], "hard_skills": ["web", "ai", "maintenance", "adobe after effect", "premiere", "html", "analytical skills", "video editing", "acumen", "wordpress", "css", "adobe creative suite", "photoshop"], "soft_skills": ["self-motivated", "independent", "fast-paced environment", "analytical skills", "communication and interpersonal skills", "business acumen", "creative", "result-oriented", "hardworking", "work under pressure"], "languages_combined": [{"language": "cantonese", "language_level": ["fluent"]}, {"language": "english", "language_level": ["fluent"]}, {"language": "mandarin", "language_level": ["fluent"]}]}, "experience_required": {"duration": [], "field": []}}, {"job_id": "100003008999490", "location_code": "hk", "company": "Links International", "job_title": "Key Account Manager", "description": "'Hungry to make a difference? Then foodpanda may be the place for you!'\n\nAt foodpanda, we\u2019re on a mission to redefine customers\u2019 food and shopping experience as a multifaceted online platform across the 14 countries we operate in. We\u2019re all about bringing on the smartest and brightest minds as we continue to grow in a fast-moving and agile environment, and hiring those who can thrive in an energetic and hardworking start-up culture. We strive to become everybody\u2019s most loved delivery platform, however, this won't happen without some really awesome people!\n\nWe are looking for a highly-driven and motivated\u00a0Account Management Coordinator\u00a0to join our fun, professional and dedicated\u00a0Commercial Department\u00a0based here in Hong Kong.\u00a0\u00a0Our Commercial Department oversees the end-to-end restaurant partners\u2019 operations and businesses, from partners identification & signing to onboarding & account management, as well as new venture developments.\u00a0If you are a food lover, join us now to make a direct impact and contribute to large-scale success!\u00a0\u00a0\n\nKnow more about the team\n\nOur Account Management team operates under the Commercial Department, which is responsible for relationship management and strategic business planning, such as tailor-made branding and marketing campaigns, with the aim of growing the accounts\u2019 portfolios in order to achieve their business goals!\n\nRoles and Responsibilities\n\nAssist Account Management Team on operations such as Salesforce management, PowerPoint presentation preparation, promotional tool management, support team operations as well as other administrative duties including meeting arrangements\nRegular communication with internal teams and departments, collect and consolidate team requirements accordingly\nClear communication on the progress of monthly/quarterly initiatives\nPerform data analysis and collaborate with business users to provide data insights\nResponsible for the calculation, administration and maintenance of vendor discounts\nExecute and proofread the back-end settings of content displayed on our platform\nWork closely with account managers to identify and resolve quality issues\nGo the \u201cextra mile\u201d and support the team to achieve KPI\nSupport any ad hoc requests from the team\n\nQualifications and Requirements\n\n1-2 year of experience in Sales Supporting and Administrative role\nA detail minded and resilient team player with strong\u00a0authoring, editing and reviewing skills\nStrong numerical sense and analytical skills with good commercial awareness\u00a0\nWork independently with multitasking and organizational skills under specific timeframe\u00a0\nAble to speak, read & write in English and Cantonese fluently, Mandarin will be an advantage\nKnowledge in Chinese Word Processing is mandatory\nKnowledge in the use of MS Office is a must, Salesforce & Tableau will be an advantage\nFresh graduates are also welcome\n\nWhat We Offer\n\nA dynamic, fast paced environment\nA vibrant and international team with diverse background\nSteep learning curve in e-commerce & entrepreneurship\nLearning & development programs and skills trainings\nFlexible working hours and agile company with a flat hierarchical structure\nMonthly staff allowance and corporate discounts including at restaurants, gyms and many more\nAgile office environment with a fully-stocked beverage fridge and self-serve beer\nUnlimited paid leave policy", "employment_types": ["Full Time", "Permanent"], "selling_points": ["UK Listed Technology Company", "Strong data analytic skills", "4-6 years in B2B2C account management"], "locations": ["Not Specified"], "categories": ["Information Technology (IT)", "Others", "Sales, CS & Business Devpt", "Account Servicing", "E-commerce", "Others"], "post_time": "2021-12-24T07:26:06Z", "salary": {"currency": "HKD", "max": 69999, "min": 45000, "period": "monthly", "term": null}, "salary_visible": true, "title_keywords": ["account manager"], "responsibilities": ["collaborate with", "management team", "management", "maintenance", "data", "operations", "ad hoc requests", "teams", "quality", "communication", "data analysis", "administrative duties", "support the team", "administration"], "requirements": {"degrees": [], "majors": [], "languages": ["cantonese", "english", "chinese", "mandarin"], "language_level": ["advantage"], "hard_skills": ["salesforce", "chinese word processing", "tableau", "analytical skills", "ms office"], "soft_skills": ["organizational skills", "team player", "work independently", "analytical skills"], "languages_combined": [{"language": "cantonese", "language_level": []}, {"language": "english", "language_level": []}, {"language": "chinese", "language_level": []}, {"language": "mandarin", "language_level": ["advantage"]}]}, "experience_required": {"duration": ["1-2 year"], "field": ["administrative"]}}]