[{"job_id": "100003009052764", "location_code": "hk", "company": "Konew Financial Express Ltd", "job_title": "Analyst Programmer/Software Developer", "description": "Main Duties & Responsibilities:\n\n\nResponsible for development of latest FinTech systems and enhancement of existing IT systems\nTo participate in the entire System Development Life Cycle (SDLC) for successful project delivery\nTo assist IT Manager in requirement study, analysis, design, documentation and co-ordination with users and operations teams\nProvide support to end users on various business systems\nExplore new technologies and drive for innovation, especially new development tools, new algorithmic code, bring better solution for existing environment\nActive participation on latest company FinTech initiatives\n\nRequirements:\n\n\nDiploma or above in Computer Studies / Computer Science / Information Technology (I.T.) or related disciplines\nProficiency in at least one modern object-oriented programming language\nFast learner and willing to pick up new technology and skill\nHave knowledge in cloud development is an advantage\nAble to work in fast paced environment\nEnergetic, self-motivated, teamwork, dynamic and out of the box thinking\nFresh graduate is welcome. Less experience will be considered as software developer\n\nWe offer:\n\nDiscretionary bonus\nMedical insurance\nDental insurance\nHardship allowance\nCompetitive annual leave days\nBirthday leave\nAnniversary leave\nStudy leave\nMarriage leave\nCompassionate leave\n\nHow to apply:\n\nInterested parties, please send your resume stating your expected salary to Human Capital Department\u00a0by clicking \"APPLY NOW\".\n\n(We are an equal opportunity employer.\u00a0 Personal data collected will be used for recruitment purpose only.\u00a0 The unsuccessful applications will be destroyed after 6 months.)", "employment_types": ["Full Time", "Permanent"], "selling_points": ["Fintech job opportunity", "Development of latest FinTech systems", "Diploma in Computer Studies/Science"], "locations": ["Central"], "categories": ["Information Technology (IT)", "Application Specialist - Software", "Software Development", "E-commerce", "Software Development"], "post_time": "2022-01-17T03:58:51Z", "salary": {"currency": null, "max": null, "min": null, "period": "monthly", "term": null}, "salary_visible": false, "title_keywords": ["analyst programmer", "developer"], "responsibilities": ["provide support", "operations", "analysis", "systems", "teams", "design", "documentation"], "requirements": {"degrees": ["fresh graduate", "diploma or above"], "majors": ["information technology", "computer science", "computer studies"], "languages": [], "language_level": [], "hard_skills": ["dynamic", "programming"], "soft_skills": ["self-motivated", "teamwork", "dynamic", "energetic", "fast learner"], "languages_combined": []}, "experience_required": {"duration": [], "field": ["developer"]}}, {"job_id": "100003009047126", "location_code": "hk", "company": "ANGLO EAST GROUP LTD.", "job_title": "Programmer", "description": "Responsibilities\n\nTo conduct user requirement and objective analysis.\nTo assist in system analysis and design\nTo develop and maintain high quality robust cloud application (eg. NetSuite).\nTo conduct unit test / system test / user acceptance test / integration test to ensure the functionality meet user requirements\nTo provide user support, training and prepare system documentation\nReport to System Analyst Manager\u00a0\n\nRequirements\n\nDiploma in Computer Studies/Computer Science or equivalent\nAt least 2-3 years working exp. in programming, requirement analysis, system integration & solution design\nPassionate and enthusiastic in new technology\nAble to work independently, self-motivated and under pressure\nStrong analytical mind, sense of responsibility, organized, attention to details\nProficiency in HTML/JavaScript is a must\nAPI/System integration experience is preferred\nExperience CRM or ERP experience is advantageous\nKnowledge in Oracle Netsuit & Odoo system is preferred\nFresh graduate will also be considered", "employment_types": ["Full Time", "Permanent"], "selling_points": [], "locations": ["Hung Hom"], "categories": ["Information Technology (IT)", "IT Management", "Product Management / Business Analyst", "E-commerce", "Software Development"], "post_time": "2022-01-14T03:09:58Z", "salary": {"currency": null, "max": null, "min": null, "period": "monthly", "term": null}, "salary_visible": false, "title_keywords": ["programmer"], "responsibilities": ["user requirement", "system documentation", "analysis", "quality", "design", "develop", "maintain", "report"], "requirements": {"degrees": ["diploma", "fresh graduate"], "majors": ["computer science", "computer studies"], "languages": [], "language_level": [], "hard_skills": ["analysis", "html", "erp", "javascript", "programming", "integration", "oracle"], "soft_skills": ["passionate", "organized", "work independently", "self-motivated", "under pressure", "sense of responsibility", "analytical mind", "attention to details", "enthusiastic"], "languages_combined": []}, "experience_required": {"duration": [], "field": []}}, {"job_id": "100003009055725", "location_code": "hk", "company": "FWD Life Insurance Company (Bermuda) Limited", "job_title": "System Analyst (Enterprise Architecture - Cloud & DevOps Team), Information Technology", "description": "Established in Asia in 2013 with a trailblazer mentality, FWD is the primary insurance business of investment group, Pacific Century Group (PCG), with minority shareholders Swiss Re Group, GIC Ventures, RRJ Capital and Hopu Investments.\n\nFWD spans 10 markets in Asia including Hong Kong SAR & Macau SAR, Thailand, Indonesia, the Philippines, Singapore, Vietnam, Japan, Malaysia and Cambodia. In Hong Kong, FWD offers life and medical insurance, general insurance, employee benefits, and financial planning. We focus on creating fresh customer experiences and making the insurance journey simpler, faster and smoother, with innovative propositions and easy-to-understand products, supported by digital technology. Through this customer-led approach, FWD aims to be a leading pan-Asian insurer by changing the way people feel about insurance.\n\nIf you are looking for a company where can fuel your inspiration and cultivate your expertise, join us on our exciting journey.\n\nThe Job\n\nBe a member of Enterprise Architecture & Common Platforms team and report to IT Senior Manager for the Open API, OpenShift, DevOps and Cloud projects\n\nLead and execute the architecture governance frameworks and strategies\n\nDeliver high quality solutions and in compliance with group standard\n\nInteract with stakeholders from various levels to ensure smooth communication\n\nEnsure change requests are well managed and prioritized according the change management control\n\nCoordinate and facilitate the project execution related activities\n\nCoordinate with IT and user team on project implementation arrangement\n\nAd-hoc duties as assigned\n\nThe Person\n\nUniversity degree in Computer Science or equivalent\n\nMinimum 5 years' related working experience in system design and development\n\nExperience in development and implementation on Enterprise Application Architecture solutions\n\nSolid experience in development and implementation in Java, JBOSS, API and DevOps\n\nExperience with AWS / Azure Cloud\n\nExperience in SprintBoot, Node.js, MicroServices and Java Spring is an advantage\n\nGood knowledge of Kubernetes, RPA and software implementation best practices\n\nUnderstanding of Agile/Lean software delivery methodology is preferred, able to work with user departments and vendors\n\nGood problem-solving skills and communication\n\nAble to work under pressure\n\nGood team player, self-initiative and pro-active\n\nWe offer 5-day work, 20-22 days annual leaves, excellent learning & development opportunities and an attractive package to the right candidate.\n\nInformation collected will be treated in strict confidence and used solely for recruitment purpose. The company will retain all applications no longer than 24 months of which will be destroyed thereafter. When there are vacancies in any of our subsidiaries, holding companies, associated or affiliated companies of, or companies controlled by, or under common control with the Company during that period, we may transfer your application to them for consideration of employment. We are an equal opportunity employer. We do not discriminate on the basis of race, sex, disability or family status in employment process.", "employment_types": ["Full Time"], "selling_points": ["Handle Open API, OpenShift, DevOps, Cloud projects", "Exp in Java, JBOSS, API, DevOps, AWS / Azure Cloud", "Permanent, Discretionary Bonus, 20days AL, Medical"], "locations": ["Kwun Tong"], "categories": ["Information Technology (IT)", "Application Specialist - Software", "Software Development", "E-commerce", "Software Development"], "post_time": "2022-01-18T02:53:37Z", "salary": {"currency": null, "max": null, "min": null, "period": "monthly", "term": null}, "salary_visible": false, "title_keywords": ["system analyst"], "responsibilities": [], "requirements": {"degrees": [], "majors": [], "languages": [], "language_level": [], "hard_skills": [], "soft_skills": [], "languages_combined": []}, "experience_required": {"duration": [], "field": []}}, {"job_id": "100003009047611", "location_code": "hk", "company": "Au C\u0153ur du Luxe", "job_title": "Designer (UX/UI)", "description": "The Opportunity\u00a0\n\nJoin a fast-growing company, global leader in the\u00a0EDtech\u00a0for luxury brands, and get access to tremendous career opportunities. Working at ACDL means more than having a job:\u00a0 you will be surrounded by enthusiastic and driven people who do great\u00a0work, and\u00a0have fun while doing so.\u00a0\n\nDesigner (UX/UI)\u00a0is based in our Hong Kong regional office, and is a key position within the Learning & Development team and the marketing team\u00a0\n\nThe role reports into the\u00a0CEO\u00a0and works cross functionally with internal ACDL teams\u00a0\u00a0\n\n\u00a0\nYour role:\u00a0\n\nAct as the main point-of-contact with the\u00a0Technical,\u00a0Training teams\u00a0and designated learning technology provider.\u00a0\n\nProduct design which included all kind of graphic and digital design, and presentation materials\u00a0\u00a0\n\nCreate compelling website and mobile app user interface designs\u00a0\u00a0\n\nTranslate user flow into wireframes,\u00a0mockups, components, and clickable prototypes for website and\u202fmobile application\u00a0\u00a0\n\nCreate a visual identity as reference of all design initiatives\u00a0\u00a0\n\nRequirements\n\nWho are we looking for:\u00a0\u00a0\n\nEnergetic and engaging with a \u2018can do\u2019 attitude, with excellent interpersonal skills\u00a0\n\nHigh level of communication skills both verbal and written\u00a0\n\nCollaborative spirit and influence in a \u201cwin as a team\u201d environment.\u00a0\n\n\u00a0What you will\u00a0develop\u00a0\n\nElearning\u00a0technologies\u00a0\n\nUI: graphic design in a digital environment\u00a0\n\nSoftware for Data tracking to integrate the customer at the core of your design\u00a0\u00a0\n\n\u00a0Your Qualifications\u00a0\u00a0\n\nDegree holder in Graphic Design, Multimedia,\u00a0Information\u00a0or related disciplines\u00a0\u00a0\n\nAt least 2 years digital experience of\u202fWeb and Mobile Apps UI/UX design\u00a0\n\n3-5 years of work experience (above 5 years will not be considered)\n\n\nPossess a strong portfolio of UI/UX-focused work for both web and mobile applications\u00a0\u00a0\n\nExperience in\u00a0EdTech\u00a0would be an advantage\u00a0\u00a0\n\nHigh competence in web design and wireframe tools,\u00a0\u00a0\n\nSketch,\u00a0Adobe Creative Cloud, and Microsoft environment are a must\u00a0\n\nPrinciple, Invision, Final Cut Pro, HTML, CSS,\u00a0Javascript\u00a0are a plus\u00a0\n\nGreat command of Chinese (preferably both Simplified and Traditional) and English with confidence in communicating with Mandarin / English speaking counterparts across the region\u00a0\n\nBenefits\n\nWhat\u2019s\u00a0on offer?\u00a0\n\nFast\u00a0career development within the company\u00a0\u00a0\n\nCorporate and B2B exposure\u00a0\n\nAttractive remuneration package with annual discretionary bonus\u00a0\n\nMedical coverage\u00a0\n\n\u00a0Industry:\u00a0\u00a0Digital Education, E-learning, Corporate training\u00a0\n\n\u00a0Employment type:\u00a0\u00a0Full time\u00a0\n\n\u00a0Job Functions: Learning & Development, Content design and Marketing.\u00a0\u00a0\n\nLocation: Wong Chuk Hang\n\nShould this opportunity sound exciting and motivating to you, do send your resume and expected package to us\u00a0with reference\u00a0UX/UI\u00a0Designer Senior in\u00a0APAC. Only candidates allow to work in\u00a0 Hong Kong will be contacted. No visa sponsoring.\u00a0", "employment_types": ["Full Time"], "selling_points": ["Digital Education, E-learning, Corporate training", "Learning & Development, Content design, Marketing", "Employment type: Full time"], "locations": ["Aberdeen"], "categories": ["Design", "Graphics", "Marketing / Public Relations", "Marketing - Brand / Product Management", "E-commerce", "Software Development"], "post_time": "2022-01-14T03:34:16Z", "salary": {"currency": null, "max": null, "min": null, "period": "monthly", "term": null}, "salary_visible": false, "title_keywords": ["designer"], "responsibilities": ["software", "data", "graphic design", "design", "communicating with", "ui", "tracking"], "requirements": {"degrees": [], "majors": [], "languages": [], "language_level": [], "hard_skills": [], "soft_skills": ["communication skills", "energetic", "interpersonal skills", "collaborative"], "languages_combined": []}, "experience_required": {"duration": [], "field": []}}, {"job_id": "100003009051764", "location_code": "hk", "company": "2GoTrade Ltd", "job_title": "(Senior) Software Engineer / Analyst Programmer / Developer (.NET)", "description": "Primary Responsibilities\u00a0\n\nDesign and implement\u00a0Securities\u202ftrading and settlement systems\u00a0as well as wealth management\u00a0systems\u00a0for\u202fthe global financial market;\u00a0\nGather user requirements,\u202fanalyze and design systems;\u00a0\nWork with multiple teams\u00a0on projects;\u00a0\nProvide operational support.\n\n\u00a0Requirements\u00a0\n\n2+\u00a0year of software development working experience;\u00a0\nCandidates with lesser experience will be considered for junior position;\nStrong analytical and\u00a0problem solving\u00a0skill;\u00a0\nHands-on experience in MS Visual Studio, C#/VB.Net\u00a0/\u00a0ASP.NET, Winform, SQL;\u00a0\nFamiliar with\u00a0the\u00a0Securities Industry, or\u00a0working experience in brokerage firm/ bank\u00a0will be an\u00a0advantage.\u00a0\n\n\u00a0Character\u00a0\n\nPassionate to build great software solution;\u00a0\nWilling to learn, and self-motivated;\u00a0\nGood team player.\u00a0\n\nWe assemble passionate people who build solution smartly.\u00a0\u00a0We leverage cutting edge technologies to get things ready. And\u00a0we are\u00a0looking forward\u00a0to you, the\u00a0talented person,\u00a0to join us.\u00a0\u00a0Please email your detailed resume with current, expected salary and availability by clicking \u201cApply Now\u201d.\n\nNo recruitment agencies please.", "employment_types": ["Full Time", "Permanent"], "selling_points": ["FinTech co in Science Park, competitive salary", "5-day work, B'day Leave, Performance Incentive", "One of the local renowned BSS vendors"], "locations": ["Shatin Area"], "categories": ["Information Technology (IT)", "Application Specialist - Software", "Software Development", "E-commerce", "Software Development"], "post_time": "2022-01-17T00:56:33Z", "salary": {"currency": null, "max": null, "min": null, "period": "monthly", "term": null}, "salary_visible": false, "title_keywords": ["software engineer", "developer", "analyst programmer"], "responsibilities": ["management", "operational support", "systems", "teams", "design"], "requirements": {"degrees": [], "majors": [], "languages": [], "language_level": [], "hard_skills": ["problem solving", "no", "sql", "c#"], "soft_skills": ["passionate", "self-motivated", "good team player", "analytical and problem solving skill", "willing to learn", "hands-on", "detailed"], "languages_combined": []}, "experience_required": {"duration": ["2+ year"], "field": ["brokerage", "securities industry", "software development"]}}, {"job_id": "100003009053598", "location_code": "hk", "company": "Toray Industries (South China) Co Ltd", "job_title": "Application Support (ERP)", "description": "Responsibilities:\n\n\nWork closely with the Team Leader and users to develop, support and rollout of application systems\nPlay a key role in the System Development Life Cycle, from requirement study, system analysis and design, system development and testing, implementation to maintenance and support\nMonitor and maintain application system, including trouble-shooting, bug fixing and ad-hoc queries\nEnsure proper process on testing planning, execution and documentation of all test results\nHandle any ad-hoc projects as assigned\n\nRequirements:\n\n\nDegree in Information Technology, Computer Science or related disciplines\nExperience in the implementation and support of ERP software and reporting tools will be an advantage\nFresh graduates are welcome\nAble to work under pressure and meet tight deadlines\nSelf-motivated, responsible, well-organized, detail-oriented and willing to learn\nExcellent interpersonal and communication skills\nProficiency in both written and spoken English, Cantonese and Mandarin\nBusiness travel to PRC is occasionally required\nImmediate available is highly preferred\n\nWe offer attractive remuneration package including 5-day work, 15-day annual leave & medical insurance to successful candidate.\u00a0 Please send your full resume stating your availability, current and expected salary, contact details by clicking \"Apply Now\"\n\n(All data collected will be treated as strictly confidential and will be used for recruitment purpose only)", "employment_types": ["Full Time", "Permanent"], "selling_points": [], "locations": ["Tsim Sha Tsui"], "categories": ["Information Technology (IT)", "Application Specialist - Software", "Software Development", "E-commerce", "Software Development"], "post_time": "2022-01-17T07:12:55Z", "salary": {"currency": null, "max": null, "min": null, "period": "monthly", "term": null}, "salary_visible": false, "title_keywords": ["application support"], "responsibilities": ["ad-hoc", "ad-hoc projects", "maintenance", "analysis", "monitor", "implementation", "design", "testing", "develop", "application system", "maintain", "documentation", "application systems", "planning"], "requirements": {"degrees": ["degree"], "majors": ["related disciplines", "computer science", "information technology"], "languages": ["cantonese", "english", "mandarin"], "language_level": ["proficiency"], "hard_skills": ["erp"], "soft_skills": ["communication skills", "meet tight deadlines", "self-motivated", "responsible", "well-organized", "willing to learn", "detail-oriented", "interpersonal", "work under pressure"], "languages_combined": [{"language": "cantonese", "language_level": ["proficiency"]}, {"language": "english", "language_level": ["proficiency"]}, {"language": "mandarin", "language_level": ["proficiency"]}]}, "experience_required": {"duration": [], "field": []}}, {"job_id": "100003009050421", "location_code": "hk", "company": "Initial Innovation Limited", "job_title": "Web Developer", "description": "Involve in discussion and brainstorming creative ideas for our e-commerce solution\nDevelop new features/bug fixes for our web service according to the sprint plan after development meeting\nCross-check the mobile platforms with the web, making sure a unified customer experience and a bug-free user experience\nContinuously exploring emerging technologies to implement in our platform, providing better user experience\n\nSHOPAGE (https://shopage.org) is a rapidly evolving online store building tool. We are seeking energetic and proactive university/high diploma graduates to join our Web Development team to maintain and improve our store building platform. Welcome to join our fun, young and joyful office environment.\n\nResponsibilities:\n\n\nDeliver and maintain high-quality interface implementation to enable a great user experience\nAssist in project implementation, maintenance, and web-based system testing & documentation\nImplement projects in a timely manner and to ensure quality and project efficiency\nMonitor website performance and proactively identify site usability problems\nCollaborate with team members and stakeholders to shape the product\u2019s design\nRequirements:\n\nDegree in Computer Science, Computer Engineering, or equivalent\nFresh graduate welcome. Experienced candidates will be offered a more senior position\nReact JS experience is a must\nExperience in RESTful development is an advantage\nKnowledgeable in database design and HTTP, with working experience in MySQL and NoSQL\nExperience with deployment using Google App Engine, AWS would be an asset\nAble to communicate in Cantonese is a must\nBackend development opportunity\nPerform architectural design, development, and hands-on implementation of mobile and web applications\nStrong learning capabilities and ability to solve problems independently\nStrong communication skills with cooperation skills within a team", "employment_types": ["Full Time", "Permanent"], "selling_points": [], "locations": ["Lai Chi Kok"], "categories": ["Information Technology (IT)", "Software Development", "E-commerce", "Software Development"], "post_time": "2022-01-14T10:22:40Z", "salary": {"currency": "HKD", "max": 44999, "min": 20000, "period": "monthly", "term": null}, "salary_visible": true, "title_keywords": ["developer"], "responsibilities": ["collaborate with", "maintenance", "quality", "implementation", "user experience", "testing", "a timely manner", "monitor", "website", "maintain", "design", "documentation"], "requirements": {"degrees": ["degree", "fresh graduate"], "majors": ["computer engineering", "computer science"], "languages": ["cantonese"], "language_level": [], "hard_skills": ["web applications", "react", "aws", "mobile", "deployment"], "soft_skills": ["communication skills", "independently", "solve problems", "hands-on", "learning"], "languages_combined": [{"language": "cantonese", "language_level": []}]}, "experience_required": {"duration": [], "field": ["development", "database", "design"]}}, {"job_id": "100003009048924", "location_code": "hk", "company": "Morgan McKinley", "job_title": "Senior UI/ Frontend Software Engineer (React.JS), Fintech", "description": "The Senior UI / Frontend Software Engineer will provide efficient UX to clients' digital platforms.\n\nResponsibilities\n\nDesign and implement products and platforms to provide highly efficient user experiences for all functionalities\nPassionate about using the latest frontend technologies to tackle complex business problems\nCollaborate with product design, product manager and other software engineer to deliver high quality code\nDevelop the mobile App and Web browser site\nParticipate in extensive and candid code review peers\nMentor junior developers\n\nRequirements\n\nSc or high degree in computer science and related fields.\nMore than 3 years of front-end experience.\nStrong JavaScript/HTML/CSS frontend engineering experience.\nDeep understanding of underlying design philosophy and implementation of common web frameworks, including React/Vue.\nExperience with Babel, Webpack, Rollup, or other JavaScript building tools\nExperience in building large-scale web applications and optimizing front-end performance in fast-moving team environment.\n\nApplication\n\nDon't miss out on this exciting opportunity to work in a fast-growing fintech companys! To apply, click 'Apply Now' to submit your resume to us.\n\nAny questions, please feel free to contact Yvonne Hung at +852 3907 3977 or email your inquiry to yhung@morganmckinley.com.", "employment_types": ["Full Time", "Permanent"], "selling_points": ["Multicultural environment & convenient location", "Work with experts from financial services", "5-day work week, medical insurance and more"], "locations": ["Not Specified"], "categories": ["Information Technology (IT)", "Software Development", "E-commerce", "Software Development", "UI/UX Designer"], "post_time": "2022-01-14T07:43:01Z", "salary": {"currency": "HKD", "max": 54999, "min": 45000, "period": "monthly", "term": null}, "salary_visible": true, "title_keywords": ["software engineer"], "responsibilities": ["collaborate with", "mobile app", "software", "review", "quality", "design", "develop", "product design"], "requirements": {"degrees": ["degree"], "majors": ["computer science"], "languages": [], "language_level": [], "hard_skills": ["web applications", "web", "react", "html", "javascript", "css"], "soft_skills": ["deep"], "languages_combined": []}, "experience_required": {"duration": ["3 years"], "field": ["web applications", "engineering", "team"]}}, {"job_id": "100003009055591", "location_code": "hk", "company": "Aurex Group Limited", "job_title": "Leasing Manager", "description": "Family Office\nMixed use portfolio\nInvolve in redevelopment projects\nMy client is a family business with multiple mixed-use properties in Hong Kong. They are looking for a Leasing Manager to join and support the Chairman on leasing activities.\n\nResponsibilities\n\nHandle daily leasing enquiries and all tenancy matters\nWork closely with agents on leasing matters\nFostering customer relationships, interacting with prospective and existing clients on new lettings, tenancy renewals and rent reviews\nConduct market analysis and cost benchmarking\nRequirements\n\nDegree holder in real estate or business-related discipline\nMinimum 7 years of relevant experience\nFluent and spoken and written English, Mandarin and Cantonese\nCan-do attitude and proactive\n\u00a0\u00a0\nIf you believe this opportunity is right for you, please send your CV in English to Sharon Lam by using the \"Apply Now\" button below.\n\nTo view similar opportunities or express interest in related positions, please visit our website www.aurexgroup.com and follow us on LinkedIn https://lnkd.in/fgAWEBa", "employment_types": ["Full Time"], "selling_points": ["Family Office", "Mixed use portfolio", "Involve in redevelopment projects"], "locations": ["Central & Western Area"], "categories": ["Property / Real Estate", "Property Consultancy", "Property Management", "E-commerce", "Software Development"], "post_time": "2022-01-18T02:46:16Z", "salary": {"currency": null, "max": null, "min": null, "period": "monthly", "term": null}, "salary_visible": false, "title_keywords": ["leasing manager"], "responsibilities": ["cost", "market analysis"], "requirements": {"degrees": ["degree holder"], "majors": ["business"], "languages": ["cantonese", "english", "mandarin"], "language_level": ["fluent"], "hard_skills": [], "soft_skills": ["proactive", "can-do attitude"], "languages_combined": [{"language": "cantonese", "language_level": ["fluent"]}, {"language": "english", "language_level": ["fluent"]}, {"language": "mandarin", "language_level": ["fluent"]}]}, "experience_required": {"duration": ["minimum 7 years"], "field": ["relevant experience"]}}, {"job_id": "100003009042037", "location_code": "hk", "company": "EC Healthcare", "job_title": "eCommerce Web Developer", "description": "Job Responsibilities:\n\nResponsible for development, implementation and testing of web application and responsive website with CMS backend;\nProvide support on user acceptance test and system maintenance;\nWork closely with UI/UX designer and eCommerce team to deliver the best experience on both web and mobile platforms; and\nTroubleshoot and resolve application production issues.\n\nRequirements:\n\nHigher Diploma / Associate Degree or above in Computer Science, Information Technology, or any related disciplines;\n2+ years\u2019 experience in web application development;\nStrong & hands-on development skills in WordPress, WooCommerce, PHP, CSS, JavaScript, MySQL, and responsive web;\nFamiliar with SEO, Google Analytics, Git, Bootstrap, Angular, Drupal, and Wix would be an advantage;\nGood analytical and problem-solving skills;\nAggressive, self-motivated, result-orientated, and able to work under pressure;\nExcellent interpersonal and communication skills; and\nGood command of Cantonese, English, and Mandarin.", "employment_types": ["Full Time", "Permanent"], "selling_points": ["Web Application Development", "WordPress, PHP", "Self-motivated, Result-orientated"], "locations": ["Mong Kok"], "categories": ["Information Technology (IT)", "Software Development", "Technical Writing", "E-commerce", "Software Development"], "post_time": "2022-01-12T05:33:08Z", "salary": {"currency": null, "max": null, "min": null, "period": "monthly", "term": null}, "salary_visible": false, "title_keywords": ["developer"], "responsibilities": ["provide support", "maintenance", "implementation", "website", "testing", "troubleshoot", "ui"], "requirements": {"degrees": ["diploma", "degree or above"], "majors": ["related disciplines", "computer science", "information technology"], "languages": ["cantonese", "english", "mandarin"], "language_level": ["good command"], "hard_skills": ["google analytics", "git", "web application development", "seo", "web", "php", "problem-solving skills", "wordpress", "javascript", "angular", "css"], "soft_skills": ["communication skills", "self-motivated", "hands-on", "problem-solving skills", "responsive", "interpersonal", "work under pressure"], "languages_combined": [{"language": "cantonese", "language_level": ["good command"]}, {"language": "english", "language_level": ["good command"]}, {"language": "mandarin", "language_level": ["good command"]}]}, "experience_required": {"duration": ["2+ years"], "field": ["application development"]}}, {"job_id": "100003009050059", "location_code": "hk", "company": "Mani Limited", "job_title": "E-COMMERCE EXECUTIVE", "description": "Responsibilities:\n\nAssist e-Commerce Manager in setting up e-commerce platforms (e-shop, website, mobile app\u2026.).\nManage day-to-day operation and update content materials of e-commerce platforms.\nManage daily online shop order to ensure smooth order delivery process and excellent customer service.\nPrepare regular reports for monitoring online sales performance and stock inventory.\nLiaise with sales, purchasing and warehouse teams for product listing and inventory replenishment.\nAssist in data analysis and prepare relevant reports for key stakeholders\u2019 review.\nInitiate e-commerce platform enhancement and development to improve user interface and customer user experience.\n\nRequirements:\n\nDegree holder in Business Administration, Marketing or related discipline.\nMinimum 3 years working experience in e-commerce operations, preferably in toys, gifts or FMCG.\nExperience in setting up e-commerce platforms is definitely a bonus.\nStrong analytical, project management and interpersonal skills.\nDetail-oriented, self-motivated, responsible and independent.\nExcellent command in English and Chinese.\nProficiency in Microsoft Office Applications.\n\nWe offer 5-day work, attractive remuneration package and a challenging environment for professionals with immediate availability. Interested parties please send email with current and expected salary for application.\n\nFor more information about our company, please visit our facebook :\u00a0https://www.facebook.com/tclubfanshk/\n\n", "employment_types": ["Full Time", "Permanent"], "selling_points": [], "locations": ["Lai Chi Kok"], "categories": ["E-commerce", "Marketing - Brand / Product Management", "Product Management / Business Analyst", "Software Development"], "post_time": "2022-01-14T09:42:13Z", "salary": {"currency": null, "max": null, "min": null, "period": "monthly", "term": null}, "salary_visible": false, "title_keywords": ["executive"], "responsibilities": ["e-shop", "inventory", "e-commerce platforms", "website", "user interface", "customer service", "liaise with", "relevant reports", "mobile app", "product listing", "sales performance", "teams", "reports", "monitoring", "review", "daily online shop order", "data analysis", "customer user experience", "order delivery process", "e-commerce platform enhancement", "update content materials", "inventory replenishment", "day-to-day operation"], "requirements": {"degrees": ["degree holder"], "majors": ["marketing", "business administration"], "languages": ["english", "chinese"], "language_level": ["excellent"], "hard_skills": ["microsoft office", "project management", "e-commerce"], "soft_skills": ["self-motivated", "independent", "responsible", "detail-oriented", "project management", "interpersonal skills"], "languages_combined": [{"language": "english", "language_level": ["excellent"]}, {"language": "chinese", "language_level": ["excellent"]}]}, "experience_required": {"duration": ["minimum 3 years"], "field": ["toys", "fmcg", "e-commerce"]}}, {"job_id": "100003009048487", "location_code": "hk", "company": "HomePlus (Hong Kong) Limited (HOME+)", "job_title": "API Programmer - HOME+ E-Commerce Platform", "description": "Opportunities\u00a0\n\nDevelop API service with latest technologies.\u00a0\u00a0\nWorking with a highly dynamic and innovative team\u00a0in Agile/Scrum\u00a0approach.\nThis position will be under HOME+ e-commerce platform\nThis position can be Programmer/ Senior Programmer/ Analyst Programmer/ System Analyst, depends on experiences\nWhat efforts you need to make for this role?\n\nCollaborate with Business Analysts, Programmer to resolve issues and ensuring solutions are viable and consistent\u00a0\nAnalyse, design and setup API integration in\u00a0AWS Lambda/\u00a0Mule\nAnalyse, design and develop RESTful/ GraphQL API for system integration\u00a0\nDefine or assist in API design standards, patterns, and best practices\nWork closely with cross-functional members of a team to ensure alignment of the APIs\nReview existing systems/ API design and develop the enhancement\u00a0\n\n\u00a0Let's check if you are/ have\u2026\n\nHigher diploma/Degree holder in Computer Science, Engineering or equivalent\u00a0\n0-5\u00a0years' working experience in software development\u00a0\nHands on experience on RESTful/\u00a0GraphQL\u00a0API\nUnderstanding of DevOps (e.g. GitHub, Jenkins) to build, deploy and maintain the code pipeline is an advantage\u00a0\nExperience on API Integration with internal system and third-party software is an advantage\u00a0\nInnovative and strong analytical skill\u00a0\nKeen on technology and able to pick up latest technical skills\u00a0\nFresh graduates\u202fare welcome and considered as\u202fProgrammer\u00a0\nCandidates with\u202fmore experience\u202fcan be considered as\u202fSystem\u00a0Analyst\u00a0\u00a0\n\nWhat you get in return\u2026\n\nApart from competitive salary package and benefits, in HKBN, you will work flexibly under our Talent-first\u00a0culture\u00a0and we uphold Life-Work Priority. Examples of our flexible initiatives:\n\nFive-day work week and shorten working hours (8 hours including 1 hour 15 mins meal break)\nHalf Day Off Friday once a month (compensation leave for Talents who work on shift)\nHalf Day Off on Festival Eve (compensation leave for Talents who work on shift)\nUnique leaves arrangement: Family-care leave, Anniversary leave, Bonus leave, Volunteer leave, Sabbatical leave, etc.\nComprehensive medical and life insurance coverage\nUpgraded maternity leave and paternity leave\nDiscounted Talent plan offers including broadband and mobile plans and other promoted products\nEducation subsidies and Examination leave\nYear-end discretionary bonus", "employment_types": ["Full Time", "Permanent"], "selling_points": ["API integration in AWS Lambda/ Mule", "RESTful/ GraphQL API for system integration", "Software Development"], "locations": ["Kwai Hing"], "categories": ["Information Technology (IT)", "Application Specialist - Software", "Software Development", "E-commerce", "Software Development"], "post_time": "2022-01-14T06:39:59Z", "salary": {"currency": null, "max": null, "min": null, "period": "monthly", "term": null}, "salary_visible": false, "title_keywords": ["programmer"], "responsibilities": ["collaborate with", "software", "review", "design and develop", "systems", "design", "develop", "maintain", "deploy", "e-commerce platform", "setup", "analyse"], "requirements": {"degrees": ["diploma", "degree holder"], "majors": ["engineering", "computer science"], "languages": [], "language_level": [], "hard_skills": ["analytical skill", "agile", "jenkins", "e-commerce", "devops", "aws", "make", "dynamic", "integration", "code"], "soft_skills": ["analytical skill", "agile", "keen", "hands on", "dynamic", "technical skills", "innovative"], "languages_combined": []}, "experience_required": {"duration": ["0-5 years"], "field": ["system analyst", "software development"]}}, {"job_id": "100003009037045", "location_code": "hk", "company": "Innovation X Company Limited", "job_title": "Software Engineer", "description": "Key Responsibilities:\nAssist to design, development and implement mobile/web apps\nWorking with Image process in 3D model area\nGood team player and self-motivated\nExplore new\u00a0technology\u00a0for mobile development\n\nRequirements:\n\n\nDiploma/Degree in CS, IT, Electric Engineering or related fields\nExperience in web/apps development\u00a0\nSolid\u00a0Experience in one of the program languages: Python, C/C#/C++, Java, or other languages\u00a0\nExperience in MSSQL or MySQL\nFluent written and spoken English and Chinese is an advantage\nImmediate availability is preferred\nCandidate with more experience will be considered as Senior Software Engineer\nFresh Graduates are Welcome!\n\n\nBenefits & Others\n\nAttractive salary and fringe benefits package will be offered to the right candidates with friendly working environment. Interested parties please submit your application with a resume, certificate, and transcripts. Birthday leaves and annual leaves will also be provided.", "employment_types": ["Full Time"], "selling_points": [], "locations": ["Shatin Area"], "categories": ["Information Technology (IT)", "Software Development", "Technical / Functional Consulting", "E-commerce", "Software Development"], "post_time": "2022-01-13T18:55:01Z", "salary": {"currency": null, "max": null, "min": null, "period": "monthly", "term": null}, "salary_visible": false, "title_keywords": ["software engineer"], "responsibilities": ["design"], "requirements": {"degrees": ["diploma", "degree"], "majors": ["it", "engineering"], "languages": ["english", "chinese"], "language_level": ["advantage", "fluent"], "hard_skills": ["java", "c++", "web", "mssql", "c", "python", "c#"], "soft_skills": [], "languages_combined": [{"language": "english", "language_level": ["fluent", "advantage"]}, {"language": "chinese", "language_level": ["fluent", "advantage"]}]}, "experience_required": {"duration": [], "field": ["development"]}}, {"job_id": "100003009042122", "location_code": "hk", "company": "Youth Global Network Limited", "job_title": "Software Engineer", "description": "Job Description:\n\nOur ministry needs experienced software engineers to manage and produce state-of-the-art web and mobile solutions for our business clients. We want people with experience in the entire product lifecycle who have a track record of developing production-ready software and are excited by the challenge of finding innovative solutions to client needs. Moreover, we want growth-driven engineers who are passionate about societal change and eager to coach and mentor motivated students on software projects.\n\nProspective applicants should not only possess excellent technical skills and rich software experience but must also be artful in leadership and communication, able to liaise with our business clients and train and lead new students at the same time.\n\n\u00a0Key Responsibilities:\n\nSoftware Development\n\n\u00a0 \u00a0 \u00a0 o\u00a0\u00a0 Produce software under an Agile\u00a0development methodology\n\n\u00a0 \u00a0 \u00a0 o\u00a0\u00a0 Develop web and/or mobile applications independently or with other members of the software team\n\n\u00a0 \u00a0 \u00a0 o\u00a0\u00a0 Assure software quality and integration\n\n\u00a0 \u00a0 \u00a0 \u00a0 \u00a0 \u00a0 2.\u00a0 Leadership and teamwork\n\n\u00a0 \u00a0 \u00a0 o\u00a0\u00a0 Work with business clients to translate business needs into software solutions\n\n\u00a0 \u00a0 \u00a0 o\u00a0\u00a0 Drive development within our software team and potentially lead and mentor our freelance software engineers and students\n\n\u00a0 \u00a0 \u00a0 \u00a0 \u00a0 \u00a0 3.\u00a0 Contribute to the knowledge base by documenting development processes, software, training methods, and other areas of our work\n\n\n\nMinimum Qualifications:\n\n1-3 years of experience or more in web and/or mobile application development\nDegree in Computer Science (or related fields) or equivalent practical experience\nProficient in: (Web) ReactJS;(Mobile) React Native and/or Flutter + Dart\nExperienced in software integration/VCS (Git), testing, and quality assurance\nExperienced in building production-ready software\n\n\u00a0Preferred Qualifications:\n\nFamiliar with any of the technologies in our frontend, backend, and mobile stacks:\n\n\u00a0 \u00a0 \u00a0 \u00a0 o\u00a0\u00a0 Frontend: ReactJS, Apollo GraphQL, Storybook, React Hooks, Redux\n\n\u00a0 \u00a0 \u00a0 \u00a0 o\u00a0\u00a0 Backend: Apollo GraphQL, ExpressJS, GraphQL, MySQL/MongoDB, Prisma\n\n\u00a0 \u00a0 \u00a0 \u00a0 o\u00a0\u00a0 Mobile: React Native, Flutter+Dart, BLoC\n\n\u00a0 \u00a0 \u00a0 \u00a0 o\u00a0\u00a0 Testing: React-testing-library, Jest, Cypress\n\n\u00a0 \u00a0 \u00a0 \u00a0 o\u00a0\u00a0 Others: Microservices, Kubernetes, Docker, Google Cloud Platform\n\nExperience with Agile Development and Scrum Methodology\nExperience with managing a software project or product\nAble to deal with multiple stakeholders and manage multiple concurrent projects\nAble to work independently and drive product development while managing external freelance engineers or internal programmer trainees\nFamiliar with application deployment and CI/CD\nA plus to have knowledge in e-learning and App Inventor (MIT), Python, and Java.\n\n\u00a0Application:\u00a0\n\nFor interested parties, please apply with full resume, stating clearly current and expected salary, to Human Resources Department, Youth Global Network Limited, 14th Floor, Breakthrough Centre, 191 Woosung Street, Jordan, Kowloon. or\u00a0email to APPLY NOW\n\nFor more information, please visit our website https://www.ygn.org.hk/\n\nAll information provided will be treated with strictest confidence & used for recruitment purposes only. All unsuccessful applications will be kept for a period of no longer than two years after completion of the recruitment exercise.\u00a0", "employment_types": ["Full Time", "Permanent", "Contract"], "selling_points": ["Software Engineer", "Software Development", "Leadership and teamwork"], "locations": ["Tsim Sha Tsui"], "categories": ["Engineering", "Engineering Project Management", "Information Technology (IT)", "Software Development", "E-commerce", "Software Development"], "post_time": "2022-01-12T06:18:11Z", "salary": {"currency": null, "max": null, "min": null, "period": "monthly", "term": null}, "salary_visible": false, "title_keywords": ["software engineer"], "responsibilities": ["software", "quality", "agile development", "developing", "develop", "communication", "testing", "liaise with", "application development"], "requirements": {"degrees": ["degree"], "majors": ["computer science"], "languages": [], "language_level": [], "hard_skills": ["plus", "git", "java", "agile", "web", "dart", "react", "microservices", "python", "mobile", "react native", "deployment", "integration"], "soft_skills": ["work independently", "independently", "agile", "teamwork", "communication", "motivated", "learning", "technical skills", "innovative", "leadership", "driven", "passionate about"], "languages_combined": []}, "experience_required": {"duration": ["1-3 years"], "field": ["related", "development", "developing", "business", "application development"]}}, {"job_id": "100003009041380", "location_code": "hk", "company": "Osmium Consulting Group Limited", "job_title": "Automation QA Engineer - MNC", "description": "Responsibilities:\n\n\nWorking in the Digital Products Group Department\nTesting AI, Cloud, IoT products\u00a0\nDesigning test plans, scenarios, scripts, and procedures.\nPerform UAT and SIT\nWorking with the development team to correct bugs and errors\nAgile working environment\nRequirements:\n\nMinimum of 3 years experience in QA with at least 2 years experience in Automation Testing\nA Bachelor's degree in Computer Science, Engineering, or related field\nSolid knowledge of SQL and scripting\nKnowledge of Java / Python / Node.js\u00a0\nKnowledge of Selenium\u00a0\u00a0\nGood team working and critical thinking skills.", "employment_types": ["Full Time", "Permanent"], "selling_points": ["MNC", "good working location", "Attractive benefits & 5 day work week"], "locations": ["Wan Chai"], "categories": ["Information Technology (IT)", "Software Development", "Testing / QA", "E-commerce", "Software Development"], "post_time": "2022-01-12T03:49:21Z", "salary": {"currency": "HKD", "max": 44999, "min": 25000, "period": "monthly", "term": null}, "salary_visible": true, "title_keywords": ["engineer"], "responsibilities": ["uat", "procedures", "testing", "designing", "plans"], "requirements": {"degrees": ["degree", "bachelor"], "majors": ["engineering", "computer science"], "languages": [], "language_level": [], "hard_skills": ["sql", "java", "python"], "soft_skills": ["team working"], "languages_combined": []}, "experience_required": {"duration": ["at least 2 years", "minimum of 3 years"], "field": ["qa", "testing"]}}, {"job_id": "100003009042863", "location_code": "hk", "company": "Casetagram Limited", "job_title": "Senior UXUI Designer", "description": "Casetify is looking for a Senior UXUI designer experienced in information architecture, interaction, and user testing to join our team. You will collaborate with the E-commerce team to design and build next generation Web/mobile applications. The right candidates will be excellent communicators, comfortable in a high-velocity startup, and passionate about creating products that transform people\u2019s lifestyle.\nResponsibilities:\nPrepare UX/UI design and materials including wire framing, mockup and rapid prototyping for various interfaces, including websites, mobile devices and apps for ecommerce site;\nAnalyze current user journey to understand motivation, expose pain points, issues and improvement opportunities;\nConduct user research, A/B testing, and propose solutions to optimize customer experience;\nCommunicate concepts and work collaboratively with project team / Tech team in order to develop the most efficient design schemas;\nSit with developers to do pixel-perfect reviews of frontend products before they are pushed in production;\nConsume our Design System library and contribute to its evolution.\nRequirements:\n\n\nBachelor Degree in Creative Media / Interactive Design / Web Design / Web Development;\n5+ years of experience building transactional website;\nSpecific experience in a fast growing ecommerce company;\nAbility to solve problems of complexity through smart design;\nBeing data-driven, and be able to back up your assertions with data, with proficiency in analytic tools - Hotjar, Google Analytics, Optimizely etc;\nA user-first attitude and ensure we consistently deliver a user-centric culture;\nStrong understanding of web grids and browser limitations;\nFamiliarity with usability testing, A/B testing methods;\nProficiency with Photoshop, Adobe XD, Webflow, HTML, CSS, PHP;\nBouns: Experience with Shopify site designs / SDK.\nPlease include 2 URLs of your Open Source, personal projects into your resume.\n\n", "employment_types": ["Full Time", "Permanent"], "selling_points": ["Websites/ Mobile/ Apps - Senior UXUI Designer", "E-commerce & Transactional Site Design", "Shopify Site Designs / SDK are advantageous"], "locations": ["Kwun Tong"], "categories": ["Design", "Multi-media", "Web Designer", "E-commerce", "Software Development"], "post_time": "2022-01-12T09:02:48Z", "salary": {"currency": null, "max": null, "min": null, "period": "monthly", "term": null}, "salary_visible": false, "title_keywords": ["designer"], "responsibilities": ["design", "develop", "testing", "mobile devices", "ui"], "requirements": {"degrees": ["degree", "bachelor"], "majors": ["creative media", "web design", "design"], "languages": [], "language_level": [], "hard_skills": ["web design", "web development", "google analytics", "web", "php", "adobe xd", "shopify", "html", "css", "photoshop"], "soft_skills": ["solve problems", "creative", "driven"], "languages_combined": []}, "experience_required": {"duration": ["5+ years"], "field": ["ecommerce"]}}, {"job_id": "100003009040128", "location_code": "hk", "company": "Pricerite Home Ltd", "job_title": "Assistant Business Analyst", "description": "Job Responsibilities:\u00a0\n\nAct as an important communication bridge between business users, IT development team, project team and other internal departments\nParticipate in the full project life cycle, including requirement gathering, development, testing and change management\u00a0\nWork closely with internal users to collect business requirements and prepare business documentation (e.g. Flow Chart, User Requirement Spec)\nResponsible for aligning internal business processes with eCommerce system, streamline and reduce manual works by system integration and automation\nDesigning the business processes and system integrations among different systems (e.g. eCommerce system, POS, ERP, PIM, CRM)\nAnalyze user behavior and target funnels and provide insights and make recommendations for web and app enhancement and other related projects\nParticipate in technological evaluation\nHandle ad hoc projects assigned by management\n\nJob Requirements:\n\nDegree holder in Computer Science, Computing, Information Technology or related discipline;\n2 years\u2019 experience in web application or related system development and building web service architecture on cloud computing platforms (e.g. Rackspace, AWS, AliCloud)\nExperience in Magento 1 or 2 development environment including the extension installation and customization\nExperience on handling vendors and project management is a must\nAble to work under pressure and deliver on schedule\nImmediate available is highly preferred\n\nWe offer attractive remuneration package including\u00a0comprehensive medical insurance scheme, birthday leave, full pay paternity leave, discretionary bonus, education subsidies & leave and job-related training etc.\n\nPlease apply in confidence with cover letter and full resume, quoting reference to the\u00a0Manager, Human Resources, Pricerite Home Limited,\u00a028/F, Manhattan Place, 23 Wang Tai Road, Kowloon Bay, Hong Kong\u00a0or\u00a0press below \"Apply Now\".\n\nThe information provided will be used for selection purpose only. All information of unsuccessful applicants will be destroyed within six months.", "employment_types": ["Full Time", "Permanent"], "selling_points": ["Purchase Discount", "Birthday Leave", "Computer Science, Computing, IT"], "locations": ["Kowloon Bay"], "categories": ["Information Technology (IT)", "Software Development", "E-commerce", "Product Management / Business Analyst", "Software Development"], "post_time": "2022-01-12T01:33:31Z", "salary": {"currency": null, "max": null, "min": null, "period": "monthly", "term": null}, "salary_visible": false, "title_keywords": ["business analyst", "assistant"], "responsibilities": ["change management", "testing", "communication", "documentation", "collect business requirements"], "requirements": {"degrees": ["degree holder"], "majors": ["computer science", "information technology"], "languages": [], "language_level": [], "hard_skills": ["computing platforms", "web", "pos", "scheme", "erp", "aws", "make", "project management", "integration"], "soft_skills": ["make recommendations", "confidence", "responsible", "project management", "comprehensive", "work under pressure"], "languages_combined": []}, "experience_required": {"duration": ["2 years"], "field": ["installation", "related", "development", "system development", "project management"]}}, {"job_id": "100003009039250", "location_code": "hk", "company": "GP Acoustics Group", "job_title": "Operations Specialist (E-Commerce Platform)", "description": "About the Role\nAs an Operation Specialist (E-Commerce Platform) for both KEF and GP Batteries, you will execute creative projects and ensure all web content is accurately published and up-to-date according to the digital brand guideline. You will work closely with Digital Creative Team based in Kuala Lumpur and Global Digital Marketing team in Hong Kong Headquarter.\n\nKey responsibilities:\n\nPlans and conceptualizes the necessary tests to be carried out for each project.\nPerform UAT occasionally to ensure website content is published accurately, and web applications are working as expected.\nProvide support for the development and maintenance of web content, experience on using ecommerce platform like Shopify will be an advantage.\nAdapt and build content on websites in local context and languages by referring to the branded wireframes and mock-ups.\nReview & crosscheck all graphics, layouts before and after publishing pages.\nAble to work with members from regional teams, and manage multiple projects simultaneously.\nManage digital contents of marketing campaigns across all regional markets.\nEducation & Experience:\n2-4 years of professional experience in CMS operation (preferable in Shopify & Magento), digital design for web, desktop and mobile.\nProven work experience as a web content editor with knowledge in E-Commerce/Mobile Commerce platforms\nPortfolio of completed work experience on websites and E-Commerce/Mobile Commerce platforms\nBasic knowledge of HTML and web development systems\nAn ability to manage multiple projects and meet deadlines in a timely manner\nCreative problem solver with attention to detail\nHands-on experience with graphic design software and image editing tools (e.g. Photoshop and Adobe Illustrator) is preferred\nAdditional qualification in Graphic Design is a plus\nHighly organised with strong project management skills (Fluency with Asana preferred)\nWe offer 5-day work, double pay, medical benefit, free company coaches and bright career prospect to the right candidate. Interested parties please send your application letter with detailed resume stating current salary, expected salary and date of available to hr @ kef.com .\n\nWe are an equal opportunities employer. Personal data collected will be treated as strictly confidential and used for recruitment purpose only.", "employment_types": ["Full Time", "Permanent"], "selling_points": ["Execute creative projects", "2-4 years of professional exp in CMS operation", "Web content development & maintenance"], "locations": ["Shatin Area"], "categories": ["Information Technology (IT)", "IT - Webmaster / SEO", "Marketing / Public Relations", "Digital Marketing", "E-commerce", "Software Development"], "post_time": "2022-01-11T09:10:16Z", "salary": {"currency": null, "max": null, "min": null, "period": "monthly", "term": null}, "salary_visible": false, "title_keywords": ["specialist", "operations"], "responsibilities": ["software", "mock-ups", "website", "design", "plans", "editing", "graphics", "uat", "teams", "manage multiple projects", "marketing campaigns", "provide support", "review", "digital marketing", "contents", "maintenance", "graphic design", "systems", "a timely manner", "project management", "e-commerce platform"], "requirements": {"degrees": [], "majors": [], "languages": [], "language_level": [], "hard_skills": ["graphics", "web development", "plus", "web applications", "basic", "maintenance", "web", "e-commerce", "shopify", "html", "adobe illustrator", "mobile", "project management", "photoshop"], "soft_skills": ["manage multiple projects simultaneously", "problem solver", "project management skills", "timely", "hands-on", "attention to detail", "organised", "meet deadlines", "creative"], "languages_combined": []}, "experience_required": {"duration": ["2-4 years"], "field": ["ecommerce", "maintenance", "e-commerce", "editor", "development", "graphic design", "design", "education", "operation", "digital", "editing"]}}, {"job_id": "100003009038757", "location_code": "hk", "company": "HomePlus (Hong Kong) Limited (HOME+)", "job_title": "Software QA Engineer - E-Commerce Platform", "description": "What efforts you need to make?\nReview requirements, specifications and technical design documents to provide timely and meaningful feedback\nCreate detailed, comprehensive and well-structured test plans and test cases\nEstimate, prioritize, plan and coordinate testing activities\nDesign, develop and execute automation scripts using open source tools\nIdentify, record, document thoroughly and track bugs\nPerform thorough regression testing when bugs are resolved\nDevelop and apply testing processes for new and existing products to meet client needs\nLiaise with internal teams (e.g. developers and product managers) to identify system requirements\nMonitor debugging process results\nInvestigate the causes of non-conforming software and train users to implement solutions\nTrack quality assurance metrics, like defect densities and open defect counts\nStay up-to-date with new testing tools and test strategies\nLet's check if you are/have\u2026\nProven work experience in software development\nProven work experience in software quality assurance\nStrong knowledge of software QA methodologies, tools and processes\nExperience in writing clear, concise and comprehensive test plans and test cases\nHands-on experience with both white box and black box testing\nHands-on experience with automated testing tools (e.g. Selenium, Appium)\nSolid knowledge of SQL and scripting (e.g. Python browser library, robot framework)\nExperience working in an Agile/Scrum development process\nExperience with performance and/or security testing is a plus\nBS/MS degree in Computer Science, Engineering or a related subject\n\nWhat you get in return\u2026\n\nApart from competitive salary package and benefits, in HKBN, you will work flexibly under our Talent-first\u00a0culture\u00a0and we uphold Life-Work Priority. Examples of our flexible initiatives:\n\nFive-day work week and shorten working hours (8 hours including 1 hour 15 mins meal break)\nHalf Day Off Friday once a month (compensation leave for Talents who work on shift)\nHalf Day Off on Festival Eve (compensation leave for Talents who work on shift)\nUnique leaves arrangement: Family-care leave, Anniversary leave, Bonus leave, Volunteer leave, Sabbatical leave, etc.\nComprehensive medical and life insurance coverage\nUpgraded maternity leave and paternity leave\nDiscounted Talent plan offers including broadband and mobile plans and other promoted products\nEducation subsidies and Examination leave\nYear-end discretionary bonus", "employment_types": ["Full Time", "Permanent"], "selling_points": ["Software QA methodologies", "SQL and scripting", "LIFE-Work Priority & Talent-first Culture"], "locations": ["Kwai Hing"], "categories": ["Information Technology (IT)", "Software Development", "Technical Writing", "E-commerce", "Software Development"], "post_time": "2022-01-11T07:45:11Z", "salary": {"currency": null, "max": null, "min": null, "period": "monthly", "term": null}, "salary_visible": false, "title_keywords": ["engineer"], "responsibilities": ["software", "review", "teams", "monitor", "design", "plan and coordinate", "testing activities", "develop", "testing", "specifications", "quality", "bs", "liaise with", "plans"], "requirements": {"degrees": ["degree"], "majors": ["engineering", "computer science"], "languages": [], "language_level": [], "hard_skills": ["plus", "agile", "sql", "make", "python"], "soft_skills": ["agile", "timely", "prioritize", "clear", "hands-on", "comprehensive", "thorough", "structured", "detailed"], "languages_combined": []}, "experience_required": {"duration": [], "field": ["development", "testing", "writing", "security", "software development", "quality assurance"]}}, {"job_id": "100003009034737", "location_code": "hk", "company": "HomePlus (Hong Kong) Limited (HOME+)", "job_title": "(Senior) IT Project Executive (Magento) - E-Commerce Platform", "description": "This\u00a0position will be under HOME+ e-commerce platform.\n\nOur Vision of Home+ is to set up a merchant ecosystem of merchants with shared value, covering different aspects of our customers\u2019 daily household purchases. The mission is to provide customers with the best value for money for the promotional products and services offered, from time to time. For more information, please feel free to visit our website at\u00a0https://home-plus.hk/\n\nTo be part of our mission, we are looking for a (Senior) Project Executive to\u2026\n\nIdentify and close the gap between users and IT or vendor when evaluating the digital platform solutions and approach with system and business knowledge\nResponsible for day-to-day IT project management, user experience design, UAT, platform support\nCollaborate with UX team to create and review the UX/UI and GUI of the solutions\nConduct SIT & UAT of the system\nProvide administrative support to the project manager, including task scheduling, presentation materials, documentation and projects\u2019 activities\nThe follow attributes will be valued\u2026\n\nBachelor\u2019s Degree in Business Administration, Management Information Systems, Computer Science or related disciplines\nA minimum of 3 years working experience\nSolid experience in IT & digital project management (Website/Mobile APP Projects)\nMagento experience is a plus (not a must)\nMySQL, Coding (PHP, JSON) & API Integration knowledge is a plus (not a must)\nGood analytical and problem solving skills, self-initiated, attentive to details and customer focused\nPossesses sense of ownership and responsibility\nEnjoy a dynamic and multi-tasking working environment\nDetail-oriented and organized person\nLess Experience will be considered as Project Executive\n\nWhat you get in return\u2026\n\nApart from competitive salary package and benefits, in HKBN, you will work flexibly under our Talent-first\u00a0culture\u00a0and we uphold Life-Work Priority. Examples of our flexible initiatives:\n\nFive-day work week and shorten working hours (8 hours including 1 hour 15 mins meal break)\nHalf Day Off Friday once a month (compensation leave for Talents who work on shift)\nHalf Day Off on Festival Eve (compensation leave for Talents who work on shift)\nUnique leaves arrangement: Family-care leave, Anniversary leave, Bonus leave, Volunteer leave, Sabbatical leave, etc.\nComprehensive medical and life insurance coverage\nUpgraded maternity leave and paternity leave\nDiscounted Talent plan offers including broadband and mobile plans and other promoted products\nEducation subsidies and Examination leave\nYear-end discretionary bonus", "employment_types": ["Full Time", "Permanent"], "selling_points": ["User experience design, UAT, platform support", "Website/Mobile APP Projects", "MySQL, Coding (PHP, JSON) & API Integration know"], "locations": ["Kwai Hing"], "categories": ["Information Technology (IT)", "IT Project Management / Team Lead", "Product Management / Business Analyst", "E-commerce", "Software Development"], "post_time": "2022-01-10T04:06:31Z", "salary": {"currency": null, "max": null, "min": null, "period": "monthly", "term": null}, "salary_visible": false, "title_keywords": ["it project executive"], "responsibilities": ["collaborate with", "management", "documentation", "mobile app", "uat", "review", "systems", "website", "digital platform", "user experience", "design", "project management", "scheduling", "coding", "provide administrative support", "e-commerce platform", "ui", "administration"], "requirements": {"degrees": ["degree", "bachelor"], "majors": ["related disciplines", "business administration", "computer science"], "languages": [], "language_level": [], "hard_skills": ["plus", "integration", "e-commerce", "php", "gap", "vendor", "project management", "mobile", "dynamic", "documentation", "problem solving skills"], "soft_skills": ["organized", "attentive to details", "responsible", "focused", "detail-oriented", "project management", "analytical and problem solving skills", "dynamic", "multi-tasking", "presentation"], "languages_combined": []}, "experience_required": {"duration": ["minimum of 3 years"], "field": ["project management", "it", "design", "digital"]}}, {"job_id": "100003009034855", "location_code": "hk", "company": "Osmium Consulting Group Limited", "job_title": "Web Developer / Programmer ( PHP ) / Happy Work Environment with excellent career path", "description": "Responsibilities :\n\nWork closely with Project Lead to develop application for users\nMaintain and support the application for production and usage\nWeb development\u00a0\n\nRequirements :\n\nDegree holder in Computer Science or related disciplines\nExperience in PHP\u00a0\nWelcome Fresh graduates", "employment_types": ["Full Time", "Permanent"], "selling_points": ["PHP", "Web Developer", "Attractive Package"], "locations": ["Yau Tsim Mong Area"], "categories": ["Information Technology (IT)", "Application Specialist - Software", "Software Development", "E-commerce", "Software Development"], "post_time": "2022-01-10T04:25:55Z", "salary": {"currency": "HKD", "max": 34999, "min": 25000, "period": "monthly", "term": null}, "salary_visible": true, "title_keywords": ["developer", "programmer"], "responsibilities": ["maintain", "develop"], "requirements": {"degrees": ["degree holder"], "majors": ["related disciplines", "computer science"], "languages": [], "language_level": [], "hard_skills": ["php"], "soft_skills": [], "languages_combined": []}, "experience_required": {"duration": [], "field": []}}, {"job_id": "100003009036938", "location_code": "hk", "company": "Sa Sa Dot Com Limited", "job_title": "System Developer  / Programmer", "description": "Responsibilities:\n\nDevelop and maintain enterprise systems used by E-commerce business.\nProgramming and technical support for ad-hoc requests/ incidents.\nParticipate in new projects and adopt new tools and technologies to enable business growth.\nWork closely with the business units to cope with their requirement for enhancing the existing applications\n\nRequirements:\n\nGraduate in Computer Science/ Information Technology or relevant discipline\n2+ years of experience with system development, technical design, and system integration flow design.\nKnowledge of E-commerce systems is an advantage.\nProficient in Java, JSP, PHP, HTML, Restful API, RDBDM SQL, GIT in a cloud environment.\nFresh graduates will be considered.\nExperience with Oracle, AWS and Aliyun.\nStrong analytical and problem-solving skills.\nProficient in spoken and written English and Cantonese. Mandarin is a plus.\n\n\nWe offer\n\n\n5 - day work week\nMedical Benefits\nAnnual Merit Bonus\nStaff Purchase Discounts\nStaff Recreation Activity\nShuttle Bus Service\nEducation Sponsorship\n\nInterested parties please send a full resume with current and expected salary by email by clicking\u00a0APPLY NOW:\n\nHuman Resources Department\nSa Sa Cosmetic Co Ltd\n14/F, Block B, MP Industrial Centre\n18 Ka Yip Street\nChai Wan\nHong Kong\n\nPlease visit our corporate website at\u00a0http://corp.sasa.com/en/home\u00a0to know more about us.\n\n(Sa Sa is an Equal Opportunity Employer and all qualified applicants will receive consideration for employment. Personal data collected will be kept confidential and used for recruitment purpose only.)", "employment_types": ["Full Time"], "selling_points": ["Java, JSP, PHP, html", "E-commerce platform", "Fresh grad also consider"], "locations": ["Siu Sai Wan"], "categories": ["Information Technology (IT)", "Network & System", "E-commerce", "Business Development", "Software Development"], "post_time": "2022-01-11T00:53:32Z", "salary": {"currency": null, "max": null, "min": null, "period": null, "term": null}, "salary_visible": false, "title_keywords": ["system developer", "programmer"], "responsibilities": ["technical support", "systems", "develop", "maintain", "ad-hoc requests"], "requirements": {"degrees": [], "majors": [], "languages": ["cantonese", "english", "mandarin"], "language_level": ["proficient"], "hard_skills": ["java", "restful api", "git", "plus", "php", "e-commerce", "problem-solving skills", "html", "aws", "sql", "integration", "cloud environment", "oracle"], "soft_skills": ["problem-solving skills"], "languages_combined": [{"language": "cantonese", "language_level": ["proficient"]}, {"language": "english", "language_level": ["proficient"]}, {"language": "mandarin", "language_level": []}]}, "experience_required": {"duration": ["2+ years"], "field": ["design", "system development"]}}, {"job_id": "100003009037718", "location_code": "hk", "company": "Hong Kong Express Airways Limited", "job_title": "Assistant Manager/ Specialist, Digital Experience", "description": "DEAR TALENT, YOUR MOVE!\n\nBeing the new rising airline since 2013, we are the Hong Kong\u2019s only Low Cost Carrier (LCC) offering you safe and flexible service options to Hong Kong and beyond.\n\nWe\u2019re on a mission to inspire you to be different, to shake things up, to inspire the spirit of adventure by bringing you to fascinating destinations that few others serve.\n\nSpread your wings and fly with us!\n\nWhat will you do?\u00a0\n\n\u2022As a project lead for assigned projects associated to digital experience\n\n\u2022Engage in digital experience project roadmap planning to drive improvements on different digital touch points on both direct (IBE, app, WeChat miniapp) and non-direct channels\n\n\u2022Work with different business units to review digital journey and make suggestions to improve digital experiences using data driven approach\n\n\u2022Support day-to-day operations and management of booking website systems (front-end / back-end);\n\n\u2022Act as technical point of contact/ support between business users and vendors;\n\n\u2022Support different departments & analytics teams to deploy required codes to website;\n\n\u2022Work with various teams (UX, Analytics) and develop AB tests to optimize booking site performance\n\n\u2022Arrange update of dynamic contents with programming/ CMS on the website;\n\n\u2022Monitor digital channels performance including website architecture governance, navigation and overall customer journey;\n\n\u2022Act as the systems subject matter expert to collaborate across various business units and alliance partners to find opportunities and realize conceptual ideas into implementation in an agile approach;\n\n\u2022Prepare adhoc report and other documentation assigned by supervisor.\n\nWe are a perfect match, if you are/have:\n\nDegree holder\nMinimum 5 years of working experience and 3 years relevant experience in website management of eCommerce platforms (Candidate with less experience will be considered as Specialist level);\nHands-on experience with responsive website development, UX/UI, Mobile application, WeChat mini-program, and content management system.\nKnowledge of Google and Adobe analytics tools\nKnowledge and experience in using Dynamic Tag Management and Javascript programming languages;\nPassionate about driving product/performance improvement and enhancing customer digital experience;\nStrong business insight, highly organized and attention to detail;\nCreative and innovative thinker with a \u201ccan do\u201d attitude.\n\nYour Future Work Life?\n\nWork flexibly with staggered working hours and flexible workplace\nDress Casual and Smart everyday\nWork in a newly-designed office with open seating, stylish breakout areas, game room, gym and free coffee\u2026\nWork with a group of energetic and multicultural professionals (up to 50 nationalities!)\nHave great fun in Snack Friday, New Year Market, Fly with your Kids Day, Basketball Team\u2026\nHave your voice heard through Townhalls, Crew forums, CEO live sessions etc.\n\nWhat will you enjoy?\n\nFly anywhere we fly for free plus taxes during leisure with your friends and family\nSpecial privileges to buy duty free products\nCareer Express\n\nYou will be inspired by our core values.\nYou will be inspired by our vibrant, efficient and entrepreneurial spirit. Join our fun, collaborative and reliable team to ignite your dream!\n\nInterested? It\u2019s time to have YOUR MOVE!\nIf you're ready to embark your adventure, start by clicking the \u2018Apply now\u2019 and get on the plane to fly with HK Express", "employment_types": ["Full Time"], "selling_points": ["website management", "UX/UI", "Mobile application"], "locations": ["Airport Area"], "categories": ["E-commerce", "Software Development"], "post_time": "2022-01-11T03:36:36Z", "salary": {"currency": null, "max": null, "min": null, "period": "monthly", "term": null}, "salary_visible": false, "title_keywords": ["specialist", "assistant manager"], "responsibilities": ["ideas", "data", "day-to-day operations", "website", "deploy", "collaborate", "teams", "implementation", "develop", "architecture", "ui", "report", "cost", "management", "review", "booking", "contact", "contents", "documentation", "analytics tools", "systems", "subject matter expert", "planning"], "requirements": {"degrees": ["degree holder"], "majors": [], "languages": [], "language_level": [], "hard_skills": ["analytics tools", "plus", "agile", "fun", "airline", "wechat", "make", "safe", "dynamic", "mobile", "lcc", "programming", "adobe", "documentation", "javascript", "codes"], "soft_skills": ["flexible", "organized", "efficient", "agile", "collaborative", "innovative", "hands-on", "dynamic", "energetic", "reliable", "attention to detail", "creative", "responsive", "driven", "passionate about"], "languages_combined": []}, "experience_required": {"duration": ["3 years", "minimum 5 years"], "field": ["ecommerce", "management", "development", "business", "relevant experience", "programming", "digital", "planning"]}}, {"job_id": "100003009034784", "location_code": "hk", "company": "Mix Solution Company Limited", "job_title": "Senior Web Developer (Freelancer is welcomed too)", "description": "MixCare Health is a healthtech SaaS solution targeting the well-being of employees, insurers and end-users. Our vision is to provide a digitalised, affordable and flexible well-beings solution for companies, hence to drive policyholder and employees\u2019 engagement and health. We have more than 4,500+ consumers and trusted by 1300+ health and wellness vendors in HK. We are now part of Cyberport Incubation Program, HKAI Lab, Mizuho Crowd Brain and EthAum Plug-in ASEAN accelerator.\n\nwww.mixcarehealth.com\n\nJob Highlights\n\nResponsible for development of web/application based applications with insurance, HR solution and fintech companies.\nAssist in user requirement study, system analysis and design, implementation, testing and deployment\nAwesome startup experience\n5-day work week\n\nJob Descriptions\n\nWe are expanding our team and looking for a number of passionate and talented IT professionals to join us and support our business growth.\u00a0\u00a0\n\nExcept supporting our operation team\u2019s daily work, you will take the ownership of the systems to plan and develop new features to enhance the operation workflow.\u00a0\u00a0\n\nResponsibilities\n\nBuild, and maintain efficient, reusable, and reliable PHP code and API\nEnsure the best possible performance, quality, and responsiveness of the applications\nMaintain system stability and bug fixing\nWorking in highly collaborative teams and building quality code\nUnderstanding the business domain deeply and working closely with business stakeholders\n\nRequirements\n\nMinimum 3 year of web development experience working with HTML, CSS, PHP, JavaScript, JQuery, AJAX, and MySQL\nExperienced in PHP framework such as Laravel is an added advantage\nProblem solving skill and able to work independent\nAbility to quickly grasp any new technologies\nGood communication skill in both Chinese (optional) & English\n\n\u00a0Compensation\u00a0\n\nFull-Time: HK$35,000 - $55,000 (negotiable)\nAttractive performance bonus\nCompany shares\n\n\u00a0To learn more the role, please reach out to Kelvin Chu via Whatsapp +852 9872 1830", "employment_types": ["Full Time", "Permanent", "Temporary", "Contract", "Freelance"], "selling_points": ["min 3 years experiences in web development", "HTML, CSS, PHP, JavaScript, JQuery, AJAX, and MySQ", "Regional role and relocation opportunity"], "locations": ["Lai Chi Kok"], "categories": ["Information Technology (IT)", "Application Specialist - Software", "Software Development", "E-commerce", "Software Development"], "post_time": "2022-01-10T04:14:26Z", "salary": {"currency": "HKD", "max": 54999, "min": 35000, "period": "monthly", "term": null}, "salary_visible": true, "title_keywords": ["developer"], "responsibilities": ["systems", "quality", "system stability", "teams", "develop", "maintain", "plan"], "requirements": {"degrees": [], "majors": [], "languages": ["english", "chinese"], "language_level": ["good"], "hard_skills": ["web development", "php", "jquery", "html", "problem solving", "whatsapp", "javascript", "ajax", "css"], "soft_skills": ["problem solving skill", "communication skill", "independent"], "languages_combined": [{"language": "english", "language_level": ["good"]}, {"language": "chinese", "language_level": ["good"]}]}, "experience_required": {"duration": ["minimum 3 year"], "field": ["development"]}}, {"job_id": "100003009043497", "location_code": "hk", "company": "FWD Life Insurance Company (Bermuda) Limited", "job_title": "System Analyst / Senior Analyst Programmer (.NET), Information Technology (3 headcounts, Permanent / 1-year Contract)", "description": "Established in Asia in 2013 with a trailblazer mentality, FWD is the primary insurance business of investment group, Pacific Century Group (PCG), with minority shareholders Swiss Re Group, GIC Ventures, RRJ Capital and Hopu Investments.\n\nFWD spans 10 markets in Asia including Hong Kong SAR & Macau SAR, Thailand, Indonesia, the Philippines, Singapore, Vietnam, Japan, Malaysia and Cambodia. In Hong Kong, FWD offers life and medical insurance, general insurance, employee benefits, and financial planning. We focus on creating fresh customer experiences and making the insurance journey simpler, faster and smoother, with innovative propositions and easy-to-understand products, supported by digital technology. Through this customer-led approach, FWD aims to be a leading pan-Asian insurer by changing the way people feel about insurance.\n\nIf you are looking for a company where can fuel your inspiration and cultivate your expertise, join us on our exciting journey.\n\nThe Job\n\nPerform system design and program specifications preparation\nPerform program development, maintain and enhance environments\nCarry out feasibility study of any new requirements\nPrepare documentation on requirement, technical specification and user manual\nPerform development, testing, implementation, support, maintenance and enhancement\nPrepare SIT / UAT test plan and manage test execution and documentation to ensure completeness and traceability\nPerform user training and prepare user manual\nPerform system implementation and enhancement\nCoordinate with IT and user team on system deployment arrangement\nAd-hoc duties as assigned\n\n\u00a0 \u00a0 \u00a0\nThe Person\n\nUniversity degree in Computer Science or equivalent with 6 years working experience in Information Technology for System Analyst position. Candidate with less experience will be considered as Senior Analyst Programmer position.\nSolid experience in development and implementation of Finance / Life Insurance system\nHands on coding experience in MS .NET application development, preferably with practical experience in ASP.NET, VB.NET or C#.NET application\nHands on MS.NET programming skill, MS SQL/Oracle, JavaScript frameworks and client-server technologies\nSolid understanding Software Development Life Cycle and object-oriented programming (OOP)\nHands on experience on Agile Methodology is preferable\nGood knowledge in Life Insurance products and business flow is preferable\nGood communication skills, able to work with various user departments, technical teams and vendors\nGood analytical mind and problem-solving skills\nAble to work under pressure, Good team player, self-initiative and pro-active\n\nRemark: We have 2 permanent and 1 direct contract (1-year) headcounts, more information will be shared during interview assessment.\n\nWe offer 5-day work, 20-22 days annual leaves, excellent learning & development opportunities and an attractive package to the right candidate.\n\nInformation collected will be treated in strict confidence and used solely for recruitment purpose. The company will retain all applications no longer than 24 months of which will be destroyed thereafter. When there are vacancies in any of our subsidiaries, holding companies, associated or affiliated companies of, or companies controlled by, or under common control with the Company during that period, we may transfer your application to them for consideration of employment. We are an equal opportunity employer. We do not discriminate on the basis of race, sex, disability or family status in employment process.", "employment_types": ["Full Time"], "selling_points": ["Perform system design, testing & implementation", "Exp in ASP.NET, VB.NET or C#.NET application", "Project exposure with fringe benefits"], "locations": ["Kwun Tong"], "categories": ["Information Technology (IT)", "Application Specialist - Software", "Software Development", "E-commerce", "Software Development"], "post_time": "2022-01-12T14:26:08Z", "salary": {"currency": null, "max": null, "min": null, "period": "monthly", "term": null}, "salary_visible": false, "title_keywords": ["system analyst", "senior analyst programmer"], "responsibilities": [], "requirements": {"degrees": [], "majors": [], "languages": [], "language_level": [], "hard_skills": [], "soft_skills": [], "languages_combined": []}, "experience_required": {"duration": [], "field": []}}, {"job_id": "100003009029156", "location_code": "hk", "company": "Money Plaza Hong Kong Limited", "job_title": "Web app Developer/ Programmer", "description": "Job Description\n\nResponsibilities:\u00a0\n\nWork closely with designers and other developers to maintain and develop responsive websites and applications\nResponsible for development, testing, maintenance and documentation.\nPassionate about exploring and learning new technologies and willing to share your knowledge with the team.\nStrongly senses in design, graphics and responsive architecture.\n\nRequirements:\n\nHigher Diploma or Degree holder preferable in Computer Science, Information Engineering or related disciplines\nExperience in\u00a0 Node.js, HTML5, CSS\u00a0 and MVC concepts is a plus.\nKnowledge in Search Engine Optimization (SEO).\nExperience or Good Knowledge of iOS / Android Apps, ReactJS, Flutter and PHP.\nKnowledge in Wordpress is a plus.\nGood team player and able to work independently.\nFull stack experience programmer can be considered as a senior role\n\nWe offer a competitive remuneration package to the right candidate, interested candidate please send us your CV with expected salary. Thanks.", "employment_types": ["Full Time", "Part Time", "Permanent", "Contract", "Freelance"], "selling_points": ["Passionate in a highly growth industry", "Flexible employment terms - project based possible", "Great Compensation with performance bonus"], "locations": ["Tsuen Wan Area"], "categories": ["Information Technology (IT)", "Application Specialist - Software", "E-commerce", "Software Development", "UI/UX Designer"], "post_time": "2022-01-10T02:50:26Z", "salary": {"currency": null, "max": null, "min": null, "period": "monthly", "term": null}, "salary_visible": false, "title_keywords": ["developer", "programmer"], "responsibilities": ["graphics", "maintenance", "design", "testing", "develop", "maintain", "documentation", "architecture"], "requirements": {"degrees": ["diploma", "degree holder"], "majors": ["related disciplines", "engineering", "computer science"], "languages": [], "language_level": [], "hard_skills": ["plus", "seo", "php", "wordpress", "css", "android"], "soft_skills": ["good team player", "work independently"], "languages_combined": []}, "experience_required": {"duration": [], "field": []}}, {"job_id": "100003009037153", "location_code": "hk", "company": "Centaline Data Technology Limited", "job_title": "UX / UI Designer (5-day work)", "description": "To cope with our continuous growth and business expansion, we are looking for energetic and high calibre of candidates to join.\u00a0\n\nDuties:\n\n\nResponsible for user interface design of system, mobile apps and websites\nBanner, image retouch and other graphics design\n\n\nRequirements:\n\n\nDiploma holder or above in Web / Multimedia / Graphics design or related discipline;\nAt least\u00a03 years\u2019 solid experience in Web/App/Multimedia design;\nProficiency in graphics & web design tools such as Adobe Photoshop,\u00a0 Illustrator, XD or Sketch;\nKnowledge of design, prototyping tools and usability best practices in wire frames and prototypes;\nStrong sense on responsive design, UI/UX and technology trends;\nKnowledge of iOS & Android app official UI guideline;\nKnowledge of JavaScript, HTML5, CSS3\u00a0is a plus;\nResponsible, detail-minded, have good interpersonal and communication skills;\nImmediately available is preferable;\nCandidates with more experience will be considered as Senior UX/UI Designer\n\nAt least\u00a03 portfolios provided\u00a0for review is a must\n\nInterested parties, please send full resume with CURRENT & EXPECTED SALARY to Centaline Data Technology Limited.", "employment_types": ["Full Time", "Permanent"], "selling_points": ["Diploma in Web / Multimedia / Graphics design", "Solid exp in Web/App/Multimedia design", "Quaterly Bonus / Medical & Study Allowance, etc"], "locations": ["Tsim Sha Tsui"], "categories": ["Design", "Multi-media", "E-commerce", "Software Development", "Information Technology (IT)", "UI/UX Designer"], "post_time": "2022-01-11T01:55:07Z", "salary": {"currency": null, "max": null, "min": null, "period": "monthly", "term": null}, "salary_visible": false, "title_keywords": ["ui designer"], "responsibilities": ["graphics", "user interface", "design"], "requirements": {"degrees": ["diploma holder"], "majors": ["design"], "languages": [], "language_level": [], "hard_skills": ["graphics", "web design", "plus", "web", "adobe photoshop", "illustrator", "javascript", "multimedia", "android"], "soft_skills": ["detail-minded", "communication skills", "responsible", "responsive", "interpersonal"], "languages_combined": []}, "experience_required": {"duration": ["at least 3 years"], "field": ["designer", "design"]}}, {"job_id": "100003009053512", "location_code": "hk", "company": "Bape Hong Kong Limited", "job_title": "Senior Business Analyst - Ecommerce", "description": "Accountabilities \u2013 Key Result Areas\n\n\n\nAct as the subject matter expert in digital and consumer applications (e.g., E-Commerce, CRM)\nParticipate in digital transformation projects in the areas of business requirements collection, process development, functional spec development, testing etc.\nManage both internal and external resources for system enhancements and projects\nManage business demands, analyze business requirements and ensure consistent communication to all stakeholders across all levels on project status, issues and risks\nWork with cross-functional teams to design, evaluate, and prioritize product features to shape the development roadmap of Company\u2019s digital transformation\nSupport the business to ensure smooth production systems operations\nApply ITIL methodology in problem, issue change and enhancement management\nExperience / Qualification Requirements\n\n\nDegree in Computer Science or a related technical field\n5 years\u2019 online product management or E-Commerce platform management experience\nExperience in e-Commerce platform e.g. Shopify, Web application, mobile APP, O2O, CRM and/or digital transformation, preferable in retail industry\nFamiliar with project management lifecycles\nStrong communicator, both verbal and written, proven ability to coordinate different teams of Vendors, Internal Developers and\u00a0Marketing\nFast learner for various online and offline retail business processes\nStrong written and verbal language efficiency in English, Cantonese, and Mandarin\n\nCompetitive remuneration and benefit package will be offered to the right candidate. Please submit your application by clicking \"Apply Now\" below.\n\n\n\nAll data collected is for recruitment purpose only.", "employment_types": ["Full Time"], "selling_points": ["5 years\u2019 e-Commerce platform management experience", "Participate in digital transformation projects", "Familiar with project management lifecycles"], "locations": ["Southern Area"], "categories": ["Information Technology (IT)", "Product Management / Business Analyst", "E-commerce", "Product Management / Business Analyst", "Software Development"], "post_time": "2022-01-17T07:04:31Z", "salary": {"currency": null, "max": null, "min": null, "period": "monthly", "term": null}, "salary_visible": false, "title_keywords": ["senior business analyst"], "responsibilities": ["management", "mobile app", "data", "operations", "systems", "teams", "subject matter expert", "design", "testing", "communication", "evaluate", "project management", "coordinate", "recruitment", "e-commerce platform", "cross-functional teams"], "requirements": {"degrees": ["degree"], "majors": ["computer science"], "languages": ["cantonese", "english", "mandarin"], "language_level": [], "hard_skills": ["itil", "web", "e-commerce", "shopify", "mobile", "project management"], "soft_skills": ["prioritize", "communication", "project management", "smooth", "communicator", "fast learner"], "languages_combined": [{"language": "cantonese", "language_level": []}, {"language": "english", "language_level": []}, {"language": "mandarin", "language_level": []}]}, "experience_required": {"duration": ["5 years"], "field": ["product management", "management", "e-commerce"]}}, {"job_id": "100003009034787", "location_code": "hk", "company": "HomePlus (Hong Kong) Limited (HOME+)", "job_title": "AWS Engineer / AWS Administrator", "description": "This\u00a0position will be under HOME+ e-commerce platform.\n\nOur Vision of Home+ is to set up a merchant ecosystem of merchants with shared value, covering different aspects of our customers\u2019 daily household purchases. The mission is to provide customers with the best value for money for the promotional products and services offered, from time to time. For more information, please feel free to visit our website at\u00a0https://home-plus.hk/\n\nTo be part of our mission, we are looking for an AWS Engineer / AWS Administrator to\u2026\n\nAct as first contact person in case of alerts\nDesign and\u00a0maintain highly available, cloud-based infrastructures in AWS.\nUnderstand of auto-scaling technologies and high-throughput designs.\nMonitor and troubleshoot in case of alerts and manage incidents to closure.\nManage full AWS Lifecycle, Provisioning, Automation and Security.\nConfigure and fine-tune cloud infrastructure systems.\nPerform software upgrades. Kernel patching, errata patches.\nAutomate deployment of infrastructure through the use of Cloud Formation or Terraform.\nEnforce resource tagging to designate costs and for planning of budgeting, governance, and reporting.\nCommunicate with the Cloud team to manage network connections on VPCs, VPNs.\nMonitor billing and to develop cost optimization strategies.\nEnforce AWS best practice in managing infrastructure\nMaintain a backup plan for all resources used on AWS.\nManage disaster recovery and create backups.\n\nThe follow attributes will be valued\u2026\n\n0 -2 years of experience in building infrastructure for enterprise applications and solutions using AWS.\nExperience with AWS cloud-based architectures\nExperience on using metrics to monitor the health, utilization and availability of AWS resources on a full scale by Amazon CloudWatch, CloudTrail and third party tools such as NewRelic.\nVery strong skills on the basics (Route53, EC2, ACM, ELB, VPC and S3).\nHands on experience on overcoming and protecting against a DDoS attack.\nHands on implementing one or more CloudFront Distributions and the core use-cases for a CDN.\n\nWhat you get in return\u2026\n\nApart from competitive salary package and benefits, in HKBN, you will work flexibly under our Talent-first\u00a0culture\u00a0and we uphold Life-Work Priority. Examples of our flexible initiatives:\n\nFive-day work week and shorten working hours (8 hours including 1 hour 15 mins meal break)\nHalf Day Off Friday once a month (compensation leave for Talents who work on shift)\nHalf Day Off on Festival Eve (compensation leave for Talents who work on shift)\nUnique leaves arrangement: Family-care leave, Anniversary leave, Bonus leave, Volunteer leave, Sabbatical leave, etc.\nComprehensive medical and life insurance coverage\nUpgraded maternity leave and paternity leave\nDiscounted Talent plan offers including broadband and mobile plans and other promoted products\nEducation subsidies and Examination leave\nYear-end discretionary bonus\n\n\n", "employment_types": ["Full Time", "Permanent"], "selling_points": ["Maintain cloud-based infrastructure in AWS", "Manage full AWS Lifecycle/Provisioning/Automation", "Monitor health/utilization/AWS Resources"], "locations": ["Kwai Hing"], "categories": ["Information Technology (IT)", "Support", "Technical Writing", "E-commerce", "Software Development"], "post_time": "2022-01-10T04:14:54Z", "salary": {"currency": null, "max": null, "min": null, "period": "monthly", "term": null}, "salary_visible": false, "title_keywords": ["administrator", "engineer"], "responsibilities": ["software", "budgeting", "website", "design", "maintain", "troubleshoot", "plan", "costs", "infrastructure", "monitor", "develop", "reporting", "upgrades", "contact", "backups", "third party", "communicate with", "cost optimization", "systems", "e-commerce platform", "planning"], "requirements": {"degrees": [], "majors": [], "languages": [], "language_level": [], "hard_skills": ["plus", "amazon", "e-commerce", "aws", "deployment", "s3"], "soft_skills": ["hands on", "troubleshoot"], "languages_combined": []}, "experience_required": {"duration": ["0 -2 years"], "field": ["infrastructure"]}}, {"job_id": "100003009033425", "location_code": "hk", "company": "Calioo Technologies", "job_title": "Product Manager", "description": "At the core of Accenture's Technology business, you are eager to learn and use that curiosity to solve technology problems through developing, designing and maintaining software products or systems that enable client strategies to improve the way our clients and the world works. You will be using your versatility and experience to create and support technology solutions that meet client requirements from analysis to implementation. The latest SDLC best practices will be applied to continuously improve the quality and efficiency of the Accenture development teams.\n\nKey Competencies & Experience Requirement\n\u2022 2+ years hands-on experience in application design and development on large scale/ mission critical systems using different technologies\n\u2022 Strong in Backend integration development with technologies that are market relevant (such as Native Mobile, Responsive UI, HTML, Angular, JavaScript, React, Java, Spring, Node.js, MongoDB, node.JS, Kafka, DevOps, ETL...)\n\u2022 Interested to explore other technologies integration, and act as a full-stack development professional\n\u2022 Passionate and keen to develop your profession in technical delivery, and strive to deliver the best design, codes and practice\n\u2022 Excellent communication skill and the ability to interact professionally with diverse group of stakeholders, internally and externally\n\u2022 University Degree in Computer Science/Engineering, Information Technology/System, or other relevant disciplines desirable\n\u2022 High proficiency in both verbal and written English and Cantonese (Mandarin is an added advantage)\n\u2022 Dynamic and adaptive to the global collaborative project team environment", "employment_types": ["Full Time", "Part Time", "Permanent", "Contract"], "selling_points": [], "locations": ["Causeway Bay"], "categories": ["Information Technology (IT)", "Product Management / Business Analyst", "Software Development", "E-commerce", "Software Development"], "post_time": "2022-01-09T15:36:59Z", "salary": {"currency": null, "max": null, "min": null, "period": null, "term": null}, "salary_visible": false, "title_keywords": ["product manager"], "responsibilities": ["software", "maintaining", "analysis", "systems", "quality", "developing", "implementation", "teams", "design", "develop", "communication", "designing", "ui"], "requirements": {"degrees": ["university degree"], "majors": ["engineering", "computer science", "information technology"], "languages": ["cantonese", "english", "mandarin"], "language_level": ["advantage", "proficiency"], "hard_skills": ["java", "react", "analysis", "devops", "html", "mobile", "sdlc", "javascript", "dynamic", "angular", "spring", "integration", "codes"], "soft_skills": ["passionate", "keen", "communication skill", "collaborative", "eager to learn", "hands-on", "diverse", "dynamic", "responsive"], "languages_combined": [{"language": "cantonese", "language_level": ["proficiency"]}, {"language": "english", "language_level": ["proficiency"]}, {"language": "mandarin", "language_level": ["advantage", "proficiency"]}]}, "experience_required": {"duration": ["2+ years"], "field": ["development", "design"]}}, {"job_id": "100003009035237", "location_code": "hk", "company": "FWD Life Insurance Company (Bermuda) Limited", "job_title": "System Analyst / Senior Analyst Programmer (Java), Information Technology (few headcounts, Permanent / 1-year Contract)", "description": "Responsibilities\n\n\nOversee the development of UI design and experience of both web and mobile applications by translating brand value, proposition and product insights\nDefine & maintain the branding & design guidelines and set global design standard, best practices and standards across the digital team\u2019s output\nCollaborate closely with Business Development Team, Product Development Team & Digital Team to understand the design needs and optimize user experience\nWork with the Digital Team to assess the impact of UI design and to conduct A/B testing\nCreate world-class, customer-centered designs through consideration of market research, business requirements, customer feedback, and usability study findings\nActively conducting or participating in usability research and testing\nFacilitate design thinking workshops to synthesize the outputs to craft ideas and solutions for prototyping\n\nRequirements\n\n\nBachelor\u2019s degree or equivalent required\n8 years of Digital Product development & management experience in B2B/B2C domain\nExpertise in user interface and user experience design\nExcellent understanding of UX principles: research, conceptualization, development, etc.\nDemonstrated ability to incorporate design thinking into the product development process\nStrong understanding on User Research, User Task Flow, Wireframe, Storyboards, Information Architecture and Usability\nProficiency in software like Sketch, Adobe XD, Figma, Illustrator, InVision Studio, etc.\nExperience in Agile software development with Scrum or other Agile methodologies/frameworks\nHigh degree of internet savvy, with a curiosity and enthusiasm for digital or media trend\nSolid experience in developing enterprise level of web and mobile applications (iOS/Android) with track record\nGood experience in change management with skills gained in a diversified organization\nProven ability to translate business requirements into high quality, cost effective solutions\nExcellent communication, interpersonal, planning and organization skills\nExperience in textile and manufacturing industry is an advantage", "employment_types": ["Full Time"], "selling_points": ["Assist in system design & prepare program spec", "3 years exp of Java, JavaScript, Angular & Spring", "Project exposure with great career opportunity"], "locations": ["Kwun Tong"], "categories": ["Information Technology (IT)", "Application Specialist - Software", "Software Development", "E-commerce", "Software Development"], "post_time": "2022-01-10T06:27:55Z", "salary": {"currency": null, "max": null, "min": null, "period": "monthly", "term": null}, "salary_visible": false, "title_keywords": ["system analyst", "senior analyst programmer"], "responsibilities": ["collaborate", "ideas", "guidelines", "user experience", "design", "testing", "market research", "facilitate design", "maintain", "ui"], "requirements": {"degrees": ["degree", "bachelor"], "majors": [], "languages": [], "language_level": [], "hard_skills": ["agile", "web", "adobe xd", "illustrator", "mobile", "android"], "soft_skills": ["communication", "interpersonal", "organization skills", "agile"], "languages_combined": []}, "experience_required": {"duration": ["8 years"], "field": ["management", "developing", "design", "software development", "textile", "digital", "product development", "manufacturing industry"]}}, {"job_id": "100003009035243", "location_code": "hk", "company": "FWD Life Insurance Company (Bermuda) Limited", "job_title": "Senior Analyst Programmer (Cloud Project, Angular, Node.js), Information Technology (2-year Contract)", "description": "Established in Asia in 2013 with a trailblazer mentality, FWD is the primary insurance business of investment group, Pacific Century Group (PCG), with minority shareholders Swiss Re Group, GIC Ventures, RRJ Capital and Hopu Investments.\n\nFWD spans 10 markets in Asia including Hong Kong SAR & Macau SAR, Thailand, Indonesia, the Philippines, Singapore, Vietnam, Japan, Malaysia and Cambodia. In Hong Kong, FWD offers life and medical insurance, general insurance, employee benefits, and financial planning. We focus on creating fresh customer experiences and making the insurance journey simpler, faster and smoother, with innovative propositions and easy-to-understand products, supported by digital technology. Through this customer-led approach, FWD aims to be a leading pan-Asian insurer by changing the way people feel about insurance.\n\nIf you are looking for a company where can fuel your inspiration and cultivate your expertise, join us on our exciting journey.\n\nThe Job\n\nAssist to manage projects implementation and development\nCoordinate and facilitate the project execution related activities\nCarry out feasibility study of any new requirements\nPrepare documentation on requirement, technical specification and user manual\nPerform system design, development, testing, implementation, support, maintenance and enhancement\nGather business requirements, perform analysis and work out project prioritization which agree with business and IT team.\nPrepare SIT / UAT test plan and manage test execution and documentation to ensure completeness and traceability.\nPerform user training and prepare user manual\nCoordinate with IT application, IT security, IT infrastructure and user team on system deployment arrangement\nAd hoc duties as assigned\n\nThe Person\n\nUniversity degree in Computer Science or equivalent, minimum 5 years' related working experience\nExperience in development and implementation of Web Application\nProficient in .NET, JavaScript, JQuery , HTML5, PHP, web application development\nSolid experience in development, trouble shooting and performance tuning in RDBMS (MS SQL, mySQL, Oracle)\nExperience with Microservice, API and Web Services, e.g. REST, SOAP\nExperience in WordPress development is a plus\nAzure Cloud and Mongo knowledge is preferable\nGood knowledge of software implementation best practices\nGood project management (Waterfall/Agile Scrum) and communication skills, able to work with user departments and vendors\nGood problem solving skills and communication\nAble to work under pressure\nGood team player, self-initiative and pro-active\n\nInformation collected will be treated in strict confidence and used solely for recruitment purpose. The company will retain all applications no longer than 24 months of which will be destroyed thereafter. When there are vacancies in any of our subsidiaries, holding companies, associated or affiliated companies of, or companies controlled by, or under common control with the Company during that period, we may transfer your application to them for consideration of employment. We are an equal opportunity employer. We do not discriminate on the basis of race, sex, disability or family status in employment process.", "employment_types": ["Full Time"], "selling_points": ["Perform system design, development & testing", "4 years exp on Node.js, AngularJS, Java & .Net", "Project exposure in cloud and transformation"], "locations": ["Kwun Tong"], "categories": ["Information Technology (IT)", "Application Specialist - Software", "Software Development", "E-commerce", "Software Development"], "post_time": "2022-01-10T06:28:21Z", "salary": {"currency": null, "max": null, "min": null, "period": "monthly", "term": null}, "salary_visible": false, "title_keywords": ["senior analyst programmer"], "responsibilities": [], "requirements": {"degrees": [], "majors": [], "languages": [], "language_level": [], "hard_skills": [], "soft_skills": [], "languages_combined": []}, "experience_required": {"duration": [], "field": []}}, {"job_id": "100003009028359", "location_code": "hk", "company": "Drake Overload Ltd", "job_title": "Programmer - Fresh Graduate Welcome", "description": "About Calioo\n\nCalioo is transforming the way people discover and experience food.\u00a0\n\nFounded by some of the most prominent leaders within the food tech industry in Asia,\u00a0Calioo is Hong Kong\u2019s leading online marketplace that brings together the most unique handcrafted food from HK\u2019s local small businesses and the community through a shared passion for food. We are committed to inspire and empower home grown chefs to share their culinary ideas and build it into businesses. At Calioo, everyday is a new journey where you will discover one of a kind food that will surprise your taste buds.\u00a0\n\nJoin us in our mission of empowering our small business community and helping customers discover the latest and tastiest artisanal food!\u00a0\n\nAs a Product Manager, you will be working closely with the founder to help build the next 2.0 product and grow the business for Hong Kong. Calioo is a flat organisation so you are expect to be proactively taking up various responsibilities in different units. If you are a marathon sprinter- you are someone who enjoys a fast paced environment, with unlimited energy and obsessed with learning something new everyday, this is the perfect position for you.\n\nJob Requirements:\u00a0\n\nDevelop technical aspects of the company\u2019s strategy to ensure alignment with its business goals\nDiscover and implement new technologies that yield competitive advantage\nSupervise system infrastructure to ensure functionality and efficiency\nBuild quality assurance and data protection processes\nMonitor KPIs and IT budgets to assess technological performance\nManage data partnerships from introduction, demo to signed commercial agreements\nGather business requirements, write feature requirements and map out customer journey\nCollaborate with other teams in the company to refine product backlog and project plan\nProvide support to the QA teams on UAT when needed\nCarry out user feedback session, product discovery, feature research and competitor analysis to ensure product market fit\nDrive product analytics plan for your features and use the data to conduct experiments\n\nWho are we looking for?\n\n\u2022 Independent thinkers with a startup and mamba mentality who can work with limited resources\u00a0\n\n\u2022 An independent fast learner with critical thinking\n\n\u2022 Embrace new challenges and enjoy living within the uncertainties\n\n\u2022 Excellent communication and interpersonal skills, fluency in both English and Cantonese", "employment_types": ["Full Time", "Permanent"], "selling_points": ["Web application development in Java, PHP", "Fresh Graduate Welcome", "In-house team, permanent role, 5-days work, FSI"], "locations": ["Quarry Bay"], "categories": ["Information Technology (IT)", "Application Specialist - Software", "Software Development", "E-commerce", "Software Development"], "post_time": "2022-01-07T02:07:56Z", "salary": {"currency": null, "max": null, "min": null, "period": "monthly", "term": null}, "salary_visible": false, "title_keywords": ["programmer"], "responsibilities": ["collaborate with", "budgets", "business goals", "provide support", "ideas", "uat", "data", "analysis", "infrastructure", "quality", "monitor", "teams", "develop", "project plan", "communication", "plan", "kpis"], "requirements": {"degrees": [], "majors": [], "languages": ["cantonese", "english"], "language_level": ["fluency", "excellent"], "hard_skills": ["small", "analysis"], "soft_skills": ["independent", "passion for", "unique", "committed", "learning", "communication and interpersonal skills", "organisation", "fast learner"], "languages_combined": [{"language": "cantonese", "language_level": ["fluency", "excellent"]}, {"language": "english", "language_level": ["fluency", "excellent"]}]}, "experience_required": {"duration": [], "field": ["food"]}}, {"job_id": "100003009031940", "location_code": "hk", "company": "Q P Group Holdings Limited", "job_title": "System Analyst (e-Commerce)", "description": "Established in Asia in 2013 with a trailblazer mentality, FWD is the primary insurance business of investment group, Pacific Century Group (PCG), with minority shareholders Swiss Re Group, GIC Ventures, RRJ Capital and Hopu Investments.\n\nFWD spans 10 markets in Asia including Hong Kong SAR & Macau SAR, Thailand, Indonesia, the Philippines, Singapore, Vietnam, Japan, Malaysia and Cambodia. In Hong Kong, FWD offers life and medical insurance, general insurance, employee benefits, and financial planning. We focus on creating fresh customer experiences and making the insurance journey simpler, faster and smoother, with innovative propositions and easy-to-understand products, supported by digital technology. Through this customer-led approach, FWD aims to be a leading pan-Asian insurer by changing the way people feel about insurance.\n\nIf you are looking for a company where can fuel your inspiration and cultivate your expertise, join us on our exciting journey.\n\nThe Job\n\nAssist in system design and prepare program specifications\nPerform program development and maintain enhance environments\nCarry out feasibility study of any new requirements\nPrepare documentation on requirement, technical specification and user manual\nResponsible for system design, development, testing, implementation, support, maintenance and enhancement\nPrepare SIT / UAT test plan and manage test execution and documentation to ensure completeness and traceability.\nPerform user training and prepare user manual\nPerform system implementation and enhancement\nCoordinate with IT and user team on system deployment arrangement\nEvaluate and recommend new IT products and technologies\nAd-hoc duties as assigned\n\n\u00a0 \u00a0 \u00a0\nThe Person\n\nUniversity degree in Computer Science or equivalent, minimum 3 years working experience in Information Technology\nCandidate with more experience will be considered as System Analyst\nSolid experience in development and implementation of Life Insurance systems\nProficient in Java application development, preferably with practical experience in large scale J2EE application\nGood knowledge in Life Insurance products and business flow\nHands on Java programming skill, MS SQL/Oracle, JavaScript, Angular, Spring Boot, Hibernate and client-server technologies\nExperience in micro-service design and DevOps is preferable\nExperience in DevOps tools such as Jenkins, sonarqube, selenium automation testing, Appium would be an advantage\nFamiliar Docker Solution such as (OpenShift and kubernetes) and experience in MongoDB\nGood communication skills, able to work with different user departments, good team player, self-initiative and pro-active\nGood analytical mind and problem solving skills\nAble to work under pressure\n\nRemark: We have both permanent and direct contract (1-year) headcounts, more information will be shared during interview assessment.\n\nWe offer 5-day work, 20-22 days annual leaves, excellent learning & development opportunities and an attractive package to the right candidate.\n\nInformation collected will be treated in strict confidence and used solely for recruitment purpose. The company will retain all applications no longer than 24 months of which will be destroyed thereafter. When there are vacancies in any of our subsidiaries, holding companies, associated or affiliated companies of, or companies controlled by, or under common control with the Company during that period, we may transfer your application to them for consideration of employment. We are an equal opportunity employer. We do not discriminate on the basis of race, sex, disability or family status in employment process.", "employment_types": ["Full Time", "Permanent"], "selling_points": ["Develop B2B2C e-Commerce Platform", "Highly dynamic and innovative team", "WordPress + Woo Commerce"], "locations": ["Shatin Area"], "categories": ["Information Technology (IT)", "Application Specialist - Software", "Network & System", "E-commerce", "Software Development"], "post_time": "2022-01-07T19:21:00Z", "salary": {"currency": null, "max": null, "min": null, "period": "monthly", "term": null}, "salary_visible": false, "title_keywords": ["system analyst"], "responsibilities": [], "requirements": {"degrees": [], "majors": [], "languages": [], "language_level": [], "hard_skills": [], "soft_skills": [], "languages_combined": []}, "experience_required": {"duration": [], "field": []}}, {"job_id": "100003009031155", "location_code": "hk", "company": "Ztore HK Limited", "job_title": "Analyst Programmer (PHP, ERP)", "description": "Opportunities:\n\nDevelop B2B2C e-Commerce Platform with latest technologies\nBe a teammate in a highly dynamic and innovative team in Agile/Scrum approach\n\nResponsibilities:\n\nResponsible for the eCommerce Platform (WordPress + WooCommerce) Development: User requirement collection and feasibility study; Convert systems requirements into application systems through system design and physical development of the system on cloud environment\nAnalysis requirement and provide requirement specification, functional specification, system design, prototype\nParticipate in Agile/Scrum Project Management, coordinate with different stakeholders to gather and convert new business requirement/workflow to new change request\nLead development team for system design, development, testing, quality assurance and system launch; and monitor their progress through project planning, project tasks review and status report\nPerform adhoc tasks assigned by Project Manager\n\nRequirements:\n\nDegree / Higher Diploma in Computer Science, Information Technology or related disciplines\nAt least 7 years working experience, with at least 3 years in development, system, database and architectural design in WordPress + WooCommerce / e-Commerce Platform\nHands-on experience in web application design and development (PHP, HTML5, CSS, Vue.js, React.js, Node.js, Responsive Design), good knowledge in RDBMS (e.g. Oracle, MSSQL, MySQL) and NoSQL (e.g. Mongo DB)\nHands-on experience in Project Management Tool, e.g. Open Project, JIRA\nHands-on experience in Git or related version control concepts\nExperience with Agile/Scrum Development, Microservices architecture and REST API Integration\nExperience with SEO, Google Analytics, Cloud (Azure/AWS) serverless development (Azure Function/AWS Lambda, Docker Container, DevOps+CI/CD) would be an advantage\nStrong analytical skills, self-motivated and good leadership, can work independently and deal with the tight project schedule\nGood command of written and spoken English and Mandarin\nCandidate with more experience will be considered as Senior System Analyst\n\n\n\nApplication:\n\nPlease send your CV, existing salary & expected salary in WORD format to hkghr @ qpp.com. \u00a0\n\nAll personal information collected will be kept for employment related purposes only.", "employment_types": ["Full Time"], "selling_points": ["PHP, Laravel", "Latest techs: Docker, Swoole, Message Queue", "Test Driven Development"], "locations": ["Lai Chi Kok"], "categories": ["E-commerce", "Software Development"], "post_time": "2022-01-07T09:01:16Z", "salary": {"currency": null, "max": null, "min": null, "period": "monthly", "term": null}, "salary_visible": false, "title_keywords": ["analyst programmer"], "responsibilities": ["user requirement", "project planning", "analysis", "systems", "coordinate with", "quality", "monitor", "testing", "review", "project management", "system design", "application systems", "report"], "requirements": {"degrees": ["diploma", "degree"], "majors": ["related disciplines", "computer science", "information technology"], "languages": ["english", "mandarin"], "language_level": ["good command"], "hard_skills": ["azure", "agile", "e-commerce", "word", "web application design", "git", "microservices", "integration", "mssql", "seo", "aws", "analytical skills", "wordpress", "container", "oracle", "google analytics", "php", "react", "project management", "css"], "soft_skills": ["self-motivated", "work independently", "agile", "analytical skills", "project management", "hands-on", "leadership", "responsive"], "languages_combined": [{"language": "english", "language_level": ["good command"]}, {"language": "mandarin", "language_level": ["good command"]}]}, "experience_required": {"duration": ["at least 3 years", "at least 7 years"], "field": ["e-commerce", "related", "development", "design", "project management", "database", "system analyst"]}}, {"job_id": "100003009029155", "location_code": "hk", "company": "HomePlus (Hong Kong) Limited", "job_title": "Android App Developer - HOME+ E-Commerce Platform", "description": "Established in Asia in 2013 with a trailblazer mentality, FWD is the primary insurance business of investment group, Pacific Century Group (PCG), with minority shareholders Swiss Re Group, GIC Ventures, RRJ Capital and Hopu Investments.\n\nFWD spans 10 markets in Asia including Hong Kong SAR & Macau SAR, Thailand, Indonesia, the Philippines, Singapore, Vietnam, Japan, Malaysia and Cambodia. In Hong Kong, FWD offers life and medical insurance, general insurance, employee benefits, and financial planning. We focus on creating fresh customer experiences and making the insurance journey simpler, faster and smoother, with innovative propositions and easy-to-understand products, supported by digital technology. Through this customer-led approach, FWD aims to be a leading pan-Asian insurer by changing the way people feel about insurance.\n\nIf you are looking for a company where can fuel your inspiration and cultivate your expertise, join us on our exciting journey.\n\nThe Job\n\nResponsible for the development of web portals, API integrations with different systems\nMigrate exiting applications to Azure\nPrepare documentation on functional and technical specification\nPrepare SIT / UAT test plan and manage test execution and documentation to ensure completeness and traceability\nEnsure change requests are well managed and prioritized according to project plan\nAd-hoc duties as assigned\n\nThe Person\n\nUniversity degree in Computer Science or equivalent\nMinimum 3 years working experience in application development\nSolid experience in using Angular, Node.js and/or React etc.\nSolid understanding of object-oriented programming (OOP)\nProficient in MS SQL\nExperience with Microservice, API and Web Services, e.g. REST, SOAP\nCloud service knowledge such as Azure, AWS experience\u00a0\nGood team player, self-initiative and pro-active\nExperience with mobile development is a plus\n\nInformation collected will be treated in strict confidence and used solely for recruitment purpose. The company will retain all applications no longer than 24 months of which will be destroyed thereafter. When there are vacancies in any of our subsidiaries, holding companies, associated or affiliated companies of, or companies controlled by, or under common control with the Company during that period, we may transfer your application to them for consideration of employment. We are an equal opportunity employer. We do not discriminate on the basis of race, sex, disability or family status in employment process.", "employment_types": ["Full Time", "Permanent"], "selling_points": ["Implementation and testing of web application", "Experience in web application development", "LIFE-Work Priority & Talent-first Culture"], "locations": ["Kwai Hing"], "categories": ["Information Technology (IT)", "Application Specialist - Software", "Technical Writing", "E-commerce", "Software Development"], "post_time": "2022-01-07T04:06:54Z", "salary": {"currency": null, "max": null, "min": null, "period": "monthly", "term": null}, "salary_visible": false, "title_keywords": ["developer"], "responsibilities": [], "requirements": {"degrees": [], "majors": [], "languages": [], "language_level": [], "hard_skills": [], "soft_skills": [], "languages_combined": []}, "experience_required": {"duration": [], "field": []}}, {"job_id": "100003009030139", "location_code": "hk", "company": "Sing Tao Management Services Limited", "job_title": "E-Commerce Platform Specialist (Shimba)", "description": "Why we are looking for this position?\n\nWe are expanding our team and looking for a number of passionate and talented IT professionals to join us and support our business to grow innovatively.\n\nExcept supporting our operation team\u2019s daily work, you will take the ownership of the systems to plan and develop new feature to enhance the operation workflow.\n\nResponsibilities\n\nCommunicating with commercial side colleague, translating business idea and use cases into functional applications\nDesign, build, and maintain efficient, reusable, and reliable PHP code\nEnsure the best possible performance, quality, and responsiveness of the applications\nIdentify bottlenecks and bugs, and devise solutions to these problems\nHelp maintain code quality, organisation, and automatisation\nWorking in highly collaborative teams and building quality code\nUnderstanding the business domain deeply and working closely with business stakeholders\nRequirements\n\nMinimum 4 Year of web development experience working with HTML, CSS, PHP, JavaScript, JQuery, AJAX, and MySQL\nExperienced in PHP framework such as Laravel is an added advantage\nExperienced in project management is an added advantage\nProblem solving skill and able to work independent\nAbility to quickly grasp any new technologies\nGood communication skill in both Chinese & English\nWhat you will learn:\n\nAuto CI/CD\nVersioning tools, such as Git\nContainerized Application (Docker, AWS Fargate)\nHow to solve a business problem\nHow to manage a project\nExperienced in a well-planned software development cycle\n\u202fWhat We Offer?\n\n5-day work week\nCompetitive remuneration\nFlexible working hour\nAwesome startup experience\nInteresting problems and smart coworkers\nOpportunity to grow your skills and learn new ones\u202f", "employment_types": ["Full Time", "Permanent"], "selling_points": [], "locations": ["Tseung Kwan O"], "categories": ["E-commerce", "Marketing - Brand / Product Management", "Product Management / Business Analyst", "Software Development"], "post_time": "2022-01-07T06:51:44Z", "salary": {"currency": null, "max": null, "min": null, "period": "monthly", "term": null}, "salary_visible": false, "title_keywords": ["specialist"], "responsibilities": ["teams", "quality", "design", "maintain", "communicating with"], "requirements": {"degrees": [], "majors": [], "languages": ["english", "chinese"], "language_level": ["good"], "hard_skills": ["web development", "git", "php", "jquery", "html", "aws", "problem solving", "project management", "javascript", "ajax", "css"], "soft_skills": ["project management", "problem solving skill", "communication skill", "independent"], "languages_combined": [{"language": "english", "language_level": ["good"]}, {"language": "chinese", "language_level": ["good"]}]}, "experience_required": {"duration": ["minimum 4 year"], "field": ["development"]}}, {"job_id": "100003009032960", "location_code": "hk", "company": "Ringus Solution Enterprise Limited", "job_title": "Mobile Developer / Programmer (12 months Contract/Permanent)", "description": "This\u00a0position will be under HOME+ e-commerce platform.\n\nTo be part of our mission, we are looking for an Android Mobile Application Developer to\u2026\n\nDevelop, enhance & maintain e-commerce mobile native application with latest cloud, web & mobile technologies\nWorking with a highly dynamic and innovative team (both internal & external parties) in Agile/Scrum approach.\n\nWhat efforts you need to make?\n\nDevelop and support the mobile application for our e-commerce system\nParticipate in Mobile Application design, coding, testing, and documentation\nDiscuss and advise Mobile Application requirements from users\nDesign the API spec for support the mobile app\n\nLet's check if you are/have...\n\nDegree holder in Computer Science, Engineering or equivalent is preferred\nMinimum 3-5 years' hands on experience on Android native development\u00a0(Kotlin)\nFamiliar with Agile development methodology\nStrong communication and people skills, needs to interact with diversified group of stakeholders such as different departments of the team, vendors, partners\nInnovative and strong analytical skill\nKeen on technology and able to pick up latest technical skills\nExperience on e-commerce business is a big advantage\nExperience on Flutter / React Native is an advantage\n\n\n\nWhat you get in return\u2026\n\nApart from competitive salary package and benefits, in HKBN, you will work flexibly under our Talent-first\u00a0culture\u00a0and we uphold Life-Work Priority. Examples of our flexible initiatives:\n\nFive-day work week and shorten working hours (8 hours including 1 hour 15 mins meal break)\nHalf Day Off Friday once a month (compensation leave for Talents who work on shift)\nHalf Day Off on Festival Eve (compensation leave for Talents who work on shift)\nUnique leaves arrangement: Family-care leave, Anniversary leave, Bonus leave, Volunteer leave, Sabbatical leave, etc.\nComprehensive medical and life insurance coverage\nUpgraded maternity leave and paternity leave\nDiscounted Talent plan offers including broadband and mobile plans and other promoted products\nEducation subsidies and Examination leave\nYear-end discretionary bonus", "employment_types": ["Full Time", "Permanent", "Contract"], "selling_points": ["experience in hybrid/ native mobile development", "E-commerce app is an advantage", "Knowledge with UI layouts and localization"], "locations": ["Sheung Wan"], "categories": ["E-commerce", "Software Development"], "post_time": "2022-01-08T04:18:05Z", "salary": {"currency": null, "max": null, "min": null, "period": "monthly", "term": null}, "salary_visible": false, "title_keywords": ["developer", "programmer"], "responsibilities": ["mobile app", "external parties", "agile development", "design", "develop", "coding", "testing", "communication", "maintain", "documentation", "e-commerce platform"], "requirements": {"degrees": ["degree holder"], "majors": ["engineering", "computer science"], "languages": [], "language_level": [], "hard_skills": ["analytical skill", "agile", "e-commerce", "mobile", "web & mobile", "dynamic", "make", "react native", "documentation", "kotlin", "android"], "soft_skills": ["analytical skill", "agile", "keen", "communication", "hands on", "dynamic", "technical skills", "innovative"], "languages_combined": []}, "experience_required": {"duration": ["minimum 3-5 years"], "field": ["development", "business", "e-commerce"]}}, {"job_id": "100003009031484", "location_code": "hk", "company": "Osmium Consulting Group Limited", "job_title": "Backend Developer ( Java ) |  ( Fresh Grad are Welcome )", "description": "Responsibilities:\n\nResponsible for formulating and implementing the project development plan, including various work processes related to the project, to ensure that the project is completed on time\nManage project planning, sort out project and related team information\nFormulate project goals, assist in analysis, and confirm the project requirements plan. Including the overall project goals, stage goals, project functional requirements and system functional framework, understanding and tracking of project non-functional requirements (performance indicators, reliability, safety, configurability, scalability, maintainability, Portability)\nUse agile development and test team management (Scrum framework)\nUnderstand the product design path, and can assist related teams in product design & demand analysis\nSupervise and track the project plan, including checking status and progress, communicating with different teams, reminding problems, giving risks to project stakeholders, participating in cross-team meetings and recording meeting minutes\nManage project deliverables, and the corresponding processes and stakeholders\nResponsible for daily project management, tracking, communication, problem definition, management and resolution, change management, etc\nMonitor and formulate the main milestones, overall quality and plan of the project, as well as related deliverables and version management\nProvide weekly reports on project status and activities, and synchronize progress with project stakeholders and even customers\nResponsible for organizing the project team to write various project engineering documents and process documents in accordance with process requirements\n\nRequirements:\n\nMore than 3 years of experience in product development and IT-related project management\nRelevant work experience in the new media industry and/or e-commerce field\nFamiliar with the related process of software project management and process implementation experience\nFamiliar with various project management software and mainstream development technologies and frameworks\nExpert in Digital Marketing and E-Commerce\nFamiliar with agile development and test team management (Scrum framework)\nHave strong document processing ability, learning ability, summarizing ability\nPossess good communication skills, teamwork skills and business understanding skills\nPossess good professional ethics, work conscientiously, can withstand pressure and adapt to business trips\nWorking Location : Tseung Kwan O Industrial Estate\n\nInterested parties please\u00a0click \u201cApply Now\"\u00a0to submit your complete resume with\u00a0employment history and expected salary or by\u00a0post to\u00a0Human Resources Department, 3/F, Sing Tao News Corporation Building, 7 Chun Cheong Street, Tseung Kwan O Industrial Estate, Tseung Kwan O, New Territories, Hong Kong.\n\nWe are an equal opportunity employer and welcome applications from all qualified candidates. Information provided will be treated in strict confidence and only be used for recruitment related purpose. Applicant who is not invited for an interview within 6 weeks may consider their application not successful. All personal data of unsuccessful applicants will be destroyed within 6 months.\n\nwww.singtaonewscorp.com\u00a0", "employment_types": ["Full Time"], "selling_points": ["Java", "Attractive Salary and Beneifts", "5-day Work Week"], "locations": ["Not Specified"], "categories": ["Information Technology (IT)", "Application Specialist - Software", "Software Development", "E-commerce", "Software Development"], "post_time": "2022-01-07T09:21:58Z", "salary": {"currency": null, "max": null, "min": null, "period": "monthly", "term": null}, "salary_visible": false, "title_keywords": ["developer"], "responsibilities": ["related team information", "project requirements plan", "quality", "agile development", "giving risks", "communication", "project development plan", "plan", "sort out project", "product design path", "checking status and progress", "cross-team meetings", "teams", "formulate project goals", "monitor", "resolution", "communicating with different teams", "recording meeting minutes", "reminding problems", "management", "change management", "weekly reports", "product design", "version management", "tracking", "manage project planning", "demand analysis", "project deliverables", "analysis", "daily project management", "project plan", "test team management", "problem definition"], "requirements": {"degrees": [], "majors": [], "languages": [], "language_level": [], "hard_skills": ["agile", "e-commerce", "project management", "scrum framework", "processing"], "soft_skills": ["communication skills", "learning ability", "agile", "teamwork", "project management"], "languages_combined": []}, "experience_required": {"duration": ["3 years"], "field": ["e-commerce", "related", "project management", "it", "product development", "media"]}}, {"job_id": "100003008462724", "location_code": "hk", "company": "Assembly Limited", "job_title": "Web Developer (Frontend)", "description": "Ringus Solution Enterprise Limited is an IT solution provider offering a wide range of\nservices, including financial e-trade solutions, e/m-commerce solutions & IT security\nTo cope with business expansion, we invite high-caliber people to join our team.\n\nWhy Ringus Digital Solution\n\n\nChance to handle commercial systems with high traffic, brands that are well-know\u00a0in public\nGain solid experiences in IT vendor workflow, co-operate with Project Manager, Technical team, Designers and Quality assurance\nYoung teammates and well experiences mentors to work with.\n\nJob Responsibilities:\n\nParticipate in for designing and implementing mobile applications\n\u00a0Work closely with PM, designer and QA to meet the requirement and project schedule\n\u00a0\u00a0Review team's coding and provide guidance to junior developer\n\u00a0\u00a0Ensure APP performance and coding quality meeting latest standard\n\u00a0\u00a0Assist in technical documentation\n\nJob Requirements:\n\n\nMinimum 2 years of progressively related experience in hybrid/ native mobile development\nLess experience will be considered as junior developer\nProficient in full mobile development for iPhone / Android, such as design, build, deploy, test and release to app store\nSolid Knowledge with UI layouts and localization\nProficiency in Node. js, React Native, React.js\nExperienced in E-commerce app is an advantage\nWell organized and responsible\nStrong communication, analytic and problem-solving skills\nAble to work under pressure and meet deadline\nImmediate available preferred\n\n\nWe offer attractive salary package and career advancement opportunities to the right candidates. Interested parties please send your detail resume with\u00a0EXPECTED SALARY\u00a0& AVAILABLE DATE\u00a0in\u00a0WORD FORMAT\u00a0and\u00a0portfolio\u00a0(if any), by clicking \"Apply Now\".|\n\n\n(Personal data collected will be kept & used for recruitment purpose only)\n\n\nCompany Overview\n\nRingus\u2019 online marketing team \u2013 Goodsight is an online design and mobile marketing group which provides an all-rounded digital marketing solution. We work across media from web, mobile apps and print to produce cutting edge solutions with our creative and professional background. If you think you are a good team player and interested in online marketing, I would like to invite you to join our team to explore the broadness of Internet.\n\nTo understand our team, please refer to\u00a0www.goodsight.hk\n\nTo know more our company, please refer to\u00a0www.ringus-solution.com\n\n\n", "employment_types": ["Full Time"], "selling_points": ["Awarded design firm with enterprise-class clients", "Welcome both fresh-grad or experienced", "5-Day work in friendly work environment"], "locations": ["Shatin Area"], "categories": ["Information Technology (IT)", "Support", "Software Development", "E-commerce", "Software Development"], "post_time": "2022-01-06T02:30:45Z", "salary": {"currency": null, "max": null, "min": null, "period": "monthly", "term": null}, "salary_visible": false, "title_keywords": ["developer"], "responsibilities": ["review", "quality", "coding", "schedule", "designing", "documentation", "provide guidance"], "requirements": {"degrees": [], "majors": [], "languages": [], "language_level": [], "hard_skills": ["e-commerce", "react", "mobile", "react native", "problem-solving skills", "android"], "soft_skills": ["responsible", "well organized", "communication", "problem-solving skills", "work under pressure"], "languages_combined": []}, "experience_required": {"duration": ["minimum 2 years"], "field": ["related", "development", "developer"]}}, {"job_id": "100003009016820", "location_code": "hk", "company": "BUPA Asia Limited", "job_title": "Project Officer / Project Senior Officer \u2013 UAT (1 Year Contract)", "description": "Job Description\n\nKey Responsibilities:\u00a0\n\nCreate and execute tests using CI/CD pipeline, and test scenarios, test cases, test scripts that will determine optimal application performance according to specifications, fulfill business requirements, and identify existing or potential issues.\nTest our software to ensure integration into company systems meets functional requirements, system compliance, and technical specifications; and is fit for user acceptance test (UAT). Implement and maintain CI/CD pipeline for automated application testing.\nAnalyse bugs and errors found during tests.\u00a0\nDocument results of tests for the software development team.\u00a0\nRecommend improvements in software to enhance user experience.\u00a0\nMotivate the development process for efficiency and performance.\nWorks together with the software developer and UIUX team to enhance and improve programs.\nParticipates in Agile sprints and ceremonies.\u00a0\n\n\u00a0Requirement:\u00a0\n\nHigher Diploma\u00a0or above in Computer Science/Information Technology or related discipline\u00a0\nExperience in using version control software such as GitHub, Gitlab\u00a0\nExperience in using task management software such as JIRA\u00a0\nSolid experience in software development and\u00a0automated\u00a0testing\u00a0\nHigh proficiency in computer technology and programming languages\u00a0\nIn-depth understanding of Java,\u00a0JavaScript\u00a0and SQL\u00a0is a great plus\u00a0\nExceptional attention to detail\u00a0\nGood oral and written communication skills\u00a0\nGreat team player and able to work efficiently with minimal supervision\u00a0\n\n\u00a0Technologies of Interest:\u00a0\n\nAny modern CI/CD\u00a0\nGitLab\u00a0\nJira\u00a0\n\n\u00a0You will be able to:\u00a0\n\nMake decisions on the latest trending CI/CD technology to facilitate automation\u00a0\nOpportunities to step up and shine\u00a0\nFreedom on making\u00a0QA\u00a0related tech decisions to improve the system\u00a0", "employment_types": ["Full Time", "Contract"], "selling_points": ["1+ year experience in UAT testing", "Collaborate with users", "Highly customer focused"], "locations": ["Not Specified"], "categories": ["Information Technology (IT)", "Software Development", "Insurance", "Others", "E-commerce", "Software Development"], "post_time": "2022-01-03T09:54:16Z", "salary": {"currency": null, "max": null, "min": null, "period": "monthly", "term": null}, "salary_visible": false, "title_keywords": ["senior officer", "project officer"], "responsibilities": ["uat", "software", "compliance", "systems", "user experience", "testing", "specifications", "maintain", "analyse"], "requirements": {"degrees": ["higher diploma or above"], "majors": ["computer science", "information technology"], "languages": [], "language_level": [], "hard_skills": ["java", "plus", "sql", "make", "javascript", "programming"], "soft_skills": ["communication skills", "oral", "team player", "attention to detail"], "languages_combined": []}, "experience_required": {"duration": [], "field": ["testing", "management", "software development"]}}, {"job_id": "100003009017153", "location_code": "hk", "company": "A.S. Watson Retail (HK) Limited", "job_title": "[Strategic Problem Solver] Techie Developer", "description": "The Job\n\nIT Trainee Programme is\n\n\na fast track programme to develop professionalism in the IT industry. It is a 28 months program that cultivates young potential talents in an accelerated learning environment\n4 months in depth practical learning on java programming, which is the hottest programming language with the highest commercial demand\u00a0\nGaining solid commercial experience by serving as an independent software engineer for 24 months on site at our client\u00a0\nGuaranteed salary increment at the second year\u00a0\n\nWhat are the benefits for you?\n\n28-months programme\nGuaranteed salary increment in the second year\nIn-depth Java programming course\nOn-the-job Training\nCoaching & Buddy Support\n\nWhy should you consider your career in the IT industry?\n\nIt is a skill set that can be employed globally.\nHigh demand for IT talents.\nFast track promotion for the right talent as it is a result driven career.\nGrowing job Industry even in the pandemic.\n\nYour Profile\n\nBachelor\u2019s degree in any discipline\nPassion in IT with keen interest to build a career in IT industry\nNo IT knowledge and experience is required\nStrong presentation and communication skills, self-motivated with confidence\nFluent in English, Cantonese and Mandarin\nFresh graduate or with less than 5 years of working experience\n\nApplication deadline : 21 January, 2022 (Friday)", "employment_types": ["Full Time", "Permanent"], "selling_points": ["/*EXPERIENCE: 2 YEARS", "/*UNIVERSITY GRADUATE IN COMPUTER SCIENCE", "/*APP KNOWLEDGE OF JAVA, JAVASCRIPT, KOTLIN"], "locations": ["Shatin Area"], "categories": ["Information Technology (IT)", "Application Specialist - Software", "Technical / Functional Consulting", "E-commerce", "Software Development"], "post_time": "2022-01-03T10:50:42Z", "salary": {"currency": null, "max": null, "min": null, "period": null, "term": null}, "salary_visible": false, "title_keywords": ["developer"], "responsibilities": ["software", "develop"], "requirements": {"degrees": [], "majors": [], "languages": [], "language_level": [], "hard_skills": ["java", "programming"], "soft_skills": ["learning", "independent"], "languages_combined": []}, "experience_required": {"duration": [], "field": ["commercial"]}}, {"job_id": "100003009012875", "location_code": "hk", "company": "Chicle Communications Limited", "job_title": "Web Developer / Programmer (5 days work)", "description": "Responsibilities\u00a0\n\nThe duties and responsibilities include UAT testing, test management, communication and test reporting, test planning, defect and data management.\nCollaborate with users to ensure effective end to end testing is done for all of the products.\nPerform the following types of testing: user acceptance, functional, regression, and usability.\nProvide back up sales support to internal sales teams including all administrative work and coordination of documentations and insurance policies issuance\nQualifications, Training and Experience\n\nAt least 1-year experience in UAT testing experience\nGood communication skills in spoken and written English\nGood interpersonal and problem solving skills\nResponsible, well organized and attention to details\nProactive, mature, positive and decisive\nGood team player with strong commitment in delivering quality customer service\nHighly customer focused\n\nBupa offers 5 days work per week and comprehensive remuneration packages including base salary, performance bonus, study assistance plan, non-contributory pension plan, life and medical benefit, dental benefit, annual leave, examination leave, etc.\n\nBupa is an equal opportunity employer and welcomes applications from qualified candidates. Information provided will be treated in strict confidence and only be used for consideration of application with Bupa.\n\nPersonal data collected will be used for recruitment purposes only. Only candidates selected for interviews will be contacted. Bupa will be in touch for any opportunities that matches your profile. All personal data of unsuccessful application will be destroyed 24 months from the date of receiving the application.", "employment_types": ["Full Time"], "selling_points": ["Opportunity to work on global-scale projects", "Young, energetic and joyful working environment", "Experienced in web-based application development"], "locations": ["Tsuen Wan Area"], "categories": ["Information Technology (IT)", "Application Specialist - Software", "IT - Webmaster / SEO", "E-commerce", "Software Development"], "post_time": "2022-01-02T14:29:04Z", "salary": {"currency": null, "max": null, "min": null, "period": "monthly", "term": null}, "salary_visible": false, "title_keywords": ["developer", "programmer"], "responsibilities": ["collaborate with", "reporting", "management", "administrative work", "data", "policies", "uat testing", "teams", "quality", "testing", "communication", "customer service", "recruitment", "coordination", "plan", "personal data", "insurance", "planning"], "requirements": {"degrees": [], "majors": [], "languages": ["english"], "language_level": ["good"], "hard_skills": ["problem solving skills", "data management", "documentations", "sales support"], "soft_skills": ["communication skills", "good team player", "confidence", "responsible", "focused", "well organized", "mature", "communication", "decisive", "customer service", "comprehensive", "coordination", "attention to details", "problem solving skills", "proactive", "interpersonal", "positive"], "languages_combined": [{"language": "english", "language_level": ["good"]}]}, "experience_required": {"duration": ["at least 1-year"], "field": ["training", "testing"]}}, {"job_id": "100003009017166", "location_code": "hk", "company": "A.S. Watson Retail (HK) Limited", "job_title": "System Analyst /  Analyst Programmer  - eCom System", "description": "To Put A smile on our Customers\u2019 Faces\n\n\"WHAT do the systems need to do, HOW\u00a0do they do it, WHO do we need to get\u00a0input from, and important thing is NOT\u00a0TO STOP QUESTIONING.\"\n\n\n\nOur eLab Technology Team's Mission & Value:\n\nJoin a team of 300 Spartans & battle side by side in squad formation\nUnleash the power of programming - Java, React. Native, \u2026\nDefend the system and eliminate any threat to uphold the stability\nBuild digital products that serve millions\nThe battleground is on the cloud\nEmbrace new technologies to be faster, easier and to inspire an\u00a0inventive culture\nAlways respect the man and woman you are working with, and leave\u00a0no man behind, as we work as one team\nContinuous professional training is provided for your survival\nThere is always time to retreat from the frontline and enjoy freshly\u00a0brewed coffee and countless refreshments\nWe take care of you and your family, healthcare coverage and health\u00a0insurance is provided\nEnjoy amazing discount from all company's brands\n\nInterested parties please e-mail your full resume in WORD FORMAT with expected salary to our company email (shown in our Company Profile).\n\nWe are an equal opportunity employer and welcome applications from all qualified candidates. The information provided will be treated in strict confidence and be used only for consideration of your application for relevant / similar posts within the A.S. Watson Group.\n\nApplicants not hearing from us within 6 weeks from the date of advertisement may consider their applications unsuccessful. All personal data of unsuccessful applicants will be destroyed within 12 months from the date of application.\u00a0", "employment_types": ["Full Time", "Permanent"], "selling_points": ["Suggest to optimize eCom operations efficiency", "Microservices", "Strong in SQL and programming"], "locations": ["Shatin Area"], "categories": ["Information Technology (IT)", "Application Specialist - Software", "Technical / Functional Consulting", "E-commerce", "Software Development"], "post_time": "2022-01-03T10:55:08Z", "salary": {"currency": null, "max": null, "min": null, "period": "monthly", "term": null}, "salary_visible": false, "title_keywords": ["analyst programmer", "system analyst"], "responsibilities": ["systems", "insurance"], "requirements": {"degrees": [], "majors": [], "languages": [], "language_level": [], "hard_skills": ["no", "java", "programming", "react"], "soft_skills": [], "languages_combined": []}, "experience_required": {"duration": [], "field": []}}, {"job_id": "100003009016483", "location_code": "hk", "company": "Expert Systems IVR (Asia) Co Ltd", "job_title": "Software Developer  (Graduates / Intern Welcome)", "description": "Responsibilities\n\nDevelopment and deployment of websites and/or web-based applications;\nImplement appropriate and tidy codes and test them in various environments, enhance and/or modify them if necessary;\nFollow standardized procedures to ensure the smoothness of development;\nHandle multiple projects simultaneously in a timely and professional manner.\n\nRequirements\n\nDiploma, associate degree or bachelor degree in Computer Science, I.T. or related disciplines;\n1-2 years relevant working experience in related fields;\nSolid knowledge in web technologies and frameworks: HTML, SCSS, jQuery, PHP, MySQL, Bootstrap, Symfony;\nProficiency in front-end development would be a bonus;\nSelf-motivated, energetic and passionate in exploring new technology;\nStrong problem solving, interpersonal & communication skills and team player;\nAbility to work under pressure by handling multiple assignments and meeting tight deadlines;\nDetailed mind, proactive and willing to take responsibility;\nFresh graduates will also be considered\nImmediate availability would be a high priority.\u00a0\n\nWe offer:\n\n5-day work\nMedical Insurance\nYoung and joyful working environment\nComprehensive training and career development opportunities\n\nInterested parties please send your application with a full resume stating your present and expected salary to the Company.\n\nJOIN OUR CHICLE'S FAMILY. APPLY NOW!\n\n**All information will be used for recruitment purposes only**", "employment_types": ["Full Time", "Part Time"], "selling_points": ["Opportunities\u00a0to\u00a0develop\u00a0your\u00a0career\u00a0with\u00a0us", "5 days work week, Year-end bonus", "Proficiency in C#, Java, Eclipse, Tomcat"], "locations": ["Kwun Tong Area"], "categories": ["Information Technology (IT)", "Application Specialist - Software", "Software Development", "E-commerce", "Software Development"], "post_time": "2022-01-03T09:11:41Z", "salary": {"currency": null, "max": null, "min": null, "period": "monthly", "term": null}, "salary_visible": false, "title_keywords": ["developer", "intern"], "responsibilities": ["multiple projects", "procedures", "professional manner"], "requirements": {"degrees": ["associate degree", "diploma", "degree", "bachelor"], "majors": ["computer science"], "languages": [], "language_level": [], "hard_skills": ["php", "jquery", "html", "problem solving", "web technologies"], "soft_skills": ["passionate", "communication skills", "self-motivated", "proactive", "meeting tight deadlines", "detailed mind", "problem solving", "team player", "energetic", "interpersonal", "work under pressure"], "languages_combined": []}, "experience_required": {"duration": ["1-2 years"], "field": ["related", "relevant working experience"]}}, {"job_id": "100003008996727", "location_code": "hk", "company": "Conners Consulting Limited", "job_title": "Systems Analyst / Analyst Programmer", "description": "Job Responsibilities:\n\nWork closely with both internal and external parties to manage the e-commerce site to ensure the success of all deliverables as per schedule;\nManage new features implementation from collecting user requirements, defining project scope, specification, timeline/resource, and final testing;\nManage third party and external providers\u2019 contracts and Statement of Work;\nTrack project deliverables and prepare reports defining project progress, issues and solutions;\nOptimize user experience on various devices according to best practices;\nConstantly strive for new/innovated ideas and solutions for the business & improve operation efficiency of the team;\nPropose solutions with options to solve the problems arising out of the website development;\nSupport ecommerce operation on routine operation tasks\n\n\u00a0Requirement\n\nDegree holder in Computer Science, IT or other related discipline\nAt least 4 years relevant experience in E-commerce website management\nProficient PC skills in MS Excel, Word and Power Point\nExperience in Magento is an advantage\nAbility to handle multi-task, target-oriented, work under pressure and meet deadlines required\nWork independently, self-motivated, detail-minded, good attitude, strong sense of responsibility\nGood team player and good in communicating with different levels within the organization\nGood command in both oral and written English, Cantonese and Mandarin\n\nWe offer 5-day work week, medical and dental insurance, MPF, bank holidays and competitive remuneration package to the right candidate.\n\nAll information collected will be used for recruitment related purpose only and will be treated in strict confidence. Applicants who are not notified within 8 weeks may consider their application unsuccessful. All applications will be retained for maximum 6 months and will be destroyed.", "employment_types": ["Full Time", "Permanent"], "selling_points": ["Engage in the entire system development life cycle", "Self-motivated and can work independently", "Experience candidates will be considered as SSA"], "locations": ["Not Specified"], "categories": ["Information Technology (IT)", "Application Specialist - Software", "Software Development", "E-commerce", "Software Development"], "post_time": "2022-01-02T22:53:27Z", "salary": {"currency": null, "max": null, "min": null, "period": "monthly", "term": null}, "salary_visible": false, "title_keywords": ["analyst programmer", "analyst"], "responsibilities": ["ideas", "project deliverables", "contracts", "internal and external parties", "implementation", "project progress", "testing", "user experience", "website", "schedule", "prepare reports", "third party"], "requirements": {"degrees": ["degree holder"], "majors": ["it", "computer science"], "languages": ["cantonese", "english", "mandarin"], "language_level": ["good command"], "hard_skills": ["e-commerce", "word", "ms excel", "power point", "pc skills"], "soft_skills": ["detail-minded", "work independently", "self-motivated", "multi-task", "good team player", "oral", "sense of responsibility", "meet deadlines", "work under pressure"], "languages_combined": [{"language": "cantonese", "language_level": ["good command"]}, {"language": "english", "language_level": ["good command"]}, {"language": "mandarin", "language_level": ["good command"]}]}, "experience_required": {"duration": ["at least 4 years"], "field": ["management", "relevant experience", "e-commerce"]}}, {"job_id": "100003009007528", "location_code": "hk", "company": "A&A Limited", "job_title": "Web Programmer/ Web Developer (Senior/ Junior)", "description": "Come and join a Winning Team\n\nWe are Awesome!\n\nWhy Should You Join Us?\nAt ASW, we believe in our people, in teamwork and the importance of your personal growth.\u00a0If you are looking for the opportunity to join our award-winning international family with 15,000+ stores across 25 markets in Asia and Europe, the ASW family welcomes you\u2026\u00a0\u00a0#BePartofMORE\n\nYou can enjoy:\n\n\nComprehensive Medical and Life insurance coverage, including your spouse and children!\nProfessional training and career advancement opportunities!\nAttractive ACCA and CPA Australia Recognized Employer Program for F&A talents!\nExclusive company pension schemes!\u00a0 Marriage, Maternity and Paternity Leave!\nConvenient office location, less than 5 min. walk from MTR!\nContemporary workplace with Onsite Clinic, Lactation Rooms, free drinks and chill out areas!\nWell-equipped Gym inside our office building, plus fitness and interest class packages!\nFree round-trip lunchtime shuttle bus services to Shatin!\nExclusive shopping discount, Bazaar Sales for our people only!\n\nRole Purpose:\n\nThis position manages the retail eCommerce platforms.\u00a0The main responsibilities are to drive improvement projects in our Asia businesses.\n\nA typical day in this Role:\n\n\nAssist in the whole system development life cycle.\nProvide support to systems including troubleshooting, bug fixing and ad-hoc queries.\nPerform software development to application systems including new initiatives, change request and performance tuning.\nProvide technical development and support on integrating other enterprise systems.\nDevelop training materials and assist in user training.\n\n\u00a0This job is a good fit for You if:\n\n\nYou have a strong logical mind with data manipulation skill like Excel/SQL tools.\nYou have sound knowledge in retail systems, and eCommerce digital applications systems.\nYou are passionate about Digital or E-commerce trends.\n\n\u00a0What we look for:\n\nDegree in Computer Science, Information Technology, Engineering or related disciplines\n3+ years of experience in IT application system design and development.\n\u00a0Possess technical knowledge of ANY of the following areas:\nOracle PL/SQL, MySQL\nJava or Web based development platform\nMicrosoft.NET\nExperience in using open-sourced frameworks (Spring, SpringMVC, Hibernate, Struts) or using tools like Git and CI/CD is a definite advantage\nGood communication skills, mature, Independent and a good teamwork player\n\n\u00a0What is holding you back?\u00a0\n\nDon\u2019t miss out on this great chance to shape Your life!\u00a0\n\nApply now!\n\nInterested parties please e-mail your full resume in WORD FORMAT with expected salary to our company email (shown in our Company Profile).\n\nWe are an equal opportunity employer and welcome applications from all qualified candidates. The information provided will be treated in strict confidence and be used only for consideration of your application for relevant / similar posts within the A.S. Watson Group.\n\nApplicants not hearing from us within 6 weeks from the date of advertisement may consider their applications unsuccessful. All personal data of unsuccessful applicants will be destroyed within 12 months from the date of application.\u00a0", "employment_types": ["Full Time", "Permanent"], "selling_points": ["Programming: PHP, Laravel, MySQL", "5-day work; Medical and dental allowance", "Excellent learning environment with great exposure"], "locations": ["Kwun Tong"], "categories": ["Information Technology (IT)", "Application Specialist - Software", "Software Development", "E-commerce", "Software Development"], "post_time": "2021-12-30T03:14:39Z", "salary": {"currency": null, "max": null, "min": null, "period": "monthly", "term": null}, "salary_visible": false, "title_keywords": ["developer", "web programmer", "junior"], "responsibilities": ["ad-hoc", "manipulation", "provide support", "software", "data", "systems", "troubleshooting", "application system", "develop", "design", "communication", "application systems", "insurance"], "requirements": {"degrees": ["degree"], "majors": ["related disciplines", "engineering", "computer science", "information technology"], "languages": [], "language_level": [], "hard_skills": ["excel", "acca", "plus", "java", "hibernate", "web", "e-commerce", "struts", "git", "application system", "chill", "cpa", "sql", "spring", "data manipulation", "pl", "oracle"], "soft_skills": ["communication skills", "independent", "teamwork", "troubleshooting", "mature", "comprehensive", "passionate about"], "languages_combined": []}, "experience_required": {"duration": ["3+ years"], "field": ["development", "it", "system design"]}}, {"job_id": "100003009005753", "location_code": "hk", "company": "Bonjour Global Development Limited", "job_title": "E-Commerce Software Engineer / Programmer", "description": "What you\u2019ll be doing?\n\nYou will participate in the development of Voice applications\nYou will perform software testing and troubleshoot the problems\nYou will conduct\u00a0onsite hardware and software installation\nYou will maintain user communication and system support\u00a0\n\nWho\u00a0are\u00a0we\u00a0looking\u00a0for?\n\nA\u00a0candidate\u00a0with Higher Diploma or above in Computer Science or equivalent.\u00a0\nFresh graduates will also be considered\nAt least\u00a01 year post-qualification relevant experience\nProficiency in with C#, Java, Eclipse, Tomcat\n\nWhy you should consider this opportunity:\nWe offer attractive remuneration package with fringe benefits to right candidates. such as\n\n5 days work week\nBank Holidays\nYear-end bonus\nMedical Scheme\nYoung & Energetic Team\nFriendly Environment\u00a0\u00a0\n\nThe opportunity:\u00a0\n\nAre your working at a high turnover company and most your teammates working the company for only a few years?\n\u00a0Are you working at a vertical single business company? Working on single backend system only?\nWorking with a group of energetic and high-calibrated teammates with over 10 years working at ESi, you are encouraged to further develop your self-esteem and technical skill throughout your career path.\nWe have various successful projects on Government, Insurance, Banking, Commercial and Telco environment and you will gain exposure to project on various kind of business.\nCommunication with different type of project stakeholders\u00a0\u00a0\u00a0\n\nPlease send your\u00a0complete resume, inclusive of your available date, current and expected salary by clicking \"Apply Now\".\u00a0\n\nAll information received will be kept in strict confidential and for employment-related purpose only.\u00a0\u00a0", "employment_types": ["Full Time", "Permanent"], "selling_points": [], "locations": ["Tsuen Wan Area"], "categories": ["E-commerce", "Software Development"], "post_time": "2021-12-29T04:23:53Z", "salary": {"currency": null, "max": null, "min": null, "period": "monthly", "term": null}, "salary_visible": false, "title_keywords": ["software engineer", "programmer"], "responsibilities": ["installation", "software", "testing", "communication", "hardware", "maintain", "troubleshoot"], "requirements": {"degrees": ["higher diploma or above"], "majors": ["computer science"], "languages": [], "language_level": [], "hard_skills": ["hardware", "java", "c#"], "soft_skills": ["communication", "troubleshoot"], "languages_combined": []}, "experience_required": {"duration": ["at least 1 year"], "field": ["post-qualification", "relevant experience"]}}, {"job_id": "100003009009739", "location_code": "hk", "company": "A.S. Watson Retail (HK) Limited", "job_title": "(Senior) QA Specialists (Asia, UAT for eCommerce systems)", "description": "Responsibilities:\n\nEngage in the entire system development life cycle, including user requirements analysis, system design, testing and implementation\nPrepare documents, provide user training, support and problem solving\nProvide end-user support and maintenance on existing systems\n\nRequirements:\n\nDiploma or above in Computer Science, Information Systems, or related disciplines\nAt least 2 years\u2019 experience in application development and support\nHands-on programming experience in either Java, .Net, COBOL, C or SQL\nSelf-motivated, well organized and can work independently\nGood interpersonal and communication skills in both English and Chinese\nCandidates with more experience will be considered as Senior Systems Analyst\n\nTo apply, please send your detailed resume or contact Ernest WU at 2851 7763 for a confidential discussion.\n\nOnly shortlisted candidates will be notified.\n\nApplicants who are not contacted within two weeks may consider their applications unsuccessful.\n\nAll data collected will be used for recruitment purpose only & will be used strictly confidential.\n\nConners Consulting Limited\n\n2005 Kai Tak Commercial Building 317 Des Voeux Road Central Hong Kong\n\nTel: (852) 3996 8090", "employment_types": ["Full Time", "Permanent"], "selling_points": ["Responsible for UAT test cases", "Testing on eCommerce website/App", "Regional exposure"], "locations": ["Shatin Area"], "categories": ["Information Technology (IT)", "Testing / QA", "E-commerce", "Software Development"], "post_time": "2021-12-31T02:01:16Z", "salary": {"currency": null, "max": null, "min": null, "period": null, "term": null}, "salary_visible": false, "title_keywords": [], "responsibilities": ["maintenance", "analysis", "systems", "implementation", "testing", "system design", "prepare documents"], "requirements": {"degrees": ["diploma or above"], "majors": ["related disciplines", "computer science"], "languages": ["english", "chinese"], "language_level": ["good"], "hard_skills": ["java", "sql", "c", "programming", "cobol"], "soft_skills": ["communication skills", "work independently", "self-motivated", "well organized", "hands-on", "interpersonal", "detailed"], "languages_combined": [{"language": "english", "language_level": ["good"]}, {"language": "chinese", "language_level": ["good"]}]}, "experience_required": {"duration": ["at least 2 years"], "field": ["application development", "programming"]}}, {"job_id": "100003009009269", "location_code": "hk", "company": "Kontec Development Limited", "job_title": "Web Developer", "description": "A&A's mission: We're here to make digital transformation happen!\n\nWe have a big plan to grow our business and expand our teams for the coming year!\u00a0 Our clients range from private to public sectors, start-ups to listed companies, and local to international enterprises.\u00a0 We always look for adventurer who is eager to explore and hungry for success.\u00a0 You will have great opportunity to unleash your full potential to realise your dreams and goals.\n\nResponsibilities:\n\nDevelop / Enhance digital solutions (Website/ Mobile App/ E-commerce/ Chatbot/ System) based on specification/ requirements\nIntegrate APIs for web applications/ mobile app e.g. payment gateway; other systems\nTrouble-shooting on system or data issues and follow through issues with debugging and fine-tuning\nRequirements:\n\nHigher Diploma / Degree Holder in Information Technology, Computer Engineering, Computer Science or related disciplines\nHands-on experience with PHP & Laravel\nExperience and knowledge in HTML5/ CSS3/ JavaScript/ MySQL/ Gitlab/ Wordpress/ Woocommerce\nSelf-motivated, eager to learn with a responsible attitude\nProficiency in both Cantonese and English\n\n4-6 related work experience would be considered as senior programmer\nFresh graduates would also be considered as junior programmer\nReasons to join:\n\nExcellent learning environment with wide range of exposure to the latest digital trend\u00a0\n5 days\u2019 work with flexible working hours\nEducation allowance\nMedical and dental allowance\nMaternity, paternity, birthday and exam leave\nCareer advancement opportunities\nPerformance Bonus\nRegular company activities\nFree snacks and drinks\nYoung and dynamic team members", "employment_types": ["Full Time"], "selling_points": ["Minimum 2 years of website FRONTEND development", "5-Day working week, birthday Leave", "Happy working environment"], "locations": ["Lai Chi Kok"], "categories": ["Information Technology (IT)", "Application Specialist - Software", "Software Development", "E-commerce", "Software Development"], "post_time": "2021-12-30T12:01:33Z", "salary": {"currency": null, "max": null, "min": null, "period": "monthly", "term": null}, "salary_visible": false, "title_keywords": ["developer"], "responsibilities": ["mobile app", "data", "systems", "website", "develop", "payment"], "requirements": {"degrees": ["diploma", "degree holder"], "majors": ["related disciplines", "computer engineering", "computer science", "information technology"], "languages": ["cantonese", "english"], "language_level": ["proficiency"], "hard_skills": ["wordpress", "javascript", "dynamic", "php"], "soft_skills": ["flexible", "self-motivated", "responsible", "eager to learn", "hands-on", "learning", "dynamic"], "languages_combined": [{"language": "cantonese", "language_level": ["proficiency"]}, {"language": "english", "language_level": ["proficiency"]}]}, "experience_required": {"duration": [], "field": ["related"]}}, {"job_id": "100003009005429", "location_code": "hk", "company": "Hong Kong Broadband Network Limited", "job_title": "Web Developer (E-Commerce Platform)", "description": "Responsibility:\n\nUnderstand customer\u2019s needs. Turn the needs into deliverables.\nDevelop the Mobile App and Website for e-Commerce environment.\nParticipate programming, testing, debugging.\n\nRequirement:\n\nBachelor degree on computer science, e-commerce or equivalence.\nHands-on experience in web application development.\nGood skills on PHP, Laravel, Augular, Lonic Framework, Node.js, etc\nGood knowledge in RDBMS (MS SQL, MySQL)\nExperience with Cloud (AWS, GCP, AliCloud) serverless development (DevOps + CI/CD) is preferred\nPassion to win. Keep growing. Good teamwork spirit", "employment_types": ["Full Time", "Permanent"], "selling_points": ["C#, ASP.NET MVC & WebAPI, .NET Core, SQL Server", "ES5/6, ReactJS, Redux, Webpack, Sass / SCSS / LESS", "Node.js, Bootstrap, JQuery"], "locations": ["Kwai Hing"], "categories": ["Information Technology (IT)", "Software Development", "Technical Writing", "E-commerce", "Software Development"], "post_time": "2021-12-29T03:52:31Z", "salary": {"currency": null, "max": null, "min": null, "period": "monthly", "term": null}, "salary_visible": false, "title_keywords": ["developer"], "responsibilities": ["testing", "mobile app", "website", "develop"], "requirements": {"degrees": ["degree", "bachelor"], "majors": ["computer science", "e-commerce"], "languages": [], "language_level": [], "hard_skills": ["web application development", "php", "e-commerce", "devops", "aws", "ms sql"], "soft_skills": ["hands-on", "teamwork spirit"], "languages_combined": []}, "experience_required": {"duration": [], "field": ["development", "application development", "devops"]}}, {"job_id": "100003009005821", "location_code": "hk", "company": "Intepay Company Limited", "job_title": "Full-time/Part-time/Internship-Backend Developer/Web Developer/CMS System Developer", "description": "Responsibilities:\nWebsite, web application and web based application development\nWork closely with project teams to deliver client projects\nDeliver the work in high quality and efficiency\nRequirements:\nMinimum 2 years of website FRONTEND development\nTechnical knowledge on HTML5, CSS3, JavaScript and RestAPI\nSolid experience on ReactJS or VueJS\nExperience in PHP, MySQL, Laravel, Unity, Linux and GIT is a PLUS\nGood team player, positive attitude, a strong sense of responsibility and self-motivated to meet project deadlines", "employment_types": ["Full Time", "Part Time", "Internship"], "selling_points": ["Monthly Salary up to HKD30K \u6708\u85aa\u9ad8\u90543\u842c", "Working five days a week/public holidays 5\u5929\u5de5\u4f5c \u7d05\u65e5\u653e\u5047", "Flexible Working in Hong Kong Science Park \u9999\u6e2f\u79d1\u6280\u5712\u5de5\u4f5c"], "locations": ["Shatin Area"], "categories": ["Design", "Web Designer", "Information Technology (IT)", "Network & System", "E-commerce", "Software Development"], "post_time": "2021-12-29T05:00:52Z", "salary": {"currency": null, "max": null, "min": null, "period": "monthly", "term": null}, "salary_visible": false, "title_keywords": ["developer", "system developer", "internship"], "responsibilities": ["quality", "application development", "teams", "website"], "requirements": {"degrees": [], "majors": [], "languages": [], "language_level": [], "hard_skills": ["linux", "plus", "git", "php", "javascript", "unity"], "soft_skills": ["positive attitude", "good team player", "self-motivated", "sense of responsibility"], "languages_combined": []}, "experience_required": {"duration": [], "field": []}}, {"job_id": "100003009001999", "location_code": "hk", "company": "OKLink Investment Holdings Limited", "job_title": "Senior Quantitative Strategist", "description": "This\u00a0position will be under HOME+ e-commerce platform.\n\nOpportunities\nDevelop web application with latest web technologies.\nWorking with a highly dynamic and innovative team in Agile approach.\nWhat efforts you need to make?\nDesign and develop web application for internal and external users\nDesign and develop RESTful API for system integration\nDiscuss and advise application requirements from users\nReview existing systems and develop the enhancement\nLet's check if you are/have\u2026\nDegree holder in Computer Science, Engineering or equivalent\nMinimum 2 years' working experience in software development.\nExperience in C#, ASP.NET MVC & WebAPI, .NET Core, SQL Server\nExperience in ES5/6, ReactJS, Redux, Webpack, Sass / SCSS / LESS is an advantage\nExperience in Node.js, Bootstrap, JQuery is an advantage\nExperience in Azure technologies is a big advantage\nInnovative and strong analytical skill\nKeen on technology and able to pick up latest technical skills\n\nWhat you get in return\u2026\n\n\nApart from competitive salary package and benefits, in HKBN, you will work flexibly under our Talent-first\u00a0culture\u00a0and we uphold Life-Work Priority. Examples of our flexible initiatives:\n\n\nFive-day work week and shorten working hours (8 hours including 1 hour 15 mins meal break)\nHalf Day Off Friday once a month (compensation leave for Talents who work on shift)\nHalf Day Off on Festival Eve (compensation leave for Talents who work on shift)\nUnique leaves arrangement: Family-care leave, Anniversary leave, Bonus leave, Volunteer leave, Sabbatical leave, etc.\nComprehensive medical and life insurance coverage\nUpgraded maternity leave and paternity leave\nDiscounted Talent plan offers including broadband and mobile plans and other promoted products\nEducation subsidies and Examination leave\nYear-end discretionary bonus", "employment_types": ["Full Time"], "selling_points": ["Master or Ph.D. degree in a relevant area", "2~5 years of relevant working experience", "Proficient in at least one programming language"], "locations": ["Causeway Bay"], "categories": ["Information Technology (IT)", "Software Development", "Network & System", "E-commerce", "Software Development"], "post_time": "2021-12-28T03:31:48Z", "salary": {"currency": null, "max": null, "min": null, "period": "monthly", "term": null}, "salary_visible": false, "title_keywords": [], "responsibilities": ["software", "review", "design and develop", "systems", "develop", "e-commerce platform"], "requirements": {"degrees": ["degree holder"], "majors": ["engineering", "computer science"], "languages": [], "language_level": [], "hard_skills": ["server", "restful api", "analytical skill", "azure", "agile", "web", "e-commerce", "jquery", "sql", "make", "dynamic", "integration", "web technologies", "c#"], "soft_skills": ["analytical skill", "agile", "keen", "dynamic", "technical skills", "innovative"], "languages_combined": []}, "experience_required": {"duration": ["minimum 2 years"], "field": ["software development"]}}, {"job_id": "100003009004487", "location_code": "hk", "company": "Hong Kong Broadband Network Limited", "job_title": "API Programmer / System Analyst - HOME+ E-Commerce Platform", "description": "Job Highlights\n\nFast-growing new FinTech startup company\nFriendly Working Environment in Hong Kong Science Park\uff08Sha Tin\uff09\nFull-Time: HKD18000-HKD30000 per month\nPart-Time: HKD 70-100 per hour (at least 2 days per week)\nWinter Break/Sem B Internship: HKD 10500 per month\nWorking Days: Mon-Fri 10:00-19:00\nJob Descriptions\n\n\nResponsible for\u00a0\u00a0the design, building, and development of our backend & CMS system to improve business process and business operations.\nFamiliar with Google Firebase, Web design, APIs and GitHub.\nCoordinate with the project team to perform system integration and implementation\nKnowledge of algorithm, data structure and design patterns.\nMaintain and administrator company intranet website and improve function according to company needs\nDevelop IT solutions for management to visualize the business and performance trends\nParticipation in entrepreneurial activities (if required)\n\nJob Requirements\n\nDiploma and degree holder in computer science, information technology or related disciplines\nSolid experience in backend development is a must\nIndependent, logical mind with problem-solving skills\nFamiliar with Google Firebase,\u00a0Web design and GitHub.\nIn-depth knowledge of Java, Typescript, PHP, Python,\u00a0Node.js, NativeScript\nSelf-motivated, energetic and passionate on exploring new technology\nFluent in written and oral Chinese and English", "employment_types": ["Full Time", "Permanent"], "selling_points": ["API integration in AWS Lambda/ Mule", "RESTful/ GraphQL API for system integration", "Software Development"], "locations": ["Kwai Hing"], "categories": ["Information Technology (IT)", "Application Specialist - Software", "Software Development", "E-commerce", "Software Development"], "post_time": "2021-12-29T02:34:28Z", "salary": {"currency": null, "max": null, "min": null, "period": "monthly", "term": null}, "salary_visible": false, "title_keywords": ["system analyst", "programmer"], "responsibilities": ["management", "data", "operations", "coordinate with", "implementation", "design", "website", "develop", "business process", "maintain"], "requirements": {"degrees": ["diploma", "degree holder"], "majors": ["related disciplines", "computer science", "information technology"], "languages": ["english", "chinese"], "language_level": ["fluent"], "hard_skills": ["web design", "java", "php", "typescript", "python", "problem-solving skills"], "soft_skills": ["passionate", "self-motivated", "oral", "independent", "problem-solving skills", "energetic"], "languages_combined": [{"language": "english", "language_level": ["fluent"]}, {"language": "chinese", "language_level": ["fluent"]}]}, "experience_required": {"duration": [], "field": ["development"]}}, {"job_id": "100003009006735", "location_code": "hk", "company": "SampsonStore.com Limited", "job_title": "Senior Software Developer (E-commerce & Robotics)", "description": "\u00a0Come and join a Winning Team\n\n\u00a0We are Awesome !\n\n\u00a0Why Should You Join Us?\n\n\u00a0At ASW, we believe in our people, in teamwork and the importance of your personal growth.\u00a0If you are looking for the opportunity to join our award-winning international family with 16,200+ stores across 28 markets in Asia and Europe, the ASW family welcomes you\u2026\u00a0\u00a0#BePartofMORE\n\n\u00a0You can enjoy :\u00a0\u00a0\u00a0\n\nComprehensive Medical and Life insurance coverage, including your spouse and children!\nProfessional training and career advancement opportunities!\nAttractive ACCA and CPA Australia Recognized Employer Program for F&A talents!\nExclusive company pension schemes!\u00a0 Marriage, Maternity and Paternity Leave!\nConvenient office location, less than 5 min. walk from MTR!\nContemporary workplace with Onsite Clinic, Lactation Rooms, free drinks and chill out areas!\nWell-equipped Gym inside our office building, plus fitness and interest class packages!\nFree round-trip lunchtime shuttle bus services to Shatin!\nExclusive shopping discount, Bazaar Sales for our people only!\n\nRole Purpose:\n\n\nAs part of the Watsons International eCommerce team, you will be playing an important role in delivering great customer experience on our website and mobile apps. You will be responsible for testing the new digital solution, and coordinate on testing process with various teams to ensure the deliverable fit release to Watsons customers.\n\nA typical day in this Role:\u00a0\n\nPrepare UAT test cases according to user requirement and UI design.\nExecute UAT test case in regular or ad-hoc release cycle.\nReport defects/issue clearly with detail steps.\nGenerate daily test report for management.\nSupport or lead design review sessions with cross-functional team members to review requirements and sign off testing specifications.\nCollaborate with other Testers to ensure testing artefacts across functions.\nConduct or provide training sessions for business teams\n\n\u00a0This job is a good fit for You if:\u00a0\u00a0\n\nYou are committed to drive smooth customer journey on websites and mobile apps.\nYou are confident to handle UAT across systems and regions.\nYou have good time management.\n\n\u00a0What we look for:\u00a0\u00a0\n\nSolid experience in performing UAT (min. 5 years of exp. for Senior QA Specialist and min. 1 year of exp. for QA Specialist).\nExperience in performance and/or security testing is a plus.\nStrong communication and presentation skills is an advantage.\nFamiliar with Jira, Confluence, Excel.\nProficient in English and Chinese\n\nWhat is holding you back?\n\n\u00a0Don\u2019t miss out on this great chance to shape Your life!\n\n\u00a0\u00a0Apply now!\u00a0\n\nInterested parties, please send your resume with current and expected salary package to our Company\u2019s email.\u00a0\u00a0\n\nWe are an equal opportunity employer and welcome applications from all qualified candidates. The information provided will be treated in strict confidence and be used only for consideration of your application for relevant/ similar posts within the A.S. Watson Group.\u00a0", "employment_types": ["Full Time", "Permanent"], "selling_points": ["E-commerce, web & robotics development", "Full stack development", "International exposure"], "locations": ["Lai Chi Kok"], "categories": ["Engineering", "Electrical / Electronics", "Information Technology (IT)", "Software Development", "E-commerce", "Software Development"], "post_time": "2021-12-29T10:07:37Z", "salary": {"currency": null, "max": null, "min": null, "period": "monthly", "term": null}, "salary_visible": false, "title_keywords": ["developer"], "responsibilities": ["ad-hoc", "user requirement", "management", "collaborate with", "provide training", "uat", "review", "teams", "website", "design", "testing", "coordinate", "systems", "communication", "specifications", "insurance", "ui", "report"], "requirements": {"degrees": [], "majors": [], "languages": ["english", "chinese"], "language_level": ["proficient"], "hard_skills": ["excel", "acca", "plus", "chill", "cpa", "mobile"], "soft_skills": ["confident", "responsible", "teamwork", "communication", "committed", "presentation skills", "comprehensive", "smooth", "time management"], "languages_combined": [{"language": "english", "language_level": ["proficient"]}, {"language": "chinese", "language_level": ["proficient"]}]}, "experience_required": {"duration": [], "field": ["ecommerce", "testing", "security", "team"]}}, {"job_id": "100003009003849", "location_code": "hk", "company": "Casetagram Limited", "job_title": "Senior UXUI Designer", "description": "Job Description:\n\nWork\u00a0with\u00a0quantitative\u00a0analyst\u00a0to\u00a0continuously\u00a0optimize\u00a0existing\u00a0quantitative\u00a0library\u00a0and\u00a0develop\u00a0new\u00a0models\u00a0to\u00a0facilitate\u00a0our\u00a0risk\u00a0management\u00a0system.\nWork\u00a0with\u00a0developers\u00a0to\u00a0maintain\u00a0and\u00a0optimize\u00a0the\u00a0current\u00a0ultra-low\u00a0latency\u00a0trading\u00a0systems,\u00a0as\u00a0well\u00a0as\u00a0the\u00a0order\u00a0/\u00a0position\u00a0management\u00a0system,\u00a0market\u00a0data\u00a0storage\u00a0and\u00a0analysis,\u00a0exchange\u00a0connectivity,\u00a0etc.\nWork\u00a0with\u00a0traders\u00a0to\u00a0optimize\u00a0the\u00a0algorithms,\u00a0including\u00a0data\u00a0analysis,\u00a0backtests,\u00a0algorithm\u00a0implementation\u00a0etc.\n\nJob requirements:\n\nMaster\u00a0or\u00a0Ph.D.\u00a0degree\u00a0in\u00a0a\u00a0relevant\u00a0area\u00a0(Mathematics/Physics/Engineering/Computer\u00a0Science)\u00a0from\u00a0a\u00a0top\u00a0University.\u00a0Degree\u00a0in\u00a0mathematical\u00a0finance\\financial\u00a0engineering\u00a0is\u00a0preferred.\u00a0\n2~5\u00a0years\u00a0of\u00a0working\u00a0experience\u00a0as\u00a0a\u00a0quantitative\u00a0analyst/deveoper/trader.\u00a0Must\u00a0have\u00a0some\u00a0experience\u00a0in\u00a0the\u00a0quantitative\u00a0modeling\u00a0/\u00a0trading\u00a0of\u00a0options\u00a0or\u00a0other\u00a0structured\u00a0products.\nMust\u00a0be\u00a0proficient\u00a0in\u00a0at\u00a0least\u00a0one\u00a0programming\u00a0language\u00a0(Java/C++/C#).\n\nGood\u00a0communication\u00a0skills.\nBasic\u00a0knowledge\u00a0in\u00a0crypto\u00a0products\u00a0and\u00a0trading\u00a0is\u00a0a\u00a0plus.\nExperience\u00a0with\u00a0high\u00a0frequency\u00a0trading\u00a0systems\u00a0is\u00a0a\u00a0plus.", "employment_types": ["Full Time", "Permanent"], "selling_points": ["Websites/ Mobile/ Apps - Senior UXUI Designer", "E-commerce & Transactional Site Design", "Shopify Site Designs / SDK are advantageous"], "locations": ["Kwun Tong"], "categories": ["Design", "Multi-media", "Web Designer", "E-commerce", "Software Development"], "post_time": "2021-12-28T11:04:25Z", "salary": {"currency": null, "max": null, "min": null, "period": "monthly", "term": null}, "salary_visible": false, "title_keywords": ["designer"], "responsibilities": ["management", "analysis", "systems", "implementation", "develop", "data analysis", "maintain", "market data"], "requirements": {"degrees": ["degree", "master"], "majors": ["mathematics", "computer science", "engineering", "physics"], "languages": [], "language_level": [], "hard_skills": ["java", "plus", "basic", "crypto", "c++", "programming", "c#"], "soft_skills": ["communication skills", "structured"], "languages_combined": []}, "experience_required": {"duration": ["2~5 years"], "field": ["trading"]}}, {"job_id": "100003009003833", "location_code": "hk", "company": "Infinity Technology Corporation Limited", "job_title": "UX/UI Designer", "description": "Feel curious about how can you develop your IT career in a company that sells sexual well-being products? Our hardcore IT culture enables us to think of any innovative IT tool that assists their sales. We focus on this specific merchandise and use our skills to automate the business process that makes it readily available to a large crowd. A bigger challenge yet, we will work it on a global scale, working in markets including Hong Kong, Taiwan, Singapore, and the UK. The successful candidate would join our team to enhance our online e-commerce shops, develop new process automation modules, sales support systems, patented warehouse robotic picking systems, and research on a drone-based delivery system.\n\nDuties\n\nDevelop a program that can create product master on e-marketplaces automatically from our official e-shop.\nDevelop a program that can update inventories to e-marketplaces automatically from our official e-shop\nDevelop a program that can collect orders from e-marketplaces and save them to our official e-shop\nDevelop a program that can send our orders to 3PL for order fulfilment\nUnderstand the system workflow and identify areas that can be automated by machines.\nInvolve in designing system specifications and obtaining users' requirements in the new workflow.\nCoding and system testing.\nDeployment of the system to Hong Kong, Taiwan, Singapore, and UK sites. Occasional travelling is required.\nResearch on the latest automation technologies.\nRequirements\n\nDegree in CS/IT or related discipline.\nSound knowledge in web application development. Must be familiar with at least 2 of the below technology aspects (please state them in your application letter):\nJava or Python or PHP, with git\nDatabase development (at least experience in outer-join)\nUnix based environment (at least understanding of shell script, cron and vi)\nhtml5, css3, javascript (jQuery or angular or vuejs or reactjs), building UI from wireframes and designs.\nMobile app development (both Android and iOS)\nNetwork deployment - docker or Cloudflare CDN or related\nRobotics system development - digital circuit design; hands-on experience in using onshape\nGood command of English and Putonghua.\nPreference for candidates with hands-on experience in developing robotics systems.\nOur working environment\n\nSmall team, close relationship.\nFree working hours adapt to your working habit.\nOpen to using the latest technologies.\nIf you enjoy programming something to move, this is a job for you.\n\nPlease send your CV, expected annual package, and the answer of \"A bat and a ball cost $1.10 in total. The bat costs $1.00 more than the ball. How much does the ball cost?\" for application.", "employment_types": ["Full Time"], "selling_points": ["UX/UI Design; Digital Design", "Dynamic and Fast-paced Environment", "Website, Mobile App, System, POS and Digital"], "locations": ["Lai Chi Kok"], "categories": ["Design", "Web Designer", "E-commerce", "Software Development", "Information Technology (IT)", "UI/UX Designer"], "post_time": "2021-12-28T10:58:59Z", "salary": {"currency": null, "max": null, "min": null, "period": "monthly", "term": null}, "salary_visible": false, "title_keywords": ["ui designer"], "responsibilities": ["e-shop", "coding", "develop", "testing", "specifications", "designing"], "requirements": {"degrees": ["degree"], "majors": ["it"], "languages": ["putonghua", "english"], "language_level": ["good command"], "hard_skills": ["small", "java", "git", "web application development", "php", "jquery", "mobile", "javascript", "deployment", "angular", "programming", "python", "android"], "soft_skills": ["hands-on"], "languages_combined": [{"language": "putonghua", "language_level": ["good command"]}, {"language": "english", "language_level": ["good command"]}]}, "experience_required": {"duration": [], "field": ["development", "developing", "database"]}}, {"job_id": "100003009003857", "location_code": "hk", "company": "Infinity Technology Corporation Limited", "job_title": "Quality Assurance Engineer", "description": "Casetify is looking for a Senior UXUI designer experienced in information architecture, interaction, and user testing to join our team. You will collaborate with the E-commerce team to design and build next generation Web/mobile applications. The right candidates will be excellent communicators, comfortable in a high-velocity startup, and passionate about creating products that transform people\u2019s lifestyle.\nResponsibilities:\nPrepare UX/UI design and materials including wire framing, mockup and rapid prototyping for various interfaces, including websites, mobile devices and apps for ecommerce site;\nAnalyze current user journey to understand motivation, expose pain points, issues and improvement opportunities;\nConduct user research, A/B testing, and propose solutions to optimize customer experience;\nCommunicate concepts and work collaboratively with project team / Tech team in order to develop the most efficient design schemas;\nSit with developers to do pixel-perfect reviews of frontend products before they are pushed in production;\nConsume our Design System library and contribute to its evolution.\nRequirements:\n\n\nBachelor Degree in Creative Media / Interactive Design / Web Design / Web Development;\n5+ years of experience building transactional website;\nSpecific experience in a fast growing ecommerce company;\nAbility to solve problems of complexity through smart design;\nBeing data-driven, and be able to back up your assertions with data, with proficiency in analytic tools - Hotjar, Google Analytics, Optimizely etc;\nA user-first attitude and ensure we consistently deliver a user-centric culture;\nStrong understanding of web grids and browser limitations;\nFamiliarity with usability testing, A/B testing methods;\nProficiency with Photoshop, Adobe XD, Webflow, HTML, CSS, PHP;\nBouns: Experience with Shopify site designs / SDK.\nPlease include 2 URLs of your Open Source, personal projects into your resume.\n\n", "employment_types": ["Full Time"], "selling_points": ["Degree Holder in Computer Science", "QA /software testing and methodology", "Excellent analytical, problem solving"], "locations": ["Lai Chi Kok"], "categories": ["Information Technology (IT)", "Software Development", "Testing / QA", "E-commerce", "Software Development"], "post_time": "2021-12-28T11:08:18Z", "salary": {"currency": null, "max": null, "min": null, "period": "monthly", "term": null}, "salary_visible": false, "title_keywords": ["engineer"], "responsibilities": ["design", "develop", "testing", "mobile devices", "ui"], "requirements": {"degrees": ["degree", "bachelor"], "majors": ["creative media", "web design", "design"], "languages": [], "language_level": [], "hard_skills": ["web design", "web development", "google analytics", "web", "php", "adobe xd", "shopify", "html", "css", "photoshop"], "soft_skills": ["solve problems", "creative", "driven"], "languages_combined": []}, "experience_required": {"duration": ["5+ years"], "field": ["ecommerce"]}}, {"job_id": "100003009003982", "location_code": "hk", "company": "FWD Life Insurance Company (Bermuda) Limited", "job_title": "System Analyst (Enterprise Architecture - Cloud & DevOps Team), Information Technology", "description": "Responsibilities:\n\nDesign user interface for Portal, POS, Customer Frontends (Mobile Apps, Tablet, PC);\nDesign for UI and UX;\nCollaborate with our development team to bring your designs to live;\nCommunicate with clients to gather requirements and present design concept.\n\nRequirements:\n\nDegree Holder in digital design or related disciplines;\nMinimum 1 year of UI /UX design experience (especially on web and Mobile App), or equivalent experience;\nExperience designing intuitive user experiences based on requirements;\nProficiency in graphic design - familiar with Photoshop or AI;\nProficiency in prototyping tools like Sketch, Figma;\nPassionate to provide innovative, creative and reliable digital business solutions (web, app, system) to our clients;\nGood team player with strong growth mindset, excellent communication, work with strict deadlines and under high-pressure situations;\nGood command of spoken and written English, Chinese and Mandarin;\nCandidate with more experience will be considered as SeniorUX/UI Designer;\nImmediate availability or short notice is highly preferred.\n\nWe offer attractive salary and fringe benefits to the right candidate.\u00a0 Interested candidates should send FULL RESUME with Current & Expected salary.\n\nData collected will be used for recruitment purpose only.\n\n\n\n", "employment_types": ["Full Time"], "selling_points": ["Handle Open API, OpenShift, DevOps, Cloud projects", "Exp in Java, JBOSS, API, DevOps, AWS / Azure Cloud", "Permanent, Discretionary Bonus, 20days AL, Medical"], "locations": ["Kwun Tong"], "categories": ["Information Technology (IT)", "Application Specialist - Software", "Software Development", "E-commerce", "Software Development"], "post_time": "2021-12-28T14:26:09Z", "salary": {"currency": null, "max": null, "min": null, "period": "monthly", "term": null}, "salary_visible": false, "title_keywords": ["system analyst"], "responsibilities": ["collaborate with", "communicate with", "design concept", "design", "user interface", "ui"], "requirements": {"degrees": ["degree holder"], "majors": ["related disciplines", "design"], "languages": ["english", "chinese", "mandarin"], "language_level": ["good command"], "hard_skills": ["ai", "mobile", "web", "photoshop"], "soft_skills": ["passionate", "good team player", "creative", "innovative", "communication", "reliable"], "languages_combined": [{"language": "english", "language_level": ["good command"]}, {"language": "chinese", "language_level": ["good command"]}, {"language": "mandarin", "language_level": ["good command"]}]}, "experience_required": {"duration": ["minimum 1 year"], "field": ["designer", "design"]}}, {"job_id": "100003009000313", "location_code": "hk", "company": "A.S. Watson Retail (HK) Limited", "job_title": "Senior Developer / Developer - Web & App", "description": "Responsibilities:\n\nAnalyse user requirements to design and implement test plan, and ensure test coverage;\nRespond feature test, integration test and performance test of systems;\nProvide test result record and track issue status updates/status;\nSupport and coordinate closely with internal teams to understand user requirements;\nReport and provide feedback to make improvement in the quality of deliverable as well as the QA process;\nAssist in the implementation of quality assurance operation or additional work flow updates or process;\nAd hoc involvement in tasks or projects as assigned by supervisor/team leader.\n\nRequirements:\n\nDegree Holder in Computer Science, Information Technology, or related disciplines;\nMinimum 2 years working experience in quality assurance or software testing, with F&B or retails exposure is a definite advantage;\nExperience in test tool (i.e. Postman, Chrome Dev Tools etc.);\nStrong knowledge in QA process and methodology;\nExcellent analytical, problem solving, and documentation skills;\nFast learner, self-motivated, responsible and a good team player;\nGood command of spoken and written English, Chinese and Mandarin;\nImmediate availability or short notice is highly preferred.\n\nWe offer attractive salary and fringe benefits to the right candidate.\u00a0 Interested candidates should send FULL RESUME with Current & Expected salary.\n\n\nData collected will be used for recruitment purpose only.", "employment_types": ["Full Time", "Permanent"], "selling_points": ["Programming / Development in Java / Restful API", "Microservices", "MS SQL / Oracle Database"], "locations": ["Shatin Area"], "categories": ["Information Technology (IT)", "Application Specialist - Software", "Technical / Functional Consulting", "E-commerce", "Software Development"], "post_time": "2021-12-25T00:06:12Z", "salary": {"currency": null, "max": null, "min": null, "period": "monthly", "term": null}, "salary_visible": false, "title_keywords": ["developer"], "responsibilities": ["ad hoc", "systems", "teams", "quality", "design", "implementation", "coordinate", "plan", "report", "analyse"], "requirements": {"degrees": ["degree holder"], "majors": ["related disciplines", "computer science", "information technology"], "languages": ["english", "chinese", "mandarin"], "language_level": ["good command"], "hard_skills": ["problem solving", "documentation"], "soft_skills": ["good team player", "self-motivated", "responsible", "problem solving", "fast learner"], "languages_combined": [{"language": "english", "language_level": ["good command"]}, {"language": "chinese", "language_level": ["good command"]}, {"language": "mandarin", "language_level": ["good command"]}]}, "experience_required": {"duration": ["minimum 2 years"], "field": ["testing", "f&b", "quality assurance"]}}, {"job_id": "100003009000317", "location_code": "hk", "company": "A.S. Watson Retail (HK) Limited", "job_title": "Full Stack Marketing Intern (UX & Frontend development)", "description": "Opportunities\u00a0\n\nDevelop API service with latest technologies.\u00a0\u00a0\nWorking with a highly dynamic and innovative team\u00a0in Agile/Scrum\u00a0approach.\nThis position will be under HOME+ e-commerce platform\nThis position can be Programmer/ Senior Programmer/ Analyst Programmer/ System Analyst, depends on experiences\nWhat efforts you need to make for this role?\n\nCollaborate with Business Analysts, Programmer to resolve issues and ensuring solutions are viable and consistent\u00a0\nAnalyse, design and setup API integration in AWS Lambda/ Mule\nAnalyse, design and develop RESTful/ GraphQL API for system integration\u00a0\nDefine or assist in API design standards, patterns, and best practices\nWork closely with cross-functional members of a team to ensure alignment of the APIs\nReview existing systems/ API design and develop the enhancement\u00a0\n\n\u00a0Let's check if you are/ have\u2026\n\nHigher diploma/Degree holder in Computer Science, Engineering or equivalent\u00a0\n0-5\u00a0years' working experience in software development\u00a0\nHands on experience on RESTful/\u00a0GraphQL\u00a0API\nUnderstanding of DevOps (e.g. GitHub, Jenkins) to build, deploy and maintain the code pipeline is an advantage\u00a0\nExperience on API Integration with internal system and third-party software is an advantage\u00a0\nInnovative and strong analytical skill\u00a0\nKeen on technology and able to pick up latest technical skills\u00a0\nFresh graduates\u202fare welcome and considered as\u202fProgrammer\u00a0\nCandidates with\u202fmore experience\u202fcan be considered as\u202fSystem\u00a0Analyst\u00a0\u00a0", "employment_types": ["Part Time", "Temporary", "Contract", "Internship"], "selling_points": ["Students are welcome for the application!", "At least 2 days per week & hourly rate", "Gain practical O2O experience, drive ideas"], "locations": ["Shatin Area"], "categories": ["Others", "Student / Fresh Graduate / No Experience", "Marketing / Public Relations", "Digital Marketing", "E-commerce", "Software Development"], "post_time": "2021-12-25T00:07:47Z", "salary": {"currency": null, "max": null, "min": null, "period": null, "term": null}, "salary_visible": false, "title_keywords": ["full stack marketing intern"], "responsibilities": ["collaborate with", "software", "review", "design and develop", "systems", "design", "develop", "maintain", "deploy", "e-commerce platform", "setup", "analyse"], "requirements": {"degrees": ["diploma", "degree holder"], "majors": ["engineering", "computer science"], "languages": [], "language_level": [], "hard_skills": ["analytical skill", "agile", "jenkins", "e-commerce", "devops", "aws", "make", "dynamic", "integration", "code"], "soft_skills": ["analytical skill", "agile", "keen", "hands on", "dynamic", "technical skills", "innovative"], "languages_combined": []}, "experience_required": {"duration": ["0-5 years"], "field": ["system analyst", "software development"]}}, {"job_id": "100003009000316", "location_code": "hk", "company": "A.S. Watson Retail (HK) Limited", "job_title": "IT Business Analyst  - Website focus", "description": "Established in Asia in 2013 with a trailblazer mentality, FWD is the primary insurance business of investment group, Pacific Century Group (PCG), with minority shareholders Swiss Re Group, GIC Ventures, RRJ Capital and Hopu Investments.\n\nFWD spans 10 markets in Asia including Hong Kong SAR & Macau SAR, Thailand, Indonesia, the Philippines, Singapore, Vietnam, Japan, Malaysia and Cambodia. In Hong Kong, FWD offers life and medical insurance, general insurance, employee benefits, and financial planning. We focus on creating fresh customer experiences and making the insurance journey simpler, faster and smoother, with innovative propositions and easy-to-understand products, supported by digital technology. Through this customer-led approach, FWD aims to be a leading pan-Asian insurer by changing the way people feel about insurance.\n\nIf you are looking for a company where can fuel your inspiration and cultivate your expertise, join us on our exciting journey.\n\nThe Job\n\nBe a member of Enterprise Architecture & Common Platforms team and report to IT Senior Manager for the Open API, OpenShift, DevOps and Cloud projects\n\nLead and execute the architecture governance frameworks and strategies\n\nDeliver high quality solutions and in compliance with group standard\n\nInteract with stakeholders from various levels to ensure smooth communication\n\nEnsure change requests are well managed and prioritized according the change management control\n\nCoordinate and facilitate the project execution related activities\n\nCoordinate with IT and user team on project implementation arrangement\n\nAd-hoc duties as assigned\n\nThe Person\n\nUniversity degree in Computer Science or equivalent\n\nMinimum 5 years' related working experience in system design and development\n\nExperience in development and implementation on Enterprise Application Architecture solutions\n\nSolid experience in development and implementation in Java, JBOSS, API and DevOps\n\nExperience with AWS / Azure Cloud\n\nExperience in SprintBoot, Node.js, MicroServices and Java Spring is an advantage\n\nGood knowledge of Kubernetes, RPA and software implementation best practices\n\nUnderstanding of Agile/Lean software delivery methodology is preferred, able to work with user departments and vendors\n\nGood problem-solving skills and communication\n\nAble to work under pressure\n\nGood team player, self-initiative and pro-active\n\nWe offer 5-day work, 20-22 days annual leaves, excellent learning & development opportunities and an attractive package to the right candidate.\n\nInformation collected will be treated in strict confidence and used solely for recruitment purpose. The company will retain all applications no longer than 24 months of which will be destroyed thereafter. When there are vacancies in any of our subsidiaries, holding companies, associated or affiliated companies of, or companies controlled by, or under common control with the Company during that period, we may transfer your application to them for consideration of employment. We are an equal opportunity employer. We do not discriminate on the basis of race, sex, disability or family status in employment process.", "employment_types": ["Full Time", "Permanent"], "selling_points": ["Suggest to optimize eCom operations efficiency", "eCom system analyzing and trouble-shooting", "Strong in SQL and programming"], "locations": ["Shatin Area"], "categories": ["Information Technology (IT)", "Application Specialist - Software", "Technical / Functional Consulting", "E-commerce", "Software Development"], "post_time": "2021-12-25T00:06:13Z", "salary": {"currency": null, "max": null, "min": null, "period": "monthly", "term": null}, "salary_visible": false, "title_keywords": ["business analyst"], "responsibilities": [], "requirements": {"degrees": [], "majors": [], "languages": [], "language_level": [], "hard_skills": [], "soft_skills": [], "languages_combined": []}, "experience_required": {"duration": [], "field": []}}, {"job_id": "100003008998651", "location_code": "hk", "company": "Taste of Asia Group Limited", "job_title": "E-Commerce Specialist (IT)", "description": "Come and join a Winning Team\n\nWe are Awesome!\n\nWhy Should You Join Us?\n\nAt ASW, we believe in our people, in teamwork and the importance of your personal growth.\u00a0If you are looking for the opportunity to join our award-winning international family with 15,000+ stores across 25 markets in Asia and Europe, the ASW family welcomes you\u2026\u00a0 #BePartofMORE\n\nYou can enjoy:\n\nCompetitive compensation and benefits!\nFive-day work, plus casual wear every Friday, TGIF!\nAttractive ACCA and CPA Australia Recognized Employee Partnership for F&A talents!\nExclusive company pension schemes for our people!\nConvenient office location, less than 5 min. walk from MTR!\nExclusive shopping discount!\nContemporary workplace, free drinks and chill out areas!\nOnsite Clinic and Lactation Room!\nFree round-trip lunchtime shuttle bus services to Shatin!\nExclusive Bazaar Sales for our people only!\n\nRole Purpose:\nAs a Full Stack Marketing Intern, you will be supporting in our New Brand (\u4e0a\u5009\u80c3\u5b50). Including both digital marketing and business development team in ad-hoc research, assist in developing social strategies and upcoming Online + Offline projects.\n\nCheck out more about \u4e0a\u5009\u80c3\u5b50\u00a0\u2192 eShop\u00a0\u00a0Facebook\u00a0\u00a0Instagram\u00a0\u00a0Youtube\n\nA typical day in this Role:\u00a0\n\n\nResponsible for frontend development for the website\nBuild reusable code and libraries for development\nMaintain the good performance, quality applications\n\nThis job is a good fit for You if:\n\n\nYou are creative, outgoing &\u00a0sociable\u00a0candidate\nYou are interested in O2O\u00a0shop\nYou want to gain\u00a0practical\u00a0O2O experience & proven your ability in coding\u00a0\n\n\u00a0What we look for:\n\nKnowledge of\u00a0JavaScript, HTML 5, CSS3, Flash\u00a0\nAble to work independently, learn and pick up new technology\nGood communication skills in both Chinese and English\nPassionate for technology, eCommerce and lifestyle brands and with creative mindset\n\n\u00a0What is holding you back?\u00a0\n\nDon\u2019t miss out on this great chance to shape Your life!\u00a0\n\nApply now!\n\nInterested parties please e-mail your full resume in WORD FORMAT with expected salary to our company email (shown in our Company Profile).\n\nWe are an equal opportunity employer and welcome applications from all qualified candidates. The information provided will be treated in strict confidence and be used only for consideration of your application for relevant / similar posts within the A.S. Watson Group.\n\nApplicants not hearing from us within 6 weeks from the date of advertisement may consider their applications unsuccessful. All personal data of unsuccessful applicants will be destroyed within 12 months from the date of application.\u00a0", "employment_types": ["Full Time"], "selling_points": ["Five-day work week", "Medical & dental allowance", "Performance bonus"], "locations": ["Wong Tai Sin Area"], "categories": ["E-commerce", "Product Management / Business Analyst", "Software Development", "Supply Chain"], "post_time": "2021-12-24T04:00:08Z", "salary": {"currency": null, "max": null, "min": null, "period": "monthly", "term": null}, "salary_visible": false, "title_keywords": ["specialist"], "responsibilities": [], "requirements": {"degrees": [], "majors": [], "languages": [], "language_level": [], "hard_skills": [], "soft_skills": ["teamwork"], "languages_combined": []}, "experience_required": {"duration": [], "field": []}}, {"job_id": "100003008997146", "location_code": "hk", "company": "Super Hero Holdings Limited", "job_title": "Product Manager / Assistant Product Manager - TapNow", "description": "Responsibilities:\n\nResponsible for formulating and implementing the project development plan, including various work processes related to the project, to ensure that the project is completed on time\nUnderstand the product design path, and able to assist related teams in product design & demand analysis\nManage project deliverable, and the corresponding processes and stakeholders\nManage daily operations of the e-commerce platform functions\n\nRequirements:\n\nDegree or Higher Diploma or above in\u00a0Computer Science, Information Technology, Digital Marketing or related disciplines\nRelevant work experience in the new media industry and/or e-commerce field is preferred\nResponsible and able to work independently\nGood command of spoken and written in English and Chinese\n\n\u00a0Job Location: San Po Kong\n\nCompetitive remuneration package and benefits as below:\nFive-day work week\nMarriage leave\nStaff discount\nMedical & dental allowance\nPerformance bonus\nIn-service training course\n5 days paternity leave\nCompassionate Leave\nPromotion opportunities", "employment_types": ["Full Time", "Permanent"], "selling_points": ["Revolutionized business model", "Executive suite of this BU", "Pioneer of the founding product team"], "locations": ["Lai Chi Kok"], "categories": ["E-commerce", "Marketing - Brand / Product Management", "Product Management / Business Analyst", "Software Development"], "post_time": "2021-12-23T10:08:20Z", "salary": {"currency": null, "max": null, "min": null, "period": "monthly", "term": null}, "salary_visible": false, "title_keywords": ["assistant product manager", "product manager"], "responsibilities": ["demand analysis", "teams", "product design", "project development plan", "e-commerce platform", "manage daily operations", "product design path"], "requirements": {"degrees": ["higher diploma or above", "degree"], "majors": ["related disciplines", "digital marketing", "computer science", "information technology"], "languages": ["english", "chinese"], "language_level": ["good command"], "hard_skills": ["e-commerce"], "soft_skills": ["work independently", "responsible"], "languages_combined": [{"language": "english", "language_level": ["good command"]}, {"language": "chinese", "language_level": ["good command"]}]}, "experience_required": {"duration": [], "field": ["media", "e-commerce"]}}, {"job_id": "100003008997109", "location_code": "hk", "company": "Swire Properties Limited \u592a\u53e4\u5730\u7522\u6709\u9650\u516c\u53f8", "job_title": "Digital Officer (Project Management) (Ref: OS00065)", "description": "Come and join a Winning Team\n\nWe are Awesome!\n\nWhy Should You Join Us?\nAt ASW, we believe in our people, in teamwork and the importance of your personal growth.\u00a0If you are looking for the opportunity to join our award-winning international family with 15,000+ stores across 25 markets in Asia and Europe, the ASW family welcomes you\u2026\u00a0\u00a0#BePartofMORE\n\nYou can enjoy:\n\n\nComprehensive Medical and Life insurance coverage, including your spouse and children!\nProfessional training and career advancement opportunities!\nAttractive ACCA and CPA Australia Recognized Employer Program for F&A talents!\nExclusive company pension schemes!\u00a0 Marriage, Maternity and Paternity Leave!\nConvenient office location, less than 5 min. walk from MTR!\nContemporary workplace with Onsite Clinic, Lactation Rooms, free drinks and chill out areas!\nWell-equipped Gym inside our office building, plus fitness and interest class packages!\nFree round-trip lunchtime shuttle bus services to Shatin!\nExclusive shopping discount, Bazaar Sales for our people only!\n\nRole Purpose:\n\nThis position manages the retail eCommerce platforms.\u00a0 The main responsibilities are to drive improvement projects, from gathering requirements to project delivery across our Asia businesses. The role involves cross-functional project management across commercial, eCommerce, supply chain, and IT functional teams. The scope of the role includes understanding the business problem, developing solutions, preparing change documentation, and ensuring a successful deployment. You will on the lookout for continuous improvement opportunities and will be supporting our business units with best-in-class eCommerce/supply chain solutions.\n\n\nA typical day in this Role:\n\n\nResponsible for owning the project management process and methodology acting as the gatekeeper to the production environment, while ensuring a smooth delivery of planned system implementation.\nLiaise with Asia business units and development resources on eCommerce management system improvements and implementation\nEngage with technical, business and stakeholders in business units to ensure BU is fully on-board and deployment readiness.\nManage project implementation end-to-end (i.e., requirements gathering, change documentation, and creation of release notes) and ensure smooth and timely communication among stakeholders.\nKeep abreast of market knowledge and to recommend process improvement and streamlining to identify the best practice\n\nThis job is a good fit for You if:\n\n\nYou have a strong logical mind with data manipulation skill like Excel/SQL tools.\nYou have sound knowledge in retail systems, and eCommerce digital application systems.\nYou are passionate about Digital or E-commerce trends.\n\n\nWhat we look for:\n\n\nRelevant Bachelor degree or higher diploma, preferably in Business, Information Systems, Computer Science or IT related discipline\nExperience in implementation or support of eCommerce platform, or any other digital services such as website and mobile applications\nAbility to work in a fast-paced environment with a must-do attitude to deliver the best quality of work and provide account management services\nExcellent analytical, planning, and presentation skills\nExcellent written and verbal communication skills, fluent in both Cantonese and English, Mandarin is a plus\nCandidate with more experience will be considered as System Analyst\u00a0\n\n\u00a0What is holding you back?\u00a0\n\nDon\u2019t miss out on this great chance to shape Your life!\u00a0\n\nApply now!\n\nInterested parties please e-mail your full resume in WORD FORMAT with expected salary to our company email (shown in our Company Profile).\n\nWe are an equal opportunity employer and welcome applications from all qualified candidates. The information provided will be treated in strict confidence and be used only for consideration of your application for relevant / similar posts within the A.S. Watson Group.\n\nApplicants not hearing from us within 6 weeks from the date of advertisement may consider their applications unsuccessful. All personal data of unsuccessful applicants will be destroyed within 12 months from the date of application.\u00a0", "employment_types": ["Full Time", "Permanent"], "selling_points": ["Digital product development projects", "Work closely with project team, BU & vendor", "Conduct QA/acceptance testing"], "locations": ["Quarry Bay"], "categories": ["Information Technology (IT)", "Product Management / Business Analyst", "Marketing / Public Relations", "Marketing - Brand / Product Management", "E-commerce", "Software Development"], "post_time": "2021-12-23T09:58:12Z", "salary": {"currency": null, "max": null, "min": null, "period": null, "term": null}, "salary_visible": false, "title_keywords": ["officer"], "responsibilities": ["manipulation", "management", "data", "system improvements", "systems", "teams", "developing", "implementation", "website", "communication", "project management", "liaise with", "quality", "documentation", "application systems", "insurance", "planning"], "requirements": {"degrees": ["diploma", "degree", "bachelor"], "majors": ["business", "it", "computer science"], "languages": ["cantonese", "english", "mandarin"], "language_level": ["excellent", "fluent"], "hard_skills": ["excel", "acca", "plus", "e-commerce", "system implementation", "chill", "cpa", "project management", "sql", "mobile", "deployment", "documentation", "data manipulation"], "soft_skills": ["communication skills", "responsible", "fast-paced environment", "timely", "teamwork", "communication", "project management", "presentation skills", "comprehensive", "smooth", "passionate about"], "languages_combined": [{"language": "cantonese", "language_level": ["fluent", "excellent"]}, {"language": "english", "language_level": ["fluent", "excellent"]}, {"language": "mandarin", "language_level": ["excellent"]}]}, "experience_required": {"duration": [], "field": ["ecommerce", "digital", "system analyst"]}}, {"job_id": "100003008992912", "location_code": "hk", "company": "Osmium Consulting Group Limited", "job_title": "Backend Developer", "description": "This\u00a0position will be under HOME+ e-commerce platform.\n\nOur Vision of Home+ is to set up a merchant ecosystem of merchants with shared value, covering different aspects of our customers\u2019 daily household purchases. The mission is to provide customers with the best value for money for the promotional products and services offered, from time to time. For more information, please feel free to visit our website at\u00a0https://home-plus.hk/\n\nTo be part of our mission, we are looking for an AWS Engineer / AWS Administrator to\u2026\n\nAct as first contact person in case of alerts\nDesign and maintain highly available, cloud-based infrastructures in AWS.\nUnderstand of auto-scaling technologies and high-throughput designs.\nMonitor and troubleshoot in case of alerts and manage incidents to closure.\nManage full AWS Lifecycle, Provisioning, Automation and Security.\nConfigure and fine-tune cloud infrastructure systems.\nPerform software upgrades. Kernel patching, errata patches.\nAutomate deployment of infrastructure through the use of Cloud Formation or Terraform.\nEnforce resource tagging to designate costs and for planning of budgeting, governance, and reporting.\nCommunicate with the Cloud team to manage network connections on VPCs, VPNs.\nMonitor billing and to develop cost optimization strategies.\nEnforce AWS best practice in managing infrastructure\nMaintain a backup plan for all resources used on AWS.\nManage disaster recovery and create backups.\n\nThe follow attributes will be valued\u2026\n\n0 -2 years of experience in building infrastructure for enterprise applications and solutions using AWS.\nExperience with AWS cloud-based architectures\nExperience on using metrics to monitor the health, utilization and availability of AWS resources on a full scale by Amazon CloudWatch, CloudTrail and third party tools such as NewRelic.\nVery strong skills on the basics (Route53, EC2, ACM, ELB, VPC and S3).\nHands on experience on overcoming and protecting against a DDoS attack.\nHands on implementing one or more CloudFront Distributions and the core use-cases for a CDN.", "employment_types": ["Full Time"], "selling_points": ["Java", "Attractive Salary and Beneifts", "5-day Work Week"], "locations": ["Not Specified"], "categories": ["Information Technology (IT)", "Application Specialist - Software", "Software Development", "E-commerce", "Software Development"], "post_time": "2021-12-22T06:32:47Z", "salary": {"currency": null, "max": null, "min": null, "period": "monthly", "term": null}, "salary_visible": false, "title_keywords": ["developer"], "responsibilities": ["software", "budgeting", "website", "design", "maintain", "troubleshoot", "plan", "costs", "infrastructure", "monitor", "develop", "reporting", "upgrades", "contact", "backups", "third party", "communicate with", "cost optimization", "systems", "e-commerce platform", "planning"], "requirements": {"degrees": [], "majors": [], "languages": [], "language_level": [], "hard_skills": ["plus", "amazon", "e-commerce", "aws", "deployment", "s3"], "soft_skills": ["hands on", "troubleshoot"], "languages_combined": []}, "experience_required": {"duration": ["0 -2 years"], "field": ["infrastructure"]}}, {"job_id": "100003008987876", "location_code": "hk", "company": "Osmium Consulting Group Limited", "job_title": "Web Developer / Programmer ( PHP ) / Happy Work Environment with excellent career path", "description": "You can enjoy:\u00a0\n\nComprehensive Medical and Life Insurance coverage, including your spouse and children\nExclusive company pension schemes\nMarriage, Maternity and Paternity Leave\nExclusive shopping discount, Bazaar Sales for our people only\nProfessional training and career advancement opportunities\nConvenient office location, less than 5 min. walk from MTR\nContemporary workplace with Onsite Clinic, Lactation Rooms, free drinks and chill out areas\nWell-equipped Gym inside our office building, plus fitness and interest class packages\nFree round-trip lunchtime shuttle bus services to Shatin\n\nResponsibilities:\n\nAssist in operating and developing the eCommerce & digital front-end platform (including eCommerce Store, desktop & mobile website, mobile apps etc)\nAssist and ensure the smooth execution of eCommerce activities including promotion campaigns, content management, logistics arrangement and all other related web activities\nWork closely with internal and external parties such as IT, CS, Marketing and Trading to execute marketing activities on eCommerce platforms\nRequirements:\n\nUniversity graduate in, eCommerce, information system or related disciplines\n2-3 years hands-on experience in eCommerce, web/ app project development\nExperience in UI/UX in eCommerce sites & mobile apps\nKnowledge in content management system\nFamiliar with eCommerce platforms and payment gateways and operation.\nStrong sense of responsibility and self-motivation\nGood Interpersonal and communication skills\nGood level of spoken and written English, Chinese and Mandarin\nAn attractive salary and benefit package will be offered. Interested parties please forward detailed resume stating expected salary to: People Department, A.S. Watson Retail Hong Kong, Watson House, 1-5 Wo Liu Hang Road, Fotan, N.T. or e-mail to us.\n\nWe are an equal opportunity employer and welcome applications from all qualified candidates. The information provided will be treated in strict confidence and be used only for consideration of your application for relevant / similar posts within the A.S. Watson Group. All personal data of unsuccessful applicants will be destroyed within 12 months from the date of application.", "employment_types": ["Full Time", "Permanent"], "selling_points": ["PHP", "Web Developer", "Attractive Package"], "locations": ["Yau Tsim Mong Area"], "categories": ["Information Technology (IT)", "Application Specialist - Software", "Software Development", "E-commerce", "Software Development"], "post_time": "2021-12-20T08:24:21Z", "salary": {"currency": "HKD", "max": 34999, "min": 25000, "period": "monthly", "term": null}, "salary_visible": true, "title_keywords": ["developer", "programmer"], "responsibilities": ["management", "logistics arrangement", "internal and external parties", "developing", "website", "promotion campaigns"], "requirements": {"degrees": ["university graduate"], "majors": ["ecommerce", "related disciplines"], "languages": ["english", "chinese", "mandarin"], "language_level": ["good"], "hard_skills": ["mobile", "information system", "web"], "soft_skills": ["communication skills", "sense of responsibility", "hands-on", "self-motivation", "interpersonal"], "languages_combined": [{"language": "english", "language_level": ["good"]}, {"language": "chinese", "language_level": ["good"]}, {"language": "mandarin", "language_level": ["good"]}]}, "experience_required": {"duration": ["2-3 years"], "field": ["ecommerce", "development"]}}]