[{"job_id": "100003009053219", "location_code": "hk", "company": "Eternity Commerce Limited", "job_title": "E-Commerce Supply Chain Assistant/Officer (Logistics&Procurement/Sourcing/Merchandising/Purchasing)", "description": "Job Responsibilities:\n\nCollaborate with sales team and warehouse for delivery schedule arrangement and issue delivery note\nAssist in sourcing and purchasing raw materials\nLiaise with suppliers to drive on- time shipment delivery\nHandle order processing, inventory control and coordinate all transportation including ocean and air freight forwarding\nHandle purchase orders and shipping documents. Freight rate checking and transit time analysis\nMonitor supply availability, quality standards, cost & contracts and ensure deliverables are achieved to project site\nAssist in handling product quality issue and quality control\nAd hoc tasks as assigned\n\nRequirement:\n\nHigher Diploma or above, major in Supply Chain Management/Logistics, Mathematics, Science, Business or equivalent\nFresh graduates with passion and willing to learn are welcomed\nGood knowledge of PC and Excel is essential\nGood command of both spoken and written English and Chinese\nSelf-motivated, well organized, able to work independently and strong compliance with ability to meet deadlines\nCandidate with more experience will be consider as Supply Chain Officer\nImmediately available is preferred\u00a0\n\nOur attractive remuneration includes:\n\nMedical Insurance\nDouble Pay\nDiscretionary Bonus\nBirthday Leave\nPaid Sick Leave\nGym Membership\nFive Days Work Week\nFlexible working hours\nEducation Allowance", "employment_types": ["Full Time"], "selling_points": ["Logistics/Procurement/Purchasing/Merchandising", "Fresh Graduates are Welcome", "Young & Energetic Working Environment"], "locations": ["Quarry Bay"], "categories": ["Transportation & Logistics", "Supply Chain", "Merchandising & Purchasing", "Procurement / Purchasing / Sourcing", "E-commerce", "Supply Chain"], "post_time": "2022-01-17T06:27:59Z", "salary": {"currency": null, "max": null, "min": null, "period": "monthly", "term": null}, "salary_visible": false, "title_keywords": ["officer", "merchandising", "supply chain assistant"], "responsibilities": ["collaborate with", "shipping documents", "quality", "product quality issue", "purchase", "contracts", "monitor", "cost", "air freight", "ad hoc tasks", "checking", "delivery schedule", "inventory control", "analysis", "coordinate", "sales team", "order processing", "quality control", "liaise with suppliers"], "requirements": {"degrees": ["higher diploma or above"], "majors": ["mathematics", "business", "science"], "languages": ["english", "chinese"], "language_level": ["good command"], "hard_skills": ["pc", "excel"], "soft_skills": ["flexible", "self-motivated", "work independently", "willing to learn", "well organized", "meet deadlines"], "languages_combined": [{"language": "english", "language_level": ["good command"]}, {"language": "chinese", "language_level": ["good command"]}]}, "experience_required": {"duration": [], "field": ["supply chain"]}}, {"job_id": "100003009052762", "location_code": "hk", "company": "G3 Worldwide Hong Kong Limited", "job_title": "Business Development Manager / Assistant Business Development Manager", "description": "To prospect, analyze, and recommend business solutions to major accounts from e-platforms, consolidators and direct e-sellers.\nTo make sales plan and meet the sales targets given by the company, ensuring continuous growth and maximizing returns.\nTo obtain information of market trends and customer needs, therefore providing insights to the management, with recommendations.\nTo establish business pipeline in parallel with sales plan, ensuring sales force efficiency and healthy new business development in line with sales and strategic plans.\nTo maintain regular contact and follow up with existing accounts, for maximum retention and sustainable business relationship.\nTo analyze trading portfolio and identify threat and opportunity.\u00a0\nProvide weekly sales updates and report.\u00a0\nHandle ad hoc projects as assigned.\nRequirements\nDegree holder in any disciplines.\nMin. 5 years of B2B sales / account servicing experience preferably in logistics industry\nKnowledgeable in e-platform / supply chain management is desirable.\nProficient in both English and Chinese.\nExcellent negotiation and interpersonal skills.\nAggressive, flexible and can-do attitude preferred.\u00a0\nFrequently travel to China or Asia Pacific region is envisaged.\u00a0\nImmediately availability is preferred\n\nG3 Worldwide Hong Kong Limited\u00a0is an equal opportunity employer and welcomes applications from all qualified candidates. Information provided will be treated in strict confidence and only be used for recruitment related purposes. Applicants who are not contacted within 6 weeks may consider their application unsuccessful. Unsuccessful applications may be kept for another 3 months for being considered for other suitable positions available in our Company. The unsuccessful applications will be destroyed after the said period of retention.\n", "employment_types": ["Full Time"], "selling_points": [], "locations": ["Ngau Tau Kok"], "categories": ["Transportation & Logistics", "Shipping", "E-commerce", "Business Development", "Supply Chain"], "post_time": "2022-01-17T03:58:17Z", "salary": {"currency": null, "max": null, "min": null, "period": "monthly", "term": null}, "salary_visible": false, "title_keywords": ["business development manager", "assistant business development manager"], "responsibilities": ["management", "strategic plans", "maintain", "ad hoc projects", "contact", "plan", "logistics", "recruitment", "report"], "requirements": {"degrees": ["degree holder"], "majors": ["any disciplines"], "languages": ["english", "chinese"], "language_level": ["proficient"], "hard_skills": ["make"], "soft_skills": ["flexible", "confidence", "negotiation", "can-do attitude", "interpersonal skills"], "languages_combined": [{"language": "english", "language_level": ["proficient"]}, {"language": "chinese", "language_level": ["proficient"]}]}, "experience_required": {"duration": ["5 years"], "field": ["logistics industry", "account servicing"]}}, {"job_id": "100003009052336", "location_code": "hk", "company": "KW-Commerce Asia Limited", "job_title": "Supply Chain Planner", "description": "To cope with our business development and expansion in eCommerce, our Hong Kong office is now inviting high caliber candidate to join us for the position of\u00a0Business Support Executive, eCommerce, South China & HK\n\u00a0\n\u00a0\nThe job\u00a0holder will assisting the Head of eCommerce, South China & HK, on the support all commercial activities and\u00a0client management of the eCommerce business for South China & HK markets through the following major responsibilities including but not limited to:\n\n\u00a0Duties & Responsibilities:\n\u00a0\nProvide support on client onboarding, system training, shipment tracking\u00a0and billing.\nHandle clients' enquiries and resolve complaint in timely and professional manner.\nIdentify clients' needs and new opportunities throughout regular communication with client.\nAdminister and maintain eCommerce portal.\nAssist in analyzing and monitoring performance and shipping trend of clients, and preparing monthly report to management.\n\nRequirements:\n\nDegree holder in Business Administration, Supply Chain Management or related discipline.\nMinimum 2 years' working experience, preferably in eCommerce industry.\nTeam player with good communication and problem-solving skills, and attention to details.\nPatient and proactive to build relationship with customers.\nFamiliarized with MS Office and data analytics applications and methodologies.\nGood command of both spoken and written English, Mandarin and Chinese\n\nWORKING CONDITIONS\n\nThe office working environment is generally favorable. We offer attractive remuneration and benefits including,\u00a05 days work per week, annual leave, discretionary bonus, medical & dental scheme and 13th payroll. Our office is located in Diamond Hill.", "employment_types": ["Full Time", "Permanent"], "selling_points": ["Talented Fresh Graduates would be considered", "Flexible working hours and work-from-home option", "Work with people who are friendly and supportive"], "locations": ["Kwai Fong"], "categories": ["E-commerce", "Supply Chain", "Others"], "post_time": "2022-01-17T02:48:13Z", "salary": {"currency": null, "max": null, "min": null, "period": "monthly", "term": null}, "salary_visible": false, "title_keywords": ["supply chain planner"], "responsibilities": ["provide support", "shipping", "management", "monitoring", "professional manner", "communication", "maintain", "monthly report", "tracking"], "requirements": {"degrees": ["degree holder"], "majors": ["business administration"], "languages": ["english", "chinese", "mandarin"], "language_level": ["good command"], "hard_skills": ["problem-solving skills", "data analytics", "scheme", "ms office"], "soft_skills": ["patient", "communication", "attention to details", "problem-solving skills", "team player", "proactive"], "languages_combined": [{"language": "english", "language_level": ["good command"]}, {"language": "chinese", "language_level": ["good command"]}, {"language": "mandarin", "language_level": ["good command"]}]}, "experience_required": {"duration": ["minimum 2 years"], "field": ["ecommerce"]}}, {"job_id": "100003009052609", "location_code": "hk", "company": "Crane Worldwide Logistics Hong Kong Limited", "job_title": "Business Support Executive, eCommerce, South China & HK", "description": "E-commerce SpecialistJob Highlights\nFive-day work week\nMedical & dental allowance\nPerformance bonus\n\nJob Description\n\n\u00b7 To build a B2B E-commerce platform from zero, ensure it is deliverable. Must be knowledgeable and multitask in sales, marketing, operation, logistics...etc. across different field\n\n\u00b7 To support development and implementation of a new-built B2B E-commerce platform towards company\u2019s vision, roadmap and strategy\u00a0\n\n\u00b7 To develop standard operation procedures, deliver user training and launch new e-Commerce channels and logistics\u00a0\n\n\u00b7 To work with internal and external stakeholders on the new E-commerce platform delivery, knowledge transfer workshop, and KPI monitoring\n\n\u00b7 To act as an ambassador and coordinate internal/external stakeholders with a strong sense of communication, and off-site visit is required whenever necessary\u00a0\n\n\u00b7 To optimize the group\u2019s end-to-end E-commerce journey by devising a new solution, service, or proposition\u00a0\n\n\u00b7 To identify and implement new opportunities throughout the E-commerce journey to deliver high-performing, agile stakeholder interactions and touchpoints.\u00a0\n\n\u00b7 To collaborate with the management team on the next wave of company\u2019s E-commerce strategies\u00a0\n\nJob Requirement\n\n\u00b7 Degree in Business Management / E-commerce / Computer Science / I.T. or related disciplines\n\n\u00b7 Minimum 2-3 years working experience in E-commerce, IT background is an advantage\n\n\u00b7 Experience in working with system UAT / UX / UI is preferable\u00a0\n\n\u00b7 Analytical with excellent business and market sense\n\n\u00b7 Confident in approaching new products / business model / concepts / solutions\u00a0\n\n\u00b7 Good command of spoken and written English and Chinese\n\n\u00b7 Independent, good interpersonal communication skills, able to work with critical timelines and challenges\u00a0\n\n\u00b7 Deep understanding of commercial levers in driving performance and growth\u00a0\n\nJob location: San Po Kong\n\nCompetitive remuneration package and benefits as below:\n\nFive-day work week / Marriage leave / Staff discount / Medical & dental allowance / Performance bonus / In-service training course / 5 days paternity leave / Compassionate Leave / Promotion opportunities", "employment_types": ["Full Time", "Permanent"], "selling_points": ["5 days work", "Medical & dental scheme", "competitive remuneration package and benefits"], "locations": ["Wong Tai Sin Area"], "categories": ["Transportation & Logistics", "Freight Forwarding", "E-commerce", "Product Management / Business Analyst", "Supply Chain"], "post_time": "2022-01-17T03:32:09Z", "salary": {"currency": null, "max": null, "min": null, "period": "monthly", "term": null}, "salary_visible": false, "title_keywords": ["executive"], "responsibilities": ["collaborate with", "management team", "workshop", "monitoring", "procedures", "implementation", "e-commerce strategies", "develop", "coordinate", "communication", "logistics", "e-commerce platform"], "requirements": {"degrees": ["degree"], "majors": ["business", "computer science", "e-commerce"], "languages": ["english", "chinese"], "language_level": ["good command"], "hard_skills": ["business management", "e-commerce"], "soft_skills": ["confident", "communication skills", "independent", "deep", "interpersonal"], "languages_combined": [{"language": "english", "language_level": ["good command"]}, {"language": "chinese", "language_level": ["good command"]}]}, "experience_required": {"duration": ["minimum 2-3 years"], "field": ["it", "e-commerce"]}}, {"job_id": "100003009052754", "location_code": "hk", "company": "Taste of Asia Group Limited", "job_title": "E-commerce Specialist", "description": "Job Description\n\nTo formulate online marketing plans and strategies to drive sales\nTo manage all online sales channels in relation to traffic acquisition, sales, conversion, and reporting.\nTo manage the whole operation between warehouse, logistic company, and end customers.\nTo work closely with internal parties to align all campaigns to drive sales.\nTo develop and implement digital marketing strategy, e-Commerce brand sites, other Channels for business growth for the company.\nTo enhance the website content and flow to grow customer usage, traffic, and conversion rate.\nTo perform Ad-hoc assignments as required.\n\n\u00a0Requirements:\n\nBachelor or above in e-Commerce, Marketing, IT, Communications or related disciplines.\nMinimum 3 years solid experience in operating online store systems (ex. Shopify) and other online marketplaces such as Amazon, Lazada, Zalora etc.\nPreferences will be given to candidates with experience in online selling of fashion products.\nDigital marketing skills such as SEO, Paid search, Social Media advertising are needed.\nCreative, proactive, and independent with a strong marketing sense.\nDetail minded, Data sensitive, strong sense of responsibility and a good team player.\nFluent in written and spoken English and Cantonese, Mandarin a plus.\nCandidate with less experience will be considered as Assistant Ecommerce Manager.\n\n\u00a0Benefits:\n\nAttractive Salary Package\nYear-end Performance Bonus\n10 - 22 days Annual Leave\nPaid Sick Leave\u00a0\n5-day work week\nBirthday\u00a0Leave\nBirthday gift\nStaff Purchase Discount\nTravel Allowance", "employment_types": ["Full Time"], "selling_points": ["Five-day work week", "Medical & dental allowance", "Performance bonus"], "locations": ["Wong Tai Sin Area"], "categories": ["Information Technology (IT)", "Software Development", "E-commerce", "Supply Chain", "Others"], "post_time": "2022-01-17T03:55:55Z", "salary": {"currency": null, "max": null, "min": null, "period": "monthly", "term": null}, "salary_visible": false, "title_keywords": ["specialist"], "responsibilities": ["reporting", "marketing plans", "ad-hoc assignments", "website", "develop", "digital marketing", "brand sites", "drive sales", "internal parties"], "requirements": {"degrees": ["bachelor"], "majors": ["e-commerce", "related disciplines", "marketing", "it", "communications"], "languages": ["cantonese", "english", "mandarin"], "language_level": ["fluent"], "hard_skills": ["marketing skills", "amazon", "seo", "plus", "e-commerce", "shopify"], "soft_skills": ["good team player", "proactive", "marketing sense", "independent", "sense of responsibility", "sensitive", "creative"], "languages_combined": [{"language": "cantonese", "language_level": []}, {"language": "english", "language_level": []}, {"language": "mandarin", "language_level": ["fluent"]}]}, "experience_required": {"duration": ["minimum 3 years"], "field": ["ecommerce"]}}, {"job_id": "100003009048736", "location_code": "hk", "company": "Market Hong Kong Limited", "job_title": "Logistics Officer (5-day work)", "description": "Responsibilities\n\nHandle daily local stock replenishment orders from 3PL warehouse\nWork closely with 3PL for daily logistic and warehouse operation\nHandle import and export shipments, manage inbound and outbound orders and documentations among different countries and customs\nSupport on reporting, prepare and review monthly supply chain and inventory reports\nSupport the Showroom pickup counter & handle customers\u00a0enquiries\nPerform other duties as assigned by management\u00a0\n\nRequirements\n\nHigher Diploma in Logistics or related disciplines\n2-3\u00a0years\u2019 experience in\u00a0 logistic or supply chain operations\nIndependent, responsible, mature, well-organized and detail-minded\nStrong communication and interpersonal skills\nGood command of written and spoken English, Cantonese and Putonghua\nProficient in MS Excel such as Vlookup, Pivot Table, advanced formulas\nImmediate available will be an advantage\nWorking hours: 11:30am - 8:30pm (Mon - Fri) , 10:30am - 7:30pm (Sat)\nCandidates with more experience might be considered as Senior / Supervisor position\n\n\u00a0The post comes with:\n\n5-day working week\nCompetitive salary\nMedical & dental coverage\nBank Holidays\n13th month pay\nBirthday Leave\nStaff purchase discount\n\n\u00a0Interested parties please send your CV with expected salary and available date by clicking \u201cApply Now\u201d. We offer competitive remuneration package to the right candidate.\n\nNote: All information provided by applicants will be treated in strict confidence and used for recruitment purpose only. All personal data of unsuccessful applicants will be destroyed within one year.", "employment_types": ["Full Time", "Permanent"], "selling_points": [], "locations": ["Tsim Sha Tsui"], "categories": ["Transportation & Logistics", "Inventory / Warehousing", "Supply Chain", "E-commerce", "Supply Chain"], "post_time": "2022-01-14T07:10:59Z", "salary": {"currency": null, "max": null, "min": null, "period": "monthly", "term": null}, "salary_visible": false, "title_keywords": ["logistics officer"], "responsibilities": ["reporting", "perform other duties", "stock replenishment", "management", "inventory", "review", "reports"], "requirements": {"degrees": ["diploma"], "majors": ["related disciplines"], "languages": ["cantonese", "putonghua", "english"], "language_level": ["good command"], "hard_skills": ["pivot table", "ms excel", "vlookup"], "soft_skills": ["detail-minded", "independent", "advanced", "responsible", "well-organized", "mature", "communication and interpersonal skills"], "languages_combined": [{"language": "cantonese", "language_level": ["good command"]}, {"language": "putonghua", "language_level": ["good command"]}, {"language": "english", "language_level": ["good command"]}]}, "experience_required": {"duration": ["2-3 years"], "field": ["supply chain", "supervisor position"]}}, {"job_id": "100003009052058", "location_code": "hk", "company": "PERSOLKELLY Hong Kong Limited", "job_title": "Administrator, Procurement team (e-commerce company)", "description": "About Us:\n\nWe are an international e-commerce company with headquarters in the start-up metropolis Berlin.\u00a0\n\nAt KW-Commerce, we have an ambitious goal: Great products everywhere. We are building the leading global marketplace seller. We bring color and variety into the lives of our customers. We think and act big. We market globally. We sell affordable long-tail products for everyone.\u00a0\n\nWe are expanding our team in the Hong Kong Office now, and we want YOU to be part of this amazing adventure!\n\nYour Role:\n\nWe\u2019re looking for some fantastic colleagues to join our new planning team at KW to support moving our products around the globe in the most efficient way. We are looking for a diverse, agile, and passionate Supply Chain planner. We are looking for candidates who have some planning experience. However, we will accept candidates such as fresh graduates or candidates with less experience who have a high aptitude and an energetic outlook excited to build up a new process and optimize as the company grows.\u00a0\n\nCreating forecasts for our carriers: reviewing all of our current requirements to ship stock to our global markets to determine our equipment requirements across the company\u00a0\nBuilding and planning containers and ensuring the data flow throughout the process\u00a0\nCreating/ uploading shipping plans to Amazon and using Seller central / shipper central amongst other key system interfaces\nWorking with many internal and external parties such as 3PLs/ Transport team / Merchandising team / Category Managers \u2013 reviewing key priorities and amending any plans to fit relevant requirements\nMake decisions on what stock to expedite or delay based on business priority and rulesets\nWorking in a multinational environment dealing with ad hoc challenges and improving/ changing processes to handle our business growth\n\nWhat we\u2019d like to see in our ideal candidate:\n\nBachelor\u2019s degree or above\nExperience in\u00a0Supply Chain / Logistic is preferred but not essential\nExperience in following processes and managing daily activities through excel and other systems\nStrong business acumen and analytical skills. Eager to learn and develop soft/ hard skills\nGlobal supply chain experience working with E-Commerce/ Amazon/ FBA is desirable\nAbility to problem solve and make suggestions for business process improvements\nFluent English (Business English), Mandarin / Cantonese beneficial\u00a0\nDrive and hunger to make a difference at pace\nTalented Fresh Graduates would be considered\nWhat else awaits you:\n\nFlat hierarchies, open communication, quick decisions, and fast results\u00a0\u00a0\nA lot of personal accountability in a working environment that gives you plenty of room to realize your ideas and visions\u00a0\nA friendly and supportive team as well as a workplace equipped with state-of-the-art tools and equipment\u00a0\nTransparent corporate communication\u00a0\nFlexible working hours and work-from-home option\u00a0\nA fast-paced environment with a steep learning curve\u00a0\n\nAll applications will be collected for recruitment purposes only and treated in strict confidentiality.", "employment_types": ["Full Time", "Contract"], "selling_points": ["5 days working", "Renewable contract", "Innovative culture"], "locations": ["Causeway Bay"], "categories": ["Admin & HR", "Clerical / Admin Staff", "E-commerce", "Supply Chain"], "post_time": "2022-01-17T01:59:31Z", "salary": {"currency": null, "max": null, "min": null, "period": "monthly", "term": null}, "salary_visible": false, "title_keywords": ["administrator"], "responsibilities": ["shipping", "ad hoc", "ideas", "data", "internal and external parties", "merchandising", "systems", "develop", "communication", "business process", "recruitment", "plans", "planning"], "requirements": {"degrees": ["degree or above", "bachelor"], "majors": [], "languages": ["cantonese", "english", "mandarin"], "language_level": ["fluent"], "hard_skills": ["planner", "excel", "amazon", "agile", "e-commerce", "analytical skills", "goal", "make", "outlook", "seller central", "acumen"], "soft_skills": ["efficient", "passionate", "supportive", "flexible", "agile", "accountability", "problem solve", "fast-paced environment", "analytical skills", "communication", "diverse", "eager to learn", "learning", "friendly", "business acumen", "energetic", "ideal"], "languages_combined": [{"language": "cantonese", "language_level": []}, {"language": "english", "language_level": ["fluent"]}, {"language": "mandarin", "language_level": []}]}, "experience_required": {"duration": [], "field": ["supply chain", "e-commerce", "planning"]}}, {"job_id": "100003009050542", "location_code": "hk", "company": "Sa Sa Dot Com Limited", "job_title": "Assistant Logistics Officer (Fresh Graduate Welcome)", "description": "Our client is\u00a0a Chinese e-commerce, retail and technology conglomerate is seeking for a Procurement Assistant to support their daily operations.\n\nResponsibilities:\n\nHands on source-to-pay procurement process with multiple categories focus (mainly in IT & Telcom, Facility Services & Marketing Services) via in-house group procurement platform.\nProvides full process support with internal stakeholders and external suppliers in order to achieve business targets by implementing sourcing & procurement execution within the group procurement policy and procedures.\u00a0\nKeep constant collaboration with central Group Procurement team in Hangzhou, as well as other regional teams, to maintain the synergy of category strategies, process improvement, and best practice sharing of overseas procurement operation.\nCollaborates with other functions such as Finance, Legal, HR in maintaining overall process control and mutual key performance metrics.\nExecuting project-based sourcing with guidance of the line manager. Develop local category strategy and expand local supply base.\nRequirements and Qualifications:\n\nAt least one year working experience in supply chain or procurement related industry;\nBachelor degree in supply chain, business management, finance, or related disciplines.\nFast learning in a very dynamic and fast pace environment;\nPatient with sense of customer care, open-minded and willing to pro-actively communicate with others;\nProficient English and Mandarin, other language is a plus;\nFamiliar with online procurement tools as well as major IT tools. Advance user of Excel and Power Point, or database tools is a plus;\nTo apply for this position, please click on \u201cApply Now\u201d bottom.\u00a0 All applications will be treated in strict confidence, and used for recruitment purposes only in accordance with PERSOLKELLY Hong Kong Limited\u2019s Privacy Notice.\u00a0\u00a0", "employment_types": ["Full Time"], "selling_points": ["Participate on project execution", "Performance reporting and automation on reports", "Exp in cross-border eCom trade to PRC is a plus"], "locations": ["Siu Sai Wan"], "categories": ["Transportation & Logistics", "Inventory / Warehousing", "Supply Chain", "E-commerce", "Supply Chain"], "post_time": "2022-01-14T10:40:15Z", "salary": {"currency": null, "max": null, "min": null, "period": null, "term": null}, "salary_visible": false, "title_keywords": ["assistant logistics officer"], "responsibilities": ["guidance", "control", "maintaining", "hr", "teams", "procedures", "performance metrics", "develop", "maintain", "executing"], "requirements": {"degrees": ["degree", "bachelor"], "majors": ["related disciplines", "finance", "business"], "languages": ["english", "mandarin"], "language_level": ["proficient"], "hard_skills": ["business management", "excel", "plus", "dynamic", "power point"], "soft_skills": ["confidence", "open-minded", "dynamic", "learning", "patient"], "languages_combined": [{"language": "english", "language_level": ["proficient"]}, {"language": "mandarin", "language_level": ["proficient"]}]}, "experience_required": {"duration": ["at least one year"], "field": ["related", "supply chain", "procurement"]}}, {"job_id": "100003009050544", "location_code": "hk", "company": "Sa Sa Dot Com Limited", "job_title": "Operations Officer (eCommerce)", "description": "Responsibilities\u00a0\nParticipate on project execution;\nAssist on performance reporting and automation on reports to improve efficiency;\nSupport on planning delivery schedule on stock replenishment to China;\nParticipate on preparing flowchart of processes, user guide and training material;\nWork closely with other departments to follow up logistics processes;\nProvide ad hoc support to managers.\n\nRequirements\n\n\nDegree holder in Logistics or supply chain disciplines;\n1 year or above logistics working experience, familiar with operations on cross-border e-commerce trade to China is preferable;\nIndependent, self-motivated and good team-player;\nGood communication skills in written and spoken Cantonese, English and Mandarin;\nProficient PC skills, Word and Excel, acknowledge of SAP & VBA & Macro is preferable;\nImmediate available is an advantage.\n\nWe offer\n\n5 - day work week\nMedical Benefits\nAnnual Merit Bonus\nStaff Purchase Discounts\nStaff Recreation Activity\nShuttle Bus Service\nEducation Sponsorship\n\nInterested parties please send a full resume with current and expected salary by clicking APPLY NOW:\n\nPlease visit our corporate website at\u00a0http://corp.sasa.com/en/home\u00a0to know more about us.\n\n(Sa Sa is an Equal Opportunity Employer and all qualified applicants will receive consideration for employment. Personal data collected will be kept confidential and used for recruitment purpose only)", "employment_types": ["Full Time"], "selling_points": ["Operations of various eCom channels", "Manage daily operation of multiple eCom channels", "Support in planning & promotional activities"], "locations": ["Siu Sai Wan"], "categories": ["E-commerce", "Product Management / Business Analyst", "Supply Chain"], "post_time": "2022-01-14T10:40:15Z", "salary": {"currency": null, "max": null, "min": null, "period": null, "term": null}, "salary_visible": false, "title_keywords": ["operations officer"], "responsibilities": ["reporting", "stock replenishment", "ad hoc", "follow up logistics processes", "work closely with other departments", "delivery schedule", "reports", "planning"], "requirements": {"degrees": ["degree holder"], "majors": [], "languages": ["cantonese", "english", "mandarin"], "language_level": ["good"], "hard_skills": ["excel", "vba", "macro", "sap", "e-commerce", "word", "pc skills"], "soft_skills": ["team-player", "communication skills", "self-motivated", "independent"], "languages_combined": [{"language": "cantonese", "language_level": ["good"]}, {"language": "english", "language_level": ["good"]}, {"language": "mandarin", "language_level": ["good"]}]}, "experience_required": {"duration": ["1 year"], "field": ["logistics", "e-commerce"]}}, {"job_id": "100003009049001", "location_code": "hk", "company": "", "job_title": "Warehouse and Logistics Coordinator", "description": "Responsibilities\nManage daily operation of multiple e-commerce channels including orders, products, contents and promotion;\nResponsible for uploading & maintenance of all listed products;\nMonitor stock level to avoid OOS of platforms;\nHandle ad hoc operation tasks about eCommerce channels per request;\nLiaise and coordinate with business partners and related departments on day-to-day business operations.\n\nRequirements\n\nDiploma or above with minimum of 3 years relevant working experience;\nExperience in operating CN and Oversea platforms is highly preferred;\nProficiency in Microsoft Excel and Word;\nExcellent in both written and spoken Chinese and English;\nHigh level of flexibility and adaptability with good problem-solving skills.\n\nWe offer\n\n5 - day work week\nMedical Benefits\nAnnual Merit Bonus\nStaff Purchase Discounts\nStaff Recreation Activity\nShuttle Bus Service\nEducation Sponsorship\n\nInterested parties please send a full resume with current and expected salary by clicking APPLY NOW:\n\nPlease visit our corporate website at\u00a0http://corp.sasa.com/en/home\u00a0to know more about us.\n\n(Sa Sa is an Equal Opportunity Employer and all qualified applicants will receive consideration for employment. Personal data collected will be kept confidential and used for recruitment purpose only)", "employment_types": ["Full Time"], "selling_points": ["3PL and warehouse management", "Logistics costs analysis", "Familiar with supply chain operations"], "locations": ["Kwun Tong Area"], "categories": ["E-commerce", "Supply Chain"], "post_time": "2022-01-14T08:00:42Z", "salary": {"currency": null, "max": null, "min": null, "period": "monthly", "term": null}, "salary_visible": false, "title_keywords": ["logistics coordinator"], "responsibilities": ["liaise", "ad hoc", "maintenance", "operations", "monitor", "daily operation", "coordinate with", "contents"], "requirements": {"degrees": ["diploma or above"], "majors": [], "languages": ["english", "chinese"], "language_level": ["excellent"], "hard_skills": ["problem-solving skills", "word", "microsoft excel"], "soft_skills": ["problem-solving skills", "adaptability"], "languages_combined": [{"language": "english", "language_level": ["excellent"]}, {"language": "chinese", "language_level": ["excellent"]}]}, "experience_required": {"duration": ["minimum of 3 years"], "field": ["relevant working experience"]}}, {"job_id": "100003009051077", "location_code": "hk", "company": "Talent Blue Search Limited", "job_title": "Demand Planning Manager (Ecommerce) \u2013 Fashion Label Worldwide Market", "description": "Responsibilities\n\nOversee Hong Kong and overseas 3PL regional warehouses\nLead a small team to oversee inventory replenishment between all warehouses\nOversee Hong Kong, China and oversea warehouse inventory control process\nAnalyze and Negotiate warehousing, B2C & B2B price with vendors\nMonitor service levels with all vendors\nGenerate KPI reports to measure supply chain performance\nSupervise warehousing, B2C and B2B team in daily operations\nCreate policy and procedures for logistics activities\nEvaluating and developing solutions to issues or opportunities for improvement in warehousing, and shipping with objective of shortening lead time and offering improved services to customers and/or reduction in operating cost\nReview warehouse and logistics monthly reports and analysis\nExecute and discuss implementation with IT\nAssist the management of ad hoc assignment to support the global business\n\nRequirements\n\nDegree in supply chain management or related discipline\nMinimum 3 years in Global Supply Chain with 1+ years in leadership position, preferably from e-commerce/ FMCG / retail environment / warehouse operations / 3PL\nExperience in managing all aspects of supply chain operations\nExperience in e-commerce would be an advantage\nExcellent leadership, interpersonal and communication skills and with high energy levels\nDemonstrated ability to work effectively with all levels of management, internal and external clients, all around the world\nDemonstrated ability to drive change and continuous improvement\nExcellent oral and written communication skills in both English, Cantonese and Mandarin\nInterested candidates, please contact us at 55274271 for company details before applying.", "employment_types": ["Full Time", "Permanent"], "selling_points": ["Supply Chain Leadership Global Exposure Ecommerce", "Beauty Fashion Consumer Logistics Experience", "720K \u2013 800K per annual"], "locations": ["Not Specified"], "categories": ["Engineering", "Manufacturing & Production", "Transportation & Logistics", "Shipping", "E-commerce", "Supply Chain"], "post_time": "2022-01-15T01:53:27Z", "salary": {"currency": null, "max": null, "min": null, "period": "monthly", "term": null}, "salary_visible": false, "title_keywords": ["manager"], "responsibilities": ["warehousing", "cost", "shipping", "management", "monthly reports", "lead a small team", "review", "monitor", "procedures", "developing", "analysis", "implementation", "ad hoc assignment", "daily operations", "inventory control", "reports", "logistics", "inventory replenishment"], "requirements": {"degrees": ["degree"], "majors": [], "languages": ["cantonese", "english", "mandarin"], "language_level": ["excellent"], "hard_skills": ["e-commerce"], "soft_skills": ["work effectively", "communication skills", "oral", "leadership", "interpersonal"], "languages_combined": [{"language": "cantonese", "language_level": ["excellent"]}, {"language": "english", "language_level": ["excellent"]}, {"language": "mandarin", "language_level": ["excellent"]}]}, "experience_required": {"duration": [], "field": ["supply chain", "e-commerce"]}}, {"job_id": "100003009050539", "location_code": "hk", "company": "Walters People (HK)", "job_title": "Supply Chain Analyst (F&B)", "description": "Our client is a fast growing F&B brand based in HK, they are now looking for talent to join their fast expanding supply chain team to support their business growth.\n\nJob responsibilities\n* Handling retail store demand & supply planning, monthly order calculation and forecasting\n* Coordinate with different internal parties for sales performance estimation and evaluation\n* Maintain data accuracy, consolidate forecast summary, identify potential risks and propose action plan\n* Monitor retail distribution, imply store replenishment parameters\n* Prepare inventory reports and KPI to monitor stock level and progress\n* Maintain the accuracy and consistency of sales forecasting to ensure best practice\n\nJob requirements\n* Degree holder in Supply Chain with at least 2 years of experience\n* Experience in F&B background is an advantage\n* Self-motivated and adaptive to fast-paced working environment\n* Proficient in MS Office including Excel & Word\n* Good command of both spoken and written English and Chines\n* Candidate with more experience will consider as senior position", "employment_types": ["Full Time", "Permanent"], "selling_points": ["HK based F&B brand", "End-to-end supply chain process", "Competitive remuneration package"], "locations": ["Not Specified"], "categories": ["Transportation & Logistics", "Inventory / Warehousing", "Manufacturing", "Production Planning / Control", "E-commerce", "Supply Chain"], "post_time": "2022-01-14T10:40:03Z", "salary": {"currency": "HKD", "max": 24999, "min": 17000, "period": "monthly", "term": null}, "salary_visible": true, "title_keywords": ["analyst"], "responsibilities": ["sales performance", "inventory", "coordinate with", "monitor", "replenishment", "identify potential risks", "maintain", "reports", "maintain data", "evaluation", "forecast", "plan", "forecasting", "internal parties", "planning"], "requirements": {"degrees": ["degree holder"], "majors": [], "languages": ["english"], "language_level": ["good command"], "hard_skills": ["excel", "word", "ms office"], "soft_skills": ["self-motivated"], "languages_combined": [{"language": "english", "language_level": ["good command"]}]}, "experience_required": {"duration": ["at least 2 years"], "field": ["supply chain", "f&b"]}}, {"job_id": "100003009046361", "location_code": "hk", "company": "Furrytails Limited", "job_title": "E-Commerce Assistant", "description": "Requirements:\n\n-\u00a0\u00a0\u00a0\u00a0\u00a0\u00a0 Higher Diploma or above in any discipline\n\n-\u00a0\u00a0\u00a0\u00a0\u00a0\u00a0 At least 1 year working experience is preferred\n\n-\u00a0\u00a0\u00a0\u00a0\u00a0\u00a0 Good communication and organizational skills with attention to details\n\n-\u00a0\u00a0\u00a0\u00a0\u00a0\u00a0 Customer focused and quality driven\n\n-\u00a0\u00a0\u00a0\u00a0\u00a0\u00a0 Proficient in MS applications\n\n-\u00a0\u00a0\u00a0\u00a0\u00a0\u00a0 Ability to adapt to a fast-paced and intense working environment\n\n-\u00a0\u00a0\u00a0\u00a0\u00a0\u00a0 Good command of both written and spoken English, Cantonese and\u00a0Mandarin\n\n-\u00a0\u00a0\u00a0\u00a0\u00a0\u00a0 Fresh graduate will be considered\n\nResponsibilities:\n\n-\u00a0\u00a0\u00a0\u00a0\u00a0\u00a0 Handle telephone and email enquiries, client instruction and complaints in a professional and timely manner\n\n-\u00a0\u00a0\u00a0\u00a0\u00a0\u00a0 Coordinate with internal departments to satisfy customers\u2019 needs by providing efficient feedback and the best solutions\n\n-\u00a0\u00a0\u00a0\u00a0\u00a0\u00a0 Assist website operation\n\n-\u00a0\u00a0\u00a0\u00a0\u00a0\u00a0 Provide prompt response and solution of customer inquiries\n\n-\u00a0\u00a0\u00a0\u00a0\u00a0\u00a0 Follow-up daily order with customers and liaise with logistics team", "employment_types": ["Full Time", "Part Time"], "selling_points": [], "locations": ["Kwai Tsing Area"], "categories": ["Sales, CS & Business Devpt", "Call Centre", "Customer Service - Supervisor / Officer", "E-commerce", "Supply Chain"], "post_time": "2022-01-13T10:41:20Z", "salary": {"currency": null, "max": null, "min": null, "period": "monthly", "term": null}, "salary_visible": false, "title_keywords": ["assistant"], "responsibilities": ["customer inquiries", "coordinate with", "website operation", "logistics", "liaise with"], "requirements": {"degrees": ["higher diploma or above", "fresh graduate"], "majors": [], "languages": ["cantonese", "english", "mandarin"], "language_level": ["good command"], "hard_skills": ["ms applications"], "soft_skills": ["organizational skills", "focused", "communication", "attention to details", "driven"], "languages_combined": [{"language": "cantonese", "language_level": ["good command"]}, {"language": "english", "language_level": ["good command"]}, {"language": "mandarin", "language_level": ["good command"]}]}, "experience_required": {"duration": ["at least 1 year"], "field": []}}, {"job_id": "100003009040200", "location_code": "hk", "company": "Pacific Coffee Co Ltd", "job_title": "Customer Service Officer", "description": "This is a Fashion Label with presence in Europe, US and Asia is seeking a Demand Planning Manager to head up the forecast, demand assumption.\n\nIt is a fashion label with market share all over the world and you will gain global exposure to the worldwide market, particularly in the e commerce realm.\n\n\u00a0You will:\n\nFormulate effective forecast models using: market trends, demand assumption and demand for all retail + etailers channels\nEvaluate and follow up on demand and supply status such as phase in/out,\npromotional, sales event items.\nKeep management updated on sales forecasts, budgets, and business strategies\nBe an internal expert on complex analysis and provide consultancy to other departments.\nIdentify potential risks and provide suggestion and improvement plan\nBachelor degree in Business, statistics, supply chain, accounting, engineering or others.\n\nYou are:\n\nAt least 6 years of experience in supply / demand / logistics with strong analysis responsibilities.\nFrom FMCG, fashion, retail, beauty, etc.\nSolid skills in Microsoft Office Powerpoint and Excel.\nPower BI and tableau is highly preferable\nFluency in Cantonese and English is a must, Mandarin is a bonus\n\n\u00a0This opportunity offers exposure to the global market in the digital / Ecommerce World.\n\n\u00a0720K \u2013 800K per annual\u00a0", "employment_types": ["Full Time", "Permanent"], "selling_points": [], "locations": ["Sheung Wan"], "categories": ["Hospitality / F & B", "Food & Beverage", "E-commerce", "Product Management / Business Analyst", "Supply Chain"], "post_time": "2022-01-12T01:50:59Z", "salary": {"currency": null, "max": null, "min": null, "period": "monthly", "term": null}, "salary_visible": false, "title_keywords": ["customer service officer"], "responsibilities": ["budgets", "management", "power bi", "demand planning", "analysis", "evaluate", "identify potential risks", "logistics", "forecast", "plan"], "requirements": {"degrees": ["degree", "bachelor"], "majors": ["business", "statistics", "engineering", "accounting"], "languages": ["cantonese", "english", "mandarin"], "language_level": ["fluency"], "hard_skills": ["excel", "bi", "microsoft office", "demand planning", "analysis", "powerpoint", "tableau"], "soft_skills": [], "languages_combined": [{"language": "cantonese", "language_level": ["fluency"]}, {"language": "english", "language_level": ["fluency"]}, {"language": "mandarin", "language_level": []}]}, "experience_required": {"duration": ["at least 6 years"], "field": ["logistics"]}}, {"job_id": "100003009045587", "location_code": "hk", "company": "Silenus (Hong Kong) Limited", "job_title": "E-Commerce Inventory & Logistic Executive", "description": "Our client, a global E-Commerce business branding company, is now looking for an experienced candidate to join them.\n\nResponsibilities:\n\nMake the optimal inventory forecast and planning for each client and their own E-commerce business\nRegularly review and track the existing sales and inventory data\nDevelop a model for inventory data analysis, for better forecasting and planning\nWork closely with existing logistic vendor for product delivery\nHandle and record customer\u2019s inquire for improvement\n\nRequirements:\n\nDegree or Diploma in the relevant discipline\nMore than 2 years in E-Commerce inventory planning and execution, preferably with cross border handlings\nSolid achievement for improving inventory performance\nStrong analytical and communication skills\nFluent in English and Mandarin\n\nFor a confidential discussion about this role please contact Clarence at 2185 6309.", "employment_types": ["Full Time", "Permanent"], "selling_points": ["Strong technical support for data tracking", "CEO with solid experience in E-Commerce sector", "Adaptive and flexible working environment"], "locations": ["Kwun Tong"], "categories": ["E-commerce", "Marketing - Brand / Product Management", "Product Management / Business Analyst", "Supply Chain"], "post_time": "2022-01-13T08:08:23Z", "salary": {"currency": "HKD", "max": 29999, "min": 20000, "period": "monthly", "term": null}, "salary_visible": true, "title_keywords": ["executive"], "responsibilities": ["data", "inventory", "review", "develop", "data analysis", "forecast", "forecasting", "planning"], "requirements": {"degrees": ["diploma", "degree"], "majors": [], "languages": ["english", "mandarin"], "language_level": ["fluent"], "hard_skills": ["e-commerce"], "soft_skills": ["communication skills"], "languages_combined": [{"language": "english", "language_level": ["fluent"]}, {"language": "mandarin", "language_level": ["fluent"]}]}, "experience_required": {"duration": [], "field": []}}, {"job_id": "100003009048145", "location_code": "hk", "company": "Think China", "job_title": "Warehouse Assistant \u5009\u52d9\u54e1", "description": "\u5de5\u4f5c\u5167\u5bb9\u00a0Job descriptions :\n\n\u8ca0\u8cac\u57f7\u8ca8\u3001\u5305\u88dd\u00a0To pick & pack goods for daily orders\n\u5b89\u6392\u5165\u5009\u8ca8\u54c1\u5b58\u653e\u5230\u8ca8\u67b6\u00a0To arrange incoming goods on racks / shelves\n\u5b9a\u671f\u76e4\u9ede\u8ca8\u5009\u5b58\u8ca8\u00a0To attend regular stock-take\n\u6574\u7406\u53ca\u6e05\u6f54\u8ca8\u5009\u885b\u751f\u00a0To clean up warehouse\n\n\u5165\u8077\u689d\u4ef6\u00a0Requirements :\n\n\u4e2d\u4e94\u6216\u4ee5\u4e0a\u7a0b\u5ea6\u00a0F. 5 or above\n\u4e8c\u81f3\u4e09\u5e74\u5de5\u4f5c\u7d93\u9a57\u00a02-3 years working experience\n\u80fd\u95b1\u8b80\u7c21\u55ae\u82f1\u8a9e\u00a0Able to read simple English\n\n\u5f85\u9047\u00a0Offer :\n\n\u85aa\u512a\u00a015-17K Attractive Salary : 15-17K\n5\u5929\u534a\u5de5\u4f5c\u00a05\u00a0 1/2 day work per week\n\u9280\u884c\u5047\u671f\u00a0Banking holidays\n\u91ab\u7642\u4fdd\u96aa\u00a0Medical insurance coverage", "employment_types": ["Full Time"], "selling_points": ["\u4e2d\u4e94\u7562\u696d F.5 or above", "\u51b7\u6c23\u5de5\u4f5c\u7a7a\u9593 Air-conditioned working environment", "\u91ab\u7642\u4fdd\u96aa Medical insurance coverage"], "locations": ["Lai Chi Kok"], "categories": ["Transportation & Logistics", "Fulfillment", "Inventory / Warehousing", "E-commerce", "Supply Chain"], "post_time": "2022-01-14T05:19:16Z", "salary": {"currency": "HKD", "max": 16999, "min": 14000, "period": "monthly", "term": null}, "salary_visible": true, "title_keywords": ["warehouse assistant", "\u5009\u52d9\u54e1"], "responsibilities": ["daily orders"], "requirements": {"degrees": [], "majors": [], "languages": ["english"], "language_level": [], "hard_skills": ["simple"], "soft_skills": [], "languages_combined": [{"language": "english", "language_level": []}]}, "experience_required": {"duration": ["2-3 years"], "field": []}}, {"job_id": "100003009040285", "location_code": "hk", "company": "Starkford Limited", "job_title": "Shipping Clerk", "description": "Responsibilities\n\n\u2022 Track, document and communicate the project progress, obstacles, delays, and risks to all team members\n\u2022 Create and review project plans and manage project schedules based on established priorities and available resources\n\u2022 Ability to bridge the gap between technical and non-technical resources\n\u2022 Co-ordinate with various internal departments to resolve issues on business transaction process\n\u2022 Provide technical support to trading partners on product testing and implementation\n\u2022 Approve/supervise business transactions flow design\n\u2022 Facilitate regular reporting and reviews\n\nRequirements\n\n\u2022 Degree holder in Information Technology, Supply Chain Management or related disciplines\n\u2022 At least 3 years of management experience, with an excellent track record of successful completion of projects\n\u2022 Understand the concept of Supply Chain Management and E-Commerce\n\u2022 Willing to work under pressure and commitment to deadlines\n\u2022 Strong interpersonal, communication, and people management skills\n\u2022 Good command in written and spoken English & Mandarin, and Cantonese\n\nWe offer 5-day work & competitive remuneration.\u00a0 Interested parties please apply in full resume with expected annual salary and date of availability.\n\nAll information will be kept confidential and used for recruitment purposes only, unsuccessful applications will be destroyed.", "employment_types": ["Full Time", "Permanent"], "selling_points": ["Diploma or above", "Monitor shipments, prepare invoice & shipping doc", "5-day work, Double Pay, flexible working hour"], "locations": ["Kwai Hing"], "categories": ["Transportation & Logistics", "Others", "Shipping", "E-commerce", "Supply Chain"], "post_time": "2022-01-12T02:08:16Z", "salary": {"currency": null, "max": null, "min": null, "period": "monthly", "term": null}, "salary_visible": false, "title_keywords": ["shipping clerk"], "responsibilities": ["reporting", "schedules", "co-ordinate with", "technical support", "review", "project progress", "implementation", "testing", "transactions", "design", "plans"], "requirements": {"degrees": ["degree holder"], "majors": ["related disciplines", "information technology"], "languages": ["cantonese", "english", "mandarin"], "language_level": ["good command"], "hard_skills": ["e-commerce"], "soft_skills": ["communication", "interpersonal", "work under pressure"], "languages_combined": [{"language": "cantonese", "language_level": ["good command"]}, {"language": "english", "language_level": ["good command"]}, {"language": "mandarin", "language_level": ["good command"]}]}, "experience_required": {"duration": ["at least 3 years"], "field": ["management"]}}, {"job_id": "100003009046828", "location_code": "hk", "company": "TradeLink Technologies Ltd", "job_title": "Business Information Services Manager", "description": "Job Description\n\nLead the e-commerce team to drive business development\nAchieve sales target and manage spending within budget\nAnalyze customer insights, consumer trends, market analysis, marketing best practices in order to build business strategies\nResponsible for providing strategic sales and promotion plans to key retailers and drive e-commerce business\nEstablish partnership with e-commerce customers and agencies in order to develop and maintain strategic collaboration with major customers of all channels\nProvide continuous improvement plans to uplift key performance index\nExplore new channels / platforms to maximize sales opportunities and enhance brand awareness\nHandle any other ad-hoc company projects as assigned\u00a0\n\n\u00a0Job Requirements\n\nDegree holder in Marketing, E-commerce or Information Technology\n7 years of relevant experience in FMCG industry in which 3 years of hands-on e-commerce planning and sales management\nExperience in managing promotional calendars/ digital campaigns\nShopify operation experience is a must\nOnline Marketplace operation experience is an advantage\nEnergetic, result-oriented, well-organized, self-motivated, able to work independently and under pressure\nGood communication, presentation, interpersonal & analytical skills\nGood command of written and spoken English and Chinese\n\u00a0\n\n\nWe offer competitive remuneration package and good prospects to the right candidates. Interested parties please send your full resume with expected salary to our email.\n\n*Data collected will be kept confidential and used for recruitment purposes only.", "employment_types": ["Full Time"], "selling_points": [], "locations": ["Hung Hom"], "categories": ["Transportation & Logistics", "Supply Chain", "E-commerce", "Supply Chain"], "post_time": "2022-01-14T01:23:10Z", "salary": {"currency": null, "max": null, "min": null, "period": "monthly", "term": null}, "salary_visible": false, "title_keywords": ["manager"], "responsibilities": ["consumer trends", "ad-hoc", "sales target", "budget", "customer insights", "develop", "market analysis", "maintain", "plans"], "requirements": {"degrees": ["degree holder"], "majors": ["marketing", "information technology", "e-commerce"], "languages": ["english", "chinese"], "language_level": ["good command"], "hard_skills": ["shopify", "fmcg industry", "analytical skills", "e-commerce"], "soft_skills": ["self-motivated", "work independently", "under pressure", "interpersonal", "presentation", "well-organized", "analytical skills", "communication", "hands-on", "energetic", "result-oriented"], "languages_combined": [{"language": "english", "language_level": ["good command"]}, {"language": "chinese", "language_level": ["good command"]}]}, "experience_required": {"duration": ["7 years", "3 years"], "field": ["management", "fmcg", "e-commerce", "online marketplace", "operation", "relevant experience", "digital", "planning"]}}, {"job_id": "100003009046122", "location_code": "hk", "company": "City Super Ltd", "job_title": "E-Commerce Manager", "description": "Benefits:\u00a0\n\n5-day Work\nStarting with 12 Days Annual Leave\nBirthday Leave\nMarriage Leave\nSpecial Care Leave\nReferral Staff Bonus\nMedical Benefit\nEducational Sponsorship\n\n\u00a0Responsibilities:\n\n\nResponsible for daily operations for Ecommerce shipments including prepare orders collection, delivery, return, re-delivery & recall orders\nHandle daily orders picking, repacking, labelling, sorting and bagging for outbound and local return arrangement (including preparation of required paperwork)\nHandle daily inbound and outbound processing of all shipments\nHandle daily email enquiries on shipment status and problem solving\nAssist superior to monitor cost effectiveness and efficiency in regard to the movement and storage of shipments\nPerform any adhoc duties/projects as assigned by the superior\n\n\u00a0Requirements:\u00a0\n\nHKCEE / HKDSE or above\nFresh graduates are also welcomed\nProficiency in MS Office, include MS Word and Excel\nGood command of spoken and written English and Chinese\nStrong sense of responsibilities, teamwork, detail-oriented and well-organized\nGood communication skills\nKnowledge of\u00a0 Supply Chain Security, TAPA TSR FSR, AEO and ISO standard is an advantage\n\n\u00a0Working Hours:\u00a0\n\n\n(A) 12:00 - 21:30 (B) 14:00 - 23:30\nWork on shift, weekend and holiday is required\nFor those who work less than 17 hours per week, can be considered as Part Time Assistant \u5982\u7533\u8acb\u70ba\u517c\u8077\u54e1, \u6bcf\u661f\u671f\u5de5\u4f5c\u4e0d\u9700\u591a\u65bc17\u5c0f\u6642\n\nPlease visit our web site\u00a0https://www.royaleinternational.com\u00a0for company information.\n\nInterested applicants please send your detailed resume stating your current and expected salary to us\u00a0by clicking \u2018Apply Now\u2019\n\n\nAll information collected will be used for recruitment purposes only.", "employment_types": ["Full Time", "Permanent"], "selling_points": ["Lead the e-commerce team to drive business", "Hands-on e-commerce planning and sales mgt.", "Shopify operation experience"], "locations": ["Tsim Sha Tsui"], "categories": ["E-commerce", "Business Development", "Marketing - Brand / Product Management", "Supply Chain"], "post_time": "2022-01-13T09:39:57Z", "salary": {"currency": null, "max": null, "min": null, "period": "monthly", "term": null}, "salary_visible": false, "title_keywords": ["manager"], "responsibilities": [], "requirements": {"degrees": [], "majors": [], "languages": [], "language_level": [], "hard_skills": [], "soft_skills": [], "languages_combined": []}, "experience_required": {"duration": [], "field": []}}, {"job_id": "100003009044592", "location_code": "hk", "company": "Royale International Couriers Limited", "job_title": "Ecommerce Assistant (5-day work)", "description": "Highlights\n\nFull-time 40 hours per week\n\nCompetitive salary\n\nHave a major impact on company performance\n\nRemote position\n\nHealth insurance stipend\n\nPaid vacation\n\n90 Day Objectives\n\nBecome proficient with Durabasics supply chain processes.\n\nWork with Operations Senior Manager to facilitate consistent inventory practices (factory > consolidation > ocean freight > 3PL > Amazon).\n\nProvide feedback on processes and how they might be improved or changed.\n\n\n\n\n\nKey Performance Indicators\n\nMaintain inventory levels as set by the Operations Senior Manager for SKUs at our 3PL warehouse and at Amazon.\n\nEnsure Durabasics has 0 SKUs out of stock at Amazon.\n\nResponse times for actively managing the Supply Chain within 24 hours.\n\nAmazon Inventory Performance Index (IPI) - Greater than 475\n\nWhat\u2019s the Role\n\nAs the Logistics Analyst, you will have a daily impact on helping drive Durabasics\u2019 future growth and profitability. You will work closely with the Operations Senior Manager to ensure our product pipeline is always full so we can meet our annual goals. We are on the lookout for an enthusiastic individual who knows how to take direction but is also able to provide diagnostic feedback with respect to keeping the Supply Chain active and on track.\u00a0 We need a self-starter who is capable of working independently within the framework stipulated by the Operations Senior Manager.\n\n\n\n\nYou\u2019re an ideal fit for this role if you are a person who enjoys being organized, loves small business entrepreneurship, and finds success in the details.\u00a0 You also bring knowledge across multiple supply chain disciplines -- for example, import/export, ocean freight, trucking, warehousing, and demand forecasting.\n\n\n\n\n\nWhat You\u2019ll Do\n\nWork with the Operations Senior Manager to:\n\nReview inventory levels of all SKUs to determine replenishment plan.\n\nMonitor sales trends to assist in determining the seasonality of products.\n\nWork with 3PL to monitor inventory levels and transfer stock to Amazon.\n\nMaintain paperwork and details of transfers to Amazon.\n\nReview PO\u2019s and invoices for accuracy and reconciling.\n\nPartner with factories to ensure timely delivery and the highest quality products to our exact specifications.\n\nReview charges from third-party vendors to ensure we are receiving the best rates and opportunities.\n\nOther duties as assigned by the Operations Senior Manager.\n\n\n\n\n\nWhat Will Make Someone Successful\n\nExperience and knowledge of supply chain and inventory management.\n\nCritical thinking and problem-solving abilities using numbers (e.g. modeling out in Excel different options, comparing costs, identifying the qualitative pros/cons of each, identifying our business need and level of importance, and making a recommendation based on data)\n\nAttention to detail to ensure all data is accurate and correct -- this position requires consistent accuracy.\n\nVery strong organizational skills to manage multiple duties at the same time.\n\nStrong understanding of warehousing, inventory, and records maintenance.\n\nUnderstanding of China logistics operations and manufacturing processes.\n\nYou are thorough and detail-oriented. Please email me at polly at\u00a0durabasics . com with your resume and cover letter. Use the word \u2018jellyfish\u2019 along with the position you\u2019re applying for in the email subject line to be considered for the role.\n\nStrong personal drive and ability to work independently the majority of the time in a fast-paced, urgent environment.\n\n\n\n\n\nWhat You\u2019ll Bring\n\n3+ years experience in logistics, warehousing, or transportation operations\n\n2+ years of experience in inventory management systems\n\n1+ years of experience in remote work\n\nFluent in English \u2013 you will be communicating regularly with both native and non-native English speakers\n\nHighly proficient in Microsoft Office and Google Suite products (specifical spreadsheets)\n\n\n\n\n\nNice to Have\u2019s\n\nFluency in Chinese (Mandarin) a plus - you will be communicating with Chinese factories and forwarders often\n\nPrevious Amazon experience\n\nExperience with procurement, incoterm and negotiations", "employment_types": ["Full Time", "Permanent"], "selling_points": ["Fresh graduates are also welcomed", "Responsible for eCommerce local/overseas shipments", "Multi-cultural environment; Flexible working hours"], "locations": ["Kowloon Bay"], "categories": ["Transportation & Logistics", "Freight Forwarding", "Shipping", "E-commerce", "Supply Chain"], "post_time": "2022-01-13T04:43:05Z", "salary": {"currency": null, "max": null, "min": null, "period": "monthly", "term": null}, "salary_visible": false, "title_keywords": ["assistant"], "responsibilities": ["data", "operations", "inventory", "quality", "inventory management", "maintain", "plan", "costs", "invoices", "other duties", "monitor", "logistics", "forecasting", "warehousing", "review", "specifications", "maintenance", "systems", "replenishment", "communicating with", "insurance"], "requirements": {"degrees": [], "majors": [], "languages": ["english", "chinese", "mandarin"], "language_level": ["fluency", "native", "fluent"], "hard_skills": ["small", "excel", "plus", "amazon", "maintenance", "microsoft office", "problem-solving", "nice", "word", "make"], "soft_skills": ["organized", "organizational skills", "independently", "work independently", "capable", "exact", "accurate", "timely", "problem-solving", "detail-oriented", "thorough", "attention to detail", "enthusiastic", "active", "ideal"], "languages_combined": [{"language": "english", "language_level": ["fluent", "native"]}, {"language": "chinese", "language_level": ["fluency"]}, {"language": "mandarin", "language_level": ["fluency"]}]}, "experience_required": {"duration": ["1+ years", "2+ years", "3+ years"], "field": ["inventory management systems", "supply chain", "inventory management", "logistics", "procurement"]}}, {"job_id": "100003009040462", "location_code": "hk", "company": "Hypebeast Hong Kong Limited", "job_title": "Warehouse Assistant", "description": "Responsibilities:\n\nHandle retail customers\u2019 enquiries & complaints via various channels, e.g. phone, email, social media, etc.\nHandle eCommerce order fulfillment, inventory control, logistics and after-sale service\nMaintain CRM and membership database\nLiaise with internal & external parties to facilitate daily operation\nPrepare periodical reports to manager and department head\nTo implement Standard Operation Procedure and ensure the company internal requirements are followed\nAd hoc project as assigned\n\nRequirements:\n\nHolder of Diploma or above\n3 years or above relevant experience in sales/customer services, experience on complaints handling is preferred\nPleasant, patient, high EQ and excellent telephone manner is a must\nAble to work independently and work under pressure;\nFamiliar with Word, Excel, Chinese and English typing\nGood command of spoken and written English is a must;\nImmediate available is preferred\n\nWe offer rewarding career with attractive remuneration package including\u00a05-day work week, medical benefit, generous annual leave, staff discounts and competitive salary\u00a0to the right candidates.\n\nInterested parties please send full resume with your current & expected salary and availability by\u00a0clicking\u00a0\"APPLY NOW\"\u00a0to submit your application.\n\nPacific Coffee Company Limited\u00a0is an equal opportunity employer and welcomes applications from all qualified candidates. Information provided will be treated in strict confidence and only be used for recruitment related purpose.Please visit our website\u00a0www.pacificcoffee.com\u00a0for more details.", "employment_types": ["Full Time"], "selling_points": ["Recent graduate with positive attitude are welcome", "Young, fun and energetic team members", "Global e-commerce with international customers"], "locations": ["Tsuen Wan Area"], "categories": ["Transportation & Logistics", "Inventory / Warehousing", "E-commerce", "Supply Chain"], "post_time": "2022-01-12T02:37:37Z", "salary": {"currency": null, "max": null, "min": null, "period": "monthly", "term": null}, "salary_visible": false, "title_keywords": ["warehouse assistant"], "responsibilities": ["social media", "ad hoc", "external parties", "daily operation", "maintain", "inventory control", "order fulfillment", "logistics", "database", "liaise with", "reports"], "requirements": {"degrees": ["diploma or above"], "majors": [], "languages": ["english", "chinese"], "language_level": ["good command"], "hard_skills": ["excel", "word", "typing"], "soft_skills": ["work independently", "pleasant", "patient", "telephone manner", "work under pressure"], "languages_combined": [{"language": "english", "language_level": ["good command"]}, {"language": "chinese", "language_level": []}]}, "experience_required": {"duration": ["3 years"], "field": ["relevant experience", "customer services"]}}, {"job_id": "100003009036889", "location_code": "hk", "company": "Durabasics LLC", "job_title": "Logistics Analyst", "description": "Overview\n\nAre you a movement maker? Do you love building sincere connection with customers, creatively scheming marketing and sales conversion? Are you seeking new, challenging, tough yet exciting career opportunities?\n\nHere is what you need to know about the job: \u200b We are a small startup international team based in Hong Kong, Taipei, Tokyo, and Shanghai, a new subsidiary department under a Hong Kong Listing Company for our brand meroware https://www.lovemero.jp/en/home/). In Japanese, \u201cmero \u30e1\u30ed\u30e1\u30ed\u201d describes that crazy moment of falling totally in love at first sight. Born in 2018 in Japan, toddlerware brand mero is named after the same love for beautiful design.\n\nOur business growth, just like any other startup, like a roller coaster ride, and most of the time, you will be scratching your head and pulling your hairs trying to break through the unknown and unexpected challenges every day. If you like problem solving, socializing, getting your hands dirty, and looking for thrills of building of your own path, strong sense of ownership and achievement of your own contribution.\u00a0 Come meet our team and learn more about us.\u00a0\n\nResponsibilities\n\nAssist in planning and carrying out sales and marketing campaigns to support business goals and achieve KPIs\nAssist in monitor and manage budgets to achieve sales and marketing objectives\nManage dayday order operations and actively communicate with customers to ensure positive customer purchasing journey.\nConduct regular market research and initiate research analysis, recommendations, propose action plans including but not limited to products, packaging, brands, competitor strategies etc for marketing and design team\nAnalyze and evaluate the effectiveness of each campaign and activities\nAssist in managing social media, influencers, and e-commerce platforms\nPrepare and update the content of sales and marketing materials\nAssist in replenishing consignment inventories at assigned retailers location\nAssist in quality and stock management before leaving to customers\nWork closely with internal and external parties to ensure all marketing campaigns can be effectively executed\nHandle ad hoc projects as assigned\nQualifications\n\u00a0Diploma or post graduate certificate in Business or related field; High School certificate holders with substantial years of related experience will be considered\nMin 2- 3 years of relevant experience in marketing and sales coordination, customer service, or marketing support function. Preferably within the fashion, or household product industry\nPrior experience in retail customer service is highly preferred\nGood interpersonal and communication skills with fluency in English, Mandarin, and Cantonese; Good command of both written and spoken English and Chinese is a must\nProficiency in Microsoft office skills\nExtrovert and sociable who love meeting new people and enjoy sharing the joy of playing with products, collaborative, resourceful and the willingness to grow and learn within the organization\nOccasional travel is required\nWe offer an exciting fast-paced environment and a stable reward system with a focus on professional development and branding effectiveness. If you seek a global, end-to-end business experience within a disruptor culture this job is for you, we urge you to click \"APPLY NOW\" to submit your application with detailed resume, availability date, current and expected salary to us.\n\nYour application may also be considered for other suitable positions within the group or its associated companies.\n\nAll personal data provided by\u00a0applicants will be used\u00a0for recruitment purpose only.", "employment_types": ["Full Time", "Contract"], "selling_points": [], "locations": ["Not Specified"], "categories": ["Transportation & Logistics", "Fulfillment", "Inventory / Warehousing", "E-commerce", "Supply Chain"], "post_time": "2022-01-11T16:01:37Z", "salary": {"currency": null, "max": null, "min": null, "period": "monthly", "term": null}, "salary_visible": false, "title_keywords": ["logistics analyst"], "responsibilities": ["business goals", "operations", "internal and external parties", "quality", "e-commerce platforms", "design", "communication", "customer service", "plans", "listing", "monitor", "marketing campaigns", "kpis", "research analysis", "social media", "stock management", "communicate with", "budgets", "market research", "evaluate", "ad hoc projects", "coordination", "marketing materials", "planning"], "requirements": {"degrees": ["certificate", "diploma", "high school"], "majors": ["business"], "languages": ["cantonese", "english", "mandarin", "japanese", "chinese"], "language_level": ["fluency", "good command", "good"], "hard_skills": ["small", "microsoft office", "e-commerce", "analysis", "problem solving", "joy"], "soft_skills": ["communication skills", "resourceful", "sincere", "sociable", "collaborative", "problem solving", "customer service", "coordination", "interpersonal", "positive"], "languages_combined": [{"language": "cantonese", "language_level": ["fluency", "good"]}, {"language": "english", "language_level": ["fluency", "good command", "good", "good"]}, {"language": "mandarin", "language_level": ["fluency", "good"]}, {"language": "japanese", "language_level": []}, {"language": "chinese", "language_level": ["good command", "good"]}]}, "experience_required": {"duration": ["min 2- 3 years"], "field": ["related", "customer service", "marketing", "relevant experience", "sales coordination", "retail"]}}, {"job_id": "100003009042971", "location_code": "hk", "company": "SIM Design Ltd", "job_title": "Assistant Marketing & Sales Executive (Retail & Wholesale)", "description": "You will be part of a small team in a growing company, with the opportunity to learn and grow with the business.\n\nInitial responsibilities include:\n\nHandle daily operations of e-commerce platform, including customer support, order fulfilment and product delivery arrangement\nPrepare daily sales report\nOffer help in inventory management and current stock levels to internal teams to facilitate accuracy and product availability\nExecute regular inventory counts and supply audits to monitor shrinkage and generate insights into purchasing decisions.\nProvide administration and operation support to the team\nCompliance with ISO22000\nHandle ad hoc assignments as assigned\n\nRequirements:\n\nFamiliar with Microsoft Office (especially Excel and Outlook)\n\nKnowledge of Shopify, Zendesk, Unleashed is preferred, training would also be provided\n\n2-3 years previous experience; preferably in the food industry, customer service or purchasing\n\nGood command of spoken and written English, Cantonese\n\nGood interpersonal and communication skills\n\nHighly organised with excellent time management skills\n\nImmediate start preferred\n\n\n", "employment_types": ["Full Time", "Permanent"], "selling_points": ["Up and coming concept brand for stylish moms", "Startup project team in an established corporation", "Disruptor culture"], "locations": ["Sheung Wan"], "categories": ["E-commerce", "Business Development", "Marketing - Brand / Product Management", "Supply Chain"], "post_time": "2022-01-12T09:21:38Z", "salary": {"currency": null, "max": null, "min": null, "period": "monthly", "term": null}, "salary_visible": false, "title_keywords": ["marketing & sales executive", "assistant"], "responsibilities": ["sales report", "inventory", "compliance", "teams", "monitor", "inventory management", "daily operations", "ad hoc assignments", "audits", "e-commerce platform", "administration"], "requirements": {"degrees": [], "majors": [], "languages": ["cantonese", "english"], "language_level": ["good command"], "hard_skills": ["excel", "outlook", "shopify", "microsoft office"], "soft_skills": ["communication skills", "time management skills", "customer service", "organised", "interpersonal"], "languages_combined": [{"language": "cantonese", "language_level": ["good command"]}, {"language": "english", "language_level": ["good command"]}]}, "experience_required": {"duration": ["2-3 years"], "field": []}}, {"job_id": "100003009038210", "location_code": "hk", "company": "Eat the Kiwi", "job_title": "E-commerce Administrator - Food Industry (Kwai Chung)", "description": "Job Responsibilities:\u00a0\u00a0\n\nMonitor import/export shipments with courier/logistics service provider\nPrepare invoice, shipping documents\u00a0and clerical duties\nWork closely with Procurement team and Operation team\nGenerate monthly reports\nPerform ad-hoc duties as assigned\u00a0\n\n\u00a0Job Requirements:\n\nDiploma or above, preferably in Logistics or Supply Chain related fields\n1-3 years\u00a0relevant working experience, fresh graduate will also be considered\nGood Cantonese, Mandarin and English written and verbal communication skills\nFamiliar with MS Office application, including Word, Excel & Chinese Word Processing\nMust be flexible, independent, challenging and able to work under pressure\nImmediately available preferred\n\nWe offer friendly team environment, good career prospect, also attractive remuneration package including discretionary bonus incentive, together with other benefits like five-day work week, flexible working hours, double pay, medical and dental insurance. Interested parties please send full resume with available date, present and expected salary by clicking \u201cApply Now\u201d for an interview.\n\n\n\nAll personal data collected will be used for recruitment purpose only.\n\n%MCEPASTEBIN%", "employment_types": ["Full Time", "Permanent"], "selling_points": [], "locations": ["Tsuen Wan Area"], "categories": ["Hospitality / F & B", "Food & Beverage", "Sales, CS & Business Devpt", "Retail Sales", "E-commerce", "Supply Chain"], "post_time": "2022-01-11T06:07:15Z", "salary": {"currency": null, "max": null, "min": null, "period": "monthly", "term": null}, "salary_visible": false, "title_keywords": ["administrator"], "responsibilities": ["shipping documents", "monthly reports", "invoice", "monitor", "logistics", "ad-hoc duties"], "requirements": {"degrees": ["fresh graduate", "diploma or above"], "majors": [], "languages": ["cantonese", "english", "chinese", "mandarin"], "language_level": ["good"], "hard_skills": ["excel", "chinese word processing", "word", "ms office"], "soft_skills": ["flexible", "communication skills", "independent", "friendly", "work under pressure"], "languages_combined": [{"language": "cantonese", "language_level": ["good"]}, {"language": "english", "language_level": ["good"]}, {"language": "chinese", "language_level": []}, {"language": "mandarin", "language_level": ["good"]}]}, "experience_required": {"duration": ["1-3 years"], "field": ["relevant working experience"]}}, {"job_id": "100003009039991", "location_code": "hk", "company": "Localised Hong Kong Limited", "job_title": "Customer Care Specialist (Native in Japanese)", "description": "about the company.\nOur client is a leading fashion retail company with a strong presence in the world. Their headcounts have been expanded by 25% last year. Currently they are hiring a Merchandise Planner to join their team. This is a new headcount.\n\nabout the job.\nAs a Merchandise Planner, you will\n-Partner with franchise partners on determining seasonal OTB & alignment with financial targets\n-Forecast order quantity for the assigned category\n-Undertake tactical actions to hit KPIs which include sales target, sell through and achieve optimal inventory level closing stocks\n-Support execution of pre-season activities which include launch planning, allocation plan, pricing for new season & range planning\n-Build and maintain productive relationships within the team, cross-functional teams and franchise partners\n-Understand country/partner level nuances and competitive landscape to optimise business performance\n\nskills & experiences required.\n-Degree in Finance/Accountancy/Business/Retail Management / Supply Chain\n-Candidates without prior experience would be considered\n-Excellent computing skills, proficient in MS Excel\n-Excellent interpersonal, planning and organisation skills to multi-task in a fast-paced environment\n-Positive work attitude and able to work under pressure\n-Good interpersonal and leadership skills\n-Enjoy interacting with people of diverse cultures\n-Keen sense of fashion and a passion or the fashion industry\n\nabout the package\n-5 day work\n-Double Pay\n-Discretionary Bonus\n-Medical Insurance\n-Dental Insurance\n-Regional Exposure\n-New Headcount\n-Summer time\n\nIf you're interested in this role, click 'apply now' to forward an up-to-date copy of your CV, or email to sally.lo@randstad.com.hk", "employment_types": ["Full Time"], "selling_points": ["Work for a fast-growing startup in Customer Care", "Competitive salary and full benefits", "Work in our new Causeway Bay office or remote"], "locations": ["Central & Western Area"], "categories": ["Sales, CS & Business Devpt", "Customer Service - Supervisor / Officer", "E-commerce", "Supply Chain"], "post_time": "2022-01-12T02:51:32Z", "salary": {"currency": null, "max": null, "min": null, "period": "monthly", "term": null}, "salary_visible": false, "title_keywords": ["specialist"], "responsibilities": ["management", "work under pressure", "sales target", "inventory", "otb", "maintain", "plan", "kpis", "insurance", "cross-functional teams", "planning"], "requirements": {"degrees": [], "majors": [], "languages": [], "language_level": [], "hard_skills": ["planner", "ms excel"], "soft_skills": ["productive", "multi-task", "fast-paced environment", "leadership skills", "interested in", "diverse", "organisation", "interpersonal", "work under pressure"], "languages_combined": []}, "experience_required": {"duration": [], "field": []}}, {"job_id": "100003009043896", "location_code": "hk", "company": "Pattern Holdings Company Limited", "job_title": "Head of Logistics (eCommerce)", "description": "Oversee all E-Commerce customer service touchpoints include but not limit to email, WhatsApp etc. to ensure service standard\nMonitor and ensure proper E-Commerce operations includes but not limit to order processing, return and exchange\nResearch and analyze the market trend to identify new channel / partnership / co-branding opportunities and bring new insights to the management\nProactively identify operational, procedural and technical issues, initiative and execute optimizations to enhance customer experience\nIdentify cross-sell opportunities and customer relationship building to improve overall sales\nPlan and implement efficient promotion strategies on social platforms\nProvide support to sales team occasionally\nAssist in team building and\u00a0training of other colleagues\n\nRequirements\n\nDegree holder with min. 6 years relevant E-Commerce experience in sizeable organization\nExperience of working with E-Commerce platforms (e.g., E-shop, HKTVmall, Jou Sun) and knowledge in E-Commerce tools\nExceptional understanding of consumer online behavior, trends and market analysis\nStrong sense of customer orientation with good problem-solving abilities, attention to details, pleasant and out-going personality\nExcellent command of both written and spoken English and Chinese\nProficiency in Microsoft Excel, Word, PowerPoint and Chinese Word Processing\nImmediate availability would be a definite bonus\nInterested parties please send your CV,\u00a0expected salary & availability by clicking \"APPLY NOW\" button or contact Human Resources Department at\u00a03656 1388\u00a0for enquiries. Personal data collected will be used for recruitment related purpose only.", "employment_types": ["Full Time"], "selling_points": [], "locations": ["Causeway Bay"], "categories": ["Transportation & Logistics", "Inventory / Warehousing", "Supply Chain", "E-commerce", "Supply Chain"], "post_time": "2022-01-13T02:22:01Z", "salary": {"currency": null, "max": null, "min": null, "period": "monthly", "term": null}, "salary_visible": false, "title_keywords": ["logistics"], "responsibilities": ["management", "provide support", "e-shop", "service standard", "operations", "monitor", "e-commerce platforms", "customer service", "sales team", "market analysis", "order processing", "plan"], "requirements": {"degrees": ["degree holder"], "majors": [], "languages": ["english", "chinese"], "language_level": ["excellent", "proficiency"], "hard_skills": ["chinese word processing", "e-commerce", "analysis", "problem-solving", "word", "powerpoint", "microsoft excel", "whatsapp", "order processing", "exchange"], "soft_skills": ["efficient", "problem-solving", "pleasant", "customer service", "attention to details", "initiative"], "languages_combined": [{"language": "english", "language_level": ["excellent"]}, {"language": "chinese", "language_level": ["excellent", "proficiency"]}]}, "experience_required": {"duration": ["6 years"], "field": ["e-commerce"]}}, {"job_id": "100003009045774", "location_code": "hk", "company": "Randstad Hong Kong Limited", "job_title": "Merchandise Planner", "description": "To prospect, analyze, and recommend business solutions to major accounts from e-platforms, consolidators and direct e-sellers.\nTo make sales plan and meet the sales targets given by the company, ensuring continuous growth and maximizing returns.\nTo obtain information of market trends and customer needs, therefore providing insights to the management, with recommendations.\nTo establish business pipeline in parallel with sales plan, ensuring sales force efficiency and healthy new business development in line with sales and strategic plans.\nTo maintain regular contact and follow up with existing accounts, for maximum retention and sustainable business relationship.\nTo analyze trading portfolio and identify threat and opportunity.\u00a0\nProvide weekly sales updates and report.\u00a0\nHandle ad hoc projects as assigned.\nRequirements\nDegree holder in any disciplines.\nMin. 5 years of B2B sales / account servicing experience preferably in logistics industry\nKnowledgeable in e-platform / supply chain management is desirable.\nProficient in both English and Chinese.\nExcellent negotiation and interpersonal skills.\nAggressive, flexible and can-do attitude preferred.\u00a0\nFrequently travel to China or Asia Pacific region is envisaged.\u00a0\nImmediately availability is preferred\n\nG3 Worldwide Hong Kong Limited\u00a0is an equal opportunity employer and welcomes applications from all qualified candidates. Information provided will be treated in strict confidence and only be used for recruitment related purposes. Applicants who are not contacted within 6 weeks may consider their application unsuccessful. Unsuccessful applications may be kept for another 3 months for being considered for other suitable positions available in our Company. The unsuccessful applications will be destroyed after the said period of retention.\n", "employment_types": ["Full Time", "Permanent"], "selling_points": ["Market leader in the industry", "Regional office in Hong Kong", "Young and dynamic working culture"], "locations": ["Not Specified"], "categories": ["Transportation & Logistics", "Supply Chain", "Sales, CS & Business Devpt", "Wholesale", "E-commerce", "Supply Chain"], "post_time": "2022-01-13T08:38:54Z", "salary": {"currency": "HKD", "max": 29999, "min": 20000, "period": "monthly", "term": null}, "salary_visible": true, "title_keywords": [], "responsibilities": ["management", "strategic plans", "maintain", "ad hoc projects", "contact", "plan", "logistics", "recruitment", "report"], "requirements": {"degrees": ["degree holder"], "majors": ["any disciplines"], "languages": ["english", "chinese"], "language_level": ["proficient"], "hard_skills": ["make"], "soft_skills": ["flexible", "confidence", "negotiation", "can-do attitude", "interpersonal skills"], "languages_combined": [{"language": "english", "language_level": ["proficient"]}, {"language": "chinese", "language_level": ["proficient"]}]}, "experience_required": {"duration": ["5 years"], "field": ["logistics industry", "account servicing"]}}, {"job_id": "100003009044581", "location_code": "hk", "company": "Honour Lane Shipping Ltd", "job_title": "Customer Services Coordinator (online/e-Commerce)", "description": "Key Responsibilities:\n\n\n\nHandle customer enquiries and support company\u2019s online platforms\nBooking order and logistics arrangements for all online platforms\u00a0\nProvide administrative support to Customer Service team\nExplore new business channel\nWebsite Searching\nJob Requirements:\n\n\nForm 5 / DSE or above\nGood communication skills\nPassionate and enjoy online / website searching\nCreative thinking, self-motivated and willing to learn\nShort notice or immediate available is preferable\nFresh graduate or less working experience will also be considered\n\nInterested parties please submit your resume, present and expected salary at \"Apply Now\" at JobsDB or email to\u00a0hlshrhk @ hlsholding.com\n\nHuman Resources and Administration Department\n\nHonour Lane Shipping Limited\nRoom 1501, 15th Floor, Tower 2, Nina Tower, 8 Yeung Uk Road, Tsuen Wan, NT, Hong Kong.\nAttn : HR Department\nWeb-site :\u00a0http://www.hlsholding.com\u00a0-->Join us\n\n(Personal data collected will be used for recruitment purpose only)", "employment_types": ["Full Time", "Permanent"], "selling_points": ["Passionate and enjoy online / website searching", "Explore new business channel", "5 day work & Year End Pay & Discretionary Bonus"], "locations": ["Tsuen Wan Area"], "categories": ["Transportation & Logistics", "Freight Forwarding", "E-commerce", "Supply Chain"], "post_time": "2022-01-13T04:38:40Z", "salary": {"currency": null, "max": null, "min": null, "period": "monthly", "term": null}, "salary_visible": false, "title_keywords": ["coordinator"], "responsibilities": ["handle customer enquiries", "logistics arrangements", "website", "customer service", "booking", "provide administrative support"], "requirements": {"degrees": ["fresh graduate", "form 5", "dse"], "majors": [], "languages": [], "language_level": [], "hard_skills": [], "soft_skills": ["passionate", "communication skills", "self-motivated", "willing to learn", "creative"], "languages_combined": []}, "experience_required": {"duration": [], "field": []}}, {"job_id": "100003009050686", "location_code": "hk", "company": "Hutchison Telecommunications (Hong Kong) Limited", "job_title": "E-Commerce Specialist", "description": "Responsibilities:\n\nOversee the sales and operation performance of e-Commerce business\nDevelop new suppliers and business partners\nExplore and develop new online sales channels integrating with external and internal systems\u00a0\nContinuously improve the entire supply chain to higher efficiency, accuracy and minimize operating cost\n\nRequirements:\n\nHigher Diploma or above in Marketing, e-Commence, Business Administration or related discipline\n3\u00a0years of experience in e-Commence or e-Shop related projects\nAbility to work under pressure and manage multiple marketing programs with tight deadlines\nStrong presentation and negotiation skills\nIndependent, proactive team player\u00a0and innovative thinking\nProficient in MS Excel and PowerPoint\nGood command of written and spoken English and Chinese\u00a0\n\nApart from competitive remuneration package and exciting opportunity for career development within the Group, we provide attractive employee benefits such as free company shuttle, free company SIM card and preferential SIM plan offers, comprehensive medical & insurance schemes, as well as full range of other employee well-being provisions.\u00a0\n\nInterested parties, please apply with full resume, present and expected salary, by clicking \u201cAPPLY NOW\u201d. Please quote the reference number on the e-mail subject.\n\nWe are an equal opportunity employer and welcome applications from all qualified candidates. Personal data collected will be treated in the strictest confidence and handled confidentially by authorised personnel for recruitment-related purposes only within the CK Hutchison Group of companies. The personal data of unsuccessful applicants will be destroyed after the recruitment exercise pursuant to the requirements of the Personal Data (Privacy) Ordinance in Hong Kong.", "employment_types": ["Full Time", "Permanent"], "selling_points": [], "locations": ["Tsing Yi"], "categories": ["E-commerce", "Business Development", "Product Management / Business Analyst", "Supply Chain"], "post_time": "2022-01-14T11:10:26Z", "salary": {"currency": null, "max": null, "min": null, "period": "monthly", "term": null}, "salary_visible": false, "title_keywords": ["specialist"], "responsibilities": ["cost", "internal systems", "develop"], "requirements": {"degrees": ["higher diploma or above"], "majors": ["marketing", "business administration"], "languages": ["english", "chinese"], "language_level": ["good command"], "hard_skills": ["ms excel", "powerpoint"], "soft_skills": ["independent", "innovative", "negotiation skills", "comprehensive", "team player", "proactive", "presentation", "work under pressure"], "languages_combined": [{"language": "english", "language_level": ["good command"]}, {"language": "chinese", "language_level": ["good command"]}]}, "experience_required": {"duration": ["3 years"], "field": ["related"]}}, {"job_id": "100003009041051", "location_code": "hk", "company": "Retail Technology (Hong Kong) Limited", "job_title": "Senior Buyer", "description": "The Job\n\nWe are looking for a\u00a0Senior Category Executive who will be a core member within the RTA team, will work closely with the Teams to drive the sales and competitiveness of item offerings on the site, and ensure that the key KPI\u2019s for sales and performance are met and exceeded. This person will report to the Merchandising Manager.\u00a0\n\nDrives and owns the sales & performance of certain categories on the platform, ensuring that the daily sales, repeat purchase, item competitiveness of the site are as excellent\nMonitor the real-time performance and make timely decisions to switch items/ price features to drive the best performance possible\nAble to pick and drive star hero products based on customer profile, seasonality, and other factors.\nDrive data-driven decisions, especially with leveraging analysis from past campaigns, data, and other factors to make the best decisions\nWorks closely with Ops team to do item forecasting & proper e-commerce packaging\nWorks hand in hand with the Site Operations team till ensure the site(s) operate excellently and look good\nKey KPI\u2019s owned: sales, the performance of promotions, customer ratings by product.\n\nThe Person\u00a0\n\nStrong analytical and problem-solving skills, performance-driven, and well-organized\nHands-on and details oriented. Knows how to read sales dashboards to make timely decisions to drive performance.\nExtremely results oriented and drive the team to get the best possible topline results at all times.\nVery strong familiarity with\u00a0HK local retail market and competitor pulse\nAnalytical and able to leverage data to make decisions, pre/ during/ post-campaign\nE-commerce experience is not a must, should have a passion and strong interest in the e-commerce field.\u00a0\nComfortable working in fast-paced, agile, collaborative, and competitive team environment.\nHas a good grasp of HK grocery market, the strong familiarity of local competitor offers (on and off)\nComfortable working across cultures (local HK, mainland Chinese, MNC\u2019s in HK).\nTeam player and able to manage different stakeholders well\nUniversity degree with at least 5 years of relevant experience in grocery retail in HK.", "employment_types": ["Full Time"], "selling_points": ["Minimum 3 years of buying experience", "Experience in FMCG or grocery", "Guarantee 13 months salary with performance bonus"], "locations": ["Tai Koo"], "categories": ["Merchandising & Purchasing", "Procurement / Purchasing / Sourcing", "E-commerce", "Marketing - Brand / Product Management", "Supply Chain"], "post_time": "2022-01-12T03:22:59Z", "salary": {"currency": "HKD", "max": 34999, "min": 25000, "period": "monthly", "term": null}, "salary_visible": true, "title_keywords": [], "responsibilities": ["data", "operations", "analysis", "merchandising", "teams", "monitor", "purchase", "forecasting", "report"], "requirements": {"degrees": ["university degree"], "majors": [], "languages": ["chinese"], "language_level": [], "hard_skills": ["problem-solving skills", "make", "agile", "e-commerce"], "soft_skills": ["agile", "timely", "well-organized", "collaborative", "hands-on", "problem-solving skills", "team player", "driven"], "languages_combined": [{"language": "chinese", "language_level": []}]}, "experience_required": {"duration": ["at least 5 years"], "field": ["retail", "relevant experience", "e-commerce"]}}, {"job_id": "100003009042191", "location_code": "hk", "company": "Leader Marine Products Trading Limited", "job_title": "E-Commerce Manager", "description": "Oversee all E-Commerce customer service touchpoints include but not limit to email, WhatsApp etc. to ensure service standard\nMonitor and ensure proper E-Commerce operations includes but not limit to order processing, return and exchange\nResearch and analyze the market trend to identify new channel / partnership / co-branding opportunities and bring new insights to the management\nProactively identify operational, procedural and technical issues, initiative and execute optimizations to enhance customer experience\nIdentify cross-sell opportunities and customer relationship building to improve overall sales\nPlan and implement efficient promotion strategies on social platforms\nProvide support to sales team occasionally\nAssist in team building and\u00a0training of other colleagues\n\nRequirements\n\nDegree holder with min. 6 years relevant E-Commerce experience in sizeable organization\nExperience of working with E-Commerce platforms (e.g., E-shop, HKTVmall, Jou Sun) and knowledge in E-Commerce tools\nExceptional understanding of consumer online behavior, trends and market analysis\nStrong sense of customer orientation with good problem-solving abilities, attention to details, pleasant and out-going personality\nExcellent command of both written and spoken English and Chinese\nProficiency in Microsoft Excel, Word, PowerPoint and Chinese Word Processing\nImmediate availability would be a definite bonus\nInterested parties please send your CV,\u00a0expected salary & availability by clicking \"APPLY NOW\" button or contact Human Resources Department at\u00a03656 1388\u00a0for enquiries. Personal data collected will be used for recruitment related purpose only.", "employment_types": ["Full Time"], "selling_points": [], "locations": ["Aberdeen"], "categories": ["E-commerce", "Business Development", "Product Management / Business Analyst", "Supply Chain"], "post_time": "2022-01-12T06:33:08Z", "salary": {"currency": null, "max": null, "min": null, "period": "monthly", "term": null}, "salary_visible": false, "title_keywords": ["manager"], "responsibilities": ["management", "provide support", "e-shop", "service standard", "operations", "monitor", "e-commerce platforms", "customer service", "sales team", "market analysis", "order processing", "plan"], "requirements": {"degrees": ["degree holder"], "majors": [], "languages": ["english", "chinese"], "language_level": ["excellent", "proficiency"], "hard_skills": ["chinese word processing", "e-commerce", "analysis", "problem-solving", "word", "powerpoint", "microsoft excel", "whatsapp", "order processing", "exchange"], "soft_skills": ["efficient", "problem-solving", "pleasant", "customer service", "attention to details", "initiative"], "languages_combined": [{"language": "english", "language_level": ["excellent"]}, {"language": "chinese", "language_level": ["excellent", "proficiency"]}]}, "experience_required": {"duration": ["6 years"], "field": ["e-commerce"]}}, {"job_id": "100003009038907", "location_code": "hk", "company": "G3 Worldwide Hong Kong Limited", "job_title": "Business Development Manager / Assistant Business Development Manager", "description": "To prospect, analyze, and recommend business solutions to major accounts from e-platforms, consolidators and direct e-sellers.\nTo make sales plan and meet the sales targets given by the company, ensuring continuous growth and maximizing returns.\nTo obtain information of market trends and customer needs, therefore providing insights to the management, with recommendations.\nTo establish business pipeline in parallel with sales plan, ensuring sales force efficiency and healthy new business development in line with sales and strategic plans.\nTo maintain regular contact and follow up with existing accounts, for maximum retention and sustainable business relationship.\nTo analyze trading portfolio and identify threat and opportunity.\u00a0\nProvide weekly sales updates and report.\u00a0\nHandle ad hoc projects as assigned.\nRequirements\nDegree holder in any disciplines.\nMin. 5 years of B2B sales / account servicing experience preferably in logistics industry\nKnowledgeable in e-platform / supply chain management is desirable.\nProficient in both English and Chinese.\nExcellent negotiation and interpersonal skills.\nAggressive, flexible and can-do attitude preferred.\u00a0\nFrequently travel to China or Asia Pacific region is envisaged.\u00a0\nImmediately availability is preferred\n\nG3 Worldwide Hong Kong Limited\u00a0is an equal opportunity employer and welcomes applications from all qualified candidates. Information provided will be treated in strict confidence and only be used for recruitment related purposes. Applicants who are not contacted within 6 weeks may consider their application unsuccessful. Unsuccessful applications may be kept for another 3 months for being considered for other suitable positions available in our Company. The unsuccessful applications will be destroyed after the said period of retention.\n", "employment_types": ["Full Time"], "selling_points": [], "locations": ["Ngau Tau Kok"], "categories": ["Transportation & Logistics", "Shipping", "E-commerce", "Business Development", "Supply Chain"], "post_time": "2022-01-11T08:07:09Z", "salary": {"currency": null, "max": null, "min": null, "period": "monthly", "term": null}, "salary_visible": false, "title_keywords": ["business development manager", "assistant business development manager"], "responsibilities": ["management", "strategic plans", "maintain", "ad hoc projects", "contact", "plan", "logistics", "recruitment", "report"], "requirements": {"degrees": ["degree holder"], "majors": ["any disciplines"], "languages": ["english", "chinese"], "language_level": ["proficient"], "hard_skills": ["make"], "soft_skills": ["flexible", "confidence", "negotiation", "can-do attitude", "interpersonal skills"], "languages_combined": [{"language": "english", "language_level": ["proficient"]}, {"language": "chinese", "language_level": ["proficient"]}]}, "experience_required": {"duration": ["5 years"], "field": ["logistics industry", "account servicing"]}}, {"job_id": "100003009036963", "location_code": "hk", "company": "Yusen Logistics Global Management Limited", "job_title": "Process Analyst- Global Freight Forwarding Process Management Team", "description": "Your responsibilities will include:\n\nPurchase projections and place purchase orders with suppliers\nSourcing of new suppliers\nWork with product development team in new designs\nLiaise with suppliers for pricing and tracking orders, following up on back orders and pending orders\nCommunicate efficiently and effectively with internal and external stakeholders\nLogistics partner liaison\nProvide ad-hoc administrative support as required\n\nWe are looking for:\n\nComputer literacy with knowledge of Microsoft Office and Excel\nHave the ability top prioritise and manage various tasks\nAbility to communicate articulately and effectively with suppliers, customers and internal stakeholders\nTeam player with excellent communication skills who is also able to work autonomously", "employment_types": ["Full Time", "Permanent"], "selling_points": ["5 days work 14-20 AL, freight forward process mgt", "Operational KPI, processes change & improvement", "PMP/6 sigma w/ logistics/related biz diploma or up"], "locations": ["Kwai Hing"], "categories": ["Transportation & Logistics", "Supply Chain", "E-commerce", "Supply Chain", "Information Technology (IT)", "Data Scientist"], "post_time": "2022-01-11T01:02:43Z", "salary": {"currency": null, "max": null, "min": null, "period": "monthly", "term": null}, "salary_visible": false, "title_keywords": ["analyst"], "responsibilities": ["ad-hoc", "administrative support", "communication", "purchase", "logistics", "liaise with suppliers", "tracking"], "requirements": {"degrees": [], "majors": [], "languages": [], "language_level": [], "hard_skills": ["excel", "microsoft office"], "soft_skills": ["communication skills", "computer literacy", "team player", "prioritise"], "languages_combined": []}, "experience_required": {"duration": [], "field": []}}, {"job_id": "100003009044388", "location_code": "hk", "company": "Michael Page", "job_title": "Product Manager - Sustainability", "description": "About Pattern\n\nYour Premier Trade Partner for Worldwide eCommerce Acceleration.\u00a0Pattern provides a proven blend of marketplace analytics, global distribution, MAP compliance, and brand management to drive eCommerce acceleration for premium brands.\n\nWith more than 1000 employees across 18 global locations, Pattern uses its proprietary technology and data-driven insights to help brands deliver profitable eCommerce growth on their own websites and marketplaces. We work with reputable brands like Google, LVMH, Nestle, Pandora and Skullcandy which make us one of the largest sellers on Amazon and a Tmall 5* Trade Partner.\n\nRead on to find out if you have what it takes to join us and ensure you ride the next wave of eCommerce growth!\n\nThe role\n\nThe Logistics & Operations Manager, oversees and leads our APAC fulfilment strategies. The ideal candidate will be a problem solver - who takes ownership and pride in their work and possess the core tasks of supply chain management and operational efficiency optimisation.\n\nTo be successful in this role, you will have excellent stakeholder management skill, good attention to detail and a data-driven mindset.\n\nWhat you will be working on\n\nLead and manage the regional logistics team; define and monitor the team\u2019s performance metrics\nOwn the day-to-day operations of handling reverse supply chain for a billion-dollar company, including working with the warehouses, sellers, and brands to manage the distribution flow for various eCommerce channels\nReview and improve on supply chain / operational practice with costs reduction measures, lead time turnaround improvements, accuracy in deliveries & fulfilment, and service level enhancements\nDevelop innovation initiatives to enhance Borderless\u2019 product offering and streamline the operation flow\nAct as the in-house expert for all eCommerce reporting\n\nYour skillset and background\n\n8+ years of experience in logistics, supply chain or operation management\nStrong functional knowledge in eCommerce channels\nProven experience and know-how in cost efficiency / reduction and productivity improvement initiatives\nSolid working knowledge of Microsoft Excel including pivot tables and macros or data analysis programs like Tableau\nExcellent communication skills in English and Mandarin\nDemonstrate a strong sense of responsibility and commitment\nStrong analytical skills, detail oriented, self-motivated, and proactive\n\nIf this is a position you would like to learn more about, then please don't delay your application and apply today!", "employment_types": ["Full Time", "Permanent"], "selling_points": ["Apparel Industry", "B2B Data Products", "Global Trade"], "locations": ["Not Specified"], "categories": ["Manufacturing", "Product Development / Management", "Others", "Trading", "E-commerce", "Supply Chain"], "post_time": "2022-01-13T03:56:50Z", "salary": {"currency": null, "max": null, "min": null, "period": "monthly", "term": null}, "salary_visible": false, "title_keywords": ["product manager"], "responsibilities": ["reporting", "management", "cost", "data", "operations", "compliance", "monitor", "performance metrics", "day-to-day operations", "review", "develop", "data analysis", "communication", "logistics", "costs"], "requirements": {"degrees": [], "majors": [], "languages": ["english", "mandarin"], "language_level": ["excellent"], "hard_skills": ["amazon", "analysis", "tableau", "microsoft excel", "analytical skills", "make"], "soft_skills": ["communication skills", "self-motivated", "problem solver", "sense of responsibility", "detail oriented", "analytical skills", "attention to detail", "proactive", "driven", "ideal"], "languages_combined": [{"language": "english", "language_level": ["excellent"]}, {"language": "mandarin", "language_level": ["excellent"]}]}, "experience_required": {"duration": ["8+ years"], "field": ["supply chain", "operation management", "logistics"]}}, {"job_id": "100003009033945", "location_code": "hk", "company": "Maryling Asia Pacific Group Limited", "job_title": "Retail Operations Officer", "description": "We are growing fast, and looking for a Customer Care Specialist to join our team, supporting shoppers\u00a0from Japan. This role will help our customers with their shopping from brands like Asos, Urban Outfitters and Anthropologie, assisting with their orders, billing, cancellations and other inquiries.\nIn this role you will be enthusiastic, solutions-oriented, compassionate and focused on being an advocate for our customers at all times.\n\nAs a Customer Care Specialist, you will:\n\nHandle emails from Japanese customers; helping them with any issues in their online shopping experience\nUse internal applications and systems to track deliveries, look up payments, modify orders, etc.\nCoordinate with Shipping department, Finance team, Logistics partners and other global teams to help find solutions for our customers' problems\nHelp customers to solve problems, de-escalate issues and work through difficult conversations with professionalism\n\nThis might be a perfect fit for you if you:\n\nAre a fluent speaker, reader and writer of Japanese and English\nHave excellent communication and problem-solving skills\nEnjoy working in a fast-paced environment\nHave experience working in Ecommerce Customer Service", "employment_types": ["Full Time", "Permanent"], "selling_points": ["Support retail stores operations", "Provide services to online customers", "Assist in logistics management"], "locations": ["Tsim Sha Tsui"], "categories": ["Sales, CS & Business Devpt", "Others", "E-commerce", "Supply Chain"], "post_time": "2022-01-10T02:14:20Z", "salary": {"currency": null, "max": null, "min": null, "period": "monthly", "term": null}, "salary_visible": false, "title_keywords": ["operations officer"], "responsibilities": ["shipping", "systems", "coordinate with", "teams", "communication", "customer service", "payments", "finance team", "logistics"], "requirements": {"degrees": [], "majors": [], "languages": ["japanese", "english"], "language_level": ["fluent"], "hard_skills": ["problem-solving skills"], "soft_skills": ["focused", "fast-paced environment", "enjoy working", "communication", "solve problems", "customer service", "enthusiastic", "problem-solving skills"], "languages_combined": [{"language": "japanese", "language_level": ["fluent"]}, {"language": "english", "language_level": ["fluent"]}]}, "experience_required": {"duration": [], "field": ["ecommerce", "customer service"]}}, {"job_id": "100003009038663", "location_code": "hk", "company": "Gift Something", "job_title": "Procurement/ Purchasing Officer", "description": "Responsibilities:\n\nCollaborate with teams to develop eCommerce business for Asia Pacific including, business planning, content strategy and development, promotional campaigns and online marketing, website design, customer service, web analytics, etc.;\nAct as a project manager to evaluate, prioritize, develop, manage, implement and test eCommerce initiatives;\nAccountable for eCommerce sales performance of APAC (except Japan and Taiwan).\nShare best practice with Headquarter digital team\nResponsible for managing the entire process of the eCommerce platforms enhancement project, including improving the user experience, omni-channel development, especially for future projects O2O (Online to Offline, Ship from store)\u00a0 etc.;\nPartner with external vendor and Headquarter & local IT Departments to further improve the design, engineering, UX/UI, logistics of the e-Commerce platforms;\nAct as a leader on e-merchandising with P.I.M (Quable) tool;\nEstablish a logistic flow with Logistics Department, external vendor and IT team for stock transfer; monitor and control the related costs;\nWork with different departments on preparing sales forecast, pricing, marketing and merchandising strategies;\nKeep track of daily and monthly sales, sell-through, inventory level, etc.\u00a0 Implement contingency plan(s) if KPIs and Campaign ROI fall behind required standard;\nClosely work with Digital Marketing Team for planning and executing digital marketing strategies including but not limited to website optimization, SEM/SEO, social media, sales promotion, to drive site traffic, sales and revenue;\nAnalyze market and in-house data to understand consumer behaviors and identify marketing trends and provide regular reports for management review.\n\nRequirements:\n\nDegree holder in E-commerce, Marketing or related discipline;\nAt least 5 years of experience in similar role;\nKnowledge of eCommerce in other Asia Pacific markets is an additional advantage.\nStrong planning and organizing skills;\nExcellent analytical and project management skills;\nGood understanding of Fashion and Retail Industry;\nFamiliar with mobile and web technologies, including but not limit to UI/UX, SEO, SEM, e-Commerce, P.I.M & D.A.M,\u00a0 Order orchestration,\u00a0 Social Media Marketing, APIs, etc.;\nGood knowledge in e-Commerce system architecture and technical solutions is highly preferred\nImmediate availability is preferable.\nWe offer competitive remuneration package, 5-day work week and career development to successful candidate. Interested parties, please submit your resume with current and expected salary Apply Now.\n\n\n\u00a0* All personal data collected will be used for recruitment purpose only.\u00a0", "employment_types": ["Full Time"], "selling_points": ["Attractive Package", "Medical Insurance", "Energetic & Dynamic Team"], "locations": ["Tsuen Wan Area"], "categories": ["Merchandising & Purchasing", "Procurement / Purchasing / Sourcing", "E-commerce", "Supply Chain"], "post_time": "2022-01-11T07:36:24Z", "salary": {"currency": null, "max": null, "min": null, "period": "monthly", "term": null}, "salary_visible": false, "title_keywords": ["purchasing officer"], "responsibilities": ["collaborate with", "data", "inventory", "merchandising", "website", "design", "e-commerce platforms", "customer service", "regular reports for management", "costs", "control", "digital marketing strategies", "sales performance", "monitor", "teams", "user experience", "develop", "logistics", "forecast", "kpis", "ui", "social media", "seo", "review", "digital marketing", "executing", "evaluate", "sem", "planning"], "requirements": {"degrees": ["degree holder"], "majors": ["marketing", "e-commerce"], "languages": [], "language_level": [], "hard_skills": ["seo", "e-commerce", "project management", "mobile", "sem", "web technologies"], "soft_skills": ["project management skills"], "languages_combined": []}, "experience_required": {"duration": ["at least 5 years"], "field": []}}, {"job_id": "100003009043009", "location_code": "hk", "company": "Agnes b. HK Limited", "job_title": "eCommerce Manager", "description": "This\u00a0position will be under HOME+ e-commerce platform.\n\nOur Vision of Home+ is to set up a merchant ecosystem of merchants with shared value, covering different aspects of our customers\u2019 daily household purchases. The mission is to provide customers with the best value for money for the promotional products and services offered, from time to time. For more information, please feel free to visit our website at\u00a0https://home-plus.hk/\n\n\n\nWhat efforts you need to make?\n\nProviding administrative support to daily sales related activities\nResponse customer enquiry, ordering input, invoicing, order delivery & after sales service\nPerform the general administrative works for document printing, scanning, copying, mailing, filing and report generation\nCoordination and communication with different departments\u00a0\nLet's check if you are /have\u2026\n\nF.5 or above\nAt least 1-2 years sales/contract administration experience, experience in handling Stationary & Supplies products is preferable\nCustomer oriented, responsible, well-organized, work with minimum supervision & able to work under pressure\nGood working attitude and communication skill\nProficient in using MS Office such as Word and Excel\nImmediate available is\u00a0highly preferred\n\n", "employment_types": ["Full Time", "Permanent"], "selling_points": ["Degree holder in E-commerce / Marketing", "At least 5 years of experience in similar role", "Familiar with mobile and web technologies"], "locations": ["Tai Koo"], "categories": ["E-commerce", "Business Development", "Product Management / Business Analyst", "Supply Chain"], "post_time": "2022-01-12T09:31:28Z", "salary": {"currency": null, "max": null, "min": null, "period": null, "term": null}, "salary_visible": false, "title_keywords": ["manager"], "responsibilities": ["scanning", "copying", "administrative support", "work under pressure", "contract administration", "website", "invoicing", "communication", "coordination", "e-commerce platform", "report"], "requirements": {"degrees": [], "majors": [], "languages": [], "language_level": [], "hard_skills": ["excel", "plus", "e-commerce", "word", "make", "ms office"], "soft_skills": ["good working attitude", "responsible", "communication skill", "well-organized", "communication", "coordination", "work under pressure"], "languages_combined": []}, "experience_required": {"duration": ["at least 1-2 years"], "field": ["administration"]}}, {"job_id": "100003009036386", "location_code": "hk", "company": "HomePlus (Hong Kong) Limited (HOME+)", "job_title": "Sales Support Executive", "description": "Responsibilities:\n\nWork closely with Warehouse Operation Team to ensure smooth daily operation\nAssist Manager to maintain key performance indicators\nCo-ordinate with internal and CS team to ensure on-time order fulfilment\nPrepare regular report and data analysis to clients\nDevelop your interpersonal skills and management skills to be a part of the management team in the later stage of your career\nPerform ad-hoc assignment as required\n\nRequirements:\n\nQuicker learner in a fast-paced environment\nSelf-motivated, detail-minded and willing to go extra mile\nWith relevant experience in Warehouse Operations / WMS will be an advantage\nFamiliar with MS Excel applications\nSelf-motivated, independent and willing to work as a team player\nFresh graduates are welcome\n\nEmployment Terms:\n\nDiscretionary Bonus, Free Lunch Meal, Free Shuttle Bus, Annual Leave, Bank Holiday, Overtime Allowance, 5.5 Days or Alternate Saturday off per week\n\nApplication Information:\n\nJob seekers please click the \"Apply Now\".", "employment_types": ["Full Time", "Permanent"], "selling_points": ["Sales Administration/Administrative support", "Stationary & Supplies products", "invoicing, order delivery & after sales service"], "locations": ["Kwai Hing"], "categories": ["E-commerce", "Supply Chain", "Others", "Sales, CS & Business Devpt", "Sales Administration"], "post_time": "2022-01-10T10:13:18Z", "salary": {"currency": null, "max": null, "min": null, "period": "monthly", "term": null}, "salary_visible": false, "title_keywords": ["sales support executive"], "responsibilities": ["ad-hoc", "management team", "management", "co-ordinate with", "daily operation", "develop", "data analysis", "maintain", "prepare regular report"], "requirements": {"degrees": [], "majors": [], "languages": [], "language_level": [], "hard_skills": ["ms excel", "go"], "soft_skills": ["detail-minded", "self-motivated", "independent", "work as a team", "fast-paced environment"], "languages_combined": []}, "experience_required": {"duration": [], "field": ["relevant experience"]}}, {"job_id": "100003009034399", "location_code": "hk", "company": "Times Express Limited", "job_title": "Supervisor Trainee (E-commerce Warehouse Operations)", "description": "Reporting to Business Solution Manager to maintain assigned key accounts and provide customer support. The role is a crucial interface between internal and external customers, and manage relationship with external customers to drive the growth of the business.\n\n\nJob Responsibilities\u00a0\n\nMaintain and provide customer support to assigned major accounts for business development and sales process\nIdentify and qualify customer needs and requirement\nProvide business solution to explore new business opportunities by working with Business Development Managers\nConduct customer profile analysis and prepare monthly performance reports\nImplement SOP for new customers to ensure smooth onboarding\nProactively identify and resolve customer escalations, issues and manage exceptions\n\u00a0Job Requirements\nMinimum 2 year logistic industry experience\nAccount management and customer service experience preferrable\nPostal distribution background with knowledge of e-commerce market place and air freight preferable\nData proficiency including excel\nBusiness analysis and proposal proficiency\nGood problem solving and effective communication skills\nProcess driven and result oriented\nWilling to work as team\nFluent spoken and written English and Chinese (Mandarin)\nWilling to travel with expected frequencies to different cities of China\nA recognized university degree\nImmediate availability is preferable\nG3 Worldwide Hong Kong Limited\u00a0is an equal opportunity employer and welcomes applications from all qualified candidates. Information provided will be treated in strict confidence and only be used for recruitment related purposes. Applicants who are not contacted within 6 weeks may consider their application unsuccessful. Unsuccessful applications may be kept for another 3 months for being considered for other suitable positions available in our Company. The unsuccessful applications will be destroyed after the said period of retention.\n", "employment_types": ["Full Time"], "selling_points": ["Fast Growing E-commerce Field", "Cooperate with 100+ Luxury and Wrold-famous Brands", "Energetic Team with Good Career Prospect"], "locations": ["Kwai Fong"], "categories": ["Transportation & Logistics", "Fulfillment", "Inventory / Warehousing", "E-commerce", "Supply Chain"], "post_time": "2022-01-10T03:18:47Z", "salary": {"currency": null, "max": null, "min": null, "period": "monthly", "term": null}, "salary_visible": false, "title_keywords": ["operations", "supervisor", "trainee"], "responsibilities": ["performance reports", "analysis", "maintain", "explore new business opportunities"], "requirements": {"degrees": ["university degree"], "majors": [], "languages": ["english", "chinese", "mandarin"], "language_level": ["fluent"], "hard_skills": ["problem solving", "excel", "analysis", "e-commerce"], "soft_skills": ["communication skills", "confidence", "problem solving", "result oriented", "customer service", "driven"], "languages_combined": [{"language": "english", "language_level": ["fluent"]}, {"language": "chinese", "language_level": ["fluent"]}, {"language": "mandarin", "language_level": ["fluent"]}]}, "experience_required": {"duration": ["minimum 2 year"], "field": ["customer service", "account management"]}}, {"job_id": "100003009036417", "location_code": "hk", "company": "Manta Lab Limited", "job_title": "eCommerce Executive", "description": "Highlights\n\nAnalyse operational performance through application, reports and data analyses to identify and segregate issues with negative impact on Performance Scores.\nLiaise directly with business partners around the world to develop solutions for immediate implementation.\nManage all aspects of database uploads to update service standards\nDevelop robust Peak Period plans and Seasonal Plans to ensure performance\nParticipate in facilities audit program and assist with the production of audit reports as assigned.\nDevelop and generate regular reporting of performance analytics\nPrepare graphs for presentations, decision papers and advice papers as required\nProvide ad-hoc analytical support and performance score cards to Senior Management\n\nRequirements\n\nExperience in Supply Chain & Logistics is highly desirable\nExtensive and applied knowledge of reporting\nExtensive analytical skills\n5 years minimum experience in analytical field or related field\n2 years minimum Project Management experience\nExcellent command of both written and verbal English, knowledge of other languages preferred\nPreferred experience in parcel shipping industry\nExtensive proficiency in MS Excel and demonstrated ability to manipulate data rapidly and efficiently\nExcellent computer skills in MS Word, and PowerPoint; MS Access and MS Project knowledge desirable\nMust sign a non-disclosure agreement (as applicable)\nQualities of an organized, self-motivated and committed team member able to take initiative\nHigh cultural awareness\n\nIf you are interested please send your full resume in MS Word format, along with salary history and expectation to Daniel Luk (dan.luk @ globalassociates.com) and a cc: copy to cv @ globalassociates.com.", "employment_types": ["Full Time", "Permanent"], "selling_points": [], "locations": ["Kwun Tong"], "categories": ["E-commerce", "Business Development", "Marketing - Brand / Product Management", "Supply Chain"], "post_time": "2022-01-10T10:22:17Z", "salary": {"currency": null, "max": null, "min": null, "period": "monthly", "term": null}, "salary_visible": false, "title_keywords": ["ecommerce executive"], "responsibilities": ["liaise", "reporting", "ad-hoc", "shipping", "data", "implementation", "audit", "develop", "presentations", "project management", "service standards", "reports", "logistics", "database", "plans", "senior management", "analyse"], "requirements": {"degrees": [], "majors": [], "languages": ["english"], "language_level": ["excellent"], "hard_skills": ["presentations", "analytical skills", "powerpoint", "project management", "ms excel", "computer skills", "ms word"], "soft_skills": ["organized", "self-motivated", "robust", "analytical skills", "project management", "committed", "team member", "extensive", "initiative"], "languages_combined": [{"language": "english", "language_level": ["excellent"]}]}, "experience_required": {"duration": ["5 years", "2 years"], "field": ["analytical", "related", "supply chain", "project management", "logistics", "shipping industry"]}}, {"job_id": "100003009035548", "location_code": "hk", "company": "Geek Plus International Company Limited", "job_title": "Site Engineer", "description": "Job Descriptions\n\n\nAs a member for the global process management team, manage and participate in \u2026\n\nDefine, monitor and follow-up on operational KPIs; working with global, regional and local business teams to continuously improve operational productivity and quality across the global organization;\nPlan and execute global or regional processes change and improvement initiative in line with changes in regulations, market conditions, industry practices and customer needs;\nDevelop training material and conduct process related training (online or face-to-face depending on circumstances) for operational staff across the globe;\nParticipate in larger process improvement and digital transformation projects, focusing on operational processes and change management.\n\nQualification & experience Requirements:-\n\nThe candidates must have high intellectual capacity with a detail-oriented mindset and the ability to zoom out and look at the big picture;\nMinimum 3 years of working experience , ideally in International Logistics or Supply Chain Management;\nA diploma or above in a related subject such as Information Technology, Computer Science, Logistics or Supply Chain Management, is preferred;\nStrong communication and analytical skills; with ability to bridge the gap between business and technology;\nTraining / experience in Project Management;\nExperience from working with Business Process Design, Process Management and /or Process Outsourcing will be a plus;\nGood command of both written and spoken English;\nImmediately available preferred.\u00a0\n\nInterested parties please send full resume with employment history and\u00a0expected salary\u00a0to HRA Division,\u00a0Yusen Logistics Global Management Limited at Level 31, Tower 1, Kowloon Commerce Centre, 51 Kwai Cheong Road, Kwai Chung or by email to hr.ylhk @ hk.yusen-logistics.com.\n\nYusen Logistics Global Management Limited is an equal opportunity employer. All information collected will be used for recruitment purpose only.", "employment_types": ["Full Time", "Permanent"], "selling_points": ["Exp in onsite technical support and installation", "Discipline & seld-motivated, willing to learn", "Familiar in AutoCAD is a plus"], "locations": ["Kwai Fong"], "categories": ["Engineering", "Mechanical", "Others", "E-commerce", "Supply Chain"], "post_time": "2022-01-10T07:37:22Z", "salary": {"currency": null, "max": null, "min": null, "period": "monthly", "term": null}, "salary_visible": false, "title_keywords": ["site engineer"], "responsibilities": ["regulations", "management team", "change management", "teams", "monitor", "quality", "develop", "plan", "kpis"], "requirements": {"degrees": ["diploma or above"], "majors": ["computer science", "information technology"], "languages": ["english"], "language_level": ["good command"], "hard_skills": ["project management", "plus", "gap", "analytical skills"], "soft_skills": ["communication", "project management", "analytical skills", "detail-oriented"], "languages_combined": [{"language": "english", "language_level": ["good command"]}]}, "experience_required": {"duration": ["minimum 3 years"], "field": ["management", "training", "supply chain", "design", "project management", "business", "logistics"]}}, {"job_id": "100003009036212", "location_code": "hk", "company": "I.T Apparels Limited", "job_title": "E-Commerce & Operation Assistant (REF: JDB-IT-EOA)", "description": "Accountabilities \u2013 Key Result Areas\n\nSupport daily operations, preparing and updating weekly/monthly reports and product creation.\nManaging stock allocation to all retail stores and price maintenance, helping to arrange stock transfer when necessary.\nPrepare regular merchandising & stock reports for management review\nWork with buyers and warehouse team to create transfers and as needed to drive sales and to maintain a healthy stock level with effective allocation plan\nManage and able to propose markdowns and retail prices during sale period to maximize sales and maintain planned gross profit\nAssist report preparations on sales trends and patterns, stock replenishment and inventory level in weekly cycle\n\nExperience / Qualification Requirements\n\nDegree holder in business or supply chain related discipline\nWith at least 1 years working in a planning, buying or merchandising functions\nHighly sensitive to figures and strong analytical skills\nAttention to detail with high level of accuracy\nGood interpersonal skills and presentation skills\nExperience using Excel\n\nCompetitive remuneration and benefit package will be offered to the right candidate. Please submit your application by clicking \"Apply Now\" below.\n\nAll data collected is for recruitment purpose only.\n\nSure you want to know more about our company and brands, simply follow our\n\nWEBSITE at\u00a0http://www.ithk.com\u00a0\u00a0 \u00a0 \u00a0 \u00a0 \u00a0 \u00a0 \u00a0 \u00a0 \u00a0 \u00a0 \u00a0 \u00a0 \u00a0 \u00a0 \u00a0 \u00a0 \u00a0 \u00a0 \u00a0 \u00a0 \u00a0 \u00a0 \u00a0 \u00a0 \u00a0 \u00a0 \u00a0 \u00a0 \u00a0 \u00a0 \u00a0 \u00a0 \u00a0 \u00a0\n\nFACEBOOK at\u00a0http://www.facebook.com/I.Ttheofficialpage\u00a0\u00a0 \u00a0 \u00a0 \u00a0 \u00a0 \u00a0 \u00a0 \u00a0 \u00a0 \u00a0 \u00a0 \u00a0 \u00a0 \u00a0\n\nINSTAGRAM at\u00a0http://instagram.com/ithk\u00a0 \u00a0 \u00a0 \u00a0 \u00a0 \u00a0 \u00a0 \u00a0 \u00a0 \u00a0 \u00a0 \u00a0 \u00a0 \u00a0 \u00a0 \u00a0 \u00a0 \u00a0 \u00a0 \u00a0 \u00a0 \u00a0 \u00a0 \u00a0 \u00a0 \u00a0 \u00a0 \u00a0\n\nWEIBO at\u00a0http://e.weibo.com/ithongkong", "employment_types": ["Full Time", "Permanent"], "selling_points": ["Managing stock allocation to all retail stores", "1 years working in a planning, buying", "Immediave available"], "locations": ["Southern Area"], "categories": ["E-commerce", "Product Management / Business Analyst", "Supply Chain", "Sales, CS & Business Devpt", "Sales Administration"], "post_time": "2022-01-10T09:40:07Z", "salary": {"currency": null, "max": null, "min": null, "period": "monthly", "term": null}, "salary_visible": false, "title_keywords": ["operation assistant"], "responsibilities": ["monthly reports", "data", "inventory", "merchandising", "website", "maintain", "plan", "price maintenance", "facebook", "management review", "stock replenishment", "reports", "report", "stock allocation", "daily operations", "drive sales", "maintain a healthy stock level", "recruitment", "planning"], "requirements": {"degrees": ["degree holder"], "majors": ["business"], "languages": [], "language_level": [], "hard_skills": ["excel", "facebook", "maintenance", "analytical skills"], "soft_skills": ["sensitive to figures", "analytical skills", "presentation skills", "interpersonal skills", "attention to detail"], "languages_combined": []}, "experience_required": {"duration": [], "field": []}}, {"job_id": "100003009034391", "location_code": "hk", "company": "Times Express Limited", "job_title": "E-commerce Assistant / Senior Assistant / Assistant Supervisor (Warehouse Operations)", "description": "Responsibilities:\n\nWork closely with Warehouse Operation Team to ensure smooth daily operation\nAssist Manager / Supervisor to maintain key performance indicators\nCo-ordinate with internal and CS team to ensure on-time order fulfilment\nPrepare regular report and data analysis to clients\nProvide administrative support to operations team\nPerform ad-hoc assignment as required\n\nRequirements:\n\nQuicker learner in a fast-paced environment\nSelf-motivated, detail-minded and willing to go extra mile\nWith relevant experience in Warehouse Operations / WMS will be an advantage\nFamiliar with MS Excel applications\nSelf-motivated, independent and willing to work as a team player\nFresh graduates will be considered\nWith relevant experience in Warehouse Operations will be consider as Senior Assistant\nWith relevant experience in Warehouse Management / Costs Control will be consider as Assistant Supervisor\n\nEmployment Terms:\n\nDiscretionary Bonus, Free Lunch Meal, Free Shuttle Bus, Annual Leave, Bank Holiday, Overtime Allowance, 5.5 Days or Alternate Saturday off per week\n\nApplication Information:\n\nJob seekers may click the \"Apply Now\" or whatsapp\u00a0Mr Szeto at 70729297 for further info.", "employment_types": ["Full Time"], "selling_points": ["Fast Growing E-commerce Field", "Cooperate with 100+ Luxury and Wrold-famous Brands", "Energetic Team with Good Career Prospect"], "locations": ["Kwai Fong"], "categories": ["Transportation & Logistics", "Fulfillment", "Inventory / Warehousing", "E-commerce", "Supply Chain"], "post_time": "2022-01-10T03:17:47Z", "salary": {"currency": null, "max": null, "min": null, "period": "monthly", "term": null}, "salary_visible": false, "title_keywords": ["operations", "assistant supervisor", "assistant"], "responsibilities": ["ad-hoc", "co-ordinate with", "operations", "daily operation", "data analysis", "maintain", "provide administrative support", "prepare regular report"], "requirements": {"degrees": [], "majors": [], "languages": [], "language_level": [], "hard_skills": ["whatsapp", "ms excel", "go"], "soft_skills": ["detail-minded", "self-motivated", "independent", "work as a team", "fast-paced environment"], "languages_combined": []}, "experience_required": {"duration": [], "field": ["warehouse management", "relevant experience"]}}, {"job_id": "100003009035430", "location_code": "hk", "company": "KOS International Limited", "job_title": "Supply Chain Analyst (Project Management)", "description": "Responsibilities\n\n\nBe responsible for store infrastructure management of all retail stores including tools and equipment procurement, repair and maintenance;\nLiaise with outsourcing partner for logistics and storage management;\nAssist e-commerce daily operations, including stock transit, and providing customer services.\nRequirements\nBachelor degree holder with 1-2 year(s) of experience in retail industry;\nProficient in Microsoft Office Applications and Chinese Word Processing;\nGood command of written & spoken English, Mandarin, and Cantonese;\nDetail-minded;\nA team player with good communication and interpersonal skills.\n\n\nInterest parties, please send full resume with current and expected salary and date of availability by clicking \"Apply Now\".\u00a0Personal data provided in application will be treated as strictly confidential and used for recruitment purpose by\u00a0MARYLING\u00a0only.\u00a0All unsuccessful applications will be destroyed upon completion of the process.", "employment_types": ["Full Time", "Permanent"], "selling_points": ["Global FMCG Retailer", "Good Business Prospect", "Regional Role"], "locations": ["Shatin Area"], "categories": ["Information Technology (IT)", "IT Project Management / Team Lead", "Transportation & Logistics", "Supply Chain", "E-commerce", "Supply Chain"], "post_time": "2022-01-10T07:08:19Z", "salary": {"currency": null, "max": null, "min": null, "period": "monthly", "term": null}, "salary_visible": false, "title_keywords": ["analyst"], "responsibilities": ["management", "e-commerce daily operations", "maintenance", "infrastructure", "customer services", "repair", "logistics", "liaise with"], "requirements": {"degrees": ["bachelor degree holder"], "majors": [], "languages": ["cantonese", "english", "chinese", "mandarin"], "language_level": ["good command", "proficient"], "hard_skills": ["chinese word processing", "microsoft office"], "soft_skills": ["detail-minded", "team player", "communication and interpersonal skills"], "languages_combined": [{"language": "cantonese", "language_level": ["good command"]}, {"language": "english", "language_level": ["good command"]}, {"language": "chinese", "language_level": ["proficient"]}, {"language": "mandarin", "language_level": ["good command"]}]}, "experience_required": {"duration": [], "field": ["retail industry"]}}, {"job_id": "100003009034051", "location_code": "hk", "company": "B B World (HK) Limited", "job_title": "Part Time Clerk  (Online Cosmetics, Beauty Shop, H.K. Branch)", "description": "About Our Client\n\nOur client is a leading FMCG retailer with over 15,000 stores worldwide. Due to the business expansion plan in the region, they are looking for a Supply Chain Analyst (Project Management) in Hong Kong office.\n\nJob Duties\n\n\nLiaise with and support different functional teams on supply chain optimization projects by formulating and documenting Supply Chain bets practice\nAssist to Supply Chain team and IT team to provide operational guidelines and system training to different Regional BUs\nExplore and advise the best practice and reinforcement in the area of Supply Chain and Logistics to ensure the compliance standard are met\nAnalyse current supply chain operation and follow up on poor performing business by providing process reviews, retaining, and reinforcement of best practices to make improvements\nMonitor and maintain issue logs of all Supply Chain initiatives in the region to ensure the status of deployments, change requests, and application suite updates are recorded\nRequirement\n\n\nDegree holder or above in Supply Chain/ Operation Management/ Business or related disciplines\nAt least 2 years of experience in supply chain inventory planning/business analyst/ project management\nExperience in project management and replenishment is preferable\nExperience in MS Office, Excel, ERP, Python or any supply chain software solutions is preferable\nKnowledge in IT coding and IT context is an advantage\nFluent communication in English, Mandarin, and Cantonese\nFlexible to travel in Asia region\n\nClick \"Apply Now\" to apply for this position or call Sandy Chan at +852 3180 4951 for a confidential discussion. All information collected will be kept in strict confidence and will be used for recruitment purpose only.", "employment_types": ["Part Time"], "selling_points": ["e-commerce", "digital customer service", "1-2 yr working exp"], "locations": ["Kwun Tong Area"], "categories": ["Marketing / Public Relations", "Marketing - General / Support", "E-commerce", "Supply Chain", "Sales, CS & Business Devpt", "Sales Administration"], "post_time": "2022-01-10T02:30:24Z", "salary": {"currency": null, "max": null, "min": null, "period": "monthly", "term": null}, "salary_visible": false, "title_keywords": ["part time clerk"], "responsibilities": ["guidelines", "compliance", "teams", "monitor", "maintain", "logistics", "liaise with", "analyse"], "requirements": {"degrees": ["degree holder"], "majors": ["related disciplines", "business"], "languages": ["cantonese", "english", "mandarin"], "language_level": ["fluent"], "hard_skills": ["excel", "erp", "project management", "python", "ms office"], "soft_skills": ["communication", "project management", "confidence", "flexible"], "languages_combined": [{"language": "cantonese", "language_level": ["fluent"]}, {"language": "english", "language_level": ["fluent"]}, {"language": "mandarin", "language_level": ["fluent"]}]}, "experience_required": {"duration": ["at least 2 years"], "field": ["supply chain", "project management", "business", "planning"]}}, {"job_id": "100003009033936", "location_code": "hk", "company": "Morrison Express Co Ltd", "job_title": "Assistant Manager - HR & Administration (New Headcount)", "description": "Essential Job Functions\u00a0\n\n\nProvide professional administrative and customer services support\u00a0\nResponsible for answering customer enquiries via different channels, including WhatsApp, or even social media platform\u00a0\n\nDeliver quality customer service through texting, follow up and handle inquiries with good communication skills, friendly and polite manner\u00a0\n\nProvide pro-active follow-up and quality service to customers\u00a0\u00a0\n\nAssist operation team in\u00a0logistic\u00a0processing\u00a0\nAny other ad hoc duties assigned by the supervisor\n\n\n\nRequirements:\u00a0\n\nMatriculated OR equivalent to 5 subjects obtained Level 3 or above in HKDSE, including English and Chinese with min. 1 year experience in customer services.\u00a0\nBasic PC knowledge including Word Processing, Excel.\n\nGood communication, and interpersonal skills.\u00a0\nMature, service-oriented and attentive to details.\u00a0\nHigh EQ\u00a0", "employment_types": ["Full Time", "Permanent"], "selling_points": ["Oversee all round HR & Administration Operation", "Able to work independently and under pressure", "Good Career Prospects"], "locations": ["Kwai Tsing Area"], "categories": ["Admin & HR", "Administration / Operation Manager", "Transportation & Logistics", "Freight Forwarding", "E-commerce", "Supply Chain"], "post_time": "2022-01-10T02:10:58Z", "salary": {"currency": null, "max": null, "min": null, "period": "monthly", "term": null}, "salary_visible": false, "title_keywords": ["assistant manager", "hr"], "responsibilities": ["ad hoc duties", "social media", "customer enquiries", "quality", "customer services", "communication", "customer service"], "requirements": {"degrees": ["hkdse"], "majors": [], "languages": ["english", "chinese"], "language_level": [], "hard_skills": ["excel", "basic", "word processing", "whatsapp", "pc knowledge", "processing"], "soft_skills": ["communication skills", "polite", "responsible", "attentive to details", "service-oriented", "mature", "communication", "customer service", "friendly", "interpersonal skills", "pro-active"], "languages_combined": [{"language": "english", "language_level": []}, {"language": "chinese", "language_level": []}]}, "experience_required": {"duration": ["1 year"], "field": ["customer services"]}}, {"job_id": "100003009031515", "location_code": "hk", "company": "Chow Sang Sang Holdings International Limited", "job_title": "Associate Executive/Executive, E-Commerce", "description": "Jobs Description:\n\nWork closely with customer service department in delivering quality service to customers\nManage day-to-day operation and update content materials of e-commerce platforms\nHandle e-commerce logistic and orders issues\nLiaise and coordinate with business partners and related departments on day-to-day business operations\nSupport daily operations, preparing and updating daily/monthly reports\nSupport E-commerce team on departmental administration\nAssist in ad-hoc duties as assigned by the supervisor\nRequirements:\n\nDegree in e-commerce/Communication or related discipline\nMinimum 3 years\u2019 experience working in online business or e-commerce operation\nPatient, detail-minded, well-organized, multi-tasking and able to work under pressure\nProficiency in MS Word, Excel, PowerPoint and Chinese Word Processing\u00a0\nExcellent in both written and spoken Chinese and English\nWe offer 5-day-work week with competitive remuneration packages to the right candidate.\u00a0 Interested parties please send your CV with EXPECTED SALARY through the below application procedure.\n(Personal data will be used by Chow Sang Sang (CSS) for recruitment only.\u00a0 CSS may refer suitable applications to other vacancies within CSS and its associated companies.\u00a0 We will retain unsuccessful applications for a maximum period of 24 months.)", "employment_types": ["Full Time", "Permanent"], "selling_points": ["Deliver quality service to customers", "Manage day-to-day operation of e-commerce platform", "3 yrs exp in e-commerce operation"], "locations": ["Cheung Sha Wan"], "categories": ["Sales, CS & Business Devpt", "Others", "E-commerce", "Supply Chain", "Others"], "post_time": "2022-01-07T09:24:19Z", "salary": {"currency": null, "max": null, "min": null, "period": "monthly", "term": null}, "salary_visible": false, "title_keywords": ["associate", "executive"], "responsibilities": ["liaise", "monthly reports", "operations", "support e-commerce team", "quality", "e-commerce platforms", "coordinate with", "daily operations", "customer service", "ad-hoc duties", "update content materials", "day-to-day operation", "administration"], "requirements": {"degrees": ["degree"], "majors": ["e-commerce"], "languages": ["english", "chinese"], "language_level": ["proficiency", "excellent"], "hard_skills": ["excel", "chinese word processing", "e-commerce", "powerpoint", "ms word"], "soft_skills": ["detail-minded", "well-organized", "communication", "multi-tasking", "patient", "work under pressure"], "languages_combined": [{"language": "english", "language_level": ["excellent"]}, {"language": "chinese", "language_level": ["proficiency", "excellent"]}]}, "experience_required": {"duration": ["minimum 3 years"], "field": ["operation", "business", "e-commerce"]}}, {"job_id": "100003009024326", "location_code": "hk", "company": "Crazy Group Limited", "job_title": "Operation Assistance", "description": "We are a fast-growing and integrated Fin-Tech/ e-commerce Company in Hong Kong.\n\nOur Company culture is creative and positive with goal-oriented and customer-driven, just like a family group.\nTo cope with our rapid expansion, we are looking for a high-calibre person to fill the following position:\n\n- Assist in preparing product launch on online shop\n- Manage online shop order flow control including placing orders, logistics, CS issues, etc.\n- Assist in product price review and modification\n- Coordinate with IT team for website enhancement\n- Assist in other operations and ad-hoc project\n\nRequirements:\n\n- Willing to participate in e-commerce and working with the creative team as a priority.\n- Higher diploma + in marketing, education, business administration or related discipline\n- Minimum of 1 year's relevant experience; fresh graduates will also be considered\n- Proficiency in Chinese Writing with creative sense.\n- Proficiency in MS Office, PowerPoint, English & Chinese word processing\n- Photoshop skills will be considered\n- Good communication and problem-solving skills\n- Ability to work with Passion\n- Result-oriented, responsible and self-motivated\n\nWe offer 5 days work.\nInterested parties please apply with full resume/portfolio, present & EXPECTED SALARY, date availability.\n\nAll applications will be handled in strict confidence and all data will only be used for recruitment-related purposes.", "employment_types": ["Full Time", "Permanent"], "selling_points": [], "locations": ["Hung Hom"], "categories": ["E-commerce", "Supply Chain"], "post_time": "2022-01-07T08:02:26Z", "salary": {"currency": null, "max": null, "min": null, "period": "monthly", "term": null}, "salary_visible": false, "title_keywords": ["assistance"], "responsibilities": ["ad-hoc", "control", "operations", "review", "coordinate with", "website", "communication", "logistics", "placing orders", "administration"], "requirements": {"degrees": ["diploma"], "majors": ["marketing", "business administration"], "languages": ["english", "chinese"], "language_level": ["proficiency"], "hard_skills": ["chinese word processing", "e-commerce", "powerpoint", "goal", "photoshop", "rapid", "problem-solving skills", "ms office"], "soft_skills": ["result-oriented", "self-motivated", "responsible", "communication", "problem-solving skills", "creative", "driven", "positive"], "languages_combined": [{"language": "english", "language_level": ["proficiency"]}, {"language": "chinese", "language_level": ["proficiency", "proficiency"]}]}, "experience_required": {"duration": ["minimum of 1 year"], "field": ["relevant experience"]}}, {"job_id": "100003009028599", "location_code": "hk", "company": "Profit Sail Int'l Express (H.K.) Ltd", "job_title": "Personal Assistant", "description": "Responsibilities\n\nResponsible for assisting in all-round HR & Administrative functions mainly in full cycle of recruitment process, compensation & benefits as well as monthly payroll processing, training & development, performance management and employee relationship;\nBenchmark and recommend remuneration package for potential candidates to ensure competitiveness in the market and internal equity;\nEnsure Human Resources Functions in compliance with Hong Kong Labour Ordinance and local regulations;\nReview and update all HR policies and procedures in accordance with latest statutorily requirement;\nImplement HR policies in compliance with labour ordinances, HQ SOP, internal policies & procedures;\nSupport Human Resources function, benefits administration; leave management;\nAssisting in regularly reports, such as staff turnover, monthly headcount, exit interview, etc.;\nMonitor and administer the office administration such as facility maintenance and repair management etc.;\nSupport in organizing company functions; annual dinner and staff activities;\nProvide day-to-day support to the team;\nPrepare monthly reports and analysis for management\u2019s review;\nPerform ad-hoc assignments.\n\n\u00a0Requirements\n\nDegree in Human Resources or related disciplines;\n\nAt least 6 years relevant working experience in HR function;\nWell-versed in Hong Kong Employment Ordinance and related legislations\nGood numerical sense, excellent data interpretation and analytical skills\nStrong sense of responsibilities and commitment, well-organized, effective communications skills in interacting with people at all levels\nProficient with Microsoft Word, Chinese, Excel\nFluency in written & spoken in English and Mandarin\nAble to communicate with all levels of staff\n\nCandidates with lower qualification and experience will be considered for lower position.\u00a0 Interested parties, please send full resume, availability and expected salary to our company.\n\nAll information provided by applicants will be treated in strict confidence and used only for employment-related purposes. All personal data of unsuccessful applicants will be destroyed within 6 months.", "employment_types": ["Full Time", "Permanent"], "selling_points": ["Provide all-round secretarial support", "Great Career Exposure", "12 Days AL, Performance Bonus, Near Kwai Fong MTR"], "locations": ["Kwai Fong"], "categories": ["Admin & HR", "Personal / Executive Assistant", "Transportation & Logistics", "Freight Forwarding", "E-commerce", "Supply Chain"], "post_time": "2022-01-07T02:39:08Z", "salary": {"currency": null, "max": null, "min": null, "period": "monthly", "term": null}, "salary_visible": false, "title_keywords": ["personal assistant"], "responsibilities": ["regulations", "management", "policies", "hr", "compliance", "review", "procedures", "recruitment process", "payroll", "human resources functions"], "requirements": {"degrees": [], "majors": [], "languages": [], "language_level": [], "hard_skills": [], "soft_skills": [], "languages_combined": []}, "experience_required": {"duration": [], "field": []}}, {"job_id": "100003009031127", "location_code": "hk", "company": "Ztore HK Limited", "job_title": "[Neigbuy.com] Business Executive", "description": "This is an opportunity to become a highly impactful contributor of a rapidly growing startup. We are seeking a self-motivated, detail-oriented, and fast-learning Business Executive to help grow our business. Ultimately, this person is responsible for selecting the best products for the market, maintaining healthy relationships with suppliers, and performing daily operations to make sourced products sell on the platform.\nResponsibilities:\nHOW will you perform in the position?\nBe a curious learner to understand the market\nBe a negotiator to obtain the best deals from vendors/suppliers\nBe an adventurer and not be afraid to do lots of trial and error\nWHAT duties will you be responsible for?\nCollaborate with key vendors and suppliers to get the best products for our customers\nLiaise with vendors on terms and conditions, pricing and purchase order issues\nBe ambitious and take initiative to lead the team to achieve monthly sales target\nActively search & source for our expanding categories, mainly fashion-related or intangible goods\nUnderstand products\u2019 winning criteria and cooperate with Growth Team members to promote winning products\nPerform Daily Operations to expose your innovative selling ideas on our APP\nCommunicate well with different internal teams such as CS, logistics, warehouse to ensure our quality of service\nNegotiate with suppliers on product costs and promotion offers\nPrepare sales reports for management review\nRequirements:\n2+ years of working experience is preferred but not a must, fresh graduates are also welcomed\nStrong market and growth sense, customer-oriented, eager to learn and adaptable to changes\nStrong negotiation and communication skills\nAble to work in high pressure and fast-paced environment\nGood command of written and spoken English and Chinese\nGood presentation, interpersonal, organizing and communication skills", "employment_types": ["Full Time"], "selling_points": ["Rapid Growing FMCG E-commerce Platform", "Start-up Environment: Fun, Fast Paced", "Expanding categories (Fashion & Intangible goods)"], "locations": ["Lai Chi Kok"], "categories": ["Merchandising & Purchasing", "Others", "Procurement / Purchasing / Sourcing", "E-commerce", "Supply Chain"], "post_time": "2022-01-07T09:00:45Z", "salary": {"currency": null, "max": null, "min": null, "period": "monthly", "term": null}, "salary_visible": false, "title_keywords": ["business executive"], "responsibilities": ["collaborate with", "ideas", "sales target", "teams", "quality", "prepare sales", "management review", "purchase", "daily operations", "logistics", "reports", "liaise with", "cooperate with", "costs"], "requirements": {"degrees": [], "majors": [], "languages": ["english", "chinese"], "language_level": ["good command"], "hard_skills": [], "soft_skills": ["communication skills", "negotiation", "adaptable", "fast-paced environment", "eager to learn", "customer-oriented", "interpersonal", "presentation"], "languages_combined": [{"language": "english", "language_level": ["good command"]}, {"language": "chinese", "language_level": ["good command"]}]}, "experience_required": {"duration": ["2+ years"], "field": []}}, {"job_id": "100003009028622", "location_code": "hk", "company": "Profit Sail Int'l Express (H.K.) Ltd", "job_title": "Clerk - Air Freight Operation", "description": "Job Description\n\nResponsibilities:\n\n\u00a0Drive the company online business growth through different online platforms\n\u00a0Manage the operations of online platform functions, marketing/graphics, customer support and online inventory\nDesigning and implementing processes to effectively launch products onto different online platforms such as HKTVmall, Tmall, Ebay, Lazada, etc.\n\u00a0Responsible for order follow up, issue PO, liaise with customer and internal parties\n\u00a0Researching competitive pricing & promotions\n\nRequirements:\n\nDiploma holder or above in business / e-Commerce or related disciplines\nrelevant working experience in B2C online platform is an advantage\nBasic knowledge in PHOTOSHOP and photo-shooting\nIndependent, self-motivated, Aggressive, Positive \u201ccan-do\u201d attitude\nGood command of written and spoken English, Cantonese and Mandarin\nGood command of PC software including Microsoft Office and word processing\nFresh graduate will also be consider as junior position\n\nBENEFIT:\n\nDouble pay and year-end bonus after one year employment\nIncentive Bonus provided for outstanding candidate\nMedical provided after probation\u00a0\nAnnual leave 10 days (Maximum to 19 days)\nOT allowance provided (Max. $70/hr)\nPublic Holiday\nFree Snack provided\nMonthly Birthday party celebration / game party\nBirthday Coupon\n5-days work\u00a0 (**Note: 2 of Saturdays per each month must be shifted and counted OT allowance)", "employment_types": ["Full Time"], "selling_points": ["DSE or above, Fresh Graduates are welcome", "Performance Bonus, 12 Days AL", "Near Kwai Fong MTR Station"], "locations": ["Kwai Fong"], "categories": ["Transportation & Logistics", "Freight Forwarding", "Shipping", "E-commerce", "Supply Chain"], "post_time": "2022-01-07T02:41:44Z", "salary": {"currency": null, "max": null, "min": null, "period": "monthly", "term": null}, "salary_visible": false, "title_keywords": ["clerk", "air freight operation"], "responsibilities": ["graphics", "operations", "inventory", "designing", "liaise with", "internal parties"], "requirements": {"degrees": ["diploma holder", "fresh graduate"], "majors": ["related disciplines", "business", "e-commerce"], "languages": ["cantonese", "english", "mandarin"], "language_level": ["good command"], "hard_skills": ["basic", "microsoft office", "e-commerce", "word processing", "pc", "photoshop"], "soft_skills": ["can-do", "self-motivated", "independent", "positive"], "languages_combined": [{"language": "cantonese", "language_level": ["good command"]}, {"language": "english", "language_level": ["good command"]}, {"language": "mandarin", "language_level": ["good command"]}]}, "experience_required": {"duration": [], "field": ["relevant working experience"]}}, {"job_id": "100003009025185", "location_code": "hk", "company": "Union Camera Hong Kong Limited", "job_title": "E-commerce Assistant / Coordinator", "description": "This is an opportunity to become a highly impactful contributor of a rapidly growing startup. We need a buyer who is data driven and curious. Ultimately, this person is responsible for selecting the good product, maintaining relationship with suppliers, and formulating the promotion plan to drive sales.\n\nResponsibilities:\n\n\nHOW\u00a0will you perform in the position?\n\nBe a curious learner to understand the market\nBe a strategic planner to formulate promotion plan\nBe a collaborator to improve relationships with suppliers\n\nWHAT\u00a0duties will you be responsible for?\n\nHelp to expand product assortments on assigned categories (mainly Beauty and Cosmetics)\nAssist to achieve aggressive sales and margin target through strategic and product planning\nNegotiate with suppliers on product costs and promotion offers\nFormulate order forecast and maintain healthy inventory control\nFrequent market visits to identify market potentials\nPrepare sales reports for management review\n\nRequirements:\n\n2+ year experience with FMCG category management experience is required\nStrong market sense, customer-oriented, eager to learn and adaptable to changes\nStrong negotiation and analytical skills\nAble to work in high pressure and fast-paced environment\nGood command of written and spoken English and Chinese\nGood presentation, interpersonal, organizing and communication skills", "employment_types": ["Full Time"], "selling_points": [], "locations": ["Tsuen Wan Area"], "categories": ["E-commerce", "Business Development", "Marketing - Brand / Product Management", "Supply Chain"], "post_time": "2022-01-06T03:45:29Z", "salary": {"currency": null, "max": null, "min": null, "period": "monthly", "term": null}, "salary_visible": false, "title_keywords": ["coordinator", "assistant"], "responsibilities": ["prepare sales", "management review", "maintain", "order forecast", "inventory control", "plan", "reports", "costs", "planning"], "requirements": {"degrees": [], "majors": [], "languages": ["english", "chinese"], "language_level": ["good command"], "hard_skills": ["analytical skills"], "soft_skills": ["communication skills", "negotiation", "adaptable", "fast-paced environment", "analytical skills", "eager to learn", "customer-oriented", "strong market sense", "interpersonal", "presentation"], "languages_combined": [{"language": "english", "language_level": ["good command"]}, {"language": "chinese", "language_level": ["good command"]}]}, "experience_required": {"duration": ["2+ year"], "field": ["management", "fmcg"]}}, {"job_id": "100003009031154", "location_code": "hk", "company": "Ztore HK Limited", "job_title": "Buyer/ Category Executive (Beauty & Cosmetics, E-commerce)", "description": "This is an opportunity to become a highly impactful contributor of a rapidly growing startup. We need a Category Executive / Buyer who can lead the strategy and management of Non-Food category. Ultimately, this person is responsible for selecting the good products, maintaining relationship with suppliers, and formulating the promotion plans to drive sales.\n\nResponsibilities:\n\nHOW\u00a0will you perform in the position?\n\nBe an empathetic diplomat to maintain excellent relationships with suppliers\nBe a strategic planner to formulate category goals and plans\nBe a leader who prioritizes team success over individual success\n\nWHAT\u00a0duties will you be responsible for?\n\nHelp to expand product assortments on non-food category\nAssist to achieve aggressive sales and margin target through strategic and product planning\nNegotiate with suppliers on product costs and promotion offers\nFormulate order forecast and maintain healthy inventory control\nFrequent market visits to identify market potentials\nPrepare sales reports for management review\nAdministrative support to Merchandising Team\u00a0\u00a0\n\nRequirements:\n\n2 years+ relevant category experience is required\nStrong market sense, customer-oriented, eager to learn and adaptable to changes\nStrong negotiation and analytical skills\nAble to work in high pressure and fast-paced environment\nGood command of written and spoken English and Chinese\nGood presentation, interpersonal, organizing and communication skills", "employment_types": ["Full Time"], "selling_points": ["Rapid growing FMCG E-commerce", "Beauty & cosmetics category management", "2+ year relevant experience"], "locations": ["Lai Chi Kok"], "categories": ["E-commerce", "Supply Chain"], "post_time": "2022-01-07T09:01:16Z", "salary": {"currency": null, "max": null, "min": null, "period": "monthly", "term": null}, "salary_visible": false, "title_keywords": ["executive"], "responsibilities": ["administrative support", "prepare sales", "merchandising", "management review", "maintain", "order forecast", "inventory control", "reports", "plans", "costs", "planning"], "requirements": {"degrees": [], "majors": [], "languages": ["english", "chinese"], "language_level": ["good command"], "hard_skills": ["analytical skills"], "soft_skills": ["communication skills", "negotiation", "adaptable", "fast-paced environment", "analytical skills", "eager to learn", "customer-oriented", "strong market sense", "interpersonal", "presentation"], "languages_combined": [{"language": "english", "language_level": ["good command"]}, {"language": "chinese", "language_level": ["good command"]}]}, "experience_required": {"duration": [], "field": []}}, {"job_id": "100003009031153", "location_code": "hk", "company": "Ztore HK Limited", "job_title": "Category Executive / Buyer (E-commerce)", "description": "Highlight of Benefits\uff1a\n\n\n12 Days annual leave\nPleasant Working Environment\nPerformance Bonus\nGreat Career Exposure\nComprehensive Medical Coverage\n\nWho is our Right Fit :\n\n\nUniversity graduate in supply chain or logistics related disciplines\n3-5 years relevant working experience with freight forwarding industry, e-Commerce, supply-chain or related disciplines are advantages\nExcellent communication skills in written and spoken English, Chinese and Mandarin\nProficient in MS Word, Excel and PowerPoint\nIndependent, proactive, detail-oriented and able to work under pressure\nSolid business sense, analytical-minded, performance-driven, details- & results-oriented\nGood skills in problem solving, self-initiated, attentive to details and customer focused\nPresentable with outgoing and pleasant personality\n\nWhat you will be doing\uff1a\n\n\nProvide all-rounded administrative and secretarial support to Directors in both business and personal matters\nLiaise with internal and external parties on business issues proactively & independently\nSupport senior management to formulate the overall strategy on freight forwarding industry and e-Commerce industry\nMaintain a good relationship with clients and ensure to delivery of excellent customer experience\nWorking closely with members of the team to generate new business\nPrepare and realize marketing plans and commercial activities, make follow up with potential customers\nAssist the Project Managers in managing various freight forwarding and e-Commerce projects\nUnderstand business needs and work closely with different teams and stakeholders to deliver high quality business solutions\nLocation: near Kwai Fong MTR Station\n\nInterested parties please send your resume with your current and expected salary by clicking the Apply Now.\n\nPlease visit our website at: www.profitsail.com for more information about us\n\nAll applications will be treated in the strictest confidence and personal data collected will be used for recruitment related purposes only.", "employment_types": ["Full Time"], "selling_points": ["Rapid growing FMCG E-commerce", "Lead Category Management", "5-days work, flexible working Hours"], "locations": ["Lai Chi Kok"], "categories": ["Merchandising & Purchasing", "Others", "E-commerce", "Supply Chain"], "post_time": "2022-01-07T09:01:16Z", "salary": {"currency": null, "max": null, "min": null, "period": "monthly", "term": null}, "salary_visible": false, "title_keywords": ["executive"], "responsibilities": [], "requirements": {"degrees": [], "majors": [], "languages": [], "language_level": [], "hard_skills": [], "soft_skills": [], "languages_combined": []}, "experience_required": {"duration": [], "field": []}}, {"job_id": "100003009030267", "location_code": "hk", "company": "Linde HKO Limited", "job_title": "eCommerce Officer", "description": "Job Scope:\u00a0\u00a0\n\nResponsible for maintenance of Hong Kong & China eShop\nGather products information from different departments (Sales & marketing, CSC, supply chain, CSC, communication\u2026)\nConvert the marketing and Graphics requirements in an HTML it can be uploaded on company CMS for website usage.\nUpload and maintain updated product pages and related downloadable documents.\nPerform new release UAT and debug issues that arise with the performance of the website.\nWork directly with management of the organization to develop business campaigns.\nPrepare eShop analysis reports and marketing plan.\nPerform miscellaneous job-related duties as assigned.\n\nJob Requirements:\n\nDegree holder with at least 2 years relevant experience in eCommerce, website building and business analysis.\nExperience in Web platform including content management and eCommerce systems (IBM management centre - Websphere Commerce a plus)\nknowledge and experience in web analytical tools, HTML, CSS, Javascript, eCommerce platforms and payment gateways, i.e. Google Analytics, social media analytical tool, PayPal, Alipay, WeChat pay will be an advantage.\nProficient in Adobe Photoshop, illustrator, in-design and photography is a must. Knowledge of Premiere Pro and After Effect is an advantage\nHands on experience in marketing in a B2C and B2B multi-channel sales environment\nResult-oriented, self-motivated, able to work independently and under pressure, communicate in English and Mandarin fluently with internal and external customers to achieve company goals.", "employment_types": ["Full Time", "Permanent"], "selling_points": ["eShop", "Double Pay & Bonus", "eCommerce"], "locations": ["Tseung Kwan O"], "categories": ["E-commerce", "Marketing - Brand / Product Management", "Product Management / Business Analyst", "Supply Chain"], "post_time": "2022-01-07T07:07:12Z", "salary": {"currency": null, "max": null, "min": null, "period": "monthly", "term": null}, "salary_visible": false, "title_keywords": ["ecommerce officer"], "responsibilities": ["graphics", "social media", "management", "internal and external customers", "uat", "maintenance", "analysis reports", "systems", "website", "design", "develop", "communication", "marketing plan", "payment", "maintain", "business analysis"], "requirements": {"degrees": ["degree holder"], "majors": ["ecommerce", "business"], "languages": ["english", "mandarin"], "language_level": [], "hard_skills": ["graphics", "google analytics", "plus", "web", "maintenance", "analysis", "adobe photoshop", "illustrator", "html", "wechat", "in-design", "javascript", "premiere pro", "css", "after effect"], "soft_skills": ["self-motivated", "work independently", "under pressure", "responsible", "communication", "hands on", "result-oriented"], "languages_combined": [{"language": "english", "language_level": []}, {"language": "mandarin", "language_level": []}]}, "experience_required": {"duration": ["at least 2 years"], "field": ["ecommerce", "management", "analytical", "marketing", "relevant experience", "business analysis"]}}, {"job_id": "100003009030590", "location_code": "hk", "company": "Kin Shun Information Technology Limited", "job_title": "Operations Manager, Parcel Delivery", "description": "About Zeek\nZeek is the brand name under Kin Shun Information Technology Limited which incorporated in 2019. Zeek aims to provide smart logistics, SaaS solutions and online / offline integrated instant delivery service for Hong Kong and Southeast Asia market, meeting their needs for food & parcel delivery and last-mile logistics.\n\nWe strive for building an excellent delivery experience by adopting big data and artificial intelligence. With existing business in Hong Kong, Singapore, Malaysia, Thailand and Vietnam, we will continue to expand our business to Southeast Asia countries and regions like Taiwan, Philippines and Indonesia in near future.\n\n\nResponsibilities:\n\n\nTo supervise and managing the delivery operations, particularly on workforce management strictly on company regulation to ensure the operations flow is smoothly and efficiency;\nOversees the strategy , planning .and execution of projects to \u00a0ensure accuracy\u00a0 and cost-efficiency;\nExperience with sortation center/ parcel fulfillment center, cost benefit analysis, labor productivity analysis in order to\u00a0effectively plan and scheduling the operations resources in order to meet and exceed internal and external\u00a0services levels at all times with productive and cost efficiency;\nWork with related departments to maintain and enhance the platform of reward system for member activation and engagement;\nMeasure performance, provide a feedback as well as taking proactive steps to ensure the best\u00a0practices are shared across all departments;\nCreate a positive and collaborative team environment by setting and regularly reviewing the\u00a0achievement of team goals;\nDocument and track any failures/error including reporting on failure rates, causes, and preventable\u00a0incidents;\nAssist in training and coaching new and existing team members;\nPerform ad-hoc duties / projects assigned by top management\n\nRequirements:\n\nDiploma holder or above in Logistics, Supply Chain Management or related disciplines;\n5-7 years\u2019 relevant experience of which 2 years were at supervisory level in operations from logistics/supply chain industries;\nExperience in emerging technology in logistics and supply chain, including but not limited to open-platform, dynamic pricing; knowledge of cloud service in logistics is a plus;\nStrong planning and analytical skills. Sensitive to numbers;\nGood people management and presentation skills;\nIndependent, flexible, stress resistant and able to work in a fast pace team-base environment;\nProficiency in MS Excel, Word, PowerPoint and Chinese word processing;\nGood command of both written and spoken English, Chinese and Putonghua\n\nWe offer competitive remuneration, birthday and work anniversary holidays and benefit packages to the right candidate.\n\nPlease send your detailed resume, with last and expected salary to our Human Resources Department by clicking \"Apply Now\u201d.\u00a0\n\n(All information collected will be treated in strict confidence and used solely for recruitment)", "employment_types": ["Full Time", "Permanent"], "selling_points": [], "locations": ["Lai Chi Kok"], "categories": ["Transportation & Logistics", "Fulfillment", "Supply Chain", "E-commerce", "Supply Chain"], "post_time": "2022-01-07T07:50:30Z", "salary": {"currency": null, "max": null, "min": null, "period": "monthly", "term": null}, "salary_visible": false, "title_keywords": ["operations manager"], "responsibilities": ["reporting", "management", "cost", "operations", "fulfillment", "analysis", "scheduling", "maintain", "plan", "ad-hoc duties", "planning"], "requirements": {"degrees": ["diploma holder"], "majors": ["related disciplines"], "languages": ["putonghua", "english", "chinese"], "language_level": ["proficiency", "good command"], "hard_skills": ["plus", "chinese word processing", "word", "powerpoint", "analytical skills", "ms excel", "dynamic"], "soft_skills": ["flexible", "independent", "analytical skills", "presentation skills", "dynamic", "sensitive to numbers"], "languages_combined": [{"language": "putonghua", "language_level": ["good command"]}, {"language": "english", "language_level": ["good command"]}, {"language": "chinese", "language_level": ["proficiency", "good command"]}]}, "experience_required": {"duration": ["5-7 years", "2 years"], "field": ["supervisory level", "logistics", "relevant experience", "supply chain"]}}, {"job_id": "100003009030993", "location_code": "hk", "company": "B B World (HK) Limited", "job_title": "Part Time Clerk  (Online Cosmetics, Beauty Shop, H.K. Branch)", "description": "Qualifications & Requirements:\n\nDSE or above\nWilling to work over-time\nShift duty required (Day shift and night shift)\nProficiency in fair English and Mandarin\nProficiency in MS Word, Excel and Chinese typing\nFresh Graduates are welcome\nAttractive Benefit & Allowance\nWorking location: near Kwai Fong MTR station\n\n\u00a0Responsibilities:\n\nResponsible for handling\u00a0air freight export and import documents\nCoordinate and\u00a0handle cargo flow with internal and external parties\nHandle\u00a0booking instruction, consolidation and customs clearance\nCommunicate with airline and oversea agents\u00a0ensure a smooth running of the process\n\n\u00a0Remarks:\n\nWe are an equal opportunity employer and we offer the rewarding package plus fringe benefit to the right team player.\u00a0Interested parties please send your resume with your current and expected salary by clicking the Apply Now.\n\nCandidates are also welcome to visit our website: www.profitsail.com to know us more", "employment_types": ["Part Time"], "selling_points": ["e-commerce", "digital customer service", "1-2 yr working exp"], "locations": ["Kwun Tong Area"], "categories": ["Marketing / Public Relations", "Marketing - General / Support", "E-commerce", "Supply Chain", "Sales, CS & Business Devpt", "Sales Administration"], "post_time": "2022-01-07T08:47:15Z", "salary": {"currency": null, "max": null, "min": null, "period": "monthly", "term": null}, "salary_visible": false, "title_keywords": ["part time clerk"], "responsibilities": ["communicate with", "air freight", "internal and external parties", "coordinate", "booking"], "requirements": {"degrees": ["dse"], "majors": [], "languages": ["english", "chinese", "mandarin"], "language_level": ["proficiency"], "hard_skills": ["excel", "typing", "ms word"], "soft_skills": [], "languages_combined": [{"language": "english", "language_level": ["proficiency"]}, {"language": "chinese", "language_level": []}, {"language": "mandarin", "language_level": ["proficiency"]}]}, "experience_required": {"duration": [], "field": []}}, {"job_id": "100003009024651", "location_code": "hk", "company": "The Hong Kong And China Gas Co Ltd", "job_title": "Temporary Assistant Supply Chain Systems Executive (1-year Contract)", "description": "Responsibilities:\n\nTo mainly handle e-commerce shipments, receive orders and handle general inquiry from customers by phone & email\nTo coordinate and support air export / import operation, sales section as per standard operation procedure\nTo maintain effective communication with customer and overseas agent (mainly group branch in Japan)\nTo enter data & prepare documentation for courier, air export / import shipment\n\nRequirements:\n\nForm 5 graduate or above\nAt least 2 years relevant experience in air freight forwarding & express\nExcellent communication skill\nMicrosoft excel and words processing, accurate typing skill\nGood command of spoken and written English and Chinese, Japanese speaker preferred\n\n\nWe offer competitive salary and benefits package including : 12-month salary, annual leave, medical scheme and MPF to right candidates.\n\n*All information collected will be used for recruitment purpose only.", "employment_types": ["Full Time", "Temporary"], "selling_points": ["Support sourcing initiatives and procurement pro", "Developing in-house application; internal process", "Involve in changes and innovations projects"], "locations": ["North Point"], "categories": ["Merchandising & Purchasing", "Others", "Procurement / Purchasing / Sourcing", "E-commerce", "Supply Chain"], "post_time": "2022-01-06T02:03:45Z", "salary": {"currency": null, "max": null, "min": null, "period": "monthly", "term": null}, "salary_visible": false, "title_keywords": ["executive", "temporary assistant"], "responsibilities": ["data", "coordinate", "communication", "maintain", "documentation"], "requirements": {"degrees": ["form 5"], "majors": [], "languages": ["japanese", "english", "chinese"], "language_level": ["good command"], "hard_skills": ["processing", "typing", "words", "microsoft excel"], "soft_skills": ["communication skill", "accurate"], "languages_combined": [{"language": "japanese", "language_level": ["good command"]}, {"language": "english", "language_level": ["good command"]}, {"language": "chinese", "language_level": ["good command"]}]}, "experience_required": {"duration": ["at least 2 years"], "field": ["relevant experience"]}}, {"job_id": "100003009028497", "location_code": "hk", "company": "Rich Fame International Limited", "job_title": "PHP Programmer", "description": "To align with our continued expansion, we are now looking for candidates with high calibre to join our vibrant 3PL warehouse operations team in our Shatin temperature and humidity-controlled warehouse:\n\nJob Responsibilities:\n\nSupport Warehouse Operations Manager to supervise a team of workers and manage all aspects of the daily warehouse operations including goods receiving, sorting, putaway, pick-n-pack, inventory update and record management\nSupport Warehouse Operations Manager to communicate with warehouse customer service team proactively, with an ability to make suggestions for constant improvements in operations productivity\nAble to make fast response to warehouse irregularities and offer possible alternatives/solutions; act as the bridge between Management and the whole warehouse team to timely report and escalate to Warehouse Manager when there is any irregularity.\nWork together with Warehouse Operations Manager to optimize employee workflow and collaborate with all warehouse workers\nAttentive to details on customer requirements and expectation; and execute customer and company\u2019s SOPs in a professional manner\nProvide regular reports, constantly monitor and fulfill KPIs required by the company and client.\n\n\u00a0Job Requirements:\n\nMin. 5 years relevant experience in warehouse & logistics operations and with preferably at least 2 years at supervisory or management level\nCandidate with less experience would be considered as Senior Supervisor / Supervisor\nAlways being customer-oriented and energetic to take initiatives\nGood leadership, planning, organizing, supervisory and people management skills\nPossess with a strong problem-solving mentalityand an ability to prioritize multiple tasks to meet tight warehouse project timelines\nPossess a valid Fork-lift Truck Operator License (Counter Balance Type)is a MUST\nWith hands-on experience with e-commerce logistics / pharma cold-chain logistics / robotic automation will be a plus\nBeing immediately available will be a definite advantage", "employment_types": ["Full Time", "Permanent"], "selling_points": ["2 to 3 years experience in programming", "Strong knowledge of DB design in MySQL", "Performance Bonus"], "locations": ["Kwai Fong"], "categories": ["Information Technology (IT)", "IT - Webmaster / SEO", "Transportation & Logistics", "Freight Forwarding", "E-commerce", "Supply Chain"], "post_time": "2022-01-07T02:26:04Z", "salary": {"currency": null, "max": null, "min": null, "period": "monthly", "term": null}, "salary_visible": false, "title_keywords": ["programmer"], "responsibilities": ["communicate with", "collaborate with", "management", "irregularities", "operations", "inventory", "professional manner", "monitor", "customer service", "reports", "sops", "kpis", "warehouse operations", "report"], "requirements": {"degrees": [], "majors": [], "languages": [], "language_level": [], "hard_skills": ["problem-solving", "plus", "e-commerce"], "soft_skills": ["multiple tasks", "problem-solving", "prioritize", "customer-oriented", "hands-on", "energetic", "leadership"], "languages_combined": []}, "experience_required": {"duration": ["5 years", "at least 2 years"], "field": ["supervisory", "management", "e-commerce", "logistics", "relevant experience"]}}, {"job_id": "100003009026060", "location_code": "hk", "company": "NAF Global Logistics Limited", "job_title": "Warehouse Operations Assistant Manager", "description": "(Working Location: 5.5 Days work in Yuen Long)\u00a0\n\nPosition Summary\n\nResponsible for effective management of stock allocation process, including proactively reviewing demand & supply simulations and executing customer behavior analysis. Collaborates across market functions to align on actions to mitigate risk and impact, while enhancing the business' ability to provide proactive communication to customers in need for out of stock situations.\n\nA day in the life of...\nResponsible for effective management of stock allocation process\nCollaborates across market functions to align on actions to mitigate OOS risk and impact\nManagement customer demand and ensure on time and in full delivery of physical goods to customers\nWhat will make you successful\n\n- Higher Diploma or above in related\u00a0disciplines\n\n- 1-3 years related experience in order fulfillment/processing, preferable FMCG\n\n-\u00a0Attention to details and\u00a0sensitive of data\n\n- Advanced Use of SAP and Microsoft Excel (Vlookup & Pivot Table)\n\n-\u00a0Fluent in spoken and written Cantonese,\u00a0Mandarin\u00a0and English", "employment_types": ["Full Time"], "selling_points": [], "locations": ["Shatin Area"], "categories": ["Transportation & Logistics", "Inventory / Warehousing", "E-commerce", "Supply Chain"], "post_time": "2022-01-06T07:19:29Z", "salary": {"currency": null, "max": null, "min": null, "period": "monthly", "term": null}, "salary_visible": false, "title_keywords": ["manager", "operations assistant"], "responsibilities": ["management", "data", "stock allocation", "analysis", "communication", "order fulfillment", "executing"], "requirements": {"degrees": ["higher diploma or above"], "majors": ["related disciplines"], "languages": ["cantonese", "english", "mandarin"], "language_level": ["fluent"], "hard_skills": ["sap", "analysis", "pivot table", "microsoft excel", "make", "vlookup", "processing"], "soft_skills": ["advanced", "responsible", "communication", "attention to details", "sensitive", "proactive"], "languages_combined": [{"language": "cantonese", "language_level": ["fluent"]}, {"language": "english", "language_level": ["fluent"]}, {"language": "mandarin", "language_level": ["fluent"]}]}, "experience_required": {"duration": ["1-3 years"], "field": ["related", "fmcg"]}}, {"job_id": "100003008952592", "location_code": "hk", "company": "Nestle Hong Kong Ltd", "job_title": "Order Fulfillment Officer", "description": "Key Responsibilities:\n\nDevelop strategic plans\u00a0and\u00a0further growth in business\u00a0of Express/Courier and Freight Forwarding\nCreate \u201cOne Stop Solution\u201d logistics service\u00a0for new or current clients\nPromoting and managing operations in e-commerce B2C service\nHandle and follow up\u00a0import and export inquiries\nReview and maintain business relationships with\u00a0local or overseas\u00a0clients and business partners\nAchieve\u00a0commitments and clients inquiries\nCooperate\u00a0with management and other divisions\n\nRequirements\n\n2-5 years in regional or global sales experience in Express/Courier or Freight Forwarding\nSelf-standing, proactive, interpersonal, analysis, negotiation, implementation and problem solving skills\nAble to act as a team player to execute the operation among multiple divisions\nAble to prepare reports\u00a0as agreed with customers\nAble to tackle problematic area and enhance service quality;\nNumeric analysis ability;\nMiddle user level of MS Excel and PowerPoint with good presentation skill;\nFluent in both written and spoken English and Mandarin, Japanese language is a plus but not necessarily required.\nImmediately available preferred\n\n**Less experience will be considered to non-managerial level\n\nWe offer 5 days work and attractive remuneration package including discretionary bonus and medical coverage to right candidate.\n\nAll information provided will be used for recruitment purpose only.", "employment_types": ["Full Time", "Permanent"], "selling_points": ["Challenge work and strong expectation for success", "Work hard play hard and energetic culture", "Bringing Nutrition, Health and Wellness to HK"], "locations": ["Yuen Long"], "categories": ["Transportation & Logistics", "Fulfillment", "Supply Chain", "E-commerce", "Supply Chain"], "post_time": "2022-01-05T03:46:03Z", "salary": {"currency": null, "max": null, "min": null, "period": "monthly", "term": null}, "salary_visible": false, "title_keywords": ["officer"], "responsibilities": ["management", "strategic plans", "operations", "review", "develop", "maintain", "logistics", "cooperate with"], "requirements": {"degrees": [], "majors": [], "languages": ["japanese", "english", "mandarin"], "language_level": ["fluent"], "hard_skills": ["presentation skill", "plus", "analysis", "powerpoint", "ms excel", "problem solving skills"], "soft_skills": ["presentation skill", "negotiation", "team player", "problem solving skills", "proactive", "interpersonal"], "languages_combined": [{"language": "japanese", "language_level": ["fluent"]}, {"language": "english", "language_level": ["fluent"]}, {"language": "mandarin", "language_level": ["fluent"]}]}, "experience_required": {"duration": ["2-5 years"], "field": ["managerial"]}}, {"job_id": "100003009026271", "location_code": "hk", "company": "Sagawa Express (H.K.) Company Limited", "job_title": "Sales Manager/Asst Sales Manager  - Express/Courier & Freight Forwarding (5 days work)", "description": "\u8077\u8cac\uff1a\n\n\n\u5c08\u8cac\u96f6\u552e\u5e97\u5167\u7684\u5009\u52d9\u5de5\u4f5c\n\u512a\u5316\u96f6\u552e\u5e97\u5167\u5916\u53ca\u5009\u52d9\u7684\u6574\u6f54\n\u8207\u5176\u4ed6\u96f6\u552e\u5e97/\u5167\u90e8\u90e8\u9580\u6e9d\u901a\u4ee5\u6574\u7406\u5eab\u5b58\n\u5982\u679c\u9700\u8981\uff0c\u9700\u652f\u63f4\u8cfc\u7269\u9928\u5834\u5167\u6d3b\u52d5\u548c\u5176\u4ed6\u81e8\u6642\u8077\u8cac\n\u8981\u6c42\uff1a\n\n\u4e2d\u5b78\u6587\u6191\u6216\u4ee5\u4e0a\u5b78\u6b77\n\u6700\u5c11\u67093\u5e74\u96f6\u552e\u884c\u696d\u76f8\u95dc\u7d93\u9a57\n\u6709\u8cac\u4efb\u611f\u3001\u6ce8\u91cd\u7d30\u7bc0\u3001\u53ca\u826f\u597d\u7684\u7d44\u7e54\n\u7cbe\u901a\u5ee3\u6771\u8a71\u53ca\u82f1\u8a9e\n\u719f\u6089\u5fae\u8edf\u8fa6\u516c\u61c9\u7528\u7a0b\u5e8f\uff0c\u4f8b\u5982 excel\u3001word\n\nResponsibilities:\nResponsible for stock room maintenance in our retail shop\nMaintaining shop and stock room tidiness\nCommunicate with other shops / internal stakeholders for stock arrangement\nSupport event and other ad hoc duties if required\n\nRequirements:\n\nSecondary Education or above\nAt least 3 year relevant experience in retail industry\nResponsible, detail-oriented and well-organized\nGood command of Cantonese and English\nKnowledge of Microsoft office applications, e.g. Excel, Word", "employment_types": ["Full Time", "Permanent"], "selling_points": ["Sales in Express / Courier and Freight Forwarding", "Provide one stop solution to client and ecommerce", "2-5 yrs of exp in regional and global forwarding"], "locations": ["Lai Chi Kok"], "categories": ["Sales, CS & Business Devpt", "Others", "E-commerce", "Supply Chain", "Others"], "post_time": "2022-01-06T07:49:43Z", "salary": {"currency": null, "max": null, "min": null, "period": "monthly", "term": null}, "salary_visible": false, "title_keywords": ["sales manager"], "responsibilities": ["communicate with", "ad hoc duties", "maintaining", "maintenance"], "requirements": {"degrees": ["secondary education"], "majors": [], "languages": ["cantonese", "english"], "language_level": ["good command"], "hard_skills": ["excel", "word", "microsoft office"], "soft_skills": ["well-organized", "responsible", "detail-oriented"], "languages_combined": [{"language": "cantonese", "language_level": ["good command"]}, {"language": "english", "language_level": ["good command"]}]}, "experience_required": {"duration": ["at least 3 year"], "field": ["retail industry", "relevant experience"]}}, {"job_id": "100003009025437", "location_code": "hk", "company": "K11 Concepts Limited", "job_title": "\u5009\u52d9\u5c08\u54e1 Stock Specialist (\u96f6\u552e Retail)", "description": "Manage procurement-related channels including Tmall Direct Import, Ali-Health, JD Direct, Instagram, Facebook) and logistics support to achieve sales\u00a0 objectives.\nCoordinate delivery schedules on a daily, weekly and monthly basis. Ensuring that all the sales channels have enough stock with optimal inventory level.\nAssist manager in developing product strategies, Identify and build brand salience and corporate images, to achieve business objectives,\nPlan and forecast promotion items for online retailers to drive sales and brand awareness.\n\n\u00a0REQUIREMENT\n\nExcellent communication skills of both spoken and written Mandarin a MUST\nGood at numbers and software knowledge on Microsoft Office.\nLogistics and procurement experience is a plus.\nSelf-motivated, eager to learn, good team player, but also able to work independently and under pressure to meet occasional tight schedules\nImmediate available is preferred\nNon Degree Tertiary and fresh graduate will also be considered", "employment_types": ["Full Time", "Permanent"], "selling_points": ["\u5c16\u6c99\u5634\u96f6\u552e\u5e97 Retail Store in Tsim Sha Tsui", "\u53ef\u5373\u6642\u4e0a\u73ed\u53ca\u5c0d\u6642\u88dd\u6709\u8208\u8da3\u512a\u5148 Immd available & passion in fashion", "\u64c1\u5ba2\u6236\u670d\u52d9\u53ca\u5009\u52d9\u7d93\u9a57\u512a\u5148CS exp and goods & supplies management"], "locations": ["Tsim Sha Tsui"], "categories": ["Transportation & Logistics", "Inventory / Warehousing", "Supply Chain", "E-commerce", "Supply Chain"], "post_time": "2022-01-06T04:31:20Z", "salary": {"currency": null, "max": null, "min": null, "period": "monthly", "term": null}, "salary_visible": false, "title_keywords": ["specialist"], "responsibilities": ["drive sales", "software", "schedules", "inventory", "developing", "coordinate", "communication", "logistics", "plan", "forecast", "facebook"], "requirements": {"degrees": ["degree", "fresh graduate"], "majors": [], "languages": ["mandarin"], "language_level": ["excellent"], "hard_skills": ["facebook", "plus", "microsoft office"], "soft_skills": ["communication skills", "self-motivated", "good team player", "work independently", "under pressure", "eager to learn"], "languages_combined": [{"language": "mandarin", "language_level": ["excellent"]}]}, "experience_required": {"duration": [], "field": ["logistics", "procurement"]}}, {"job_id": "100003009006934", "location_code": "hk", "company": "Yangtao International Company Limited", "job_title": "Digital Marketing Officer", "description": "The Role:\n\n\nSupport operation and maintenance of various supply chain related systems\nAssist in developing in-house application for facilitating internal process re-engineering\nInvolve in changes and innovations projects to ensure supply and improve end-to-end procurement process\nSupport sourcing initiatives and procurement processes, including evaluation of supplier performance and annual supplier review\nProvide assistance on tender preparation and contract review\nAssist in ad-hoc duties and projects as required\n\nThe Person:\n\nDegree in Supply Chain Management, Logistics, Industrial Engineering, or related disciplines\nPreferably with 1-2 years\u2019 relevant experience in process improvement, business re-engineering or operation digitalization\nProficiency in PC applications such as Access, Excel and Word; SAP knowledge is preferable\u00a0\nKnowledge in Microsoft database-related applications, such as Access, SharePoint, PowerApps and PowerBI will be an advantage\nProactive, self-motivated and able to work independently\nGood command of written and spoken English and Chinese\n\nApplication with full details stating current and expected salary to: APPLY NOW\n\nPlease quote the reference number (CSAD/ASCSE/JDB01/22) in your application.\n\n(All personal data provided will be treated in strict confidence and used for recruitment purposes only.)", "employment_types": ["Full Time", "Part Time", "Permanent"], "selling_points": ["5 days work, Double-pay, Bank holidays", "Good knowledge of photoshop is plus", "Immediate available is preferred"], "locations": ["Wong Tai Sin Area"], "categories": ["Merchandising & Purchasing", "Procurement / Purchasing / Sourcing", "Marketing / Public Relations", "Digital Marketing", "E-commerce", "Supply Chain"], "post_time": "2022-01-06T16:07:42Z", "salary": {"currency": "HKD", "max": 24999, "min": 17000, "period": "monthly", "term": null}, "salary_visible": true, "title_keywords": ["digital marketing officer"], "responsibilities": ["management", "maintenance", "ad-hoc duties", "procurement processes", "systems", "review", "developing", "logistics", "recruitment", "tender preparation", "evaluation", "database", "personal data", "provide assistance", "re-engineering"], "requirements": {"degrees": ["degree"], "majors": ["related disciplines", "engineering"], "languages": ["english", "chinese"], "language_level": ["good command"], "hard_skills": ["excel", "sap", "maintenance", "word", "pc applications"], "soft_skills": ["self-motivated", "confidence", "work independently", "ad-hoc duties", "proactive"], "languages_combined": [{"language": "english", "language_level": ["good command"]}, {"language": "chinese", "language_level": ["good command"]}]}, "experience_required": {"duration": ["1-2 years"], "field": ["operation", "business", "relevant experience", "engineering"]}}, {"job_id": "100003009018157", "location_code": "hk", "company": "JAC Recruitment Hong Kong Co., Limited", "job_title": "E-commerce Executive (Japanese Trading Company)", "description": "Job Description\n\nWHY WORK WITH US?\n\nAre you someone with passion for fashion and eyewear who is looking to fast track your career? Come join our unique and multinational team and be a part of a growing digital company.\n\nA world Leading designer eyewear e-retailer (smartbuyglasses.com)\nMulticultural team representing over 30 nationalities\nFast growing, dynamic and young and passionate\u00a0\u00a0\n\nThe Position\n\nWe are hiring a Logistics Assistant to participate in our warehouse operations and activities. Logistics Assistant responsibilities include prepare shipping documents, picking and scanning orders. The goal is to increase efficiency, profitability and customer satisfaction.\n\nWe are looking for a passionate professional who enjoys wearing multiple hats. Comfortable in handling a wide range of operational and administrative duties and able to work independently with little or no supervision. Well organized, flexible and enjoy the challenges of supporting an office of diverse people.\n\nResponsibilities\n\nPrepare and complete orders for delivery or pickup according to schedule\u00a0\nReceive and process warehouse stock products\u00a0\nPerform inventory controls and keep quality standards high for audits\nKeep a clean and safe working environment and optimize space utilization\nReport any discrepancies\nCommunicate and cooperate with supervisors and coworkers\nFollow quality service standards and comply with procedures, rules and regulations\n\nThe Candidate\n\nHigh School or diploma holder\n1 year experience working in logistics/warehouse function\nFluent in both spoken and written English and Cantonese\nProficient in Microsoft Word and Excel\nMust be detail oriented, efficient and self-motivated\nAble to work under pressure with strong sense of responsibility\nGreat team player with excellent communication skills\n\nCompany Profile\n\nSmartBuyGlasses Optical Group, operated under Motion Global Ltd., is the world\u2019s leading designer eyewear e-retailer. With operations across Asia Pacific, Europe and the Americas, SmartBuyGlasses has become the market leader in over 30 countries worldwide. With over 160 employees, we retail the world\u2019s best eyewear brands including Ray-Ban, Tom Ford, Gucci and many more. SmartBuyGlasses has a young, international and entrepreneurial culture that promotes fast career progression and self-development. Passionate and effective employees are usually promoted quickly to managerial positions, operating teams with high degrees of responsibility.\n\nOffice Location\n\nKennedy Town, 1 minute from MTR station\n\nWhat We Offer\n\nCompetitive salary\nMedical coverage + 13th Salary\nFast-paced, dynamic and multicultural work environment\nGreat career development opportunities and comprehensive training programme", "employment_types": ["Full Time", "Permanent"], "selling_points": ["Japanese company", "Good location", "Start up business"], "locations": ["Admiralty"], "categories": ["E-commerce", "Marketing - Brand / Product Management", "Product Management / Business Analyst", "Supply Chain"], "post_time": "2022-01-04T02:57:54Z", "salary": {"currency": null, "max": null, "min": null, "period": "monthly", "term": null}, "salary_visible": false, "title_keywords": ["executive"], "responsibilities": ["shipping documents", "regulations", "operations", "quality", "logistics assistant", "communication", "service standards", "inventory controls", "cooperate with", "work under pressure", "scanning", "teams", "logistics", "schedule", "report", "procedures", "administrative duties", "audits", "warehouse operations"], "requirements": {"degrees": ["diploma holder", "high school"], "majors": [], "languages": ["cantonese", "english"], "language_level": ["fluent"], "hard_skills": ["clean", "excel", "no", "microsoft word", "goal", "safe", "dynamic", "tom"], "soft_skills": ["passionate", "flexible", "work independently", "efficient", "self-motivated", "communication skills", "passion for", "sense of responsibility", "detail oriented", "well organized", "unique", "diverse", "dynamic", "team player", "work under pressure"], "languages_combined": [{"language": "cantonese", "language_level": ["fluent"]}, {"language": "english", "language_level": ["fluent"]}]}, "experience_required": {"duration": ["1 year"], "field": ["logistics"]}}, {"job_id": "100003009025348", "location_code": "hk", "company": "Hasbro Far East Limited", "job_title": "Manager Trade Compliance", "description": "This role is responsible for implementing and coordinating import and export compliance programs by applying technical expertise, oversight and operational support for customs counterparts located across the Asia and Asia-Pacific (\u201cAPAC\u201d) region. This team member works in conjunction with the other members of the Global Trade Compliance Team under the support and directive of the Director Global Trade Compliance to apply tools and procedures to streamline and enhance best practices across all global affiliate markets.\n\nThis role will serve as the lead person for questions and issue resolution associated with brokerage operations for the APAC region; applying specialized knowledge to solve a wide range of complex issues with a focus on ensuring compliance with trade laws and regulations relevant to our business. This team member will also be responsible for the oversight and management of APAC regional requests for proposals (RFPs) to manage the continued development and implementation of Hasbro\u2019s internal global trade compliance program alongside the Director, Global Trade Compliance as well as other Global Trade Compliance Team members.\n\nAs the regional lead for APAC Trade Compliance, this role is responsible for serving as the functional representative leading the development and implementation of the strategic trade model across our (11) APAC countries where Hasbro is the importer and/or exporter of record; establishing and defining trade management and customs compliance capabilities across our supply chain in support of Hasbro\u2019s commercial business efforts. The successful candidate will demonstrate an ability to operate with situations involving ambiguity and complexity, anticipate potential risks, develop corresponding contingency plans, and can act proactively to support strategic and complex decisions.\n\nThis person interfaces with internal / external customers, foreign subsidiaries, distributors, vendors, brokers and carriers to ensure compliance with all applicable import / export regulations.\n\nStrategy / Continuous Improvement\u00a0\u00a0\u00a0\u00a0\u00a0\u00a0\u00a0\u00a0\u00a0\u00a0\u00a0\u00a0\u00a0\u00a0\u00a0\u00a0\u00a0\u00a0\u00a0\u00a0\u00a0\u00a0\u00a0\u00a0\u00a0\u00a0\u00a0\u00a0\u00a0\u00a0\u00a0\u00a0\u00a0\u00a0\u00a0\u00a0\u00a0\u00a0\u00a0\u00a0\u00a0\u00a0\u00a0\u00a0\u00a0\u00a0\u00a0\u00a0\u00a0\u00a0\u00a0\u00a0\u00a0\u00a0\u00a0\u00a0\u00a0\u00a0\u00a0\u00a0\u00a0\u00a0\u00a0\u00a0\u00a0\u00a0\u00a0\u00a0\u00a0\u00a0\u00a0\u00a0\u00a0\u00a0\u00a0\u00a0\u00a0\u00a0\u00a0\u00a0\u00a0\u00a0\u00a0\u00a0\u00a0\u00a0\u00a0\u00a0\u00a0\u00a0\u00a0\u00a0\u00a0\u00a0\u00a0\u00a0\u00a0\u00a0\u00a0\u00a0\u00a0\u00a0\u00a0\n\nManage the company's trade compliance program to ensure a best practices program consistent with local laws and regulations for the various countries in the HAPM region and other trade-related requirements.\nDrive resolutions to complex issues that impact the team's efficiencies, conducting root cause analyses and developing roadmaps to resolve.\nStay abreast of regulatory changes related to trade compliance and provide regulatory interpretation and implementation guidance to impacted geographies and businesses.\nDevelop and maintain an effective regional training program to improve trade compliance competency across local markets.\nConduct risk & compliance trade management framework design to promote/maintain shared practices and operational effectiveness.\nPartners\u00a0 \u00a0 \u00a0 \u00a0 \u00a0 \u00a0 \u00a0 \u00a0 \u00a0 \u00a0 \u00a0 \u00a0 \u00a0 \u00a0 \u00a0 \u00a0 \u00a0 \u00a0 \u00a0 \u00a0 \u00a0 \u00a0 \u00a0 \u00a0 \u00a0 \u00a0 \u00a0 \u00a0 \u00a0 \u00a0 \u00a0 \u00a0 \u00a0 \u00a0 \u00a0 \u00a0 \u00a0 \u00a0 \u00a0 \u00a0 \u00a0 \u00a0 \u00a0 \u00a0 \u00a0 \u00a0 \u00a0 \u00a0 \u00a0 \u00a0 \u00a0 \u00a0 \u00a0 \u00a0 \u00a0 \u00a0 \u00a0 \u00a0 \u00a0 \u00a0 \u00a0 \u00a0 \u00a0 \u00a0 \u00a0 \u00a0 \u00a0 \u00a0 \u00a0 \u00a0 \u00a0 \u00a0 \u00a0 \u00a0 \u00a0 \u00a0 \u00a0 \u00a0 \u00a0 \u00a0 \u00a0 \u00a0 \u00a0 \u00a0\n\nLead team efforts to develop relationships with strategic partners and 3PL\u2019s which standardize processes and provide a reliable, responsive and cost-efficient supply chain supporting Hasbro\u2019s APAC commercial business efforts.\nCollaborate with team members and Hasbro Affiliate markets to evaluate opportunities to streamline and standardize trade compliance best practices.\nActively engage and consult with the Director of Global Trade Compliance on key initiatives; effectively identify and communicating strategic operational gaps.\nWork with legal and internal audit to implement policies and practices that reduce risk associated with regulatory and governmental requirements that impact the flow of goods.\u00a0\nCollaborate with geographies or countries to evaluate and implement opportunities to maximize efficiencies and benefits realized from available duty drawback, tariff preference programs, free trade zones or similar types of programs.\nConduct and oversee periodic assessments to ensure compliance with applicable trade laws and policies and, as applicable, coordinate with internal audit to ensure the implementation and documentation of corrective and preventative measures.\nImplement a standardized process for customs brokerage relationship management including preparing and hosting quarterly business reviews to assess performance, challenges and successes\nPeople\u00a0 \u00a0 \u00a0 \u00a0 \u00a0 \u00a0 \u00a0 \u00a0 \u00a0 \u00a0 \u00a0 \u00a0 \u00a0 \u00a0 \u00a0 \u00a0 \u00a0 \u00a0 \u00a0 \u00a0 \u00a0 \u00a0 \u00a0 \u00a0 \u00a0 \u00a0 \u00a0 \u00a0 \u00a0 \u00a0 \u00a0 \u00a0 \u00a0 \u00a0 \u00a0 \u00a0 \u00a0 \u00a0 \u00a0 \u00a0 \u00a0 \u00a0 \u00a0 \u00a0 \u00a0 \u00a0 \u00a0 \u00a0 \u00a0 \u00a0 \u00a0 \u00a0 \u00a0 \u00a0 \u00a0 \u00a0 \u00a0 \u00a0 \u00a0 \u00a0 \u00a0 \u00a0 \u00a0 \u00a0 \u00a0 \u00a0 \u00a0 \u00a0 \u00a0 \u00a0 \u00a0 \u00a0 \u00a0 \u00a0 \u00a0 \u00a0 \u00a0 \u00a0\n\nProvide motivation and direction on continuous improvement initiatives including streamlining processes and managing the implementation of key performance indicators.\nEnsure effective integration of global trade compliance processes and standards within Asia and Pacific markets\nBuild and maintain exceptional relationships across affiliate/regional/global teams through integration of trade champions to ensure operational success and business success; Manage relationships with regional and local trade authorities.\nEffectively manage and influence team and cross-functional teams to produce high-quality outputs\n\nEducation required:\n\nBachelor\u2019s degree, preferably in Supply Chain, International business or associated discipline.\n\nExperience required:\n\n5-7+ years\u2019 experience within supply chain operations and/or trade compliance function.\n\nKnowledge/Skills required:\n\nExpert knowledge and understanding of global trade laws and or similar regulatory agency requirements applicable to trade in applicable international geographies.\nStrong project management skills.\nAbility to properly interpret and strategically apply government regulations and related technical requirements to global business and trade scenarios.\nA highly motivated individual with strong interpersonal, leadership, organizational and project management skills and proven problem solving and decision-making capabilities.\nStrong cross-functional collaboration skills and ability to influence others through demonstrated expertise in a direct and matrix environment.\nDemonstrated ability to work effectively and efficiently in a dynamic global team environment, across all levels of middle and upper management, with minimal supervision and to recognize the need for and effectively solicit input from relevant stakeholders while managing multiple projects and their deadlines.\nExcellent analytical, written and oral communication and presentation skills and the ability to clearly convey relevant information to a broad spectrum of global audiences.", "employment_types": ["Full Time"], "selling_points": [], "locations": ["Tsim Sha Tsui"], "categories": ["E-commerce", "Supply Chain"], "post_time": "2022-01-06T04:12:31Z", "salary": {"currency": null, "max": null, "min": null, "period": "monthly", "term": null}, "salary_visible": false, "title_keywords": ["manager"], "responsibilities": ["regulations", "collaborate with", "operational support", "internal audit", "brokerage", "operations", "quality", "design", "communication", "maintain", "plans", "compliance", "teams", "implementation", "developing", "develop", "resolution", "guidance", "management", "cost", "procedures", "coordinate with", "documentation", "cross-functional teams", "policies", "ensure compliance", "evaluate", "project management", "multiple projects"], "requirements": {"degrees": ["degree", "bachelor"], "majors": ["international business"], "languages": [], "language_level": [], "hard_skills": ["integration", "import and export", "problem solving", "project management", "dynamic", "documentation", "focus"], "soft_skills": ["efficient", "work effectively", "oral", "responsible", "project management skills", "organizational", "problem solving", "motivated individual", "communication", "dynamic", "presentation skills", "reliable", "leadership", "focus", "team member", "responsive", "interpersonal"], "languages_combined": []}, "experience_required": {"duration": ["7+ years"], "field": ["supply chain", "compliance"]}}, {"job_id": "100003009022871", "location_code": "hk", "company": "Walters People (HK)", "job_title": "Assistant Supply Chain Manager (Fragrance)", "description": "Our client is a leading European Cosmetic brand with global presence within the local market. To cope with the continuous expansion, their Hong Kong office is currently seeking to hire a high calibre supply chain professional to join their operation in HK.\n\nJob descriptions\n\nHandling whole supply chain process, from forecast and demand planning to monthly re-order calculation and stock allocation\nDemand plan estimation and follow up fulfilment rate with Central Distribution Centre\nAnalyse demand, loading and capacity on a regular basis to flag and recommend key actions by the various teams of sales and operations team member\nCollecting information from the brand and product performance analysis\nMonitor retail distribution, imply store replenishment parameters\n\n\n\nJob requirement\n\nDegree holder in Supply Chain and Business Management or any related discipline\nAt least 5-6 years relevant experience preferably from FMCG or retail\nStrong interpersonal skill, detail minded and self-motivated\nProficient in MS Office including Excel & Word\nFluency in English and Chinese is a must", "employment_types": ["Full Time", "Permanent"], "selling_points": ["European leading cosmetic brand", "Demand planning, stock control, SAP", "CBD working location"], "locations": ["Not Specified"], "categories": ["Transportation & Logistics", "Supply Chain", "E-commerce", "Marketing - Brand / Product Management", "Supply Chain"], "post_time": "2022-01-05T06:45:27Z", "salary": {"currency": "HKD", "max": 34999, "min": 30000, "period": "monthly", "term": null}, "salary_visible": true, "title_keywords": ["assistant supply chain manager"], "responsibilities": ["stock allocation", "demand planning", "operations", "teams", "analysis", "monitor", "replenishment", "forecast", "plan", "supply chain process", "analyse"], "requirements": {"degrees": ["degree holder"], "majors": ["business"], "languages": ["english", "chinese"], "language_level": ["fluency"], "hard_skills": ["business management", "excel", "word", "ms office"], "soft_skills": ["self-motivated", "interpersonal skill"], "languages_combined": [{"language": "english", "language_level": ["fluency"]}, {"language": "chinese", "language_level": ["fluency"]}]}, "experience_required": {"duration": ["at least 5-6 years"], "field": ["fmcg", "relevant experience", "retail"]}}, {"job_id": "100003009023782", "location_code": "hk", "company": "Simbans Limited", "job_title": "Logistic Assistant", "description": "Looking for an entry level position for a Logistic assistant.\n\nJob Responsibilities:\n\nReceive shipments from Vendors\nCreate Shipping Labels and documents.\nHelp with Pack and Label goods\nCoordinate with FedEx, DHL and other Shipping company\nManage Inventory\nQualifications:\nMust have a high school diploma or higher\nBasic proficiency in spoken English, Cantonese and Mandarin\nBenefits:\n\nDouble Pay and Bonus\n2 Weeks annual leave and sick leaves\nPay Negotiable\nRecent graduates are welcome", "employment_types": ["Full Time", "Permanent"], "selling_points": ["Double Pay and Bonus", "2 Weeks annual leave and sick leaves", "Pay Negotiable"], "locations": ["Tsuen Wan Area"], "categories": ["E-commerce", "Supply Chain"], "post_time": "2022-01-05T09:47:31Z", "salary": {"currency": "HKD", "max": 16999, "min": 11000, "period": "monthly", "term": null}, "salary_visible": true, "title_keywords": ["assistant"], "responsibilities": ["inventory", "shipping", "coordinate with"], "requirements": {"degrees": ["high school diploma"], "majors": [], "languages": ["cantonese", "english", "mandarin"], "language_level": ["proficiency", "basic"], "hard_skills": ["basic"], "soft_skills": [], "languages_combined": [{"language": "cantonese", "language_level": ["proficiency", "basic"]}, {"language": "english", "language_level": ["proficiency", "basic"]}, {"language": "mandarin", "language_level": ["proficiency", "basic"]}]}, "experience_required": {"duration": [], "field": []}}, {"job_id": "100003009014622", "location_code": "hk", "company": "A.S. Watson Retail (HK) Limited", "job_title": "Supply Chain Officer (Group level, warehouse/DC projects for Asia)", "description": "Come and join a Winning Team\n\n\u00a0We are Awesome !\n\nWhy Should You Join Us?\n\n\u00a0At ASW, we believe in our people, in teamwork and the importance of your personal growth.\u00a0If you are looking for the opportunity to join our award-winning international family with 16,200+ stores across 29 markets in Asia and Europe, the ASW family welcomes you\u2026\u00a0\u00a0#BePartofMORE\n\n\u00a0You can enjoy :\u00a0\u00a0\u00a0\n\nComprehensive Medical and Life insurance coverage, including your spouse and children!\nProfessional training and career advancement opportunities!\nAttractive ACCA and CPA Australia Recognized Employer Program for F&A talents!\nExclusive company pension schemes!\u00a0 Marriage, Maternity and Paternity Leave!\nConvenient office location, less than 5 min. walk from MTR!\nContemporary workplace with Onsite Clinic, Lactation Rooms, free drinks and chill out areas!\nWell-equipped Gym inside our office building, plus fitness and interest class packages!\nFree round-trip lunchtime shuttle bus services to Shatin!\nExclusive shopping discount, Bazaar Sales for our people only!\n\nRole Purpose:\nWorking in the Group Supply Chain Department, this position is responsible for supporting the managers in roll out of various supply chain projects in our Asia markets.\n\nA typical day in this Role:\u00a0\n\nSupport the managers of Group Supply Chain to coordinate with business units, Group IT in system enhancement or operation optimization projects\nSupport the delivery of new initiatives and operational projects\u00a0to\u00a0business units, reinforce best practice and compliance to the Retail Operation Standards in the areas of Supply Chain and Logistics\nFollow up on regional KPIs and assist to make improvements through constant KPI analysis, process reviews, retraining and reinforcement\nAssist in formulating & documenting supply chain best practice\n\n\u00a0This job is a good fit for You if:\u00a0\u00a0\n\nYou have keen interest to develop your career in supply chain management\nYou enjoy communication with BUs in different markets;\nYou would like to have regional exposure\nYou love to have travel to different BUs for widening your horizon\n\n\u00a0What we look for:\u00a0\u00a0\n\nUniversity graduate in\u00a0Supply Chain Management, Logistics Management, Industrial Engineering or\u00a0similar\u00a0discipline\nMin. 2-3 years experiences with supply chain / distributions operation and logistics provider; FMCG industry is a plus.\nBusiness analysis (e.g BI tools, Tableau or Excel), project coordination and system knowledge experiences\nFluency in English and Chinese is a must; with knowledge of Mandarin would be an asset\nBe proactive, self-disciplined and be able to work under minimal supervision\nFlexible on travel to Asia countries\n\nWhat is holding you back?\n\n\u00a0Don\u2019t miss out on this great chance to shape Your life!\n\n\u00a0\u00a0Apply now!\u00a0\n\nInterested parties, please send your resume with current and expected salary package to our Company\u2019s email.\u00a0\u00a0\n\nWe are an equal opportunity employer and welcome applications from all qualified candidates. The information provided will be treated in strict confidence and be used only for consideration of your application for relevant/ similar posts within the A.S. Watson Group.", "employment_types": ["Full Time", "Permanent"], "selling_points": ["Asia supply chain projects", "Data analysis, Warehouse / DC knowledge", "Travel to BUs in Asia"], "locations": ["Shatin Area"], "categories": ["Transportation & Logistics", "Inventory / Warehousing", "Supply Chain", "E-commerce", "Supply Chain"], "post_time": "2022-01-03T03:49:33Z", "salary": {"currency": null, "max": null, "min": null, "period": null, "term": null}, "salary_visible": false, "title_keywords": ["supply chain officer"], "responsibilities": ["management", "project coordination", "analysis", "compliance", "coordinate with", "develop", "communication", "logistics", "business analysis", "kpis", "insurance"], "requirements": {"degrees": ["university graduate"], "majors": ["engineering"], "languages": ["english", "chinese", "mandarin"], "language_level": ["fluency"], "hard_skills": ["excel", "acca", "plus", "bi", "analysis", "fmcg industry", "tableau", "chill", "cpa", "make"], "soft_skills": ["flexible", "responsible", "keen", "teamwork", "communication", "comprehensive", "coordination", "proactive"], "languages_combined": [{"language": "english", "language_level": ["fluency"]}, {"language": "chinese", "language_level": ["fluency"]}, {"language": "mandarin", "language_level": []}]}, "experience_required": {"duration": ["2-3 years"], "field": ["supply chain", "operation", "logistics"]}}, {"job_id": "100003009024188", "location_code": "hk", "company": "RecruitFirst Limited", "job_title": "Project Warehouse Coordinator (up to 16k)", "description": "We are hiring for a Project Warehouse Coordinator to join us in an exciting ecommerce BPO project in HK\n\nJob Scope\n\nPlan and manage the allocation of manpower resources\u00a0\nAssist to ensure any manpower backfill services are completed\nDesign policies and processes to enhance productivity and minimise labor costs\nAssist to create and review SOP for logistics outsourcing activities\nCoordinate with internal/external parties to assist daily operations\nSupport admin duties\nJob Requirements\n\nHigher Diploma and above\n2 years logistics and/or recruitment experience\nProficient in Excel\nGood in English & Chinese\n\n\n", "employment_types": ["Full Time", "Contract"], "selling_points": [], "locations": ["Not Specified"], "categories": ["Admin & HR", "Recruitment / Executive Search", "Transportation & Logistics", "Supply Chain", "E-commerce", "Supply Chain"], "post_time": "2022-01-05T11:17:54Z", "salary": {"currency": "HKD", "max": 19999, "min": 14000, "period": "monthly", "term": null}, "salary_visible": true, "title_keywords": ["coordinator"], "responsibilities": [], "requirements": {"degrees": ["diploma"], "majors": [], "languages": ["english", "chinese"], "language_level": ["good"], "hard_skills": ["excel"], "soft_skills": [], "languages_combined": [{"language": "english", "language_level": ["good"]}, {"language": "chinese", "language_level": ["good"]}]}, "experience_required": {"duration": ["2 years"], "field": ["recruitment", "logistics"]}}, {"job_id": "100003009025194", "location_code": "hk", "company": "ConnectedGroup Limited", "job_title": "Indirect Procurement Manager , APAC (Marketing & Media)", "description": "ConnectedGroup is partnering with a well-known multinational consumer goods company to search for a Regional Strategic Procurement Manager.\n\nKey responsibilities:\n\n- Look after specifically the Marketing & Media category and cover sub-categories across both Digital Marketing and Offline including Creative / Marketing / Advertising Agencies, Social Influencers, Print, Premium, etc.\n- Oversee all 10+ markets in the Asia Pacific region\n- Responsible for Internal stakeholder management - maintaining and enhancing relationships with people on your work\n- Drive category strategy development, aligning global, regional, and local strategies, developing and refining supplier negotiation strategies, etc.\n\nKey requirements:\n\n- Experienced in managing Marketing procurement\n- Ideally have a background in the Consumer Goods, Retails or FMCG industries (not mandatory)\n- Strong understanding and knowledge of the major sub-categories within Marketing\n- Excellent track record of working effectively with various stakeholders and end-users, and excellent negotiation, persuasion, communication, and interpersonal skills.\n- Proficient in English is a must", "employment_types": ["Full Time", "Permanent"], "selling_points": ["Leading global consumer goods company", "Marketing & media procurement experience required", "Covering all 10+ markets in APAC"], "locations": ["Not Specified"], "categories": ["Others", "Others", "E-commerce", "Supply Chain"], "post_time": "2022-01-06T03:47:27Z", "salary": {"currency": null, "max": null, "min": null, "period": "monthly", "term": null}, "salary_visible": false, "title_keywords": ["manager"], "responsibilities": ["management", "advertising", "maintaining", "developing", "digital marketing"], "requirements": {"degrees": [], "majors": [], "languages": ["english"], "language_level": ["proficient"], "hard_skills": [], "soft_skills": ["communication", "interpersonal skills", "negotiation"], "languages_combined": [{"language": "english", "language_level": ["proficient"]}]}, "experience_required": {"duration": [], "field": []}}, {"job_id": "100003009019170", "location_code": "hk", "company": "Crane Worldwide Logistics Hong Kong Limited", "job_title": "Business Support Executive, eCommerce, South China & HK", "description": "Our client, a Japanese Trading company is looking for candidates\u00a0E-commerce Executive roles.\u00a0\n\nResponsibilities:\n\n\nSupporting daily operations of ESHOP\nManage product listings, inventory & stock management , research and other sales supporting tasks\nManage daily online shop orders to ensure a smooth order delivery process\u00a0\nCommunicate with Japan HQ\n\n\nRequirements:\n\n\nMinimum 1-2 years of solid experiences in operating e-commerce platforms in retail industry is preferred\n\nCantonese and English *Japanese skill would be highly advantage\n\nInterested candidates, kindly send your detailed resume in MS Word including:\n\n\n1) Expected salary\n2) Current and last drawn salaries\n3) Reason for leaving current and past employments\n\u00a0\ndirectly to:\u00a0jac.hk\u00a0@jac-recruitment.com and CC to:\u00a0akihisa.watanabe\u00a0@jac-recruitment.com\n\nPersonal data collected will be used for employment-related purpose only. We regret to inform that only shortlisted candidates will be notified, thank you", "employment_types": ["Full Time", "Permanent"], "selling_points": ["5 days work", "Medical & dental scheme", "competitive remuneration package and benefits"], "locations": ["Wong Tai Sin Area"], "categories": ["Transportation & Logistics", "Freight Forwarding", "E-commerce", "Product Management / Business Analyst", "Supply Chain"], "post_time": "2022-01-04T08:34:36Z", "salary": {"currency": null, "max": null, "min": null, "period": "monthly", "term": null}, "salary_visible": false, "title_keywords": ["executive"], "responsibilities": ["communicate with", "sales supporting tasks", "daily online shop orders", "order delivery process", "inventory & stock management", "product listings", "supporting daily operations"], "requirements": {"degrees": [], "majors": [], "languages": ["cantonese", "japanese", "english"], "language_level": ["advantage"], "hard_skills": ["e-commerce"], "soft_skills": [], "languages_combined": [{"language": "cantonese", "language_level": ["advantage"]}, {"language": "japanese", "language_level": ["advantage"]}, {"language": "english", "language_level": ["advantage"]}]}, "experience_required": {"duration": ["minimum 1-2 years"], "field": ["retail industry", "e-commerce"]}}, {"job_id": "100003009016047", "location_code": "hk", "company": "Hypebeast Hong Kong Limited", "job_title": "Inventory Assistant", "description": "To cope with our business development and expansion in eCommerce, our Hong Kong office is now inviting high caliber candidate to join us for the position of\u00a0Business Support Executive, eCommerce, South China & HK\n\u00a0\n\u00a0\nThe job\u00a0holder will assisting the Head of eCommerce, South China & HK, on the support all commercial activities and\u00a0client management of the eCommerce business for South China & HK markets through the following major responsibilities including but not limited to:\n\n\u00a0Duties & Responsibilities:\n\u00a0\nProvide support on client onboarding, system training, shipment tracking\u00a0and billing.\nHandle clients' enquiries and resolve complaint in timely and professional manner.\nIdentify clients' needs and new opportunities throughout regular communication with client.\nAdminister and maintain eCommerce portal.\nAssist in analyzing and monitoring performance and shipping trend of clients, and preparing monthly report to management.\n\nRequirements:\n\nDegree holder in Business Administration, Supply Chain Management or related discipline.\nMinimum 2 years' working experience, preferably in eCommerce industry.\nTeam player with good communication and problem-solving skills, and attention to details.\nPatient and proactive to build relationship with customers.\nFamiliarized with MS Office and data analytics applications and methodologies.\nGood command of both spoken and written English, Mandarin and Chinese\n\nWORKING CONDITIONS\n\nThe office working environment is generally favorable. We offer attractive remuneration and benefits including,\u00a05 days work per week, annual leave, discretionary bonus, medical & dental scheme and 13th payroll. Our office is located in Diamond Hill.", "employment_types": ["Full Time"], "selling_points": ["Recent graduate with positive attitude are welcome", "Global e-commerce with international customers", "Creative, young and energetic team members"], "locations": ["Tsuen Wan Area"], "categories": ["Transportation & Logistics", "Inventory / Warehousing", "E-commerce", "Supply Chain"], "post_time": "2022-01-03T08:10:27Z", "salary": {"currency": null, "max": null, "min": null, "period": "monthly", "term": null}, "salary_visible": false, "title_keywords": ["assistant"], "responsibilities": ["provide support", "shipping", "management", "monitoring", "professional manner", "communication", "maintain", "monthly report", "tracking"], "requirements": {"degrees": ["degree holder"], "majors": ["business administration"], "languages": ["english", "chinese", "mandarin"], "language_level": ["good command"], "hard_skills": ["problem-solving skills", "data analytics", "scheme", "ms office"], "soft_skills": ["patient", "communication", "attention to details", "problem-solving skills", "team player", "proactive"], "languages_combined": [{"language": "english", "language_level": ["good command"]}, {"language": "chinese", "language_level": ["good command"]}, {"language": "mandarin", "language_level": ["good command"]}]}, "experience_required": {"duration": ["minimum 2 years"], "field": ["ecommerce"]}}, {"job_id": "100003009015311", "location_code": "hk", "company": "Taste of Asia Group Limited", "job_title": "E-commerce Specialist", "description": "HBX (previously known as HYPEBEAST Store) commenced business in May 2012, is a one-stop news source for internet-savvy fashion enthusiasts and cultural tastemakers. HBX is the global e-commerce platform that targets male and female online shoppers between the age of 18 and 35, and primarily sells third-party branded clothing, shoes and accessories to customers.\n\nResponsibilities:\n\nExecute inventory control measures to ensure the company minimizes stock holding and maximizes stock system and paperwork accuracy.\nParticipate in perpetual inventory stock taking and inventory accuracy checks.\nResponsible for all product measurement and data entry for product pages maintenance.\nProvide merchandising support to the Studio with photo shoots.\nEnsure all inbound and outbound goods are properly unpacked, labeled and accounted for.\nThere is a possibility of working on weekends during busy periods.\nCover Saturday shifts and work on ad-hoc projects.\nRequirements:\n\nF.7 Diploma and/or higher educations; fresh graduates with passion are welcome.\nPossess strong analytical and problem solving skills.\nPossess a high level of attention to detail.\nSelf-starter, willingness to learn, improve and adapt.\nPossess good verbal and written communication skills.\nAble to lift boxes up to 25lb.\nIf you think you\u2019ve got what it takes, please provide your cover letter, CV, translation samples and expected salary.\n\nThis role is located and based in Hong Kong. Candidate must be eligible to work in Hong Kong.\n\nPersonal data collected is for recruitment purpose only.", "employment_types": ["Full Time"], "selling_points": ["Five-day work week", "Medical & dental allowance", "Performance bonus"], "locations": ["Wong Tai Sin Area"], "categories": ["Information Technology (IT)", "Software Development", "E-commerce", "Supply Chain", "Others"], "post_time": "2022-01-03T06:30:18Z", "salary": {"currency": null, "max": null, "min": null, "period": "monthly", "term": null}, "salary_visible": false, "title_keywords": ["specialist"], "responsibilities": ["maintenance", "data entry", "inventory", "measurement", "merchandising", "inventory control", "ad-hoc projects"], "requirements": {"degrees": ["diploma"], "majors": [], "languages": [], "language_level": [], "hard_skills": ["translation", "problem solving skills"], "soft_skills": ["communication skills", "analytical and problem solving skills", "attention to detail"], "languages_combined": []}, "experience_required": {"duration": [], "field": []}}, {"job_id": "100003009019397", "location_code": "hk", "company": "Sky City Y2K Limited", "job_title": "Warehouse Operations \u5009\u52d9\u54e1 (\u5168/\u517c\u8077)", "description": "Job Description\n\nTo build a B2B E-commerce platform from zero, make sure it is profitable. Must be knowledgeable and multitask in sales, marketing, operation, logistics...etc. different field\nDevelop and implement B2B warehouse\u00a0standard operation\u00a0procedures in e-Commerce channels and logistics\nManage the existing logistic channel and explore new channels of E-commerce platform\nResearch and identify new potential partnerships and e-commerce opportunities\nSet the strategic direction, oversee and co-ordinate all e-commerce activity through different media\nFacilitate and monitor the KPIs of the warehouse, ensure timely and accuracy of orders fulfillment\n\nJob Requirement\n\nDegree in E-commerce / Computer Science / I.T. or related disciplines\nMinimum 2-3 years working experience in E-commerce, IT background is an advantage\nAnalytical with excellent business and market sense\nConfident in selling products/ business model/ concepts\nGood command of spoken and written English and Chinese\nIndependent and able to work under pressure\n\nJob location: San Po Kong\n\nCompetitive remuneration package and benefits as below:\nFive-day work week\nMarriage leave\nStaff discount\nMedical & dental allowance\nPerformance bonus\nIn-service training course\n5 days paternity leave\nCompassionate Leave\nPromotion opportunitie", "employment_types": ["Full Time", "Part Time"], "selling_points": ["\u5009\u52d9\u54e1", "14\u5e74\u5047", "\u4e0a\u6c34\u5de5\u4f5c"], "locations": ["Sheung Shui"], "categories": ["Transportation & Logistics", "Inventory / Warehousing", "Merchandising & Purchasing", "Toy", "E-commerce", "Supply Chain"], "post_time": "2022-01-04T07:33:22Z", "salary": {"currency": null, "max": null, "min": null, "period": "hourly", "term": null}, "salary_visible": false, "title_keywords": ["operations", "\u5009\u52d9\u54e1"], "responsibilities": ["fulfillment", "monitor", "procedures", "develop", "logistics", "kpis", "e-commerce platform"], "requirements": {"degrees": ["degree"], "majors": ["computer science", "e-commerce"], "languages": ["english", "chinese"], "language_level": ["good command"], "hard_skills": ["e-commerce"], "soft_skills": ["confident", "independent", "work under pressure"], "languages_combined": [{"language": "english", "language_level": ["good command"]}, {"language": "chinese", "language_level": ["good command"]}]}, "experience_required": {"duration": ["minimum 2-3 years"], "field": ["it", "e-commerce"]}}, {"job_id": "100003009014665", "location_code": "hk", "company": "G3 Worldwide Hong Kong Limited", "job_title": "Business Development Manager / Assistant Business Development Manager", "description": "\u5168/\u517c\u8077\u5009\u52d9\u54e1\nJob Description\n\n\u8077\u8cac\n\n\u6574\u7406\u8ca8\u5009\u3001\u6536\u8ca8\u3001\u9ede\u8ca8\u3001\u57f7\u8ca8\u3001\u767c\u8ca8\u3001\u8ddf\u8eca\u6d3e\u8ca8\u3001\u76e4\u9ede\u3001\u5305\u88dd\u7b49\u5009\u52d9\u4e8b\u5b9c\n\n\u5f85\u9047\u53ca\u798f\u5229\n\n\n5\u5929\u5de5\u4f5c\n\u5e74\u504714\u5929\n\u9280\u884c\u5047\u671f\n\u5de5\u8cfc\u7269\u512a\u60e0\u7b49\n\u5165\u8077\u8981\u6c42\uff1a\n\n\u4e2d\u5b78\u6216\u4ee5\u4e0a\u7a0b\u5ea6\n\u61c2\u4f7f\u7528\u5527\u8eca\uff0c\u6709\u5009\u52d9\u7d93\u9a57\u8005\u512a\u5148\n\u61c2\u5f97\u96fb\u8166\u61c9\u7528\n\u5177\u8cac\u4efb\u611f\uff0c\u80fd\u7368\u7acb\u5de5\u4f5c\u53ca\u64c1\u6709\u826f\u597d\u6e9d\u901a\u6280\u5de7\n\n\u6709\u610f\u8005\u8acb\u767c\u9001\u5c65\u6b77\u53ca\u8981\u6c42\u5f85\u9047\u81f3whatsapp:46898300\u6216\u9ede\u64ca\"Apply Now\"\n\n\nIf you want to join our energetic, young and fun team,\u00a0please\u00a0send your resume in pdf format\u00a0and\u00a0expected salary\u00a0by clicking apply now. Those without expected salary will not be considered.\u00a0\n\nAll Personal data collected will be used for recruitment purposes only.\n\n\n\n", "employment_types": ["Full Time"], "selling_points": [], "locations": ["Ngau Tau Kok"], "categories": ["Transportation & Logistics", "Shipping", "E-commerce", "Business Development", "Supply Chain"], "post_time": "2022-01-03T03:57:05Z", "salary": {"currency": null, "max": null, "min": null, "period": "monthly", "term": null}, "salary_visible": false, "title_keywords": ["business development manager", "assistant business development manager"], "responsibilities": ["personal data", "recruitment"], "requirements": {"degrees": [], "majors": [], "languages": [], "language_level": [], "hard_skills": ["fun"], "soft_skills": ["energetic"], "languages_combined": []}, "experience_required": {"duration": [], "field": []}}, {"job_id": "100003009015588", "location_code": "hk", "company": "Profit Sail Int'l Express (H.K.) Ltd", "job_title": "Air Freight Operation Manager / Assistant Air Freight Operation Manager", "description": "Responsibilities:\n\nSupport Sales Team to optimize product listings.\nSupport Sales Team to complete projects.\nSupport order processing, customer service and website product information.\u00a0\nComplete manager's multi-task.\n\nRequirements:\n\nUniversity Degree in Business, Marketing, or E-Commerce field\n1-2 years of working experience\nSelf-Starter, detail oriented, ability to multi-task\nAble to work 2-3 days a week.\nExcellent written and verbal communication skills in English, Cantonese and Mandarin\nGood leadership skill, excellent communication and interpersonal skills, result-oriented, well organized, able to work independent and under pressure.\u00a0\nAdobe Illustrator, Adobe photoshop, Microsoft office, etc...\n\nInterested party please click \"APPLY NOW\" to submit your full resume in ENGLISH and Current & Expected salary.\n\n\nPersonal data collected will be treated in strict confidence and will only be used for recruitment related purpose only.", "employment_types": ["Full Time"], "selling_points": ["Experience in Europe / South East Asia market", "To lead and manage effectively and efficiently", "Plan and organize air freight all aspect"], "locations": ["Kwai Fong"], "categories": ["Transportation & Logistics", "Freight Forwarding", "Supply Chain", "E-commerce", "Supply Chain"], "post_time": "2022-01-03T07:07:16Z", "salary": {"currency": null, "max": null, "min": null, "period": "monthly", "term": null}, "salary_visible": false, "title_keywords": ["manager", "assistant", "air freight operation"], "responsibilities": ["product listings", "website", "customer service", "sales team", "order processing"], "requirements": {"degrees": ["university degree"], "majors": ["business", "e-commerce", "marketing"], "languages": ["cantonese", "english", "mandarin"], "language_level": ["excellent"], "hard_skills": ["microsoft office", "adobe illustrator", "adobe photoshop", "e-commerce"], "soft_skills": ["communication skills", "confidence", "multi-task", "independent", "under pressure", "detail oriented", "well organized", "communication and interpersonal skills", "leadership skill", "result-oriented"], "languages_combined": [{"language": "cantonese", "language_level": ["excellent"]}, {"language": "english", "language_level": ["excellent"]}, {"language": "mandarin", "language_level": ["excellent"]}]}, "experience_required": {"duration": ["1-2 years"], "field": []}}, {"job_id": "100003009017381", "location_code": "hk", "company": "ideali Limited", "job_title": "Logistics and Admin Manager (Full Time)", "description": "\u00a0Job Description\n\nProvide CBX expertise to customers\nCommunicate, translate, and simplify business requirements to ensure buy-in from all stakeholders\nDiscover, organize, and clarify business needs and review/produce specifications for change\nWork with the Technical Architects and development team to ensure that they understand the specifications.\nAnalyze functional and non functional requirements and seek clarifications for better understanding of requirements.\nPrepare for and conduct conference room pilots for customers demonstrating the capabilities of the CBX PLM and Sourcing Software\nConfigure software application to support the customer's business processes\nMonitor project progress relative to assigned tasks and communicate progress regularly to management\nWork with CBX architecture, development and quality assurance teams to ensure the customer's software solution needs are met\n\nSkills\n\n3 - 5 years of experience in business analysis and requirements elicitation\nExcellent written and verbal presentation skills (Specially in English)\nPreferably with systems integration experience\nFamiliarity with some or all of these technologies a plus: Java, XML, J2EE,\u00a0\u00a0JSON, API\nFamiliarity in Agile Development, particularly Scrum or Kanban\nScrum Master experience is an advantage\nRetail / Consumer products experience (business or information technology) is a plus\nMust have at least a Bachelor's Degree\n\nRelocation Requirement:\n\nAble to relocate to Vancouver, B.C. Canada in short notice\nCanadian Citizenships/Permanent Residency is preferred\nThe ability to obtain open work permit to work in Canada\nVancouver local applicant will be prioritized\n\nInterested parties, please apply together with resume, stating current and expected salary, and send it via\u00a0APPLY NOW.\n\nWe are an equal opportunity employer and welcome applications from all qualified candidates. All information provided by applicants will be treated in strictest confidence and handled confidentially for recruitment-related purposes within the company and our associated company. Applicants may be considered for other suitable positions within the company over a one-year period, after which their personal data will be destroyed", "employment_types": ["Full Time"], "selling_points": ["Manage Ideali's innovative just-in-time logistics", "Fluent English and Cantonese to service customers", "Young, high energy and fun loving colleagues"], "locations": ["Causeway Bay"], "categories": ["Admin & HR", "Administration / Operation Manager", "Sales, CS & Business Devpt", "Customer Service - Supervisor / Officer", "E-commerce", "Supply Chain"], "post_time": "2022-01-03T16:51:37Z", "salary": {"currency": "HKD", "max": 24999, "min": 17000, "period": "monthly", "term": null}, "salary_visible": true, "title_keywords": ["admin", "logistics", "manager"], "responsibilities": ["management", "monitor project progress", "software", "review", "quality", "teams", "systems", "agile development", "specifications", "business analysis", "architecture"], "requirements": {"degrees": [], "majors": [], "languages": [], "language_level": [], "hard_skills": ["c"], "soft_skills": [], "languages_combined": []}, "experience_required": {"duration": [], "field": []}}, {"job_id": "100003009019125", "location_code": "hk", "company": "Page Personnel", "job_title": "Warehouse Operator - Luxury Retail", "description": "Industry: E-commerce\n\nJob Description\n- Manage Ideali's just-in-time logistics, including\u00a0consolidation of goods of multiple customer orders in European gateway cities, shipment from Europe to Asia and local deliveries mainly in Hong Kong and Singapore.\n- Collaborate closely with freight forwarders and their Europe-based partners, as well as Ideali's own overseas team that handles suppliers' local deliveries in Europe.\n- Liaise with customers on non-standard arrangements, solve problems and handle difficult situations.\n- Execute offline marketing operations (e.g. work with printers, offline mailing campaigns), and co-ordinate with overseas teams on Chinese language matters (e.g. websites)\n- Handle the company's administrative matters\n\nRequirements\n1) Fluent English - written and spoken. Comfort with working with colleagues from diverse nationalities and cultural backgrounds\n2) Experience in trading, logistics, or distribution of goods is preferred. Customer service experience preferred\n3) Proficiency in MS Word and Excel\n\nSalary: commensurate with relevant work experience", "employment_types": ["Full Time", "Permanent"], "selling_points": ["Pick and Pack, Stock take", "Staff discount offered", "Young and dynamic working environment"], "locations": ["Not Specified"], "categories": ["Transportation & Logistics", "Inventory / Warehousing", "Supply Chain", "E-commerce", "Supply Chain"], "post_time": "2022-01-04T06:45:08Z", "salary": {"currency": null, "max": null, "min": null, "period": "monthly", "term": null}, "salary_visible": false, "title_keywords": ["warehouse operator"], "responsibilities": ["collaborate", "co-ordinate with", "operations", "teams", "logistics", "liaise with"], "requirements": {"degrees": [], "majors": [], "languages": ["english"], "language_level": ["fluent"], "hard_skills": ["excel", "ms word"], "soft_skills": ["diverse", "customer service"], "languages_combined": [{"language": "english", "language_level": ["fluent"]}]}, "experience_required": {"duration": [], "field": ["logistics", "customer service", "trading"]}}, {"job_id": "100003009018595", "location_code": "hk", "company": "Randstad Hong Kong Limited", "job_title": "Director of Inbound Operations", "description": "Excellent opportunity for inventory management and warehouse operation experts to work for a Luxury Retailer. The chosen candidate will be responsible for inventory and warehouse management to the team.\n\nClient Details\n\nOur client is one of the most reputable companies within the luxury industry. With over decades of history, they have been delivering the best products and services to the world. With steady and rapid expansion in business in Hong Kong, they are actively looking for a Warehouse Operator to join their dynamic company.\n\nDescription\n\nEnsure inventory data accuracy and eliminate discrepancies in system\nResponsible for daily warehouse operation including stock taking, stock recording, delivery documentations, etc.\nAssist in formulating warehouse operation process to improve working efficiency\nAssist in ad-hoc duties as per assigned\n\nProfile\n\nMin. 1 year of experience in Warehouse Operation\nStrong analytical skills with numerical sense\nOrganized and detail-oriented individual\nExcellent command in both English and Chinese\n\nJob Offer\n\nCareer progression\nMedical and dental\nCompetitive pay\n5-day work\nStaff discount", "employment_types": ["Full Time", "Permanent"], "selling_points": [], "locations": ["Not Specified"], "categories": ["Transportation & Logistics", "Supply Chain", "E-commerce", "Supply Chain"], "post_time": "2022-01-04T04:02:14Z", "salary": {"currency": null, "max": null, "min": null, "period": "monthly", "term": null}, "salary_visible": false, "title_keywords": ["operations", "director"], "responsibilities": ["management", "data", "inventory", "inventory management", "ad-hoc duties"], "requirements": {"degrees": [], "majors": [], "languages": ["english", "chinese"], "language_level": ["excellent"], "hard_skills": ["analytical skills", "dynamic", "luxury industry", "rapid", "documentations"], "soft_skills": ["organized", "responsible", "analytical skills", "detail-oriented", "dynamic", "ad-hoc duties"], "languages_combined": [{"language": "english", "language_level": ["excellent"]}, {"language": "chinese", "language_level": ["excellent"]}]}, "experience_required": {"duration": ["1 year"], "field": ["operation"]}}, {"job_id": "100003009016338", "location_code": "hk", "company": "Bollyman Express Company Limited", "job_title": "IT MANAGER (5 days work)", "description": "about the company.\nOur client is a remarkable US buying office with their products mainly delivered to US/Europe. Currently they are hiring a Director of Inbound Operations in the team. This is a new headcount.\n\nabout the job.\nAs a Director of Inbound Operations, you will\n-Supervise the daily operations of APAC inbound operations department\n-Drive continuous efficiency improvements in the operational processes and logistic workflow\n-Ensure lead times and existing cost structure are constantly challenged and reduced\n-Manage import/export customs compliance across supply chain functions\n-Lead the execution of regional logistics related projects and change initiatives according to the global strategy\n-Support in creation and update of SOPs across the supply chain, including vendor manual update, KPIs of vendor performance\n\nskills & experiences required.\n-Degree holder in Supply Chain or Logistics\n-10 years of experience working in an inbound operations position\n-Candidates from sourcing office background is a plus\n-Commercial and strategic awareness with solid project management experience\n-Excellent framing skills and ability to synthesize information and communicate impact to a broad audience\n-Big picture-oriented thinking and good communication skills with ability to partner with and influence across all levels of the organization and cross-functionally\n-Capable of achieving results in a highly-matrixed and global environment\n\nabout the package\n-5 day work\n-Double Pay\n-Discretionary Bonus\n-Leadership Experience\n-Medical Insurance\n-Dental Insurance\n-Work-life balance\n-New headcount\n\nIf you're interested in this role, click 'apply now' to forward an up-to-date copy of your CV, or email to sally.lo@randstad.com.hk", "employment_types": ["Full Time"], "selling_points": ["Young & Energetic Team", "5 days work at Tsuen Wan", "Attractive Package"], "locations": ["Tsuen Wan Area"], "categories": ["Information Technology (IT)", "Application Specialist - Network", "Transportation & Logistics", "Freight Forwarding", "E-commerce", "Supply Chain"], "post_time": "2022-01-03T08:53:24Z", "salary": {"currency": null, "max": null, "min": null, "period": "monthly", "term": null}, "salary_visible": false, "title_keywords": ["it manager"], "responsibilities": ["cost", "operations", "compliance", "communication", "project management", "daily operations", "logistics", "sops", "kpis", "insurance"], "requirements": {"degrees": [], "majors": [], "languages": [], "language_level": [], "hard_skills": ["project management", "plus", "vendor"], "soft_skills": ["communication skills", "project management", "interested in"], "languages_combined": []}, "experience_required": {"duration": [], "field": ["project management"]}}, {"job_id": "100003009014670", "location_code": "hk", "company": "G3 Worldwide Hong Kong Limited", "job_title": "Key Account Executive", "description": "Job Responsibilities:\n\nPerform in-house system development, technical support, maintenance on both hardware/software.\nLead projects to launch effectively within time and resource constraints\nAnticipate stakeholder needs, and develop and discuss potential solutions\nStay current on web technology trends and innovations and share information with the team\u00a0\n\nRequirements:\u00a0\n\nHD or Degree Holder in Computer Science, Computer Studies, Information Technology or related\nMin 2 years of software development\nKnowledge and experience with Microsoft C#.NET, MS SQL, JavaScript, HTML, CSS, API WEB development\nProficient in written and spoken English and Chinese (incl. Mandarin);\nGood team player, enjoy mixed team environment with HK and PRC colleagues.\nWork independently\nOccasional travel to Shenzhen\nImmediate available\u00a0", "employment_types": ["Full Time"], "selling_points": [], "locations": ["Ngau Tau Kok"], "categories": ["Transportation & Logistics", "Shipping", "E-commerce", "Business Development", "Supply Chain"], "post_time": "2022-01-03T03:57:45Z", "salary": {"currency": null, "max": null, "min": null, "period": "monthly", "term": null}, "salary_visible": false, "title_keywords": ["key account executive"], "responsibilities": ["software", "maintenance", "technical support", "develop", "hardware", "share information"], "requirements": {"degrees": ["degree holder"], "majors": ["information technology", "computer science", "computer studies"], "languages": ["english", "chinese", "mandarin"], "language_level": ["proficient"], "hard_skills": ["web development", "html", "javascript", "css", "ms sql", "c#"], "soft_skills": ["good team player", "work independently"], "languages_combined": [{"language": "english", "language_level": ["proficient"]}, {"language": "chinese", "language_level": ["proficient"]}, {"language": "mandarin", "language_level": []}]}, "experience_required": {"duration": [], "field": []}}, {"job_id": "100003009016906", "location_code": "hk", "company": "CBX Software Limited", "job_title": "Marketing Campaign Manager (Five-day work)", "description": "Our client is\u00a0a Chinese e-commerce, retail and technology conglomerate is seeking for a Procurement Assistant to support their daily operations.\n\nResponsibilities:\n\nHands on source-to-pay procurement process with multiple categories focus (mainly in IT & Telcom, Facility Services & Marketing Services) via in-house group procurement platform.\nProvides full process support with internal stakeholders and external suppliers in order to achieve business targets by implementing sourcing & procurement execution within the group procurement policy and procedures.\u00a0\nKeep constant collaboration with central Group Procurement team in Hangzhou, as well as other regional teams, to maintain the synergy of category strategies, process improvement, and best practice sharing of overseas procurement operation.\nCollaborates with other functions such as Finance, Legal, HR in maintaining overall process control and mutual key performance metrics.\nExecuting project-based sourcing with guidance of the line manager. Develop local category strategy and expand local supply base.\nRequirements and Qualifications:\n\nAt least one year working experience in supply chain or procurement related industry;\nBachelor degree in supply chain, business management, finance, or related disciplines.\nFast learning in a very dynamic and fast pace environment;\nPatient with sense of customer care, open-minded and willing to pro-actively communicate with others;\nProficient English and Mandarin, other language is a plus;\nFamiliar with online procurement tools as well as major IT tools. Advance user of Excel and Power Point, or database tools is a plus;\nTo apply for this position, please click on \u201cApply Now\u201d bottom.\u00a0 All applications will be treated in strict confidence, and used for recruitment purposes only in accordance with PERSOLKELLY Hong Kong Limited\u2019s Privacy Notice.\u00a0\u00a0", "employment_types": ["Full Time", "Permanent"], "selling_points": ["attracting new clients to join e-commerce platform", "Customer DB management and create segmentation", "Excellent Marketing sense and relevant experience"], "locations": ["Lai Chi Kok"], "categories": ["Information Technology (IT)", "Product Management / Business Analyst", "E-commerce", "Marketing - Brand / Product Management", "Supply Chain"], "post_time": "2022-01-03T10:05:12Z", "salary": {"currency": null, "max": null, "min": null, "period": "monthly", "term": null}, "salary_visible": false, "title_keywords": ["manager"], "responsibilities": ["guidance", "control", "maintaining", "hr", "teams", "procedures", "performance metrics", "develop", "maintain", "executing"], "requirements": {"degrees": ["degree", "bachelor"], "majors": ["related disciplines", "finance", "business"], "languages": ["english", "mandarin"], "language_level": ["proficient"], "hard_skills": ["business management", "excel", "plus", "dynamic", "power point"], "soft_skills": ["confidence", "open-minded", "dynamic", "learning", "patient"], "languages_combined": [{"language": "english", "language_level": ["proficient"]}, {"language": "mandarin", "language_level": ["proficient"]}]}, "experience_required": {"duration": ["at least one year"], "field": ["related", "supply chain", "procurement"]}}, {"job_id": "100003009011949", "location_code": "hk", "company": "JD Express Investment I (Hong Kong) Limited", "job_title": "Warehouse Specialist / Warehouse Officer \u5009\u5eab\u5c08\u54e1 / \u5009\u5eab\u4e3b\u4efb", "description": "Job Description\nAs our Marketing Campaign Manager. You will be in charge of attracting new clients to join our e-commerce platforms and to aide us to run various online and physical e-commerce, trading and other engagement activities.\n\nWork with management to create customer segmentation and data strategy to drive value in marketing from online tradeshows to eCommerce.\nPropose and deliver relevant customer segmentation frameworks for marketing promotions including audience lists for online and offline campaigns.\nBuild customer insights for business actions across business units\nDrive physical and online marketing events and attendance thru various online and offline promotion channels.\nCoordinate with internal and external parties for content marketing opportunities.\nCompile reports to analyse program and campaign effectiveness to drive constant improvements.\nRequirements\n\nDegree holder in marketing, business analysis, or other related field\n6-8 years\u2019 experience in marketing and database management\nTradeshows related work experience preferred\nHands on experience with CRM or database systems\nExcellent marketing sense especially in B2B trading business and customer segmentation\nCan work independently and under pressure\nGood command of English and Chinese (Cantonese and Mandarin)\n\nBenefits\n\nFriendly and collaborative work environment with diverse and inclusive international teams\nExcellent career development opportunities\nAttractive remuneration packages\nOn-job training\n5 minute walk to MTR from office\nMonthly fun activities\nMedical insurances\nPerformance bonuses\nReferral bonuses\nEmployment visa sponsorship (if required)", "employment_types": ["Full Time"], "selling_points": ["Min 2yrs of exp in warehouse management", "Experienced in WMS/ERP systems", "Competitive salary package and good benefit"], "locations": ["Yuen Long Area"], "categories": ["Transportation & Logistics", "Inventory / Warehousing", "Supply Chain", "E-commerce", "Supply Chain"], "post_time": "2021-12-31T08:35:52Z", "salary": {"currency": null, "max": null, "min": null, "period": "monthly", "term": null}, "salary_visible": false, "title_keywords": ["specialist", "officer"], "responsibilities": ["marketing events", "attendance", "work with management", "data", "compile reports", "internal and external parties", "customer insights", "e-commerce platforms", "coordinate with", "marketing promotions", "analyse"], "requirements": {"degrees": ["degree holder"], "majors": ["business", "marketing"], "languages": ["cantonese", "english", "chinese", "mandarin"], "language_level": ["good command"], "hard_skills": ["analysis"], "soft_skills": ["work independently", "hands on", "marketing sense", "under pressure"], "languages_combined": [{"language": "cantonese", "language_level": ["good command"]}, {"language": "english", "language_level": ["good command"]}, {"language": "chinese", "language_level": ["good command"]}, {"language": "mandarin", "language_level": ["good command"]}]}, "experience_required": {"duration": ["6-8 years"], "field": ["related", "marketing", "database management", "database"]}}, {"job_id": "100003009008497", "location_code": "hk", "company": "Cellarmaster Wines (H.K.) Limited", "job_title": "Sales Coordinator", "description": "About Zeek\nZeek is the brand name under Kin Shun Information Technology Limited which incorporated in 2019. Zeek aims to provide smart logistics, SaaS solutions and online / offline integrated instant delivery service for Hong Kong and Southeast Asia market, meeting their needs for food & parcel delivery and last-mile logistics.\n\nWe strive for building an excellent delivery experience by adopting big data and artificial intelligence. With existing business in Hong Kong, Singapore, Malaysia, Thailand and Vietnam, we will continue to expand our business to Southeast Asia countries and regions like Taiwan, Philippines and Indonesia in near future.\n\nResponsibilities:\u00a0\n\nRepresent headquarter to oversee operational and financial KPIs of Food & Quick Commerce business across multiple SEA markets, and provide executional inputs to local operations teams in optimizing operational efficiency and service level\nTake lead in operational planning for launch of new markets or services in existing markets;\nMaintain right sets of indicators and reports for effective analysis on services and operations, and also identifying improvement opportunities for Hong Kong and overseas markets;\nFacilitate local operations team to diagnose existing issues in operations and the execution of initiatives by cooperating with various internal parties and external partners;\nTake ownership on urgent issues in operations and take timely actions;\nKeep abreast of the market\u2019s leading practices and understand competitors\u2019 operating models to ensure company\u2019s practice has its competitive advantages;\nShare knowledge and leading practices in operations in Headquarter for local operations teams to take reference;\nDevelop standard operating procedures and guidelines for overseas markets;\nDevelop BI report templates for operations management and monitoring across markets;\nPerform ad-hoc duties assigned by Management\n\nRequirements:\n\nDegree holder in any disciplines;\u00a0\nMinimum 4 years of experience in operations management, project management or consulting, with experiences in start-ups, logistic platforms, F&B or e-commerce sectors preferred;\nStrong planning and analytical skills with strong business sense and problem-solving skill;\nSensitive to numbers and capable in scientific analysis, candidates with BI reporting experience have advantage;\nProactive and able to work under pressure with multi-tasking ability;\nIndependent, self-motivated, detail-oriented, good team player and able to work in a fast paced and dynamic working environment;\nGood command of written and spoken English, Cantonese and Mandarin;\nProficient in MS applications, e.g. PowerPoint, Excel and Word\n\nWe offer competitive remuneration, birthday and work anniversary holidays and benefit packages to the right candidate.\n\nPlease send your detailed resume, with last and expected salary to our Human Resources Department by clicking \"Apply Now\u201d.\u00a0\u2028\n\n(All information collected will be treated in strict confidence and used solely for recruitment)", "employment_types": ["Full Time"], "selling_points": [], "locations": ["Causeway Bay"], "categories": ["Transportation & Logistics", "Fulfillment", "E-commerce", "Supply Chain", "Sales, CS & Business Devpt", "Sales Administration"], "post_time": "2021-12-30T08:11:40Z", "salary": {"currency": null, "max": null, "min": null, "period": "monthly", "term": null}, "salary_visible": false, "title_keywords": ["sales coordinator"], "responsibilities": ["management", "guidelines", "operations", "analysis", "monitoring", "teams", "diagnose", "procedures", "develop", "maintain", "reports", "ad-hoc duties", "kpis", "report", "internal parties", "planning"], "requirements": {"degrees": ["degree holder"], "majors": ["any disciplines"], "languages": ["cantonese", "english", "mandarin"], "language_level": ["good command"], "hard_skills": ["excel", "bi", "ms applications", "e-commerce", "problem-solving", "analysis", "word", "powerpoint", "analytical skills", "project management", "dynamic"], "soft_skills": ["self-motivated", "good team player", "independent", "capable", "business sense", "problem-solving", "analytical skills", "detail-oriented", "project management", "multi-tasking", "dynamic", "sensitive to numbers", "proactive", "work under pressure"], "languages_combined": [{"language": "cantonese", "language_level": ["good command"]}, {"language": "english", "language_level": ["good command"]}, {"language": "mandarin", "language_level": ["good command"]}]}, "experience_required": {"duration": ["minimum 4 years"], "field": ["consulting", "e-commerce", "project management", "f&b", "operations management"]}}, {"job_id": "100003009011928", "location_code": "hk", "company": "Bollyman Express Company Limited", "job_title": "IT MANAGER (5 days work)", "description": "Daily delivery arrangement and perform orders fulfilment for online platform and warehouse management system;\nCommunicate with Logistics Supervisor, warehouse and delivery team on delivery arrangement and stock issue;\nCoordinate with Customer Service Executive in case of any problems on stock and delivery arrangement;\nPreparation of reports as required, e.g. inventory report, order summary, sales report etc.\nAssist in company events, if necessary\n\n\u00a0Requirements\n\nDiploma or above or with minimum 3 years\u2019 experience in order processing, preferable for online shop\nGood team player and able to work in a fast-paced environment\nGood problem solving, communication and negotiation skills\nProficiency in MS office\nFluent in Mandarin, English and Chinese (both spoken and written)", "employment_types": ["Full Time"], "selling_points": ["Young & Energetic Team", "5 days work at Tsuen Wan", "Attractive Package"], "locations": ["Tsuen Wan Area"], "categories": ["Information Technology (IT)", "Application Specialist - Network", "Transportation & Logistics", "Freight Forwarding", "E-commerce", "Supply Chain"], "post_time": "2021-12-31T08:30:01Z", "salary": {"currency": null, "max": null, "min": null, "period": "monthly", "term": null}, "salary_visible": false, "title_keywords": ["it manager"], "responsibilities": ["communicate with", "sales report", "inventory", "coordinate with", "warehouse management system", "communication", "customer service", "logistics", "reports", "order processing", "report"], "requirements": {"degrees": ["diploma or above"], "majors": [], "languages": ["english", "chinese", "mandarin"], "language_level": ["fluent"], "hard_skills": ["problem solving", "order processing", "ms office"], "soft_skills": ["good team player", "fast-paced environment", "communication", "problem solving", "negotiation skills", "customer service"], "languages_combined": [{"language": "english", "language_level": ["fluent"]}, {"language": "chinese", "language_level": ["fluent"]}, {"language": "mandarin", "language_level": ["fluent"]}]}, "experience_required": {"duration": ["minimum 3 years"], "field": ["order processing"]}}, {"job_id": "100003008999939", "location_code": "hk", "company": "Yue Hwa Chinese Products Emporium Ltd", "job_title": "\u7db2\u8cfc\u8ddf\u55ae\u5009\u52d9\u54e1", "description": "Our client, a global E-Commerce business branding company, is now looking for an experienced candidate to join them.\n\nResponsibilities:\n\nMake the optimal sales strategy and planning for each client and their own E-commerce business\nRegularly review and track the existing sales and inventory data for improvement\nLaunch new products and manage the daily operation in various market places (Amazon, Ebay, Shopify etc)\nWork closely with the internal teams for logistic and inventory arrangement\nAssist Marketing team for promotion and sales strategy\n\nRequirements:\n\n\nDegree or Diploma in the relevant discipline\nMore than 2 years in E-Commerce field, experiences of managing and operating market places (e.g. Amazon, ebay etc)\nStrong analytical and communication skills\nFluent in English and Mandarin\n\n\n\nFor a confidential discussion about this role please contact Clarence at 2185 6309.", "employment_types": ["Full Time"], "selling_points": ["\u7db2\u8cfc", "\u5009\u52d9", "\u7db2\u5e97"], "locations": ["Yau Ma Tei"], "categories": ["Sales, CS & Business Devpt", "Retail Sales", "E-commerce", "Supply Chain", "Others"], "post_time": "2021-12-29T01:44:42Z", "salary": {"currency": null, "max": null, "min": null, "period": "monthly", "term": null}, "salary_visible": false, "title_keywords": [], "responsibilities": ["data", "inventory", "review", "daily operation", "teams", "planning"], "requirements": {"degrees": ["diploma", "degree"], "majors": [], "languages": ["english", "mandarin"], "language_level": ["fluent"], "hard_skills": ["amazon", "e-commerce"], "soft_skills": ["communication skills"], "languages_combined": [{"language": "english", "language_level": ["fluent"]}, {"language": "mandarin", "language_level": ["fluent"]}]}, "experience_required": {"duration": ["2 years"], "field": ["e-commerce"]}}, {"job_id": "100003008998651", "location_code": "hk", "company": "Taste of Asia Group Limited", "job_title": "E-Commerce Specialist (IT)", "description": "Job Responsibilities:\n\nManage daily operations\u00a0of website\nParticipate in the development of Omni-channel strategies\nUpdate various project progress on daily/weekly basis with reporting and logging duties\nCommunicate with 3rd\u00a0party vendors for project updates\nAssist in various E-commerce project developments and perform quality check on testing environment\nMaintain, update and publish 3rd party marketplace content including products description and image\nGenerate sales report and perform marketing research for management review\nSupport E-commerce team on departmental administration\nAssist in ad hoc duties as assigned\u00a0by the supervisor\n\nJob Requirements:\n\nUniversity graduate in E-commerce, Business or related discipline\n2 years solid E-commerce experience, preferably from retail industry\nFundamental knowledge and experience in Magento\u00a0will be an advantage along with web analytical tools, E-commerce platforms and payment gateways, i.e. Google Analytics & PayPal\nProficiency in MS Office applications (Excel, Word, PowerPoint and Chinese Word Processing)\nSelf-motivated and able to work under pressure\nCustomer-oriented, Good team spirit and good communication skill\nGood level of spoken and written English, Chinese and Mandarin\nCandidate with more experience will be considered as Officer\n\nWe offer an attractive package commensurate with your qualifications and experience. Please apply with full resume, present and expected salary, quoting the ref. no. to the Human Resources Department, Pricerite Home Limited, 28/F Manhattan Place, 23 Wang Tai Road, Kowloon Bay, Kowloon, HK; or fax to 2820 0651 or press \"APPLY NOW\"\n\nAll information provided by applicants will be treated in strict confidentiality and used for recruitment purpose only. We will retain your application for a maximum period of 6 months and may refer it to other vacancies within the Group.", "employment_types": ["Full Time"], "selling_points": ["Five-day work week", "Medical & dental allowance", "Performance bonus"], "locations": ["Wong Tai Sin Area"], "categories": ["E-commerce", "Product Management / Business Analyst", "Software Development", "Supply Chain"], "post_time": "2021-12-24T04:00:08Z", "salary": {"currency": null, "max": null, "min": null, "period": "monthly", "term": null}, "salary_visible": false, "title_keywords": ["specialist"], "responsibilities": ["website", "marketing research", "maintain", "e-commerce project", "management review", "administration", "ad hoc duties", "sales report", "support e-commerce team", "project progress", "testing environment", "manage daily operations", "3rd party vendors", "quality check", "products description and image", "3rd party marketplace content", "reporting and logging duties", "communicate with", "project updates", "omni-channel strategies"], "requirements": {"degrees": ["university graduate"], "majors": ["business", "e-commerce"], "languages": ["english", "chinese", "mandarin"], "language_level": ["proficiency", "good"], "hard_skills": ["google analytics", "excel", "chinese word processing", "web", "e-commerce", "word", "powerpoint", "ms office"], "soft_skills": ["self-motivated", "team spirit", "communication skill", "customer-oriented", "work under pressure"], "languages_combined": [{"language": "english", "language_level": ["good"]}, {"language": "chinese", "language_level": ["proficiency", "good"]}, {"language": "mandarin", "language_level": ["good"]}]}, "experience_required": {"duration": ["2 years"], "field": ["retail industry", "analytical", "e-commerce"]}}, {"job_id": "100003008996323", "location_code": "hk", "company": "Choi Fung Hong Company Limited", "job_title": "E-commerce Assistant", "description": "Responsibilities:\n\u2022 Coordinating new product & existing products\n\u2022 Manage the operations of online platforms to meet or exceed launch goals\n\u2022 Designing and implementing processes to effectively launch products onto different online platforms such as HKTVmall, Ztore, etc.\n\u2022 Responsible for order follow up, liaise with customer and internal parties\n\u2022 Researching competitive pricing & promotions\n\nRequirements:\n\u2022 Diploma or Degree holder in business or related disciplines\n\u2022 1 - 2 years relevant experience in B2C online platform\n\u2022 Independent, self-motivated\n\u2022 Interested in beauty products\n\u2022 Good command of written and spoken English and Chinese\n\u2022 Good command of PC software including Microsoft Office and word processing\n\u2022 Fresh graduate will be considered", "employment_types": ["Full Time"], "selling_points": ["Independent, self-motivated", "Interested in beauty products", "Coordinating new product & existing"], "locations": ["Tuen Mun Area"], "categories": ["E-commerce", "Supply Chain"], "post_time": "2021-12-23T06:33:32Z", "salary": {"currency": null, "max": null, "min": null, "period": "monthly", "term": null}, "salary_visible": false, "title_keywords": ["assistant"], "responsibilities": ["liaise with", "operations", "internal parties", "designing"], "requirements": {"degrees": ["diploma", "fresh graduate", "degree holder"], "majors": ["related disciplines", "business"], "languages": ["english", "chinese"], "language_level": ["good command"], "hard_skills": ["pc", "word processing", "microsoft office"], "soft_skills": ["self-motivated", "interested in", "independent"], "languages_combined": [{"language": "english", "language_level": ["good command"]}, {"language": "chinese", "language_level": ["good command"]}]}, "experience_required": {"duration": ["1 - 2 years"], "field": ["relevant experience"]}}, {"job_id": "100003008993173", "location_code": "hk", "company": "GOAT Group HK Limited", "job_title": "Inventory Associate", "description": "As an Inventory Associate, you will be a vital member of a fast growing operation with the ability to massively impact the customer experience as part of our advanced Operations line-up. You must thrive in working in a fast paced environment exhibiting organization skills and team oriented decisions to be a part of the Operations Team.\n\n\u00a0In this role you will:\n\nPrioritize and execute daily tasks in compliance with the Operations team and priorities.\nLead and execute daily cycle counting process for inventory compliance\nDrive compliance of\u00a0 inventory product storage standards\nTake responsibility for on hand products and their physical and systematic locations\nTake responsibility in delivering commitments and positive results\nExecute daily cycle counts in compliance with GOAT standards\nPick daily orders according to priority to meet or exceed order SLA\nResearch daily variances and determine root cause; report trends\nBe flexible with other projects as they surface, fostering a team dynamic and can-do attitude\nMeet or exceed inventory goals for picking, shelving, and accuracy\nLead and drive processes and methods\nLocate and reconcile discrepancies using inventory exception reports\nReconcile exception items related to inventory cycle counting, shelving accuracy, and order picking\nTeach and train new employees on inventory processes, products, and order status\nFoster a positive and collaborative work environment\nTake risks, try new things, and be a natural problem solver\nSet high team standards and lead by example\n\nWe are looking for:\n\nStrong work ethic, works with a sense of urgency, and motivated by meeting team and individual goals\nExcels and thrives in a fast paced and goal oriented environment\nMinimum 1 year of experience working in an inventory control setting \u2013 sneaker industry is a plus\nExperience in order fulfillment, fulfillment support, order picking and all inbound/outbound mechanisms\nAbility to multitask and prioritize\nProactive\nProblem solver with accuracy and a high attention to detail\nFlexible schedule with the ability to work evenings, weekends and holidays\nMust be able to work while standing and walking in long hours\nStrong knowledge of the sneaker industry is a plus", "employment_types": ["Full Time"], "selling_points": ["inventory control setting", "order fulfillment, fulfillment support", "high attention to detail"], "locations": ["Shatin Area"], "categories": ["E-commerce", "Supply Chain"], "post_time": "2021-12-22T07:10:05Z", "salary": {"currency": null, "max": null, "min": null, "period": "monthly", "term": null}, "salary_visible": false, "title_keywords": ["inventory associate"], "responsibilities": ["operations", "inventory", "compliance", "fulfillment", "daily orders", "inventory control", "reports", "order fulfillment", "schedule", "report"], "requirements": {"degrees": [], "majors": [], "languages": [], "language_level": [], "hard_skills": ["sla", "plus", "dynamic", "goal"], "soft_skills": ["flexible", "advanced", "problem solver", "can-do attitude", "urgency", "collaborative", "prioritize", "systematic", "dynamic", "natural problem solver", "motivated", "work ethic", "attention to detail", "organization skills", "ability to multitask", "proactive", "positive", "goal oriented"], "languages_combined": []}, "experience_required": {"duration": ["minimum 1 year"], "field": ["inventory control", "operation"]}}, {"job_id": "100003008994308", "location_code": "hk", "company": "ProductIP (HK) Limited", "job_title": "Project Executive (PE)", "description": "The Club is HKT\u2019s customer loyalty program and digital ventures arm. Anyone can join the program for free and enjoy the rewards, privileges, and services such as online shopping, travel, insurance, and CSR. Members can earn Clubpoints from spending through HKT lines of business, affiliate services, or partnered merchants. Clubpoints can be used to redeem rewards or discount spending on the various The Club services.\n\nAt The Club by HKT, we are passionately working together and dedicated to creating a digital ecosystem so frictionless our members can live better, earn more.\n\nThe Club is seeking a eCommerce Operations Executive (3-month contract) to play a key role in supporting the implementation of an ERP system.\n\nYour Role\n\nPerform clerical and administrative support\nHandle price comparison of product\nPerform operational duties include product uploading and information checking\nPhoto retouching\nOther ad hoc assignments as required\n\nTo succeed in this role\n\nHigher Diploma or above\nProficient in MS Office Application, especially Excel is a MUST\nFamiliar with Photoshop skill and E-commerce experience is an advantage\nReasonable level of fluency in Chinese and English\nGood command of written and spoken Chinese and English\nSelf-motivated, independent, mature and strong sense of responsibility\nGood communication skills and time management\nImmediate availability is preferred", "employment_types": ["Full Time", "Permanent"], "selling_points": ["5-day work; 13-month basic salary per year", "Comprehensive TCF & compliance on-the-job training", "Teamwork with both European & Chinese colleagues"], "locations": ["Northern NT Area"], "categories": ["Engineering", "Manufacturing & Production", "Manufacturing", "Quality Assurance, Control & Testing / ISO", "E-commerce", "Supply Chain"], "post_time": "2021-12-22T22:18:28Z", "salary": {"currency": null, "max": null, "min": null, "period": "monthly", "term": null}, "salary_visible": false, "title_keywords": ["project executive"], "responsibilities": ["management", "photo retouching", "administrative support", "operations", "implementation", "checking", "communication", "ad hoc assignments", "insurance", "operational duties"], "requirements": {"degrees": ["higher diploma or above"], "majors": [], "languages": ["english", "chinese"], "language_level": ["fluency", "good command"], "hard_skills": ["excel", "e-commerce", "erp system", "ms office", "photoshop"], "soft_skills": ["communication skills", "self-motivated", "independent", "sense of responsibility", "mature", "time management"], "languages_combined": [{"language": "english", "language_level": ["fluency", "good command"]}, {"language": "chinese", "language_level": ["fluency", "good command"]}]}, "experience_required": {"duration": [], "field": ["e-commerce"]}}, {"job_id": "100003008996255", "location_code": "hk", "company": "Granful Solutions Limited", "job_title": "Digital Marketing Executive", "description": "Job Description:\n\n09:00 - 18:00 per day; 5-day work;\nProviding user support for international clients in using ProductIP system and services;\nCo-coordinating with clients and their suppliers/partners in completing all works necessary for the creation, fulfillment and repair of product technical files (or a.k.a. \u201cTCF\u201d/ \u201cTechnical Construction File\u201d), plus reporting its status;\nProviding general sales and administration support for daily operation;\nPerforming duties, task or assignments up to the requirements and expectation of the Hong Kong Management;\nBasic work management skills;\nPotential candidate with more experience or higher qualification would be offered a more senior position.\nWork locations:\n1a. In view of the current Covid travel limits set by the governments, the candidate will have a mix of working at designated working premises in Hong Kong and/or working at home (to be instructed by the Hong Kong Management).\n1b. When situation allows, the candidate will resume working at our Futian Shenzhen office (Connected to Shenzhen Metro Station \u201cConvention and Exhibition Center\u201d Exit E) on daily basis;\n2. Hong Kong for trade shows and seminar events.\nQualifications:\n\nIt is an advantage (but NOT a must) for candidate with proven customer services / external communication experience in the following industries:\nProduct testing\nQA for Supply chain industry (e.g. retail/buying/sourcing/merchandising offices, trading companies, manufacturers, etc.)\nStrong written and spoken language abilities, especially in English and Mandarin.\nWithin 3-5 years of working experience.\nHigher Diploma, Bachelor Degree in Engineering, Quality Management, Supply Chain Management or related disciplines.\nSelf-starter, diligent, efficient, team player with good attitude and strong commitment to work.\n\nBenefit highlights:\n\n5-day work;\u00a0\n13-month basic salary per year;\nPerformance bonus, medical insurance, paid annual leave and travel allowance provided by the company;\nExpertise/knowledge development: Intensive on-the-job training provided by the company;\nGood promotion opportunities for career development.\n\nHow to apply:\n\nPlease send your resume to\u00a0Sandy Tsang\nYour resume must be written in English and include your current and expected salary\nPlease mark the email subject with \u201cApplication for the position of Project Executive (PE)\u201d.", "employment_types": ["Full Time", "Permanent"], "selling_points": ["Plan and execute online campaigns", "Proactively manage all social media platform", "Creative, proactive and energetic"], "locations": ["Kwai Fong"], "categories": ["E-commerce", "Marketing - Brand / Product Management", "Supply Chain"], "post_time": "2021-12-23T06:15:37Z", "salary": {"currency": null, "max": null, "min": null, "period": "monthly", "term": null}, "salary_visible": false, "title_keywords": ["digital marketing executive"], "responsibilities": ["reporting", "management", "fulfillment", "daily operation", "repair", "administration"], "requirements": {"degrees": [], "majors": [], "languages": [], "language_level": [], "hard_skills": ["plus", "basic"], "soft_skills": [], "languages_combined": []}, "experience_required": {"duration": [], "field": []}}, {"job_id": "100003008992234", "location_code": "hk", "company": "G3 Worldwide Hong Kong Limited", "job_title": "Key Account Executive", "description": "Highlight of Benefits :\n\nGreat Career Exposure\nYoung and\u00a0Energetic\u00a0Working Environment\nComprehensive medical Coverage\nDigital and brand building Marketing Talent\nConvenient office location, 10mins walk to MTR\nAccess to dynamic mixed business\nGlobal eCommerce operation and logistics\nPerformance Bonus\nOffice working hours\n\n\u00a0\u00a0Who is our Right Fit\uff1a\n\nDegree or above in Advertising, Marketing, E-commerce, PR or related discipline\nMore than 1 year relevant experience Experience in digital media/online content platform\nIndependent, self-motivated, Well-organized and communication skill, strong time management with commitment to excellence\nKnowledge of implementation of search and social media platforms (Facebook, Instagram) and analytic tools is a must\nGood analytical skills and number sensitive\n\nJob Responsibilities:\n\nPlan and execute online campaigns on marketing platforms such as Google, Facebook and Instagram ads, and optimize performance across all stages of the conversion funnel\nTo manage and monitor the day-to-day performance of social and online marketing platforms\nProactively manage social media platform to drive customer engagement\nAnalyze and report marketing performance of digital platforms\nCollaborate with internal and external parties such as content creators, designers, media agencies, etc.\nConduct research to gain access to up-to-date market trends in the digital industry and bring in new ideas to enhance the digital & content marketing plan\u00a0\n\n\u00a0Remarks:-\n\nWe are an equal opportunity employer and we offer the rewarding package plus fringe benefit to the right team player. For interested candidates, please email your full resume with current and expected salary by email to Attn: Admin Dept.", "employment_types": ["Full Time"], "selling_points": [], "locations": ["Ngau Tau Kok"], "categories": ["Transportation & Logistics", "Shipping", "E-commerce", "Business Development", "Supply Chain"], "post_time": "2021-12-22T04:33:42Z", "salary": {"currency": null, "max": null, "min": null, "period": "monthly", "term": null}, "salary_visible": false, "title_keywords": ["key account executive"], "responsibilities": [], "requirements": {"degrees": [], "majors": [], "languages": [], "language_level": [], "hard_skills": [], "soft_skills": [], "languages_combined": []}, "experience_required": {"duration": [], "field": []}}, {"job_id": "100003008993904", "location_code": "hk", "company": "Randstad Hong Kong Limited", "job_title": "Planner (Regional role)", "description": "Reporting to Business Solution Manager to maintain assigned key accounts and provide customer support. The role is a crucial interface between internal and external customers, and manage relationship with external customers to drive the growth of the business.\n\n\nJob Responsibilities\u00a0\n\nMaintain and provide customer support to assigned major accounts for business development and sales process\nIdentify and qualify customer needs and requirement\nProvide business solution to explore new business opportunities by working with Business Development Managers\nConduct customer profile analysis and prepare monthly performance reports\nImplement SOP for new customers to ensure smooth onboarding\nProactively identify and resolve customer escalations, issues and manage exceptions\n\u00a0Job Requirements\nMinimum 2 year logistic industry experience\nAccount management and customer service experience preferrable\nPostal distribution background with knowledge of e-commerce market place and air freight preferable\nData proficiency including excel\nBusiness analysis and proposal proficiency\nGood problem solving and effective communication skills\nProcess driven and result oriented\nWilling to work as team\nFluent spoken and written English and Chinese (Mandarin)\nWilling to travel with expected frequencies to different cities of China\nA recognized university degree\nImmediate availability is preferable\nG3 Worldwide Hong Kong Limited\u00a0is an equal opportunity employer and welcomes applications from all qualified candidates. Information provided will be treated in strict confidence and only be used for recruitment related purposes. Applicants who are not contacted within 6 weeks may consider their application unsuccessful. Unsuccessful applications may be kept for another 3 months for being considered for other suitable positions available in our Company. The unsuccessful applications will be destroyed after the said period of retention.\n", "employment_types": ["Full Time", "Permanent"], "selling_points": [], "locations": ["Not Specified"], "categories": ["Transportation & Logistics", "Inventory / Warehousing", "Supply Chain", "E-commerce", "Supply Chain"], "post_time": "2021-12-22T09:44:42Z", "salary": {"currency": null, "max": null, "min": null, "period": "monthly", "term": null}, "salary_visible": false, "title_keywords": [], "responsibilities": ["performance reports", "analysis", "maintain", "explore new business opportunities"], "requirements": {"degrees": ["university degree"], "majors": [], "languages": ["english", "chinese", "mandarin"], "language_level": ["fluent"], "hard_skills": ["problem solving", "excel", "analysis", "e-commerce"], "soft_skills": ["communication skills", "confidence", "problem solving", "result oriented", "customer service", "driven"], "languages_combined": [{"language": "english", "language_level": ["fluent"]}, {"language": "chinese", "language_level": ["fluent"]}, {"language": "mandarin", "language_level": ["fluent"]}]}, "experience_required": {"duration": ["minimum 2 year"], "field": ["customer service", "account management"]}}, {"job_id": "100003008988453", "location_code": "hk", "company": "CKC Solutions Limited", "job_title": "Merchandiser/ Buyer (E-Commerce) - Rapidly Growing Start-Up  - HKD20K - 23K", "description": "about the company.\nOur client is a well-known US lifestyle company with their regional office in Hong Kong. They have more than 30 years of history and are considered as market leaders in their industry. Currently they are hiring a Planner to join their team. They are looking for someone detail-minded, analytical with a good command of English.\n\nabout the job.\nAs a Planner, you will\n-Manage and deliver the components supply and inventory performance from suppliers\n-Support in delivering the targets by effective collaboration with internal stakeholders\n-Manager the respective branded regional service fulfilment\n-Participate with the Supply Chain Team and affiliates SI&OP meeting to attain the business goals\n-Collaborate closely with key organisational partners in the performance of the supply planning function\n-Monitor the KPI performance in relation to supply chain planning for APAC regions\n\nskills & experiences required.\n-Associate degree/Degree from logistics/supply chain or any relevant discipline\n-Good command of Mandarin English is a must\n-Minimum 3 years of experience working as a Planner\n-Candidates from Retail/FMCG/regional planning background are highly preferred\n-Detail-minded with good communication skills\n-ERP/Oracle/SAP user is a plus\n\nabout the benefits.\nOur clients offer competitive salary package, they also offer\n-5 day work\n-Discretionary Bonus\n-Medical Insurance\n-Dental Insurance\n-Stable business; famous brand in their industry\n\nIf you're interested in this role, click 'apply now' to forward an up-to-date copy of your CV, or email to sally.lo@randstad.com.hk", "employment_types": ["Full Time", "Permanent"], "selling_points": ["FMCG E-commerce", "Groceries/Beauty/Non-Food General Merchandising", "1+ year of FMCG exp required"], "locations": ["Lai Chi Kok"], "categories": ["Sales, CS & Business Devpt", "Business Development", "Merchandising & Purchasing", "Others", "E-commerce", "Supply Chain"], "post_time": "2021-12-20T10:43:22Z", "salary": {"currency": null, "max": null, "min": null, "period": "monthly", "term": null}, "salary_visible": false, "title_keywords": ["merchandiser"], "responsibilities": ["business goals", "inventory", "communication", "logistics", "planning"], "requirements": {"degrees": ["degree"], "majors": [], "languages": ["english", "mandarin"], "language_level": ["good command"], "hard_skills": ["planner", "supply planning", "plus", "sap", "oracle"], "soft_skills": ["detail-minded", "communication skills"], "languages_combined": [{"language": "english", "language_level": ["good command", "good command"]}, {"language": "mandarin", "language_level": ["good command"]}]}, "experience_required": {"duration": ["3 years"], "field": []}}, {"job_id": "100003008985651", "location_code": "hk", "company": "Inforich Asia Hong Kong Limited", "job_title": "\u71df\u904b\u52a9\u7406 Operation Assistant", "description": "Responsibilities\n\nManage the assigned catrgory\u00a0(Groceries/\u00a0Beauty/\u00a0Non-Food, General Merchandising & Pets)\nExpand the product types to drive sales and margin target\nMaintain a healthy inventory management\nNegotiate with suppliers on product costs and promotion offers\nPrepare reports for management review and trend forecasting\nGood communictaions needed with different partners\n\nRequirements\n\n1+ years experience with FMCG category management experience is required\nDiploma or above in Business, Marketing, or other related discipline\nStrong market sense and awareness\nAble to work in high pressure and fast-paced environment\nGood command of spoken Chinese and English\nLocation: Lai Chi Kok\n\nThis is a great opportunity to be part of the team and get more new exposure. If you are interested in this role please send us your CV or call us on +852 2552 7616 for a further discussion.", "employment_types": ["Full Time", "Permanent"], "selling_points": ["\u4e94\u5929\u5de5\u4f5c", "\u7522\u54c1\u8abf\u914d", "\u5916\u52e4\u5de5\u4f5c"], "locations": ["Kwun Tong Area"], "categories": ["Hospitality / F & B", "Food & Beverage", "Transportation & Logistics", "Inventory / Warehousing", "E-commerce", "Supply Chain"], "post_time": "2021-12-19T20:48:43Z", "salary": {"currency": null, "max": null, "min": null, "period": "monthly", "term": null}, "salary_visible": false, "title_keywords": ["operation assistant", "\u71df\u904b\u52a9\u7406"], "responsibilities": ["merchandising", "management review", "groceries", "inventory management", "maintain", "prepare reports", "drive sales", "forecasting", "costs"], "requirements": {"degrees": ["diploma or above"], "majors": ["business", "marketing"], "languages": ["english", "chinese"], "language_level": ["good command"], "hard_skills": [], "soft_skills": ["fast-paced environment", "strong market sense", "interested in"], "languages_combined": [{"language": "english", "language_level": ["good command"]}, {"language": "chinese", "language_level": ["good command"]}]}, "experience_required": {"duration": ["1+ years"], "field": ["management", "fmcg"]}}]