[{"job_id": "100003009054818", "location_code": "hk", "company": "Victoria\u2019s Secret", "job_title": "Technologist, Raw Materials / Colorist (6 months contract)", "description": "PURPOSE/GENERAL SUMMARY:\n\nSupport the end to end process of all raw material components of lingerie and/or apparel products from development to production including quality assurance, risk assessment to assure final product quality.\n\nPRINCIPAL DUTIES & RESPONSIBILITIES:\n\nSupport sourcing and developments of all raw material components including color and print for lingerie and/or apparel products to meet the design\u2019s expectation\nMaintain internal systems for record update after raw material approval, lab dips/print development approval and bulk submission approval.\u00a0Data entry/ system input/ simple data drawing with analysis from FlexPLM and shared drive.\nSupport bulk management, e.g. color management, physical performance and quality check\nApply effective systems of Quality Management and regulatory standards, both internally and with vendors to support the fabric and color development process and assure final product quality\nCoordinate with mills to gather information on raw material production lead time and machine capacity for analysis and planning\nSupport mills\u2019 evaluation, onboarding and calibration to ensure their capabilities meet the business expectations\nTake control of the submissions with responsibility for the interpretation and communication of all departmental laboratory testing\nFollow the business calendar timeline to assure the operations on track\n\nREQUIREMENTS:\n\nBachelor Degree holder of Technical Education in Textile Science or equivalent\n3-5 years of related experience in fabric, print and color development in related product category(-ies), as well as in quality assurance in textile industry\nGood command of written and spoken English and Chinese\nGood command of computer skills.\u00a0Experience in FlexPLM system is highly preferable\nProactive and willing to learn\n\nCandidates not invited for interview within 8 weeks may consider their applications unsuccessful. All personal information will be treated as confidential and be used for recruitment purposes only.", "employment_types": ["Temporary", "Contract"], "selling_points": ["6 months renewable contract", "fabric development and color approval", "5 days work week; flexible work hours"], "locations": ["Kowloon Bay"], "categories": ["Manufacturing", "Garment / Textile", "Merchandising & Purchasing", "Fabrics", "Textiles"], "post_time": "2022-01-17T11:21:36Z", "salary": {"currency": null, "max": null, "min": null, "period": "monthly", "term": null}, "salary_visible": false, "title_keywords": [], "responsibilities": ["management", "quality check", "control", "data entry", "data", "operations", "analysis", "systems", "quality", "coordinate with", "design", "testing", "communication", "maintain", "system input", "evaluation", "internal systems", "planning"], "requirements": {"degrees": ["bachelor degree holder"], "majors": ["science"], "languages": ["english", "chinese"], "language_level": ["good command"], "hard_skills": ["computer skills"], "soft_skills": ["proactive", "willing to learn"], "languages_combined": [{"language": "english", "language_level": ["good command"]}, {"language": "chinese", "language_level": ["good command"]}]}, "experience_required": {"duration": ["3-5 years"], "field": ["related", "development", "print", "textile", "quality assurance"]}}, {"job_id": "100003009055472", "location_code": "hk", "company": "API Lab Testing Limited", "job_title": "TCF Engineer (Textile)", "description": "Job Overview:\n\nAs a TCF Textile Engineer, he/she need to conduct the compliance and tracerabaility documentation check under the projects from fibre, style and final product accrording to the customer request. He/she need to contact and communicate with the worldwide suppliers for chasing the documents, reviewing the document, providing the status report to customer and joining the customer review meeting with KAM and other managmnent occasionally & regularly.\n\nEssential Duties and Responsibilities:\n\nCollecting, reviewing and validating certificates and test reports from suppliers reg. traceability.\nKeep clients and their suppliers updated and monitor the program status.\nUndertake any other duties in coping with the business growth.\nAssists in other duties as directed by the Manager.\n\nExperience & Competencies Required:\n\nAt least 2 years' experience in textile product testing or textile trading / manufacturing company,\nFamiliar with raw material / fabric/ garment compliance/ supply chain traceability\nExtensive knowledge of textile manufacturing processes will be strong plus.\nWorking experience in commercial testing laboratory/ in house testing laboratory will be an advantage\nFamiliar with EU/US regulation on Textile, knowledge on other categories such as toys, furniture, chemical and related regulations are highly preferable\nCandidate with more experience will be considered as Senior Engineer.\nHighly-organized, capable of working under pressure with multi-task assignments\nGood command of English and Chinese.\n\nEducation and Qualifications Required:\n\nHigh Diploma or above in Textile or related discipline\n\nTools Skills:\n\nProficient in Microsoft Programs, including Word, Excel, PowerPoint and Outlook.\n\nDisclaimer:\n\nJob duties and requirements are subject to change. The company reserves the right to modify position descriptions accordingly at any time with little or no prior notice.", "employment_types": ["Full Time"], "selling_points": ["TCF Engineer, Textile, Lai Chi Kok", "Material, Fabric, Garment Compliance, Supply chain", "Reviewing & Validating Certificates, Quality"], "locations": ["Kowloon City"], "categories": ["Manufacturing", "Garment / Textile", "Professional Services", "Legal & Compliance", "Quality Assurance, Control & Testing / ISO"], "post_time": "2022-01-18T02:38:04Z", "salary": {"currency": "HKD", "max": 24999, "min": 20000, "period": "monthly", "term": null}, "salary_visible": true, "title_keywords": ["engineer"], "responsibilities": ["communicate with", "any other duties", "regulations", "other duties", "compliance", "review", "monitor", "testing", "reports", "contact", "documentation", "report"], "requirements": {"degrees": ["high diploma or above"], "majors": [], "languages": ["english", "chinese"], "language_level": ["good command"], "hard_skills": ["excel", "plus", "no", "word", "powerpoint", "outlook", "documentation"], "soft_skills": ["organized", "under pressure", "capable", "multi-task", "extensive"], "languages_combined": [{"language": "english", "language_level": ["good command"]}, {"language": "chinese", "language_level": ["good command"]}]}, "experience_required": {"duration": ["at least 2 years"], "field": ["laboratory", "manufacturing", "senior engineer", "testing", "commercial", "textile", "trading"]}}, {"job_id": "100003009054580", "location_code": "hk", "company": "New Fashion Global Limited", "job_title": "MERCHANDISING MANAGER", "description": "A well-established fashion exporter is looking for MERCHANDISING MANAGER working in Shenzhen with following requirements :\n\n- 5 years or above in related experience.\n- Off-shore production experience is preferable.\n- Proficient in English Writing, Reading and Speaking.\n- Post-college graduated or above is preferable.\n\nWe offer generous salary and bonus for the right candidate. Interested parties please send full resume to\u00a0Human Resources\u00a0Department.", "employment_types": ["Full Time"], "selling_points": ["5 years or above in related experience", "Off-shore production experience is preferable", "Proficient in English Writing, Reading & Speaking"], "locations": ["Others - China"], "categories": ["Manufacturing", "Garment / Textile"], "post_time": "2022-01-17T10:32:28Z", "salary": {"currency": null, "max": null, "min": null, "period": "monthly", "term": null}, "salary_visible": false, "title_keywords": ["merchandising manager"], "responsibilities": ["merchandising"], "requirements": {"degrees": [], "majors": [], "languages": ["english"], "language_level": ["proficient"], "hard_skills": [], "soft_skills": [], "languages_combined": [{"language": "english", "language_level": ["proficient"]}]}, "experience_required": {"duration": ["5 years"], "field": ["related"]}}, {"job_id": "100003009054817", "location_code": "hk", "company": "Victoria\u2019s Secret", "job_title": "Technologist, Raw Materials", "description": "PURPOSE/GENERAL SUMMARY:\n\nSupport the end to end process of all raw material components of lingerie and/or apparel products from development to production including quality assurance, risk assessment to assure final product quality.\n\nPRINCIPAL DUTIES & RESPONSIBILITIES:\n\nSupport sourcing and developments of all raw material components including specification set up, physical performance validation, quality approval, color and print approval for lingerie and/or apparel products to meet the design\u2019s expectation\nMaintain internal systems for record update after raw material approval, lab dips/print development approval and bulk submission approval.\u00a0Data entry/ system input/ simple data drawing with analysis from FlexPLM and shared drive.\nCoordinate with mills to gather information on raw material production lead time and machine capacity for analysis and planning\nApply effective systems of Quality Management and regulatory standards, both internally and with vendors to support the fabric and color development process and assure final product quality\nSupport mills\u2019 evaluation, onboarding and calibration to ensure their capabilities meet the business expectations\nSupport bulk management, e.g. color management, physical performance, quality check and problem solving\nTake control of the submissions with responsibility for the interpretation and communication of all departmental laboratory testing\nFollow the business calendar timeline to assure the operations on track\n\n\n\nREQUIREMENTS:\n\nBachelor\u2019s degree holder of Technical Education in Textile Science or equivalent\n3-5 years of related experience in synthetic fabric, lace and embroidery products, print and color development in related product category(-ies), as well as in quality assurance in textile industry\nGood command of written and spoken English and Chinese\nGood command of computer skills.\u00a0Experience in FlexPLM system is highly preferable\nProactive and willing to learn\n\nCandidates not invited for interview within 8 weeks may consider their applications unsuccessful. All personal information will be treated as confidential and be used for recruitment purposes only.", "employment_types": ["Full Time", "Permanent"], "selling_points": ["Fabric technical development", "Lace/embroidery/intimate experience is a plus", "5 days' work week; flexible work model"], "locations": ["Kowloon Bay"], "categories": ["Manufacturing", "Garment / Textile", "Merchandising & Purchasing", "Fabrics", "Textiles"], "post_time": "2022-01-17T11:21:35Z", "salary": {"currency": null, "max": null, "min": null, "period": "monthly", "term": null}, "salary_visible": false, "title_keywords": [], "responsibilities": ["management", "quality check", "control", "data entry", "data", "operations", "analysis", "systems", "quality", "coordinate with", "design", "testing", "communication", "maintain", "system input", "evaluation", "internal systems", "planning"], "requirements": {"degrees": ["bachelor", "degree holder"], "majors": ["science"], "languages": ["english", "chinese"], "language_level": ["good command"], "hard_skills": ["computer skills"], "soft_skills": ["proactive", "willing to learn"], "languages_combined": [{"language": "english", "language_level": ["good command"]}, {"language": "chinese", "language_level": ["good command"]}]}, "experience_required": {"duration": ["3-5 years"], "field": ["related", "development", "print", "textile", "quality assurance"]}}, {"job_id": "100003009052513", "location_code": "hk", "company": "Global Management Services Limited", "job_title": "Associate Merchandiser (Woven/Outdoor)", "description": "PRINCIPAL DUTIES & RESPONSIBILITIES:\n\nAssess product construction based on fabrics, trims and treatments and to build the Smart product to achieve the aesthetics and margin goals\u00a0\nCall out any risks on quality, capability and capacity at the early development stage\u00a0and escalate to supervisor\u00a0\nAssess risks early to pull in CFT and QA expertise and work on\u00a0solutions\u00a0\nCome up with different cost options to achieve the business goals\u00a0\nManage tech pack in and out, work closely with vendors on meeting sample follow up.\u00a0\nFollow up costing with vendors to ensure costing to counterpart is provided in a timely manner.\u00a0\nCoordinate sample tracking\u00a0\nUpdate cost sheet per style\u00a0\nFollow up with vendors for the compliance questionnaires and check the completeness and accuracy for system update \u00a0\u00a0\nCo-ordinate with cross functional team including fit approval and style duplication per Senior Merchandiser direction\u00a0\u00a0\nLearn and work on enterprise software (e.g. Salesforce)\u00a0\n\nREQUIREMENTS:\n\n\n3+\u00a0years related experience\u00a0in\u00a0following up time and actions\u00a0\nProficient in Word, Excel and\u00a0Powerpoint\u00a0\u00a0\nCertificate/Diploma or equivalent\u00a0\nGood command of spoken and written English\nCandidates not invited for interview within 8 weeks may consider their applications unsuccessful. All personal information will be treated as confidential and be used for recruitment purposes only.", "employment_types": ["Full Time", "Permanent"], "selling_points": [], "locations": ["Kowloon Bay"], "categories": ["Manufacturing", "Garment / Textile", "Merchandising & Purchasing", "Procurement / Purchasing / Sourcing"], "post_time": "2022-01-17T03:17:25Z", "salary": {"currency": null, "max": null, "min": null, "period": "monthly", "term": null}, "salary_visible": false, "title_keywords": ["merchandiser", "associate"], "responsibilities": ["cost", "business goals", "software", "co-ordinate with", "system update", "compliance", "quality", "a timely manner", "coordinate", "assess risks", "tracking"], "requirements": {"degrees": ["certificate", "diploma"], "majors": [], "languages": ["english"], "language_level": ["good command"], "hard_skills": ["excel", "word", "powerpoint"], "soft_skills": [], "languages_combined": [{"language": "english", "language_level": ["good command"]}]}, "experience_required": {"duration": ["3+ years"], "field": ["related"]}}, {"job_id": "100003009054820", "location_code": "hk", "company": "Victoria\u2019s Secret", "job_title": "Contract Merchandiser (Product Development)", "description": "Job Responsibilities:\n\nAssist General Manager on a project based to explore and develop new factory plant in overseas\nProvide full spectrum of administrative functions including facilities repair and maintenance, deliver services, catering and accommodation services, etc\nTo lead, supervise, review, recommend and implement policies & operational procedures to meet with the Company's development needs and to ensure compliance of the Corporate policies\nDevelop and implement staffing and business plans to achieve business target\nResponsible for overall factory operations and management\nHandle ad hoc projects as assigned by immediate supervisor\n\nJob Requirements:\n\nDegree holder or above\nStrong solid experience in all-round garment manufacturing factory environment is a\u00a0MUST\nMinimum 10 years relevant experience in manufacturing industry including 5 years at managerial level\nSelf-motivated, result-oriented and able to work under pressure\nExcellent interpersonal skills and project management skills\nExcellent command in both spoken and written English and Chinese including Mandarin\nStationed in Overseas\n\nWe\u00a0offer\u00a0attractive remuneration package to the right candidate. Interested parties please click the \"APPLY NOW\" button below and send your application together with a detailed resume including current & expected salary and availability to Human Resources Department.\n\nCompany website:\u00a0https://www.lawsgroup.com\n\n(Data collected will be treated in strict confidence and used for recruitment purpose only)\n", "employment_types": ["Temporary", "Contract"], "selling_points": ["Renewable Contract", "Assess product construction - intimate and apparel", "5 days work week"], "locations": ["Kowloon Bay"], "categories": ["Manufacturing", "Garment / Textile", "Product Development / Management", "Merchandising & Purchasing", "Woven / Knit"], "post_time": "2022-01-17T11:22:08Z", "salary": {"currency": null, "max": null, "min": null, "period": "monthly", "term": null}, "salary_visible": false, "title_keywords": ["merchandiser", "product development"], "responsibilities": ["management", "maintenance", "policies", "operations", "review", "business plans", "develop", "ensure compliance", "repair", "operational procedures", "ad hoc projects", "catering"], "requirements": {"degrees": ["degree holder"], "majors": [], "languages": ["english", "chinese", "mandarin"], "language_level": ["excellent"], "hard_skills": ["project management"], "soft_skills": ["self-motivated", "project management skills", "interpersonal skills", "result-oriented", "work under pressure"], "languages_combined": [{"language": "english", "language_level": ["excellent"]}, {"language": "chinese", "language_level": ["excellent"]}, {"language": "mandarin", "language_level": ["excellent"]}]}, "experience_required": {"duration": ["5 years", "minimum 10 years"], "field": ["garment", "managerial", "manufacturing", "relevant experience", "manufacturing industry"]}}, {"job_id": "100003009051869", "location_code": "hk", "company": "LAWSGROUP", "job_title": "Assistant General Manager (Stationed in Overseas)", "description": "Job Responsibilities:\n\n\nManage and follow up with production line to ensure the product quality\nAssist to analyze quarterly forecast align with merchandising strategies\nLiaise with internal and external customers to keep tracking the product development\nRetrieve and facilitate problem solution when necessaries\nAssist to prepare material for\u00a0price negotiation\n\nJob Requirements:\n\nDiploma\u00a0graduate in Textile / Clothing or related discipline\nMinimum\u00a02 years\u2019 solid experience in\u00a0cut & sewn\u00a0merchandising , preferably in U.S. market\nWith factory background is an advantage\nStrong leadership, energetic & dynamic\nGood command of written and spoken English and Chinese including Putonghua\nWeekly Travel\u00a0to Zhuhai office is required\nCandidate with less experience will be considered as Assistant Merchandiser\n\nWe\u00a0offer\u00a0attractive remuneration package to the right candidate. Interested parties please click the \"APPLY NOW\" button below and send your application together with a detailed resume including current & expected salary and availability to Human Resources Department.\n\nCompany website:\u00a0https://www.lawsgroup.com\n\n(Data collected will be treated in strict confidence and used for recruitment purpose only)", "employment_types": ["Full Time", "Permanent"], "selling_points": ["Degree holder with 8 yrs relevant work exp.", "Solid exp in garment manufacturing factory", "Stationed in Overseas"], "locations": ["Overseas"], "categories": ["Admin & HR", "Others", "Manufacturing", "Garment / Textile", "Others"], "post_time": "2022-01-17T01:25:47Z", "salary": {"currency": null, "max": null, "min": null, "period": "monthly", "term": null}, "salary_visible": false, "title_keywords": ["assistant general manager"], "responsibilities": ["internal and external customers", "price negotiation", "merchandising", "quality", "forecast", "liaise with", "tracking"], "requirements": {"degrees": ["diploma"], "majors": [], "languages": ["putonghua", "english", "chinese"], "language_level": ["good command"], "hard_skills": ["dynamic"], "soft_skills": ["dynamic", "energetic", "leadership"], "languages_combined": [{"language": "putonghua", "language_level": ["good command"]}, {"language": "english", "language_level": ["good command"]}, {"language": "chinese", "language_level": ["good command"]}]}, "experience_required": {"duration": ["minimum 2 years"], "field": ["merchandising"]}}, {"job_id": "100003009051872", "location_code": "hk", "company": "LAWSGROUP", "job_title": "Merchandiser / Assistant Merchandiser, Cut & Sewn Knit", "description": "\u00a0Responsibilities\n\nFollow up order from samples development to bulk production in applying supply chain management and quality assurance independently\nCo-ordinate with sub-contractors / shipping department and ensure on time delivery of merchandise\nParticipate in price negotiation and liaison with vendors or suppliers\nHandle customers\u2019 inquiries and assist to translate detailed technical production\nOther duties assigned by supervisor\n\n\u00a0Requirements\n\nHigher Diploma or above in Textiles & Clothing or related disciplines\n3 years garment merchandising experience\u00a0(woven and cut & sewn knit ladies high fashion items)\nCapable to work with direct customers / designers / sample room\nGood communication and interpersonal skills\nAttentive to details and able\u00a0to work under pressure\nGood command of both spoken and written English and Chinese (including Putonghua)\nImmediate available is preferred\n\nWe offer attractive remuneration package including Five-day work, free shuttle bus, medical insurance and performance bonus.\u00a0 Interested parties, please email your full\u00a0resume, present and expected salary to us.\n\nFor more company information, please visit our website at\u00a0http://www.pfghl.com.\n\nAll applications will be treated in strict confidence and used for recruitment-related purpose only.", "employment_types": ["Full Time", "Permanent"], "selling_points": ["Min. 2 yrs  exp in cut & sewn merchandising", "Manage and follow up with production line", "Excellent career development exposure"], "locations": ["Others - China"], "categories": ["Manufacturing", "Garment / Textile", "Merchandising & Purchasing", "Woven / Knit", "Textiles"], "post_time": "2022-01-17T01:25:49Z", "salary": {"currency": null, "max": null, "min": null, "period": "monthly", "term": null}, "salary_visible": false, "title_keywords": ["merchandiser", "assistant merchandiser"], "responsibilities": ["management", "shipping", "price negotiation", "other duties", "co-ordinate with", "quality", "ensure on time delivery"], "requirements": {"degrees": ["higher diploma or above"], "majors": ["related disciplines"], "languages": ["putonghua", "english", "chinese"], "language_level": ["good command"], "hard_skills": [], "soft_skills": ["communication and interpersonal skills", "capable", "attentive to details", "work under pressure"], "languages_combined": [{"language": "putonghua", "language_level": ["good command"]}, {"language": "english", "language_level": ["good command"]}, {"language": "chinese", "language_level": ["good command"]}]}, "experience_required": {"duration": ["3 years"], "field": ["garment", "merchandising"]}}, {"job_id": "100003009054159", "location_code": "hk", "company": "Profits Fund Fashion Manufacturing Ltd", "job_title": "Merchandiser", "description": "Job Responsibilities:\n\n\nResponsible for merchandise order and planning in accordance with respective merchandising strategies\nCollaborate with internal parties to ensure the timeline and monitor the on-time shipment\nDay to day communication with PRC and offshore vendors for tracking production & delivery schedule without delay.\nPO management\nMaintain the KPI for on time delivery\n\nJob Requirements:\n\n\nDiploma in Textiles and Clothing or related subjects\nMinimum 5 years or above working experience in garment trading or buying office, preferably in one catering to the US market\nDetail oriented, flexible minded with self confidence, able to work under pressure and overtime\nWork independently with good work ethics\nFluent in spoken & written English, Cantonese and Mandarin\nGood computer skills e.g. Word, Excel, PowerPoint\n\nFor more information about our company and business, please visit our website at:\u00a0https://www.sparcgroup.com/\n\nWe offer prosperous career path, competitive compensation package plus attractive fringe benefits such as: 13-month salary, discretionary bonus, dental, life,\u00a0 comprehensive medical coverage including spouse & children, employee discount, additional provident fund from employer, gym & education sponsorship...and more for the right candidate. Please send your full resume with current and expected salary by \"Apply Now\".\n\nPersonal data collected will be used for recruitment purpose only and we regret that\u00a0 only shortlisted candidates will be notified.\n", "employment_types": ["Full Time", "Permanent"], "selling_points": [], "locations": ["Kwai Fong"], "categories": ["Manufacturing", "Garment / Textile", "Merchandising & Purchasing", "Woven / Knit"], "post_time": "2022-01-17T08:37:15Z", "salary": {"currency": null, "max": null, "min": null, "period": "monthly", "term": null}, "salary_visible": false, "title_keywords": ["merchandiser"], "responsibilities": ["collaborate with", "tracking", "management", "monitor", "merchandising", "communication", "delivery schedule", "maintain", "internal parties", "planning"], "requirements": {"degrees": ["diploma"], "majors": [], "languages": ["cantonese", "english", "mandarin"], "language_level": ["fluent"], "hard_skills": ["excel", "plus", "word", "powerpoint", "computer skills"], "soft_skills": ["flexible", "work independently", "confidence", "detail oriented", "comprehensive", "work under pressure"], "languages_combined": [{"language": "cantonese", "language_level": ["fluent"]}, {"language": "english", "language_level": ["fluent"]}, {"language": "mandarin", "language_level": ["fluent"]}]}, "experience_required": {"duration": ["minimum 5 years"], "field": ["garment", "trading"]}}, {"job_id": "100003009053099", "location_code": "hk", "company": "SPARC Far East Limited", "job_title": "Supply Chain Analyst - Production (Apparel MNC Sourcing Office)", "description": "Job Description:\n\nCommunicate with oversea customers on day-to-day basis and address corresponding concerns\nUnderstand customers' expectation on their samples and translate the idea to factory technicians\nReview and comment on samples\nKeep track on sample and production status to ensure on-time delivery\nCoordinate neccessary materials for bulk production and sampling\n\n\nJob Requirements:\n\nPolyU, HKDI or CITA graduate in Textile / Clothing or related discipline\u00a0\nMinimum 3 years\u2019 solid experience in sweater merchandising\u00a0\nStrong technical knowledge in sweater knit\nGood sense of styling\u00a0and\u00a0fitting\nGood command in English and Mandarin\nWilling to travel to China\nStrong organizing and analytical skills, energetics and willing to work as a team\n\n\nInterested parties please send your full resume with current and expected salary by email or by fax at 2325 3225\n\n\nPersonal data will be used for recruitment purpose only.", "employment_types": ["Full Time", "Permanent"], "selling_points": ["Luxury Multi-national Sourcing Office", "Comprehensive Fringe Benefits & Career Growth", "5 Days Work & Work Life Balance"], "locations": ["Kwun Tong"], "categories": ["Manufacturing", "Garment / Textile", "Production Planning / Control", "Merchandising & Purchasing", "Woven / Knit"], "post_time": "2022-01-17T06:20:25Z", "salary": {"currency": null, "max": null, "min": null, "period": "monthly", "term": null}, "salary_visible": false, "title_keywords": ["analyst"], "responsibilities": ["communicate with", "review", "coordinate"], "requirements": {"degrees": [], "majors": [], "languages": ["english", "mandarin"], "language_level": ["good command"], "hard_skills": ["analytical skills"], "soft_skills": ["work as a team", "analytical skills"], "languages_combined": [{"language": "english", "language_level": ["good command"]}, {"language": "mandarin", "language_level": ["good command"]}]}, "experience_required": {"duration": ["minimum 3 years"], "field": ["merchandising"]}}, {"job_id": "100003009051837", "location_code": "hk", "company": "LAWSGROUP", "job_title": "Factory Manager (Stationed in Overseas)", "description": "Responsibilities:\n\nResponsible for overall operation and logistic arrangement for factory (Cut & Sewn Knit)\nMonitor and review the overall budget for P&L\nReview and prepare production plan for factory\nReview and implement policies & operational procedures ensure compliance of the Corporate policies\nAd-hoc duties upon request.\n\nRequirements:\n\nDegree holder in Textile Technology / Clothing or equivalent qualification\nStrong solid experience in all-round factory experience in garment manufacturing environment is a MUST\nAt least 8 years relevant experience in manufacturing industry including 3 years at managerial level\nSelf-motivated, result-oriented and able to work under pressure\nExcellent interpersonal skills and project management skills\nExcellent command in both spoken and written English and Chinese including Mandarin\nCandidate with less experience will be considered as Assistant Factory Manager\n\n\nWe offer attractive remuneration package to the right candidate. Interested parties please click the \"APPLY NOW\" button below and send your application together with a detailed resume including current & expected salary and availability to Human Resources Department.\nCompany website:\u00a0https://www.lawsgroup.com/\n(Data collected will be treated in strict confidence and used for recruitment purpose only)", "employment_types": ["Full Time", "Permanent"], "selling_points": ["Degree holder with 8 yrs relevant work exp.", "Solid exp. in garment manufacturing factory", "Stationed in Overseas is required"], "locations": ["Overseas"], "categories": ["Manufacturing", "Garment / Textile", "Manufacturing Management", "Product Development / Management"], "post_time": "2022-01-17T01:22:45Z", "salary": {"currency": null, "max": null, "min": null, "period": "monthly", "term": null}, "salary_visible": false, "title_keywords": ["factory manager"], "responsibilities": ["policies", "review", "monitor", "p&l", "logistic arrangement", "ensure compliance", "operational procedures", "plan", "ad-hoc duties", "overall budget"], "requirements": {"degrees": ["degree holder"], "majors": [], "languages": ["english", "chinese", "mandarin"], "language_level": ["excellent"], "hard_skills": ["project management"], "soft_skills": ["self-motivated", "project management skills", "interpersonal skills", "result-oriented", "work under pressure"], "languages_combined": [{"language": "english", "language_level": ["excellent"]}, {"language": "chinese", "language_level": ["excellent"]}, {"language": "mandarin", "language_level": ["excellent"]}]}, "experience_required": {"duration": ["at least 8 years", "3 years"], "field": ["garment", "managerial", "manufacturing", "relevant experience", "manufacturing industry"]}}, {"job_id": "100003009053468", "location_code": "hk", "company": "High Fashion Group", "job_title": "Marketing & Product Development Manager", "description": "Responsibilities:\u00a0\n\nAcquire the latest trends of the market, Develop and explore new business opportunities in overseas market\nConduct planning, execution and communication of a development strategy that meets and exceeds financial goal\nDevelop new customers for company, visit customers on a regular basis, maintain good relationship with customers\nDrive effective and efficient communication between fabric, development and production teams to ensure that contract, budgets and development schedules are targeted\nFormulating marketing and sales strategies, implementing action plans to achieve business KPI objectives\n\nRequirements:\u00a0\u00a0\n\nDegree / Diploma in Textiles and Clothing, Design or related disciplines\nRich customer resources, has ability to develop new customers and new market\n8+ year\u2019s solid experience in handling ladies high fashion or sporty fashion mainly in US or European market\nPresentable, pro-active, energetic, global vision, judgmental marketing insight, aggressive with good communication skills\nBase in HK, willing to travel occasionally\n\nWe offer an attractive package, good prospects and fringe benefits to the right candidate. Interested parties, please apply with full resume, current and expected salary to: Group Human Resources Manager of High Fashion Group. By click below \"APPLY NOW\"(in MS Word format), or by mail: 11/F., High Fashion Centre, 1-11 Kwai Hei Street, Kwai Chung, New Territories\n\n(The information received will be used for consideration of employment only and all personal data supplied will be destroyed within 6 months.)", "employment_types": ["Full Time", "Permanent"], "selling_points": ["5 days, bonus, medical & life insurance", "Lunch allowance, birthday leave", "Flexible working hours"], "locations": ["Kwai Fong"], "categories": ["Manufacturing", "Garment / Textile", "Product Development / Management", "Marketing / Public Relations", "Marketing - General / Support"], "post_time": "2022-01-17T07:01:07Z", "salary": {"currency": null, "max": null, "min": null, "period": "monthly", "term": null}, "salary_visible": false, "title_keywords": ["product development manager"], "responsibilities": ["budgets", "explore new business opportunities", "schedules", "teams", "maintain good relationship", "communication", "develop", "plans", "planning"], "requirements": {"degrees": ["diploma", "degree"], "majors": ["related disciplines", "design"], "languages": [], "language_level": [], "hard_skills": [], "soft_skills": ["communication skills", "energetic", "pro-active", "presentable"], "languages_combined": []}, "experience_required": {"duration": ["8+ year"], "field": []}}, {"job_id": "100003009052957", "location_code": "hk", "company": "", "job_title": "Asst Merchandiser / Merchandiser/ Senior Merchandiser (Woven Fashion)", "description": "Key Responsibilities\n\nProvide daily support to team members throughout the merchandising cycles;\n\nResponsible for gathering and inputting data into the system as well as ensuring order details accuracy before issuing purchase orders to suppliers;\nPerform samples measurement according to company\u2019s quality standard requirements and identify quality issues at an early stage;\nPrepare individual product style and quality requirement packages to Quality Assurance & Quality Control (\u201cQA & QC\u201d) team for inspection;\nProvide general clerical assistance to team members throughout the merchandising cycles from the arrangement of courier, general samples packing to filing;\nProvide other ad-hoc support to the team.\n\nRequirements\n\n\n\nCompletion of higher secondary school or diploma studies ideally with fashion or textile educational background;\nMinimum 2 years\u2019 relevant experience in the garment industry and preferably with knowledge in Woven/Outdoor items;\nAbility to work under pressure and tight deadlines with a proactive and positive attitude;\nGood communication skills, well-organized and attentive to details;\nExperience in order follow up ranged from sample development to bulk production;\nProficiency in MS Excel, Word, and Outlook Express;\nGood command of written and spoken English and Chinese (fluency in Cantonese and Mandarin).\n\nWhat we offer\n\nExcellent development and career growth opportunity;\nMultinational and open-minded work environment;\nCompetitive remuneration and benefits.", "employment_types": ["Full Time"], "selling_points": [], "locations": ["Not Specified"], "categories": ["Manufacturing", "Garment / Textile", "Merchandising & Purchasing", "Woven / Knit", "Procurement / Purchasing / Sourcing"], "post_time": "2022-01-17T04:42:16Z", "salary": {"currency": null, "max": null, "min": null, "period": "monthly", "term": null}, "salary_visible": false, "title_keywords": ["merchandiser", "senior merchandiser"], "responsibilities": ["ad-hoc", "data", "quality", "merchandising", "measurement", "inspection", "purchase", "quality control"], "requirements": {"degrees": ["diploma"], "majors": [], "languages": ["cantonese", "english", "chinese", "mandarin"], "language_level": ["fluency", "good command"], "hard_skills": ["garment industry", "ms excel", "outlook", "word"], "soft_skills": ["communication skills", "attentive to details", "well-organized", "positive attitude", "proactive", "work under pressure"], "languages_combined": [{"language": "cantonese", "language_level": ["fluency", "good command"]}, {"language": "english", "language_level": ["fluency", "good command"]}, {"language": "chinese", "language_level": ["fluency", "good command"]}, {"language": "mandarin", "language_level": ["fluency", "good command"]}]}, "experience_required": {"duration": ["minimum 2 years"], "field": ["garment", "development", "relevant experience"]}}, {"job_id": "100003009053941", "location_code": "hk", "company": "Lai's Knitters Limited", "job_title": "FASHIION DESIGNER / KNITWEAR DESIGNER", "description": "Takara company\n\n\u00a0\n-\u00a0F.5, IVE or Poly Graduate, Over\u00a01years Garment exp.\n\n- Strong High Fashion Item\n- Good English & Mandarin\n- Factory experiences and advantage\n- Good knowledge of Sourcing, sampling and following orders\n- Knowledge of Travel to China\n- MUST Be immediate availbale\n\n\n\n\n\n\nPlease send your application with detailed resume and expected salary to\nhr@takara.hk\u00a0\u00a0\n**Personal data collected will be used for recruitment purpose only**\n", "employment_types": ["Full Time", "Permanent"], "selling_points": [], "locations": ["Kowloon City Area"], "categories": ["Design", "Fashion", "Manufacturing", "Garment / Textile", "Merchandising & Purchasing", "Sweater"], "post_time": "2022-01-17T07:48:37Z", "salary": {"currency": null, "max": null, "min": null, "period": "monthly", "term": null}, "salary_visible": false, "title_keywords": ["designer"], "responsibilities": ["personal data", "recruitment"], "requirements": {"degrees": [], "majors": [], "languages": ["english", "mandarin"], "language_level": ["good"], "hard_skills": [], "soft_skills": ["detailed"], "languages_combined": [{"language": "english", "language_level": ["good"]}, {"language": "mandarin", "language_level": ["good"]}]}, "experience_required": {"duration": [], "field": []}}, {"job_id": "100003009053960", "location_code": "hk", "company": "Lai's Knitters Limited", "job_title": "ASST. MERCHANDISER / MERCHANDISER / SENIOR MERCHANDISER (SWEATERS KNIT)", "description": "Job Description:\n\nManage and develop the in-house collection\nResearch on the fashion and colour trend\nDevelop and design new stitches\nReview and comment on samples\nKeep track on sample and development status to ensure on-time delivery\nCoordinate necessary materials for sampling\nDevelop trend board for presentation\nAd-hoc brand related duties\n\nJob Requirements:\n\nPolyU, HKDI or CITA\u00a0graduate in Fashion Design or related discipline, majoring in knit would be an advantage.\u00a0\nMinimum 3 years\u2019 solid experience in sweater design or merchandising\nStrong technical knowledge in sweater knit\nGood sense of styling\u00a0and\u00a0fitting\nGood command in English and Mandarin\nWilling to travel to China\nStrong organizing and analytical skills, energetics and willing to work as a team\nAmbitious in sweater knit\nFresh graduate will also be considered as Assistant Fashion Designer\n\nInterested parties please send your full resume with current and expected salary by\u00a0fax to 2325 3225 or by email via jobsdb.\n\n\n\n\nPersonal data will be used for recruitment purpose only.", "employment_types": ["Full Time", "Permanent", "Contract"], "selling_points": [], "locations": ["Wong Tai Sin Area"], "categories": ["Manufacturing", "Garment / Textile", "Merchandising & Purchasing", "Sweater"], "post_time": "2022-01-17T07:52:49Z", "salary": {"currency": null, "max": null, "min": null, "period": "monthly", "term": null}, "salary_visible": false, "title_keywords": ["merchandiser", "senior merchandiser", "asst. merchandiser"], "responsibilities": ["ad-hoc", "review", "design", "develop", "coordinate"], "requirements": {"degrees": ["fresh graduate"], "majors": [], "languages": ["english", "mandarin"], "language_level": ["good command"], "hard_skills": ["analytical skills"], "soft_skills": ["work as a team", "analytical skills"], "languages_combined": [{"language": "english", "language_level": ["good command"]}, {"language": "mandarin", "language_level": ["good command"]}]}, "experience_required": {"duration": ["minimum 3 years"], "field": ["merchandising", "design"]}}, {"job_id": "100003009024866", "location_code": "hk", "company": "Jetco Zipper Limited", "job_title": "Brand Marketing / Business Relationship Specialist", "description": "Job Responsibilities:\n\nHandle the process of the product development.\nProvide product information and advices for customers.\nLiaise closely and independently with customers, factories and internal departments.\nBrain storm with colleagues for innovative product design, catalog design, seasonal material boards and predicting market trend.\nAssist Marketing Manager in various kinds of programs.\n\nJob Requirements:\n\nTertiary education with 1-2 years experience.\nKnowledge of image editing and layout design will be an advantage.\nPassionate and observant about fashion and lifestyle news and trends.\nResponsible, self-motivated, independent, willing to learn and positive attitude.\nGood command of English, Mandarin and Cantonese.\n\nWe offer 5-day work week, bank holidays, medical insurance, double pay and discretionary bonus to the right candidate. Interested parties please send your full resume with past & expected salary and availability to Jetco Zipper Limited.", "employment_types": ["Full Time", "Permanent"], "selling_points": [], "locations": ["Kwai Fong"], "categories": ["Manufacturing", "Garment / Textile"], "post_time": "2022-01-17T16:20:52Z", "salary": {"currency": null, "max": null, "min": null, "period": "monthly", "term": null}, "salary_visible": false, "title_keywords": ["specialist"], "responsibilities": ["liaise", "product design", "design"], "requirements": {"degrees": [], "majors": [], "languages": ["cantonese", "english", "mandarin"], "language_level": ["good command"], "hard_skills": [], "soft_skills": ["passionate", "self-motivated", "independent", "responsible", "willing to learn", "positive attitude"], "languages_combined": [{"language": "cantonese", "language_level": ["good command"]}, {"language": "english", "language_level": ["good command"]}, {"language": "mandarin", "language_level": ["good command"]}]}, "experience_required": {"duration": ["1-2 years"], "field": ["education"]}}, {"job_id": "100003009044444", "location_code": "hk", "company": "Foot Locker Sourcing, Inc", "job_title": "ASSISTANT MERCHANDISER", "description": "Foot Locker, Inc., public listed in New York and the world's leading retailer of athletic footwear and apparel, has an open position for its worldwide sourcing operations in Hong Kong:\n\nASSISTANT MERCHANDISER\n\n2 years experience in the garment field\nHKCEE/DSE or above\nGood PC knowledge. Proficient in Excel.\nGood command in written & spoken English and Mandarin\nSelf-motivated, detailed minded, hardworking and able to work independently\nResponsible for sample packing, measurement, some data input and reporting\n\nJob Types: Full-time", "employment_types": ["Full Time", "Permanent"], "selling_points": [], "locations": ["Kwun Tong"], "categories": ["Manufacturing", "Garment / Textile", "Others"], "post_time": "2022-01-16T21:50:14Z", "salary": {"currency": null, "max": null, "min": null, "period": "monthly", "term": null}, "salary_visible": false, "title_keywords": ["assistant merchandiser"], "responsibilities": ["operations", "measurement", "data input", "reporting"], "requirements": {"degrees": ["dse"], "majors": [], "languages": ["english", "mandarin"], "language_level": ["good command"], "hard_skills": ["excel", "pc knowledge"], "soft_skills": ["self-motivated", "work independently", "responsible", "hardworking", "detailed"], "languages_combined": [{"language": "english", "language_level": ["good command"]}, {"language": "mandarin", "language_level": ["good command"]}]}, "experience_required": {"duration": ["2 years"], "field": ["garment"]}}, {"job_id": "100003009043942", "location_code": "hk", "company": "Hong Kong Knitters Limited", "job_title": "Merchandiser (5 Days Work)", "description": "Job\u00a0Responsibilities:\n\nAssist the merchandising team to ensure the garment development to production in a timely manner\nLiaise with internal and external parties to ensure the production is on track and the quality is up to customer\u2019s standard\nPerform strategic merchandising plan through various market research, analysis and forecasting to achieve company objective\nEstablish good relationship with existing and new customers\nRetrieve and facilitate problem solution when necessaries\nPerform ad hoc tasks as assigned by immediate superior\n\nJob\u00a0Requirements:\n\nDiploma\u00a0or above in Textile / Clothing or related discipline\nMinimum 3 years relevant working experience (with garment factory background\u00a0is an advantage)\nEnergetic person with strong leadership and enjoy team work\nWith \u201cCan-do\u201d attitude and able to work independently under pressure\nGood command of both written and spoken English and Chinese\nCandidate with less experience will be considered as Merchandiser\nWe\u00a0offer\u00a0attractive remuneration package to the right candidate. Interested parties please click the \"APPLY NOW\" button below and send your application together with a detailed resume including current & expected salary and availability to Human Resources Department.\nCompany website:\u00a0https://www.lawsgroup.com\n(Data collected will be treated in strict confidence and used for recruitment purpose only)", "employment_types": ["Full Time", "Permanent"], "selling_points": [], "locations": ["Not Specified"], "categories": ["Design", "Fashion", "Manufacturing", "Garment / Textile", "Merchandising & Purchasing", "Woven / Knit"], "post_time": "2022-01-15T03:49:17Z", "salary": {"currency": null, "max": null, "min": null, "period": "monthly", "term": null}, "salary_visible": false, "title_keywords": ["merchandiser"], "responsibilities": ["analysis", "internal and external parties", "a timely manner", "merchandising", "quality", "market research", "good relationship", "ad hoc tasks", "plan", "liaise with", "forecasting"], "requirements": {"degrees": ["diploma or above"], "majors": [], "languages": ["english", "chinese"], "language_level": ["good command"], "hard_skills": [], "soft_skills": ["work independently", "under pressure", "can-do", "energetic", "leadership"], "languages_combined": [{"language": "english", "language_level": ["good command"]}, {"language": "chinese", "language_level": ["good command"]}]}, "experience_required": {"duration": ["minimum 3 years"], "field": ["garment", "relevant working experience"]}}, {"job_id": "100003009051873", "location_code": "hk", "company": "LAWSGROUP", "job_title": "Senior Merchandiser, Sweater", "description": "Job Responsibilities:\n\nSupervise the merchandising team to ensure the garment development to production in a timely manner\nLiaise with internal and external parties to ensure the production is on track and the quality is up to customer\u2019s standard\nPerform strategic merchandising plan through various market research, analysis and forecasting to achieve company objective\nEstablish good relationship with existing and new customers\nRetrieve and facilitate problem solution when necessaries\nPerform ad hoc tasks as assigned by immediate superior\n\nJob Requirements:\n\nDiploma\u00a0or above in Textile / Clothing or related discipline\nMinimum 3 years relevant working experience (with garment factory background\u00a0is an advantage)\nEnergetic person with strong leadership and enjoy team work\nWith \u201cCan-do\u201d attitude and able to work independently under pressure\nGood command of both written and spoken English and Chinese\nCandidate with less experience will be considered as Merchandiser\nFrequently travel to China is required\nWe\u00a0offer\u00a0attractive remuneration package to the right candidate. Interested parties please click the \"APPLY NOW\" button below and send your application together with a detailed resume including current & expected salary and availability to Human Resources Department.\nCompany website:\u00a0http://www.lawsgroup.com\n(Data collected will be treated in strict confidence and used for recruitment purpose only)", "employment_types": ["Full Time", "Permanent"], "selling_points": ["Dip. in Textile/Clothing or related discipline", "Min. 3 years relevant working experience", "Perform strategic merchandising plan"], "locations": ["Lai Chi Kok"], "categories": ["Manufacturing", "Garment / Textile", "Production Planning / Control", "Merchandising & Purchasing", "Sweater"], "post_time": "2022-01-17T01:25:49Z", "salary": {"currency": null, "max": null, "min": null, "period": "monthly", "term": null}, "salary_visible": false, "title_keywords": ["senior merchandiser"], "responsibilities": ["analysis", "internal and external parties", "a timely manner", "merchandising", "quality", "market research", "good relationship", "ad hoc tasks", "plan", "liaise with", "forecasting"], "requirements": {"degrees": ["diploma or above"], "majors": [], "languages": ["english", "chinese"], "language_level": ["good command"], "hard_skills": [], "soft_skills": ["work independently", "under pressure", "can-do", "energetic", "leadership"], "languages_combined": [{"language": "english", "language_level": ["good command"]}, {"language": "chinese", "language_level": ["good command"]}]}, "experience_required": {"duration": ["minimum 3 years"], "field": ["garment", "relevant working experience"]}}, {"job_id": "100003009051868", "location_code": "hk", "company": "LAWSGROUP", "job_title": "Senior Merchandiser, Cut & Sewn Knit", "description": "Responsibilities:\n\nMonitor and follow up orders, shipments and testing;\nHandle sample development;\n\nRequirements:\n\nF.7 or above;\nAt least 1-2 years merchandising experience (manufacturing / trading / buying office), and preferable in garment / toys field;\nGood command of English / Mandarin and MS Office software (Excel, Word, PowerPoint & Outlook);\nGood communication skill;\nWell organize, mature, a good team player and fast learner;\nOccasional travel to China;\nImmediate available is highly preferable.\n\n\nWe offer attractive competitive package to right candidates.\n\nAll related information will be used solely for recruitment purpose and will be destroyed upon completion of recruitment process.", "employment_types": ["Full Time", "Permanent"], "selling_points": ["Perform strategic merchandising plan", "Dip. in Textile/Clothing with 3 yrs relevant exp.", "Frequently travel to China is required"], "locations": ["Lai Chi Kok"], "categories": ["Manufacturing", "Garment / Textile", "Production Planning / Control", "Merchandising & Purchasing", "Sweater"], "post_time": "2022-01-17T01:25:47Z", "salary": {"currency": null, "max": null, "min": null, "period": "monthly", "term": null}, "salary_visible": false, "title_keywords": ["senior merchandiser"], "responsibilities": ["follow up orders", "monitor", "testing"], "requirements": {"degrees": [], "majors": [], "languages": ["english", "mandarin"], "language_level": ["good command"], "hard_skills": ["excel", "word", "powerpoint", "outlook", "ms office"], "soft_skills": ["good team player", "communication skill", "fast learner", "mature"], "languages_combined": [{"language": "english", "language_level": ["good command"]}, {"language": "mandarin", "language_level": ["good command"]}]}, "experience_required": {"duration": ["at least 1-2 years"], "field": ["garment", "toys", "manufacturing", "merchandising", "trading"]}}, {"job_id": "100003009043926", "location_code": "hk", "company": "Hong Kong Knitters Limited", "job_title": "Merchandising Assistant", "description": "Requirements\n\n-Dipolma or above in Fashion & Textiles, Merchandising & Retailing is preferred;\n\n-Minimum 4 years cut and sewn knit or woven garment merchandising experience;\n\n-Previous experience in high fashion and casual wear is definitely advantage;\n\n-Excellent communication and interpersonal skill with all levels in working with customers, staff and\u00a0vendors;\n\n-Fluent in spoken and written in English, Chinese and Mandarin;\n\n-Familiar with MS Office operation\n\n-Less experience will be consider to be a Junior Merchandiser\n\nWe offer attractive remuneration packages including 13 months payment, 5 days' work, medical insurance, annual leave, wedding leave, education allowance, meal allowance and good career prospects to the right candidate(s). Interested parties, please send your full resume, with expected salary and availability, fax to (852) 2726 7590.\n\nCollected information is only for recruitment purpose.", "employment_types": ["Full Time", "Permanent"], "selling_points": [], "locations": ["Not Specified"], "categories": ["Design", "Fashion", "Manufacturing", "Garment / Textile", "Merchandising & Purchasing", "Woven / Knit"], "post_time": "2022-01-15T03:49:16Z", "salary": {"currency": null, "max": null, "min": null, "period": "monthly", "term": null}, "salary_visible": false, "title_keywords": ["merchandising assistant"], "responsibilities": ["communication", "payment", "insurance", "merchandising"], "requirements": {"degrees": [], "majors": [], "languages": ["english", "chinese", "mandarin"], "language_level": [], "hard_skills": ["ms office"], "soft_skills": ["communication", "interpersonal skill"], "languages_combined": [{"language": "english", "language_level": []}, {"language": "chinese", "language_level": []}, {"language": "mandarin", "language_level": []}]}, "experience_required": {"duration": ["4 years"], "field": ["garment", "merchandising"]}}, {"job_id": "100003009035012", "location_code": "hk", "company": "Winner Sky (International) Ltd.", "job_title": "Merchandiser / Senior Merchandiser", "description": "Job Description and responsibility\u00a0\n\nFollow up product development, sample presentation and assist Top Management for costing calculation.\nLiaise with clients and suppliers in handling product development, discuss development quality and product delivery.\nProactively work with fellow merchandising team, technical team and workshop to ensure quality on garment delivery.\nMaintain and update production record and data.\nstay connection with customer, analysis message and share with team.\n\nJob requirement\u00a0\n\nCan work under pressure\nexperienced working with European market.\ncut and sewn item, (t-shirt, jersey dress, ladies top, yoga legging, underwear boxer etc.)\nnot woven item\n10 yrs or above merchandising experience in cut and sewn garment industry\ncan share his/her idea to others, team work contributions.\ntravel to Dongguan, Cambodia or Myanmar when needed.\nCandidate with more experience will also be consider as Senior Merchandiser", "employment_types": ["Full Time"], "selling_points": [], "locations": ["Tsuen Wan Area"], "categories": ["Manufacturing", "Garment / Textile"], "post_time": "2022-01-10T05:15:54Z", "salary": {"currency": null, "max": null, "min": null, "period": "monthly", "term": null}, "salary_visible": false, "title_keywords": ["merchandiser", "senior merchandiser"], "responsibilities": ["liaise with clients", "management", "data", "workshop", "analysis", "merchandising", "quality", "maintain"], "requirements": {"degrees": [], "majors": [], "languages": [], "language_level": [], "hard_skills": ["garment industry"], "soft_skills": ["work under pressure"], "languages_combined": []}, "experience_required": {"duration": [], "field": ["garment", "merchandising"]}}, {"job_id": "100003009049410", "location_code": "hk", "company": "Showtex Hong Kong Limited", "job_title": "Production Assistant (Textile/Event/Stage insdustry)", "description": "We are now seeking for assertive and highly motivated candidate to take up the following post:\n\nFabric Merchandiser\n\nHolder of HK Polytechnic University Degree or Higher Diploma in Textile & Clothing discipline\n5 years working experience in woven and knit fabric sourcing for US / Europe markets\nKnowledge in woven and knitted fabrics\nProficiency in spoken English and Mandarin included\nWell-organized, detailed oriented, time line sensitive, able to work under pressure\nGood team player with effective communication skill\nImmediate available is preferred", "employment_types": ["Full Time"], "selling_points": ["Bespoke textile production for stage/event", "5 day work, medical insurance, discretionary bonus", "On-job training provided"], "locations": ["Kwun Tong Area"], "categories": ["Manufacturing", "Garment / Textile", "Production Planning / Control"], "post_time": "2022-01-14T09:12:44Z", "salary": {"currency": null, "max": null, "min": null, "period": "monthly", "term": null}, "salary_visible": false, "title_keywords": ["production assistant"], "responsibilities": ["communication", "work under pressure"], "requirements": {"degrees": ["university degree", "diploma"], "majors": [], "languages": ["english", "mandarin"], "language_level": ["proficiency"], "hard_skills": [], "soft_skills": ["good team player", "detailed oriented", "assertive", "communication skill", "well-organized", "motivated", "sensitive", "work under pressure"], "languages_combined": [{"language": "english", "language_level": ["proficiency"]}, {"language": "mandarin", "language_level": ["proficiency"]}]}, "experience_required": {"duration": ["5 years"], "field": []}}, {"job_id": "100003009049975", "location_code": "hk", "company": "Lululemon HK Limited", "job_title": "Senior Merchandiser (6 months)", "description": "Job Description\n\nKey Responsibilities :\n\nPlan and review full spectrum of quality policy associated product specification and customer requirement to improve the efficiency and effectiveness in preventing and detecting quality problem.\nCoordinate with production sites to identify the required inspection plans and quality standards.\nKnowledge in garment manufacturing, knowledge in both woven & knitted items, tops & bottoms\nExecute inspections assigned by head office in a timely manner\nConduct audits in the manufacturing sites of the company, suppliers and subcontractors to ensure in compliance with the set policies and procedures\nManage all compliance requirements and provide solutions and recommendations\nKeep abreast of the industrial trends in social compliance\nKnowledge in quality management, social compliance standards, international compliance standard requirements for Europe\n\nRequirements :\n\nDegree holder in Fashion Design, Textile & Clothing, or related disciplines\nMinimum 3 years experience in garment's Quality Assurance & Quality Control\nGood time management and communication skills, can work under pressure and meet tight schedules\nGood command of both written and spoken English\nGood knowledge of computer skills (email & excel)\nAdvanced knowledge in pattern creation, grading and sample creation with the ability to provide effective and cost efficient pattern and workmanship solutions and an understanding of apparel construction, material construction and properties related to fit.", "employment_types": ["Full Time", "Contract"], "selling_points": ["Experience with apparel and outerwear products", "Knowledge in fabrics & garment construction", "Eager to collaborate and learn with the team"], "locations": ["Tin Hau"], "categories": ["Manufacturing", "Garment / Textile"], "post_time": "2022-01-14T09:34:18Z", "salary": {"currency": null, "max": null, "min": null, "period": "monthly", "term": null}, "salary_visible": false, "title_keywords": ["senior merchandiser"], "responsibilities": ["management", "policies", "review", "quality", "coordinate with", "a timely manner", "inspection", "conduct audits", "compliance", "procedures", "provide solutions", "plan", "plans"], "requirements": {"degrees": ["degree holder"], "majors": ["related disciplines", "design"], "languages": ["english"], "language_level": ["good command"], "hard_skills": ["excel", "computer skills"], "soft_skills": ["efficient", "communication skills", "advanced", "work under pressure", "time management", "meet tight schedules"], "languages_combined": [{"language": "english", "language_level": ["good command"]}]}, "experience_required": {"duration": ["minimum 3 years"], "field": ["garment", "quality control", "quality assurance"]}}, {"job_id": "100003009048765", "location_code": "hk", "company": "Brother Machinery (Asia) Limited", "job_title": "Technical Specialist / Technical Support Engineer - Garment Printing / Industrial Printer", "description": "Job responsibilities:\nUnderstand wide range of ShowTex products to combine with production techniques and knowledge\nWork closely with technical and production team to ensure production quality control\nMaintain good time management and multi-tasking to execute production according to project requirement\nAssist with Operation Manager to sustain good production planning, resources allocation, inventory control and daily report\nCommunicate with all stakeholders to understand project requirement and help on assist\u00a0R&D\u00a0on new design if need\nOrganize a suitable and clean environment for production compliance to safety standard\nResponsible for daily maintenance and research for necessary tools and machinery\u00a0\nOccasional travelling and overtime work if needed\u00a0\nAssist in any ad hoc project assigned\n\u00a0\nRequirement:\nHigher diploma or above\u00a0with at least 1 year working experience in related industry\nEager to learn with passion\u00a0and further develop in the industry\nDetailed minded with good time management and able to perform multi-tasking\nGood command of English/Cantonese/Mandarin is a must\nCan do attitude, motivated and problem solving mind set are required\nWorking Area: Yau Tong (10 mins walk from Yau Tong MTR station)", "employment_types": ["Full Time", "Permanent"], "selling_points": [], "locations": ["Kwai Hing"], "categories": ["Engineering", "Mechanical", "Manufacturing", "Garment / Textile", "Sales, CS & Business Devpt", "Technical Sales / Sales Engineer"], "post_time": "2022-01-15T03:50:04Z", "salary": {"currency": null, "max": null, "min": null, "period": "monthly", "term": null}, "salary_visible": false, "title_keywords": ["technical specialist", "technical support engineer"], "responsibilities": ["communicate with", "management", "ad hoc", "maintenance", "compliance", "production planning", "design", "maintain", "inventory control", "quality control", "daily report"], "requirements": {"degrees": ["higher diploma or above"], "majors": [], "languages": ["cantonese", "english", "mandarin"], "language_level": ["good command"], "hard_skills": ["problem solving"], "soft_skills": ["problem solving", "eager to learn", "multi-tasking", "motivated", "time management", "detailed"], "languages_combined": [{"language": "cantonese", "language_level": ["good command"]}, {"language": "english", "language_level": ["good command"]}, {"language": "mandarin", "language_level": ["good command"]}]}, "experience_required": {"duration": ["at least 1 year"], "field": ["related"]}}, {"job_id": "100003009049094", "location_code": "hk", "company": "South Asia Knitting Factory Limited", "job_title": "Purchaser - Yarn (5 day work)", "description": "\u00a0Requirements\n\n- Higher Diploma or above;\n\n- Minimum\u00a02 years cut and sewn knit experience;\n\n- Fluent in spoken and written in English and Mandarin;\n\n- Familiar with MS Office\n\n- Fresh graduates will be considered\n\n- More experience will be Junior Merchandiser\n\nWe offer attractive remuneration packages including 13 months payment, medical insurance, annual leave (10~16 days), 10 days wedding leave, education allowance and good career prospects to the right candidate(s). Interested parties, please send your full resume, with expected salary and availability, fax to (852) 2726 7590.\n\nCollected information is strictly for recruitment purpose.", "employment_types": ["Full Time", "Permanent"], "selling_points": ["Purchaser (Yarn)", "yarn sourcing", "4 years of solid experience in yarn is perferable;"], "locations": ["Kwun Tong"], "categories": ["Manufacturing", "Garment / Textile"], "post_time": "2022-01-14T08:06:46Z", "salary": {"currency": null, "max": null, "min": null, "period": "monthly", "term": null}, "salary_visible": false, "title_keywords": [], "responsibilities": ["payment", "insurance"], "requirements": {"degrees": ["higher diploma or above"], "majors": [], "languages": ["english", "mandarin"], "language_level": ["fluent"], "hard_skills": ["ms office"], "soft_skills": [], "languages_combined": [{"language": "english", "language_level": ["fluent"]}, {"language": "mandarin", "language_level": ["fluent"]}]}, "experience_required": {"duration": ["minimum 2 years"], "field": []}}, {"job_id": "100003009047287", "location_code": "hk", "company": "HK Research Institute of Textiles & Apparel Ltd", "job_title": "Project Manager / Project Officer (Ref. No.: HKRITA-PM-11/21)", "description": "Responsibilities\nProviding Service Support and Technical Trouble Shooting for Brother products to our customers in HK and ASEAN\nProviding Print\u00a0technical support to our product distributors\nSupervising and managing distributors (e.g. Training)\nMaintaining CRM system\nData analyzing and Reporting (Failure ratio, parts demand forecast, field situation etc.)\nAttending trade exhibition to provide technical advice for visitors' inquiry\n\nTraining & Development\n\nProvide product training\nProvide in house E-learning platform and study subsidy for job related topics\n\nOur Ideal Candidate\n\nDiploma,\u00a0Higher Diploma or\u00a0Undergraduate Bachelor Degree\n3 years Engineering, Electrical or Printing field working experience (Garment printing industry experience will be a plus)\u00a0\nCommunication skill, critical thinking and troubleshooting skill\nWell planning, organizing and interpersonal skills\nSelf-motivated and Team player\nGood command of both written and spoken English (Mandarin will be an advantage)\n\nStaff Benefits\n\n5 days work\nBank Holiday\nFlexible Working Hours\nWork From Home\nTransportation Allowance\nOvertime pay\nMedical & Dental Insurance\nBody check\n\nInterested?\nIf you are interested please send your\u00a0full resume,\u00a0current and expected salary\u00a0and availability by clicking \"APPLY NOW\".\n\n*Personal data provided are treated in strictest confidence and for recruitment purposes only.\u00a0 All information will be destroyed after the process completed.*", "employment_types": ["Full Time", "Contract"], "selling_points": [], "locations": ["Hung Hom"], "categories": ["Engineering", "Chemical", "Manufacturing", "Garment / Textile", "Sciences, Lab, R&D", "Research & Development (R&D)"], "post_time": "2022-01-15T03:50:47Z", "salary": {"currency": null, "max": null, "min": null, "period": "monthly", "term": null}, "salary_visible": false, "title_keywords": ["project manager", "project officer"], "responsibilities": ["reporting", "supervising", "maintaining", "data", "technical support", "technical advice", "troubleshooting", "communication", "forecast", "planning"], "requirements": {"degrees": ["diploma", "degree", "bachelor"], "majors": [], "languages": ["english", "mandarin"], "language_level": ["advantage", "good command"], "hard_skills": ["plus"], "soft_skills": ["self-motivated", "communication skill", "troubleshooting", "learning", "interpersonal skills", "team player", "ideal"], "languages_combined": [{"language": "english", "language_level": ["advantage", "good command"]}, {"language": "mandarin", "language_level": ["advantage", "good command"]}]}, "experience_required": {"duration": ["3 years"], "field": ["garment", "engineering"]}}, {"job_id": "100003009051228", "location_code": "hk", "company": "Easy Job Centre", "job_title": "Garment Technician / Senior Garment Technician (5 days)", "description": "Job Description:\n\nLiaising and price negotiating with suppliers, yarn sourcing;\nCommunicate with fabric mill and customers;\nEnsure the quality meets customers\u2019 standards and requirements;\nPrepare quotation for sales manager review;\nFollow up from fabrics sourcing to bulk shipment;\nInventory control and delivery arrangement;\n\nJob Requirement:\n\n4\u00a0years of solid experience in yarn is perferable;\nPolytechnic / IVE/ F.5 or above\u00a0graduate in Merchandising, Garments, Textile or\u00a0related discipline;\nMature, independent, detail-minded, initiative, stable with good interpersonal\u00a0& communication skills;\nGood command of English, Chinese & Mandarin;\nFamiliar with MS Office - Word, Excel, PowerPoint & Chinese word processing.\nWe provide the high caliber\u00a0with\u00a0attractive salary, good career prospect and benefits package\u00a0including\u00a05 day work week,\u00a0discretionary bonus,\u00a0education allowance and\u00a0medical scheme.\nInterested parties please send your full resume with your availability, current and expected salary details by clicking \"APPLY NOW\"\n\n(All applications will be treated in strict confidence and data collected will be used for recruitment purposes only)", "employment_types": ["Full Time"], "selling_points": [], "locations": ["Yau Tsim Mong Area"], "categories": ["Manufacturing", "Garment / Textile", "Merchandising & Purchasing", "Woven / Knit", "Quality Assurance, Control & Testing / ISO"], "post_time": "2022-01-15T05:19:58Z", "salary": {"currency": "HKD", "max": 54999, "min": 20000, "period": "monthly", "term": null}, "salary_visible": true, "title_keywords": ["technician"], "responsibilities": ["communicate with", "review", "quotation", "quality", "inventory control"], "requirements": {"degrees": [], "majors": [], "languages": ["english", "chinese", "mandarin"], "language_level": ["good command"], "hard_skills": ["excel", "chinese word processing", "word", "powerpoint", "ms office"], "soft_skills": ["detail-minded", "communication skills", "independent", "mature", "stable", "interpersonal", "initiative"], "languages_combined": [{"language": "english", "language_level": ["good command"]}, {"language": "chinese", "language_level": ["good command"]}, {"language": "mandarin", "language_level": ["good command"]}]}, "experience_required": {"duration": ["4 years"], "field": []}}, {"job_id": "100003009044795", "location_code": "hk", "company": "Profits Fund Fashion Manufacturing Ltd", "job_title": "Merchandiser", "description": "Woven / Denim\u00a0 \u00a0 \u00a0 \u00a0 \u00a0 \u00a02 Posts\nKnit\u00a0 \u00a0 \u00a0 \u00a0 \u00a0 \u00a0 \u00a0 \u00a0 \u00a0 \u00a0 \u00a0 \u00a0 \u00a0 \u00a0 \u00a0 1 Post\nSweater \u00a0 \u00a0 \u00a0 \u00a0 \u00a0 \u00a0 \u00a0 \u00a0 \u00a0 \u00a0 \u00a0 \u00a01 Post\nBra & Underwear\u00a0 \u00a0 \u00a0 \u00a01 Post\nOuterwear\u00a0 \u00a0 \u00a0 \u00a0 \u00a0 \u00a0 \u00a0 \u00a0 \u00a0 \u00a0 1 Post\nPattern Maker\u00a0 \u00a0 \u00a0 \u00a0 \u00a0 \u00a0 \u00a01 Post\n\nJob Responsibilities:\n\nProvide technical support to tech team and merchandising department\u00a0\nKeep track of Tech Pack with update information to merchandising and vendor\nProvide technical advice to tech team and vendor for problem solving\nReview samples and ensure the products meets expectations as provided in the tech pack\n\nJob\u00a0Requirements:\n\nSecondary School level\n3-4 years' experience in technical and fitting\nGood technical skills in Garment construction\nAble to communicate in English and Mandarin\n\nInterested parties, please send your resume with expected salary by clicking the below \"apply now\" button.\u00a0You can ask click on the website\u00a0www.easyjobhk.com\u00a0for more details about the company", "employment_types": ["Full Time", "Permanent"], "selling_points": [], "locations": ["Kwai Fong"], "categories": ["Manufacturing", "Garment / Textile", "Merchandising & Purchasing", "Woven / Knit"], "post_time": "2022-01-13T06:17:54Z", "salary": {"currency": null, "max": null, "min": null, "period": "monthly", "term": null}, "salary_visible": false, "title_keywords": ["merchandiser"], "responsibilities": ["technical support", "technical advice", "review", "merchandising"], "requirements": {"degrees": [], "majors": [], "languages": ["english", "mandarin"], "language_level": [], "hard_skills": [], "soft_skills": ["technical skills"], "languages_combined": [{"language": "english", "language_level": []}, {"language": "mandarin", "language_level": []}]}, "experience_required": {"duration": ["3-4 years"], "field": []}}, {"job_id": "100003009050422", "location_code": "hk", "company": "Majestic Product Development Ltd.", "job_title": "Assistant Merchandiser/ Merchandiser (No experience candidates are welcome)", "description": "Responsibilities:\n\nMonitor and follow up orders, shipments and testing;\nHandle sample development;\n\nRequirements:\n\nF.7 or above;\nAt least 1-2 years merchandising experience (manufacturing / trading / buying office), and preferable in garment / toys field;\nGood command of English / Mandarin and MS Office software (Excel, Word, PowerPoint & Outlook);\nGood communication skill;\nWell organize, mature, a good team player and fast learner;\nOccasional travel to China;\nImmediate available is highly preferable.\n\n\nWe offer attractive competitive package to right candidates.\n\nAll related information will be used solely for recruitment purpose and will be destroyed upon completion of recruitment process.", "employment_types": ["Full Time", "Permanent"], "selling_points": [], "locations": ["Tsim Sha Tsui"], "categories": ["Manufacturing", "Garment / Textile", "Merchandising & Purchasing", "Toy", "Procurement / Purchasing / Sourcing"], "post_time": "2022-01-14T10:22:52Z", "salary": {"currency": null, "max": null, "min": null, "period": "monthly", "term": null}, "salary_visible": false, "title_keywords": ["merchandiser", "assistant merchandiser"], "responsibilities": ["follow up orders", "monitor", "testing"], "requirements": {"degrees": [], "majors": [], "languages": ["english", "mandarin"], "language_level": ["good command"], "hard_skills": ["excel", "word", "powerpoint", "outlook", "ms office"], "soft_skills": ["good team player", "communication skill", "fast learner", "mature"], "languages_combined": [{"language": "english", "language_level": ["good command"]}, {"language": "mandarin", "language_level": ["good command"]}]}, "experience_required": {"duration": ["at least 1-2 years"], "field": ["garment", "toys", "manufacturing", "merchandising", "trading"]}}, {"job_id": "100003009048565", "location_code": "hk", "company": "Verde Apparel Limited", "job_title": "Fabric Merchandiser", "description": "We are now seeking for assertive and highly motivated candidate to take up the following post:\n\nFabric Merchandiser\n\nHolder of HK Polytechnic University Degree or Higher Diploma in Textile & Clothing discipline\n5 years working experience in woven and knit fabric sourcing for US / Europe markets\nKnowledge in woven and knitted fabrics\nProficiency in spoken English and Mandarin included\nWell-organized, detailed oriented, time line sensitive, able to work under pressure\nGood team player with effective communication skill\nImmediate available is preferred", "employment_types": ["Full Time", "Permanent"], "selling_points": [], "locations": ["Tsuen Wan Area"], "categories": ["Manufacturing", "Garment / Textile"], "post_time": "2022-01-14T06:49:33Z", "salary": {"currency": null, "max": null, "min": null, "period": "monthly", "term": null}, "salary_visible": false, "title_keywords": ["fabric merchandiser"], "responsibilities": ["communication", "work under pressure"], "requirements": {"degrees": ["university degree", "diploma"], "majors": [], "languages": ["english", "mandarin"], "language_level": ["proficiency"], "hard_skills": [], "soft_skills": ["good team player", "detailed oriented", "assertive", "communication skill", "well-organized", "motivated", "sensitive", "work under pressure"], "languages_combined": [{"language": "english", "language_level": ["proficiency"]}, {"language": "mandarin", "language_level": ["proficiency"]}]}, "experience_required": {"duration": ["5 years"], "field": []}}, {"job_id": "100003009045530", "location_code": "hk", "company": "Tri-Win Limited", "job_title": "QC/QA at Bangladesh", "description": "Job Description\n\nKey Responsibilities :\n\nPlan and review full spectrum of quality policy associated product specification and customer requirement to improve the efficiency and effectiveness in preventing and detecting quality problem.\nCoordinate with production sites to identify the required inspection plans and quality standards.\nKnowledge in garment manufacturing, knowledge in both woven & knitted items, tops & bottoms\nExecute inspections assigned by head office in a timely manner\nConduct audits in the manufacturing sites of the company, suppliers and subcontractors to ensure in compliance with the set policies and procedures\nManage all compliance requirements and provide solutions and recommendations\nKeep abreast of the industrial trends in social compliance\nKnowledge in quality management, social compliance standards, international compliance standard requirements for Europe\n\nRequirements :\n\nDegree holder in Fashion Design, Textile & Clothing, or related disciplines\nMinimum 3 years experience in garment's Quality Assurance & Quality Control\nGood time management and communication skills, can work under pressure and meet tight schedules\nGood command of both written and spoken English\nGood knowledge of computer skills (email & excel)\nAdvanced knowledge in pattern creation, grading and sample creation with the ability to provide effective and cost efficient pattern and workmanship solutions and an understanding of apparel construction, material construction and properties related to fit.", "employment_types": ["Full Time"], "selling_points": [], "locations": ["Overseas"], "categories": ["Manufacturing", "Garment / Textile"], "post_time": "2022-01-13T08:01:50Z", "salary": {"currency": null, "max": null, "min": null, "period": "monthly", "term": null}, "salary_visible": false, "title_keywords": [], "responsibilities": ["management", "policies", "review", "quality", "coordinate with", "a timely manner", "inspection", "conduct audits", "compliance", "procedures", "provide solutions", "plan", "plans"], "requirements": {"degrees": ["degree holder"], "majors": ["related disciplines", "design"], "languages": ["english"], "language_level": ["good command"], "hard_skills": ["excel", "computer skills"], "soft_skills": ["efficient", "communication skills", "advanced", "work under pressure", "time management", "meet tight schedules"], "languages_combined": [{"language": "english", "language_level": ["good command"]}]}, "experience_required": {"duration": ["minimum 3 years"], "field": ["garment", "quality control", "quality assurance"]}}, {"job_id": "100003009046831", "location_code": "hk", "company": "L.L.Bean, Inc.", "job_title": "Senior Fabric Merchandiser (Knit & Sweater) - US buying office", "description": "Job Duties :\n\nWork with US sourcing team on fabric material sourcing, color review and development/ commercialization\nCommunicate with mills/ suppliers on order & production tracking, fabric quality testing and color approval, cost & lead time negotiation and development\nResearch on fabric trend and maintain fabric library\n\nJob Requirements :\n\nF.5 or above;\u00a0 Polytechnic/ IVE graduate in Textile/Clothing studies preferred\u00a0\n8 years relevant experience in fabric sourcing ; preferable in knit and sweater\nPrevious work experience in fabric mill is an advantageous\nDetail oriented with high initiative and strong team spirit\n\nGood command of written and spoken English and Cantonese; Mandarin a plus\nPC knowledge is required (MS-Word, Excel and Outlook e-mail)\nOccasional overseas travelling may be required\nImmediate available is required\n\nWe offer a competitive salary and benefits package: 5-day week; 13-month payment; employee medical, life and disability insurance; discretionary bonus; tuition reimbursement; and merchandise discount.\n\nPlease send your resume (with employment history, expected salary and available date) to L.L. Bean, Inc. - HK, Human Resources Department by clicking \"Apply Now\".\u00a0The information supplied for the purposes of this application will be used only in accordance with L.L. Bean\u2019s data policies.\n", "employment_types": ["Full Time"], "selling_points": [], "locations": ["Ngau Tau Kok"], "categories": ["Manufacturing", "Garment / Textile", "Merchandising & Purchasing", "Woven / Knit", "Textiles"], "post_time": "2022-01-14T01:23:55Z", "salary": {"currency": null, "max": null, "min": null, "period": "monthly", "term": null}, "salary_visible": false, "title_keywords": ["fabric merchandiser"], "responsibilities": ["communicate with", "cost", "review", "quality", "testing", "commercialization", "maintain", "tracking"], "requirements": {"degrees": [], "majors": [], "languages": ["cantonese", "english", "mandarin"], "language_level": ["good command"], "hard_skills": ["ms-word", "plus", "excel", "outlook", "pc knowledge"], "soft_skills": ["detail oriented", "team spirit", "initiative"], "languages_combined": [{"language": "cantonese", "language_level": ["good command"]}, {"language": "english", "language_level": ["good command"]}, {"language": "mandarin", "language_level": []}]}, "experience_required": {"duration": ["8 years"], "field": ["relevant experience"]}}, {"job_id": "100003009043358", "location_code": "hk", "company": "Smart Force (HK) Limited", "job_title": "Sales Director", "description": "Job Highlights\n\nCustomized career development opportunities\nPerformance bonus\nKwun Tong Area\n5 working days\n\n\u00a0\nJob Description\n\nIn order to meet the fast growing businesses, we are looking for a capable candidate with professional skill for sales.\u00a0 The primary focus of the role is to be responsible for develop new business opportunities, manage assigned clients and cultivate strong working relationships with the assigned customers to drive customer satisfaction and profit growth.\u00a0 Analyze customer category and brand sales and evaluate promotions for business opportunities to grow sales, volume and distribution\n\n\u00a0Job Responsibilities\n\nHandle yarn sales businesses\nUnderstand customer expectation and deliver first class services\nIdentify global consolidation opportunities and develop new business, especially focus on OVERSEAS Markets\nContinuous updating of market knowledge inc advancement in technologies and sustainability.\nExperience of working directly with mills and cotton suppliers across the globe.\n\nJob Requirements\n\nDegree or above in relevant discipline\nAt least 10 years working experience with min 5 years for the relevant field\nStrong yarn knowledge, especially for Cotton and/or Cotton blend\nKnowledge for knit items is an advantage\nGood communication and organizational skill with attention to details\nFluent English speaking is a must\nWe offer competitive salary and benefits to the right candidate.\u00a0 Interested parties please send your application with date of availability, present & expected salary in attn Mr. Chow.", "employment_types": ["Full Time"], "selling_points": ["10 years or above working experience", "Strong yarn knowledge, especially for Cotton", "Competitive salary and benefits"], "locations": ["Kwun Tong"], "categories": ["Manufacturing", "Garment / Textile", "Sales, CS & Business Devpt", "Direct Sales"], "post_time": "2022-01-13T05:17:10Z", "salary": {"currency": null, "max": null, "min": null, "period": "monthly", "term": null}, "salary_visible": false, "title_keywords": ["director", "sales"], "responsibilities": ["evaluate", "business opportunities", "develop new business", "working relationships"], "requirements": {"degrees": ["degree or above"], "majors": [], "languages": ["english"], "language_level": ["fluent"], "hard_skills": [], "soft_skills": ["communication", "organizational skill", "attention to details"], "languages_combined": [{"language": "english", "language_level": ["fluent"]}]}, "experience_required": {"duration": ["at least 10 years", "min 5 years"], "field": []}}, {"job_id": "100003009049091", "location_code": "hk", "company": "South Asia Knitting Factory Limited", "job_title": "Senior Merchandiser (Sweater) - 5  day work", "description": "Job Duties:\n\nResponsible for the coordination of operating merchandising cycle from sample development, sourcing, costing till production\nLiaise with overseas buyer and PRC factories\n\nJob Requirement:\n\nForm\u00a07 or above with minimum 5 years\u2019 merchandising experience in sweater, experience in factories is an advantage\nFamiliar with USA market is preferable\nWell-organized, detail-minded and good interpersonal skills\nGood command of both written and spoken English, Chinese & Mandarin\nWe provide the high caliber\u00a0with\u00a0attractive salary, good career prospect and benefits package\u00a0including\u00a05 day work,\u00a0\u00a0discretionary bonus,\u00a0education allowance and\u00a0medical scheme.\nInterested parties please send your full resume with your availability, current and expected salary details by \"APPLY\"\n\n(All applications will be treated in strict confidence and data collected will be used for recruitment purposes only)", "employment_types": ["Full Time", "Permanent"], "selling_points": ["Fluent Speaking and Writing English", "Diploma in Fashion / Textile is an advantage", "5 days work"], "locations": ["Kwun Tong Area"], "categories": ["Manufacturing", "Garment / Textile", "Merchandising & Purchasing", "Sweater"], "post_time": "2022-01-14T08:06:45Z", "salary": {"currency": null, "max": null, "min": null, "period": "monthly", "term": null}, "salary_visible": false, "title_keywords": ["senior merchandiser"], "responsibilities": ["liaise with", "merchandising", "coordination"], "requirements": {"degrees": [], "majors": [], "languages": ["english", "chinese", "mandarin"], "language_level": ["good command"], "hard_skills": [], "soft_skills": ["detail-minded", "well-organized", "interpersonal skills"], "languages_combined": [{"language": "english", "language_level": ["good command"]}, {"language": "chinese", "language_level": ["good command"]}, {"language": "mandarin", "language_level": ["good command"]}]}, "experience_required": {"duration": ["minimum 5 years"], "field": ["merchandising"]}}, {"job_id": "100003009050416", "location_code": "hk", "company": "Majestic Product Development Ltd.", "job_title": "Shipping Clerk (No experience candidates are welcome)", "description": "Job Highlights\n\u00a0Manage full set of I/E , L/C and shipping\n\u00a0At least 2 years relevant experience\n\u00a0Form 5 or above\nJob Description\n\nJob Responsibilities:\n\nManage full set of I/E , L/C and shipping documents\nMonitor shipment schedule and assign carriers to meet delivery requirements\nCoordinate with forwarder for delivery arrangement\n\nRequirements:\n\nForm 5 or above\nAt least 7 years relevant experience in handling full set of shipping document\nGood command of English and Mandarin\nSelf-motivated, independent, well-organized and with sense of responsible\nProficient in Microsoft Excel and Word Office\nImmediate availability is highly preferable\n\nWe offer attractive competitive remuneration, annual holiday, career growth opportunities, birthday leave, MPF, dental and medical benefit to right candidates.\n\nInterested parties please send your resume,\u00a0current\u00a0and\u00a0expected salary\u00a0to our HR Department via email by clicking \"Apply Now\"\n\nAll related information will be used solely for recruitment purpose and will be destroyed upon completion of recruitment process.", "employment_types": ["Full Time", "Permanent"], "selling_points": [], "locations": ["Tsim Sha Tsui"], "categories": ["Manufacturing", "Garment / Textile"], "post_time": "2022-01-14T10:21:18Z", "salary": {"currency": null, "max": null, "min": null, "period": "monthly", "term": null}, "salary_visible": false, "title_keywords": ["shipping clerk"], "responsibilities": ["shipping documents", "coordinate with", "monitor shipment schedule"], "requirements": {"degrees": ["form 5 or above"], "majors": [], "languages": ["english", "mandarin"], "language_level": ["good command"], "hard_skills": ["shipping document", "word", "microsoft excel"], "soft_skills": ["self-motivated", "independent", "well-organized", "responsible"], "languages_combined": [{"language": "english", "language_level": ["good command"]}, {"language": "mandarin", "language_level": ["good command"]}]}, "experience_required": {"duration": ["at least 7 years"], "field": ["relevant experience"]}}, {"job_id": "100003009043131", "location_code": "hk", "company": "MGF Sourcing Far East, Limited", "job_title": "Senior Merchandiser (Woven)", "description": "PRINCIPAL DUTIES & RESPONSIBILITIES:\nManage development to bulk production process\nWork with garment factories to achieve best prices\nWork to ensure a seamless co-ordination with internal colleagues related to development issues\nMonitor suppliers and the production market to update market situation\nPartner with local and overseas technical teams to ensure Brand requirements are met, i.e. fit, fabric, color, wash, general quality assurance and production techniques\nReview tech packs and samples with fit tech to ensure the product requirements are followed\nLiaison with Fabric team to ensure on-time submission of quality and obtain approval\nEnsure clear and timeliness of the communication with all the counterparts, i.e. clients, Fabric teams, Technical teams etc.\nProvide updated market information to customers in respect of style, fabrics, delivery etc.\nProvide information of competitors\u2019 activities within ability to access the market\n\u00a0JOB SPECIFICATIONS (e.g. Qualification, Job Experience):\nCollege degree or equivalent work experience\n6-10 years' related work experience in sourcing and production\nStrong technical knowledge in woven apparel\nDetail-oriented, strong planning and coordination skills\nExcellent verbal and written communication skills (strong English language skills)\nAbility to work well within a team environment\nWe offer 5\u2013day work week, attractive compensation package and comprehensive employee benefits to the right candidate. Interested parties please send your full resume with your existing salary and expected salary by clicking \"Apply Now\".\n\nAll personal information collected will be kept for employment related purposes only", "employment_types": ["Full Time", "Permanent"], "selling_points": ["Senior Merchandiser on Woven apparel", "Manage development to bulk production process", "6-10 years' work exp. in sourcing & production"], "locations": ["Kwun Tong"], "categories": ["Manufacturing", "Garment / Textile", "Merchandising & Purchasing", "Woven / Knit"], "post_time": "2022-01-12T09:52:26Z", "salary": {"currency": null, "max": null, "min": null, "period": "monthly", "term": null}, "salary_visible": false, "title_keywords": ["senior merchandiser"], "responsibilities": ["market information", "production process", "review", "quality", "monitor", "teams", "communication", "specifications", "coordination", "planning"], "requirements": {"degrees": ["degree"], "majors": [], "languages": ["english"], "language_level": ["excellent"], "hard_skills": [], "soft_skills": ["communication skills", "coordination skills", "detail-oriented", "clear", "communication"], "languages_combined": [{"language": "english", "language_level": ["excellent"]}]}, "experience_required": {"duration": ["6-10 years"], "field": ["related"]}}, {"job_id": "100003009048346", "location_code": "hk", "company": "Top Personnel Consultant", "job_title": "Business Development Director (Zipper / Trims \u2013 Global Market)", "description": "Our client is a manufacturer of zipper & garment trims located at Kwun Tong\u00a0with 5 days\u2019 work urgently looking for a Business Development Director\u00a0to join their company with details as follows:\n\nResponsibilities:\n\n\u0178\u00a0\u00a0 Explore & develop new business in Global\n\n\u0178\u00a0\u00a0 Conduct market research to identify market trend\n\nY..\u00a0 \u00a0 \u00a0 \u00a0 \u00a0Supervise\u00a0 3 S&M Manager\n\nRequirements:\n\n\u0178\u00a0\u00a0 Degree holder\n\n\u0178\u00a0\u00a0 10 years in sales & marketing experience in zipper, garment trims or accessories\n\n\u0178\u00a0 \u00a0With supervisory experience\n\n\u0178\u00a0\u00a0 Can bring clientele\u00a0\n\n\u0178\u00a0\u00a0 Strong communication skill with good command of spoken Mandarin\u00a0& English\n\nSalary highly negotiable depends on qualifications & experience.\n\nInterested parties, please email detailed resume by Clicking \"Apply Now\"\u00a0or call 2866 1088 (Ms. Yuen) for further inquiries.\n\nFor more information about our\u00a0agency, please visit www.toppersonnel.com.hk\n\nThe information provided by applicants will be used for employment related purpose only.", "employment_types": ["Full Time", "Permanent"], "selling_points": ["Manufacturer of Zippers & trim, bring clientele", "BD for global Markets, 10 yrs relevant exp., 5 D", "$ & benefits negotiable + attractive com, KwunTong"], "locations": ["Kwun Tong"], "categories": ["Sales, CS & Business Devpt", "Business Development", "Manufacturing", "Garment / Textile", "Merchandising & Purchasing", "Woven / Knit"], "post_time": "2022-01-14T06:23:26Z", "salary": {"currency": null, "max": null, "min": null, "period": "monthly", "term": null}, "salary_visible": false, "title_keywords": ["business development director"], "responsibilities": ["conduct market research", "develop new business"], "requirements": {"degrees": ["degree holder"], "majors": [], "languages": ["english", "mandarin"], "language_level": ["good command"], "hard_skills": [], "soft_skills": ["communication skill"], "languages_combined": [{"language": "english", "language_level": ["good command"]}, {"language": "mandarin", "language_level": ["good command"]}]}, "experience_required": {"duration": ["10 years"], "field": ["garment", "marketing", "supervisory experience"]}}, {"job_id": "100003009039300", "location_code": "hk", "company": "Giordano Limited", "job_title": "Assistant QA Manager", "description": "Responsibilities\n\nTo ensure products meet the quality requirements of our customers (especially newly developed markets)\nTo build quality concepts in the system and process to deliver consistency\nCoordinate with the corporate office and different teams to deliver results\u00a0\nUnderstand the quality requirement of newly developed markets & current standards to establish a suitable quality plan for those markets\nTo implement and communicate the plans to the vendors & all concerned parties\u00a0\nTo identify & evaluate risks in design, material & trims early in the process concerning the newly developed markets\nEnsure vendors conduct required tests and compliance with standards to ensure on-time delivery. Make proper filing records\u00a0\nTo audit vendors and arrange QC inspection\nConduct pre-production meetings, on-site inspections in the supplier's office or through zoom meetings\nIdentify and fix the ongoing quality problems and continuously identify areas of improvement\nCommunicate constantly with other teams to align goals and objectives\nProvide updated QA reports on a continued basis\n\n\u00a0\u00a0Qualifications:\n\nBachelor's degree in Industrial engineering/garment/textile\nExperience of at least five years in QA/QC in the garment/textile industry\nGood understanding of knitting and woven apparel\nGood English proficiency & hands-on knowledge of computer & QA statistics\nHaving analytical and logical thinking and must have good attention to detail\nWilling to travel\u00a0\nImmediate available are preferred", "employment_types": ["Full Time", "Permanent"], "selling_points": ["5 days work, 9:00 am to 5:00 pm", "5 years experience in QA/QC in garment industry", "Immediate available are preferred"], "locations": ["Lai Chi Kok"], "categories": ["Manufacturing", "Garment / Textile", "Quality Assurance, Control & Testing / ISO"], "post_time": "2022-01-11T09:23:11Z", "salary": {"currency": null, "max": null, "min": null, "period": "monthly", "term": null}, "salary_visible": false, "title_keywords": ["manager", "assistant"], "responsibilities": ["pre-production", "compliance", "teams", "quality", "coordinate with", "design", "evaluate", "audit", "inspection", "reports", "site inspections", "quality plan", "plans"], "requirements": {"degrees": ["degree", "bachelor"], "majors": ["engineering"], "languages": ["english"], "language_level": ["proficiency", "good"], "hard_skills": ["make"], "soft_skills": ["hands-on", "attention to detail"], "languages_combined": [{"language": "english", "language_level": ["proficiency", "good"]}]}, "experience_required": {"duration": ["at least five years"], "field": ["garment", "qa", "textile"]}}, {"job_id": "100003009043854", "location_code": "hk", "company": "Top Form International Limited", "job_title": "IT Project Manager", "description": "Job Responsibilities:\n\n\nReport to Group Technology Director, the incumbent will collaborate amongst business units, IT Teams and external vendors to drive technical development work of key upgrade and digital transformation initiatives that are aligned to group business objectives\nAssist in the formulation and realization of information technology strategies and digital transformation programs that can enable the success of business initiatives\nPerform master planning, organizing, staffing, controlling of programs and project activities to ensure successful project delivery with expected results and benefits within budget and on-time\nPlay an important role in the development of the next generation ERP platform to optimize vertical business operation for the Group\nWork closely with application, infrastructure and business process optimization projects\nOccasional travel is required\n\nJob Requirements:\n\n\nDegree holder in Information Technology, Information Management or related disciplines\nHolder of Project Management Certifications such as PMP, PRINCE2 or equivalent\nMinimum 5 years\u2019 solid experience in designing, developing, deploying and enhancing enterprise class web based application systems for regional multiple locations, manufacturing and supply chain businesses\nFamiliar with problem solving and programming methodology, able to identify system and programming issues and resourceful in providing solutions\nFamiliar with current technology such as RPA, BI reporting, AI, and IoT\nAble to perform Proof-of-Concept for new technology adoption\nExcellent interpersonal and leadership skills\nGood command of written and spoken English, Cantonese and Mandarin\nSelf-starter, hands-on, result-oriented, good team player and high level of integrity\nGarment manufacturing experience is an advantage\n\nWe offer competitive remuneration package including 5-day work week, birthday leave, personal accident insurances as well as excellent career prospects to the right candidate. Interested parties please send full resume with current and expected salary to the Group HR & Administration\u00a0Department.\u00a0\n\nFor more details about our Group, please visit our website at http://www.topformbras.com/\n\nWe are an equal opportunity employer. We value the diversity of individuals, ideas, perspectives, insights and values, and what they bring to the workplace. Applications from all qualified candidates are welcome. Personal data collected will be kept and handled confidentially by authorized personnel for recruitment purpose only. It may also be disclosed to our subsidiaries or associates to process the information for appointment. Applicants who are not contacted within four weeks may consider their application unsuccessful. The applications will be retained for a maximum period of 12 months after the selection process is finalized and we may refer suitable applicants to other vacancies within the Group. A copy of our Personal Information Collection Statement can be provided upon request by contacting Group HR & Administration Department at the above email address.", "employment_types": ["Full Time", "Permanent"], "selling_points": ["Collaborate amongst team for technical development", "Formulate and realize IT strategies and programs", "5-days work, 13-mth salary, Birthday Leave"], "locations": ["Wong Tai Sin Area"], "categories": ["Manufacturing", "Garment / Textile", "Information Technology (IT)", "IT Project Management / Team Lead", "IT Management"], "post_time": "2022-01-13T02:11:26Z", "salary": {"currency": null, "max": null, "min": null, "period": "monthly", "term": null}, "salary_visible": false, "title_keywords": ["it project manager"], "responsibilities": ["collaborate", "business operation", "business initiatives", "budget", "technology strategies", "teams", "infrastructure", "business process", "master planning", "report"], "requirements": {"degrees": ["degree holder"], "majors": ["related disciplines", "information technology"], "languages": ["cantonese", "english", "mandarin"], "language_level": ["good command"], "hard_skills": ["bi", "web", "ai", "problem solving", "project management", "rpa", "programming", "pmp"], "soft_skills": ["result-oriented", "good team player", "resourceful", "leadership skills", "integrity", "problem solving", "project management", "hands-on", "interpersonal"], "languages_combined": [{"language": "cantonese", "language_level": ["good command"]}, {"language": "english", "language_level": ["good command"]}, {"language": "mandarin", "language_level": ["good command"]}]}, "experience_required": {"duration": ["minimum 5 years"], "field": ["garment", "manufacturing", "supply chain", "developing", "application systems"]}}, {"job_id": "100003009044452", "location_code": "hk", "company": "Newtimes Development Limited", "job_title": "Merchandiser (Woven's / Knit's wear)", "description": "Essential Duties & Responsibilities\n\nLiaise closely with internal counterparts of design, technical, QC and logistics for orders follow-up.\nExecute the T&A on time to ensure material on delivery to offshore factories for both production and sampling, close monitor bulk order follow up with correct quality and quantity.\nAssist the team superiors in the costing and quotation review.\nResponsible for system data entry, tech pack and BOM download.\nPrepare presentation for the buying trip including sample styles, price, supplier and factory information.\nEnsure that fabric/trims/proto/samples are developed to meet customer\u2019s requirements, adequate quotations are negotiated and obtained to achieve business objectives.\u00a0 Follow up on development.\n\nJob Requirements (Education / Experience / Skill-set)\n\nImmediately available is preferable.\nDiploma or above in Textile / Clothing or related discipline.\nAt least 2- 4 years\u2019 solid experience in the garment trading field.\nExperience in USA or Canada market is highly preferable.\nDetail-minded, strong accuracy with good problem-solving skills and able to meet various deadlines.\nStrong multi-tasking ability.\nA good team player with strong communication skills.\nGood command of both written and spoken English, Chinese including Mandarin.\nProficient in Microsoft Office \u2013 Word, Excel, Powerpoint, Outlook\n\nInterested parties please send your application with\u00a0current salary, expected salary and availability\u00a0via \u201cAPPLY NOW\u201d button.\n\n(Collected personal data will be kept strictly confidential and used for recruitment purpose only.)", "employment_types": ["Full Time", "Permanent"], "selling_points": ["Immediately available preferable", "US Clients served", "Focus on Woven or Knits"], "locations": ["Lai Chi Kok"], "categories": ["Manufacturing", "Garment / Textile", "Merchandising & Purchasing", "Woven / Knit", "Textiles"], "post_time": "2022-01-13T04:08:49Z", "salary": {"currency": null, "max": null, "min": null, "period": "monthly", "term": null}, "salary_visible": false, "title_keywords": ["merchandiser"], "responsibilities": ["liaise", "quotation", "quality", "monitor", "design", "review", "system data", "logistics"], "requirements": {"degrees": ["diploma or above"], "majors": [], "languages": ["english", "chinese", "mandarin"], "language_level": ["good command"], "hard_skills": ["excel", "microsoft office", "word", "powerpoint", "outlook", "problem-solving skills"], "soft_skills": ["detail-minded", "communication skills", "good team player", "multi-tasking", "problem-solving skills"], "languages_combined": [{"language": "english", "language_level": ["good command"]}, {"language": "chinese", "language_level": ["good command"]}, {"language": "mandarin", "language_level": ["good command"]}]}, "experience_required": {"duration": ["at least 2- 4 years"], "field": ["garment", "trading", "education"]}}, {"job_id": "100003009042388", "location_code": "hk", "company": "Mainland Sewing Headwear Manufacturing Limited", "job_title": "Senior Marketing Executive", "description": "Job Duties:\n\n- Follow up orders form\n\n- Sample development\n\n- Costing and production\n\n- Communicate with overseas customers\n\n- China & Bangladesh factories efficiently in daily business\n\nRequirements:\n\n- University graduate in Business/Marketing or related discipline\n\n- At least 5 years of merchandising experience related to garment manufacturing is preferable\n\n- CRM & order follow up\n\n- Event / exhibition organization\n\n- Good at research, presentable\n\n- Good command in spoken and written English & Mandarin\n\n- Computer literacy\n\n- Detail-minded, good business sense and good team player\n\n- Dynamic, out going and mature\n\n- Immediate available is preferred\n\n- Occasional business travel is required\n\n\n- Candidates with less experience will be considered as a position of Marketing Executive", "employment_types": ["Full Time", "Permanent"], "selling_points": [], "locations": ["Kowloon Bay"], "categories": ["Manufacturing", "Garment / Textile", "Merchandising & Purchasing", "Textiles", "Procurement / Purchasing / Sourcing"], "post_time": "2022-01-12T07:17:00Z", "salary": {"currency": null, "max": null, "min": null, "period": "monthly", "term": null}, "salary_visible": false, "title_keywords": ["senior marketing executive"], "responsibilities": ["follow up orders", "communicate with"], "requirements": {"degrees": ["university graduate"], "majors": ["business", "marketing"], "languages": ["english", "mandarin"], "language_level": ["good command"], "hard_skills": ["dynamic"], "soft_skills": ["detail-minded", "good team player", "business sense", "mature", "presentable", "computer literacy", "dynamic"], "languages_combined": [{"language": "english", "language_level": ["good command"]}, {"language": "mandarin", "language_level": ["good command"]}]}, "experience_required": {"duration": ["at least 5 years"], "field": ["garment", "manufacturing", "related", "merchandising", "marketing"]}}, {"job_id": "100003009038214", "location_code": "hk", "company": "Clover Global Limited", "job_title": "Manager - QA (Garment/ Lingerie/ Material)", "description": "\u00a0Job Duties\n\n\nTo direct, lead and manage day-to-day activities and performance of QA (Quality Assurance) team\nTo lead, manage and guide the development and execution of quality system meeting and exceeding the company and customer requirements\nTo\u00a0 develop, contribute, drive and monitor the operational plans of the Field QA for each country/region globally\nTo enhance and modify the SOP of quality control process periodically\nTo monitor and ensure raw materials are achieving qualified standard for production\nTo specify quality requirements of raw materials with suppliers\nTo provide timely technical support in addressing performance issues and other quality opportunities\nTo implement sound practices, processes, improvement programs and systems to ensure high quality of raw materials and to review the current system standard for achieving continuous improvement on quality\nTo analyze quality assurance data and market feedback for making recommendation on product improvement\nTo communicate with customer and present the quality data to them with CAP regularly\nTo perform any other duties as assigned by the superior and/or their designate from time to time\n\nJob Requirements\n\n\nBachelor Degree in Textile / Clothing Technology or related disciplines\n10 years or above experience in fabric, trims accessories or garment industry in which 3 years in managerial level\nUnderstand the details of US/EU safety standards\nExcellent team management, technical and quality problem solving skills\nGood command in spoken and written English and Chinese including Mandarin\u00a0\nOccasionally\u00a0 travel to PRC and occasionally travel to overseas will be required\nCandidate with less experience will be considered as Assistant Manager - QA\n\nWe offer competitive remuneration package including 5-day work, discretionary bonus, medical & group life insurance to the right candidate. Interested parties please send your full resume with current & expected salary by clicking \"APPLY NOW\"\n\nFor more details on Clover Group, please visit our website: http://www.clover.com.hk\u00a0\u00a0\n\nWe are an equal opportunity employer and we welcome applications from all qualified candidates. Information provided will be treated in strict confidence and used for recruitment purposes within our Group and our related companies only. Applicants not having heard from us within 6 weeks from the date of this advertisement may consider their application unsuccessful. All personal data of unsuccessful applications will be destroyed after one full calendar year.\n", "employment_types": ["Full Time", "Permanent"], "selling_points": [], "locations": ["Lai Chi Kok"], "categories": ["Manufacturing", "Garment / Textile"], "post_time": "2022-01-11T06:09:34Z", "salary": {"currency": null, "max": null, "min": null, "period": "monthly", "term": null}, "salary_visible": false, "title_keywords": ["manager"], "responsibilities": ["communicate with", "any other duties", "data", "technical support", "systems", "monitor", "quality", "review", "develop", "quality control", "plans"], "requirements": {"degrees": ["degree", "bachelor"], "majors": ["related disciplines"], "languages": ["english", "chinese", "mandarin"], "language_level": ["good command"], "hard_skills": ["garment industry", "problem solving skills"], "soft_skills": ["problem solving skills"], "languages_combined": [{"language": "english", "language_level": ["good command"]}, {"language": "chinese", "language_level": ["good command"]}, {"language": "mandarin", "language_level": ["good command"]}]}, "experience_required": {"duration": ["3 years", "10 years"], "field": ["garment", "managerial", "qa"]}}, {"job_id": "100003009043156", "location_code": "hk", "company": "YKK Hong Kong Limited", "job_title": "Sales & Marketing Executive", "description": "Job Descriptions:\n\nHandle customers' enquiries, provide product information;\nFollow customers' developments and provide advices;\nNegotiate price with customers and follow up sales orders;\nArrange vendor/customer-visit and build up relationship;\nPromote new products to vendors/customers;\nPrepare sales reports, analysis and sales forecast;\nAssist managers in various kinds of sales-related programs and meet sales targets;\n\nBusiness trip to is required, especially China / other Asian countries;\nAssist in ad hoc duties as assigned, i.e. market research, survey, etc.\n\nJob Requirements:\n\nTertiary education or above\u00a0with 1 - 2 years working experience in sales, manufacturing, garment or merchandising industry is preferred; knowledge in snap and button will be a plus;\u00a0FRESH graduate will also be considered;\nGood command of spoken and written English & Chinese (Cantonese and Mandarin);\nWell versed with PC applications like MS Word, Excel, PowerPoint & Chinese Word Processing,\u00a0proficiency in Excel Function (i.e. v-lookup, pivot table) is preferable;\nCustomer-oriented, teamwork spirit and outgoing characters are preferred;\nCandidates with less/more experience may be considered as Associate/Senior Sales & Marketing Executive respectively.\n\nBenefits:\n\n5-day work\u00a0(staggered working hours)\nDouble pay\nDiscretionary bonus\nGroup medical\nOT pay\nStatutory Annual Leave with extra\u00a07 days Company Annual Leave\nStatutory Holiday and Other General Holiday\nOther Special Leave i.e. Marriage Leave, etc.\n\nWe offer competitive remuneration and benefits, holidays, stable working environment to the right candidates. Interested parties please click \"Apply Now\" and send your full resume with expected salary in MS Word Format to us (Please quote Position Name & Reference No.)\n\n*All personal data collected will be kept strictly confidential and used for recruitment-related purpose only.", "employment_types": ["Full Time", "Permanent"], "selling_points": ["customer-visit, promote products, handle enquiries", "1 - 2 years exp.,Good command of English & Chinese", "5-day, 13-mth, discretionary bonus, extra leave"], "locations": ["Tsim Sha Tsui"], "categories": ["Manufacturing", "Garment / Textile", "Sales, CS & Business Devpt", "Account Servicing", "Wholesale"], "post_time": "2022-01-13T18:54:52Z", "salary": {"currency": null, "max": null, "min": null, "period": "monthly", "term": null}, "salary_visible": false, "title_keywords": ["sales & marketing executive"], "responsibilities": ["ad hoc duties", "provide advices", "analysis", "prepare sales", "market research", "assist managers", "reports", "business trip", "forecast"], "requirements": {"degrees": ["fresh graduate"], "majors": [], "languages": ["cantonese", "english", "chinese", "mandarin"], "language_level": ["proficiency", "good command"], "hard_skills": ["excel", "plus", "chinese word processing", "pivot table", "powerpoint", "pc applications", "ms word"], "soft_skills": ["outgoing", "customer-oriented", "teamwork spirit"], "languages_combined": [{"language": "cantonese", "language_level": ["good command"]}, {"language": "english", "language_level": ["good command"]}, {"language": "chinese", "language_level": ["proficiency", "good command"]}, {"language": "mandarin", "language_level": ["good command"]}]}, "experience_required": {"duration": ["1 - 2 years"], "field": ["garment", "manufacturing", "merchandising", "education", "marketing"]}}, {"job_id": "100003009051226", "location_code": "hk", "company": "Easy Job Centre", "job_title": "Trims Merchandiser / Senior Trims Merchandiser (Garment Accessories / Packaging Products) (5 days)", "description": "Form 5 or above;\n3-5 years working experience in garment accessories / packaging products field;\nTrims orders follow up / co-ordination with client and factory\nWell organized and good team player;\nGood communication & interpersonal skills;\nAble to communicate English and Mandarin\nLess experience candidates will also considered as Assistant Merchandiser\n\n\u00a0Interested parties, please send your resume with expected salary by clicking the below \"apply now\" button.\u00a0You can ask click on the website\u00a0www.easyjobhk.com\u00a0for more details about the company", "employment_types": ["Full Time"], "selling_points": [], "locations": ["Yau Tsim Mong Area"], "categories": ["Manufacturing", "Garment / Textile", "Merchandising & Purchasing", "Textiles", "Procurement / Purchasing / Sourcing"], "post_time": "2022-01-15T05:19:57Z", "salary": {"currency": null, "max": null, "min": null, "period": "monthly", "term": null}, "salary_visible": false, "title_keywords": ["trims merchandiser", "senior trims merchandiser"], "responsibilities": ["communication"], "requirements": {"degrees": ["form 5 or above"], "majors": [], "languages": ["english", "mandarin"], "language_level": [], "hard_skills": [], "soft_skills": ["communication", "good team player", "well organized", "interpersonal skills"], "languages_combined": [{"language": "english", "language_level": []}, {"language": "mandarin", "language_level": []}]}, "experience_required": {"duration": ["3-5 years"], "field": ["garment"]}}, {"job_id": "100003009037746", "location_code": "hk", "company": "", "job_title": "Merchandiser / Assistant Merchandiser / Trainee", "description": "Requirement:\nHigher Diploma or above in any disciplines, preferably major in Textile and Clothing\nStrong sense of Time & Action and cost control\nAt least 3- 5 years solid experience in garment merchandising , less experience should be consider as Assistant Merchandiser / Trainee\nProficient in Microsoft application , eg. Word, Excel, PowerPoint, Photoshop, CLO\nGood command of spoken & written English and Chinese\nExperience in factory manufacturing is preferable\n\nJob Description:\n\nIndependently work closely with customer and factory on whole processes from product development, bulk production to final shipment\nMonitoring production status and order status to meet shipment deadline\nSourcing Fabric and trims ; Prepare Fabric, Production Order\nStrong sense of Time & Action and cost control\nGood communication skill with customer and factory\nWilling to travel to China / oversea\nInterested candidates, please contact us at 22110516 for company details before applying.", "employment_types": ["Full Time", "Permanent"], "selling_points": [], "locations": ["Kwai Hing"], "categories": ["Manufacturing", "Garment / Textile", "Merchandising & Purchasing", "Woven / Knit", "Others"], "post_time": "2022-01-11T04:45:13Z", "salary": {"currency": null, "max": null, "min": null, "period": "monthly", "term": null}, "salary_visible": false, "title_keywords": ["merchandiser", "assistant merchandiser", "trainee"], "responsibilities": ["communication", "monitoring", "cost control"], "requirements": {"degrees": ["higher diploma or above"], "majors": ["any disciplines"], "languages": ["english", "chinese"], "language_level": ["good command"], "hard_skills": ["excel", "word", "powerpoint", "photoshop"], "soft_skills": [], "languages_combined": [{"language": "english", "language_level": ["good command"]}, {"language": "chinese", "language_level": ["good command"]}]}, "experience_required": {"duration": ["at least 3- 5 years"], "field": ["garment", "manufacturing", "merchandising"]}}, {"job_id": "100003009040103", "location_code": "hk", "company": "Tien Sung Group Ltd", "job_title": "Senior Merchandiser (fabric and trim sourcing)", "description": "Job Responsibilities\n\n\nCarry out efficient and qualified fabric sourcing for fabric and trim items\nInitiate appropriate new development with mills/ supplier and follow through to commercialization\n\nWork closely\u00a0with mills/suppliers on development and color approval and tracking status\n\nCollaborate with Buyers, Sales Team and Merchandising Team on material sourcing and development\nWork with Customer for color review/color matching\nCo-ordinate the cost and price negotiations\nResponsible for Fabric Library maintenance\nPrepare weekly report for status review on development, testing and production\nPrepare fabric & trims forecast for every season start\n\nJob Requirement\n\n\nDiploma or above in textile or related discipline, with sound fabric knowledge\nAt least 5 years experience in knit fabric and trims sourcing & development is required\nKnowledge in Regional Material Testing Standards would be an advantage\nHaving worked in fabric mill or trading company is preferred\n\nWilling to travel and meet with suppliers when necessary\nAble to communicate proficiently in Mandarin and English", "employment_types": ["Full Time"], "selling_points": ["development, colour approval", "cost and price negotiation", "5 years experience"], "locations": ["Kwai Hing"], "categories": ["Manufacturing", "Garment / Textile", "Merchandising & Purchasing", "Woven / Knit", "Procurement / Purchasing / Sourcing"], "post_time": "2022-01-12T01:25:24Z", "salary": {"currency": null, "max": null, "min": null, "period": "monthly", "term": null}, "salary_visible": false, "title_keywords": ["senior merchandiser"], "responsibilities": ["collaborate with", "cost", "maintenance", "review", "merchandising", "testing", "commercialization", "sales team", "forecast", "report", "tracking"], "requirements": {"degrees": ["diploma or above"], "majors": [], "languages": ["english", "mandarin"], "language_level": [], "hard_skills": [], "soft_skills": [], "languages_combined": [{"language": "english", "language_level": []}, {"language": "mandarin", "language_level": []}]}, "experience_required": {"duration": ["at least 5 years"], "field": ["development"]}}, {"job_id": "100003009038501", "location_code": "hk", "company": "Etam International Sourcing Asia Limited", "job_title": "Assistant Colorist/Coordinator", "description": "Job responsibilities include but are not limited to:\n\n\nMaterial Color Control and Approval;\nRecap and follow up Material Color Approval status to Merchandising team;\nDaily communication with the merchandizing team in HK, China, Bangladesh and Headquarter in France for the LD and Bulk status;\nUpdating the data base (PLM);\nSending color submission to Headquarter in France and Suppliers;\nFollow up Material Color Submission Filing system;\nDiploma or above in Coloration, Textile Chemistry or related disciplines;\n3 years relevant experience in color and printing approval", "employment_types": ["Full Time"], "selling_points": ["5-day work, 15-day annual leave, medical insurance", "Performance bonus, multi-national firm", "French well-known Lingerie Brand"], "locations": ["Sai Ying Pun"], "categories": ["Manufacturing", "Garment / Textile"], "post_time": "2022-01-11T08:17:05Z", "salary": {"currency": null, "max": null, "min": null, "period": "monthly", "term": null}, "salary_visible": false, "title_keywords": ["coordinator", "assistant"], "responsibilities": ["communication", "control", "merchandising", "data"], "requirements": {"degrees": ["diploma or above"], "majors": ["related disciplines", "chemistry"], "languages": [], "language_level": [], "hard_skills": ["merchandizing"], "soft_skills": ["communication"], "languages_combined": []}, "experience_required": {"duration": ["3 years"], "field": ["relevant experience"]}}, {"job_id": "100003009051224", "location_code": "hk", "company": "Easy Job Centre", "job_title": "Merchandiser / Senior Merchandiser  (Garment) (5 days)", "description": "1 Post for Woven\n1 Post for Denim\n1 Post for Sweater\n1 Post for Knit\n1 Post for Bra & Underwear\n\nJob Responsibilities:\u00a0\n\nFollow-up orders with vendors, customers and internal parties to ensure customer satisfaction and on-time delivery\nProduct development process and production follow up\nParticipate in price negotiation and liaison with vendors or suppliers\nArrange sample submission to customers for approval\n\nJob Requirements:\n\nF.5 or above\n3 - 7 years merchandising experience for\u00a0Woven or Denim or Knit or Sweater or Bra & Underwear / Swimwear items\nMature, positive, self-motivated, detail-minded, responsible & able to work under pressure\nAble to communicate in English and Mandarin\nLess experienced candidates will also be considered as Assistant Merchandiser\n\nInterested parties, please send your resume with expected salary by clicking the below \"apply now\" button.\u00a0You can ask click on the website\u00a0www.easyjobhk.com\u00a0for more details about the company", "employment_types": ["Full Time"], "selling_points": [], "locations": ["Yau Tsim Mong Area"], "categories": ["Manufacturing", "Garment / Textile", "Merchandising & Purchasing", "Fabrics", "Woven / Knit"], "post_time": "2022-01-15T05:19:56Z", "salary": {"currency": null, "max": null, "min": null, "period": "monthly", "term": null}, "salary_visible": false, "title_keywords": ["merchandiser", "senior merchandiser"], "responsibilities": ["price negotiation", "internal parties"], "requirements": {"degrees": [], "majors": [], "languages": ["english", "mandarin"], "language_level": [], "hard_skills": [], "soft_skills": ["detail-minded", "self-motivated", "responsible", "mature", "positive", "work under pressure"], "languages_combined": [{"language": "english", "language_level": []}, {"language": "mandarin", "language_level": []}]}, "experience_required": {"duration": ["3 - 7 years"], "field": ["merchandising"]}}, {"job_id": "100003009036921", "location_code": "hk", "company": "Amer Sports Sourcing Ltd", "job_title": "Quality Manager, Apparel & Gear", "description": "Position Objective/Mission:\n\nAssist daily operation of Quality & Process Improvement Manager\nAssist in monitoring the checking on the status of Work in Progress in factories\nAssist in monitoring QA team workload across region\nAssures consistent quality of data, developing and enforcing good data management systems; validating processes; providing documentation.\nHandle Factory technical evaluation as per brand\u2019s requirements\nParticipate to product risk assessments when needed and pro-actively identify/resolve quality issues at pre-prod stage\nFollow through quality plans and carry-out all necessary actions to achieve quality targets;\n\nKey Responsibilities:\n\nInterpret and comply with quality assurance standards\nOversee the implementation and ensure efficiency of inspection and quality system\nAssist to manage collocated quality team in South East Asia\nFollow through quality assurance plans for Quality processes and system in production in relation to quality plans developed by Brands\nFollow through CAP plan in production and collaborating with other members of the Brands and Corporate QA management\nManage vendor KPIs and production status\nEnsure consistency and quality of Master Data and related process execution\nImplement quality data checks, standard and rules. Updates of standard document, quality KPIs and work procedure\nRun Master Data analysis, summarize information & prepare quality documentation and trends including failed processes, stability studies, corrective actions, and re-validations\nRaise concerns about master data quality and potential related issues, including action plan for improvement\nCreates awareness around Master Data quality and procedures\nAssists in initiates to improve Master Data quality\nCheck implementation and progress of CIP actions defined\nBased on WIP, assist to summarize factory loading and analyze field QA workload\n\nRequirements:\n\nCollege or above in quality / engineering / industrial areas;\nAt least 10+ years professional experience in the field of quality & at least 5+ years professional experience in data management;\nKnowledge in quality management system and Statistical analysis;\nMotivated to adhere to standard and process;\nFamiliar with Data Quality Dashboard tooling;\nEmphasizing Excellence, able to deal with complexity and good communication skills;\nFluency in spoken & written English is a must;\nFrequent travel required.\n\nOthers Information\n\n\nWe offer competitive compensation package include 5 days work, medical insurance covering dependents, top up contribution for MPF and etc.\u00a0\n\nInterested parties please send application letter with details resume (please specify current & expected salary to HR Manager.\u00a0\u00a0", "employment_types": ["Full Time", "Permanent"], "selling_points": ["Apparel quality team for a global sourcing office", "Famous technical garment brands", "Quality data system management and analysis"], "locations": ["Ngau Tau Kok"], "categories": ["Manufacturing", "Garment / Textile", "Quality Assurance, Control & Testing / ISO"], "post_time": "2022-01-11T00:38:29Z", "salary": {"currency": null, "max": null, "min": null, "period": "monthly", "term": null}, "salary_visible": false, "title_keywords": ["quality manager"], "responsibilities": ["management", "data", "quality", "implementation", "procedures", "inspection", "data analysis", "plan", "kpis", "documentation", "plans", "quality plans"], "requirements": {"degrees": [], "majors": [], "languages": ["english"], "language_level": ["fluency"], "hard_skills": ["data management", "statistical analysis"], "soft_skills": ["communication skills", "motivated"], "languages_combined": [{"language": "english", "language_level": ["fluency"]}]}, "experience_required": {"duration": ["at least 5+ years", "at least 10+ years"], "field": ["management"]}}, {"job_id": "100003009051225", "location_code": "hk", "company": "Easy Job Centre", "job_title": "Fabric Merchandiser / Senior Fabric Merchandiser (5 days)", "description": "1 Post for Woven Fabric\n1 Post for Knit Fabric\n1 Post for Denim Fabric\n1 Post for Underwear Lace\nF.5 or above\n3-5 years experience in garment/textile industry\nCoordinate and execute the orders with mills in China\nCommunicate with customer and mills factory for development and production\nGood knowledge of Woven Fabric or Knit Fabric or Denim Fabric\n\nGood interpersonal and communication skills\nAble to communicate\u00a0English and Mandarin\nLess experience candidates will also considered as Assistant Merchandiser\n\nInterested parties, please send your resume with expected salary by clicking the below \"apply now\" button.\u00a0You can ask click on the website\u00a0www.easyjobhk.com\u00a0for more details about the company", "employment_types": ["Full Time"], "selling_points": [], "locations": ["Yau Tsim Mong Area"], "categories": ["Manufacturing", "Garment / Textile", "Merchandising & Purchasing", "Fabrics", "Textiles"], "post_time": "2022-01-15T05:19:57Z", "salary": {"currency": null, "max": null, "min": null, "period": "monthly", "term": null}, "salary_visible": false, "title_keywords": ["fabric merchandiser"], "responsibilities": ["coordinate", "communication", "communicate with"], "requirements": {"degrees": [], "majors": [], "languages": ["english", "mandarin"], "language_level": [], "hard_skills": [], "soft_skills": ["communication skills", "interpersonal"], "languages_combined": [{"language": "english", "language_level": []}, {"language": "mandarin", "language_level": []}]}, "experience_required": {"duration": ["3-5 years"], "field": ["garment", "textile"]}}, {"job_id": "100003009042737", "location_code": "hk", "company": "Top Form International Limited", "job_title": "IT Support Officer", "description": "Job Responsibilities:\n\n\nManage HK offices day-to-day end users support and IT operations support activities\nProvide first line quality and prompt IT service to internal end users\nRespond to IT Helpdesk calls to provide technical support, troubleshooting and resolution\nPerform regular tasks for computer operations, include hardware and software installation, configuration and upgrade on desktops, laptops, printers, phones and video systems\nProvide support on video conferencing and AV facilities\nProvide staff on boarding and leave process on necessary PC, desk phone, software and access right setup and removal\nProvide guidance, user training material and conduct training to end users on current technology and IT policies\nMonitoring and handling backup and restoration operations\nWork with vendor for resolving technical issue\nPerform daily health check for IT equipment\nMaintain supported product inventory, including hardware and software\nPerform IT Procurement process / contract and billing handling\nPerform ad-hoc duties and support infrastructure-related project as assigned\nOccasion travel is required\n\nJob Requirements:\n\n\nDiploma in Computer Science/Information Systems or related disciplines\nMinimum 3 years of relevant work experience\nHigh awareness and consciousness in IT security and IT policy compliance\nSolid knowledge in computer hardware and software, including PC, Windows OS, MS Office (Excel, Outlook and Access), etc.\nSolid experience in operating and supporting Cisco Phone system, Cisco video conference system, Cisco Webex, and various web meeting products\nMicrosoft, VMWare, Cisco certificate are welcome but not necessary\nExperience in networking, Windows Server OS, Active Directory, SCCM, Azure, O365, VMWare, Veeam, Antivirus/security software would be an advantage\nExcellent interpersonal and communication skills\nGood analytical and problem-solving skills\nGood command of written and spoken Cantonese, English and Putonghua\n\nWe offer competitive remuneration package including 5-day work week, birthday leave, personal accident insurances as well as excellent career prospects to the right candidate. Interested parties please send full resume with current and expected salary to the Group HR & Administration\u00a0Department.\u00a0\n\nFor more details about our Group, please visit our website at http://www.topformbras.com/\n\nWe are an equal opportunity employer. We value the diversity of individuals, ideas, perspectives, insights and values, and what they bring to the workplace. Applications from all qualified candidates are welcome. Personal data collected will be kept and handled confidentially by authorized personnel for recruitment purpose only. It may also be disclosed to our subsidiaries or associates to process the information for appointment. Applicants who are not contacted within four weeks may consider their application unsuccessful. The applications will be retained for a maximum period of 12 months after the selection process is finalized and we may refer suitable applicants to other vacancies within the Group. A copy of our Personal Information Collection Statement can be provided upon request by contacting Group HR & Administration Department at the above email address.", "employment_types": ["Full Time", "Permanent"], "selling_points": ["Manage end users support and IT Operations support", "Perform regular tasks for computer operations", "5-days work, 13-mth salary, Birthday Leave"], "locations": ["Wong Tai Sin Area"], "categories": ["Manufacturing", "Garment / Textile", "Information Technology (IT)", "Support", "Network & System"], "post_time": "2022-01-12T08:35:00Z", "salary": {"currency": null, "max": null, "min": null, "period": "monthly", "term": null}, "salary_visible": false, "title_keywords": ["it support officer"], "responsibilities": ["it service", "software", "operations", "inventory", "quality", "troubleshooting", "maintain", "it procurement", "configuration", "infrastructure", "resolution", "setup", "installation", "provide support", "monitoring", "it policies", "ad-hoc duties", "provide guidance", "technical support", "systems", "hardware", "it equipment"], "requirements": {"degrees": ["certificate", "diploma"], "majors": ["related disciplines", "computer science"], "languages": ["cantonese", "putonghua", "english"], "language_level": ["good command"], "hard_skills": ["excel", "o365", "azure", "vmware", "web", "active directory", "sccm", "problem-solving skills", "hardware", "os", "outlook", "pc", "windows server", "antivirus", "ms office"], "soft_skills": ["problem-solving skills", "communication skills", "active", "interpersonal"], "languages_combined": [{"language": "cantonese", "language_level": ["good command"]}, {"language": "putonghua", "language_level": ["good command"]}, {"language": "english", "language_level": ["good command"]}]}, "experience_required": {"duration": ["minimum 3 years"], "field": ["video", "security"]}}, {"job_id": "100003009035951", "location_code": "hk", "company": "", "job_title": "Asst Merchandiser /Merchandiser/ Senior Merchandiser -- Knit", "description": "Takara\u00a0Company\n\nAsst Merchandiser /Merchandiser/ Senior Merchandiser -- Knit\u00a0\n\u00a0\n-\u00a0F.5 Or Above, Fresh Grad\u00a0\n- Good English & Mandarin\n- Factory experiences and advantage\n- Good knowledge of consumption, costing, Sourcing\n\u00a0- MUST Be immediate available\n\u00a0\n\u00a0\n\n\n\n\nPlease send your application with detailed resume and expected salary to\nhr@takara.hk\u00a0\u00a0\n**Personal data collected will be used for recruitment purpose only**\n", "employment_types": ["Full Time", "Permanent"], "selling_points": [], "locations": ["Not Specified"], "categories": ["Manufacturing", "Garment / Textile", "Product Development / Management", "Merchandising & Purchasing", "Woven / Knit"], "post_time": "2022-01-10T08:55:00Z", "salary": {"currency": null, "max": null, "min": null, "period": "monthly", "term": null}, "salary_visible": false, "title_keywords": ["merchandiser", "senior merchandiser"], "responsibilities": ["personal data", "recruitment"], "requirements": {"degrees": [], "majors": [], "languages": ["english", "mandarin"], "language_level": ["good"], "hard_skills": [], "soft_skills": ["detailed"], "languages_combined": [{"language": "english", "language_level": ["good"]}, {"language": "mandarin", "language_level": ["good"]}]}, "experience_required": {"duration": [], "field": []}}, {"job_id": "100003009035697", "location_code": "hk", "company": "G2000 (Apparel) Ltd", "job_title": "Merchandiser/ Senior Merchandiser", "description": "This role is responsible for managing critical paths of sampling and bulk production, follow-through of delivery, and development of new product lines.\n\nResponsibilities:\u00a0\n\n\nEnsure smooth workflow in coordination with factories on sampling and bulk order allocation, follow-through of production status and process, updating production requirement and delivery.\nParticipate in the negotiation and distribution of orders to factories and ensure productions are in accordance with Company and customer requirements.\nWork closely with Design Team on sampling and product development.\nStudy and evaluate production capacity and product quality of potential factories for fabric & garment assembling whenever necessary.\nAssist in setting up and updating production schedules to ensure maximum use of factories\u2019 capacity.\nWork closely with the Technical team to improve sample quality.\nParticipate actively in fitting sessions.\nSource trims and fabrics for product development.\nCoordinate with the Product Planning & Sales team for order consolidation.\nCoordinate with the Shipping team to ensure on-time delivery of merchandise.\nFrequent and extensive travel offshore for a factory visit.\n\nRequirements:\n\nMinimum of 5 years relevant experience in apparel manufacturing\nStrong technical knowledge of fabric & product manufacturing processes\nEssential skill includes production planning, negotiation, analytical, presentation, communication skill & leadership with the strong problem-solving ability\u00a0\nGood negotiation skills & fluent English-Cantonese-Mandarin speaking\nGood co-ordination skill\nUnderstanding of lab test standards is a plus", "employment_types": ["Permanent"], "selling_points": ["Exp. in Suit/Blazer/Casual Pants/Outerwear", "Knowledge and exp. in GB standards", "Strong communication & presentation skills"], "locations": ["Kwai Fong"], "categories": ["Manufacturing", "Garment / Textile", "Merchandising & Purchasing", "Woven / Knit", "Procurement / Purchasing / Sourcing"], "post_time": "2022-01-10T08:11:56Z", "salary": {"currency": null, "max": null, "min": null, "period": "monthly", "term": null}, "salary_visible": false, "title_keywords": ["merchandiser", "senior merchandiser"], "responsibilities": ["shipping", "schedules", "coordination with", "quality", "coordinate with", "design", "evaluate", "sales team", "planning"], "requirements": {"degrees": [], "majors": [], "languages": ["cantonese", "english", "mandarin"], "language_level": ["fluent", "good"], "hard_skills": ["problem-solving", "plus"], "soft_skills": ["negotiation", "problem-solving", "communication skill", "negotiation skills", "leadership", "presentation"], "languages_combined": [{"language": "cantonese", "language_level": ["fluent", "good"]}, {"language": "english", "language_level": ["fluent", "good"]}, {"language": "mandarin", "language_level": ["fluent", "good"]}]}, "experience_required": {"duration": ["minimum of 5 years"], "field": ["manufacturing", "relevant experience"]}}, {"job_id": "100003009036923", "location_code": "hk", "company": "Amer Sports Sourcing Ltd", "job_title": "Apparel Brand Quality Manager - Arc'teryx", "description": "The position is focus on Arc\u2019teryx brand.\n\nResponsibilities:\n\nCoordinate Brand\u2019s expectations alignment with ASO team and vendor\u2019s Quality system\nAssures consistent quality of production by developing and enforcing good quality assurance systems; validating processes; providing documentation; managing staff.\nImplement all quality plans and carry-out all necessary actions (corrective and preventive) to achieve quality targets;\nContinuously improve quality system to drive cost down ( less rework, less reject, warranty rate down, \u2026; and LEAN QC);\nSupervise quality from Buy & Bulk ready to FG shipment;\nEnsure FG delivered to market fulfill specifications and regulations\nManage quality system CIP and harmonization;\nSupport vendors to improve compliance audit results with CSR targets and local regulations.\nAchieves sourcing quality assurance operational objectives by implementing and monitoring Amer Sports corporate strategic plans; preparing and completing action plans; implementing production, productivity, quality, and Amer Sports Brands\u2019 standard requirements; identifying and resolving problems; completing audits; determining system improvements; implementing change.\nEnhances department and organization performance by accepting ownership for accomplishing new and different requests; exploring opportunities to add value to job accomplishments.\nDevelops quality assurance plans for Quality processes and system in production in relation to quality plans developed by Brands for product by conducting hazard analyses; identifying critical control points and preventive measures; establishing critical limits, monitoring procedures, corrective actions, and verification procedures.\nValidates quality processes by brands requirements; measuring production capability for CTQ attributes (Critical To Quality) prior production by implementing Cp, Cpk validation; documenting evidence; determining operational and performance qualification; monitoring and updating quality assurance procedures.\nMaintains and improves product quality by completing product, company, system, compliance, and surveillance audits; investigating complaints from internal clients to understand root causes and develop CAP plan in production and; collaborating with other members of the Brands and Corporate QA management to develop new product engineering, manufacturing and training methods (CIP).\nAudit and Approve vendor SOP and QC plan in conformance of brands expectations before mass production;\nDefine and manage quality KPIs and reporting: define and drive CIP (corrective and preventive) to close the gap with brands expectations;\nAudit quality system and QC plan in vendors and sourcing team to identify CIP plan and check implementation and progress of actions defined;\nPrepares quality documentation and reports by collecting, analyzing and summarizing information and trends including failed processes, stability studies, corrective actions, and re-validations.\nAccomplishes quality assurance human resource objectives by recruiting, selecting, orienting, training, assigning, scheduling, coaching, counselling, and disciplining employees; communicating job expectations; planning, monitoring, appraising, and reviewing job contributions; planning and reviewing compensation actions; enforcing policies and procedures.\nMeets quality assurance financial objectives by estimating requirements; scheduling expenditures; analyzing variances; initiating corrective actions\nRequirements:\n\nAt least 10+ years professional experience in the field of quality (preferably within the apparel or outdoor hardgoods industry)\nDegree or above in quality / engineering / industrial areas; major on garment or textile is an advantage\nProfessional knowledge in quality management system and Statistical analysis\nStrategic Planning, Process Improvement & Problem solving skills\nEmphasizing Excellence, able to deal with complexity and good communication skills;\nFluency in spoken & written English is a must\nFrequent Travel required\nOthers Information:\u00a0\n\nWe offer competitive compensation package include 5 days work, medical insurance covering dependents, top up contribution for MPF and etc.\u00a0\n\nInterested parties please send application letter with details resume (please specify current & expected salary to HR Department.\u00a0\u00a0", "employment_types": ["Full Time", "Permanent"], "selling_points": ["Manage quality system CIP and harmonization", "Focus on Arc\u2019teryx brand", "Quality data analysis"], "locations": ["Ngau Tau Kok"], "categories": ["Manufacturing", "Garment / Textile", "Quality Assurance, Control & Testing / ISO"], "post_time": "2022-01-11T00:39:06Z", "salary": {"currency": null, "max": null, "min": null, "period": "monthly", "term": null}, "salary_visible": false, "title_keywords": ["quality manager"], "responsibilities": ["regulations", "quality", "audit", "plan", "plans", "control", "compliance", "developing", "implementation", "develop", "reports", "kpis", "reporting", "cost", "management", "monitoring", "procedures", "scheduling", "specifications", "audits", "documentation", "strategic plans", "policies", "system improvements", "systems", "coordinate", "quality plans", "planning"], "requirements": {"degrees": ["degree or above"], "majors": ["engineering"], "languages": ["english"], "language_level": ["fluency"], "hard_skills": ["problem solving skills", "statistical analysis"], "soft_skills": ["communication skills", "problem solving skills"], "languages_combined": [{"language": "english", "language_level": ["fluency"]}]}, "experience_required": {"duration": ["at least 10+ years"], "field": []}}, {"job_id": "100003009043724", "location_code": "hk", "company": "HRnet One Limited", "job_title": "Apparel Design Developer (other openings incl Merchandisers)", "description": "We are looking for an enthusiastic person to join an international business , which requires an proactive attitude and entrepreneurial\u00a0spirit. Passionate in casual or active wear.\u00a0\n\nBase on the business expansion purpose of the brand, we welcome Designers, PDs, Merchandisers as other openings are also available.\u00a0\nAssist PD Head & HQ in mock up , fixing sketches in developing products\u00a0\nCreate a record of all developments in work and communicate the progress and updates to ensure regional teams are aligned.\nEnsure timelines are met and samples are prepared for style reviews\u00a0\nAct as main contact window in region for status updates\u00a0\nWork closely with HQ, and Asia team in development\u00a0tracking, oversee TNA together\u00a0with Head of PD\nProvide support on aesthetic and intent of the garment.\nSpecification:\u00a0\n\nAdobe Illustrator /\u00a0Photoshop\nPLM experience is a plus\nRelevant Bachelor Degree in Fashion Textile is a plus\u00a0", "employment_types": ["Full Time", "Permanent"], "selling_points": ["Double pay, Year end incentive", "growing MNC with strong track record", "Stable working environment, practical leadership"], "locations": ["Kwun Tong"], "categories": ["Design", "Fashion", "Manufacturing", "Garment / Textile"], "post_time": "2022-01-13T01:40:29Z", "salary": {"currency": null, "max": null, "min": null, "period": "monthly", "term": null}, "salary_visible": false, "title_keywords": ["developer"], "responsibilities": ["provide support", "teams", "developing", "sketches", "contact", "tracking"], "requirements": {"degrees": ["degree", "bachelor"], "majors": [], "languages": [], "language_level": [], "hard_skills": ["plus", "photoshop", "adobe illustrator"], "soft_skills": ["passionate", "active", "proactive", "enthusiastic"], "languages_combined": []}, "experience_required": {"duration": [], "field": []}}, {"job_id": "100003009043147", "location_code": "hk", "company": "YKK Hong Kong Limited", "job_title": "Business Planning Officer (Japanese Speaking)", "description": "Job Descriptions:\n\nSupport internal requests to prepare weekly and monthly reports of sales data, make weekly/ monthly reports, consolidate and analyze sales and research data;\n\nCreate the business yearly plan by using Excel Format;\nRegular updates and prepares internal database and distribute the summary of some specific items sales by month;\nPerform data extraction, collect and analyze the marketing information of HK & China for apparel business and generate reports for management's review;\nPrepare PowerPoint, presentation\u00a0materials and ad-hoc analysis or tasks for the Department or seniors;\nSupporting RPA & EDI arrangement as well as build and maintain digitalization of working processing;\nHandle enquiries from Japan HQ about business situation;\nAssist in ad-hoc duties if necessary.\nJob Requirements:\n\nBachelor Degree or above majoring in Statistics or Sciences or other business related subjects with 2 years working experience in data analysis, fresh graduates with also be considered;\nMUST be sensitive to figures / numbers with\u00a0analytical and organized thinking;\nMust be proficient in the following computer skills:-\nMS Office Excel\nAble to arrange a series of data with \"Pivot Table\"\nFamiliar with other functions such as \"VLOOKUP\", \"HLOOKUP\", \"AVERAGE\", etc.\nAccess\nWith basic knowledge of Access.\nVBA\nWith basic knowledge of VBA is a plus.\nProficient in MS Word, PowerPoint, Chinese Word Processing;\nGood command of both spoken and written Cantonese, English and Mandarin;\nCandidates with study (JPLT N2 or above) or working experience in Japan will be an advantage;\nFast learner and able to work under pressure;\nSelf-motivated, good writing and presentation skills.\n\nBenefits:\n\n5-day work (Staggered Work Hour System)\nDouble Pay\nDiscretionary bonus\nGroup medical\nOT pay\nStatutory Annual Leave with extra 7 days Company Annual Leave\nBank Holiday\nOther Special Leave i.e. Marriage Leave, etc.\n\nWe offer competitive remuneration and benefits, holidays, stable working environment to the right candidates. Interested parties please click \"Apply Now\" and send your full resume with expected salary in MS Word Format to us (Please quote Position Name & Reference No.)", "employment_types": ["Full Time", "Permanent"], "selling_points": ["2 year work exp in data analysis, fresh grad ok", "Bachelor Degree in Statistics, Science", "5-day, 13-mth, discretionary bonus, extra leave"], "locations": ["Tsim Sha Tsui"], "categories": ["Manufacturing", "Garment / Textile", "Sales, CS & Business Devpt", "Others", "Professional Services", "Translation"], "post_time": "2022-01-12T09:56:21Z", "salary": {"currency": null, "max": null, "min": null, "period": "monthly", "term": null}, "salary_visible": false, "title_keywords": ["officer"], "responsibilities": ["ad-hoc", "management", "ad-hoc duties", "monthly reports", "data", "analysis", "review", "handle enquiries", "maintain", "reports", "database", "plan", "weekly and monthly reports"], "requirements": {"degrees": ["degree or above", "bachelor"], "majors": ["business", "statistics"], "languages": ["cantonese", "english", "chinese", "mandarin"], "language_level": ["good command", "proficient"], "hard_skills": ["excel", "vba", "plus", "basic", "chinese word processing", "ms word", "analysis", "pivot table", "powerpoint", "vlookup", "ms office"], "soft_skills": ["organized", "self-motivated", "sensitive to figures", "presentation skills", "fast learner", "work under pressure"], "languages_combined": [{"language": "cantonese", "language_level": ["good command"]}, {"language": "english", "language_level": ["good command"]}, {"language": "chinese", "language_level": ["proficient"]}, {"language": "mandarin", "language_level": ["good command"]}]}, "experience_required": {"duration": ["2 years"], "field": ["related", "business", "statistics", "data analysis"]}}, {"job_id": "100003009036007", "location_code": "hk", "company": "", "job_title": "Merchandising Manager / Senior Merchandiser", "description": "Requirement:\u00a0\n\nHigher Diploma or above, preferably major in Textile and Clothing\u00a0\nStrong \u00a0garment knowledge in cut and sewn \u00a0casual & performance wear\u00a0\nDetail-minded, able to work independently and under tight schedule\u00a0\u00a0\nStrong leadership, good communication and problem solving skills\u00a0\nProficiency in both spoken and written English and Mandarin\u00a0\nSolid experience in formulating marketing & sales strategies & implementing action plans to achieve business objectives \u00a0\nPresentable, initiative, aggressive with good communication skills \u00a0\nGood computer & presentation skills \u00a0\nExperience in factory manufacturing is preferable \u00a0\nAt least\u00a0 8 years solid experience in management level, less experience should be consider as Senior Merchandiser.\u00a0\nJob Description:\u00a0\n\nManage and train the merchandising team (include both local , China and oversea staffs) to establish relationship with customers and ensure customer satisfaction\u00a0\nAbility to identify problems and prevent issue in advance\u00a0\nManage the operation of merchandising team to maximize work efficiency and effectiveness with both internal and external parties in order to achieve production schedule and on-time quality delivery\u00a0\nDevelop and implement sales strategy, sales plans and profit target \u00a0\nManage costing analysis and budget control\u00a0\nGood Fashion senses, market trend and fabric knowledge.\u00a0\n\n\n\nInterested candidates, please contact us at 22110516 for company details before applying.", "employment_types": ["Full Time", "Permanent"], "selling_points": [], "locations": ["Kwai Hing"], "categories": ["Manufacturing", "Garment / Textile", "Merchandising & Purchasing", "Woven / Knit"], "post_time": "2022-01-10T10:30:26Z", "salary": {"currency": null, "max": null, "min": null, "period": "monthly", "term": null}, "salary_visible": false, "title_keywords": ["merchandising manager", "senior merchandiser"], "responsibilities": ["profit target", "internal and external parties", "quality", "merchandising", "develop", "schedule", "sales plans", "costing analysis", "budget control"], "requirements": {"degrees": ["higher diploma or above"], "majors": [], "languages": ["english", "mandarin"], "language_level": ["proficiency"], "hard_skills": ["problem solving skills"], "soft_skills": ["detail-minded", "communication skills", "work independently", "presentable", "communication", "presentation skills", "problem solving skills", "leadership", "initiative"], "languages_combined": [{"language": "english", "language_level": ["proficiency"]}, {"language": "mandarin", "language_level": ["proficiency"]}]}, "experience_required": {"duration": ["8 years"], "field": ["business", "manufacturing", "marketing", "management"]}}, {"job_id": "100003009039737", "location_code": "hk", "company": "Cyber Smart Limited", "job_title": "Tactical Gears Product Designer", "description": "We are a local manufacturer focused on law enforcement customer (e.g. Fire Service, Police, Marine, Prison, Immigration, Custom, Military) around the world.\u00a0 Since our brand is just 3 years old, we are seeking a designer to help develop our products including but not limited to tactical vest & pouches, boots, helmet, uniform, gloves, bulletproof gears, backpacks, etc.\n\nThe candidate shall have\n1) Good knowledge of worldwide brand products such as 5.11, Crye Precision, SafariLand, etc\n2) Solid practical knowledge and experience in using the tactical gears. We need a serious gears lover\n3) Good knowledge of materials being used in all different products\n4) Work in detail\n5) Speak Mandarin, Cantonese and English.", "employment_types": ["Full Time"], "selling_points": [], "locations": ["Shatin Area"], "categories": ["Manufacturing", "Garment / Textile", "Product Development / Management", "Production Planning / Control"], "post_time": "2022-01-11T10:47:16Z", "salary": {"currency": null, "max": null, "min": null, "period": null, "term": null}, "salary_visible": false, "title_keywords": ["product designer"], "responsibilities": ["develop"], "requirements": {"degrees": [], "majors": [], "languages": ["cantonese", "english", "mandarin"], "language_level": [], "hard_skills": [], "soft_skills": ["focused"], "languages_combined": [{"language": "cantonese", "language_level": []}, {"language": "english", "language_level": []}, {"language": "mandarin", "language_level": []}]}, "experience_required": {"duration": [], "field": []}}, {"job_id": "100003009049092", "location_code": "hk", "company": "South Asia Knitting Factory Limited", "job_title": "Accounting Clerk (5 day work)", "description": "Job Description\n\nDaily work for issue, register and complete payment in various payment means (for example cheque, TT) ;\nMaintain proper accounting records and filing;\nHandle account department full range and day-to-day office administration duties;\nAssist preparation of cash flow forecast and other routine reports;\nPerform other ad hoc assignment as required\n\n\u00a0Job Requirements:\n\nDiploma holder in Accounting or LCC & I (Level 3);\nHands on PC skills and familiar with computerized accounting system;\nResponsible, self-motivated, hard-working with good interpersonal skills;\nGood numerical sensitivity and attentive to details\nGood command of both spoken and written English and Chinese\nFresh graduates are also welcomed\n\n\nWe provide the high caliber\u00a0with\u00a0attractive salary, good career prospect and benefits package\u00a0including\u00a05 day work week,\u00a0discretionary bonus,\u00a0education allowance and\u00a0medical scheme.\n\n\u00a0Interested parties please send your full resume with your availability, current and expected salary details by clicking \"APPLY NOW\"\n\n\u00a0(All applications will be treated in strict confidence and data collected will be used for recruitment purposes only)", "employment_types": ["Full Time", "Permanent"], "selling_points": ["5 day work", "Kwun Tong", "discretionary bonus"], "locations": ["Kwun Tong"], "categories": ["Manufacturing", "Garment / Textile"], "post_time": "2022-01-14T08:06:45Z", "salary": {"currency": null, "max": null, "min": null, "period": "monthly", "term": null}, "salary_visible": false, "title_keywords": ["accounting clerk"], "responsibilities": ["ad hoc assignment", "payment", "maintain", "cash flow", "reports", "forecast", "office administration duties"], "requirements": {"degrees": ["diploma holder"], "majors": ["accounting"], "languages": ["english", "chinese"], "language_level": ["good command"], "hard_skills": ["pc skills", "lcc", "accounting system"], "soft_skills": ["self-motivated", "responsible", "attentive to details", "sensitivity", "hands on", "hard-working", "interpersonal skills"], "languages_combined": [{"language": "english", "language_level": ["good command"]}, {"language": "chinese", "language_level": ["good command"]}]}, "experience_required": {"duration": [], "field": []}}, {"job_id": "100003009036145", "location_code": "hk", "company": "Varner Far East Limited", "job_title": "Garment Technician", "description": "VARNER Group is one of the largest fashion retailers in Scandinavia, consisting of 6 retail concepts, with nearly 11,000 employees and 1,400 stores across 6 countries.\u00a0We have a production office based in Hong Kong and supporting offices in Hangzhou and Beijing. We are now seeking a high caliber\u00a0candidate to fill the Varner Far East Garment Technician position at our Hong Kong office.\n\nThe Garment Technician has a problem-solving role with the aim to communicate with internal stakeholders effectively about a specific matter. The Technician works with a specific product, finds the best practice and instructs effectively on how to proceed.\u00a0 The Technician works closely alongside the Pattern and Measurement\u00a0Department at the HQ, designers, buyers, suppliers, merchandisers and QC team.\u00a0\n\nMajor areas of responsibility:\n\nMeasuring and evaluating samples (development, fit, size-set, pre-production and shipment) before submitting to our HQ.\nUnderstanding garment construction techniques and suitability for bulk production.\nEstablish communication between internal stakeholders and suppliers.\nGuide suppliers to make necessary corrections with clear instructions.\nCollaborate with suppliers to improve understanding of our brands' fitting requirements.\nBeing part of risk analysis of product quality.\nExecuting follow-up and documentation in internal software.\n\nThe position requires frequent travelling in China/Far East region.\u00a0It is estimated that 3-5 days a month will be spent traveling.\u00a0You will be reporting to Varner Far East Production Office Manager.\n\nRequired experience:\n\nStrong technical knowledge in pattern making, garment sewing, construction, fitting and grading.\nPreferably experienced on different product groups.\u00a0Candidates with strong lingerie experience and knowledge will be prioritized.\nLiterate in Microsoft office programs, exposure to PLM, Pattern CAD/CAM system and 3D would be an advantage\nMinimum 3 years working experience at sourcing offices and/or in production.\nHigher Diploma or above in Fashion Design, Fashion Technology, Technical Design, Clothing studies or related disciplines.\n\nPersonality:\n\nResults oriented and efficient\nAbility to work independently\nPro-active and problem solver\nWell organized and good planning abilities\nExcellent communication skills\nHonest, positive and outgoing\n\nLanguage skills: Excellent skills in written and spoken Mandarin and English.\n\nAn attractive package and 5-day work week will be offered to the right candidate.\nWe can offer a position in a dynamic and results driven organization\u00a0built on the following values;\nBusiness Minded, Passion, Make it Easy, Friendship, Happiness, and Responsibility.\n\nInterested parties please apply with full resume, state current and expected salaries and available\u00a0starting date by clicking\u00a0\"Apply Now\".", "employment_types": ["Full Time"], "selling_points": [], "locations": ["Hung Hom"], "categories": ["Manufacturing", "Garment / Textile", "Merchandising & Purchasing", "Woven / Knit", "Textiles"], "post_time": "2022-01-10T16:52:47Z", "salary": {"currency": null, "max": null, "min": null, "period": "monthly", "term": null}, "salary_visible": false, "title_keywords": ["technician"], "responsibilities": ["communicate with", "collaborate with", "reporting", "software", "measurement", "quality", "design", "communication", "executing", "risk analysis", "documentation", "pre-production", "planning"], "requirements": {"degrees": ["higher diploma or above"], "majors": ["related disciplines", "design"], "languages": ["english", "mandarin"], "language_level": ["excellent"], "hard_skills": ["microsoft office", "cad", "problem-solving", "analysis", "make", "dynamic", "documentation"], "soft_skills": ["efficient", "communication skills", "work independently", "outgoing", "problem solver", "problem-solving", "well organized", "communication", "clear", "business minded", "dynamic", "honest", "pro-active", "driven", "positive"], "languages_combined": [{"language": "english", "language_level": ["excellent"]}, {"language": "mandarin", "language_level": ["excellent"]}]}, "experience_required": {"duration": ["minimum 3 years"], "field": []}}, {"job_id": "100003009035896", "location_code": "hk", "company": "SPARC Far East Limited", "job_title": "Senior Costing Analyst (Apparel MNC Sourcing Office)", "description": "Job Responsibilities:\n\nSeasonally maintain and analyze costing database, e.g. profit, labor, overhead, tooling & material cost, forecast and order volume\nProvide Process & Technical Support for PLM Costing System\nEnsure costing data for all categories are accurately stored in a central database\nAnalyze material consumption, productivity standards and processing cost across the region and propose aligned standards\nAnalyze and benchmark factory manufacturing and development overhead cost\nMonitor exchange rate movements and initiate product cost revisions as per exchange rate policy\nPrepare seasonal and ad hoc reports with key insights into suppliers\u2019 costing performance, cost driver developments, cost savings opportunities, factory allocation decision etc.\nSupport Costing policy creation/ update for Sourcing decision, ensure consistent approach to costing through monitoring and validation of relevant data\n\nJob Requirements:\n\nBachelor\u2019s degree in Analytical Field, Industrial Engineering or Finance is preferred\n3-5 years relevant experience in apparel industry\nFamiliar with PLM / SAP system will be a plus\nProficient in MS Office application (Excel, Power point, Word, Outlook)\nGood command of both written and spoken English, Cantonese and Mandarin\nAnalytical and systematic\nStrong ability to drive initiatives and work independently\nStrong communication and presentation\n\nFor more information about our company and business, please visit our website at:\u00a0https://www.sparcgroup.com/\n\n\nWe offer prosperous career path, competitive compensation package plus attractive fringe benefits such as: 13-month salary, discretionary bonus, dental, life,\u00a0 comprehensive medical coverage including spouse & children, employee discount, additional provident fund from employer, gym & education sponsorship...and more for the right candidate. Please send your full resume with current and expected salary by \"Apply Now\".\n\nPersonal data collected will be used for recruitment purpose only and we regret that\u00a0 only shortlisted candidates will be notified.\n", "employment_types": ["Full Time", "Permanent"], "selling_points": ["Luxury Multi-national Sourcing Office", "Comprehensive Fringe Benefits & Career Growth", "5 Days Work & Work Life Balance"], "locations": ["Kwun Tong"], "categories": ["Manufacturing", "Garment / Textile", "Product Development / Management", "Merchandising & Purchasing", "Woven / Knit"], "post_time": "2022-01-10T08:46:27Z", "salary": {"currency": null, "max": null, "min": null, "period": "monthly", "term": null}, "salary_visible": false, "title_keywords": ["analyst"], "responsibilities": ["cost", "ad hoc", "data", "technical support", "monitoring", "monitor", "maintain", "reports", "forecast", "database"], "requirements": {"degrees": ["degree", "bachelor"], "majors": ["finance", "engineering"], "languages": ["cantonese", "english", "mandarin"], "language_level": ["good command"], "hard_skills": ["excel", "plus", "sap", "word", "outlook", "power point", "ms office"], "soft_skills": ["work independently", "systematic", "communication", "comprehensive", "presentation"], "languages_combined": [{"language": "cantonese", "language_level": ["good command"]}, {"language": "english", "language_level": ["good command"]}, {"language": "mandarin", "language_level": ["good command"]}]}, "experience_required": {"duration": ["3-5 years"], "field": ["relevant experience"]}}, {"job_id": "100003009034379", "location_code": "hk", "company": "Bluestream Limited", "job_title": "Customer Service Garments", "description": "Roles & Responsibilities\n\n\nPerform day-to-day duties, such as following up on development and sample orders, work with customer & team to get the work done within a deadline.\nCoordinate - Maintain continuous and agile communication with design, production merchandising, Logistic & third-party partners to align and synchronize content.\nCoordinating Sample Development with factories to ensure final product is as per customer requirements.\nAssist on production planning with Sales / Merchandising for product style, quantity, delivery date etc. for factory planner to gauge the capacity for bulk production.\nCalculate costings through existing tools and maintenance of database.\nMaintain relationship & smooth communication with suppliers.\nAd hoc assignments for communication and certification purpose (FSC, OEKO TEX, etc)\n\nRequirements\n\n2-3 years of relevant experience working a R&D / Product Merchandiser.\nHigher Diploma in Textile Merchandising, Fashion Technology, or related discipline.\nGood communication skills in spoken and written English and Chinese (Mandarin preferably).\nProficiency in PC skills, such as MS Office (Excel, Word, PPT) - Chinese and English word processing.\nGood analytical skills.\nCapability to prioritize work and manage several projects at a time.\nPrior knowledge in printing, labels and/or packaging industry will be a plus, but not necessary.\nBe flexible and adaptable to a challenging working environment.\nImmediate availability is an advantage.", "employment_types": ["Full Time"], "selling_points": [], "locations": ["Tuen Mun Area"], "categories": ["Admin & HR", "Clerical / Admin Staff", "Manufacturing", "Garment / Textile", "Merchandising & Purchasing", "Textiles"], "post_time": "2022-01-10T03:16:53Z", "salary": {"currency": null, "max": null, "min": null, "period": "monthly", "term": null}, "salary_visible": false, "title_keywords": ["customer service"], "responsibilities": ["maintenance", "merchandising", "production planning", "design", "coordinate", "communication", "maintain", "ad hoc assignments", "database"], "requirements": {"degrees": ["diploma"], "majors": [], "languages": ["english", "chinese", "mandarin"], "language_level": ["proficiency", "good"], "hard_skills": ["r&d", "excel", "plus", "chinese and english word processing", "word", "analytical skills", "pc skills", "ms office"], "soft_skills": ["flexible", "communication skills", "adaptable", "prioritize", "analytical skills"], "languages_combined": [{"language": "english", "language_level": ["proficiency", "good"]}, {"language": "chinese", "language_level": ["proficiency", "good"]}, {"language": "mandarin", "language_level": ["good"]}]}, "experience_required": {"duration": ["2-3 years"], "field": ["relevant experience"]}}, {"job_id": "100003009035694", "location_code": "hk", "company": "Newsprint Production Group Ltd", "job_title": "Product Developer", "description": "Job Responsibilities:\n\nResponsible for managing the overall process of new and seasonal fabrics that meet designer's aesthetic vision while balancing quality, cost and speed\nProvide inspirational leadership to direct reports\nEffectively executes against design briefs\nManage and train mills across defined region\nPerform periodic SWOT analysis of mill performance and alignment to strategic sourcing needs\nOversee fabric testing and ensure mills understand expectations\nProactively monitor and meet calendar deadlines for approvals and mill executive\nMaintain a supply chain that supports the overarching strategic vision\nCollaborate with Mills, Raw Material team, and Supply Chain Partners\nJob Requirements:\n\nDegree in Textile or related subject with 8 years or above relevant industry experience\nExtensive knowledge of raw materials, construction, costing, macro-economic trends, capacity planning and Chemicals\nStrong organizational skills\nResults & solutions driven\nAble to drive change, inspire, coach, mentor and develop a high performing team\nAble to establish and maintain strong working relationships cross-functionally and cross-divisionally, as well as externally\nStrong negotiating skills in diverse cultural environments\nAbility to balance competing priorities in a fast-paced environment\nComputer literate, knowledge of Web PLM preferred\u00a0\nGood command of both spoken and written English\nPrevious people management experience is a plus\nInterested parties please send your full resume, current package, salary expectation and date of availability to us by clicking \u201cApply Now\u201d.\n(Applicants not contacted within six weeks should consider their application unsuccessful. Personal data provided by applicants will be treated confidence and used solely for recruitment purpose only.)", "employment_types": ["Full Time", "Permanent"], "selling_points": ["2-3 years of relevant experience working", "Spoken & Written English & Mandarin, PC Skill", "Double pay, medical, dental insurance"], "locations": ["Chai Wan"], "categories": ["Manufacturing", "Garment / Textile", "Product Development / Management", "Printing"], "post_time": "2022-01-10T08:11:48Z", "salary": {"currency": null, "max": null, "min": null, "period": "monthly", "term": null}, "salary_visible": false, "title_keywords": ["product developer"], "responsibilities": ["collaborate with", "cost", "quality", "monitor", "testing", "design briefs", "maintain", "reports", "swot analysis"], "requirements": {"degrees": ["degree"], "majors": [], "languages": ["english"], "language_level": ["good command"], "hard_skills": ["macro", "web", "plus"], "soft_skills": ["organizational skills", "fast-paced environment", "diverse", "extensive", "driven"], "languages_combined": [{"language": "english", "language_level": ["good command"]}]}, "experience_required": {"duration": ["8 years"], "field": ["textile", "people management", "related"]}}, {"job_id": "100003009033318", "location_code": "hk", "company": "PVH Far East Limited", "job_title": "Manager, Raw Material (Knit)", "description": "Job Responsibilities:\n\n\nReport directly to CEO and Board of Directors, dotted line to CFO\nSupport the continual improvement of financial control framework and help implementation across the Group\nReview and monitor system flow, accounting and control policies\nEstablish internal process to assess market / industry / product risk\nEstablish risk and control matrix for monitoring the effectiveness of business\n\nJob Requirements:\n\n\nBachelor Degree in Finance, Accounting or equivalent; Qualified CPA\nMinimum 8 years of relevant experience in internal audit, controllership and public accounting\nWith internal audit experience in sizeable MNCs or HK listed companies or manufacturing organizations is highly preferred\nHands-on experience in balance sheet ownership and knowledgeable in Enterprise Risk Management (ERM), credit control, reporting control, fixed asset control, internal control policies and business processes\nStrong technical accounting and familiar with Hong Kong and PRC accounting standards\nExcellent coordination, supervisory and management skills\nSuperb communication and sound analytical skills\nFrequent travel is required\n\nWe offer competitive remuneration package including 13-month salary, 5-day work week, birthday leave, personal accident insurances as well as excellent career prospects to the right candidate. Interested parties please send full resume with current and expected salary to the Group HR & Administration\u00a0Department.\u00a0\n\nFor more details about our Group, please visit our website at http://www.topformbras.com/\n\nWe are an equal opportunity employer. We value the diversity of individuals, ideas, perspectives, insights and values, and what they bring to the workplace. Applications from all qualified candidates are welcome. Personal data collected will be kept and handled confidentially by authorized personnel for recruitment purpose only. It may also be disclosed to our subsidiaries or associates to process the information for appointment. Applicants who are not contacted within four weeks may consider their application unsuccessful. The applications will be retained for a maximum period of 12 months after the selection process is finalized and we may refer suitable applicants to other vacancies within the Group. A copy of our Personal Information Collection Statement can be provided upon request by contacting Group HR & Administration Department at the above email address.", "employment_types": ["Full Time", "Permanent"], "selling_points": ["Responsible for managing the overall process", "Provide inspirational leadership to direct reports", "8 years or above relevant industry experience"], "locations": ["Lai Chi Kok"], "categories": ["Manufacturing", "Garment / Textile", "Merchandising & Purchasing", "Fabrics"], "post_time": "2022-01-09T07:43:24Z", "salary": {"currency": null, "max": null, "min": null, "period": "monthly", "term": null}, "salary_visible": false, "title_keywords": ["manager"], "responsibilities": ["control", "policies", "review", "monitor", "implementation", "monitoring", "report"], "requirements": {"degrees": ["degree", "bachelor"], "majors": ["finance", "accounting"], "languages": [], "language_level": [], "hard_skills": ["prc accounting", "cpa", "analytical skills", "internal control"], "soft_skills": ["communication", "hands-on", "coordination", "analytical skills"], "languages_combined": []}, "experience_required": {"duration": ["minimum 8 years"], "field": ["risk management", "manufacturing", "audit", "business", "relevant experience", "audit experience", "accounting"]}}, {"job_id": "100003009042765", "location_code": "hk", "company": "Top Form International Limited", "job_title": "Internal Audit Manager", "description": "This position is responsible for supporting the development and production in the region. Manages the technical development process and to work with the customer side (technical designers) and regional production team (merchandising team, QA team and vendors), taking responsibility for the technical development of new styles and the application of all quality standards relating to fit and construction.\n\nPRINCIPAL DUTIES & RESPONSIBILITIES:\n\nWork with PD team on the customer new development such as construction, size specification and modification\nDevelop the client-approved block and instruct the sample production factories to use the specified pattern\nReview from product development stage to ensure factories fully understand and will follow the first fit sample\nValidate the sample submission per Time and Action calendar and execute timely\nReview samples per customers\u2019 specification and construction details. Visit factories to troubleshoot and make corrective arrangement Join PP meetings for quality enhancement and urge for TOP samples if necessary\nPrepare and submit monthly report for Brand Leaders for overviewing sample performance\nWork with Brand Leaders to address underperforming factories and set up remedial measures\nFactory visit to measure factory improvement progress and alert merchandising team on relative sample weakness\nJOB SPECIFICATIONS (e.g. Qualification, Job Experience):\n\nCollege degree or equivalent work experience\nMore than 4 years' related work experience in woven/knit manufacturing process in a factory, production management and quality control. Less experience will be considered as Associate Tech.\nA recognized expert with about 6 years of pattern making/grading and machinery limitations\nAble to provide constructive solutions and directions for manufacturer to improve fit and product appearance\nGood analytical skills to solve complex technical problems which have impact to the business\nWe offer 5\u2013day work week, attractive compensation package and comprehensive employee benefits to the right candidate. Interested parties please send your full resume with your existing salary and expected salary by clicking \"Apply Now\".\n\nAll personal information collected will be kept for employment related purposes only", "employment_types": ["Full Time", "Permanent"], "selling_points": ["Support the improvement of financial framework", "Review and monitor system flow", "5-days work, 13-mth salary, Birthday Leave"], "locations": ["Wong Tai Sin Area"], "categories": ["Accounting", "Audit", "Manufacturing", "Garment / Textile"], "post_time": "2022-01-12T08:45:04Z", "salary": {"currency": null, "max": null, "min": null, "period": "monthly", "term": null}, "salary_visible": false, "title_keywords": ["manager"], "responsibilities": ["management", "review", "quality", "merchandising", "develop", "specifications", "troubleshoot", "monthly report", "quality control"], "requirements": {"degrees": ["degree"], "majors": [], "languages": [], "language_level": [], "hard_skills": ["make", "analytical skills"], "soft_skills": ["responsible", "timely", "analytical skills", "troubleshoot", "constructive"], "languages_combined": []}, "experience_required": {"duration": ["4 years"], "field": ["management", "manufacturing", "related", "tech", "quality control"]}}, {"job_id": "100003009030365", "location_code": "hk", "company": "MGF Sourcing Far East, Limited", "job_title": "Technologist, Fit", "description": "\u9999\u6e2f\u77e5\u5c08\u8a2d\u8a08\u5b78\u9662\u53ca\u9999\u6e2f\u5c08\u696d\u6559\u80b2\u5b78\u9662 (\u674e\u60e0\u5229)\n\u00a0\nDepartment / Section : \u6642\u88dd\u53ca\u5f62\u8c61\u8a2d\u8a08\u5b78\u7cfb\nRef. no : C/HKDI-FID/MEC3/01/22-AP1\n\u00a0\n\u4e3b\u8981\u8077\u8cac\uff1a\n(a) \u00a0\u00a0 \u00a0\u64cd\u4f5c\u3001\u5b89\u88dd\u3001\u6e2c\u8a66\u3001\u4fdd\u990a\u53ca\u7dad\u4fee\u5be6\u9a57\u5ba4\u53ca\u5de5\u5834\u5167\u7684\u76f8\u95dc\u6280\u8853\u5100\u5668\u53ca\u6a5f\u5668\u7b49\u914d\u5099\uff1b\n(b) \u00a0\u00a0 \u00a0\u6e96\u5099\u6559\u5b78\u8f14\u52a9\u7528\u5177\u3001\u6240\u9700\u7684\u7269\u6599\u3001\u5100\u5668\u53ca\u914d\u5099\u4f5c\u8a13\u7df4\u4e4b\u7528\uff1b\n(c) \u00a0\u00a0 \u00a0\u5354\u52a9\u7ba1\u7406\u6709\u95dc\u5668\u6750\u53ca\u7269\u8cc7\u7684\u6536\u767c\u5b58\u53d6\uff0c\u4e26\u6aa2\u67e5\u662f\u5426\u640d\u58de\uff1b\n(d) \u00a0\u00a0 \u00a0\u642c\u904b\u6559\u5b78\u8a2d\u5099\u3001\u5100\u5668\u53ca\u7269\u8cc7\uff0c\u4e26\u4fdd\u6301\u5de5\u5834\u7684\u5b89\u5168\u53ca\u6574\u6f54\uff1b\u53ca\n(e) \u00a0\u00a0 \u00a0\u652f\u63f4\u5b78\u9662\u8209\u8fa6\u4e4b\u6d3b\u52d5\u3001\u5c55\u89bd\u548c\u8868\u6f14\u3002\n\u00a0\n\u5165\u8077\u689d\u4ef6\uff1a\n(a) \u00a0\u00a0 \u00a0(i) \u00a0\u00a0 \u00a0\u5b8c\u6210\u76f8\u95dc\u8a8d\u53ef\u8a13\u7df4\u8ab2\u7a0b (\u5305\u62ec\u5b78\u5f92\u53ca\u6280\u5de5\u8a13\u7df4) ; \u6216\n\u00a0 \u00a0\u00a0 \u00a0(ii) \u00a0\u00a0 \u00a0\u901a\u904e\u6280\u80fd\u6e2c\u8a66\u6216\u76f8\u7b49\u6c34\u5e73\u6e2c\u8a66\uff1b\n(b) \u00a0\u00a0 \u00a0\u5177\u5099\u4e0b\u5217\u6280\u80fd\uff1a\n\u00a0 \u00a0\u00a0 \u00a0(i) \u00a0\u00a0 \u00a0\u68ad\u7e54\u8eca\u9593\u7f1d\u7d09\u6280\u8853\uff1b\n\u00a0 \u00a0\u00a0 \u00a0(ii) \u00a0\u00a0 \u00a0\u68ad\u7e54\u6a5f\u5668\u6e05\u6f54\u3001\u7dad\u4fee\u53ca\u4fdd\u990a\uff1b\u53ca / \u6216\n\u00a0 \u00a0\u00a0 \u00a0(iii) \u00a0\u00a0 \u00a0\u68ad\u7e54\u6280\u8853 (\u5982\u61c9\u7528\u548c\u4fee\u88dc\u7b49)\uff1b\n(c) \u00a0\u00a0 \u00a0\u61c2\u57fa\u672c\u96fb\u8166\u64cd\u4f5c\uff1b\n(d) \u00a0\u00a0 \u00a0\u80fd\u95b1\u8b80\u53ca\u66f8\u5beb\u4e2d\u6587\u548c\u7c21\u55ae\u82f1\u8a9e\uff1b\u53ca\n(e) \u00a0\u00a0 \u00a0\u5177\u5099\u61c2\u5f97\u64cd\u4f5c/\u7dad\u4fee\u4ee5\u4e0b\u6a5f\u5668 / \u5de5\u5177\u7684\u7533\u8acb\u4eba\u53ef\u7372\u512a\u5148\u8003\u616e\uff1a\n\u00a0 \u00a0\u00a0 \u00a0(i) \u00a0\u00a0 \u00a0\u5de5\u696d\u8863\u8eca (\u5e73\u8eca)\uff1b\n\u00a0 \u00a0\u00a0 \u00a0(ii) \u00a0\u00a0 \u00a0\u9212\u9aa8\u8eca\uff1b\n\u00a0 \u00a0\u00a0 \u00a0(iii) \u00a0\u00a0 \u00a0\u6311\u8173\u8eca\uff1b\n\u00a0 \u00a0\u00a0 \u00a0(iv) \u00a0\u00a0 \u00a0\u91d8\u9215\u53ca\u958b\u9215\u9580\u8eca\uff1b\n\u00a0 \u00a0\u00a0 \u00a0(v) \u00a0\u00a0 \u00a0\u9ecf\u6734\u6a5f\uff1b\n\u00a0 \u00a0\u00a0 \u00a0(vi) \u00a0\u00a0 \u00a0\u5047\u7f1d\u8eca\uff1b\n\u00a0 \u00a0\u00a0 \u00a0(vii) \u00a0\u00a0 \u00a0\u57cb\u593e\u8eca\uff1b\n\u00a0 \u00a0\u00a0 \u00a0(viii) \u00a0\u00a0 \u00a0\u519a\u8eca\uff1b\n\u00a0 \u00a0\u00a0 \u00a0(ix) \u00a0\u00a0 \u00a0\u5277\u76ae\u6a5f\uff1b\n\u00a0 \u00a0\u00a0 \u00a0(x) \u00a0\u00a0 \u00a0\u9ad8\u982d\u6a5f\uff1b\n\u00a0 \u00a0\u00a0 \u00a0(xi) \u00a0\u00a0 \u00a0\u4eba\u5b57 / \u4e09\u91dd\u8eca\u3002\n\u00a0 \u00a0\u00a0 \u00a0 \u00a0\u00a0\u00a0 \u00a0\n\u5099\u8a3b\uff1a\n(1) \u00a0\u00a0 \u00a0\u7533\u8acb\u8005\u82e5\u5177\u5169\u5e74\u6216\u4ee5\u4e0a\u76f8\u95dc\u5de5\u4f5c\u7d93\u9a57\uff0c\u6216\u6703\u88ab\u8003\u616e\u70ba\u4e8c\u7d1a\u6a5f\u68b0\u5de5\u3002\n(2)\n\u00a0 \u00a0\u00a0 \u00a0\u8a72\u7a7a\u7f3a\u73fe\u65bc\u9999\u6e2f\u77e5\u5c08\u8a2d\u8a08\u5b78\u9662\u53ca\u9999\u6e2f\u5c08\u696d\u6559\u80b2\u5b78\u9662\uff08\u674e\u60e0\u5229\uff09\uff0c\u70ba\u914d\u5408\u904b\u4f5c\u9700\u8981\uff0c\u53d7\u8058\u8005\u65e5\u5f8c\u53ef\u80fd\u6703\u88ab\u8abf\u6d3e\u81f3\u5176\u4ed6\u5730\u9ede\u5de5\u4f5c\u3002\n(3) \u00a0\u00a0 \u00a0\u8acb\u65bc\u7533\u8acb\u8868\u300c(VII) \u5176\u4ed6\u8cc7\u6599\u300d\u6b04\u5167\u5217\u51fa\u80fd\u64cd\u4f5c\u4e4b\u76f8\u95dc\u6a5f\u5668\u8a2d\u5099\u548c\u6280\u80fd\u3002\n(4) \u00a0\u00a0 \u00a0\u7533\u8acb\u8005\u9700\u8981\u53c3\u52a0\u6280\u80fd\u6e2c\u8a66\u3002\n(5) \u00a0\u00a0 \u00a0\u53d7\u8058\u8005\u53ef\u80fd\u9700\u8981\u8f2a\u73ed\u5de5\u4f5c\uff0c\u5305\u62ec\u591c\u73ed\uff0c\u4e26\u65bc\u661f\u671f\u516d\u3001\u65e5\u53ca\u516c\u773e\u5047\u671f\u5de5\u4f5c\uff0c\u4ea6\u53ef\u80fd\u6703\u5728\u4e0d\u540c\u5de5\u5834\u5167\u5de5\u4f5c\u3002\n\n\u7533\u8acb\u8fa6\u6cd5\uff1a\n\u586b\u59a5\u7684\u7533\u8acb\u8868\u683c [VTC-1 (Rev. 1/2018)] \u9023\u540c\u500b\u4eba\u5c65\u6b77\uff0c\u9808\u5bc4\u56de\u9999\u6e2f\u7063\u4ed4\u6d3b\u905327\u865f\uff0c\u8077\u696d\u8a13\u7df4\u5c40\u5927\u6a1318\u6a13\uff0c\u4eba\u529b\u8cc7\u6e90\u79d1\u3002\u8acb\u5728\u4fe1\u5c01\u9762\u8a3b\u660e\u6240\u7533\u8acb\u7684\u8077\u4f4d\u53ca\u53c3\u8003\u7de8\u865f\u3002\n\u00a0\n\u622a\u6b62\u7533\u8acb\u65e5\u671f\uff1a2022\u5e741\u670825\u65e5\n\u00a0\n\u5982\u5728\u622a\u6b62\u7533\u8acb\u5f8c\u7684\u5341\u661f\u671f\u5167\u672a\u6709\u6536\u5230\u9762\u8a66\u901a\u77e5\uff0c\u5373\u8868\u793a\u9019\u9805\u7533\u8acb\u4e0d\u7372\u63a5\u7d0d\u3002\n\u00a0\n\u672c\u5c40\u4fdd\u7559\u4e0d\u586b\u88dc\u4e0a\u8ff0\u8077\u4f4d\u7684\u6b0a\u5229\u3002\n\u00a0\n\u7533\u8acb\u4eba\u7684\u8cc7\u6599\u53ea\u6703\u7528\u65bc\u6709\u95dc\u672c\u5c40\u7684\u4eba\u4e8b\u62db\u8058\u4e8b\u5b9c\u3002\u5728\u4e00\u822c\u60c5\u6cc1\u4e0b\uff0c\u672a\u7372\u53d6\uf93f\u7533\u8acb\u4eba\u7684\u8cc7\uf9be\u5c07\u65bc\u62db\u8058\u5de5\u4f5c\u5b8c\u6210\u5341\u4e8c\u500b\u6708\u5f8c\u5168\u90e8\u92b7\u6bc0\u3002\n\n", "employment_types": ["Full Time", "Permanent"], "selling_points": ["Quality standards relating to fit and construction", "4+ years\u2019 Woven/Knit Fit Tech exp. for US market", "Double pay & comprehensive benefit scheme"], "locations": ["Kwun Tong"], "categories": ["Manufacturing", "Garment / Textile", "Merchandising & Purchasing", "Fabrics", "Textiles"], "post_time": "2022-01-09T23:42:51Z", "salary": {"currency": null, "max": null, "min": null, "period": "monthly", "term": null}, "salary_visible": false, "title_keywords": [], "responsibilities": [], "requirements": {"degrees": [], "majors": [], "languages": [], "language_level": [], "hard_skills": ["no", "c"], "soft_skills": [], "languages_combined": []}, "experience_required": {"duration": [], "field": []}}, {"job_id": "100003009043149", "location_code": "hk", "company": "Vocational Training Council", "job_title": "\u4e09\u7d1a\u6a5f\u68b0\u5de5 (\u670d\u98fe)", "description": "Major roles:\n\nEffectively lead and manage the Merchandising & Purchasing and Central Procurement teams as part of monitoring the critical path from product development to goods delivery;\nReport to the Chief Commercial Officer;\nKeep abreast of the market trend and carry out excellent customer relationship management to meet different markets\u2019 and customers\u2019 changing needs in a competitive approach;\nSet sourcing strategies for relevant countries of origin, in particular China and Vietnam, in support of new and existing product development;\nDevise innovative approach to achieve best pricing;\nDevise best-in-class and continue to improve procurement processes, and provide direction on assessing and monitoring supplier capabilities in the areas of fabric and trims;\nSupport business growth strategies across customer accounts by providing insights and directions on business model based on the company\u2019s strengths and dynamic global market situation.\nSet up sales and sourcing strategies and targets for different sales regions / customers / suppliers and to strive for meeting / exceeding the related KPIs;\nStation in Guangdong province for 4 days per week and in Hong Kong for 1 day per week;\nOccasional overseas travelling required;\n\nRequirements:\n\nBachelor\u2019s degree holder or above in Fashion / Textiles / Clothing or related disciplines, with at least 10 years\u2019 experience at managerial level in the apparel industry;\nA mature leader, independent, pro-active, well-organised, creative, and result-oriented;\nStrong business acumen, analytical, problems solving, and negotiation skills;\nKnowledgeable and experienced in product development, sourcing, and production processes, preferably in the lingerie / swimwear areas, and European / North American experience & exposure, a definite asset;\nStrong interpersonal and communication skills and good command of written and spoken English and Chinese;\nProficient in computer applications, such as MS Office / ERP system\n\nWe offer a competitive compensation package to the right candidate.\u00a0Please apply with full resume including salary expectation and availability by clicking \"Apply Now\".\n\nAll data collected will only be used for recruitment purpose and kept confidential.", "employment_types": ["Full Time"], "selling_points": ["\u64cd\u4f5c\u3001\u5b89\u88dd\u3001\u6e2c\u8a66\u3001\u4fdd\u990a\u53ca\u7dad\u4fee\u5be6\u9a57\u5ba4\u53ca\u5de5\u5834\u5167\u7684\u76f8\u95dc\u6280\u8853\u5100\u5668\u53ca\u6a5f\u5668\u7b49\u914d\u5099", "\u5b8c\u6210\u76f8\u95dc\u8a8d\u53ef\u8a13\u7df4\u8ab2\u7a0b (\u5305\u62ec\u5b78\u5f92\u53ca\u6280\u5de5\u8a13\u7df4)", "\u7533\u8acb\u8005\u82e5\u5177\u5169\u5e74\u6216\u4ee5\u4e0a\u76f8\u95dc\u5de5\u4f5c\u7d93\u9a57\uff0c\u6216\u6703\u88ab\u8003\u616e\u70ba\u4e8c\u7d1a\u6a5f\u68b0\u5de5"], "locations": ["Not Specified"], "categories": ["Design", "Fashion", "Manufacturing", "Garment / Textile", "Merchandising & Purchasing", "Textiles"], "post_time": "2022-01-12T09:59:55Z", "salary": {"currency": null, "max": null, "min": null, "period": "monthly", "term": null}, "salary_visible": false, "title_keywords": [], "responsibilities": ["management", "problems solving", "provide direction", "procurement processes", "monitoring", "teams", "merchandising", "communication", "computer applications", "kpis", "report"], "requirements": {"degrees": ["bachelor", "degree holder"], "majors": ["related disciplines"], "languages": ["english", "chinese"], "language_level": ["good command"], "hard_skills": ["erp system", "dynamic", "ms office", "acumen"], "soft_skills": ["communication skills", "independent", "creative", "interpersonal", "business acumen", "mature", "negotiation skills", "dynamic", "pro-active", "well-organised", "innovative", "result-oriented"], "languages_combined": [{"language": "english", "language_level": ["good command"]}, {"language": "chinese", "language_level": ["good command"]}]}, "experience_required": {"duration": ["at least 10 years"], "field": ["related", "managerial", "product development"]}}, {"job_id": "100003009034240", "location_code": "hk", "company": "RVC Enterprises Limited", "job_title": "\u9ad8\u7d1a\u5e97\u52d9\u52a9\u7406", "description": "Perform general sales & marketing activities\nHandle customers\u2019 enquiries and follow up on samples and orders\u00a0\nUpdating company websites, B2B websites and any other online promotional media.\nData entry and assist in processing of Import & Export shipping documents.\u00a0\nAssist in ad hoc duties from top management\u00a0\nMust be independent, self-motivated, responsible and well organized\nGood in both spoken and written English & Mandarin\u00a0\nHigher Diploma or University graduate is preferred\u00a0", "employment_types": ["Full Time"], "selling_points": [], "locations": ["Not Specified"], "categories": ["Education", "Others", "Manufacturing", "Garment / Textile", "Others", "Others"], "post_time": "2022-01-10T03:01:00Z", "salary": {"currency": null, "max": null, "min": null, "period": "monthly", "term": null}, "salary_visible": false, "title_keywords": [], "responsibilities": ["company websites", "ad hoc duties", "management", "data entry", "import & export shipping documents", "sales & marketing activities"], "requirements": {"degrees": ["university graduate", "diploma"], "majors": [], "languages": ["english", "mandarin"], "language_level": ["good"], "hard_skills": ["processing"], "soft_skills": ["self-motivated", "independent", "well organized", "responsible"], "languages_combined": [{"language": "english", "language_level": ["good"]}, {"language": "mandarin", "language_level": ["good"]}]}, "experience_required": {"duration": [], "field": []}}, {"job_id": "100003009036804", "location_code": "hk", "company": "r-pac Hong Kong Ltd", "job_title": "Product Developer", "description": "\u00a0Responsibilities:\nResponsible for samples review and approval process\nEvaluate sample comments and tech packs to fulfill customer requirements\nProvide technical support to merchandisers, customers, and factories\nLiaise with merchandisers and factories to establish correction action plans\nPerform other ad hoc duties\u00a0\nRequirements:\nAt least 5 years' garment trading or buying office experience\u00a0\nExperience in USA market for both Men & Women is preferred\nGood knowledge of woven and knits fabric, knowledge of pattern and grading & quality of thread and stitch type\nGood computer knowledge (MS Office - Word, Excel, Chinese Word Processing)\nGood communication skills to liaise with external parties\u00a0\nAble to work independently, a good team player, attentive to details, and able to work under pressure\nImmediate available is highly preferred\n\nInterested parties please send\u00a0your\u00a0detailed resume\u00a0with\u00a0current and\u00a0expected salary\u00a0via the\u00a0\u201cAPPLY NOW\u201d button.", "employment_types": ["Full Time"], "selling_points": ["Familiar with soft-line items eg. woven, paper tag", "Interface overseas staff, customer & factories", "Work in multinational company with 5 days workweek"], "locations": ["Kwai Hing"], "categories": ["Manufacturing", "Garment / Textile", "Product Development / Management"], "post_time": "2022-01-10T14:38:50Z", "salary": {"currency": null, "max": null, "min": null, "period": "monthly", "term": null}, "salary_visible": false, "title_keywords": ["product developer"], "responsibilities": ["ad hoc duties", "technical support", "review", "comments", "evaluate", "liaise with", "plans"], "requirements": {"degrees": [], "majors": [], "languages": ["chinese"], "language_level": ["good"], "hard_skills": ["excel", "chinese word processing", "word", "ms office"], "soft_skills": ["communication skills", "work independently", "good team player", "attentive to details", "work under pressure"], "languages_combined": [{"language": "chinese", "language_level": ["good"]}]}, "experience_required": {"duration": ["at least 5 years"], "field": ["garment", "trading"]}}, {"job_id": "100003009028847", "location_code": "hk", "company": "Topfame (HK) Trading Limited", "job_title": "Assistant Merchandiser/ Merchandiser", "description": "Talent development is at the forefront of Esquel\u2019s strategy. We are inviting high caliber graduates to join us for an exciting career opportunity and be part of a company that believes in innovation and sustainability.\n\nThe Program\nOur Global Management Trainee Program is designed for undergraduates and postgraduates who aspire to advance and excel.\n\nThe Opportunities\u00a0\n\n\nFast track career path\n3 months intensive training from cotton to shirt in our flagship facilities in Guangdong, China\n3 rotations in 2 years in our business units\nParticipation in challenging cross-functional corporate projects\nMentoring by Senior Management\nDevelopment through well-structured curriculum\n360\u00b0\u00a0assessment and feedback\n\nThe Candidates\n\nUndergraduates and postgraduates of any discipline, with no more than 2 years of full time working experience\nGood language skills (English and Mandarin)\nStrong leadership, analytical and presentation skills\nInterest in searching for a new development model in textile industry\nStrong ethics, passion and commitment\nOpen-minded and creative\nIndependent critical thinking\nAgile to be an agent of positive changes\nFlexible in taking up China and/or international posting\n\nAPPLY NOW: http://graduates.esquel.com/\n\nLearn about Esquel and its eCulture values at http://www.esquel.com\u00a0\n\nApplication Deadline: Jan 31, 2022\n\nData collected will be used for recruitment purpose only and will be kept for 24 months.\nAll applications will be treated in strict confidence.\n\n", "employment_types": ["Full Time"], "selling_points": ["Near Lai Chi Kok MTR station", "3yr+ exp about gmt manufacturing  & merchandising", "Travelling is required when needed"], "locations": ["Lai Chi Kok"], "categories": ["Manufacturing", "Garment / Textile", "Merchandising & Purchasing", "Textiles", "Others"], "post_time": "2022-01-07T03:23:40Z", "salary": {"currency": null, "max": null, "min": null, "period": "monthly", "term": null}, "salary_visible": false, "title_keywords": ["merchandiser", "assistant merchandiser"], "responsibilities": ["recruitment", "management", "data", "senior management"], "requirements": {"degrees": [], "majors": [], "languages": ["english", "mandarin"], "language_level": ["good"], "hard_skills": ["excel", "no", "agile"], "soft_skills": ["flexible", "confidence", "independent", "creative", "agile", "open-minded", "presentation skills", "structured", "leadership", "positive"], "languages_combined": [{"language": "english", "language_level": ["good"]}, {"language": "mandarin", "language_level": ["good"]}]}, "experience_required": {"duration": ["2 years"], "field": []}}, {"job_id": "100003009029180", "location_code": "hk", "company": "Hong Kong Aosheng Hi-Tech Limited", "job_title": "Marketing & shipping assistant", "description": "Job Responsibilities\n\nWork closely with Product Development teams and vendors on price negotiations, sample development and approvals.\nCommunicate and negotiate with factories for samples development, cost analysis, etc. to meet client\u2019s quality, cost requirement and due dates.\nFollow-up and monitor orders to ensure quality control and on-time delivery.\nMonitor production schedule to make sure on \u2013time delivery.\n\nJob Requirements\n\nMinimum 2 years working experience in Customer Service and sourcing. Knowledge in labels and garment items are preferable.\u00a0\nDetail-minded, flexible, self-initiative with excellent interpersonal skills.\nNeed to be able to work under pressure, be very clear-minded to handle multi-tasks and project details.\nAbility to work independently and good problem solving skills.\nProficiency in spoken and written English & Chinese (Cantonese & Mandarin).\nProficiency in MS Office applications including Word, Excel and Vlookup.\nImmediate available is preferable.", "employment_types": ["Full Time"], "selling_points": [], "locations": ["Kwai Hing"], "categories": ["Manufacturing", "Garment / Textile"], "post_time": "2022-01-09T07:25:44Z", "salary": {"currency": null, "max": null, "min": null, "period": "monthly", "term": null}, "salary_visible": false, "title_keywords": ["shipping", "assistant"], "responsibilities": ["cost", "quality", "teams", "monitor", "schedule", "quality control", "cost analysis", "negotiate with factories"], "requirements": {"degrees": [], "majors": [], "languages": ["cantonese", "english", "chinese", "mandarin"], "language_level": ["proficiency"], "hard_skills": ["excel", "vlookup", "word", "problem solving skills", "ms office"], "soft_skills": ["detail-minded", "flexible", "work independently", "multi-tasks", "clear", "customer service", "self-initiative", "interpersonal skills", "problem solving skills", "work under pressure"], "languages_combined": [{"language": "cantonese", "language_level": ["proficiency"]}, {"language": "english", "language_level": ["proficiency"]}, {"language": "chinese", "language_level": ["proficiency"]}, {"language": "mandarin", "language_level": ["proficiency"]}]}, "experience_required": {"duration": ["minimum 2 years"], "field": ["customer service"]}}, {"job_id": "100003009035856", "location_code": "hk", "company": "Newtimes Development Limited", "job_title": "Senior Technician (Garment)", "description": "Responsibilities:\n\nDevelop the quality standards,\u00a0policies\u00a0and quality management systems\nManage\u00a0in-house, subcontracting factories, suppliers\u2019 quality standards; conduct audits and performance evaluations\nProvide quality related technical advices and strengthen the supports to merchandising, production and technical related departments in factories\u00a0\u00a0 \u00a0Manage the WIP reports and QA/QC documentation\nCoordinate with all related departments and customers to\u00a0problem-solve the quality issues, build corrective and preventive measures\nSupervise the QA team very closely\nRequirements:\n\nTertiary education or above in Apparel/ Clothing/ Textiles\n5 years or above solid quality management experience in garment manufacturing\nFamilar of printing, embroidery & paper patterns\u00a0\u00a0 \u00a0\u00a0\u00a0 \u00a0\nSound practical skills in building up quality standards and systems, and using QM tools\nProficient verbal and written English and Mandarin\nGood interpersonal communication skills, problem-solving, detailed mind, hands-on approach\nGood PC skills in MS Office and Chinese Word Processing\nWe offer attractive remuneration package to the right candidate.\nPlease send full resume and expected salary via e mail by clicking \"Apply Now\"", "employment_types": ["Full Time", "Permanent"], "selling_points": ["5 years' related experience in garment industry", "5-day work, Lai Chi Kok", "Double Pay, Discretionary Bonus, Birthday Leave"], "locations": ["Lai Chi Kok"], "categories": ["Manufacturing", "Garment / Textile", "Merchandising & Purchasing", "Woven / Knit", "Textiles"], "post_time": "2022-01-10T08:34:02Z", "salary": {"currency": null, "max": null, "min": null, "period": "monthly", "term": null}, "salary_visible": false, "title_keywords": ["technician"], "responsibilities": ["management", "policies", "systems", "quality", "conduct audits", "merchandising", "develop", "coordinate with", "reports", "documentation"], "requirements": {"degrees": [], "majors": [], "languages": ["english", "chinese", "mandarin"], "language_level": ["good", "proficient"], "hard_skills": ["problem-solving", "pc skills", "chinese word processing", "ms office"], "soft_skills": ["communication skills", "problem-solving", "hands-on", "detailed mind", "interpersonal"], "languages_combined": [{"language": "english", "language_level": ["proficient"]}, {"language": "chinese", "language_level": ["good"]}, {"language": "mandarin", "language_level": ["proficient"]}]}, "experience_required": {"duration": ["5 years"], "field": ["garment", "manufacturing", "quality management"]}}, {"job_id": "100003009035925", "location_code": "hk", "company": "Esquel Enterprises Limited", "job_title": "Management Trainee 2022", "description": "\n\u5de5\u4f5c\u5730\u9ede\uff1a\u6e2f\u9435\u6cbf\u7dda\u5206\u5e97\n\n\u85aa\u91d1\uff1a$13,600 (\u4e5d\u9f8d\u6216\u65b0\u754c\u5340) $14,600 (\u6e2f\u5cf6\u5340)\n\u5bcc\u7d93\u9a57\u53ca\u512a\u79c0\u7533\u8acb\u8005\uff0c\u85aa\u91d1\u53ef\u53e6\u8b70\u3002\n\n\u4ee5\u4e0a\u8077\u4f4d\u6bcf\u5929\u5de5\u4f5c9.5\u5c0f\u6642 (\u5305\u62ec1\u5c0f\u6642\u5916\u51fa\u7528\u81b3)\u30016\u5929\u8f2a\u73ed\u5de5\u4f5c\u53ca\u8f2a\u4f11\n\nApply Now 2707 9363 / 2609 4363 / WhatsApp 6109 9397 \u5b89\u6392\u9762\u8a66\n\n\u798f\u5229\u5305\u62ec\u5e74\u5047\u3001\u96d9\u7ce7\u3001\u71df\u696d\u8d85\u984d\u734e\u91d1\u3001\u91ab\u7642\u6d25\u8cbc\u3001\u8d85\u6642\u88dc\u85aa\u3001\u6bcf\u5e74\u81ea\u52d5\u589e\u85aa$200\u3001\u751f\u65e5\u5229\u662f\u53ca\u5f37\u7a4d\u91d1\u7b49\u3002\n\n", "employment_types": ["Full Time", "Permanent"], "selling_points": ["Fast track career path", "3 rotations in 2 years", "Mentoring by senior management"], "locations": ["Not Specified"], "categories": ["Manufacturing", "Garment / Textile", "Sales, CS & Business Devpt", "Retail Sales", "Management", "Management Trainee"], "post_time": "2022-01-10T08:49:30Z", "salary": {"currency": null, "max": null, "min": null, "period": "monthly", "term": null}, "salary_visible": false, "title_keywords": ["management trainee"], "responsibilities": [], "requirements": {"degrees": [], "majors": [], "languages": [], "language_level": [], "hard_skills": ["whatsapp"], "soft_skills": [], "languages_combined": []}, "experience_required": {"duration": [], "field": []}}, {"job_id": "100003009037672", "location_code": "hk", "company": "LAWSGROUP", "job_title": "Administration Manager (Stationed in Overseas)", "description": "Job Responsibilities:\n\nExecuting the account strategies to drive market share gain at Brand level or vendor level for Corporate Accounts to exceed the sales plan;\nIdentifying and develop new business opportunities by developing new customers and maintaining a good relationships with existing customers;\nUnderstanding market and competitive landscape, conducting competitor analysis to formulate the right sales strategies;\nResponsible for pricing negotiation with customers for gaining more business and also meet company's margin expectation;\nLead and collaborate with different departments to meet customer needs;\nAssist in any ad-hoc projects when assigned.\n\nJob Requirements:\n\nDiploma / Degree holder, preferably in sales and marketing or printing-related disciplines;\nMinimum of 1-2\u00a0years sales work experience; printing, trims, and packaging will be an advantage;\nGood command of spoken and written English, Chinese and Mandarin; and other languages would also be an advantage;\nSales-driven personality, independent, analytical and results-oriented\nGood\u00a0interpersonal, commercial, presentation, and solutions selling skills.\n\nWe offer excellent career development opportunities with a highly competitive salary supported by a benefits program including 5-days work, medical, MPF, and sales incentive plan. Interested parties please click \"APPLY NOW\" for application information.\n\n\u00a0**All information collected will be keptstrictly\u00a0 confidential and solely for recruitment purposes.**", "employment_types": ["Full Time", "Permanent"], "selling_points": ["Degree holder with 8 yr relevant work exp.", "Solid exp in garment manufacturing factory", "Stationed in Overseas is required"], "locations": ["Overseas"], "categories": ["Admin & HR", "Others", "Manufacturing", "Garment / Textile", "Others"], "post_time": "2022-01-11T03:27:35Z", "salary": {"currency": null, "max": null, "min": null, "period": "monthly", "term": null}, "salary_visible": false, "title_keywords": ["administration manager"], "responsibilities": ["collaborate with", "develop new business", "maintaining", "analysis", "developing", "executing", "plan", "ad-hoc projects"], "requirements": {"degrees": ["diploma", "degree holder"], "majors": ["related disciplines", "marketing"], "languages": ["english", "chinese", "mandarin"], "language_level": ["good command"], "hard_skills": [], "soft_skills": ["presentation", "interpersonal", "independent", "driven"], "languages_combined": [{"language": "english", "language_level": ["good command"]}, {"language": "chinese", "language_level": ["good command"]}, {"language": "mandarin", "language_level": ["good command"]}]}, "experience_required": {"duration": ["minimum of 1-2 years"], "field": []}}, {"job_id": "100003009036805", "location_code": "hk", "company": "r-pac Hong Kong Ltd", "job_title": "Sales Executive", "description": "Job Responsibilities:\n\nHandle full set of accounts\nPerform daily accounting function including data entries, documents checking, payment and filing\nConduct month-end closing tasks, management & financial reports\nHandle bank reconciliation, monitor bank loan and prepare summary & statement\nReview company transactions, expense & payment vouchers and claims and costing\nUndertake ad-hoc project assigned by the Management\n\nJob Requirements:\n\nLCC Higher or equivalent\nProcess 5 years above solid relevant accounting experience\nProficient in MS office and Accounting system : MYOB, Quick Book\nWell versed in English and Chinese\nCommunicative, accountable, well-organized and logical thinking\n\nApplicant should send application, together with detailed resume, recent photo, current and expected salary, and contact telephone number by clicking APPLY NOW. All personal data collected will be kept in strict confidential and used for recruitment purpose only.", "employment_types": ["Full Time", "Permanent"], "selling_points": ["Selling branding, packaging & RFID solution", "Work with Global Brands & their suppliers", "Work in a multinational company, 5 days workweek"], "locations": ["Kwai Hing"], "categories": ["Sales, CS & Business Devpt", "Business Development", "Manufacturing", "Garment / Textile", "Printing"], "post_time": "2022-01-10T14:38:50Z", "salary": {"currency": null, "max": null, "min": null, "period": "monthly", "term": null}, "salary_visible": false, "title_keywords": ["sales executive"], "responsibilities": ["ad-hoc", "management", "financial reports", "data", "full set of accounts", "monitor", "checking", "bank reconciliation", "review", "transactions", "payment", "month-end closing", "daily accounting"], "requirements": {"degrees": [], "majors": [], "languages": ["english", "chinese"], "language_level": [], "hard_skills": ["lcc", "accounting system", "quick book", "myob", "ms office"], "soft_skills": ["well-organized", "accountable", "detailed"], "languages_combined": [{"language": "english", "language_level": []}, {"language": "chinese", "language_level": []}]}, "experience_required": {"duration": ["5 years"], "field": ["accounting experience"]}}, {"job_id": "100003009038979", "location_code": "hk", "company": "Charter Link Limited", "job_title": "Assistant Accountant", "description": "About the role\nThe Senior Merchandiser, Product Development will be responsible for developing the garment samples for the assigned product / style while working closely with the Merchandising teams of the Vendors. As part of product development team s/he will also be providing support in identifying opportunities of cost saving, onboarding new vendors and executing the innovation agenda for the department in the assigned product.\n\nWhat you will do\n\n\nDownloads tech pack and BOM. Works with vendors for development sampling and initial costs.\nManages counter costing; Handling samples; Tracking fit approvals; Tracking lab dips.\nFollowing up with vendor on system-updates. Manages wear-test samples and tailoring samples.\nEnsures Systems are updated with costs and details. Coordinates MST legacy ID communications for purchase order.\nPartners with brand Design, R&D and key suppliers to develop innovative and quality product.\nPartners with Mill management, QA and technical teams to resolve fabric or quality issues.\nResolves issues within a timely manner while working to continuously improve and create internal and external processes and procedures.\nWho you are\n\nMerchandise Sourcing Knowledge \u2013 Experience in sample development and with offshore production exposure; in large-sized buying office or trading company ; handling Plus size products is a must (Please specify Plus size products experience in detail)\nPlanning & Influencing \u2013 proven experience in plan, prioritize and influence at all levels\nDrive Results \u2013 ability to analyze situations and proactively suggest solutions to meet deliverables\nLearning Agility & Experimentation \u2013 demonstrates eagerness to learn and explore new ways of approaching goals\nEffective Communicator & Team Player - proven capability to communicate effectively, verbal and written\n\nFor over 50 years, Gap Inc. has done more than sell clothes \u2013 we give back to the community and engage in sustainability and environmental initiatives.\u00a0As our communities react to the global health crisis caused by COVID-19, our focus remains on supporting the health and livelihood of our employees while caring for our customers and communities.\u00a0To read more, visit\u00a0https://corporate.gapinc.com/en-us/news/coronavirus-response.\n\nGap Inc. is an equal-opportunity employer and continues to foster a diverse and inclusive environment. We have received numerous awards for our long-held commitment to equality. This year, we\u2019ve been named as one of the\u00a0Best Places to Work by the Humans Rights Campaign for the fifteenth consecutive year\u00a0and have been included in the\u00a02020 Bloomberg Gender-Equality Index for the\u00a0third year in a row.\u00a0\u00a0\n\nAny personal information collected relating to employment applications will be used for recruitment purposes only.\u00a0", "employment_types": ["Full Time"], "selling_points": [], "locations": ["Lai Chi Kok"], "categories": ["Manufacturing", "Garment / Textile"], "post_time": "2022-01-11T16:01:48Z", "salary": {"currency": null, "max": null, "min": null, "period": "monthly", "term": null}, "salary_visible": false, "title_keywords": ["assistant accountant"], "responsibilities": ["management", "systems", "quality", "teams", "design", "develop", "a timely manner", "procedures", "purchase", "costs", "tracking"], "requirements": {"degrees": [], "majors": [], "languages": [], "language_level": [], "hard_skills": ["plus", "bloomberg", "react", "gap", "focus"], "soft_skills": ["focus", "prioritize", "ability to analyze", "diverse", "learning", "team player", "communicator"], "languages_combined": []}, "experience_required": {"duration": [], "field": ["development", "planning"]}}, {"job_id": "100003009030634", "location_code": "hk", "company": "Gap International Sourcing Ltd", "job_title": "Senior Merchandiser  - Knits", "description": "Job Description:\n\nFacilitates the factory quality teams by setting objectives, clear standards, and guidelines to ensure effective cooperation with all suppliers and business counterparts.\nDefines and implement global quality standards, policies, and procedures for the company\nProvides technical advice to buyers, manufacturers, and merchandisers\nDevelops, monitors, and measures quality KPI and implement corrective action plans to improve performance\nWorks with internal HR and 3rd-party suppliers to ensure all are aware and trained on quality expectations\nSources new tech for further enhance quality efficiency\nMaintains and refines group QMS\n\nJob Requirements:\n\nDegree holder\u00a0in Textile & Clothing / IE / Manufacturing\n10 years of solid apparel QA experience in sizeable garment manufacturer (knit or woven), in which 5 years solid management experience in QA team\nWorking experience at buyer office is a plus\nStrong team player who can also work independently and in fast paced environment\nAn ability to identify relevant solutions to address the needs of the customer or sales team\nGood communication skills with different level of people\nStrong data analytical and presentation skills and logical thinking\nFast learner and able to influence suppliers for improvements\nProficiency in computer skills including Microsoft Word & Excel, and Chinese word processing\nGood in spoken & written English, fluent Cantonese and Mandarin\nFrequent travel to China & Cambodia\n\nWe offer competitive remuneration package including\u00a0medical benefit, Year-end bonus and Discretionary Bonus to the right candidate. Interested parties, please email to personnel808@gmail.com or contact us at 5194 1567 for enquiry of further information / to obtain an application form. Please quote the Ref.\u201d JDB \u2013Group Quality Manager\u201d.\u00a0 \u00a0 \u00a0 \u00a0 \u00a0 \u00a0 \u00a0 \u00a0 \u00a0 \u00a0 (All personal data collected will be treated in strict confidence and will be used for the recruitment purposed only. Unsuccessful applications will be properly disposed within 6 months after the end of the selection process.)", "employment_types": ["Full Time"], "selling_points": ["Partner with regional teams", "Multicultural and dynamic environment", "WFH and Flexible working hour"], "locations": ["Kwun Tong"], "categories": ["Manufacturing", "Garment / Textile", "Merchandising & Purchasing", "Woven / Knit", "Textiles"], "post_time": "2022-01-07T07:57:26Z", "salary": {"currency": null, "max": null, "min": null, "period": "monthly", "term": null}, "salary_visible": false, "title_keywords": ["senior merchandiser"], "responsibilities": ["guidelines", "policies", "technical advice", "hr", "teams", "quality", "procedures", "plans"], "requirements": {"degrees": ["degree holder"], "majors": ["manufacturing"], "languages": ["cantonese", "english", "chinese", "mandarin"], "language_level": ["fluent", "proficiency", "good"], "hard_skills": ["excel", "plus", "microsoft word", "chinese word processing", "computer skills"], "soft_skills": ["communication skills", "work independently", "presentation skills", "team player", "fast learner"], "languages_combined": [{"language": "cantonese", "language_level": ["good"]}, {"language": "english", "language_level": ["fluent"]}, {"language": "chinese", "language_level": ["proficiency"]}, {"language": "mandarin", "language_level": ["good"]}]}, "experience_required": {"duration": ["5 years", "10 years"], "field": ["garment", "management", "qa", "team"]}}, {"job_id": "100003009024761", "location_code": "hk", "company": "Wingreat Limited", "job_title": "SENIOR FABRIC MERCHANDISER", "description": "The Role:\nThe Styling Intern will be responsible for assists Stylists on and off set throughout the day in our APAC production studio. The Key responsibilities are including:\n\nWhat You'll Do:\n\nOrganize toolkit and making sure the studio and all materials are tidy\nand in proper place\nSupport toolkit management and organization\nReturn each product to correct rail and department after shooting\nKeep track of toolkit items and make sure all new items are tagged\nproperly\nArrange laundry and dry cleaning for toolkits and essentials regularly\nCreate and maintain an upbeat atmosphere in the studios that is\nconducive to high productivity\n\nWho You Are:\n\nF.7 graduate or Diploma\u00a0holder in related discipline\nAbility to maintain a calm and composed temperament in a frenetic\u00a0environment\nAbility to make quick, on-the-spot decisions \u00a0\u00a0\nKeen eye for detail and style \u00a0\u00a0\nUnderstanding business\u2019 needs from both a creative and production\nperspective\nFlexible \u2018can-do\u2019 attitude\nUnderstanding of seasonal trends and brand adjacencies\nPassionate to Fashion and Styling", "employment_types": ["Full Time"], "selling_points": ["Guaranteed double pay", "Good fringe benefit", "Good working environment"], "locations": ["Kowloon Bay"], "categories": ["Manufacturing", "Garment / Textile"], "post_time": "2022-01-06T02:26:01Z", "salary": {"currency": null, "max": null, "min": null, "period": "monthly", "term": null}, "salary_visible": false, "title_keywords": ["fabric merchandiser"], "responsibilities": ["management", "maintain", "cleaning"], "requirements": {"degrees": ["diploma holder"], "majors": [], "languages": [], "language_level": [], "hard_skills": ["make"], "soft_skills": ["flexible", "passionate", "keen", "calm", "eye for detail", "can-do", "creative"], "languages_combined": []}, "experience_required": {"duration": [], "field": []}}, {"job_id": "100003009028692", "location_code": "hk", "company": "", "job_title": "Assistant Merchandising Manager - Cut & Sewn Knit (Stationed in Cambodia)", "description": "Responsibilities:\n\nLead the team for handling customers enquiries and complaints\nManage our Customer Services team and Quality Assurances team\u00a0including but not limited to\u00a0handle expatriation of QC technician and coordinate the fabric stocks\nResponsible for risk management and problem solving\nPrepare daily and monthly\u00a0evaluation and analysis reports\nFrequent business travel is\u00a0required\nAssist in ad-hoc tasks and projects as assigned\n\nRequirements:\n\nBachelor or above in textile or relevant discipline\nAt least\u00a05 years\u2019 relevant experience at managerial level, preferably with fabric experience\nProactive, Patience, Excellent\u00a0Leadership, Interpersonal and Communication Skills\nFluent in spoken and written Mandarin and English\n\n\u8077\u8cac\uff1a\n\n\u5e36\u9818\u90e8\u9580\u8655\u7406\u5ba2\u6236\u7684\u67e5\u8a62\u548c\u6295\u8a34\n\u7ba1\u7406\u5ba2\u6236\u670d\u52d9\u548c\u54c1\u8cea\u7ba1\u7406\u7684\u5de5\u4f5c\uff0c\u5305\u62ec\u4f46\u4e0d\u9650\u65bc\u6280\u8853\u54e1\u7684\u6d77\u5916\u8abf\u6d3e\u5de5\u4f5c\u53ca\u7d71\u7c4c\u5b58\u5e03\u5b89\u6392\n\u8ca0\u8cac\u98a8\u96aa\u7ba1\u7406\u53ca\u89e3\u6c7a\u554f\u984c\n\u9810\u5099\u65e5\u5e38\u5206\u6790\u5831\u544a\u53ca\u8a55\u4f30\n\u9700\u8981\u5230\u570b\u5167\u5916\u51fa\u5dee\n\u57f7\u884c\u5176\u4ed6\u76f8\u95dc\u6307\u6d3e\u5de5\u4f5c\n\n\u8981\u6c42\uff1a\n\n\u5b78\u58eb\u5b78\u4f4d\u6216\u4ee5\u4e0a\uff0c\u4e3b\u4fee\u7d21\u7e54\n5\u5e74\u53ca\u4ee5\u4e0a\u76f8\u95dc\u7ba1\u7406\u7d93\u9a57\uff0c\u5177\u5e03\u6599\u7d93\u9a57\u8f03\u4f73\n\u4e3b\u52d5\u7a4d\u6975\uff0c\u6709\u8010\u6027\uff0c\u5177\u9818\u5c0e\u624d\u80fd\u53ca\u826f\u597d\u6e9d\u901a\u6280\u5de7\n\u7cbe\u901a\u666e\u901a\u8a71\u53ca\u82f1\u8a9e\n\nWe offer attractive remuneration package to the right candidate. Interested parties please\u00a0submit your full resume with expected salary and availability by\u00a0clicking 'APPLY NOW'.\n\nPersonal data collected will be used for recruitment purpose only.\u00a0We will retain the applications for a maximum period of 12 months after which their personal data will be destroyed.\n\n\u6709\u610f\u7533\u8acb\u8077\u4f4d\u8005\u8acb\u6309\u00a0'APPLY NOW'\uff0c\u63d0\u4f9b\u5c65\u6b77\u53ca\u8981\u6c42\u5f85\u9047\u7533\u8acb\u3002\n\u7533\u8acb\u4eba\u6240\u63d0\u4f9b\u7684\u8cc7\u6599\u5c07\u4e88\u4fdd\u5bc6\u53ca\u53ea\u4f5c\u6709\u95dc\u62db\u8058\u8077\u4f4d\u7528\u9014\uff0c\u5c07\u6703\u4fdd\u7559\u4e0d\u591a\u65bc12\u500b\u6708\u5f8c\u92b7\u6bc0\u3002\n\n\n", "employment_types": ["Full Time", "Permanent"], "selling_points": [], "locations": ["Overseas"], "categories": ["Manufacturing", "Garment / Textile", "Product Development / Management", "Merchandising & Purchasing", "Woven / Knit"], "post_time": "2022-01-07T02:53:32Z", "salary": {"currency": null, "max": null, "min": null, "period": "monthly", "term": null}, "salary_visible": false, "title_keywords": ["merchandising manager", "assistant"], "responsibilities": ["management", "analysis reports", "ad-hoc tasks", "quality", "customer services", "coordinate", "evaluation"], "requirements": {"degrees": ["bachelor"], "majors": [], "languages": ["english", "mandarin"], "language_level": ["fluent"], "hard_skills": [], "soft_skills": ["communication skills", "patience", "proactive", "leadership", "interpersonal"], "languages_combined": [{"language": "english", "language_level": ["fluent"]}, {"language": "mandarin", "language_level": ["fluent"]}]}, "experience_required": {"duration": ["at least 5 years"], "field": ["managerial", "relevant experience"]}}, {"job_id": "100003009024074", "location_code": "hk", "company": "Farfetch HK Production Limited", "job_title": "Styling Intern", "description": "Job Responsibilities:\n\nWork as a project based to explore and develop new factory plant in overseas\nProvide full spectrum of administrative functions including facilities repair and maintenance, deliver services, catering and accommodation services, etc\nTo lead, supervise, review, recommend and implement policies & operational procedures to meet with the Company's development needs and to ensure compliance of the Corporate policies\nResponsible for overall factory operations and management\nHandle ad hoc projects as assigned by immediate supervisor\n\nJob Requirements:\n\nDegree holder or above\nStrong solid experience in all-round garment manufacturing factory environment is a MUST\nMinimum 8 years relevant experience in manufacturing industry including 3 years at managerial level\nSelf-motivated, result-oriented and able to work under pressure\nExcellent interpersonal skills and project management skills\nExcellent command in both spoken and written English and Chinese including Mandarin\nStationed in Overseas is required\n\nWe\u00a0offer\u00a0attractive remuneration package to the right candidate. Interested parties please click the \"APPLY NOW\" button below and send your application together with a detailed resume including current & expected salary and availability to Human Resources Department.\n\nCompany website:\u00a0https://www.lawsgroup.com\n\n(Data collected will be treated in strict confidence and used for recruitment purpose only)", "employment_types": ["Part Time", "Temporary", "Freelance"], "selling_points": ["APAC Production House of Luxury Ecommerce Platform", "High Volume In-House Product Shooting- Model&Still", "Small Team in Proactive StartUp Studio Environment"], "locations": ["Aberdeen"], "categories": ["Design", "Fashion", "Manufacturing", "Garment / Textile", "Quality Assurance, Control & Testing / ISO"], "post_time": "2022-01-07T13:43:18Z", "salary": {"currency": null, "max": null, "min": null, "period": "hourly", "term": null}, "salary_visible": false, "title_keywords": ["intern"], "responsibilities": ["management", "maintenance", "policies", "operations", "review", "develop", "ensure compliance", "repair", "operational procedures", "ad hoc projects", "catering"], "requirements": {"degrees": ["degree holder"], "majors": [], "languages": ["english", "chinese", "mandarin"], "language_level": ["excellent"], "hard_skills": ["project management"], "soft_skills": ["self-motivated", "project management skills", "interpersonal skills", "result-oriented", "work under pressure"], "languages_combined": [{"language": "english", "language_level": ["excellent"]}, {"language": "chinese", "language_level": ["excellent"]}, {"language": "mandarin", "language_level": ["excellent"]}]}, "experience_required": {"duration": ["3 years", "minimum 8 years"], "field": ["garment", "managerial", "manufacturing", "relevant experience", "manufacturing industry"]}}, {"job_id": "100003009030740", "location_code": "hk", "company": "Kam Hing Piece Works Ltd", "job_title": "Manager / Senior Manager \u2013 CS Dept. (\u5ba2\u6236\u670d\u52d9\u7d93\u7406\uff0f\u9ad8\u7d1a\u7d93\u7406) (Stationed in Panyu)", "description": "The Lenzing Group is a world market leader headquartered in Austria, with production sites in all major markets as well as a worldwide network of sales and marketing offices. Lenzing supplies the global textile and nonwovens industry with sustainable high-quality, botanic cellulose fibers. Its portfolio ranges from dissolving pulp to standard and specialty cellulose fibers. In addition to its core business of fibers, the Lenzing Group also operates in the field of engineering and plant construction.\u00a0The Global Marketing and Branding function based in Hong Kong manages the portfolio of consumer ingredient brands including TENCEL(TM) and LENZING(TM) ECOVERO(TM) for fashion and home products, VEOCEL(TM) for wipes, beauty, and hygiene products. Our portfolio of branded fibers are well-positioned to leverage the global trend of environmental protection and mounting consumer demand for sustainable and quality ingredient brands.\u00a0The Lenzing Group invites applications for the position of\u00a0Brand Manager LENZING\u2122 ECOVERO\u2122\u00a0to be based in Hong Kong.\u00a0\n\nReporting to the Head of Global Brand Management, the successful candidate would be responsible mainly for:\n\n\n\nDefine & execute global brand strategy for LENZING\u2122 ECOVERO\u2122, incl. process for branding support to new product launches and development of global campaigns on brand activation. Develop brand content of assigned projects globally & regionally, manage access to brand assets;\nTake responsibility for overall brand performance incl. benchmarking and reporting systems and drive consistency of brand usage throughout the organization;\nAlign with retail brands for co-branding activities;\nSupport and guide regional marketing teams, to ensure a powerful brand activation and execution for regional communications plans and collaborate with the legal team for trademark protection & licensing;\nAlign internal & external partners, media & licensees to ensure execution of branding initiatives;\nSupport brand management process on TX Branding Guidelines, claims, and brand materials development including claims and swing tag system;\nSupport in assigned global brand projects including retailer education and E-learning.\u00a0\nOur expectations for this exciting role:\n\n\n10+ years of experience in Brand Management in consumer-driven /FMCG /Branded Fashion industry or related industry with A-brands;\nProven track record in brand strategy development;\nExperience in 360 global brand activation management;\nA result-oriented experienced brand marketer with a strong business drive;\nExceptional communication and influencing skills in English.\n\nThe annual compensation for this position will fit regional practice and depends on qualifications and experience. Additionally, you will also take part in the Lenzing Group bonus system.\n\nTake the chance to contribute to the success of Lenzing Group's new consumer-first strategy! We look forward to your application.\u00a0\u00a0", "employment_types": ["Full Time", "Permanent"], "selling_points": [], "locations": ["Others - China"], "categories": ["Sales, CS & Business Devpt", "Customer Service - Manager", "Manufacturing", "Garment / Textile", "Quality Assurance, Control & Testing / ISO"], "post_time": "2022-01-07T08:13:43Z", "salary": {"currency": null, "max": null, "min": null, "period": "monthly", "term": null}, "salary_visible": false, "title_keywords": ["senior manager", "manager"], "responsibilities": ["collaborate with", "reporting", "management", "guidelines", "quality", "teams", "develop", "communication", "hygiene", "brand materials", "reporting systems", "plans"], "requirements": {"degrees": [], "majors": [], "languages": ["english"], "language_level": [], "hard_skills": ["reporting systems"], "soft_skills": ["responsible", "driven", "communication", "learning", "result-oriented"], "languages_combined": [{"language": "english", "language_level": []}]}, "experience_required": {"duration": ["10+ years"], "field": ["related", "management", "fmcg", "brand"]}}, {"job_id": "100003009026137", "location_code": "hk", "company": "", "job_title": "Group Quality Manager (Frequent travel to China & Cambodia)", "description": "Job Responsibilities:\n\nHandle the process of the product development.\n\nBrain storm with colleagues for innovative product design, catalog design, seasonal material boards and predicting market trend.\n\nDrive content and graphic creation to promote company for direct marketing.\n\nProvide product information and advices for customers.\n\nPlan and organize marketing programs and events.\n\nLiaise closely and independently with customers, factories and internal departments.\n\nJob Requirements:\n\nTertiary education or above. Minimum 1-2 years related experience (preferably in garment, zipper & trim products industry).\n\nKnowledge of image editing and layout design will be an advantage.\n\nPassionate and observant about fashion and lifestyle news and trends.\n\nCreative, able to work with conceptual ideas and convert to innovative execution.\n\nResponsible, self-motivated, independent, willing to learn and positive attitude.\n\nGood command of English, Mandarin and Cantonese.\n\nWe offer 5-day work week, bank holidays, medical insurance, double pay and discretionary bonus to the right candidate. Interested parties please send your full resume with past & expected salary and availability to Jetco Zipper Limited.", "employment_types": ["Permanent"], "selling_points": ["Provides technical advice to buyers, manufacturers", "Setting objectives, clear standards, and guideline", "Strong data analytical and presentation skills"], "locations": ["Sham Shui Po Area"], "categories": ["Manufacturing", "Garment / Textile", "Others", "Quality Assurance, Control & Testing / ISO"], "post_time": "2022-01-06T07:28:30Z", "salary": {"currency": null, "max": null, "min": null, "period": "monthly", "term": null}, "salary_visible": false, "title_keywords": ["quality manager"], "responsibilities": ["liaise", "product design", "design", "plan"], "requirements": {"degrees": [], "majors": [], "languages": ["cantonese", "english", "mandarin"], "language_level": ["good command"], "hard_skills": [], "soft_skills": ["passionate", "self-motivated", "independent", "responsible", "willing to learn", "innovative", "positive attitude", "creative"], "languages_combined": [{"language": "cantonese", "language_level": ["good command"]}, {"language": "english", "language_level": ["good command"]}, {"language": "mandarin", "language_level": ["good command"]}]}, "experience_required": {"duration": ["minimum 1-2 years"], "field": ["related", "garment"]}}, {"job_id": "100003009027325", "location_code": "hk", "company": "Lenzing Fibers (Hong Kong) Limited", "job_title": "Brand Manager LENZING\u2122 ECOVERO\u2122", "description": "Form 5 graduate or above\nMin 3years experience about garment manufacturing & merchandising.\nOrder follow up with both factory & customers is required\nPC knowledge of Excel, Word and Chinese word processing\nFluent in spoken and written Cantonese, English and Mandarin\nTravelling is required when needed and off-shore manufacturing experience is preferred\nInterested parties, please send full resume by clicking APPLY NOW.", "employment_types": ["Full Time"], "selling_points": ["European MNC (5-day work week)", "Marketing and Branding", "Global Brand exposure"], "locations": ["Kwun Tong"], "categories": ["Manufacturing", "Garment / Textile"], "post_time": "2022-01-06T09:43:24Z", "salary": {"currency": null, "max": null, "min": null, "period": "monthly", "term": null}, "salary_visible": false, "title_keywords": ["manager"], "responsibilities": ["merchandising"], "requirements": {"degrees": ["form 5"], "majors": [], "languages": ["cantonese", "english", "chinese", "mandarin"], "language_level": ["fluent"], "hard_skills": ["excel", "pc knowledge", "chinese word processing", "word"], "soft_skills": [], "languages_combined": [{"language": "cantonese", "language_level": ["fluent"]}, {"language": "english", "language_level": ["fluent"]}, {"language": "chinese", "language_level": []}, {"language": "mandarin", "language_level": ["fluent"]}]}, "experience_required": {"duration": [], "field": ["garment", "manufacturing", "merchandising"]}}, {"job_id": "100003009015549", "location_code": "hk", "company": "Jetco Zipper Limited", "job_title": "Marketing Executive", "description": "SPEED & SPIRIT is what we look for in our candidates, defined by some simple values that inspire us to BE DRIVEN in our performance, BE VIBRANT in our sporting legacy, BE TOGETHER in our team spirit, and BE YOU to let our individual talent and experience shine. Applying for a job at PUMA is easy and all genders are welcome. Simply click APPLY ONLINE and follow the steps to upload your application.\n\nYour Mission\n\nDevelop styles/collections in collaboration with PLM, design and suppliers to secure all possible business opportunities for PUMA\nMake sure products are properly developed to a high standard and at a good price for sales subsidiaries and key accounts\nDrive cross functional communication proactively with internal and external stakeholders to achieve efficient and effective product development process\nEnsure on time sample delivery, product finalization and approval prior to bulk order placement\nResponsible for creation, maintenance and follow up of all work documents (e.g. tech pack, style specification, size tables, fabric and trim selection, fitting and sealing comments, etc.)\nEnsure on time and accurate data administration in systems\nResponsible for cost review and negotiations to meet target FOB prices and profit margins\nCoordinate and take part in seasonal development trips aboard\n\nYour Talent\n\nDiploma or Degree in Textile / Fashion / Clothing related discipline\nover 5 years' relevant experience in garment/sportswear industry is a must\nWoven and knitted garment with strong fabric knowledge and experience\nGood understanding and knowledge of apparel components and product costing\nProficiency in Excel (vlookup and pivot table) is necessary and knowledge of 3D sampling, Photoshop and Adobe Illustrator is preferred\nGood communication and interpersonal skills\nIndependent, self-motivated, responsible, well-organized, team oriented and flexible\nGood command of English and Mandarin\n\nPUMA supports over 14,000 employees across 120+ countries. The PUMA Group owns the brand PUMA, Cobra Golf and stichd, and is headquartered in Herzogenaurach, Germany.\nPUMA provides equal opportunities for all job applicants, regardless of race, color, religion, national origin, sex, gender identity or expression, sexual orientation, age, or disability. Equality for all is one of the core principles at PUMA and we do not tolerate any form of harassment or discrimination.", "employment_types": ["Full Time", "Permanent"], "selling_points": [], "locations": ["Kwai Fong"], "categories": ["Manufacturing", "Garment / Textile"], "post_time": "2022-01-09T16:25:34Z", "salary": {"currency": null, "max": null, "min": null, "period": "monthly", "term": null}, "salary_visible": false, "title_keywords": ["marketing executive"], "responsibilities": ["cost", "maintenance", "data", "business opportunities", "comments", "systems", "review", "design", "develop", "communication", "coordinate", "administration"], "requirements": {"degrees": ["diploma", "degree"], "majors": [], "languages": ["english", "mandarin"], "language_level": ["good command"], "hard_skills": ["simple", "excel", "cobra", "maintenance", "pivot table", "adobe illustrator", "make", "vlookup", "photoshop"], "soft_skills": ["efficient", "flexible", "self-motivated", "team spirit", "independent", "responsible", "well-organized", "communication", "communication and interpersonal skills", "accurate", "driven"], "languages_combined": [{"language": "english", "language_level": ["good command"]}, {"language": "mandarin", "language_level": ["good command"]}]}, "experience_required": {"duration": ["5 years"], "field": ["garment", "relevant experience", "team"]}}, {"job_id": "100003009032363", "location_code": "hk", "company": "World Cat Limited", "job_title": "Senior Developer Apparel", "description": "- At least 1~5 years exerience in sweater field\n- Responsible for communication w/ buyers and production follow up\n- Good command of English and Mandarin\n- Proficient in PC knowledge", "employment_types": ["Full Time", "Permanent"], "selling_points": ["Garment Development", "Flexible working hours", "Fun and energetic working environment"], "locations": ["Kowloon Bay"], "categories": ["Manufacturing", "Garment / Textile", "Product Development / Management"], "post_time": "2022-01-07T10:54:44Z", "salary": {"currency": null, "max": null, "min": null, "period": "monthly", "term": null}, "salary_visible": false, "title_keywords": ["developer"], "responsibilities": ["communication"], "requirements": {"degrees": [], "majors": [], "languages": ["english", "mandarin"], "language_level": ["good command"], "hard_skills": ["pc knowledge"], "soft_skills": ["communication", "responsible"], "languages_combined": [{"language": "english", "language_level": ["good command"]}, {"language": "mandarin", "language_level": ["good command"]}]}, "experience_required": {"duration": [], "field": []}}, {"job_id": "100003009027224", "location_code": "hk", "company": "Winline Knitting Factory Limited", "job_title": "Assistant Merchandiser & Merchandiser", "description": "Responsibilities:\n\nOversee all sample fabric and trim ordering, all initial fabric testing, and reports plus FOB costs negotiation\nProvide solutions for bulk fabric quality issues to support the production process\nManage timely sample fabric ordering, color and quality approval, bulk lot, and test approval to meet all required deadlines\nEvaluate and track mills\u2019 performance, resolve potential risk and conduct trouble-shooting to avoid quality or delivery issues at the bulk stage\nManage & maintain a color library on a seasonal base and support the production team for bulk color and qualities issues\u00a0\n\nRequirements:\n\nDiploma holder with at least 5 years relevant experience\nSolid experience in\u00a0garment or raw material manufacturing, woven fabric development especially in suiting and shirt fabric categories for apparel brands\nIn-depth knowledge of fiber, weaving, dyeing and finishing, inspection procedures, and testing methods for textiles\nSound fabric and lab test knowledge, proven experience in mills training, specific on quality/color approval is a plus\nGood command of spoken and written English and Chinese (including Cantonese & Mandarin)\n\nWe offer:\u00a0\n\nAttractive salary package\nDiscretionary Performance Bonus\nMedical Insurance\nStaff Discounts on Purchases\n5-day work week with flexible work options\nVoluntary MPF Contributions\n\nInterested parties, please send us your application via\u00a0APPLY NOW.\n\nOnly shortlisted candidates will be notified. If you are not contacted by us within\u00a02 weeks, please consider your application unsuccessful. All personal data collected would be used for recruitment purpose only.\n\n\u00a0Please visit our website for more information:\u00a0www.G2000.com.hk", "employment_types": ["Full Time"], "selling_points": ["Bank Holidays", "Medical Scheme", "8 Days Extra Paid Annual Leave"], "locations": ["Kwai Hing"], "categories": ["Manufacturing", "Garment / Textile"], "post_time": "2022-01-06T09:24:59Z", "salary": {"currency": null, "max": null, "min": null, "period": "monthly", "term": null}, "salary_visible": false, "title_keywords": ["merchandiser", "assistant merchandiser"], "responsibilities": ["production process", "delivery issues", "quality", "provide solutions", "testing", "evaluate", "maintain", "reports", "costs"], "requirements": {"degrees": ["diploma holder"], "majors": [], "languages": ["cantonese", "english", "chinese", "mandarin"], "language_level": ["good command"], "hard_skills": ["plus"], "soft_skills": [], "languages_combined": [{"language": "cantonese", "language_level": ["good command"]}, {"language": "english", "language_level": ["good command"]}, {"language": "chinese", "language_level": ["good command"]}, {"language": "mandarin", "language_level": ["good command"]}]}, "experience_required": {"duration": ["at least 5 years"], "field": ["garment", "manufacturing", "training", "development", "relevant experience"]}}, {"job_id": "100003009027594", "location_code": "hk", "company": "G2000 (Apparel) Ltd", "job_title": "Senior / Fabric Merchandiser", "description": "Responsibilities:\n\nMonitor and coordinate finance and accounting activities of overseas offices in Asia\u00a0\nFocus on Account Receivables functions and financial reporting\nPrepare monthly consolidated management accounts, cash flow reports, annual budget and various financial/ management analysis of overseas offices\nPerform expense, working capital, CAPEX control of overseas offices\nCommunicate and\u00a0Focus on Account Receivables functions and financial reporting to ensure compliance of company standards and local statutory laws\nAssist in ad hoc projects\n\nRequirements:\n\nImmediately available is highly preferred\nTertiary educated and above\nA minimum 3 years relevant work experience, and experience of fashion/ garment industry would be an advantage\nDetailed-oriented and self-motivated\nAble to perform job with accuracy and able to meet tight deadlines\nHigh proficiency in MS Office application, knowledge in Microsoft Dynamics AX would be an advantage\nGood command of English and Chinese\n\nInterested parties please send your application with current salary, expected salary and availability via \u201cAPPLY NOW\u201d button.\n\n(Collected personal data will be kept strictly confidential and used for recruitment purpose only.)", "employment_types": ["Full Time", "Permanent"], "selling_points": ["Sound fabric and lab test knowledge", "Good order and venders management skills", "Strong communication & negotiation skills"], "locations": ["Kwai Fong"], "categories": ["Manufacturing", "Garment / Textile", "Merchandising & Purchasing", "Fabrics", "Woven / Knit"], "post_time": "2022-01-06T10:31:38Z", "salary": {"currency": null, "max": null, "min": null, "period": "monthly", "term": null}, "salary_visible": false, "title_keywords": ["fabric merchandiser"], "responsibilities": ["management", "control", "analysis", "budget", "monitor", "capex", "cash flow reports", "ensure compliance", "coordinate", "ad hoc projects", "financial reporting"], "requirements": {"degrees": [], "majors": [], "languages": ["english", "chinese"], "language_level": ["good command"], "hard_skills": ["garment industry", "ms office"], "soft_skills": ["self-motivated", "meet tight deadlines", "detailed"], "languages_combined": [{"language": "english", "language_level": ["good command"]}, {"language": "chinese", "language_level": ["good command"]}]}, "experience_required": {"duration": ["minimum 3 years"], "field": ["garment"]}}, {"job_id": "100003009026067", "location_code": "hk", "company": "Lululemon HK Limited", "job_title": "Production Analyst (6 Months)", "description": "We prioritize to go through applicants who apply through our career web page and encourage you to apply using the link below:\u00a0https://careers.lululemon.com/en_US/careers/JobDetail/Hong-Kong-Island-Hong-Kong-Production-Analyst-6-Months/16178\n\nWho we are\nlululemon is an innovative performance apparel company for yoga, running, training, and other athletic pursuits. Setting the bar in technical fabrics and functional design, we create transformational products and experiences that support people in moving, growing, connecting, and being well. We owe our success to our innovative product, emphasis on stores, commitment to our people, and the incredible connections we make in every community we're in. As a company, we focus on creating positive change to build a healthier, thriving future. In particular, that includes creating an equitable, inclusive and growth-focused environment for our people.\n\nAbout this team\nThe lululemon Liaison Office (LLO) team is dedicated to ensuring our components are produced of the highest quality, delivered when we need them, and manufactured with partners who share our commitment to elevating the world. Not only do we manage the production of great product, we also build great relationships.\n\n\nA day in the life:\n\nReport and support the Merchandising Manager to manage production from BUY confirmation to shipment\nWork closely with the vendors on lululemon production and logistics policies, processes and IT systems;\nManage production process, which includes WIP, PO change, WWMT and the BUY confirmation to negotiate the best delivery with vendors;\nAnalyze the capacity and capability of vendors to make sure they can deliver the right product and on time, escalate potential issues to support teams;\nFollow up on liability SOP with vendors due to cancellation;\nAble to anticipate high-risk areas and take the lead in resolving any potential or current issues with cross-functional teams to minimize the immediate impact;\nPrepare the Past Due Date and Delay Reason Code report;\nWork closely with our Compliance and Quality teams in ensuring that our social compliance and quality standards are adhered to, and goals are met, and communicate delivery statuses and issues to appropriate SSC counterparts in a timely and concise manner\n\nQualifications:\n\nYour ideal background: Higher Diploma or Bachelor\u2019s degree in Textiles or related fields; 5+ years experience in a similar role within a production environment; good understanding of technical fabrics, garment construction and related machinery.\nYou can analyze work flow and can access bottlenecks; are fluent in Mandarin and English;\nStrong IT skills needed \u2013 you are an MS Excel guru (V Lookup and Pivot Table knowledge essential)! And you love working with a lot of Microsoft Office, Tradestone, GTNexus and FlexPLM!\nMust haves:\n\nAcknowledges the presence of choice in every moment and takes personal responsibility for their life.\nPossesses an entrepreneurial spirit and continuously innovates to achieve great results.\nCommunicates with honesty and kindness, and creates the space for others to do the same.\nLeads with courage, knowing the possibility of greatness is bigger than the fear of failure.\nFosters connection by putting people first and building trusting relationships.\nIntegrates fun and joy as a way of being and working, aka doesn\u2019t take themselves too seriously.\u00a0\nNOTE: Only those applicants under consideration will be contacted. Please accept our utmost appreciation for your interest. lululemon is an Equal Employment Opportunity employer. Employment decisions are based on merit and business needs, and not on race, color, creed, age, sex, gender, sexual orientation, national origin, religion, marital status, medical condition, physical or mental disability, military service, pregnancy, childbirth and related medical conditions or any other classification protected by federal, state or provincial and local laws and ordinances. Reasonable accommodation is available for qualified individuals with disabilities, upon request. This Equal Employment Opportunity policy applies to all practices relating to recruitment and hiring, compensation, benefits, discipline, transfer, termination and all other terms and conditions of employment. While management is primarily responsible for seeing that lululemon equal employment opportunity policies are implemented, you share in the responsibility for assuring that, by your personal actions, the policies are effective.", "employment_types": ["Full Time", "Contract"], "selling_points": ["Good understanding of technical fabrics/garment", "Strong in V Lookup and Pivot Table", "Eager to collaborate and grow with the team"], "locations": ["Tin Hau"], "categories": ["Manufacturing", "Garment / Textile", "Merchandising & Purchasing", "Woven / Knit", "Textiles"], "post_time": "2022-01-06T07:18:13Z", "salary": {"currency": null, "max": null, "min": null, "period": "monthly", "term": null}, "salary_visible": false, "title_keywords": ["analyst"], "responsibilities": [], "requirements": {"degrees": [], "majors": [], "languages": [], "language_level": [], "hard_skills": ["go", "web"], "soft_skills": ["prioritize"], "languages_combined": []}, "experience_required": {"duration": [], "field": []}}, {"job_id": "100003009018797", "location_code": "hk", "company": "Farfetch HK Production Limited", "job_title": "Part Time Production Assistant", "description": "THE ROLE\n\nThe Production Assistant will be responsible for the shipment and handling of clothing and accessories items in our APAC production studio, in order to ensure that these items are in good conditions after being used for photoshoot and before being sent back to the respective boutiques.\n\nWHAT YOU'LL DO\u00a0\n\nHandling and preparing articles (clothing and accessories) for the production process, including ironing, data entry and packing of various branded fashion items\nQuality and defect control of received articles\nIroning of clothing articles\nData entry and validation of the articles in the production system\nPacking articles of clothing/accessories for shipment\n\nWHO YOU ARE\n\nDiploma or above in Fashion or related discipline\nProficient in MS Excel\nAble to work to tight deadlines, have sense of urgency and attitude of \"making things happen\"\nAmazing communication and interpersonal skills\nExperience in handling clothes and accessories is an advantage\nIndependent, detail-minded with good efficiency and very organized person;\nWilling to learn, responsible, patient and able to work under pressure;\nOutgoing, creative, self-motivated and interested in fashion;\nGood command of both spoken and written English\nPassionate on what Farfetch does and the role\nFresh graduate will also be considered\n\n\nEQUAL OPPORTUNITIES STATEMENT\n\nFARFETCH is an equal opportunities employer ensuring that all applicants are treated equally and fairly throughout our recruitment process. We are determined that no applicant experiences discrimination on the basis of sex, race, ethnicity, religion or belief, disability, age, gender identity, ancestry, sexual orientation, veteran status, marriage and civil partnership, pregnancy and maternity, or any other basis prohibited by applicable law. We continue to build our consciously inclusive culture as part of our Positively FARFETCH strategy throughout our business, partnerships and communities.", "employment_types": ["Part Time", "Temporary"], "selling_points": ["APAC Production House of Luxury Ecommerce Platform", "Handling of Luxury Fashion Items for Photoshoots", "Small Team in Proactive StartUp Studio Environment"], "locations": ["Ngau Tau Kok"], "categories": ["Manufacturing", "Garment / Textile", "Transportation & Logistics", "Inventory / Warehousing", "Sales, CS & Business Devpt", "Retail Sales"], "post_time": "2022-01-07T13:36:48Z", "salary": {"currency": null, "max": null, "min": null, "period": "monthly", "term": null}, "salary_visible": false, "title_keywords": ["production assistant"], "responsibilities": ["control", "production process", "data entry", "quality", "communication", "recruitment process", "work under pressure"], "requirements": {"degrees": ["fresh graduate", "diploma or above"], "majors": [], "languages": ["english"], "language_level": ["good command"], "hard_skills": ["no", "ms excel"], "soft_skills": ["detail-minded", "organized", "outgoing", "self-motivated", "independent", "passionate", "responsible", "determined", "urgency", "interested in", "willing to learn", "communication and interpersonal skills", "patient", "creative", "work under pressure"], "languages_combined": [{"language": "english", "language_level": ["good command"]}]}, "experience_required": {"duration": [], "field": []}}, {"job_id": "100003009035375", "location_code": "hk", "company": "Ka Hung Gloves Industrial Co Ltd", "job_title": "Accounts Clerk", "description": "\u00a0Responsibilities\n\nResponsible\u00a0for handling full set account, handling general accounting duties, data entry, invoice checking, supplier statement reconciliation, consolidation, month\u00ad end and year\u00ad end accounting report, financial reports, etc.\nCarry out routine account duties include invoice and payment process\nResponsible for data input, AR and AP related transactions\nFull set of Accounts experience would be preference\nLiaise with auditors to facilitate external audits\nAssisting ad-hoc assignment as required\n\nRequirement\n\nAt least 5 years' experience in both Manufacturing & Trading background ;\nHigher Diploma or above in Accounting related discipline with LCCI Level 3 or above\nWell experience in MS Word/Excel and Chinese Word processing; well versed in using accounting software(MYOB), Peachtree/ ERP systems and MS office;\u00a0\nExperience in liaising with auditor, mainland supplier and overseas customers is\u00a0\u00a0\u00a0\u00a0\u00a0 preferrable\nKnowledge of handling company secretarial tasks (e.g. filing of annual return) would\u00a0be a plus\nGood command of both spoken and written English, Cantonese and Mandarin\nSelf-motivated, detail-oriented, good time management and with strong sense of responsibility\nHandling HR & Adminstration duties.\n\nWe offer 5 days + Alternate Saturday.\u00a0 Excellent career prospects, personalized on job trainings and fringe benefits to the right candidate.\u00a0 Interested parties please send full resume and expected salary for application.", "employment_types": ["Full Time"], "selling_points": ["Double pay/Discretionary bonus & Medical Ins", "Exp in Med size Co, handle for more Co's A/Cs", "Manufacturing & Trading background"], "locations": ["Ngau Tau Kok"], "categories": ["Accounting", "Accountant", "Admin & HR", "Clerical / Admin Staff", "Manufacturing", "Garment / Textile"], "post_time": "2022-01-10T06:57:58Z", "salary": {"currency": null, "max": null, "min": null, "period": "monthly", "term": null}, "salary_visible": false, "title_keywords": ["accounts clerk"], "responsibilities": ["ap", "ad-hoc", "financial reports", "ar", "data entry", "invoice", "full set of accounts", "checking", "data input", "transactions", "audits", "general accounting duties", "payment process", "liaise with", "report"], "requirements": {"degrees": ["higher diploma or above"], "majors": ["accounting"], "languages": ["cantonese", "english", "chinese", "mandarin"], "language_level": ["good command"], "hard_skills": ["excel", "erp systems", "plus", "chinese word processing", "peachtree", "ms office", "ms word"], "soft_skills": ["self-motivated", "time management", "sense of responsibility", "detail-oriented"], "languages_combined": [{"language": "cantonese", "language_level": ["good command"]}, {"language": "english", "language_level": ["good command"]}, {"language": "chinese", "language_level": []}, {"language": "mandarin", "language_level": ["good command"]}]}, "experience_required": {"duration": ["at least 5 years"], "field": ["manufacturing", "trading"]}}, {"job_id": "100003009025713", "location_code": "hk", "company": "G.A. Operations Hong Kong Limited", "job_title": "Senior Merchandiser - Garment Production", "description": "This position will be responsible to make sure the vendors production of our garment products from planning to pre-production, into bulk and quality control phases.\n\nKey responsibilities:\n\nl Review production planning with vendors / HQ Italy\nl Work closely with Italy counterpart to understand the production requirements, communicate with\u00a0 the factories on technical aspects and make necessary recommendations for quality improvements\nl Check and review all bulk production materials and manage production costs and negotiate production surcharge with vendors\nl Coordinate and monitor day-to-day production activities in accordance with the master production plan\nl Monitor the quality control process to ensure end-products aligning with the product specifications\n\nRequirements:\n\nl Diploma or above in Garment or Merchandising related disciplines\nl 6 to 8 years\u2019 solid experience in manufacturing industry, specifically in production and quality area\nl Good technical knowledge in garment production phases\nl Attentive to details and willing to take up challenges\nl Good interpersonal and communication skills, strong sense of team spirit and responsibility\nl Good verbal and written command of the English is a must", "employment_types": ["Full Time", "Permanent"], "selling_points": [], "locations": ["Kowloon Bay"], "categories": ["Manufacturing", "Garment / Textile"], "post_time": "2022-01-06T06:19:18Z", "salary": {"currency": null, "max": null, "min": null, "period": "monthly", "term": null}, "salary_visible": false, "title_keywords": ["senior merchandiser"], "responsibilities": ["communicate with", "review", "quality", "production planning", "monitor", "coordinate", "specifications", "plan", "quality control", "costs"], "requirements": {"degrees": ["diploma or above"], "majors": ["related disciplines"], "languages": ["english"], "language_level": ["good"], "hard_skills": [], "soft_skills": ["communication skills", "team spirit", "interpersonal", "attentive to details"], "languages_combined": [{"language": "english", "language_level": ["good"]}]}, "experience_required": {"duration": ["6 to 8 years"], "field": ["manufacturing industry"]}}, {"job_id": "100003009032433", "location_code": "hk", "company": "Delta Bogart Lingerie Limited", "job_title": "Lingerie Design / Fashion Graphic Designer", "description": "Job Requirements:\n\n\nDegree holder in Fashion, Textiles or Graphic Design\n2-3 years of relevant design experience, preferred in Garment\nWith knowledge in software Browzwear is preferred\nGood command of written and spoken, English and Chinese\nProficiency in Illustrator, Photoshop and MS Office\nStrong research and analysis skills\nCreative with ability to explore assemble methods and material used\nIndependent, from research, design to supervision of samples made\nCandidate with less experience will be considered as Assistant Designer\nImmediately available is preferred\n\n\n\nWe offer attractive remuneration package and career development opportunities for the right candidate.\n\nFor qualified candidates, please send your application with\u00a0full resume, stating salary expectations\u00a0to the HR Department by e-mail to \u201chr at hk.bogartlingerie.com\u201d, or by \u201cApply Now\u201d via JobsDB for interview.\n\nPersonal data provided by job applicants will be used for recruitment purposes only. Applicants who are not invited for interviews within six weeks may consider their applications unsuccessful. All personal data of unsuccessful applicants will be destroyed.", "employment_types": ["Full Time"], "selling_points": [], "locations": ["Kowloon Bay"], "categories": ["Design", "Fashion", "Graphics", "Manufacturing", "Garment / Textile"], "post_time": "2022-01-07T11:05:54Z", "salary": {"currency": null, "max": null, "min": null, "period": "monthly", "term": null}, "salary_visible": false, "title_keywords": ["fashion graphic designer"], "responsibilities": ["graphic design", "analysis", "software", "design"], "requirements": {"degrees": ["degree holder"], "majors": ["graphic design"], "languages": ["english", "chinese"], "language_level": ["good command"], "hard_skills": ["analysis", "ms office", "illustrator", "photoshop"], "soft_skills": ["creative", "independent"], "languages_combined": [{"language": "english", "language_level": ["good command"]}, {"language": "chinese", "language_level": ["good command"]}]}, "experience_required": {"duration": ["2-3 years"], "field": ["garment", "designer", "design"]}}, {"job_id": "100003009026994", "location_code": "hk", "company": "HK Research Institute of Textiles & Apparel Ltd", "job_title": "Researcher (Ref. No.: HKRITA-RP)", "description": "[Work Location: Science Park, Shatin]\nThe appointee(s) will be required to\ntake preliminary research/analysis of target technology areas;\nbe responsible for conducting R&D activities, such as literature review, carrying out experiments, studying and summarizing research findings and development of prototypes;\nmanage R&D projects, including technical and financial aspects and other project administrative tasks, such as preparing project updates and reports;\nwork closely with R&D researchers and personnel; coordinate with local and overseas universities, research institutions and business partners, and handle enquiries in a professional manner; and\nperform any other duties as assigned.\nRequirements:\nA bachelor\u2019s degree or above in any STEM subjects from a well-recognized university;\nHighly-organized and capable of working under pressure with multi-task assignments;\nGood interpersonal skills; and\nA good command of both written and spoken English and Chinese, with fluency in Putonghua being an advantage.\nApplicants should state their current and expected salary in the application. Salary offered will be commensurate with qualifications and experience. Appointment will be offered on a contract basis, re-engagement thereafter is subject to mutual agreement.\nApplicants are invited to send detailed curriculum vitae in strict confidence to Human Resources Manager, HKRITA, R906-8, Shirley Chan Building, The Hong Kong Polytechnic University, Hung Hom, Kowloon. (E-mail via \"Apply Now\"). Recruitment will continue until the position is filled. HKRITA reserves the right to consider late applications and nominations, and to fill or not to fill the positions. Personal data provided by applicants will be used for recruitment and other employment-related purpose. Please mark \u201cPRIVATE & CONFIDENTIAL\u201d and quote the position applied for and its reference number on the envelope.", "employment_types": ["Full Time", "Contract"], "selling_points": [], "locations": ["Shatin Area"], "categories": ["Engineering", "Chemical", "Manufacturing", "Garment / Textile", "Sciences, Lab, R&D", "Research & Development (R&D)"], "post_time": "2022-01-07T19:19:30Z", "salary": {"currency": null, "max": null, "min": null, "period": "monthly", "term": null}, "salary_visible": false, "title_keywords": ["researcher"], "responsibilities": [], "requirements": {"degrees": [], "majors": [], "languages": [], "language_level": [], "hard_skills": [], "soft_skills": [], "languages_combined": []}, "experience_required": {"duration": [], "field": []}}, {"job_id": "100003009031496", "location_code": "hk", "company": "Links International", "job_title": "Associate Sourcing Manager - Production focus", "description": "Associate Sourcing Manager - Apparel\n\nOur client is a large international fashion retailer, looking for a Associate Sourcing Manager join their organisation.\n\nJob Description:\n\n\nIdentify and source vendors, taking into account of cost, quality, delivery and capacity.\nMaintain vendor relationships to execute regional sourcing strategies\nManage KPI and Vendor Action Plans to obtain Vendor Scorecard results above targets set by Strategic Sourcing\nPlan orders and capacity management with vendors based on the seasonal forecasts and business needs.\nAnalyze over/ under capacity adoption, assist & support the senior management in delivering, leading & quality requirement.\nWork with key business stakeholders to ensure and maintain agreed dates and timeline.\nAssess and evaluate the overall capabilities and performance of all vendors ( including development, bulk execution, quality and CSR rating ), and make recommendation to management.\nSupport price negotiation processes and provide best market intelligence to deliver the cost optimization.\nPartner with technical and product development team to improve vendors' product capabilities and lead time reduction.\nManage liability in respect to verify liability amount and cross check if it is eligible to achieve the goal of liability control.\n\nRequirements:\n\n\nDegree caliber - ideally a degree gained from Manufacturing, Textiles, Apparel Merchandising or Business Administration\nMinimum 8 years working experience in product development and sourcing. Product knowledge of lifestyle/functional, sports and printing techniques is preferrable.\nSolid experience in global sourcing environment, product development/ production and sourcing bases in China and Far East Asia.\nExperience in working with USA and China Market is an advantage.\nExcellent project management, communication, time management and interpersonal skills.\nStrong analytical, creative problem solving and decision-making skills.\nGood knowledge in MS office, skillful of MS Excel (Vlookup), PowerPoint are essential.\nExcellent command of written and spoken English, Cantonese, and Mandarin.\nWilling to travel.", "employment_types": ["Full Time", "Permanent"], "selling_points": ["Degree in Merchandising, Fashion or related", "8 years of sourcing experience(US market)", "International working environment"], "locations": ["Not Specified"], "categories": ["Manufacturing", "Garment / Textile", "Manufacturing Management", "Merchandising & Purchasing", "Procurement / Purchasing / Sourcing"], "post_time": "2022-01-07T09:22:46Z", "salary": {"currency": null, "max": null, "min": null, "period": "monthly", "term": null}, "salary_visible": false, "title_keywords": ["associate sourcing manager"], "responsibilities": ["cost", "management", "make recommendation", "price negotiation", "cost optimization", "control", "quality", "evaluate", "maintain", "plan", "plans", "senior management"], "requirements": {"degrees": ["degree"], "majors": ["manufacturing", "business administration"], "languages": ["cantonese", "english", "mandarin"], "language_level": ["excellent"], "hard_skills": ["powerpoint", "problem solving", "project management", "ms excel", "vlookup", "ms office"], "soft_skills": ["creative", "communication", "project management", "problem solving", "interpersonal skills", "time management"], "languages_combined": [{"language": "cantonese", "language_level": ["excellent"]}, {"language": "english", "language_level": ["excellent"]}, {"language": "mandarin", "language_level": ["excellent"]}]}, "experience_required": {"duration": ["minimum 8 years"], "field": ["product development"]}}, {"job_id": "100003009022680", "location_code": "hk", "company": "Newsprint Production Group Ltd", "job_title": "Product Developer", "description": "APPLY NOW\u00a0\n\nDegree Holder or above with 2 years working experience;\nProficiency in Microsoft Excel; Good analytical skills;\nCapability to prioritize work and manage several projects at a time;\nCommunication ability in spoken and written English and Chinese (Mandarin is a MUST);\nPrior knowledge in labels and packaging industry will be a plus, but not necessary.\n\nTHE JOB\n\nGet brief from Sales team and study product's feasibility;\nSelect suitable materials and processes;\nCalculate costings through existing tools and maintenance of databases;\nMaintain relationship & smooth communication with suppliers;\nWork closely with HK other teams such Production, Logistic & Merchandising;\nEuropean customer oriented\nAd hoc assignments for communication and certification purpose (FSC, OEKO TEX, etc);\nBecome part of our dynamic team, bring your vision and your energy.\n\nWe work in a nice, modern and convenient office (only 3 minutes walk from Chai Wan MTR station).\n\nPlease visit our website: www.newsprintgroup.com\u00a0\n\nWe offer competitive remuneration package with comprehensive fringe benefits to the right candidate. Interested parties, please CLICK the \"APPLY NOW\" button,\u00a0and send your resume to us with your last and expected salary.\n\nAll personal data collected will be treated in strict confidence and used for recruitment only.", "employment_types": ["Full Time", "Permanent"], "selling_points": ["Proficiency in Microsoft Excel, Foreigner welcome", "Off-set Printing, paper, labels", "Spoken & Written English & Mandarin"], "locations": ["Chai Wan"], "categories": ["Manufacturing", "Garment / Textile", "Product Development / Management", "Printing"], "post_time": "2022-01-05T06:12:46Z", "salary": {"currency": null, "max": null, "min": null, "period": "monthly", "term": null}, "salary_visible": false, "title_keywords": ["product developer"], "responsibilities": ["maintenance", "teams", "merchandising", "website", "communication", "maintain", "sales team", "ad hoc assignments", "databases"], "requirements": {"degrees": ["degree holder"], "majors": [], "languages": ["english", "chinese", "mandarin"], "language_level": [], "hard_skills": ["plus", "maintenance", "tex", "nice", "analytical skills", "microsoft excel", "dynamic", "databases", "wan"], "soft_skills": ["prioritize", "analytical skills", "communication", "dynamic", "smooth"], "languages_combined": [{"language": "english", "language_level": []}, {"language": "chinese", "language_level": []}, {"language": "mandarin", "language_level": []}]}, "experience_required": {"duration": ["2 years"], "field": []}}, {"job_id": "100003009026482", "location_code": "hk", "company": "Triumph International Services (APAC) Limited", "job_title": "Pattern Maker", "description": "Triumph is one of the world\u2019s largest intimate apparel companies. It enjoys a presence in over 120 countries with the core brands Triumph\u00ae and sloggi\u00ae. Globally, the company serves 40,000 wholesale customers and sells its products in 4,050\u00a0controlled points of sale as well as via several own online shops. The Triumph Group is a member of the Business Social Compliance Initiative (BSCI).\n\nLearn more about Triumph on:\n\nwww.triumph.com\n\nwww.linkedin.com/company/triumph-international/\n\nOur Pattern & Fit Department at the Kowloon Bay, Hong Kong is looking immediately for a highly motivated\u00a0Pattern Maker\n\nRoles & Responsibilities:\n\nPrototype creation: patternmake and develop and fitting process to critical deadlines of all new concepts for presentation to the brand.\nAdvise suitable construction and solve fitting and workmanship problems.\nInteract with sewing room, relevant departments and production centres.\nPrepare documents and patterns for sewing and costing.\nCreate Bom\u2019s and splitting.\nFit process: following up styles development according to critical deadlines until styles ready for production.\nDevelop product based on input and in accordance to deadline.\nInitiate testing of new materials\nPrepare documents (BOM\u2019s, size splitting) and patterns for sewing,\nStyle development (from first prototype to production pattern) and fitting process according to workflow, solve fitting problems\nInteract with sewing room and production centers to solve workmanship problems and ensure constructions are workable for production.\nLiaise with Molding department and PD department for sample making.\n\nYour ideal profile:\n\nTechnical skills \u2013 Pattern Development with 3D software (Gerber, Lectra or similar), Garment Construction, Ability to translate 2D design into 3D prototype\nLanguage Skills \u2013 Cantonese, good command of English (written and spoken), Mandarin (optional)\nIT proficiency \u2013 MS Ofiice, Gerber/Lectra, PLM\nTeam player with great communication skills.\nAbility to travel if required to other regions.\n\nWe offer an opportunity in a fast paced organization which gives those looking for a challenge the possibility to grow with the company and shape the future.\n\nWe are a family owned company with strong values, operating at a global level with key markets in Germany, Japan and China - where our iconic brands, Sloggi and Triumph, continue to delight our consumers.\n\nTriumph Group is committed to employing a diverse workforce. Qualified applicants will receive consideration without regard to race, color, religion, sex, national origin, age, sexual orientation, gender identity, gender expression, veteran status, or disability.\u00a0\n\nIf you are seeking a great opportunity to develop your career, please send us your application letter and CV in English, diplomas and expected salary range by clicking on Apply.\u00a0", "employment_types": ["Full Time", "Permanent"], "selling_points": ["pattern maker", "Similar experience in Lingerie, active wear, swim", "pattern development"], "locations": ["Kowloon Bay"], "categories": ["Manufacturing", "Garment / Textile", "General / Production Workers"], "post_time": "2022-01-06T08:15:56Z", "salary": {"currency": null, "max": null, "min": null, "period": "monthly", "term": null}, "salary_visible": false, "title_keywords": [], "responsibilities": ["software", "compliance", "design", "testing", "develop", "communication", "liaise with", "prepare documents"], "requirements": {"degrees": [], "majors": [], "languages": ["cantonese", "english", "mandarin"], "language_level": ["good command"], "hard_skills": ["3d software"], "soft_skills": ["communication skills", "technical skills", "committed", "diverse", "motivated", "controlled", "team player", "initiative", "presentation", "ideal"], "languages_combined": [{"language": "cantonese", "language_level": ["good command"]}, {"language": "english", "language_level": ["good command"]}, {"language": "mandarin", "language_level": ["good command"]}]}, "experience_required": {"duration": [], "field": []}}, {"job_id": "100003009020836", "location_code": "hk", "company": "Tchibo Merchandising Hong Kong LP", "job_title": "Pattern Maker / Technologist (Apparel) (Quality Assurance/ Management Department)", "description": "Responsibilities\n\nPerform pattern adjustment in pattern software (Accumark)\nTurn style pattern into block pattern\nCreate style pattern from block pattern if required\nManage e-pattern library (and hard pattern) and digitize approved pattern\nRegularly review pattern requirements with Senior Fit Engineers and improve block pattern and/or style pattern from vendor\nAssist Fit Engineers with any pattern improvement and adjustments\nVerify correct block usage and graded nest pattern of running projects with Asian vendor base\nClose working relationship with German headquarter patternmaker to develop block pattern library across Ladies wear, menswear and kids causal wear\n\nRequirements\n\nDiploma in Patternmaking, Garment Manufacturing, Garment Technology or similar\n5-7 years hands on experience with pattern making in 2D CAD software\nHighly skilled computer skills in 2D CAD Software (Gerber Accumark or similar)\n3D virtual development experience is a plus\nOpen minded, flexible and open for new technologies\nGood computer skills (MS Office, Outlook, PLM)\nGood command of English and Chinese is a must\n\nWe offer attractive remuneration package including 5-day week, double pay, discretionary bonus, medical & dental insurance, travel allowance, etc. Interested parties, please send your CV with expected salary and availability, and by quoting reference number (QMTX003) in the subject by clicking \"Apply Now\" . Candidates who are not contacted within 8 weeks should consider their application as unsuccessful.\n\n(The information provided will be used for selection purpose only.)\n\n\n%MCEPASTEBIN%", "employment_types": ["Full Time", "Permanent"], "selling_points": ["Perform pattern adjustment in pattern software", "5 -7 years\u2019 experience with pattern making", "European Buying Office, Flexible Working Hours"], "locations": ["Tsim Sha Tsui"], "categories": ["Design", "Industrial / Product", "Manufacturing", "Garment / Textile", "Product Development / Management"], "post_time": "2022-01-05T02:12:44Z", "salary": {"currency": null, "max": null, "min": null, "period": "monthly", "term": null}, "salary_visible": false, "title_keywords": [], "responsibilities": ["review", "software", "develop"], "requirements": {"degrees": ["diploma"], "majors": ["manufacturing"], "languages": ["english", "chinese"], "language_level": ["good command"], "hard_skills": ["plus", "cad", "computer skills", "outlook", "ms office"], "soft_skills": ["flexible", "hands on", "open minded"], "languages_combined": [{"language": "english", "language_level": ["good command"]}, {"language": "chinese", "language_level": ["good command"]}]}, "experience_required": {"duration": ["5-7 years"], "field": ["development"]}}, {"job_id": "100003009026989", "location_code": "hk", "company": "HK Research Institute of Textiles & Apparel Ltd", "job_title": "Project Manager (Ref. No.: HKRITA-PM)", "description": "[Work Location: Science Park, Shatin]\nThe appointee(s) will be required to\nperform project research design, write project proposals and conduct research works, including data acquisition and analysis, model development, consolidation of results, as well as preparation and presentation of research reports;\nlead the whole project and be responsible for achieving project deliverables;\nmanage R&D projects, including technical and financial aspects and other project administrative tasks, such as preparing project updates and reports;\nwork closely with R&D researchers and personnel; coordinate with local and overseas universities, research institutions and business partners, and handle enquiries in a professional manner; and\nperform any other duties as assigned.\nRequirements:\nA master\u2019s degree or above in any STEM subjects;\n5 or more years of research / relevant work experience;\nHighly-organized and capable of working under pressure with multi-task assignments;\nExcellent presentation and interpersonal skills; and\nFluent in both written and spoken English and Chinese, with a good command of Putonghua being an advantage.\nApplicants should state their current and expected salary in the application. Salary offered will be commensurate with qualifications and experience. Appointment will be offered on a contract basis, re-engagement thereafter is subject to mutual agreement.\nApplicants are invited to send detailed curriculum vitae in strict confidence to Human Resources Manager, HKRITA, R906-8, Shirley Chan Building, The Hong Kong Polytechnic University, Hung Hom, Kowloon. (E-mail via \"Apply Now\"). Recruitment will continue until the position is filled. HKRITA reserves the right to consider late applications and nominations, and to fill or not to fill the positions. Personal data provided by applicants will be used for recruitment and other employment-related purpose. Please mark \u201cPRIVATE & CONFIDENTIAL\u201d and quote the position applied for and its reference number on the envelope.", "employment_types": ["Full Time", "Contract"], "selling_points": [], "locations": ["Shatin Area"], "categories": ["Engineering", "Chemical", "Manufacturing", "Garment / Textile", "Sciences, Lab, R&D", "Research & Development (R&D)"], "post_time": "2022-01-07T19:19:30Z", "salary": {"currency": null, "max": null, "min": null, "period": "monthly", "term": null}, "salary_visible": false, "title_keywords": ["project manager"], "responsibilities": [], "requirements": {"degrees": [], "majors": [], "languages": [], "language_level": [], "hard_skills": [], "soft_skills": [], "languages_combined": []}, "experience_required": {"duration": [], "field": []}}, {"job_id": "100003009024881", "location_code": "hk", "company": "King-Choice Group Limited", "job_title": "Assistant Sales Manager (Trims)", "description": "Industry Field: Trims Accessories Trading\n\n- Be responsible and work hard\n- Contact with customers via e-mail and phone\n- Follow up the sample order\n- Work with colleagues as teamwork\n- Work out of office sometimes\n- Report constantly to directors for sales planning", "employment_types": ["Full Time", "Permanent"], "selling_points": ["Minimum 3 years of experience", "Competitive package", "5 Days Work"], "locations": ["Shatin Area"], "categories": ["Manufacturing", "Garment / Textile", "Merchandising & Purchasing", "Woven / Knit", "Others", "Trading"], "post_time": "2022-01-06T02:48:03Z", "salary": {"currency": "HKD", "max": 24999, "min": 20000, "period": "monthly", "term": null}, "salary_visible": true, "title_keywords": ["assistant sales manager"], "responsibilities": ["planning", "contact", "report"], "requirements": {"degrees": [], "majors": [], "languages": [], "language_level": [], "hard_skills": [], "soft_skills": ["teamwork", "responsible"], "languages_combined": []}, "experience_required": {"duration": [], "field": []}}]