[{"job_id": "100003009055062", "location_code": "hk", "company": "Man King Jewellery Company Limited", "job_title": "Sales Co-ordinator", "description": "Responsibilities:\n\n- Provide general support to the sales department\n- Prepare quotation, invoices and data entry\n- Handle customer inquiries and follow up orders\u00a0\n- Arrange shipment/delivery of goods\n- Attend local trade shows\n\nRequirements\n\n- Higher diploma or above\n- Minimum 1 year working experience\n- Fresh graduates are also welcome\n- High sense of responsibility\n- Detail-minded, well-organized and hard working\n- Knowledge of MS office software and Chinese typing\n- Good command of both written & spoken English & Chinese\u00a0\n\n\n\nFor qualified candidates, we offer:\n\n- 5 working days\n- Bank holidays\n- Year-end bonus\n- Medical insurance\u00a0\n\nInterested candidates please send CV/ resume with expected salary and state of availability by clicking 'Apply now'.\u00a0", "employment_types": ["Full Time"], "selling_points": [], "locations": ["Hung Hom"], "categories": ["Manufacturing", "Jewelry"], "post_time": "2022-01-18T01:07:50Z", "salary": {"currency": null, "max": null, "min": null, "period": "monthly", "term": null}, "salary_visible": false, "title_keywords": ["sales"], "responsibilities": ["follow up orders", "invoices", "customer inquiries", "data entry", "quotation", "general support"], "requirements": {"degrees": ["higher diploma or above"], "majors": [], "languages": ["english", "chinese"], "language_level": ["good command"], "hard_skills": ["typing", "ms office"], "soft_skills": ["detail-minded", "high sense of responsibility", "well-organized", "hard working"], "languages_combined": [{"language": "english", "language_level": ["good command"]}, {"language": "chinese", "language_level": ["good command"]}]}, "experience_required": {"duration": ["minimum 1 year"], "field": []}}, {"job_id": "100003009054292", "location_code": "hk", "company": "CHOW TAI FOOK JEWELLERY CO LTD", "job_title": "\u54c1\u8cea\u6aa2\u5b9a\u54e1", "description": "\u8077\u8cac\uff1a\n\n\u8655\u7406\u947d\u77f3\u539f\u6599\u7684\u6aa2\u6e2c\u7a0b\u5e8f\n\u64cd\u4f5c\u6aa2\u6e2c\u5100\u5668\u53ca\u9032\u884c\u65e5\u5e38\u7dad\u8b77\n\u5354\u52a9\u6578\u64da\u5206\u6790\u53ca\u8cc7\u6599\u8f38\u5165\n\u4fdd\u6301\u5be6\u9a57\u5ba4\u6574\u6f54\n\u5176\u4ed6\u5de5\u4f5c\u652f\u63f4\n\n\u8077\u4f4d\u8981\u6c42\uff1a\n\n\u4e2d\u5b78\u7a0b\u5ea6\n2 - 4\u5e74\u6587\u66f8\u8655\u7406\u7d93\u9a57\u53ca\u5177\u76f8\u95dc\u73e0\u5bf6\u8655\u7406\u7d93\u9a57\u8f03\u4f73\n\u61c2\u4e00\u822c\u96fb\u8166\u64cd\u4f5c\uff08 Word \u3001 Excel \uff09\uff1b\u61c2\u5009\u9821\uff0f\u901f\u6210\u8f38\u5165\u6cd5\n\u66fe\u4fee\u8b80\u73e0\u5bf6\u9996\u98fe\u9451\u8b49\u76f8\u95dc\u8ab2\u7a0b\u66f4\u4f73\n\u8aa0\u5be6\u3001\u7d30\u5fc3\u3001\u6e96\u78ba\u3001\u6709\u8cac\u4efb\u611f\n\n\u53ef\u4eab\u798f\u5229\ufe30\u00a0\n\n\u4e94\u5929\u5de5\u4f5c\n\u512a\u85aa\u3001\u54e1\u5de5\u81b3\u98df\uff0c\u91ab\u7642\u53ca\u7259\u79d1\u798f\u5229\uff0c\u4eba\u58fd\u4fdd\u96aa\n\u4eab\u5404\u985e\u5047\u671f\uff0c\u5305\u62ec\u5e78\u798f\u5bb6\u5ead\u5047\u3001\u81ea\u6211\u767c\u5c55\u5047\u3001\u8003\u8a66\u5047\u3001\u751f\u65e5\u5047\u3001\u7d50\u5a5a\u5047\u3001\u7fa9\u5de5\u5047\u7b49\u2026\u2026", "employment_types": ["Full Time"], "selling_points": ["\u4e94\u5929\u5de5\u4f5c", "\u947d\u77f3\u6aa2\u6e2c", "\u8cc7\u6599\u8f38\u5165"], "locations": ["Kwai Hing"], "categories": ["Manufacturing", "Jewelry", "Sciences, Lab, R&D", "Laboratory"], "post_time": "2022-01-17T09:04:45Z", "salary": {"currency": null, "max": null, "min": null, "period": "monthly", "term": null}, "salary_visible": false, "title_keywords": [], "responsibilities": [], "requirements": {"degrees": [], "majors": [], "languages": [], "language_level": [], "hard_skills": ["excel", "word"], "soft_skills": [], "languages_combined": []}, "experience_required": {"duration": [], "field": []}}, {"job_id": "100003009054307", "location_code": "hk", "company": "CHOW TAI FOOK JEWELLERY CO LTD \u5468\u5927\u798f\u73e0\u5bf6\u91d1\u884c\u6709\u9650\u516c\u53f8", "job_title": "\u5404\u7d1a\u71df\u696d\u54e1", "description": "\u5de5\u4f5c\u8077\u8cac\uff1a\n\n\u65bc\u5e97\u8216\u5167\u70ba\u9867\u5ba2\u63d0\u4f9b\u5c08\u696d\u53ca\u89aa\u5207\u7684\u670d\u52d9\uff0c\u4ee5\u9054\u81f3\u92b7\u552e\u76ee\u6a19\n\u5c08\u696d\u53ca\u6709\u79ae\u5730\u89e3\u7b54\u9867\u5ba2\u7684\u67e5\u8a62\n\u8207\u9867\u5ba2\u5efa\u7acb\u53ca\u7dad\u7e6b\u826f\u597d\u95dc\u4fc2\uff0c\u63a8\u5ee3\u54c1\u724c\u5f62\u8c61\n\u5354\u52a9\u5e97\u8216\u65e5\u5e38\u904b\u4f5c\n\n\u8077\u4f4d\u8981\u6c42\uff1a\n\n\u4e2d\u4e94\u7a0b\u5ea6\u6216\u4ee5\u4e0a\uff0c\u5177\u73e0\u5bf6\u96f6\u552e\u7d93\u9a57\u8005\u512a\u5148\n\u7a4d\u6975\u4e3b\u52d5\u3001\u5f85\u5ba2\u71b1\u8aa0\u6709\u79ae\n\u5177\u826f\u597d\u9867\u5ba2\u670d\u52d9\u53ca\u6e9d\u901a\u6280\u5de7\n\u80fd\u64cd\u5ee3\u6771\u8a71\u3001\u666e\u901a\u8a71\uff0c\u7565\u61c2\u82f1\u8a9e\u8f03\u4f73\n\n\u53ef\u4eab\u798f\u5229\uff1a\n\n\u00a0\u512a\u85aa\u3001\u54e1\u5de5\u81b3\u98df\uff0c\u91ab\u7642\u53ca\u7259\u79d1\u798f\u5229\uff0c\u4eba\u58fd\u4fdd\u96aa\n\u4eab\u5404\u985e\u5047\u671f\uff0c\u5305\u62ec\u5e78\u798f\u5bb6\u5ead\u5047\u3001\u81ea\u6211\u767c\u5c55\u5047\u3001\u8003\u8a66\u5047\u3001\u751f\u65e5\u5047\u3001\u7d50\u5a5a\u5047\u3001\u7fa9\u5de5\u5047\u7b49\u2026\u2026\n\n\n\n\u516c\u53f8\u5c07\u63d0\u4f9b\u5728\u8077\u57f9\u8a13\uff0c\u826f\u597d\u798f\u5229\u53ca\u524d\u9014\u3002\u00a0\n\n\n\u61c9\u5fb5\u8005\u53ef\u81f4\u96fb\u00a03720 8008\u00a0\u6216\u5c07\u5c65\u6b77\u3001\u8981\u6c42\u85aa\u91d1\uff0c\u5bc4\u00a0\u4e5d\u9f8d\u65fa\u89d2\u5f4c\u6566\u9053580A-580F\u865f\u5468\u5927\u798f\u5546\u696d\u4e2d\u5fc322\u6a13\u00a0\u6216 \u6309\u00a0\"Apply Now\"\n\n\n\u6240\u6709\u6536\u96c6\u4e4b\u8cc7\u6599\u53ea\u7528\u4f5c\u62db\u8058\u7528\u9014", "employment_types": ["Full Time", "Permanent"], "selling_points": ["\u4e2d\u4e94\u7a0b\u5ea6\u6216\u4ee5\u4e0a\uff0c\u5177\u73e0\u5bf6\u96f6\u552e\u7d93\u9a57\u8005\u512a\u5148", "\u7a4d\u6975\u4e3b\u52d5\u3001\u5f85\u5ba2\u71b1\u8aa0\u6709\u79ae", "\u5177\u826f\u597d\u9867\u5ba2\u670d\u52d9\u53ca\u6e9d\u901a\u6280\u5de7"], "locations": ["Not Specified"], "categories": ["Sales, CS & Business Devpt", "Customer Service - Supervisor / Officer", "Manufacturing", "Jewelry", "Retail Sales"], "post_time": "2022-01-17T09:06:12Z", "salary": {"currency": null, "max": null, "min": null, "period": "monthly", "term": null}, "salary_visible": false, "title_keywords": [], "responsibilities": [], "requirements": {"degrees": [], "majors": [], "languages": [], "language_level": [], "hard_skills": [], "soft_skills": [], "languages_combined": []}, "experience_required": {"duration": [], "field": []}}, {"job_id": "100003009048298", "location_code": "hk", "company": "GIA Hong Kong Laboratory Limited", "job_title": "Diamond Grader Associate (Excellent career prospect)", "description": "Responsibilities:\n\nResponsible for gemstone inspection, authentication, record, conduct instrument maintenance and calibration and other daily activities in the gemological laboratory\nVerify the authenticity and other attributes of the gemstone inspected, preparation of reports, certificates and other related documentations, assure the quality and accuracy of the results\nAssist to verify and audit testing data and information, signing reports/certificates\nDevelop relevant documentation and inspection protocols\nKeep update of the latest gemological information within the industry, provide training and instructions to junior and supporting staff\nHandling where necessary in special projects as assigned\n\nRequirements:\n\nUniversity degree or above in Geology, Chemistry, Materials Sciences or related areas is preferred\nShould have gemstone qualification certificate such as GIA GG and FGA\nCandidate with a HKAS Approved Signatory is preferred\nFamiliar with HOKLAS accreditation and ISO17025 quality system\nExperienced with analytical equipment such as FTIR, Micro-Raman or ICP-MS preferred\nAbility to multi-task and deal with a varied workload, able to work well in a team environment or independently\nProficient in both English and Chinese for communication & writing\nFresh graduates will be considered\n\nWe offer 5-days-work week with competitive remuneration packages to the right candidate.\u00a0 Interested parties please send your CV with EXPECTED SALARY through the below application procedure.\n\n(Personal data will be used by Chow Sang Sang (CSS) for recruitment only.\u00a0 CSS may refer suitable applications to other vacancies within CSS and its associated companies.\u00a0 We will retain unsuccessful applications for a maximum period of 24 months.)", "employment_types": ["Full Time", "Permanent"], "selling_points": ["6-Month Paid Training Period", "5-Day Work Week & Double Pay & Performance Bonus", "Excellent Career Prospect"], "locations": ["Kowloon Bay"], "categories": ["Manufacturing", "Jewelry", "Sciences, Lab, R&D", "Laboratory", "Quality Assurance, Control & Testing / ISO"], "post_time": "2022-01-15T03:49:56Z", "salary": {"currency": null, "max": null, "min": null, "period": "monthly", "term": null}, "salary_visible": false, "title_keywords": ["associate"], "responsibilities": ["provide training", "maintenance", "data", "quality", "audit", "inspection", "testing", "develop", "reports", "documentation"], "requirements": {"degrees": ["certificate", "degree or above"], "majors": ["chemistry"], "languages": ["english", "chinese"], "language_level": ["proficient"], "hard_skills": [], "soft_skills": ["communication", "independently", "multi-task"], "languages_combined": [{"language": "english", "language_level": ["proficient"]}, {"language": "chinese", "language_level": ["proficient"]}]}, "experience_required": {"duration": [], "field": []}}, {"job_id": "100003009046129", "location_code": "hk", "company": "Goldage Jewellery Limited", "job_title": "Sales & Marketing assistant / Sales Administrator", "description": "2022 March Group Diamond Grader Hiring\n\nInterested to join Jewelry Industry and be a professional Diamond Grader? Due to our aggressive expansion, we are hiring a large group of Diamond Graders to meet our high production requirements.\n\nCome build a unique career as a Diamond Grader Associate in GIA Hong Kong Laboratory. You will work with diamonds, microscopes and computers in a laboratory production environment that emphasizes detail, quality and precision.\n\nWe offer an intensive 6 month paid training period that provides hands-on individualized training incorporating GIA Laboratory policies, procedures, and established guidelines in the documentation of pertinent data for the GIA Laboratory Diamond Grading Report.\n\nRESPONSIBILITIES\n\nEvaluate and grade loose diamonds. Identify, documents and plot characteristics, treatments and other features of a diamond.\nWork in a team setting with other graders of various skill levels.\nPerformed detailed evaluations using tools such as a microscope, a loupe, tweezers and a computer.\n\n\u00a0QUALIFICATIONS/REQUIREMENTS\n\nDiploma or above required with fluent English.\nNo relevant education or working experience required.\nAbility to work with microscopes.\u00a0\nDetail-minded with good concentration skills.\u00a0\nEffective communication and good interpersonal skills is a must.\u00a0\nAbility to get along with a diverse group of individuals in Hong Kong and other international locations.\u00a0\nProven ability to accept and learn from constructive criticism.\u00a0\nWell organized, responsible, mature & ability to work independently.\u00a0\n\n\u201cWe are an equal opportunity employer and welcome applications from all qualified candidates.\u00a0 Personal data provided by job applicants will be used strictly in accordance with our personal data policy. The information will only be used for appointment to the Company and other company-related purposes.\u201d\n\nContact & Company Information\n\nPlease submit resumes via Apply Now. All resumes must include your past salary history and current salary requirements.\u00a0\n\nWe encourage you to visit our corporate website at http://www.gia.edu/ to learn more information about GIA.", "employment_types": ["Full Time"], "selling_points": ["Jewellery", "Performance Bonus, Staff discount", "Luxury managment opportunity"], "locations": ["Hung Hom"], "categories": ["Manufacturing", "Jewelry", "General / Production Workers", "Marketing / Public Relations", "Marketing - Brand / Product Management"], "post_time": "2022-01-13T09:41:57Z", "salary": {"currency": null, "max": null, "min": null, "period": "monthly", "term": null}, "salary_visible": false, "title_keywords": ["marketing assistant", "sales administrator", "sales"], "responsibilities": ["evaluate"], "requirements": {"degrees": ["diploma or above"], "majors": [], "languages": ["english"], "language_level": ["fluent"], "hard_skills": ["no"], "soft_skills": ["detail-minded", "work independently", "responsible", "well organized", "mature", "communication", "diverse", "interpersonal skills", "constructive"], "languages_combined": [{"language": "english", "language_level": ["fluent"]}]}, "experience_required": {"duration": [], "field": ["education"]}}, {"job_id": "100003009047842", "location_code": "hk", "company": "Chow Sang Sang Holdings International Limited", "job_title": "Assistant Gemologist", "description": "\n\n\n1. Responsible for customer enquiries, order & quotations\n\n2. Follow up for order processing & communicate with vendors for production line\n\n3. Assist in preparation and organizing of Jewellery Show / Promotion material\n\n4. Handle inventory and products information\n\n5. Ad-Hoc takes & Outgoing work is required\n\nRequirement:\n\n1. Form 7 or DSE grad.\n\n2. Min. 1 year clerical work experience &\u00a0Knowledge in MS office is must\n\n3. Experience in in Jewellery industry\u00a0& Photoshop are\u00a0advantage\n\n4. Detail-mind oriented, self-motivated, well organization\n\n\n\n5. Good in spoken English, Cantonese and Mandarin\n\n\n\nWe offer attritive remuneration package include performance bonus, bank holidays, purchasing discount for staff, alternative off on Saturday work.\n\nInterested parties, please send full resume with current and expected salary to us\u00a0", "employment_types": ["Full Time", "Permanent"], "selling_points": ["Responsible for gemstone inspection", "Verify the authenticity of the gemstone inspected", "Fresh graduates will be considered"], "locations": ["Cheung Sha Wan"], "categories": ["Sciences, Lab, R&D", "Chemical", "Manufacturing", "Jewelry", "Laboratory"], "post_time": "2022-01-14T09:17:17Z", "salary": {"currency": null, "max": null, "min": null, "period": "monthly", "term": null}, "salary_visible": false, "title_keywords": ["assistant"], "responsibilities": ["ad-hoc", "communicate with", "customer enquiries", "inventory", "order processing"], "requirements": {"degrees": ["dse"], "majors": [], "languages": ["cantonese", "english", "mandarin"], "language_level": ["good"], "hard_skills": ["photoshop", "order processing", "ms office"], "soft_skills": ["outgoing", "self-motivated", "responsible"], "languages_combined": [{"language": "cantonese", "language_level": ["good"]}, {"language": "english", "language_level": ["good"]}, {"language": "mandarin", "language_level": ["good"]}]}, "experience_required": {"duration": ["1 year"], "field": ["clerical"]}}, {"job_id": "100003009042776", "location_code": "hk", "company": "Camex Jewellery Limited", "job_title": "Sales Coordinator", "description": "Responsibilities:\n\nPerform basic clerical duties following detailed instructions and procedures\nGenerate sales reports and support sales department on assigned daily administrative duties\nAssist to Sales Department\nArrange shipment to the customer\nProvide good customer service with internal and external parties\nFollow up orders & deal with overseas customers\nAttend local & oversea jewellery trade fairs\nHandle other ad hoc tasks as assigned;\n\nRequirement:\n\nF.7 or above\nWith min. 2 years' relevant experience (preferably in Jewellery industry/Sales & Marketing)\nExperience in handling shipping documents is an advantage\nFriendly personality, proactive, detail minded,willing to learn and responsible\nHands-on PC knowledge (MS Word, Excel)\nAble to communicate in Cantonese, Mandarin and English\nEager to learn, patient & able to work under pressure\nImmediately available preferred\n\nINTERESTED PARTIES, PLEASE SEND YOUR FULL C.V. WITH CURRENT AND EXPECTED SALARY BY CLICKING \"APPLY NOW\". ALL INFORMATION RECEIVED WILL BE KEPT IN STRICT CONFIDENTIAL AND RECRUITMENT PURPOSE ONLY.", "employment_types": ["Full Time", "Permanent"], "selling_points": ["Perform basic clerical duties", "Attend local & oversea jewellery trade fairs", "2 years' relevant experience"], "locations": ["Tsim Sha Tsui"], "categories": ["Sales, CS & Business Devpt", "Customer Service - Supervisor / Officer", "Manufacturing", "Jewelry", "Transportation & Logistics", "Shipping"], "post_time": "2022-01-12T08:47:57Z", "salary": {"currency": null, "max": null, "min": null, "period": "monthly", "term": null}, "salary_visible": false, "title_keywords": ["sales coordinator"], "responsibilities": ["follow up orders", "sales reports", "internal and external parties", "procedures", "ad hoc tasks", "customer service", "administrative duties"], "requirements": {"degrees": [], "majors": [], "languages": ["cantonese", "english", "mandarin"], "language_level": [], "hard_skills": ["excel", "pc knowledge", "ms word"], "soft_skills": ["responsible", "willing to learn", "eager to learn", "hands-on", "friendly", "patient", "proactive", "work under pressure"], "languages_combined": [{"language": "cantonese", "language_level": []}, {"language": "english", "language_level": []}, {"language": "mandarin", "language_level": []}]}, "experience_required": {"duration": ["2 years"], "field": ["marketing", "relevant experience"]}}, {"job_id": "100003009044380", "location_code": "hk", "company": "International Gemological Institute (HK) Limited", "job_title": "Graduate Gemologist / Graduate Coloured Stone Grader", "description": "Job Highlights\n\nExciting vacancy in a truly global and dynamic company, with potential for growth to managerial level position in coloured stones department\n5-day working week\nMedical insurance\nOvertime and double pay\n\nJob Description\n\nInternational Gemological Institute\u00a0(IGI)\u00a0is the largest organisation of its kind, operating 18 laboratory locations around the world, grading finished jewellery, natural diamonds, lab-grown diamonds and gemstones - and 14 schools of gemology, graduating thousands of new jewellery professionals each year.\u00a0\n\nIGI is the only worldwide gemological institute focusing on consumer protection by evaluating and grading finished jewellery creations, as well as loose diamonds and coloured gemstones.\u00a0\n\nIGI Worldwide\u2019s Hong Kong laboratory, which was established in 2004, is looking for an experienced\u00a0COLOURED STONES GRADER\u00a0to join its dynamic team of gemological professionals.\n\nThe ideal candidate will have:\n\nA minimum of 5 years experience in a\u00a0senior\u00a0coloured stones grading role in reputed international gemological laboratory\nGG \u2013 FGA \u2013 DGA qualifications (or equivalent)\nGood command of / experience in gemstone origin determination based on microscopic analysis\nA keen interest in gemology and its related fields\nGood command of spoken and written English and Chinese\n\nPlease apply with your resume and salary expectations, as well as for interview appointments, to\u00a0Ms May Mak, by email.", "employment_types": ["Full Time", "Permanent"], "selling_points": [], "locations": ["Hung Hom"], "categories": ["Manufacturing", "Jewelry", "Sciences, Lab, R&D", "Laboratory"], "post_time": "2022-01-13T03:55:01Z", "salary": {"currency": null, "max": null, "min": null, "period": "monthly", "term": null}, "salary_visible": false, "title_keywords": [], "responsibilities": ["analysis", "insurance"], "requirements": {"degrees": [], "majors": [], "languages": ["english", "chinese"], "language_level": ["good command"], "hard_skills": ["analysis", "dynamic"], "soft_skills": ["keen", "dynamic", "organisation", "ideal"], "languages_combined": [{"language": "english", "language_level": ["good command"]}, {"language": "chinese", "language_level": ["good command"]}]}, "experience_required": {"duration": ["minimum of 5 years"], "field": ["laboratory"]}}, {"job_id": "100003009046891", "location_code": "hk", "company": "ACH & Co. HK Limited", "job_title": "Sales Co-ordinator / Sales Administrator", "description": "** Candidate with better experience will consider a senior post of Sales Administration Officer **\n\nResponsibilities :\n\nAssist the sales teammates in preparing all sales-related documents and keep central database of all materials\nEnsure the adequacy of sales-related equipment or materials\nLiaison\u00a0with factory to ensure production and delivery\u00a0schedule\nManage showroom and samples\nRespond to complaints from customers and give after-sales support when requested\nAssist in the preparation and organizing of promotional material or events\nProvide additional support to colleagues when needed\n\nRequirements:\n\nProven experience in sales; at least 2-3 years experience as a sales\u00a0administration position (Jewelry or Garment industry will be an advantage)\nFresh graduation will also be considered\nGood computer skills (MS Office)\nProficiency in English and Putonghua\nWell-organized and responsible with an aptitude in problem-solving\nExcellent verbal and written communication skills\nDetail mind and patient for routine\u00a0works\nA team player with high level of dedication\nDiploma\u00a0in sales or marketing will be\u00a0an asset\nImmediate available preferrable\n\nWe offer 5 days work, friendly culture and\u00a0excellent career prospects and competitive remuneration to the right candidate.", "employment_types": ["Full Time", "Permanent"], "selling_points": [], "locations": ["Hung Hom"], "categories": ["Sales, CS & Business Devpt", "Customer Service - Supervisor / Officer", "Manufacturing", "Jewelry", "Marketing / Public Relations", "Marketing - General / Support"], "post_time": "2022-01-14T01:38:07Z", "salary": {"currency": null, "max": null, "min": null, "period": "monthly", "term": null}, "salary_visible": false, "title_keywords": ["sales administrator", "sales"], "responsibilities": ["related documents", "delivery schedule", "assist the sales", "database"], "requirements": {"degrees": ["diploma"], "majors": ["marketing"], "languages": ["putonghua", "english"], "language_level": ["proficiency"], "hard_skills": ["garment industry", "problem-solving", "computer skills", "ms office"], "soft_skills": ["communication skills", "responsible", "problem-solving", "well-organized", "patient", "team player"], "languages_combined": [{"language": "putonghua", "language_level": ["proficiency"]}, {"language": "english", "language_level": ["proficiency"]}]}, "experience_required": {"duration": ["at least 2-3 years"], "field": ["garment", "sales administration"]}}, {"job_id": "100003009046446", "location_code": "hk", "company": "CHOW TAI FOOK JEWELLERY CO LTD", "job_title": "Jewellery Designer / Senior Jewellery Designer", "description": "What You Do\n\nDevelop design proposal for creative projects, collaborating with project manager and different business units\nConduct market research, analyze sales data to develop concept and create jewellery designs\n\u00a0Create presentation to visualize creative idea\nActively assist in prototyping process ensure high quality and completeness\nCommunicate closely with internal teams for completion of tasks within lead time\nHandle ad-hoc project as assigned by supervisor\n\nWho Will Thrive\n\n\u00a0Diploma\u00a0or above\u00a0in Design or related disciplines\nMin. 3 years\u2019experience in jewellery design (Candidates possess 5+ years of relevant experience can apply for senior jewellery designer)\nGood at hand sketching, mastery of Photoshop, Illustrator and Powerpoint\nKnowledge in jewellery production\nPassionate in art and design with global vision, aesthetic and creative sense\nIndependent, detail oriented, self-motivated and responsible\nStrong communication and presentation skill\nGood command of written and spoken English and Chinese\n\nBenefits:\n\n5-day work\nCompetitive salary, staff meal, medical and dental insurance, life insurance\nVarious types of leave, e.g. Family-friendly leave, self-development Leave, examination leave, marriage leave, birthday leave, volunteer service leave, etc\n\nWe offer excellent career opportunities, attractive remuneration package & benefits to the right candidate. Interested parties please click \"Apply Now\" below or apply with full resume with portfolio by stating latest and expected salaries to 22/F, Chow Tai Fook Centre, 580A-580F Nathan Road, Mongkok, Kowloon, Hong Kong.\n\nAll information collected for recruitment purpose only.", "employment_types": ["Full Time", "Contract"], "selling_points": ["Concept development, jewellery design", "Global vision of design, aesthetic, creative sense", "\u2022\tHand sketching, Illustrator, Photoshop"], "locations": ["Kwai Hing"], "categories": ["Design", "Others", "Manufacturing", "Jewelry"], "post_time": "2022-01-13T11:14:34Z", "salary": {"currency": null, "max": null, "min": null, "period": "monthly", "term": null}, "salary_visible": false, "title_keywords": ["designer"], "responsibilities": ["ad-hoc", "data", "conduct market research", "quality", "teams", "design", "develop", "communication"], "requirements": {"degrees": ["diploma or above"], "majors": ["related disciplines", "design"], "languages": ["english", "chinese"], "language_level": ["good command"], "hard_skills": ["presentation skill", "illustrator", "powerpoint", "photoshop"], "soft_skills": ["passionate", "presentation skill", "self-motivated", "independent", "responsible", "detail oriented", "communication", "creative", "presentation"], "languages_combined": [{"language": "english", "language_level": ["good command"]}, {"language": "chinese", "language_level": ["good command"]}]}, "experience_required": {"duration": ["5+ years"], "field": ["relevant experience", "designer", "design"]}}, {"job_id": "100003009042045", "location_code": "hk", "company": "Fossil (East) Ltd", "job_title": "Senior Product Executive - Watch", "description": "What\u2019s the role about?\nDrive the development process and product plans from the design concept to sample\u00a0approval.\nMonitor the works with vendors to ensure daily\u00a0operations run smoothly\nReview and provide recommendations for product improvement and valued\nengineering\nManage and contribute to design proposals, sourcing and pricing\nCollaborate with Supply Chain Management Team and Quality Assurance Team to\nensure production and quality standard.\u00a0Monitor product testing (including wear test)\nto meet product safety standard\nCommunicate effectively with key stakeholders locally and globally\nResponsible for accuracy of data setup attributes into the component materials\ninformation system\nWhat we are looking for:\n\nDiploma or above or any equivalent\nMinimum\u00a05 years of relevant experience\nFamiliar with product safety specification\nWell-organized, detail-oriented, have analytical mind and high sense of responsibility\nAble to work flexible, multi-task and under pressure\nKnowledge in both Watch and Jewelry fields is an advantage\nFamiliar with PLM system is a definite advantage\nGood command in both spoken and written English\n\nTogether, we make great things happen. Apply now and be part of our tomorrow.\n\nInterested parties please send us your full resume with contact details, preferably with your current and expected salary.\n\nFossil Group is an Equal Opportunity employer. All qualified applicants will receive consideration of employment without regard to race, disability, gender, religion, family status, marital status, national origin, sexual orientation, veteran status, gender identity or \u00a0expression or any other basis protected by local, state, or national law. Only short-listed candidates will be notified. All information received will be kept in strict confidence and only for employment-related purpose.", "employment_types": ["Full Time"], "selling_points": ["Drive the development process and product plans", "Monitor the works with vendors", "Manage design proposals, sourcing and pricing"], "locations": ["Tsuen Wan Area"], "categories": ["Manufacturing", "Jewelry", "Product Development / Management", "Others"], "post_time": "2022-01-12T05:40:41Z", "salary": {"currency": null, "max": null, "min": null, "period": "monthly", "term": null}, "salary_visible": false, "title_keywords": ["senior product executive"], "responsibilities": ["collaborate with", "management team", "data", "design concept", "review", "monitor", "quality", "design", "testing", "daily operations", "provide recommendations", "plans", "setup"], "requirements": {"degrees": ["diploma or above"], "majors": [], "languages": ["english"], "language_level": ["good command"], "hard_skills": ["make", "information system"], "soft_skills": ["flexible", "multi-task", "under pressure", "responsible", "high sense of responsibility", "well-organized", "detail-oriented", "analytical mind"], "languages_combined": [{"language": "english", "language_level": ["good command"]}]}, "experience_required": {"duration": ["minimum 5 years"], "field": ["relevant experience"]}}, {"job_id": "100003009040445", "location_code": "hk", "company": "RecruitFirst Limited", "job_title": "\u3010\u570b\u969b\u77e5\u540d\u76f8\u6a5f\u54c1\u724c\u552e\u8ca8\u54e1 Sales Executive\u3011(\u2b5023K+\u2b50CWB/IFC\u2b50\u9996\u4e09\u500b\u6708\u5305\u85aa\u2b50\u9418\u9336\u73e0\u5bf6\u96f6\u552e\u696d\u512a\u5148)", "description": "\u6211\u5011\u7684\u5ba2\u6236\u662f\u5fb7\u570b\u8457\u540d\u751f\u7522\u76f8\u6a5f\u4e4b\u516c\u53f8\uff0c\u73fe\u6b63\u5c0b\u627e\u4eba\u6750\u52a0\u5165\uff0c\u6210\u70ba\u7576\u4e2d\u4e00\u5206\u5b50\u3002\n\n\u4e3b\u8981\u8077\u8cac:\n\n\u4ecb\u7d39\u5404\u7a2e\u9ad8\u7d1a\u76f8\u6a5f\u4e88\u5ba2\u4eba\uff0c\u63d0\u4f9b\u5c08\u696d\u610f\u898b\n\u4ecb\u7d39\u5ba2\u4eba\u651d\u5f71\u6280\u5de7\uff0c\u9054\u81f4\u5e97\u92ea\u92b7\u552e\u76ee\u6a19\n\u5efa\u7acb\u53ca\u7dad\u6301\u826f\u597d\u5ba2\u6236\u95dc\u4fc2\uff0c\u63d0\u4f9b\u5c08\u696d\u5ba2\u6236\u670d\u52d9\n\u7ba1\u7406\u65e5\u5e38\u5e97\u92ea\u904b\u71df\n\n\u8981\u6c42:\n\n\u4e00\u5e74\u76f8\u6a5f\uff0c\u9418\u9336\u6216\u73e0\u5bf6\u96f6\u552e\u7d93\u9a57\u8005\u512a\u5148\n\u5c0d\u76f8\u6a5f\u7522\u54c1\u6709\u8208\u8da3\u53ca\u57fa\u672c\u8a8d\u8b58\n\u4e3b\u52d5\u7a4d\u6975", "employment_types": ["Full Time", "Permanent"], "selling_points": [], "locations": ["Central"], "categories": ["Sales, CS & Business Devpt", "Customer Service - Supervisor / Officer", "Manufacturing", "Jewelry", "Retail Sales"], "post_time": "2022-01-12T02:36:02Z", "salary": {"currency": null, "max": null, "min": null, "period": "monthly", "term": null}, "salary_visible": false, "title_keywords": ["sales"], "responsibilities": [], "requirements": {"degrees": [], "majors": [], "languages": [], "language_level": [], "hard_skills": [], "soft_skills": [], "languages_combined": []}, "experience_required": {"duration": [], "field": []}}, {"job_id": "100003009039479", "location_code": "hk", "company": "Just Gold Company Ltd", "job_title": "Jewellery Designer", "description": "Job Responsibilities:\n\nResponsible for jewellery and product designs range from concept development, designs from conception to delivery, follow-up on product development, etc;\nConduct market research and analysis from time to time;\nParticipate ad-hoc assignments as assigned.\u00a0\n\nJob Requirements:\n\nDiploma or above in Jewellery Design;\nMinimum 3 years solid\u00a0experience in luxury fine jewellery and 24K gold product\u00a0industries;\nStrong sense\u00a0of market trend and\u00a0knowledge in jewellery/ornament production;\nExtensive knowledge of diamonds and colored gems;\nPassion for innovative design;\nCreative, meticulous and a good team player;\nExcellent presentation and communication skills;\u00a0\nProficiency in illustrator, Photoshop applications and 3D software;\nAble to meet tight deadline;\nFluent in spoken & written English, Chinese and Mandarin;\nCandidates with less experience will be considered as Junior Jewellery Designer.", "employment_types": ["Full Time"], "selling_points": [], "locations": ["Tsim Sha Tsui"], "categories": ["Design", "Industrial / Product", "Manufacturing", "Jewelry"], "post_time": "2022-01-11T09:54:16Z", "salary": {"currency": null, "max": null, "min": null, "period": "monthly", "term": null}, "salary_visible": false, "title_keywords": ["designer"], "responsibilities": ["ad-hoc assignments", "conduct market research", "analysis"], "requirements": {"degrees": ["diploma or above"], "majors": ["design"], "languages": ["english", "chinese", "mandarin"], "language_level": ["fluent"], "hard_skills": ["3d software", "illustrator", "photoshop"], "soft_skills": ["meticulous", "good team player", "communication skills", "creative", "passion for", "meet tight deadline", "innovative", "extensive", "presentation"], "languages_combined": [{"language": "english", "language_level": ["fluent"]}, {"language": "chinese", "language_level": ["fluent"]}, {"language": "mandarin", "language_level": ["fluent"]}]}, "experience_required": {"duration": ["minimum 3 years"], "field": ["designer"]}}, {"job_id": "100003009035121", "location_code": "hk", "company": "Nelson Jewellery Arts Co Ltd", "job_title": "Assistant Costing Officer (Jewelry)", "description": "Task & responsibilities\n\nCalculate prices and tagging for products\nPrepare quotations and develop standard costing sheets\nDevelop costing/ pricing database\nExecute costing/ pricing strategies and policies\nAssist the Department head in developing a support team in PRC\nWork with logistic department for shipment arrangement\u00a0\nRequirements\nDiploma or above in any discipline (graduated in Engineering, Mathematics or Statistics are highly preferred)\n1-3 years of working experience (prefer in jewellery field)\nKnowledge in Dynamics AX system is definite an advantage but not essential\nGood written English and Chinese skills with some Mandarin a plus\nNumeric sensitive, detail-minded, logical, self-motivated and willing to work under pressure and tight schedule\nA team player with good integrity\noccasionally travel to Mainland China\nImmediately available preferred", "employment_types": ["Full Time", "Permanent"], "selling_points": [], "locations": ["Hung Hom"], "categories": ["Manufacturing", "Jewelry"], "post_time": "2022-01-10T06:03:36Z", "salary": {"currency": null, "max": null, "min": null, "period": "monthly", "term": null}, "salary_visible": false, "title_keywords": ["officer", "assistant"], "responsibilities": ["shipment arrangement", "policies", "developing", "develop", "database"], "requirements": {"degrees": ["diploma or above"], "majors": ["mathematics", "statistics", "engineering"], "languages": ["english", "chinese", "mandarin"], "language_level": ["good"], "hard_skills": ["plus"], "soft_skills": ["detail-minded", "self-motivated", "integrity", "sensitive", "team player", "work under pressure"], "languages_combined": [{"language": "english", "language_level": ["good"]}, {"language": "chinese", "language_level": ["good"]}, {"language": "mandarin", "language_level": ["good"]}]}, "experience_required": {"duration": ["1-3 years"], "field": []}}, {"job_id": "100003009043083", "location_code": "hk", "company": "William E Connor & Associates Ltd", "job_title": "Product Development Manager - Jewelries & Accessories", "description": "Job Accountabilities\n\nResponsible for execution of jewelry product development briefs and assist in formulating product strategies.\nCommunicate with clients on their upcoming needs & wants\nCoordinate with related parties to ensure new products from design stage to launch are effectively monitored.\nCollaborate with design team to develop seasonal concepts for jewelry\nStrong in research and development to assist in identifying a continuous stream of commercially valuable new products.\nResponsible for the evaluation of product sales and generate necessary analytical reports accordingly.\nPrepare client portfolios for upcoming trends design\nReview sales performance and formulate incentive programs in time to enhance it.\nConduct in-depth research on similar products among competitors in order to implement effective sales strategies for achievement of sales target.\nOther duties as assigned.\n\nJob Requirements\nUniversity degree or equivalent, in jewelry design & supply chain\nMinimum 8 years relevant working experience of which at least 4 years at managerial level, experience in Merchandising especially in Jewelry & Accessories\nPrevious experience in handling clients & meeting their requests is a must\nSound knowledge and experience in cost calculation, quality control, and jewelry production process, and be able to balance design with commercial constraints.\nExperience working directly with factories in China with knowledge of vendor base\nHave a good product eye and jewelry and accessories knowledge; familiar with US market will be a huge plus\nFamiliar with research resources & channels\nFluency in both written and spoken Cantonese, English and Mandarin.\nExcellent presentation skills\nResponsible, detail-minded, flexible, good team player while be able to work independently, able to cope with deadline.\nImmediate available is highly preferable.\nConnor provides excellent career opportunities & attractive fringe benefits to the right candidate. Further information about Connor and our career opportunities can be viewed on our website\u00a0 www.weconnor.com.\u00a0 If you are interested in joining our team, please send your resume with current and expected remuneration packages to us\u00a0by MS Word attachment.\n\n\nConnor is an equal opportunities employer. Personal data provided by applicants will be used strictly for recruitment purposes only. Only short-listed candidates will be notified. Applicants who are not invited for an interview within 8 weeks may consider their applications filed for future reference.", "employment_types": ["Full Time", "Permanent"], "selling_points": ["Attractive package with good career development", "Familiar with merchandising in jewelry products", "Fashion & Jewelry design, product development"], "locations": ["Kowloon Bay"], "categories": ["Manufacturing", "Jewelry", "Product Development / Management", "Merchandising & Purchasing", "Procurement / Purchasing / Sourcing"], "post_time": "2022-01-12T09:45:30Z", "salary": {"currency": null, "max": null, "min": null, "period": "monthly", "term": null}, "salary_visible": false, "title_keywords": ["product development manager"], "responsibilities": ["communicate with", "collaborate with", "cost", "production process", "other duties", "sales performance", "sales target", "review", "coordinate with", "merchandising", "design", "develop", "reports", "quality control", "evaluation"], "requirements": {"degrees": ["university degree"], "majors": ["design"], "languages": ["cantonese", "english", "mandarin"], "language_level": ["fluency"], "hard_skills": ["plus", "vendor"], "soft_skills": ["detail-minded", "flexible", "good team player", "work independently", "responsible", "presentation skills"], "languages_combined": [{"language": "cantonese", "language_level": ["fluency"]}, {"language": "english", "language_level": ["fluency"]}, {"language": "mandarin", "language_level": ["fluency"]}]}, "experience_required": {"duration": ["minimum 8 years", "at least 4 years"], "field": ["managerial", "merchandising", "relevant working experience", "design", "commercial", "quality control"]}}, {"job_id": "100003009047697", "location_code": "hk", "company": "Luk Fook Holdings Company Limited", "job_title": "Senior Marketing Manager", "description": "Responsibilities:\n\n\u00a0Report to the Deputy Marketing Director\n\u00a0Build marketing programs to support specific marketing objectives across different\u00a0 \u00a0channels and segments in support of overall strategic marketing plan\nSet and monitor annual marketing strategies in correlating with budgets for brand building, product launching and marketing positioning\nMotivate an efficient and effective team work of the marketing department\n\nRequirements:\n\n\nBachelor Degree with major in Marketing , Communications or related disciplines\nMinimum 10 years related experience in retail industry, with track records in jewellery industry an advantage\nWith outstanding communication, leadership and project management skills\nStrong problem-solving ability\nGood command of spoken and written English, Chinese and Mandarin\nWorking exposure in China and experience on digital marketing are a definite must\nTravel to China is required\nWork in Shek Mun area\n\nInterested parties please send full resume with expected salary to\u00a0Human Resources Manager, Luk Fook Holdings Co Ltd., Floor 25, Metropole Square, No.2 On Yiu Street, Shek Mun, Shatin, N.T., Hong Kong\u00a0or\u00a0(click here)\u00a0to submit your application.\n\nAll personal data are handled in accordance with our personal data privacy policies.\u00a0 A copy of our statement on personal data collection is available upon request.\n\n\n\n\n", "employment_types": ["Full Time", "Permanent"], "selling_points": ["Experience on Emarketing is a definite must", "Working exposure in China", "Travel to China is required"], "locations": ["Shatin Area"], "categories": ["Manufacturing", "Jewelry", "Marketing / Public Relations", "Management", "E-commerce", "Marketing - Brand / Product Management"], "post_time": "2022-01-14T03:46:25Z", "salary": {"currency": null, "max": null, "min": null, "period": "monthly", "term": null}, "salary_visible": false, "title_keywords": ["senior marketing manager"], "responsibilities": ["budgets", "marketing strategies", "monitor", "marketing plan", "report"], "requirements": {"degrees": ["degree", "bachelor"], "majors": ["related disciplines", "marketing", "communications"], "languages": ["english", "chinese", "mandarin"], "language_level": ["good command"], "hard_skills": ["project management", "problem-solving"], "soft_skills": ["communication", "project management skills", "problem-solving", "leadership"], "languages_combined": [{"language": "english", "language_level": ["good command"]}, {"language": "chinese", "language_level": ["good command"]}, {"language": "mandarin", "language_level": ["good command"]}]}, "experience_required": {"duration": ["minimum 10 years"], "field": ["related", "retail industry", "digital marketing"]}}, {"job_id": "100003009032081", "location_code": "hk", "company": "\u745f\u7433\u947d\u77f3\u6709\u9650\u516c\u53f8", "job_title": "Quality Control Manager", "description": "Responsibilities\n- Grading, Sorting and Quality Assurance of Diamonds (Rough, Polished, Coloured, Lab Grown, etc)\n- Devise procedures to inspect and report quality issues\n- Monitor all operations that affect quality\n- Supervise and guide staffs\n- Assure the reliability and consistency of products Appraise customers\u2019 requirements and make sure they are satisfied\n- Collect report of all malfunctions from clients to ensure immediate action\n- Facilitate proactive solutions by collecting and analyzing quality data\n- Review current standards and policies\n- Keep records of quality reports, statistical reviews and relevant documentation\n- Ensure all legal standards are met\n\nRequirements\n- Bachelors in business administration or relevant field \u00a0\n- Proven experience as a Quality Assurance Manager (at least 4+ years of managerial experience is a MUST)\n- Thorough knowledge of methodologies of quality assurance and standards in the Diamond Industry is a MUST\n- Having relevant experience in quality inspection, auditing, and testing is an added advantage\n- Ample experience in implementing corrective/preventive measures\n- Excellent numerical skills and understanding of data analysis/statistical methods\n- Good knowledge of MS Office and databases\n- Knowledge of Inventory / CRM Software is an added advantage\n- Outstanding communication skills\n- Great attention to detail and results driven approach\n- Excellent organizational and leadership abilities\n- Reliable and Trustworthy\n- Able to speak South Asian Languages is a plus", "employment_types": ["Full Time", "Permanent"], "selling_points": [], "locations": ["Not Specified"], "categories": ["Manufacturing", "Jewelry", "Management", "General Management", "Quality Assurance, Control & Testing / ISO"], "post_time": "2022-01-07T10:11:38Z", "salary": {"currency": null, "max": null, "min": null, "period": "monthly", "term": null}, "salary_visible": false, "title_keywords": ["manager"], "responsibilities": ["data", "operations", "policies", "review", "monitor", "quality", "procedures", "reports", "documentation", "report"], "requirements": {"degrees": [], "majors": [], "languages": [], "language_level": [], "hard_skills": ["plus", "analysis", "numerical skills", "databases", "ms office"], "soft_skills": ["communication skills", "trustworthy", "organizational", "thorough", "attention to detail", "reliable", "leadership", "driven"], "languages_combined": []}, "experience_required": {"duration": ["at least 4+ years"], "field": ["managerial", "relevant experience", "testing", "quality assurance"]}}, {"job_id": "100003009028169", "location_code": "hk", "company": "Man King Jewellery Company Limited", "job_title": "Sales Co-ordinator", "description": "Responsibilities:\n\n- Provide general support to the sales department\n- Prepare quotation, invoices and data entry\n- Handle customer inquiries and follow up orders\u00a0\n- Arrange shipment/delivery of goods\n- Attend local trade shows\n\nRequirements\n\n- Higher diploma or above\n- Minimum 1 year working experience\n- Fresh graduates are also welcome\n- High sense of responsibility\n- Detail-minded, well-organized and hard working\n- Knowledge of MS office software and Chinese typing\n- Good command of both written & spoken English & Chinese\u00a0\n\n\n\nFor qualified candidates, we offer:\n\n- 5 working days\n- Bank holidays\n- Year-end bonus\n- Medical insurance\u00a0\n\nInterested candidates please send CV/ resume with expected salary and state of availability by clicking 'Apply now'.\u00a0", "employment_types": ["Full Time"], "selling_points": [], "locations": ["Hung Hom"], "categories": ["Manufacturing", "Jewelry"], "post_time": "2022-01-07T01:41:09Z", "salary": {"currency": null, "max": null, "min": null, "period": "monthly", "term": null}, "salary_visible": false, "title_keywords": ["sales"], "responsibilities": ["follow up orders", "invoices", "customer inquiries", "data entry", "quotation", "general support"], "requirements": {"degrees": ["higher diploma or above"], "majors": [], "languages": ["english", "chinese"], "language_level": ["good command"], "hard_skills": ["typing", "ms office"], "soft_skills": ["detail-minded", "high sense of responsibility", "well-organized", "hard working"], "languages_combined": [{"language": "english", "language_level": ["good command"]}, {"language": "chinese", "language_level": ["good command"]}]}, "experience_required": {"duration": ["minimum 1 year"], "field": []}}, {"job_id": "100003009028228", "location_code": "hk", "company": "Chow Sang Sang Holdings International Limited", "job_title": "Assistant Gemologist", "description": "Responsibilities:\n\nResponsible for gemstone inspection, authentication, record, conduct instrument maintenance and calibration and other daily activities in the gemological laboratory\nVerify the authenticity and other attributes of the gemstone inspected, preparation of reports, certificates and other related documentations, assure the quality and accuracy of the results\nAssist to verify and audit testing data and information, signing reports/certificates\nDevelop relevant documentation and inspection protocols\nKeep update of the latest gemological information within the industry, provide training and instructions to junior and supporting staff\nHandling where necessary in special projects as assigned\n\nRequirements:\n\nUniversity degree or above in Geology, Chemistry, Materials Sciences or related areas is preferred\nShould have gemstone qualification certificate such as GIA GG and FGA\nCandidate with a HKAS Approved Signatory is preferred\nFamiliar with HOKLAS accreditation and ISO17025 quality system\nExperienced with analytical equipment such as FTIR, Micro-Raman or ICP-MS preferred\nAbility to multi-task and deal with a varied workload, able to work well in a team environment or independently\nProficient in both English and Chinese for communication & writing\nFresh graduates will be considered\n\nWe offer 5-days-work week with competitive remuneration packages to the right candidate.\u00a0 Interested parties please send your CV with EXPECTED SALARY through the below application procedure.\n\n(Personal data will be used by Chow Sang Sang (CSS) for recruitment only.\u00a0 CSS may refer suitable applications to other vacancies within CSS and its associated companies.\u00a0 We will retain unsuccessful applications for a maximum period of 24 months.)", "employment_types": ["Full Time", "Permanent"], "selling_points": ["Responsible for gemstone inspection", "Verify the authenticity of the gemstone inspected", "Fresh graduates will be considered"], "locations": ["Cheung Sha Wan"], "categories": ["Sciences, Lab, R&D", "Chemical", "Manufacturing", "Jewelry", "Laboratory"], "post_time": "2022-01-07T09:26:10Z", "salary": {"currency": null, "max": null, "min": null, "period": "monthly", "term": null}, "salary_visible": false, "title_keywords": ["assistant"], "responsibilities": ["provide training", "maintenance", "data", "quality", "audit", "inspection", "testing", "develop", "reports", "documentation"], "requirements": {"degrees": ["certificate", "degree or above"], "majors": ["chemistry"], "languages": ["english", "chinese"], "language_level": ["proficient"], "hard_skills": [], "soft_skills": ["communication", "independently", "multi-task"], "languages_combined": [{"language": "english", "language_level": ["proficient"]}, {"language": "chinese", "language_level": ["proficient"]}]}, "experience_required": {"duration": [], "field": []}}, {"job_id": "100003009026003", "location_code": "hk", "company": "Camex Jewellery Limited", "job_title": "Senior Marketing Executive", "description": "Responsibilities:\n\nPerform basic clerical duties following detailed instructions and procedures\nSample development experience is preferred\nCommunicate with factory about the production\nDaily email with customer\nAssist to Sales and Marketing Department\nArrange shipment to the customer\nProvide good customer service with internal and external parties\nFollow up orders & deal with overseas customers\nAttend local & oversea jewellery trade fairs\nHandle other ad hoc tasks as assigned;\n\nRequirement:\n\nF.7 or above\nWith min. 3 years' relevant experience (preferably in Jewellery industry/Sales & Marketing)\nExperience in handling shipping documents is an advantage\nFriendly personality, proactive, detail minded,willing to learn and responsible\nHands-on PC knowledge (MS Word, Excel)\nAble to communicate in Cantonese, Mandarin and English\nEager to learn, patient & able to work under pressure\nImmediately available preferred\n\nINTERESTED PARTIES, PLEASE SEND YOUR FULL C.V. WITH CURRENT AND EXPECTED SALARY BY CLICKING \"APPLY NOW\". ALL INFORMATION RECEIVED WILL BE KEPT IN STRICT CONFIDENTIAL AND RECRUITMENT PURPOSE ONLY.", "employment_types": ["Full Time", "Permanent"], "selling_points": ["Perform basic clerical duties", "Attend local & oversea jewellery trade fairs", "3 years' relevant experience"], "locations": ["Tsim Sha Tsui"], "categories": ["Sales, CS & Business Devpt", "Customer Service - Supervisor / Officer", "Manufacturing", "Jewelry", "Transportation & Logistics", "Shipping"], "post_time": "2022-01-06T07:02:26Z", "salary": {"currency": null, "max": null, "min": null, "period": "monthly", "term": null}, "salary_visible": false, "title_keywords": ["senior marketing executive"], "responsibilities": ["communicate with", "follow up orders", "internal and external parties", "procedures", "ad hoc tasks", "customer service"], "requirements": {"degrees": [], "majors": [], "languages": ["cantonese", "english", "mandarin"], "language_level": [], "hard_skills": ["excel", "pc knowledge", "ms word"], "soft_skills": ["responsible", "willing to learn", "eager to learn", "hands-on", "friendly", "patient", "proactive", "work under pressure"], "languages_combined": [{"language": "cantonese", "language_level": []}, {"language": "english", "language_level": []}, {"language": "mandarin", "language_level": []}]}, "experience_required": {"duration": ["3 years"], "field": ["marketing", "relevant experience"]}}, {"job_id": "100003009030638", "location_code": "hk", "company": "Aaron Shum Jewelry Limited", "job_title": "Sales Administrator", "description": "Responsible for order follow up\u00a0and assist in all sales / shipping\u00a0related matters\nKnowledge in Jewelry field is an advantage\nLiaise with China factory\n2-3 years relevant experience\nProficient in English\nSelf-motivated and able to work independently", "employment_types": ["Full Time", "Permanent"], "selling_points": ["Sales Administrator, order follow up", "Jewelry, watch", "5 days work"], "locations": ["Hung Hom"], "categories": ["Manufacturing", "Jewelry", "Sales, CS & Business Devpt", "Account Servicing", "Sales Administration"], "post_time": "2022-01-07T07:58:04Z", "salary": {"currency": null, "max": null, "min": null, "period": "monthly", "term": null}, "salary_visible": false, "title_keywords": ["sales administrator"], "responsibilities": ["liaise with", "shipping"], "requirements": {"degrees": [], "majors": [], "languages": ["english"], "language_level": ["proficient"], "hard_skills": [], "soft_skills": ["self-motivated", "work independently", "responsible"], "languages_combined": [{"language": "english", "language_level": ["proficient"]}]}, "experience_required": {"duration": ["2-3 years"], "field": ["relevant experience"]}}, {"job_id": "100003009025458", "location_code": "hk", "company": "William E Connor & Associates Ltd", "job_title": "Merchandiser - Jewelries & Accessories", "description": "Job Accountabilities\n\nAble to help customer to follow up on sampling, pricing, order placement, quality control and shipping arrangement.\nUpdate client database in system and maintain an accurate record.\nKeep abreast of market trend by visiting both existing and new suppliers.\nWork closely with other departments for updating the quality standard and shipment status.\nOrder follow-up for production and delivery schedule with suppliers.\nAssist in sampling checking.\nOther duties as assigned.\nJob Requirements\nDiploma or above in related disciplines\nMinimum 3 years relevant working experience; experience in Merchandising especially in Jewelry & Accessories\nFluency in both written and spoken Cantonese, English and Mandarin.\nGood sense of fashion & jewelry accessories\nResponsible, detail-minded, flexible, good team player, a fast-learner, able to cope with deadline.\nFresh graduates are also welcome and will be considered as Assistant Merchandiser\nImmediate available is highly preferable.\n\nConnor provides excellent career opportunities & attractive fringe benefits to the right candidate. Further information about Connor and our career opportunities can be viewed on our website\u00a0 www.weconnor.com.\u00a0 If you are interested in joining our team, please send your resume with current and expected remuneration packages to us\u00a0by MS Word attachment.\n\n\nConnor is an equal opportunities employer. Personal data provided by applicants will be used strictly for recruitment purposes only. Only short-listed candidates will be notified. Applicants who are not invited for an interview within 8 weeks may consider their applications filed for future reference.", "employment_types": ["Full Time", "Permanent"], "selling_points": ["Attractive package with good career development", "Familiar with merchandising in jewelry products", "Fresh graduates are welcomed"], "locations": ["Kowloon Bay"], "categories": ["Manufacturing", "Jewelry", "Merchandising & Purchasing", "Others", "Procurement / Purchasing / Sourcing"], "post_time": "2022-01-06T04:35:38Z", "salary": {"currency": null, "max": null, "min": null, "period": "monthly", "term": null}, "salary_visible": false, "title_keywords": ["merchandiser"], "responsibilities": ["shipping", "other duties", "quality", "checking", "merchandising", "work closely with other departments", "delivery schedule", "maintain", "quality control", "database"], "requirements": {"degrees": ["diploma or above"], "majors": ["related disciplines"], "languages": ["cantonese", "english", "mandarin"], "language_level": ["fluency"], "hard_skills": [], "soft_skills": ["detail-minded", "flexible", "good team player", "responsible", "accurate"], "languages_combined": [{"language": "cantonese", "language_level": ["fluency"]}, {"language": "english", "language_level": ["fluency"]}, {"language": "mandarin", "language_level": ["fluency"]}]}, "experience_required": {"duration": ["minimum 3 years"], "field": ["merchandising", "relevant working experience"]}}, {"job_id": "100003009023178", "location_code": "hk", "company": "Traly Hong Kong Ltd", "job_title": "QC & QA Supervisor / Manager -  metal jewelry / gifts / souvenirs / toys (OEM items)", "description": "Traly Hong Kong Limited, a well established trading and manufacturing company, with a number of well-known and prestige clients in worldwide, is urgently seeking the following posts:\n\n\n- Form 5 graduated or above\n- At least 5 year QC & QA experiences on metal Jewelry, gift & souvenir items for US markets;\n- Experience in metal pins, jewelry, gifts and souvenir items is an advantage\n- familiar with jewelry & souvenir international safety standards / regulations / product testing\n- experience in factory compliance / audit for branded customers is an advantage.\n- Strong in both spoken and written English and Chinese with fluency in spoken Putonghua\n- Strong communication, organization, and analytical skills\n- detail-orientated, Self-motivated; responsible; well organized and can work independently and under pressure;\n- Proficiency in MS Office, Outlook and Internet for daily operation;\n\nJob Duties:\nCommunicate with factories and QC team for inspection and quality control\nCoordinate with merchandising team for order inspection, quality control and testing arrangement\nSupervise in-house QC team in China\nFactory compliance or factory audit follow up\nDealing with customers\u2019 QC & QA department\nrequire occasionally travel to China\n\n- 5 Day work; Medical, Performance Bonus\n\nInterested parties, please email your full resume with contact number and expected salary by clicking \"Apply now\"\n\n\n\n", "employment_types": ["Full Time", "Permanent"], "selling_points": ["Form 5 graduated or above", "Factory compliance or factory audit follow up", "5 Day work; Medical, Performance Bonus"], "locations": ["Not Specified"], "categories": ["Manufacturing", "Jewelry", "Manufacturing Management", "Quality Assurance, Control & Testing / ISO"], "post_time": "2022-01-05T08:34:17Z", "salary": {"currency": null, "max": null, "min": null, "period": "monthly", "term": null}, "salary_visible": false, "title_keywords": ["manager", "supervisor"], "responsibilities": ["regulations", "communicate with", "compliance", "daily operation", "audit", "coordinate with", "testing", "communication", "inspection", "merchandising", "quality control", "safety standards"], "requirements": {"degrees": ["form 5"], "majors": [], "languages": ["putonghua", "english", "chinese"], "language_level": ["fluency"], "hard_skills": ["ms office", "outlook", "analytical skills"], "soft_skills": ["self-motivated", "work independently", "under pressure", "responsible", "well organized", "analytical skills", "communication"], "languages_combined": [{"language": "putonghua", "language_level": []}, {"language": "english", "language_level": ["fluency"]}, {"language": "chinese", "language_level": ["fluency"]}]}, "experience_required": {"duration": ["at least 5 year"], "field": ["compliance", "audit", "qa"]}}, {"job_id": "100003009028230", "location_code": "hk", "company": "Chow Sang Sang Holdings International Limited", "job_title": "Jewellery Designer", "description": "Responsibilities:\n\nResponsible for the jewellery design\nCreate new ranges of innovative jewellery products via sketches\nCommunicate effectively with production team to track prototype development progress within lead time\n\nRequirements:\n\nDiploma\u00a0or above\u00a0in Jewellery Design or related disciplines\nMin. 2 years experience in jewellery design, working experience in\u00a0sizable company will be an advantage\nKnowledge in jewellery production\nGood hand sketching\u00a0\nProficient in computer design software Jewel Cad, \u00a0Illustrator and 3D Design\nCreative, independent and with a passion for innovation design\nGood command of written and spoken English and Chinese (Mandarin)\n\nWe offer 5-day-work week with competitive remuneration packages to the right candidate. Interested parties please send your CV with EXPECTED SALARY through the below application procedure.\n\n(Personal data will be used by Chow Sang Sang (CSS) for recruitment only. CSS may refer suitable applications to other vacancies within CSS and its associated companies. We will retain unsuccessful applications for a maximum period of 24 months.)", "employment_types": ["Full Time", "Permanent"], "selling_points": ["Responsible for the jewellery design", "Diploma or above in Jewellery Design", "2 years or above experience in jewellery design"], "locations": ["Cheung Sha Wan"], "categories": ["Design", "Industrial / Product", "Others", "Manufacturing", "Jewelry"], "post_time": "2022-01-07T09:25:48Z", "salary": {"currency": null, "max": null, "min": null, "period": "monthly", "term": null}, "salary_visible": false, "title_keywords": ["designer"], "responsibilities": ["sketches", "design"], "requirements": {"degrees": ["diploma or above"], "majors": ["related disciplines", "design"], "languages": ["english", "chinese", "mandarin"], "language_level": ["good command"], "hard_skills": ["cad", "illustrator"], "soft_skills": ["creative", "independent", "passion for"], "languages_combined": [{"language": "english", "language_level": ["good command"]}, {"language": "chinese", "language_level": ["good command"]}, {"language": "mandarin", "language_level": ["good command"]}]}, "experience_required": {"duration": ["2 years"], "field": ["design"]}}, {"job_id": "100003009024999", "location_code": "hk", "company": "Advance Jewellery MFG Limited", "job_title": "Senior Purchasing Officer", "description": "JOB Mission\uff1a\nDiamond, gem procurement, new supplier development, evaluation, improve material supply system, improve procurement quality.\nJOB DESCRIPTION:\n1\u3001\uff0825%\uff09\uff1aFamiliar with diamond purchasing process, can work independently, and can judge diamond quality\u00a0\n2\u3001\uff0825%\uff09\uff1aFamiliar with gem purchasing process, able to work independently and judge gem quality\u00a0\n3\u3001\uff0820%\uff09\uff1a Familiar with diamond market in India and gem supply market in Thailand, and can develop overseas suppliers independently \u00a0\n4\u3001\uff0820%\uff09\uff1aAccording to the diamond and gemstone material list, market price research, understand the supply and demand situation, follow the price trend, provide suggestions for the company's purchase price.\u00a0\n5\u3001\uff0810%\uff09\uff1aHandle other tasks assigned by superior.\n\n", "employment_types": ["Full Time", "Contract"], "selling_points": ["Thailand Gemstone", "India diamond", "Purchasing management"], "locations": ["Not Specified"], "categories": ["Manufacturing", "Jewelry", "Merchandising & Purchasing", "Procurement / Purchasing / Sourcing"], "post_time": "2022-01-06T03:05:37Z", "salary": {"currency": "HKD", "max": 19999, "min": 17000, "period": "monthly", "term": null}, "salary_visible": true, "title_keywords": ["purchasing officer"], "responsibilities": ["quality", "develop", "other tasks", "purchase", "evaluation"], "requirements": {"degrees": [], "majors": [], "languages": [], "language_level": [], "hard_skills": [], "soft_skills": ["work independently", "independently", "superior"], "languages_combined": []}, "experience_required": {"duration": [], "field": []}}, {"job_id": "100003009028014", "location_code": "hk", "company": "ACH & Co. HK Limited", "job_title": "Sales Co-ordinator / Sales Administrator", "description": "** Candidate with better experience will consider a senior post of Sales Administration Officer **\n\nResponsibilities :\n\nAssist the sales teammates in preparing all sales-related documents and keep central database of all materials\nEnsure the adequacy of sales-related equipment or materials\nLiaison\u00a0with factory to ensure production and delivery\u00a0schedule\nManage showroom and samples\nRespond to complaints from customers and give after-sales support when requested\nAssist in the preparation and organizing of promotional material or events\nProvide additional support to colleagues when needed\n\nRequirements:\n\nProven experience in sales; at least 2-3 years experience as a sales\u00a0administration position (Jewelry or Garment industry will be an advantage)\nFresh graduation will also be considered\nGood computer skills (MS Office)\nProficiency in English and Putonghua\nWell-organized and responsible with an aptitude in problem-solving\nExcellent verbal and written communication skills\nDetail mind and patient for routine\u00a0works\nA team player with high level of dedication\nDiploma\u00a0in sales or marketing will be\u00a0an asset\nImmediate available preferrable\n\nWe offer 5 days work, friendly culture and\u00a0excellent career prospects and competitive remuneration to the right candidate.", "employment_types": ["Full Time", "Permanent"], "selling_points": [], "locations": ["Hung Hom"], "categories": ["Sales, CS & Business Devpt", "Customer Service - Supervisor / Officer", "Manufacturing", "Jewelry", "Marketing / Public Relations", "Marketing - General / Support"], "post_time": "2022-01-07T01:07:40Z", "salary": {"currency": null, "max": null, "min": null, "period": "monthly", "term": null}, "salary_visible": false, "title_keywords": ["sales administrator", "sales"], "responsibilities": ["related documents", "delivery schedule", "assist the sales", "database"], "requirements": {"degrees": ["diploma"], "majors": ["marketing"], "languages": ["putonghua", "english"], "language_level": ["proficiency"], "hard_skills": ["garment industry", "problem-solving", "computer skills", "ms office"], "soft_skills": ["communication skills", "responsible", "problem-solving", "well-organized", "patient", "team player"], "languages_combined": [{"language": "putonghua", "language_level": ["proficiency"]}, {"language": "english", "language_level": ["proficiency"]}]}, "experience_required": {"duration": ["at least 2-3 years"], "field": ["garment", "sales administration"]}}, {"job_id": "100003009027675", "location_code": "hk", "company": "TSL Management Services Limited", "job_title": "Assistant Officer \u2013 Production / Jewellery Arts & Technology", "description": "The position holder will work under the company\u2019s Hong Kong Production Department and report to the Production Manager.\u00a0\n\nResponsibilities:\n\nHandle the production materials in/out and system record registration\nHandle the production labor cost and scrap calculation\nTake care of the stock warehouse and in charge of the regular stock take\nHandle the handover of repair goods with shops and answer any enquiry about the repair status\nHandle all administrative work in the production site including any compliance and safety documents preparation\nSupport the jewellery photo shooting, laser inscription and Quality Assurance\n\nRequirements:\n\nDiploma or above, jewellery related qualification preferred\nJewellery and/or production related experience will be an advantage\nQuick learner and team player, with passion in jewellery industry\nGood communication skill with strong sense of responsibilities\nSensitive to numbers and detail-minded\nHands-on experience in MS Excel; knowledge in MS Word, PowerPoint or any jewellery software will be an advantage\n5.5 wording days per week (Mon-Fri, Sat am)\n\nInterested parties please send your application with\u00a0full resume, present and expected salary\u00a0by clicking \"Apply Now\".\n\n(All information collected would be used for recruitment purposes only.)", "employment_types": ["Full Time", "Permanent"], "selling_points": ["5.5 wording days per week (Mon-Fri, Sat am)", "Handle the production team admin work", "Diploma or above, jewellery related qualification"], "locations": ["Hung Hom"], "categories": ["Admin & HR", "Clerical / Admin Staff", "Manufacturing", "Jewelry", "Others"], "post_time": "2022-01-06T11:02:51Z", "salary": {"currency": null, "max": null, "min": null, "period": null, "term": null}, "salary_visible": false, "title_keywords": ["assistant officer"], "responsibilities": ["cost", "administrative work", "compliance", "quality", "stock take", "repair"], "requirements": {"degrees": ["diploma or above"], "majors": [], "languages": [], "language_level": [], "hard_skills": ["ms excel", "powerpoint", "ms word"], "soft_skills": ["detail-minded", "passion in", "communication skill", "sensitive to numbers", "quick learner", "hands-on", "team player", "sense of responsibilities"], "languages_combined": []}, "experience_required": {"duration": [], "field": ["related"]}}, {"job_id": "100003009034254", "location_code": "hk", "company": "Royal Pearl Materials Group Limited", "job_title": "Marketing Executive/ Assistant Marketing Executive", "description": "Job Responsibilities\n\n\nDevelop New Business\nOrder follow up\nOrganize and Participate Exhibitions\nPerform Sales and Marketing Activities\n\nRequirements:\n\n\nF. 7 or above with min 2 years relevant experience\nAggressive, responsible and detail minded\nA good team player\nExcellent communication skill\nFluent in both written and spoken English is a must\nGood PC skills in MS office\n\n** Fresh Graduate will be considered as Assistant Marketing Executive\n\nInterested parties, pls send your resume with expected salary and available date email via \"Apply Now\"", "employment_types": ["Full Time", "Permanent"], "selling_points": [], "locations": ["Tsim Sha Tsui"], "categories": ["Sales, CS & Business Devpt", "Business Development", "Manufacturing", "Jewelry", "Marketing / Public Relations", "Marketing - Direct Marketing"], "post_time": "2022-01-11T02:06:08Z", "salary": {"currency": null, "max": null, "min": null, "period": "monthly", "term": null}, "salary_visible": false, "title_keywords": ["assistant marketing executive", "marketing executive"], "responsibilities": ["develop new business"], "requirements": {"degrees": ["fresh graduate"], "majors": ["marketing"], "languages": ["english"], "language_level": ["fluent"], "hard_skills": ["pc skills", "ms office"], "soft_skills": ["good team player", "communication skill", "responsible"], "languages_combined": [{"language": "english", "language_level": ["fluent"]}]}, "experience_required": {"duration": ["min 2 years"], "field": ["relevant experience"]}}, {"job_id": "100003009034437", "location_code": "hk", "company": "ACH & Co. HK Limited", "job_title": "Sales & Marketing Assistant", "description": "** Candidate with better experience will consider a senior post of Sales Administration Officer **\n\nResponsibilities :\n\nFollow up customer inquiry and sampling\nAssist the sales person in preparing all sales-related documents and keep central database\nEnsure the adequacy of sales-related equipment or materials\nLiaison\u00a0with factory to ensure production and delivery\u00a0schedule\nManage showroom and samples\nProvide after-sales support when requested\nPrepare and organize of promotional material or events\n\nRequirements:\n\n2-3 years experience as a sales assistant or coordinator (Jewelry or Garment industry will be an advantage\nDiploma\u00a0in sales or marketing will be\u00a0an asset\nFresh graduation will also be considered\nGood computer skills (MS Office)\nProficiency in English and Putonghua\nWell-organized and responsible with an aptitude in problem-solving\nExcellent verbal and written communication skills\nDetail mind and patient for routine\u00a0works\nA team player with high level of dedication\nImmediate available preferable\n\nWe offer 5 days work, friendly culture and\u00a0excellent career prospects and competitive remuneration to the right candidate.", "employment_types": ["Full Time", "Permanent"], "selling_points": [], "locations": ["Hung Hom"], "categories": ["Sales, CS & Business Devpt", "Customer Service - Supervisor / Officer", "Manufacturing", "Jewelry", "Marketing / Public Relations", "Marketing - General / Support"], "post_time": "2022-01-10T03:23:13Z", "salary": {"currency": null, "max": null, "min": null, "period": "monthly", "term": null}, "salary_visible": false, "title_keywords": ["marketing assistant", "sales"], "responsibilities": ["related documents", "delivery schedule", "assist the sales", "database"], "requirements": {"degrees": ["diploma"], "majors": ["marketing"], "languages": ["putonghua", "english"], "language_level": ["proficiency"], "hard_skills": ["garment industry", "problem-solving", "computer skills", "ms office"], "soft_skills": ["communication skills", "responsible", "problem-solving", "well-organized", "patient", "team player"], "languages_combined": [{"language": "putonghua", "language_level": ["proficiency"]}, {"language": "english", "language_level": ["proficiency"]}]}, "experience_required": {"duration": ["2-3 years"], "field": ["garment"]}}, {"job_id": "100003009021212", "location_code": "hk", "company": "Darton Ltd", "job_title": "General Manager (Fine Jewelry)", "description": "\u00a0\u5d17\u4f4d\u8077\u8cac\uff1a\n\n\n\u5168\u9762\u8ca0\u8cac\u516c\u53f8\u751f\u7522\u8a08\u5283\u3001\u751f\u7522\u73fe\u5834\u7ba1\u7406\u3001\u751f\u7522\u5b89\u5168\u7ba1\u7406\u7b49\u5de5\u4f5c\uff0c\u78ba\u4fdd\u751f\u7522\u7684\u6b63\u5e38\u904b\u884c\uff1b\n\u63a8\u9032\u53ca\u7d44\u7e54\u5354\u8abf\u751f\u7522\u904b\u71df\u8a08\u756b\uff0c\u638c\u63e1\u5e02\u5834\u8ca8\u54c1\u6d41\u884c\u6b3e\u5f0f\uff0c\u8207\u6642\u4ff1\u9032\uff1b\n\u8ca0\u8cac\u5c0d\u751f\u7522\u9032\u5ea6\u7684\u5b89\u6392\u548c\u751f\u7522\u904e\u7a0b\u7684\u76e3\u63a7\uff1b\n\u5bc6\u5207\u914d\u5408\u71df\u92b7\u90e8\u9580\uff0c\u78ba\u4fdd\u8a02\u55ae\u7522\u54c1\u6e96\u6642\u51fa\u8ca8\uff1b\n\u7dad\u8b77\u6240\u8f44\u5340\u57df\u7684\u5916\u90e8\u516c\u5171\u95dc\u4fc2\uff08\u653f\u5e9c\u3001\u91cd\u8981\u5ba2\u6236\u7b49\uff09\u3002\n\n\u4efb\u8077\u8981\u6c42\uff1a\n\n10\u5e74\u6216\u4ee5\u4e0a\u73e0\u5bf6\u884c\u696d\u751f\u7522\u904b\u71df\u7ba1\u7406\u7d93\u9a57\uff0c5\u5e74\u4ee5\u4e0a\u540c\u7b49\u5d17\u4f4d\u7ba1\u7406\u7d93\u9a57\uff0c\u5177\u5927\u578b\u73e0\u5bf6\u88fd\u9020\u696d\u751f\u7522\u7d93\u9a57\uff0c\u719f\u6089\u73e0\u5bf6\u751f\u7522\u5de5\u85dd\u6280\u8853\uff1b\n\u77ad\u89e3\u73e0\u5bf6\u884c\u696d\u73fe\u72c0\u53ca\u767c\u5c55\uff0c\u5177\u524d\u77bb\u6027\u601d\u7dad\u53ca\u773c\u5149\uff1b\n\u719f\u6089\u751f\u7522\u6210\u672c\u63a7\u5236\u3001\u54c1\u8cea\u63a7\u5236\u7ba1\u7406\u7b49\u7d71\u7c4c\u5de5\u4f5c\uff1b\n\u5177\u512a\u79c0\u7684\u898f\u5283\u80fd\u529b\u3001\u63a8\u52d5\u80fd\u529b\u3001\u7d44\u7e54\u80fd\u529b\u53ca\u6e9d\u901a\u80fd\u529b\uff1b\n\u570b\u3001\u7cb5\u8a9e\u6d41\u5229\u8005\u512a\u5148\u3002\n\u6d3e\u99d0\u756a\u79ba\u5ee0\u4e0a\u73ed\n\n\u00a0\u00a0Interested parties please\u00a0send full resume with expected salary to\u00a0Human Resources Manager, Luk Fook Holdings Co Ltd., Floor 25, Metropole Square, No.2 On Yiu Street, Shek Mun, Shatin, N.T., Hong Kong; or click here\u00a0to submit your application.\n\n\u00a0All personal data are handled in accordance with our personal data privacy policies. A copy of our statement on personal data collection is available upon request.\u00a0\u00a0", "employment_types": ["Full Time"], "selling_points": [], "locations": ["Central"], "categories": ["Manufacturing", "Jewelry", "Management", "Top Executives (CEO, CFO, CTO, GM, MD etc.)"], "post_time": "2022-01-05T03:19:22Z", "salary": {"currency": null, "max": null, "min": null, "period": "monthly", "term": null}, "salary_visible": false, "title_keywords": ["general manager"], "responsibilities": [], "requirements": {"degrees": [], "majors": [], "languages": [], "language_level": [], "hard_skills": [], "soft_skills": [], "languages_combined": []}, "experience_required": {"duration": [], "field": []}}, {"job_id": "100003009029961", "location_code": "hk", "company": "Luk Fook Holdings Company Limited", "job_title": "\u9ad8\u7d1a\u696d\u52d9\u7d93\u7406", "description": "\u5c08\u8cac\u570b\u5167\u696d\u52d9\u62d3\u5c55\u53ca\u5e97\u8216\u71df\u904b\u7ba1\u7406\u5de5\u4f5c\n\u4e2d\u4e03\u6216\u4ee5\u4e0a\u7a0b\u5ea6\n\u5177\u516b\u5e74\u6216\u4ee5\u4e0a\u73e0\u5bf6\u96f6\u552e\u7ba1\u7406\u7d93\u9a57\uff0c\u719f\u6089\u570b\u5167\u5e02\u5834\u3002\n\u5177\u826f\u597d\u7ba1\u7406\u3001\u7d44\u7e54\u53ca\u6e9d\u901a\u80fd\u529b\n\u64cd\u6d41\u5229\u5ee3\u6771\u8a71\u53ca\u666e\u901a\u8a71\n\u9700\u9577\u99d0\u570b\u5167\u5de5\u4f5c\n\n\u00a0\u00a0Interested parties please\u00a0send full resume with expected salary to\u00a0Human Resources Manager, Luk Fook Holdings Co Ltd., Floor 25, Metropole Square, No.2 On Yiu Street, Shek Mun, Shatin, N.T., Hong Kong; or\u00a0click here\u00a0to submit your application.\n\n\u00a0All personal data are handled in accordance with our personal data privacy policies. A copy of our statement on personal data collection is available upon request.", "employment_types": ["Full Time"], "selling_points": ["\u5c08\u8cac\u570b\u5167\u696d\u52d9\u62d3\u5c55\u53ca\u5e97\u8216\u71df\u904b\u7ba1\u7406\u5de5\u4f5c", "\u9700\u9577\u99d0\u570b\u5167\u5de5\u4f5c", "\u91ab\u7642\u6d25\u8cbc"], "locations": ["Others - China"], "categories": ["Sales, CS & Business Devpt", "Business Development", "Manufacturing", "Jewelry", "Product Development / Management"], "post_time": "2022-01-07T06:30:36Z", "salary": {"currency": null, "max": null, "min": null, "period": "monthly", "term": null}, "salary_visible": false, "title_keywords": [], "responsibilities": [], "requirements": {"degrees": [], "majors": [], "languages": [], "language_level": [], "hard_skills": [], "soft_skills": [], "languages_combined": []}, "experience_required": {"duration": [], "field": []}}, {"job_id": "100003009016269", "location_code": "hk", "company": "Michael Page", "job_title": "Purchasing Manager/Buyer (Gems/Precious Stones) @ HKD 60,000", "description": "Source for gems/precious stones\n\nManage a team of buyers\n\nClient Details\n\nMy client is a wholesaler in luxury jewelry and is looking for a new purchasing manager to build its new team.\n\nDescription\n\nSourcing, assessing and selecting high-end stones and suppliers, enhancing the effectiveness of purchasing workflow\nNegotiate with vendors on price, terms and conditions and conclude contracts\nResponsible for the training within Purchasing team to enhance the skill-set, know-how and expertise of the Purchasing teammates.\nReview and assess the price, production capacity, quality, and delivery date of suppliers\nMonitor the performance of the existing vendors to ensure the quality of the materials\n\nProfile\n\nEducation in relevant disciplines\nAt least 6 - 8 years purchasing experience in the jewellery industry,\nStrong product knowledge\nGood communication skills\n\nJob Offer\n\nInterested applicant please send me your CV to Marcochong@michaelpage com hk OR you can contact me @ 52909990\n\nTo apply online please click the 'Apply' button below. For a confidential discussion about this role please contact Marco Chong on +852 3476 6336", "employment_types": ["Full Time", "Permanent"], "selling_points": ["Attractive salary with great benefits", "Top jewel wholesaler in Hong Kong", "Great working environment"], "locations": ["Not Specified"], "categories": ["Manufacturing", "Jewelry", "Merchandising & Purchasing", "Others", "Procurement / Purchasing / Sourcing"], "post_time": "2022-01-03T08:43:57Z", "salary": {"currency": null, "max": null, "min": null, "period": "monthly", "term": null}, "salary_visible": false, "title_keywords": ["purchasing manager"], "responsibilities": ["contracts", "review", "quality", "communication", "monitor the performance", "contact"], "requirements": {"degrees": [], "majors": [], "languages": [], "language_level": [], "hard_skills": ["marco"], "soft_skills": ["communication skills", "responsible"], "languages_combined": []}, "experience_required": {"duration": ["at least 6 - 8 years"], "field": ["purchasing"]}}, {"job_id": "100003009029979", "location_code": "hk", "company": "Luk Fook Holdings Company Limited", "job_title": "Senior Marketing Manager", "description": "Responsibilities:\n\n\u00a0Report to the Deputy Marketing Director\n\u00a0Build marketing programs to support specific marketing objectives across different\u00a0 \u00a0channels and segments in support of overall strategic marketing plan\nSet and monitor annual marketing strategies in correlating with budgets for brand building, product launching and marketing positioning\nMotivate an efficient and effective team work of the marketing department\n\nRequirements:\n\n\nBachelor Degree with major in Marketing , Communications or related disciplines\nMinimum 10 years related experience in retail industry, with track records in jewellery industry an advantage\nWith outstanding communication, leadership and project management skills\nStrong problem-solving ability\nGood command of spoken and written English, Chinese and Mandarin\nWorking exposure in China and experience on digital marketing are a definite must\nTravel to China is required\nWork in Shek Mun area\n\nInterested parties please send full resume with expected salary to\u00a0Human Resources Manager, Luk Fook Holdings Co Ltd., Floor 25, Metropole Square, No.2 On Yiu Street, Shek Mun, Shatin, N.T., Hong Kong\u00a0or\u00a0(click here)\u00a0to submit your application.\n\nAll personal data are handled in accordance with our personal data privacy policies.\u00a0 A copy of our statement on personal data collection is available upon request.\n\n\n\n\n", "employment_types": ["Full Time", "Permanent"], "selling_points": ["Experience on Emarketing is a definite must", "Working exposure in China", "Travel to China is required"], "locations": ["Shatin Area"], "categories": ["Manufacturing", "Jewelry", "Marketing / Public Relations", "Management", "E-commerce", "Marketing - Brand / Product Management"], "post_time": "2022-01-07T06:33:16Z", "salary": {"currency": null, "max": null, "min": null, "period": "monthly", "term": null}, "salary_visible": false, "title_keywords": ["senior marketing manager"], "responsibilities": ["budgets", "marketing strategies", "monitor", "marketing plan", "report"], "requirements": {"degrees": ["degree", "bachelor"], "majors": ["related disciplines", "marketing", "communications"], "languages": ["english", "chinese", "mandarin"], "language_level": ["good command"], "hard_skills": ["project management", "problem-solving"], "soft_skills": ["communication", "project management skills", "problem-solving", "leadership"], "languages_combined": [{"language": "english", "language_level": ["good command"]}, {"language": "chinese", "language_level": ["good command"]}, {"language": "mandarin", "language_level": ["good command"]}]}, "experience_required": {"duration": ["minimum 10 years"], "field": ["related", "retail industry", "digital marketing"]}}, {"job_id": "100003009015570", "location_code": "hk", "company": "VDA Jewellery Limited", "job_title": "Account Manager", "description": "JOB Description\n\nAccount Manager is a member of the Sales Team under VDA Group. This team explores and follows up all the sales activities with customers in order to achieve the goals that have been set by the supervisor.\n\n\nJOB Responsibilities:\nAchieve the sales and GP target that has been set by the supervisor\nFollow and achieve the strategic plan that has been set by the supervisor\nExplore new business opportunities with regular and new customers\nLiaise and maintain a good relationship with overseas customers\nHandle clients inquiries\u00a0on products development, order delivery, pricing, complaints, and account receivables\nProvide quality sales services to attain total customer satisfaction\nConducting market research to identify selling possibilities and evaluate customer needs\nTravel overseas to meet with customers regularly\nJOB Requirements:\nDiploma or above with at least 2 years experience from the wholesale jewellery industry\nA driving licence holder is preferably but not a must\nVery good verbal and written communication skills in English, Chinese, and Mandarin is essential\nGood communication, organization & correspondence skill, able to work under pressure\nVery good knowledge of MS Office\nThorough understanding of marketing and negotiating techniques\nFast learner and passion\nSelf-motivated with a results-driven approach\nAptitude in delivering attractive presentations\nOffice location: Kowloon Bay\n\n\nWe offer a competitive remuneration package and excellent career prospects to the right candidates. Interested parties please send your full resume with present &\u00a0EXPECTED SALARY,\u00a0and AVAILABILITY to our Human Resources & Administration Department by \"Clicking Apply Now\"\nPersonal data will be used for recruitment purposes only.", "employment_types": ["Full Time"], "selling_points": [], "locations": ["Kowloon Bay"], "categories": ["Manufacturing", "Jewelry", "Sales, CS & Business Devpt", "Sales - Sales Management", "Wholesale"], "post_time": "2022-01-03T07:04:27Z", "salary": {"currency": null, "max": null, "min": null, "period": "monthly", "term": null}, "salary_visible": false, "title_keywords": ["account manager"], "responsibilities": ["liaise", "sales activities", "explore new business opportunities", "quality", "market research", "good relationship", "evaluate", "maintain", "sales team", "plan"], "requirements": {"degrees": ["diploma or above"], "majors": [], "languages": ["english", "chinese", "mandarin"], "language_level": ["good"], "hard_skills": ["presentations", "ms office"], "soft_skills": ["communication skills", "self-motivated", "communication", "thorough", "fast learner", "driven", "work under pressure"], "languages_combined": [{"language": "english", "language_level": ["good"]}, {"language": "chinese", "language_level": ["good"]}, {"language": "mandarin", "language_level": ["good"]}]}, "experience_required": {"duration": ["at least 2 years"], "field": []}}, {"job_id": "100003009005557", "location_code": "hk", "company": "Goldenage International Limited", "job_title": "Jewellery Production Assistant", "description": "Responsible for order follow up\u00a0and assist in all sales / shipping\u00a0related matters\nKnowledge in Jewelry field is an advantage\nLiaise with China factory\n2-3 years relevant experience\nProficient in English\nSelf-motivated and able to work independently", "employment_types": ["Full Time", "Permanent"], "selling_points": ["Create Beautiful Jewellery", "Cost calculations, Data & Inventory Management", "Great Work Culture"], "locations": ["Hung Hom"], "categories": ["Manufacturing", "Jewelry", "Product Development / Management", "Merchandising & Purchasing", "Procurement / Purchasing / Sourcing"], "post_time": "2021-12-29T04:02:06Z", "salary": {"currency": null, "max": null, "min": null, "period": "monthly", "term": null}, "salary_visible": false, "title_keywords": ["production assistant"], "responsibilities": ["liaise with", "shipping"], "requirements": {"degrees": [], "majors": [], "languages": ["english"], "language_level": ["proficient"], "hard_skills": [], "soft_skills": ["self-motivated", "work independently", "responsible"], "languages_combined": [{"language": "english", "language_level": ["proficient"]}]}, "experience_required": {"duration": ["2-3 years"], "field": ["relevant experience"]}}, {"job_id": "100003009005556", "location_code": "hk", "company": "Goldenage International Limited", "job_title": "Sales Coordinator - Jewellery Industry", "description": "Regional Sales Executive is one of the member of the jewellery sales team under VDA Jewellery. The candidate is required to manage all assigned accounts given by the Regional sales director with his or her team and to enhance the relationship with the clients as a priority. The candidate is responsible to perform the given task and goal with the sales team including communicating with the product development team, analyzing data, and all daily sales operation work for assigned clients.\n\n\u00a0JOB Responsibilities\u00a0:\n\nDaily communication work with clients about order management and product development.\nConstant research and understanding of the client\u2019s market and opportunities.\nExplore new clients and businesses in a given region.\nLiaise with the China team for order coordination and travel to PanYu when necessary.\nRequire to travel overseas in meeting clients.\n\n\u00a0JOB Requirements\u00a0:\n\nMinimum 3 years of experience in sales work.\nExperience in the Jewellery industry and/or B2B business nature.\nExcellent communication and interpersonal skills.\nConsistent attention to detail.\nGreat endurance and determination.\n\nOffice location: Kowloon Bay\n\nWe offer a competitive remuneration package and excellent career prospects to the right candidates. Interested parties please send your full resume with present &\u00a0EXPECTED SALARY, AND AVAILABILITY to our Human Resources & Administration Department by \"Clicking Apply Now\"\n\nPersonal data will be used for recruitment purposes only.", "employment_types": ["Full Time"], "selling_points": ["Client Services Management", "5 Day weeks  $19K+", "Great Work Culture"], "locations": ["Hung Hom"], "categories": ["Manufacturing", "Jewelry", "Marketing / Public Relations", "Marketing - Brand / Product Management", "Sales, CS & Business Devpt", "Sales - Sales Management"], "post_time": "2021-12-29T04:02:05Z", "salary": {"currency": null, "max": null, "min": null, "period": "monthly", "term": null}, "salary_visible": false, "title_keywords": ["sales coordinator"], "responsibilities": ["communication", "liaise with", "order management", "coordination"], "requirements": {"degrees": [], "majors": [], "languages": [], "language_level": [], "hard_skills": [], "soft_skills": ["communication and interpersonal skills", "attention to detail"], "languages_combined": []}, "experience_required": {"duration": ["minimum 3 years"], "field": ["business"]}}, {"job_id": "100003009002534", "location_code": "hk", "company": "VDA Jewellery Limited", "job_title": "Regional Sales Executive", "description": "The Role and Responsibilities\n\u2022 Follow up on Sales Leads, confirm orders, send quotations and sales enquirers\n\u2022 Liaise with clients and work independently\n\u2022 Able to explore various business opportunities\n\u2022 Develop and strengthen relationship with overseas customers\n\u2022 Develop new markets and customers worldwide\n\u2022 Handle sales office operations\n\u2022 Attend trade fairs and exhibitions\n\nRequirements\n\u2022 Experience in jewellery industry advantageous\n\u2022 Proficiency in Microsoft applications including Excel, Word & Outlook\n\u2022 Fluency in written and spoken Chinese (Cantonese and Mandarin) and English\n\u2022 Good Mathematics and strong with numbers encouraged to APPLY\n\u2022 High achiever with strong communication, interpersonal skills and a \u201cCAN DO\" attitude!\n\u2022 Recent Graduates welcome to apply\n\nWorking Conditions :\u00a0\n\u2022\u00a0 Full Time Employee benefits: year end bonus, 10 days annual leave\n\u2022\u00a0Work hours: 9:00am to 5:30pm (Mon - Fri)\nSubmit your resume with date availability, expected salary and a recent Photo for reference.\n\n\nThe right candidate will be competitively Remunerated", "employment_types": ["Full Time"], "selling_points": [], "locations": ["Kowloon Bay"], "categories": ["Manufacturing", "Jewelry"], "post_time": "2021-12-28T06:15:39Z", "salary": {"currency": null, "max": null, "min": null, "period": "monthly", "term": null}, "salary_visible": false, "title_keywords": ["regional sales executive"], "responsibilities": ["liaise with clients", "operations", "business opportunities", "develop"], "requirements": {"degrees": [], "majors": [], "languages": ["cantonese", "english", "chinese", "mandarin"], "language_level": ["fluency"], "hard_skills": ["excel", "outlook", "word", "microsoft applications"], "soft_skills": ["communication", "interpersonal skills"], "languages_combined": [{"language": "cantonese", "language_level": ["fluency"]}, {"language": "english", "language_level": ["fluency"]}, {"language": "chinese", "language_level": ["fluency"]}, {"language": "mandarin", "language_level": ["fluency"]}]}, "experience_required": {"duration": [], "field": []}}, {"job_id": "100003009002765", "location_code": "hk", "company": "VDA Jewellery Limited", "job_title": "Senior Buyer/ Buyer - Jewellery (Stone)", "description": "Senior Buyer/ Buyer is a member of the Purchasing Team under VDA Group. This post explores and manage all the diamond purchasing, cost, and inventory control, for the company be able in the fierce international market in the jewelry industry to increase competitiveness.\n\nJOB Responsibilities:\n\nResponsible for all color stone (included Precious stone and some Semi-Precious) requirements\nStone quality control: responsible for setting up all the color stone standards as per customer\u2019s need.\u00a0\nManaging: stone purchasing management and inventory control\nDeveloped a reliable vendor base and negotiated the most favorable terms & price.\nEvaluate: stone price review and supplier evaluation report\nCoach and support new material to our sales team\nJOB Requirements:\n\nDiploma holder orat least 2 years purchasing experience in jewellery' industry\nWith strong stone knowledge\nWell-organized, with analytical and communication skills\nGood in presentation and interpersonal skill\nGood command of English, Cantonese as well as Putonghua\nGood in computer software applications\nTravel to China is necessary", "employment_types": ["Full Time"], "selling_points": [], "locations": ["Kowloon Bay"], "categories": ["Manufacturing", "Jewelry"], "post_time": "2021-12-28T07:10:18Z", "salary": {"currency": null, "max": null, "min": null, "period": "monthly", "term": null}, "salary_visible": false, "title_keywords": [], "responsibilities": ["management", "review", "evaluate", "inventory control", "sales team", "quality control", "evaluation", "report"], "requirements": {"degrees": ["diploma holder"], "majors": [], "languages": ["cantonese", "putonghua", "english"], "language_level": ["good command"], "hard_skills": [], "soft_skills": ["communication skills", "well-organized", "presentation", "interpersonal skill"], "languages_combined": [{"language": "cantonese", "language_level": ["good command"]}, {"language": "putonghua", "language_level": ["good command"]}, {"language": "english", "language_level": ["good command"]}]}, "experience_required": {"duration": ["least 2 years"], "field": ["purchasing"]}}, {"job_id": "100003009002757", "location_code": "hk", "company": "VDA Jewellery Limited", "job_title": "Senior Buyer/ Buyer - Jewellery (Diamond)", "description": "Senior Buyer/ Buyer is a member of the Purchasing Team under VDA Group. This post explores and manage all the diamond purchasing, cost, and inventory control, for the company be able in the fierce international market in the jewelry industry to increase competitiveness.\n\nJOB Responsibilities:\n\nResponsible for all\u00a0diamond requirements\nDiamond quality control: responsible for setting up all the color stone standards as per customer\u2019s need.\u00a0\nManaging:\u00a0diamond purchasing management and inventory control\nDeveloped a reliable vendor base and negotiated the most favorable terms & price.\nEvaluate:\u00a0diamond price review and supplier evaluation report\nCoach and support new material to our sales team\nJOB Requirements:\n\nDiploma holder orat least 2 years purchasing experience in jewellery' industry\nWith diamond knowledge\nWell-organized, with diamond analytical and communication skills\nGood in presentation and interpersonal skill\nGood command of English, Cantonese as well as Putonghua\nGood in computer software applications\nTravel to China is necessary", "employment_types": ["Full Time"], "selling_points": [], "locations": ["Kowloon Bay"], "categories": ["Manufacturing", "Jewelry"], "post_time": "2021-12-28T07:09:21Z", "salary": {"currency": null, "max": null, "min": null, "period": "monthly", "term": null}, "salary_visible": false, "title_keywords": [], "responsibilities": [], "requirements": {"degrees": ["diploma holder"], "majors": [], "languages": ["cantonese", "putonghua", "english"], "language_level": ["good command"], "hard_skills": ["vendor"], "soft_skills": ["communication skills", "responsible", "well-organized", "interpersonal skill", "reliable", "presentation"], "languages_combined": [{"language": "cantonese", "language_level": ["good command"]}, {"language": "putonghua", "language_level": ["good command"]}, {"language": "english", "language_level": ["good command"]}]}, "experience_required": {"duration": ["least 2 years"], "field": ["purchasing"]}}, {"job_id": "100003009007866", "location_code": "hk", "company": "J K Sons Limited", "job_title": "Manager (Diamond Merchandising and Supply Chain)", "description": "Primary Duties and Responsibilities:\n\n\nDevelop and drive and strategy for the diamond category:\n\nManage, innovate and monitor Company\u2019s diamond supply and grow the category\nIdentify strategic growth opportunities in a dynamic growing business\nManage and monitor company\u2019s existing vendor base and identify potential new partnerships supporting company initiatives.\n\nSupport and build a high-performing team:\u00a0\n\nSuccessfully lead, develop and mentor a team of multiple direct reports to achieve performance goals.\nDefine organizational structure to support continued category growth\n\nDrive organizational, product, and process improvements across the entire team:\n\nStrategize and collaborate to understand existing processes creating challenges and bottlenecks and develop new sustainable and concise programs and processes to address\nTrain the team and cross functional partners on the programs and processes\n\nManages the day-to-day supply chain execution and vendor management:\n\nManage the global procurement of diamonds for the marketplace as well as Company owned diamonds\nSupport merchandising revenue, margin, and inventory plans\nPartner with suppliers to understand current and evolving business trends in the diamond market and how they may impact company\nIdentify opportunities for new partnerships to increase supply in key areas of need and growth\n\n\nQualifications:\u00a0\n\nBachelor\u2019s Degree in Business or related field\n10+ years\u2019 experience in merchandising, buying, planning for Diamonds, Gemstone, Jewellery, etc is a MUST\n5+ with management experience\nExceptional Excel skills required, including the ability to manipulate large sets of data\nRobust understanding of pricing strategy, previous Retail Pricing experience preferred\nStrong business acumen: ability to see the big picture and the ability to understand and solve for strategic objectives\nStrong communication skills (Fluency in English, Hindi and Indian Dialect is preferred)\nDemonstrated problem solving/decision making skills; ability to make timely effective, fact-based decisions\nAccept Flexible working hours", "employment_types": ["Full Time"], "selling_points": [], "locations": ["Not Specified"], "categories": ["Manufacturing", "Jewelry", "Transportation & Logistics", "Supply Chain", "Merchandising & Purchasing", "Procurement / Purchasing / Sourcing"], "post_time": "2021-12-30T04:55:49Z", "salary": {"currency": null, "max": null, "min": null, "period": "monthly", "term": null}, "salary_visible": false, "title_keywords": ["manager", "merchandising"], "responsibilities": ["collaborate", "management", "data", "inventory", "monitor", "merchandising", "develop", "communication", "reports", "plans", "planning"], "requirements": {"degrees": ["degree", "bachelor"], "majors": ["business"], "languages": ["english", "hindi"], "language_level": ["fluency"], "hard_skills": ["excel", "vendor", "problem solving", "make", "dynamic", "acumen"], "soft_skills": ["flexible", "communication skills", "decision making skills", "organizational", "timely", "robust", "problem solving", "dynamic", "business acumen"], "languages_combined": [{"language": "english", "language_level": ["fluency"]}, {"language": "hindi", "language_level": ["fluency"]}]}, "experience_required": {"duration": ["10+ years"], "field": ["management", "retail", "merchandising", "planning"]}}, {"job_id": "100003009006222", "location_code": "hk", "company": "William E Connor & Associates Ltd", "job_title": "Product Development & Design Specialist", "description": "Job Accountabilities\n\nCreating trend and concept boards for colour, mood, themes and runway inspiration.\nCreating and presenting seasonal collection for client presentations.\nCreating and presenting brand appropriate print, graphic and embellishment projects.\nWork closely with design team to translate seasonal concepts to graphic design.\nAbility in apparel 2D CADs. 3D an advantage\nAbility to meet tight deadlines.\nOther duties as assigned.\nJob Requirements\n\nHigher diploma or above in fashion, graphics or related disciplines\nMinimum 4 years relevant experience with exposure in the US/UK fashion market an advantage\nHands-on experience in ladies, mens and kids apparel particularly design.\nGood command in English.\nSkillful in Adobe Illustrator & Photoshop are must\nIndependent in creating prints, embellishment artworks & Flat drawing CADs\nGood fashion sense, knowledgeable in wovens and cut & sewn knits\nGood time management skills & able to work under pressure\nImmediate available is highly preferable.\nConnor provides excellent career opportunities & attractive fringe benefits to the right candidate. Further information about Connor and our career opportunities can be viewed on our website\u00a0 www.weconnor.com.\u00a0 If you are interested in joining our team, please send your resume with current and expected remuneration packages to us\u00a0by MS Word attachment.\n\n\nConnor is an equal opportunities employer. Personal data provided by applicants will be used strictly for recruitment purposes only. Only short-listed candidates will be notified. Applicants who are not invited for an interview within 8 weeks may consider their applications filed for future reference.", "employment_types": ["Full Time", "Permanent"], "selling_points": ["Attractive package with good career development", "Familiar with merchandising in apparel", "Fashion & apparel design, product development"], "locations": ["Kowloon Bay"], "categories": ["Manufacturing", "Jewelry", "Product Development / Management", "Merchandising & Purchasing", "Procurement / Purchasing / Sourcing"], "post_time": "2021-12-29T07:45:06Z", "salary": {"currency": null, "max": null, "min": null, "period": "monthly", "term": null}, "salary_visible": false, "title_keywords": ["design specialist", "product development"], "responsibilities": ["graphics", "management", "other duties", "graphic design", "presentations", "design", "work under pressure"], "requirements": {"degrees": ["higher diploma or above"], "majors": ["related disciplines"], "languages": ["english"], "language_level": ["good command"], "hard_skills": ["graphics", "photoshop", "presentations", "adobe illustrator"], "soft_skills": ["meet tight deadlines", "independent", "time management skills", "hands-on", "work under pressure"], "languages_combined": [{"language": "english", "language_level": ["good command"]}]}, "experience_required": {"duration": ["minimum 4 years"], "field": ["relevant experience", "design"]}}, {"job_id": "100003009002726", "location_code": "hk", "company": "VDA Jewellery Limited", "job_title": "Assistant Stone Purchasing Manager", "description": "Assistant Stone Purchasing Manager\u00a0is a member of the Purchasing Team under VDA Group. This post explores and manage all the diamond purchasing, cost, and inventory control, for the company be able in the fierce international market in the jewelry industry to increase competitiveness.\n\nJOB Responsibilities\n\nAssist to manage the Purchasing team\nSupport the team to identify strengths and gaps in performance and to seek solutions\nImplement and maintain regular communication channels to keep teams up-to-date with current performance.\nAssist in analyzing the purchasing management report and stone cost control\nManaging suppliers\u2019 relationships\nParticipate and assist in stone inventory management\nDevelop and implement purchasing planning in alignment with the Group's revenue target and the direction of product development\nWork with subordinates to oversee the entire purchasing process in both Hong Kong and China including sourcing targeted products and prices & monitoring material inventory balance\nWork with internal & external parties effectively to ensure product compliance & flawless production execution\nAttend exhibitions and fairs whenever necessary\n\nJOB Requirements\n\nDiploma holder of purchasing or relevant disciplines\nAt least 8 years purchasing experience in the luxury jewellery industry, in which 3 years at supervisory level\nWith strong stone knowledge\nWell-organized, with strong analytical and communication skills\nGood in presentation and interpersonal skill\nGood command of English, Cantonese as well as Putonghua\nGood in computer software applications\nFrequent travel to China is necessary", "employment_types": ["Full Time"], "selling_points": [], "locations": ["Kowloon Bay"], "categories": ["Manufacturing", "Jewelry"], "post_time": "2021-12-28T07:00:36Z", "salary": {"currency": null, "max": null, "min": null, "period": "monthly", "term": null}, "salary_visible": false, "title_keywords": ["purchasing manager", "assistant"], "responsibilities": ["inventory", "monitoring", "teams", "external parties", "compliance", "develop", "communication", "inventory management", "maintain", "cost control", "management report", "support the team", "planning"], "requirements": {"degrees": ["diploma holder"], "majors": [], "languages": ["cantonese", "putonghua", "english"], "language_level": ["good command"], "hard_skills": [], "soft_skills": ["communication skills", "well-organized", "presentation", "interpersonal skill"], "languages_combined": [{"language": "cantonese", "language_level": ["good command"]}, {"language": "putonghua", "language_level": ["good command"]}, {"language": "english", "language_level": ["good command"]}]}, "experience_required": {"duration": ["at least 8 years", "3 years"], "field": ["purchasing", "supervisory level"]}}, {"job_id": "100003009001105", "location_code": "hk", "company": "ACH & Co. HK Limited", "job_title": "Sales Co-ordinator / Sales Administrator", "description": "** Candidate with better experience will consider a senior post of Sales Administration Officer **\n\nResponsibilities :\n\nAssist the sales teammates in preparing all sales-related documents and keep central database of all materials\nEnsure the adequacy of sales-related equipment or materials\nLiaison\u00a0with factory to ensure production and delivery\u00a0schedule\nManage showroom and samples\nRespond to complaints from customers and give after-sales support when requested\nAssist in the preparation and organizing of promotional material or events\nProvide additional support to colleagues when needed\n\nRequirements:\n\nProven experience in sales; at least 2-3 years experience as a sales\u00a0administration position (Jewelry or Garment industry will be an advantage)\nFresh graduation will also be considered\nGood computer skills (MS Office)\nProficiency in English and Putonghua\nWell-organized and responsible with an aptitude in problem-solving\nExcellent verbal and written communication skills\nDetail mind and patient for routine\u00a0works\nA team player with high level of dedication\nDiploma\u00a0in sales or marketing will be\u00a0an asset\nImmediate available preferrable\n\nWe offer 5 days work, friendly culture and\u00a0excellent career prospects and competitive remuneration to the right candidate.", "employment_types": ["Full Time", "Permanent"], "selling_points": [], "locations": ["Hung Hom"], "categories": ["Sales, CS & Business Devpt", "Customer Service - Supervisor / Officer", "Manufacturing", "Jewelry", "Marketing / Public Relations", "Marketing - General / Support"], "post_time": "2021-12-28T01:33:00Z", "salary": {"currency": null, "max": null, "min": null, "period": "monthly", "term": null}, "salary_visible": false, "title_keywords": ["sales administrator", "sales"], "responsibilities": ["related documents", "delivery schedule", "assist the sales", "database"], "requirements": {"degrees": ["diploma"], "majors": ["marketing"], "languages": ["putonghua", "english"], "language_level": ["proficiency"], "hard_skills": ["garment industry", "problem-solving", "computer skills", "ms office"], "soft_skills": ["communication skills", "responsible", "problem-solving", "well-organized", "patient", "team player"], "languages_combined": [{"language": "putonghua", "language_level": ["proficiency"]}, {"language": "english", "language_level": ["proficiency"]}]}, "experience_required": {"duration": ["at least 2-3 years"], "field": ["garment", "sales administration"]}}, {"job_id": "100003008994818", "location_code": "hk", "company": "C&K Jewellery Limited", "job_title": "Accounting Assistant", "description": "Responsible for order follow up\u00a0and assist in all sales / shipping\u00a0related matters\nKnowledge in Jewelry field is an advantage\nLiaise with China factory\n2-3 years relevant experience\nProficient in English\nSelf-motivated and able to work independently", "employment_types": ["Contract"], "selling_points": ["2-3 years related working experience", "Immediate available", "Diploma or above"], "locations": ["Tsim Sha Tsui"], "categories": ["Accounting", "Accounting Clerk / Supervisor", "Manufacturing", "Jewelry", "Merchandising & Purchasing", "Procurement / Purchasing / Sourcing"], "post_time": "2021-12-23T02:31:54Z", "salary": {"currency": null, "max": null, "min": null, "period": "monthly", "term": null}, "salary_visible": false, "title_keywords": ["accounting assistant"], "responsibilities": ["liaise with", "shipping"], "requirements": {"degrees": [], "majors": [], "languages": ["english"], "language_level": ["proficient"], "hard_skills": [], "soft_skills": ["self-motivated", "work independently", "responsible"], "languages_combined": [{"language": "english", "language_level": ["proficient"]}]}, "experience_required": {"duration": ["2-3 years"], "field": ["relevant experience"]}}, {"job_id": "100003008997162", "location_code": "hk", "company": "Aaron Shum Jewelry Limited", "job_title": "Sales Administrator", "description": "Job description\n\nMaintain the costing and pricing database;\nHandle data input, filing and update the ERP system in timely and accurate manner;\nProvide the back-end services to the Purchasing Department;\nOther ad-hoc tasks as required.\n\nRequirements\n\nDiploma or above with minimum 2 years solid working experience in trading and manufacturing industry;\nWith experience in operating ERP system is a bonus;\u00a0\nWith Accounting LCCI level 2;\nProficiency in written English, Chinese;\nImmediate available is preferred.\nWelcome to explore more on our website at www.cnkjewellery.com", "employment_types": ["Full Time", "Permanent"], "selling_points": ["Sales Administrator, order follow up", "Jewelry, watch", "5 days work"], "locations": ["Hung Hom"], "categories": ["Manufacturing", "Jewelry", "Sales, CS & Business Devpt", "Account Servicing", "Sales Administration"], "post_time": "2021-12-23T10:12:37Z", "salary": {"currency": null, "max": null, "min": null, "period": "monthly", "term": null}, "salary_visible": false, "title_keywords": ["sales administrator"], "responsibilities": ["ad-hoc tasks", "maintain", "data input", "database"], "requirements": {"degrees": ["diploma or above"], "majors": ["manufacturing"], "languages": ["english", "chinese"], "language_level": ["proficiency"], "hard_skills": ["erp system"], "soft_skills": [], "languages_combined": [{"language": "english", "language_level": ["proficiency"]}, {"language": "chinese", "language_level": []}]}, "experience_required": {"duration": ["minimum 2 years"], "field": ["erp system", "trading", "manufacturing industry"]}}, {"job_id": "100003008986158", "location_code": "hk", "company": "C&K Jewellery Limited", "job_title": "Clerk", "description": "Job description\n\nHandle data input, filing and update the ERP system in timely and accurate manner;\nCommunicate with courier services;\nProvide the back-end services to the Purchasing Department;\nOther ad-hoc tasks as required.\n\nRequirements\n\nTeritary education with minimum 2 years solid working experience in trading and manufacturing industry;\nWith experience in operating ERP system is a bonus;\u00a0\nWith Accounting LCCI level 2;\nProficiency in written English, Chinese;\nImmediate available is preferred.\nWelcome to explore more on our website at www.cnkjewellery.com", "employment_types": ["Contract"], "selling_points": ["2-3 years related working experience", "Immediate available", "Teritary education"], "locations": ["Tsim Sha Tsui"], "categories": ["Manufacturing", "Jewelry", "Transportation & Logistics", "Shipping", "Merchandising & Purchasing", "Procurement / Purchasing / Sourcing"], "post_time": "2021-12-20T02:10:58Z", "salary": {"currency": null, "max": null, "min": null, "period": "monthly", "term": null}, "salary_visible": false, "title_keywords": ["clerk"], "responsibilities": ["communicate with", "ad-hoc tasks", "data input"], "requirements": {"degrees": [], "majors": [], "languages": ["english", "chinese"], "language_level": ["proficiency"], "hard_skills": ["erp system"], "soft_skills": [], "languages_combined": [{"language": "english", "language_level": ["proficiency"]}, {"language": "chinese", "language_level": []}]}, "experience_required": {"duration": ["minimum 2 years"], "field": ["erp system", "trading", "manufacturing industry", "education"]}}, {"job_id": "100003008995932", "location_code": "hk", "company": "Fook Tai Jewellery Group Limited", "job_title": "\u73e0\u5bf6\u71df\u696d\u54e1", "description": "\n\u2022 \u8ca0\u8cac\u73e0\u5bf6\u92b7\u552e\u5de5\u4f5c\n\u2022 \u63d0\u4f9b\u512a\u8cea\u9867\u5ba2\u670d\u52d9\n\u2022 \u5354\u52a9\u4e00\u822c\u5e97\u52d9\u904b\u4f5c\n\u2022 \u4e2d\u4e94\u6216\u4ee5\u4e0a\u7a0b\u5ea6\n\u2022 \u51773\u5e74\u6216\u4ee5\u4e0a\u76f8\u95dc\u7d93\u9a57\u53ef\u8003\u616e\u66f4\u9ad8\u8077\u4f4d\n\u2022 \u5177\u826f\u597d\u92b7\u552e\u6280\u5de7\u53ca\u670d\u52d9\u614b\u5ea6\n\u5206\u5e97\u5730\u5740:\u8343\u7063\u3001\u6df1\u6c34\u57d7\u3001\u9577\u6c99\u7063\u3001\u4e0a\u6c34\u3001\u89c0\u5858\n\u9762\u8a66\u5730\u5740:\u4f50\u6566\u5ee3\u6771\u9053513\u865f\u7389\u5668\u4ea4\u6613\u5ee3\u58341\u6a1311\u5ba4\n\u6709\u610f\u8005\u8acb\u6309Apply Now\u7533\u8acb ,\u6216\u76f4\u63a5\u81f4\u96fb\u6797\u5c0f\u59d0\u9810\u7d04\u9762\u8a66,\u96fb\u8a712543-0918\u3002\n\u85aa\u916c: \u6bcf\u6708 $13,000.00 \u8d77\n\n", "employment_types": ["Full Time"], "selling_points": [], "locations": ["Not Specified"], "categories": ["Manufacturing", "Jewelry", "Marketing / Public Relations", "Public Relations - Event Management", "Sales, CS & Business Devpt", "Retail Sales"], "post_time": "2021-12-23T05:10:24Z", "salary": {"currency": null, "max": null, "min": null, "period": "monthly", "term": null}, "salary_visible": false, "title_keywords": [], "responsibilities": [], "requirements": {"degrees": [], "majors": [], "languages": [], "language_level": [], "hard_skills": [], "soft_skills": [], "languages_combined": []}, "experience_required": {"duration": [], "field": []}}]