[{"job_id": "100003009051837", "location_code": "hk", "company": "LAWSGROUP", "job_title": "Factory Manager (Stationed in Overseas)", "description": "Responsibilities:\n\nLead the production line to optimize the production efficiency;\nResponsible for formulating supply chain strategy and perform cost management or processing procurement orders\nReview the production capacity regularly to ensure the product deliver on time;\nMonitor the workflow of the production to ensure the operation run smoothly;\nContinuously improve the product quality to reduce the food risk;\nCommunicate with the team and management to reach the common goal;\nFormulate and implement the standard the operation procedure;\nWork with internal parties i.e: sales team to coordinate delivery schedule or stock arrangement;\nPerform ad hoc duties\n\nRequirements:\n\nBachelor's degree in relevant disciplines\nWith at least 8 years experience in food and beverage manufacturing, not less than 5 years experience in factory management\nWork experience in large-scale of food and beverage manufacturing is preferred\nEquipping with HACCP / ISO quality management standards qualifications\nStrong interpersonal skill and good leadership skills Result-oriented, detailed mined and organized\nProactive, detail-minded and willing to take up challenges\nProficient in PC application including Chinese word processing\nGood command of spoken and written English and Chinese / Cantonese\nLess experience will be considered as Assistant Factory Manager;\nImmediate available is preferable", "employment_types": ["Full Time", "Permanent"], "selling_points": ["Degree holder with 8 yrs relevant work exp.", "Solid exp. in garment manufacturing factory", "Stationed in Overseas is required"], "locations": ["Overseas"], "categories": ["Manufacturing", "Garment / Textile", "Manufacturing Management", "Product Development / Management"], "post_time": "2022-01-17T01:22:45Z", "salary": {"currency": null, "max": null, "min": null, "period": "monthly", "term": null}, "salary_visible": false, "title_keywords": ["factory manager"], "responsibilities": ["communicate with", "ad hoc duties", "cost", "management", "review", "quality", "monitor", "coordinate", "delivery schedule", "sales team", "internal parties"], "requirements": {"degrees": ["degree", "bachelor"], "majors": [], "languages": ["cantonese", "english", "chinese"], "language_level": ["good command", "proficient"], "hard_skills": ["pc", "chinese word processing"], "soft_skills": ["detail-minded", "organized", "leadership skills", "interpersonal skill", "proactive", "result-oriented", "detailed"], "languages_combined": [{"language": "cantonese", "language_level": ["good command"]}, {"language": "english", "language_level": ["good command"]}, {"language": "chinese", "language_level": ["good command", "proficient"]}]}, "experience_required": {"duration": ["at least 8 years", "5 years"], "field": ["food", "management", "manufacturing"]}}, {"job_id": "100003009053250", "location_code": "hk", "company": "Tai Nam Industrial Co Ltd", "job_title": "Engineering Manager", "description": "Responsibilities:\n\nResponsible for overall operation and logistic arrangement for factory (Cut & Sewn Knit)\nMonitor and review the overall budget for P&L\nReview and prepare production plan for factory\nReview and implement policies & operational procedures ensure compliance of the Corporate policies\nAd-hoc duties upon request.\n\nRequirements:\n\nDegree holder in Textile Technology / Clothing or equivalent qualification\nStrong solid experience in all-round factory experience in garment manufacturing environment is a MUST\nAt least 8 years relevant experience in manufacturing industry including 3 years at managerial level\nSelf-motivated, result-oriented and able to work under pressure\nExcellent interpersonal skills and project management skills\nExcellent command in both spoken and written English and Chinese including Mandarin\nCandidate with less experience will be considered as Assistant Factory Manager\n\n\nWe offer attractive remuneration package to the right candidate. Interested parties please click the \"APPLY NOW\" button below and send your application together with a detailed resume including current & expected salary and availability to Human Resources Department.\nCompany website:\u00a0https://www.lawsgroup.com/\n(Data collected will be treated in strict confidence and used for recruitment purpose only)", "employment_types": ["Full Time", "Permanent"], "selling_points": [], "locations": ["Kwai Fong"], "categories": ["Engineering", "Manufacturing & Production", "Mechanical", "Manufacturing", "Manufacturing Management"], "post_time": "2022-01-17T06:32:04Z", "salary": {"currency": null, "max": null, "min": null, "period": "monthly", "term": null}, "salary_visible": false, "title_keywords": ["engineering manager"], "responsibilities": ["policies", "review", "monitor", "p&l", "logistic arrangement", "ensure compliance", "operational procedures", "plan", "ad-hoc duties", "overall budget"], "requirements": {"degrees": ["degree holder"], "majors": [], "languages": ["english", "chinese", "mandarin"], "language_level": ["excellent"], "hard_skills": ["project management"], "soft_skills": ["self-motivated", "project management skills", "interpersonal skills", "result-oriented", "work under pressure"], "languages_combined": [{"language": "english", "language_level": ["excellent"]}, {"language": "chinese", "language_level": ["excellent"]}, {"language": "mandarin", "language_level": ["excellent"]}]}, "experience_required": {"duration": ["at least 8 years", "3 years"], "field": ["garment", "managerial", "manufacturing", "relevant experience", "manufacturing industry"]}}, {"job_id": "100003009052381", "location_code": "hk", "company": "Simatelex Manufactory Co., Ltd.", "job_title": "Production Manager (Shenzhen Stationed)", "description": "Job Responsibilities\n\nTake active roles in providing technical support and feasibility studies for new product launch;\nActively involved in line set up, layout planning and workers\u2019 training plan;\nContinue improvement on output and efficiency;\nMonitor the day-to-day operations of the plant;\u00a0\nReview and improve operational management for all levels in the plant to achieve effectiveness and efficiency;\nEnsure a smooth plant operation that complies with internal policies and customer requirements;\nResponsible for overseeing assembly and industrial engineering department;\nTrouble shooting, problem solving, process improvement, automation, product testing, etc.;\nProvide support to other departments in customers audit and enquiry;\nHandle ad hoc assignments as require.\n\nJob Requirements\n\nUniversity graduate in Production Management / Mechanical Engineering or Industrial engineering or related discipline;\nA minimum of 10 years working experience of which at least 5 years in managing a sizeable PRC factory and managing people; experience in household electrical appliance is an advantage;\nFast pace, flexible mindset, willing to learn;\nExcellent communication skills with fluency in spoken and written English, Cantonese and Mandarin;\nStrong problem solving, influencing skills, communication and people management skills;\nPreferred to have knowledge and experience in LEAN manufacturing;\nStrong knowledge in fixture and equipment;\nStation in PRC Dongguan plant is required.\n\nInterested parties, please send your full resume stating your expected salary and date of availability to the Human Resources Department\u00a0for application.\u00a0 We offer successful candidates an attractive remuneration packages (Basic salary + Bonus + Medical Scheme) and the opportunity to work in a dynamic and exciting environment.\u00a0 (Data collected will be used for recruitment purpose only)", "employment_types": ["Full Time", "Permanent"], "selling_points": [], "locations": ["Others - China"], "categories": ["Engineering", "Manufacturing & Production", "Manufacturing", "Manufacturing Management", "Others"], "post_time": "2022-01-17T02:54:26Z", "salary": {"currency": null, "max": null, "min": null, "period": null, "term": null}, "salary_visible": false, "title_keywords": ["production manager"], "responsibilities": ["management", "provide support", "technical support", "policies", "review", "day-to-day operations", "monitor", "audit", "testing", "ad hoc assignments", "plan", "planning"], "requirements": {"degrees": ["university graduate"], "majors": ["engineering", "mechanical engineering"], "languages": ["cantonese", "english", "mandarin"], "language_level": ["fluency", "excellent"], "hard_skills": ["problem solving", "lean"], "soft_skills": ["flexible", "communication skills", "willing to learn", "communication", "problem solving"], "languages_combined": [{"language": "cantonese", "language_level": ["fluency", "excellent"]}, {"language": "english", "language_level": ["fluency", "excellent"]}, {"language": "mandarin", "language_level": ["fluency", "excellent"]}]}, "experience_required": {"duration": ["at least 5 years", "minimum of 10 years"], "field": ["manufacturing"]}}, {"job_id": "100003009051718", "location_code": "hk", "company": "Advance Thermo Control Ltd", "job_title": "General Manager", "description": "Lead the team and oversee the functions of production planning and material control\n\nMaterial planning from control of material flow to optimisation of work processes and production capacity\n\nClient Details\n\nMy client is Hong Kong top manufacturer and is looking for Production and Materials Planning Manager\n\nDescription\n\nLead the team and oversee the functions of production planning and material control\nResponsible for capacity planning and overall production scheduling based on demand from forecast to ensure supply capacity copes with forecast\nMaterial planning from control of material flow to optimisation of work processes and production capacity\nEnsures materials are ordered and in stock to meet company requirements, while maintaining acceptable inventory levels\nControl expenses and production efficiency through proper manpower scheduling and production plan\nTo perform analysis on work flow and production efficiency, collect and maintain accurate records and support month-end reporting;\n\nProfile\n\nBachelor or above, major in industrial engineering, supply chain, or related discipline is preferable;\nOver 6 - 8 years of solid relevant working experiences in similar position in production and material planning\nDetail minded, multi-tasks, strong sense of responsibility\nGood command of communication skill\n\nJob Offer\n\nInterested applicant please send me your resume to Marcochong@michaelpage com hk OR you can contact Marco @ 52909990", "employment_types": ["Full Time"], "selling_points": ["Degree in Manufacturing/Engineering/Management", "Medical insurance", "US base company"], "locations": ["Others - China"], "categories": ["Manufacturing", "Manufacturing Management", "Management", "Top Executives (CEO, CFO, CTO, GM, MD etc.)"], "post_time": "2022-01-16T21:51:06Z", "salary": {"currency": null, "max": null, "min": null, "period": "monthly", "term": null}, "salary_visible": false, "title_keywords": ["general manager"], "responsibilities": ["reporting", "control", "maintaining", "inventory", "expenses", "production planning", "analysis", "month-end", "communication", "scheduling", "maintain", "contact", "forecast", "plan", "planning"], "requirements": {"degrees": ["bachelor"], "majors": ["engineering"], "languages": [], "language_level": [], "hard_skills": ["marco", "analysis"], "soft_skills": ["multi-tasks", "responsible", "sense of responsibility", "communication skill", "accurate"], "languages_combined": []}, "experience_required": {"duration": ["6 - 8 years"], "field": ["planning"]}}, {"job_id": "100003009054654", "location_code": "hk", "company": "Hop Hing Management Company (Hong Kong) Limited", "job_title": "Senior Production / Manufacturing Engineer (Ref. No.: SE/1701/22)", "description": "Responsibilities:\n\nPlan and lead project from concept to production\nMonitor project progress and status\nDesign mechanism based on specification from customer\nLiaise with customers on design, cost, materials / components selection\nResponsible for product functionality and quality issues\nSupport sales teams in technical issue\nMaintain project development milestone on schedule\nDevelop and manage project plans and time lines within the scope of the new product development guidelines\nPlan, manage and control all project engineering processes for production and meet product safety standard\nSupervise Engineering Team\nCandidate with more experience will be considered as Senior Engineering Manager\n\nQualifications:\n\nDegree in Mechanical, Manufacturing Engineering or equivalent\nMinimum 5 yrs working experience in product development with at least\u00a02 yrs at management level\nExperience in Toys design and manufacturing process\nExcellent PC skills in MS Word and Excel\nProficiency in writing, fluent in spoken English and Mandarin\nGood interpersonal skill and able to communicate with customer\nWork and travel PRC frequently\n\nWe offer attractive remuneration package to the successful candidates. Interest parties, please send your application and full resume stating current and expected salary as well as date available to the Human Resources Department via email to HR Manager.\n\nWe are an equal opportunities employer. Personal data collected will be used for employment purpose only and all personal data of unsuccessful application will be destroyed within 6 months.", "employment_types": ["Full Time"], "selling_points": ["Optimize production line with efficiency & quality", "Minimum 5 years solid experience", "Trouble shooting & process improvement"], "locations": ["Yuen Long"], "categories": ["Engineering", "Engineering Project Management", "Manufacturing & Production", "Manufacturing", "Manufacturing Management"], "post_time": "2022-01-17T10:25:06Z", "salary": {"currency": null, "max": null, "min": null, "period": "monthly", "term": null}, "salary_visible": false, "title_keywords": ["engineer"], "responsibilities": ["communicate with", "cost", "control", "monitor project progress", "management", "guidelines", "quality", "teams", "design", "develop", "maintain", "schedule", "plan", "liaise with", "plans"], "requirements": {"degrees": ["degree"], "majors": ["manufacturing", "engineering"], "languages": ["english", "mandarin"], "language_level": ["proficiency", "fluent"], "hard_skills": ["excel", "pc skills", "ms word"], "soft_skills": ["responsible", "interpersonal skill"], "languages_combined": [{"language": "english", "language_level": ["proficiency", "fluent"]}, {"language": "mandarin", "language_level": ["proficiency", "fluent"]}]}, "experience_required": {"duration": [], "field": ["toys", "management", "manufacturing", "engineering", "design", "product development"]}}, {"job_id": "100003009051965", "location_code": "hk", "company": "OPC Manufacturing Ltd", "job_title": "Production Leader (Engineering Background, fast track to supervisor)", "description": "\u8077\u8cac:\n\n\u4f9d\u64da\u751f\u7522\u9700\u6c42\u78ba\u4fdd\u539f\u6599\u53ca\u7269\u6599\u4f9b\u61c9\u6b63\u5e38\n\u6839\u64da\u8ca8\u7269\u3001\u5546\u54c1\u7684\u5eab\u5b58\u91cf\uff0c\u898f\u5283\u63a5\u6536\u7269\u6599\uff08\u6cb9\u6599\u53ca\u5305\u6750\uff09\u5de5\u4f5c\u8a08\u5283\n\u8655\u7406\u539f\u6599/\u5305\u6750\u5ef6\u9072\u5230\u8ca8/\u8b8a\u66f4\u7684\u4f9b\u61c9\u554f\u984c\n\u9032\u884c\u9a57\u6536\u4f5c\u696d\uff0c\u78ba\u8a8d\u8ca8\u54c1\u7684\u54c1\u8cea\u548c\u898f\u683c\n\u5009\u5b58\u7ba1\u7406\u53ca\u7d71\u7c4c\u76e4\u9ede\u5de5\u4f5c\n\u4f9b\u61c9\u5546\u4f86\u8ca8\u7570\u5e38\u554f\u984c\uff08\u55ae\u64da\u3001\u6279\u6b21\u3001\u5668\u5177\u3001\u5b89\u5168\u7b49\uff09\u8655\u7406\uff0c\u4f86\u8ca8\u7570\u5e38\u554f\u984c\u8003\u6838\n\u6e9d\u901a\u5354\u8abf\u8de8\u90e8\u9580\u7269\u6599\u5de5\u4f5c\n\n\u5de5\u4f5c\u8981\u6c42:\n\n\u5c08\u4e0a\u6559\u80b2\uff1a\u6587\u6191/\u8b49\u66f8\n5\u5e74\u76f8\u95dc\u5de5\u4f5c\u7d93\u9a57\uff0c\u5305\u62ec2\u5e74\u7ba1\u7406\u7d93\u9a57\uff0c\u6709\u7269\u6599/\u63a1\u8cfc\u5de5\u4f5c\u7d93\u9a57\u512a\u5148\n\u826f\u597d\u7cb5\u8a9e; \u4e00\u822c\u666e\u901a\u8a71\uff1b\u61c2\u8b80\u5beb\u4e2d\u82f1\u6587\uff0c\u5177\u96fb\u8166\u64cd\u4f5c\u77e5\u8b58\n\u66fe\u65bc\u98df\u54c1\u5ee0/\u85e5\u5ee0\u5de5\u4f5c\u3001\u8a8d\u8b58ISO9001\u53caISO22000\u512a\u5148\n\u6709\u8cac\u4efb\u611f\u3001\u4e3b\u52d5\u53ca\u523b\u82e6\u8010\u52de\n\u9700\u8981\u52a0\u73ed\u53ca\u9ad4\u529b\u52de\u52d5\n\n\u672c\u516c\u53f8\u63d0\u4f9b\u5b8c\u5584\u7684\u85aa\u916c\u53ca\u798f\u5229\u8a08\u5283\uff0c\u6709\u610f\u61c9\u5fb5\u8005\u8acb\u5c07\u5c65\u6b77\u53ca\u8981\u6c42\u5f85\u9047\u96fb\u90f5\u6211\u5011\u6216\u50b3\u771f\u81f326677049\u3002\n\n\u5982\u6b32\u67e5\u8a62\u516c\u53f8\u8a73\u60c5\uff0c\u8acb\u700f\u89bdwww.lamsoon.com\u3002\n\n(\u6309\u5357\u9806\u9999\u6e2f\u96c6\u5718\u8077\u4f4d\u7533\u8acb\u4eba\u4e4b\u500b\u4eba\u8cc7\u6599\u653f\u7b56\uff0c\u6211\u53f8\u5c07\u5c0d\u7533\u8acb\u4eba\u63d0\u4f9b\u4e4b\u5168\u90e8\u8cc7\u6599\u7d55\u5c0d\u4fdd\u5bc6\u53ca\u53ea\u4f5c\u62db\u8058\u4e4b\u7528\u3002\u8a73\u60c5\u8acb\u700f\u89bdwww.lamsoon.com\u3002)\n\n\n\u9999\u6e2f\u65b0\u754c\u5927\u57d4\u5de5\u696d\u90a8\u5927\u5bcc\u885721\u865f\u5357\u9806\u5927\u5ec8", "employment_types": ["Full Time", "Permanent"], "selling_points": ["Young and Energetic, with Engineering mindset", "Love Challenge, pushing for improvement", "Good career opportunity"], "locations": ["Tai Po Area"], "categories": ["Engineering", "Engineering Project Management", "Manufacturing & Production", "Manufacturing", "Manufacturing Management"], "post_time": "2022-01-17T01:39:43Z", "salary": {"currency": null, "max": null, "min": null, "period": "monthly", "term": null}, "salary_visible": false, "title_keywords": ["supervisor"], "responsibilities": [], "requirements": {"degrees": [], "majors": [], "languages": [], "language_level": [], "hard_skills": [], "soft_skills": [], "languages_combined": []}, "experience_required": {"duration": [], "field": []}}, {"job_id": "100003009051574", "location_code": "hk", "company": "A.S. Watson Industries", "job_title": "Production Manager", "description": "Manage the production line of a local manufacturer\n\nClient Details\n\nMy client a manufacturer is looking for a production manager to run its entire production line\n\nDescription\n\nEstablishing and monitoring production performance\nArrange and manage the production schedule and communicate with other dept. to ensure the smoothness of operation to meet the production target\nEstablish and review work process within production and make resource could be utilized high effectiveness\nEnsures the operation in compliance with all the rules and regulations which legislated by government authorities\nContinuously improve the product quality to reduce food risk;\nFacility, Machine, Equipment, and Tools maintenance management\nMonitor pre-production preparation and implementation of bulk production by supervision of the production planning control program\n\nProfile\n\nDegree holder in relevant education\nAt least 6 - 8 years of relevant working experience production manufacturing, of which at least 3 years in managerial level\nGood command of written and spoken language skills\nAbility to manage multi-task well in a fast-paced environment\n\nJob Offer\n\nInterested applicant please send me your cv to marcochong@michaelpage com hk OR you can contact me @ 52909990", "employment_types": ["Full Time", "Permanent"], "selling_points": ["Responsible for daily production operations", "Production scheduling and material planning", "Supply sufficient stock & meet sales requirements"], "locations": ["Tai Po Area"], "categories": ["Manufacturing", "Manufacturing Management", "Production Planning / Control", "Quality Assurance, Control & Testing / ISO"], "post_time": "2022-01-16T11:27:28Z", "salary": {"currency": null, "max": null, "min": null, "period": "monthly", "term": null}, "salary_visible": false, "title_keywords": ["production manager"], "responsibilities": ["communicate with", "regulations", "management", "control", "maintenance", "compliance", "review", "monitoring", "quality", "monitor", "implementation", "production planning", "schedule", "contact", "pre-production"], "requirements": {"degrees": ["degree holder"], "majors": [], "languages": [], "language_level": [], "hard_skills": ["make", "maintenance"], "soft_skills": ["fast-paced environment", "multi-task"], "languages_combined": []}, "experience_required": {"duration": ["at least 3 years", "at least 6 - 8 years"], "field": ["managerial", "manufacturing", "relevant working experience"]}}, {"job_id": "100003009054104", "location_code": "hk", "company": "3 Wells Watch Ind Ltd", "job_title": "Marketing & Sales Executive", "description": "Responsible for leading & managing the production engineering team for jig/fixture design, machine maintenance and overseeing the general operation of the department of a factory with over 1,000 staff.\n\nDiploma or above in Production, Manufacturing, Mechanical, Industrial Engineering or related disciplines\n\nAt least 7 years experience at managerial level in manufacturing industry\n\nGood at manufacturing technique of electrical household appliances\n\nWith experience in ISO9001, lean manufacturing and 6-Sigma is preferable\nAggressive, self-motivated, attentive to details and highly quality-conscious\n\nGood command of both English and Chinese\nCandidates with less experience will be considered as Assistant\u00a0Production Manager (Shenzhen Stationed)\n\nWe offer\u00a0attractive remuneration package including 5-day work, bank holidays, group medical insurance etc to the right candidates. Interested parties please send your full resume including expected salary and date available to Human Resources Department by clicking \"Apply Now\" button.\n\nFor more details, please visit our web-site at www.simatelex.com.hk", "employment_types": ["Full Time"], "selling_points": [], "locations": ["Kwai Fong"], "categories": ["Manufacturing", "Manufacturing Management"], "post_time": "2022-01-17T08:23:44Z", "salary": {"currency": null, "max": null, "min": null, "period": "monthly", "term": null}, "salary_visible": false, "title_keywords": ["marketing & sales executive"], "responsibilities": ["maintenance", "quality", "design"], "requirements": {"degrees": ["diploma or above"], "majors": ["related disciplines", "manufacturing", "engineering"], "languages": ["english", "chinese"], "language_level": ["good command"], "hard_skills": ["lean", "maintenance"], "soft_skills": ["self-motivated", "attentive to details", "responsible"], "languages_combined": [{"language": "english", "language_level": ["good command"]}, {"language": "chinese", "language_level": ["good command"]}]}, "experience_required": {"duration": ["at least 7 years"], "field": ["managerial", "manufacturing", "manufacturing industry"]}}, {"job_id": "100003009052305", "location_code": "hk", "company": "GrammyTech Ltd", "job_title": "Quality Director/ Senior Quality Manager (China Based)", "description": "1. Degree in Manufacturing/ Engineering / Management study\n2. At least 10 years experience in managerial position and electrical appliance industry\n3.\u00a0Monitor all department in the organization including factory, engineering, sales, purchasing and shipping. Especially to assist the Engineering to complete projects in a timely basis.\n4. Develop and implement business plan for profitability\u00a0\n5. Assist in budget preparation and expense management activities.\n6. Evaluate the effectiveness of marketing program and recommend improvements.\n7. Develop strategies to improve overall quality and productivity.\n8. Generate business, cost and employee reports to management.\n9. Schedule regular team meetings to discuss about business updates, issues and suggestions\u00a0\n10. Respond to employee concerns in timely manner.\n11. Provide direction and guidance to employees in their assigned job duties.\n12. Determine staffing requirements and ensure that office positions are filled promptly.\n13. Assist in employee recruitment, training, performance evaluation, promotion and termination.\n14. Manage administrative,logistical, human resources and accounting services to support company operation\n15. Station at China factory mainly and HK office depend on job requirement.\n\n", "employment_types": ["Full Time", "Permanent"], "selling_points": ["Automotive Products", "Industrial Products", "Medical Products"], "locations": ["Others - China"], "categories": ["Engineering", "Manufacturing & Production", "Manufacturing", "Manufacturing Management", "Quality Assurance, Control & Testing / ISO"], "post_time": "2022-01-17T02:42:38Z", "salary": {"currency": null, "max": null, "min": null, "period": "monthly", "term": null}, "salary_visible": false, "title_keywords": ["quality manager", "director"], "responsibilities": ["guidance", "management", "shipping", "develop strategies", "cost", "provide direction", "budget", "monitor", "quality", "develop", "evaluate", "reports", "schedule", "recruitment", "evaluation", "business plan"], "requirements": {"degrees": ["degree"], "majors": ["manufacturing", "engineering"], "languages": [], "language_level": [], "hard_skills": [], "soft_skills": ["timely"], "languages_combined": []}, "experience_required": {"duration": ["at least 10 years"], "field": ["managerial"]}}, {"job_id": "100003009051000", "location_code": "hk", "company": "Lucky Bell Plastic Factory Ltd", "job_title": "Deputy General Manager (Station in India)\u901a\u95dc\u5f8c\u5373\u8d77\u7a0b\u99d0\u5370\u5ea6", "description": "Responsibilities:\n\n\nSetting up and balancing automatic production lines\nDevelop and evaluate production processes and methods to improve productivity\nOptimize existing process control of production line to maintain and improve reliability, consistency efficiency and quality in operations\nTrouble shooting, problem solving, process improvement, automation, product testing, etc\nResponsible for spare parts management and production line optimization\u00a0\nWork with the engineering team for equipment and facilities maintenance\nParticipate in new project development\nRequirements:\u00a0\n\n\nHigher Diploma/ Degree holder in Manufacturing Engineering or related discipline\nMinimum 5 years solid experience in manufacturing process control and automation\nProficient in PC applications including MS Office and AutoCad\nAble to work independently, hardworking, strong problem solving skills\nExperience in industrial control, PLC and food manufacturing would be advantage\nPossession of valid Hong Kong driving licence (code 1) and Electrician Grade A would be advantages\n\n\n\nInterested parties, please email detail resume and expected salary email to the Human Resources Department\u00a0(Please quote the reference no.).\n\nData collected will be treated in strictly confidential and in used for recruitment purposes only.", "employment_types": ["Full Time"], "selling_points": [], "locations": ["Overseas"], "categories": ["Manufacturing", "Manufacturing Management", "Management", "Top Executives (CEO, CFO, CTO, GM, MD etc.)"], "post_time": "2022-01-14T23:46:35Z", "salary": {"currency": null, "max": null, "min": null, "period": "monthly", "term": null}, "salary_visible": false, "title_keywords": ["general manager"], "responsibilities": ["control", "management", "maintenance", "operations", "quality", "develop", "evaluate", "testing", "maintain"], "requirements": {"degrees": ["diploma", "degree holder"], "majors": ["manufacturing", "engineering"], "languages": [], "language_level": [], "hard_skills": ["plc", "pc applications", "hong kong driving licence", "code", "problem solving skills", "ms office", "autocad"], "soft_skills": ["work independently", "problem solving skills", "hardworking"], "languages_combined": []}, "experience_required": {"duration": ["minimum 5 years"], "field": ["food manufacturing", "manufacturing"]}}, {"job_id": "100003009047912", "location_code": "hk", "company": "", "job_title": "Vice President of Manufacturing", "description": "Summary\n\nLidl are hiring a\u00a0Manufacturing Excellence Specialist for our production and quality control\u00a0team. The successful candidate will ensures that factories/Mills are evaluated fairly and ethically, also support factories/Mills that do not meet our internal/ legal minimum requirements via monitoring on Corrective Action Plans, conducting the follow ups and re-assessment.\n\nWhat will you do?\n\n\u2022\u00a0\u00a0 \u00a0Ensure all FCE (Factory Social Compliance Evaluations) are in line with Lidl Asia defined SOP\u2019s\n\n\u2022\u00a0\u00a0 \u00a0Assist in development of Factory Evaluation plans and schedules. Communicate with the Shenzhen booking team to ensure all FCEs are arranged and conducted in line with the agreed company timelines and ensure CAPs are closed off.\n\n\u2022\u00a0\u00a0 \u00a0Conduct FCE (Factory Social Compliance Evaluation) of Lidl Asia\u2019s supplier base for factories/Mills to ensure they comply to Lidl\u2019s C&S (Compliance & Sustainability) requirements, inclusive of International & local labor regulations/ applicable laws.\n\n\u2022\u00a0\u00a0 \u00a0Review and verify the Critical Non-Compliance (CNC) found during an ongoing audit, by the ME audit team, authorized agencies or assigned 3rd parties.\n\n\u2022\u00a0\u00a0 \u00a0Perform the FCE audit report review, analyze and report compliance discrepancies and \u00a0follow up with ME audit team and authorized agencies or assigned 3rd parties.\n\n\u2022\u00a0\u00a0 \u00a0Perpare the FCE audit report to summarize the evaluation result, inclusive of non-compliance issues \u00a0and share internally to all internal stakeholders (Sourcing, Merchandising and Production) for new FCE assessments and Existing factories.\n\n\u2022\u00a0\u00a0 \u00a0Ensure all FCE data are accurate and updated in the LUP system by the Shenzhen booking team after completion of the latest compliance evaluations.\n\n\u2022\u00a0\u00a0 \u00a0 Prepare FCE data for the monthly/Quartely report.\n\n\u2022\u00a0\u00a0 \u00a0Monitor the CAP status and support factories deemed not meeting our evaluation criteria via CAPs, follow up meetings and or discussions and re-audits.\n\n\u2022\u00a0\u00a0 \u00a0Communicate with Lidl Asia Sourcing and Merchandizing teams, keep them up-to-date with factory compliance status, flag critical non-complaince issues immediately to the Sourcing teams to ensure they are updated on the social compliance risks in their supply base and work out a solution in a collaborative manner.\n\n\u2022\u00a0\u00a0 \u00a0Conduct Shadow audits when required to ensure integrity of Auditing program\n\n\u2022\u00a0\u00a0 \u00a0Prepare the notification letter and send out pre-alert notification letter to all internal stakeholders and Regulartory Compliance team\n\n\u2022\u00a0\u00a0 \u00a0Support Senior ME Manager in conducting process & system audits and make continual improvements in protocols/work procedures.\n\n\u2022\u00a0\u00a0 \u00a0Support Senior ME Manager in the creation of standard work documentation, visual work instructions and training material.\n\n\u2022\u00a0\u00a0 \u00a0Support in system upgrade and development to ensure end-state solutions meet all users\u2019 requirements in support of business strategic goals and objectives.\n\n\u2022\u00a0\u00a0 \u00a0Support in special investigation case or other tasks requested by Regulatory Compliance team\n\n\u2022\u00a0\u00a0 \u00a0Support in Monitoring Day to Day data management (CBX/LUP/DE) Liaise with relevant department and sourcing team for Factory Registration Form follow up.\n\n\u2022\u00a0\u00a0 \u00a0Monitor and ensure the distribution and communicate company Guidelines and Requirements to factories when required\n\nWhat will you need?\n\n\u2022\u00a0\u00a0 \u00a0Minimum Bachelor\u2019s degree holder in related field\n\n\u2022\u00a0\u00a0 \u00a0At least 3-5 years relevant experience in a sizeable organization with social compliance, BSCI/ SA8000, Better Work Factory, ACCORD or equivalent standards is a must\n\n\u2022\u00a0\u00a0 \u00a0leadership experience and preferably with remote team(s); leading remote team experience preferred.\n\n\u2022\u00a0\u00a0 \u00a0Experience with manufacturing environment, auditing and remediation\n\n\u2022\u00a0\u00a0 \u00a0Profound understanding on environment, health & safety regulations and international labour standard\n\n\u2022\u00a0\u00a0 \u00a0Sensitive to cultural differences with country / regional coverage\n\n\u2022\u00a0\u00a0 \u00a0Strong communication, interpersonal and problem-solving skills, able to interact with all levels\n\n\u2022\u00a0\u00a0 \u00a0Autonomous, proactive, detailed and commercially minded\n\n\u2022\u00a0\u00a0 \u00a0High degree of work ethics and integrity\n\n\u2022\u00a0\u00a0 \u00a0Good command of both in spoken & written English, \u00a0in spoken Cantonese and Mandarin.\n\n\u2022\u00a0\u00a0 \u00a0Good knowledge of Microsoft applications PowerPoint, Word & Excel\u00a0\n\n\u2022\u00a0\u00a0 \u00a0ISO14000 experience is also beneficial\n\n\u2022\u00a0\u00a0 \u00a0Willing to travel occasionally\n\nWhat do we offer?\n\nWe are dedicated to fostering a family-friendly culture and work environment and we are an equal opportunities employer and welcome applications from all candidates with the required skills and experience.\n\nMarket Leading Remuneration Package:\n\nDouble pay and discretionary bonus\n\nChoice of MPF provider\n\nLife Insurance\n\nMedical Insurance\n\n\n\n\u00a0\n\nSupportive Environment:\n\nRental re-imbursement scheme\n\nFlexible work arrangements\n\nIn-house training courses\n\nTraining sponsorship scheme\n\nHealth Check\n\nVision Check\n\nSupporting your child's education with advice from a leading education consultant\n\n\n\n\u00a0\n\nWork-Life Balance:\n\n5 day week\n\nCompetitive Annual Leave\n\nCharity, Community and Sporting Events", "employment_types": ["Full Time", "Permanent"], "selling_points": ["EMS manufacturing, Bsc degree in electronics,Lean", "ISO audit,Six Sigma,exp managing factories Vietnam", "10 yrs exp in EMS mfg, 5 yrs Plant Mgr exp, SAP"], "locations": ["Others - China"], "categories": ["Engineering", "Electrical / Electronics", "Manufacturing & Production", "Manufacturing", "Manufacturing Management"], "post_time": "2022-01-14T04:13:30Z", "salary": {"currency": null, "max": null, "min": null, "period": "monthly", "term": null}, "salary_visible": false, "title_keywords": ["vice president"], "responsibilities": ["regulations", "data", "schedules", "merchandising", "audit", "communication", "evaluation", "liaise with", "plans", "compliance", "monitor", "teams", "other tasks", "visual", "report", "management", "monitoring", "review", "procedures", "investigation", "booking", "audits", "documentation", "communicate with", "company guidelines", "quality control", "auditing"], "requirements": {"degrees": ["degree", "bachelor", "degree holder"], "majors": [], "languages": ["cantonese", "english", "mandarin"], "language_level": ["good command"], "hard_skills": ["merchandizing", "excel", "data management", "microsoft applications", "word", "powerpoint", "make", "documentation", "problem-solving skills"], "soft_skills": ["proactive", "integrity", "collaborative", "communication", "sensitive to", "autonomous", "problem-solving skills", "accurate", "leadership", "interpersonal", "detailed"], "languages_combined": [{"language": "cantonese", "language_level": ["good command"]}, {"language": "english", "language_level": ["good command"]}, {"language": "mandarin", "language_level": ["good command"]}]}, "experience_required": {"duration": ["at least 3-5 years"], "field": ["manufacturing", "compliance", "relevant experience", "team"]}}, {"job_id": "100003009046656", "location_code": "hk", "company": "Maxim's Caterers Ltd", "job_title": "Assistant Production Manager (Cakes & Bakery Factory)", "description": "Responsible for the day-to-day operation of Production Department\nOversee overall production scheduling and material planning for all production lines\nOversee production lines performance to achieve departmental target\nCoordinate with Procurement, Warehouse and Sales teams to supply sufficient stock and meet sales requirement\nPrepare and control Departmental budget and expense\nAssist new capital investment and project implementation\n\n\u00a0Job Requirement\n\nDegree holder in Engineering or other related disciplines\nMinimum 8years relevant working experience in managing sizeable manufacturing companies, in which 4 years at managerial level. Experience in Food and Beverage and FMCG companies is an added advantage\nStrong leadership and problem-solving skills\nKnowledge in ISO22000 and GMP\nERP or Oracle knowledge is advanced\nEnergetic, well-organized, detail-minded, strong sense of responsibility, able to work independently & multi-task\nGood communication, presentation and interpersonal skill\nGood command of written and spoken English, Chinese and Mandarin\nPC knowledge in MS Excel, Word & PowerPoint and Chinese Processing\n\nWe offer competitive salary, discretionary performance bonus, medical and retirement benefits, free company coach services and excellent career prospects. Please send your resume together with salary expectation via\u00a0APPLY NOW\n\nFor more information, please visit our website at\u00a0www.aswatson.com\n\nAll information provided will be used for recruitment and other employment-related purposes by A.S. Watson & Company Limited (for and on behalf of the A.S. Watson Group of companies). It may be provided to companies/parties authorized to process the information for purposes relating to recruitment, e.g. qualifications assessment.\n\nWith the consent of applicant, all personal data of unsuccessful applicants will be retained for future consideration for two years. Otherwise, all personal data of unsuccessful applicants will be retained for twelve months.\n\nApplication will not be considered if the applicant does not provide all information as requested.\n\nAll information provided will be held in strict confidence.\n\nIf applicant request access to, and to request correction of personal data in relation to the application, please contact our People Department at 2660 1880.", "employment_types": ["Full Time"], "selling_points": ["5 years experience in food production", "Preferably with supervisory experience", "Strong analytical and problem-solving skills"], "locations": ["Tai Po Area"], "categories": ["Hospitality / F & B", "Food & Beverage", "Manufacturing", "Manufacturing Management", "Quality Assurance, Control & Testing / ISO"], "post_time": "2022-01-13T18:54:06Z", "salary": {"currency": null, "max": null, "min": null, "period": "monthly", "term": null}, "salary_visible": false, "title_keywords": ["assistant production manager"], "responsibilities": ["control", "budget", "teams", "coordinate with", "implementation", "website", "communication", "scheduling", "recruitment", "contact", "personal data", "day-to-day operation", "planning"], "requirements": {"degrees": ["degree holder"], "majors": ["related disciplines", "engineering"], "languages": ["english", "chinese", "mandarin"], "language_level": ["good command"], "hard_skills": ["word", "erp", "powerpoint", "ms excel", "problem-solving skills", "pc knowledge", "processing", "oracle"], "soft_skills": ["detail-minded", "work independently", "confidence", "multi-task", "advanced", "responsible", "sense of responsibility", "well-organized", "interpersonal skill", "communication", "problem-solving skills", "energetic", "leadership", "presentation"], "languages_combined": [{"language": "english", "language_level": ["good command"]}, {"language": "chinese", "language_level": ["good command"]}, {"language": "mandarin", "language_level": ["good command"]}]}, "experience_required": {"duration": ["4 years"], "field": ["managerial", "manufacturing", "fmcg", "relevant working experience", "food"]}}, {"job_id": "100003009052451", "location_code": "hk", "company": "Eternity Consultants (HK) Ltd", "job_title": "Assistant Project Manager / Project Manager - Toys", "description": "Major Job Duties\nBe held responsible for Customer meetings & orders follow-ups, co-ordinating with other departments (PRC & HK) for customer inquiries, new projects, orders & all related requests from overseas customers.\nParticipating in local & overseas exhibitions.\u00a0\nWorking with other departments in Shenzhen production plant 2 to 3 days a week (Day trip /\u00a0Own company car transfer back and forth China border & plant)\n\nRequirements :\n\nDegree holder preferable\nAt least 5 years practical experience in marketing & sales field of watch industry and equipped with prominent watch product knowledge\u00a0\nCustomer-oriented with good communications and interpersonal skills.\u00a0\nGood command of written & spoken English, Mandarin & Cantonese\u00a0\nHigh proficiency in computer literacy Eg, Microsoft Office Suite (Outlook, Word, Excel, PowerPoint)\n\nWorking hours : Mon \u2013 Fri : 9:30a.m. \u2013 6p.m.\nWebsite : www.3wells.com\n\nAttractive remuneration package and career prospects including Discretionary Double-pay, Banking Holidays, Free lunch as well as Medical Insurance will be offered to the\u00a0right Candidate. Interested parties please reply with resume stating details of\u00a0qualification, experience, current salary & EXPECTED SALARY.\n\n(All personal data collected would be used for recruitment purpose only)", "employment_types": ["Full Time", "Permanent"], "selling_points": ["5 days, 13 months+bonus, bank medical", "6-8 years in project follow up in toy, plastic", "project follow up"], "locations": ["Not Specified"], "categories": ["Engineering", "Engineering Project Management", "Manufacturing", "Manufacturing Management", "Product Development / Management"], "post_time": "2022-01-17T03:04:12Z", "salary": {"currency": null, "max": null, "min": null, "period": "monthly", "term": null}, "salary_visible": false, "title_keywords": ["assistant project manager", "project manager"], "responsibilities": ["customer inquiries"], "requirements": {"degrees": ["degree holder"], "majors": [], "languages": ["cantonese", "english", "mandarin"], "language_level": ["good command"], "hard_skills": ["excel", "word", "powerpoint", "microsoft office suite", "outlook"], "soft_skills": ["computer literacy", "customer-oriented", "interpersonal skills"], "languages_combined": [{"language": "cantonese", "language_level": ["good command"]}, {"language": "english", "language_level": ["good command"]}, {"language": "mandarin", "language_level": ["good command"]}]}, "experience_required": {"duration": ["at least 5 years"], "field": ["marketing"]}}, {"job_id": "100003009042930", "location_code": "hk", "company": "Wise Ally Holdings Limited", "job_title": "Manager -  Lean Manufacturing (Stationed in Dongguan)", "description": "Responsibilities\n\n\nAct as a leader of Duty Office to ensure a smooth operation and take necessary follow-up action as required\nPerform in-house and airport ramp areas patrolling and report irregularities\nMake decision when handles accidents, irregularities and emergency cases and perform investigations and follow up actions\nServe as the key coordinator to handle flight movement to ensure timely information and service quality\nExecute company\u2019s BCP when applicable to minimize impact on operations\nUnderstand and uphold company quality standards in terms of hygiene, safety and security requirement\nCoordinate transportation service arrangement and answer enquiries from customers\nRequirements\n\nTertiary educated, preferably related to operations or facilities management\nAt least 7 years\u2019 relevant working experience, preferably in airline or transportation industry\nHands-on experience in crisis/risk management, handling of emergency cases, facility management or execution of business continuity plan is an advantage\nHolder of driving license no. 1 or/and 2\nProficiency in MS Office\nGood command of written and spoken English and Chinese\nStrong problem solving and interpersonal skills\n24-hours shift duty is required\nWe offer a competitive remuneration package and a full range of benefits. Interested parties please send\u00a0your resume\u00a0with\u00a0your current and expected salary\u00a0to Head of People,11 Catering Road East, Hong Kong International Airport, Lantau, Hong Kong or by clicking the \"Apply Now\" button\u00a0on or before 10 February 2022.\n\n\nPersonal data collected will be treated in the strictest confidence and only be used for recruitment related purpose. Applicants who do not receive notification for interview within six weeks may consider their application unsuccessful.", "employment_types": ["Full Time", "Permanent"], "selling_points": ["Initiate and manage the MIT", "Create and present LEAN / cost savings analysis", "5-day work, 13th-month salary"], "locations": ["Not Specified"], "categories": ["Manufacturing", "Manufacturing Management", "Production Planning / Control", "Others"], "post_time": "2022-01-12T09:15:28Z", "salary": {"currency": null, "max": null, "min": null, "period": "monthly", "term": null}, "salary_visible": false, "title_keywords": ["manager"], "responsibilities": ["irregularities", "operations", "quality", "coordinate", "hygiene", "security requirement", "report irregularities"], "requirements": {"degrees": [], "majors": [], "languages": ["english", "chinese"], "language_level": ["good command"], "hard_skills": ["no", "airline", "problem solving", "facilities management", "ms office"], "soft_skills": ["problem solving", "hands-on", "interpersonal skills"], "languages_combined": [{"language": "english", "language_level": ["good command"]}, {"language": "chinese", "language_level": ["good command"]}]}, "experience_required": {"duration": ["at least 7 years"], "field": ["risk management", "management", "business", "relevant working experience"]}}, {"job_id": "100003009050238", "location_code": "hk", "company": "Saint Honore Cake Shop Ltd", "job_title": "\u751f\u7522\u4e3b\u7ba1(\u901a\u5bb5\u73ed)", "description": "\u8077\u8cac\uff1a\n\n\u64cd\u4f5c\u751f\u7522\u6a5f\u5668 / \u9810\u5099\u539f\u6599\u00a0\n\u9810\u5099\u751f\u7522\u7269\u6599\uff0c\u914d\u5408\u751f\u7522\u8981\u6c42\n\u7dad\u6301\u751f\u7522\u7dda\u4e4b\u6b63\u5e38\u904b\u4f5c\n\u5165\u8077\u8981\u6c42\uff1a\n\u51771-2\u5e74\u7684\u98df\u54c1\u751f\u7522\n\u85aa\u91d1\u4e36\u798f\u5229\u53ca\u5de5\u4f5c\u6642\u9593\uff1a\n\n\n\u6bcf\u6708$15,000 - $18,000\n\u514d\u8cbb\u7a7f\u68ad\u5df4\u58eb\u670d\u52d9\n\u514d\u8cbb\u5348\u994d\u63d0\u4f9b\n\u914c\u60c5\u82b1\u7d05\n\u52a0\u73ed\u6d25\u8cbc\n\u5728\u8077\u57f9\u8a13\n\u54e1\u5de5\u8cfc\u7269\u512a\u60e0\n\u661f\u671f\u4e00\u81f3\u4e94\uff1a\u4e0a\u53488:15 \u81f3\u4e0b\u53486:20\n\n\u4e0d\u9700\u8f2a\u73ed\n\n\u7533\u8acb\u65b9\u6cd5\n1. \u81f4\u96fb 5545-8814 \u6216\n2. \u6309\u201cApply Now\u201d \u6216\n3. \u5c07\u500b\u4eba\u5c65\u6b77\u90f5\u5bc4\u81f3\u65b0\u754c\u5927\u57d4\u5de5\u696d\u90a8\u5927\u5bcc\u885711-15\u865f \u4eba\u529b\u8cc7\u6e90\u90e8\u6536 \u6216\n4. \u50b3\u771f\u81f32666-6575\n\n\uff08\u7533\u8acb\u4eba\u63d0\u4f9b\u4e4b\u8cc7\u6599\u5c07\u7d55\u5c0d\u4fdd\u5bc6\u53ca\u53ea\u4f5c\u62db\u8058\u7528\u9014\uff09\u00a0", "employment_types": ["Full Time"], "selling_points": ["\u7ba1\u7406\u5de5\u5834\u78ba\u4fdd\u751f\u7522\u6d41\u7a0b\u6309\u6a19\u6e96\u7a0b\u5e8f\u9032\u884c", "5\u5e74\u6216\u4ee5\u4e0a\u98df\u54c1\u5ee0\u751f\u7522\u7dda\u7ba1\u7406\u7d93\u9a57", "\u5de5\u4f5c\u6642\u9593\uff1a21:00 - 6:00 \uff0c\u6bcf\u6708\u4e94\u5929\u4f11\u606f\u65e5"], "locations": ["Kwai Tsing Area"], "categories": ["Manufacturing", "Manufacturing Management", "Product Development / Management", "Production Planning / Control"], "post_time": "2022-01-14T09:59:59Z", "salary": {"currency": null, "max": null, "min": null, "period": null, "term": null}, "salary_visible": false, "title_keywords": [], "responsibilities": [], "requirements": {"degrees": [], "majors": [], "languages": [], "language_level": [], "hard_skills": [], "soft_skills": [], "languages_combined": []}, "experience_required": {"duration": [], "field": []}}, {"job_id": "100003009048261", "location_code": "hk", "company": "Q P Group Holdings Limited", "job_title": "Group Safety Officer", "description": "Responsibilities\n\nMaintains a high standard of loading & unloading procedures and ensures an on-time performance of all flights\nEnsures efficient aircraft handling and smoothen daily operations\nMonitor and enhances subordinates\u2019 working performance\nEnsures the Company\u2019s regulations are followed strictly\nReviews the existing procedures/resources and plans for a better development\nMaintains a harmonic working atmosphere and executes fair-minded measures at all times\nMaintains a good relationship with the customers and provides satisfactory services to minimize complaints\nPerforms ad hoc duties as directed by Loading Services Manager\nRequirements\n\nTertiary Education in Operations Management or related disciplines\nMinimum 5 years of relevant working experience in a supervisory level\nHolder of a valid driving license (No. 1 and 2) is an advantage\nGood communication skills, leadership and interpersonal skills\nAble to work independently under pressure and follow tight schedules\nProficient in PC applications, including MS Word, PowerPoint and Excel\nGood command of English and Chinese, both written and spoken\nShift duty is required\nWe offer a competitive remuneration package and a full range of benefits. Interested parties please send your resume with your current and expected salary to Head of People,11 Catering Road East, Hong Kong International Airport, Lantau, Hong Kong or by clicking the \"Apply Now\" button\u00a0on or before 10 February 2022.\nPersonal data collected will be treated in the strictest confidence and only be used for recruitment-related purposes. Applicants who do not receive notification for an interview within six weeks may consider their application unsuccessful.", "employment_types": ["Full Time", "Permanent"], "selling_points": ["Assure Occupational Health & Safety across Company", "Registered Safety Officer (RSO)", "Fast Growing Listed Company"], "locations": ["Others - China"], "categories": ["Engineering", "Manufacturing & Production", "Manufacturing", "Manufacturing Management", "Others", "Security / Safety Control"], "post_time": "2022-01-15T03:49:52Z", "salary": {"currency": null, "max": null, "min": null, "period": "monthly", "term": null}, "salary_visible": false, "title_keywords": ["group safety officer"], "responsibilities": ["regulations", "ad hoc duties", "procedures", "monitor", "good relationship", "daily operations", "plans"], "requirements": {"degrees": [], "majors": [], "languages": ["english", "chinese"], "language_level": ["good command"], "hard_skills": ["excel", "no", "powerpoint", "pc applications", "ms word"], "soft_skills": ["communication skills", "work independently", "under pressure", "interpersonal skills", "leadership"], "languages_combined": [{"language": "english", "language_level": ["good command"]}, {"language": "chinese", "language_level": ["good command"]}]}, "experience_required": {"duration": ["minimum 5 years"], "field": ["supervisory level", "relevant working experience"]}}, {"job_id": "100003009034439", "location_code": "hk", "company": "Simatelex Manufactory Co., Ltd.", "job_title": "Assistant Factory Manager (Qingyuan Stationed)", "description": "ConnectedGroup is partnering with a multinational consumer electronics company headquartered in the U.S in searching for an Assistant Supply Chain Manager.\n\nResponsibilities:\n\n* Responsible for preparing and analyzing Demand and Supply forecasts to ensure the delivery of highly accurate plans\n* Control and maintain appropriate inventory norms and ensure availability of materials anytime\n* Enhance relationships with suppliers as well as be responsible for negotiation with suppliers\n* Supervise receiving and warehousing procedure\n* Oversee distribution of suppliers in the organization\n\nRequirement:\n\n* Higher diploma or degree holder in Supply Chain or logistic management or related discipline\n* 4+ years' experience in end-to-end supply chain management\n* Good understanding of chemical components OR manufacturing industry is a plus\n* Willing to travel to China regularly", "employment_types": ["Full Time", "Permanent"], "selling_points": [], "locations": ["Others - China"], "categories": ["Engineering", "Manufacturing & Production", "Manufacturing", "Manufacturing Management", "Others"], "post_time": "2022-01-10T03:23:21Z", "salary": {"currency": null, "max": null, "min": null, "period": null, "term": null}, "salary_visible": false, "title_keywords": ["assistant", "factory manager"], "responsibilities": ["warehousing", "control", "inventory", "maintain", "plans"], "requirements": {"degrees": ["diploma", "degree holder"], "majors": [], "languages": [], "language_level": [], "hard_skills": ["plus"], "soft_skills": [], "languages_combined": []}, "experience_required": {"duration": ["4+ years"], "field": ["supply chain", "management"]}}, {"job_id": "100003009050767", "location_code": "hk", "company": "Golden Resources Development Ltd", "job_title": "Assistant Engineering Manager", "description": "\u00a0Deputy General Manager (Station in India)\n\nDegree or above in Manufacturing Engineering or relative area\nMin. 15 years solid experience in toy business(both plastic & electronic toys)\nMin. 7 years experience in management level of sizable toy factories / companies\nMin. 7 years in dealing the manufacturing / engineering & quality issues with\u00a0repute OEM\u00a0toy companies. (no more than 5 years removed from such experience)\nProfessional knowledge in plastic toy\u00a0products manufacturing processes (with good understanding of routine manufacturing management), production planning, store operations and specially in toy products, QA requirement and quality control\u00a0\nFluent English\nStation in India (4-5 breaks back to HK every year, negotiable)\nGood health, able to adapt different environment and culture\nCandidate with much experiences or higher qualification\u00a0may\u00a0be considered as Deputy Managing Director\u00a0\n\u7372\u8058\u5f8c\u66ab\u6642\u5728\u6e2f\u5de5\u4f5c\u76f4\u81f3\u5370\u5ea6\u901a\u95dc\u5f8c\u624d\u555f\u7a0b\u524d\u5f80\u7576\u5730\u99d0\u5ee0", "employment_types": ["Full Time", "Permanent"], "selling_points": [], "locations": ["Tsing Yi"], "categories": ["Engineering", "Manufacturing & Production", "Manufacturing", "Manufacturing Management"], "post_time": "2022-01-14T11:19:29Z", "salary": {"currency": null, "max": null, "min": null, "period": "monthly", "term": null}, "salary_visible": false, "title_keywords": ["assistant engineering manager"], "responsibilities": ["management", "operations", "quality", "production planning", "quality control"], "requirements": {"degrees": ["degree or above"], "majors": ["manufacturing", "engineering"], "languages": ["english"], "language_level": ["fluent"], "hard_skills": ["no"], "soft_skills": [], "languages_combined": [{"language": "english", "language_level": ["fluent"]}]}, "experience_required": {"duration": ["7 years", "5 years", "15 years"], "field": ["toys", "managing director", "management"]}}, {"job_id": "100003009048675", "location_code": "hk", "company": "Gifi Asia Limited", "job_title": "Quality Assurance Engineer (QA) - Toys", "description": "Responsibilities:\nInitiate and manage the MIT (Manufacturing Improvement Team) with plant personnel driving production efficiency, OEE improvement and scrap reduction consistent with manufacturing goals and objectives\nCreate and present LEAN / cost savings analysis to plant management and staff to ensure proper justification of MIT processes\nManage a team of engineers and/or outside vendors for the development and debugging of internally designed machinery\nProvide expert services, inclusive of troubleshooting, upgrade recommendations, and quotes for new equipment, to various manufacturing facilities to evaluate current and new processes\nAssist in ad hoc projects as assigned\n\nRequirements:\u00a0\n\nBachelor degree in manufacturing, industrial, mechanical engineering or related engineering discipline\nMinimum 5 years\u2019 experience on PCBA / Electronic Industry, with minimum 5 years in managerial position and solid experience in Continuous Improvement in Production Process\nMust have the ability to critically analyze production equipment and recognize opportunities for efficiency improvements and cost savings\nSound understanding in LEAN and/or Six Sigma\nSolid experience in Lean Manufacturing Management, or related Continuous Improvement / Manufacturing Process Change management is an advantage\nKnowledge and experience in APQP, PPAP, MSA, PFMEA, 8D, 5 Why, Fishbone diagram, as well as KPI setting\n\nResult-oriented, teamwork, good communication and interpersonal skills\nGood command in both spoken and written English, Cantonese and Mandarin\nStationed in Dongguan China\nOccasional international travel will be required\nImmediately available is highly preferred\n\n*Candidate with more experience will be considered as\u00a0 Senior Manager - Lean Manufacturing\n\n\nWe offer 5-DAY WORK WEEK plus long term career prospect with competitive remuneration package, 13th-month salary, and fringe benefits to the right candidate. Interested parties please apply in full resume including current and expected salary by clicking APPLY NOW.\n\nFor more information, please visit our website:\u00a0 http://www.wiseally.com.hk/\n\nPersonal data collected will be used for recruitment purpose only.", "employment_types": ["Full Time"], "selling_points": ["3 yrs\u2019 experience in QA/ QC", "Flexible working hours, 5 working days", "13 months' salary plus discretionary bonus"], "locations": ["Hung Hom"], "categories": ["Manufacturing", "Manufacturing Management", "Production Planning / Control", "Quality Assurance, Control & Testing / ISO"], "post_time": "2022-01-14T07:01:21Z", "salary": {"currency": null, "max": null, "min": null, "period": "monthly", "term": null}, "salary_visible": false, "title_keywords": ["engineer"], "responsibilities": ["cost", "management", "analysis", "troubleshooting", "evaluate", "ad hoc projects"], "requirements": {"degrees": ["degree", "bachelor"], "majors": ["manufacturing", "engineering", "mechanical engineering"], "languages": ["cantonese", "english", "mandarin"], "language_level": ["good command"], "hard_skills": ["six sigma", "lean", "plus"], "soft_skills": ["teamwork", "result-oriented", "communication and interpersonal skills"], "languages_combined": [{"language": "cantonese", "language_level": ["good command"]}, {"language": "english", "language_level": ["good command"]}, {"language": "mandarin", "language_level": ["good command"]}]}, "experience_required": {"duration": ["minimum 5 years"], "field": ["related", "managerial", "management", "manufacturing"]}}, {"job_id": "100003009048952", "location_code": "hk", "company": "Find Asia Limited", "job_title": "Procurement Manager (Electronics)", "description": "\u5de5\u4f5c\u7bc4\u570d\uff1a\n\n\u7ba1\u7406\u5de5\u5834\n\u78ba\u4fdd\u751f\u7522\u6d41\u7a0b\u6309\u6a19\u6e96\u7a0b\u5e8f\u9032\u884c\n\u78ba\u4fdd\u98df\u54c1\u5b89\u5168\u53ca\u885b\u751f\n\u5206\u914d\u751f\u7522\u5de5\u4f5c\n\u8ca0\u8cac\u76e3\u7763\u53ca\u8a13\u7df4\u54e1\u5de5\n\n\u5de5\u4f5c\u5730\u9ede\uff1a\u8475\u6d8c\u5340\n\n\u5de5\u4f5c\u6642\u9593\uff1a21:00 - 6:00 \uff0c\u6bcf\u6708\u4e94\u5929\u4f11\u606f\u65e5\uff0c\u8f2a\u4f11\n\n\u5de5\u4f5c\u8981\u6c42\uff1a\n\n5\u5e74\u6216\u4ee5\u4e0a\u98df\u54c1\u5ee0\u751f\u7522\u7dda\u7ba1\u7406\u7d93\u9a57\n\u6709\u76f8\u95dc\u98df\u54c1\u885b\u751f\u8b49\u66f8\u512a\u5148\n\u5b78\u6b77\u4e0d\u62d8\uff0c\u826f\u597d\u7cb5\u8a9e\u3001\u61c2\u8b80\u5beb\u4e2d\u6587\u3001\u7565\u61c2\u8b80\u5beb\u82f1\u6587\n\u5177\u5099\u826f\u597d\u6e9d\u901a\u6280\u5de7\uff0c\u6709\u8cac\u4efb\u5fc3\u53ca\u80fd\u7368\u7acb\u5de5\u4f5c\n\n\u54e1\u5de5\u798f\u5229\uff1a\u6bcf\u6708\u734e\u91d1\u3001\u00a0\u81b3\u98df\u6d25\u8cbc\u3001\u901a\u5bb5\u73ed\u6d25\u8cbc\u3001\u8d85\u6642\u6d25\u8cbc\u3001\u914c\u60c5\u6027\u82b1\u7d05\u3001\u91ab\u7642\u798f\u5229\u3001\u5f37\u7a4d\u91d1\u3001\u5bb6\u5ead\u53cb\u5584\u5047\u3001\u54e1\u5de5\u8cfc\u7269\u512a\u60e0\u3001\u826f\u597d\u6649\u5347\u6a5f\u6703\n\n\u61c9\u5fb5\u8005\u53ef\u900f\u904e\u4ee5\u4e0b\u9014\u5f91\u9810\u7d04\u9762\u8a66\u6216\u67e5\u8a62\uff1a\n\n\u96fb\u90f5\u500b\u4eba\u5c65\u6b77\u9023\u540c\u671f\u671b\u85aa\u91d1\u53ca\u53ef\u4e0a\u73ed\u65e5\u671f\u61c9\u5fb5\uff1b\u6216\n\u81f4\u96fb2991 6680\u9810\u7d04\u9762\u8a66\u6216\u67e5\u8a62\uff1b\u6216\n\u5c07(1)\u59d3\u540d\u3001(2)\u61c9\u5fb5\u8077\u4f4d\u3001(3)\u5c45\u4f4f\u5730\u5340\u3001(4)\u806f\u7d61\u96fb\u8a71 (5)\u76f8\u95dc\u5de5\u4f5c\u7d93\u9a57Whatsapp \u52306596 6174\n\n\u6240\u6709\u7533\u8acb\u5747\u7372\u56b4\u683c\u4fdd\u5bc6\u3002\u61c9\u5fb5\u8005\u6240\u63d0\u4f9b\u7684\u500b\u4eba\u8cc7\u6599\u53ea\u4f9b\u4f5c\u62db\u8058\u7528\u9014\u3002\u82e5\u99ae\u6c0f\u96c6\u5718\u7684\u5176\u4ed6\u6210\u54e1\u516c\u53f8\u6709\u985e\u4f3c\u8077\u4f4d\u7a7a\u7f3a\uff0c\u4fdd\u7559\u6b0a\u5229\u5c07\u7533\u8acb\u4eba\u6240\u63d0\u4f9b\u4e4b\u8cc7\u6599\u8f49\u4ea4\u5176\u4ed6\u6210\u54e1\u516c\u53f8\u4f5c\u62db\u8058\u7528\u9014\u3002\n\n\u61c9\u5fb5\u8005\u9700\u63d0\u4f9b\u5145\u8db3\u5b8c\u6574\u7684\u8cc7\u6599\u4ee5\u9032\u884c\u7504\u9078\u3002\u61c9\u5fb5\u8005\u6709\u6b0a\u67e5\u95b1\u53ca\u6539\u6b63\u6240\u63d0\u4f9b\u7684\u500b\u4eba\u8cc7\u6599\uff0c\u8acb\u4ee5\u66f8\u9762\u900f \u904e\u96fb\u90f5\u5411\u4eba\u529b\u8cc7\u6e90\u7d93\u7406\u63d0\u51fa\u3002", "employment_types": ["Full Time", "Permanent"], "selling_points": ["Japanese electronics components manufacturing", "procurement, purchasing", "5 days, Double Pay, Bonus"], "locations": ["Tsuen Wan Area"], "categories": ["Manufacturing", "Manufacturing Management", "Product Development / Management", "Merchandising & Purchasing", "Procurement / Purchasing / Sourcing"], "post_time": "2022-01-15T03:50:06Z", "salary": {"currency": null, "max": null, "min": null, "period": "monthly", "term": null}, "salary_visible": false, "title_keywords": ["manager"], "responsibilities": [], "requirements": {"degrees": [], "majors": [], "languages": [], "language_level": [], "hard_skills": [], "soft_skills": [], "languages_combined": []}, "experience_required": {"duration": [], "field": []}}, {"job_id": "100003009049340", "location_code": "hk", "company": "OKIA Optical Co Ltd", "job_title": "Merchandiser", "description": "Company :\nThe company is a global OEM/ODM contract manufacturer providing turnkey design & manufacturing services since 1989. The company is headquartered in Hong Kong with a global offices in North America and Japan, and manufacturing facilities in China and Vietnam. Example product areas include power supplies, consumer electronics medical devices, and electro-mechanical products and magnetic components. As a family business, the company is currently focused on sustainable growth and embracing new products and technologies. The company is seeking an experienced VP of manufacturing to join their team and lead the company into the future.\nJob Description:\u00a0\nReporting directly to the company\u2019s Managing Director, the Vice President of Manufacturing is responsible for the overall strategy, development, and execution of global production for our client\u2019s company.\n\nProfile:\nYou are an experienced leader and manufacturing professional. You have experience running a mid to large scale EMS facility. You know plastic injection machines, SMT/assembly lines and ISO processes inside and out. You are obsessed about quality and cannot stand inefficient processes. You are a natural leader and strong communicator. You respect people from different cultures, have managed cross-cultural teams, and can work with anyone. You love mentoring and coaching people to reach their full potential.\n\nKey roles and responsibilities:\n1. Day-to-day\n\u2022 Oversee production operations across China and Vietnam factories and ensure manufacturing processes run smoothly, efficiently and on budget\n\u2022 Define and own aggressive KPIs for quality, performance and delivery and cost for all manufacturing activities.\n\u2022 Recommend, evaluate, qualify and deploy production equipment and facilities to support scalable & flexible ramp ups for customer accounts.\n\u2022 Builds best-in-class quality department. Collaborate closely with R&D and supply chain teams to drive quality activities, including manufacturing verification test development, root cause analysis & corrective action.\n\u2022 Collaborate with business development to develop & manage project timelines. Lead or participate in customer meetings or in-person factory audits as necessary to present production capabilities and provide project input.\n\u2022 Collaborate with R&D/technical, supply-chain and other cross functional teams to support new product introduction from pilot to production; ensuring product manufacturability & scalability.\n\n2. Strategy& long-term improvements\n\u2022 Participate in high level strategic planning with management. Provide thoughtful recommendations and input on manufacturing priorities.\n\u2022 Adopts \u201cKaizen\u201d mentality and continually improves processes and systems. Seeks out and drives cost savings & production efficiency gains. Marshalls resources necessary to reduce cost &initiate lean projects.\n\u2022 Lead scaling efforts per company direction. Oversees factory relocation or new factory expansion initiatives. Facilitates effective technology and knowledge transfer across manufacturing teams and locations.\n\n3\u00a0 Leadership, team & culture building\n\u2022 Build and grow manufacturing organization while promoting company values of team-work and respect.\n\u2022 Hire and retain high performers. Motivate and coach junior to mid-career staff to achieve career goals.\n\u2022 Develop and implement policies and standards to increase manufacturing team output and quality of work.\n\nThe successful candidate will:\n\u2022 Be an experienced leader and people-manager, with experience managing an a production organization of 100+ production staff and 1000+ workers.\n\u2022 Leads with purpose, integrity and respect. Fosters cross-team/cross-culture communication and effectively resolves conflict.\n\u2022 Has big picture focus and the ability to think strategically \u2013 while also willing to roll up their sleeves to get things done.\n\u2022 Thrives in ambiguity and exercises solid judgment in times of uncertainty, including COVID, supply chain shocks & fluctuating volumes.\n\u2022 Have strong analytical, planning, and project management skills. Is organized, and can effectively multi-task.\n\u2022 Possesses a strong scientific and technical background, able to establish credibility with senior management and cross-functional teams.\n\u2022 Uses industry accepted concepts and tools to solve complex problems in creative and effective ways as they apply to compliance issues.\n\u2022 Has excellent verbal/written skills in English, Cantonese and Mandarin - confident and effective communication with company management, customers, suppliers, and agencies at all levels.\n\nJob Requirements:\n\u2022 Bsc degree in Electronics/ Mechanical/Electro-Mechanical Engineering.\n\u2022 At least 10 years of experience in in EMS manufacturing industry.\n\u2022 At least 5 years at senior factory management or plant manager position.\n\u2022 At least 5 years of experience working with & managing ERP systems. (specific experience with SAP a plus)\n\u2022 Working knowledge EMS manufacturing and testing processes (SMT, Through-hole assembly, wave soldering, etc), and complex engineering grade plastic part manufacturing (eg. mold design, processing of engineering grade resins).\n\u2022 Flexibility to travel between China and Vietnam factories and extended periods of stay (months at time) in both manufacturing facilities.\n\u2022 Experience working or managing teams across cultures\n\nPreferred Requirements (huge plus):\n\u2022 Previous work experience managing factories in Vietnam.\n\u2022 Ability to read/write or speak Vietnamese\n\u2022 Previous product experience with power supplies & LED/lighting manufacturing\n\u2022 Third party auditing (eg. ISO) or experience leading customer or third party audits\n\u2022 Lean and/or Six Sigma, PPAP/APQP certification or experience\nInterested candidates, please contact us at 67616886 for company details before applying.", "employment_types": ["Full Time"], "selling_points": ["Young and energetic team", "Self-motivated & hardworking", "Immediate available preferred"], "locations": ["Lai Chi Kok"], "categories": ["Manufacturing", "Manufacturing Management"], "post_time": "2022-01-14T08:30:15Z", "salary": {"currency": null, "max": null, "min": null, "period": "monthly", "term": null}, "salary_visible": false, "title_keywords": ["merchandiser"], "responsibilities": ["collaborate with", "operations", "budget", "quality", "communication", "deploy", "senior management", "collaborate", "ems", "compliance", "teams", "develop", "kpis", "reporting", "cost", "management", "strategic planning", "audits", "cross-functional teams", "policies", "analysis", "systems", "evaluate", "project management", "planning"], "requirements": {"degrees": ["degree", "bsc"], "majors": ["mechanical engineering"], "languages": ["vietnamese"], "language_level": [], "hard_skills": ["erp systems", "plus", "lean", "sap", "ems", "six sigma", "processing"], "soft_skills": [], "languages_combined": [{"language": "vietnamese", "language_level": []}]}, "experience_required": {"duration": ["at least 10 years", "at least 5 years"], "field": ["manufacturing", "manufacturing industry"]}}, {"job_id": "100003009051249", "location_code": "hk", "company": "Chu Kong Optical Mfy Ltd", "job_title": "Shipping Assistant / Operations Officer", "description": "Jobs Duties :\n\nIn Charge of Engineering Department\nCo-ordination with suppliers, contractors and technical staff\n\nRequirements :\n\nDegree in\u00a0Electrical / Mechanical Engineering or relevant disciplines\nMinimum 7 years\u2019 working experience in manufacturing environment, preferred gained from food industry\nAt least 3 years in supervisory position\nFamiliar with Manufacturing Automation System\nStrong interpersonal and communication skill\nISO 9001 & HACCP exposures are a definite asset\nFluent in spoken / written English and Mandarin\u00a0\nHolder of Registered Electrical Worker (Grade A) is an advantage\n\nPlease send a full resume with contact telephone number and expected salary\u00a0by clicking\u00a0\"APPLY NOW\".", "employment_types": ["Full Time"], "selling_points": ["5 days work", "Modern Office Environment", "FREE shuttle bus service provided"], "locations": ["Kwai Tsing Area"], "categories": ["Transportation & Logistics", "Shipping", "Manufacturing", "Manufacturing Management", "Merchandising & Purchasing", "Others"], "post_time": "2022-01-15T06:15:09Z", "salary": {"currency": null, "max": null, "min": null, "period": "monthly", "term": null}, "salary_visible": false, "title_keywords": ["operations officer", "shipping", "assistant"], "responsibilities": [], "requirements": {"degrees": ["degree"], "majors": ["mechanical engineering"], "languages": ["english", "mandarin"], "language_level": ["fluent"], "hard_skills": [], "soft_skills": ["communication skill", "interpersonal"], "languages_combined": [{"language": "english", "language_level": ["fluent"]}, {"language": "mandarin", "language_level": ["fluent"]}]}, "experience_required": {"duration": ["minimum 7 years"], "field": ["manufacturing", "food industry"]}}, {"job_id": "100003009054041", "location_code": "hk", "company": "Eternity Consultants (HK) Ltd", "job_title": "Assistant Compliance Specialist / Compliance Specialist - BSCI / SA8000 (Fresh graduate)", "description": "Responsibilities:\n\nAssist the marketing manager to fix business strategies\nManage the full process of projects including RFQ, project meeting, order management and follow up the payments\nWork with the internal and external teams to conduct marketing Research\u00a0\nProvide customer services in order to maintain existing accounts and further expand the customer base\nGenerate cost analysis on budget and to achieve the KPI of department\nPerform any ad-hoc assignments/projects as assigned\n\nRequirements:\n\nHigher Diploma or above in Marketing, Manufacturing Engineering and Product Design and etc.\nMinimum 3-5 years relevant working experience\nExcellent communication, negotiation, persuasion skills, planning and organization skills.\nStrong presentation, problem solving skills, analytical power and opened mind.\nStrong sense of team work, aggressiveness, responsible and proactive character.\nProficient in MS Office applications. (Excel, Access, PowerPoint, etc)\nExcellent command of written and spoken English and Mandarin.\nBased in Dongguan factory\nLess experience will be considered as Senior Marketing Executive\n\nInterested parties please click \"Apply Now\" to send\u00a0full resume with the date of availability and expected salary\u00a0\n\nOr post it to \"The\u00a0 Group HR Department, Karrie International Holdings Limited, 9/F, Southeast Industrial Building, 611-619 Castle Peak Road, Tsuen Wan, N.T.\" (Please Attn Recruitment Team and quote Ref. on the envelope)\n\nFor more information, please visit our website at http://www2.karrie.com/en, or visit\u00a0 \u00a0https://www.youtube.com/watch?v=y3Lhgl7ylf8&list=PL66rAPgv5k9ykDxduveZ6E7Yni9e39jBZ\n\n** We are an equal opportunity employer and welcome applications from all qualified candidates.\u00a0Personal data\u00a0provided by job applicants will be used strictly in accordance with the employer's personal data policies, a copy of which will be provided immediately upon request. **", "employment_types": ["Full Time"], "selling_points": ["5 days, 13 months, bank, medical, 12 AL", "1-3 years in social compliance in trading", "buying office, factory audit, conflict mineral"], "locations": ["Not Specified"], "categories": ["Engineering", "Manufacturing & Production", "Manufacturing", "Manufacturing Management", "Quality Assurance, Control & Testing / ISO"], "post_time": "2022-01-17T08:11:05Z", "salary": {"currency": null, "max": null, "min": null, "period": "monthly", "term": null}, "salary_visible": false, "title_keywords": ["specialist", "assistant"], "responsibilities": ["order management", "ad-hoc assignments", "budget", "teams", "customer services", "marketing research", "maintain", "payments", "cost analysis"], "requirements": {"degrees": ["higher diploma or above"], "majors": ["manufacturing", "marketing", "engineering", "design"], "languages": ["english", "mandarin"], "language_level": ["excellent"], "hard_skills": ["excel", "problem solving skills", "powerpoint", "ms office"], "soft_skills": ["negotiation", "responsible", "communication", "organization skills", "problem solving skills", "proactive", "presentation"], "languages_combined": [{"language": "english", "language_level": ["excellent"]}, {"language": "mandarin", "language_level": ["excellent"]}]}, "experience_required": {"duration": ["minimum 3-5 years"], "field": ["marketing", "relevant working experience"]}}, {"job_id": "100003009051108", "location_code": "hk", "company": "Yeko Manufacturing Limited", "job_title": "Plastic injection specialist", "description": "Responsibilities:\n\nLaunch new product and closely work with QA and R&D department\nLead a team of operators and manage day-to-day operation of food production lines to achieve production schedules and targets\nAssist Manager in developing and implementing production and quality systems and ensure compliance of related requirements and standards with strong food safety sense\nPerform analysis on work flow and production efficiency regularly, collect and maintain accurate records and support month-end reports\nParticipate in regular factory audits and checks, and take up ad hoc assignments\n\nRequirements:\n\nHigher Diploma or above in Food Science,\u00a0Manufacturing, Industrial Engineering or related discipline\n2-4 years of relevant experience in manufacturing industry, preferably in food factory\nKnowledge of ISO22000 / HACCP / BRC will be an advantage\nDetail-minded, well-organized and sensitive to figures, self-motivated and willing to take up challenges\nTeam-player, willing to learn and with good communication and problem-solving skills\nProficient in both English and Mandarin as well as in computer applications, knowledge in SAP will be an advantage\nCandidate with more experience will be considered as Senior Production Officer\n\n\u00a0Interested parties please send your resume with current and expected salary and availability:\n\n- \u00a0by fax to 2666 6575\n- \u00a0by mail to\n\u00a0 \u00a0Human Resources Director\n\u00a0 \u00a0Amoy Food Limited\n\u00a0 \u00a011-15 Dai Fu Street,Tai Po Industrial Estate,Tai Po, N.T.\n- \u00a0by \u201cApply Now\u201d\n\nFor enquiries, please contact our Recruitment Hotline at 26603403.\u00a0Employment Application Form can be downloaded from the company website\u00a0www.amoy.com\n\nAll applications will be treated in strict confidence and retained for 6 months for recruitment purposes only.\u00a0\u00a0", "employment_types": ["Full Time"], "selling_points": ["Plastic injection specialists", "Vietnam stationed", "8 years experience"], "locations": ["Overseas"], "categories": ["Manufacturing", "Manufacturing Management", "Merchandising & Purchasing", "Toy"], "post_time": "2022-01-15T02:26:23Z", "salary": {"currency": null, "max": null, "min": null, "period": "monthly", "term": null}, "salary_visible": false, "title_keywords": ["specialist"], "responsibilities": ["food safety", "schedules", "analysis", "systems", "quality", "developing", "month-end", "ensure compliance", "lead a team", "maintain", "reports", "ad hoc assignments", "audits", "day-to-day operation"], "requirements": {"degrees": ["higher diploma or above"], "majors": ["manufacturing", "engineering", "food science"], "languages": ["english", "mandarin"], "language_level": ["advantage", "proficient"], "hard_skills": ["problem-solving skills", "sap"], "soft_skills": ["detail-minded", "self-motivated", "team-player", "sensitive to figures", "well-organized", "willing to learn", "communication", "problem-solving skills"], "languages_combined": [{"language": "english", "language_level": ["advantage", "proficient"]}, {"language": "mandarin", "language_level": ["advantage", "proficient"]}]}, "experience_required": {"duration": ["2-4 years"], "field": ["food", "relevant experience", "manufacturing industry"]}}, {"job_id": "100003009042911", "location_code": "hk", "company": "", "job_title": "Operation Assistant Director / Director (EMS Industry - Based in Dongguan)", "description": "\nJob Description\nManage the daily operation and monitor the performance of production team and outsourced workers;\nResponsible for manpower control and staff issue of production team;\nParticipate the planning and implementation of policy and procedures in the areas of product quality, manufacturing strategies, manpower and cost control;\nClosely communicate with all shift and level of operation management to ensure the production is smooth and effective;\nCoach and motivate the production team to accomplish production target and practice the group core values.Job Requirements\nBachelor or equivalent in Business Management, Manufacturing or related discipline;\n\n5 years of working experience at supervisory level, preferably in labour-intensive industries;\nSelf-motivated, independent\nA good team player with good communication skills;\nWell-organized with good analytical skill;\nProficient in PC applications including Chinese word processing;\nGood command of spoken and written English and Chinese / Cantonese;\n5-day work week;\nWorking location: Tai Po Industrial Estate (with shuttle bus);\n\nStaff Benefits\n\nMedical Insurance Coverage\nBirthday & Wedding Leave\nFree Meal & Shuttle Bus\nStaff Purchase Benefits\nAll applications and data collected will be treated in strict confidence and used exclusively for recruitment purposes.\u00a0 Only short listed candidates will be invited for interview.\u00a0 The company will retain the applications for a maximum period of 6 months and may refer suitable candidates to other vacancies within the Group.", "employment_types": ["Full Time", "Permanent"], "selling_points": ["Bachelor Degree in Product Engineering", "Manufacturing Engineering, based in Dongguan", "Attractive Remuneration Package"], "locations": ["Others - China"], "categories": ["Engineering", "Manufacturing & Production", "Manufacturing", "Manufacturing Management"], "post_time": "2022-01-12T09:14:56Z", "salary": {"currency": null, "max": null, "min": null, "period": "monthly", "term": null}, "salary_visible": false, "title_keywords": ["operation assistant", "director"], "responsibilities": ["communicate with", "control", "management", "daily operation", "implementation", "procedures", "quality", "monitor the performance", "cost control", "planning"], "requirements": {"degrees": ["bachelor"], "majors": ["manufacturing", "business"], "languages": ["cantonese", "english", "chinese"], "language_level": ["good command", "proficient"], "hard_skills": ["business management", "analytical skill", "chinese word processing", "pc applications"], "soft_skills": ["communication skills", "good team player", "self-motivated", "independent", "analytical skill", "well-organized"], "languages_combined": [{"language": "cantonese", "language_level": ["good command"]}, {"language": "english", "language_level": ["good command"]}, {"language": "chinese", "language_level": ["good command", "proficient"]}]}, "experience_required": {"duration": ["5 years"], "field": ["supervisory level"]}}, {"job_id": "100003009041783", "location_code": "hk", "company": "Online Retail Solutions Limited", "job_title": "Project Manager - Manufacturing", "description": "Job Duties:\n\nManage, monitor and enhance the efficiency and effectiveness of all aspects of engineering activities within an organization including sampling and product review\nEnsure all engineering projects, initiatives, and processes are in conformance with organization\u2019s established policies and objectives\nManage the daily operations of engineering team and deliver the KPI of company for engineering and technical functions\nTo lead the team member to drive the team structure and solve the problems in consistent way\nWork on product costing, budget and control repairing and maintenance costs\nTypically reports to top management\n\nJob Requirements:\n\nBachelor\u2019s degree in Industrial Engineering or equivalent\nMinimum 6 years plastic toys\n\nSolid experience in the manufacturing field with exposure in areas of production, quality, safety, logistics and maintenance\nGood understanding of production processes and manufacturing capabilities\nStrong knowledge of practices and procedures to effectively resolve workflow issues\nStrong ability to gather, analyze and interpret information and develop, recommend and implement solutions\nDemonstrate experience in leading, guiding, and mentoring teams and individuals; understand group dynamics and team development\nResult and quality focused; great attention to detail\nEffectively communicate, both verbally and written to all levels of the organization\nGood analytical and problem solving skills are essential\nFluency in both spoken and written English and Chinese (Mandarin & Cantonese)\nERP application experience is preferable\u00a0\n\n*Interested parties, please Email full resume with current & expected salary & date available in MS WORD FORMAT ONLY to us\u00a0\u00a0or fax to 3527 0634*\n\nWe are welcome applicants resend resumes to us even you have applied jobs in our company before.\n\nFor more jobs, please visit our website:\u00a0www.hketernity.com\n\n(Personal data submitted are for recruitment purpose only.)\u00a0\n\nFor more jobs, please visit our website:\u00a0www.hketernity.com\n\n\u00a0(Personal data submitted are for recruitment purpose only.)", "employment_types": ["Full Time"], "selling_points": [">5+ yrs project management exp. in manufacturing", "We are a purpose led brand to make a difference", "Be part of the TaKeBambooMovement! Apply Today"], "locations": ["Kwai Tsing Area"], "categories": ["Manufacturing", "Manufacturing Management"], "post_time": "2022-01-12T04:22:52Z", "salary": {"currency": null, "max": null, "min": null, "period": "monthly", "term": null}, "salary_visible": false, "title_keywords": ["project manager"], "responsibilities": ["control", "management", "maintenance", "policies", "review", "monitor", "budget", "daily operations", "reports", "costs"], "requirements": {"degrees": ["degree", "bachelor"], "majors": ["engineering"], "languages": ["cantonese", "english", "chinese", "mandarin"], "language_level": ["fluency"], "hard_skills": ["problem solving skills", "maintenance", "erp"], "soft_skills": ["analytical and problem solving skills", "attention to detail", "focused"], "languages_combined": [{"language": "cantonese", "language_level": []}, {"language": "english", "language_level": ["fluency"]}, {"language": "chinese", "language_level": ["fluency"]}, {"language": "mandarin", "language_level": []}]}, "experience_required": {"duration": [], "field": ["manufacturing", "logistics", "maintenance"]}}, {"job_id": "100003009047965", "location_code": "hk", "company": "Solent Manufacturing Ltd", "job_title": "Merchandiser - Health & Beauty / Household / Bags", "description": "Responsible for assisting the factory manager in overseeing all aspects of the factory operation with over 3,000 staff and monitoring daily operations of production, quality and engineering.\n\n\nDiploma or above in Manufacturing, Mechanical, Industrial Engineering or related disciplines\n\nAt least 15 years relevant experience of which 7 years experience at managerial level in OEM manufacturing\n\nGood at manufacturing technique of electrical household appliances and have in depth knowledge in all aspects of sizable factory operation\n\nWith experience in ISO9000, ISO14000, lean manufacturing and 6-Sigma is preferable\n\nGood command of English and Chinese\nAggressive, self-motivated, attentive to details and highly quality-conscious\n\nCandidates with less experience will be considered as Production Engineering Manager (Qingyuan Stationed)\n\nWe offer\u00a0attractive remuneration package including 5-day work, bank holidays, group medical insurance etc to the right candidates. Interested parties please send your full resume including expected salary and date available to Human Resources Department by clicking \"Apply Now\" button.\n\nFor more details, please visit our web-site at www.simatelex.com.hk", "employment_types": ["Full Time", "Permanent"], "selling_points": ["Flexible Working Hour", "Hybrid Working", "Double Pay & Discretionary Bonus"], "locations": ["Hung Hom"], "categories": ["Manufacturing", "Manufacturing Management", "Product Development / Management", "Merchandising & Purchasing", "Procurement / Purchasing / Sourcing"], "post_time": "2022-01-14T04:23:58Z", "salary": {"currency": null, "max": null, "min": null, "period": "monthly", "term": null}, "salary_visible": false, "title_keywords": ["merchandiser"], "responsibilities": ["daily operations", "monitoring", "quality"], "requirements": {"degrees": ["diploma or above"], "majors": ["related disciplines", "manufacturing", "engineering"], "languages": ["english", "chinese"], "language_level": ["good command"], "hard_skills": ["lean"], "soft_skills": ["self-motivated", "attentive to details", "responsible"], "languages_combined": [{"language": "english", "language_level": ["good command"]}, {"language": "chinese", "language_level": ["good command"]}]}, "experience_required": {"duration": ["7 years", "at least 15 years"], "field": ["managerial", "manufacturing", "relevant experience", "engineering"]}}, {"job_id": "100003009056260", "location_code": "hk", "company": "Bless International Group Limited", "job_title": "Factory Manager", "description": "Responsibilities:\n\nLead the production line to optimize the production efficiency;\nResponsible for formulating supply chain strategy and perform cost management or processing procurement orders\nReview the production capacity regularly to ensure the product deliver on time;\nMonitor the workflow of the production to ensure the operation run smoothly;\nContinuously improve the product quality to reduce the food risk;\nCommunicate with the team and management to reach the common goal;\nFormulate and implement the standard the operation procedure;\nWork with internal parties i.e: sales team to coordinate delivery schedule or stock arrangement;\nPerform ad hoc duties\n\nRequirements:\n\nBachelor's degree in relevant disciplines\nWith at least 8 years experience in food and beverage manufacturing, not less than 5 years experience in factory management\nWork experience in large-scale of food and beverage manufacturing is preferred\nEquipping with HACCP / ISO quality management standards qualifications\nStrong interpersonal skill and good leadership skills Result-oriented, detailed mined and organized\nProactive, detail-minded and willing to take up challenges\nProficient in PC application including Chinese word processing\nGood command of spoken and written English and Chinese / Cantonese\nLess experience will be considered as Assistant Factory Manager;\nImmediate available is preferable", "employment_types": ["Full Time"], "selling_points": ["Factory management", "Food and beverage manufacturing", "Immediate available is preferable"], "locations": ["Kwai Hing"], "categories": ["Manufacturing", "Manufacturing Management"], "post_time": "2022-01-18T03:44:20Z", "salary": {"currency": null, "max": null, "min": null, "period": "monthly", "term": null}, "salary_visible": false, "title_keywords": ["factory manager"], "responsibilities": ["communicate with", "ad hoc duties", "cost", "management", "review", "quality", "monitor", "coordinate", "delivery schedule", "sales team", "internal parties"], "requirements": {"degrees": ["degree", "bachelor"], "majors": [], "languages": ["cantonese", "english", "chinese"], "language_level": ["good command", "proficient"], "hard_skills": ["pc", "chinese word processing"], "soft_skills": ["detail-minded", "organized", "leadership skills", "interpersonal skill", "proactive", "result-oriented", "detailed"], "languages_combined": [{"language": "cantonese", "language_level": ["good command"]}, {"language": "english", "language_level": ["good command"]}, {"language": "chinese", "language_level": ["good command", "proficient"]}]}, "experience_required": {"duration": ["at least 8 years", "5 years"], "field": ["food", "management", "manufacturing"]}}, {"job_id": "100003009056066", "location_code": "hk", "company": "Top Link Industrial Company Limited", "job_title": "Manufacturing Manager (Station Dongguan)", "description": "Job Responsibilities\n\nTake active roles in providing technical support and feasibility studies for new product launch;\nActively involved in line set up, layout planning and workers\u2019 training plan;\nContinue improvement on output and efficiency;\nMonitor the day-to-day operations of the plant;\u00a0\nReview and improve operational management for all levels in the plant to achieve effectiveness and efficiency;\nEnsure a smooth plant operation that complies with internal policies and customer requirements;\nResponsible for overseeing assembly and industrial engineering department;\nTrouble shooting, problem solving, process improvement, automation, product testing, etc.;\nProvide support to other departments in customers audit and enquiry;\nHandle ad hoc assignments as require.\n\nJob Requirements\n\nUniversity graduate in Production Management / Mechanical Engineering or Industrial engineering or related discipline;\nA minimum of 10 years working experience of which at least 5 years in managing a sizeable PRC factory and managing people; experience in household electrical appliance is an advantage;\nFast pace, flexible mindset, willing to learn;\nExcellent communication skills with fluency in spoken and written English, Cantonese and Mandarin;\nStrong problem solving, influencing skills, communication and people management skills;\nPreferred to have knowledge and experience in LEAN manufacturing;\nStrong knowledge in fixture and equipment;\nStation in PRC Dongguan plant is required.\n\nInterested parties, please send your full resume stating your expected salary and date of availability to the Human Resources Department\u00a0for application.\u00a0 We offer successful candidates an attractive remuneration packages (Basic salary + Bonus + Medical Scheme) and the opportunity to work in a dynamic and exciting environment.\u00a0 (Data collected will be used for recruitment purpose only)", "employment_types": ["Full Time", "Permanent"], "selling_points": [], "locations": ["Others - China"], "categories": ["Manufacturing", "Manufacturing Management"], "post_time": "2022-01-18T03:14:45Z", "salary": {"currency": null, "max": null, "min": null, "period": "monthly", "term": null}, "salary_visible": false, "title_keywords": ["manager"], "responsibilities": ["management", "provide support", "technical support", "policies", "review", "day-to-day operations", "monitor", "audit", "testing", "ad hoc assignments", "plan", "planning"], "requirements": {"degrees": ["university graduate"], "majors": ["engineering", "mechanical engineering"], "languages": ["cantonese", "english", "mandarin"], "language_level": ["fluency", "excellent"], "hard_skills": ["problem solving", "lean"], "soft_skills": ["flexible", "communication skills", "willing to learn", "communication", "problem solving"], "languages_combined": [{"language": "cantonese", "language_level": ["fluency", "excellent"]}, {"language": "english", "language_level": ["fluency", "excellent"]}, {"language": "mandarin", "language_level": ["fluency", "excellent"]}]}, "experience_required": {"duration": ["at least 5 years", "minimum of 10 years"], "field": ["manufacturing"]}}, {"job_id": "100003009055481", "location_code": "hk", "company": "Michael Page", "job_title": "Production and Material Planning Manager", "description": "Lead the team and oversee the functions of production planning and material control\n\nMaterial planning from control of material flow to optimisation of work processes and production capacity\n\nClient Details\n\nMy client is Hong Kong top manufacturer and is looking for Production and Materials Planning Manager\n\nDescription\n\nLead the team and oversee the functions of production planning and material control\nResponsible for capacity planning and overall production scheduling based on demand from forecast to ensure supply capacity copes with forecast\nMaterial planning from control of material flow to optimisation of work processes and production capacity\nEnsures materials are ordered and in stock to meet company requirements, while maintaining acceptable inventory levels\nControl expenses and production efficiency through proper manpower scheduling and production plan\nTo perform analysis on work flow and production efficiency, collect and maintain accurate records and support month-end reporting;\n\nProfile\n\nBachelor or above, major in industrial engineering, supply chain, or related discipline is preferable;\nOver 6 - 8 years of solid relevant working experiences in similar position in production and material planning\nDetail minded, multi-tasks, strong sense of responsibility\nGood command of communication skill\n\nJob Offer\n\nInterested applicant please send me your resume to Marcochong@michaelpage com hk OR you can contact Marco @ 52909990", "employment_types": ["Full Time", "Permanent"], "selling_points": ["Top Hong Kong Food manufacturer", "Manage production and material planning", "Attractive salary with great benefits"], "locations": ["Not Specified"], "categories": ["Manufacturing", "Manufacturing Management", "Production Planning / Control", "Others"], "post_time": "2022-01-18T02:38:36Z", "salary": {"currency": null, "max": null, "min": null, "period": "monthly", "term": null}, "salary_visible": false, "title_keywords": ["manager"], "responsibilities": ["reporting", "control", "maintaining", "inventory", "expenses", "production planning", "analysis", "month-end", "communication", "scheduling", "maintain", "contact", "forecast", "plan", "planning"], "requirements": {"degrees": ["bachelor"], "majors": ["engineering"], "languages": [], "language_level": [], "hard_skills": ["marco", "analysis"], "soft_skills": ["multi-tasks", "responsible", "sense of responsibility", "communication skill", "accurate"], "languages_combined": []}, "experience_required": {"duration": ["6 - 8 years"], "field": ["planning"]}}, {"job_id": "100003009056304", "location_code": "hk", "company": "Lam Soon (Hong Kong) Limited", "job_title": "Production Material Officer (\u751f\u7522\u90e8\u7269\u6599\u4e3b\u4efb) (Ref. JDB_21_037)", "description": "\u8077\u8cac:\n\n\u4f9d\u64da\u751f\u7522\u9700\u6c42\u78ba\u4fdd\u539f\u6599\u53ca\u7269\u6599\u4f9b\u61c9\u6b63\u5e38\n\u6839\u64da\u8ca8\u7269\u3001\u5546\u54c1\u7684\u5eab\u5b58\u91cf\uff0c\u898f\u5283\u63a5\u6536\u7269\u6599\uff08\u6cb9\u6599\u53ca\u5305\u6750\uff09\u5de5\u4f5c\u8a08\u5283\n\u8655\u7406\u539f\u6599/\u5305\u6750\u5ef6\u9072\u5230\u8ca8/\u8b8a\u66f4\u7684\u4f9b\u61c9\u554f\u984c\n\u9032\u884c\u9a57\u6536\u4f5c\u696d\uff0c\u78ba\u8a8d\u8ca8\u54c1\u7684\u54c1\u8cea\u548c\u898f\u683c\n\u5009\u5b58\u7ba1\u7406\u53ca\u7d71\u7c4c\u76e4\u9ede\u5de5\u4f5c\n\u4f9b\u61c9\u5546\u4f86\u8ca8\u7570\u5e38\u554f\u984c\uff08\u55ae\u64da\u3001\u6279\u6b21\u3001\u5668\u5177\u3001\u5b89\u5168\u7b49\uff09\u8655\u7406\uff0c\u4f86\u8ca8\u7570\u5e38\u554f\u984c\u8003\u6838\n\u6e9d\u901a\u5354\u8abf\u8de8\u90e8\u9580\u7269\u6599\u5de5\u4f5c\n\n\u5de5\u4f5c\u8981\u6c42:\n\n\u5c08\u4e0a\u6559\u80b2\uff1a\u6587\u6191/\u8b49\u66f8\n5\u5e74\u76f8\u95dc\u5de5\u4f5c\u7d93\u9a57\uff0c\u5305\u62ec2\u5e74\u7ba1\u7406\u7d93\u9a57\uff0c\u6709\u7269\u6599/\u63a1\u8cfc\u5de5\u4f5c\u7d93\u9a57\u512a\u5148\n\u826f\u597d\u7cb5\u8a9e; \u4e00\u822c\u666e\u901a\u8a71\uff1b\u61c2\u8b80\u5beb\u4e2d\u82f1\u6587\uff0c\u5177\u96fb\u8166\u64cd\u4f5c\u77e5\u8b58\n\u66fe\u65bc\u98df\u54c1\u5ee0/\u85e5\u5ee0\u5de5\u4f5c\u3001\u8a8d\u8b58ISO9001\u53caISO22000\u512a\u5148\n\u6709\u8cac\u4efb\u611f\u3001\u4e3b\u52d5\u53ca\u523b\u82e6\u8010\u52de\n\u9700\u8981\u52a0\u73ed\u53ca\u9ad4\u529b\u52de\u52d5\n\n\u672c\u516c\u53f8\u63d0\u4f9b\u5b8c\u5584\u7684\u85aa\u916c\u53ca\u798f\u5229\u8a08\u5283\uff0c\u6709\u610f\u61c9\u5fb5\u8005\u8acb\u5c07\u5c65\u6b77\u53ca\u8981\u6c42\u5f85\u9047\u96fb\u90f5\u6211\u5011\u6216\u50b3\u771f\u81f326677049\u3002\n\n\u5982\u6b32\u67e5\u8a62\u516c\u53f8\u8a73\u60c5\uff0c\u8acb\u700f\u89bdwww.lamsoon.com\u3002\n\n(\u6309\u5357\u9806\u9999\u6e2f\u96c6\u5718\u8077\u4f4d\u7533\u8acb\u4eba\u4e4b\u500b\u4eba\u8cc7\u6599\u653f\u7b56\uff0c\u6211\u53f8\u5c07\u5c0d\u7533\u8acb\u4eba\u63d0\u4f9b\u4e4b\u5168\u90e8\u8cc7\u6599\u7d55\u5c0d\u4fdd\u5bc6\u53ca\u53ea\u4f5c\u62db\u8058\u4e4b\u7528\u3002\u8a73\u60c5\u8acb\u700f\u89bdwww.lamsoon.com\u3002)\n\n\n\u9999\u6e2f\u65b0\u754c\u5927\u57d4\u5de5\u696d\u90a8\u5927\u5bcc\u885721\u865f\u5357\u9806\u5927\u5ec8", "employment_types": ["Full Time", "Permanent"], "selling_points": ["5\u5e74\u76f8\u95dc\u5de5\u4f5c\u7d93\u9a57 ; \u5c08\u4e0a\u6559\u80b2\uff1a\u6587\u6191/\u8b49\u66f8", "\u5177\u6709ISO9001\u53caISO22000\u77e5\u8b58", "\u98df\u54c1\u5ee0\u5de5\u4f5c\u7d93\u9a57\u512a\u5148 ; \u7269\u6599\u5de5\u4f5c\u7d93\u9a57\u512a\u5148"], "locations": ["Tai Po Area"], "categories": ["Manufacturing", "Manufacturing Management", "Product Development / Management", "Production Planning / Control"], "post_time": "2022-01-18T03:53:24Z", "salary": {"currency": null, "max": null, "min": null, "period": "monthly", "term": null}, "salary_visible": false, "title_keywords": ["officer"], "responsibilities": [], "requirements": {"degrees": [], "majors": [], "languages": [], "language_level": [], "hard_skills": [], "soft_skills": [], "languages_combined": []}, "experience_required": {"duration": [], "field": []}}, {"job_id": "100003009055483", "location_code": "hk", "company": "Michael Page", "job_title": "Production Manager (Pharmaceutical)", "description": "Manage the production line of a local manufacturer\n\nClient Details\n\nMy client a manufacturer is looking for a production manager to run its entire production line\n\nDescription\n\nEstablishing and monitoring production performance\nArrange and manage the production schedule and communicate with other dept. to ensure the smoothness of operation to meet the production target\nEstablish and review work process within production and make resource could be utilized high effectiveness\nEnsures the operation in compliance with all the rules and regulations which legislated by government authorities\nContinuously improve the product quality to reduce food risk;\nFacility, Machine, Equipment, and Tools maintenance management\nMonitor pre-production preparation and implementation of bulk production by supervision of the production planning control program\n\nProfile\n\nDegree holder in relevant education\nAt least 6 - 8 years of relevant working experience production manufacturing, of which at least 3 years in managerial level\nGood command of written and spoken language skills\nAbility to manage multi-task well in a fast-paced environment\n\nJob Offer\n\nInterested applicant please send me your cv to marcochong@michaelpage com hk OR you can contact me @ 52909990", "employment_types": ["Full Time", "Permanent"], "selling_points": ["Attractive salary with great benefits", "Open salary budget", "Great working environment"], "locations": ["Not Specified"], "categories": ["Engineering", "Manufacturing & Production", "Manufacturing", "Manufacturing Management", "Production Planning / Control"], "post_time": "2022-01-18T02:38:41Z", "salary": {"currency": null, "max": null, "min": null, "period": "monthly", "term": null}, "salary_visible": false, "title_keywords": ["production manager"], "responsibilities": ["communicate with", "regulations", "management", "control", "maintenance", "compliance", "review", "monitoring", "quality", "monitor", "implementation", "production planning", "schedule", "contact", "pre-production"], "requirements": {"degrees": ["degree holder"], "majors": [], "languages": [], "language_level": [], "hard_skills": ["make", "maintenance"], "soft_skills": ["fast-paced environment", "multi-task"], "languages_combined": []}, "experience_required": {"duration": ["at least 3 years", "at least 6 - 8 years"], "field": ["managerial", "manufacturing", "relevant working experience"]}}, {"job_id": "100003009056312", "location_code": "hk", "company": "Lidl Hong Kong Limited", "job_title": "Manufacturing Excellence Specialist", "description": "Summary\n\nLidl are hiring a\u00a0Manufacturing Excellence Specialist for our production and quality control\u00a0team. The successful candidate will ensures that factories/Mills are evaluated fairly and ethically, also support factories/Mills that do not meet our internal/ legal minimum requirements via monitoring on Corrective Action Plans, conducting the follow ups and re-assessment.\n\nWhat will you do?\n\n\u2022\u00a0\u00a0 \u00a0Ensure all FCE (Factory Social Compliance Evaluations) are in line with Lidl Asia defined SOP\u2019s\n\n\u2022\u00a0\u00a0 \u00a0Assist in development of Factory Evaluation plans and schedules. Communicate with the Shenzhen booking team to ensure all FCEs are arranged and conducted in line with the agreed company timelines and ensure CAPs are closed off.\n\n\u2022\u00a0\u00a0 \u00a0Conduct FCE (Factory Social Compliance Evaluation) of Lidl Asia\u2019s supplier base for factories/Mills to ensure they comply to Lidl\u2019s C&S (Compliance & Sustainability) requirements, inclusive of International & local labor regulations/ applicable laws.\n\n\u2022\u00a0\u00a0 \u00a0Review and verify the Critical Non-Compliance (CNC) found during an ongoing audit, by the ME audit team, authorized agencies or assigned 3rd parties.\n\n\u2022\u00a0\u00a0 \u00a0Perform the FCE audit report review, analyze and report compliance discrepancies and \u00a0follow up with ME audit team and authorized agencies or assigned 3rd parties.\n\n\u2022\u00a0\u00a0 \u00a0Perpare the FCE audit report to summarize the evaluation result, inclusive of non-compliance issues \u00a0and share internally to all internal stakeholders (Sourcing, Merchandising and Production) for new FCE assessments and Existing factories.\n\n\u2022\u00a0\u00a0 \u00a0Ensure all FCE data are accurate and updated in the LUP system by the Shenzhen booking team after completion of the latest compliance evaluations.\n\n\u2022\u00a0\u00a0 \u00a0 Prepare FCE data for the monthly/Quartely report.\n\n\u2022\u00a0\u00a0 \u00a0Monitor the CAP status and support factories deemed not meeting our evaluation criteria via CAPs, follow up meetings and or discussions and re-audits.\n\n\u2022\u00a0\u00a0 \u00a0Communicate with Lidl Asia Sourcing and Merchandizing teams, keep them up-to-date with factory compliance status, flag critical non-complaince issues immediately to the Sourcing teams to ensure they are updated on the social compliance risks in their supply base and work out a solution in a collaborative manner.\n\n\u2022\u00a0\u00a0 \u00a0Conduct Shadow audits when required to ensure integrity of Auditing program\n\n\u2022\u00a0\u00a0 \u00a0Prepare the notification letter and send out pre-alert notification letter to all internal stakeholders and Regulartory Compliance team\n\n\u2022\u00a0\u00a0 \u00a0Support Senior ME Manager in conducting process & system audits and make continual improvements in protocols/work procedures.\n\n\u2022\u00a0\u00a0 \u00a0Support Senior ME Manager in the creation of standard work documentation, visual work instructions and training material.\n\n\u2022\u00a0\u00a0 \u00a0Support in system upgrade and development to ensure end-state solutions meet all users\u2019 requirements in support of business strategic goals and objectives.\n\n\u2022\u00a0\u00a0 \u00a0Support in special investigation case or other tasks requested by Regulatory Compliance team\n\n\u2022\u00a0\u00a0 \u00a0Support in Monitoring Day to Day data management (CBX/LUP/DE) Liaise with relevant department and sourcing team for Factory Registration Form follow up.\n\n\u2022\u00a0\u00a0 \u00a0Monitor and ensure the distribution and communicate company Guidelines and Requirements to factories when required\n\nWhat will you need?\n\n\u2022\u00a0\u00a0 \u00a0Minimum Bachelor\u2019s degree holder in related field\n\n\u2022\u00a0\u00a0 \u00a0At least 3-5 years relevant experience in a sizeable organization with social compliance, BSCI/ SA8000, Better Work Factory, ACCORD or equivalent standards is a must\n\n\u2022\u00a0\u00a0 \u00a0leadership experience and preferably with remote team(s); leading remote team experience preferred.\n\n\u2022\u00a0\u00a0 \u00a0Experience with manufacturing environment, auditing and remediation\n\n\u2022\u00a0\u00a0 \u00a0Profound understanding on environment, health & safety regulations and international labour standard\n\n\u2022\u00a0\u00a0 \u00a0Sensitive to cultural differences with country / regional coverage\n\n\u2022\u00a0\u00a0 \u00a0Strong communication, interpersonal and problem-solving skills, able to interact with all levels\n\n\u2022\u00a0\u00a0 \u00a0Autonomous, proactive, detailed and commercially minded\n\n\u2022\u00a0\u00a0 \u00a0High degree of work ethics and integrity\n\n\u2022\u00a0\u00a0 \u00a0Good command of both in spoken & written English, \u00a0in spoken Cantonese and Mandarin.\n\n\u2022\u00a0\u00a0 \u00a0Good knowledge of Microsoft applications PowerPoint, Word & Excel\u00a0\n\n\u2022\u00a0\u00a0 \u00a0ISO14000 experience is also beneficial\n\n\u2022\u00a0\u00a0 \u00a0Willing to travel occasionally\n\nWhat do we offer?\n\nWe are dedicated to fostering a family-friendly culture and work environment and we are an equal opportunities employer and welcome applications from all candidates with the required skills and experience.\n\nMarket Leading Remuneration Package:\n\nDouble pay and discretionary bonus\n\nChoice of MPF provider\n\nLife Insurance\n\nMedical Insurance\n\n\n\n\u00a0\n\nSupportive Environment:\n\nRental re-imbursement scheme\n\nFlexible work arrangements\n\nIn-house training courses\n\nTraining sponsorship scheme\n\nHealth Check\n\nVision Check\n\nSupporting your child's education with advice from a leading education consultant\n\n\n\n\u00a0\n\nWork-Life Balance:\n\n5 day week\n\nCompetitive Annual Leave\n\nCharity, Community and Sporting Events", "employment_types": ["Full Time"], "selling_points": ["Social compliance, BSCI/ SA8000, Better Work Factory, ACCORD or equivalent standards is a must", "At least 3-5 years relevant experience in a sizeable organization", "Experience with manufacturing environment, auditing and remediation"], "locations": ["Others"], "categories": ["Manufacturing", "Manufacturing Management", "Quality Assurance, Control & Testing / ISO"], "post_time": "2022-01-18T03:56:27Z", "salary": {"currency": null, "max": null, "min": null, "period": "monthly", "term": null}, "salary_visible": false, "title_keywords": ["specialist"], "responsibilities": ["regulations", "data", "schedules", "merchandising", "audit", "communication", "evaluation", "liaise with", "plans", "compliance", "monitor", "teams", "other tasks", "visual", "report", "management", "monitoring", "review", "procedures", "investigation", "booking", "audits", "documentation", "communicate with", "company guidelines", "quality control", "auditing"], "requirements": {"degrees": ["degree", "bachelor", "degree holder"], "majors": [], "languages": ["cantonese", "english", "mandarin"], "language_level": ["good command"], "hard_skills": ["merchandizing", "excel", "data management", "microsoft applications", "word", "powerpoint", "make", "documentation", "problem-solving skills"], "soft_skills": ["proactive", "integrity", "collaborative", "communication", "sensitive to", "autonomous", "problem-solving skills", "accurate", "leadership", "interpersonal", "detailed"], "languages_combined": [{"language": "cantonese", "language_level": ["good command"]}, {"language": "english", "language_level": ["good command"]}, {"language": "mandarin", "language_level": ["good command"]}]}, "experience_required": {"duration": ["at least 3-5 years"], "field": ["manufacturing", "compliance", "relevant experience", "team"]}}, {"job_id": "100003009056165", "location_code": "hk", "company": "Cathay Pacific Catering Services (H.K.) Limited", "job_title": "Duty Manager", "description": "Responsibilities\n\n\nAct as a leader of Duty Office to ensure a smooth operation and take necessary follow-up action as required\nPerform in-house and airport ramp areas patrolling and report irregularities\nMake decision when handles accidents, irregularities and emergency cases and perform investigations and follow up actions\nServe as the key coordinator to handle flight movement to ensure timely information and service quality\nExecute company\u2019s BCP when applicable to minimize impact on operations\nUnderstand and uphold company quality standards in terms of hygiene, safety and security requirement\nCoordinate transportation service arrangement and answer enquiries from customers\nRequirements\n\nTertiary educated, preferably related to operations or facilities management\nAt least 7 years\u2019 relevant working experience, preferably in airline or transportation industry\nHands-on experience in crisis/risk management, handling of emergency cases, facility management or execution of business continuity plan is an advantage\nHolder of driving license no. 1 or/and 2\nProficiency in MS Office\nGood command of written and spoken English and Chinese\nStrong problem solving and interpersonal skills\n24-hours shift duty is required\nWe offer a competitive remuneration package and a full range of benefits. Interested parties please send\u00a0your resume\u00a0with\u00a0your current and expected salary\u00a0to Head of People,11 Catering Road East, Hong Kong International Airport, Lantau, Hong Kong or by clicking the \"Apply Now\" button\u00a0on or before 10 February 2022.\n\n\nPersonal data collected will be treated in the strictest confidence and only be used for recruitment related purpose. Applicants who do not receive notification for interview within six weeks may consider their application unsuccessful.", "employment_types": ["Full Time", "Permanent"], "selling_points": ["Ensure a smooth operation", "Make decision when handles accidents", "Perform patrolling"], "locations": ["Airport Area"], "categories": ["Manufacturing", "Manufacturing Management", "Property / Real Estate", "Property Management", "Others", "Security / Safety Control"], "post_time": "2022-01-18T03:27:30Z", "salary": {"currency": null, "max": null, "min": null, "period": "monthly", "term": null}, "salary_visible": false, "title_keywords": ["manager"], "responsibilities": ["irregularities", "operations", "quality", "coordinate", "hygiene", "security requirement", "report irregularities"], "requirements": {"degrees": [], "majors": [], "languages": ["english", "chinese"], "language_level": ["good command"], "hard_skills": ["no", "airline", "problem solving", "facilities management", "ms office"], "soft_skills": ["problem solving", "hands-on", "interpersonal skills"], "languages_combined": [{"language": "english", "language_level": ["good command"]}, {"language": "chinese", "language_level": ["good command"]}]}, "experience_required": {"duration": ["at least 7 years"], "field": ["risk management", "management", "business", "relevant working experience"]}}, {"job_id": "100003009055760", "location_code": "hk", "company": "Amoy Food Ltd", "job_title": "\u751f\u7522\u6280\u8853\u54e1 (\u4e0d\u9700\u8f2a\u73ed)", "description": "\u8077\u8cac\uff1a\n\n\u64cd\u4f5c\u751f\u7522\u6a5f\u5668 / \u9810\u5099\u539f\u6599\u00a0\n\u9810\u5099\u751f\u7522\u7269\u6599\uff0c\u914d\u5408\u751f\u7522\u8981\u6c42\n\u7dad\u6301\u751f\u7522\u7dda\u4e4b\u6b63\u5e38\u904b\u4f5c\n\u5165\u8077\u8981\u6c42\uff1a\n\u51771-2\u5e74\u7684\u98df\u54c1\u751f\u7522\n\u85aa\u91d1\u4e36\u798f\u5229\u53ca\u5de5\u4f5c\u6642\u9593\uff1a\n\n\n\u6bcf\u6708$15,000 - $18,000\n\u514d\u8cbb\u7a7f\u68ad\u5df4\u58eb\u670d\u52d9\n\u514d\u8cbb\u5348\u994d\u63d0\u4f9b\n\u914c\u60c5\u82b1\u7d05\n\u52a0\u73ed\u6d25\u8cbc\n\u5728\u8077\u57f9\u8a13\n\u54e1\u5de5\u8cfc\u7269\u512a\u60e0\n\u661f\u671f\u4e00\u81f3\u4e94\uff1a\u4e0a\u53488:15 \u81f3\u4e0b\u53486:20\n\n\u4e0d\u9700\u8f2a\u73ed\n\n\u7533\u8acb\u65b9\u6cd5\n1. \u81f4\u96fb 5545-8814 \u6216\n2. \u6309\u201cApply Now\u201d \u6216\n3. \u5c07\u500b\u4eba\u5c65\u6b77\u90f5\u5bc4\u81f3\u65b0\u754c\u5927\u57d4\u5de5\u696d\u90a8\u5927\u5bcc\u885711-15\u865f \u4eba\u529b\u8cc7\u6e90\u90e8\u6536 \u6216\n4. \u50b3\u771f\u81f32666-6575\n\n\uff08\u7533\u8acb\u4eba\u63d0\u4f9b\u4e4b\u8cc7\u6599\u5c07\u7d55\u5c0d\u4fdd\u5bc6\u53ca\u53ea\u4f5c\u62db\u8058\u7528\u9014\uff09\u00a0", "employment_types": ["Full Time", "Permanent"], "selling_points": ["\u64cd\u4f5c\u751f\u7522\u6a5f\u5668 / \u9810\u5099\u539f\u6599", "\u4e94\u5929\u5de5\u4f5c\uff0c \u5ee0\u8eca\u63a5\u9001\uff0c\u82b1\u7d05\uff0c\u91ab\u7642\u798f\u5229\uff0c\u5f37\u7a4d\u91d1", "\u9810\u5099\u751f\u7522\u7269\u6599\uff0c\u914d\u5408\u751f\u7522\u8981\u6c42\uff0c\u7dad\u6301\u751f\u7522\u7dda\u4e4b\u6b63\u5e38\u904b\u4f5c"], "locations": ["Tai Po Area"], "categories": ["Manufacturing", "Manufacturing Management", "Production Planning / Control", "Quality Assurance, Control & Testing / ISO"], "post_time": "2022-01-18T02:55:46Z", "salary": {"currency": null, "max": null, "min": null, "period": "monthly", "term": null}, "salary_visible": false, "title_keywords": ["\u751f\u7522\u6280\u8853\u54e1"], "responsibilities": [], "requirements": {"degrees": [], "majors": [], "languages": [], "language_level": [], "hard_skills": [], "soft_skills": [], "languages_combined": []}, "experience_required": {"duration": [], "field": []}}, {"job_id": "100003009056156", "location_code": "hk", "company": "Cathay Pacific Catering Services (H.K.) Limited", "job_title": "Assistant Logistics Manager (Ramp Services)", "description": "Responsibilities\n\nMaintains a high standard of loading & unloading procedures and ensures an on-time performance of all flights\nEnsures efficient aircraft handling and smoothen daily operations\nMonitor and enhances subordinates\u2019 working performance\nEnsures the Company\u2019s regulations are followed strictly\nReviews the existing procedures/resources and plans for a better development\nMaintains a harmonic working atmosphere and executes fair-minded measures at all times\nMaintains a good relationship with the customers and provides satisfactory services to minimize complaints\nPerforms ad hoc duties as directed by Loading Services Manager\nRequirements\n\nTertiary Education in Operations Management or related disciplines\nMinimum 5 years of relevant working experience in a supervisory level\nHolder of a valid driving license (No. 1 and 2) is an advantage\nGood communication skills, leadership and interpersonal skills\nAble to work independently under pressure and follow tight schedules\nProficient in PC applications, including MS Word, PowerPoint and Excel\nGood command of English and Chinese, both written and spoken\nShift duty is required\nWe offer a competitive remuneration package and a full range of benefits. Interested parties please send your resume with your current and expected salary to Head of People,11 Catering Road East, Hong Kong International Airport, Lantau, Hong Kong or by clicking the \"Apply Now\" button\u00a0on or before 10 February 2022.\nPersonal data collected will be treated in the strictest confidence and only be used for recruitment-related purposes. Applicants who do not receive notification for an interview within six weeks may consider their application unsuccessful.", "employment_types": ["Full Time", "Permanent"], "selling_points": ["Logistics Management", "Operations Services Enhancement", "Career advancement opportunities"], "locations": ["Airport Area"], "categories": ["Transportation & Logistics", "Aviation Services", "Shipping", "Manufacturing", "Manufacturing Management"], "post_time": "2022-01-18T03:26:29Z", "salary": {"currency": null, "max": null, "min": null, "period": "monthly", "term": null}, "salary_visible": false, "title_keywords": ["logistics manager", "assistant"], "responsibilities": ["regulations", "ad hoc duties", "procedures", "monitor", "good relationship", "daily operations", "plans"], "requirements": {"degrees": [], "majors": [], "languages": ["english", "chinese"], "language_level": ["good command"], "hard_skills": ["excel", "no", "powerpoint", "pc applications", "ms word"], "soft_skills": ["communication skills", "work independently", "under pressure", "interpersonal skills", "leadership"], "languages_combined": [{"language": "english", "language_level": ["good command"]}, {"language": "chinese", "language_level": ["good command"]}]}, "experience_required": {"duration": ["minimum 5 years"], "field": ["supervisory level", "relevant working experience"]}}, {"job_id": "100003009056029", "location_code": "hk", "company": "ConnectedGroup Limited", "job_title": "Assistant Supply Chain Manager", "description": "ConnectedGroup is partnering with a multinational consumer electronics company headquartered in the U.S in searching for an Assistant Supply Chain Manager.\n\nResponsibilities:\n\n* Responsible for preparing and analyzing Demand and Supply forecasts to ensure the delivery of highly accurate plans\n* Control and maintain appropriate inventory norms and ensure availability of materials anytime\n* Enhance relationships with suppliers as well as be responsible for negotiation with suppliers\n* Supervise receiving and warehousing procedure\n* Oversee distribution of suppliers in the organization\n\nRequirement:\n\n* Higher diploma or degree holder in Supply Chain or logistic management or related discipline\n* 4+ years' experience in end-to-end supply chain management\n* Good understanding of chemical components OR manufacturing industry is a plus\n* Willing to travel to China regularly", "employment_types": ["Full Time", "Permanent"], "selling_points": ["A well- known multinational chemical company", "Solid experience in End-to-end Supply Chain", "Chemical/Manufacturing background is preferable"], "locations": ["Not Specified"], "categories": ["Transportation & Logistics", "Inventory / Warehousing", "Manufacturing", "Manufacturing Management"], "post_time": "2022-01-18T03:12:18Z", "salary": {"currency": null, "max": null, "min": null, "period": "monthly", "term": null}, "salary_visible": false, "title_keywords": ["assistant supply chain manager"], "responsibilities": ["warehousing", "control", "inventory", "maintain", "plans"], "requirements": {"degrees": ["diploma", "degree holder"], "majors": [], "languages": [], "language_level": [], "hard_skills": ["plus"], "soft_skills": [], "languages_combined": []}, "experience_required": {"duration": ["4+ years"], "field": ["supply chain", "management"]}}, {"job_id": "100003009050064", "location_code": "hk", "company": "Karrie International Holdings Limited", "job_title": "Assistant Marketing Manager (Manufacturing Experience Needed & Based in Dongguan)", "description": "Responsibilities:\n\nAssist the marketing manager to fix business strategies\nManage the full process of projects including RFQ, project meeting, order management and follow up the payments\nWork with the internal and external teams to conduct marketing Research\u00a0\nProvide customer services in order to maintain existing accounts and further expand the customer base\nGenerate cost analysis on budget and to achieve the KPI of department\nPerform any ad-hoc assignments/projects as assigned\n\nRequirements:\n\nHigher Diploma or above in Marketing, Manufacturing Engineering and Product Design and etc.\nMinimum 3-5 years relevant working experience\nExcellent communication, negotiation, persuasion skills, planning and organization skills.\nStrong presentation, problem solving skills, analytical power and opened mind.\nStrong sense of team work, aggressiveness, responsible and proactive character.\nProficient in MS Office applications. (Excel, Access, PowerPoint, etc)\nExcellent command of written and spoken English and Mandarin.\nBased in Dongguan factory\nLess experience will be considered as Senior Marketing Executive\n\nInterested parties please click \"Apply Now\" to send\u00a0full resume with the date of availability and expected salary\u00a0\n\nOr post it to \"The\u00a0 Group HR Department, Karrie International Holdings Limited, 9/F, Southeast Industrial Building, 611-619 Castle Peak Road, Tsuen Wan, N.T.\" (Please Attn Recruitment Team and quote Ref. on the envelope)\n\nFor more information, please visit our website at http://www2.karrie.com/en, or visit\u00a0 \u00a0https://www.youtube.com/watch?v=y3Lhgl7ylf8&list=PL66rAPgv5k9ykDxduveZ6E7Yni9e39jBZ\n\n** We are an equal opportunity employer and welcome applications from all qualified candidates.\u00a0Personal data\u00a0provided by job applicants will be used strictly in accordance with the employer's personal data policies, a copy of which will be provided immediately upon request. **", "employment_types": ["Full Time", "Permanent"], "selling_points": ["5 Days Work", "Medical Claim", "Performance Bonus"], "locations": ["Others - China"], "categories": ["Manufacturing", "Manufacturing Management", "Marketing / Public Relations", "Marketing - General / Support"], "post_time": "2022-01-15T03:50:49Z", "salary": {"currency": null, "max": null, "min": null, "period": "monthly", "term": null}, "salary_visible": false, "title_keywords": ["assistant marketing manager"], "responsibilities": ["order management", "ad-hoc assignments", "budget", "teams", "customer services", "marketing research", "maintain", "payments", "cost analysis"], "requirements": {"degrees": ["higher diploma or above"], "majors": ["manufacturing", "marketing", "engineering", "design"], "languages": ["english", "mandarin"], "language_level": ["excellent"], "hard_skills": ["excel", "problem solving skills", "powerpoint", "ms office"], "soft_skills": ["negotiation", "responsible", "communication", "organization skills", "problem solving skills", "proactive", "presentation"], "languages_combined": [{"language": "english", "language_level": ["excellent"]}, {"language": "mandarin", "language_level": ["excellent"]}]}, "experience_required": {"duration": ["minimum 3-5 years"], "field": ["marketing", "relevant working experience"]}}, {"job_id": "100003009055762", "location_code": "hk", "company": "Amoy Food Ltd", "job_title": "Senior Production Officer / Production Officer (Food Industry)", "description": "Responsibilities:\n\nLaunch new product and closely work with QA and R&D department\nLead a team of operators and manage day-to-day operation of food production lines to achieve production schedules and targets\nAssist Manager in developing and implementing production and quality systems and ensure compliance of related requirements and standards with strong food safety sense\nPerform analysis on work flow and production efficiency regularly, collect and maintain accurate records and support month-end reports\nParticipate in regular factory audits and checks, and take up ad hoc assignments\n\nRequirements:\n\nHigher Diploma or above in Food Science,\u00a0Manufacturing, Industrial Engineering or related discipline\n2-4 years of relevant experience in manufacturing industry, preferably in food factory\nKnowledge of ISO22000 / HACCP / BRC will be an advantage\nDetail-minded, well-organized and sensitive to figures, self-motivated and willing to take up challenges\nTeam-player, willing to learn and with good communication and problem-solving skills\nProficient in both English and Mandarin as well as in computer applications, knowledge in SAP will be an advantage\nCandidate with more experience will be considered as Senior Production Officer\n\n\u00a0Interested parties please send your resume with current and expected salary and availability:\n\n- \u00a0by fax to 2666 6575\n- \u00a0by mail to\n\u00a0 \u00a0Human Resources Director\n\u00a0 \u00a0Amoy Food Limited\n\u00a0 \u00a011-15 Dai Fu Street,Tai Po Industrial Estate,Tai Po, N.T.\n- \u00a0by \u201cApply Now\u201d\n\nFor enquiries, please contact our Recruitment Hotline at 26603403.\u00a0Employment Application Form can be downloaded from the company website\u00a0www.amoy.com\n\nAll applications will be treated in strict confidence and retained for 6 months for recruitment purposes only.\u00a0\u00a0", "employment_types": ["Full Time", "Permanent"], "selling_points": ["Launch new product/revamp product with QA & R&D", "Higher diploma in Food Science / Nutrition", "Open-minded, seek for new challenges, passion"], "locations": ["Tai Po Area"], "categories": ["Manufacturing", "Manufacturing Management", "Production Planning / Control", "Quality Assurance, Control & Testing / ISO"], "post_time": "2022-01-18T02:55:46Z", "salary": {"currency": null, "max": null, "min": null, "period": "monthly", "term": null}, "salary_visible": false, "title_keywords": ["production officer"], "responsibilities": ["food safety", "schedules", "analysis", "systems", "quality", "developing", "month-end", "ensure compliance", "lead a team", "maintain", "reports", "ad hoc assignments", "audits", "day-to-day operation"], "requirements": {"degrees": ["higher diploma or above"], "majors": ["manufacturing", "engineering", "food science"], "languages": ["english", "mandarin"], "language_level": ["advantage", "proficient"], "hard_skills": ["problem-solving skills", "sap"], "soft_skills": ["detail-minded", "self-motivated", "team-player", "sensitive to figures", "well-organized", "willing to learn", "communication", "problem-solving skills"], "languages_combined": [{"language": "english", "language_level": ["advantage", "proficient"]}, {"language": "mandarin", "language_level": ["advantage", "proficient"]}]}, "experience_required": {"duration": ["2-4 years"], "field": ["food", "relevant experience", "manufacturing industry"]}}, {"job_id": "100003009052401", "location_code": "hk", "company": "Defond Electrical Industries Limited", "job_title": "Senior Project Coordinator / Assistant Project Manager", "description": "Responsibilities:\nHandle projects of electronics/electro-mechanical modules to ensure timeline and cost are match with expectation\nPrepare product planning, quotation/cost analysis, budgeting, new product introduction process and other project activities\nCommunication with stakeholders on progress review for smooth project management\nManage and advice for all issues of projects like quality, provide alternative and solutions for problem solving and suggest for operation improvement\n\n\nRequirements:\n\nDegree holder in Engineering or related disciplines; PMP certification holder is preferable\n5\u00a0years\u2019 project management experience in electronic manufacturing\u00a0industry\nStrong knowledge in manufacturing and engineering drawings\nStrong analytical and problem solving skills, proactive and result-oriented\nExcellent interpersonal, negotiation and prioritization skills within tight schedule\nTeam player with good communication and interpersonal skills\nExcellent command of both written and spoken English and Putonghua\nOccasional travel to China is required\nImmediate availability is an advantage\n\nFor more information, please visit our website:\u00a0\u00a0http://defondetech.com/\n\nPersonal data collected will be used for recruitment purpose only.", "employment_types": ["Full Time"], "selling_points": ["Responsible for project management and milestones", "Product planning, quotation/cost analysis", "5-day work week, 13th-month salary"], "locations": ["Chai Wan"], "categories": ["Engineering", "Engineering Project Management", "Manufacturing & Production", "Manufacturing", "Manufacturing Management"], "post_time": "2022-01-17T02:57:32Z", "salary": {"currency": null, "max": null, "min": null, "period": "monthly", "term": null}, "salary_visible": false, "title_keywords": ["assistant project manager", "senior project coordinator"], "responsibilities": ["cost", "budgeting", "quotation", "review", "quality", "communication", "project management", "cost analysis", "planning"], "requirements": {"degrees": ["degree holder"], "majors": ["related disciplines", "engineering"], "languages": ["putonghua", "english"], "language_level": ["excellent"], "hard_skills": ["project management", "pmp", "problem solving skills"], "soft_skills": ["negotiation", "interpersonal", "project management", "analytical and problem solving skills", "communication and interpersonal skills", "team player", "proactive", "result-oriented"], "languages_combined": [{"language": "putonghua", "language_level": ["excellent"]}, {"language": "english", "language_level": ["excellent"]}]}, "experience_required": {"duration": ["5 years"], "field": ["project management", "manufacturing industry"]}}, {"job_id": "100003009048057", "location_code": "hk", "company": "The Hang Seng University of Hong Kong", "job_title": "Procurement Manager \u2013 Finance Office  (Ref: PM (FO) 2022-01-14)", "description": "Responsibilities:\n\nLead Production & PIE team, responsible for plant level daily production issue & related issues.\nWork with Quality & Supply Chain team, achieve quality and delivery requirement.\nDrive Production and PIE team for continuous improvement, including but not limited to Quality, efficiency and cost\nEnsure a smooth plant operation that complies with internal policies & customer requirements.\nDriving the team performance by set up proper KPI.\nDesign & prepare various report to management regarding Operation performance \u2013 efficiency, Quality, cost etc.\nGood team player with strong management skills\nAd hot assignment from management\n\nRequirement:\n\nDegree or above in Industrial Engineering, Manufacturing / Mechanical / Electronic engineering or other related discipline.\nMin 10 years\u2019 experience in Manufacturing Engineering industry, at least 5 years in managerial level.\nExtensive knowledge in IE, automation & Lean implementation experience. Good ERP experience will be an advantage but not essential.\nExperience in ISO 13485 or FDA requirement will be an advantages\nWell-organized, detail-minded, responsible and able to work independent under pressure.\nA good leader with self-motivation, strong data analytical, problem-solving and logical thinking abilities.\nHigh level of interpersonal, negotiation and presentation skills.\nFluent proficiency in both spoken and written Chinese, English and Mandarin.\nStation in China.\nCandidates with less experience will considered as Senior Manager, Operation.\nCandidates with less working experience will be considered as\u00a0Operation\nAssistant Director.\n\n\n\nAttractive remuneration package will be offered to suitable talent. Please send us an email to obtain an application form.\n\nInterested candidates, please contact us at 51238635 for company details before applying.", "employment_types": ["Full Time", "Permanent"], "selling_points": [], "locations": ["Not Specified"], "categories": ["Manufacturing", "Manufacturing Management", "Merchandising & Purchasing", "Others", "Procurement / Purchasing / Sourcing"], "post_time": "2022-01-14T11:52:34Z", "salary": {"currency": null, "max": null, "min": null, "period": "monthly", "term": null}, "salary_visible": false, "title_keywords": ["manager"], "responsibilities": ["cost", "management", "policies", "quality", "design", "report"], "requirements": {"degrees": ["degree or above"], "majors": ["manufacturing", "engineering"], "languages": ["english", "chinese", "mandarin"], "language_level": ["proficiency", "fluent"], "hard_skills": ["problem-solving", "lean", "erp"], "soft_skills": ["detail-minded", "independent", "under pressure", "responsible", "negotiation", "problem-solving", "well-organized", "presentation skills", "self-motivation", "extensive", "interpersonal"], "languages_combined": [{"language": "english", "language_level": ["proficiency", "fluent"]}, {"language": "chinese", "language_level": ["proficiency", "fluent"]}, {"language": "mandarin", "language_level": ["proficiency", "fluent"]}]}, "experience_required": {"duration": ["at least 5 years", "min 10 years"], "field": ["managerial", "manufacturing", "engineering", "operation"]}}, {"job_id": "100003009041887", "location_code": "hk", "company": "Goodrich Asia-Pacific Limited", "job_title": "Continuous Improvement Lead", "description": "Position summary:\n\nResponsible for leading and implementing organizational change, Lean manufacturing, development of quality and production management programs to assist internal and external parties with initiatives to reengineer processes and methods to ensure company objectives in the area of cost, efficiency, and quality are met.\u00a0\n\nJob Responsibilities:\n\nEnhance continuous improvement culture by implementing RTX CORE operating system\nAssess CORE initiatives and provide input and recommendations on future events and plans for CORE deployment activity\nPlan, lead, facilitate, close and follow-up on improvement events and projects\nManage improvement projects to align with and support policy deployment goals, using the fundamental tools\nPrepare training materials and reports, and train employees on CORE tools, skills and principles\nDevelop and mentor others (and self) to become leaders in CORE principles\nOther duties as assigned\n\n\u00a0Requirements:\n\nDegree in an Engineering discipline, preferably Mechanical, Manufacturing, Industrial or Production Engineering.\n4 - 7 years of working experience in a manufacturing environment is preferred.\nStrong skills and knowledge of lean, continuous improvement or six sigma.\nSelf-starter with strong communication skills and ability to work with all levels of staff.\nIndependent and possess initiative to drive the continuous improvement culture\nFluent English and Cantonese\nComputer literate\n\nWe offer excellent career prospects and attractive remuneration package to the right candidate. Interested parties please apply with a full resume and expected salary and click \u201cApply Now\u201d\n\n\n\nRaytheon Technologies Corporation is An Equal Opportunity/Affirmative Action Employer. All qualified applicants will receive consideration for employment without regard\u00a0to race, color, religion,\u00a0sex, sexual orientation, gender identity, national origin, disability or veteran status, age or any other federally protected class.\n\nAll information provided by candidates will be treated in strict confidence and will be used for employment purposes only.\n\n\n", "employment_types": ["Full Time", "Permanent"], "selling_points": ["Leading and implementing organizational change", "Lean manufacturing", "Continuous Improvement"], "locations": ["Tseung Kwan O"], "categories": ["Engineering", "Manufacturing & Production", "Manufacturing", "Manufacturing Management"], "post_time": "2022-01-14T09:24:58Z", "salary": {"currency": null, "max": null, "min": null, "period": "monthly", "term": null}, "salary_visible": false, "title_keywords": ["lead"], "responsibilities": ["other duties", "develop", "reports", "plan", "plans"], "requirements": {"degrees": ["degree"], "majors": ["manufacturing", "engineering"], "languages": ["cantonese", "english"], "language_level": ["fluent"], "hard_skills": ["six sigma", "lean"], "soft_skills": ["communication skills", "independent", "initiative"], "languages_combined": [{"language": "cantonese", "language_level": ["fluent"]}, {"language": "english", "language_level": ["fluent"]}]}, "experience_required": {"duration": ["4 - 7 years"], "field": ["manufacturing"]}}, {"job_id": "100003009042532", "location_code": "hk", "company": "Hong Kong Gourmet Ltd", "job_title": "\u5eda\u5e2b - \u4e2d\u592e\u5eda\u623f", "description": "\u4e3b\u8981\u8077\u8cac:\n\n\u8ca0\u8cac\u65bc\u4e2d\u592e\u5eda\u623f\u88fd\u4f5c\u5b78\u751f\u98ef\u76d2\u81b3\u98df;\u00a0\u76e3\u63a7\u751f\u7522\u6d41\u7a0b\u904b\u4f5c;\n\u70f9\u8abf\u98df\u6750\u53ca\u63a7\u5236\u98df\u7269\u8cea\u7d20\u53ca\u5473\u9053;\n\u8ca0\u8cac\u5b78\u6821\u53ca\u54e1\u5de5\u98ef\u5802\u6bcf\u65e5\u7684\u9910\u55ae\u8a2d\u8a08;\n\u54c1\u8cea\u76e3\u63a7\u3001\u98df\u54c1\u5b89\u5168\u885b\u751f\u53ca\u8077\u5b89\u5065\n\n\u8077\u4f4d\u8981\u6c42:\n\n\n\u4e2d\u4e94\u7a0b\u5ea6;\n5\u5e74\u4ee5\u4e0a\u4e2d\u53ca\u897f\u5eda\u7d93\u9a57;\n\u6709\u9152\u5e97\u5927\u578b\u5bb4\u6703\u3001\u8655\u7406\u5718\u9ad4\u81b3\u98df\u7d93\u9a57\u512a\u5148\n\u5177\u826f\u597d\u6e9d\u901a\u5354\u8abf\u53ca\u9818\u5c0e\u7ba1\u7406\u6280\u5de7;\n\u719f\u6089\u98df\u54c1\u5b89\u5168\u885b\u751f\u689d\u4f8b\u53ca\u5177\u300c\u98df\u7269\u885b\u751f\u7d93\u7406\u300d\u8a8d\u8b49\u512a\u5148\n\n\u5de5\u4f5c\u5730\u9ede\u53ca\u6642\u9593:\n\n\n\u5c6f\u9580\u5de5\u696d\u5340\u5de5\u4f5c\n\u665a\u4e0a11\u6642\u81f3\u65e9\u4e0a10\u6642(5\u5929\u5de5\u4f5c\u958b\u5b78\u5f8c) \u53ca \u65e9\u4e0a6\u6642\u81f3\u4e0b\u53484\u6642(5.5\u5929\u6691\u5047/\u505c\u8ab2\u671f\u9593), 55\u5c0f\u6642/\u4e00\u661f\u671f\n\u9700\u8f2a\u73ed, \u6bcf\u90315-6\u5929\u5de5\u4f5c\n\u516c\u53f8\u798f\u5229:\n\n\u96d9\u7ce7\n\u9280\u884c\u5047\u671f\n\u6709\u85aa\u5e74\u5047\n\u91ab\u7642\u798f\u5229\n\u914c\u60c5\u6027\u82b1\u7d05\n\u7533\u8acb\u8fa6\u6cd5:\n\n\n\u7533\u8acb\u8005\u8acb\u8a73\u5217\u7533\u8acb\u8077\u4f4d\u540d\u7a31\u3001\u8cc7\u6b77\u53ca\u8981\u6c42\u5f85\u9047\uff0c\u4e26\u900f\u904e\"APPLY NOW\"\u00a0\u7533\u8acb\u3002\u5982\u6709\u4efb\u4f55\u67e5\u8a62\uff0c\u8acbwhatsapp 9382 9238\u3002\n\n\u7533\u8acb\u4eba\u6240\u63d0\u4f9b\u7684\u500b\u4eba\u8cc7\u6599\u5c07\u53ea\u7528\u65bc\u672c\u516c\u53f8\u53ca\u5176\u95dc\u806f\u53ca\u9644\u5c6c\u6a5f\u69cb\u4e4b\u62db\u8058\u7528\u9014\u3002\u5982\u679c\u3000\u95a3\u4e0b\u4e0d\u63d0\u4f9b\u62db\u8058\u5ee3\u544a\u4e2d\u63d0\u53ca\u7684\u8cc7\u6599\uff0c\u6211\u5011\u53ef\u80fd\u7121\u6cd5\u8a55\u4f30\u3000\u95a3\u4e0b\u7684\u5de5\u4f5c\u7533\u8acb\u3002\u3000\u95a3\u4e0b\u6709\u6b0a\u5411\u6211\u5011\u7684\u8cc7\uf9be\u4fdd\u969c\u4e3b\u4efb\u806f\u7e6b\u00a0(\u96fb\u90f5: pdpo@ vitasoy.com)\u00a0\u63d0\u51fa\u67e5\u95b1\u53ca\u6216\u6539\u6b63\u95a3\u4e0b\u7684\u500b\u4eba\u8cc7\u6599\uff0c\u60df\u672c\u516c\u53f8\u6703\u5728\u62db\u8058\u904e\u7a0b\u7d50\u675f\u5f8c\u624d\u8655\u7406\u6709\u95dc\u67e5\u95b1\u8981\u6c42\u3002", "employment_types": ["Full Time"], "selling_points": ["\u5eda\u5e2b - \u4e2d\u592e\u5eda\u623f", "55\u5c0f\u6642/\u4e00\u661f\u671f", "\u6709\u9152\u5e97\u5927\u578b\u5bb4\u6703\u3001\u8655\u7406\u5718\u9ad4\u81b3\u98df\u7d93\u9a57\u512a\u5148"], "locations": ["Tuen Mun Area"], "categories": ["Hospitality / F & B", "Food & Beverage", "Others", "Manufacturing", "Manufacturing Management"], "post_time": "2022-01-12T07:53:20Z", "salary": {"currency": null, "max": null, "min": null, "period": "monthly", "term": null}, "salary_visible": false, "title_keywords": ["\u5eda\u5e2b"], "responsibilities": [], "requirements": {"degrees": [], "majors": [], "languages": [], "language_level": [], "hard_skills": [], "soft_skills": [], "languages_combined": []}, "experience_required": {"duration": [], "field": []}}, {"job_id": "100003009039229", "location_code": "hk", "company": "Ampd Energy Limited", "job_title": "Director of Manufacturing", "description": "Summary of the Position\n\nAMPD Energy is seeking a talented and passionate individual to plan, direct, coordinate, and implement a world class assembly, configuration, and test process and to localize this process to multiple global sites. You will be working closely with leaders and teams in R&D, Field Engineering, and Supply Chain to assess the current state and develop plans for standardization and improvement and then implement. The successful candidate will be passionate about continuous improvement and excited about the opportunity to manage a process at multiple sites.\n\nWe are specifically looking for individuals who are organised, detail-oriented, and dependable. Ideally you have extensive experience in Process Management and a strong background in Lean-Six Sigma principles, Quality Tools, and best practices. This is a leadership role and so you must have specific leadership experience and outstanding leadership qualities. You will be expected to work well independently and to communicate clearly and effectively in English and preferably also Chinese.\n\nKnowledge, Qualifications and Skills\n\n\u00a0\u00a0\u00a0\u00a0\u00a0\u00a0\u00a0 Higher diploma or bachelor\u2019s degree preferably in Engineering or related field. Master\u2019s degree preferred.\n\u00a0\u00a0\u00a0\u00a0\u00a0\u00a0\u00a0 Minimum 5 years of Process or Manufacturing Management experience.\n\u00a0\u00a0\u00a0\u00a0\u00a0\u00a0\u00a0 Great planning skills, and excellent project and time management track record.\n\u00a0\u00a0\u00a0\u00a0\u00a0\u00a0\u00a0 Experience with Lean & Six Sigma principles. Experience with Quality Control in a manufacturing environment.\n\u00a0\u00a0\u00a0\u00a0\u00a0\u00a0\u00a0 Knowledge of and practice with the basic Quality Tools, 8D problem solving, SPC, ANOVA, GR&R, PPAP, Cpk analysis, and other common measurement and analytical tools.\n\u00a0\u00a0\u00a0\u00a0\u00a0\u00a0\u00a0 Great documentation, presentation, and report writing skills.\n\u00a0\u00a0\u00a0\u00a0\u00a0\u00a0\u00a0 Background in industrial and/or electrical workplace safety is a huge plus.\n\u00a0\u00a0\u00a0\u00a0\u00a0\u00a0\u00a0 Proficient in MS Office Applications (Word, Excel, Powerpoint).\n\u00a0\u00a0\u00a0\u00a0\u00a0\u00a0\u00a0 Self-motivated, detailed oriented, organized.\n\u00a0\u00a0\u00a0\u00a0\u00a0\u00a0\u00a0 Good command of spoken and written English, and ideally Chinese.\n\nSpecific duties include:\n\n\u00a0\u00a0\u00a0\u00a0\u00a0\u00a0\u00a0 Manage the assembly and configuration process for the company\u2019s products and be responsible for reporting implementation status, creating and maintaining process documentation such as Process Control Plans and Work Instructions.\n\u00a0\u00a0\u00a0\u00a0\u00a0\u00a0\u00a0 Ensure internal and external documentation meets requirements for compliance, suppliers, customers, and other stakeholders.\n\u00a0\u00a0\u00a0\u00a0\u00a0\u00a0\u00a0 Work effectively and constructively within the company\u2019s Quality Management System\n\u00a0\u00a0\u00a0\u00a0\u00a0\u00a0\u00a0 Continue to keep up to date with latest developments in all relevant standards.\n\u00a0\u00a0\u00a0\u00a0\u00a0\u00a0\u00a0 Provide periodic training for the internal team and suppliers on the assembly process and Process Management.\n\u00a0\u00a0\u00a0\u00a0\u00a0\u00a0\u00a0 Participate in new product development to ensure Assembly and manufacturing issues are addressed throughout the development process and all stakeholders understand requirements from the beginning.\n\nBenefits\n\n\u00a0\u00a0\u00a0\u00a0\u00a0\u00a0\u00a0 Competitive cash package\n\u00a0\u00a0\u00a0\u00a0\u00a0\u00a0\u00a0 Full medical, dental & travel insurance coverage\n\u00a0\u00a0\u00a0\u00a0\u00a0\u00a0\u00a0 Uber travel policy (for business travel & travel after 8pm)\n\nHow to apply\n\nPlease submit your application via https://www.linkedin.com/jobs/view/2868244993.\n\nAll information provided will be treated in strict confidence and used solely for recruitment purposes. We regret that we are only able to notify short-listed candidates.\n\nAmpd Energy is an equal opportunity employer. All candidates will be assessed on merit without regard to race, gender, sexual orientation, religion, nationality, marital status, political affiliation or any other factor protected by law.", "employment_types": ["Full Time", "Permanent"], "selling_points": ["Rapidly Growing Startup Environment", "Minimum 5 years of Related Experience", "Self-motivated, Detailed Oriented, Organized"], "locations": ["Lai Chi Kok"], "categories": ["Management", "General Management", "Manufacturing", "Manufacturing Management", "Others"], "post_time": "2022-01-11T09:05:45Z", "salary": {"currency": null, "max": null, "min": null, "period": "monthly", "term": null}, "salary_visible": false, "title_keywords": ["director"], "responsibilities": ["quality", "plan", "plans", "control", "maintaining", "configuration", "compliance", "teams", "measurement", "implementation", "develop plans", "report", "reporting", "management", "documentation", "analysis", "coordinate", "quality control", "planning"], "requirements": {"degrees": ["diploma", "degree", "bachelor", "master"], "majors": ["engineering"], "languages": ["english", "chinese"], "language_level": ["good command"], "hard_skills": ["r&d", "excel", "lean", "plus", "basic", "analysis", "word", "writing skills", "powerpoint", "problem solving", "six sigma", "documentation", "ms office"], "soft_skills": ["passionate", "planning skills", "self-motivated", "independently", "detailed oriented", "organized", "responsible", "work effectively", "writing skills", "detail-oriented", "problem solving", "leadership", "organised", "time management", "extensive", "presentation", "passionate about"], "languages_combined": [{"language": "english", "language_level": ["good command"]}, {"language": "chinese", "language_level": ["good command"]}]}, "experience_required": {"duration": ["minimum 5 years"], "field": ["management", "manufacturing", "quality control"]}}, {"job_id": "100003009042577", "location_code": "hk", "company": "Swire Coca-Cola HK Ltd", "job_title": "Field Service Operations Supervisor \u5916\u52e4\u670d\u52d9\u71df\u904b\u4e3b\u7ba1", "description": "Responsibilities:\n\n\nSupervise field service team including mechanics & trainees to implement an efficient field service program for cold drink equipment\nAssist the Cold Drink Equipment Service Manager to develop and handle special projects\nMaintain a good communication with customers as well as our internal sales department to facilitate the equipment installation, withdrawal & replacement process\nCommunicate and work closely with workshop supervisor / team leader and other level of staff to improve the technical performance of various equipment & reflect various equipment performance in the market\nAct as an instructor to provide necessary training to different staffs within the department.\nCommunicate both internally and externally with customers, colleagues & suppliers to know the cold drink equipment performance & hence improve the service efficiency\nEnsure customer satisfaction towards the customer service program and carry out corrective actions if any discrepancies are found\nSuggest improvements for upgrading the service efficiency of the in-plant operation of field service activities\nRequirements:\n\nHigher Diploma/Certificate in Electronics & Electrical / Mechanical or Manufacturing Engineering is preferred\n\nAt least 5 years of experience in engineering and maintenance management with at least 1 year in managing a team\nKnowledge of engineering, equipment servicing and quality control (ISO22000 and food safety training is a plus)\nCertificate of Registration of Electrical Worker (Grade R / A) is preferred\nAlways be thinking of how to improve process to be more efficient\nAbility to provide leadership, coaching and mentoring to team members\nExcellent interpersonal and communication skills; a team player\nChange management and project management skills\nGood command of written and spoken English and Cantonese\nHK Driving License 2 is preferred\n\u5de5\u4f5c\u8077\u8cac:\n\n\u76e3\u7763\u5916\u52e4\u670d\u52d9\u5718\u968a\uff0c\u5305\u62ec\u6a5f\u68b0\u5de5\u7a0b\u5e2b\u5e2b\u548c\u5be6\u7fd2\u751f\uff0c\u5be6\u65bd\u9ad8\u6548\u7684\u51b7\u98f2\u8a2d\u5099\u5916\u52e4\u670d\u52d9\u7a0b\u5e8f\n\u5354\u52a9\u51b7\u98f2\u8a2d\u5099\u5916\u52e4\u52d9\u670d\u7d93\u7406\uff0c\u958b\u767c\u548c\u8655\u7406\u7279\u5b9a\u7684\u9805\u76ee\n\u8207\u5ba2\u6236\u4ee5\u53ca\u6211\u5011\u5167\u90e8\u7684\u92b7\u552e\u90e8\u9580\u4fdd\u6301\u826f\u597d\u7684\u6e9d\u901a\uff0c\u4ee5\u4fc3\u9032\u8a2d\u5099\u5b89\u88dd\u3001\u56de\u6536\u548c\u66f4\u63db\u7684\u904e\u7a0b\n\u8207\u5de5\u5834\u4e3b\u7ba1/\u7d44\u9577\u548c\u5176\u4ed6\u7d1a\u5225\u7684\u54e1\u5de5\u5bc6\u5207\u6e9d\u901a\u548c\u5408\u4f5c\uff0c\u4ee5\u63d0\u9ad8\u5404\u7a2e\u8a2d\u5099\u7684\u6280\u8853\u4e0a\u7684\u6027\u80fd\u4e26\u53cd\u5c04\u5230\u5728\u5e02\u5834\u4e0a\u7684\u5404\u7a2e\u8a2d\u5099\n\u4f5c\u70ba\u6307\u5c0e\u54e1\uff0c\u70ba\u90e8\u9580\u4e0d\u540c\u54e1\u5de5\u63d0\u4f9b\u5fc5\u8981\u7684\u57f9\u8a13\n\u8207\u5ba2\u6236\u3001\u540c\u4e8b\u548c\u4f9b\u61c9\u5546\u9032\u884c\u5167\u5916\u90e8\u6e9d\u901a\uff0c\u4e86\u89e3\u51b7\u98f2\u8a2d\u5099\u6027\u80fd\uff0c\u5f9e\u800c\u63d0\u9ad8\u670d\u52d9\u6548\u7387\n\u78ba\u4fdd\u5ba2\u6236\u5c0d\u5ba2\u6236\u670d\u52d9\u8a08\u5283\u7684\u6eff\u610f\u5ea6\uff0c\u4e26\u5728\u767c\u73fe\u4efb\u4f55\u554f\u984c\u6642\u63a1\u53d6\u7cfe\u6b63\u63aa\u65bd\n\u70ba\u63d0\u5347\u5916\u52e4\u670d\u52d9\u6548\u7387\u7684\u5ee0\u5167\u904b\u71df\u5354\u8abf\u63d0\u51fa\u6539\u9032\u5efa\u8b70\n\u8077\u4f4d\u8981\u6c42:\n\n\n\u96fb\u5b50\u8207\u96fb\u6a5f/\u6a5f\u68b0\u6216\u88fd\u9020\u5de5\u7a0b\u9ad8\u7d1a\u6587\u6191/\u8b49\u66f8\u8005\u512a\u5148\n\u81f3\u5c115\u5e74\u7684\u5de5\u7a0b\u548c\u7dad\u8b77\u7ba1\u7406\u7d93\u9a57\uff0c\u81f3\u5c111\u5e74\u7684\u5718\u968a\u7ba1\u7406\u7d93\u9a57\n\u5de5\u7a0b\u3001\u8a2d\u5099\u7dad\u4fee\u548c\u8cea\u91cf\u63a7\u5236\u77e5\u8b58\uff08ISO22000\u548c\u98df\u54c1\u5b89\u5168\u57f9\u8a13\u70ba\u52a0\u5206\u9805\uff09\n\u6301\u6709\u96fb\u696d\u5de5\u7a0b\u4eba\u54e1\u8a3b\u518a\u8b49\u66f8(R / A\u7d1a)\u8005\u512a\u5148\n\u6642\u523b\u5728\u601d\u8003\u5982\u4f55\u6539\u9032\u6d41\u7a0b\u4ee5\u63d0\u9ad8\u6548\u7387\n\u80fd\u5920\u70ba\u5718\u968a\u6210\u54e1\u63d0\u4f9b\u9818\u5c0e\u3001\u6307\u5c0e\u548c\u5e36\u9818\n\u512a\u79c0\u7684\u4eba\u969b\u95dc\u4fc2\u548c\u6e9d\u901a\u6280\u5de7\uff1b\u5718\u968a\u5408\u4f5c\u8005\n\u826f\u597d\u8b8a\u9769\u7ba1\u7406\u548c\u9805\u76ee\u7ba1\u7406\u6280\u80fd\n\u826f\u597d\u7684\u82f1\u8a9e\u548c\u7cb5\u8a9e\u66f8\u9762\u548c\u53e3\u8a9e\u80fd\u529b\n\u9999\u6e2f\u99d5\u99db\u57f7\u71672\u512a\u5148\nPlease apply with full resume,\u00a0current and expected salary and availability\u00a0to:\u00a0The Human Resources Manager, Swire Coca-Cola HK, 17-19 Yuen Shun Circuit, Siu Lek Yuen, Shatin, or by clicking 'Apply Now'.\u00a0\n\n\n*Personal data provided are treated in strictest confidence and for recruitment purposes only.\u00a0 All information will be destroyed after the process completed.*", "employment_types": ["Full Time", "Contract"], "selling_points": ["\u76e3\u7763\u51b7\u98f2\u8a2d\u5099\u5916\u52e4\u670d\u52d9\u5718\u968a", "\u96fb\u5b50/\u96fb\u6a5f\u5de5\u7a0b\u9ad8\u7d1a\u6587\u6191", "\u6301\u6709\u96fb\u5b50/\u96fb\u6a5f\u76f8\u95dc\u8b49\u66f8"], "locations": ["Shatin Area"], "categories": ["Engineering", "Electrical / Electronics", "Manufacturing & Production", "Manufacturing", "Manufacturing Management"], "post_time": "2022-01-12T08:03:38Z", "salary": {"currency": null, "max": null, "min": null, "period": "monthly", "term": null}, "salary_visible": false, "title_keywords": ["operations", "supervisor"], "responsibilities": ["installation", "workshop", "develop", "communication", "maintain", "customer service", "suggest improvements"], "requirements": {"degrees": ["certificate", "diploma"], "majors": ["manufacturing", "engineering"], "languages": ["cantonese", "english"], "language_level": ["good command"], "hard_skills": ["plus", "r", "maintenance", "project management", "certificate of registration of electrical worker"], "soft_skills": ["efficient", "communication skills", "confidence", "project management skills", "team player", "leadership", "interpersonal"], "languages_combined": [{"language": "cantonese", "language_level": ["good command"]}, {"language": "english", "language_level": ["good command"]}]}, "experience_required": {"duration": ["at least 5 years", "at least 1 year"], "field": ["management", "managing a team", "engineering", "maintenance"]}}, {"job_id": "100003009050450", "location_code": "hk", "company": "Links International", "job_title": "Sourcing Manager - Homeware & Kitchenware", "description": "Sourcing Manager - Houseware & Kitchenware\n\nOur client is a local trading company, looking for a Sourcing Manager to join their organisation.\n\nYour focus will be:\n\n\nSourcing, dealing with current suppliers, negotiate the right price and quality.\nProject coordination with our team and direct with our customers.\nCalculating cost pricing and arranging shipments.\nWork with other functional teams and manage the merchandising team for business migration from client's current operation to the company.\nFull ownership of the whole supply chain from factory sourcing, development till shipment with in-depth technical knowledge, proactive on problem precaution & strong decision maker.\nSearch new potential suppliers, having the desire to build up a network of suppliers within the packaging area, and a high level of service.\nDevelop a close relationship with existing suppliers and develop new suppliers through personal connections, trade fairs and sourcing trips\n\nYour profile and Experience:\n\n\nDiploma or above or related disciplines\nSelf-motivated and have strong sense of responsibility.\nPrevious experience in handling tabletop / kitchenware will be a plus. General hardgoods experience is a must.\nAble to perform price break down for analysis\nStrong project management experience and organization skills\nResponsible, patient, self-motivated, detailed minded, professional integrity and trustworthiness\nFamiliar with European / US market\nWilling to travel to China frequently\nGood command of English on writing & speaking", "employment_types": ["Full Time", "Permanent"], "selling_points": ["Solid exp. in houseware & kitchenware sourcing", "Work with wholesale / distributor clients", "18days AL, Double Pay + Bonus"], "locations": ["Others - China"], "categories": ["Manufacturing", "Manufacturing Management", "Product Development / Management"], "post_time": "2022-01-14T10:27:06Z", "salary": {"currency": "HKD", "max": 44999, "min": 30000, "period": "monthly", "term": null}, "salary_visible": true, "title_keywords": ["sourcing manager"], "responsibilities": ["cost", "project coordination", "analysis", "merchandising", "quality", "teams", "develop", "project management", "migration"], "requirements": {"degrees": ["diploma or above"], "majors": ["related disciplines"], "languages": ["english"], "language_level": ["good command"], "hard_skills": ["project management", "focus", "analysis", "plus"], "soft_skills": ["self-motivated", "responsible", "sense of responsibility", "integrity", "project management", "coordination", "organisation", "organization skills", "patient", "focus", "proactive", "detailed"], "languages_combined": [{"language": "english", "language_level": ["good command"]}]}, "experience_required": {"duration": [], "field": ["project management"]}}, {"job_id": "100003009050600", "location_code": "hk", "company": "JFE Consulting Limited", "job_title": "Senior Project Engineer", "description": "Do you have a passion for sustainability, making a difference on the environment and the local community with project management experience?\n\nIf so, we have an impactful opportunity at The TaKe Group. Ideally you will have manufacturing start up experience or eager to drive and manage the setup.\u00a0\n\nThis is a full-time role, 9am-6pm Monday to Friday, based in our factory in Kwai Chung.\n\nYou will be:\n\n\u00b7\u00a0\u00a0\u00a0\u00a0\u00a0\u00a0\u00a0Passionate about making a positive difference to our planet\n\n\u00b7\u00a0\u00a0\u00a0\u00a0\u00a0\u00a0\u00a0Hungry to make a difference\n\n\u00b7\u00a0\u00a0\u00a0\u00a0\u00a0\u00a0\u00a0Organised, self-motivated, and a multi-tasker\u00a0\n\n\u00b7\u00a0\u00a0\u00a0\u00a0\u00a0\u00a0\u00a0Proactive, and able to work to deadlines\u00a0\n\n\u00b7\u00a0\u00a0\u00a0\u00a0\u00a0\u00a0\u00a0Able to work with all stakeholders and lead a team\n\n\u00b7\u00a0\u00a0\u00a0\u00a0\u00a0\u00a0\u00a0Liaising daily with senior management on current opportunities\n\n\u00b7\u00a0\u00a0\u00a0\u00a0\u00a0\u00a0\u00a0Discipline in planning, time management and organization skills\n\n\u00b7\u00a0\u00a0\u00a0\u00a0\u00a0\u00a0\u00a0Hungry for new challenges with a problem-solving mindset\n\nKey Accountabilities & Responsibilities:\n\n\u00b7\u00a0\u00a0\u00a0\u00a0\u00a0\u00a0Leading project planning sessions\n\n\u00b7\u00a0\u00a0\u00a0\u00a0\u00a0\u00a0Coordinating staff and internal resources\n\n\u00b7\u00a0\u00a0\u00a0\u00a0\u00a0\u00a0Managing project progress and adapt work as required\n\n\u00b7\u00a0\u00a0\u00a0\u00a0\u00a0\u00a0Ensuring projects meet deadlines\n\n\u00b7\u00a0\u00a0\u00a0\u00a0\u00a0\u00a0Managing relationships with clients and stakeholders\n\n\u00b7\u00a0\u00a0\u00a0\u00a0\u00a0\u00a0Designing and signing off on contracts\n\n\u00b7\u00a0\u00a0\u00a0\u00a0\u00a0\u00a0Overseeing all incoming and outgoing project documentation\n\n\u00b7\u00a0\u00a0\u00a0\u00a0\u00a0\u00a0Participating in tender process i.e. design, submission and review\n\n\u00b7\u00a0\u00a0\u00a0\u00a0\u00a0\u00a0Designing risk mitigation plan\n\n\u00b7\u00a0\u00a0\u00a0\u00a0\u00a0\u00a0Conducting project review and creating detailed reports for executive staff\n\n\u00b7\u00a0\u00a0\u00a0\u00a0\u00a0\u00a0Optimising and improving processes and the overall approach where necessary\n\n\u00b7\u00a0\u00a0\u00a0\u00a0\u00a0\u00a0Securing growth opportunities and initiating new projects\n\n\u00b7\u00a0\u00a0\u00a0\u00a0\u00a0\u00a0Managing diverse teams\n\nKnowledge, Skills and Experience\n\n\u00b7\u00a0\u00a0\u00a0\u00a0\u00a0\u00a0Bachelor\u2019s degree in engineering / Project Management\n\n\u00b7\u00a0\u00a0\u00a0\u00a0\u00a0\u00a0Develop SOP for Product Development Processes\n\n\u00b7\u00a0\u00a0\u00a0\u00a0\u00a0\u00a0Written and verbal communication skills\n\n\u00b7\u00a0\u00a0\u00a0\u00a0\u00a0\u00a0Capacity to manage high stress situations\n\n\u00b7\u00a0\u00a0\u00a0\u00a0\u00a0\u00a0Ability to multi-task and manage various project elements simultaneously\n\n\u00b7\u00a0\u00a0\u00a0\u00a0\u00a0\u00a0Leadership skills\n\n\u00b7\u00a0\u00a0\u00a0\u00a0\u00a0\u00a0Big picture thinking and vision\n\n\u00b7\u00a0\u00a0\u00a0\u00a0\u00a0\u00a0Attention to detail\n\n\u00b7\u00a0\u00a0\u00a0\u00a0\u00a0\u00a0Conflict resolution skills\n\n\u00b7\u00a0\u00a0\u00a0\u00a0\u00a0\u00a0PMP certificate will be a plus\n\n\u00b7\u00a0\u00a0\u00a0\u00a0\u00a0\u00a0Injection moulding experience will be a plus\n\n\u00b7\u00a0\u00a0\u00a0\u00a0\u00a0\u00a05+ years of Project Management experience in Manufacturing for consumer products", "employment_types": ["Full Time", "Permanent"], "selling_points": ["Leading OEM manufacturer in electrical appliances", "Project development from design  to  production", "Good knowledge of 3D program and AutoCAD"], "locations": ["Not Specified"], "categories": ["Engineering", "Engineering Project Management", "Manufacturing & Production", "Manufacturing", "Manufacturing Management"], "post_time": "2022-01-14T10:53:02Z", "salary": {"currency": null, "max": null, "min": null, "period": "monthly", "term": null}, "salary_visible": false, "title_keywords": ["senior project engineer"], "responsibilities": ["project planning", "contracts", "review", "teams", "project progress", "design", "reports", "tender", "designing", "plan", "project documentation"], "requirements": {"degrees": ["certificate", "degree", "bachelor"], "majors": ["project management", "engineering"], "languages": [], "language_level": [], "hard_skills": ["project management", "pmp", "plus"], "soft_skills": ["communication skills", "multi-task", "leadership skills", "project management", "attention to detail"], "languages_combined": []}, "experience_required": {"duration": ["5+ years"], "field": ["project management", "manufacturing"]}}, {"job_id": "100003009050415", "location_code": "hk", "company": "Links International", "job_title": "Hardgoods Merchandiser - Product Developer", "description": "Our client is an award-winning market leader in manufacturing operating offices across the world. To cope with the expansion of the business, they are seeking for a high-caliber individual to join their expanding team.\n\nJob\u00a0Responsibilities:\u00a0\n\nResponsible for managing project development from design stage to mass production, handling product cost evaluation,\nPerforming feasibility study.\nSupervise Engineering Team, resource & job arrangement for the project team.\n\nJob\u00a0Requirements:\n\nHigher Diploma/Degree in Manufacturing, Mechanical, Electronic , Industrial Engineering or related;\nAt least 3 year experience in OEM/ODM product development & project follow-up with consumer product manufacturing company;\nStrong product design and construction senses;\nGood knowledge of 3D program and AutoCAD;\u00a0\nMature, independent, analytical mind and under pressure;\nGood command of spoken & written English & Mandarin.", "employment_types": ["Full Time", "Permanent"], "selling_points": ["Toys, textile / bedding sourcing exp", "Sourcing office exp is preferable", "15days AL + 1 day birthday leave"], "locations": ["Kwun Tong Area"], "categories": ["Manufacturing", "Manufacturing Management", "Product Development / Management", "Merchandising & Purchasing", "Sundries"], "post_time": "2022-01-14T10:21:06Z", "salary": {"currency": "HKD", "max": 24999, "min": 20000, "period": "monthly", "term": null}, "salary_visible": true, "title_keywords": ["merchandiser", "product developer"], "responsibilities": ["cost", "design", "evaluation"], "requirements": {"degrees": ["diploma", "degree"], "majors": ["manufacturing", "engineering"], "languages": ["english", "mandarin"], "language_level": ["good command"], "hard_skills": ["autocad"], "soft_skills": ["analytical mind", "independent", "under pressure", "mature"], "languages_combined": [{"language": "english", "language_level": ["good command"]}, {"language": "mandarin", "language_level": ["good command"]}]}, "experience_required": {"duration": ["at least 3 year"], "field": ["product development", "manufacturing", "consumer product"]}}, {"job_id": "100003009036768", "location_code": "hk", "company": "Moose Far East Limited", "job_title": "Production Planning Manager", "description": "Hardgoods Merchandiser - Product Development\n\nOur client is an international supplies retailer, focusing on pet products including food, toys, bedding, etc. They are looking for a Merchandiser to join their organization, responsible for sourcing, product development, and price negotiation process.\n\nJob Description\n\nDevelop and monitor sourcing strategies and procedures, ensure the vendors is fulfilling the sourcing plans\nSource potential suppliers within Asia to support the company's sourcing plans\nCollaborate with different teams to enhance brand identity and product features, keep track of projects' critical paths\nWork closely with UK Headquarter on category & supplier strategies\nUnderstand the product trends and market insight, develop competitive product ranges\nNegotiate and improve price competitiveness, deliver margin gains, improve payment terms and shipment date\nFollow up sourcing processes and help maintain sourcing systems\nTravel to factories /suppliers for buying trips & new product development\nManage any ad hoc projects, frequent travel to PRC\n\nRequirements\n\nDegree holder or above in the relevant discipline\nExperience of working in a sourcing/buying office is preferable\n2 - 5 years solid experience in developing or sourcing toys, textile or bedding products\nStrong negotiation and presentation skills, attention to details\nGood command of both spoken and written English, Cantonese & Mandarin\nWilling to travel to PRC\n\n", "employment_types": ["Full Time", "Permanent"], "selling_points": [], "locations": ["Tsim Sha Tsui"], "categories": ["Manufacturing", "Manufacturing Management", "Production Planning / Control"], "post_time": "2022-01-10T13:45:55Z", "salary": {"currency": null, "max": null, "min": null, "period": "monthly", "term": null}, "salary_visible": false, "title_keywords": ["manager"], "responsibilities": ["collaborate with", "systems", "monitor", "procedures", "teams", "develop", "payment", "maintain", "ad hoc projects", "plans"], "requirements": {"degrees": ["degree holder"], "majors": [], "languages": ["cantonese", "english", "mandarin"], "language_level": ["good command"], "hard_skills": [], "soft_skills": ["presentation skills", "negotiation", "attention to details"], "languages_combined": [{"language": "cantonese", "language_level": ["good command"]}, {"language": "english", "language_level": ["good command"]}, {"language": "mandarin", "language_level": ["good command"]}]}, "experience_required": {"duration": ["2 - 5 years"], "field": ["toys", "developing", "textile"]}}, {"job_id": "100003009045393", "location_code": "hk", "company": "Morgan Philips Hong Kong Limited", "job_title": "ESG Manager/ Assistant ESG Manager", "description": "My client is a well known Sportswear brand with strong presence globally. As of business expansion, they are now recruiting an ESG Manager to join their team.\u00a0\n\n\nManage an organization's sustainability programs.\nConduct research and analysis used to develop corporate sustainability strategies to ensure that business practices, products, and services are environmentally friendly and compliant with government rules and regulations.\nHelp to design the sustainability projects and initiatives required to achieve the group's ESG targets\nCollaborate with other parties to implement ESG related projects and initiatives\nPromote and explain the organization's sustainability philosophy to internal and external parties\nLead the preparation of the group's annual ESG report to fulfil the Hong Kong stock exchange requirement\nAssist in responding to various ESG ratings (e.g., MSCI, Sustainalytics, DJSI, etc.)\nEnsure that projects, milestones, and goals are met and adhering to approved budgets", "employment_types": ["Full Time"], "selling_points": ["Leading Sportswear Brand", "Project Management", "HK Listed Company"], "locations": ["Not Specified"], "categories": ["Sciences, Lab, R&D", "Energy / Natural Resources / Oil & Gas", "Environmental Science / Waste Management", "Manufacturing", "Manufacturing Management"], "post_time": "2022-01-13T07:45:36Z", "salary": {"currency": null, "max": null, "min": null, "period": "monthly", "term": null}, "salary_visible": false, "title_keywords": ["manager", "assistant"], "responsibilities": ["regulations", "collaborate with", "budgets", "analysis", "internal and external parties", "design", "develop", "conduct research", "report"], "requirements": {"degrees": [], "majors": [], "languages": [], "language_level": [], "hard_skills": ["analysis", "exchange"], "soft_skills": ["friendly"], "languages_combined": []}, "experience_required": {"duration": [], "field": []}}, {"job_id": "100003009039333", "location_code": "hk", "company": "Advance Pharmaceutical Company Limited", "job_title": "Production Officer", "description": "To assist in developing, implementing and maintaining the documentation system, including the Standard Operating Procedures (SOPs) and other production documents\nTo ensure and maintain the adequate and accurate records for controlling and monitoring conformity to specified GMP and statutory requirements\nTo assist monitor the production process according to the production plan\nTo assist in performing investigation to production deviation\nTo perform the daily operation and ad-hoc functions of Production Department\nTo assist the head of production to monitor the daily production workflow", "employment_types": ["Full Time"], "selling_points": [], "locations": ["Tai Po Area"], "categories": ["Manufacturing", "Manufacturing Management", "Product Development / Management", "Medical Services", "Pharmaceutical"], "post_time": "2022-01-11T09:27:01Z", "salary": {"currency": null, "max": null, "min": null, "period": "monthly", "term": null}, "salary_visible": false, "title_keywords": ["production officer"], "responsibilities": ["ad-hoc", "production process", "maintaining", "monitoring", "procedures", "developing", "monitor", "investigation", "daily operation", "statutory requirements", "maintain", "sops", "plan", "documentation"], "requirements": {"degrees": [], "majors": [], "languages": [], "language_level": [], "hard_skills": ["documentation"], "soft_skills": ["accurate"], "languages_combined": []}, "experience_required": {"duration": [], "field": []}}, {"job_id": "100003009044456", "location_code": "hk", "company": "GP Acoustics International Limited", "job_title": "Print Production Specialist", "description": "Job Description\n\nImprove and be the gate keeper of print production quality for all our brands.\nSet standards, Implement state of the art tools, processes, best practices and due diligence compliance check list.\nArrange print testing, briefing supplier for print test, and keep log and record\nReview and approve print tests, color proofs and samples and manage related process, budget and timeline.\nCoordinate with artwork / designer with correct AI file to proceed print test\nCommunicate with supplier pass/failure/improvement of print test\nManager supplier to deliver print proof as per schedule\nOrganise, supervise and monitor quality production of all printed materials, from prototype to mass production.\nUnderstand the project and design\u2019s vision, needs and requirements to provide the advice and print solutions, techniques, vendors, effects to designers to achieve what the desired outcome.\nEvaluate and negociate costs and manage timelines, to ensure quality service is provided to the other teams.\nReview output files\nSource, select and recommend appropriate materials, techniques, factories.\nControl and approve mass-production on site if necessary.\nInvestigate vendors and new print technologies, develop our vendor network.\nCoordinate with factories and maintain relationships, evaluate suppliers.\nConduct project post-mortem evaluations with the stakeholders, recap issues faced and propose solutions for improvement.\n\nRequirements\n\nExpert in printing\n6-8 years in printing (packaging a plus) from small volumes to mass production\nFamiliar and eager about the latest color and quality monitoring tools and technology\nFamiliar with high end packaging and its standards\nKnowledge in softwares: Asana, MsTeams, Adobe Creative Suite is an advantage\nFluent Cantonese / English / Mandarin", "employment_types": ["Full Time", "Permanent"], "selling_points": ["Science Park", "6-8 years in printing (packaging a plus)", "5 days works and flexible working hour"], "locations": ["Shatin Area"], "categories": ["Design", "Graphics", "Manufacturing", "Manufacturing Management", "Printing"], "post_time": "2022-01-13T04:09:14Z", "salary": {"currency": null, "max": null, "min": null, "period": "monthly", "term": null}, "salary_visible": false, "title_keywords": ["specialist"], "responsibilities": ["communicate with", "due diligence", "control", "maintain relationships", "review", "compliance", "quality", "budget", "testing", "coordinate with", "monitor", "design", "evaluate", "teams", "schedule", "develop", "costs"], "requirements": {"degrees": [], "majors": [], "languages": ["cantonese", "english", "mandarin"], "language_level": ["fluent"], "hard_skills": ["small", "plus", "adobe creative suite"], "soft_skills": ["creative"], "languages_combined": [{"language": "cantonese", "language_level": ["fluent"]}, {"language": "english", "language_level": ["fluent"]}, {"language": "mandarin", "language_level": ["fluent"]}]}, "experience_required": {"duration": [], "field": []}}, {"job_id": "100003009044661", "location_code": "hk", "company": "Nestle Hong Kong Ltd", "job_title": "Project Engineer (Automation)", "description": "(Working Location: Yuen Long)\u00a0\n\nPosition Summary\n\nProvide professional and technical support on Manufacturing Execution Systems (MES), Electricity and/or Automation (E&A) for Factory operation purpose.\n\nA day in the life of...\nPerform in Electrical & Automation, Factory Automation System, Manufacturing Execution System, MP4 etc. safety and modification.\nDevelop routine maintenance, modification and improvements\u00a0of quality, safety or efficiency.\nManage external system integrators and contractors.\nProvide technical supports on mechanization projects.\u00a0\u00a0\nEnsure that people health and safety, product safety, and environment.\nWhat will make you successful\n\n- Degree holder\u00a0in Electrical or Automation or related\u00a0disciplines\n\n- At least 3 years related experience in mechanical project engineer with Electrical skills\n\n-\u00a0Exposure to Total Productive Maintenance, preventive maintenance planning and/or maintenance execution desired\n\n-\u00a0Experience required in Electricity, Process Control, Loop Tuning and Instrumentation\n\n-\u00a0Food processing plants and technologies, including food safety or hygienic engineering is an advantage\n\n-\u00a0Process IT knowledge including understanding of\u00a0Federated Authentication Service infrastructure\n\n-\u00a0Fluent in spoken and written Cantonese,\u00a0Mandarin\u00a0and English\n\nWe, at all levels, are strongly committed to the Company, its development and its culture. We practice what we preach and give great importance to training and development of people. We offer excellent career development opportunities, attractive remuneration package, comprehensive fringe benefits and wellness programs to the right candidates.\u00a0\n\nWe are an equal opportunity employer and committed to workforce diversity with opportunity for continuous development and growth to all employees.\n\nPlease apply in full resume (in Microsoft Word or PDF format) with your employment history, present and expected salary via https://career2.successfactors.eu/sfcareer/jobreqcareer?jobId=128276&company=nestleHRprdBX\n\n(All information will be treated in strict confidence and will be used exclusively for recruitment related purpose only. Information of unsuccessful applicants will be destroyed upon completion of the recruitment process.)\n", "employment_types": ["Full Time", "Permanent"], "selling_points": ["Bringing Nutrition, Health and Wellness to HK", "Innovative team with Collaborative culture", "1st F&B Company in the World"], "locations": ["Yuen Long"], "categories": ["Engineering", "Electrical / Electronics", "Engineering Project Management", "Manufacturing", "Manufacturing Management"], "post_time": "2022-01-13T05:04:47Z", "salary": {"currency": null, "max": null, "min": null, "period": "monthly", "term": null}, "salary_visible": false, "title_keywords": ["project engineer"], "responsibilities": ["technical supports", "control", "food safety", "maintenance", "technical support", "systems", "quality", "infrastructure", "develop", "recruitment", "career development", "recruitment process", "planning"], "requirements": {"degrees": ["degree holder"], "majors": ["related disciplines"], "languages": ["cantonese", "english", "mandarin"], "language_level": ["fluent"], "hard_skills": ["microsoft word", "it knowledge", "maintenance", "make", "processing"], "soft_skills": ["productive", "committed", "comprehensive", "confidence"], "languages_combined": [{"language": "cantonese", "language_level": ["fluent"]}, {"language": "english", "language_level": ["fluent"]}, {"language": "mandarin", "language_level": ["fluent"]}]}, "experience_required": {"duration": ["at least 3 years"], "field": ["related"]}}, {"job_id": "100003009040120", "location_code": "hk", "company": "OPC Manufacturing Ltd (a member of TTM Technologies Group)", "job_title": "Planner - Production & Material Planning", "description": "Job Responsibilities:\n\nCoordinate shipment data and production planning for customers\nDevelop planning, OTD analysis and shipment system\nMaster schedule planning and order movement control\nSupport internal workflow system development and enhancement project\nHandle ad hoc projects as assigned \u00a0\n\nJob Requirements:\u00a0\n\nDegree holder in Manufacturing, Industrial Engineering or Supply Chain or Higher Diploma study with 3 years relevant experience\n\u00a01-2 years Production Planning & Control experience would be an advantage, fresh graduate is also welcome\nPC literate in Word, Excel and Chinese word processing\nWell familiar with developing programs, Excel Functions, i.e. VBA, v-lookup, pivot table, etc.\nGood command of English, Cantonese and Putonghua\nSelf-motivated, independent, well organized and strong sense of responsibility\nAlternative Saturday work is required\n\n\u00a0Our\u00a0Offer:\n\nAttractive remuneration package including 12 \u2013 14 days annual leave, public holiday, overtime allowance, medical scheme, life insurance, training subsidy, etc.\nShuttle buses available between Kowloon Tong, Tsuen Wan, Shatin, Tai Po, Sheung Shui, Fanling, Tuen Mun, Yuen Long and HK Office\n\nInterested parties please send your full resume to us with recent and expected salary by clicking \"Apply Now\".\n\n(Personal data provided by job applicants will be used for recruitment purpose only)", "employment_types": ["Full Time", "Permanent"], "selling_points": ["Support internal workflow system development", "Master schedule planning, order movement control", "Clear career development ladder in a US company"], "locations": ["Tai Po Area"], "categories": ["Engineering", "Manufacturing & Production", "Manufacturing", "Manufacturing Management", "Production Planning / Control"], "post_time": "2022-01-12T01:31:12Z", "salary": {"currency": null, "max": null, "min": null, "period": "monthly", "term": null}, "salary_visible": false, "title_keywords": [], "responsibilities": ["control", "data", "analysis", "production planning", "develop", "coordinate", "ad hoc projects", "schedule", "planning"], "requirements": {"degrees": ["diploma", "fresh graduate", "degree holder"], "majors": ["manufacturing", "engineering"], "languages": ["cantonese", "putonghua", "english", "chinese"], "language_level": ["good command"], "hard_skills": ["excel", "vba", "chinese word processing", "pivot table", "word", "scheme", "pc literate", "wan"], "soft_skills": ["self-motivated", "independent", "well organized", "sense of responsibility"], "languages_combined": [{"language": "cantonese", "language_level": ["good command"]}, {"language": "putonghua", "language_level": ["good command"]}, {"language": "english", "language_level": ["good command"]}, {"language": "chinese", "language_level": []}]}, "experience_required": {"duration": ["3 years", "1-2 years"], "field": ["manufacturing", "engineering", "supply chain", "relevant experience", "planning"]}}, {"job_id": "100003009050103", "location_code": "hk", "company": "Karrie International Holdings Limited", "job_title": "Accounting Officer/ Senior Account Clerk", "description": "Responsibilities\n\nResponsible for month-end closing, intercompany reconciliation, and fixed assets recording and reporting\nTimely conduct monthly financial reports and analysis for management review\nPrepare accounting schedules, reconciliation and follow up outstanding matters\nPrepare monthly provisions or accruals, including turnover rent\nProvide support for annual audit, tax computation and prepare reporting package for external auditors\nProvide secretarial and administrative supports to the department\nPerform any other ad-hoc assignments\n\nRequirements\n\nDegree holder or above in Accountancy or equivalent\n2-3 years relevant experience in accounting, preferably in Retail industry\nMatured, well organized, able to meet tight deadline with high accuracy\nSound business knowledge and analytical skills\nSelf-motivated, independent and a good team player\nHigh proficiency in Excel Pivot Table, Vlookup and familiar with computerized accounting system\nHands-on experience in SAP is an advantage\nGood command of written and spoken Chinese, English and Mandarin\nImmediate available is preferred\nFresh graduate is also welcome\n\nInterested parties please click \"Apply Now\" to send\u00a0full resume with the date of availability and expected salary.\u00a0\n\nOr post it to \"The\u00a0 Group HR Department, Karrie International Holdings Limited, 9/F, Southeast Industrial Building, 611-619 Castle Peak Road, Tsuen Wan, N.T.\" (Please Attn Recruitment Team and quote Ref. on the envelope)\n\nFor more information, please visit our website at http://www.karrie.com/en, or visit\u00a0 \u00a0https://www.youtube.com/watch?v=y3Lhgl7ylf8&list=PL66rAPgv5k9ykDxduveZ6E7Yni9e39jBZ\n\n** We are an equal opportunity employer and welcome applications from all qualified candidates.\u00a0Personal data\u00a0provided by job applicants will be used strictly in accordance with the employer's personal data policies, a copy of which will be provided immediately upon request. **", "employment_types": ["Full Time", "Permanent"], "selling_points": ["Responsible for month-end closing", "Hands-on experience in SAP", "High proficiency in Excel Pivot Table, Vlookup"], "locations": ["Tsuen Wan Area"], "categories": ["Banking / Finance", "Others", "Manufacturing", "Manufacturing Management"], "post_time": "2022-01-15T03:50:50Z", "salary": {"currency": null, "max": null, "min": null, "period": "monthly", "term": null}, "salary_visible": false, "title_keywords": ["accounting officer", "senior account clerk"], "responsibilities": ["reporting", "financial reports", "provide support", "tax computation", "annual audit", "schedules", "ad-hoc assignments", "analysis", "month-end closing", "management review", "external auditors"], "requirements": {"degrees": ["fresh graduate", "degree holder"], "majors": ["accountancy"], "languages": ["english", "chinese", "mandarin"], "language_level": ["good command"], "hard_skills": ["excel", "sap", "pivot table", "analytical skills", "accounting system", "vlookup"], "soft_skills": ["self-motivated", "good team player", "independent", "well organized", "analytical skills", "hands-on", "meet tight deadline"], "languages_combined": [{"language": "english", "language_level": ["good command"]}, {"language": "chinese", "language_level": ["good command"]}, {"language": "mandarin", "language_level": ["good command"]}]}, "experience_required": {"duration": ["2-3 years"], "field": ["retail industry", "accounting", "relevant experience"]}}, {"job_id": "100003009045766", "location_code": "hk", "company": "Page Personnel", "job_title": "Senior Quality Assurance Officer - Toys", "description": "An excellent opportunity in joining a world renowed buying office.\n\nClient Details\n\nOur client is a well known buying firm, they are operating with an international presence for delivering a hardline items in Hong Kong, they are seeking to recruit a Senior Quality Assurance Officer.\n\nDescription\n\nExecute QC inspection duties for purchased items and formulate reports on defects/ damages and identify the root cause for the cause of damage\nWork with multiple parties to fulfil internal expectations, such as but not limited to packaging specifications of each order, quality & critical time point controls, shipments, etc\nCommunicate with third party laboratories for chemical testings and to ensure all materials are submitted prior to the test under the policy of international regulations and policy\n\nProfile\n\nBachelor's Degree in Supply Chain Management, Mechanical Engineering or any other discipline\nMin. 3 years of relevant experience, all of which preferably obtained within a trading office/ sourcing office\nCandidate must have extensive experiences with the product of Toys\nA candidate with high efficiency who possess an analytical mindset for evaluations and reporting\nGood team player, self-motivated, proactive and able to work under pressure in meeting tight deadline\n\nJob Offer\n\nDiscretionary Bonus\nOn job training\nMNC exposure\nFive days work week\n\nTo apply online please click the 'Apply' button below.\nFor a confidential discussion about this role please contact Ryan Ng on +852 3602 2450.", "employment_types": ["Full Time", "Permanent"], "selling_points": ["Conduct the inspection cycle", "Experiences from Sourcing Office/ Trading Firm", "Liaise with vendors for project objectives"], "locations": ["Kowloon Bay"], "categories": ["Engineering", "Manufacturing & Production", "Manufacturing", "Manufacturing Management", "Production Planning / Control"], "post_time": "2022-01-13T08:35:59Z", "salary": {"currency": "HKD", "max": 29999, "min": 20000, "period": "monthly", "term": null}, "salary_visible": true, "title_keywords": ["senior quality assurance officer"], "responsibilities": ["communicate with", "regulations", "management", "reporting", "quality", "inspection", "specifications", "reports", "contact", "third party", "work under pressure"], "requirements": {"degrees": ["degree", "bachelor"], "majors": ["mechanical engineering"], "languages": [], "language_level": [], "hard_skills": [], "soft_skills": ["good team player", "self-motivated", "meeting tight deadline", "proactive", "extensive", "work under pressure"], "languages_combined": []}, "experience_required": {"duration": ["3 years"], "field": ["toys", "relevant experience", "trading"]}}, {"job_id": "100003009039915", "location_code": "hk", "company": "Yeko Manufacturing Limited", "job_title": "Injection Manager (Toys)", "description": "Description:\u00a0\n\n10 years+ solid experience in hard toys injection in manufacturing plants\nStation in Vietnam\nDaily operation and control, timeline management and meeting clients' quality standard a must\nGood communication skills, problem solving and highly responsible", "employment_types": ["Full Time"], "selling_points": ["Injection Manager (Toys)", "Vietnam stationed", "10 years experience"], "locations": ["Overseas"], "categories": ["Manufacturing", "Manufacturing Management", "Merchandising & Purchasing", "Toy"], "post_time": "2022-01-11T15:07:38Z", "salary": {"currency": null, "max": null, "min": null, "period": "monthly", "term": null}, "salary_visible": false, "title_keywords": ["manager"], "responsibilities": ["control", "management", "quality", "daily operation", "communication"], "requirements": {"degrees": [], "majors": [], "languages": [], "language_level": [], "hard_skills": ["problem solving"], "soft_skills": ["problem solving", "communication skills", "responsible"], "languages_combined": []}, "experience_required": {"duration": [], "field": ["toys", "manufacturing"]}}, {"job_id": "100003009031045", "location_code": "hk", "company": "Wright Life Pharmaceutical Limited", "job_title": "\u751f\u7522\u7d93\u7406 Production Manager", "description": "Key Responsibilities:\n\n\nBuilding strong cross-department links to ensure all aspects of the business are engaged in successful delivery of projects.\nManaging critical path from product sign off to shipment.\nWorking closely with UK commercial team on tracking the budgets.\nClosely tracking on the forecast and inventory management.\nDeveloping and managing project plans to ensure timescales are met and are clearly communicated to all manufacturers and suppliers.\nReviewing all completed projects to ensure that improvement actions are taken forward into new projects.\nDriving changes in response to business needs including continuous improvement to procedures governing all of the above\n\nKey Requirements:\n\n\nHigh diploma or above\u00a0with\u00a0merchandising\u00a0experience. Project management experience is a plus.\nSolid experience in product development & life cycle/product management of Health & Beauty/ Households/ Bags\nGood understanding\u00a0on manufacturing process.\nEffective business and personal skills to build relationships with all stakeholders\nGood knowledge of methodologies and techniques for planning, monitoring and controlling projects\nInnovative with strong passion in driving changes and continuous improvements\nSelf confidence in front of factories, oversea offices and customers\nAble to communicate and conduct presentation well in English\nEnjoy travelling to factories in Asia Regions\n\nPersonal data provided by applicants will be strictly used for recruitment purpose only.", "employment_types": ["Full Time"], "selling_points": ["5\u5929\u5de5\u4f5c + \u9280\u884c\u5047\u671f", "5\u5e74\u85e5\u5ee0\u7ba1\u7406\u7d93\u9a57", "\u719f\u6089\u9999\u6e2f\u5de5\u5834\u7d93\u71df\u6cd5\u4f8b"], "locations": ["Tsuen Wan Area"], "categories": ["Management", "General Management", "Manufacturing", "Manufacturing Management", "Production Planning / Control"], "post_time": "2022-01-07T09:51:49Z", "salary": {"currency": null, "max": null, "min": null, "period": "monthly", "term": null}, "salary_visible": false, "title_keywords": ["\u751f\u7522\u7d93\u7406", "production manager"], "responsibilities": ["budgets", "procedures", "developing", "inventory management", "forecast", "plans", "tracking"], "requirements": {"degrees": ["high diploma or above"], "majors": [], "languages": ["english"], "language_level": [], "hard_skills": ["project management", "plus"], "soft_skills": ["confidence", "passion in", "project management", "innovative", "presentation"], "languages_combined": [{"language": "english", "language_level": []}]}, "experience_required": {"duration": [], "field": ["merchandising", "product management", "project management", "beauty", "product development"]}}, {"job_id": "100003009033874", "location_code": "hk", "company": "Koon Chun Hing Kee Soy & Sauce Factory Limited", "job_title": "Repair & Maintenance Section Supervisor \u98df\u54c1\u5ee0\u5de5\u7a0b\u90e8\u4e3b\u7ba1", "description": "\u8077\u4f4d\u8077\u8cac:\n\n\u7ba1\u7406\u5ee0\u623f\u53ca\u8eca\u9593\u751f\u7522\uff0c\u8ddf\u9032\u751f\u7522\u9032\u5ea6\uff0c\u63d0\u9ad8\u751f\u7522\u6548\u7387\uff0c\u8ca0\u8cac\u7522\u54c1\u751f\u7522\u6d41\u7a0b\u8207\u8cc7\u6e90\u898f\u5283\uff0c\u5305\u62ec\u5b89\u6392\u4eba\u624b\u548c\u7269\u6599\uff0c\u76e3\u7763\u8cea\u91cf\uff0c\u5354\u52a9\u89e3\u6c7a\u751f\u7522\u554f\u984c\u3002\n\n\u8077\u4f4d\u8981\u6c42:\n\n\u4e2d\u4e94\u6216\u4ee5\u4e0a\u7a0b\u5ea6\uff1b5\u5e74\u6216\u4ee5\u4e0a\u85e5\u5ee0\u71df\u904b\u53ca\u7ba1\u7406\u7d93\u9a57\uff1b\u719f\u6089\u9999\u6e2f\u5de5\u5834\u7d93\u71df\u6cd5\u4f8b\uff1b\u826f\u597d\u7684\u7d44\u7e54\u751f\u7522\u548c\u7ba1\u7406\u80fd\u529b\uff1b\u61c2\u96fb\u8166\u57fa\u672c\u64cd\u4f5c\uff0c\u5982Excel\uff0cWord\u53ca\u4e2d\u6587\u8f38\u5165\u6cd5\u3002\n\n\u61c9\u5fb5\u8005\u8acb\u6309Apply Now\u63d0\u4ea4\u500b\u4eba\u4e2d\u6587\u5c65\u6b77\u3001\u73fe\u6642\u85aa\u91d1\u53ca\u8981\u6c42\u85aa\u91d1\u7b49\u3002\n\n\u6240\u6709\u8cc7\u6599\u5c07\u6703\u7d55\u5c0d\u4fdd\u5bc6\uff0c\u4e26\u53ea\u7528\u4f5c\u7533\u8acb\u8077\u4f4d\u4e4b\u7528\u9014\u3002", "employment_types": ["Full Time"], "selling_points": [], "locations": ["Yuen Long"], "categories": ["Engineering", "Manufacturing & Production", "Manufacturing", "Manufacturing Management"], "post_time": "2022-01-11T16:01:46Z", "salary": {"currency": null, "max": null, "min": null, "period": "monthly", "term": null}, "salary_visible": false, "title_keywords": ["supervisor"], "responsibilities": [], "requirements": {"degrees": [], "majors": [], "languages": [], "language_level": [], "hard_skills": [], "soft_skills": [], "languages_combined": []}, "experience_required": {"duration": [], "field": []}}, {"job_id": "100003009043810", "location_code": "hk", "company": "UA Global Sourcing Limited", "job_title": "Sr. Professional, Logistics (5 Months Maternity Leave Cover)", "description": "This position will provide support to the internal office and the Asia supply logistics functions, to ensure efficient & effective product delivery from Asia supply locations\n\nESSENTIAL DUTIES AND RESPONSIBILITIES\n\nCoordinate with 3PL of cross dock shipment in HK CFS to overseas\nAssist Logistics Manager to coordinate with 3PL of day to day operation such as consolidation, container utilization control and problem solving for all apparel, accessory and footwear product within Asia and Middle East Regional\nCoordinate with 3PL of monitor inbound documents\nCoordinate with US logistics team and licensing dept for moving goods to international destinations.\nAssist the management of ad hoc assignments to support the global business such as moving finished goods and/or material globally\nProviding operations support to external customers such as vendors, APAC supply chain team, UA HK production team to ensure operation efficiently\nAssist group to execute all logistics support for the new sourcing countries within Asia and Middle East Regional\nCoordinate with designated customers of supporting the pick up and logistics movement globally\nEDUCATION and/or EXPERIENCE\n\nForm 5 or above with\u00a04 years experience in garment, accessories and/or footwear field\nAble to handle international shipment independent\nStrong self-initiative, sense of responsibility and good team player\nAble to speak simple English and Mandarin\n\n\n", "employment_types": ["Temporary", "Contract"], "selling_points": ["Coordinate with 3PL, logistics team, factories", "Administrative and Operational Support", "Sourcing support"], "locations": ["Kowloon Bay"], "categories": ["Transportation & Logistics", "Supply Chain", "Manufacturing", "Manufacturing Management", "Merchandising & Purchasing", "Procurement / Purchasing / Sourcing"], "post_time": "2022-01-13T02:02:56Z", "salary": {"currency": null, "max": null, "min": null, "period": "monthly", "term": null}, "salary_visible": false, "title_keywords": ["logistics"], "responsibilities": ["provide support", "control", "management", "operations", "monitor", "coordinate with", "logistics", "ad hoc assignments"], "requirements": {"degrees": ["form 5 or above"], "majors": [], "languages": ["english", "mandarin"], "language_level": [], "hard_skills": ["problem solving", "container", "simple"], "soft_skills": ["efficient", "good team player", "independent", "sense of responsibility", "problem solving", "self-initiative"], "languages_combined": [{"language": "english", "language_level": []}, {"language": "mandarin", "language_level": []}]}, "experience_required": {"duration": ["4 years"], "field": ["garment", "education"]}}, {"job_id": "100003009040117", "location_code": "hk", "company": "OPC Manufacturing Ltd (a member of TTM Technologies Group)", "job_title": "Engineer - Product Engineering (5 day) (Fresh Graduates is also welcomed!)", "description": "\u5d17\u4f4d\u8981\u6c42:\n\u5927\u5b78\u5b78\u4f4d\uff0c\u81ea\u7136\u79d1\u5b78\u6216\u5de5\u7a0b\u7cfb\u7562\u696d\u8005\u512a\u5148\u8003\u616e\n\u64c1\u6709 5 - 6 \u5e74\u5e02\u5834\u7d93\u9a57\n\u719f\u6089\u4e9e\u6d32\u5730\u5340\u92b7\u552e\u53ca\u5e02\u5834\u6587\u5316\n\u719f\u6089\u96fb\u5b50\u5e02\u5834\u5a92\u9ad4\u53ca\u92b7\u552e\n\u64cd\u6d41\u5229\u82f1\u8a9e\u53ca\u666e\u901a\u8a71\n\u5fc5\u9808\u9858\u610f\u516c\u5e79\n\n\u5de5\u4f5c\u7bc4\u570d\u53ca\u8077\u8cac:\n\n\n\u7ba1\u7406\u53ca\u5354\u8abf\u5e02\u5834\u90e8\u7684\u5de5\u4f5c\uff0c\u4ee5\u9054\u81f4\u516c\u53f8\u76ee\u6a19;\n\u7dad\u7e6b\u5ba2\u6236\u9577\u4e45\u4e4b\u95dc\u4fc2;\n\u8655\u7406\u516c\u53f8\u96a8\u6642\u5b89\u6392\u4e4b\u8a08\u5283;\n\u61c9\u5fb5\u8005\u5fc5\u9808\u63d0\u4f9b\u77ed\u7247\uff0c\u5305\u62ec\u81ea\u6211\u4ecb\u7d39\u53ca\u5982\u4f55\u63d0\u5347\u8077\u4f4d\u7684\u50f9\u503c;\n\u61c9\u5fb5\u8005\u5fc5\u9808\u63d0\u4f9b\u65b0\u51a0\u75ab\u82d7\u6ce8\u5c04\u8b49\u66f8 (\u5982\u56e0\u5065\u5eb7\u7406\u7531\uff0c\u61f7\u5b55\u4e0d\u9069\u5b9c\u6ce8\u5c04\u9664\u5916)\u3002\n\n", "employment_types": ["Full Time", "Permanent"], "selling_points": ["Immediate available highly preferred", "Participate in regular manufacturing design", "Provide technical engineering support"], "locations": ["Tai Po Area"], "categories": ["Engineering", "Electrical / Electronics", "Manufacturing & Production", "Manufacturing", "Manufacturing Management"], "post_time": "2022-01-12T01:30:44Z", "salary": {"currency": null, "max": null, "min": null, "period": "monthly", "term": null}, "salary_visible": false, "title_keywords": ["engineer"], "responsibilities": [], "requirements": {"degrees": [], "majors": [], "languages": [], "language_level": [], "hard_skills": [], "soft_skills": [], "languages_combined": []}, "experience_required": {"duration": [], "field": []}}, {"job_id": "100003009046084", "location_code": "hk", "company": "", "job_title": "Procurement & HR Officer", "description": "Our group\u00a0is now inviting high calibre persons to apply for this position:\n\nResponsibilities\n\nAssist in procurement activities including preparing purchase orders, purchase planning, price negotiation, etc\nWork closely with suppliers and overseas factories for order follow up and delivery schedule\nProvide administrative support including procurement for office supplies and\u00a0full circle of purchasing activities\nPreparation of presentable reports for management within a strictly prescribed timeframe\nHandle ad hoc projects\u00a0\n\nRequirements\n\nDegree/Diploma in related disciplines\nGood command of spoken and written English and Chinese\nImmediately available is preferred", "employment_types": ["Full Time"], "selling_points": [], "locations": ["Tsim Sha Tsui"], "categories": ["Manufacturing", "Manufacturing Management"], "post_time": "2022-01-13T18:55:13Z", "salary": {"currency": null, "max": null, "min": null, "period": "monthly", "term": null}, "salary_visible": false, "title_keywords": ["hr officer"], "responsibilities": ["price negotiation", "management", "office supplies", "delivery schedule", "purchase", "reports", "ad hoc projects", "provide administrative support", "planning"], "requirements": {"degrees": ["diploma", "degree"], "majors": ["related disciplines"], "languages": ["english", "chinese"], "language_level": ["good command"], "hard_skills": [], "soft_skills": [], "languages_combined": [{"language": "english", "language_level": ["good command"]}, {"language": "chinese", "language_level": ["good command"]}]}, "experience_required": {"duration": [], "field": []}}, {"job_id": "100003009045207", "location_code": "hk", "company": "Fujifilm Hong Kong Limited", "job_title": "\u5370\u5237\u6a5f\u76e3\u5bdf\u54e1", "description": "\n\u8aa0\u8058\u5927\u91cf\n\u5168\u8077\u6216\u517c\u8077\n\u8ca0\u8cac\u64cd\u4f5c\u5927\u578b/\u5c08\u696d\u5370\u5237\u6a5f\uff0c\u6309\u6642\u5b8c\u6210\u76f8\u95dc\u6253\u5370\u5de5\u4f5c\u3002\u9808\u6309\u5de5\u4f5c\u6307\u793a\u9078\u64c7\u9069\u7576\u7684\u96fb\u8166\u6a94\u6848\u53ca\u7d19\u5f35\uff0c\u64cd\u4f5c\u5370\u5237\u6a5f\u6253\u5370\u6587\u4ef6\u6216\u4fe1\u4ef6\uff0c\u4e26\u7d30\u5fc3\u7559\u610f\u5370\u5237\u6a5f\u904b\u4f5c\u60c5\u6cc1\u3002\n\n\u5de5\u4f5c\u6642\u9593\uff1a \u661f\u671f\u4e00\u81f3\u65e5(\u65e9\u73ed\uff1a08:00 - 17:00 \u53ca \u4e2d\u73ed\uff1a14:00 - 23:00 \u53ca \u901a\u5bb5\u73ed\uff1a23:00 - 08:00)\n\u5de5\u4f5c\u5730\u9ede\uff1a \u67f4\u7063\u6216\u6cb9\u5858 *\u6bcf\u9031\u5de5\u4f5c\u4e94\u81f3\u516d\u5929\uff0c\u9808\u8f2a\u73ed\u53ca\u8f2a\u4f11\u5de5\u4f5c\n\u6bcf\u6708\u85aa\u91d1 $10,400\u8d77 + \u6bcf\u6708\u52e4\u5de5\u734e\u91d1$1,000 + \u8f2a\u73ed\u6d25\u8cbc (\u6700\u9ad8\u85aa\u91d1\u53ef\u9054$13,000)\n\n\u5168\u8077\u54e1\u5de5\u798f\u5229\uff1a\n\u8d85\u6642\u6d25\u8cbc / \u52e4\u5de5\u734e\u91d1 / \u66f4\u671f\u6d25\u8cbc / \u6709\u85aa\u5e74\u5047 / \u91ab\u7642\u798f\u5229 / \u9280\u884c\u5047\u671f / \u6649\u5347\u6a5f\u6703 / \u54e1\u5de5\u98ef\u5802 / \u7a7f\u68ad\u5df4\u58eb / \u826f\u597d\u57f9\u8a13 / \u51b7\u6c23\u958b\u653e\n\u6709\u610f\u8005\u8acb\u65bc\u661f\u671f\u4e00\u81f3\u4e949:00am - 12:00pm \u62161:00pm - 5:00pm\n\u81f4\u96fb9828 0862 \u6216\u5c07\u5c65\u6b77\u96fb\u90f5\u81f3[via\u00a0 Apply Now ]\n\u8207\u4eba\u529b\u8cc7\u6e90\u90e8\u9810\u7d04\u9762\u8a66\n\n", "employment_types": ["Full Time"], "selling_points": [], "locations": ["Kwun Tong"], "categories": ["Manufacturing", "Manufacturing Management", "Others", "Printing"], "post_time": "2022-01-13T07:26:20Z", "salary": {"currency": null, "max": null, "min": null, "period": "monthly", "term": null}, "salary_visible": false, "title_keywords": [], "responsibilities": [], "requirements": {"degrees": [], "majors": [], "languages": [], "language_level": [], "hard_skills": [], "soft_skills": [], "languages_combined": []}, "experience_required": {"duration": [], "field": []}}, {"job_id": "100003009025392", "location_code": "hk", "company": "CN Innovations Limited", "job_title": "Assistant General Manager", "description": "\u8077\u8cac :\u7ba1\u7406\u5de5\u7a0b\u53ca\u958b\u767c\u90e8, \u5236\u5b9a\u9805\u76ee\u8a08\u5283\u4e26\u70ba\u9805\u76ee\u5be6\u65bd\u5b89\u6392\u5fc5\u8981\u7684\u8cc7\u6e90; \u8a2d\u8a08\u9a57\u8b49\u548c\u6545\u969c\u6392\u9664; \u8207\u5ba2\u6236\u806f\u7d61\u4ee5\u88fd\u5b9a\u7522\u54c1\u898f\u683c (\u9577\u99d0\u5728\u6771\u839e\u5de5\u4f5c)\n\u8cc7\u6b77 :\u5c08\u4e0a\u6559\u80b2\uff1a\u5b78\u58eb\u5b78\u4f4d; 5\u5e746\u500b\u6708\u7d93\u9a57; \u4e00\u822c\u7cb5\u8a9e; \u826f\u597d\u666e\u901a\u8a71; \u4e00\u822c\u82f1\u8a9e; \u61c2\u8b80\u5beb\u4e2d\u6587; \u61c2\u8b80\u5beb\u82f1\u6587\n\u5f85\u9047 :\u6bcf\u6708$33,000 - $35,000, \u6709\u4f9b\u4f4f\u5bbf, \u9280\u884c\u5047\u671f, \u751f\u65e5\u5047, \u914c\u60c5\u6027\u82b1\u7d05, \u91ab\u7642\u4fdd\u96aa\u53ca\u5176\u4ed6\u6d25\u8cbc/\u798f\u5229, \u661f\u671f\u4e00\u81f3\u4e94: \u4e0a\u53488\u6642\u534a\u81f3\u4e0b\u53487\u6642, \u6bcf\u9031\u5de5\u4f5c5\u5929, \u6bcf\u5929\u5de5\u4f5c 9 \u5c0f\u6642\n\u7533\u8acb\u9808\u77e5 :\u6c42\u8077\u8005\u53ef\u96fb\u90f5\u00a0[via APPLY NOW]\u00a0\u5c65\u6b77\u8868\u7d66\u5609\u5229\u7522\u54c1\u6709\u9650\u516c\u53f8\u3002\u5982\u8981\u7d22\u53d6\u6536\u96c6\u500b\u4eba\u8cc7\u6599\u8072\u660e, \u8acb\u8207\u738b\u5c0f\u59d0(Email)\u806f\u7d61\u3002", "employment_types": ["Full Time", "Permanent"], "selling_points": ["5 days works, Attractive remuneration package", "Degree in Engineering, Manufacturing, Business etc", ">10 yrs operation management exp. in Manufacturing"], "locations": ["Others - China"], "categories": ["Engineering", "Engineering Project Management", "Manufacturing & Production", "Manufacturing", "Manufacturing Management"], "post_time": "2022-01-06T04:21:07Z", "salary": {"currency": null, "max": null, "min": null, "period": "monthly", "term": null}, "salary_visible": false, "title_keywords": ["assistant general manager"], "responsibilities": [], "requirements": {"degrees": [], "majors": [], "languages": [], "language_level": [], "hard_skills": [], "soft_skills": [], "languages_combined": []}, "experience_required": {"duration": [], "field": []}}, {"job_id": "100003009035288", "location_code": "hk", "company": "Karrie International Holdings Limited", "job_title": "\u9ad8\u7d1a\u7d50\u69cb\u5de5\u7a0b\u7d93\u7406", "description": "Our client is one of the designing and exporting companies in Hong Kong with a rich history specializing in kitchenware & houseware products.\n\nJob Responsibilities:\n\nDevelop and implement sales strategy, tactic, sales plans and profit targets.\nUpsell and Increase market share in existing markets and maximize new business development opportunities.\nDrive the continuous improvement to enhance the operations effectiveness and business performance.\nOversee supervisors and merchandising team to ensure procedures and standards are being executed to company standards\nMonitor T&A and ensure on-time delivery;\nDevelop and maintain good customer relationships with multi clients not limited to local and global (EU/US) clients\nResponsible to report and analyse merchandising trends and marketability\n\nJob Requirements:\n\nA minimum of 5-10 years of solid experience in the field of kitchenware or gadgets\nHave experience in merchandising role from wholesales business/ importer / distributors\nFamiliar with US and European Market, clear understanding of the international market and industrial characteristics\nGood knowledge of EU / UL /US standards and regulations concerning product safety and requirements\nExperience in handling mid to high end clients will be a definite advantage\nAggressive, proactive and passionate about work and to be able to work independently with motivation\nStrong commercial sense is required while fluency in Chinese and English is required\nFrequent travel to factories in China is required\nAbility to address multiple time zones (China, Europe, US)\nGood interpersonal skills and communication in written and spoken English, Cantonese and Putonghua is essential\nImmediately available is preferred\nInterested parties please click \u201cApply Now\u201d to submit your application stating current and expected salary, and availability. If you have any enquiries, please contact Mr. Jason Yim at\u00a0+852 3586 3077\u00a0for a confidential discussion.\n\nPlease note that by submitting your job application you understand and agree that all personal data provided by you will be treated in strict confidence in accordance with the Personal Data (Privacy) Ordinance for recruitment purposes only. Your information will be reviewed by\u00a0Flex Consultancy Limited and/or its appointing client who is hiring for this job opening. Shortlisted candidates will be contacted by Flex and/or its appointing client who is hiring for this job opening for proceeding further selection processes.", "employment_types": ["Full Time"], "selling_points": [], "locations": ["Others - China"], "categories": ["Manufacturing", "Manufacturing Management", "Others"], "post_time": "2022-01-10T06:44:36Z", "salary": {"currency": null, "max": null, "min": null, "period": "monthly", "term": null}, "salary_visible": false, "title_keywords": [], "responsibilities": ["operations", "procedures", "merchandising", "monitor", "develop", "maintain", "sales plans", "analyse", "report"], "requirements": {"degrees": [], "majors": [], "languages": ["cantonese", "putonghua", "english", "chinese"], "language_level": ["fluency", "good"], "hard_skills": [], "soft_skills": ["work independently", "clear", "communication", "interpersonal skills", "proactive", "passionate about"], "languages_combined": [{"language": "cantonese", "language_level": ["good"]}, {"language": "putonghua", "language_level": ["good"]}, {"language": "english", "language_level": ["fluency", "good"]}, {"language": "chinese", "language_level": ["fluency"]}]}, "experience_required": {"duration": ["minimum of 5-10 years"], "field": ["business", "merchandising"]}}, {"job_id": "100003009042716", "location_code": "hk", "company": "Flex Recruitment", "job_title": "Merchandising Manager (Wholesales) (40-45K,18 days AL,Double Pay, Kitchen & Gadget, EU/US Clients)", "description": "Purpose& Overall Relevance for the Organization:\n\nDrive and coordinate production allocation and availability management for finished products and components across all Footwear LOs/functions\nDrive conceptual evolution, implementation and ramp-up of Speed programs; and coordinate all operations of Speed programs across the Footwear organization, incl. feasibility checks, material staging, capacity and availability management\nSupport the Director Allocation & Capacity in the operational and strategic planning process; and in identifying/implementing initiatives that enhance the capabilities, efficiency, effectiveness and collaboration within Footwear Sourcing\n\nKey Responsibilities:\n\nOptimize seasonal production allocation along various dimensions incl. availability, landed costs (FOB, duty, VA), key technologies, model mix and factory capabilities; drive allocation strategy implementation through production allocation on BU and franchises level; actively influence and shape development allocation through production allocation decisions\nDrive monthly performance of Footwear Sourcing operations along relevant dimensions (e.g. order fulfilment KPIs, capacity utilization, process compliance and efficiency, etc.)\nDrive component business and feasibility checks and develop alternative sourcing options to optimize trade benefits\nProactively identify potential issues for fulfilment and capacity utilization and work closely with the LOs and/or functional teams to develop mitigation measures\nManage end to end planning process of special Statement projects (e.g Yeezy..)\nManage the current Footwear Speed programs Continuous Replenishment / Planned Responsiveness / In-Season Creation: monitor execution of all on/off-system processes to ensure high degree of speed feasibility, order fulfilment, and to identify improvement opportunities; specifically, own and drive the seasonal speed feasibility checks and support SMU requests\nSupport the department in ad-hoc data analyses\nSupport selected projects as defined by Director Allocation & Capacity\n\nKey Relationships:\n\nLO teams and esp. LO Planning Managers, DPCs and SDOMs\nSupplier teams and esp. Business Planning Managers\nGlobal Supply Planning and BU planning\nGOPS Speed team\nProduct Operations\nother COPS functions\n\nKnowledge Skills and Abilities:\n\nStrong analytical and quantitative skills\nGood interpersonal and communication skills\nUnderstanding of trade topics (import duties, FTA, trade barriers) affecting imports from the Footwear source countries into major markets\nGood knowledge of Footwear industry and manufacturing methods a plus\nGood knowledge of standard Software applications (Excel, PowerPoint)\nProject management skills a plus\n\nRequisite Education and Experience / Minimum Qualifications:\n\nUndergraduate university degree\nMinimum of 5 years working experience in a Sourcing role or operations\nFluency in English, knowledge of another language (ideally Mandarin, Vietnamese, Bahasa, or German) an advantage.", "employment_types": ["Full Time", "Permanent"], "selling_points": ["Manage global (EU/US) clients", "Experience in wholesale/importer/distributors", "5-10 years experience in kitchenware or gadgets"], "locations": ["Ngau Tau Kok"], "categories": ["Manufacturing", "Manufacturing Management", "Merchandising & Purchasing", "Others"], "post_time": "2022-01-12T08:29:59Z", "salary": {"currency": null, "max": null, "min": null, "period": "monthly", "term": null}, "salary_visible": false, "title_keywords": ["merchandising manager"], "responsibilities": ["management", "strategic planning", "operations", "compliance", "implementation", "coordinate", "kpis", "costs"], "requirements": {"degrees": [], "majors": [], "languages": [], "language_level": [], "hard_skills": [], "soft_skills": [], "languages_combined": []}, "experience_required": {"duration": [], "field": []}}, {"job_id": "100003009034674", "location_code": "hk", "company": "AY Talent Solutions Limited", "job_title": "Supply Chain Manager (JDM)", "description": "Background\n\n\nMy client\u00a0operates as a unified virtual system with their customers and suppliers by acting as seamless extensions of their operations. They offer customized, flexible and integrated supply chain solutions, supported by a global technology platform and a dedicated, market-focused team.\nThey are currently seeking a Supply Chain Manager - JDM (Joint Design and Manufacturing to join their global team to lead their strategic sourcing, supplier selection; development, commodity engineering, component engineering and materials cost-reduction initiatives in support of our Connectivity and Cloud Solutions (CCS) segment\nJob Requirements\n\n\nProvides direction for source selection and ensures proper process implementation.\nWorks with the Commodity Management teams to ensure negotiations meet business requirements and growth plans.\nWorks with the supply chain management process for customers, from materials pricing and BOM analysis to delivery execution and flexibility performance.\nQuotes and negotiates critical high dollar or strategic commodities, or provides direction to a team of commodity managers.\nProvides support in the analysis of costed customer bids or quarterly BOM Costing exercises for global customers.\nDevelop a robust forecast review process with the Customer Focus Team at the\u00a0manufacturing sites that will enable forecast attainment improvements.\nDrive account inventory performance through analytical MPS management.\nSupports quarterly business reviews with customers, and with senior management at\u00a0key/strategic suppliers.\nProvides leadership and direction with respect to interaction with suppliers. Leads\u00a0process development and development of commodity strategies.\nSupports projects or programs on a global basis.\nSkills & Requirements\n\n\nDegree holder in Supply Chain Management / Electronics or related discipline\nIn-depth knowledge and understanding of supply chain management, inventory\nmanagement, marketplace conditions for a broad range of strategic commodities,\u00a0industry pricing, technology, emerging trends.\nGood understanding of IT concepts and integrated business applications.\nExcellent analytical, negotiation, and problem resolution skills.\nPrevious experience within an electronics manufacturing services environment is\u00a0required.", "employment_types": ["Full Time", "Permanent"], "selling_points": ["Joint Design and Manufacturing", "Customer Management", "Design for supply chain initiatives"], "locations": ["Shatin Area"], "categories": ["Engineering", "Manufacturing & Production", "Transportation & Logistics", "Supply Chain", "Manufacturing", "Manufacturing Management"], "post_time": "2022-01-10T03:59:33Z", "salary": {"currency": null, "max": null, "min": null, "period": "monthly", "term": null}, "salary_visible": false, "title_keywords": ["supply chain manager"], "responsibilities": ["management teams", "cost", "management", "operations", "analysis", "review", "inventory", "implementation", "design", "develop", "resolution", "forecast", "meet business requirements", "plans", "senior management"], "requirements": {"degrees": ["degree holder"], "majors": [], "languages": [], "language_level": [], "hard_skills": ["analysis", "focus"], "soft_skills": ["flexible", "negotiation", "focused", "robust", "customer focus", "leadership"], "languages_combined": []}, "experience_required": {"duration": [], "field": ["manufacturing"]}}, {"job_id": "100003009037241", "location_code": "hk", "company": "adidas Sourcing Limited", "job_title": "Senior Manager Delivery Management FW", "description": "Senior Purchasing Supervisor - Building Material\n\nJob Description\n\nResponsible for building material e.g. aluminum/glass (glass curtain wall) quotation, contract, purchasing orders, order follow up, on time delivery, as well as handling client enquiries.\nWorking closely with own factories (South China) follow up purchasing orders to ensure on time delivery\nHandle client independently on construction project tendering and quotation, planning & organization skills and able to follow up details closely\nWorking independently in full Sales & purchasing duties from follow up the orders with clients, mass production quality control until shipment completed\n\nRequirements\n\nMinimum of 5 years of experience in building material sales & merchandising position\nKnowledge in building materials or aluminum/glass (glass curtain wall) products\nStrong analytical and project management skills, attention to details\nHigh sense of accountability and ownership\nGood interpersonal & communication skills and able to work under pressure\nGood command of written and spoken English and Chinese, Mandarin\nAbility to multi-task, highly adaptable in a dynamic growing environment.\nWilling to travel to China (for 1sttime training only)", "employment_types": ["Full Time", "Permanent"], "selling_points": ["Global Sourcing HQ", "Footwear Sourcing Function", "Inclusive and Diverse Culture"], "locations": ["Ngau Tau Kok"], "categories": ["Transportation & Logistics", "Shipping", "Supply Chain", "Manufacturing", "Manufacturing Management"], "post_time": "2022-01-11T02:17:08Z", "salary": {"currency": null, "max": null, "min": null, "period": "monthly", "term": null}, "salary_visible": false, "title_keywords": ["senior manager"], "responsibilities": ["quotation", "ensure on time delivery", "tendering", "quality control", "planning"], "requirements": {"degrees": [], "majors": [], "languages": ["english", "chinese", "mandarin"], "language_level": ["good command"], "hard_skills": ["project management", "dynamic"], "soft_skills": ["communication skills", "multi-task", "accountability", "adaptable", "project management skills", "dynamic", "attention to details", "interpersonal", "work under pressure"], "languages_combined": [{"language": "english", "language_level": ["good command"]}, {"language": "chinese", "language_level": ["good command"]}, {"language": "mandarin", "language_level": ["good command"]}]}, "experience_required": {"duration": ["minimum of 5 years"], "field": ["merchandising"]}}, {"job_id": "100003009043132", "location_code": "hk", "company": "Links International", "job_title": "Senior Supervisor - Merchandising", "description": "SPEED & SPIRIT is what we look for in our candidates, defined by some simple values that inspire us to BE DRIVEN in our performance, BE VIBRANT in our sporting legacy, BE TOGETHER in our team spirit, and BE YOU to let our individual talent and experience shine. Applying for a job at PUMA is easy and all genders are welcome. Simply click APPLY ONLINE and follow the steps to upload your application.\n\nComply and act in accordance with Apparel/ Accessories OPD processing in terms of ordering process, confirmation timeline, minimum and data maintenance policy\nMaintain seasonal buying catalog and distribute it to the global market with forecast planning to ensure customer can place orders in accurate and timely manner\nManage system data maintenance to ensure the data is up to date and executed end-to-end correctly in seasonal opening preparation and daily operations\nCoordinate with R&D and business units on style readiness for order placement and act as the main point of contact of global sales offices on PO collaboration, ensure smooth and efficient communication as well as information exchange\nCompile scheduled reports including but not limited to KPI, PO confirmation status, style readiness, accurately and timely\nPrepare presentation materials and assist in projects related new system implementation, process automation and workflow enhancement\nTertiary education or above, preferably major in Supply Chain, Business or related discipline\n5+ years working experience, related to Order Management is highly preferred\nProficiency in MS office, especially advanced in Excel and Power BI; experience in ERP system is a plu\nFluent in English, Cantonese and Mandarin\nExcellent communication & interpersonal skills; able to be a team player is a must\nSelf-motivated, proactive, detail-minded with multi-tasking capabilities\nGood problem-solving skills and analytical skills\n\nPUMA supports over 14,000 employees across 120+ countries. The PUMA Group owns the brand PUMA, Cobra Golf and stichd, and is headquartered in Herzogenaurach, Germany.\nPUMA provides equal opportunities for all job applicants, regardless of race, color, religion, national origin, sex, gender identity or expression, sexual orientation, age, or disability. Equality for all is one of the core principles at PUMA and we do not tolerate any form of harassment or discrimination.", "employment_types": ["Full Time", "Permanent"], "selling_points": ["Building material exp preferred", "Focus on sales & merchandising", "Double Pay + Bonus, 5 day work week"], "locations": ["Not Specified"], "categories": ["Engineering", "Manufacturing & Production", "Manufacturing", "Manufacturing Management", "Merchandising & Purchasing", "Others"], "post_time": "2022-01-12T09:52:38Z", "salary": {"currency": "HKD", "max": 34999, "min": 30000, "period": "monthly", "term": null}, "salary_visible": true, "title_keywords": ["merchandising", "supervisor"], "responsibilities": ["order management", "power bi", "maintenance", "data", "new system implementation", "coordinate with", "system data", "communication", "daily operations", "maintain", "reports", "contact", "forecast", "planning"], "requirements": {"degrees": [], "majors": [], "languages": ["cantonese", "english", "mandarin"], "language_level": ["fluent"], "hard_skills": ["simple", "r&d", "excel", "bi", "maintenance", "analytical skills", "erp system", "system implementation", "problem-solving skills", "cobra", "processing", "ms office", "exchange"], "soft_skills": ["efficient", "detail-minded", "self-motivated", "team spirit", "proactive", "advanced", "timely", "presentation", "analytical skills", "communication", "multi-tasking", "interpersonal skills", "smooth", "problem-solving skills", "team player", "accurate", "driven"], "languages_combined": [{"language": "cantonese", "language_level": ["fluent"]}, {"language": "english", "language_level": ["fluent"]}, {"language": "mandarin", "language_level": ["fluent"]}]}, "experience_required": {"duration": ["5+ years"], "field": ["related", "management", "erp system", "team"]}}, {"job_id": "100003009042253", "location_code": "hk", "company": "PUMA International Trading Services Limited", "job_title": "Senior Executive Order Management Apparel & Accessories", "description": "Job Description\n\n\nSolid Sales & Merchandising experience in building material e.g. aluminum/glass/ceramics for local Market preferred\nCapable to deal with buyers/factories independently\nStrong negotiation, planning & organization skills and able to follow up details closely\nWorking independently in full Sales & Merchandising duties from follow up the orders with customers, mass production quality control until shipment completed\nGood interpersonal & communication skills and able to work under pressure\nGood command of written and spoken English and Chinese, Mandarin\n\nRequirements\n\n\nMinimum of 5 years of experience in building material sales & merchandising position\nStrong analytical and project management skills, attention to details\nHigh sense of accountability and ownership\nAbility to multi-task, highly adaptable in a dynamic growing environment.\nWilling to travel to China (for training only)", "employment_types": ["Full Time", "Permanent"], "selling_points": ["Order Management", "Flexible working hours", "Fun and energetic working environment"], "locations": ["Kowloon Bay"], "categories": ["Transportation & Logistics", "Supply Chain", "Manufacturing", "Manufacturing Management", "Merchandising & Purchasing", "Procurement / Purchasing / Sourcing"], "post_time": "2022-01-12T06:44:37Z", "salary": {"currency": null, "max": null, "min": null, "period": "monthly", "term": null}, "salary_visible": false, "title_keywords": ["senior executive"], "responsibilities": ["merchandising", "communication", "planning", "quality control", "work under pressure"], "requirements": {"degrees": [], "majors": [], "languages": [], "language_level": [], "hard_skills": ["project management", "dynamic"], "soft_skills": ["multi-task", "accountability", "adaptable", "project management skills", "dynamic", "attention to details"], "languages_combined": []}, "experience_required": {"duration": ["minimum of 5 years"], "field": ["merchandising"]}}, {"job_id": "100003009037716", "location_code": "hk", "company": "Links International", "job_title": "Senior Supervisor - Merchandising", "description": "\u5d17\u4f4d\u8077\u8cac\uff1a\n\n1\u3001\u8ca0\u8cac\u6df7\u51dd\u571fMic\u9805\u76ee\u7684\u7e3d\u9ad4\u898f\u5283\u8a2d\u8a08\uff0c\u7d44\u7e54\u64ec\u8a02\u958b\u767c\u9805\u76ee\u7684\u5177\u9ad4\u5efa\u8a2d\u65b9\u6848\uff0c\u7de8\u5236\u548c\u4e0a\u5831\u5de5\u4f5c\u8a08\u5283\u548c\u7e3d\u7d50\n\n2\u3001\u6839\u64da\u516c\u53f8\u7684\u90e8\u7f72\uff0c\u5236\u5b9a\u6df7\u51dd\u571fMic\u516c\u53f8\u7684\u767c\u5c55\u898f\u5283\u8207\u5e74\u5ea6\u61c9\u5b8c\u6210\u7684\u5404\u9805\u5de5\u4f5c\u6307\u6a19\uff0c\u4e26\u8a8d\u771f\u8cab\u5fb9\u3001\u57f7\u884c\u5efa\u7bc9\u516c\u53f8\u5404\u9805\u5de5\u4f5c\u6c7a\u8b70\uff0c\u843d\u5be6\u4e0b\u9054\u7684\u5404\u9805\u5de5\u4f5c\u6307\u6a19\n\n3\u3001\u5168\u9762\u4e3b\u6301\u6df7\u51dd\u571fMic\u516c\u53f8\u7684\u5de5\u4f5c\uff0c\u5c0d\u751f\u7522\u7d93\u71df\u3001\u5de5\u7a0b\u8cea\u91cf\u3001\u8ca1\u52d9\u72c0\u6cc1\u3001\u5b89\u5168\u5de5\u4f5c\u8ca0\u8cac\n\n4\u3001\u7d44\u7e54\u958b\u5c55\u6210\u672c\u63a7\u5236\uff0c\u5c0d\u524d\u671f\u8cbb\u7528\u7b49\u5f48\u6027\u8f03\u5927\u7684\u5de5\u7a0b\u8cbb\u7528\u548c\u95dc\u9375\u74b0\u7bc0\u9032\u884c\u91cd\u9ede\u63a7\u5236\uff0c\u5b9a\u671f\u9032\u884c\u5de5\u7a0b\u8cbb\u7528\u5dee\u7570\u5206\u6790\n\n5\u3001\u6df1\u5165\u4e86\u89e3\u5efa\u7bc9\u69cb\u4ef6\u884c\u696d\u767c\u5c55\u548c\u5e02\u5834\u9700\u6c42\uff0c\u5c0d\u516c\u53f8\u7684\u5e02\u5834\u5b9a\u4f4d\u3001\u5168\u9762\u898f\u5283\u3001\u71df\u92b7\u7b56\u7565\u3001\u65bd\u5de5\u9032\u5c55\u5177\u6709\u5168\u5c40\u6027\u7684\u6307\u5c0e\u3001\u9818\u5c0e\u4f5c\u7528\n\n6\u3001\u5efa\u7acb\u7cfb\u7d71\u3001\u5b8c\u5584\u7684\u8cea\u91cf\u7ba1\u7406\u9ad4\u7cfb\uff0c\u5efa\u8a2d\u516c\u53f8\u7684\u6a19\u6e96\u5316\u9805\u76ee\u7ba1\u7406\uff0c\u5168\u9762\u7d71\u7c4c\u516c\u53f8\u5404\u9805\u76ee\u63a8\u9032\uff0c\u78ba\u4fdd\u5de5\u7a0b\u8cea\u91cf\u3001\u9032\u5ea6\u548c\u6210\u672c\u63a7\u5236\uff0c\u69cb\u5efa\u516c\u53f8\u7cbe\u54c1\u9805\u76ee\u53ca\u54c1\u724c\n\n\u4efb\u8077\u8981\u6c42\uff1a\n\n1\u3001\u672c\u79d1\u6216\u4ee5\u4e0a\u5b78\u6b77\uff0c\u571f\u6728\u5de5\u7a0b\u3001\u5efa\u7bc9\u5b78\u3001\u6750\u6599\u63a7\u5236\u3001\u6a5f\u68b0\u985e\u76f8\u95dc\u5c08\u696d\u512a\u5148\n\n2\u3001\u719f\u7df4\u4f7f\u7528CAD\u3001OFFICE\u8edf\u4ef6\n\n3\u3001\u5177\u6709\u5efa\u9020\u5e2b\u8cc7\u8cea\u6216\u4e2d\u7d1a\u53ca\u4ee5\u4e0a\u6280\u8853\u8077\u7a31\n\n4\u3001\u719f\u6089\u9999\u6e2f\u53ca\u570b\u5167\u88dd\u914d\u5f0f\u884c\u696d\u53ca\u5efa\u7bc9\u5de5\u696d\u5316\u7684\u653f\u7b56\u548c\u6280\u8853\u6a19\u6e96\n\n5\u3001\u719f\u6089\u6df7\u51dd\u571f\u7bb1\u9ad4\u7684\u751f\u7522\u3001\u5b89\u88dd\u904e\u7a0b\uff0c\u4e86\u89e3\u9ad8\u5f37\u5ea6\u6df7\u51dd\u571f\u7684\u6750\u6599\u914d\u65b9\u3001\u5de5\u85dd\u53ca\u6aa2\u9a57\u8981\u6c42\n\n6\u3001\u719f\u6089\u5efa\u7bc9\u884c\u696d\u5408\u898f\u3001\u5be9\u8a08\u3001\u9805\u76ee\u7ba1\u7406\u77e5\u8b58\uff0c\u4ee5\u53ca\u570b\u5bb6\u5efa\u7bc9\u65b9\u9762\u6cd5\u5f8b\u6cd5\u898f\u689d\u6b3e\uff0c\u6709\u8f03\u5f37\u8a55\u5be9\u80fd\u529b\n\n7\u3001\u5c0d\u6df7\u51dd\u571f\u7bb1\u9ad4\u914d\u7b4b\u8a2d\u8a08\u3001\u6a21\u5177\u7d50\u69cb\u53ca\u4f7f\u7528\u3001\u69cb\u4ef6\u6f86\u7bc9\u3001\u990a\u8b77\u6709\u4e00\u5b9a\u7684\u7406\u8ad6\u57fa\u790e\n\n8\u30015\u5e74\u4ee5\u4e0a\u5efa\u7bc9\u9810\u88fd\u69cb\u4ef6\u884c\u696d\u904b\u71df\u7ba1\u7406\u5de5\u4f5c\u7d93\u9a57\uff0c\u8981\u6c42\u6709\u9999\u6e2f\u9805\u76ee\u7d93\u6b77\n\n9\u3001\u5177\u5099\u5f88\u5f37\u7684\u6230\u7565\u601d\u7dad\u80fd\u529b\u3001\u826f\u597d\u7684\u7d93\u71df\u610f\u8b58\u3001\u7a81\u51fa\u7684\u9818\u5c0e\u80fd\u529b\uff08\u5206\u6790\u3001\u5224\u65b7\u3001\u6c7a\u7b56\u3001\u554f\u984c\u7684\u80fd\u529b\uff09\uff0c\u4ee5\u53ca\u793e\u6703\u4ea4\u969b\u3001\u653f\u5e9c\u516c\u95dc\u53ca\u696d\u52d9\u6d3d\u8ac7\u80fd\u529b\n\n10\u3001\u6709\u672c\u884c\u696d\u5e02\u5834\u71df\u92b7\u7d93\u9a57\u548c\u8c50\u5bcc\u7684\u4eba\u8108\u8cc7\u6e90\u3001\u76f8\u95dc\u5ba2\u6236\u8cc7\u6e90\u3001\u5f37\u5927\u7684\u696d\u52d9\u62d3\u5c55\u80fd\u529b\u8005\u512a\u5148\n\n\u798f\u5229\uff1a\u5305\u5403\u4f4f\u3001\u7bc0\u65e5\u798f\u5229\u3001\u8cfc\u8cb7\u4e94\u96aa\n\n\u5de5\u4f5c\u6642\u9593\uff1a\u5927\u5c0f\u5468\u5de5\u4f5c\u5236\uff0c\u5de5\u4f5c\u6642\u9593\uff1a8\uff1a30-17\uff1a30\n\n", "employment_types": ["Full Time", "Permanent"], "selling_points": ["Building material exp preferred", "Focus on sales & merchandising", "Double Pay + Bonus, 5 day work week"], "locations": ["Not Specified"], "categories": ["Engineering", "Manufacturing & Production", "Manufacturing", "Manufacturing Management", "Merchandising & Purchasing", "Others"], "post_time": "2022-01-11T03:36:26Z", "salary": {"currency": "HKD", "max": 34999, "min": 30000, "period": "monthly", "term": null}, "salary_visible": true, "title_keywords": ["merchandising", "supervisor"], "responsibilities": [], "requirements": {"degrees": [], "majors": [], "languages": [], "language_level": [], "hard_skills": [], "soft_skills": [], "languages_combined": []}, "experience_required": {"duration": [], "field": []}}, {"job_id": "100003009031359", "location_code": "hk", "company": "Links International", "job_title": "Deputy General Manager, \u526f\u7e3d\u7d93\u7406 - \u6df7\u51dd\u571f", "description": "\n\u8077\u8cac :\u5354\u52a9\u7e3d\u7d93\u7406\u8655\u7406\u516c\u53f8\u65e5\u5e38\u8077\u52d9\n\n\u8cc7\u6b77 :\u5c08\u4e0a\u6559\u80b2\uff1a\u5b78\u58eb\u5b78\u4f4d; 2\u5e74\u7d93\u9a57; \u826f\u597d\u7cb5\u8a9e; \u4e00\u822c\u666e\u901a\u8a71; \u826f\u597d\u82f1\u8a9e; \u61c2\u8b80\u5beb\u4e2d\u6587; \u61c2\u8b80\u5beb\u82f1\u6587; \u61c2MS Word; \u61c2MS Excel; \u5177\u6709\u4e00\u822c\u4e92\u806f\u7db2\u77e5\u8b58; \u61c2\u4e2d\u82f1\u6587\u96fb\u8166\u64cd\u4f5c; \u5177\u57fa\u672c\u6cd5\u5f8b\u77e5\u8b58\u53ca\u79fb\u6c11\u516c\u53f8\u5de5\u4f5c\u7d93\u9a57\u512a\u5148\n\n\u5f85\u9047 :\u6bcf\u6708$15,000 - $17,000, \u6709\u96d9\u7ce7 \u53ca\u8d85\u6642\u5de5\u4f5c\u88dc\u5047, \u661f\u671f\u4e00\u81f3\u4e94: \u4e0a\u53489\u6642\u81f3\u4e0b\u53486\u6642, \u6bcf\u9031\u5de5\u4f5c5\u5929, \u6bcf\u5929\u5de5\u4f5c 9 \u5c0f\u6642, 1\u5c0f\u6642\u7528\u81b3\u6642\u9593\n\n\u7533\u8acb\u9808\u77e5 :\u6c42\u8077\u8005\u53ef\u96fb\u90f5(Apply Now)\u5c65\u6b77\u8868\u7d66\u5929\u4e00\u96c6\u5718(\u570b\u969b)\u63a7\u80a1\u6709\u9650\u516c\u53f8\u3002\u5982\u8981\u7d22\u53d6\u6536\u96c6\u500b\u4eba\u8cc7\u6599\u8072\u660e, \u8acb\u8207\u6731\u5148\u751f(Email)\u806f\u7d61\u3002\n\n", "employment_types": ["Full Time", "Permanent"], "selling_points": ["\u719f\u6089\u6df7\u51dd\u571f\u7bb1\u9ad4\u7684\u751f\u7522\u3001\u5b89\u88dd\u904e\u7a0b", "\u5305\u5403\u4f4f\u3001\u7bc0\u65e5\u798f\u5229", "\u5de5\u4f5c\u5730\u9ede\uff1a\u5ee3\u6771\u7701"], "locations": ["Others - China"], "categories": ["Building & Construction", "Building / Construction / QS", "Engineering", "Manufacturing & Production", "Manufacturing", "Manufacturing Management"], "post_time": "2022-01-07T09:14:45Z", "salary": {"currency": null, "max": null, "min": null, "period": "monthly", "term": null}, "salary_visible": false, "title_keywords": ["general manager"], "responsibilities": [], "requirements": {"degrees": [], "majors": [], "languages": [], "language_level": [], "hard_skills": ["excel", "word"], "soft_skills": [], "languages_combined": []}, "experience_required": {"duration": [], "field": []}}, {"job_id": "100003009041330", "location_code": "hk", "company": "Rich Top Group International Holding Limited", "job_title": "\u7e3d\u7d93\u7406\u52a9\u7406**", "description": "Key Role & Job Responsibilities:\n\nReport to General manager and work closely with internal departments for effective management and improvement of company operation\nManage the operation departments and lead the team to achieve the business strategic goal successfully in fast business environment and fast changing pace\nReview and improve the standardized management system, process and procedure in PMC, production efficiency and quality, IE and automation, customer service, health and safety, human resources and factory administration, etc.\nFacilitate the initiatives of cost control measures and manage the overall cost reduction in the factory\n\nQualifications & Job Requirements:\n\nDegree holders in Engineering, Manufacturing or Business administration equivalent subject\nAt least 10 years operation management experience in manufacturing industry\nExperience in mobile phone parts or metal injection industry is an advantage\nGood knowledge in organizational planning, data analysis, operation management, personnel training and development\nExcellent communication and leadership skill, decisive, planning and resource integration ability, quick thinking, able to withstand pressure\nProfessional ethics, Strong sense of responsibility\nGood command of both written & spoken English\nStation in Guangzhou and need to travel if required\n\nWe offer an attractive remuneration with excellent opportunities to the right candidate. Interested parties please click\u00a0\"APPLY NOW\"\u00a0to apply with detailed resume\u00a0stating present and expected salary. \u00a0Please quote the position you applied for in all correspondence.\u00a0\n\nWe are an equal opportunity employer and welcome applications from all qualified candidates. Personal data collected will be treated in strictest confidential and handled confidentially by authorized personnel for recruitment-related purposes. Applicants not hearing from us within six weeks from the date of advertisement may consider their applications unsuccessful.\n\nCompany website:\u00a0www.cn-innovations.com", "employment_types": ["Full Time"], "selling_points": [], "locations": ["Tsim Sha Tsui"], "categories": ["Manufacturing", "Manufacturing Management"], "post_time": "2022-01-12T03:45:35Z", "salary": {"currency": null, "max": null, "min": null, "period": "monthly", "term": null}, "salary_visible": false, "title_keywords": [], "responsibilities": ["administration", "management", "cost", "review", "quality", "customer service", "cost control", "report"], "requirements": {"degrees": ["degree"], "majors": ["manufacturing", "business administration", "engineering"], "languages": ["english"], "language_level": ["good command"], "hard_skills": ["integration", "mobile", "analysis"], "soft_skills": ["sense of responsibility", "organizational", "communication", "decisive", "leadership skill"], "languages_combined": [{"language": "english", "language_level": ["good command"]}]}, "experience_required": {"duration": ["at least 10 years"], "field": ["operation management", "manufacturing industry"]}}, {"job_id": "100003009024265", "location_code": "hk", "company": "FSE Engineering Group Limited", "job_title": "Assistant Factory Manager", "description": "\u00a0Qualification & requirements:\n\nHigher Diploma or above in Industrial Engineering/ Manufacturing Engineering/ Logistic Management or equivalent.\nWith knowledge of industrial engineering / mechanical engineering would be an advantage.\nMinimum 10 years of relevant working experience in factory management, preferably in the construction industry.\nGood command of spoken and written English and Chinese.\nHighly responsible, Independent, detail-minded, organized, self-motivated, and with strong communication skills.\u00a0\nDuties:\n\nThe tasks include manpower management, production planning, material ordering, product fabrication, handling temporary equipment/material storage for project teams, logistics, and report of work done to Management.\nOn-site inspection of product defect investigation, arrangement of internal workshop and warehouse transportation, assist in coordination works and other ad-hoc projects as assigned.", "employment_types": ["Full Time", "Permanent"], "selling_points": ["HD Industrial Engrg/Manufacturing Engrg", "Min 10yrs+ relevant factory management.", "Good knowledge industrial engrg/mechanical engrg"], "locations": ["Fanling"], "categories": ["Engineering", "Manufacturing & Production", "Transportation & Logistics", "Inventory / Warehousing", "Manufacturing", "Manufacturing Management"], "post_time": "2022-01-05T12:10:34Z", "salary": {"currency": null, "max": null, "min": null, "period": "monthly", "term": null}, "salary_visible": false, "title_keywords": ["assistant", "factory manager"], "responsibilities": ["management", "material storage", "coordination works", "workshop", "production planning", "teams", "investigation", "site inspection", "logistics", "ad-hoc projects", "report"], "requirements": {"degrees": ["higher diploma or above"], "majors": ["manufacturing", "engineering"], "languages": ["english", "chinese"], "language_level": ["good command"], "hard_skills": [], "soft_skills": ["detail-minded", "organized", "self-motivated", "communication skills", "independent", "responsible"], "languages_combined": [{"language": "english", "language_level": ["good command"]}, {"language": "chinese", "language_level": ["good command"]}]}, "experience_required": {"duration": ["minimum 10 years"], "field": ["management", "construction industry", "relevant working experience"]}}, {"job_id": "100003009030157", "location_code": "hk", "company": "Lee & Man Paper Manufacturing Limited", "job_title": "Factory Deputy General Manager", "description": "Company background:\n\n\u00a0A leading global packaging and tissue paper manufacturer\nWe are recruiting different talents to facilitate our expansion globally\nLee & Man Paper keeps pursuing the highest quality by being innovative; highly concerns on different areas of the company, such as production, HR, sales & marketing, R & D, logistics and environmental management\n\nJob Responsibilities:\u00a0\n\nHandle the day-to-day operations of the plant\nCoordinate the planning and management of production, safety, fire protection,\u00a0environmental protection, logistics, material storage and other plant affairs\nCoordinate, communicate and cooperate among all departments in the factory in order to improve management efficiency\nManage the production schedule, delivery and production in the plant, and expand production capacity to reduce costs\nDevelop performance standards, supervise staff regularly, give advice and monitor staff performance assessment\n\n\u00a0Job Requirements:\u00a0\n\nAssociate Degree or above\nGood leadership skills, problem solving skills and good communication skills\nProactive, diligent, self-motivated and accountable for responsibilities\nWith more than 10 years of work experience, at least 5 years in the factory management, have solid experiences in working for large and medium-sized factory experience is preferred\nStation in China or Southeast Asia\n\nWe offer competitive remuneration package to the right candidate.\u00a0 For interested candidates, please send your CV by clicking \"Apply Now\" button or fax it to (852) 2171 7314.\u00a0\n\nFor more company information, please visit our web-site at http://www.leemanpaper.com\n\n(All information gathered will be used to assess a candidate\u2019s suitability for applied position. Only short-listed candidates will be contacted)", "employment_types": ["Full Time", "Permanent"], "selling_points": ["Attractive remuneration package", "A leading global paper manufacturer", "Global business exposure opportunity"], "locations": ["Not Specified"], "categories": ["Manufacturing", "Manufacturing Management"], "post_time": "2022-01-07T06:53:07Z", "salary": {"currency": null, "max": null, "min": null, "period": "monthly", "term": null}, "salary_visible": false, "title_keywords": ["factory deputy general manager"], "responsibilities": ["management", "material storage", "day-to-day operations", "monitor", "develop", "coordinate", "logistics", "schedule", "costs", "planning"], "requirements": {"degrees": ["degree or above"], "majors": [], "languages": [], "language_level": [], "hard_skills": ["problem solving skills"], "soft_skills": ["communication skills", "self-motivated", "leadership skills", "diligent", "accountable", "problem solving skills", "proactive"], "languages_combined": []}, "experience_required": {"duration": ["10 years", "at least 5 years"], "field": ["management"]}}, {"job_id": "100003009028147", "location_code": "hk", "company": "Modern Dental Laboratory Company Limited", "job_title": "Operations Manager", "description": "Our expanding company is seeking to hire an Operations Manager to join our team. Your main role is mainly to ensure proper implementation of processes and practices across the organization. The specific duties include supply chain management, ensure timely delivery of products and services and securing compliance. You should be ready to mentor your team members, find ways to improve customer service levels and implement best practices.\n\n\u00a0Job Responsibilities\u00a0 \u00a0 \u00a0\u00a0 \u00a0 \u00a0 \u00a0\n\nWork with management to organise and manage operational activities\nImplementation of process and practices, including procurement, warehouse management, fulfilment, and quality assurance\nEnsure daily customer orders are handled by the appropriate internal teams, monitor production progress, and ensure timely delivery of products and services\nAssist with the conducting of continuous improvement projects\nUpdate and maintain SOP documents to reflect changes to process and practices\nPurchase materials, plan inventory and oversee warehouse operations\nRecruit, train and supervise administration and supporting staff\nProvide regular reporting of various KPI\nLead and liaise with stakeholders for process enhancement project\n\nJob Requirements\n\n\nDegree in Engineering, Business Administration, or related disciplines\nMinimum 3 years working experience in a manager role\nExperience with made-to-order manufacturing will be an advantage\nIn depth knowledge in ISO 9001 or ISO 13485 is essential\nKnowledge in ERP system or Netsuite is an advantage\nOutstanding communication and interpersonal skills\nFluent in written and spoken English, proficiency in spoken Mandarin\nWilling to work overtime and can work under pressure\nInterested Candidates,\u00a0please send your\u00a0full resume with your\u00a0recent photo, current & expected salary\u00a0by e-mail to\u00a0hr @moderndentallab.com\n\n\nAll personal data collected will be used for recruitment and employment related purpose only.", "employment_types": ["Full Time", "Permanent"], "selling_points": ["Production Operations Management", "Inventory Control, logistics, Customer Services", "ERP, shipping, post-sales support"], "locations": ["Lai Chi Kok"], "categories": ["Sales, CS & Business Devpt", "Customer Service - Supervisor / Officer", "Manufacturing", "Manufacturing Management", "Sales Administration"], "post_time": "2022-01-07T01:37:51Z", "salary": {"currency": null, "max": null, "min": null, "period": "monthly", "term": null}, "salary_visible": false, "title_keywords": ["operations manager"], "responsibilities": ["continuous improvement projects", "management", "reporting", "work with management", "inventory", "quality", "implementation", "teams", "monitor", "purchase", "maintain", "plan", "daily customer orders", "liaise with", "warehouse operations", "administration"], "requirements": {"degrees": ["degree"], "majors": ["related disciplines", "business administration", "engineering"], "languages": ["english", "mandarin"], "language_level": ["proficiency", "fluent"], "hard_skills": ["erp system"], "soft_skills": ["work overtime", "communication and interpersonal skills", "work under pressure"], "languages_combined": [{"language": "english", "language_level": ["proficiency", "fluent"]}, {"language": "mandarin", "language_level": ["proficiency", "fluent"]}]}, "experience_required": {"duration": ["minimum 3 years"], "field": ["manufacturing"]}}, {"job_id": "100003009029358", "location_code": "hk", "company": "Edwin McAuley Electronics Ltd", "job_title": "Operation Assistant/ Operation Manager", "description": "The position reports directly to the Financial Controller.\n\n\u00a0\nJob Responsibilities:\u00a0\u00a0\n\nStart the career by visiting different operations like Customer Services, Logistic and Custom, MIS, Purchasing, Costing analysis, etc..\nBy working in the different operations for a period of time, review the work flow, suggest improvement and push working efficiency.\nDrive the overall operations to cope with the latest technology, e.g. working with MIS department to introduce automation in data input and output, implementing ERP in specific areas that reduces manual work, etc..\nWork with various counter parties, seek for overall improvement of the Company as a whole.\n\nJob Requirements:\n\nUniversity graduate in Information Technology, Manufacturing or Logistics related discipline.\n2 years\u2019 working experience, preferably in manufacturing field.\nGood communication, negotiation and interpersonal skills.\nWith critical-thinking mindset, not be afraid of arguing and conflict.\nWith confidence and be persistent to drive long term goal.\nWilling to frequently travel to Dongguan factory.\n\nWe place much emphasis on the career development of our employees, respect the worthiness of individual contributions and expect strong commitment to performance excellence. We offer 5 days work per week, competitive remuneration package and fringe benefits including year-end and mid-year bonuses, medical scheme, life & accident insurance etc. to the right candidate. \u00a0\n\u00a0\nInterested parties please send full resume stating current salary, expected salary and availability by clicking \"Apply Now\".\n\u00a0\nAll information received will strictly be kept confidential and be used for employment-related purposes only.", "employment_types": ["Full Time", "Permanent"], "selling_points": ["5 days work per week with double pay & Dis. bonus", "2 years working exp. preferably in manufacturing", "Willing to travel"], "locations": ["North Point"], "categories": ["Engineering", "Manufacturing & Production", "Manufacturing", "Manufacturing Management", "Merchandising & Purchasing", "Procurement / Purchasing / Sourcing"], "post_time": "2022-01-07T04:51:47Z", "salary": {"currency": null, "max": null, "min": null, "period": "monthly", "term": null}, "salary_visible": false, "title_keywords": ["operation assistant", "operation manager"], "responsibilities": ["operations", "review", "data input", "customer services", "costing analysis"], "requirements": {"degrees": ["university graduate"], "majors": ["manufacturing", "information technology"], "languages": [], "language_level": [], "hard_skills": ["goal", "scheme"], "soft_skills": ["confidence", "negotiation", "persistent", "communication", "interpersonal skills"], "languages_combined": []}, "experience_required": {"duration": ["2 years"], "field": ["manufacturing"]}}, {"job_id": "100003009037635", "location_code": "hk", "company": "Champion Union Holdings Limited", "job_title": "Safety Officer", "description": "Job Duties:\n\n-\u00a0Perform Safety Officer duties in according with F&IU(SOSS)R\n\n-\u00a0Establish site safety management system in accordance with legal and contractual requirements\n\n-\u00a0Develop - Administer the Company Safety Policies and procedures, safety and health regulations, rules and standards, i.e. the F&IU (Safety Management) Regulation\n\n-\u00a0Conduct Job hazards analysis/ Risk Assessment\n\n-\u00a0Implement and maintain the health and safety standards\n\n-\u00a0Prepare accident or Incident Investigation\n\nJob Requirements:\n\n-\u00a0Bachelor's Degree or higher diploma in Occupational Health & Safety or any other related discipline of education is required\n\n-\u00a0At least 5 year's of relevant experience in H&S, all of which preferably obtained within a sizeable organisation\n\n-\u00a0A candidate with Registration to Health & Safety in Hong Kong (ROS) under the HK Labour Department\n\n-\u00a0Extensive knowledge in carrying out H&S programs\n\n-\u00a0Candidate should have great interpersonal and communication skills to direct different parties in facilitation of corporate initiatives\n\nWork location:\u00a0Ha Tsuen,Yuen Long", "employment_types": ["Full Time"], "selling_points": [], "locations": ["Tin Shui Wai"], "categories": ["Manufacturing", "Manufacturing Management", "Others", "Security / Safety Control"], "post_time": "2022-01-11T03:20:24Z", "salary": {"currency": null, "max": null, "min": null, "period": "monthly", "term": null}, "salary_visible": false, "title_keywords": ["safety officer"], "responsibilities": ["regulations", "management", "policies", "analysis", "procedures", "investigation", "develop", "maintain", "safety standards"], "requirements": {"degrees": ["diploma", "degree", "bachelor"], "majors": [], "languages": [], "language_level": [], "hard_skills": [], "soft_skills": ["communication skills", "extensive", "interpersonal", "organisation"], "languages_combined": []}, "experience_required": {"duration": ["at least 5 year"], "field": ["relevant experience"]}}, {"job_id": "100003009035938", "location_code": "hk", "company": "Profit Hero Corporation Limited", "job_title": "Assistant Financial Controller (Station in S.E. Asian Country)", "description": "Required Skills & Experience:\u00a0\n\nDegree holder in Finance or Accounting with professional qualification or equivalent\nMinimum 10 years\u2019 experience with at least 5 years in manufacturing environment\nFamiliar with Hong Kong/PRC accounting rules and tax regulations policies\nExperienced in EMS industry and ERP system implementation is an advantage\nGood command of written and spoken Cantonese, Mandarin and English\nProactive and able to work in dynamic environment\nPrior PRC/Overseas exposure is a must\nImmediate available is preferable\n\nWe offer 5 day work week, attractive remuneration and fast promotion opportunities to the right talents. Interested parties please submit your full resume with qualifications, career history, availability, current and expected salary by kicking \"APPLY NOW\"", "employment_types": ["Full Time", "Permanent"], "selling_points": ["10+ yrs exp.& 5yrs in Manufacturing environment", "Familiar with HK & PRC Acc rules & tax regulations", "Degree in Finance/Acc with Prof. Qualification"], "locations": ["Overseas"], "categories": ["Accounting", "Finance / Accounting Manager", "Financial Controller", "Manufacturing", "Manufacturing Management"], "post_time": "2022-01-10T08:52:34Z", "salary": {"currency": null, "max": null, "min": null, "period": "monthly", "term": null}, "salary_visible": false, "title_keywords": ["assistant financial controller"], "responsibilities": ["tax", "regulations", "policies", "ems", "implementation"], "requirements": {"degrees": ["degree holder"], "majors": ["finance", "accounting"], "languages": ["cantonese", "english", "mandarin"], "language_level": ["good command"], "hard_skills": ["ems", "erp system", "dynamic", "prc accounting"], "soft_skills": ["dynamic environment", "proactive"], "languages_combined": [{"language": "cantonese", "language_level": ["good command"]}, {"language": "english", "language_level": ["good command"]}, {"language": "mandarin", "language_level": ["good command"]}]}, "experience_required": {"duration": ["at least 5 years", "minimum 10 years"], "field": ["manufacturing"]}}, {"job_id": "100003009025554", "location_code": "hk", "company": "Links International", "job_title": "Deputy General Manager (Concrete) - (Based in Zhao Qing)", "description": "Deputy General Manager (Concrete) - (Based in ZhaoQing)\n\nLocation: Sihui City, Zhaoqing City\n\nBenefit: included accommodation, annual leaves, social insurance\n\nWorking hour: Monday to Friday, Saturday (by-weekly half day), 8:30am - 5:30 pm\n\nResponsibilities\n\n\n\nResponsible for MiC project overall concrete planning and design, prepare the formulation of the specific construction, and report the work plan and summary\nResponsible for the concrete MiC Company's development plan and work indicators, make sure the assigned work should be completed\nTake full responsibilities on the work of Concrete Mic Company, responsible for production and operation, project quality, company P&L, and safety\nCarry out cost control, especially on project costs and key links with greater flexibility such as preliminary costs, and conduct periodic analysis of project cost differences\nIn depth understanding of the building material and construction industry and market demand. And understanding of company's market positioning, overall planning, marketing strategy and etc.\nDevelop a systematic quality management system and standardised project management, ensure project quality, progress and cost control as well as company branding\n\nRequirements:\n\n\n\nBachelor degree or above, majors in civil engineering, architecture, materials control, and machinery are preferred\nProficiency in using CAD and OFFICE software\nPossess construction engineer qualification or intermediate or above technical title\nFamiliar with the construction and building policies and technical standards of Hong Kong and China\nFamiliar with the production and installation process of concrete boxes, understand the material formula, technology and inspection requirements of high-strength concrete\nFamiliar with construction industry compliance, auditing, project management knowledge, as well as national construction laws and regulations, and have strong review capabilities;\nUnderstanding of theoretical basis for concrete box reinforcement design, mold structure and use, component pouring and maintenance\nAt least 5 years of operational management experience in the construction component industry, with Hong Kong project experience is required.\nStrong strategic thinking skills, good business awareness, outstanding leadership skills (analysis, judgment, decision-making, and problem-solving skills), as well as strong communication, government public relations and business negotiation skills;\nWith Sales & marketing experience in this industry, rich network resources, relevant customer resources, and strong business development capabilities are preferred.", "employment_types": ["Full Time", "Permanent"], "selling_points": ["Responsible for MiC concrete project and planning", "Handle whole concrete company operation", "Based in ZhaoQing with concrete experience"], "locations": ["Others - China"], "categories": ["Building & Construction", "Building / Construction / QS", "Engineering", "Manufacturing & Production", "Manufacturing", "Manufacturing Management"], "post_time": "2022-01-06T05:05:29Z", "salary": {"currency": "HKD", "max": 119999, "min": 55000, "period": "monthly", "term": null}, "salary_visible": true, "title_keywords": ["general manager"], "responsibilities": ["cost", "management", "analysis", "quality", "design", "p&l", "develop", "project management", "planning", "plan", "cost control", "costs", "report"], "requirements": {"degrees": ["degree or above", "bachelor"], "majors": ["architecture", "civil engineering"], "languages": [], "language_level": [], "hard_skills": ["maintenance", "cad", "analysis", "project management", "problem-solving skills", "office software"], "soft_skills": ["strategic thinking", "leadership skills", "communication", "project management", "negotiation skills", "problem-solving skills"], "languages_combined": []}, "experience_required": {"duration": ["at least 5 years"], "field": ["management", "marketing", "construction", "business development"]}}, {"job_id": "100003009036645", "location_code": "hk", "company": "Links International", "job_title": "Hardgoods Merchandiser - Product Developer", "description": "Hardgoods Merchandiser - Product Development\n\nOur client is an international supplies retailer, focusing on pet products including food, toys, bedding, etc. They are looking for a Merchandiser to join their organization, responsible for sourcing, product development, and price negotiation process.\n\nJob Description\n\nDevelop and monitor sourcing strategies and procedures, ensure the vendors is fulfilling the sourcing plans\nSource potential suppliers within Asia to support the company's sourcing plans\nCollaborate with different teams to enhance brand identity and product features, keep track of projects' critical paths\nWork closely with UK Headquarter on category & supplier strategies\nUnderstand the product trends and market insight, develop competitive product ranges\nNegotiate and improve price competitiveness, deliver margin gains, improve payment terms and shipment date\nFollow up sourcing processes and help maintain sourcing systems\nTravel to factories /suppliers for buying trips & new product development\nManage any ad hoc projects, frequent travel to PRC\n\nRequirements\n\nDegree holder or above in the relevant discipline\nExperience of working in a sourcing/buying office is preferable\n2 - 5 years solid experience in developing or sourcing toys, textile or bedding products\nStrong negotiation and presentation skills, attention to details\nGood command of both spoken and written English, Cantonese & Mandarin\nWilling to travel to PRC\n", "employment_types": ["Full Time", "Permanent"], "selling_points": ["Toys, textile / bedding sourcing exp", "Sourcing office exp is preferable", "15days AL + 1 day birthday leave"], "locations": ["Kwun Tong Area"], "categories": ["Manufacturing", "Manufacturing Management", "Product Development / Management", "Merchandising & Purchasing", "Sundries"], "post_time": "2022-01-10T11:38:18Z", "salary": {"currency": "HKD", "max": 24999, "min": 20000, "period": "monthly", "term": null}, "salary_visible": true, "title_keywords": ["merchandiser", "product developer"], "responsibilities": ["collaborate with", "systems", "monitor", "procedures", "teams", "develop", "payment", "maintain", "ad hoc projects", "plans"], "requirements": {"degrees": ["degree holder"], "majors": [], "languages": ["cantonese", "english", "mandarin"], "language_level": ["good command"], "hard_skills": [], "soft_skills": ["presentation skills", "negotiation", "attention to details"], "languages_combined": [{"language": "cantonese", "language_level": ["good command"]}, {"language": "english", "language_level": ["good command"]}, {"language": "mandarin", "language_level": ["good command"]}]}, "experience_required": {"duration": ["2 - 5 years"], "field": ["toys", "developing", "textile"]}}, {"job_id": "100003009037805", "location_code": "hk", "company": "OKIA Optical Co Ltd", "job_title": "System Administrator", "description": "Responsibilities\n\nProvide first level technical support to office users in a timely manner;\nPerform troubleshooting and quality tape management;\nSupport daily IT operations, e.g. system maintenance including MS Windows servers, Active Directory, MS Exchange, firewall, router and network monitoring, etc.\nMaintenance of all hardware and software inventory control\nProvide helpdesk support, technical services and daily routine task and system operation;\nHandle/analyst in-house system and/or program;\nLiaise with external providers of hardware and software to resolves IT issues\nCarry out other ad-hoc assignments\nRequirement\n\nDiploma or above in Information Technology related discipline or equivalent experience\n3 years' experience in providing helpdesk / IT support / back office operations\nStrong sense of analytical and problem solving skills;\nThe ability to work independently, coordinate others to accomplish overall corporate goals and deal with business users at all levels;\nExcellent Communication and interpersonal skills;\nPositive thinking, hardworking, responsible, Independent, attentive to details, initiative, with good communication, strong problem-solving, analytical and interpersonal skills\nAbility to multi-task and work in a fast paced environment to meet daily goals and willing to work overtime and outdoor work occasionally\nImmediate available is an advantage\nInterested parties please go to www.okia.com for more details, and send full resume, current and expected salary to us.\n", "employment_types": ["Full Time"], "selling_points": ["Good knowledge in Hardware /Software", "Have a can-do & willing to learn attitude", "Good working environment"], "locations": ["Lai Chi Kok"], "categories": ["Manufacturing", "Manufacturing Management"], "post_time": "2022-01-11T03:55:02Z", "salary": {"currency": null, "max": null, "min": null, "period": "monthly", "term": null}, "salary_visible": false, "title_keywords": ["system administrator"], "responsibilities": ["management", "software", "maintenance", "active directory", "technical support", "operations", "ad-hoc assignments", "monitoring", "quality", "a timely manner", "troubleshooting", "hardware", "inventory control", "liaise with"], "requirements": {"degrees": ["diploma or above"], "majors": ["information technology"], "languages": [], "language_level": [], "hard_skills": ["problem-solving", "problem solving skills"], "soft_skills": ["work independently", "work overtime", "independent", "multi-task", "responsible", "attentive to details", "problem-solving", "positive thinking", "communication", "analytical and problem solving skills", "communication and interpersonal skills", "interpersonal skills", "work in a fast paced environment", "initiative", "hardworking"], "languages_combined": []}, "experience_required": {"duration": ["3 years"], "field": ["related", "it support", "information technology"]}}, {"job_id": "100003009037050", "location_code": "hk", "company": "Caf\u00e9 de Coral Group Limited", "job_title": "Registered Safety Officer (Managerial Level)", "description": "Responsibilities:\n\nMonitor, review and implement the Company\u2019s Safety Management System including safety policy, operational & work procedures, safety & health training promotion and so on in order to comply with relevant statutory, standards and contractor requirements and also industrial best practices.\nConduct regular safety inspection, risk assessment, incident investigation and job hazard analysis.\u00a0 Follow up with preventive measures and corrective plans.\nDesign and implement the Environmental, Health and Safety (EHS) Management System and provide training (e.g. Tool-box-Trainings, briefings and classroom training) for staff and contractors\nCoordinate with internal & external parties for EHS compliance activities, including but not limited to regular safety patrol and audit programs to ensure plant\u2019s safety;\nOrganize and participate in various Safety Management Committee Meetings on regular basis\nPrepare regular EHS reports for management review\nRequirements:\n\nDiploma or above in Health and Safety and/or Occupational Safety and Health related disciplines.\nHong Kong Registered Safety Officer is a must with minimum 5 years\u2019 relevant experience in the manufacturing field, with experience in ISO45001, ISO14001, ISO9001 audit and a qualified first-aider preferred\nBe familiar with the regulatory safety requirements and standards.\nA determined and self-motivated team player with strong analytical, communication and problem-solving skills\nNon-managerial grade position will be considered for candidate with less experience.\n\nInterested parties please send full resume with\u00a0PRESENT & EXPECTED SALARY\u00a0to Human Resources Department by clicking\u00a0\"Apply Now\".\n\nWe are an EQUAL OPPORTUNITIES EMPLOYER.\nAll information received will be kept in strict confidence and be used for employment-related purpose only.", "employment_types": ["Full Time", "Permanent"], "selling_points": ["Conduct regular safety inspection", "Prepare regular EHS reports", "Diploma or above in Health and Safety"], "locations": ["Tai Po Area"], "categories": ["Manufacturing", "Manufacturing Management"], "post_time": "2022-01-11T01:33:01Z", "salary": {"currency": null, "max": null, "min": null, "period": "monthly", "term": null}, "salary_visible": false, "title_keywords": ["safety officer"], "responsibilities": ["provide training", "management", "analysis", "review", "monitor", "procedures", "investigation", "inspection", "design", "coordinate with", "external parties", "compliance", "audit", "reports", "plans", "management review"], "requirements": {"degrees": ["diploma or above"], "majors": ["related disciplines"], "languages": [], "language_level": [], "hard_skills": ["problem-solving skills"], "soft_skills": ["self-motivated", "determined", "communication", "problem-solving skills", "team player"], "languages_combined": []}, "experience_required": {"duration": ["minimum 5 years"], "field": ["managerial", "manufacturing", "relevant experience", "audit"]}}, {"job_id": "100003009031496", "location_code": "hk", "company": "Links International", "job_title": "Associate Sourcing Manager - Production focus", "description": "Associate Sourcing Manager - Apparel\n\nOur client is a large international fashion retailer, looking for a Associate Sourcing Manager join their organisation.\n\nJob Description:\n\n\nIdentify and source vendors, taking into account of cost, quality, delivery and capacity.\nMaintain vendor relationships to execute regional sourcing strategies\nManage KPI and Vendor Action Plans to obtain Vendor Scorecard results above targets set by Strategic Sourcing\nPlan orders and capacity management with vendors based on the seasonal forecasts and business needs.\nAnalyze over/ under capacity adoption, assist & support the senior management in delivering, leading & quality requirement.\nWork with key business stakeholders to ensure and maintain agreed dates and timeline.\nAssess and evaluate the overall capabilities and performance of all vendors ( including development, bulk execution, quality and CSR rating ), and make recommendation to management.\nSupport price negotiation processes and provide best market intelligence to deliver the cost optimization.\nPartner with technical and product development team to improve vendors' product capabilities and lead time reduction.\nManage liability in respect to verify liability amount and cross check if it is eligible to achieve the goal of liability control.\n\nRequirements:\n\n\nDegree caliber - ideally a degree gained from Manufacturing, Textiles, Apparel Merchandising or Business Administration\nMinimum 8 years working experience in product development and sourcing. Product knowledge of lifestyle/functional, sports and printing techniques is preferrable.\nSolid experience in global sourcing environment, product development/ production and sourcing bases in China and Far East Asia.\nExperience in working with USA and China Market is an advantage.\nExcellent project management, communication, time management and interpersonal skills.\nStrong analytical, creative problem solving and decision-making skills.\nGood knowledge in MS office, skillful of MS Excel (Vlookup), PowerPoint are essential.\nExcellent command of written and spoken English, Cantonese, and Mandarin.\nWilling to travel.", "employment_types": ["Full Time", "Permanent"], "selling_points": ["Degree in Merchandising, Fashion or related", "8 years of sourcing experience(US market)", "International working environment"], "locations": ["Not Specified"], "categories": ["Manufacturing", "Garment / Textile", "Manufacturing Management", "Merchandising & Purchasing", "Procurement / Purchasing / Sourcing"], "post_time": "2022-01-07T09:22:46Z", "salary": {"currency": null, "max": null, "min": null, "period": "monthly", "term": null}, "salary_visible": false, "title_keywords": ["associate sourcing manager"], "responsibilities": ["cost", "management", "make recommendation", "price negotiation", "cost optimization", "control", "quality", "evaluate", "maintain", "plan", "plans", "senior management"], "requirements": {"degrees": ["degree"], "majors": ["manufacturing", "business administration"], "languages": ["cantonese", "english", "mandarin"], "language_level": ["excellent"], "hard_skills": ["powerpoint", "problem solving", "project management", "ms excel", "vlookup", "ms office"], "soft_skills": ["creative", "communication", "project management", "problem solving", "interpersonal skills", "time management"], "languages_combined": [{"language": "cantonese", "language_level": ["excellent"]}, {"language": "english", "language_level": ["excellent"]}, {"language": "mandarin", "language_level": ["excellent"]}]}, "experience_required": {"duration": ["minimum 8 years"], "field": ["product development"]}}, {"job_id": "100003009033157", "location_code": "hk", "company": "Lynns Limited", "job_title": "Product Development Manager", "description": "Responsibilities:\n\nIdentify and develop new products based on customers\u2019 perspective, products research and data analysis.\nLead the product team from the product development, order execution to shipment.\nCollaborate closely with internal parties to ensure the procurement of new potential products, the availability of products and the quality standard of content creation for global strategy.\nCollaborate with external suppliers, ensure business and creativity accurately reflected in our products.\nEvaluate and optimize the vendor base. Measure supplier performance and capacity in order to make the right sourcing decisions.\nOverall manage and follow up on responsible projects, make sure new product development and upgrading meet timely deliveries, with quality and cost effectiveness.\nEngage with customers to understand strategies and objectives.\nPerform and handle other ad hoc projects as assigned.\n\nRequirements:\n\nBachelor with a major in product designs / development / engineering / business preferred\nWork experience in product companies, especially in consumer products, preferably in product design / development / engineering\nKnowledge of photo software, 3D software, engineering management\nProficient in MS Office Suite, strong Excel skills\nExcellent interpersonal skills, communication as with global offices\nExcellent in written and spoken English, Mandarin and Cantonese\nIndependent work, decision making and comfortable with remote work\nImmediate availability or short notice will be an advantage", "employment_types": ["Full Time"], "selling_points": [], "locations": ["Wan Chai"], "categories": ["Manufacturing", "Manufacturing Management", "Product Development / Management", "Merchandising & Purchasing", "Procurement / Purchasing / Sourcing"], "post_time": "2022-01-08T11:30:50Z", "salary": {"currency": null, "max": null, "min": null, "period": "monthly", "term": null}, "salary_visible": false, "title_keywords": ["product development manager"], "responsibilities": ["collaborate", "collaborate with", "cost", "quality", "develop", "data analysis", "evaluate", "ad hoc projects", "products research", "internal parties"], "requirements": {"degrees": ["bachelor"], "majors": ["business", "engineering"], "languages": ["cantonese", "english", "mandarin"], "language_level": ["excellent"], "hard_skills": ["3d software", "excel", "ms office"], "soft_skills": ["communication", "independent", "interpersonal skills", "decision making"], "languages_combined": [{"language": "cantonese", "language_level": ["excellent"]}, {"language": "english", "language_level": ["excellent"]}, {"language": "mandarin", "language_level": ["excellent"]}]}, "experience_required": {"duration": [], "field": ["development", "product design", "engineering"]}}, {"job_id": "100003009025574", "location_code": "hk", "company": "Yong Feng Hardware Factory Limited", "job_title": "Factory Manger (Stationed in Huizhou China.)", "description": "At least 8 years of experience in Manufacturing.\n\n\u00a0Higher Diploma holder or above in Manufacturing/Mechanical Engineering are preferred.\n\n\u00a0Experience in Machining, Stamping, bolts & Nuts productions.\n\n\u00a0Strong leadership skills, Flexible and team-player.\n\n\u00a0Fluent in English, Cantonese and Mandarin Chinese.\n\nJob Duties:\n\n-Responsible for factory operation, such as quality control, customer satisfaction, production safety protocol, Engineering R&D, Manufacturing process and scheduling, purchasing and outsourcing, etc.\n\n\u00a0-Monitoring all the productions, ensure it follows certain protocol, quality standard/requirements must be met, procedures have to be tracible and transparent.\n\n\u00a0-Flexibility and adaptability in decisions making, providing alternatives and corrective actions.\n\n\u00a0-Keeping factory in order and disciplined, from Human resources to daily production, maximising the productivity and in the meantime, controlling the efficiency and scrap rates.\n\n\u00a0-Short business trip to Vietnam manufacturing plant is required.\n\n\u00a0-Stationed in Huizhou, China.\n\nOffers & Benefits:\n\n\u00a0-En-suite accommodation and meals provided\n\n\u00a0-Travel Allowances\n\n\u00a0-Insurance", "employment_types": ["Full Time"], "selling_points": [], "locations": ["Others - China"], "categories": ["Manufacturing", "Manufacturing Management"], "post_time": "2022-01-06T05:24:03Z", "salary": {"currency": "HKD", "max": 44999, "min": 30000, "period": "monthly", "term": null}, "salary_visible": true, "title_keywords": [], "responsibilities": ["quality", "procedures", "scheduling", "business trip", "quality control"], "requirements": {"degrees": ["higher diploma holder"], "majors": ["manufacturing", "mechanical engineering"], "languages": ["cantonese", "english", "mandarin chinese"], "language_level": ["fluent"], "hard_skills": ["r&d"], "soft_skills": ["flexible", "team-player", "leadership skills", "adaptability"], "languages_combined": [{"language": "cantonese", "language_level": ["fluent"]}, {"language": "english", "language_level": ["fluent"]}, {"language": "mandarin chinese", "language_level": ["fluent"]}]}, "experience_required": {"duration": ["at least 8 years"], "field": ["manufacturing"]}}, {"job_id": "100003009023651", "location_code": "hk", "company": "GrammyTech Ltd", "job_title": "Senior Quality Manager/ Quality Manager IATF 16949 / Senior Production Manager (China Based)", "description": "A Hong Kong listed company with diversified business in industrial products is looking for Senior Quality Manager (IATF 16949) & Senior Production Manager to be based in Guangdong Province\n\n\u00a0Senior Quality Manager (China Based)\n\n\u00a0Key Responsibilities:\n\nEnsure operations compliance to IATF16969 regulation standards\nLead advanced product quality planning (APQP) discipline\nDrive shop floor quality assurance planning and quality control\nDrive effective problem solving and a continuous improvement mindset culture\nDrive quality systematic KPI continuous improvement\n\nRequirements:\n\nEngineering Bachelor\u2019s degree, with 15 years or above relevant experience\nSkilled in advanced product quality planning (APQP) and quality tools; PPAP, SPC, MSA, FMEA\nExperienced in problem solving and continuous improvement tools; 8D, 5-Why,\u00a0Taguchi\u00a0DOE methods\nStrong practical experience, knowledge of relevant manufacturing systems and process technologies\nGood interpersonal communication skills\nFluency in English preferred\nCandidate with less experience will be considered a Quality Manager\nBased in China\n\nSenior Production Manager \u2013 Motor Manufacturing (China Based)\n\nResponsibilities:\n\nTake lead of Assembly Business Unit automation implementation and headcount reduction of the manufacturing plants\nInvolve new project smoothly launch on time and on quality\nAll W3 of each lines can be monitor and close on time\nNew line SOP preparation\nPrepare for customer audit\nWork with team to reduce production line hot issue\nTo follow up Jiangmen coming Automation line smoothly launching\nRoll out ASA and Automation strategy from top management and meet HC saving target\nAudit experience for 3rd Party\nPM team skill upgrade\nIATF system work flow\nMES system implementation and execution\nRequirements:\nDegree or above in Engineering or related disciplines with 15 years or above production management experience, at least 5 years motor assembly production management\nKnowledge and experience in DC motor, Gear motor.\nGood knowledge in IATF 16949 and\u00a0 PMPs system\nCapable of people management and coordinate capability\nGood communication skills and ownership\nStrong leadership skill and ability to drive team achieve different assignment.\nPrior experience in relocation project is preferred\nFluency in both oral and written English skills\n\nInterested parties please forward your CV in Word Format to anthonyko @grammytech.com", "employment_types": ["Full Time", "Permanent"], "selling_points": ["Automotive Products", "Industrial Products", "Medical Products"], "locations": ["Others - China"], "categories": ["Engineering", "Manufacturing & Production", "Manufacturing", "Manufacturing Management", "Quality Assurance, Control & Testing / ISO"], "post_time": "2022-01-05T09:22:33Z", "salary": {"currency": null, "max": null, "min": null, "period": "monthly", "term": null}, "salary_visible": false, "title_keywords": ["quality manager", "senior production manager"], "responsibilities": ["operations", "compliance", "quality", "quality control", "planning"], "requirements": {"degrees": ["degree or above", "degree", "bachelor"], "majors": ["related disciplines", "engineering"], "languages": ["english"], "language_level": ["fluency"], "hard_skills": ["problem solving", "dc", "system implementation"], "soft_skills": ["communication skills", "oral", "capable", "advanced", "problem solving", "leadership skill", "interpersonal"], "languages_combined": [{"language": "english", "language_level": ["fluency", "fluency"]}]}, "experience_required": {"duration": ["at least 5 years", "15 years"], "field": ["management", "manufacturing", "engineering", "related", "relevant experience", "audit experience"]}}, {"job_id": "100003009041398", "location_code": "hk", "company": "Find Asia Limited", "job_title": "Procurement Officer (Japanese Electronics)", "description": "Our client, a Japanese electronics components manufacturing co. is looking for the candidate with the following details\u00a0\n\nDuties\n\nHandle order processing\nClosely liaise with assigned suppliers and manufacturers for ordering and processing handling\u00a0\nAssist in sourcing, negotiation, procurement and ensure the delivery on schedule\u00a0\nSupervise a team for management reporting preparation\u00a0\nHandle projects, workflow enhancement\u00a0\n\nRequirement\u00a0\n\nUniversity graduate\nGood English and Mandarin\nWith solid experience in procurement, order processing in electronics field\u00a0\nProficient in MS Office\u00a0\nIndependent, good analytical and problem solving skills\u00a0\nGood Interpersonal and communication skills\u00a0", "employment_types": ["Full Time", "Permanent"], "selling_points": ["Purchasing, Procurement", "Japanese Electronics, Officer/ Supervisor", "5 days, Double Pay, Bonus"], "locations": ["Yau Tsim Mong Area"], "categories": ["Transportation & Logistics", "Supply Chain", "Manufacturing", "Manufacturing Management", "Merchandising & Purchasing", "Electronics"], "post_time": "2022-01-12T03:50:18Z", "salary": {"currency": null, "max": null, "min": null, "period": "monthly", "term": null}, "salary_visible": false, "title_keywords": ["procurement officer"], "responsibilities": ["liaise with", "management reporting", "schedule", "order processing"], "requirements": {"degrees": ["university graduate"], "majors": [], "languages": ["english", "mandarin"], "language_level": ["good"], "hard_skills": ["problem solving skills", "order processing", "ms office"], "soft_skills": ["communication skills", "analytical and problem solving skills", "independent", "interpersonal"], "languages_combined": [{"language": "english", "language_level": ["good"]}, {"language": "mandarin", "language_level": ["good"]}]}, "experience_required": {"duration": [], "field": ["procurement", "order processing"]}}, {"job_id": "100003009026491", "location_code": "hk", "company": "Marching Pharmaceutical Limited", "job_title": "Assistant Production Officer (Pharmaceutical)", "description": "Key Responsibilities:\n\nPreparing documents (e.g. MBPR & SOPs) and reports;\nOrganize production schedule to ensure smooth and efficient production operations;\nSupervise and monitor day-to-day running of the production operation;\nCoordinate with other departments on production schedule and validation arrangement;\nPerform routine check in the Production Department to ensure GMP implementation and compliance;\nProvide technical support and trouble shooting.\n\nRequirements:\n\nHigher Diploma or above\u00a0in\u00a0Pharmaceutical Sciences\u00a0or any related Sciences Studies;\nGood command of both spoken and written English and Chinese.\nProficient in MS Office application (Excel, Word & PowerPoint) and Chinese Word Processing;\nRecent graduates will be considered;\nImmediate available is highly preferable;\nFresh graduates are welcomed.\n\n\u00a0How to Apply\n\nYou are invited\u00a0to\u00a0send in your application and CV stating the position\u00a0(with reference number)\u00a0you are applying for together with your current and expected salary, either by \"Apply Now\"\u00a0or mail to Rm 5-6, 9/F, Block B, Vigor Industrial Building, 14-20 Cheung Tat Road, Tsing Yi\u00a0on or before 31\u00a0May\u00a02021.\n\nMarching Pharmaceutical Limited is an\u00a0Equal Opportunities Employer. Personal data provided by job applicants will be used strictly in accordance with our personal data policy and for recruitment purposes only. We aim to respond to successful applicants within 8 weeks and related information will be kept in our file for up to 12 months for other suitable vacancies in our organization and thereafter destroyed.", "employment_types": ["Full Time", "Permanent"], "selling_points": [], "locations": ["Tsing Yi"], "categories": ["Manufacturing", "Manufacturing Management", "Product Development / Management", "Production Planning / Control"], "post_time": "2022-01-06T08:13:46Z", "salary": {"currency": null, "max": null, "min": null, "period": null, "term": null}, "salary_visible": false, "title_keywords": ["assistant production officer"], "responsibilities": ["technical support", "operations", "compliance", "monitor", "coordinate with", "implementation", "reports", "schedule", "sops"], "requirements": {"degrees": ["higher diploma or above"], "majors": [], "languages": ["english", "chinese"], "language_level": ["good command", "proficient"], "hard_skills": ["excel", "chinese word processing", "word", "powerpoint", "ms office"], "soft_skills": [], "languages_combined": [{"language": "english", "language_level": ["good command"]}, {"language": "chinese", "language_level": ["proficient", "good command"]}]}, "experience_required": {"duration": [], "field": []}}, {"job_id": "100003009024949", "location_code": "hk", "company": "Lidl Hong Kong Limited", "job_title": "Senior Production Support Engineer (E&E)", "description": "Summary\n\nLidl are hiring a Senior Production Support Engineer in the Production Support (E&E) team. The successful candidate will be responsible for ensuring that production is cost effective, quality controlled and on time.\n\nWhat will you do?\nEnsures all production occurs in line with Lidl\u2019s strict Ethical Sourcing Policies\nEnsure TnA\u2019s for each IAN confirmed in each Selection is accurate and correct\nReceive, upload, and review weekly production schedules from suppliers\nLiaise with Quality Control Officers and suppliers on capacity planning / schedules\nProvide weekly in production traffic light reporting to Merchandise Managers and General Managers\nNotify key stakeholders of any major or critical production and quality issues identified\u00a0\nWorks closely with Quality Assurance team to resolve any critical or major issues found during production\nSupport or conduct Pre-Production meetings in factory when required\nProvide manufacturing technical support and procedure to reduce manufacturing costs and / or improve quality levels and production efficiency when identified\u00a0\nReviews IVA data provided by QC Officers and ensures IVA form is accurate and correct\nPerform unannounced audits and inspections when requested\nPerform Lidl factory evaluations, implement, and control CAPs\nWhat will you need?\nDiploma or degree in electrical or mechanical engineering or at least 5 years\u2019 experience in a Quality Assurance / Quality Control role in electrical product category\nPossess strong leadership and managerial skills with sound problem solving techniques\nAutonomous, proactive, detailed and commercially minded\nGood command of both spoken and written English and fluent in Mandarin\nStrong knowledge of Microsoft applications especially Excel & Word\nTravel is required\nWhat do we offer?\n\nWe are dedicated to fostering a family-friendly culture and work environment. We are an equal opportunities employer and welcome applications from all candidates with the required skills and experience.\n\n\u00a0\nMarket Leading Remuneration Package:\n\nDouble pay and discretionary bonus\nChoice of MPF provider\nLife Insurance\nMedical Insurance\n\u00a0\n\nSupportive Environment:\n\nRental re-imbursement scheme\nFlexible work arrangements\nIn-house training courses\nTraining sponsorship scheme\nHealth Check\nVision Check\nSupporting your child\u2019s education with advice from a leading education consultant\n\u00a0\n\nWork-Life Balance:\n\n5 day week\nCompetitive Annual Leave\nCharity, Community and Sporting Events", "employment_types": ["Permanent"], "selling_points": ["Must have electrical product exp.", "Flexible work arrangements", "Office located in ICC"], "locations": ["Others"], "categories": ["Manufacturing", "Manufacturing Management", "Production Planning / Control", "Quality Assurance, Control & Testing / ISO"], "post_time": "2022-01-06T02:58:28Z", "salary": {"currency": null, "max": null, "min": null, "period": "monthly", "term": null}, "salary_visible": false, "title_keywords": ["senior production support engineer"], "responsibilities": ["reporting", "cost", "control", "data", "schedules", "policies", "technical support", "review", "quality", "audits", "quality control", "liaise with", "pre-production", "costs", "planning"], "requirements": {"degrees": ["diploma", "degree"], "majors": ["mechanical engineering"], "languages": ["english", "mandarin"], "language_level": ["good command", "fluent"], "hard_skills": ["problem solving", "excel", "word", "microsoft applications"], "soft_skills": ["proactive", "responsible", "problem solving", "autonomous", "ethical", "controlled", "accurate", "leadership", "detailed"], "languages_combined": [{"language": "english", "language_level": ["fluent", "good command"]}, {"language": "mandarin", "language_level": ["good command"]}]}, "experience_required": {"duration": ["at least 5 years"], "field": ["engineering", "quality control", "quality assurance"]}}, {"job_id": "100003009024950", "location_code": "hk", "company": "Lidl Asia Pte. Limited (Hong Kong Branch)", "job_title": "Senior Production Support Engineer - Household", "description": "Summary\n\nLidl Asia are looking for a Senior Production Support Engineer in our Household team to drive the most cost effective, quality controlled, and on-time production through key building blocks, such as kick-off meetings, pre-production meetings, production schedule, CAPs, and Quality Control inspection program.\n\nWhat will you do?\n\nEnsure all production occurs in line with Lidl HK SOP and Lidl\u2019s strict Ethical Sourcing Policies\n\nTakes control and leads all pre-production meetings in factory as determined by the \u2018kick-off\u2019 meeting at Lidl HQ\n\nProvide manufacturing technical support and procedure to reduce manufacturing costs and / or improve quality levels and production efficiency when identified\n\nNotify key stakeholders of any major or critical production and quality issues identified whilst in factory. Follow up and close off outstanding CAPs with the supplier in question.\n\nDrive compressed production impacts training with any impacting product category\n\nPerform Lidl factory evaluations, implement and control CAPs\n\nMonitor the efficiency of the Lidl China QC team\n\nMonitor the efficiency of the Lidl agency for offshore countries\n\nTravel is required\n\nWhat will you need?\n\nDiploma or degree in electrical or mechanical engineering and at least 5 years\u2019 experience in QA/QC within the Household product category\n\nAutonomous, proactive, detailed and commercially minded\n\nGood command of both spoken and written English and fluent in Mandarin\n\nBasic knowledge of Microsoft applications Word & Excel & Lotus Notes\n\nA can-do attitude with entrepreneurial spirit is a must\n\nWhat do we offer?\n\nWe are dedicated to fostering a family-friendly culture and work environment and we are an equal opportunities employer and welcome applications from all candidates with the required skills and experience.\n\n\u00a0\nMarket Leading Remuneration Package:\n\nDouble pay and discretionary bonus\nChoice of MPF provider\nLife Insurance\nMedical Insurance\n\u00a0\n\nSupportive Environment:\n\nRental re-imbursement scheme\nFlexible work arrangements\nIn-house training courses\nTraining sponsorship scheme\nHealth Check\nVision Check\nSupporting your child\u2019s education with advice from a leading education consultant\n\u00a0\n\nWork-Life Balance:\n\n5 day week\nCompetitive Annual Leave\nCharity, Community and Sporting Events\n\nWe are dedicated to fostering a family-friendly culture and work environment and we are an equal opportunities employer and welcome applications from all candidates with the required skills and experience.\n\n\u00a0\nMarket Leading Remuneration Package:\n\nDouble pay and discretionary bonus\nChoice of MPF provider\nLife Insurance\nMedical Insurance\n\u00a0\n\nSupportive Environment:\n\nRental re-imbursement scheme\nFlexible work arrangements\nIn-house training courses\nTraining sponsorship scheme\nHealth Check\nVision Check\nSupporting your child\u2019s education with advice from a leading education consultant\n\u00a0\n\nWork-Life Balance:\n\n5 day week\nCompetitive Annual Leave\nCharity, Community and Sporting Events", "employment_types": ["Full Time"], "selling_points": ["Experience with Household products (bathroom & kitchen)", "Office located in ICC building", "Know production processes"], "locations": ["Tsim Sha Tsui"], "categories": ["Manufacturing", "Manufacturing Management", "Production Planning / Control", "Quality Assurance, Control & Testing / ISO"], "post_time": "2022-01-06T02:58:34Z", "salary": {"currency": null, "max": null, "min": null, "period": "monthly", "term": null}, "salary_visible": false, "title_keywords": ["senior production support engineer"], "responsibilities": ["cost", "control", "technical support", "policies", "quality", "monitor", "inspection", "schedule", "quality control", "pre-production", "costs"], "requirements": {"degrees": ["diploma", "degree"], "majors": ["mechanical engineering"], "languages": ["english", "mandarin"], "language_level": ["good command", "fluent"], "hard_skills": ["excel", "basic", "word", "microsoft applications"], "soft_skills": ["determined", "can-do attitude", "autonomous", "ethical", "controlled", "proactive", "detailed"], "languages_combined": [{"language": "english", "language_level": ["fluent", "good command"]}, {"language": "mandarin", "language_level": ["good command"]}]}, "experience_required": {"duration": ["at least 5 years"], "field": ["engineering", "qa"]}}, {"job_id": "100003009032914", "location_code": "hk", "company": "Best Fine International Enterprise Limited", "job_title": "QA Manager (Station in Cambodia)", "description": "Responsibilities:\n\nDevelop the quality standards,\u00a0policies\u00a0and quality management systems\nManage\u00a0in-house, subcontracting factories, suppliers\u2019 quality standards; conduct audits and performance evaluations\nProvide quality related technical advices and strengthen the supports to merchandising, production and technical related departments in factories\u00a0\u00a0 \u00a0Manage the WIP reports and QA/QC documentation\nCoordinate with all related departments and customers to\u00a0problem-solve the quality issues, build corrective and preventive measures\nSupervise the QA team very closely\nRequirements:\n\nTertiary education or above in Apparel/ Clothing/ Textiles\n5 years or above solid quality management experience in garment manufacturing\nFamilar of printing, embroidery & paper patterns\u00a0\u00a0 \u00a0\u00a0\u00a0 \u00a0\nSound practical skills in building up quality standards and systems, and using QM tools\nProficient verbal and written English and Mandarin\nGood interpersonal communication skills, problem-solving, detailed mind, hands-on approach\nGood PC skills in MS Office and Chinese Word Processing\nWe offer attractive remuneration package to the right candidate.\nPlease send full resume and expected salary via e mail by clicking \"Apply Now\"", "employment_types": ["Full Time", "Permanent"], "selling_points": [], "locations": ["Overseas"], "categories": ["Manufacturing", "Garment / Textile", "Manufacturing Management", "Quality Assurance, Control & Testing / ISO"], "post_time": "2022-01-08T02:52:39Z", "salary": {"currency": null, "max": null, "min": null, "period": "monthly", "term": null}, "salary_visible": false, "title_keywords": ["manager"], "responsibilities": ["management", "policies", "systems", "quality", "conduct audits", "merchandising", "develop", "coordinate with", "reports", "documentation"], "requirements": {"degrees": [], "majors": [], "languages": ["english", "chinese", "mandarin"], "language_level": ["good", "proficient"], "hard_skills": ["problem-solving", "pc skills", "chinese word processing", "ms office"], "soft_skills": ["communication skills", "problem-solving", "hands-on", "detailed mind", "interpersonal"], "languages_combined": [{"language": "english", "language_level": ["proficient"]}, {"language": "chinese", "language_level": ["good"]}, {"language": "mandarin", "language_level": ["proficient"]}]}, "experience_required": {"duration": ["5 years"], "field": ["garment", "manufacturing", "quality management"]}}, {"job_id": "100003009036355", "location_code": "hk", "company": "Eternity Consultants (HK) Ltd", "job_title": "Assistant Social Compliance Executive / Senior Compliance Executive - BSCI / SA8000 (Fresh graduate)", "description": "Benefits: Bonus,\u00a09:00am- 6:00pm, 5-day,\u00a0medical, dental\u2026\n\nEmployment:\u00a0\u00a0permanent job\u00a0\n\n\nResponsibilities:\n\nAdminister audit schedule and pre-audit coordination with suppliers\nConduct Code of Conduct Audits in China and Asian countries\nSubmit audit report in timely and quality manner\nPrepare regular updates to management\nManage in-house factory database\nProvide clerical and administrative support to the team\nAssist internal and external social compliance\n\nPerform ad hoc visits & projects\nTravel to China\n\nRequirements:\n\nAt least 1-3 years social compliance and audit experience for factories producing diversified merchandises in China and Asian countries\nDegree holder in Social Science or Accounting preferred\nHigh degree of work ethics and integrity is a must\nSA8000 Lead Auditor and background with animal welfare practices are absolute advantages\nKnowledgeable in local labor, health and safety and environmental laws as well as CSR standards such as EICC & SA8000\n\nExperience in developing and monitoring Corrective Actions Plan (CAP) with suppliers will be a definite advantage\nExperience in suppliers\u2019 training and coaching is highly preferred\nKnowledge of\u00a0conflict mineral control\u00a0\n\nFor more jobs, please visit our website:\u00a0www.hketernity.com\n\n\u00a0(Personal data submitted are for recruitment purpose only.)", "employment_types": ["Full Time"], "selling_points": ["5 days, 13 months, bank, medical, 12 AL", "1-3 years in social compliance in trading", "buying office, factory audit, conflict mineral"], "locations": ["Not Specified"], "categories": ["Engineering", "Manufacturing & Production", "Manufacturing", "Manufacturing Management", "Quality Assurance, Control & Testing / ISO"], "post_time": "2022-01-10T10:08:22Z", "salary": {"currency": null, "max": null, "min": null, "period": "monthly", "term": null}, "salary_visible": false, "title_keywords": ["executive", "assistant"], "responsibilities": [], "requirements": {"degrees": [], "majors": [], "languages": [], "language_level": [], "hard_skills": [], "soft_skills": [], "languages_combined": []}, "experience_required": {"duration": [], "field": []}}, {"job_id": "100003009019376", "location_code": "hk", "company": "Headsearch21 Consultancy Ltd", "job_title": "Operations Manager (5 days / Manufacturing / 60-70K)", "description": "To cope with the expansion of the Company, our client is now looking for high caliber candidates to join the Operations Team in China:\n\nResponsibilities:\n\nMonitor the daily operations of the China Plant\nLead the Manufacturing/Engineering/Production/Quality/Procurement/Material Control Team Teams in China\nHandle resources strategic planning and cost controlling in order to achieve organizational goal\nFormulation and implementation of continuous improvement programs\nMake continuously improvement to ensure all manufacturing operations can run so smoothly and efficiency\nProvide technical advice and trouble-shooting\n\nRequirements:\n\nAt least 8 years relevant experience in Manufacturing\nFamiliar with Metal Stamping is a MUST\nDiploma in Manufacturing Management, Industrial Engineering or related disciplines\nFamiliar with manufacturing operations, ISO documentation and safety standard\nProficiency in MS Office, ERP / SAP system and Chinese Word Processing\nGood command of English and Mandarin\n\nContact Us:\u00a0\n\nMs. Sandy Leung\nEmail:\u00a0eng @headsearch21.com\nTel:\u00a031883072\nWhatsapp:\u00a096745650\n\nRef#: SD01002\n\nAll information collected will be treated in strict confidence and be used for recruitment purpose only\n\nCompany Web-Site:\u00a0www.headsearch21.com\u00a0\n\nHotline: (852) 3188 3586", "employment_types": ["Full Time", "Permanent"], "selling_points": ["Diploma + 8 years Operations exp in Manufacturing", "Familiar with Metal Stamping (MUST)", "Free Company Car / Hostel / Meal are provided"], "locations": ["Others - China"], "categories": ["Engineering", "Manufacturing & Production", "Management", "General Management", "Manufacturing", "Manufacturing Management"], "post_time": "2022-01-04T07:31:09Z", "salary": {"currency": "HKD", "max": 69999, "min": 55000, "period": "monthly", "term": null}, "salary_visible": true, "title_keywords": ["operations manager"], "responsibilities": ["control", "cost", "strategic planning", "operations", "technical advice", "quality", "monitor", "teams", "implementation", "daily operations"], "requirements": {"degrees": ["diploma"], "majors": ["related disciplines", "manufacturing", "engineering"], "languages": ["english", "chinese", "mandarin"], "language_level": ["proficiency", "good command"], "hard_skills": ["chinese word processing", "sap", "web", "erp", "whatsapp", "documentation", "ms office"], "soft_skills": ["confidence"], "languages_combined": [{"language": "english", "language_level": ["good command"]}, {"language": "chinese", "language_level": ["proficiency"]}, {"language": "mandarin", "language_level": ["good command"]}]}, "experience_required": {"duration": ["at least 8 years"], "field": ["manufacturing", "relevant experience"]}}, {"job_id": "100003009015899", "location_code": "hk", "company": "Michael Page", "job_title": "Production and Material Planning Manager", "description": "Lead the team and oversee the functions of production planning and material control\n\nMaterial planning from control of material flow to optimisation of work processes and production capacity\n\nClient Details\n\nMy client is Hong Kong top manufacturer and is looking for Production and Materials Planning Manager\n\nDescription\n\nLead the team and oversee the functions of production planning and material control\nResponsible for capacity planning and overall production scheduling based on demand from forecast to ensure supply capacity copes with forecast\nMaterial planning from control of material flow to optimisation of work processes and production capacity\nEnsures materials are ordered and in stock to meet company requirements, while maintaining acceptable inventory levels\nControl expenses and production efficiency through proper manpower scheduling and production plan\nTo perform analysis on work flow and production efficiency, collect and maintain accurate records and support month-end reporting;\n\nProfile\n\nBachelor or above, major in industrial engineering, supply chain, or related discipline is preferable;\nOver 6 - 8 years of solid relevant working experiences in similar position in production and material planning\nDetail minded, multi-tasks, strong sense of responsibility\nGood command of written and spoken English and Putonghua\n\nJob Offer\n\nInterested applicant please send me your resume to Marcochong@michaelpage com hk OR you can contact Marco @ 52909990\n\nTo apply online please click the 'Apply' button below. For a confidential discussion about this role please contact Marco Chong on +852 3476 6336", "employment_types": ["Full Time", "Permanent"], "selling_points": ["Top Hong Kong Food manufacturer", "Manage production and material planning", "Attractive salary with great benefits"], "locations": ["Not Specified"], "categories": ["Manufacturing", "Manufacturing Management", "Production Planning / Control", "Others"], "post_time": "2022-01-03T07:52:59Z", "salary": {"currency": null, "max": null, "min": null, "period": "monthly", "term": null}, "salary_visible": false, "title_keywords": ["manager"], "responsibilities": ["reporting", "control", "maintaining", "inventory", "expenses", "production planning", "analysis", "month-end", "scheduling", "maintain", "contact", "forecast", "plan", "planning"], "requirements": {"degrees": ["bachelor"], "majors": ["engineering"], "languages": ["putonghua", "english"], "language_level": ["good command"], "hard_skills": ["marco", "analysis"], "soft_skills": ["multi-tasks", "accurate", "responsible", "sense of responsibility"], "languages_combined": [{"language": "putonghua", "language_level": ["good command"]}, {"language": "english", "language_level": ["good command"]}]}, "experience_required": {"duration": ["6 - 8 years"], "field": ["planning"]}}, {"job_id": "100003009024953", "location_code": "hk", "company": "Lidl Asia Pte. Limited (Hong Kong Branch)", "job_title": "Senior Production Support Engineer (SDA & Electronics)", "description": "Summary\n\nLidl are hiring a Senior Production Support Engineer in the Production Support (SDA / Electronics) team. The successful candidate will be responsible for ensuring that production is cost effective, quality controlled and on time.\n\nWhat will you do?\nEnsure all production occurs in line with Lidl HK SOP\nEnsures all production occurs in line with Lidl\u2019s strict Ethical Sourcing Policies\nTakes control and leads all Pre-Production meetings in factory as determined by the \u2018Kick off\u2019 meeting at Lidl HQ\nProvide manufacturing technical support and procedure to reduce manufacturing costs and / or improve quality levels and production efficiency when identified\nNotify key stakeholders of any major or critical production and quality issues identified whilst in factory and follow up and close off outstanding CAPs with the supplier in question\nDrive compressed production impacts training with any impacting product category\nPerform Lidl factory evaluations, implement and control CAPs\nMonitor the efficiency of the Lidl China QC team\nMonitor the efficiency of the Lidl agency for offshore countries\nWhat will you need?\nDiploma or degree in electrical or mechanical engineering or at least 5 years\u2019 experience as a QC supervisor in the required product category\nAutonomous, proactive, detailed and commercially minded\nGood command of both spoken and written English and fluent in Mandarin\nBasic knowledge of Microsoft applications Word & Excel & Lotus Notes\nA can-do attitude with entrepreneurial spirit is a must\nWhat do we offer?\n\nWe are dedicated to fostering a family-friendly culture and we are an equal opportunities employer and welcome applications from all candidates with the required skills and experience.\n\n\u00a0\nMarket Leading Remuneration Package:\n\nDouble pay and discretionary bonus\nChoice of MPF provider\nLife Insurance\nMedical Insurance\n\u00a0\n\nSupportive Environment:\n\nRental re-imbursement scheme\nFlexible work arrangements\nIn-house training courses\nTraining sponsorship scheme\nHealth Check\nVision Check\nSupporting your child\u2019s education with advice from a leading education consultant\n\u00a0\n\nWork-Life Balance:\n\n5 day week\nCompetitive Annual Leave\nCharity, Community and Sporting Events", "employment_types": ["Permanent"], "selling_points": ["Must have either SDA or EE product experience", "Must understand the production process", "Office located in ICC building"], "locations": ["Tsim Sha Tsui"], "categories": ["Manufacturing", "Manufacturing Management", "Production Planning / Control", "Quality Assurance, Control & Testing / ISO"], "post_time": "2022-01-06T02:58:43Z", "salary": {"currency": null, "max": null, "min": null, "period": "monthly", "term": null}, "salary_visible": false, "title_keywords": ["senior production support engineer"], "responsibilities": ["cost", "control", "technical support", "policies", "quality", "monitor", "pre-production", "costs"], "requirements": {"degrees": ["diploma", "degree"], "majors": ["mechanical engineering"], "languages": ["english", "mandarin"], "language_level": ["good command", "fluent"], "hard_skills": ["excel", "basic", "word", "microsoft applications"], "soft_skills": ["determined", "responsible", "can-do attitude", "autonomous", "ethical", "controlled", "proactive", "detailed"], "languages_combined": [{"language": "english", "language_level": ["fluent", "good command"]}, {"language": "mandarin", "language_level": ["good command"]}]}, "experience_required": {"duration": ["at least 5 years"], "field": ["engineering"]}}, {"job_id": "100003009024978", "location_code": "hk", "company": "Burberry Asia Limited", "job_title": "Sustainable Manufacturing Programme Manager - Chemicals & Water Specialist", "description": "INTRODUCTION\n\nFounded in 1856 by Thomas Burberry, Burberry is a global luxury brand with a distinctly British attitude.\u00a0We are a global business with an extensive network of both owned and franchised stores across EMEIA, Asia Pacific and Americas. We are digital pioneers, and innovative technology underpins every aspect of our business, from product design to distribution and marketing. We believe that modern luxury means being socially and environmentally responsible; this mindset is core to our business and key to our long-term success.\n\nJOB PURPOSE\nAs the sustainable manufacturing programme manager, you will be\u00a0responsible\u00a0for driving Burberry\u2019s chemical management programme and\u00a0supporting\u00a0other sustainability initiatives.\nThe role entails strong stakeholder management internally and externally and we seek someone who is passionate about environmental issues. You are somebody who\u00a0enjoys\u00a0working with others, constantly seeks to collaborate and has strong integrity.\nYou will report to the Director of Quality & Sustainable Manufacturing, and work on a small but impactful team who are\u00a0.\u00a0responsible\u00a0for chemical management and water conservation\nRESPONSIBILITIES\nManage Burberry\u2019s chemical and water management implementation and supply chain performance in Asia\nBuild and maintain strong relationships with internal teams and supply chain partners\nSupport product compliance teams with RSL updates and non-conformity resolution\nEnsure accuracy of data for reporting purposes such as monthly KPI dashboards\nWork closely with the regional corporate responsibility team on joint initiatives and external reporting requirements, e.g. annual report, DJSI\nWork closely with regional SC teams to ensure support and awareness of initiatives and risks\nWork actively with external stakeholders and constantly seek opportunities to collaborate e.g. ZDHC\nPERSONAL PROFILE\n6 \u2013 8 years\u2019 experience in a similar role\nProven Chemical and Environmental education and experience\nStrong understanding of Microsoft Office programmes such as Excel, PowerPoint\nAbility to work in partnership with cross functional partners in other Burberry teams to ensure alignment of goals\nUnderstanding of textile and leather production processes\nStrong stakeholder management skills\nExcellent communication skills and experience of building rapport and influence across all levels\nA deep understanding of sustainability issues in the fashion industry and a passion to address these\nExcellent spoken and written English and Mandarin language.\nMEASURES OF SUCCESS\n\n\u00a0\u00a0\u21b5\n\nEnsure the achievement of partners KPIs as set every FY\nEnsure timely resolution of chemical non conformities\nEnsure accurate planning and performance of partner assessments\nEnsure accurate and timely reporting for internal and external purpose\n\nBurberry is an Equal Opportunities Employer and as such, treats all applications equally and recruits purely on the basis of skills and experience.", "employment_types": ["Full Time", "Permanent"], "selling_points": ["Chemicals & Water Specialist", "Fashion Retail Industry Experience", "Sustainable Manufacturing or Related Background"], "locations": ["Quarry Bay"], "categories": ["Manufacturing", "Manufacturing Management"], "post_time": "2022-01-06T03:02:01Z", "salary": {"currency": null, "max": null, "min": null, "period": "monthly", "term": null}, "salary_visible": false, "title_keywords": ["specialist", "manager"], "responsibilities": ["collaborate", "reporting", "management", "data", "compliance", "quality", "environmental issues", "implementation", "teams", "resolution", "communication", "product design", "maintain", "planning", "kpis", "report"], "requirements": {"degrees": [], "majors": [], "languages": ["english", "mandarin"], "language_level": ["excellent"], "hard_skills": ["small", "excel", "microsoft office", "powerpoint", "rsl"], "soft_skills": ["communication skills", "responsible", "accurate", "timely", "deep", "integrity", "innovative", "extensive", "passionate about"], "languages_combined": [{"language": "english", "language_level": ["excellent"]}, {"language": "mandarin", "language_level": ["excellent"]}]}, "experience_required": {"duration": ["8 years"], "field": ["environmental", "education"]}}, {"job_id": "100003009020701", "location_code": "hk", "company": "Jing Du Yang Sheng Tang Chinese Herbal Mfg Ltd", "job_title": "Production Officer / Assistant (5 days work)", "description": "Job description and responsibilities:\n\nAssist the Production Manager in organizing and coordinating daily operations of Production Department.\nPrepare Batch Production Records, Validation/Qualification documents and relevant SOPs.\nMonitor and check records & logbooks in production areas.\nEnsure all production flows and processes are compliant with GMP requirements and internal policy.\nAssistant in developing, implementing and maintaining the documentation system.\nMonitor the equipment and cleanroom hygiene according to the approval GMP procedure.\nParticipate in induction and on-job training to production staff.\nOther ad-hoc tasks as assigned by production manager.\n\nJob requirements:\n\n\n\nDiploma\u00a0or above in\u00a0Science related discipline\nGood command of Chinese and English;\nProficiency in computer skills, e.g. MS Office and Chinese Word Processing;\nGood communication skill ,Proactive, hardworking and independently.\nApplicant with less experiences will be considered as Production Assistant.\nFresh graduates are\u00a0also considered.\n\nWe offer 5 days work, 13 months\u2019salary, annual leave, medical allowance, overtime pay, transportation allowance, attendance award, paid sick leave, on-the-job training, etc. to the right candidates\n\nInterested candidate please send your updated CV with expected salary by clicking \"Apply Now\".\n\n\u00a0All applications will be treated in strict confidence and used solely for recruitment purpose.", "employment_types": ["Full Time", "Permanent"], "selling_points": [], "locations": ["Tsing Yi"], "categories": ["Manufacturing", "Manufacturing Management", "Medical Services", "Pharmaceutical"], "post_time": "2022-01-05T20:32:02Z", "salary": {"currency": null, "max": null, "min": null, "period": "monthly", "term": null}, "salary_visible": false, "title_keywords": ["assistant", "production officer"], "responsibilities": ["maintaining", "ad-hoc tasks", "monitor", "developing", "hygiene", "daily operations", "sops", "documentation"], "requirements": {"degrees": ["diploma or above"], "majors": ["science"], "languages": ["english", "chinese"], "language_level": ["good command"], "hard_skills": ["chinese word processing", "computer skills", "ms office"], "soft_skills": ["confidence", "independently", "communication skill", "proactive", "hardworking"], "languages_combined": [{"language": "english", "language_level": ["good command"]}, {"language": "chinese", "language_level": ["good command"]}]}, "experience_required": {"duration": [], "field": []}}, {"job_id": "100003009023178", "location_code": "hk", "company": "Traly Hong Kong Ltd", "job_title": "QC & QA Supervisor / Manager -  metal jewelry / gifts / souvenirs / toys (OEM items)", "description": "Traly Hong Kong Limited, a well established trading and manufacturing company, with a number of well-known and prestige clients in worldwide, is urgently seeking the following posts:\n\n\n- Form 5 graduated or above\n- At least 5 year QC & QA experiences on metal Jewelry, gift & souvenir items for US markets;\n- Experience in metal pins, jewelry, gifts and souvenir items is an advantage\n- familiar with jewelry & souvenir international safety standards / regulations / product testing\n- experience in factory compliance / audit for branded customers is an advantage.\n- Strong in both spoken and written English and Chinese with fluency in spoken Putonghua\n- Strong communication, organization, and analytical skills\n- detail-orientated, Self-motivated; responsible; well organized and can work independently and under pressure;\n- Proficiency in MS Office, Outlook and Internet for daily operation;\n\nJob Duties:\nCommunicate with factories and QC team for inspection and quality control\nCoordinate with merchandising team for order inspection, quality control and testing arrangement\nSupervise in-house QC team in China\nFactory compliance or factory audit follow up\nDealing with customers\u2019 QC & QA department\nrequire occasionally travel to China\n\n- 5 Day work; Medical, Performance Bonus\n\nInterested parties, please email your full resume with contact number and expected salary by clicking \"Apply now\"\n\n\n\n", "employment_types": ["Full Time", "Permanent"], "selling_points": ["Form 5 graduated or above", "Factory compliance or factory audit follow up", "5 Day work; Medical, Performance Bonus"], "locations": ["Not Specified"], "categories": ["Manufacturing", "Jewelry", "Manufacturing Management", "Quality Assurance, Control & Testing / ISO"], "post_time": "2022-01-05T08:34:17Z", "salary": {"currency": null, "max": null, "min": null, "period": "monthly", "term": null}, "salary_visible": false, "title_keywords": ["manager", "supervisor"], "responsibilities": ["regulations", "communicate with", "compliance", "daily operation", "audit", "coordinate with", "testing", "communication", "inspection", "merchandising", "quality control", "safety standards"], "requirements": {"degrees": ["form 5"], "majors": [], "languages": ["putonghua", "english", "chinese"], "language_level": ["fluency"], "hard_skills": ["ms office", "outlook", "analytical skills"], "soft_skills": ["self-motivated", "work independently", "under pressure", "responsible", "well organized", "analytical skills", "communication"], "languages_combined": [{"language": "putonghua", "language_level": []}, {"language": "english", "language_level": ["fluency"]}, {"language": "chinese", "language_level": ["fluency"]}]}, "experience_required": {"duration": ["at least 5 year"], "field": ["compliance", "audit", "qa"]}}, {"job_id": "100003009026436", "location_code": "hk", "company": "MDS Ltd", "job_title": "\u5ba4\u5167\u8a2d\u8a08\u5e2b**", "description": "\n\u8077\u8cac :\u4e00\u822c\u8a2d\u8a08\u5e2b(\u5ba4\u5167)\u5de5\u4f5c, \u5ea6\u5c3a\u53ca\u8a2d\u8a08\u7e6a\u5716, \u7368\u7acb\u8655\u7406\u5ba2\u55ae\uff0c\u8207\u5ba2\u6236\u6e9d\u901a\u5c0d\u5716\uff0c\u8ddf\u9032\u5de5\u7a0b\u4e8b\u5b9c\n\n\u8cc7\u6b77 :\u5c08\u4e0a\u6559\u80b2\uff1a\u6587\u6191/\u8b49\u66f8; 5\u5e74\u7d93\u9a57; \u826f\u597d\u7cb5\u8a9e; \u826f\u597d\u666e\u901a\u8a71; \u826f\u597d\u82f1\u8a9e; \u61c2\u8b80\u5beb\u4e2d\u6587; \u61c2\u8b80\u5beb\u82f1\u6587; \u61c2SketchUp; \u61c2PhotoShop; \u61c2Illustrator; \u61c2AutoCAD; \u7368\u7acb\u8655\u7406\u5de5\u4f5c\uff0c\u670d\u5f9e\u4e0a\u53f8\u6307\u4ee4\uff0c\u8aa0\u5be6\n\n\u5f85\u9047 :\u6bcf\u6708$10,000 - $20,000(\u8996\u4e4e\u5de5\u4f5c\u7d93\u9a57), \u6709\u4f63\u91d1, \u71df\u696d\u734e\u91d1 \u53ca\u5e74\u7d42\u734e\u91d1, \u4e0a\u534811\u6642\u81f3\u4e0b\u53489\u6642, \u6bcf\u9031\u5de5\u4f5c6\u5929,\u8f2a\u4f11, \u6bcf\u5929\u5de5\u4f5c 9 \u5c0f\u6642\n\n\u7533\u8acb\u9808\u77e5 :\u6c42\u8077\u8005\u53ef\u96fb\u90f5(Apply Now)\u5c65\u6b77\u8868\u7d66M.D.S.\u3002\u5982\u8981\u7d22\u53d6\u6536\u96c6\u500b\u4eba\u8cc7\u6599\u8072\u660e, \u8acb\u8207\u9673\u5c0f\u59d0(Email)\u806f\u7d61\u3002\n\n", "employment_types": ["Full Time"], "selling_points": [], "locations": ["Sai Ying Pun"], "categories": ["Design", "Interior", "Manufacturing", "Manufacturing Management", "Sales, CS & Business Devpt", "Others"], "post_time": "2022-01-06T08:08:41Z", "salary": {"currency": null, "max": null, "min": null, "period": "monthly", "term": null}, "salary_visible": false, "title_keywords": [], "responsibilities": [], "requirements": {"degrees": [], "majors": [], "languages": [], "language_level": [], "hard_skills": [], "soft_skills": [], "languages_combined": []}, "experience_required": {"duration": [], "field": []}}]