[{"job_id": "100003009045267", "location_code": "hk", "company": "Life Solutions", "job_title": "Sales Account Manager", "description": "Job Duties:\u00a0\nExpand and acquire potential B2B partners and support business development strategies\nBuild-up and maintain long-term relationship with new and existing B2B partners & B2C clients\nSales lead and order follow-up; prepare sales visit and presentation to pitch solution, service, and combination packages to clients\nProvide pre-sales & after-sales support to potential and existing clients\nSupport sales and marketing events\n\u00a0Requirements:\u00a0\nDegree holder with 3 years relevant knowledge and hands-on experience in fitting-out equipment industry: electrical appliances, kitchen utensils, lighting, carpet, furniture, bathroom utensils.\nA proactive personality with self-motivation; Independent at work is a must\n\u00a0Good interpersonal and communication skills\n\u00a0Good command of written and spoken English & Chinese / Cantonese\n\u00a0 Good PC skills: Word, Excel & PowerPoint\n\nWe offer attractive remuneration packages:-\nMonthly salary with team commission,\u00a05 days work, Bank holidays, medical benefits and MPF to the right candidates.\u00a0\n\nThe information provided will be kept confidential and used for recruitment purposes only.\u00a0\u00a0 The company will retain all applications for a maximum period of one year.", "employment_types": ["Full Time", "Permanent"], "selling_points": ["Kwai Hing MTR", "Monthly salary with team commission", "5 days work, Bank Holidays, Medical insurance"], "locations": ["Kwai Tsing Area"], "categories": ["Manufacturing", "Others", "Sales, CS & Business Devpt", "Sales - Sales Management", "Direct Sales"], "post_time": "2022-01-17T16:21:01Z", "salary": {"currency": null, "max": null, "min": null, "period": "monthly", "term": null}, "salary_visible": false, "title_keywords": ["account manager", "sales"], "responsibilities": ["marketing events", "maintain", "prepare sales"], "requirements": {"degrees": ["degree holder"], "majors": [], "languages": ["cantonese", "english", "chinese"], "language_level": ["good command"], "hard_skills": ["excel", "pc skills", "word", "powerpoint"], "soft_skills": ["communication skills", "independent", "hands-on", "self-motivation", "proactive", "interpersonal"], "languages_combined": [{"language": "cantonese", "language_level": ["good command"]}, {"language": "english", "language_level": ["good command"]}, {"language": "chinese", "language_level": ["good command"]}]}, "experience_required": {"duration": ["3 years"], "field": []}}, {"job_id": "100003009055758", "location_code": "hk", "company": "Amoy Food Ltd", "job_title": "\u5277\u624b\uff0f\u5277\u8eca\u64cd\u4f5c\u54e1\uff0f\u5009\u52d9\u54e1\uff0f\u57f7\u8ca8", "description": "\u8077\u8cac\u00a0:\n\n\u99d5\u99db\u6297\u8861\u5f0f\u5277\u8eca (\u5750\u5277)\u5de5\u4f5c\n\n\u8ca0\u8cac\u64cd\u4f5c\u5277\u8eca\uff0c\u8ca8\u7269\u6574\u7406\u8ca8\u7269\u53ca\u642c\u904b\u7b49\u5de5\u4f5c\n\n\u8981\u6c42 :\n\n\u4e2d\u4e09\u7a0b\u5ea6\n\u5fc5\u9808\u6301\u6709\u6297\u8861\u578b\u5277\u8eca\u724c\n\n\u7533\u8acb\u65b9\u6cd5\u00a0:\n\n1.\u00a0\u6309\u201cApply Now\u201d\u00a0\u6216\n2.\u00a0\u5c07\u500b\u4eba\u5c65\u6b77\u90f5\u5bc4\u81f3\u65b0\u754c\u5927\u57d4\u5de5\u696d\u90a8\u5927\u5bcc\u885711-15\u865f\u4eba\u529b\u8cc7\u6e90\u90e8\u6536\u00a0 \u00a0\u6216\n3.\u00a0\u50b3\u771f\u81f32666-6575\n\n\u5982\u6709\u67e5\u8a62,\u00a0\u8acb\u81f4\u96fb\u00a0\uff0fwhatsapp 5545-8814\u00a0\u806f\u7d61\u4eba\u529b\u8cc7\u6e90\u90e8\u3002\n(\u7533\u8acb\u4eba\u63d0\u4f9b\u4e4b\u8cc7\u6599\u5c07\u7d55\u5c0d\u4fdd\u5bc6\u53ca\u53ea\u4f5c\u62db\u8058\u7528\u9014)\u00a0", "employment_types": ["Full Time", "Contract"], "selling_points": ["\u8ca0\u8cac\u9ede\u6536, \u57f7\u8ca8", "\u5009\u5eab\u76e4\u9ede, \u51fa\u8ca8, \u6536\u8ca8, \u99d5\u99db\u5750\u5277", "\u53ef\u5373\u6642\u4e0a\u73ed"], "locations": ["Tai Po Area"], "categories": ["Transportation & Logistics", "Inventory / Warehousing", "Supply Chain", "Manufacturing", "Others"], "post_time": "2022-01-18T02:55:45Z", "salary": {"currency": null, "max": null, "min": null, "period": "monthly", "term": null}, "salary_visible": false, "title_keywords": [], "responsibilities": [], "requirements": {"degrees": [], "majors": [], "languages": [], "language_level": [], "hard_skills": [], "soft_skills": [], "languages_combined": []}, "experience_required": {"duration": [], "field": []}}, {"job_id": "100003009054329", "location_code": "hk", "company": "Wellcome", "job_title": "\u9ad8\u7d1a\u5207\u8089\u54e1 (\u901a\u5bb5\u73ed - \u65b0\u9bae\u98df\u54c1\u5009)", "description": "\u8077\u8cac :\u8ca0\u8cac\u5728\u51cd\u5009\u5167\u8655\u7406\u8089\u985e\uff0c\u64cd\u4f5c\u6a5f\u5668\u5207\u5272\u8089\u985e\uff0c\u5354\u52a9\u5176\u4ed6\u4e3b\u7ba1\u5206\u914d\u7684\u5de5\u4f5c (\u6709\u8d85\u6642\u5de5\u4f5c\u6d25\u8cbc, \u54e1\u5de5\u53ca\u5bb6\u5c6c\u91ab\u7642\u512a\u60e0(\u4e2d\u897f\u91ab, \u8dcc\u6253\u53ca\u7259\u91ab), \u6709\u85aa\u5a5a\u5047\u53ca\u514d\u4f9b\u6b3e\u9000\u4f11\u8a08\u5283) (\u5de5\u4f5c\u5730\u9ede:\u5c07\u8ecd\u6fb3\u5de5\u696d\u90a8, \u9700\u572812-13\u00b0C / 8\u00b0C / 0-4\u00b0C\u51cd\u5009\u5de5\u4f5c)\n\u8cc7\u6b77 :\u6c92\u6709\u5b78\u6b77\u8981\u6c42; 3\u5e74\u7d93\u9a57; \u4e00\u822c\u7cb5\u8a9e; \u61c2\u8b80\u5beb\u4e2d\u6587\n\u5f85\u9047 :\u6bcf\u6708$23,500, \u6709\u96d9\u7ce7, \u5e74\u504712\u5929, \u9280\u884c\u5047\u671f, \u54e1\u5de5\u8cfc\u7269\u512a\u60e0, \u7a7f\u68ad\u5df4\u58eb\u670d\u52d9 \u53ca\u65b0\u4eba\u734e, \u4e0b\u534810\u6642\u81f3\u4e0a\u53486\u664245\u5206, \u6bcf\u9031\u5de5\u4f5c6\u5929,\u8f2a\u4f11, \u6bcf\u5929\u5de5\u4f5c 7.5 - 8 \u5c0f\u6642\n\u7533\u8acb\u9808\u77e5 :\u6c42\u8077\u8005\u8acb\u89aa\u81e8\u4e5d\u9f8d\u8354\u679d\u89d2\u9577\u9806\u8857\u4e03\u865f\u897f\u9813\u4e2d\u5fc3\u516b\u6a13MARKET PLACE BY JASONS\u9762\u8a66\u3002\u67e5\u8a62\u8acb\u81f4\u96fb22998150\u8207\u4f55 \u5c0f\u59d0\u806f\u7d61\u3002", "employment_types": ["Full Time"], "selling_points": [], "locations": ["Tseung Kwan O"], "categories": ["Manufacturing", "General / Production Workers", "Others"], "post_time": "2022-01-17T09:10:43Z", "salary": {"currency": null, "max": null, "min": null, "period": "monthly", "term": null}, "salary_visible": false, "title_keywords": [], "responsibilities": [], "requirements": {"degrees": [], "majors": [], "languages": [], "language_level": [], "hard_skills": ["c"], "soft_skills": [], "languages_combined": []}, "experience_required": {"duration": [], "field": []}}, {"job_id": "100003009053436", "location_code": "hk", "company": "Proco International Company Limited", "job_title": "\u751f\u7522\u54e1", "description": "\n\u8077\u8cac :\u8ca0\u8cac\u79e4\u6599,\u5165\u6599,\u6df7\u6599,\u5305\u88dd(\u704c\u6ce8)\n\n\u8cc7\u6b77 :\u4e2d\u4e94\u7a0b\u5ea6; \u826f\u597d\u7cb5\u8a9e; \u61c2\u8b80\u5beb\u4e2d\u6587; \u7565\u61c2\u96fb\u6a5f\u64cd\u4f5c\n\n\u5f85\u9047 :\u6bcf\u65e5$650.00, \u661f\u671f\u4e00\u81f3\u4e94: \u4e0a\u53489\u6642\u81f3\u4e0b\u53486\u6642, \u6bcf\u9031\u5de5\u4f5c5\u5929\n\n\u7533\u8acb\u9808\u77e5 :\u6c42\u8077\u8005\u53ef\u81f4\u96fb21808086\u8207\u5bf6\u9ad8\u570b\u969b\u767c\u5c55\u6709\u9650\u516c\u53f8\u95dc\u5148\u751f\u806f\u7d61\u3002\n\n", "employment_types": ["Full Time"], "selling_points": [], "locations": ["Kwun Tong"], "categories": ["Manufacturing", "Others"], "post_time": "2022-01-17T06:59:15Z", "salary": {"currency": null, "max": null, "min": null, "period": "hourly", "term": null}, "salary_visible": false, "title_keywords": [], "responsibilities": [], "requirements": {"degrees": [], "majors": [], "languages": [], "language_level": [], "hard_skills": [], "soft_skills": [], "languages_combined": []}, "experience_required": {"duration": [], "field": []}}, {"job_id": "100003009054270", "location_code": "hk", "company": "ARCHETYPAL LIMITED", "job_title": "Showroom Sales Assistant \u2013 Part Time", "description": "The job description below is intended to describe the general nature and level of work being performed by people assigned to this job. It is not an exhaustive list of responsibilities, and it is subject to changes and exceptions at the discretion of supervisors.\n\n(This position is ideal for individuals in the design industry, who would like to be involved in the more business side of this creative environment.)\n\nJob Nature\n\nShowroom Sales Assistant\n\nTo assist Showroom Sales Executive in everyday operations of the shop over weekends and occasional weekday. Candidate with Graphic Design experience will be preferred with negotiate rate.\n\nDaily Job Responsibility\n\nTo provide service to customers and handle basic inquiry at the shop.\nUnderstanding basic sales operation procedure for our POS system and order processing.\nLearn the basic product knowledge and technique in order to assist customers\u2019 varied enquiries.\nAssist in various aspect of this small dynamic team\n\nCandidate Requirement\n\nWe are looking for someone with the following attributes:\n\nMinimum of 1 years of Retail sales experience.\nOutgoing and able to initiate conversation. Great Interpersonal Skill\nresourceful, proactive, diligent\nexcellent spoken and written English and Chinese\npassionate about design\ncheerful and willing to go an extra mile for the company", "employment_types": ["Part Time"], "selling_points": [], "locations": ["Wan Chai"], "categories": ["Manufacturing", "Others", "Sales, CS & Business Devpt", "Others", "Direct Sales"], "post_time": "2022-01-17T09:00:16Z", "salary": {"currency": null, "max": null, "min": null, "period": "hourly", "term": null}, "salary_visible": false, "title_keywords": ["sales assistant"], "responsibilities": ["order processing"], "requirements": {"degrees": [], "majors": [], "languages": [], "language_level": [], "hard_skills": [], "soft_skills": [], "languages_combined": []}, "experience_required": {"duration": [], "field": []}}, {"job_id": "100003009050777", "location_code": "hk", "company": "Golden Resources Development Ltd", "job_title": "\u8cc7\u6599\u8f38\u5165\u6587\u54e1/\u6587\u54e1 (Data Entry Clerk/Clerk)", "description": "\u8655\u7406\u9ede\u6536\u8ca8\u7269\u53ca\u6587\u66f8\u5de5\u4f5c\n\u4e2d\u5b78\u7562\u696d\u6216\u4ee5\u4e0a\n\u719f\u6089\u4e2d\u82f1\u6587\u96fb\u8166\u64cd\u4f5c\u3001\u61c2 SAP \u512a\u5148\u8003\u616e\n\u7a4d\u6975\u4e3b\u52d5\u3001\u7cbe\u5bc6\u4ed4\u7d30\u53ca\u5177\u5099\u826f\u597d\u6e9d\u901a\u6280\u5de7\n\u6709\u8ca8\u5009\u64cd\u4f5c\u7d93\u9a57\u512a\u5148\u8003\u616e\n\n\u661f\u671f\u516d\u9577\u77ed\u9031\u5de5\u4f5c\u300114\u5929\u5927\u5047\u3001\u6bcf\u6708\u984d\u5916 1 \u5929\u5047\u671f\u3001\u7d05\u767d\u5047\u3001\u8003\u8a66\u5047\u3001\u514d\u8cbb\u5348\u81b3\u4f9b\u61c9\u3001\u54e1\u5de5\u6298\u6263\u3001\u91ab\u7642\u4fdd\u96aa\u3001\u54e1\u5de5\u734e\u52f5\u91d1\u53ca\u82b1\u7d05\u7b49\n\n\u6709\u610f\u8005\u8acb\u6309Apply Now \u63d0\u4ea4\u5c65\u6b77\u8868", "employment_types": ["Full Time", "Permanent"], "selling_points": [], "locations": ["Tsing Yi"], "categories": ["Transportation & Logistics", "Supply Chain", "Manufacturing", "Others"], "post_time": "2022-01-14T11:21:26Z", "salary": {"currency": null, "max": null, "min": null, "period": "monthly", "term": null}, "salary_visible": false, "title_keywords": ["clerk", "\u6587\u54e1", "data entry clerk"], "responsibilities": [], "requirements": {"degrees": [], "majors": [], "languages": [], "language_level": [], "hard_skills": ["sap"], "soft_skills": [], "languages_combined": []}, "experience_required": {"duration": [], "field": []}}, {"job_id": "100003009053225", "location_code": "hk", "company": "DKSH Hong Kong Limited", "job_title": "Specialist, Supply Chain Management (Fresh Graduates are welcome)", "description": "Job Responsibilities:\n\nSupport in day-to-day operating expenditures to ensure efficient usage of resources\nExecute and monitor relabeling and redressing policies, standards and operating procedures in compliance with good manufacturing practice (GMP) standards, ensure timely delivery of materials\u00a0\u00a0\nCoordinate resources with staff and contractors to meet the repackaging deadlines\nCoordinate contractors including selection of contractors, quotation negotiation, training and KPI review, to ensure fulfillment of contractual service commitments\nPrepare repackaging specializations\u00a0based on client's requirements\nReview, analyze and suggest improvements regarding quality, safety and standard operating procedures\nLiaise with clients on operational issues, enquiries and requests; escalate issues to manager, if necessary\n\nJob Requirements\n\nHKCEE or DSE above\n1 years logistics / supply chain / shipping operations experience is preferred\nProficiency in computer applications, including Excel and Word\nTactful interpersonal and communication skill to work with people in different levels\nSelf-motivated with strong sense of responsibility\nGood command of written and spoken English and Chinese (Cantonese)\nImmediate available is highly preferred\nFresh Graduates are welcome\n\n\n\nWe offer performance bonus and attractive benefits including medical insurance and company shuttle bus services to the right candidate. Interested parties please apply in full resume with current and expected salaries to Human Resources Department , DKSH Hong Kong Limited, 23rd Floor, Tower A, Southmark, 11 Yip Hing Street, Wong Chuk Hang, Hong Kong or by clicking \"Apply Now\"\n\nAll personal data collected will be used for recruitment purposes only. \u00a0Candidates will be contacted within 2 weeks if the background and experience are closely relevant to the job requirement.\n\nDrive Growth. Be the Difference. Join DKSH.\n\nDKSH\u2019s strength lies in our great diversity of services, industries, clients, products, regions and employees from various nationalities. We are proud of our people: they are the reason we are successful. Our people are the best in the industry. They are passionate about their career growth and about business success. They work as part of an energetic and committed team, positively impacting millions of lives through the products and services we provide. Join us today if you are ready to \u201cDrive growth. Be the Difference.\u201d With DKSH, you will experience a world of learning and development, own your career and take business responsibility and have a positive impact that touches people\u2019s lives.", "employment_types": ["Full Time", "Permanent"], "selling_points": ["Certificate or Diploma graduate", "Immediate available is highly preferred", "Fresh Graduates are welcome"], "locations": ["Kwai Tsing Area"], "categories": ["Transportation & Logistics", "Others", "Supply Chain", "Manufacturing", "Others"], "post_time": "2022-01-17T06:29:13Z", "salary": {"currency": null, "max": null, "min": null, "period": "monthly", "term": null}, "salary_visible": false, "title_keywords": ["specialist"], "responsibilities": ["liaise with clients", "policies", "fulfillment", "compliance", "monitor", "procedures", "quotation", "review", "coordinate", "quality", "suggest improvements"], "requirements": {"degrees": ["dse"], "majors": [], "languages": ["cantonese", "english", "chinese"], "language_level": ["good command"], "hard_skills": ["excel", "word"], "soft_skills": ["self-motivated", "sense of responsibility", "communication skill", "tactful", "interpersonal"], "languages_combined": [{"language": "cantonese", "language_level": ["good command"]}, {"language": "english", "language_level": ["good command"]}, {"language": "chinese", "language_level": ["good command"]}]}, "experience_required": {"duration": ["1 years"], "field": ["supply chain", "logistics"]}}, {"job_id": "100003009053679", "location_code": "hk", "company": "Success Development Information Technology Company Limited", "job_title": "\u4eba\u4e8b\u53ca\u884c\u653f\u52a9\u7406", "description": "\n\u8077\u8cac :\u8655\u7406\u5168\u9762\u7684\u4eba\u529b\u8cc7\u6e90\u8077\u80fd,\u5305\u62ec\u8655\u7406\u54e1\u5de5\u62db\u8058,\u5f37\u7a4d\u91d1,\u85aa\u916c\u798f\u5229,\u5de5\u8cc7\u7ba1\u7406;\u4fdd\u6301\u826f\u597d\u7684\u4eba\u529b\u8cc7\u6e90\u8a18\u9304\u548c\u500b\u4eba\u8cc7\u6599\u6b78\u6a94,\u4f11\u5047\u8a18\u9304,\u51fa\u52e4\u8a18\u9304\u7b49;\u7ba1\u7406\u516c\u53f8\u6703\u54e1\u6578\u64da\u5eab\u53ca\u5236\u4f5c\u71df\u696d\u5831\u544a;\u8ca0\u8cac\u8fa6\u516c\u5ba4\u884c\u653f\u5de5\u4f5c\u5305\u62ec\u8a2d\u5099\u7dad\u8b77\u548c\u8fa6\u516c\u7528\u54c1\u63a1\u8cfc,\u6587\u4ef6\u6574\u7406\u53ca\u6b78\u6a94\u7b49\n\n\u8cc7\u6b77 :\u4e2d\u4e94\u7a0b\u5ea6; 2\u5e74\u7d93\u9a57; \u4e00\u822c\u7cb5\u8a9e; \u4e00\u822c\u666e\u901a\u8a71; \u4e00\u822c\u82f1\u8a9e; \u61c2\u8b80\u5beb\u4e2d\u6587; \u7565\u61c2\u8b80\u5beb\u82f1\u6587; \u61c2Microsoft Office; \u5177\u6709\u4e00\u822c\u4e92\u806f\u7db2\u77e5\u8b58; \u61c2\u82f1\u6587\u6253\u5b57; \u61c2\u5009\u9821/\u901f\u6210\u8f38\u5165\u6cd5; \u53ef\u5373\u6642\u4e0a\u73ed\u512a\u5148(\u6839\u64da\u9700\u57f7\u884c\u81e8\u6642\u5206\u914d\u5de5\u4f5c)\n\n\u5f85\u9047 :\u6bcf\u6708$14,000 - $16,000, \u4e00\u81f3\u4e94:\u4e0a\u53489\u6642\u534a\u81f3\u4e0b\u53486\u6642,\u6bcf\u9031\u5de5\u4f5c5\u5929,\u6bcf\u5929\u5de5\u4f5c 8.5 \u5c0f\u6642(\u8ca0\u8cac\u7b56\u5283\u548c\u7d44\u7e54\u516c\u53f8\u6d3b\u52d5)\n\n\u7533\u8acb\u9808\u77e5 :\u53ef\u96fb\u90f5(Apply Now)\u5c65\u6b77\u8868\u7d66\u6210\u529f\u767c\u5c55\u8cc7\u8a0a\u79d1\u6280\u6709\u9650\u516c\u53f8\u3002\u5982\u8981\u7d22\u53d6\u6536\u96c6\u500b\u4eba\u8cc7\u6599\u8072\u660e, \u8acb\u8207\u5f35\u5c0f\u59d0(Tel:23767000)\u806f\u7d61\u3002\n\n", "employment_types": ["Full Time"], "selling_points": [], "locations": ["Kwun Tong"], "categories": ["Admin & HR", "Clerical / Admin Staff", "Manufacturing", "Others"], "post_time": "2022-01-17T07:20:36Z", "salary": {"currency": null, "max": null, "min": null, "period": "monthly", "term": null}, "salary_visible": false, "title_keywords": [], "responsibilities": [], "requirements": {"degrees": [], "majors": [], "languages": [], "language_level": [], "hard_skills": [], "soft_skills": [], "languages_combined": []}, "experience_required": {"duration": [], "field": []}}, {"job_id": "100003009052706", "location_code": "hk", "company": "Pet-Link Company Limited", "job_title": "\u5bf5\u7269\u98df\u54c1\u751f\u7522\u54e1(\u5927\u57d4)", "description": "\u8077\u8cac :\u8ca0\u8cac\u4e00\u822c\u98df\u54c1\u751f\u7522\u5de5\u4f5c, \u5305\u62ec\u642c\u904b\u539f\u6750\u6599, \u64cd\u4f5c\u6a5f\u5668, \u5305\u88dd\u53ca\u7c21\u55ae\u6e05\u6f54\u7b49\n\u8cc7\u6b77 :\u6c92\u6709\u5b78\u6b77\u8981\u6c42; 3\u5e74\u7d93\u9a57; \u826f\u597d\u7cb5\u8a9e; \u61c2\u8b80\u5beb\u4e2d\u6587; \u5fc5\u9808\u6709\u9eb5\u5305\u70d8\u7119\u53ca\u751f\u7522\u7d93\u9a57, \u6709\u81a8\u5316\u6280\u8853\u512a\u5148\n\u5f85\u9047 :\u6bcf\u6708$14,000 - $18,000, \u6709\u6bcf\u6708\u52e4\u5de5\u734e\u91d1$500, \u9280\u884c\u5047\u671f, \u914c\u60c5\u6027\u82b1\u7d05, \u91ab\u7642\u798f\u5229 \u53ca\u8868\u73fe\u734e\u91d1, \u661f\u671f\u4e00\u81f3\u4e94: \u4e0a\u53489\u6642\u81f3\u4e0b\u53486\u6642, \u6bcf\u9031\u5de5\u4f5c5\u5929, \u6bcf\u5929\u5de5\u4f5c 9 \u5c0f\u6642\n\u7533\u8acb\u9808\u77e5 :\u6c42\u8077\u8005\u53ef\u81f4\u96fb67342960\u8207\u5bf5\u7269\u5e79\u7dda\u6709\u9650\u516c\u53f8\u6c5f\u5973\u58eb\u806f\u7d61\u3002", "employment_types": ["Full Time"], "selling_points": [], "locations": ["Tai Po Area"], "categories": ["Hospitality / F & B", "Others", "Manufacturing", "Others", "Others", "Others"], "post_time": "2022-01-17T03:45:58Z", "salary": {"currency": null, "max": null, "min": null, "period": "monthly", "term": null}, "salary_visible": false, "title_keywords": [], "responsibilities": [], "requirements": {"degrees": [], "majors": [], "languages": [], "language_level": [], "hard_skills": [], "soft_skills": [], "languages_combined": []}, "experience_required": {"duration": [], "field": []}}, {"job_id": "100003009053703", "location_code": "hk", "company": "TUV Rheinland Hong Kong Limited", "job_title": "\u5be6\u9a57\u5ba4\u6280\u8853\u54e1(\u7121\u9700\u5de5\u4f5c\u7d93\u9a57)", "description": "Job Responsibilities:\n\n\u5728\u4e3b\u7ba1\u7684\u6307\u5c0e\u4e0b\uff0c\u6309\u7167\u6a19\u6e96\u64cd\u4f5c\u7a0b\u5e8f\u9032\u884c\u98df\u54c1\u5bb9\u5668\u6aa2\u6e2c\u7b49\u5e38\u898f\u5316\u5b78\u6e2c\u8a66\n\u5728\u6e2c\u8a66\u5de5\u4f5c\u8868\u4e0a\u5408\u4f75\u548c\u8a18\u9304\u76f8\u95dc\u6578\u64da\n\u76e3\u63a7\u6e2c\u8a66\u6642\u9593\u4ee5\u78ba\u4fdd\u5de5\u4f5c\u5728\u8a08\u5283\u6642\u9593\u5167\u5b8c\u6210\n\nJob Requirements:\n\n\u4e2d\u4e94\u6216\u4ee5\u4e0a\u5b78\u6b77\n\u7121\u9700\u76f8\u95dc\u5de5\u4f5c\u7d93\u9a57\n\nOther benefits:\n\n\u9280\u884c\u5047\u671f\n\u8f2a\u73ed\u6d25\u8cbc,\u9ad8\u9054\u6708\u85aa\u768440%\n\u52a0\u73ed\u8cbb\n\u96d9\u7ce7\u53ca\u5e74\u5ea6\u8868\u73fe\u734e\u91d1\n\u91ab\u7642\u3001\u7259\u79d1\u548c\u4eba\u58fd\u4fdd\u96aa\n\u5e74\u5047\u3001\u7522\u5047\u3001\u4f8d\u7522\u5047\u3001\u5a5a\u5047\u3001\u9ad4\u6064\u5047\n\u5728\u8077\u57f9\u8a13\u4ee5\u53ca\u9032\u4fee\u88dc\u8cbc\n\nAll information received will be kept in strict confidence and used for employment purpose only. Applicants who are not invited for interview within\u00a05 weeks may assume their applications unsuccessful and their data will be retained for 6 months for other suitable vacancies in our organization and thereafter destroyed.", "employment_types": ["Full Time", "Permanent"], "selling_points": ["\u7a69\u5b9a\u5de5\u4f5c\u74b0\u5883", "\u7121\u9700\u5de5\u4f5c\u7d93\u9a57", "\u4fdd\u8b49\u96d9\u7ce7\u53ca\u8868\u73fe\u734e\u91d1"], "locations": ["Tsuen Wan Area"], "categories": ["Sciences, Lab, R&D", "Chemical", "Laboratory", "Manufacturing", "Others"], "post_time": "2022-01-17T07:22:32Z", "salary": {"currency": null, "max": null, "min": null, "period": null, "term": null}, "salary_visible": false, "title_keywords": [], "responsibilities": [], "requirements": {"degrees": [], "majors": [], "languages": [], "language_level": [], "hard_skills": [], "soft_skills": [], "languages_combined": []}, "experience_required": {"duration": [], "field": []}}, {"job_id": "100003009053857", "location_code": "hk", "company": "Regal Prosthesis Limited", "job_title": "\u751f\u7522\u54e1**", "description": "\n\u8077\u8cac :\u4e00\u822c\u751f\u7522\u54e1\u5de5\u4f5c,\u9700\u8981\u8655\u7406\u7d30\u7dfb\u5de5\u4f5c\n\n\u8cc7\u6b77 :\u6c92\u6709\u5b78\u6b77\u8981\u6c42; \u4e00\u822c\u7cb5\u8a9e; \u61c2\u95b1\u8b80\u4e2d\u6587; \u5c0d\u624b\u5de5\u85dd\u611f\u8208\u8da3, \u5de5\u4f5c\u7d30\u5fc3,\u6709\u8010\u6027,\u5177\u5099\u80fd\u6aa2\u9a57\u8ca8\u54c1\u984f\u8272\u7684\u8996\u529b\n\n\u5f85\u9047 :\u6bcf\u6708$11,500 - $14,000, \u661f\u671f\u4e00\u81f3\u4e94: \u4e0a\u53488\u6642\u81f3\u4e0b\u53486\u6642, \u6bcf\u9031\u5de5\u4f5c5\u5929\n\n\u7533\u8acb\u9808\u77e5 :\u6c42\u8077\u8005\u53ef\u96fb\u90f5(Apply Now)\u5c65\u6b77\u8868\u7d66\u7687\u5ba4\u7fa9\u80a2\u6709\u9650\u516c\u53f8\u3002\u5982\u8981\u7d22\u53d6\u6536\u96c6\u500b\u4eba\u8cc7\u6599\u8072\u660e, \u8acb\u8207\u8449\u5c0f\u59d0(Email)\u806f\u7d61\u3002\n\n", "employment_types": ["Full Time"], "selling_points": [], "locations": ["Kwai Tsing Area"], "categories": ["Manufacturing", "Others"], "post_time": "2022-01-17T07:38:06Z", "salary": {"currency": null, "max": null, "min": null, "period": "monthly", "term": null}, "salary_visible": false, "title_keywords": [], "responsibilities": [], "requirements": {"degrees": [], "majors": [], "languages": [], "language_level": [], "hard_skills": [], "soft_skills": [], "languages_combined": []}, "experience_required": {"duration": [], "field": []}}, {"job_id": "100003009051869", "location_code": "hk", "company": "LAWSGROUP", "job_title": "Assistant General Manager (Stationed in Overseas)", "description": "Job Responsibilities:\n\nAssist General Manager on a project based to explore and develop new factory plant in overseas\nProvide full spectrum of administrative functions including facilities repair and maintenance, deliver services, catering and accommodation services, etc\nTo lead, supervise, review, recommend and implement policies & operational procedures to meet with the Company's development needs and to ensure compliance of the Corporate policies\nDevelop and implement staffing and business plans to achieve business target\nResponsible for overall factory operations and management\nHandle ad hoc projects as assigned by immediate supervisor\n\nJob Requirements:\n\nDegree holder or above\nStrong solid experience in all-round garment manufacturing factory environment is a\u00a0MUST\nMinimum 10 years relevant experience in manufacturing industry including 5 years at managerial level\nSelf-motivated, result-oriented and able to work under pressure\nExcellent interpersonal skills and project management skills\nExcellent command in both spoken and written English and Chinese including Mandarin\nStationed in Overseas\n\nWe\u00a0offer\u00a0attractive remuneration package to the right candidate. Interested parties please click the \"APPLY NOW\" button below and send your application together with a detailed resume including current & expected salary and availability to Human Resources Department.\n\nCompany website:\u00a0https://www.lawsgroup.com\n\n(Data collected will be treated in strict confidence and used for recruitment purpose only)\n", "employment_types": ["Full Time", "Permanent"], "selling_points": ["Degree holder with 8 yrs relevant work exp.", "Solid exp in garment manufacturing factory", "Stationed in Overseas"], "locations": ["Overseas"], "categories": ["Admin & HR", "Others", "Manufacturing", "Garment / Textile", "Others"], "post_time": "2022-01-17T01:25:47Z", "salary": {"currency": null, "max": null, "min": null, "period": "monthly", "term": null}, "salary_visible": false, "title_keywords": ["assistant general manager"], "responsibilities": ["management", "maintenance", "policies", "operations", "review", "business plans", "develop", "ensure compliance", "repair", "operational procedures", "ad hoc projects", "catering"], "requirements": {"degrees": ["degree holder"], "majors": [], "languages": ["english", "chinese", "mandarin"], "language_level": ["excellent"], "hard_skills": ["project management"], "soft_skills": ["self-motivated", "project management skills", "interpersonal skills", "result-oriented", "work under pressure"], "languages_combined": [{"language": "english", "language_level": ["excellent"]}, {"language": "chinese", "language_level": ["excellent"]}, {"language": "mandarin", "language_level": ["excellent"]}]}, "experience_required": {"duration": ["5 years", "minimum 10 years"], "field": ["garment", "managerial", "manufacturing", "relevant experience", "manufacturing industry"]}}, {"job_id": "100003009052082", "location_code": "hk", "company": "TUMI Asia, Limited", "job_title": "Tumi - Product Development Assistant (4-month Contracted)", "description": "Job Responsibilities:\u00a0\n\nAssist Product Development Manager on material development (prepare and send swatch cards to design, vendor and Tumi lab)\nPrepare weekly sample development status report\nHandle daily courier shipment\nTake sample photo, assist Product Development Manager\u00a0prepare sample evaluation report\nMaterial master filing\nJob Requirement:\u00a0\n\nDegree holder in any disciplines\nMinimum 2 years of relevant experience in administration/ operation and fresh graduates will be considered\nProficiency in Microsoft Office, Excel and Word\nGood spoken and written English and Cantonese/Chinese\nInterested parties please send your Full Resume with current and expected salary to us by clicking the \"Apply Now\" button below.\n\nTUMI is an equal opportunity employer and welcome applications from all qualified candidates. All information provided by candidates will be used solely for recruitment purposes. Candidates not notified within eight weeks may consider their application unsuccessful. Unsuccessful applications will be destroyed in strict confidence upon completion of recruitment process.", "employment_types": ["Full Time", "Contract"], "selling_points": ["Five-day work week", "2 years of relevant experience", "Fresh Graduates are welcome to apply"], "locations": ["Tsim Sha Tsui"], "categories": ["Manufacturing", "Product Development / Management", "Others", "Merchandising & Purchasing", "Handbag"], "post_time": "2022-01-17T09:19:47Z", "salary": {"currency": null, "max": null, "min": null, "period": "monthly", "term": null}, "salary_visible": false, "title_keywords": ["product development assistant"], "responsibilities": ["evaluation", "design", "report"], "requirements": {"degrees": ["degree holder"], "majors": ["any disciplines"], "languages": ["cantonese", "english", "chinese"], "language_level": ["good"], "hard_skills": ["excel", "word", "microsoft office"], "soft_skills": [], "languages_combined": [{"language": "cantonese", "language_level": ["good"]}, {"language": "english", "language_level": ["good"]}, {"language": "chinese", "language_level": ["good"]}]}, "experience_required": {"duration": ["minimum 2 years"], "field": ["operation", "relevant experience", "administration"]}}, {"job_id": "100003009053853", "location_code": "hk", "company": "Regal Prosthesis Limited", "job_title": "\u751f\u7522\u54e1", "description": "\n\u8077\u8cac :\u4e00\u822c\u751f\u7522\u54e1\u5de5\u4f5c, \u9700\u8981\u8655\u7406\u7d30\u7dfb\u5de5\u4f5c\n\n\u8cc7\u6b77 :\u6c92\u6709\u5b78\u6b77\u8981\u6c42; \u4e00\u822c\u7cb5\u8a9e; \u61c2\u95b1\u8b80\u4e2d\u6587; \u5de5\u4f5c\u7d30\u5fc3, \u5c0d\u624b\u5de5\u85dd\u611f\u8208\u8da3, \u5c0d\u756b\u756b/\u52de\u4f5c\u7b49\u6709\u8010\u6027\u512a\u5148,\u5177\u5099\u80fd\u6aa2\u9a57\u8ca8\u54c1\u984f\u8272\u7684\u8996\u529b\n\n\u5f85\u9047 :\u6bcf\u6708$12,650 - $15,400, \u661f\u671f\u4e00\u81f3\u4e94: \u4e0a\u534811\u6642\u534a\u81f3\u4e0b\u53489\u6642\u534a, \u6bcf\u9031\u5de5\u4f5c5\u5929\n\n\u7533\u8acb\u9808\u77e5 :\u6c42\u8077\u8005\u53ef\u96fb\u90f5(Apply Now)\u5c65\u6b77\u8868\u7d66\u7687\u5ba4\u7fa9\u80a2\u6709\u9650\u516c\u53f8\u3002\u5982\u8981\u7d22\u53d6\u6536\u96c6\u500b\u4eba\u8cc7\u6599\u8072\u660e, \u8acb\u8207\u8449\u5c0f\u59d0(Email)\u806f\u7d61\u3002\n\n", "employment_types": ["Full Time"], "selling_points": [], "locations": ["Kwai Tsing Area"], "categories": ["Manufacturing", "Others"], "post_time": "2022-01-17T07:37:35Z", "salary": {"currency": null, "max": null, "min": null, "period": "monthly", "term": null}, "salary_visible": false, "title_keywords": [], "responsibilities": [], "requirements": {"degrees": [], "majors": [], "languages": [], "language_level": [], "hard_skills": [], "soft_skills": [], "languages_combined": []}, "experience_required": {"duration": [], "field": []}}, {"job_id": "100003009052848", "location_code": "hk", "company": "Tsit Wing Coffee Co Ltd", "job_title": "\u751f\u7522\u9818\u73ed /\u52a9\u7406\u751f\u7522\u9818\u73ed**", "description": "\u8077\u8cac :\u7763\u5c0e\u751f\u7522\u5de5\u4eba\u65e5\u5e38\u904b\u4f5c\u4e26\u5206\u914d\u5de5\u4f5c, \u6309\u7167\u751f\u7522\u8a08\u5283\u54e1\u7684\u7de8\u5236, \u7763\u4fc3\u751f\u7522\u9032\u5ea6, \u8a18\u9304\u8ca8\u54c1\u4ea4\u6536, \u8207\u7269\u6d41\u90e8\u806f\u7e6b\u8655\u7406\u6210\u54c1\n\u8cc7\u6b77 :\u5c08\u4e0a\u6559\u80b2\uff1a\u6587\u6191/\u8b49\u66f8; 2\u5e74\u7d93\u9a57; \u826f\u597d\u7cb5\u8a9e; \u4e00\u822c\u82f1\u8a9e; \u61c2\u8b80\u5beb\u4e2d\u6587; \u61c2\u8b80\u5beb\u82f1\u6587\n\u5f85\u9047 :\u6bcf\u6708$18,500, \u6709\u914c\u60c5\u6027\u82b1\u7d05, \u54e1\u5de5\u8cfc\u7269\u512a\u60e0, \u91ab\u7642\u798f\u5229 \u53ca\u8d85\u6642\u5de5\u4f5c\u6d25\u8cbc, \u661f\u671f\u4e00\u81f3\u516d: \u4e0a\u53488\u6642\u534a\u81f3\u4e0b\u53486\u6642, \u6bcf\u9031\u5de5\u4f5c5\u5929\u81f36\u5929\n\u7533\u8acb\u9808\u77e5 :\u6c42\u8077\u8005\u53ef\u81f4\u96fb24195909\u8207\u6377\u69ae\u5496\u5561\u6709\u9650\u516c\u53f8\u5f35\u5c0f\u59d0\u806f\u7d61\u3002\n\u5099\u8a3b :** \u50f1\u4e3b\u53ef\u5c31\u6b64\u8077\u4f4d\u7a7a\u7f3a\u7533\u8acb\u53c3\u52a0\u300c\u4e2d\u9ad8\u9f61\u5c31\u696d\u8a08\u5283\u300d\uff0c\u6b61\u8fce\u4e2d\u9ad8\u9f61\u6c42\u8077\u4eba\u58eb\u61c9\u5fb5\u3002", "employment_types": ["Full Time"], "selling_points": [], "locations": ["Kwai Tsing Area"], "categories": ["Manufacturing", "General / Production Workers", "Others"], "post_time": "2022-01-17T04:16:30Z", "salary": {"currency": null, "max": null, "min": null, "period": "monthly", "term": null}, "salary_visible": false, "title_keywords": [], "responsibilities": [], "requirements": {"degrees": [], "majors": [], "languages": [], "language_level": [], "hard_skills": [], "soft_skills": [], "languages_combined": []}, "experience_required": {"duration": [], "field": []}}, {"job_id": "100003009044444", "location_code": "hk", "company": "Foot Locker Sourcing, Inc", "job_title": "ASSISTANT MERCHANDISER", "description": "Foot Locker, Inc., public listed in New York and the world's leading retailer of athletic footwear and apparel, has an open position for its worldwide sourcing operations in Hong Kong:\n\nASSISTANT MERCHANDISER\n\n2 years experience in the garment field\nHKCEE/DSE or above\nGood PC knowledge. Proficient in Excel.\nGood command in written & spoken English and Mandarin\nSelf-motivated, detailed minded, hardworking and able to work independently\nResponsible for sample packing, measurement, some data input and reporting\n\nJob Types: Full-time", "employment_types": ["Full Time", "Permanent"], "selling_points": [], "locations": ["Kwun Tong"], "categories": ["Manufacturing", "Garment / Textile", "Others"], "post_time": "2022-01-16T21:50:14Z", "salary": {"currency": null, "max": null, "min": null, "period": "monthly", "term": null}, "salary_visible": false, "title_keywords": ["assistant merchandiser"], "responsibilities": ["operations", "measurement", "data input", "reporting"], "requirements": {"degrees": ["dse"], "majors": [], "languages": ["english", "mandarin"], "language_level": ["good command"], "hard_skills": ["excel", "pc knowledge"], "soft_skills": ["self-motivated", "work independently", "responsible", "hardworking", "detailed"], "languages_combined": [{"language": "english", "language_level": ["good command"]}, {"language": "mandarin", "language_level": ["good command"]}]}, "experience_required": {"duration": ["2 years"], "field": ["garment"]}}, {"job_id": "100003009054462", "location_code": "hk", "company": "PERSOL Hong Kong", "job_title": "Sales coordinator(5 day/Near MTR Station/Stable company)", "description": "Our client, a Japanese company, is now seeking for a high caliber individual to join their team as a Sales coordinator.\n\n\nJob Descriptions:\n\n\nHandle sales related documents for existing local clients\u00a0\nFollow up sales orders and monitor delivery schedule to fulfil customers requirement\u00a0\nPrepare invoice, P/O, liaise with factories and clients for production delivery issues\n\nRequirements:\n\n\n2 years of clerical working experience in ANY industry\u00a0\nExperience in Trading company is preferred but not a must\nCommunication level of Mandarin and English\n\nInterested parties please send your application via email to\u00a0Apply Now\u00a0or\u00a0kibi_tsang @persolhk.com.\u00a0For any inquiries, please do not hesitate to contact me at\u00a0(852) 2971-2513.\n\nPlease note that only short listed candidate will be notified.\n\nWe also have various job vacancies from our well-established clients in all kinds of fields, please feel free to contact us. We are always willing to give you support on your career development.\n\nOur company website:\u00a0http://www.persolhk.com\n\nAll information received will be treated in strict confidence and used for recruitment purpose only.", "employment_types": ["Full Time", "Permanent"], "selling_points": ["Stable company", "2 years of clerical working experience", "Communication level of Mandarin and English"], "locations": ["Eastern Area"], "categories": ["Manufacturing", "Others"], "post_time": "2022-01-17T09:39:32Z", "salary": {"currency": null, "max": null, "min": null, "period": "monthly", "term": null}, "salary_visible": false, "title_keywords": ["sales"], "responsibilities": ["delivery issues", "related documents", "invoice", "monitor", "delivery schedule", "liaise with"], "requirements": {"degrees": [], "majors": [], "languages": ["english", "mandarin"], "language_level": [], "hard_skills": [], "soft_skills": ["communication"], "languages_combined": [{"language": "english", "language_level": []}, {"language": "mandarin", "language_level": []}]}, "experience_required": {"duration": ["2 years"], "field": ["trading", "clerical"]}}, {"job_id": "100003009053361", "location_code": "hk", "company": "Safemark Alliance Security Co Limited", "job_title": "\u4e00\u822c\u884c\u653f\u52a9\u7406", "description": "\n\u8077\u8cac :\u4e00\u822c\u884c\u653f\u53ca\u79d8\u66f8\u5de5\u4f5c, \u63a5\u807d\u96fb\u8a71\n\n\u8cc7\u6b77 :\u4e2d\u4e94\u7a0b\u5ea6; 3\u5e74\u7d93\u9a57; \u826f\u597d\u7cb5\u8a9e; \u4e00\u822c\u666e\u901a\u8a71; \u4e00\u822c\u82f1\u8a9e; \u7565\u61c2\u8b80\u5beb\u4e2d\u6587; \u61c2\u8b80\u5beb\u82f1\u6587\n\n\u5f85\u9047 :\u6bcf\u6708$13,000 - $15,000, \u6709\u9280\u884c\u5047\u671f \u53ca\u914c\u60c5\u6027\u82b1\u7d05, \u661f\u671f\u4e00\u81f3\u4e94: \u4e0a\u53489\u6642\u81f3\u4e0b\u53486\u6642, \u6bcf\u9031\u5de5\u4f5c5\u5929, \u6bcf\u5929\u5de5\u4f5c 8 \u5c0f\u6642\n\n\u7533\u8acb\u9808\u77e5 :\u6c42\u8077\u8005\u53ef\u81f4\u96fb35719130\u8207\u5b89\u76df\u4fdd\u5b89\u6709\u9650\u516c\u53f8\u9673\u5973\u58eb\u806f\u7d61\u3002\n\n", "employment_types": ["Full Time"], "selling_points": [], "locations": ["Central"], "categories": ["Admin & HR", "Clerical / Admin Staff", "Manufacturing", "Others"], "post_time": "2022-01-17T06:51:41Z", "salary": {"currency": null, "max": null, "min": null, "period": "monthly", "term": null}, "salary_visible": false, "title_keywords": [], "responsibilities": [], "requirements": {"degrees": [], "majors": [], "languages": [], "language_level": [], "hard_skills": [], "soft_skills": [], "languages_combined": []}, "experience_required": {"duration": [], "field": []}}, {"job_id": "100003009055481", "location_code": "hk", "company": "Michael Page", "job_title": "Production and Material Planning Manager", "description": "Lead the team and oversee the functions of production planning and material control\n\nMaterial planning from control of material flow to optimisation of work processes and production capacity\n\nClient Details\n\nMy client is Hong Kong top manufacturer and is looking for Production and Materials Planning Manager\n\nDescription\n\nLead the team and oversee the functions of production planning and material control\nResponsible for capacity planning and overall production scheduling based on demand from forecast to ensure supply capacity copes with forecast\nMaterial planning from control of material flow to optimisation of work processes and production capacity\nEnsures materials are ordered and in stock to meet company requirements, while maintaining acceptable inventory levels\nControl expenses and production efficiency through proper manpower scheduling and production plan\nTo perform analysis on work flow and production efficiency, collect and maintain accurate records and support month-end reporting;\n\nProfile\n\nBachelor or above, major in industrial engineering, supply chain, or related discipline is preferable;\nOver 6 - 8 years of solid relevant working experiences in similar position in production and material planning\nDetail minded, multi-tasks, strong sense of responsibility\nGood command of communication skill\n\nJob Offer\n\nInterested applicant please send me your resume to Marcochong@michaelpage com hk OR you can contact Marco @ 52909990", "employment_types": ["Full Time", "Permanent"], "selling_points": ["Top Hong Kong Food manufacturer", "Manage production and material planning", "Attractive salary with great benefits"], "locations": ["Not Specified"], "categories": ["Manufacturing", "Manufacturing Management", "Production Planning / Control", "Others"], "post_time": "2022-01-18T02:38:36Z", "salary": {"currency": null, "max": null, "min": null, "period": "monthly", "term": null}, "salary_visible": false, "title_keywords": ["manager"], "responsibilities": ["reporting", "control", "maintaining", "inventory", "expenses", "production planning", "analysis", "month-end", "communication", "scheduling", "maintain", "contact", "forecast", "plan", "planning"], "requirements": {"degrees": ["bachelor"], "majors": ["engineering"], "languages": [], "language_level": [], "hard_skills": ["marco", "analysis"], "soft_skills": ["multi-tasks", "responsible", "sense of responsibility", "communication skill", "accurate"], "languages_combined": []}, "experience_required": {"duration": ["6 - 8 years"], "field": ["planning"]}}, {"job_id": "100003009053236", "location_code": "hk", "company": "Spin Master Toys Far East Limited", "job_title": "Business Analyst, Sourcing", "description": "1.0\u00a0 General:\nUsing data, statistical and analytical tools to generate supplier spend report, raw materials trend reports, productivity / savings calculations and analysis, dashboards and KPIs in support of the Souring & Procurement team and identification of sourcing opportunities. The position holder will continuously look for ways to improve efficiency and effectiveness of the tools and report utilize by the Sourcing and Procurement team to support the business strategy and goals.\n\n2.0\u00a0 Specific Responsibilities:\n\nAct as the subject matter expert for all supplier spend analysis and reporting including the process and tools.\nAssist and support the development of system and process to collect, analyse and interpret data, leverage existing data sources and tools (SAP).\nOwn and manage the historical spend database ensuring quality, accuracy, completeness and the availability of data.\nGenerate the supplier spend report including data-driven insights and recommendations.\nResearch and analyze material costs and labour cost analysis; rate analysis; and trending reports.\nSupport the identification of cost-saving opportunities through data analysis.\nDevelop and produce analysis and reporting for productivity / cost savings calculations, departmental dashboards, KPIs, targets / goals, efficiency and effectiveness measures, and other metrics.\nTake ownership for the generation and maintenance of the Productivity Tracker and Project Tracker, and ensure they are up-to-date, accurate and distributed appropriately.\nProvide general analytical support to the Sourcing team including:\n- Market analysis \u2013 perform market analysis comparing spend trends with published indices to identify opportunities\n- Other data driven / reporting projects and presentations as assigned\n\n\u00a03.0 Required Skill Set:\n\nCollaborative team players, self-motivated & initiative, able to work independently.\nExcellent interpersonal skill with the ability to work across multi-cultural environment.\nStrong data analysis skills to support the monitor set-up and result measurement.\nStrong in user communication and insight delivery / business planning.\nExpert proficiency working in Microsoft Office Suite including Outlook, Excel, PowerPoint and Word.\nProficiency in using advance statistical analysis method including Excel, SQL, Chart, Function, Pivot Table, etc.\nGood command of spoken & written English & Chinese.\n\n\u00a04.0 Required Qualifications & Experience:\n\nDegree Holder in business, finance or commerce.\n5 years\u2019 experience in data analysis and mining experience with a strong preference working with supplier / souring data.\nStrong working knowledge of SAP.\nGood knowledge of the Procure-to-Pay Process.\nExperience in developing presentations / decks to aid in communication and decision-making.", "employment_types": ["Full Time"], "selling_points": ["Business Analyst", "Sourcing", "SAP"], "locations": ["Tsim Sha Tsui"], "categories": ["Manufacturing", "Others", "Merchandising & Purchasing", "Procurement / Purchasing / Sourcing"], "post_time": "2022-01-17T06:30:30Z", "salary": {"currency": null, "max": null, "min": null, "period": "monthly", "term": null}, "salary_visible": false, "title_keywords": ["business analyst"], "responsibilities": ["reporting", "cost", "maintenance", "data", "analysis", "quality", "subject matter expert", "presentations", "develop", "data analysis", "market analysis", "reports", "database", "kpis", "report", "cost analysis", "costs", "analyse"], "requirements": {"degrees": ["degree holder"], "majors": ["finance", "business"], "languages": ["english", "chinese"], "language_level": ["good command"], "hard_skills": ["excel", "statistical analysis", "sap", "analysis", "pivot table", "word", "powerpoint", "presentations", "sql", "microsoft office suite", "outlook"], "soft_skills": ["self-motivated", "work independently", "collaborative", "interpersonal skill", "communication", "initiative"], "languages_combined": [{"language": "english", "language_level": ["good command"]}, {"language": "chinese", "language_level": ["good command"]}]}, "experience_required": {"duration": ["5 years"], "field": ["data analysis", "developing"]}}, {"job_id": "100003009052446", "location_code": "hk", "company": "AVT Design Architects Limited", "job_title": "Receptionist and Administration Clerk", "description": "Responsibilities\u00a0\u00a0\n\n\nHandle telephone calls, reception enquiries and guest greeting in a professional manner\nProvide clerical & administrative support including meeting room reservation, courier & mailing arrangement, flight & hotel bookings, management of warehouses, procurement, stationery and supplies,\u00a0etc\nCo-ordinate with internal & external parties including cleaning, maintenance for offices\nPerform other ad-hoc tasks as assigned\n\nRequirements\n\n\nForm 5 / DSE graduated or above\nPositive attitude, good interpersonal skills, telephone manner and communication skills\nCheerful, stable, well organized, detail-minded, self-motivated and able to work independently\nProficiency in MS Word, Excel, PowerPoint, English & Chinese Word Processing\nFluent in English, Chinese and Putonghua will be an advantage\nImmediate available preferred\n\n\u00a0\nBenefit\n\n\nMedical allowance\nFive-Day Work week\nBirthday Leave\u00a0\n\nPlease send us your application with current salary, expected salary and availability by clicking \"APPLY NOW\".\n\nAll personal information submitted to us is kept private and confidential and will be used for the recruitment purpose only.\u00a0", "employment_types": ["Full Time", "Permanent"], "selling_points": ["Detail-minded", "5 Days Work", "Initiative, Proactive"], "locations": ["Lai Chi Kok"], "categories": ["Admin & HR", "Others", "Manufacturing", "General / Production Workers", "Others"], "post_time": "2022-01-17T03:03:41Z", "salary": {"currency": null, "max": null, "min": null, "period": "monthly", "term": null}, "salary_visible": false, "title_keywords": ["receptionist", "clerk"], "responsibilities": ["management", "maintenance", "administrative support", "co-ordinate with", "ad-hoc tasks", "external parties", "professional manner", "stationery", "cleaning"], "requirements": {"degrees": ["form 5", "dse"], "majors": [], "languages": ["putonghua", "english", "chinese"], "language_level": ["advantage", "proficiency", "fluent"], "hard_skills": ["excel", "chinese word processing", "powerpoint", "ms word"], "soft_skills": ["detail-minded", "communication skills", "self-motivated", "cheerful", "work independently", "well organized", "positive attitude", "interpersonal skills", "stable", "telephone manner"], "languages_combined": [{"language": "putonghua", "language_level": ["advantage", "fluent"]}, {"language": "english", "language_level": ["advantage", "proficiency", "fluent"]}, {"language": "chinese", "language_level": ["advantage", "proficiency", "fluent"]}]}, "experience_required": {"duration": [], "field": []}}, {"job_id": "100003009044038", "location_code": "hk", "company": "\u9999\u6e2f\u5370\u9214\u6709\u9650\u516c\u53f8", "job_title": "\u751f\u7522\u90e8 - \u7d44\u9577/\u52a9\u7406\u7d44\u9577(\u8f2a\u73ed) (Supervisor/ Assistant Supervisor (On shift))", "description": "\u4e2d\u4e03\u6216\u4ee5\u4e0a\u5b78\u6b77\n\n\u9808\u5177\u4e09\u5e74\u6216\u4ee5\u4e0a\u5370\u5237\u3001\u54c1\u8cea\u63a7\u5236\u53ca\u6aa2\u67e5\u7b49\u5de5\u4f5c\u7d93\u9a57\n\u8ca0\u8cac\u5370\u5237\u6a5f\u64cd\u4f5c\u3001\u6210\u54c1\u6aa2\u6e2c\u6a5f\u3001\u88c1\u5207\u53ca\u5305\u88dd\u64cd\u4f5c\n\u5177\u54c1\u8cea\u63a7\u5236\u6982\u5ff5\u8a8d\u8b58\n\u9700\u61c9\u4ed8\u4e00\u822c\u9ad4\u529b\u52de\u52d5\u5de5\u4f5c\n\u5177\u9818\u5c0e\u624d\u80fd\u3001\u8cac\u4efb\u5fc3\u53ca\u826f\u597d\u6e9d\u901a\u6280\u5de7\n\u80fd\u66f8\u5beb\u4e2d\u82f1\u6587\u53ca\u64cd\u826f\u597d\u5ee3\u6771\u8a71\u3001\u82f1\u8a9e\u53ca\u666e\u901a\u8a71\n\u5177\u6709\u57fa\u672c\u96fb\u8166\u61c9\u7528\u77e5\u8b58\u53caISO\u7ba1\u7406\u7cfb\u7d71\u7d93\u9a57\n\u6bcf\u661f\u671f\u4e94\u5929\u5de5\u4f5c\n(\u82e5\u5b78\u6b77\u6216\u7d93\u9a57\u8f03\u5c11\u8005\u4ea6\u53ef\u7533\u8acb)\n\n\u672c\u516c\u53f8\u63d0\u4f9b\u512a\u539a\u85aa\u916c\u53ca\u798f\u5229\uff0c\u5305\u62ec\u5e74\u7d42\u916c\u91d1\u3001\u91ab\u7642\u53ca\u4eba\u58fd\u4fdd\u96aa\u3001\u81b3\u98df\u53ca\u4ea4\u901a\u6d25\u8cbc\u7b49\uff0c\u52de\u5de5\u5047\u671f\u3002\u6709\u610f\u8005\u8acb\u5c07\u500b\u4eba\u5c65\u6b77\u3001\u5de5\u4f5c\u7d93\u9a57\u3001\u806f\u7d61\u5730\u5740\u53ca\u96fb\u8a71\uff0c\u51fd\u5bc4\u65b0\u754c\u5927\u57d4\u5de5\u696d\u90a8\u5927\u76db\u88572-4\u865f\u4eba\u4e8b\u53ca\u884c\u653f\u90e8\u6536\u6216\u6309\"APPLY NOW\"\u63d0\u4ea4\u7533\u8acb\u6216\u50b3\u771f\u81f32664 4882\u3002\n\n\n(\u7533\u8acb\u4eba\u6240\u63d0\u4f9b\u7684\u8cc7\u6599\u5c07\u4e88\u4fdd\u5bc6\u53ca\u53ea\u4f9b\u7533\u8acb\u6709\u95dc\u8077\u4f4d\u7528\u9014)", "employment_types": ["Full Time"], "selling_points": [], "locations": ["Tai Po Area"], "categories": ["Manufacturing", "Others", "Printing", "Quality Assurance, Control & Testing / ISO"], "post_time": "2022-01-13T02:52:56Z", "salary": {"currency": null, "max": null, "min": null, "period": "monthly", "term": null}, "salary_visible": false, "title_keywords": ["assistant supervisor", "supervisor"], "responsibilities": [], "requirements": {"degrees": [], "majors": [], "languages": [], "language_level": [], "hard_skills": [], "soft_skills": [], "languages_combined": []}, "experience_required": {"duration": [], "field": []}}, {"job_id": "100003009044048", "location_code": "hk", "company": "\u9999\u6e2f\u5370\u9214\u6709\u9650\u516c\u53f8", "job_title": "\u8cea\u91cf\u5be9\u67e5\u54e1 (Quality Examiner)", "description": "\u4e2d\u516d\u7a0b\u5ea6\u6216\u4ee5\u4e0a (\u6301\u5370\u5237\u6587\u6191 / \u5316\u9a57\u6587\u6191\u512a\u5148\u8003\u616e)\n\n\u9808\u5177\u6700\u5c11\u5169\u5e74\u8cea\u91cf\u5be9\u67e5/\u5be6\u9a57\u5ba4/\u5ee0\u623f\u5de5\u4f5c\u7d93\u9a57\n\u8ca0\u8cac\u65e5\u5e38\u8cea\u91cf\u5be9\u67e5/\u5316\u9a57/\u5100\u5668\u6821\u6e96\u53ca\u4fdd\u990a\u5de5\u4f5c\u7b49\n\u8ca0\u8cac\u64b0\u5beb\u6aa2\u6e2c\u5831\u544a\n\u6709\u8cac\u4efb\u5fc3\u548c\u826f\u597d\u6e9d\u901a\u6280\u5de7\n\u80fd\u66f8\u5beb\u4e2d\u82f1\u6587\u53ca\u64cd\u5ee3\u6771\u8a71\u3001\u57fa\u672c\u82f1\u8a9e\u53ca\u666e\u901a\u8a71\n\u5177\u6709\u826f\u597d\u96fb\u8166\u61c9\u7528\u77e5\u8b58\n\u9700\u8f2a\u73ed\u5de5\u4f5c\n\n(\u6b61\u8fce\u65b0\u7562\u696d\u4eba\u58eb\u7533\u8acb)\n\n\u00a0\u672c\u516c\u53f8\u63d0\u4f9b\u512a\u539a\u85aa\u916c\u53ca\u798f\u5229\uff0c\u5305\u62ec\u5e74\u7d42\u916c\u91d1\u3001\u91ab\u7642\u53ca\u4eba\u58fd\u4fdd\u96aa\u3001\u81b3\u98df\u53ca\u4ea4\u901a\u6d25\u8cbc\u7b49\uff0c\u52de\u5de5\u5047\u671f\u3002\u6709\u610f\u8005\u8acb\u5c07\u500b\u4eba\u5c65\u6b77\u3001\u5de5\u4f5c\u7d93\u9a57\u3001\u806f\u7d61\u5730\u5740\u53ca\u96fb\u8a71\uff0c\u51fd\u5bc4\u65b0\u754c\u5927\u57d4\u5de5\u696d\u90a8\u5927\u76db\u88572-4\u865f\u4eba\u4e8b\u53ca\u884c\u653f\u90e8\u6536\u6216\u6309\"APPLY NOW\"\u63d0\u4ea4\u7533\u8acb\u6216\u50b3\u771f\u81f32664 4882\u3002\n\n(\u7533\u8acb\u4eba\u6240\u63d0\u4f9b\u7684\u8cc7\u6599\u5c07\u4e88\u4fdd\u5bc6\u53ca\u53ea\u4f9b\u7533\u8acb\u6709\u95dc\u8077\u4f4d\u7528\u9014)\n\n*(\u6b61\u8fce\u65b0\u7562\u696d\u4eba\u58eb\u7533\u8acb)", "employment_types": ["Full Time"], "selling_points": [], "locations": ["Tai Po Area"], "categories": ["Manufacturing", "Others", "Printing", "Quality Assurance, Control & Testing / ISO"], "post_time": "2022-01-13T02:54:35Z", "salary": {"currency": null, "max": null, "min": null, "period": "monthly", "term": null}, "salary_visible": false, "title_keywords": [], "responsibilities": [], "requirements": {"degrees": [], "majors": [], "languages": [], "language_level": [], "hard_skills": [], "soft_skills": [], "languages_combined": []}, "experience_required": {"duration": [], "field": []}}, {"job_id": "100003009052381", "location_code": "hk", "company": "Simatelex Manufactory Co., Ltd.", "job_title": "Production Manager (Shenzhen Stationed)", "description": "Responsible for leading & managing the production engineering team for jig/fixture design, machine maintenance and overseeing the general operation of the department of a factory with over 1,000 staff.\n\nDiploma or above in Production, Manufacturing, Mechanical, Industrial Engineering or related disciplines\n\nAt least 7 years experience at managerial level in manufacturing industry\n\nGood at manufacturing technique of electrical household appliances\n\nWith experience in ISO9001, lean manufacturing and 6-Sigma is preferable\nAggressive, self-motivated, attentive to details and highly quality-conscious\n\nGood command of both English and Chinese\nCandidates with less experience will be considered as Assistant\u00a0Production Manager (Shenzhen Stationed)\n\nWe offer\u00a0attractive remuneration package including 5-day work, bank holidays, group medical insurance etc to the right candidates. Interested parties please send your full resume including expected salary and date available to Human Resources Department by clicking \"Apply Now\" button.\n\nFor more details, please visit our web-site at www.simatelex.com.hk", "employment_types": ["Full Time", "Permanent"], "selling_points": [], "locations": ["Others - China"], "categories": ["Engineering", "Manufacturing & Production", "Manufacturing", "Manufacturing Management", "Others"], "post_time": "2022-01-17T02:54:26Z", "salary": {"currency": null, "max": null, "min": null, "period": null, "term": null}, "salary_visible": false, "title_keywords": ["production manager"], "responsibilities": ["maintenance", "quality", "design"], "requirements": {"degrees": ["diploma or above"], "majors": ["related disciplines", "manufacturing", "engineering"], "languages": ["english", "chinese"], "language_level": ["good command"], "hard_skills": ["lean", "maintenance"], "soft_skills": ["self-motivated", "attentive to details", "responsible"], "languages_combined": [{"language": "english", "language_level": ["good command"]}, {"language": "chinese", "language_level": ["good command"]}]}, "experience_required": {"duration": ["at least 7 years"], "field": ["managerial", "manufacturing", "manufacturing industry"]}}, {"job_id": "100003009044732", "location_code": "hk", "company": "Pet-Link Company Limited", "job_title": "\u5bf5\u7269\u98df\u54c1\u751f\u7522\u54e1 (\u5927\u57d4)", "description": "\n\u8077\u8cac :\u8ca0\u8cac\u4e00\u822c\u5bf5\u7269\u98df\u54c1\u751f\u7522\u5de5\u4f5c, \u5305\u62ec\u642c\u904b\u539f\u6750\u6599, \u64cd\u4f5c\u751f\u7522\u7dda, \u5305\u88dd\u53ca\u7c21\u55ae\u6e05\u6f54\u7b49\u3002\n\n\u8cc7\u6b77 :\u6c92\u6709\u5b78\u6b77\u8981\u6c42; 3\u5e74\u7d93\u9a57; \u826f\u597d\u7cb5\u8a9e; \u61c2\u8b80\u5beb\u4e2d\u6587; \u5fc5\u9808\u6709\u9eb5\u5305\u70d8\u7119\u53ca\u751f\u7522\u7d93\u9a57\uff0c\u6709\u81a8\u5316\u6280\u8853\u8005\u66f4\u4f73\n\n\u5f85\u9047 :\u6bcf\u6708$14,000 - $18,000, \u6709\u6bcf\u6708\u52e4\u5de5\u734e\u91d1$500, \u9280\u884c\u5047\u671f, \u914c\u60c5\u6027\u82b1\u7d05, \u91ab\u7642\u798f\u5229 \u53ca\u8868\u73fe\u734e\u91d1, \u661f\u671f\u4e00\u81f3\u4e94: \u4e0a\u53489\u6642\u81f3\u4e0b\u53486\u6642, \u6bcf\u9031\u5de5\u4f5c5\u5929\u3002\n\n\u7533\u8acb\u9808\u77e5 :\u6c42\u8077\u8005\u53ef\u81f4\u96fb67342960\u8207\u5bf5\u7269\u5e79\u7dda\u6709\u9650\u516c\u53f8\u6c5f\u5c0f\u59d0\u806f\u7d61\uff0c\u6216\u6309\u4ee5\u4e0b\"\nApply Now\"\u5448\u7c21\u55ae\u5c65\u6b77\u7533\u8acb\u3002\n\n\u5bf5\u54c1\u5e79\u7dda\u7db2\u5740\uff1ahttp://www.pet-link.com", "employment_types": ["Full Time"], "selling_points": [], "locations": ["Tai Po Area"], "categories": ["Hospitality / F & B", "Others", "Manufacturing", "Others", "Others", "Others"], "post_time": "2022-01-13T05:55:00Z", "salary": {"currency": null, "max": null, "min": null, "period": "monthly", "term": null}, "salary_visible": false, "title_keywords": [], "responsibilities": [], "requirements": {"degrees": [], "majors": [], "languages": [], "language_level": [], "hard_skills": [], "soft_skills": [], "languages_combined": []}, "experience_required": {"duration": [], "field": []}}, {"job_id": "100003009052288", "location_code": "hk", "company": "Eu Yan Sang (HK) Ltd", "job_title": "\u5305\u88dd\u54e1(\u5143\u6717\u5340)", "description": "\u884c\u696d :\u5176\u4ed6\u88fd\u9020\u696d\n\u8077\u8cac :\u8ca0\u8cac\u5305\u88dd\u53ca\u57f7\u6574\u8ca8\u54c1, \u9700\u642c\u904b\u91cd\u7269\n\u8cc7\u6b77 :\u6c92\u6709\u5b78\u6b77\u8981\u6c42; \u826f\u597d\u7cb5\u8a9e; \u61c2\u8b80\u5beb\u4e2d\u6587; \u53ef\u5373\u6642\u4e0a\u73ed\u512a\u5148\n\u5f85\u9047 :\u6bcf\u5c0f\u6642$50.00, \u6709\u81b3\u98df\u6d25\u8cbc \u53ca\u7a7f\u68ad\u5df4\u58eb\u670d\u52d9, \u661f\u671f\u4e00\u81f3\u4e94: \u4e0a\u53489\u6642\u81f3\u4e0b\u53486\u6642, \u6bcf\u9031\u5de5\u4f5c5\u5929, \u6bcf\u5929\u5de5\u4f5c 8 \u5c0f\u6642\n\u7533\u8acb\u9808\u77e5 :\u6c42\u8077\u8005\u53ef\u81f4\u96fb25818386\u8207\u4f59\u4ec1\u751f(\u9999\u6e2f)\u6709\u9650\u516c\u53f8\u7f85\u5c0f\u59d0\u806f\u7d61\u3002", "employment_types": ["Full Time"], "selling_points": [], "locations": ["Yuen Long"], "categories": ["Manufacturing", "General / Production Workers", "Others"], "post_time": "2022-01-17T02:39:14Z", "salary": {"currency": null, "max": null, "min": null, "period": "monthly", "term": null}, "salary_visible": false, "title_keywords": [], "responsibilities": [], "requirements": {"degrees": [], "majors": [], "languages": [], "language_level": [], "hard_skills": [], "soft_skills": [], "languages_combined": []}, "experience_required": {"duration": [], "field": []}}, {"job_id": "100003009050119", "location_code": "hk", "company": "Lucky Consumer Products Limited", "job_title": "\u63a1\u8cfc/\u751f\u7522\u63a7\u5236\u6587\u54e1", "description": "\u53e3\u7f69\u5de5\u5ee0\u8058\u8acb\n\n\u00a0\u5de5\u4f5c\u5730\u9ede :\u00a0\u00a0\u9999\u6e2f\u8475\u6d8c\n\n\u8077\u8cac:\n\u8ca0\u8cac\u806f\u7d61\u4f9b\u61c9\u5546\u4ee5\u9032\u884c\u5831\u50f9\u53ca\u683c\u50f9\uff0c\u5b89\u6392\u53ca\u8ddf\u9032\u7269\u6599\u63a1\u8cfc\u8a02\u55ae\n\u8ca0\u8cac\u5eab\u5b58\u7ba1\u7406\u53ca\u66f4\u65b0\u5eab\u5b58\u8a18\u9304 \uff0c\u6536\u8ca8\u51fa\u8ca8\u53ca\u9a57\u8ca8\n\u65e5\u5e38\u6587\u66f8\u5de5\u4f5c\u53ca\u8a02\u55ae\u8cc7\u6599\u8f38\u5165\u7b49\n\n\u8cc7\u6b77\uff1a\n\u2022 F.5 \u6216 DSE \u4ee5\u4e0a\u7a0b\u5ea6\n\u2022 1 - 2 \u5e74\u6587\u66f8\u7d93\u9a57\n\u2022 \u826f\u597d\u7684\u6e9d\u901a\u80fd\u529b\u548c\u6642\u9593\u7ba1\u7406\n\u2022 \u826f\u597d\u7684\u96fb\u8166\u77e5\u8b58 (Excel, Word, \u4e2d\u3001\u82f1\u6587\u5b57\u8655\u7406)\n\u2022 \u6709\u8cac\u4efb\u5fc3\u3001\u5b88\u6642\u3001\u8655\u4e8b\u7d30\u5fc3\n\nInterested parties should send your CV, expected salary and availability by email to us.\n\nPersonal data provided by applicants will be used strictly for recruitment purpose only.", "employment_types": ["Full Time", "Permanent"], "selling_points": [], "locations": ["Kwai Hing"], "categories": ["Manufacturing", "Others"], "post_time": "2022-01-14T09:48:32Z", "salary": {"currency": null, "max": null, "min": null, "period": "monthly", "term": null}, "salary_visible": false, "title_keywords": [], "responsibilities": [], "requirements": {"degrees": ["dse"], "majors": [], "languages": [], "language_level": [], "hard_skills": ["excel", "word"], "soft_skills": [], "languages_combined": []}, "experience_required": {"duration": [], "field": []}}, {"job_id": "100003009053070", "location_code": "hk", "company": "Li Chung Shing Tong (Holdings) Limited", "job_title": "Assistant Engineer", "description": "\u00a0Key roles and Responsibilities:\nResponsible for engineering activities, include machinery maintenance, repairing, installation and testing.\nPrepare machinery documentation in a GMP Pharmaceutical facility.\nMonitor and review daily operations of building services system and manufacturing machineries.\nAssist in negotiation and coordination with contractors, vendors and consultants.\nPerform ad-hoc duties as required.\n\nQualifications and Experience:\n\nBachelor's Degree in Engineering/Mechanical Engineering or related.\n2-3 years relevant experience in E & M service and machinery maintenance.\nHolder of\u00a0Registered Electrical Worker Certificate (Grade A) is preferred\nExperience in Practice of Occupational Safety and Health is preferred\nExperience in Good Manufacturing Practice and Cleanroom operation are preferred.\nGood communication and problem-solving skill\nProficient in MS Office and AutoCAD\nProficiency in both spoken and written English and Chinese\nHow to Apply\nYou are invited to send in your application and CV stating your latest and expected salary\u00a0 by Clicking \"Apply Now\". \u00a0\nLi Chung Shing Tong (Holdings) Limited is an equal opportunities employer. The information provided will be treated in strict confidence and used only for consideration of application for relevant/similar post(s).\u00a0 All personal data of unsuccessful applicants will be destroyed within 6 months.", "employment_types": ["Full Time"], "selling_points": [], "locations": ["Tai Po Area"], "categories": ["Engineering", "Manufacturing & Production", "Manufacturing", "Others", "Medical Services", "Pharmaceutical"], "post_time": "2022-01-17T05:34:57Z", "salary": {"currency": null, "max": null, "min": null, "period": "monthly", "term": null}, "salary_visible": false, "title_keywords": ["assistant engineer"], "responsibilities": ["installation", "maintenance", "review", "monitor", "coordination with", "testing", "communication", "daily operations", "ad-hoc duties", "documentation", "personal data"], "requirements": {"degrees": ["certificate", "degree", "bachelor"], "majors": ["engineering", "mechanical engineering"], "languages": ["english", "chinese"], "language_level": ["proficiency"], "hard_skills": ["maintenance", "problem-solving", "documentation", "ms office", "autocad"], "soft_skills": ["confidence", "negotiation", "responsible", "problem-solving", "communication", "coordination", "ad-hoc duties"], "languages_combined": [{"language": "english", "language_level": ["proficiency"]}, {"language": "chinese", "language_level": ["proficiency"]}]}, "experience_required": {"duration": ["2-3 years"], "field": ["operation", "manufacturing", "relevant experience", "maintenance"]}}, {"job_id": "100003009046801", "location_code": "hk", "company": "Wai Yuen Tong Medicine Co Ltd", "job_title": "\u751f\u7522\u54e1", "description": "\n\u8077\u8cac:\n\u8ca0\u8cac\u5354\u52a9\u751f\u7522\u53ca\u5305\u88dd\u7522\u54c1(\u85e5\u6750\u534a\u6210\u54c1\u53ca\u6210\u54c1)\n\u2022 \u6e05\u6d17\u7528\u5177\u53ca\u6e05\u6f54\u7b49\u5de5\u4f5c\n\u8cc7\u6b77:\n\u2022 \u5c0f\u516d\u7a0b\u5ea6\u6709\u8cac\u4efb\u611f;\n\u2022 \u9700\u9ad4\u529b\u52de\u52d5\n\u2022 \u6709\u76f8\u95dc\u7d93\u9a57\u512a\u5148\n\u5de5\u4f5c\u5730\u9ede:\n\u2022 \u5143\u6717\u5de5\u696d\u90a8\n\u6709\u610f\u61c9\u5fb5\u8005\u8acb\u81f4\u96fb\u806f\u7d61\u4eba\u529b\u8cc7\u6e90\u90e8\u9127\u5c0f\u59d0\uff0c\u96fb\u8a71\uff1a3526-4422\n\n", "employment_types": ["Full Time"], "selling_points": ["\u8ca0\u8cac\u5354\u52a9\u751f\u7522\u53ca\u5305\u88dd\u7522\u54c1(\u85e5\u6750\u534a\u6210\u54c1\u53ca\u6210\u54c1)", "\u6e05\u6d17\u7528\u5177\u53ca\u6e05\u6f54\u7b49\u5de5\u4f5c", "\u5c0f\u516d\u7a0b\u5ea6\u6709\u8cac\u4efb\u611f;"], "locations": ["Yuen Long"], "categories": ["Manufacturing", "General / Production Workers", "Others", "Others", "Others"], "post_time": "2022-01-14T01:13:37Z", "salary": {"currency": null, "max": null, "min": null, "period": "monthly", "term": null}, "salary_visible": false, "title_keywords": [], "responsibilities": [], "requirements": {"degrees": [], "majors": [], "languages": [], "language_level": [], "hard_skills": [], "soft_skills": [], "languages_combined": []}, "experience_required": {"duration": [], "field": []}}, {"job_id": "100003009046876", "location_code": "hk", "company": "SYNCO (H.K.) Ltd", "job_title": "\u54c1\u8cea\u4fdd\u8b49\u52a9\u7406(\u517c\u8077) QA Assistant (Part-Time)", "description": "\u5de5\u4f5c\u8077\u8cac:\n\n\u76e3\u6e2c\u751f\u7522\u6d41\u7a0b\u53ca\u7522\u54c1\u8cea\u91cf\n\u586b\u5beb\u76f8\u95dc\u8a18\u9304\u53ca\u4e00\u822c\u6587\u66f8\u5de5\u4f5c\n\n\u5165\u8077\u689d\u4ef6:\n\n\u4e2d\u4e94\u7a0b\u5ea6\n\u61c2\u8b80\u5beb\u4e2d\u6587\n\u7565\u61c2\u8b80\u5beb\u82f1\u6587\n\u5177\u98df\u54c1\u88fd\u9020\u696d\u6216GMP\u7d93\u9a57\u512a\u5148\n\u4e94\u5929\u5de5\u4f5c, \u65e9\u66f4 (\u5de5\u4f5c\u6642\u9593: 8:30-13:00)\n\nJob responsibilities:\n\nPerform routine inspection on various stages of the production line to implement GMP policy\nAssist in maintaining the documentation system\nAssist in other ad-hoc project and other QA-related duties\n\nRequirements:\n\nF.5 or above\nAttention to details, hard-working and being able to work under pressure;\nStrong communication skill\nMinimum of 2\u00a0years relevant experience;\nExperience in\u00a0pharmaceutical\u00a0is preferred;\n5 days work week, morning Shift (Working time: 8:30-13:00)\n\n\n\u6709\u610f\u8005\u8acb\u5c07\u5c65\u6b77\u53ca\u671f\u671b\u5f85\u9047\u3001\u53ef\u5230\u4efb\u65e5\u671f\u6309APPLY NOW\u7533\u8acb\u3002\n\n\u6240\u6536\u96c6\u7684\u500b\u4eba\u8cc7\u6599\u53ea\u9069\u7528\u65bc\u62db\u8058\u53ca\u7504\u9078\u7528\u9014\u3002\u5728\u4f7f\u7528\u6c42\u8077\u8005\u6240\u63d0\u4f9b\u7684\u500b\u4eba\u8cc7\u6599\u6642\uff0c\u50f1\u4e3b\u6703\u56b4\u683c\u9075\u5b88\u5176\u500b\u4eba\u8cc7\u6599\u653f\u7b56\u7684\u898f\u5b9a\u3002\u6839\u64da<<\u500b\u4eba\u8cc7\u6599(\u79c1\u4eba)\u689d\u4f8b>>\u4f60\u6709\u6b0a\u8981\u6c42\u67e5\u95b1\u6216\u66f4\u6539\u4f60\u7684\u500b\u4eba\u8cc7\u6599\u3002\u5982\u4f60\u6b32\u884c\u4f7f\u9019\u9805\u6b0a\u5229\uff0c\u8acb\u5c07\u4f60\u7684\u8981\u6c42\u4ee5\u66f8\u9762\u5411\u4eba\u529b\u8cc7\u6e90\u90e8\u63d0\u51fa\u3002\n\nWe offer attractive remuneration package including medical scheme, discretionary year-end bonus etc. Interested parties please send full resume with salary expectation and availability by click \"Apply Now\". Only shortlisted candidates will be interviewed.\n\nSynco (H.K.) Ltd\u00a0is an Equal Opportunities Employer. Personal data provided by job applicants will be used strictly in accordance with our personal data policy and for recruitment purposes only. We aim to respond to successful applicants within 8 weeks and related information will be kept in our file for up to 12 months for other suitable vacancies in our organization and thereafter destroyed.\u00a0", "employment_types": ["Part Time"], "selling_points": [], "locations": ["Tai Po Area"], "categories": ["Manufacturing", "Others", "Medical Services", "Pharmaceutical", "Quality Assurance, Control & Testing / ISO"], "post_time": "2022-01-14T01:33:41Z", "salary": {"currency": null, "max": null, "min": null, "period": null, "term": null}, "salary_visible": false, "title_keywords": ["qa assistant"], "responsibilities": ["documentation", "ad-hoc", "maintaining", "inspection"], "requirements": {"degrees": [], "majors": [], "languages": [], "language_level": [], "hard_skills": [], "soft_skills": ["communication skill", "hard-working", "attention to details", "work under pressure"], "languages_combined": []}, "experience_required": {"duration": ["minimum of 2 years"], "field": ["pharmaceutical", "relevant experience"]}}, {"job_id": "100003009051963", "location_code": "hk", "company": "OPC Manufacturing Ltd", "job_title": "Environmental, Health & Safety (EHS) Officer", "description": "Responsibilities:\n\nMonitor the Environmental, Health & Safety (EHS) issues of the factory to ensure all works are up to the statutory requirements\u00a0\nMonitor the safety performance of workers and to provide safety advice to management team from time to time\nLiaise and coordinate with the team to evaluate safety risk and operation procedures\nPrepare safety report, meeting minutes and safety promotion\nConduct accident investigation\nPrepare materials/ documentations for internal and external Safety Audit and ISO Certification\nAny other duties assigned by Senior Officer or the Department\n\nRequirements:\n\nHigher Diploma or above in Environmental, Health & Safety (EHS) studies with at least 1-year experience\nKnowledge in safety management system and ISO 14001 preferable\nGood organization and communication skills\nGood command of written and spoken English and Chinese (Cantonese & Mandarin)\nProficient in MS Office applications & Chinese Word Processing\n\n\u00a0Our\u00a0Offer:\n\nAttractive remuneration package including 12 \u2013 14 days annual leave, public holiday, overtime allowance, medical scheme, life insurance, training subsidy, etc.\nShuttle buses available between Kowloon Tong, Tsuen Wan, Shatin, Tai Po, Tai Wo, Sheung Shui, Fanling, Tuen Mun, Yuen Long and HK Office\n\nInterested parties please send your full resume to us with your recent and expected salary by clicking \"Apply Now\".\n\n\u00a0(Personal data provided by job applicants will be used for recruitment purpose only)", "employment_types": ["Full Time", "Permanent"], "selling_points": ["EHS duty with exposure to manufactory industry", "relevant study in EHS with 1 year experience", "Tai Po industrial estate w/ shuttle bus transport"], "locations": ["Tai Po Area"], "categories": ["Engineering", "Electrical / Electronics", "Manufacturing & Production", "Manufacturing", "Others"], "post_time": "2022-01-17T01:39:19Z", "salary": {"currency": null, "max": null, "min": null, "period": "monthly", "term": null}, "salary_visible": false, "title_keywords": ["officer"], "responsibilities": ["liaise", "management team", "any other duties", "monitor", "coordinate with", "procedures", "investigation", "evaluate", "statutory requirements", "audit", "report"], "requirements": {"degrees": ["higher diploma or above"], "majors": [], "languages": ["cantonese", "english", "chinese", "mandarin"], "language_level": ["good command", "proficient"], "hard_skills": ["wan", "chinese word processing", "scheme", "ms office"], "soft_skills": ["communication skills"], "languages_combined": [{"language": "cantonese", "language_level": ["good command"]}, {"language": "english", "language_level": ["good command"]}, {"language": "chinese", "language_level": ["good command", "proficient"]}, {"language": "mandarin", "language_level": ["good command"]}]}, "experience_required": {"duration": ["at least 1-year"], "field": ["environmental"]}}, {"job_id": "100003009049682", "location_code": "hk", "company": "TDF Asia Limited", "job_title": "Project Coordinator (Manufacturing for Props, Window Display, Pop-up Store)", "description": "Responsibilities\n\u00a0\u00a0\u00a0\u00a0\u00a0 coordinate multiple VM props & window display production projects\u00a0\n\u00a0\u00a0\u00a0\u00a0\u00a0 Assist to keep track on the project performance\u00a0\u00a0\n\u00a0\u00a0\u00a0\u00a0\u00a0 Handle ad hoc duties as assigned\nRequirements:\n\u00a0\u00a0\u00a0\u00a0\u00a0 Higher diploma holder or above, degree in Marketing, Event Management, Communication, Business Administration is preferable.\n\u00a0\u00a0\u00a0\u00a0\u00a0 At least 3 years in project management of Events & Exhibition, VM industries experiences.\n\u00a0\u00a0\u00a0\u00a0\u00a0 candidates with more experience will be considered for the position of Assistant Manager.\n\u00a0\u00a0\u00a0\u00a0\u00a0 Detailed - minded, independent & presentable; able to prioritize job tasks in tight timeline & organized manner.\n\u00a0\u00a0\u00a0\u00a0\u00a0 Good verbal and written communication in English, Cantonese, and Mandarin.\n\u00a0\u00a0\u00a0\u00a0\u00a0 Travelling is required.\n\u00a0\u00a0\u00a0\u00a0\u00a0 Office Location: Sham Shui Po\n\nWe offer:\n\n\u00a0\u00a0\u00a0\u00a0\u00a0 Birthday leave\n\u00a0\u00a0\u00a0\u00a0\u00a0 Performance bonus\n\nInterested candidates please send your full resume with expected salary and date of availability by \"Apply Now \". Consideration of applications will continue until the position is filled. Applications will be treated in strict confidential. Personal data collected will be used for recruitment purpose only", "employment_types": ["Full Time", "Permanent"], "selling_points": [], "locations": ["Sham Shui Po"], "categories": ["Manufacturing", "Others", "Marketing / Public Relations", "Marketing - General / Support", "Merchandising & Purchasing", "Others"], "post_time": "2022-01-14T09:11:55Z", "salary": {"currency": null, "max": null, "min": null, "period": "monthly", "term": null}, "salary_visible": false, "title_keywords": ["project coordinator"], "responsibilities": ["coordinate", "ad hoc duties"], "requirements": {"degrees": ["degree", "higher diploma holder"], "majors": ["marketing", "business administration"], "languages": ["cantonese", "english", "mandarin"], "language_level": ["good"], "hard_skills": ["project management"], "soft_skills": ["organized", "independent", "able to prioritize", "presentable", "communication", "project management", "detailed"], "languages_combined": [{"language": "cantonese", "language_level": ["good"]}, {"language": "english", "language_level": ["good"]}, {"language": "mandarin", "language_level": ["good"]}]}, "experience_required": {"duration": ["at least 3 years"], "field": ["project management"]}}, {"job_id": "100003009049622", "location_code": "hk", "company": "Nakajima Suisan (HK) Co., Limited", "job_title": "\u98df\u54c1\u5de5\u5834\u751f\u7522\u54e1**", "description": "\n\u8077\u8cac :\u9ad4\u529b\u52de\u52d5\u5de5\u4f5c\uff1b\u5354\u52a9\u642c\u904b\uff1b\u64cd\u4f5c\u98ef\u6a5f\uff1b\u8655\u7406\u7c73\u3001\u918b\u7b49\u539f\u6750\u6599\uff1b\u6574\u7406\u98ef\u7bb1\n\n\u8cc7\u6b77 :\u6c92\u6709\u5b78\u6b77\u8981\u6c42; \u4e00\u822c\u7cb5\u8a9e; \u7565\u61c2\u8b80\u5beb\u4e2d\u6587; \u5de5\u4f5c\u904e\u7a0b\u8f03\u591a\u9ad4\u529b\u52de\u52d5\n\n\u5f85\u9047 :\u6bcf\u6708$12,150, \u6709\u65b0\u4eba\u734e, \u4ea4\u901a\u6d25\u8cbc, \u8d85\u6642\u5de5\u4f5c\u6d25\u8cbc, \u96d9\u7ce7, \u52e4\u5de5\u734e\u91d1, \u914c\u60c5\u6027\u82b1\u7d05 \u53ca\u81b3\u98df\u6d25\u8cbc, \u4e0a\u53487\u6642\u534a\u81f3\u4e0b\u53485\u6642\u534a, \u6bcf\u9031\u5de5\u4f5c6\u5929,\u8f2a\u4f11, \u6bcf\u5929\u5de5\u4f5c 9 \u5c0f\u6642, \u9593\u4e2d\u9700\u8981\u8d85\u6642\u5de5\u4f5c\n\n\u7533\u8acb\u9808\u77e5 :\u6c42\u8077\u8005\u53ef\u81f4\u96fb25300128\u8207\u9999\u6e2f\u4e2d\u5cf6\u6c34\u7522\u6709\u9650\u516c\u53f8\u5433\u5c0f\u59d0\u806f\u7d61\u3002\n\n", "employment_types": ["Full Time"], "selling_points": [], "locations": ["Kwun Tong"], "categories": ["Manufacturing", "Others"], "post_time": "2022-01-14T08:59:43Z", "salary": {"currency": null, "max": null, "min": null, "period": "monthly", "term": null}, "salary_visible": false, "title_keywords": [], "responsibilities": [], "requirements": {"degrees": [], "majors": [], "languages": [], "language_level": [], "hard_skills": [], "soft_skills": [], "languages_combined": []}, "experience_required": {"duration": [], "field": []}}, {"job_id": "100003009048089", "location_code": "hk", "company": "Time Grand Limited", "job_title": "Purchaser", "description": "Placing orders with suppliers or vendors and ensuring that documentation is in order, with terms and conditions being clear;\nMaintaining a filing system in the purchase department and updating appropriate records when required;\n\nJob Requirement:\n\nAt least 3 years of relevant experience in purchase work , \u00a0experience in watch manufacturing field is highly preferred\nIn depth knowledge of Microsoft Excel and Words.\nKnowledge in ERP system is highly preferred\nFair command in both written and spoken English and Cantonese;\nGood time-management, self-motivated, willing to learn and able to work under pressure;\nImmediate available is highly preferable\n\nOur company culture and pattern:\n\n5-day work week,\n13-months Salary, Discretionary Bonus, Annual Leave, Payable Sick Leave,\nEmphasize team work,\nEncourage continuing education and on-job training,\nOpen office working environment,\nOffer\u00a0promotion opportunities and long-term career path\n\nWe offer attractive remuneration package and long-term career prospect to the appointed candidate. Please submit your application enclosing your full resume with current and expected salary in strict confidence to HR & Admin Department by clicking \"Apply Now\" below.\u00a0\n\n(All information provided will be treated in strict confidence and used solely for recruitment purpose.)", "employment_types": ["Full Time", "Permanent"], "selling_points": ["Watch Manufacturing; Microsoft Excel and Words;", "5-day work week; 13-months Salary;", "Knowledge in ERP system is preferred"], "locations": ["Kwai Hing"], "categories": ["Manufacturing", "Others", "Merchandising & Purchasing", "Watch"], "post_time": "2022-01-14T04:46:34Z", "salary": {"currency": null, "max": null, "min": null, "period": "monthly", "term": null}, "salary_visible": false, "title_keywords": [], "responsibilities": ["management", "maintaining", "purchase", "placing orders", "documentation", "work under pressure"], "requirements": {"degrees": [], "majors": [], "languages": ["cantonese", "english"], "language_level": [], "hard_skills": ["documentation", "erp system", "words", "microsoft excel"], "soft_skills": ["clear", "self-motivated", "willing to learn", "work under pressure"], "languages_combined": [{"language": "cantonese", "language_level": []}, {"language": "english", "language_level": []}]}, "experience_required": {"duration": ["at least 3 years"], "field": ["manufacturing", "relevant experience"]}}, {"job_id": "100003009048524", "location_code": "hk", "company": "Coronet Toys Company Limited", "job_title": "Assistant Accountant", "description": "Responsibilities:\n\nPrepare monthly subsidiaries\u2019 management accounts;\nSupport the senior team members\u00a0to prepare the monthly consolidated management accounts and year-end audit\nPrepare daily, weekly and monthly cash/ bank positions;\nSupport the senior team members\u00a0to prepare bi-weekly cashflow forecast;\nSupport the senior team members to prepare the budgeting;\nPerform treasury functions including arrangement of cheques payments, fund transfer and L/C arrangements;\nAssist in handling Account Receivables matters\nHandle ad-hoc projects relating to financial reporting\n\nRequirements:\n\nLCCI higher, Diploma or above in accounting or related discipline\nMinimum\u00a03\u00a0years of relevant experience plus audit experience is preferable\nExcellent knowledge in MS Excel formulations\nExperience in ERP \"Yonyou \u7528\u53cb\" system is an absolute advantage\nImmediate available\u00a0highly preferred\n\nInterested candidates please send your CV with current and expected salary by clicking \"Apply Now\"\n\nAll personal data received will be used for recruitment purpose only.", "employment_types": ["Full Time", "Permanent"], "selling_points": [], "locations": ["Kowloon Bay"], "categories": ["Accounting", "Accountant", "Accounting Clerk / Supervisor", "Manufacturing", "Others"], "post_time": "2022-01-14T06:44:50Z", "salary": {"currency": null, "max": null, "min": null, "period": "monthly", "term": null}, "salary_visible": false, "title_keywords": ["assistant accountant"], "responsibilities": ["year-end", "management", "budgeting", "audit", "cheques", "payments", "financial reporting", "forecast", "ad-hoc projects"], "requirements": {"degrees": ["diploma or above"], "majors": ["accounting"], "languages": [], "language_level": [], "hard_skills": ["plus", "ms excel", "erp"], "soft_skills": [], "languages_combined": []}, "experience_required": {"duration": ["minimum 3 years"], "field": ["audit experience", "relevant experience"]}}, {"job_id": "100003009041584", "location_code": "hk", "company": "Vogue Laundry Service Limited", "job_title": "\u6d17\u8863\u5ee0\u751f\u7522\u54e1**", "description": "\n\u8077\u8cac :\u5354\u52a9\u624b\u71a8/\u593e\u71a8/\u57f7\u561c\u7e2b\u88dc/\u4e7e\u6fd5\u6d17\u5de5\u4f5c; \u6309\u898f\u5b9a\u7a0b\u5f0f\u8207\u6a19\u6e96\u8655\u7406\u6aa2\u67e5\u3001\u5206\u985e\u53ca\u6d17\u524d\u53bb\u6c61\u5ba2\u8863; \u5982\u6709\u6d17\u8863\u54c1\u8cea\u554f\u984c\u6216\u7570\u5e38, \u53ca\u6642\u5411\u4e0a\u7d1a\u5f59\u5831; \u53ca\u6642\u5831\u544a\u8a2d\u5099\u6545\u969c\u53ca\u505c\u6a5f\u5831\u4fee; \u64cd\u4f5c\u5de5\u696d\u7528\u6d17\u8863\u6a5f\u5668/\u8a2d\u5099\n\n\u8cc7\u6b77 :\u6c92\u6709\u5b78\u6b77\u8981\u6c42; \u4e00\u822c\u7cb5\u8a9e; \u7565\u61c2\u8b80\u5beb\u4e2d\u6587; \u6709\u7d93\u9a57\u512a\u5148, \u719f\u6089\u8863\u7269\u5e03\u6599, \u6b3e\u5f0f\u53ca\u6240\u5c0d\u61c9\u4e0d\u540c\u7684\u624b\u71a8/\u593e\u71a8\u6280\u8853, \u80fd\u6aa2\u67e5\u8863\u7269\u72c0\u614b, \u8a55\u4f30\u624b\u71a8/\u593e\u71a8\u98a8\u96aa\n\n\u5f85\u9047 :\u6bcf\u6708$11,100 - $14,800, \u6709\u52e4\u5de5\u734e\u91d1, \u4f9b\u81b3\u98df \u53ca\u7a7f\u68ad\u5df4\u58eb\u670d\u52d9, \u4e0a\u53487\u6642\u534a\u81f3\u4e0b\u53485\u6642, \u4e0a\u53488\u664215\u5206\u81f3\u4e0b\u53485\u664245\u5206, \u4e2d\u534812\u6642\u81f3\u4e0b\u53489\u6642\u534a, \u4e0b\u53482\u6642\u81f3\u4e0b\u534811\u6642\u534a\u6216\u4e0b\u53489\u6642\u534a\u81f3\u4e0a\u53487\u6642, \u6bcf\u9031\u5de5\u4f5c5-6\u5929,\u8f2a\u73ed,\u8f2a\u4f11,\u6bcf\u67086\u5929\u4f11\u606f\u65e5\n\n\u7533\u8acb\u9808\u77e5 :\u6c42\u8077\u8005\u53ef\u81f4\u96fb24603502\u8207\u96c5\u6f54\u6d17\u8863\u6709\u9650\u516c\u53f8\u6e29\u5c0f\u59d0\u806f\u7d61\u3002\n\n", "employment_types": ["Full Time"], "selling_points": [], "locations": ["Yuen Long"], "categories": ["Manufacturing", "Others"], "post_time": "2022-01-12T04:04:26Z", "salary": {"currency": null, "max": null, "min": null, "period": "monthly", "term": null}, "salary_visible": false, "title_keywords": [], "responsibilities": [], "requirements": {"degrees": [], "majors": [], "languages": [], "language_level": [], "hard_skills": [], "soft_skills": [], "languages_combined": []}, "experience_required": {"duration": [], "field": []}}, {"job_id": "100003009050803", "location_code": "hk", "company": "iDance International Limited", "job_title": "Graphic Designer", "description": "We are a consumer electronics trading company which located at Kwun Tong area and we are now seeking for the following position to cope our company expansion.\n\nGRAPHIC DESIGNER\n\nResponsibilities:\n\u2022 Wide range of design jobs, such as Brand, Packaging, P.O.P. Advertising, Company Brochure and Promotion Materials\n\u2022 Assist marketing events and perform ad-hoc projects as assigned\n\nRequirements:\n\u2022 Diploma in Graphic Design or Related Discipline\n\u2022\u00a0Min. 3 years or above solid experience in Graphic Design background\n\u2022\u00a0Strong creative senses, well organized, mature, highly responsible and independent\n\u2022\u00a0Full PC and Macintosh skill is a must, proficient in Photoshop, Illustrator, InDesign, PowerPoint\n\u2022\u00a0Product photo shoot and photo retouch\n\u2022\u00a0Familiar with output and print production\n\u2022\u00a0Good command of Chinese and English\n\u2022 Immediately available is preferred\n\nInterested candidates, kindly send your detailed resume including Expected Salary.\n\n(All personal data will be collected for recruitment purposes only.)\u00a0", "employment_types": ["Full Time", "Permanent"], "selling_points": [], "locations": ["Ngau Tau Kok"], "categories": ["Design", "Graphics", "Others", "Manufacturing", "Others"], "post_time": "2022-01-14T11:26:04Z", "salary": {"currency": null, "max": null, "min": null, "period": "monthly", "term": null}, "salary_visible": false, "title_keywords": ["graphic designer"], "responsibilities": ["marketing events", "ad-hoc projects", "advertising", "design"], "requirements": {"degrees": ["diploma"], "majors": ["graphic design"], "languages": ["english", "chinese"], "language_level": ["good command"], "hard_skills": ["indesign", "illustrator", "powerpoint", "pc", "photoshop"], "soft_skills": ["independent", "responsible", "well organized", "mature", "creative"], "languages_combined": [{"language": "english", "language_level": ["good command"]}, {"language": "chinese", "language_level": ["good command"]}]}, "experience_required": {"duration": ["3 years"], "field": ["graphic design"]}}, {"job_id": "100003009041768", "location_code": "hk", "company": "Watami (China) Co. Limited", "job_title": "\u98df\u54c1\u5de5\u5834\u751f\u7522\u54e1**", "description": "Successful candidates will be required to plan the best resource utilization in workflow and workforce to achieve the highest level of operations excellence and customer satisfaction.\n\nResponsibilities:\n\nLead a small team\u00a0to perform customer orders processing and handle inquiries or complaints from the corporate customers\nEnsure the daily production reports are delivered timely and accurately\nProvide satisfactory support services to operational teams\nPrepare and follow up on the progress of the system change request\nParticipate in ad-hoc projects and perform other duties as and when required\nRequirements:\n\nDiploma / Degree holder in Business, Logistics or Operations Management\nMinimum 3 years relevant experience in various operations support disciplines\nGood team player with strong interpersonal and communication skills\nStrong problem-solving capability, able to communicate effectively\nProficient in MS Office including Excel, PowerPoint, and Word\nWe offer competitive remuneration and benefits include:\nMedical & dental benefits\nDiscount air-tickets\nDiscount laundry service\nSwire Hong Kong Staff Association membership\nStaff activity\nEducation allowance\nChildren education scholarship\nVoluntary service leave\nOn-the job training\nOutperformer awards\nDiscretionary performance bonus\nInterested parties please click \u201cApply Now\u201d to submit your application.\u00a0\nMail: People Department, 95-99 Fuk Hi Street, Yuen Long Industrial\u00a0Estate, Yuen Long, N.T.\nFax: 2480 2432\n\nApplication details will be used only for recruitment purpose, and will be destroyed after 24 months.", "employment_types": ["Part Time"], "selling_points": [], "locations": ["Kwun Tong"], "categories": ["Manufacturing", "Others"], "post_time": "2022-01-12T04:20:57Z", "salary": {"currency": null, "max": null, "min": null, "period": "hourly", "term": null}, "salary_visible": false, "title_keywords": [], "responsibilities": ["perform other duties", "lead a small team", "support services", "teams", "reports", "ad-hoc projects"], "requirements": {"degrees": ["diploma", "degree holder"], "majors": ["business"], "languages": [], "language_level": [], "hard_skills": ["excel", "problem-solving", "word", "powerpoint", "ms office"], "soft_skills": ["problem-solving", "communication skills", "good team player", "interpersonal"], "languages_combined": []}, "experience_required": {"duration": ["minimum 3 years"], "field": ["relevant experience"]}}, {"job_id": "100003009049963", "location_code": "hk", "company": "Vogue Laundry Service Limited", "job_title": "Senior Operations Support Officer", "description": "\n\u8077\u8cac :\u63a7\u5236\u751f\u7522\u6a5f\u5668\u8a2d\u5099\u65e5\u5e38\u64cd\u4f5c, \u751f\u7522\u5de5\u4f5c, \u5305\u62ec\u751f\u7522\u88fd\u4f5c, \u78c5\u6599, \u62c6\u5378\u53ca\u642c\u904b\u7b49\u5de5\u4f5c\n\n\u8cc7\u6b77 :\u5c0f\u516d\u7a0b\u5ea6; 1\u5e74\u7d93\u9a57; \u4e00\u822c\u7cb5\u8a9e; \u7565\u61c2\u8b80\u5beb\u4e2d\u6587; \u523b\u82e6, \u52e4\u596e, \u5b88\u6642, \u6709\u8cac\u4efb\u5fc3; \u61c2\u4e00\u822c\u6a5f\u68b0\u5e38\u8b58; \u5c45\u4f4f\u5143\u6717/\u5c6f\u9580\u5340\u512a\u5148\n\n\u5f85\u9047 :\u6bcf\u6708$15,000 - $20,000, \u6709\u52e4\u5de5\u734e\u91d1, \u54e1\u5de5\u8cfc\u7269\u512a\u60e0, \u5176\u4ed6\u6d25\u8cbc/\u798f\u5229 \u53ca\u5e74\u7d42\u734e\u91d1, \u661f\u671f\u4e00\u81f3\u516d: \u4e0a\u53488\u6642\u81f3\u4e0b\u53486\u6642, \u6bcf\u9031\u5de5\u4f5c6\u5929\n\n\u7533\u8acb\u9808\u77e5 :\u6c42\u8077\u8005\u53ef\u81f4\u96fb24558812\u8207\u6771\u548c\u98df\u54c1\u6709\u9650\u516c\u53f8\u6797\u5c0f\u59d0\u806f\u7d61\u3002\n\n", "employment_types": ["Full Time"], "selling_points": ["Perform Customer Orders Processing", "Handle Corporate Customers' Inquiries", "Free Meal I Shuttle Bus I Medical"], "locations": ["Yuen Long"], "categories": ["Manufacturing", "Production Planning / Control", "Others", "Quality Assurance, Control & Testing / ISO"], "post_time": "2022-01-14T09:31:16Z", "salary": {"currency": null, "max": null, "min": null, "period": "monthly", "term": null}, "salary_visible": false, "title_keywords": ["officer", "senior operations"], "responsibilities": [], "requirements": {"degrees": [], "majors": [], "languages": [], "language_level": [], "hard_skills": [], "soft_skills": [], "languages_combined": []}, "experience_required": {"duration": [], "field": []}}, {"job_id": "100003009045390", "location_code": "hk", "company": "Eastward Foods Company Limited", "job_title": "\u751f\u7522\u64cd\u4f5c\u54e1", "description": "Job Responsibilities:\n\nAssist to implement Safety Management System and\u00a0ISO 14001 Environmental Management System\nAssist in collecting and organizing the data of Environmental and Safety activities\nSupport, prepare and review ISO 14001 EMS documents\nAssist in internal and external environmental audits\nPreparation and analysis of environmental reports\nHandle document control work\nAssist in any ad hoc tasks as assigned\n\nJob Requirements:\n\nDegree holder in Japanese Studies / Safety / Environmental Management or\u00a0related disciplines\nAt least 3 years relevant experience, good written translation ability and skills\nProficient in both spoken and written English, Chinese and Japanese\nBusiness level Japanese speaking & writing ability is highly preferred\nStrong presentation, communication & interpersonal skills\nFamiliar with ISO 14001 standards will be preferable\nGood knowledge of MS Office including PowerPoint, Word, Excel and Chinese Word Processing", "employment_types": ["Full Time"], "selling_points": [], "locations": ["Tuen Mun Area"], "categories": ["Manufacturing", "Others", "Others", "Others"], "post_time": "2022-01-13T07:45:26Z", "salary": {"currency": null, "max": null, "min": null, "period": "monthly", "term": null}, "salary_visible": false, "title_keywords": [], "responsibilities": ["management", "control", "data", "ems", "analysis", "review", "ad hoc tasks", "reports", "audits"], "requirements": {"degrees": ["degree holder"], "majors": ["related disciplines"], "languages": ["japanese", "english", "chinese"], "language_level": ["good", "proficient"], "hard_skills": ["excel", "chinese word processing", "word", "powerpoint", "translation", "ms office"], "soft_skills": ["communication", "interpersonal skills", "presentation"], "languages_combined": [{"language": "japanese", "language_level": ["proficient"]}, {"language": "english", "language_level": ["proficient"]}, {"language": "chinese", "language_level": ["good", "proficient"]}]}, "experience_required": {"duration": ["at least 3 years"], "field": ["relevant experience"]}}, {"job_id": "100003009048742", "location_code": "hk", "company": "SD Electronic Materials (Hong Kong) Limited", "job_title": "Officer \u2013 Environment & Safety", "description": "Job Responsibilities:\n\nBe responsible for the factory operation in line with the local environmental and safety regulations\nEstablish annual plans for safety operation and environment protection\nEnsure the planned safety activities to be implemented as scheduled, by utilizing the internal resources, advising the departments the follow up methods\nMonitor internal ES requirements to be carried out properly by both internal staff and contractors\nDevelop and conduct safety training course for all staffs to enhance their safety awareness\nSupport the development of safety and environmental policies and programs\nAdvise and instruct on various safety-related projects and activities\nConduct risk assessment (job hazard analysis, potential hazards, identification of hazardous conditions and hazardous exposure) and enforce preventative measures\nLead and handle accident/incident, investigations, follow-ups, corrective actions, analysis, and recommendations\nRevamp and review safety and environmental guidelines constantly\nInitiate safety and environmental plans and activities to continuously improve internal operation environment and environmental protection\nHandle ad-hoc projects or duties as assigned\n\nJob Requirements:\n\nDegree holder in Occupational Safety and Health or related discipline\nWith minimum 6 years\u2019 solid experience in environmental and safety from sizable corporations, preferably factory in-house experience\nWell understood the Hong Kong environmental and safety regulations\nKnowledge of SMS and ISO 14001, energy auditing or carbon auditing\nGood communication and interpersonal skills\nSelf-motivated, able to work independently and under pressure\nGood command of both written and spoken English and Chinese\nGood knowledge of MS Office including PowerPoint, Word, Excel and Chinese Word Processing\nCandidates with less experience will be considered for the post of Senior Officer", "employment_types": ["Full Time"], "selling_points": ["5-day Work Week", "Competitive Remuneration and Benefits Package", "Year-end Bonus and Discretionary Performance Bonus"], "locations": ["Tai Po Area"], "categories": ["Manufacturing", "Others"], "post_time": "2022-01-14T07:12:11Z", "salary": {"currency": null, "max": null, "min": null, "period": "monthly", "term": null}, "salary_visible": false, "title_keywords": ["officer"], "responsibilities": ["regulations", "revamp", "guidelines", "policies", "analysis", "review", "monitor", "develop", "plans", "ad-hoc projects"], "requirements": {"degrees": ["degree holder"], "majors": [], "languages": ["english", "chinese"], "language_level": ["good command", "good"], "hard_skills": ["excel", "chinese word processing", "word", "powerpoint", "ms office"], "soft_skills": ["self-motivated", "communication and interpersonal skills", "under pressure", "work independently"], "languages_combined": [{"language": "english", "language_level": ["good command", "good"]}, {"language": "chinese", "language_level": ["good command", "good", "good"]}]}, "experience_required": {"duration": ["minimum 6 years"], "field": ["environmental"]}}, {"job_id": "100003009050610", "location_code": "hk", "company": "SD Electronic Materials (Hong Kong) Limited", "job_title": "Assistant Manager \u2013 Environment & Safety", "description": "\u4e3b\u8981\u8077\u8cac:\n\n\u8ca0\u8cac\u6aa2\u67e5\u5ee0\u5167\u8a2d\u5099\u6b63\u5e38\u904b\u4f5c, \u7dad\u4fee\u53ca\u4fdd\u990a\u7d00\u9304, \u5305\u62ec\u96fb\u5668\u7528\u5177\u3001\u51b7\u6c23\u7cfb\u7d71\u3001\u6c34\u5589\u6f54\u5177\u7b49\n\u5354\u52a9\u8655\u7406\u7a81\u767c\u6027\u5de5\u4f5c\n\u9593\u4e2d\u9808\u5916\u52e4\u5de5\u4f5c\n\n\u8077\u4f4d\u8981\u6c42:\n\n\n\u71d2\u710a\u724c, \u96fb\u71b1\u934b\u724c(\u7b2c\u4e09\u7d1a)\nA0\u96fb\u724c, \u78e8\u8f2a\u724c\u53ca\u5e73\u5b89\u5361\n\u80fd\u7368\u7acb\u5de5\u4f5c, \u6709\u8cac\u4efb\u5fc3\n\n\u5de5\u4f5c\u5730\u9ede\u53ca\u6642\u9593:\n\n\n\u5c6f\u9580\u5de5\u696d\u5340\u5de5\u4f5c\n\u6bcf\u9031\u5de5\u4f5c5.5\u5929, \u661f\u671f\u4e00\u81f3\u4e94: \u65e9\u4e0a7:00\u81f3\u4e0b\u53485:00; \u661f\u671f\u516d: \u65e9\u4e0a7:00\u81f3\u4e0b\u534812:00\n\u516c\u53f8\u798f\u5229:\n\n\u96d9\u7ce7\n\u9280\u884c\u5047\u671f\n\u6709\u85aa\u5e74\u5047\n\u91ab\u7642\u798f\u5229\n\u914c\u60c5\u6027\u82b1\u7d05\n\u7533\u8acb\u8fa6\u6cd5:\n\n\n\u7533\u8acb\u8005\u8acb\u8a73\u5217\u7533\u8acb\u8077\u4f4d\u540d\u7a31\u3001\u8cc7\u6b77\u53ca\u8981\u6c42\u5f85\u9047\uff0c\u4e26\u900f\u904e\"APPLY NOW\"\u00a0\u7533\u8acb\u3002\u5982\u6709\u4efb\u4f55\u67e5\u8a62\uff0c\u8acbwhatsapp 9382 9238\u3002\n\n\u7533\u8acb\u4eba\u6240\u63d0\u4f9b\u7684\u500b\u4eba\u8cc7\u6599\u5c07\u53ea\u7528\u65bc\u672c\u516c\u53f8\u53ca\u5176\u95dc\u806f\u53ca\u9644\u5c6c\u6a5f\u69cb\u4e4b\u62db\u8058\u7528\u9014\u3002\u5982\u679c\u3000\u95a3\u4e0b\u4e0d\u63d0\u4f9b\u62db\u8058\u5ee3\u544a\u4e2d\u63d0\u53ca\u7684\u8cc7\u6599\uff0c\u6211\u5011\u53ef\u80fd\u7121\u6cd5\u8a55\u4f30\u3000\u95a3\u4e0b\u7684\u5de5\u4f5c\u7533\u8acb\u3002\u3000\u95a3\u4e0b\u6709\u6b0a\u5411\u6211\u5011\u7684\u8cc7\uf9be\u4fdd\u969c\u4e3b\u4efb\u806f\u7e6b\u00a0(\u96fb\u90f5: pdpo@ vitasoy.com)\u00a0\u63d0\u51fa\u67e5\u95b1\u53ca\u6216\u6539\u6b63\u95a3\u4e0b\u7684\u500b\u4eba\u8cc7\u6599\uff0c\u60df\u672c\u516c\u53f8\u6703\u5728\u62db\u8058\u904e\u7a0b\u7d50\u675f\u5f8c\u624d\u8655\u7406\u6709\u95dc\u67e5\u95b1\u8981\u6c42\u3002", "employment_types": ["Full Time"], "selling_points": ["Establish annual plans for safety operation", "Monitor internal ES requirements", "Develop and conduct safety training course"], "locations": ["Tai Po Area"], "categories": ["Manufacturing", "Others"], "post_time": "2022-01-14T10:55:16Z", "salary": {"currency": null, "max": null, "min": null, "period": "monthly", "term": null}, "salary_visible": false, "title_keywords": ["assistant manager"], "responsibilities": [], "requirements": {"degrees": [], "majors": [], "languages": [], "language_level": [], "hard_skills": [], "soft_skills": [], "languages_combined": []}, "experience_required": {"duration": [], "field": []}}, {"job_id": "100003009042931", "location_code": "hk", "company": "Hong Kong Gourmet Ltd", "job_title": "\u7dad\u4fee\u6280\u8853\u54e1", "description": "\n\u8077\u8cac :\u8655\u7406\u65e5\u5e38\u5de5\u5834\u904b\u4f5c\u751f\u7522\u5de5\u5e8f\uff0c\u9700\u642c\u904b\uff0c\u4fdd\u6301\u5de5\u4f5c\u74b0\u5883\u6e05\u6f54\n\n\u8cc7\u6b77 :\u4e2d\u4e09\u7a0b\u5ea6; 1\u5e74\u7d93\u9a57; \u826f\u597d\u7cb5\u8a9e; \u4e00\u822c\u82f1\u8a9e; \u61c2\u8b80\u5beb\u4e2d\u6587; \u61c2\u95b1\u8b80\u82f1\u6587; \u6301\u6709\u4f01\u93df\u8eca\u724c\u512a\u5148\n\n\u5f85\u9047 :\u6bcf\u6708$17,170 - $19,850, \u6709\u52e4\u5de5\u734e\u91d1, \u5e74\u504710\u5929, \u8868\u73fe\u734e\u91d1 \u53ca\u8f2a\u73ed\u6d25\u8cbc, \u4e0a\u53487\u6642\u81f3\u4e0b\u53483\u664215\u5206\u6216\u4e0b\u53483\u6642\u81f3\u4e0b\u534811\u664215\u5206, \u6bcf\u9031\u5de5\u4f5c6\u5929,\u8f2a\u73ed, \u6bcf\u5929\u5de5\u4f5c 7.5 \u5c0f\u6642\n\n\u7533\u8acb\u9808\u77e5 :\u6c42\u8077\u8005\u53ef\u81f4\u96fb67654230\u8207CPL\u9999\u6599(\u9060\u6771)\u6709\u9650\u516c\u53f8\u9673\u5c0f\u59d0\u806f\u7d61\u3002\n\n", "employment_types": ["Full Time", "Permanent"], "selling_points": ["\u751f\u7522\u7dda\u6280\u8853\u54e1", "\u5c6f\u9580\u5de5\u696d\u5340", "\u6bcf\u9031\u5de5\u4f5c5.5\u5929"], "locations": ["Tuen Mun Area"], "categories": ["Engineering", "Mechanical", "Hospitality / F & B", "Others", "Manufacturing", "Others"], "post_time": "2022-01-12T09:15:34Z", "salary": {"currency": null, "max": null, "min": null, "period": "monthly", "term": null}, "salary_visible": false, "title_keywords": [], "responsibilities": [], "requirements": {"degrees": [], "majors": [], "languages": [], "language_level": [], "hard_skills": [], "soft_skills": [], "languages_combined": []}, "experience_required": {"duration": [], "field": []}}, {"job_id": "100003009041665", "location_code": "hk", "company": "CPL Aromas (Far East) Limited", "job_title": "\u751f\u7522\u54e1**", "description": "Perform reception duties including handling incoming calls, client greeting, courier receiving, letter dispatching, mailing;\nProvide office administrative supports including pantry & sundries management, water machine and vending machine maintenance, stationeries, office supplies management,\u00a0 and material printing, office equipment and facilities\u2019 maintenance, office housekeeping;\nEnsure reception area and meeting rooms are tidy, presentable and well-organized;\nProvide support to HR & Admin department;\nProvide support to employees, company events and activities and assist in ad hoc projects as required\nRequirement:\u00a0\n\nForm 5 standard or above\u00a0with 1-2 years in receptionist/administrative experience\nPleasant with good telephone manner and strong communication skills\nGood command of spoken English, Chinese & Mandarin\nProficient in PC applications including MS Outlook, Word, Excel and Chinese Word Processing", "employment_types": ["Full Time"], "selling_points": [], "locations": ["Yuen Long"], "categories": ["Manufacturing", "Others"], "post_time": "2022-01-12T04:11:14Z", "salary": {"currency": null, "max": null, "min": null, "period": "monthly", "term": null}, "salary_visible": false, "title_keywords": [], "responsibilities": ["provide support", "management", "maintenance", "office supplies", "housekeeping", "hr", "communication", "ad hoc projects"], "requirements": {"degrees": ["form 5"], "majors": [], "languages": ["english", "chinese", "mandarin"], "language_level": ["good command", "proficient"], "hard_skills": ["excel", "chinese word processing", "maintenance", "word", "pc applications", "outlook"], "soft_skills": ["communication skills", "well-organized", "pleasant", "presentable", "telephone manner"], "languages_combined": [{"language": "english", "language_level": ["good command"]}, {"language": "chinese", "language_level": ["good command", "proficient"]}, {"language": "mandarin", "language_level": ["good command"]}]}, "experience_required": {"duration": ["1-2 years"], "field": ["administrative"]}}, {"job_id": "100003009042097", "location_code": "hk", "company": "Kiu Hung Industries Limited", "job_title": "Receptionist", "description": "Career Level\nSenior\nQualification\nDegree\nYears of Experience\n5 years\nJob Type\nFull Time\nJob Functions\nManufacturing, Product Development / Management, Others", "employment_types": ["Full Time"], "selling_points": [], "locations": ["Shatin Area"], "categories": ["Manufacturing", "Others"], "post_time": "2022-01-12T06:07:14Z", "salary": {"currency": null, "max": null, "min": null, "period": "monthly", "term": null}, "salary_visible": false, "title_keywords": ["receptionist"], "responsibilities": ["management"], "requirements": {"degrees": ["degree"], "majors": [], "languages": [], "language_level": [], "hard_skills": [], "soft_skills": [], "languages_combined": []}, "experience_required": {"duration": [], "field": []}}, {"job_id": "100003009050955", "location_code": "hk", "company": "Bank of Communications Hong Kong Branch", "job_title": "Production Management Manager (Information Technology)", "description": "\u8077\u8cac\n\n\u64cd\u4f5c\u96fb\u8166\u7cfb\u7d71\uff0c\u5b89\u6392\u751f\u7522\u6d41\u7a0b\n\u64cd\u4f5c\u5668\u6750\uff0c\u6e05\u7406\u751f\u7522\u7dda\n\u8ca0\u8cac\u76f8\u95dc\u6587\u4ef6\u5de5\u4f5c\n\u9700\u8981\u8f2a\u73ed\u5de5\u4f5c\n\n\u00a0\u5165\u8077\u689d\u4ef6\n\n\u4e2d\u5b78\u7562\u696d\u6216\u4ee5\u4e0a\u7a0b\u5ea6\n\u8aa0\u5be6\u3001\u52e4\u596e\u3001\u826f\u597d\u4eba\u969b\u95dc\u4fc2\n\u719f\u6089\u96fb\u8166\u64cd\u4f5c\u66f4\u4f73\n\u6301\u6709\u5bc6\u9589\u7a7a\u9593\u8a3b\u518a\u8b49\u512a\u5148\n\u6709\u63a8\u571f\u6a5f\u724c\u512a\u5148\uff0c\u4e26\u53ef\u4eab\u6709\u984d\u5916\u6d25\u8cbc\n\u9752\u8863\u5340\u4e0a\u73ed\n\n\u9577\u5de5\u8077\u4f4d\u53ef\u4eab\u5b8c\u5584\u798f\u5229\u5305\u62ec\uff1a\n\n\n\u591a\u9805\u6d25\u8cbc\u798f\u5229/\u82b1\u7d05\n\u4eba\u58fd\u4fdd\u96aa\n\u4e2d\u3001\u897f\u3001\u7259\u79d1\u91ab\u7642\n\u5a5a\u5047\u53ca\u5176\u4ed6\u7279\u5225\u5047\u671f\n\n\u806f\u7d61\u65b9\u6cd5\uff1a\n\u96fb\u8a71 : 2862 2282\n\n\u6211\u5011\u662f\u5e73\u7b49\u6a5f\u6703\u50f1\u4e3b\uff0c\u6b61\u8fce\u6240\u6709\u5408\u8cc7\u683c\u4eba\u58eb\u7533\u8acb\u3002\n\u6240\u6709\u6536\u96c6\u7684\u500b\u4eba\u8cc7\u6599\u5c07\u7d55\u5c0d\u4fdd\u5bc6\u4e26\u53ea\u7528\u65bc\u62db\u8058\u76f8\u95dc\u7684\u4e8b\u5b9c\u3002", "employment_types": ["Full Time"], "selling_points": [], "locations": ["Not Specified"], "categories": ["Manufacturing", "Product Development / Management", "Others"], "post_time": "2022-01-14T12:01:10Z", "salary": {"currency": null, "max": null, "min": null, "period": "monthly", "term": null}, "salary_visible": false, "title_keywords": ["manager"], "responsibilities": [], "requirements": {"degrees": [], "majors": [], "languages": [], "language_level": [], "hard_skills": [], "soft_skills": [], "languages_combined": []}, "experience_required": {"duration": [], "field": []}}, {"job_id": "100003009044846", "location_code": "hk", "company": "Alliance Construction Materials Limited", "job_title": "\u5ee0\u623f\u71df\u904b\u52a9\u7406", "description": "\n\u4e2d\u4e09\u7a0b\u5ea6,\u4e94\u5e74\u76f8\u95dc\u5de5\u4f5c\u7ecf\u9a57,\u6709\u7ecf\u9a8c\u63a5\u8f7d\u50f1\u4e3b\u53ca\u5bb6\u4eba\u5f80\u8fd4\u76ee\u7684\u5730,\u5354\u52a9\u516c\u53f8\u7b80\u55ae\u6587\u66f8\u5de5\u4f5c\u53ca\u7b80\u55ae\u5916\u52e4\u3002\u8ca0\u8cac\u8eca\u8f1b\u65e5\u5e38\u6e05\u6f54,\u7ef4\u4fee\u4fdd\u990a,\u7ee7\u724c\u3002\u6301\u6709\u6548\u9a7e\u9a76\u6267\u7167,\u826f\u597d\u9a7e\u99db\u8bb0\u9304,\u719f\u6089\u6e2f\u4e5d\u65b0\u754c\u8857\u9053\u4ea4\u901a\u89c4\u5247\u3002\u8aa0\u5be6\u6709\u79ae,\u5b88\u6642,\u53bf\u8d23\u4efb\u611f,\u6709\u81ea\u5f8b\u6027,\u5de5\u4f5c\u6642\u4e0d\u5438\u7159\u3002\n\u661f\u671f\u4e00\u81f3\u661f\u671f\u516d,7am-7pm\u8d85\u6642\u88dc\u6c34\u3002\u6975\u5c11\u8d85\u6642\u3002\u2022 13\u500b\u6708\u7cae\u3002\u5f37\u7a4d\u91d1\u3002\u6709\u85aa\u5e74\u5047\u3002\n\u5929\u540e\u53d6\u8eca,\u5357\u533a,\u4e0a\u74b0\n\u9700\u8981\u8a73\u7d30\u5c65\u6b77whatsApp(852)66003884\n\u5de5\u4f5c\u985e\u578b: \u5168\u8077, \u9577\u5de5\n\u85aa\u916c: \u6bcf\u6708 $23,000.00 \u8d77\n\u6642\u9593:\n\u2022 \u65e5\u73ed\n\u798f\u5229:\n\u2022 \u80b2\u5b30\u5047\n\u88dc\u5145\u85aa\u916c:\n\u2022 13\u500b\u6708\n\u2022 \u8d85\u6642\u52a0\u73ed\u8cbb\n\u9060\u7a0b\u5de5\u4f5c:\n\u2022 \u5426\n\n", "employment_types": ["Full Time", "Permanent"], "selling_points": ["\u4e2d\u4e94\u7a0b\u5ea6\u6216\u4ee5\u4e0a", "\u719f\u6089\u96fb\u8166\u64cd\u4f5c", "\u66fe\u6709\u5ee0\u623f\u5de5\u4f5c\u7d93\u9a57\u66f4\u4f73"], "locations": ["Tsing Yi"], "categories": ["Admin & HR", "Others", "Manufacturing", "General / Production Workers", "Others"], "post_time": "2022-01-13T06:27:11Z", "salary": {"currency": null, "max": null, "min": null, "period": "monthly", "term": null}, "salary_visible": false, "title_keywords": [], "responsibilities": [], "requirements": {"degrees": [], "majors": [], "languages": [], "language_level": [], "hard_skills": [], "soft_skills": [], "languages_combined": []}, "experience_required": {"duration": [], "field": []}}, {"job_id": "100003009040638", "location_code": "hk", "company": "Karford Securities Limited", "job_title": "\u53f8\u6a5f\u517c\u529e\u516c\u5ba4\u52a9\u7406", "description": "Manulife is No.\u00a01\u00a0in MPF Market Share as well as the Best Service Provider in Hong Kong.\n\n\u00a0A tailor-made program is offered to high calibers like you to join our profession.\u00a0\n\nOffer:\n\nSpecial package tailor-made for right person according to qualification and experience\nFast Track promotion program to Management Level within 6 months\nProfessional and ongoing training programs to enhance products and marketing knowledge\nHigh Monthly and Annual Performance bonus\nMedical and Life Insurance, low interest mortgage scheme\nFree overseas trip recognition\u00a0\n\nRequirements:\n\nHong Kong Resident\nDegree Holder\nFluency in Cantonese, proficiency in Putonghua is a plus\nMinimum 3 years of working experience\nAggressive person, endeavor to start up own business with strong commitment to succeed\n\n\nOnly short-listed candidates will be contacted.\u00a0 All applicant information is treated confidentially; personal data collection is only for recruitment selection purposes.", "employment_types": ["Full Time"], "selling_points": [], "locations": ["Sheung Wan"], "categories": ["Manufacturing", "Others", "Others", "Others", "Building & Construction", "Others"], "post_time": "2022-01-12T02:53:56Z", "salary": {"currency": null, "max": null, "min": null, "period": "monthly", "term": null}, "salary_visible": false, "title_keywords": [], "responsibilities": ["management", "mpf", "recruitment", "personal data", "insurance"], "requirements": {"degrees": ["degree holder"], "majors": [], "languages": ["cantonese", "putonghua"], "language_level": ["fluency", "proficiency"], "hard_skills": ["no", "scheme", "plus"], "soft_skills": [], "languages_combined": [{"language": "cantonese", "language_level": ["fluency", "proficiency"]}, {"language": "putonghua", "language_level": ["proficiency"]}]}, "experience_required": {"duration": ["minimum 3 years"], "field": []}}, {"job_id": "100003009043420", "location_code": "hk", "company": "", "job_title": "\u53ef\u6263\u7a05\u5f37\u7a4d\u91d1\u8a08\u5283\u5c08\u54e1 MPF Service Manager", "description": "\n\u8077\u8cac :\u8ca0\u8cac\u8ca8\u54c1\u5305\u88dd\u53ca\u5354\u52a9\u751f\u7522\u98df\u54c1\n\n\u8cc7\u6b77 :\u6c92\u6709\u5b78\u6b77\u8981\u6c42; \u826f\u597d\u7cb5\u8a9e; \u61c2\u95b1\u8b80\u4e2d\u6587\n\n\u5f85\u9047 :\u6bcf\u6708$11,500 - $15,000, \u6709\u52e4\u5de5\u734e\u91d1, \u54e1\u5de5\u8cfc\u7269\u512a\u60e0, \u5728\u8077\u57f9\u8a13 \u53ca\u5e74\u7d42\u734e\u91d1, \u661f\u671f\u4e00\u81f3\u516d: \u4e0a\u53488\u6642\u534a\u81f3\u4e0b\u53486\u6642, \u6bcf\u9031\u5de5\u4f5c6\u5929, \u6bcf\u5929\u5de5\u4f5c 8.5 \u5c0f\u6642\n\n\u7533\u8acb\u9808\u77e5 :\u6c42\u8077\u8005\u53ef\u81f4\u96fb38444589\u8207\u842c\u798f\u4e9e\u6d32\u98df\u54c1\u6709\u9650\u516c\u53f8\u9673\u5c0f\u59d0\u806f\u7d61\u3002\n\n", "employment_types": ["Full Time", "Permanent"], "selling_points": ["Attractive Compensation & free overseas trip", "Fast Track Promotion to Management Level", "5-day work, bank holidays, 20-day Annual Leave"], "locations": ["Others"], "categories": ["Media & Advertising", "Account Servicing", "Manufacturing", "Others", "Merchandising & Purchasing", "Procurement / Purchasing / Sourcing"], "post_time": "2022-01-15T19:11:32Z", "salary": {"currency": "HKD", "max": 29999, "min": 20000, "period": "monthly", "term": null}, "salary_visible": true, "title_keywords": ["manager"], "responsibilities": [], "requirements": {"degrees": [], "majors": [], "languages": [], "language_level": [], "hard_skills": [], "soft_skills": [], "languages_combined": []}, "experience_required": {"duration": [], "field": []}}, {"job_id": "100003009045453", "location_code": "hk", "company": "Oriental Foods Expert Limited", "job_title": "\u98df\u54c1\u751f\u7522\u54e1(\u67f4\u7063)**", "description": "\n\u8077\u8cac :\u8ddf\u9032\u5730\u76e4\u3001\u5ea6\u544e\u3001\u8986\u544e\uff0c\u593e\u6c34\u96fb\u3001\u843d\u5eda\u6ac3\u55ae\n\n\u8cc7\u6b77 :\u6c92\u6709\u5b78\u6b77\u8981\u6c42; 3\u5e74\u7d93\u9a57; \u826f\u597d\u7cb5\u8a9e; \u4e00\u822c\u666e\u901a\u8a71; \u4e00\u822c\u82f1\u8a9e\u512a\u5148; \u61c2\u8b80\u5beb\u4e2d\u6587; \u7565\u61c2\u8b80\u5beb\u82f1\u6587; \u6709\u76f8\u95dc\u7d93\u9a57\uff1b\u6709\u8cac\u4efb\u5fc3\u53ca\u826f\u597d\u6e9d\u901a\u6280\u5de7\uff1b\u61c2\u7c21\u55ae\u6587\u66f8\uff1b\u6709\u505a\u904e\u5eda\u6ac3\u7d93\u9a57\u512a\u5148\n\n\u5f85\u9047 :\u6bcf\u6708$22,000 - $28,000, \u661f\u671f\u4e00\u81f3\u516d: \u4e0a\u53489\u6642\u81f3\u4e0b\u53486\u6642, \u6bcf\u9031\u5de5\u4f5c6\u5929\n\n\u7533\u8acb\u9808\u77e5 :\u6c42\u8077\u8005\u53ef\u81f4\u96fb92391243\u8207OUI KITCHEN COMPANY\u674e\u5973\u58eb\u806f\u7d61\u3002\n\n", "employment_types": ["Full Time"], "selling_points": [], "locations": ["Chai Wan"], "categories": ["Hospitality / F & B", "Others", "Manufacturing", "Others", "Others", "Others"], "post_time": "2022-01-13T07:53:29Z", "salary": {"currency": null, "max": null, "min": null, "period": "monthly", "term": null}, "salary_visible": false, "title_keywords": [], "responsibilities": [], "requirements": {"degrees": [], "majors": [], "languages": [], "language_level": [], "hard_skills": [], "soft_skills": [], "languages_combined": []}, "experience_required": {"duration": [], "field": []}}, {"job_id": "100003009045604", "location_code": "hk", "company": "OUI Kitchen Company", "job_title": "\u8ddf\u9032\u88dd\u4fee\u5730\u76e4\u5e2b\u5085**", "description": "Working Location: Tsing Yi\n\nWorking Time: 09:00 \u2013 17:30\n\n5 days work, Shift\u00a0\n\nBank Holiday\n\nMedical benefit\n\nShuttle bus\n\nKey roles and duties\n\nConduct inspection from raw material, processing and end products\nConduct sampling, physical / chemical testing on starting materials, intermediates and finished products\nConduct environmental monitoring in production area\nArrange the pest control service\nCalibrate the analytical equipment in the QC Laboratory\nReview and maintain the update of product specification record system\nAccomplish other tasks assigned by supervisor\n\nRequirements:\n\nF.6 or above in food science or related disciplines\nHygiene course certificate is preferable\nAble to work under pressure and independently\nExcellent interpersonal and communication skills\nStrong sense of responsibility and willing to learn\nProficient in MS Word, Excel and Chinese Word Processing\nGood command of spoken and written English and Chinese\nFresh graduates are also welcome\u00a0\n\nPlease apply with full resume including expected salary\u00a0by clicking \"Apply\"\n\n\nAll information collected will be kept in strict confidence and used for recruitment purpose only", "employment_types": ["Full Time"], "selling_points": [], "locations": ["Wan Chai"], "categories": ["Manufacturing", "Others", "Others", "Technician"], "post_time": "2022-01-13T08:11:30Z", "salary": {"currency": null, "max": null, "min": null, "period": "monthly", "term": null}, "salary_visible": false, "title_keywords": [], "responsibilities": ["control", "review", "monitoring", "testing", "inspection", "other tasks", "maintain"], "requirements": {"degrees": ["certificate"], "majors": [], "languages": ["english", "chinese"], "language_level": ["good command", "proficient"], "hard_skills": ["excel", "chinese word processing", "ms word"], "soft_skills": ["communication skills", "independently", "confidence", "sense of responsibility", "willing to learn", "interpersonal", "work under pressure"], "languages_combined": [{"language": "english", "language_level": ["good command"]}, {"language": "chinese", "language_level": ["good command", "proficient"]}]}, "experience_required": {"duration": [], "field": []}}, {"job_id": "100003009043735", "location_code": "hk", "company": "Good View Fruits Company Limited", "job_title": "QC Technician", "description": "The Job\n\nResponsible for supervising a team and monitor day to day operation\nResponsible for job roster arrangement and delegating tasks to team members\nPrepares internal reports e.g. Timesheet, working hour, MI report etc.\nPerform any ad-hoc tasks as assigned\n\nThe Person\n\n\nForm\u00a05 / DSE graduated or above\nWith experience in document scanning and data entry industry is an advantage\nProficiency in MS Office application, especially in Excel\u00a0\nMature, team player and attention to detailed person\nWork at client\u2019s premises (Banking)\nImmediate available is highly preferred\nCandidate with lass experience will be considered as Scanning Officer\n\nTo discuss this opportunity further, please send your full resume, current and expected salary to the\u00a0HR Department.\u00a0\n\nWe are an equal opportunity employer and welcome applications from all qualified candidates.\u00a0 All information provided will be treated in strict confidence and used for recruitment purposes only.\u00a0 Applicants not hearing from us within six weeks may consider their applications unsuccessful.\u00a0 All data of unsuccessful applications will be destroyed after six months.", "employment_types": ["Full Time", "Permanent"], "selling_points": [], "locations": ["Tsing Yi"], "categories": ["Sciences, Lab, R&D", "Food Science", "Manufacturing", "Others", "Quality Assurance, Control & Testing / ISO"], "post_time": "2022-01-13T01:45:59Z", "salary": {"currency": null, "max": null, "min": null, "period": "monthly", "term": null}, "salary_visible": false, "title_keywords": ["qc technician"], "responsibilities": ["supervising", "ad-hoc tasks", "monitor", "reports", "report"], "requirements": {"degrees": ["form 5", "dse"], "majors": [], "languages": [], "language_level": [], "hard_skills": ["excel", "ms office"], "soft_skills": ["team player", "confidence", "mature", "detailed"], "languages_combined": []}, "experience_required": {"duration": [], "field": []}}, {"job_id": "100003009044350", "location_code": "hk", "company": "FUJIFILM Business Innovation Hong Kong Limited", "job_title": "Scanning Team Leader", "description": "\n\u8077\u8cac :\u548c\u98df\u5de5\u5834\u8655\u7406\u98df\u6750\uff0c\u5305\u88dd\u91ac\u6c41\u7b49\u5de5\u4f5c\n\n\u8cc7\u6b77 :\u5c0f\u4e09\u7a0b\u5ea6; \u826f\u597d\u7cb5\u8a9e; \u7565\u61c2\u8b80\u5beb\u4e2d\u6587\n\n\u5f85\u9047 :\u6bcf\u5c0f\u6642$50.00, \u6709\u5728\u8077\u57f9\u8a13, \u4f9b\u81b3\u98df \u53ca\u6649\u5347\u6a5f\u6703, \u4e0a\u53488\u6642\u81f3\u4e0b\u53487\u6642, \u6bcf\u9031\u5de5\u4f5c4\u5929\u81f35\u5929,\u8f2a\u4f11, \u6bcf\u5929\u5de5\u4f5c 6 - 9 \u5c0f\u6642\n\n\u7533\u8acb\u9808\u77e5 :\u6c42\u8077\u8005\u53ef\u81f4\u96fb35286484\u8207\u548c\u6c11(\u4e2d\u570b)\u6709\u9650\u516c\u53f8\u6d2a\u5c0f\u59d0\u806f\u7d61\u3002\n\n", "employment_types": ["Full Time"], "selling_points": ["Exp. in document scanning and data entry industry", "Monitor day to day operation", "Prepares internal reports"], "locations": ["Wong Tai Sin Area"], "categories": ["Manufacturing", "Others"], "post_time": "2022-01-13T03:47:25Z", "salary": {"currency": null, "max": null, "min": null, "period": "monthly", "term": null}, "salary_visible": false, "title_keywords": ["team leader"], "responsibilities": [], "requirements": {"degrees": [], "majors": [], "languages": [], "language_level": [], "hard_skills": [], "soft_skills": [], "languages_combined": []}, "experience_required": {"duration": [], "field": []}}, {"job_id": "100003009041743", "location_code": "hk", "company": "Star Light Food Services Limited", "job_title": "\u8089\u985e\u98df\u54c1\u751f\u7522\u54e1", "description": "\n\u8077\u8cac :\u8ca0\u8cac\u8655\u7406\u8089\u985e\u98df\u54c1\u751f\u7522\u904e\u7a0b\u4e2d\u7684\u5207\u8089\u3001\u9183\u8089\u3001\u5305\u88dd\u3001\u57f7\u8ca8\u3001\u6e05\u6f54\u7b49\u76f8\u95dc\u5de5\u4f5c\n\u8cc7\u6b77 :\u4e2d\u4e00\u7a0b\u5ea6; 1\u5e74\u7d93\u9a57; \u826f\u597d\u7cb5\u8a9e\u512a\u5148; \u7565\u61c2\u8b80\u5beb\u4e2d\u6587; \u5b88\u6642\u6709\u79ae\uff0c\u5177\u8cac\u4efb\u5fc3\n\u5f85\u9047 :\u6bcf\u6708$16,000\u6216\u4ee5\u4e0a, \u6709\u6bcf\u6708\u52e4\u5de5\u734e\u91d1$1500, \u734e\u52f5\u6027\u82b1\u7d05, \u91ab\u7642\u798f\u5229, \u4f9b\u81b3\u98df \u53ca\u8d85\u6642\u5de5\u4f5c\u6d25\u8cbc, \u661f\u671f\u4e00\u81f3\u516d: \u4e0a\u53488\u6642\u81f3\u4e0b\u53486\u6642, \u6bcf\u9031\u5de5\u4f5c6\u5929, \u6bcf\u5929\u5de5\u4f5c 9 - 10 \u5c0f\u6642, \u9700\u8981\u6642\u9593\u4e2d\u9700\u8abf\u6574\u5de5\u4f5c\u6642\u9593\u6216\u8f2a\u4f11\n\n", "employment_types": ["Full Time"], "selling_points": [], "locations": ["Kwai Fong"], "categories": ["Manufacturing", "General / Production Workers", "Others", "Others", "Others"], "post_time": "2022-01-12T04:17:58Z", "salary": {"currency": null, "max": null, "min": null, "period": "monthly", "term": null}, "salary_visible": false, "title_keywords": [], "responsibilities": [], "requirements": {"degrees": [], "majors": [], "languages": [], "language_level": [], "hard_skills": [], "soft_skills": [], "languages_combined": []}, "experience_required": {"duration": [], "field": []}}, {"job_id": "100003009041748", "location_code": "hk", "company": "TruCare Enterprise Limited", "job_title": "\u751f\u7522\u54e1", "description": "\n\u8077\u8cac :\u4e00\u822c\u8eca\u9593\u751f\u7522\u53ca\u5305\u88dd\u5de5\u4f5c, \u6aa2\u67e5\u6210\u54c1\u8cea\u91cf (\u5de5\u4f5c\u671f\u9593\u9700\u7a7f\u7740\u7121\u5875\u8863)\n\n\u8cc7\u6b77 :\u6c92\u6709\u5b78\u6b77\u8981\u6c42; \u4e00\u822c\u7cb5\u8a9e; \u61c2\u8b80\u5beb\u4e2d\u6587; \u5de5\u4f5c\u4e3b\u52d5, \u52e4\u596e, \u5177\u5718\u968a\u7cbe\u795e\u53ca\u826f\u597d\u5de5\u4f5c\u614b\u5ea6\n\n\u5f85\u9047 :\u6bcf\u6708$10,000 - $11,000, \u6709\u54e1\u5de5\u8cfc\u7269\u512a\u60e0 \u53ca\u52e4\u5de5\u734e\u91d1, \u661f\u671f\u4e00\u81f3\u516d: \u4e0a\u53489\u6642\u81f3\u4e0b\u53486\u6642, \u6bcf\u9031\u5de5\u4f5c6\u5929, \u6bcf\u5929\u5de5\u4f5c 8 \u5c0f\u6642\n\n\u7533\u8acb\u9808\u77e5 :\u6c42\u8077\u8005\u53ef\u81f4\u96fb26481318\u8207\u552f\u5584\u4f01\u696d\u6709\u9650\u516c\u53f8\u9127\u5c0f\u59d0\u806f\u7d61\u3002\n\n", "employment_types": ["Full Time"], "selling_points": [], "locations": ["Tuen Mun Area"], "categories": ["Manufacturing", "Others"], "post_time": "2022-01-12T04:18:17Z", "salary": {"currency": null, "max": null, "min": null, "period": "monthly", "term": null}, "salary_visible": false, "title_keywords": [], "responsibilities": [], "requirements": {"degrees": [], "majors": [], "languages": [], "language_level": [], "hard_skills": [], "soft_skills": [], "languages_combined": []}, "experience_required": {"duration": [], "field": []}}, {"job_id": "100003009038479", "location_code": "hk", "company": "Scorpion Precision Industry (H.K.) Company Limited", "job_title": "Sales Coordinator  (5 days work)", "description": "Responsibilities:\n\nl\u00a0\u00a0 Coordinate & work closely with sales representatives for Production Monitoring , Packaging follow up and Purchasing issues to ensure customers\u2019 orders are timely produced\n\nl\u00a0\u00a0 Assist in whole production progress and follow up details\n\nl\u00a0\u00a0 Handle projects administrative works, e.g. quotation, order status update\n\nl\u00a0\u00a0 Assist in preparing various sales administration reports\n\nRequirements:\n\nl\u00a0\u00a0 Working experience in similar industry is preferred, fresh graduate is also welcome\n\nl\u00a0\u00a0 Well organized, attentive to details and able to work under pressure\n\nBenefits: 5 days work, 13-month pay, Medical Plan, Attendance bonus, Supporting commission\n\nSalary range: 13K-15K\n\nLocation: Tsuen Wan (near Tseun Wan West Station)", "employment_types": ["Full Time", "Permanent"], "selling_points": [], "locations": ["Tsuen Wan Area"], "categories": ["Manufacturing", "Others", "Sales, CS & Business Devpt", "Sales Administration"], "post_time": "2022-01-11T07:03:15Z", "salary": {"currency": null, "max": null, "min": null, "period": "monthly", "term": null}, "salary_visible": false, "title_keywords": ["sales coordinator"], "responsibilities": ["sales administration", "quotation", "monitoring", "coordinate", "reports"], "requirements": {"degrees": ["fresh graduate"], "majors": [], "languages": [], "language_level": [], "hard_skills": [], "soft_skills": ["well organized", "attentive to details", "work under pressure"], "languages_combined": []}, "experience_required": {"duration": [], "field": []}}, {"job_id": "100003009038259", "location_code": "hk", "company": "Search Eatgine Co. Ltd.", "job_title": "OFFICER / 5 DAYS WORK", "description": "Role Purpose:\n\nThe role will support the development of annual goals which align with the strategic plan of the QA Division\n\n\nA typical day in this Role:\n\nProvide support to processing plant ensuring the effective execution and development of its food safety and quality system based on HACCP principles\n\nSupport operation base management system as well as risk assessment program\n\nAble to handle multiple tasks under a tight schedule & rapidly changing environment while maintaining attention to details and accuracy\u00a0\n\nThis job is a good fit for You if:\n\nYou are proactive with strong analytical mind\n\nYou have strong written and verbal communication skills, excellent problem solving skills\n\nYou have good interpersonal skill and able to communicate with all walks of people\n\nWhat we look for:\n\nPreferably in food industry\n\nQA experience in Food industry preferred\n\nProficiency in MS Word, Excel, PowerPoint and Chinese word processing\u00a0\n\nYou can enjoy:\n\nPublic Holiday\n\n\nPerformance bonus", "employment_types": ["Full Time", "Permanent"], "selling_points": [], "locations": ["Chai Wan"], "categories": ["Manufacturing", "Others"], "post_time": "2022-01-13T02:48:40Z", "salary": {"currency": null, "max": null, "min": null, "period": "monthly", "term": null}, "salary_visible": false, "title_keywords": ["officer"], "responsibilities": ["communicate with", "provide support", "management", "food safety", "maintaining", "quality", "communication", "schedule", "plan"], "requirements": {"degrees": [], "majors": [], "languages": ["chinese"], "language_level": ["proficiency"], "hard_skills": ["excel", "chinese word processing", "powerpoint", "problem solving skills", "processing", "ms word"], "soft_skills": ["communication skills", "interpersonal skill", "handle multiple tasks", "analytical mind", "attention to details", "problem solving skills", "proactive"], "languages_combined": [{"language": "chinese", "language_level": ["proficiency"]}]}, "experience_required": {"duration": [], "field": ["food industry", "qa"]}}, {"job_id": "100003009042042", "location_code": "hk", "company": "Fossil (East) Ltd", "job_title": "Core Master Coordinator", "description": "What\u2019s the role about?\nSet up and revise Master data includes finished goods & component item card, vendor card, bill of material & consignment table\nMonitor and review accuracy of master data completed by other colleagues\nGeneral filing and clerical task\nWhat we are looking for:\n\nDiploma or above or any equivalent\nWell-organized, detail-oriented, have analytical mind and high sense of responsibility\nAble to work flexible, multi-task and under pressure\n\nTogether, we make great things happen. Apply now and be part of our tomorrow.\n\nInterested parties please send us your full resume with contact details, preferably with your current and expected salary.\n\nFossil Group is an Equal Opportunity employer. All qualified applicants will receive consideration of employment without regard to race, disability, gender, religion, family status, marital status, national origin, sexual orientation, veteran status, gender identity or \u00a0expression or any other basis protected by local, state, or national law. Only short-listed candidates will be notified. All information received will be kept in strict confidence and only for employment-related purpose.", "employment_types": ["Full Time", "Permanent"], "selling_points": ["Set up and revise data of finished goods, BOM", "Monitor and review accuracy of master data", "General filing and clerical task"], "locations": ["Tsuen Wan Area"], "categories": ["Admin & HR", "Clerical / Admin Staff", "Manufacturing", "Production Planning / Control", "Others"], "post_time": "2022-01-12T05:39:41Z", "salary": {"currency": null, "max": null, "min": null, "period": "monthly", "term": null}, "salary_visible": false, "title_keywords": ["coordinator"], "responsibilities": ["review", "monitor", "data"], "requirements": {"degrees": ["diploma or above", "master"], "majors": [], "languages": [], "language_level": [], "hard_skills": ["make", "vendor"], "soft_skills": ["flexible", "multi-task", "under pressure", "high sense of responsibility", "well-organized", "detail-oriented", "analytical mind"], "languages_combined": []}, "experience_required": {"duration": [], "field": []}}, {"job_id": "100003009041873", "location_code": "hk", "company": "Lo Hong Ka (Hong Kong) Limited", "job_title": "\u98df\u54c1\u751f\u7522\u54e1", "description": "Job Description\n\nProvide clerical support to the Department\nSource, maintain and update\u00a0vendor database system\u00a0based on past vendor assessment, pricing, quality and other useful information.\nUpdate, organize and maintain systematic filing system for the Department\nPerform ad-hoc assignments and other duties as required\n\nJob Specification\n\nForm\u00a05 or above.\nRelevant experience\u00a0in\u00a0food industry is preferred.\nExperience in manufacturing working environment is an advantage.\nInitiative and be a good team player.\nGood command\u00a0in using MS Office applications (i.e. Excel, Word & PowerPoint).\u00a0\nApplicant please email DETAILED RESUME with present & expected salary to Human Resources Dept.\n\n\n(All personal data collected\u00a0will be\u00a0used for recruitment purpose only)", "employment_types": ["Full Time"], "selling_points": [], "locations": ["Tsuen Wan Area"], "categories": ["Hospitality / F & B", "Others", "Manufacturing", "Others", "Others", "Others"], "post_time": "2022-01-12T04:32:51Z", "salary": {"currency": null, "max": null, "min": null, "period": "monthly", "term": null}, "salary_visible": false, "title_keywords": [], "responsibilities": ["provide clerical support", "other duties", "ad-hoc assignments", "quality", "maintain", "recruitment", "database", "personal data"], "requirements": {"degrees": ["form 5 or above"], "majors": [], "languages": [], "language_level": [], "hard_skills": ["excel", "vendor", "powerpoint", "word", "ms office"], "soft_skills": ["good team player", "initiative", "systematic", "detailed"], "languages_combined": []}, "experience_required": {"duration": [], "field": ["manufacturing", "relevant experience", "food industry"]}}, {"job_id": "100003009038232", "location_code": "hk", "company": "Crowne Plaza Hong Kong Causeway Bay", "job_title": "Assistant Procurement Manager", "description": "Job Responsibilities\n\nEnsure all purchases are in line with the Hotel policy;\nObtains competitive quotations and bids and ensure proper documentation for purchasing records;\nPosts orders to inventory module and produce purchase order for receiver to match against goods received;\nMaintain all F&B suppliers to fulfill the Hotel hygiene standard.\n\nJob Requirements\n\nCertificate in hotel or catering management or related field;\n4-5 years related experience in the hotel industry;\nProficient in PC application and MC system;\nGood communication and interpersonal skills;\nGood command of English and Chinese.", "employment_types": ["Full Time"], "selling_points": ["4-5 years related experience", "Good communication and interpersonal skills", "Proficient in MC system"], "locations": ["Causeway Bay"], "categories": ["Hospitality / F & B", "Hospitality / Hotel Services", "Manufacturing", "Others", "Merchandising & Purchasing", "Procurement / Purchasing / Sourcing"], "post_time": "2022-01-11T06:15:51Z", "salary": {"currency": null, "max": null, "min": null, "period": "monthly", "term": null}, "salary_visible": false, "title_keywords": ["manager", "assistant"], "responsibilities": ["inventory", "hygiene", "purchase", "maintain", "documentation"], "requirements": {"degrees": ["certificate"], "majors": ["hotel"], "languages": ["english", "chinese"], "language_level": ["good command"], "hard_skills": ["pc"], "soft_skills": ["communication and interpersonal skills"], "languages_combined": [{"language": "english", "language_level": ["good command"]}, {"language": "chinese", "language_level": ["good command"]}]}, "experience_required": {"duration": ["4-5 years"], "field": ["related", "hotel industry"]}}, {"job_id": "100003009049859", "location_code": "hk", "company": "Orient Overseas Container Line Ltd (OOCL)", "job_title": "Officer/Senior Officer, Traffic Control Center", "description": "\nWelbot Technology is a pioneering technology company specializing in robotic solutions that redefine the construction automation workflow in the industry.\n\nOur Adaptive Robotic Welder has qualified for Welding Procedure Specification(WPS), fully capable of working under harsh environmental conditions. Our technological innovation not only brings new blood into the labour market, but also reforms the traditional working nature.\n\nIn the future, Welbot Technology will continue to sharpen its competitive edge. With the adoption of Building Information Modelling (BIM), big data and cutting-edge 5G technology into AI-based robotic systems, we are well poised to make a breakthrough in the eco platform of construction robotic solutions.\n\n\u8077\u8cac:\n\u65bc\u5730\u76e4\u4e3b\u7ba1\u5e36\u9818\u53ca\u6307\u5c0e\u4e0b,\u64cd\u4f5c\u6a5f\u68b0\u81c2\u9032\u884c\u5efa\u7bc9\u5730\u76e4\u5de5\u4f5c\n\n\u5354\u52a9\u5de5\u7a0b\u5e2b\u5728\u5de5\u5834\u9032\u884c\u79d1\u7814\n\n\u57f7\u884c\u4e0a\u7d1a\u6307\u6d3e\u7684\u5176\u4ed6\u8077\u52d9 \u8cc7\u6b77\n\n\u7121\u9700\u5de5\u4f5c\u7d93\u9a57 \u2022 \u7121\u9700\u5b78\u6b77\n\n\u826f\u597d\u7cb5\u8a9e\n\n\u6301\u6709\u5e73\u5b89\u5361\u53ca\u5de5\u4eba\u8a3b\u518a\u8a3c\u512a\u5148\n\n\u6301\u6709\u71d2\u710a\u5927\u5de5\u724c\u6703\u7372\u8058\u7528\u70ba\u9ad8\u7d1a\u6280\u8853\u54e1\n\n\u5177\u5718\u968a\u7cbe\u795e, \u8aa0\u5be6\u6709\u79ae, \u6709\u8010\u5fc3\u53ca\u7d30\u5fc3, \u6709\u8cac\u4efb\u611f, \u5de5\u4f5c\u7a4d\u6975\u4e3b\u52d5\n\n\u798f\u5229:\n\u6bcf\u9031\u5de5\u4f5c5-6\u5929\n\n\u914c\u60c5\u6027\u82b1\u7d05\n\n\u5728\u8077\u57f9\u8a13\n\n\u5e74\u504710\u5929\n\n\u751f\u65e5\u5047\n\n\u91ab\u7642\u4fdd\u96aa\n\n\u85aa\u916c: $15,000.00\u81f3$20,000.00(\u6bcf\u6708)\u8d77\n\nInterested candidates please apply with full resume, present & expected salary, available date by clicking \"Apply Now\". For further information, please visit our company website: https://www.welbot-tech.com/\n\nAll data collected will be used for recruitment purpose only.\n\nFull-time,Permanent\n\n", "employment_types": ["Full Time", "Permanent"], "selling_points": ["To maximize vessel utilization of assigned service", "University graduate in Business or related", "At least 3 years relevant work experience"], "locations": ["Wan Chai"], "categories": ["Transportation & Logistics", "Shipping", "Manufacturing", "Others", "Quality Assurance, Control & Testing / ISO"], "post_time": "2022-01-14T09:19:28Z", "salary": {"currency": null, "max": null, "min": null, "period": "monthly", "term": null}, "salary_visible": false, "title_keywords": ["officer", "senior officer"], "responsibilities": ["systems", "big data"], "requirements": {"degrees": [], "majors": [], "languages": [], "language_level": [], "hard_skills": ["building information modelling", "make", "bim", "ai"], "soft_skills": ["capable", "cutting-edge"], "languages_combined": []}, "experience_required": {"duration": [], "field": []}}, {"job_id": "100003009047496", "location_code": "hk", "company": "Welbot Technology Limited", "job_title": "\u9ad8\u7d1a\u6a5f\u68b0\u64cd\u4f5c\u54e1 / \u6a5f\u68b0\u64cd\u4f5c\u54e1 (\u5730\u76e4)", "description": "What\u2019s the role about?\nDrive the development process and product plans from the design concept to sample\u00a0approval.\nMonitor the works with vendors to ensure daily\u00a0operations run smoothly\nReview and provide recommendations for product improvement and valued\nengineering\nManage and contribute to design proposals, sourcing and pricing\nCollaborate with Supply Chain Management Team and Quality Assurance Team to\nensure production and quality standard.\u00a0Monitor product testing (including wear test)\nto meet product safety standard\nCommunicate effectively with key stakeholders locally and globally\nResponsible for accuracy of data setup attributes into the component materials\ninformation system\nWhat we are looking for:\n\nDiploma or above or any equivalent\nMinimum\u00a05 years of relevant experience\nFamiliar with product safety specification\nWell-organized, detail-oriented, have analytical mind and high sense of responsibility\nAble to work flexible, multi-task and under pressure\nKnowledge in both Watch and Jewelry fields is an advantage\nFamiliar with PLM system is a definite advantage\nGood command in both spoken and written English\n\nTogether, we make great things happen. Apply now and be part of our tomorrow.\n\nInterested parties please send us your full resume with contact details, preferably with your current and expected salary.\n\nFossil Group is an Equal Opportunity employer. All qualified applicants will receive consideration of employment without regard to race, disability, gender, religion, family status, marital status, national origin, sexual orientation, veteran status, gender identity or \u00a0expression or any other basis protected by local, state, or national law. Only short-listed candidates will be notified. All information received will be kept in strict confidence and only for employment-related purpose.", "employment_types": ["Full Time"], "selling_points": ["-", "-", "-"], "locations": ["Not Specified"], "categories": ["Engineering", "Mechanical", "Manufacturing", "Others", "Printing"], "post_time": "2022-01-14T03:20:21Z", "salary": {"currency": null, "max": null, "min": null, "period": "monthly", "term": null}, "salary_visible": false, "title_keywords": [], "responsibilities": ["collaborate with", "management team", "data", "design concept", "review", "monitor", "quality", "design", "testing", "daily operations", "provide recommendations", "plans", "setup"], "requirements": {"degrees": ["diploma or above"], "majors": [], "languages": ["english"], "language_level": ["good command"], "hard_skills": ["make", "information system"], "soft_skills": ["flexible", "multi-task", "under pressure", "responsible", "high sense of responsibility", "well-organized", "detail-oriented", "analytical mind"], "languages_combined": [{"language": "english", "language_level": ["good command"]}]}, "experience_required": {"duration": ["minimum 5 years"], "field": ["relevant experience"]}}, {"job_id": "100003009042045", "location_code": "hk", "company": "Fossil (East) Ltd", "job_title": "Senior Product Executive - Watch", "description": "\u4e2d\u4e94\u6216\u4ee5\u4e0a\n\u9808\u5177\u4e09\u5e74\u76f8\u95dc\u5009\u52d9/\u7269\u6d41\u7d93\u9a57\n\u8655\u7406\u65e5\u5e38\u7269\u6599\u51fa\u5165\u6d41\u7a0b\u3001\u6536\u8ca8\u3001\u767c\u8ca8\u53ca\u8a18\u9304\uff0c\u5b9a\u671f\u9032\u884c\u7269\u6599\u76e4\u9ede\n\u8655\u7406\u7269\u6599\u76e3\u63a7\u7cfb\u7d71\n\u5177\u826f\u597d\u6e9d\u901a\u6280\u5de7\n\u9700\u61c9\u4ed8\u4e00\u822c\u9ad4\u529b\u52de\u52d5\u5de5\u4f5c\n\u5177\u6709\u57fa\u672c\u96fb\u8166\u61c9\u7528\u77e5\u8b58(MS office, \u4e2d\u6587\u8f38\u5165\u6cd5)\n\u6301\u6709\u6709\u6548\u5277\u8eca\u64cd\u4f5c\u8a3c(\u6258\u76e4\u5806\u758a/\u4f38\u5c55\u578b)\u70ba\u4f73\n\u9700\u8f2a\u73ed\u5de5\u4f5c\n\n\u672c\u516c\u53f8\u63d0\u4f9b\u512a\u539a\u85aa\u916c\u53ca\u798f\u5229\uff0c\u5305\u62ec\u5e74\u7d42\u916c\u91d1\u3001\u91ab\u7642\u53ca\u4eba\u58fd\u4fdd\u96aa\u3001\u81b3\u98df\u53ca\u4ea4\u901a\u6d25\u8cbc\u7b49\uff0c\u52de\u5de5\u5047\u671f\u3002\u6709\u610f\u8005\u8acb\u5c07\u500b\u4eba\u5c65\u6b77\u3001\u5de5\u4f5c\u7d93\u9a57\u3001\u806f\u7d61\u5730\u5740\u53ca\u96fb\u8a71\uff0c\u51fd\u5bc4\u65b0\u754c\u5927\u57d4\u5de5\u696d\u90a8\u5927\u76db\u88572-4\u865f\u4eba\u4e8b\u53ca\u884c\u653f\u90e8\u6536\u6216\u6309\"APPLY NOW\"\u63d0\u4ea4\u7533\u8acb\u6216\u50b3\u771f\u81f32664 4882\u3002\n\n\n(\u7533\u8acb\u4eba\u6240\u63d0\u4f9b\u7684\u8cc7\u6599\u5c07\u4e88\u4fdd\u5bc6\u53ca\u53ea\u4f9b\u7533\u8acb\u6709\u95dc\u8077\u4f4d\u7528\u9014)", "employment_types": ["Full Time"], "selling_points": ["Drive the development process and product plans", "Monitor the works with vendors", "Manage design proposals, sourcing and pricing"], "locations": ["Tsuen Wan Area"], "categories": ["Manufacturing", "Jewelry", "Product Development / Management", "Others"], "post_time": "2022-01-12T05:40:41Z", "salary": {"currency": null, "max": null, "min": null, "period": "monthly", "term": null}, "salary_visible": false, "title_keywords": ["senior product executive"], "responsibilities": [], "requirements": {"degrees": [], "majors": [], "languages": [], "language_level": [], "hard_skills": [], "soft_skills": [], "languages_combined": []}, "experience_required": {"duration": [], "field": []}}, {"job_id": "100003009036974", "location_code": "hk", "company": "\u9999\u6e2f\u5370\u9214\u6709\u9650\u516c\u53f8", "job_title": "\u7269\u6599\u63a7\u5236\u54e1 (Materials Inspector)", "description": "We look for true TALENTS and outstanding personalities!\n\nJoin our team as\n\nProduct & Graphic Designer\n\n\u00a0Job Location\n\n\nTsim Sha Tsui East, Kowloon, Hong Kong\n\nLanguages\u00a0\nMinimum oral and written proficiency in English, other languages are welcome\n\nEducation\u00a0 \u00a0\nTertiary or Diploma level in Graphic & Packaging / Product Design and or Design for consumer goods.\u00a0\nExperienced in working with international companies.\n\n\nMost important Requirements\nAT LEAST 2 YEARS OF EXPEREINCE IN SIMILAR POSITION;\n\nCREATIVE-OUTSIDE OF THE BOX THINKING PERSONALITY;\nKNOWLEDGE OF 3D SOFTWARE AND 3D PRINTING SYSTEMS (SLA);\n\nCAPABLE TO FULLY USE:\u00a0RHINO, KEYSHOT, PHOTOSHOP, ILLUSTRATOR, INDESIGN, POWERPOINT;\n\nCAPABLE FOR FREE HAND DESIGN;\n\nCAPABLE TO IN-CHARGE OFFICE SHOWROOM & INTERNATIONAL FAIRS;\n\nCAPABLE TO INDEPENDENTLY WORK UNDER PRESSURE;\n\nCAPABLE TO EXECUTE IN A FAST-PACED PROFESSIONAL ENVIRONMENT TO REDUCE ANY ALARMING DEADLINES.\n\nWe offer \u2026true challenges and for sure you will\u2026\u00a0\nMAKE CONCEPT PRESENTATIONS IN MULTI MEDIA FORMAT AND/OR POWERPOINT CREATE GREAT PACKAGING AND GRAPHICS;\n\nHELP TO DEVELOP NEW PRODUCTS TOGETHER WITH A PROFESSIONAL TEAM YOU WILL MAKE PROTOTYPES (3D PRINTING AND MODELLING).\u00a0\n\n*WE CAN ALSO OFFER APPLICATION ON HK WORKING VISA FOR APPROPRIATE CANDIDATE*\n\n\nAvailability: Negotiable\n\n\nSalary: Fair and based on the experience and the qualification\n\n\nPlease send full resume and\u00a0DESIGN PORTFOLIO\u00a0with the above reference quoted via email indicating current and expected salary and visit our homepage.\n\nwww.joker-group.net\n\n*APPLICATION WITHOUT PROPER PORTFOLIO INCLUDED WILL NOT BE CONSIDERED*\n\n\nPersonal data collected will be used for recruitment purpose only.", "employment_types": ["Full Time"], "selling_points": [], "locations": ["Tai Po Area"], "categories": ["Manufacturing", "General / Production Workers", "Others", "Printing"], "post_time": "2022-01-11T01:11:24Z", "salary": {"currency": null, "max": null, "min": null, "period": "monthly", "term": null}, "salary_visible": false, "title_keywords": [], "responsibilities": [], "requirements": {"degrees": [], "majors": [], "languages": [], "language_level": [], "hard_skills": [], "soft_skills": [], "languages_combined": []}, "experience_required": {"duration": [], "field": []}}, {"job_id": "100003009044106", "location_code": "hk", "company": "JOKER (FAR EAST) LTD.", "job_title": "Product & Graphic Designer (Ref. PGD_Jan2022)", "description": "Responsibilities\nParticipate in internal / external audits\nProvide on-site coaching to frontline staff\nPrepare and review SOP and other quality related documents\nConduct quality control inspections and attend meetings\nAssist to identify operational deficiency and suggest corrective / preventive plans\nAssist in implementing and maintaining quality projects\nAny ad hoc duties as assigned by superior\nRequirements\nDiploma level or above\n1 years\u2019 relevant experience in air cargo industry is highly preferred\nWork independently and attention in detail\nStrong sense of responsibility and good interpersonal skills\nFluency in spoken and written Chinese and English\nProficient in MS applications including Word, Excel and Powerpoint\nCandidate with more relevant experience will be considered as Senior Quality Assurance Officer\nInterested parties, please send application with full particulars of qualifications, experience, current and expected salary by email via \"Apply Now\"\nAll information will be kept confidential and used for recruitment purpose only.", "employment_types": ["Full Time", "Permanent"], "selling_points": [], "locations": ["Tsim Sha Tsui"], "categories": ["Design", "Graphics", "Industrial / Product", "Manufacturing", "Others"], "post_time": "2022-01-13T03:04:51Z", "salary": {"currency": null, "max": null, "min": null, "period": "monthly", "term": null}, "salary_visible": false, "title_keywords": ["graphic designer"], "responsibilities": ["ad hoc duties", "conduct quality control", "maintaining", "related documents", "review", "quality", "attend meetings", "audits", "plans"], "requirements": {"degrees": ["diploma"], "majors": [], "languages": ["english", "chinese"], "language_level": ["fluency"], "hard_skills": ["excel", "ms applications", "word", "powerpoint"], "soft_skills": ["work independently", "interpersonal skills", "sense of responsibility"], "languages_combined": [{"language": "english", "language_level": ["fluency"]}, {"language": "chinese", "language_level": ["fluency"]}]}, "experience_required": {"duration": ["1 years"], "field": ["relevant experience", "quality assurance"]}}, {"job_id": "100003009050387", "location_code": "hk", "company": "Fly King Transportation Company Ltd", "job_title": "Quality Assurance Officer", "description": "Job Description\n\nWe\u2019re looking for Internet of Things (IoT) Software Engineer to join us and who\u2019ll be responsible for developing of IoT web apps based on open source IoT platform. In this role you will be writing, testing and deploying web apps to run on Docker containers deployed on the Gateway (Raspberry Pi).\n\nRequirements:\n\n\u00a0\u00a0\u00a0\u00a0\u00a0 \u00a0Bachelor\u2019s or Master\u2019s degree in Computer Science or Engineering\n\u00a0\u00a0\u00a0\u00a0\u00a0\u00a0\u00a0Define and implement web apps with front-end technologies (Typescript)\n\u00a0\u00a0\u00a0\u00a0\u00a0\u00a0\u00a0Building and running source code for Docker images (Gradle)\n\u00a0\u00a0\u00a0\u00a0\u00a0\u00a0\u00a0Debugging of source code on Docker container (IntelliJ or Eclipse)\n\u00a0\u00a0\u00a0\u00a0\u00a0\u00a0\u00a0Programming skills to implement REST services (Java)\n\u00a0\u00a0\u00a0\u00a0\u00a0\u00a0\u00a0Understanding of IoT hardware and wireless networks (Bluetooth)\n\u00a0\u00a0\u00a0\u00a0\u00a0\u00a0\u00a0Proficient in written and verbal English\n\u00a0\u00a0\u00a0\u00a0\u00a0\u00a0\u00a0Collaborate with the other software developers\n\nQualification:\n\n\u00a0\u00a0\u00a0\u00a0\u00a0\u00a0\u00a0\u00a0For this position, we'd like to see level of expertise of web development\n\n\u00a0\u00a0\u00a0\u00a0 (Typescript, JavaScript, HTML, CSS, JWT, JSON)\n\n\u00a0\u00a0\u00a0\u00a0\u00a0\u00a0\u00a0Software development experience using web frameworks such\n\n\u00a0\u00a0\u00a0\u00a0 as Angular or React with Redux and React Router\n\n\u00a0\u00a0\u00a0\u00a0\u00a0\u00a0\u00a0Building IoT platform requires also knowledge of server software\n\n\u00a0\u00a0\u00a0\u00a0 development (REST, PostgreSQL)\n\n\u00a0\u00a0\u00a0\u00a0\u00a0\u00a0\u00a0Good knowledge of connectivity protocols (HTTP, TCP/IP and MQTT)\n\u00a0\u00a0\u00a0\u00a0\u00a0\u00a0\u00a0Understanding of authorization, authentication and security\n\n\u00a0\u00a0\u00a0\u00a0\u00a0 protocols (Keycloak, OAuth)\n\n\u00a0\u00a0\u00a0\u00a0\u00a0\u00a0\u00a0Ability to create and configure security certificates and\n\n\u00a0\u00a0\u00a0\u00a0\u00a0 keys (SSL, CA and TLS)\n\n\u00a0\u00a0\u00a0\u00a0\u00a0\u00a0\u00a0Utilizing Linux shell scripts (sh or bash)\n\u00a0\u00a0\u00a0\u00a0\u00a0\u00a0\u00a0Familiar with Linux operating systems (Ubuntu or Debian)\n\u00a0\u00a0\u00a0\u00a0\u00a0\u00a0\u00a0Experience to create commands in Dockerfiles (Docker)\n\u00a0\u00a0\u00a0\u00a0\u00a0\u00a0\u00a0Cloud computing basics (AWS, Azure or Google)", "employment_types": ["Full Time", "Permanent"], "selling_points": [], "locations": ["Airport Area"], "categories": ["Transportation & Logistics", "Others", "Manufacturing", "Others", "Quality Assurance, Control & Testing / ISO"], "post_time": "2022-01-14T10:15:56Z", "salary": {"currency": null, "max": null, "min": null, "period": "monthly", "term": null}, "salary_visible": false, "title_keywords": ["quality assurance officer"], "responsibilities": ["testing", "software", "developing"], "requirements": {"degrees": ["degree", "bachelor", "master"], "majors": ["engineering", "computer science"], "languages": ["english"], "language_level": ["proficient"], "hard_skills": ["azure", "web", "server", "java", "tcp", "code", "web development", "web apps", "html", "router", "aws", "typescript", "container", "javascript", "angular", "linux", "react", "bash", "hardware", "ip", "programming", "css"], "soft_skills": [], "languages_combined": [{"language": "english", "language_level": ["proficient"]}]}, "experience_required": {"duration": [], "field": ["software development"]}}, {"job_id": "100003009050085", "location_code": "hk", "company": "Karrie International Holdings Limited", "job_title": "Assistant Mechanical Engineering Manager/Senior Mechanical Engineer (Based in Dongguan)", "description": "Responsibilities\n\nMaintain a documentation system in order to comply with GMP requirements, e.g batch production record, logbooks, labels & documents related to production\nUpdate data in ERP system in a timely and accurate manner\nMonitor and maintain inventory stock of production consumables\nAssist in scheduling and arrangement of the staff annual medical checkup\nPerforms administrative work including staff leave balance\nAny other production related duties that may be assigned if necessary.\nRequirements\n\nForm 5 or DSE or equivalent. Vocational Training Council in clerical position or job\u2013related experience is an advantage.\nAble to read and write in Chinese and English.\nFamiliar with Microsoft office e.g. MS Excel, MS Word", "employment_types": ["Full Time", "Permanent"], "selling_points": ["Product design of plastic and sheet metal", "Proceed mechanical design with Creo", "Formulates project plan of mechanical engineering"], "locations": ["Others - China"], "categories": ["Engineering", "Manufacturing & Production", "Mechanical", "Manufacturing", "Others"], "post_time": "2022-01-15T03:50:49Z", "salary": {"currency": null, "max": null, "min": null, "period": "monthly", "term": null}, "salary_visible": false, "title_keywords": ["senior mechanical engineer", "engineering manager", "assistant"], "responsibilities": ["administrative work", "data", "inventory", "monitor", "scheduling", "maintain", "documentation", "staff leave"], "requirements": {"degrees": ["form 5", "dse"], "majors": [], "languages": ["english", "chinese"], "language_level": [], "hard_skills": ["ms word", "ms excel", "microsoft office"], "soft_skills": [], "languages_combined": [{"language": "english", "language_level": []}, {"language": "chinese", "language_level": []}]}, "experience_required": {"duration": [], "field": ["related", "training", "clerical"]}}, {"job_id": "100003009040186", "location_code": "hk", "company": "Fortune Pharmacal Company Limited", "job_title": "Administrative Assistant (Production)", "description": "\n\u8077\u8cac :\u4e00\u822c\u751f\u7522\u5305\u88dd\u5de5\u4f5c, \u7c21\u55ae\u98df\u7269\u751f\u7522\u5de5\u4f5c\u53ca\u5354\u52a9\u5176\u4ed6\u98df\u54c1\u88fd\u4f5c\n\n\u8cc7\u6b77 :\u5c0f\u516d\u7a0b\u5ea6; 6\u500b\u6708\u7d93\u9a57; \u826f\u597d\u7cb5\u8a9e; \u61c2\u95b1\u8b80\u4e2d\u6587\n\n\u5f85\u9047 :\u6bcf\u5c0f\u6642$60.00 - $70.00, \u6709\u5728\u8077\u57f9\u8a13, \u661f\u671f\u4e00\u81f3\u516d: \u4e0a\u53488\u6642\u81f3\u4e0b\u53486\u6642, \u6bcf\u9031\u5de5\u4f5c3\u5929\u81f34\u5929, \u6bcf\u5929\u5de5\u4f5c 4 - 6 \u5c0f\u6642\n\n\u7533\u8acb\u9808\u77e5 :\u6c42\u8077\u8005\u53ef\u81f4\u96fb22685306(Ext.332)\u8207\u6d77\u7687\u570b\u969b\u6709\u9650\u516c\u53f8\u9ec3\u5c0f\u59d0\u806f\u7d61\u3002\n\n", "employment_types": ["Full Time"], "selling_points": ["Knowledge in ERP system is an advantage", "Administrative support", "New manufacturing plant at Yuen Long"], "locations": ["Yuen Long"], "categories": ["Admin & HR", "Clerical / Admin Staff", "Manufacturing", "Others", "Medical Services", "Pharmaceutical"], "post_time": "2022-01-12T01:47:45Z", "salary": {"currency": null, "max": null, "min": null, "period": "monthly", "term": null}, "salary_visible": false, "title_keywords": ["administrative assistant"], "responsibilities": [], "requirements": {"degrees": [], "majors": [], "languages": [], "language_level": [], "hard_skills": [], "soft_skills": [], "languages_combined": []}, "experience_required": {"duration": [], "field": []}}, {"job_id": "100003009041108", "location_code": "hk", "company": "Ocean Empire International Limited", "job_title": "\u517c\u8077\u751f\u7522\u64cd\u4f5c\u54e1**", "description": "\n\u8077\u8cac :\u8ca0\u8cac\u6e05\u6d17\u73bb\u7483\u6a3d\u3001\u7be9\u9078\u71d5\u7aa9\u96dc\u8cea\uff1b\u5354\u52a9\u88fd\u4f5c\u3001\u52a0\u5de5\u98df\u54c1\u751f\u7522\uff1b\u4e00\u822c\u98df\u54c1\u5de5\u5834\u96dc\u52d9\n\n\u8cc7\u6b77 :\u5c0f\u516d\u7a0b\u5ea6; \u826f\u597d\u7cb5\u8a9e; \u61c2\u95b1\u8b80\u4e2d\u6587; \u5177\u98df\u54c1\u751f\u7522\u53ca\u5305\u88dd\u7d93\u9a57\u512a\u5148; \u5de5\u4f5c\u6709\u8010\u6027\u53ca\u52e4\u596e\n\n\u5f85\u9047 :\u6bcf\u6708$12,000, \u6709\u54e1\u5de5\u8cfc\u7269\u512a\u60e0, \u91ab\u7642\u798f\u5229 \u53ca\u8d85\u6642\u5de5\u4f5c\u6d25\u8cbc, \u661f\u671f\u4e00\u81f3\u516d: \u4e0a\u53489\u6642\u81f3\u4e0b\u53486\u6642, \u6bcf\u9031\u5de5\u4f5c6\u5929\n\n\u7533\u8acb\u9808\u77e5 :\u6c42\u8077\u8005\u53ef\u81f4\u96fb28323162\u8207\u8001\u884c\u5bb6(\u9999\u6e2f)\u6709\u9650\u516c\u53f8\u9127\u5c0f\u59d0\u806f\u7d61\u3002\n\n", "employment_types": ["Part Time"], "selling_points": [], "locations": ["Shatin Area"], "categories": ["Hospitality / F & B", "Food & Beverage", "Manufacturing", "General / Production Workers", "Others"], "post_time": "2022-01-12T03:28:01Z", "salary": {"currency": null, "max": null, "min": null, "period": "hourly", "term": null}, "salary_visible": false, "title_keywords": [], "responsibilities": [], "requirements": {"degrees": [], "majors": [], "languages": [], "language_level": [], "hard_skills": [], "soft_skills": [], "languages_combined": []}, "experience_required": {"duration": [], "field": []}}, {"job_id": "100003009036978", "location_code": "hk", "company": "\u9999\u6e2f\u5370\u9214\u6709\u9650\u516c\u53f8", "job_title": "\u7d44\u9577(\u8cea\u91cf\u5be9\u67e5) (Supervisor (QA))", "description": "\u5de5\u4f5c\u7bc4\u570d\n\u76e3\u5bdf\u65e5\u5e38\u8cea\u91cf\u5be9\u67e5\u5de5\u4f5c\n\u8ca0\u8cac\u9032\u884c\u539f\u6750\u6599,\u534a\u6210\u54c1\u53ca\u6210\u54c1\u7684\u5316\u5b78,\u7269\u7406\u5316\u9a57\u53ca\u76ee\u6e2c\u7b49\u5de5\u4f5c\n\u8ca0\u8cac\u64b0\u5beb\u9a57\u6e2c\u5831\u544a\n\u8ca0\u8cac\u5316\u9a57\u5ba4\u5100\u5668\u6821\u6b63\u53ca\u4fdd\u990a\u5de5\u4f5c\n\u8ca0\u8cac\u64b0\u5beb\u8cea\u91cf\u5be9\u67e5\u6587\u4ef6(\u5de5\u4f5c\u6307\u793a,\u7269\u6599\u898f\u683c,\u7cfe\u6b63\u53ca\u9810\u9632\u884c\u52d5\u5831\u544a\u7b49)\n\u8ca0\u8cac\u8655\u7406\u7531\u52a9\u7406\u7d93\u7406(\u8cea\u91cf\u5be9\u67e5)\u59d4\u6d3e\u7684\u5176\u5b83\u5de5\u4f5c\n\n\u8077\u4f4d\u8981\u6c42\n\n\u5316\u5b78\u79d1\u6280\u9ad8\u7d1a\u6587\u6191/\u61c9\u7528\u79d1\u5b78\u9ad8\u7d1a\u6587\u6191\u7b49\u6216\u4ee5\u4e0a\u76f8\u95dc\u5b78\u6b77\n\u9808\u5177\u6700\u5c11\u4e09\u5e74\u76f8\u95dc\u5de5\u4f5c\u7d93\u9a57\n\u719f\u6089ISO\u7ba1\u7406\u7cfb\u7d71\n\u80fd\u66f8\u5beb\u4e2d\u82f1\u6587\u53ca\u64cd\u5ee3\u6771\u8a71\u3001\u82f1\u8a9e\u53ca\u666e\u901a\u8a71\n\u61c2\u5f97\u904b\u7528\u96fb\u8166\u8edf\u4ef6(\u6587\u66f8\u8655\u7406(\u5305\u62ec\u4e2d\u6587\u8f38\u5165\u6cd5), \u8a66\u7b97\u8868, \u7c21\u5831\u53ca\u6295\u5f71\u7247\u7b49)\n\u7d30\u5fc3,\u6709\u8cac\u4efb\u5fc3,\u4e3b\u52d5\u53ca\u5177\u5099\u826f\u597d\u6e9d\u901a\u6280\u5de7\n\u5177\u5099\u908f\u8f2f\u601d\u7dad\u53ca\u5206\u6790\u80fd\u529b\n\u9808\u8f2a\u73ed\u5de5\u4f5c\n\n(\u6b61\u8fce\u65b0\u7562\u696d\u4eba\u58eb\u7533\u8acb)\n\n\u00a0\u672c\u516c\u53f8\u63d0\u4f9b\u512a\u539a\u85aa\u916c\u53ca\u798f\u5229\uff0c\u5305\u62ec\u5e74\u7d42\u916c\u91d1\u3001\u91ab\u7642\u53ca\u4eba\u58fd\u4fdd\u96aa\u3001\u81b3\u98df\u53ca\u4ea4\u901a\u6d25\u8cbc\u7b49\uff0c\u52de\u5de5\u5047\u671f\u3002\u6709\u610f\u8005\u8acb\u5c07\u500b\u4eba\u5c65\u6b77\u3001\u5de5\u4f5c\u7d93\u9a57\u3001\u806f\u7d61\u5730\u5740\u53ca\u96fb\u8a71\uff0c\u51fd\u5bc4\u65b0\u754c\u5927\u57d4\u5de5\u696d\u90a8\u5927\u76db\u88572-4\u865f\u4eba\u4e8b\u53ca\u884c\u653f\u90e8\u6536\u6216\u6309\"APPLY NOW\"\u63d0\u4ea4\u7533\u8acb\u6216\u50b3\u771f\u81f32664 4882\u3002\n\n(\u7533\u8acb\u4eba\u6240\u63d0\u4f9b\u7684\u8cc7\u6599\u5c07\u4e88\u4fdd\u5bc6\u53ca\u53ea\u4f9b\u7533\u8acb\u6709\u95dc\u8077\u4f4d\u7528\u9014)\n\n*(\u6b61\u8fce\u65b0\u7562\u696d\u4eba\u58eb\u7533\u8acb)", "employment_types": ["Full Time"], "selling_points": [], "locations": ["Tai Po Area"], "categories": ["Manufacturing", "Others", "Printing", "Quality Assurance, Control & Testing / ISO"], "post_time": "2022-01-11T01:11:46Z", "salary": {"currency": null, "max": null, "min": null, "period": "monthly", "term": null}, "salary_visible": false, "title_keywords": ["supervisor"], "responsibilities": [], "requirements": {"degrees": [], "majors": [], "languages": [], "language_level": [], "hard_skills": [], "soft_skills": [], "languages_combined": []}, "experience_required": {"duration": [], "field": []}}, {"job_id": "100003009037540", "location_code": "hk", "company": "DKSH Hong Kong Limited", "job_title": "Assistant Officer, Supply Chain Management (Fresh Graduates are welcome)", "description": "Job Responsibilities:\n\nSupport in day-to-day operating expenditures to ensure efficient usage of resources\nExecute and monitor relabeling and redressing policies, standards and operating procedures in compliance with good manufacturing practice (GMP) standards, ensure timely delivery of materials\u00a0\u00a0\nCoordinate resources with staff and contractors to meet the repackaging deadlines\nCoordinate contractors including selection of contractors, quotation negotiation, training and KPI review, to ensure fulfillment of contractual service commitments\nPrepare repackaging specializations\u00a0based on client's requirements\nReview, analyze and suggest improvements regarding quality, safety and standard operating procedures\nLiaise with clients on operational issues, enquiries and requests; escalate issues to manager, if necessary\n\nJob Requirements\n\nHKCEE or DSE above\n1 years logistics / supply chain / shipping operations experience is preferred\nProficiency in computer applications, including Excel and Word\nTactful interpersonal and communication skill to work with people in different levels\nSelf-motivated with strong sense of responsibility\nGood command of written and spoken English and Chinese (Cantonese)\nImmediate available is highly preferred\nFresh Graduates are welcome\n\n\n\nWe offer performance bonus and attractive benefits including medical insurance and company shuttle bus services to the right candidate. Interested parties please apply in full resume with current and expected salaries to Human Resources Department , DKSH Hong Kong Limited, 23rd Floor, Tower A, Southmark, 11 Yip Hing Street, Wong Chuk Hang, Hong Kong or by clicking \"Apply Now\"\n\nAll personal data collected will be used for recruitment purposes only. \u00a0Candidates will be contacted within 2 weeks if the background and experience are closely relevant to the job requirement.\n\nDrive Growth. Be the Difference. Join DKSH.\n\nDKSH\u2019s strength lies in our great diversity of services, industries, clients, products, regions and employees from various nationalities. We are proud of our people: they are the reason we are successful. Our people are the best in the industry. They are passionate about their career growth and about business success. They work as part of an energetic and committed team, positively impacting millions of lives through the products and services we provide. Join us today if you are ready to \u201cDrive growth. Be the Difference.\u201d With DKSH, you will experience a world of learning and development, own your career and take business responsibility and have a positive impact that touches people\u2019s lives.", "employment_types": ["Full Time", "Permanent"], "selling_points": ["Certificate or Diploma graduate", "Immediate available is highly preferred", "Fresh Graduates are welcome"], "locations": ["Kwai Tsing Area"], "categories": ["Transportation & Logistics", "Others", "Supply Chain", "Manufacturing", "Others"], "post_time": "2022-01-11T03:04:46Z", "salary": {"currency": null, "max": null, "min": null, "period": "monthly", "term": null}, "salary_visible": false, "title_keywords": ["assistant officer"], "responsibilities": ["liaise with clients", "policies", "fulfillment", "compliance", "monitor", "procedures", "quotation", "review", "coordinate", "quality", "suggest improvements"], "requirements": {"degrees": ["dse"], "majors": [], "languages": ["cantonese", "english", "chinese"], "language_level": ["good command"], "hard_skills": ["excel", "word"], "soft_skills": ["self-motivated", "sense of responsibility", "communication skill", "tactful", "interpersonal"], "languages_combined": [{"language": "cantonese", "language_level": ["good command"]}, {"language": "english", "language_level": ["good command"]}, {"language": "chinese", "language_level": ["good command"]}]}, "experience_required": {"duration": ["1 years"], "field": ["supply chain", "logistics"]}}, {"job_id": "100003009040154", "location_code": "hk", "company": "Hoe Hin Pak Fah Yeow Mfy Ltd", "job_title": "\u751f\u7522\u90e8\u7d44\u9577", "description": "\u5d17\u4f4d\u8981\u6c42:\n\n1. \u5177\u4e00\u822c\u5de5\u4f5c\u7d93\u9a57\n\n2. \u7d30\u5fc3, \u52e4\u596e, \u4e0d\u8fad\u52de\u82e6\n\n\u8077\u8cac:\n\n1. \u586b\u5beb\u751f\u7522\u6279\u8ca8\u8a18\u9304\n\n2. \u6309\u4e3b\u7ba1\u7684\u5de5\u4f5c\u5b89\u6392\u6aa2\u6536\u751f\u7522\u6240\u9700\u5305\u88dd\u7269\u6599\n\n3. \u78ba\u4fdd\u8eca\u9593\u6e05\u6f54\u53ca\u5728\u6709\u9700\u8981\u6642\u5b89\u6392\u6e05\u6f54\u54e1\u5de5\u57f7\u884c\u8eca\u9593\u6e05\u6f54\u8077\u52d9\n\n4. \u6309\u5236\u5b9a\u6709\u95dc\u6307\u5f15\u57f7\u884c\u5de5\u5e8f\n\n5. \u8ca0\u8cac\u76e3\u7763\u53ca\u6307\u5c0e\u7d44\u54e1\u9032\u884c\u5de5\u5e8f\n\n6. \u78ba\u4fdd\u6240\u6709\u5305\u88dd\u7a0b\u5e8f\u4e0a\u7684\u5de5\u85dd\u7b26\u5408\u6307\u5f15\n\n7. \u59a5\u5584\u4fdd\u5b58\u8f14\u52a9\u751f\u7522\u8a2d\u5099\n\n8.\u5354\u52a9\u8eca\u9593\u53ca\u5ee0\u52d9\u5de5\u4f5c", "employment_types": ["Full Time"], "selling_points": ["Manufactory", "Production", "Chai Wan"], "locations": ["Chai Wan"], "categories": ["Manufacturing", "Others"], "post_time": "2022-01-12T01:38:51Z", "salary": {"currency": null, "max": null, "min": null, "period": "monthly", "term": null}, "salary_visible": false, "title_keywords": [], "responsibilities": [], "requirements": {"degrees": [], "majors": [], "languages": [], "language_level": [], "hard_skills": [], "soft_skills": [], "languages_combined": []}, "experience_required": {"duration": [], "field": []}}, {"job_id": "100003009042930", "location_code": "hk", "company": "Wise Ally Holdings Limited", "job_title": "Manager -  Lean Manufacturing (Stationed in Dongguan)", "description": "Responsibilities:\nInitiate and manage the MIT (Manufacturing Improvement Team) with plant personnel driving production efficiency, OEE improvement and scrap reduction consistent with manufacturing goals and objectives\nCreate and present LEAN / cost savings analysis to plant management and staff to ensure proper justification of MIT processes\nManage a team of engineers and/or outside vendors for the development and debugging of internally designed machinery\nProvide expert services, inclusive of troubleshooting, upgrade recommendations, and quotes for new equipment, to various manufacturing facilities to evaluate current and new processes\nAssist in ad hoc projects as assigned\n\nRequirements:\u00a0\n\nBachelor degree in manufacturing, industrial, mechanical engineering or related engineering discipline\nMinimum 5 years\u2019 experience on PCBA / Electronic Industry, with minimum 5 years in managerial position and solid experience in Continuous Improvement in Production Process\nMust have the ability to critically analyze production equipment and recognize opportunities for efficiency improvements and cost savings\nSound understanding in LEAN and/or Six Sigma\nSolid experience in Lean Manufacturing Management, or related Continuous Improvement / Manufacturing Process Change management is an advantage\nKnowledge and experience in APQP, PPAP, MSA, PFMEA, 8D, 5 Why, Fishbone diagram, as well as KPI setting\n\nResult-oriented, teamwork, good communication and interpersonal skills\nGood command in both spoken and written English, Cantonese and Mandarin\nStationed in Dongguan China\nOccasional international travel will be required\nImmediately available is highly preferred\n\n*Candidate with more experience will be considered as\u00a0 Senior Manager - Lean Manufacturing\n\n\nWe offer 5-DAY WORK WEEK plus long term career prospect with competitive remuneration package, 13th-month salary, and fringe benefits to the right candidate. Interested parties please apply in full resume including current and expected salary by clicking APPLY NOW.\n\nFor more information, please visit our website:\u00a0 http://www.wiseally.com.hk/\n\nPersonal data collected will be used for recruitment purpose only.", "employment_types": ["Full Time", "Permanent"], "selling_points": ["Initiate and manage the MIT", "Create and present LEAN / cost savings analysis", "5-day work, 13th-month salary"], "locations": ["Not Specified"], "categories": ["Manufacturing", "Manufacturing Management", "Production Planning / Control", "Others"], "post_time": "2022-01-12T09:15:28Z", "salary": {"currency": null, "max": null, "min": null, "period": "monthly", "term": null}, "salary_visible": false, "title_keywords": ["manager"], "responsibilities": ["cost", "management", "analysis", "troubleshooting", "evaluate", "ad hoc projects"], "requirements": {"degrees": ["degree", "bachelor"], "majors": ["manufacturing", "engineering", "mechanical engineering"], "languages": ["cantonese", "english", "mandarin"], "language_level": ["good command"], "hard_skills": ["six sigma", "lean", "plus"], "soft_skills": ["teamwork", "result-oriented", "communication and interpersonal skills"], "languages_combined": [{"language": "cantonese", "language_level": ["good command"]}, {"language": "english", "language_level": ["good command"]}, {"language": "mandarin", "language_level": ["good command"]}]}, "experience_required": {"duration": ["minimum 5 years"], "field": ["related", "managerial", "management", "manufacturing"]}}, {"job_id": "100003009037672", "location_code": "hk", "company": "LAWSGROUP", "job_title": "Administration Manager (Stationed in Overseas)", "description": "Job Responsibilities:\n\nWork as a project based to explore and develop new factory plant in overseas\nProvide full spectrum of administrative functions including facilities repair and maintenance, deliver services, catering and accommodation services, etc\nTo lead, supervise, review, recommend and implement policies & operational procedures to meet with the Company's development needs and to ensure compliance of the Corporate policies\nResponsible for overall factory operations and management\nHandle ad hoc projects as assigned by immediate supervisor\n\nJob Requirements:\n\nDegree holder or above\nStrong solid experience in all-round garment manufacturing factory environment is a MUST\nMinimum 8 years relevant experience in manufacturing industry including 3 years at managerial level\nSelf-motivated, result-oriented and able to work under pressure\nExcellent interpersonal skills and project management skills\nExcellent command in both spoken and written English and Chinese including Mandarin\nStationed in Overseas is required\n\nWe\u00a0offer\u00a0attractive remuneration package to the right candidate. Interested parties please click the \"APPLY NOW\" button below and send your application together with a detailed resume including current & expected salary and availability to Human Resources Department.\n\nCompany website:\u00a0https://www.lawsgroup.com\n\n(Data collected will be treated in strict confidence and used for recruitment purpose only)", "employment_types": ["Full Time", "Permanent"], "selling_points": ["Degree holder with 8 yr relevant work exp.", "Solid exp in garment manufacturing factory", "Stationed in Overseas is required"], "locations": ["Overseas"], "categories": ["Admin & HR", "Others", "Manufacturing", "Garment / Textile", "Others"], "post_time": "2022-01-11T03:27:35Z", "salary": {"currency": null, "max": null, "min": null, "period": "monthly", "term": null}, "salary_visible": false, "title_keywords": ["administration manager"], "responsibilities": ["management", "maintenance", "policies", "operations", "review", "develop", "ensure compliance", "repair", "operational procedures", "ad hoc projects", "catering"], "requirements": {"degrees": ["degree holder"], "majors": [], "languages": ["english", "chinese", "mandarin"], "language_level": ["excellent"], "hard_skills": ["project management"], "soft_skills": ["self-motivated", "project management skills", "interpersonal skills", "result-oriented", "work under pressure"], "languages_combined": [{"language": "english", "language_level": ["excellent"]}, {"language": "chinese", "language_level": ["excellent"]}, {"language": "mandarin", "language_level": ["excellent"]}]}, "experience_required": {"duration": ["3 years", "minimum 8 years"], "field": ["garment", "managerial", "manufacturing", "relevant experience", "manufacturing industry"]}}, {"job_id": "100003009040152", "location_code": "hk", "company": "Hoe Hin Pak Fah Yeow Mfy Ltd", "job_title": "\u751f\u7522\u90e8\u54e1\u5de5**", "description": "\n\u8077\u8cac :\u4e00\u822c\u5305\u88dd\u5de5\u4f5c\n\n\u8cc7\u6b77 :\u6c92\u6709\u5b78\u6b77\u8981\u6c42; \u4e00\u822c\u7cb5\u8a9e; \u61c2\u8b80\u5beb\u4e2d\u6587\n\n\u5f85\u9047 :\u6bcf\u65e5$410.00, \u6709\u82b1\u7d05(12\u65e5\u65e5\u85aa), \u661f\u671f\u4e00\u81f3\u516d: \u4e0a\u53488\u664215\u5206\u81f3\u4e0b\u53486\u6642, \u6bcf\u9031\u5de5\u4f5c5\u5929\u81f36\u5929, \u55ae\u6708\u661f\u671f\u516d\u4e0a\u73ed2\u5929, \u96d9\u6708\u661f\u671f\u516d\u4e0a\u73ed1\u5929\n\n\u7533\u8acb\u9808\u77e5 :\u6c42\u8077\u8005\u53ef\u96fb\u90f5(Apply Now)\u5c65\u6b77\u8868\u7d66\u548c\u8208\u767d\u82b1\u6cb9\u85e5\u5ee0\u6709\u9650\u516c\u53f8\u3002\u5982\u8981\u7d22\u53d6\u6536\u96c6\u500b\u4eba\u8cc7\u6599\u8072\u660e, \u8acb\u8207\u5468\u5c0f\u59d0(Tel:28817713)\u806f\u7d61\u3002\n\n", "employment_types": ["Full Time"], "selling_points": ["\u6c92\u6709\u5b78\u6b77\u8981\u6c42", "\u4e00\u822c\u7cb5\u8a9e", "\u61c2\u8b80\u5beb\u4e2d\u6587"], "locations": ["Chai Wan"], "categories": ["Admin & HR", "Others", "Manufacturing", "General / Production Workers", "Others"], "post_time": "2022-01-12T01:38:38Z", "salary": {"currency": null, "max": null, "min": null, "period": "hourly", "term": null}, "salary_visible": false, "title_keywords": [], "responsibilities": [], "requirements": {"degrees": [], "majors": [], "languages": [], "language_level": [], "hard_skills": [], "soft_skills": [], "languages_combined": []}, "experience_required": {"duration": [], "field": []}}, {"job_id": "100003009034541", "location_code": "hk", "company": "Creative Wealth International Limited", "job_title": "\u6a5f\u68b0\u64cd\u4f5c\u54e1**", "description": "\n\u8077\u8cac :\u8ca0\u8cac\u5ee0\u90e8\u65e5\u5e38\u6a5f\u5668\u8a2d\u5099\u7684\u64cd\u4f5c\u3001\u7dad\u8b77\u7b49\n\n\u8cc7\u6b77 :\u4e2d\u4e03\u7a0b\u5ea6; 1\u5e74\u7d93\u9a57; \u4e00\u822c\u7cb5\u8a9e; \u4e00\u822c\u666e\u901a\u8a71; \u4e00\u822c\u82f1\u8a9e; \u7565\u61c2\u8b80\u5beb\u4e2d\u6587; \u61c2\u95b1\u8b80\u82f1\u6587\n\n\u5f85\u9047 :\u6bcf\u6708$15,000 - $18,000, \u6709\u5728\u8077\u57f9\u8a13, \u661f\u671f\u4e00\u81f3\u516d: \u4e0a\u53489\u6642\u81f3\u4e0b\u53486\u6642, \u6bcf\u9031\u5de5\u4f5c6\u5929,\u8f2a\u73ed, \u6bcf\u5929\u5de5\u4f5c 8 \u5c0f\u6642\n\n\u7533\u8acb\u9808\u77e5 :\u6c42\u8077\u8005\u53ef\u81f4\u96fb96211656\u8207\u5275\u5049\u4f01\u696d\u6709\u9650\u516c\u53f8\u9673\u5148\u751f\u806f\u7d61\u3002\n\n", "employment_types": ["Full Time"], "selling_points": [], "locations": ["Kwun Tong"], "categories": ["Engineering", "Mechanical", "Manufacturing", "Others", "Printing"], "post_time": "2022-01-10T03:37:22Z", "salary": {"currency": null, "max": null, "min": null, "period": "monthly", "term": null}, "salary_visible": false, "title_keywords": [], "responsibilities": [], "requirements": {"degrees": [], "majors": [], "languages": [], "language_level": [], "hard_skills": [], "soft_skills": [], "languages_combined": []}, "experience_required": {"duration": [], "field": []}}, {"job_id": "100003009038230", "location_code": "hk", "company": "Toppan Forms (Hong Kong) Limited", "job_title": "Data Processing Operator (Yuen Long)", "description": "Job Responsibilities:\n\nResponsible for data process, simple mail-merge program development\nConduct daily operation tasks such as automation program monitoring, printing program execution and emergency support as assigned by superior\nPrepare print-ready files and necessary documents for printing jobs\n\nJob Requirements:\n\nF6 or above\nFamiliar with Microsoft windows and desktop application\nSolid Experience in MS Office (Outlook, Word, Excel )\nCo-operative, good Sense of responsibility, good attitude and eager to learn\n\nWe offer excellent compensation package, promotion prospects and job satisfaction. Interested parties, please\u00a0email\u00a0your detailed resume with current and expected salary by click \u201cApply Now\u201d.\n\nWe are an Equal Opportunities Employer. Personal data collected will be\u00a0used strictly in accordance with the employer's personal data policy, a copy of which will be provided upon request.\u00a0Candidates who do not notified within 8 weeks after submitting your application may consider the application unsuccessful and the application will be retained up to 24 months.\n\nDisclaimer: The above position description has been designed to indicate the general nature and level of work performed by employees within this classification. It is not designed to contain or be interpreted as a comprehensive list of all duties, responsibilities, and qualifications required of employees assigned to the position.\n\nToppan Forms does not accept unsolicited referrals and/or resumes from employment businesses and/or employment agencies. Any resumes submitted in the absence of a signed agreement will become the property of Toppan Forms and no fee shall be due.\n\nFor the details of Company Information, please visit\u00a0www.toppanforms.com\u00a0", "employment_types": ["Full Time", "Permanent"], "selling_points": [], "locations": ["Yuen Long"], "categories": ["Information Technology (IT)", "IT Project Management / Team Lead", "Security", "Manufacturing", "Others"], "post_time": "2022-01-11T06:14:25Z", "salary": {"currency": null, "max": null, "min": null, "period": "monthly", "term": null}, "salary_visible": false, "title_keywords": ["operator"], "responsibilities": ["monitoring", "daily operation", "data"], "requirements": {"degrees": [], "majors": [], "languages": [], "language_level": [], "hard_skills": ["excel", "outlook", "word", "ms office"], "soft_skills": ["eager to learn", "sense of responsibility"], "languages_combined": []}, "experience_required": {"duration": [], "field": []}}, {"job_id": "100003009033651", "location_code": "hk", "company": "Top System Industrial (Hong Kong) Limited", "job_title": "\u6280\u8853\u54e1/\u8cc7\u6df1\u6280\u8853\u54e1", "description": "\u8077\u8cac :\u8ca0\u8cac\u57f7\u884c\u5ee0\u623f\u65e5\u5e38\u4fdd\u990a\uff0c\u5354\u52a9\u4e3b\u7ba1\u8655\u7406\u751f\u7522\u8a2d\u5099\u7dad\u4fee\u4fdd\u990a\u53ca\u6aa2\u6e2c\u7b49\u5de5\u4f5c\n\u8cc7\u6b77 :\u4e2d\u4e00\u7a0b\u5ea6; 2\u5e74\u7d93\u9a57; \u826f\u597d\u7cb5\u8a9e; \u61c2\u8b80\u5beb\u4e2d\u6587; \u6301\u6709\u96fb\u5de5A\u724c; \u5b88\u6642\u52e4\u596e\uff0c\u6709\u8cac\u4efb\u5fc3\uff0c\u5177\u76f8\u95dc\u5de5\u4f5c\u7d93\u9a57\u512a\u5148\n\u5f85\u9047 :\u6bcf\u6708$20,000 - $24,500, \u6709\u96d9\u7ce7, \u91ab\u7642\u798f\u5229, \u8d85\u6642\u5de5\u4f5c\u6d25\u8cbc, \u6649\u5347\u6a5f\u6703 \u53ca\u7a7f\u68ad\u5df4\u58eb\u670d\u52d9, \u661f\u671f\u4e00\u81f3\u516d: \u4e0a\u53488\u6642\u81f3\u4e0b\u53485\u6642\u534a, \u6bcf\u9031\u5de5\u4f5c6\u5929, \u6bcf\u5929\u5de5\u4f5c 9.5 \u5c0f\u6642\n\u7533\u8acb\u9808\u77e5 :\u6c42\u8077\u8005\u53ef\u81f4\u96fb68714611\u8207\u4e0a\u9032\u5de5\u696d(\u9999\u6e2f)\u6709\u9650\u516c\u53f8\u8b5a\u5148\u751f\u806f\u7d61\u3002", "employment_types": ["Full Time"], "selling_points": [], "locations": ["Tai Po Area"], "categories": ["Manufacturing", "General / Production Workers", "Others"], "post_time": "2022-01-10T01:28:55Z", "salary": {"currency": null, "max": null, "min": null, "period": "monthly", "term": null}, "salary_visible": false, "title_keywords": ["\u6280\u8853\u54e1"], "responsibilities": [], "requirements": {"degrees": [], "majors": [], "languages": [], "language_level": [], "hard_skills": [], "soft_skills": [], "languages_combined": []}, "experience_required": {"duration": [], "field": []}}, {"job_id": "100003009039229", "location_code": "hk", "company": "Ampd Energy Limited", "job_title": "Director of Manufacturing", "description": "Summary of the Position\n\nAMPD Energy is seeking a talented and passionate individual to plan, direct, coordinate, and implement a world class assembly, configuration, and test process and to localize this process to multiple global sites. You will be working closely with leaders and teams in R&D, Field Engineering, and Supply Chain to assess the current state and develop plans for standardization and improvement and then implement. The successful candidate will be passionate about continuous improvement and excited about the opportunity to manage a process at multiple sites.\n\nWe are specifically looking for individuals who are organised, detail-oriented, and dependable. Ideally you have extensive experience in Process Management and a strong background in Lean-Six Sigma principles, Quality Tools, and best practices. This is a leadership role and so you must have specific leadership experience and outstanding leadership qualities. You will be expected to work well independently and to communicate clearly and effectively in English and preferably also Chinese.\n\nKnowledge, Qualifications and Skills\n\n\u00a0\u00a0\u00a0\u00a0\u00a0\u00a0\u00a0 Higher diploma or bachelor\u2019s degree preferably in Engineering or related field. Master\u2019s degree preferred.\n\u00a0\u00a0\u00a0\u00a0\u00a0\u00a0\u00a0 Minimum 5 years of Process or Manufacturing Management experience.\n\u00a0\u00a0\u00a0\u00a0\u00a0\u00a0\u00a0 Great planning skills, and excellent project and time management track record.\n\u00a0\u00a0\u00a0\u00a0\u00a0\u00a0\u00a0 Experience with Lean & Six Sigma principles. Experience with Quality Control in a manufacturing environment.\n\u00a0\u00a0\u00a0\u00a0\u00a0\u00a0\u00a0 Knowledge of and practice with the basic Quality Tools, 8D problem solving, SPC, ANOVA, GR&R, PPAP, Cpk analysis, and other common measurement and analytical tools.\n\u00a0\u00a0\u00a0\u00a0\u00a0\u00a0\u00a0 Great documentation, presentation, and report writing skills.\n\u00a0\u00a0\u00a0\u00a0\u00a0\u00a0\u00a0 Background in industrial and/or electrical workplace safety is a huge plus.\n\u00a0\u00a0\u00a0\u00a0\u00a0\u00a0\u00a0 Proficient in MS Office Applications (Word, Excel, Powerpoint).\n\u00a0\u00a0\u00a0\u00a0\u00a0\u00a0\u00a0 Self-motivated, detailed oriented, organized.\n\u00a0\u00a0\u00a0\u00a0\u00a0\u00a0\u00a0 Good command of spoken and written English, and ideally Chinese.\n\nSpecific duties include:\n\n\u00a0\u00a0\u00a0\u00a0\u00a0\u00a0\u00a0 Manage the assembly and configuration process for the company\u2019s products and be responsible for reporting implementation status, creating and maintaining process documentation such as Process Control Plans and Work Instructions.\n\u00a0\u00a0\u00a0\u00a0\u00a0\u00a0\u00a0 Ensure internal and external documentation meets requirements for compliance, suppliers, customers, and other stakeholders.\n\u00a0\u00a0\u00a0\u00a0\u00a0\u00a0\u00a0 Work effectively and constructively within the company\u2019s Quality Management System\n\u00a0\u00a0\u00a0\u00a0\u00a0\u00a0\u00a0 Continue to keep up to date with latest developments in all relevant standards.\n\u00a0\u00a0\u00a0\u00a0\u00a0\u00a0\u00a0 Provide periodic training for the internal team and suppliers on the assembly process and Process Management.\n\u00a0\u00a0\u00a0\u00a0\u00a0\u00a0\u00a0 Participate in new product development to ensure Assembly and manufacturing issues are addressed throughout the development process and all stakeholders understand requirements from the beginning.\n\nBenefits\n\n\u00a0\u00a0\u00a0\u00a0\u00a0\u00a0\u00a0 Competitive cash package\n\u00a0\u00a0\u00a0\u00a0\u00a0\u00a0\u00a0 Full medical, dental & travel insurance coverage\n\u00a0\u00a0\u00a0\u00a0\u00a0\u00a0\u00a0 Uber travel policy (for business travel & travel after 8pm)\n\nHow to apply\n\nPlease submit your application via https://www.linkedin.com/jobs/view/2868244993.\n\nAll information provided will be treated in strict confidence and used solely for recruitment purposes. We regret that we are only able to notify short-listed candidates.\n\nAmpd Energy is an equal opportunity employer. All candidates will be assessed on merit without regard to race, gender, sexual orientation, religion, nationality, marital status, political affiliation or any other factor protected by law.", "employment_types": ["Full Time", "Permanent"], "selling_points": ["Rapidly Growing Startup Environment", "Minimum 5 years of Related Experience", "Self-motivated, Detailed Oriented, Organized"], "locations": ["Lai Chi Kok"], "categories": ["Management", "General Management", "Manufacturing", "Manufacturing Management", "Others"], "post_time": "2022-01-11T09:05:45Z", "salary": {"currency": null, "max": null, "min": null, "period": "monthly", "term": null}, "salary_visible": false, "title_keywords": ["director"], "responsibilities": ["quality", "plan", "plans", "control", "maintaining", "configuration", "compliance", "teams", "measurement", "implementation", "develop plans", "report", "reporting", "management", "documentation", "analysis", "coordinate", "quality control", "planning"], "requirements": {"degrees": ["diploma", "degree", "bachelor", "master"], "majors": ["engineering"], "languages": ["english", "chinese"], "language_level": ["good command"], "hard_skills": ["r&d", "excel", "lean", "plus", "basic", "analysis", "word", "writing skills", "powerpoint", "problem solving", "six sigma", "documentation", "ms office"], "soft_skills": ["passionate", "planning skills", "self-motivated", "independently", "detailed oriented", "organized", "responsible", "work effectively", "writing skills", "detail-oriented", "problem solving", "leadership", "organised", "time management", "extensive", "presentation", "passionate about"], "languages_combined": [{"language": "english", "language_level": ["good command"]}, {"language": "chinese", "language_level": ["good command"]}]}, "experience_required": {"duration": ["minimum 5 years"], "field": ["management", "manufacturing", "quality control"]}}, {"job_id": "100003009033086", "location_code": "hk", "company": "Maxim's Caterers Ltd", "job_title": "Production Planning Officer (Food Factory)", "description": "Responsibilities:\n\nAllocate production resources to balance the capacity usage of production lines\nCapture production data, generate statistical report\nAnalyze production capacity utilization condition\nHandle ad hoc project\nRequirements:\n\nHigh Diploma or above\nAbility to work with mathematical concepts such as statistics\nA team player, with good communication skills\nProficiency in PC applications such as Word, Excel and PowerPoint\nWorking location : Tai Po Industrial Estate\n\nAll applications and data collected will be treated in strict confidence and used exclusively for recruitment purposes.\u00a0 Only short listed candidates will be invited for interview.\u00a0 The company will retain the applications for a maximum period of 6 months and may refer suitable candidates to other vacancies within the Group.", "employment_types": ["Full Time", "Permanent"], "selling_points": ["Production Planning", "Food Factory", "Good Career Path"], "locations": ["Tai Po Area"], "categories": ["Hospitality / F & B", "Food & Beverage", "Manufacturing", "Production Planning / Control", "Others"], "post_time": "2022-01-08T07:55:53Z", "salary": {"currency": null, "max": null, "min": null, "period": null, "term": null}, "salary_visible": false, "title_keywords": ["officer"], "responsibilities": ["report", "ad hoc", "data"], "requirements": {"degrees": ["high diploma or above"], "majors": [], "languages": [], "language_level": [], "hard_skills": ["excel", "word", "powerpoint", "pc applications"], "soft_skills": ["communication skills", "team player", "confidence"], "languages_combined": []}, "experience_required": {"duration": [], "field": []}}, {"job_id": "100003009033782", "location_code": "hk", "company": "LBS Corporation Limited", "job_title": "\u53f2\u5049\u838e 5.5\u5678/9\u5678 \u53f8\u6a5f\u5927\u52df\u96c6 (\u9752\u8863/\u7c89\u5dba\u51fa\u8eca)", "description": "1. \u6e20\u52d9\u8655\u7406\u670d\u52d9 - 9\u5678\u2f9e(18\u724c)\u53f8\u6a5f (\u6708\u5165\u53ef\u905425K)\n\n\u53f2\u5049\u838e\u74b0\u4fdd\u670d\u52d9\u70ba\u5546\u696d\u53ca\u5bb6\u5c45\u5ba2\u6236\u63d0\u4f9b\u56db\u5927\u985e\u670d\u52d9\uff0c\u5305\u62ec\u6e20\u52d9\u3001\u6c61\u6c34\u3001\u6cb9\u6c61\u8655\u7406\uff0c\u4ee5\u53ca\u5bc6\u9589\u7a7a\u9593\u5de5\u4f5c\u7684\u670d\u52d9\u4e26\u7372\u5f97\u653f\u5e9c\u591a\u500b\u8a8d\u53ef\u8cc7\u683c\u3002\n\n\u65b0\u6210\u54e1\u7684\u5de5\u4f5c\u8077\u8cac\u53ca\u798f\u5229:\n\n\u99d5\u99db\u8eca\u8f1b\u5230\u6307\u5b9a\u5ba2\u6236\u5730\u9ede\u8655\u7406\u6e20\u52d9\u670d\u52d9, \u5305\u62ec\u901a\u6e20\u3001\u5438\u5316\u7cde\u6c60\u53ca\u6d17\u6c34\u7f38\u7b49\u670d\u52d9 (\u65bc\u7c89\u5dba\u53d6\u8eca)\n\u51771\u5e74\u99d5\u99db\u7d93\u9a57; \u6709\u826f\u597d\u99d5\u99db\u8a18\u9304; \u719f\u6089\u5404\u5340\u8def\u7dda\n\u4eab\u5718\u9ad4\u91ab\u7642\u3001\u751f\u65e5\u5047\u3001\u6709\u85aa\u75c5\u5047\u3001\u52a0\u73ed\u6d25\u8cbc\u3001\u5176\u4ed6\u734e\u91d1\u53ca\u82b1\u7d05\n\u5de5\u4f5c\u6642\u9593: \u661f\u671f\u4e00\u81f3\u516d\u65e9\u4e0a8\u6642\u81f3\u665a\u4e0a6\u6642\n\n*****\u5373\u5230 \u53f2\u5049\u838eYouTube Channel\u3010\u6253\u958b\u5de5\u5177\u7bb1\u3011\u4e86\u89e3\u66f4\u591a\u884c\u696d\u5de5\u4f5c\u8cc7\u8a0a*****\u00a0:\u00a0\n\n\n\u63a8\u4ecb: \u3010\u4eba\u6750\u62db\u8058\u3011 \u6708\u5165\u81f3\u5c11\u5169\u842c\u518d\u9001\u4f60\u53bb\u9032\u4fee\u2502\u53f2\u5049\u838e\u74b0\u4fdd\u9700\u8981\u4f60\nhttps://youtu.be/D2Iq-d0qB2Y\u00a0\n\n\u6c42\u8077\u8005\u5982\u6709\u8208\u8da3\u8acb\u96fb 9150 1684 \u694a\u751f\u6d3d\n\n\u2666\u2666\u2666\u2666\u2666\u2666\u2666\u2666\u2666\u2666\u2666\u2666\u2666\u2666\u2666\u2666\u2666\u2666\u2666\u2666\u2666\u2666\u2666\u2666\u2666\u2666\u2666\u2666\u2666\u2666\u2666\u2666\u2666\u2666\u2666\u2666\u2666\u2666\u2666\u2666\u2666\u2666\u2666\u2666\u2666\u2666\u2666\u2666\u2666\u2666\u2666\u2666\u2666\u2666\u2666\u2666\u2666\u2666\u2666\u2666\u2666\u2666\u2666\u2666\u2666\u2666\u2666\u2666\n\n2. \u7269\u6d41\u9001\u8ca8\u670d\u52d9\u2013 5.5\u5678\u2f9e(2\u724c)\u53f8\u6a5f / 9\u5678\u2f9e(18\u724c)\u53f8\u6a5f (\u6708\u5165\u53ef\u905419-21K)\n\n\u53f2\u5049\u838e\u7269\u6d41\u70ba\u5546\u696d\u5ba2\u6236\u6d3e\u9001\u7522\u54c1\u5305\u62ec\u6d17\u624b\u9593\u885b\u751f\u7522\u54c1\u3001\u6ec5\u87f2\u7522\u54c1\u3001\u6e05\u6f54\u5291\u7522\u54c1\u3001\u7d19\u985e\u7522\u54c1\u53ca\u5783\u573e\u888b\u7b49\u3002\n\n\u65b0\u6210\u54e1\u7684\u5de5\u4f5c\u8077\u8cac\u53ca\u798f\u5229:\n\n\u99d5\u99db\u8eca\u8f1b\u6d3e\u9001\u6307\u5b9a\u7522\u54c1\u5230\u5ba2\u6236\u5730\u9ede, \u6709\u8ddf\u8eca, \u9700\u5354\u52a9\u843d\u8ca8 (\u65bc\u9752\u8863\u53d6\u8eca)\n\u51771\u5e74\u99d5\u99db\u7d93\u9a57; \u6709\u826f\u597d\u99d5\u99db\u8a18\u9304; \u719f\u6089\u5404\u5340\u8def\u7dda\n\u4eab\u5718\u9ad4\u91ab\u7642\u3001\u751f\u65e5\u5047\u3001\u6709\u85aa\u75c5\u5047\n\u5de5\u4f5c\u6642\u9593: \u661f\u671f\u4e00\u81f3\u516d\u65e9\u4e0a8\u6642\u534a\u81f3\u665a\u4e0a7\u6642\n\n\u6c42\u8077\u8005\u5982\u6709\u8208\u8da3\u8acb\u96fb 6112 0778 \u00a0\u99ae\u751f\u6d3d", "employment_types": ["Full Time", "Permanent"], "selling_points": [], "locations": ["Fanling"], "categories": ["Manufacturing", "Others", "Others", "Others", "Building & Construction", "Others"], "post_time": "2022-01-10T01:47:33Z", "salary": {"currency": null, "max": null, "min": null, "period": "monthly", "term": null}, "salary_visible": false, "title_keywords": [], "responsibilities": [], "requirements": {"degrees": [], "majors": [], "languages": [], "language_level": [], "hard_skills": [], "soft_skills": [], "languages_combined": []}, "experience_required": {"duration": [], "field": []}}, {"job_id": "100003009033680", "location_code": "hk", "company": "Lo Hong Ka (Hong Kong) Limited", "job_title": "\u98df\u54c1\u751f\u7522\u54e1", "description": "\u8077\u8cac :\u8ca0\u8cac\u6e05\u6d17\u73bb\u7483\u6a3d\u3001\u7be9\u9078\u71d5\u7aa9\u96dc\u8cea\uff1b\u5354\u52a9\u88fd\u4f5c\u3001\u52a0\u5de5\u98df\u54c1\u751f\u7522\uff1b\u4e00\u822c\u98df\u54c1\u5de5\u5834\u96dc\u52d9\n\u8cc7\u6b77 :\u5c0f\u516d\u7a0b\u5ea6; \u826f\u597d\u7cb5\u8a9e; \u61c2\u95b1\u8b80\u4e2d\u6587; \u5177\u98df\u54c1\u751f\u7522\u53ca\u5305\u88dd\u7d93\u9a57\u512a\u5148; \u5de5\u4f5c\u6709\u8010\u6027\u53ca\u52e4\u596e\n\u5f85\u9047 :\u6bcf\u6708$12,000, \u6709\u54e1\u5de5\u8cfc\u7269\u512a\u60e0, \u91ab\u7642\u798f\u5229 \u53ca\u8d85\u6642\u5de5\u4f5c\u6d25\u8cbc, \u661f\u671f\u4e00\u81f3\u516d: \u4e0a\u53489\u6642\u81f3\u4e0b\u53486\u6642, \u6bcf\u9031\u5de5\u4f5c6\u5929\n\u7533\u8acb\u9808\u77e5 :\u6c42\u8077\u8005\u53ef\u81f4\u96fb28323162\u8207\u8001\u884c\u5bb6(\u9999\u6e2f)\u6709\u9650\u516c\u53f8\u9127\u5c0f\u59d0\u806f\u7d61\u3002", "employment_types": ["Full Time"], "selling_points": [], "locations": ["Tsuen Wan Area"], "categories": ["Manufacturing", "General / Production Workers", "Others"], "post_time": "2022-01-10T01:34:51Z", "salary": {"currency": null, "max": null, "min": null, "period": "monthly", "term": null}, "salary_visible": false, "title_keywords": [], "responsibilities": [], "requirements": {"degrees": [], "majors": [], "languages": [], "language_level": [], "hard_skills": [], "soft_skills": [], "languages_combined": []}, "experience_required": {"duration": [], "field": []}}, {"job_id": "100003009029557", "location_code": "hk", "company": "CPL Aromas (Far East) Limited", "job_title": "\u751f\u7522\u54e1**", "description": "\n\u8077\u8cac :\u8655\u7406\u65e5\u5e38\u5de5\u5834\u904b\u4f5c\u751f\u7522\u5de5\u5e8f\uff0c\u9700\u642c\u904b\uff0c\u4fdd\u6301\u5de5\u4f5c\u74b0\u5883\u6e05\u6f54\n\n\u8cc7\u6b77 :\u4e2d\u4e09\u7a0b\u5ea6; 1\u5e74\u7d93\u9a57; \u826f\u597d\u7cb5\u8a9e; \u4e00\u822c\u82f1\u8a9e; \u61c2\u8b80\u5beb\u4e2d\u6587; \u61c2\u95b1\u8b80\u82f1\u6587; \u6301\u6709\u4f01\u93df\u8eca\u724c\u512a\u5148\n\n\u5f85\u9047 :\u6bcf\u6708$17,170 - $19,850, \u6709\u52e4\u5de5\u734e\u91d1, \u5e74\u504710\u5929, \u8868\u73fe\u734e\u91d1 \u53ca\u8f2a\u73ed\u6d25\u8cbc, \u4e0a\u53487\u6642\u81f3\u4e0b\u53483\u664215\u5206\u6216\u4e0b\u53483\u6642\u81f3\u4e0b\u534811\u664215\u5206, \u6bcf\u9031\u5de5\u4f5c6\u5929,\u8f2a\u73ed, \u6bcf\u5929\u5de5\u4f5c 7.5 \u5c0f\u6642\n\n\u7533\u8acb\u9808\u77e5 :\u6c42\u8077\u8005\u53ef\u81f4\u96fb67654230\u8207CPL\u9999\u6599(\u9060\u6771)\u6709\u9650\u516c\u53f8\u9673\u5c0f\u59d0\u806f\u7d61\u3002\n\n", "employment_types": ["Full Time"], "selling_points": [], "locations": ["Yuen Long"], "categories": ["Manufacturing", "Others"], "post_time": "2022-01-07T05:34:44Z", "salary": {"currency": null, "max": null, "min": null, "period": "monthly", "term": null}, "salary_visible": false, "title_keywords": [], "responsibilities": [], "requirements": {"degrees": [], "majors": [], "languages": [], "language_level": [], "hard_skills": [], "soft_skills": [], "languages_combined": []}, "experience_required": {"duration": [], "field": []}}, {"job_id": "100003009035288", "location_code": "hk", "company": "Karrie International Holdings Limited", "job_title": "\u9ad8\u7d1a\u7d50\u69cb\u5de5\u7a0b\u7d93\u7406", "description": "\u8077\u8cac :\u7ba1\u7406\u5de5\u7a0b\u53ca\u958b\u767c\u90e8, \u5236\u5b9a\u9805\u76ee\u8a08\u5283\u4e26\u70ba\u9805\u76ee\u5be6\u65bd\u5b89\u6392\u5fc5\u8981\u7684\u8cc7\u6e90; \u8a2d\u8a08\u9a57\u8b49\u548c\u6545\u969c\u6392\u9664; \u8207\u5ba2\u6236\u806f\u7d61\u4ee5\u88fd\u5b9a\u7522\u54c1\u898f\u683c (\u9577\u99d0\u5728\u6771\u839e\u5de5\u4f5c)\n\u8cc7\u6b77 :\u5c08\u4e0a\u6559\u80b2\uff1a\u5b78\u58eb\u5b78\u4f4d; 5\u5e746\u500b\u6708\u7d93\u9a57; \u4e00\u822c\u7cb5\u8a9e; \u826f\u597d\u666e\u901a\u8a71; \u4e00\u822c\u82f1\u8a9e; \u61c2\u8b80\u5beb\u4e2d\u6587; \u61c2\u8b80\u5beb\u82f1\u6587\n\u5f85\u9047 :\u6bcf\u6708$33,000 - $35,000, \u6709\u4f9b\u4f4f\u5bbf, \u9280\u884c\u5047\u671f, \u751f\u65e5\u5047, \u914c\u60c5\u6027\u82b1\u7d05, \u91ab\u7642\u4fdd\u96aa\u53ca\u5176\u4ed6\u6d25\u8cbc/\u798f\u5229, \u661f\u671f\u4e00\u81f3\u4e94: \u4e0a\u53488\u6642\u534a\u81f3\u4e0b\u53487\u6642, \u6bcf\u9031\u5de5\u4f5c5\u5929, \u6bcf\u5929\u5de5\u4f5c 9 \u5c0f\u6642\n\u7533\u8acb\u9808\u77e5 :\u6c42\u8077\u8005\u53ef\u96fb\u90f5\u00a0[via APPLY NOW]\u00a0\u5c65\u6b77\u8868\u7d66\u5609\u5229\u7522\u54c1\u6709\u9650\u516c\u53f8\u3002\u5982\u8981\u7d22\u53d6\u6536\u96c6\u500b\u4eba\u8cc7\u6599\u8072\u660e, \u8acb\u8207\u738b\u5c0f\u59d0(Email)\u806f\u7d61\u3002", "employment_types": ["Full Time"], "selling_points": [], "locations": ["Others - China"], "categories": ["Manufacturing", "Manufacturing Management", "Others"], "post_time": "2022-01-10T06:44:36Z", "salary": {"currency": null, "max": null, "min": null, "period": "monthly", "term": null}, "salary_visible": false, "title_keywords": [], "responsibilities": [], "requirements": {"degrees": [], "majors": [], "languages": [], "language_level": [], "hard_skills": [], "soft_skills": [], "languages_combined": []}, "experience_required": {"duration": [], "field": []}}, {"job_id": "100003009033548", "location_code": "hk", "company": "M-Gen Innovation Company Limited", "job_title": "Production Supervisor", "description": "Job Description\n\nResponsibilities:\n\nLead the\u00a0production staff\u00a0to strictly following ODPC at their daily operations\nEnsure the aptitude, product knowledge and the quality concept of the production staff\nEnsure production staff understand and follow work safety practices\nWork closely with different departments to drive quality and on-time delivery improvement at production line\nMonitor the materials and manpower planning effectively and efficiently\n\nRequirements:\n\nHigher diploma\u00a0or above in industrial Engineering / Manufacturing Engineering / related disciplines\n2-3 years\u2019 experience in manufacturing field\nSelf-motivated, independent and well organized with good analytical skills\nStrong ownership, result-driven, a team player\nGood people management skills and communication skills in both written and spoken Chinese and English\nHands on MS excel / word / PPT and Chinese word processing\nImmediate available preferred", "employment_types": ["Full Time"], "selling_points": [], "locations": ["Kwai Hing"], "categories": ["Manufacturing", "Others"], "post_time": "2022-01-10T00:54:12Z", "salary": {"currency": null, "max": null, "min": null, "period": "monthly", "term": null}, "salary_visible": false, "title_keywords": ["supervisor"], "responsibilities": ["daily operations", "quality", "monitor", "planning"], "requirements": {"degrees": ["higher diploma or above"], "majors": ["related disciplines", "manufacturing", "engineering"], "languages": ["english", "chinese"], "language_level": ["good"], "hard_skills": ["ms excel", "chinese word processing", "word", "analytical skills"], "soft_skills": ["communication skills", "self-motivated", "independent", "well organized", "analytical skills", "hands on", "team player", "driven"], "languages_combined": [{"language": "english", "language_level": ["good"]}, {"language": "chinese", "language_level": ["good"]}]}, "experience_required": {"duration": ["2-3 years"], "field": ["manufacturing"]}}, {"job_id": "100003009034439", "location_code": "hk", "company": "Simatelex Manufactory Co., Ltd.", "job_title": "Assistant Factory Manager (Qingyuan Stationed)", "description": "Responsible for assisting the factory manager in overseeing all aspects of the factory operation with over 3,000 staff and monitoring daily operations of production, quality and engineering.\n\n\nDiploma or above in Manufacturing, Mechanical, Industrial Engineering or related disciplines\n\nAt least 15 years relevant experience of which 7 years experience at managerial level in OEM manufacturing\n\nGood at manufacturing technique of electrical household appliances and have in depth knowledge in all aspects of sizable factory operation\n\nWith experience in ISO9000, ISO14000, lean manufacturing and 6-Sigma is preferable\n\nGood command of English and Chinese\nAggressive, self-motivated, attentive to details and highly quality-conscious\n\nCandidates with less experience will be considered as Production Engineering Manager (Qingyuan Stationed)\n\nWe offer\u00a0attractive remuneration package including 5-day work, bank holidays, group medical insurance etc to the right candidates. Interested parties please send your full resume including expected salary and date available to Human Resources Department by clicking \"Apply Now\" button.\n\nFor more details, please visit our web-site at www.simatelex.com.hk", "employment_types": ["Full Time", "Permanent"], "selling_points": [], "locations": ["Others - China"], "categories": ["Engineering", "Manufacturing & Production", "Manufacturing", "Manufacturing Management", "Others"], "post_time": "2022-01-10T03:23:21Z", "salary": {"currency": null, "max": null, "min": null, "period": null, "term": null}, "salary_visible": false, "title_keywords": ["assistant", "factory manager"], "responsibilities": ["daily operations", "monitoring", "quality"], "requirements": {"degrees": ["diploma or above"], "majors": ["related disciplines", "manufacturing", "engineering"], "languages": ["english", "chinese"], "language_level": ["good command"], "hard_skills": ["lean"], "soft_skills": ["self-motivated", "attentive to details", "responsible"], "languages_combined": [{"language": "english", "language_level": ["good command"]}, {"language": "chinese", "language_level": ["good command"]}]}, "experience_required": {"duration": ["7 years", "at least 15 years"], "field": ["managerial", "manufacturing", "relevant experience", "engineering"]}}, {"job_id": "100003009026362", "location_code": "hk", "company": "Good View Fruits Company Limited", "job_title": "\u751f\u7522\u54e1**\u9752\u8863", "description": "\n\u00a0 \u8077\u8cac:\n\u2022 \u4e00\u822c\u98df\u54c1\u751f\u7522\u5de5\u4f5c, \u5982\u5207\u751f\u679c, \u88fd\u4f5c\u679c\u6c41\u7b49\n\u5728\u5de5\u5834\u5de5\u4f5c(12-14\u5ea6)\n\u8077\u4f4d\u8981\u6c42:\n\u2022 \u5b78\u6b77\u4e0d\u62d8\n\u2022 \u7121\u9700\u7d93\u9a57\n\u2022 \u4e00\u822c\u7cb5\u8a9e\uff0c\u61c2\u8b80\u5beb\u4e2d\u6587\n\u85aa\u916c:\n\u6708\u85aa$11,500-12,000\n\u8a66\u7528\u671f\u5f8c\u6709\u65b0\u4eba\u734e\u91d1$1500\n\u2022 \u504f\u9060\u5730\u5340\u4ea4\u901a\u6d25\u8cbc , \u52e4\u5de5\u734e\n\u5de5\u4f5c\u6642\u9593:\n\u2022 7:30 a.m. - 16:30 p.m.\n\u2022 \u6bcf\u661f\u671f\u5de5\u4f5c\u516d\u5929, \u8f2a\u73ed\n\u5de5\u4f5c\u5730\u9ede:\n\u9752\u8863 (\u5929\u5eda\u5de5\u696d\u4e2d\u5fc3E\u5ea7)\n\u2022 \u6709\u5ee0\u8eca\u63a5\u9001\u4e0a\u73ed\u53ca\u4e0b\u73ed - \u8475\u82b3\u7ad9/\u9752\u8863\u7ad9\n\u914c\u60c5\u6027\u82b1\u7d05\u3001\u54e1\u5de5\u8cfc\u7269\u512a\u60e0\u3001\u98b1\u98a8\u6d25\u8cbc\u3001\u6709\u85aa\u5e74\u5047\n**\u5982\u6709\u610f\u7533\u8acb\u6b64\u8077\u4f4d,\u8acbWhatsapp \u6216\u81f4\u96fb 9220 2218 / 3472 0730\u6216\u6309Apply Now \u8207\u8449\u5c0f\u59d0\u806f\u7d61\u3002**\n\n", "employment_types": ["Full Time"], "selling_points": [], "locations": ["Tsing Yi"], "categories": ["Manufacturing", "General / Production Workers", "Others", "Others", "Others"], "post_time": "2022-01-06T08:03:02Z", "salary": {"currency": null, "max": null, "min": null, "period": "monthly", "term": null}, "salary_visible": false, "title_keywords": [], "responsibilities": [], "requirements": {"degrees": [], "majors": [], "languages": [], "language_level": [], "hard_skills": [], "soft_skills": [], "languages_combined": []}, "experience_required": {"duration": [], "field": []}}, {"job_id": "100003009033382", "location_code": "hk", "company": "Kindford Limited", "job_title": "Senior Shipping Manager", "description": "Direct report to Expatriate Director\u00a0\nOversee and monitor all operational controls within shipping and logistics accountabilities, such as work procedures, schedule, shipping priorities/ methods\nSupervise and coach the team to ensure operation runs efficiently\nPrepare and handle full set of shipping documents\u00a0& L/C bank document (e.g. I/E shipping documents, customs, freight costs management)\nMonitor and handle daily operations, delivery arrangements, shipment issues, customs and supports customer an ensure on time shipment\nAnalyze data to monitor performance and plan improvements in routing and delivery\nKeep update shipment records and forward relevant information to Accounting Department on shipment of goods\nLiaise with internal parties, factories, forwarders, bank and overseas customers\nHandle ad hoc tasks as assigned;\nJob Requirements :\n\nHolder of diploma or above in Logistics or related discipline\nAt least 10 years relevant working experience in trading office.\nGood English and Chinese language skills, with Mandarin a plus\nGood problem-solving skills and\u00a0negotiation ability\nA good team player with leadership skills\nKnowledge in logistics booking system &\u00a0China Customs declaration preferred\nExperience in using \" International Trader\" software will be an advantage\u00a0\nImmediate available will be\u00a0an advantage\nWe offer competitive remuneration package including 5 days work, double pay, performance bonus, annual leave, hospitalization scheme & medical insurance to the right candidate.\u00a0 Interested parties please click \u201cAPPLY NOW\u201d (Personal data collected will be used for recruitment purpose only)", "employment_types": ["Full Time", "Permanent"], "selling_points": ["Handle full set I/E documents", "Over 10 years shipping experience", "Immediate availability"], "locations": ["Ngau Tau Kok"], "categories": ["Transportation & Logistics", "Shipping", "Supply Chain", "Manufacturing", "Others"], "post_time": "2022-01-09T12:47:13Z", "salary": {"currency": null, "max": null, "min": null, "period": "monthly", "term": null}, "salary_visible": false, "title_keywords": ["shipping", "manager"], "responsibilities": ["shipping documents", "shipping", "software", "plan", "liaise with", "costs", "monitor performance", "monitor", "logistics", "schedule", "analyze data", "report", "management", "procedures", "ad hoc tasks", "daily operations", "booking", "customs declaration", "insurance", "internal parties"], "requirements": {"degrees": ["diploma or above"], "majors": [], "languages": ["english", "chinese", "mandarin"], "language_level": ["good"], "hard_skills": ["problem-solving skills", "plus", "c", "scheme"], "soft_skills": ["problem-solving skills", "good team player", "leadership skills", "negotiation"], "languages_combined": [{"language": "english", "language_level": ["good"]}, {"language": "chinese", "language_level": []}, {"language": "mandarin", "language_level": []}]}, "experience_required": {"duration": ["at least 10 years"], "field": ["trading", "relevant working experience"]}}, {"job_id": "100003009037178", "location_code": "hk", "company": "ASM Technology Hong Kong Limited", "job_title": "Production Engineer (HK/Shenzhen Plant)", "description": "Job description\nMonitor and improve process on modular and machine assembly\nSupport machine functional testing, troubleshooting, designing test jig and fixture for machine and modular assembly\nJob requirements\nDegree in Mechanical / Electronic / Electrical / Manufacturing Engineering or relevant disciplines\nWorking experience in manufacturing field is preferred\nStation / regularly working in Shenzhen Plant is required (Company bus will be provided)\nCandidate with minimum 5 years\u2019 relevant working experience will be considered as Senior Production Engineer\n\nAttractive salary and fringe benefits package will be offered to the right candidates.\n\nInterested parties please submit your application with cover letter, resume, certificate and transcripts.\n\nData collected will be used for recruitment purpose only. Suitable candidates may be referred to other vacancies within our company.", "employment_types": ["Full Time", "Permanent"], "selling_points": ["Support machine functional testing", "Degree in Manufacturing Engineering", "Station / regularly working in Shenzhen Plant"], "locations": ["Tsing Yi"], "categories": ["Engineering", "Manufacturing & Production", "Manufacturing", "Others", "Quality Assurance, Control & Testing / ISO"], "post_time": "2022-01-11T01:59:12Z", "salary": {"currency": null, "max": null, "min": null, "period": "monthly", "term": null}, "salary_visible": false, "title_keywords": ["production engineer"], "responsibilities": ["designing", "monitor", "troubleshooting", "testing"], "requirements": {"degrees": ["degree"], "majors": ["manufacturing", "engineering"], "languages": [], "language_level": [], "hard_skills": [], "soft_skills": [], "languages_combined": []}, "experience_required": {"duration": ["minimum 5 years"], "field": ["manufacturing", "relevant working experience"]}}, {"job_id": "100003009025776", "location_code": "hk", "company": "APT Pharma Ltd", "job_title": "QA Assistant (Morning Shift) /\u54c1\u8cea\u4fdd\u8b49\u52a9\u7406 (\u65e9\u73ed)", "description": "Key Roles and Responsibilities\n\nPerform routine inspection on production site, raw materials packaging materials, production process and finished products as according to GMP requirements.\nOther ad hoc projects as assigned by supervisor\n\nQualifications and Experience\n\nSecondary School Graduate or above\nProactive, willing to learnand able to work independently\nAble to read Chinese and simple English\nExperience in Manufacturing Industry is welcome (preferably in pharmaceutical or food manufacturing but not a must)\nFresh Graduates are welcome\nCandidates with more experience will be considered as Assistant QA Officer\u00a0\n\nRemuneration\n\nBank holidays, Year-end bonus, On-the-job training\nWorking hours: 8:30 am to 5:30pm (1 hour for meal and 5-day work per week)\nOver-time working and Sunday shift may be required depends on production progress\n\n\u4e3b\u8981\u8077\u8cac\uff1a\n\n\u6309GMP\u8981\u6c42\u5c0d\u751f\u7522\u5834\u5340\u3001\u539f\u6599\u3001\u5305\u88dd\u6750\u6599\u3001\u751f\u7522\u904e\u7a0b\u4ee5\u81f3\u6210\u54c1\u9032\u884c\u65e5\u5e38\u6aa2\u67e5\n\u5b8c\u6210\u4e0a\u53f8\u6307\u6d3e\u7684\u5de5\u4f5c\n\n\u5165\u8077\u689d\u4ef6\uff1a\n\n\u4e2d\u5b78\u7562\u696d\u6216\u4ee5\u4e0a\n\u7a4d\u6975\u4e3b\u52d5\uff0c\u9858\u610f\u5b78\u7fd2\u53ca\u548c\u5177\u5099\u7368\u7acb\u5de5\u4f5c\u80fd\u529b\n\u80fd\u5920\u95b1\u8b80\u4e2d\u6587\u548c\u7c21\u55ae\u82f1\u6587\n\u6b61\u8fce\u6709\u88fd\u9020\u696d\u7d93\u9a57\u4eba\u58eb\u52a0\u5165 (\u5177\u85e5\u5ee0\u6216\u98df\u54c1\u5ee0\u5de5\u4f5c\u7d93\u9a57\u7d93\u9a57\u512a\u5148\u8003\u616e)\n\u6b61\u8fce\u61c9\u5c46\u7562\u696d\u751f\u52a0\u5165\n\u5177\u76f8\u95dc\u5de5\u4f5c\u7d93\u9a57\u8005\u53ef\u8996\u70ba\u52a9\u7406\u54c1\u8cea\u4fdd\u8b49\u4e3b\u4efb\n\n\n\u85aa\u916c\u5f85\u9047\uff1a\n\n\u9280\u884c\u5047\u671f\u3001\u5e74\u7d42\u82b1\u7d05\u3001\u5728\u8077\u57f9\u8a13\n\u5de5\u4f5c\u6642\u9593: \u4e0a\u53488\u664230\u5206\u81f3\u4e0b\u53485\u664230\u5206 (1\u5c0f\u6642\u7528\u81b3\uff0c5\u5929\u5de5\u4f5c)\n\u8996\u4e4e\u751f\u7522\u9032\u5ea6\uff0c\u6216\u9700\u8d85\u6642\u5de5\u4f5c\u4e26\u6709\u6a5f\u6703\u5728\u9031\u65e5\u7576\u503c\n\nHow to Apply\n\nYou are invited to send in your application and CV stating the position\u00a0(with reference number)\u00a0you are applying for together with your current and expected salary, apply via JobsDB\u00a0on or before 28 February 2022.\n\n\nAPT Pharma Limited is an Equal Opportunities Employer. Personal data provided by job applicants will be used strictly in accordance with our personal data policy and for recruitment purposes only. We aim to respond to successful applicants within 8 weeks and related information will be kept in our file for up to 12 months for other suitable vacancies in our organization and thereafter destroyed.", "employment_types": ["Full Time"], "selling_points": [], "locations": ["Kwun Tong"], "categories": ["Manufacturing", "Others", "Medical Services", "Pharmaceutical", "Quality Assurance, Control & Testing / ISO"], "post_time": "2022-01-06T06:27:43Z", "salary": {"currency": null, "max": null, "min": null, "period": "monthly", "term": null}, "salary_visible": false, "title_keywords": ["qa assistant", "\u54c1\u8cea\u4fdd\u8b49\u52a9\u7406"], "responsibilities": ["year-end", "production process", "inspection", "ad hoc projects", "recruitment", "personal data"], "requirements": {"degrees": [], "majors": [], "languages": ["english", "chinese"], "language_level": [], "hard_skills": ["simple", "apt"], "soft_skills": ["work independently", "proactive"], "languages_combined": [{"language": "english", "language_level": []}, {"language": "chinese", "language_level": []}]}, "experience_required": {"duration": [], "field": ["pharmaceutical", "food manufacturing", "manufacturing industry", "qa"]}}, {"job_id": "100003009030571", "location_code": "hk", "company": "Bright Future Pharmaceutical Laboratories Ltd", "job_title": "\u6253\u5e36\u54e1", "description": "\u8077\u8cac :\u85e5\u54c1\u5305\u88dd\u5de5\u4f5c, \u628a\u8aaa\u660e\u66f8\u653e\u5165\u76d2\u5b50\n\u8cc7\u6b77 :\u5c0f\u4e09\u7a0b\u5ea6; \u826f\u597d\u7cb5\u8a9e; \u4e00\u822c\u666e\u901a\u8a71; \u61c2\u8b80\u5beb\u4e2d\u6587\n\u5f85\u9047 :\u6bcf\u6708$12,000 - $13,000, \u6709\u91ab\u7642\u798f\u5229, \u4f9b\u81b3\u98df, \u65b0\u4eba\u734e$3000, \u8d85\u6642\u5de5\u4f5c\u6d25\u8cbc \u53ca\u7a7f\u68ad\u5df4\u58eb\u670d\u52d9, \u661f\u671f\u4e00\u81f3\u516d: \u4e0a\u53487\u6642\u81f3\u4e0b\u53485\u664210\u5206\u6216\u4e0b\u53489\u6642\u81f3\u4e0a\u53487\u664210\u5206, \u6bcf\u9031\u5de5\u4f5c6\u5929, \u6bcf\u5929\u5de5\u4f5c 10 \u5c0f\u6642\n\u7533\u8acb\u9808\u77e5 :\u6c42\u8077\u8005\u53ef\u6309 APPLY NOW\u7533\u8acb\u6216\u81f4\u96fb22112421\u8207\u6fb3\u7f8e\u88fd\u85e5\u5ee0\u6709\u9650\u516c\u53f8\u90ed\u5c0f\u59d0\u806f\u7d61\u3002", "employment_types": ["Full Time"], "selling_points": ["\u85e5\u54c1\u5305\u88dd\u5de5\u4f5c", "\u628a\u8aaa\u660e\u66f8\u653e\u5165\u76d2\u5b50", "\u5c0f\u4e09\u7a0b\u5ea6; \u826f\u597d\u7cb5\u8a9e"], "locations": ["Yuen Long"], "categories": ["Manufacturing", "General / Production Workers", "Others"], "post_time": "2022-01-07T07:47:16Z", "salary": {"currency": null, "max": null, "min": null, "period": "monthly", "term": null}, "salary_visible": false, "title_keywords": [], "responsibilities": [], "requirements": {"degrees": [], "majors": [], "languages": [], "language_level": [], "hard_skills": [], "soft_skills": [], "languages_combined": []}, "experience_required": {"duration": [], "field": []}}, {"job_id": "100003009029804", "location_code": "hk", "company": "Tsit Wing Coffee Co Ltd", "job_title": "\u751f\u7522\u6280\u8853\u54e1", "description": "\u8077\u8cac :\u4e00\u822c\u751f\u7522\u7dda\u6a5f\u68b0\u64cd\u4f5c\u53ca\u6e05\u6d17, \u64cd\u4f5c\u751f\u7522\u8a2d\u5099(\u7092\u7210/\u5012\u8c46)\u6216\u8655\u7406\u8207\u751f\u7522\u539f\u6750\u6599\u6709\u95dc\u7684\u642c\u904b\u5de5\u4f5c, \u8655\u7406\u79e4\u91cf, \u5305\u88dd, \u5c01\u53e3\u53ca\u4e0a\u677f\u7b49\u5de5\u4f5c, \u76e4\u9ede\u5de5\u4f5c\n\u8cc7\u6b77 :\u4e2d\u4e00\u7a0b\u5ea6; \u826f\u597d\u7cb5\u8a9e; \u61c2\u8b80\u5beb\u4e2d\u6587; \u7565\u61c2\u8b80\u5beb\u82f1\u6587\n\u5f85\u9047 :\u6bcf\u6708$16,000 - $20,000, \u6709\u52e4\u5de5\u734e\u91d1, \u914c\u60c5\u6027\u82b1\u7d05, \u54e1\u5de5\u8cfc\u7269\u512a\u60e0, \u91ab\u7642\u798f\u5229, \u65b0\u4eba\u734e$3000 \u53ca\u8d85\u6642\u5de5\u4f5c\u6d25\u8cbc, \u661f\u671f\u4e00\u81f3\u516d: \u4e0a\u53488\u6642\u534a\u81f3\u4e0b\u53486\u6642, \u6bcf\u9031\u5de5\u4f5c5\u5929\u81f36\u5929\n\u7533\u8acb\u9808\u77e5 :\u6c42\u8077\u8005\u53ef\u6309 APPLY NOW\u7533\u8acb\u6216\u81f4\u96fb24195909\u8207\u6377\u69ae\u5496\u5561\u6709\u9650\u516c\u53f8\u5f35\u5c0f\u59d0\u806f\u7d61\u3002", "employment_types": ["Full Time"], "selling_points": ["\u4e00\u822c\u751f\u7522\u7dda\u6a5f\u68b0\u64cd\u4f5c\u53ca\u6e05\u6d17", "\u64cd\u4f5c\u751f\u7522\u8a2d\u5099", "\u4e2d\u4e00\u7a0b\u5ea6; \u826f\u597d\u7cb5\u8a9e"], "locations": ["Kwai Tsing Area"], "categories": ["Manufacturing", "General / Production Workers", "Others"], "post_time": "2022-01-07T06:12:37Z", "salary": {"currency": null, "max": null, "min": null, "period": "monthly", "term": null}, "salary_visible": false, "title_keywords": ["\u751f\u7522\u6280\u8853\u54e1"], "responsibilities": [], "requirements": {"degrees": [], "majors": [], "languages": [], "language_level": [], "hard_skills": [], "soft_skills": [], "languages_combined": []}, "experience_required": {"duration": [], "field": []}}, {"job_id": "100003009030512", "location_code": "hk", "company": "Funville Limited", "job_title": "SHIPPING SUPERVISOR", "description": "FUNVILLE LTD is a fast growing Western Toy company, developing its own innovative products and sourcing a wide range of lines to buyers\u2019 specifications.\n\nWe invite dedicated individuals to apply for the position of:\n\nSHIPPING SUPERVISOR -\n\nRequirements:\n\nF. 5 or above\nAt least \u00a06 \u00a0years in trading company / manufacturing / buying office relevant working experience\nGood knowledge of PRC\u00a0I/E documentation & procedures\nGood knowledge of Letter of Credit procedures\nGood knowledge in EU and USA \u00a0market in bound transportation procedure is preferable\nExperience in coordinating with forwarders & shipping companies and\u00a0arrangement of\u00a0 \u00a0shipments & goods delivery schedule in the most efficient and effective way\nResponsible, detail \u2013minded, self-motivated with excellent interpersonal and communication skills\nDemonstrable ability to work independently and under pressure, to manage and achieve tight deadlines.\nStrong PC skills.\nAbility to work as a team member.\nExcellent English is a must, proficiency in Cantonese and Mandarin is essential.\n\nDuties:\n\nMonitor the daily operations of the shipping department\nResponsible for all shipping arrangements with courier and forwarder companies\nHandle full set of shipping document\nFollow up orders & shipments, preparation shipping documents\nProvide shipping options and preparation of quotations\n\nThe position offers self motivated, ambitious candidates the opportunity for growth as our business further develops and expands.\n\nThe position demands a confident and accurate command of both written and spoken English, and the ability to get things done to meet tight deadlines.\u00a0 A proven knowledge of the market and/or willingness to learn is essential.\n\nAttractive remuneration, double pay and bonus will be offered in line with experience and ability.\n\nInterested candidates should forward their detailed Curriculum Vitae in English including current and expected salary by e-mail.\n\n\n\u00a0Applications will be received in the strictest confidence.", "employment_types": ["Full Time"], "selling_points": [], "locations": ["Tsim Sha Tsui"], "categories": ["Manufacturing", "Others"], "post_time": "2022-01-07T07:37:32Z", "salary": {"currency": null, "max": null, "min": null, "period": "monthly", "term": null}, "salary_visible": false, "title_keywords": ["shipping supervisor"], "responsibilities": ["follow up orders", "shipping documents", "shipping", "monitor", "daily operations", "shipping document"], "requirements": {"degrees": [], "majors": [], "languages": ["cantonese", "english", "mandarin"], "language_level": ["excellent", "proficiency"], "hard_skills": ["documentation", "pc skills"], "soft_skills": ["efficient", "communication skills", "self-motivated", "work independently", "under pressure", "responsible", "work as a team", "interpersonal"], "languages_combined": [{"language": "cantonese", "language_level": ["proficiency"]}, {"language": "english", "language_level": ["excellent"]}, {"language": "mandarin", "language_level": ["proficiency"]}]}, "experience_required": {"duration": [], "field": ["manufacturing", "trading", "relevant working experience"]}}, {"job_id": "100003009031152", "location_code": "hk", "company": "Sanwa BioTech Limited", "job_title": "Intellectual Property Officer", "description": "Job Duty:\n\nIdentify technology with commercial applications, evaluate commercial potential of inventions and recommend whether intellectual property protection should be sought.\nResponsible for preparing materials for trademark applications\nDraft patent specifications and provide information to external attorneys to assist in determining intellectual property patentability and to oversee adherence to application timelines.\nPrepare non-confidential disclosures and descriptions of intellectual property and related information for potential licensees.\nPerform related duties as assigned.\nRequirement:\n\nDegree of above in any discipline; a strong hard science/engineering background is a plus.\nResponsible, independent with strong communication skills, good team spirit.\nFluent in both spoken and written in English & Chinese.\nKnowledge and experience in the legal and intellectual property filed is preferred.\n\n\n\nWe offer an attractive remuneration package including competitive salary, 5-day work, annual leave and medical insurance.\u00a0\u00a0If you are interested in this career opportunity,\u00a0please apply with your detailed resume, present and expected salary\u00a0by clicking \u201cApply Now\u201d\n\nPersonal data collected will be used for recruitment purpose only.", "employment_types": ["Full Time", "Permanent"], "selling_points": [], "locations": ["Shatin Area"], "categories": ["Professional Services", "Legal & Compliance", "Manufacturing", "Others", "Medical Services", "Pharmaceutical"], "post_time": "2022-01-07T09:18:55Z", "salary": {"currency": null, "max": null, "min": null, "period": "monthly", "term": null}, "salary_visible": false, "title_keywords": ["property officer"], "responsibilities": ["evaluate", "specifications", "communication"], "requirements": {"degrees": ["degree"], "majors": [], "languages": ["english", "chinese"], "language_level": ["fluent"], "hard_skills": ["plus"], "soft_skills": ["communication skills", "team spirit", "independent", "responsible"], "languages_combined": [{"language": "english", "language_level": ["fluent"]}, {"language": "chinese", "language_level": ["fluent"]}]}, "experience_required": {"duration": [], "field": ["legal"]}}, {"job_id": "100003009022301", "location_code": "hk", "company": "ICHIRAN Hong Kong Limited", "job_title": "\u98df\u54c1\u751f\u7522\u54e1**", "description": "\n\u8077\u8cac :\u8ca0\u8cac\u98df\u54c1\u88fd\u9020\u3001\u62c6\u5378\u53ca\u642c\u904b\u5de5\u4f5c\u53ca\u4e00\u822c\u6e05\u6383\u5de5\u4f5c (\u67093\u5929\u7279\u5225\u9023\u7e8c\u4f11\u5047)\n\n\u8cc7\u6b77 :\u4e2d\u4e09\u7a0b\u5ea6; \u826f\u597d\u7cb5\u8a9e; \u4e00\u822c\u82f1\u8a9e; \u61c2\u8b80\u5beb\u4e2d\u6587; \u7565\u61c2\u8b80\u5beb\u82f1\u6587; \u8aa0\u61c7\u6709\u79ae\u3001\u5bcc\u8cac\u4efb\u611f\u3001\u5de5\u4f5c\u4e3b\u52d5\u7a4d\u6975\u3001\u826f\u597d\u6e9d\u901a\u6280\u5de7\n\n\u5f85\u9047 :\u6bcf\u6708$12,000 - $14,700, \u6709\u52e4\u5de5\u734e\u91d1, \u91ab\u7642\u4fdd\u96aa, \u4f9b\u81b3\u98df, \u8d85\u6642\u5de5\u4f5c\u6d25\u8cbc, \u5e74\u50479-16\u5929 \u53ca\u4ea4\u901a\u6d25\u8cbc, \u4e0a\u53488\u6642\u81f3\u4e0b\u53485\u6642(\u6703\u56e0\u696d\u52d9\u9700\u8981\u800c\u8abf\u52d5), \u6bcf\u9031\u5de5\u4f5c5\u5929,\u8f2a\u73ed,\u8f2a\u4f11, \u6bcf\u5929\u5de5\u4f5c 8 \u5c0f\u6642\n\n\u7533\u8acb\u9808\u77e5 :\u65bc6/1, 10am-1pm,2-5pm,\u89aa\u81e8\u7063\u4ed4\u7a05\u52d9\u5927\u6a13\u5730\u4e0b\u52de\u5de5\u8655\u98f2\u98df\u696d\u62db\u8058\u4e2d\u5fc3\u62db\u8058\u65e5,\u9762\u8a66\u540d\u984d\u6709\u9650,\u8acb\u81f4\u96fb25947800\u9810\u7d04 (\u4e00\u862d\u9999\u6e2f\u6709\u9650\u516c\u53f8)\n\n", "employment_types": ["Full Time"], "selling_points": [], "locations": ["Kwun Tong"], "categories": ["Hospitality / F & B", "Others", "Manufacturing", "Others", "Others", "Others"], "post_time": "2022-01-05T05:23:11Z", "salary": {"currency": null, "max": null, "min": null, "period": "monthly", "term": null}, "salary_visible": false, "title_keywords": [], "responsibilities": [], "requirements": {"degrees": [], "majors": [], "languages": [], "language_level": [], "hard_skills": [], "soft_skills": [], "languages_combined": []}, "experience_required": {"duration": [], "field": []}}, {"job_id": "100003009023910", "location_code": "hk", "company": "Welly Die Casting International Limited", "job_title": "Sales Executive - Five Days Work", "description": "Responsibilities:\n\nTo support sales and marketing activities\nAble to follow up orders and coordinate with porduction department\nAssist your superior in daily operation\nTo communicate with factory for sampling and production\n\nRequirements:\n\nHigher\u00a0Diploma\u00a0or above with at least 2 years relevant experiences in export sales with toys manufacturing background preferable\nGood command of spoken and written English and Chinese\nIndependent, self-motivated, efficent and welloorganized\nWilling to work under pressure\nPC knowledge is essential (on MS Excel & Words)", "employment_types": ["Full Time"], "selling_points": ["Higher Diploma", "2 years experiences with toys manufacturing", "Willing to work under pressure"], "locations": ["Tsuen Wan Area"], "categories": ["Manufacturing", "Others", "Merchandising & Purchasing", "Toy", "Sales, CS & Business Devpt", "Others"], "post_time": "2022-01-05T10:00:42Z", "salary": {"currency": null, "max": null, "min": null, "period": "monthly", "term": null}, "salary_visible": false, "title_keywords": ["sales executive"], "responsibilities": ["follow up orders", "coordinate with", "communicate with", "daily operation"], "requirements": {"degrees": ["higher diploma or above"], "majors": ["manufacturing"], "languages": ["english", "chinese"], "language_level": ["good command"], "hard_skills": ["pc knowledge", "ms excel", "words"], "soft_skills": ["self-motivated", "independent", "work under pressure"], "languages_combined": [{"language": "english", "language_level": ["good command"]}, {"language": "chinese", "language_level": ["good command"]}]}, "experience_required": {"duration": ["at least 2 years"], "field": ["toys", "manufacturing"]}}, {"job_id": "100003009032543", "location_code": "hk", "company": "AVT Design Architects Limited", "job_title": "Receptionist and Administration Clerk", "description": "Responsibilities\u00a0\u00a0\n\nHandle telephone calls, reception enquiries and guest greeting in a professional manner\nProvide clerical & administrative support including meeting room reservation, courier & mailing arrangement, flight & hotel bookings, procurement, stationery and supplies, etc\nCo-ordinate with internal & external parties including cleaning, maintenance for offices\nPerform other ad-hoc tasks as assigned\n\nRequirements\n\nForm 5 / DSE graduated or above\n\nGood interpersonal skills, telephone manner and communication skills\nCheerful, Stable, well organized, detail-minded, self-motivated and able to work independently\nProficiency in MS Word, Excel, PowerPoint, English & Chinese Word Processing\nFluent in English, Chinese and Putonghua will be an advantage\n\n\u00a0\nBenefit\n\nMedical\u00a0allowance\nFive-Day Work week\nBirthday Leave\u00a0\n\nPlease send us your application with current salary, expected salary and availability by clicking \"APPLY NOW\".\n\nAll personal information submitted to us is kept private and confidential and will be used for the recruitment purpose only.\u00a0", "employment_types": ["Full Time", "Permanent"], "selling_points": ["Detail-minded", "5 Days Work", "INITIATIVE, PROACTIVE"], "locations": ["Lai Chi Kok"], "categories": ["Admin & HR", "Others", "Manufacturing", "General / Production Workers", "Others"], "post_time": "2022-01-07T11:31:58Z", "salary": {"currency": null, "max": null, "min": null, "period": "monthly", "term": null}, "salary_visible": false, "title_keywords": ["receptionist", "clerk"], "responsibilities": ["maintenance", "administrative support", "co-ordinate with", "ad-hoc tasks", "external parties", "professional manner", "stationery", "cleaning"], "requirements": {"degrees": ["form 5", "dse"], "majors": [], "languages": ["putonghua", "english", "chinese"], "language_level": ["advantage", "proficiency", "fluent"], "hard_skills": ["excel", "chinese word processing", "powerpoint", "ms word"], "soft_skills": ["detail-minded", "communication skills", "self-motivated", "cheerful", "work independently", "well organized", "interpersonal skills", "stable", "telephone manner"], "languages_combined": [{"language": "putonghua", "language_level": ["advantage", "fluent"]}, {"language": "english", "language_level": ["advantage", "proficiency", "fluent"]}, {"language": "chinese", "language_level": ["advantage", "proficiency", "fluent"]}]}, "experience_required": {"duration": [], "field": []}}, {"job_id": "100003009025718", "location_code": "hk", "company": "Fildan Accessories (Hong Kong) Limited", "job_title": "\u914d\u8272\u5e2b\u5085 / \u914d\u8272\u52a9\u7406", "description": "\n\u8077\u8cac :\u9700\u642c\u904b25\u5343\u514b\u5851\u81a0\u6599\uff0c\u958b\u8272\u7c89\u53ca\u6df7\u6599\uff1b\u57f7\u884c\u4e0a\u7d1a\u6307\u6d3e\u5404\u9805\u5de5\u4f5c\n\n\u8cc7\u6b77 :\u4e2d\u4e94\u7a0b\u5ea6; \u4e00\u822c\u7cb5\u8a9e\u512a\u5148; \u61c2\u8b80\u5beb\u4e2d\u6587; \u8655\u4e8b\u7d30\u5fc3\uff0c\u5c0d\u8abf\u914d\u984f\u8272\u6709\u8208\u8da3\n\u00a0 \u00a0 \u00a0 \u00a0 \u00a0 \u00a0\u5982\u6709\u914d\u8272\u5de5\u4f5c\u7d93\u9a57\uff0c\u6703\u8003\u616e\u70ba\u914d\u8272\u5e2b\u5085\n\n\u5f85\u9047 : \u6bcf\u6708$10,000 (\u914d\u8272\u5e2b\u5085\u85aa\u91d1\u53e6\u8b70)\uff0c\u6709\u5e74\u7d42\u734e\u91d1, \u661f\u671f\u4e00\u81f3\u516d: \u4e0a\u53488\u6642\u534a\u81f3\u4e0b\u53486\u6642, \u6bcf\u9031\u5de5\u4f5c5\u5929\u81f36\u5929, \u6bcf\u5929\u5de5\u4f5c 8.5 \u5c0f\u6642, \u661f\u671f\u516d\u9577\u77ed\u9031\n\n\u7533\u8acb\u9808\u77e5 :\u6c42\u8077\u8005\u53ef\u81f4\u96fb 39797604 \u6216 61974203 \u8207\u674e\u5148\u751f\u806f\u7d61\u3002", "employment_types": ["Full Time"], "selling_points": [], "locations": ["Kwun Tong"], "categories": ["Manufacturing", "General / Production Workers", "Others", "Others", "Others"], "post_time": "2022-01-06T06:27:29Z", "salary": {"currency": null, "max": null, "min": null, "period": "monthly", "term": null}, "salary_visible": false, "title_keywords": [], "responsibilities": [], "requirements": {"degrees": [], "majors": [], "languages": [], "language_level": [], "hard_skills": [], "soft_skills": [], "languages_combined": []}, "experience_required": {"duration": [], "field": []}}, {"job_id": "100003009026058", "location_code": "hk", "company": "RecruitFirst Limited", "job_title": "Work Supervisor Assistant [50k/ Civil Engineering/ Landscape/ 9 months contract ]", "description": "Duties:\u00a0\n\nProviding support to the Landscape Term Contract administration, such as preparing works order, cost estimate and related contract documents\nCarrying out site inspection and supervision of works, preparing reports and cost estimates of works, and keeping records\nConducting site tests and supervising the operation of equipment and plants\nAssisting in the planning and implementation of programmes for landscape/ maintenance works\nArranging relevant safety- related training\nRequirements:\u00a0\n\u00a0\nObtained a Certificate in civil engineering from a Hong Kong University or HKIVE\nCompleted a recognized Technician Apprenticeship in civil engineering\nAt least 5 years experience as a skilled worker in civil engineering\nA good command of written and spoken English and Chinese and have met the language proficiency requirements of Level 2 or above English Language in the HKDSE\nHaving basic knowledge on MS word, Excel and Powerpoint Presentation", "employment_types": ["Full Time", "Contract"], "selling_points": [], "locations": ["Kwun Tong Area"], "categories": ["Engineering", "Engineering Project Management", "Manufacturing", "Others", "Sciences, Lab, R&D", "Research & Development (R&D)"], "post_time": "2022-01-06T07:10:48Z", "salary": {"currency": null, "max": null, "min": null, "period": "monthly", "term": null}, "salary_visible": false, "title_keywords": ["supervisor", "assistant"], "responsibilities": ["cost", "supervising", "maintenance", "contract administration", "implementation", "site inspection", "preparing reports", "providing support", "planning"], "requirements": {"degrees": ["certificate", "hkdse"], "majors": ["civil engineering"], "languages": ["english", "chinese"], "language_level": ["proficiency", "good command"], "hard_skills": ["excel", "basic", "powerpoint", "ms word"], "soft_skills": ["presentation"], "languages_combined": [{"language": "english", "language_level": ["proficiency", "good command"]}, {"language": "chinese", "language_level": ["proficiency", "good command"]}]}, "experience_required": {"duration": ["at least 5 years"], "field": ["engineering"]}}, {"job_id": "100003009024449", "location_code": "hk", "company": "APT Pharma Ltd", "job_title": "QA Assistant (Night Shift) \u54c1\u8cea\u4fdd\u8b49\u52a9\u7406 (\u591c\u73ed)", "description": "Key Roles and Responsibilities\n\nPerform routine inspection on production site, raw materials packaging materials, production process and finished products as according to GMP requirements.\nOther ad hoc projects as assigned by supervisor\n\nQualifications and Experience\n\nSecondary School Graduate or above\nProactive, willing to learn\u00a0and able to work independently\nAble to read Chinese and simple English\nExperience in Manufacturing Industry is welcome (preferably in pharmaceutical or food manufacturing but not a must)\nFresh Graduates are welcome\n\nRemuneration\n\nPublic holidays, Year-end bonus, On-the-job training\nNight shift working hours: 11:00 p.m. to 8:00 a.m. (half hour for meal , with shift allowance and 5 days work per week)\nOver-time working and Sunday shift may be required depends on production progress\n\n*1-month morning shift training (8:30 a.m. to 5:30 p.m. one hour for meal) is required after commencement.\n\n\u4e3b\u8981\u8077\u8cac\uff1a\n\n\u6309GMP\u8981\u6c42\u5c0d\u751f\u7522\u5834\u5340\u3001\u539f\u6599\u3001\u5305\u88dd\u6750\u6599\u3001\u751f\u7522\u904e\u7a0b\u4ee5\u81f3\u6210\u54c1\u9032\u884c\u65e5\u5e38\u6aa2\u67e5\n\u5b8c\u6210\u4e0a\u53f8\u6307\u6d3e\u7684\u5de5\u4f5c\n\n\u5165\u8077\u689d\u4ef6\uff1a\n\n\u4e2d\u5b78\u7562\u696d\u6216\u4ee5\u4e0a\n\u7a4d\u6975\u4e3b\u52d5\uff0c\u9858\u610f\u5b78\u7fd2\u53ca\u548c\u5177\u5099\u7368\u7acb\u5de5\u4f5c\u80fd\u529b\n\u80fd\u5920\u95b1\u8b80\u4e2d\u6587\u548c\u7c21\u55ae\u82f1\u6587\n\u6b61\u8fce\u6709\u88fd\u9020\u696d\u7d93\u9a57\u4eba\u58eb\u52a0\u5165 (\u5177\u85e5\u5ee0\u6216\u98df\u54c1\u5ee0\u5de5\u4f5c\u7d93\u9a57\u7d93\u9a57\u512a\u5148\u8003\u616e)\n\u6b61\u8fce\u61c9\u5c46\u7562\u696d\u751f\u52a0\u5165\n\n\u85aa\u916c\u5f85\u9047\uff1a\n\n\u9280\u884c\u5047\u671f\u3001\u5e74\u7d42\u82b1\u7d05\u3001\u5728\u8077\u57f9\u8a13\n\u5de5\u4f5c\u6642\u9593: \u665a\u4e0a11\u6642\u6b63\u81f3\u7fcc\u65e5\u65e9\u4e0a8\u00a0 \u00a0\u00a0\u6642\u6b63\u00a0(\u534a\u5c0f\u6642\u7528\u81b3\uff0c\u5177\u591c\u73ed\u6d25\u8cbc\uff0c5\u5929\u5de5\u4f5c)\n\u8996\u4e4e\u751f\u7522\u9032\u5ea6\uff0c\u6216\u9700\u8d85\u6642\u5de5\u4f5c\u4e26\u6709\u6a5f\u6703\u5728\u9031\u65e5\u7576\u503c\n\n*\u5165\u8077\u5f8c\u9700\u8981\u5148\u63a5\u53d71\u500b\u6708\u7684\u65e9\u73ed\u57f9\u8a13\uff0c\u6642\u9593:\u65e9\u4e0a8\u6642\u534a\u81f3\u4e0b\u53485\u6642\u534a(\u4e00\u5c0f\u6642\u7528\u81b3)\u3002\n\nHow to Apply\n\nYou are invited to send in your application and CV stating the position\u00a0(with reference number)\u00a0you are applying for together with your current and expected salary, apply via JobsDB\u00a0on or before\u00a028 February 2022.\n\n\nAPT Pharma Limited is an Equal Opportunities Employer. Personal data provided by job applicants will be used strictly in accordance with our personal data policy and for recruitment purposes only. We aim to respond to successful applicants within 8 weeks and related information will be kept in our file for up to 12 months for other suitable vacancies in our organization and thereafter destroyed.", "employment_types": ["Full Time"], "selling_points": [], "locations": ["Kwun Tong"], "categories": ["Manufacturing", "Others", "Medical Services", "Pharmaceutical", "Quality Assurance, Control & Testing / ISO"], "post_time": "2022-01-06T00:54:05Z", "salary": {"currency": null, "max": null, "min": null, "period": "monthly", "term": null}, "salary_visible": false, "title_keywords": ["qa assistant", "\u54c1\u8cea\u4fdd\u8b49\u52a9\u7406"], "responsibilities": ["year-end", "production process", "inspection", "ad hoc projects", "recruitment", "personal data"], "requirements": {"degrees": [], "majors": [], "languages": ["english", "chinese"], "language_level": [], "hard_skills": ["simple", "apt"], "soft_skills": ["work independently", "proactive", "willing to learn"], "languages_combined": [{"language": "english", "language_level": []}, {"language": "chinese", "language_level": []}]}, "experience_required": {"duration": [], "field": ["pharmaceutical", "food manufacturing", "manufacturing industry"]}}]