[{"job_id": "100003009053442", "location_code": "hk", "company": "Tak Kai Co Ltd", "job_title": "\u5370\u5237\u5207\u7d19\u5e2b\u5085", "description": "Job Responsibilities\n\n\nCreate and maintain the Company Pack policy and the Pack guidelines for related products\nIdentify the Pack tasks/projects and work with suppliers, service providers and internal team in planning and executing them\nValidate Pack tests and inspection plans designed to assure quality of product Pack based on a review of all applicable safety standards and industry requirements\nValidate marking related to storage/handling & recycling for Pack (Triman, green dot,\u2026)\n\u00a0Review and resolve Pack issues with suppliers, service providers and packaging vendors\n\u00a0Coordinate and liaise with internal & external parties, related to sample evaluations\n\u00a0Maintain good communication with the suppliers to make sure our Pack requirements and standards have been well informed and implemented\nWork with France Head office to make ecotax declaration\nDevelop and follow up Supplier Pack KPI\nOther duties as assigned by Management\n\nJob Requirement\n\n\nDiploma or above in Packaging or related disciplines\n\u00a0At least 3 years working experience in of packaging and printing related field\n\u00a0Knowledge about quality assurance and quality control, raw material and finish goods markets price levels\n\u00a0Able to perform price break down for analysis\n\u00a0Knowledge in Multiple packaging materials, packaging structure design & packaging test, Flexo, Offset litho, screen printing technology, conventional and digital pre-press technologies, color management experience, green pack alternative will be an advantage\nStrong project management experience and organization skills\n\u00a0Responsible, patient, self-motivated, detailed minded, professional integrity and trustworthiness]\n\u00a0Familiar with European market\n\u00a0Good command of English on writing & speaking\nRequire travelling occasionally\n\n*Office location: Few minutes walk from Whampoa station\n\u00a0\n\n*Please send your resume with your current & expected salary. Information provided by applicants will be treated in strict confidence and will be used for recruitment purpose only.*", "employment_types": ["Full Time"], "selling_points": [], "locations": ["Southern Area"], "categories": ["Manufacturing", "Printing", "Others", "Others"], "post_time": "2022-01-17T06:59:51Z", "salary": {"currency": null, "max": null, "min": null, "period": "monthly", "term": null}, "salary_visible": false, "title_keywords": [], "responsibilities": ["management", "other duties", "guidelines", "review", "quality", "external parties", "maintain good communication", "inspection", "coordinate", "develop", "maintain", "executing", "safety standards", "liaise with", "plans", "planning"], "requirements": {"degrees": ["diploma or above"], "majors": ["related disciplines"], "languages": ["english"], "language_level": ["good command"], "hard_skills": ["project management", "analysis"], "soft_skills": ["self-motivated", "confidence", "responsible", "integrity", "project management", "organization skills", "patient", "detailed"], "languages_combined": [{"language": "english", "language_level": ["good command"]}]}, "experience_required": {"duration": ["at least 3 years"], "field": ["management", "related", "design", "project management", "digital"]}}, {"job_id": "100003009048696", "location_code": "hk", "company": "Gifi Asia Limited", "job_title": "Pack Engineer (Quality Department)", "description": "\n\u8077\u8cac :\u4e00\u822c\u5370\u5237\u5ee0\u5167\u65e5\u5e38\u5de5\u4f5c\n\n\u8cc7\u6b77 :\u4e2d\u4e00\u7a0b\u5ea6; 1\u5e74\u7d93\u9a57; \u4e00\u822c\u7cb5\u8a9e; \u7565\u61c2\u8b80\u5beb\u4e2d\u6587; \u5de5\u4f5c\u52e4\u596e, \u61c2\u5f97\u5207\u7d19\u6a5f\u64cd\u4f5c\n\n\u5f85\u9047 :\u6bcf\u6708$13,000 - $16,000, \u6709\u8d85\u6642\u5de5\u4f5c\u6d25\u8cbc, \u751f\u65e5\u5047 \u53ca\u91ab\u7642\u798f\u5229, \u661f\u671f\u4e00\u81f3\u516d: \u4e0a\u53489\u6642\u81f3\u4e0b\u53486\u6642, \u6bcf\u9031\u5de5\u4f5c6\u5929, \u6bcf\u5929\u5de5\u4f5c 8 \u5c0f\u6642\n\n\u7533\u8acb\u9808\u77e5 :\u6c42\u8077\u8005\u53ef\u81f4\u96fb67637896\u8207\u5fb7\u4f73\u6709\u9650\u516c\u53f8\u9ec3\u5c0f\u59d0\u806f\u7d61\u3002\n\n", "employment_types": ["Full Time"], "selling_points": ["3 yrs\u2019 experience in packaging field", "Flexible working hours, 5 working days", "13 months' salary plus discretionary bonus"], "locations": ["Hung Hom"], "categories": ["Manufacturing", "Product Development / Management", "Printing", "Quality Assurance, Control & Testing / ISO"], "post_time": "2022-01-14T07:03:57Z", "salary": {"currency": null, "max": null, "min": null, "period": "monthly", "term": null}, "salary_visible": false, "title_keywords": ["engineer"], "responsibilities": [], "requirements": {"degrees": [], "majors": [], "languages": [], "language_level": [], "hard_skills": [], "soft_skills": [], "languages_combined": []}, "experience_required": {"duration": [], "field": []}}, {"job_id": "100003009040320", "location_code": "hk", "company": "REWE Far East Limited", "job_title": "Project Manager, Packaging", "description": "Key Responsibilities :\n\nOversee the operations of packaging team.\nEnsure the packaging projects can be structurally organized and prioritize according to the requirements.\nDevelop and establish a project milestone controlling, and report to management.\nCoordinate projects regarding the improvement or revision of the packaging of assortment items.\nLead the vendor performance management program. Analyse supplier performance and communicate the findings and potential risks to the management and the stakeholders.\nInitiate the continuous development, implementation and improvement of daily processes in the packaging department e.g. artwork check, packaging development and packaging optimization.\nDocument packaging processes and create work instructions.\nConduct trainings for internal and external stakeholders on the REWE packaging processes.\nJob Requirements\u00a0:\n\nAt least 5 years of related professional experience, preferably in a purchasing / sourcing office or in the packaging industry.\nGood knowhow of packaging development process.\nWith solid track records in leading packaging re-launch or improvement projects.\nAbility to work in cross-cultural environment and liaise with internal and external stakeholders.\nGood command of written & spoken English and Chinese (Cantonese & Putonghua).\nKnowledge of German is an advantage.\nProficiency in MS Office.\n\nIf you are interested in the position, please submit your full resume with cover letter, current and expected salary and available date via JobsDB.\n\nAll personal information is collected for recruitment purpose only and will be treated in strict confidentiality.", "employment_types": ["Full Time", "Permanent"], "selling_points": ["Packaging, Project management", "EU buying office, Mobile Working, Flex Working Hr", "13th month Bonus, Discretionary Bonus"], "locations": ["Kwun Tong Area"], "categories": ["Transportation & Logistics", "Supply Chain", "Manufacturing", "Printing", "Merchandising & Purchasing", "Procurement / Purchasing / Sourcing"], "post_time": "2022-01-16T21:50:03Z", "salary": {"currency": null, "max": null, "min": null, "period": "monthly", "term": null}, "salary_visible": false, "title_keywords": ["project manager"], "responsibilities": ["management", "operations", "implementation", "develop", "coordinate", "analyse", "report"], "requirements": {"degrees": [], "majors": [], "languages": ["german", "cantonese", "english", "putonghua", "chinese"], "language_level": ["advantage", "good command"], "hard_skills": ["ms office"], "soft_skills": ["interested in"], "languages_combined": [{"language": "german", "language_level": ["advantage"]}, {"language": "cantonese", "language_level": ["good command"]}, {"language": "english", "language_level": ["good command"]}, {"language": "putonghua", "language_level": ["good command"]}, {"language": "chinese", "language_level": ["good command"]}]}, "experience_required": {"duration": ["at least 5 years"], "field": ["related", "purchasing"]}}, {"job_id": "100003009038265", "location_code": "hk", "company": "Educational Publishing House, Limited", "job_title": "\u5370\u5237\u8ddf\u55ae\u6587\u54e1", "description": "\n\u8077\u8cac :\u8ca0\u8cac\u5674\u756b\u88fd\u4f5c,\u505a\u7a3f\n\n\u8cc7\u6b77 :\u6c92\u6709\u5b78\u6b77\u8981\u6c42; \u826f\u597d\u7cb5\u8a9e; \u4e00\u822c\u82f1\u8a9e; \u61c2\u8b80\u5beb\u4e2d\u6587; \u61c2\u95b1\u8b80\u82f1\u6587; \u5177\u6709\u95dc\u5674\u756b,\u505a\u7a3f\u7d93\u9a57\u53ca\u61c2MAC\u6a5f,\u719f\u6089\u904b\u7528AI,PS\u7b49\u96fb\u8166\u88fd\u4f5c\u7a0b\u5f0f,\u6709\u8cac\u4efb\u5fc3,\u5de5\u4f5c\u7a4d\u6975\u4e3b\u52d5\u53ca\u71b1\u8aa0\u670d\u52d9\u614b\u5ea6\n\n\u5f85\u9047 :\u6bcf\u6708$13,310, \u6709\u5e74\u504710\u5929, \u661f\u671f\u4e00\u81f3\u4e94: \u4e0a\u53489\u6642\u81f3\u4e0b\u53485\u6642\u534a\u53ca\u661f\u671f\u516d: \u4e0a\u53489\u6642\u81f3\u4e0b\u53481\u6642, \u6bcf\u9031\u5de5\u4f5c5\u5929\u534a\n\n\u7533\u8acb\u9808\u77e5 :\u6c42\u8077\u8005\u53ef\u50b3\u771f(28345200)\u6216\u96fb\u90f5(Apply Now)\u5c65\u6b77\u8868\u7d66FINGERPRINT LIMITED\u3002\u5982\u8981\u7d22\u53d6\u6536\u96c6\u500b\u4eba\u8cc7\u6599\u8072\u660e, \u8acb\u8207\u696d\u5148\u751f(Fax/Email)\u806f\u7d61\u3002\n\n", "employment_types": ["Full Time", "Permanent"], "selling_points": ["\u4e94\u5929\u5de5\u4f5c, \u914c\u60c5\u82b1\u7d05, \u91ab\u7642\u8a08\u5283\uff08\u5305\u62ec\u7259\u79d1\uff09", "\u63d0\u4f9b\u4e00\u822c\u884c\u653f\u53ca\u6587\u66f8\u8655\u7406\u5de5\u4f5c, \u51771-2\u5e74\u884c\u653f\u652f\u63f4\u7d93\u9a57", "\u6aa2\u67e5\u5370\u5237\u6a94\u6848, \u5354\u52a9\u5b8c\u6210\u6bcf\u6708\u5831\u544a"], "locations": ["Tsuen Wan Area"], "categories": ["Admin & HR", "Clerical / Admin Staff", "Manufacturing", "Production Planning / Control", "Printing"], "post_time": "2022-01-13T04:15:07Z", "salary": {"currency": null, "max": null, "min": null, "period": "monthly", "term": null}, "salary_visible": false, "title_keywords": [], "responsibilities": [], "requirements": {"degrees": [], "majors": [], "languages": [], "language_level": [], "hard_skills": [], "soft_skills": [], "languages_combined": []}, "experience_required": {"duration": [], "field": []}}, {"job_id": "100003009047496", "location_code": "hk", "company": "Welbot Technology Limited", "job_title": "\u9ad8\u7d1a\u6a5f\u68b0\u64cd\u4f5c\u54e1 / \u6a5f\u68b0\u64cd\u4f5c\u54e1 (\u5730\u76e4)", "description": "Job Descriptions:\n\nLiaise with overseas clients and factories independently\nIndependently in handling projects follow up from sampling development to production\nHandle orders and monitor production process\nPrepare quotations, sampling and monthly reports\nOccasional travel to overseas if needed\n\nRequirements:\n\nHigh Diploma or above with 2 years relevant working experience\nWith solid printing knowledge\u00a0for garment accessories is preferred\nFluent language skills (written and oral) in English, Mandarin and Cantonese\nAble to work independent, detailed oriented, well organized & under pressure within a tight schedule\nProficient in MS office and English + Chinese word processing\nGood team player and work independently\n\nSalary Range: Negotiable\n\nBenefits:\n\n-Bank holiday\n\n-12~25 days annual leave or above\n\n-5 days working per week\n\n-Medical scheme\n\n-13 months salary\n\n-Performance based Bonus (not guarantee)\n\nWe provide attractive remuneration packages to the right candidates. Interested parties please send following by clicking \"APPLY NOW\".\n\nDetailed curriculum vitae/resume\nDate of availability\nExpected salary\n\n(All personal data provided will be treated in strict confidence and used for recruitment purposed only.)", "employment_types": ["Full Time"], "selling_points": ["-", "-", "-"], "locations": ["Not Specified"], "categories": ["Engineering", "Mechanical", "Manufacturing", "Others", "Printing"], "post_time": "2022-01-14T03:20:21Z", "salary": {"currency": null, "max": null, "min": null, "period": "monthly", "term": null}, "salary_visible": false, "title_keywords": [], "responsibilities": ["liaise with", "monitor", "production process", "monthly reports"], "requirements": {"degrees": ["high diploma or above"], "majors": [], "languages": ["cantonese", "english", "chinese", "mandarin"], "language_level": ["proficient", "fluent"], "hard_skills": ["chinese word processing", "ms office"], "soft_skills": ["oral", "good team player", "under pressure", "independent", "detailed oriented", "work independently", "well organized"], "languages_combined": [{"language": "cantonese", "language_level": ["fluent"]}, {"language": "english", "language_level": ["proficient", "fluent"]}, {"language": "chinese", "language_level": ["proficient"]}, {"language": "mandarin", "language_level": ["fluent"]}]}, "experience_required": {"duration": ["2 years"], "field": ["relevant working experience"]}}, {"job_id": "100003009045189", "location_code": "hk", "company": "Fingerprint Ltd", "job_title": "\u5674\u756b\u88fd\u4f5c\u54e1", "description": "\u8077\u8cac:\u00a0\n\n\u6aa2\u67e5\u5370\u5237\u6a94\u6848\n\u5354\u52a9\u5b8c\u6210\u6bcf\u6708\u5370\u5237\u751f\u7522\u9032\u5ea6\u5831\u544a\n\u63d0\u4f9b\u4e00\u822c\u7684\u884c\u653f\u548c\u6587\u66f8\u8655\u7406\u5de5\u4f5c (\u4f8b\u5982: \u7cfb\u7d71\u53caExcel \u8cc7\u6599\u8f38\u5165)\n\u5354\u52a9\u8ddf\u9032\u5370\u5237\u9805\u76ee\n\n\u8207\u5404\u90e8\u9580\u6e9d\u901a, \u78ba\u4fdd\u5370\u5237\u90e8\u6709\u6548\u5730\u904b\u4f5c\n\n\u8981\u6c42:\n\n\u4e2d\u5b78\u7562\u696d\n\u51771-2\u5e74\u76f8\u95dc\u884c\u653f\u652f\u63f4\u7d93\u9a57 (\u66fe\u4efb\u8077\u65bc\u5370\u5237\u884c\u696d\u512a\u5148)\n\u719f\u6089MS Office\uff08Word\uff0cExcel\u7b49\uff09\u53ca\u4e2d\u6587\u8f38\u5165\n\u7d30\u5fc3\u8b39\u614e\uff0c\u9858\u610f\u5b78\u7fd2 \uff0c \u826f\u597d\u6e9d\u901a\u6280\u5de7\n\n\u672c\u516c\u53f8\u63d0\u4f9b\u826f\u597d\u4e8b\u696d\u767c\u5c55\u6a5f\u6703\u53ca\u5177\u7af6\u722d\u6027\u85aa\u916c\u53ca\u798f\u5229\u5f85\u9047\u5305\u62ec\uff1a\u4e94\u5929\u5de5\u4f5c\u3001\u914c\u60c5\u82b1\u7d05\u3001\u91ab\u7642\u8a08\u5283\uff08\u5305\u62ec\u7259\u79d1\uff09\u3001\u54e1\u5de5\u57f9\u8a13\u53ca\u54e1\u5de5\u8cfc\u7269\u512a\u60e0\u7b49\u3002\u6709\u8208\u8da3\u8005\u8acb\u5c07\u500b\u4eba\u5c65\u6b77\uff0c-\u9023\u540c\u73fe\u6642\u85aa\u916c\u53ca\u8981\u6c42\u85aa\u916c\uff0c\u6309APPLY NOW\u7533\u8acb\u3002\n\n\u6b61\u8fce\u700f\u89bd\u672c\u516c\u53f8\u7db2\u9801\u00a0http://www.popular.com.hk\u00a0.\n\n\u6240\u6709\u8077\u4f4d\u7533\u8acb\u5c07\u4f5c\u6a5f\u5bc6\u8cc7\u6599\u8655\u7406\u53ca\u53ea\u4f5c\u62db\u8058\u7528\u9014\u3002", "employment_types": ["Full Time"], "selling_points": [], "locations": ["Chai Wan"], "categories": ["Manufacturing", "Printing", "Others", "Others"], "post_time": "2022-01-13T07:24:24Z", "salary": {"currency": null, "max": null, "min": null, "period": "monthly", "term": null}, "salary_visible": false, "title_keywords": [], "responsibilities": [], "requirements": {"degrees": [], "majors": [], "languages": [], "language_level": [], "hard_skills": [], "soft_skills": [], "languages_combined": []}, "experience_required": {"duration": [], "field": []}}, {"job_id": "100003009044513", "location_code": "hk", "company": "Global Packaging Limited", "job_title": "Account Executive", "description": "\nWelbot Technology is a pioneering technology company specializing in robotic solutions that redefine the construction automation workflow in the industry.\n\nOur Adaptive Robotic Welder has qualified for Welding Procedure Specification(WPS), fully capable of working under harsh environmental conditions. Our technological innovation not only brings new blood into the labour market, but also reforms the traditional working nature.\n\nIn the future, Welbot Technology will continue to sharpen its competitive edge. With the adoption of Building Information Modelling (BIM), big data and cutting-edge 5G technology into AI-based robotic systems, we are well poised to make a breakthrough in the eco platform of construction robotic solutions.\n\n\u8077\u8cac:\n\u65bc\u5730\u76e4\u4e3b\u7ba1\u5e36\u9818\u53ca\u6307\u5c0e\u4e0b,\u64cd\u4f5c\u6a5f\u68b0\u81c2\u9032\u884c\u5efa\u7bc9\u5730\u76e4\u5de5\u4f5c\n\n\u5354\u52a9\u5de5\u7a0b\u5e2b\u5728\u5de5\u5834\u9032\u884c\u79d1\u7814\n\n\u57f7\u884c\u4e0a\u7d1a\u6307\u6d3e\u7684\u5176\u4ed6\u8077\u52d9 \u8cc7\u6b77\n\n\u7121\u9700\u5de5\u4f5c\u7d93\u9a57 \u2022 \u7121\u9700\u5b78\u6b77\n\n\u826f\u597d\u7cb5\u8a9e\n\n\u6301\u6709\u5e73\u5b89\u5361\u53ca\u5de5\u4eba\u8a3b\u518a\u8a3c\u512a\u5148\n\n\u6301\u6709\u71d2\u710a\u5927\u5de5\u724c\u6703\u7372\u8058\u7528\u70ba\u9ad8\u7d1a\u6280\u8853\u54e1\n\n\u5177\u5718\u968a\u7cbe\u795e, \u8aa0\u5be6\u6709\u79ae, \u6709\u8010\u5fc3\u53ca\u7d30\u5fc3, \u6709\u8cac\u4efb\u611f, \u5de5\u4f5c\u7a4d\u6975\u4e3b\u52d5\n\n\u798f\u5229:\n\u6bcf\u9031\u5de5\u4f5c5-6\u5929\n\n\u914c\u60c5\u6027\u82b1\u7d05\n\n\u5728\u8077\u57f9\u8a13\n\n\u5e74\u504710\u5929\n\n\u751f\u65e5\u5047\n\n\u91ab\u7642\u4fdd\u96aa\n\n\u85aa\u916c: $15,000.00\u81f3$20,000.00(\u6bcf\u6708)\u8d77\n\nInterested candidates please apply with full resume, present & expected salary, available date by clicking \"Apply Now\". For further information, please visit our company website: https://www.welbot-tech.com/\n\nAll data collected will be used for recruitment purpose only.\n\nFull-time,Permanent\n\n", "employment_types": ["Full Time"], "selling_points": ["High Diploma or above with 2 years relevant work", "With solid printing knowledge is preferred", "5 days working"], "locations": ["Kwai Hing"], "categories": ["Merchandising & Purchasing", "Others", "Manufacturing", "Printing", "Others", "Trading"], "post_time": "2022-01-14T01:23:12Z", "salary": {"currency": null, "max": null, "min": null, "period": "monthly", "term": null}, "salary_visible": false, "title_keywords": ["account executive"], "responsibilities": ["systems", "big data"], "requirements": {"degrees": [], "majors": [], "languages": [], "language_level": [], "hard_skills": ["building information modelling", "make", "bim", "ai"], "soft_skills": ["capable", "cutting-edge"], "languages_combined": []}, "experience_required": {"duration": [], "field": []}}, {"job_id": "100003009044241", "location_code": "hk", "company": "Cos Max Medical Centre Limited", "job_title": "Senior Sourcing / Packaging Specialist \u2013 Skin Care", "description": "\n\u8aa0\u8058\u5927\u91cf\n\u5168\u8077\u6216\u517c\u8077\n\u8ca0\u8cac\u64cd\u4f5c\u5927\u578b/\u5c08\u696d\u5370\u5237\u6a5f\uff0c\u6309\u6642\u5b8c\u6210\u76f8\u95dc\u6253\u5370\u5de5\u4f5c\u3002\u9808\u6309\u5de5\u4f5c\u6307\u793a\u9078\u64c7\u9069\u7576\u7684\u96fb\u8166\u6a94\u6848\u53ca\u7d19\u5f35\uff0c\u64cd\u4f5c\u5370\u5237\u6a5f\u6253\u5370\u6587\u4ef6\u6216\u4fe1\u4ef6\uff0c\u4e26\u7d30\u5fc3\u7559\u610f\u5370\u5237\u6a5f\u904b\u4f5c\u60c5\u6cc1\u3002\n\n\u5de5\u4f5c\u6642\u9593\uff1a \u661f\u671f\u4e00\u81f3\u65e5(\u65e9\u73ed\uff1a08:00 - 17:00 \u53ca \u4e2d\u73ed\uff1a14:00 - 23:00 \u53ca \u901a\u5bb5\u73ed\uff1a23:00 - 08:00)\n\u5de5\u4f5c\u5730\u9ede\uff1a \u67f4\u7063\u6216\u6cb9\u5858 *\u6bcf\u9031\u5de5\u4f5c\u4e94\u81f3\u516d\u5929\uff0c\u9808\u8f2a\u73ed\u53ca\u8f2a\u4f11\u5de5\u4f5c\n\u6bcf\u6708\u85aa\u91d1 $10,400\u8d77 + \u6bcf\u6708\u52e4\u5de5\u734e\u91d1$1,000 + \u8f2a\u73ed\u6d25\u8cbc (\u6700\u9ad8\u85aa\u91d1\u53ef\u9054$13,000)\n\n\u5168\u8077\u54e1\u5de5\u798f\u5229\uff1a\n\u8d85\u6642\u6d25\u8cbc / \u52e4\u5de5\u734e\u91d1 / \u66f4\u671f\u6d25\u8cbc / \u6709\u85aa\u5e74\u5047 / \u91ab\u7642\u798f\u5229 / \u9280\u884c\u5047\u671f / \u6649\u5347\u6a5f\u6703 / \u54e1\u5de5\u98ef\u5802 / \u7a7f\u68ad\u5df4\u58eb / \u826f\u597d\u57f9\u8a13 / \u51b7\u6c23\u958b\u653e\n\u6709\u610f\u8005\u8acb\u65bc\u661f\u671f\u4e00\u81f3\u4e949:00am - 12:00pm \u62161:00pm - 5:00pm\n\u81f4\u96fb9828 0862 \u6216\u5c07\u5c65\u6b77\u96fb\u90f5\u81f3[via\u00a0 Apply Now ]\n\u8207\u4eba\u529b\u8cc7\u6e90\u90e8\u9810\u7d04\u9762\u8a66\n\n", "employment_types": ["Permanent"], "selling_points": ["Packaging sourcing of skincare and personal care", "Strong network with Packaging Suppliers", "Good knowledge in Photoshop"], "locations": ["Sheung Wan"], "categories": ["Beauty Care / Health", "Others", "Manufacturing", "Printing", "Quality Assurance, Control & Testing / ISO"], "post_time": "2022-01-13T03:30:18Z", "salary": {"currency": null, "max": null, "min": null, "period": "monthly", "term": null}, "salary_visible": false, "title_keywords": ["specialist"], "responsibilities": [], "requirements": {"degrees": [], "majors": [], "languages": [], "language_level": [], "hard_skills": [], "soft_skills": [], "languages_combined": []}, "experience_required": {"duration": [], "field": []}}, {"job_id": "100003009043917", "location_code": "hk", "company": "Charming Printing Limited", "job_title": "Product Development Manager (Printing/ Label/ Packaging/ Apparel Trims)", "description": "Responsibilities:\u00a0\n\nResponsible for research, new idea and trend product packaging sourcing for new collection, from containers sourcing to packaging design\nEnsure that packaging products meet set requirements and specifications\nProduce samples to try out different materials and designs to fit out the range of products\nRun trials to check packaging for suitability and testing for performance under various conditions\nEvaluate, select and negotiate with suppliers\nIdentify and choose products from suppliers\nKeep up to date with technological innovations, new idea and trend product packaging sourcing for new collection\nFollow up the package art work layout, proof read etc.\n\nRequirements:\n\n\nDegree holder in Packaging Science or equivalent discipline\n3 - 5 years hands-on experience in packaging sourcing of skincare, hair and personal care products\nStrong network with packaging suppliers\nResearch trends for seasonal skincare and cosmetic package, including containers and packaging\nGood Understanding of packaging material specifications\nSelf-motivated, confident team-player capable of high performance and excellent quality\nCollaboration and Creativity\nAttention to details and problem-solving skills\nExcellent communication skills with internal stakeholder and supplier\nDesign skill: Adobe illustrator and Photoshop", "employment_types": ["Full Time"], "selling_points": ["Station in China", "Printing, Label, Packaging", "Product Development"], "locations": ["Others - China"], "categories": ["Manufacturing", "Product Development / Management", "Printing"], "post_time": "2022-01-13T02:27:11Z", "salary": {"currency": null, "max": null, "min": null, "period": "monthly", "term": null}, "salary_visible": false, "title_keywords": ["product development manager"], "responsibilities": ["packaging design", "testing", "evaluate", "specifications", "product packaging"], "requirements": {"degrees": ["degree holder"], "majors": ["science"], "languages": [], "language_level": [], "hard_skills": ["problem-solving skills", "photoshop", "adobe illustrator"], "soft_skills": ["confident", "communication skills", "self-motivated", "capable", "team-player", "hands-on", "attention to details", "problem-solving skills"], "languages_combined": []}, "experience_required": {"duration": ["3 - 5 years"], "field": ["personal care"]}}, {"job_id": "100003009044456", "location_code": "hk", "company": "GP Acoustics International Limited", "job_title": "Print Production Specialist", "description": "Printing/ Label/ Packaging/ Apparel Trims industry\n\nResponsibilities:\n\n\nConstant communication between China, local and oversea clients, sourcing teams and production lines regarding new products, design changes update and more.\nDrive and monitor the sampling process and quality to satisfy clients\u2019 requirement.\nProvide technical solution and trouble-shooting during sample making stage\nTo ensure new samples to be completed on time.\nCommunicates with CS team and production team after approval of a new programs or items, before launching it on production lines.\n\nRequirements:\n\nUniversity/Technical college graduate/ F.7 or above with 10 yrs + related working experience\n5 years + working experience in product development for Labels or Printing industry is required\nComprehensive knowledge of printing materials and their properties.\nGood communication & interpersonal skill\nExcellent time management, able to work under pressure & meet deadline\nFluent in English, Mandarin and Cantonese\nStation in China\n\nWe offer a competitive remuneration package to successful candidate.\u00a0 Interested parties please send your full resume and expected salary.\n\nThe right candidate may join our company before or after Lunar New Year Holiday.\n(All personal information will be treated in strict confidentiality)", "employment_types": ["Full Time", "Permanent"], "selling_points": ["Science Park", "6-8 years in printing (packaging a plus)", "5 days works and flexible working hour"], "locations": ["Shatin Area"], "categories": ["Design", "Graphics", "Manufacturing", "Manufacturing Management", "Printing"], "post_time": "2022-01-13T04:09:14Z", "salary": {"currency": null, "max": null, "min": null, "period": "monthly", "term": null}, "salary_visible": false, "title_keywords": ["specialist"], "responsibilities": ["quality", "monitor", "teams", "design", "constant communication"], "requirements": {"degrees": [], "majors": [], "languages": ["cantonese", "english", "mandarin"], "language_level": ["fluent"], "hard_skills": [], "soft_skills": ["interpersonal skill", "communication", "comprehensive", "time management", "work under pressure"], "languages_combined": [{"language": "cantonese", "language_level": ["fluent"]}, {"language": "english", "language_level": ["fluent"]}, {"language": "mandarin", "language_level": ["fluent"]}]}, "experience_required": {"duration": ["5 years +"], "field": ["related", "product development"]}}, {"job_id": "100003009044048", "location_code": "hk", "company": "\u9999\u6e2f\u5370\u9214\u6709\u9650\u516c\u53f8", "job_title": "\u8cea\u91cf\u5be9\u67e5\u54e1 (Quality Examiner)", "description": "Job Description\n\nImprove and be the gate keeper of print production quality for all our brands.\nSet standards, Implement state of the art tools, processes, best practices and due diligence compliance check list.\nArrange print testing, briefing supplier for print test, and keep log and record\nReview and approve print tests, color proofs and samples and manage related process, budget and timeline.\nCoordinate with artwork / designer with correct AI file to proceed print test\nCommunicate with supplier pass/failure/improvement of print test\nManager supplier to deliver print proof as per schedule\nOrganise, supervise and monitor quality production of all printed materials, from prototype to mass production.\nUnderstand the project and design\u2019s vision, needs and requirements to provide the advice and print solutions, techniques, vendors, effects to designers to achieve what the desired outcome.\nEvaluate and negociate costs and manage timelines, to ensure quality service is provided to the other teams.\nReview output files\nSource, select and recommend appropriate materials, techniques, factories.\nControl and approve mass-production on site if necessary.\nInvestigate vendors and new print technologies, develop our vendor network.\nCoordinate with factories and maintain relationships, evaluate suppliers.\nConduct project post-mortem evaluations with the stakeholders, recap issues faced and propose solutions for improvement.\n\nRequirements\n\nExpert in printing\n6-8 years in printing (packaging a plus) from small volumes to mass production\nFamiliar and eager about the latest color and quality monitoring tools and technology\nFamiliar with high end packaging and its standards\nKnowledge in softwares: Asana, MsTeams, Adobe Creative Suite is an advantage\nFluent Cantonese / English / Mandarin", "employment_types": ["Full Time"], "selling_points": [], "locations": ["Tai Po Area"], "categories": ["Manufacturing", "Others", "Printing", "Quality Assurance, Control & Testing / ISO"], "post_time": "2022-01-13T02:54:35Z", "salary": {"currency": null, "max": null, "min": null, "period": "monthly", "term": null}, "salary_visible": false, "title_keywords": [], "responsibilities": ["communicate with", "due diligence", "control", "maintain relationships", "review", "compliance", "quality", "budget", "testing", "coordinate with", "monitor", "design", "evaluate", "teams", "schedule", "develop", "costs"], "requirements": {"degrees": [], "majors": [], "languages": ["cantonese", "english", "mandarin"], "language_level": ["fluent"], "hard_skills": ["small", "plus", "adobe creative suite"], "soft_skills": ["creative"], "languages_combined": [{"language": "cantonese", "language_level": ["fluent"]}, {"language": "english", "language_level": ["fluent"]}, {"language": "mandarin", "language_level": ["fluent"]}]}, "experience_required": {"duration": [], "field": []}}, {"job_id": "100003009044046", "location_code": "hk", "company": "\u9999\u6e2f\u5370\u9214\u6709\u9650\u516c\u53f8", "job_title": "\u5009\u52d9\u52a9\u7406 (\u8f2a\u73ed) (General Assistant) (On shift)", "description": "\u4e2d\u516d\u7a0b\u5ea6\u6216\u4ee5\u4e0a (\u6301\u5370\u5237\u6587\u6191 / \u5316\u9a57\u6587\u6191\u512a\u5148\u8003\u616e)\n\n\u9808\u5177\u6700\u5c11\u5169\u5e74\u8cea\u91cf\u5be9\u67e5/\u5be6\u9a57\u5ba4/\u5ee0\u623f\u5de5\u4f5c\u7d93\u9a57\n\u8ca0\u8cac\u65e5\u5e38\u8cea\u91cf\u5be9\u67e5/\u5316\u9a57/\u5100\u5668\u6821\u6e96\u53ca\u4fdd\u990a\u5de5\u4f5c\u7b49\n\u8ca0\u8cac\u64b0\u5beb\u6aa2\u6e2c\u5831\u544a\n\u6709\u8cac\u4efb\u5fc3\u548c\u826f\u597d\u6e9d\u901a\u6280\u5de7\n\u80fd\u66f8\u5beb\u4e2d\u82f1\u6587\u53ca\u64cd\u5ee3\u6771\u8a71\u3001\u57fa\u672c\u82f1\u8a9e\u53ca\u666e\u901a\u8a71\n\u5177\u6709\u826f\u597d\u96fb\u8166\u61c9\u7528\u77e5\u8b58\n\u9700\u8f2a\u73ed\u5de5\u4f5c\n\n(\u6b61\u8fce\u65b0\u7562\u696d\u4eba\u58eb\u7533\u8acb)\n\n\u00a0\u672c\u516c\u53f8\u63d0\u4f9b\u512a\u539a\u85aa\u916c\u53ca\u798f\u5229\uff0c\u5305\u62ec\u5e74\u7d42\u916c\u91d1\u3001\u91ab\u7642\u53ca\u4eba\u58fd\u4fdd\u96aa\u3001\u81b3\u98df\u53ca\u4ea4\u901a\u6d25\u8cbc\u7b49\uff0c\u52de\u5de5\u5047\u671f\u3002\u6709\u610f\u8005\u8acb\u5c07\u500b\u4eba\u5c65\u6b77\u3001\u5de5\u4f5c\u7d93\u9a57\u3001\u806f\u7d61\u5730\u5740\u53ca\u96fb\u8a71\uff0c\u51fd\u5bc4\u65b0\u754c\u5927\u57d4\u5de5\u696d\u90a8\u5927\u76db\u88572-4\u865f\u4eba\u4e8b\u53ca\u884c\u653f\u90e8\u6536\u6216\u6309\"APPLY NOW\"\u63d0\u4ea4\u7533\u8acb\u6216\u50b3\u771f\u81f32664 4882\u3002\n\n(\u7533\u8acb\u4eba\u6240\u63d0\u4f9b\u7684\u8cc7\u6599\u5c07\u4e88\u4fdd\u5bc6\u53ca\u53ea\u4f9b\u7533\u8acb\u6709\u95dc\u8077\u4f4d\u7528\u9014)\n\n*(\u6b61\u8fce\u65b0\u7562\u696d\u4eba\u58eb\u7533\u8acb)", "employment_types": ["Full Time"], "selling_points": [], "locations": ["Tai Po Area"], "categories": ["Transportation & Logistics", "Inventory / Warehousing", "Manufacturing", "General / Production Workers", "Printing"], "post_time": "2022-01-13T02:54:10Z", "salary": {"currency": null, "max": null, "min": null, "period": "monthly", "term": null}, "salary_visible": false, "title_keywords": ["assistant", "\u5009\u52d9\u52a9\u7406"], "responsibilities": [], "requirements": {"degrees": [], "majors": [], "languages": [], "language_level": [], "hard_skills": [], "soft_skills": [], "languages_combined": []}, "experience_required": {"duration": [], "field": []}}, {"job_id": "100003009045207", "location_code": "hk", "company": "Fujifilm Hong Kong Limited", "job_title": "\u5370\u5237\u6a5f\u76e3\u5bdf\u54e1", "description": "\u4e2d\u4e94\u7a0b\u5ea6\u6216\u4ee5\u4e0a\n\u5177\u5169\u5e74\u5ee0\u623f\u5de5\u4f5c\u7d93\u9a57\u8005\u70ba\u4f73\n\u8ca0\u8cac\u642c\u904b\u3001\u5ee0\u623f\u6e05\u6f54\u53ca\u5176\u4ed6\u96dc\u52d9\u7b49\n\u5354\u52a9\u8ca8\u5009\u4eba\u54e1\u9032\u884c\u6536\u8ca8/\u5206\u8ca8\u7b49\u5de5\u4f5c\n\u5177\u5277\u8eca\u64cd\u4f5c(\u4f38\u5c55\u578b/\u6297\u8861\u578b/\u6258\u76e4\u5806\u758a\u578b)\u7d93\u9a57\n\u9700\u8f2a\u73ed\u5de5\u4f5c\n\n\u672c\u516c\u53f8\u63d0\u4f9b\u512a\u539a\u85aa\u916c\u53ca\u798f\u5229\uff0c\u5305\u62ec\u5e74\u7d42\u916c\u91d1\u3001\u91ab\u7642\u53ca\u4eba\u58fd\u4fdd\u96aa\u3001\u81b3\u98df\u53ca\u4ea4\u901a\u6d25\u8cbc\u7b49\u3002\u6709\u610f\u8005\u8acb\u5c07\u500b\u4eba\u5c65\u6b77\u3001\u5de5\u4f5c\u7d93\u9a57\u3001\u806f\u7d61\u5730\u5740\u53ca\u96fb\u8a71\uff0c\u51fd\u5bc4\u65b0\u754c\u5927\u57d4\u5de5\u696d\u90a8\u5927\u76db\u88572-4\u865f\u4eba\u4e8b\u53ca\u884c\u653f\u90e8\u6536\u6216\u6309\"APPLY NOW\"\u63d0\u4ea4\u7533\u8acb\u6216\u50b3\u771f\u81f32664 4882\u3002\n\n\n(\u7533\u8acb\u4eba\u6240\u63d0\u4f9b\u7684\u8cc7\u6599\u5c07\u4e88\u4fdd\u5bc6\u53ca\u53ea\u4f9b\u7533\u8acb\u6709\u95dc\u8077\u4f4d\u7528\u9014)", "employment_types": ["Full Time"], "selling_points": [], "locations": ["Kwun Tong"], "categories": ["Manufacturing", "Manufacturing Management", "Others", "Printing"], "post_time": "2022-01-13T07:26:20Z", "salary": {"currency": null, "max": null, "min": null, "period": "monthly", "term": null}, "salary_visible": false, "title_keywords": [], "responsibilities": [], "requirements": {"degrees": [], "majors": [], "languages": [], "language_level": [], "hard_skills": [], "soft_skills": [], "languages_combined": []}, "experience_required": {"duration": [], "field": []}}, {"job_id": "100003009044038", "location_code": "hk", "company": "\u9999\u6e2f\u5370\u9214\u6709\u9650\u516c\u53f8", "job_title": "\u751f\u7522\u90e8 - \u7d44\u9577/\u52a9\u7406\u7d44\u9577(\u8f2a\u73ed) (Supervisor/ Assistant Supervisor (On shift))", "description": "Roles & Responsibilities\n\n- Conduct Costing Activity - Calculate costings through existing tools and maintenance of database.\n\n- Work closely with internal teams (design, merchandising, logistic & third-party partners) to draft up costing specification for both components & finished goods.\n\n- Work on cost comparison with Product Development team.\n\n- Assist day-to-day duties, on product planning with Sales / Merchandising for product style, quantity, delivery date etc. for factory planner to gauge the capacity for bulk production.\n\n- Ad hoc assignments for communication and certification purpose (FSC, OEKO TEX, etc)\n\n- Closely communicate with existing and potential vendors on production and pricing & cost, support negotiations when required. Experience working with PRC vendors appreciated.\n\n\u00a0Requirements\n\n- Higher Diploma in Textile Merchandising, Costing or related discipline.\n\n- Minimum 2/3 years relevant experience in manufacturing costing/ Industrial Engineering\n\n- Background in production, cost schedule management (cost build-up and cost contributors)\n\n- Good communication skills in spoken and written English and Chinese (Mandarin preferably).\n\n- Proficiency in PC skills, such as MS Office (Excel, Word, PPT), with a good practical experience in Excel - Chinese and English word processing.\n\n- Good analytical skills.\n\n- Capability to prioritize work and manage several projects at a time.\n\n- Be flexible and adaptable to a challenging working environment\n\n- Immediate availability is an advantage.\n\nWe offer 5-day work week, competitive salary, discretionary bonus etc. to the successful candidate.", "employment_types": ["Full Time"], "selling_points": [], "locations": ["Tai Po Area"], "categories": ["Manufacturing", "Others", "Printing", "Quality Assurance, Control & Testing / ISO"], "post_time": "2022-01-13T02:52:56Z", "salary": {"currency": null, "max": null, "min": null, "period": "monthly", "term": null}, "salary_visible": false, "title_keywords": ["assistant supervisor", "supervisor"], "responsibilities": ["communicate with", "cost", "maintenance", "merchandising", "teams", "design", "communication", "ad hoc assignments", "database", "planning"], "requirements": {"degrees": ["diploma"], "majors": [], "languages": ["english", "chinese", "mandarin"], "language_level": ["proficiency", "good"], "hard_skills": ["excel", "chinese and english word processing", "word", "analytical skills", "pc skills", "ms office"], "soft_skills": ["flexible", "communication skills", "adaptable", "prioritize", "analytical skills"], "languages_combined": [{"language": "english", "language_level": ["proficiency", "good", "good"]}, {"language": "chinese", "language_level": ["proficiency", "good", "good"]}, {"language": "mandarin", "language_level": ["good"]}]}, "experience_required": {"duration": ["3 years"], "field": ["manufacturing", "relevant experience", "engineering"]}}, {"job_id": "100003009035882", "location_code": "hk", "company": "Newsprint Production Group Ltd", "job_title": "Product Development \u2013 Costing specialist", "description": "Summary\n\nLidl are hiring an Artwork Officer\u00a0to join our Artwork & Packaging team.\u00a0The successful candidate will be provide support to the team for timely and accurate project completion,\u00a0ensure the packaging layout, label and manual are correct and is delivered on time.\n\nWhat will you do?\nHandle packaging layout, label, and manual proofreading for assigned projects\nLiaise with Merchandising team/Quality team on product details\nLiaise with artwork agencies and factories for project follow-up\nConduct quality control of artwork production\nManage quality of printing and packaging of suppliers / factories\nMaintain and update order-processing system\nWhat will you need?\nForm 6 or above\n2+ years relevant experience\nFamiliar with Adobe Illustrator, InDesign, Photoshop, Adobe Acrobat and MS Office\nPre-print knowledge is preferable\nExperience in printer house is preferable\nGood command in English (especially in writing), Mandarin and Cantonese\nPossess good project management skills and detail-oriented mindset to ensure timely production and delivery schedules are met\nGood communication, well-organised, considerate, independent, and self-motivated\nAble to work under pressure\nWhat do we offer?\n\nWe are dedicated to fostering a family-friendly culture and work environment and we are an equal opportunities employer and welcome applications from all candidates with the required skills and experience.\n\n\u00a0\nMarket Leading Remuneration Package:\n\nDouble pay and discretionary bonus\n\nChoice of MPF provider\n\nLife Insurance\n\nMedical Insurance\n\nSupportive Environment:\n\nRental re-imbursement scheme\n\nFlexible work arrangements\n\nIn-house training courses\n\nTraining sponsorship scheme\n\nHealth Check\n\nVision Check\n\nSupporting your child\u2019s education with advice from a leading education consultant\n\nWork-Life Balance:\n\n5 day week\n\nCompetitive Annual Leave\n\nCharity, Community and Sporting Events\n\nWe are dedicated to fostering a family-friendly culture and work environment and we are an equal opportunities employer and welcome applications from all candidates with the required skills and experience.\n\n\u00a0\nMarket Leading Remuneration Package:\n\nDouble pay and discretionary bonus\n\nChoice of MPF provider\n\nLife Insurance\n\nMedical Insurance\n\nSupportive Environment:\n\nRental re-imbursement scheme\n\nFlexible work arrangements\n\nIn-house training courses\n\nTraining sponsorship scheme\n\nHealth Check\n\nVision Check\n\nSupporting your child\u2019s education with advice from a leading education consultant\n\nWork-Life Balance:\n\n5 day week\n\nCompetitive Annual Leave\n\nCharity, Community and Sporting Events", "employment_types": ["Full Time", "Permanent"], "selling_points": ["2+ years relevant experience in costing", "Background in production, cost schedule management", "PC skills, good practical experience in Excel"], "locations": ["Chai Wan"], "categories": ["Manufacturing", "Production Planning / Control", "Printing", "Merchandising & Purchasing", "Procurement / Purchasing / Sourcing"], "post_time": "2022-01-10T08:39:17Z", "salary": {"currency": null, "max": null, "min": null, "period": "monthly", "term": null}, "salary_visible": false, "title_keywords": ["specialist", "product development"], "responsibilities": ["provide support", "conduct quality control", "schedules", "artwork production", "merchandising", "quality", "communication", "project management", "handle packaging layout", "proofreading", "maintain", "liaise with", "work under pressure"], "requirements": {"degrees": [], "majors": [], "languages": ["cantonese", "english", "mandarin"], "language_level": ["good command"], "hard_skills": ["ms office", "indesign", "adobe illustrator", "project management", "processing", "adobe acrobat", "photoshop"], "soft_skills": ["self-motivated", "independent", "project management skills", "timely", "detail-oriented", "communication", "well-organised", "accurate", "work under pressure"], "languages_combined": [{"language": "cantonese", "language_level": ["good command"]}, {"language": "english", "language_level": ["good command"]}, {"language": "mandarin", "language_level": ["good command"]}]}, "experience_required": {"duration": ["2+ years"], "field": ["relevant experience"]}}, {"job_id": "100003009043938", "location_code": "hk", "company": "Charming Printing Limited", "job_title": "Customer Service Manager (Printing/Label/Garment)", "description": "\u4e2d\u4e03\u6216\u4ee5\u4e0a\u5b78\u6b77\n\n\u9808\u5177\u4e09\u5e74\u6216\u4ee5\u4e0a\u5370\u5237\u3001\u54c1\u8cea\u63a7\u5236\u53ca\u6aa2\u67e5\u7b49\u5de5\u4f5c\u7d93\u9a57\n\u8ca0\u8cac\u5370\u5237\u6a5f\u64cd\u4f5c\u3001\u6210\u54c1\u6aa2\u6e2c\u6a5f\u3001\u88c1\u5207\u53ca\u5305\u88dd\u64cd\u4f5c\n\u5177\u54c1\u8cea\u63a7\u5236\u6982\u5ff5\u8a8d\u8b58\n\u9700\u61c9\u4ed8\u4e00\u822c\u9ad4\u529b\u52de\u52d5\u5de5\u4f5c\n\u5177\u9818\u5c0e\u624d\u80fd\u3001\u8cac\u4efb\u5fc3\u53ca\u826f\u597d\u6e9d\u901a\u6280\u5de7\n\u80fd\u66f8\u5beb\u4e2d\u82f1\u6587\u53ca\u64cd\u826f\u597d\u5ee3\u6771\u8a71\u3001\u82f1\u8a9e\u53ca\u666e\u901a\u8a71\n\u5177\u6709\u57fa\u672c\u96fb\u8166\u61c9\u7528\u77e5\u8b58\u53caISO\u7ba1\u7406\u7cfb\u7d71\u7d93\u9a57\n\u6bcf\u661f\u671f\u4e94\u5929\u5de5\u4f5c\n(\u82e5\u5b78\u6b77\u6216\u7d93\u9a57\u8f03\u5c11\u8005\u4ea6\u53ef\u7533\u8acb)\n\n\u672c\u516c\u53f8\u63d0\u4f9b\u512a\u539a\u85aa\u916c\u53ca\u798f\u5229\uff0c\u5305\u62ec\u5e74\u7d42\u916c\u91d1\u3001\u91ab\u7642\u53ca\u4eba\u58fd\u4fdd\u96aa\u3001\u81b3\u98df\u53ca\u4ea4\u901a\u6d25\u8cbc\u7b49\uff0c\u52de\u5de5\u5047\u671f\u3002\u6709\u610f\u8005\u8acb\u5c07\u500b\u4eba\u5c65\u6b77\u3001\u5de5\u4f5c\u7d93\u9a57\u3001\u806f\u7d61\u5730\u5740\u53ca\u96fb\u8a71\uff0c\u51fd\u5bc4\u65b0\u754c\u5927\u57d4\u5de5\u696d\u90a8\u5927\u76db\u88572-4\u865f\u4eba\u4e8b\u53ca\u884c\u653f\u90e8\u6536\u6216\u6309\"APPLY NOW\"\u63d0\u4ea4\u7533\u8acb\u6216\u50b3\u771f\u81f32664 4882\u3002\n\n\n(\u7533\u8acb\u4eba\u6240\u63d0\u4f9b\u7684\u8cc7\u6599\u5c07\u4e88\u4fdd\u5bc6\u53ca\u53ea\u4f9b\u7533\u8acb\u6709\u95dc\u8077\u4f4d\u7528\u9014)", "employment_types": ["Full Time", "Permanent"], "selling_points": ["Customer Services Manager", "Account Manager", "Printing, RFID"], "locations": ["Lai Chi Kok"], "categories": ["Sales, CS & Business Devpt", "Customer Service - Manager", "Customer Service - Supervisor / Officer", "Manufacturing", "Printing"], "post_time": "2022-01-13T02:31:51Z", "salary": {"currency": null, "max": null, "min": null, "period": "monthly", "term": null}, "salary_visible": false, "title_keywords": ["customer service manager"], "responsibilities": [], "requirements": {"degrees": [], "majors": [], "languages": [], "language_level": [], "hard_skills": [], "soft_skills": [], "languages_combined": []}, "experience_required": {"duration": [], "field": []}}, {"job_id": "100003009039505", "location_code": "hk", "company": "Lidl Asia Pte. Limited (Hong Kong Branch)", "job_title": "Artwork Officer (Packaging - Non Electrical)", "description": "Responsibilities:\n\nTypesetting English and Chinese for financial document\nRequirements:\n\nForm 5 / DSE / VTC graduate or above\nRotational shift duties are required\nOvertime working is required with OT pay\nAt least 45WPM on English and Chinese\nAble to work under pressure and tight timeframe\nBasis knowledge of Xyvision and In-Design is an advantage\nSolid clerical work experience is an advantage\nCandidates with extensive experience will be considered as Senior Operator\nBenefits:\n\n5 days work\nOvertime payment and shift allowances are provided\nMedical benefits\nOn-the-job training is provided\nWork Location: Central (one minute to MTR station)\n\nWe offer attractive package to the right candidate.\u00a0Interested parties please submit your FULL RESUME with AVAILABILITY, CURRENT and EXPECTED SALARY by clicking\u00a0APPLY NOW.\n\nAll information of candidates will be treated as strictly confidential and used for recruitment purposes only.", "employment_types": ["Full Time"], "selling_points": ["Handle packaging layout, label, and manual proofreading", "Pre-print knowledge is preferable", "5 days work. Office located in ICC."], "locations": ["Others"], "categories": ["Manufacturing", "Product Development / Management", "Printing"], "post_time": "2022-01-11T09:56:33Z", "salary": {"currency": null, "max": null, "min": null, "period": "monthly", "term": null}, "salary_visible": false, "title_keywords": ["officer"], "responsibilities": [], "requirements": {"degrees": ["form 5", "dse"], "majors": [], "languages": ["english", "chinese"], "language_level": [], "hard_skills": ["in-design"], "soft_skills": ["extensive", "work under pressure"], "languages_combined": [{"language": "english", "language_level": []}, {"language": "chinese", "language_level": []}]}, "experience_required": {"duration": [], "field": ["clerical"]}}, {"job_id": "100003009038415", "location_code": "hk", "company": "JAN Financial Press Limited", "job_title": "Operator (Central, 5 days work)", "description": "\u4e2d\u4e94\u7a0b\u5ea6(\u6703\u8003\u5408\u683c\u8005\u512a\u5148)\n\n\u5177\u5370\u5237 / \u5ee0\u623f / \u54c1\u8cea\u6aa2\u67e5\u5de5\u4f5c\u7d93\u9a57\u8005\u70ba\u4f73\n\u8ca0\u8cac\u54c1\u8cea\u63a7\u5236\u3001\u642c\u904b/\u88dd\u5378\u7d19\u5f35\u3001\u8a18\u9304\u6578\u76ee\u3001\u52a0\u6dfb\u6cb9\u58a8\u3001\u5305\u88dd\u53ca\u5176\u4ed6\u96dc\u52d9\u7b49\n\u6709\u8cac\u4efb\u5fc3\u548c\u826f\u597d\u6e9d\u901a\u6280\u5de7\n\u80fd\u66f8\u5beb\u4e2d\u82f1\u6587\u53ca\u64cd\u4e00\u822c\u5ee3\u6771\u8a71\u3001\u82f1\u8a9e\u53ca\u666e\u901a\u8a71\n\u5177\u6709\u57fa\u672c\u96fb\u8166\u61c9\u7528\u77e5\u8b58\n\u6bcf\u661f\u671f\u4e94\u5929\u5de5\u4f5c\n\u9700\u8f2a\u73ed\u5de5\u4f5c\n(\u5b78\u6b77\u6216\u7d93\u9a57\u8f03\u5c11\u8005\u4ea6\u53ef\u7533\u8acb)\n\n\n\n\u672c\u516c\u53f8\u63d0\u4f9b\u512a\u539a\u85aa\u916c\u53ca\u798f\u5229\uff0c\u5305\u62ec\u5e74\u7d42\u916c\u91d1\u3001\u91ab\u7642\u53ca\u4eba\u58fd\u4fdd\u96aa\u3001\u81b3\u98df\u53ca\u4ea4\u901a\u6d25\u8cbc\u7b49\uff0c\u52de\u5de5\u5047\u671f\u3002\u6709\u610f\u8005\u8acb\u5c07\u500b\u4eba\u5c65\u6b77\u3001\u5de5\u4f5c\u7d93\u9a57\u3001\u806f\u7d61\u5730\u5740\u53ca\u96fb\u8a71\uff0c\u51fd\u5bc4\u65b0\u754c\u5927\u57d4\u5de5\u696d\u90a8\u5927\u76db\u88572-4\u865f\u4eba\u4e8b\u53ca\u884c\u653f\u90e8\u6536\u6216\u6309\"APPLY NOW\"\u63d0\u4ea4\u7533\u8acb\u6216\u50b3\u771f\u81f32664 4882\u3002\n\n\n(\u7533\u8acb\u4eba\u6240\u63d0\u4f9b\u7684\u8cc7\u6599\u5c07\u4e88\u4fdd\u5bc6\u53ca\u53ea\u4f9b\u7533\u8acb\u6709\u95dc\u8077\u4f4d\u7528\u9014)", "employment_types": ["Full Time", "Permanent"], "selling_points": ["Typesetting English & Chinese for financial doc", "OT payment, shift allowances", "Medical benefits, on-the-job training"], "locations": ["Central"], "categories": ["Banking / Finance", "Financial Services", "Media & Advertising", "Print Media", "Manufacturing", "Printing"], "post_time": "2022-01-11T06:50:19Z", "salary": {"currency": null, "max": null, "min": null, "period": "monthly", "term": null}, "salary_visible": false, "title_keywords": ["operator"], "responsibilities": [], "requirements": {"degrees": [], "majors": [], "languages": [], "language_level": [], "hard_skills": [], "soft_skills": [], "languages_combined": []}, "experience_required": {"duration": [], "field": []}}, {"job_id": "100003009036979", "location_code": "hk", "company": "\u9999\u6e2f\u5370\u9214\u6709\u9650\u516c\u53f8", "job_title": "\u751f\u7522\u52a9\u7406(\u8f2a\u73ed) (Production Assistant (On Shift))", "description": "Hong Kong/ China\u00a0\n\nResponsibilities\n\nResponsible and supervision for the Client Support / Customer Service team.\nDevelop, motivate, coach and monitor the team members to ensure the highest quality of service to our clients.\nHandle customers\u2019 complaints\nSupport implementation of online ordering platform.\nPrepare management report for management review.\nMonitor payment from clients.\n\nRequirements\n\nDegree or equivalent/ F.5 with 10 years+ relevant working experience.\u00a0\n6 to 8 years relevant working experience, with at least 3 year managerial experience.\nExcellent communication, negotiation and presentation skills.\nSelf-motivated and aggressive, Mature, strong leadership and high responsibilities.\nMust be very strong in excel and powerpoint for monthly reporting.\nVery strong in data analyze and statistical researching.\nGood command of written & spoken English.\nExperience in Printing Industry is a must.\n\nWe offer a competitive remuneration package to successful candidate. Interested parties please send your full resume and expected salary by clicking \u2018Apply Now\u2019.\n\nThe right candidate may join our company before or after Lunar New Year Holiday.\n(All personal information will be treated in strict confidentiality)", "employment_types": ["Full Time"], "selling_points": [], "locations": ["Tai Po Area"], "categories": ["Manufacturing", "General / Production Workers", "Printing", "Quality Assurance, Control & Testing / ISO"], "post_time": "2022-01-11T01:11:46Z", "salary": {"currency": null, "max": null, "min": null, "period": "monthly", "term": null}, "salary_visible": false, "title_keywords": ["production assistant"], "responsibilities": ["quality", "monitor", "implementation", "develop", "payment", "customer service", "management report", "management review"], "requirements": {"degrees": ["degree"], "majors": [], "languages": ["english"], "language_level": ["good command"], "hard_skills": ["excel", "powerpoint"], "soft_skills": ["self-motivated", "negotiation", "mature", "communication", "presentation skills", "leadership"], "languages_combined": [{"language": "english", "language_level": ["good command"]}]}, "experience_required": {"duration": ["at least 3 year", "6 to 8 years"], "field": ["managerial", "relevant working experience"]}}, {"job_id": "100003009036974", "location_code": "hk", "company": "\u9999\u6e2f\u5370\u9214\u6709\u9650\u516c\u53f8", "job_title": "\u7269\u6599\u63a7\u5236\u54e1 (Materials Inspector)", "description": "\u4e2d\u4e94\u6216\u4ee5\u4e0a\n\u9808\u5177\u4e09\u5e74\u76f8\u95dc\u5009\u52d9/\u7269\u6d41\u7d93\u9a57\n\u8655\u7406\u65e5\u5e38\u7269\u6599\u51fa\u5165\u6d41\u7a0b\u3001\u6536\u8ca8\u3001\u767c\u8ca8\u53ca\u8a18\u9304\uff0c\u5b9a\u671f\u9032\u884c\u7269\u6599\u76e4\u9ede\n\u8655\u7406\u7269\u6599\u76e3\u63a7\u7cfb\u7d71\n\u5177\u826f\u597d\u6e9d\u901a\u6280\u5de7\n\u9700\u61c9\u4ed8\u4e00\u822c\u9ad4\u529b\u52de\u52d5\u5de5\u4f5c\n\u5177\u6709\u57fa\u672c\u96fb\u8166\u61c9\u7528\u77e5\u8b58(MS office, \u4e2d\u6587\u8f38\u5165\u6cd5)\n\u6301\u6709\u6709\u6548\u5277\u8eca\u64cd\u4f5c\u8a3c(\u6258\u76e4\u5806\u758a/\u4f38\u5c55\u578b)\u70ba\u4f73\n\u9700\u8f2a\u73ed\u5de5\u4f5c\n\n\u672c\u516c\u53f8\u63d0\u4f9b\u512a\u539a\u85aa\u916c\u53ca\u798f\u5229\uff0c\u5305\u62ec\u5e74\u7d42\u916c\u91d1\u3001\u91ab\u7642\u53ca\u4eba\u58fd\u4fdd\u96aa\u3001\u81b3\u98df\u53ca\u4ea4\u901a\u6d25\u8cbc\u7b49\uff0c\u52de\u5de5\u5047\u671f\u3002\u6709\u610f\u8005\u8acb\u5c07\u500b\u4eba\u5c65\u6b77\u3001\u5de5\u4f5c\u7d93\u9a57\u3001\u806f\u7d61\u5730\u5740\u53ca\u96fb\u8a71\uff0c\u51fd\u5bc4\u65b0\u754c\u5927\u57d4\u5de5\u696d\u90a8\u5927\u76db\u88572-4\u865f\u4eba\u4e8b\u53ca\u884c\u653f\u90e8\u6536\u6216\u6309\"APPLY NOW\"\u63d0\u4ea4\u7533\u8acb\u6216\u50b3\u771f\u81f32664 4882\u3002\n\n\n(\u7533\u8acb\u4eba\u6240\u63d0\u4f9b\u7684\u8cc7\u6599\u5c07\u4e88\u4fdd\u5bc6\u53ca\u53ea\u4f9b\u7533\u8acb\u6709\u95dc\u8077\u4f4d\u7528\u9014)", "employment_types": ["Full Time"], "selling_points": [], "locations": ["Tai Po Area"], "categories": ["Manufacturing", "General / Production Workers", "Others", "Printing"], "post_time": "2022-01-11T01:11:24Z", "salary": {"currency": null, "max": null, "min": null, "period": "monthly", "term": null}, "salary_visible": false, "title_keywords": [], "responsibilities": [], "requirements": {"degrees": [], "majors": [], "languages": [], "language_level": [], "hard_skills": [], "soft_skills": [], "languages_combined": []}, "experience_required": {"duration": [], "field": []}}, {"job_id": "100003009037320", "location_code": "hk", "company": "METRO Sourcing International Limited", "job_title": "Packaging Specialist / Packaging Coordinator", "description": "Role Purpose:\nOur Packaging Specialist is a project manager, taking charge of the entire artwork process from packaging brief to final on-time delivery of product.\n\n\nWhat you will be handling:\nEnsure execution of quality artwork - both content & layout \u2013 for boosting sales of our products\nLiaise with internal & external parties to plan and release artworks as per shipment schedule\nMaintain & update accurate data/record in network/system\nBrief and guide artwork agencies on design concepts, marketing elements & instruction manuals in 19 languages\nMonitor the performance of artwork service providers and printers\nPropose and develop innovative and sustainable packaging solutions\nTalent that we are looking for:\nAble to prioritize multiple projects and cope with the pressure of tight deadlines\nPossess strong sense of ownership and high degree of independence\nDrive for customer success and excellent service\nAttention to details, solution-oriented mindset\nPassionate in connecting with people\nExperience, knowledge and skills required:\nDegree holder in Business Administration / Supply Chain Management / Packaging Science or equivalent discipline\nAt least 5 years\u2019 experience in packaging development / project management / packaging solution / printing\nGood command of both written & spoken English & Chinese (including Mandarin)\nProficient in MS Office (Excel / Word / PowerPoint / Outlook) applications\nKnowledge of Adobe Illustrator/InDesign/Photoshop is advantageous\nCandidate with lesser experience will be considered as\u00a0Packaging Coordinator\nYou can enjoy:\nDiverse and Inclusive work environment\nFlexi Office Space with flexible working hours and home office option\n5-day work week, 13th month salary & performance bonus\nProfessional training and career advancement opportunities\nTraining Sponsorship for personal professional development\nJoin us and apply now!\n\n\nPlease send your full resume with available date, present and expected salary to us.\u00a0\nResume and personal data collected will be kept strictly confidential and used for recruitment purpose only.", "employment_types": ["Full Time", "Permanent"], "selling_points": ["Exp in packaging development / packaging solution", "Take charge of the entire artwork process", "MNC, 5-day work, insurance, double pay, bonus"], "locations": ["Kowloon Bay"], "categories": ["Marketing / Public Relations", "Others", "Merchandising & Purchasing", "Others", "Manufacturing", "Printing"], "post_time": "2022-01-11T16:01:40Z", "salary": {"currency": null, "max": null, "min": null, "period": "monthly", "term": null}, "salary_visible": false, "title_keywords": ["specialist", "coordinator"], "responsibilities": ["design concepts", "management", "data", "external parties", "quality", "develop", "project management", "maintain", "recruitment", "schedule", "plan", "monitor the performance", "liaise with", "multiple projects", "personal data", "administration"], "requirements": {"degrees": ["degree", "degree holder"], "majors": ["science", "business administration"], "languages": ["english", "chinese", "mandarin"], "language_level": ["good command"], "hard_skills": ["printers", "excel", "indesign", "word", "powerpoint", "adobe illustrator", "project management", "outlook", "photoshop", "ms office"], "soft_skills": ["passionate", "flexible", "able to prioritize", "innovative", "project management", "diverse", "attention to details", "accurate"], "languages_combined": [{"language": "english", "language_level": ["good command"]}, {"language": "chinese", "language_level": ["good command"]}, {"language": "mandarin", "language_level": ["good command"]}]}, "experience_required": {"duration": ["at least 5 years"], "field": ["development", "project management"]}}, {"job_id": "100003009035694", "location_code": "hk", "company": "Newsprint Production Group Ltd", "job_title": "Product Developer", "description": "Roles & Responsibilities\n\n\nPerform day-to-day duties, such as following up on development and sample orders, work with customer & team to get the work done within a deadline.\nCoordinate - Maintain continuous and agile communication with design, production merchandising, Logistic & third-party partners to align and synchronize content.\nCoordinating Sample Development with factories to ensure final product is as per customer requirements.\nAssist on production planning with Sales / Merchandising for product style, quantity, delivery date etc. for factory planner to gauge the capacity for bulk production.\nCalculate costings through existing tools and maintenance of database.\nMaintain relationship & smooth communication with suppliers.\nAd hoc assignments for communication and certification purpose (FSC, OEKO TEX, etc)\n\nRequirements\n\n2-3 years of relevant experience working a R&D / Product Merchandiser.\nHigher Diploma in Textile Merchandising, Fashion Technology, or related discipline.\nGood communication skills in spoken and written English and Chinese (Mandarin preferably).\nProficiency in PC skills, such as MS Office (Excel, Word, PPT) - Chinese and English word processing.\nGood analytical skills.\nCapability to prioritize work and manage several projects at a time.\nPrior knowledge in printing, labels and/or packaging industry will be a plus, but not necessary.\nBe flexible and adaptable to a challenging working environment.\nImmediate availability is an advantage.", "employment_types": ["Full Time", "Permanent"], "selling_points": ["2-3 years of relevant experience working", "Spoken & Written English & Mandarin, PC Skill", "Double pay, medical, dental insurance"], "locations": ["Chai Wan"], "categories": ["Manufacturing", "Garment / Textile", "Product Development / Management", "Printing"], "post_time": "2022-01-10T08:11:48Z", "salary": {"currency": null, "max": null, "min": null, "period": "monthly", "term": null}, "salary_visible": false, "title_keywords": ["product developer"], "responsibilities": ["maintenance", "merchandising", "production planning", "design", "coordinate", "communication", "maintain", "ad hoc assignments", "database"], "requirements": {"degrees": ["diploma"], "majors": [], "languages": ["english", "chinese", "mandarin"], "language_level": ["proficiency", "good"], "hard_skills": ["r&d", "excel", "plus", "chinese and english word processing", "word", "analytical skills", "pc skills", "ms office"], "soft_skills": ["flexible", "communication skills", "adaptable", "prioritize", "analytical skills"], "languages_combined": [{"language": "english", "language_level": ["proficiency", "good"]}, {"language": "chinese", "language_level": ["proficiency", "good"]}, {"language": "mandarin", "language_level": ["good"]}]}, "experience_required": {"duration": ["2-3 years"], "field": ["relevant experience"]}}, {"job_id": "100003009034541", "location_code": "hk", "company": "Creative Wealth International Limited", "job_title": "\u6a5f\u68b0\u64cd\u4f5c\u54e1**", "description": "Job Descriptions:\n\nLiaise with overseas clients and factories independently\nIndependently in handling projects follow up from sampling development to production\nHandle orders and monitor production process\nPrepare quotations, sampling and monthly reports\nOccasional travel to overseas if needed\n\nRequirements:\n\nHigh Diploma or above with 2 years relevant working experience\nWith solid printing knowledge\u00a0for garment accessories is preferred\nFluent language skills (written and oral) in English, Mandarin and Cantonese\nAble to work independent, detailed oriented, well organized & under pressure within a tight schedule\nProficient in MS office and English + Chinese word processing\nGood team player and work independently\n\nSalary Range: Negotiable\n\nBenefits:\n\n-Bank holiday\n\n-12~25 days annual leave or above\n\n-5 days working per week\n\n-Medical scheme\n\n-13 months salary\n\n-Performance based Bonus (not guarantee)\n\nWe provide attractive remuneration packages to the right candidates. Interested parties please send following by clicking \"APPLY NOW\".\n\nDetailed curriculum vitae/resume\nDate of availability\nExpected salary\n\n(All personal data provided will be treated in strict confidence and used for recruitment purposed only.)", "employment_types": ["Full Time"], "selling_points": [], "locations": ["Kwun Tong"], "categories": ["Engineering", "Mechanical", "Manufacturing", "Others", "Printing"], "post_time": "2022-01-10T03:37:22Z", "salary": {"currency": null, "max": null, "min": null, "period": "monthly", "term": null}, "salary_visible": false, "title_keywords": [], "responsibilities": ["liaise with", "monitor", "production process", "monthly reports"], "requirements": {"degrees": ["high diploma or above"], "majors": [], "languages": ["cantonese", "english", "chinese", "mandarin"], "language_level": ["proficient", "fluent"], "hard_skills": ["chinese word processing", "ms office"], "soft_skills": ["oral", "good team player", "under pressure", "independent", "detailed oriented", "work independently", "well organized"], "languages_combined": [{"language": "cantonese", "language_level": ["fluent"]}, {"language": "english", "language_level": ["proficient", "fluent"]}, {"language": "chinese", "language_level": ["proficient"]}, {"language": "mandarin", "language_level": ["fluent"]}]}, "experience_required": {"duration": ["2 years"], "field": ["relevant working experience"]}}, {"job_id": "100003009036112", "location_code": "hk", "company": "Global Packaging Limited", "job_title": "Account Executive", "description": "\u5de5\u4f5c\u7bc4\u570d\n\u76e3\u5bdf\u65e5\u5e38\u8cea\u91cf\u5be9\u67e5\u5de5\u4f5c\n\u8ca0\u8cac\u9032\u884c\u539f\u6750\u6599,\u534a\u6210\u54c1\u53ca\u6210\u54c1\u7684\u5316\u5b78,\u7269\u7406\u5316\u9a57\u53ca\u76ee\u6e2c\u7b49\u5de5\u4f5c\n\u8ca0\u8cac\u64b0\u5beb\u9a57\u6e2c\u5831\u544a\n\u8ca0\u8cac\u5316\u9a57\u5ba4\u5100\u5668\u6821\u6b63\u53ca\u4fdd\u990a\u5de5\u4f5c\n\u8ca0\u8cac\u64b0\u5beb\u8cea\u91cf\u5be9\u67e5\u6587\u4ef6(\u5de5\u4f5c\u6307\u793a,\u7269\u6599\u898f\u683c,\u7cfe\u6b63\u53ca\u9810\u9632\u884c\u52d5\u5831\u544a\u7b49)\n\u8ca0\u8cac\u8655\u7406\u7531\u52a9\u7406\u7d93\u7406(\u8cea\u91cf\u5be9\u67e5)\u59d4\u6d3e\u7684\u5176\u5b83\u5de5\u4f5c\n\n\u8077\u4f4d\u8981\u6c42\n\n\u5316\u5b78\u79d1\u6280\u9ad8\u7d1a\u6587\u6191/\u61c9\u7528\u79d1\u5b78\u9ad8\u7d1a\u6587\u6191\u7b49\u6216\u4ee5\u4e0a\u76f8\u95dc\u5b78\u6b77\n\u9808\u5177\u6700\u5c11\u4e09\u5e74\u76f8\u95dc\u5de5\u4f5c\u7d93\u9a57\n\u719f\u6089ISO\u7ba1\u7406\u7cfb\u7d71\n\u80fd\u66f8\u5beb\u4e2d\u82f1\u6587\u53ca\u64cd\u5ee3\u6771\u8a71\u3001\u82f1\u8a9e\u53ca\u666e\u901a\u8a71\n\u61c2\u5f97\u904b\u7528\u96fb\u8166\u8edf\u4ef6(\u6587\u66f8\u8655\u7406(\u5305\u62ec\u4e2d\u6587\u8f38\u5165\u6cd5), \u8a66\u7b97\u8868, \u7c21\u5831\u53ca\u6295\u5f71\u7247\u7b49)\n\u7d30\u5fc3,\u6709\u8cac\u4efb\u5fc3,\u4e3b\u52d5\u53ca\u5177\u5099\u826f\u597d\u6e9d\u901a\u6280\u5de7\n\u5177\u5099\u908f\u8f2f\u601d\u7dad\u53ca\u5206\u6790\u80fd\u529b\n\u9808\u8f2a\u73ed\u5de5\u4f5c\n\n(\u6b61\u8fce\u65b0\u7562\u696d\u4eba\u58eb\u7533\u8acb)\n\n\u00a0\u672c\u516c\u53f8\u63d0\u4f9b\u512a\u539a\u85aa\u916c\u53ca\u798f\u5229\uff0c\u5305\u62ec\u5e74\u7d42\u916c\u91d1\u3001\u91ab\u7642\u53ca\u4eba\u58fd\u4fdd\u96aa\u3001\u81b3\u98df\u53ca\u4ea4\u901a\u6d25\u8cbc\u7b49\uff0c\u52de\u5de5\u5047\u671f\u3002\u6709\u610f\u8005\u8acb\u5c07\u500b\u4eba\u5c65\u6b77\u3001\u5de5\u4f5c\u7d93\u9a57\u3001\u806f\u7d61\u5730\u5740\u53ca\u96fb\u8a71\uff0c\u51fd\u5bc4\u65b0\u754c\u5927\u57d4\u5de5\u696d\u90a8\u5927\u76db\u88572-4\u865f\u4eba\u4e8b\u53ca\u884c\u653f\u90e8\u6536\u6216\u6309\"APPLY NOW\"\u63d0\u4ea4\u7533\u8acb\u6216\u50b3\u771f\u81f32664 4882\u3002\n\n(\u7533\u8acb\u4eba\u6240\u63d0\u4f9b\u7684\u8cc7\u6599\u5c07\u4e88\u4fdd\u5bc6\u53ca\u53ea\u4f9b\u7533\u8acb\u6709\u95dc\u8077\u4f4d\u7528\u9014)\n\n*(\u6b61\u8fce\u65b0\u7562\u696d\u4eba\u58eb\u7533\u8acb)", "employment_types": ["Full Time"], "selling_points": ["High Diploma or above with 2 years relevant work", "With solid printing knowledge is preferred", "5 days working"], "locations": ["Kwai Hing"], "categories": ["Merchandising & Purchasing", "Others", "Manufacturing", "Printing", "Others", "Trading"], "post_time": "2022-01-10T09:23:00Z", "salary": {"currency": null, "max": null, "min": null, "period": "monthly", "term": null}, "salary_visible": false, "title_keywords": ["account executive"], "responsibilities": [], "requirements": {"degrees": [], "majors": [], "languages": [], "language_level": [], "hard_skills": [], "soft_skills": [], "languages_combined": []}, "experience_required": {"duration": [], "field": []}}, {"job_id": "100003009036978", "location_code": "hk", "company": "\u9999\u6e2f\u5370\u9214\u6709\u9650\u516c\u53f8", "job_title": "\u7d44\u9577(\u8cea\u91cf\u5be9\u67e5) (Supervisor (QA))", "description": "Key Responsibilities\n\nResponsible for full spectrum of Administration functions including offices services, insurance, repair, utilities maintenance and dormitory management etc,\nResponsible for full range of HR functions including recruitment, performance management and employee relations,\nOversee for overall factory Administration including warehouse,\nProvide support service for daily and regular office administration functions,\nTake lead for company events, ISO affairs including internal training, audit and review,\nCommunicate with all levels of staff and external partners for Administration & HR related matters,\nHandle ad hoc assignments by Directors.\n\nRequirements\n\nUniversity degree in Business Administration, HR Management or related disciplines\n3 years working experiences in manufacturing factory.\nSelf-Motivated and Aggressive Personality is a MUST\nThorough knowledge in China Labor Law\nProficiency in MS office applications and Chinese word processing\nMature & Strong in leadership with high Accountability\nCandidate must able to Work Under Pressure\nGood command of both Written & Spoken English. Good Mandarin is required\n\nWe offer a competitive remuneration package to successful candidate. Interested parties please send your full resume and expected salary by clicking \u2018Apply Now\u2019.\n\nThe right candidate may join our company before or after Lunar New Year Holiday.\n\n\n\u00a0(All personal information will be treated in strict confidentiality)", "employment_types": ["Full Time"], "selling_points": [], "locations": ["Tai Po Area"], "categories": ["Manufacturing", "Others", "Printing", "Quality Assurance, Control & Testing / ISO"], "post_time": "2022-01-11T01:11:46Z", "salary": {"currency": null, "max": null, "min": null, "period": "monthly", "term": null}, "salary_visible": false, "title_keywords": ["supervisor"], "responsibilities": ["communicate with", "management", "provide support", "maintenance", "office administration", "hr", "review", "audit", "repair", "recruitment", "ad hoc assignments", "insurance", "administration"], "requirements": {"degrees": ["university degree"], "majors": ["related disciplines", "business administration"], "languages": ["english", "chinese", "mandarin"], "language_level": ["proficiency", "good command", "good"], "hard_skills": ["chinese word processing", "ms office"], "soft_skills": ["self-motivated", "accountability", "mature", "thorough", "leadership", "work under pressure"], "languages_combined": [{"language": "english", "language_level": ["good command"]}, {"language": "chinese", "language_level": ["proficiency"]}, {"language": "mandarin", "language_level": ["good"]}]}, "experience_required": {"duration": ["3 years"], "field": ["manufacturing"]}}, {"job_id": "100003009039664", "location_code": "hk", "company": "Charming Printing Limited", "job_title": "Administration & HR Manager", "description": "\n\u8077\u8cac :\u8ca0\u8cac\u5ee0\u90e8\u65e5\u5e38\u6a5f\u5668\u8a2d\u5099\u7684\u64cd\u4f5c\u3001\u7dad\u8b77\u7b49\n\n\u8cc7\u6b77 :\u4e2d\u4e03\u7a0b\u5ea6; 1\u5e74\u7d93\u9a57; \u4e00\u822c\u7cb5\u8a9e; \u4e00\u822c\u666e\u901a\u8a71; \u4e00\u822c\u82f1\u8a9e; \u7565\u61c2\u8b80\u5beb\u4e2d\u6587; \u61c2\u95b1\u8b80\u82f1\u6587\n\n\u5f85\u9047 :\u6bcf\u6708$15,000 - $18,000, \u6709\u5728\u8077\u57f9\u8a13, \u661f\u671f\u4e00\u81f3\u516d: \u4e0a\u53489\u6642\u81f3\u4e0b\u53486\u6642, \u6bcf\u9031\u5de5\u4f5c6\u5929,\u8f2a\u73ed, \u6bcf\u5929\u5de5\u4f5c 8 \u5c0f\u6642\n\n\u7533\u8acb\u9808\u77e5 :\u6c42\u8077\u8005\u53ef\u81f4\u96fb96211656\u8207\u5275\u5049\u4f01\u696d\u6709\u9650\u516c\u53f8\u9673\u5148\u751f\u806f\u7d61\u3002\n\n", "employment_types": ["Full Time", "Permanent"], "selling_points": ["3 years working exp in manufacturing factory", "Oversee for overall factory Admin & warehouse", "Thorough knowledge in China Labor Law"], "locations": ["Lai Chi Kok"], "categories": ["Admin & HR", "Administration / Operation Manager", "HR Director / Manager", "Manufacturing", "Printing"], "post_time": "2022-01-11T10:24:54Z", "salary": {"currency": null, "max": null, "min": null, "period": "monthly", "term": null}, "salary_visible": false, "title_keywords": ["hr manager"], "responsibilities": [], "requirements": {"degrees": [], "majors": [], "languages": [], "language_level": [], "hard_skills": [], "soft_skills": [], "languages_combined": []}, "experience_required": {"duration": [], "field": []}}, {"job_id": "100003009036105", "location_code": "hk", "company": "Global Packaging Limited", "job_title": "Shipping & Administrative Clerk", "description": "Follow up shipment booking and handle all logistics activities with internal and external parties to ensure smooth delivery.\nSupport Sales team to obtain freight cost from logistics agent.\nAble to handle full set of shipping documents, Tradelink system, custom declaration and all related issues.\nOperate Hong Kong warehouse activities of dispatching, receiving, sorting, and distributing deliveries.\nSales sample arrangements.\nManage and prepare labels for goods outer cartons and samples that are shipping from the office.\nVarious office administrative duties such as handle telephone calls, local and international courier to support office daily operations.\nOther ad-hoc job duties if necessary.\n\nJob Requirements\n\n\u00a0Form 5 / DSE or above.\n\u00a02-3 years solid experience in shipment from China/HK to worldwide.\n\u00a0Knowledge of China customs clearance procedure.\n\u00a0Good command of both written and spoken English and Chinese, knowledge of Mandarin preferred.\n\u00a0Advanced computer skills including Chinese word processing, MS Word, Excel and emailing.\n\u00a0Able to work independently with high sense of responsibility, reliable, team player and a desire to drive excellent work.\n\nImmediately available is highly preferred.\n\nSalary Range: Negotiable\n\nBenefits:\n\n-\u00a0 \u00a0Bank holiday\n-\u00a0 \u00a012~25 days annual leave\n-\u00a0 \u00a05 days working per week\n-\u00a0 \u00a0Medical Scheme\n-\u00a0 \u00a013 months salary\n-\u00a0 \u00a0Performance based Bonus (not guarantee)\n\nWe provide attractive remuneration packages to the right candidates. Interested parties please send following by clicking \"APPLY NOW\".\n\n\nDetailed curriculum vitae/resume\nDate of availability\nExpected salary\n\n(All personal data provided will be treated in strict confidence and used for recruitment purposed only.)", "employment_types": ["Full Time"], "selling_points": ["Form 5 / DSE or above.", "With solid shipping knowledge is preferred", "5 days working"], "locations": ["Kwai Hing"], "categories": ["Transportation & Logistics", "Shipping", "Manufacturing", "Printing", "Others", "Trading"], "post_time": "2022-01-10T09:21:14Z", "salary": {"currency": null, "max": null, "min": null, "period": "monthly", "term": null}, "salary_visible": false, "title_keywords": ["shipping", "administrative clerk"], "responsibilities": ["ad-hoc"], "requirements": {"degrees": ["form 5", "dse"], "majors": [], "languages": ["english", "chinese", "mandarin"], "language_level": ["good command"], "hard_skills": ["excel", "chinese word processing", "computer skills", "ms word"], "soft_skills": ["work independently", "advanced", "high sense of responsibility", "team player", "reliable"], "languages_combined": [{"language": "english", "language_level": ["good command"]}, {"language": "chinese", "language_level": ["good command"]}, {"language": "mandarin", "language_level": ["good command"]}]}, "experience_required": {"duration": ["2-3 years"], "field": []}}, {"job_id": "100003009036805", "location_code": "hk", "company": "r-pac Hong Kong Ltd", "job_title": "Sales Executive", "description": "Job Responsibilities:\n\nExecuting the account strategies to drive market share gain at Brand level or vendor level for Corporate Accounts to exceed the sales plan;\nIdentifying and develop new business opportunities by developing new customers and maintaining a good relationships with existing customers;\nUnderstanding market and competitive landscape, conducting competitor analysis to formulate the right sales strategies;\nResponsible for pricing negotiation with customers for gaining more business and also meet company's margin expectation;\nLead and collaborate with different departments to meet customer needs;\nAssist in any ad-hoc projects when assigned.\n\nJob Requirements:\n\nDiploma / Degree holder, preferably in sales and marketing or printing-related disciplines;\nMinimum of 1-2\u00a0years sales work experience; printing, trims, and packaging will be an advantage;\nGood command of spoken and written English, Chinese and Mandarin; and other languages would also be an advantage;\nSales-driven personality, independent, analytical and results-oriented\nGood\u00a0interpersonal, commercial, presentation, and solutions selling skills.\n\nWe offer excellent career development opportunities with a highly competitive salary supported by a benefits program including 5-days work, medical, MPF, and sales incentive plan. Interested parties please click \"APPLY NOW\" for application information.\n\n\u00a0**All information collected will be keptstrictly\u00a0 confidential and solely for recruitment purposes.**", "employment_types": ["Full Time", "Permanent"], "selling_points": ["Selling branding, packaging & RFID solution", "Work with Global Brands & their suppliers", "Work in a multinational company, 5 days workweek"], "locations": ["Kwai Hing"], "categories": ["Sales, CS & Business Devpt", "Business Development", "Manufacturing", "Garment / Textile", "Printing"], "post_time": "2022-01-10T14:38:50Z", "salary": {"currency": null, "max": null, "min": null, "period": "monthly", "term": null}, "salary_visible": false, "title_keywords": ["sales executive"], "responsibilities": ["collaborate with", "develop new business", "maintaining", "analysis", "developing", "executing", "plan", "ad-hoc projects"], "requirements": {"degrees": ["diploma", "degree holder"], "majors": ["related disciplines", "marketing"], "languages": ["english", "chinese", "mandarin"], "language_level": ["good command"], "hard_skills": [], "soft_skills": ["presentation", "interpersonal", "independent", "driven"], "languages_combined": [{"language": "english", "language_level": ["good command"]}, {"language": "chinese", "language_level": ["good command"]}, {"language": "mandarin", "language_level": ["good command"]}]}, "experience_required": {"duration": ["minimum of 1-2 years"], "field": []}}, {"job_id": "100003009039007", "location_code": "hk", "company": "Toppan Forms (Hong Kong) Limited", "job_title": "Project Coordinator", "description": "Job Descriptions\u00a0:\n\nResponsible\u00a0to projects follow-up including project plan, design, customers\u2019 requirements & specifications, assistance in preparation of cost estimation.\nDeterminate project responsibilities by identifying project phases and elements\nConduct project UAT and follow up the implementation performance\nPrepare routine customer reports and documents\nWork closely with Sales Dept on project progress, timely update the project status and provide the problem solving\nEnsure the project is completed within the budgeted cost\nOther ad-hoc project as required\n\nJob\u00a0Requirements\u00a0:\n\nHigher diploma in Business Administration, Computer Science or related discipline\n2\u00a0years or above\u00a0working experience in\u00a0project support and coordination\u00a0\nGood in\u00a0written and spoken\u00a0English & Chinese,\u00a0fair in Mandarin speaking is preferable\nFamiliar with MS Office, including Word,\u00a0Excel\u00a0and Powerpoint\nComputer knowledge, Network is an advantage\nGood interpersonal communication skills and\u00a0self-motivated\nCandidates with more related experience will be considered as Project Engineer\n\nWe offer excellent compensation package, promotion prospects and job satisfaction. Interested parties, please\u00a0email\u00a0your detailed resume with current and expected salary by click \u201cApply Now\u201d.\n\nWe are an Equal Opportunities Employer. Personal data collected will be\u00a0used strictly in accordance with the employer's personal data policy, a copy of which will be provided immediately upon request.\u00a0Candidates who do not notified within 8 weeks may consider their application unsuccessful and the application will be retained up to 24 months.\n\nDisclaimer: The above position description has been designed to indicate the general nature and level of work performed by employees within this classification. It is not designed to contain or be interpreted as a comprehensive list of all duties, responsibilities, and qualifications required of employees assigned to the position.\n\nFor the details of Company Information, please visit\u00a0www.toppanforms.com\u00a0", "employment_types": ["Full Time", "Permanent"], "selling_points": [], "locations": ["Yuen Long"], "categories": ["Manufacturing", "Printing"], "post_time": "2022-01-11T08:22:46Z", "salary": {"currency": null, "max": null, "min": null, "period": "monthly", "term": null}, "salary_visible": false, "title_keywords": ["project coordinator"], "responsibilities": ["ad-hoc", "cost", "cost estimation", "uat", "project plan", "design", "implementation", "project progress", "specifications", "reports"], "requirements": {"degrees": ["diploma"], "majors": ["business administration", "computer science"], "languages": ["english", "chinese", "mandarin"], "language_level": ["good"], "hard_skills": ["excel", "word", "powerpoint", "ms office"], "soft_skills": ["communication skills", "self-motivated", "interpersonal", "coordination"], "languages_combined": [{"language": "english", "language_level": ["good"]}, {"language": "chinese", "language_level": ["good"]}, {"language": "mandarin", "language_level": ["good"]}]}, "experience_required": {"duration": ["2 years"], "field": ["related"]}}, {"job_id": "100003009033934", "location_code": "hk", "company": "Toppan Forms (Hong Kong) Limited", "job_title": "Production Clerk (Yuen Long)", "description": "Job Responsibilities\u00a0:\n\nResponsible to order input and incoming/outgoing goods/material receiving verification;\nCoordinate with internal and external parties to ensure orders information are accurate;\nRegular reports updating and coordinate with internal departments for the general admin. management;\nOther ad-hoc projects as required by department supervisor\n\nJob Requirements\u00a0:\n\nGood command in both English and Chinese;\nGood communication skills, self-motivated and have a good sense of responsibility;\nProficient MS Office application including\u00a0Excel and Word;\n\nWe offer excellent compensation package, promotion prospects and job satisfaction. Interested parties, please\u00a0email\u00a0your detailed resume with current and expected salary by click \u201cApply Now\u201d.\n\nWe are an Equal Opportunities Employer. Personal data collected will be\u00a0used strictly in accordance with the employer's personal data policy, a copy of which will be provided upon request.\u00a0Candidates who do not notified within 8 weeks after submitting your application may consider the application unsuccessful and the application will be retained up to 24 months.\n\nDisclaimer: The above position description has been designed to indicate the general nature and level of work performed by employees within this classification. It is not designed to contain or be interpreted as a comprehensive list of all duties, responsibilities, and qualifications required of employees assigned to the position.\n\nToppan Forms does not accept unsolicited referrals and/or resumes from employment businesses and/or employment agencies. Any resumes submitted in the absence of a signed agreement will become the property of Toppan Forms and no fee shall be due.\n\nFor the details of Company Information, please visit\u00a0www.toppanforms.com\u00a0", "employment_types": ["Full Time", "Permanent"], "selling_points": [], "locations": ["Yuen Long"], "categories": ["Admin & HR", "Clerical / Admin Staff", "Others", "Manufacturing", "Printing"], "post_time": "2022-01-10T02:10:46Z", "salary": {"currency": null, "max": null, "min": null, "period": "monthly", "term": null}, "salary_visible": false, "title_keywords": ["production clerk"], "responsibilities": ["management", "internal and external parties", "coordinate with", "material receiving", "reports", "ad-hoc projects"], "requirements": {"degrees": [], "majors": [], "languages": ["english", "chinese"], "language_level": ["good command"], "hard_skills": ["excel", "word", "ms office"], "soft_skills": ["communication skills", "self-motivated", "sense of responsibility"], "languages_combined": [{"language": "english", "language_level": ["good command"]}, {"language": "chinese", "language_level": ["good command"]}]}, "experience_required": {"duration": [], "field": []}}, {"job_id": "100003009026541", "location_code": "hk", "company": "Continental Conair Ltd", "job_title": "Packaging manager", "description": "Responsibilities:\n\n\nSupport operation of packaging production \u2013 from artwork, imaging color control to production.\nLiaise with contractors, suppliers, and stakeholders\nCoordinate projects regarding improvement or revision of the packaging of assortment items.\nLead the vendor performance management. Analyze supplier performance and communicate the findings and potential risks\nInitiate the continuous development, implementation and improvement of daily processes in the packaging department e.g. artwork, packaging development and packaging optimization.\nDevelop and establish project milestone controlling, Document packaging processes and create work instructions.\nConduct trainings for internal and external stakeholders on packaging processes.\nEnsure the packaging projects can be structurally organized and prioritize according to the requirements.\nTo negotiate the most competitive production cost, while maintaining the standard required. Control and maintain budget, ensuring every production is delivered within agreed expenditure.\n\nJob Requirements:\n\n\nDesign institute graduates or above, major in graphic design / PKG structure or equivalent\nAt least 5 years of related professional experience in the packaging industry.\nGood knowledge on packaging: development process, material, PKG structure, color management, cost & trends.\nWith solid track records in leading packaging re-launch or improvement projects.\nAbility to work in cross-cultural environment and liaise with internal and external stakeholders.\nStrong communication skills highly organized ability to handle tasks and meet deadlines\nGood command of written & spoken English and Chinese (Cantonese & Putonghua).\nImmediately available is preferred\n\nWe offer an attractive remuneration package and comprehensive fringe benefits to suitable candidate. Interested parties, please send your application together with a detail resume including availability, present and expected salary, by e-mail by clicking \"Apply Now\". Your interest will be treated in strict confidence and only shortlisted candidates will be notified.\n\nAll personal data will be treated in strict confidence and collected for recruitment purposes only.", "employment_types": ["Full Time", "Permanent"], "selling_points": [], "locations": ["Not Specified"], "categories": ["Admin & HR", "Administration / Operation Manager", "Transportation & Logistics", "Supply Chain", "Manufacturing", "Printing"], "post_time": "2022-01-07T19:19:44Z", "salary": {"currency": null, "max": null, "min": null, "period": "monthly", "term": null}, "salary_visible": false, "title_keywords": ["manager"], "responsibilities": ["control", "management", "cost", "maintaining", "budget", "implementation", "develop", "coordinate", "maintain", "liaise with contractors"], "requirements": {"degrees": [], "majors": [], "languages": ["cantonese", "putonghua", "english", "chinese"], "language_level": ["good command"], "hard_skills": [], "soft_skills": ["organized", "communication skills", "meet deadlines"], "languages_combined": [{"language": "cantonese", "language_level": ["good command"]}, {"language": "putonghua", "language_level": ["good command"]}, {"language": "english", "language_level": ["good command"]}, {"language": "chinese", "language_level": ["good command"]}]}, "experience_required": {"duration": ["at least 5 years"], "field": ["related"]}}, {"job_id": "100003009030311", "location_code": "hk", "company": "Grand Prix (H.K.) Limited", "job_title": "Project Coordinator (Toys and Games Manufacturing)", "description": "Responsibilities\n\nProvide professional customer service and project development support to clients\nLiaise with suppliers to ensure efficient product development and accurate production\nPrepare and process sales and project related documents such as product specification, quotation, and manufacturing contract\nKeep track of production schedule to ensure on-time delivery\nAssist other duties and ad hoc projects as assigned by the supervisor\nAccurately record and maintain project data in the company\u2019s ERP system\n\nRequirements\n\nBachelor degree or above\nHong Kong citizen with a valid Mainland Travel Permit for Hong Kong and Macau Residents\nFluency in spoken English, Mandarin and Cantonese\nHigh proficiency in written English and Chinese\nA strong sense of responsibility and good interpersonal skills\nAbility to communicate clearly and concisely\nDetail-minded with excellent organization and time management skills\nSelf-motivated, logical and willing to learn\nAt least 2 years of work experience is preferred\nProficiency in MS Office\nKnowledge of offset printing is an advantage\n\nWe offer attractive remuneration package to the right candidate. Interested parties please send your curriculum vitae with expected salary.", "employment_types": ["Full Time"], "selling_points": ["Toys and Games manufacturing", "Early career position", "Quality and service-oriented"], "locations": ["Chai Wan"], "categories": ["Manufacturing", "Product Development / Management", "Printing"], "post_time": "2022-01-07T07:24:04Z", "salary": {"currency": null, "max": null, "min": null, "period": "monthly", "term": null}, "salary_visible": false, "title_keywords": ["project coordinator"], "responsibilities": ["other duties", "data", "related documents", "quotation", "customer service", "ad hoc projects", "schedule", "maintain", "liaise with suppliers"], "requirements": {"degrees": ["degree or above", "bachelor"], "majors": [], "languages": ["cantonese", "english", "chinese", "mandarin"], "language_level": ["fluency", "proficiency"], "hard_skills": ["ms office"], "soft_skills": ["detail-minded", "self-motivated", "sense of responsibility", "time management skills", "willing to learn", "interpersonal skills"], "languages_combined": [{"language": "cantonese", "language_level": ["fluency"]}, {"language": "english", "language_level": ["fluency", "proficiency"]}, {"language": "chinese", "language_level": ["proficiency"]}, {"language": "mandarin", "language_level": ["fluency"]}]}, "experience_required": {"duration": ["at least 2 years"], "field": []}}, {"job_id": "100003009030905", "location_code": "hk", "company": "FUJIFILM Data Management Solutions Asia Limited", "job_title": "Supply Chain Officer", "description": "The Job\n\n\nResponsible for entire supply chain management including but not limited to printing sourcing, inventory planning, shipping and order management etc.\nManage printing vendors including but not limited to sourcing, price negotiation, quality control, etc.\nReceive delivery schedule from our clients\nReconcile request from client with warehouse team\nCooperate with Account Delivery team to define the most practicable delivery schedule\nCompile various kind of reports for management\u2019s review (e.g. delivery report, inventory report, etc.)\nCooperate\u00a0with Finance Team for billing administration\nReconcile P/O balance between warehouses and vendors\nPerform other duties as assigned by supervisor\n\n\u00a0The Person\n\n\nDiploma holder or\u00a0above in related disciplines\nPossess with 3-5 years\u2019 experience in offset printing industries whereas, prior experience in digital printing should be an advantage\nGood interpersonal and communication skills\nIndependent, initiative and a good team player\nGood in spoken and written Chinese and English\nProficiency in using Microsoft Words, Excel & PowerPoint\n\nWe are an equal opportunity employer, offer\u00a05-day week (from 9am to 5:30pm), attractive incentive, shuttle bus service, training opportunity and medical benefits. Interested applicants shall submit a full resume indicating current and expected salary with soonest availability.\n\nAll information provided will be treated in strict confidence and used for recruitment purposes only. Applicants not hearing from us within six weeks may consider their applications unsuccessful. All data of unsuccessful applications will be destroyed after six months.\n", "employment_types": ["Full Time", "Permanent"], "selling_points": ["Responsible for entire supply chain management", "Compile various kind of reports for management", "5-day work, 9:00am - 5:30pm"], "locations": ["Chai Wan"], "categories": ["Manufacturing", "Printing", "Merchandising & Purchasing", "Procurement / Purchasing / Sourcing"], "post_time": "2022-01-07T08:34:44Z", "salary": {"currency": null, "max": null, "min": null, "period": "monthly", "term": null}, "salary_visible": false, "title_keywords": ["supply chain officer"], "responsibilities": ["administration", "order management", "management", "shipping", "inventory planning", "price negotiation", "perform other duties", "inventory", "review", "delivery schedule", "reports", "finance team", "quality control", "cooperate with", "report"], "requirements": {"degrees": ["diploma holder"], "majors": ["related disciplines"], "languages": ["english", "chinese"], "language_level": ["good"], "hard_skills": ["powerpoint", "excel", "words"], "soft_skills": ["communication skills", "good team player", "confidence", "independent", "interpersonal", "initiative"], "languages_combined": [{"language": "english", "language_level": ["good"]}, {"language": "chinese", "language_level": ["good"]}]}, "experience_required": {"duration": ["3-5 years"], "field": ["digital"]}}, {"job_id": "100003009028137", "location_code": "hk", "company": "Seaman Paper Asia Company Limited", "job_title": "Graphic Designer", "description": "Description\u00a0\n\nThis position will be responsible for supporting all commercial teams with their artwork needs. The position will work with our customers/suppliers throughout the development process to ensure that all requested graphics needs can be met. The position will work with their counterparts at the factor level on all sampling processes. Furthermore, the position will develop materials in line with the companies\u2019 visual identity.\n\nTasks\n\n\nSupport all commercial teams in reviewing customer\u2019s artwork layouts\nMonitor, manage and control artwork process, liaison with counterpart at the production level\nProvide internal/external insight on technical aspects of artwork\nMaintain archive of customer artworks\nDesign and develop marketing materials.\nDevelop graphics and layouts in line with companies\u2019 visual identity.\u00a0\u00a0\n\nRequired\n\nStrong knowledge of all relevant artwork software; Illustrator, AI, Photoshop, etc.\nCreative with a strong eye for design\nResult oriented with the ability multitask, prioritize, and manage time efficiently\nWritten and verbal communication skills (Languages: English, Mandarin, Cantonese)\nTeam player with a proactive attitude", "employment_types": ["Full Time"], "selling_points": [], "locations": ["Kwai Fong"], "categories": ["Manufacturing", "Printing"], "post_time": "2022-01-07T01:35:55Z", "salary": {"currency": null, "max": null, "min": null, "period": "monthly", "term": null}, "salary_visible": false, "title_keywords": ["graphic designer"], "responsibilities": ["graphics", "control", "software", "monitor", "teams", "design and develop", "develop", "design", "communication", "maintain", "visual", "marketing materials"], "requirements": {"degrees": [], "majors": [], "languages": ["cantonese", "english", "mandarin"], "language_level": [], "hard_skills": ["graphics", "visual identity", "ai", "illustrator", "factor", "photoshop"], "soft_skills": ["communication skills", "proactive", "responsible", "prioritize", "multitask", "result oriented", "team player", "creative"], "languages_combined": [{"language": "cantonese", "language_level": []}, {"language": "english", "language_level": []}, {"language": "mandarin", "language_level": []}]}, "experience_required": {"duration": [], "field": []}}, {"job_id": "100003009025972", "location_code": "hk", "company": "SGS Hong Kong Limited", "job_title": "Certification Officer (FSC CoC)", "description": "Key responsibilities:\n\nResponsible for audit preparation and audit package submission to SGS HK office for review\nEnsure compliance with the requirements defined in Global System Procedures and Local Procedures\nExecute\u00a0of FSC CoC audits, second party audits and third party management system audits and related services, such as training and seminars\nResponsible for sustainability management projects and\u00a0decision making process of certification\nProvide technical support to Marketing, Sales Executives and Account Executives, if needed\nAssist in tasks assigned by Superiors\nRequirements:\u00a0\n\nDiploma or above; University graduate preferred\n2-4 years or above\u00a0of professional experience in manufacturing of wood / wooden products / paper / paper products; forestry and relate industry management; sustainability management\nIndustrial knowledge in wood / paper supply chain, forestry management and sustainability management; experience in management systems, such as quality, environmental and occupational health & safety, sustainability or FSC CoC\nSuccessful completion of ISO 9001 or ISO 14001 or ISO 45001 or FSC CoC LAC auditor training is an advantage\nProficiency in written English and Chinese technical report writing skills\nGood command of English, Putonghua and Cantonese\u00a0\nCandidate with less experience will be considered as Assistant Certification Officer\n\nAs a caring company, SGS not only offers a competitive remuneration package but also offers staff caring items to the right candidates, including:\n\n5-day Work Week\u00a0\u00a0\u00a0\u00a0\u00a0\u00a0\u00a0\u00a0\u00a0\u00a0\u00a0\u00a0\u00a0\u00a0\u00a0\u00a0\u00a0\u00a0\u00a0\u00a0\u00a0\u00a0\u00a0\u00a0\u00a0\u00a0\u00a0\u00a0\u00a0\u00a0\u00a0\u00a0\u00a0\u00a0\u00a0\u00a0\u00a0\u00a0\u00a0\u00a0\u00a0\u00a0\u00a0\u00a0\u00a0\u00a0\u00a0\u00a0\nDouble Pay and Performance Bonus\nDental and Medical Benefits\nLife Insurance\nAnnual Leave\nPaid Maternity Leave and Paternity Leave\nOn-the-Job Training\u00a0\u00a0\u00a0\u00a0\u00a0\u00a0\u00a0\u00a0\u00a0\u00a0\u00a0\u00a0\u00a0\u00a0\u00a0\u00a0\u00a0\u00a0\u00a0\u00a0\u00a0\u00a0\u00a0\u00a0\u00a0\u00a0\u00a0\u00a0\u00a0\u00a0\u00a0\u00a0\u00a0\u00a0\nEducation and Training Subsidies\nFree Shuttle Bus Service\nEmployee Assistance Program (EAP)\nCareer Advancement Opportunities\nStaff Activities\n\nInterested parties please send your full resume with expected salary and date available by clicking \"Apply Now\"\n\n(Data received will be kept confidential and used for processing application only.)", "employment_types": ["Full Time", "Permanent"], "selling_points": ["Double Pay and Performance Bonus", "Testing and Certification Industry", "FSC CoC Audit"], "locations": ["Shatin Area"], "categories": ["Sciences, Lab, R&D", "Environmental Science / Waste Management", "Manufacturing", "Printing", "Quality Assurance, Control & Testing / ISO"], "post_time": "2022-01-06T06:57:07Z", "salary": {"currency": null, "max": null, "min": null, "period": "monthly", "term": null}, "salary_visible": false, "title_keywords": ["officer"], "responsibilities": ["management", "technical support", "review", "procedures", "audit", "ensure compliance", "audits", "third party"], "requirements": {"degrees": ["university graduate", "diploma or above"], "majors": [], "languages": ["cantonese", "putonghua", "english", "chinese"], "language_level": ["proficiency", "good command"], "hard_skills": ["writing skills"], "soft_skills": ["writing skills"], "languages_combined": [{"language": "cantonese", "language_level": ["good command"]}, {"language": "putonghua", "language_level": ["good command"]}, {"language": "english", "language_level": ["proficiency", "good command"]}, {"language": "chinese", "language_level": ["proficiency"]}]}, "experience_required": {"duration": ["2-4 years"], "field": ["management", "manufacturing", "sustainability", "environmental", "occupational health & safety"]}}, {"job_id": "100003009030494", "location_code": "hk", "company": "Max Fortune Industrial Ltd", "job_title": "Merchandiser (5-day work)", "description": "Position highlights:\n\nUnique learning environment to develop your skills\nGreat opportunities, career path and C&B package\nA fun place to work\n\n\u00a0Responsibilities:\n\nPrepare presentation materials and offer to client\nIdentify client needs and promote business\nFollow-up sales order\nInitiate and participate in sales activities\nMaintain and enhance business relationship with customers\n\nRequirements:\n\nDegree holder in any disciplines\nPrefer with 3-5 years working experience in export business\nProactive, energetic and self-motivated.\nGood presentation and communication skills\nGood command of spoken & written English and Putonghua\nFamiliar with MS Word, Excel and Chinese typing\nCandidates with more experience will be considered as Senior post\n\nWe offer attractive remuneration package including 5-day work, 14-day annual leave, birthday leave to attract, retain and motivate talent.\u00a0\n\nInterest parties please submit your application with updated\u00a0resume\u00a0and current/ expected salary.\n\nPlease visit our web site\u00a0http://www.max-fortune.com\u00a0for company information.\n\nData collected will be used for recruitment purpose only.", "employment_types": ["Full Time"], "selling_points": [], "locations": ["Southern Area"], "categories": ["Manufacturing", "Printing", "Sales, CS & Business Devpt", "Sales - Sales Management", "Sales Administration"], "post_time": "2022-01-07T07:35:42Z", "salary": {"currency": null, "max": null, "min": null, "period": "monthly", "term": null}, "salary_visible": false, "title_keywords": ["merchandiser"], "responsibilities": ["sales activities", "maintain"], "requirements": {"degrees": ["degree holder"], "majors": ["any disciplines"], "languages": ["putonghua", "english", "chinese"], "language_level": ["good command"], "hard_skills": ["excel", "typing", "ms word"], "soft_skills": ["communication skills", "self-motivated", "proactive", "energetic", "presentation"], "languages_combined": [{"language": "putonghua", "language_level": ["good command"]}, {"language": "english", "language_level": ["good command"]}, {"language": "chinese", "language_level": []}]}, "experience_required": {"duration": ["3-5 years"], "field": ["business"]}}, {"job_id": "100003009022712", "location_code": "hk", "company": "Newsprint Production Group Ltd", "job_title": "Customer Service / CRM", "description": "Requirement\n\n\u2022 Diploma holder or above with 2-3 years working experience;\n\u2022 Good command of spoken & written English and Mandarin;\n\u2022 Detail-oriented person with good organization abilities;\n\u2022 Well verse in Microsoft Excel & Outlook\n\nJob Description\n\n\u2022 Monitor and follow up status of the on-line orders;\n\u2022 Maintain quality communication with customers and provide solutions to resolve customer requests;\n\u2022 Coordination work with our overseas office on customer care processing;\n\u2022 Assist on stock monitoring;\n\u2022 Coordination with suppliers on stock replenishment;\n\u2022 Work on system data to generate CRM reports and recommendations\n\n* Fresh graduates are welcome *\n\nWe work in a nice, modern and convenient office (only 3 minutes walk from Chai Wan MTR station).", "employment_types": ["Full Time", "Permanent"], "selling_points": ["Diploma holder; 2-3 years working experience", "Good command of spoken English and Mandarin", "Double pay, performance bonus"], "locations": ["Chai Wan"], "categories": ["Sales, CS & Business Devpt", "Business Development", "Customer Service - Supervisor / Officer", "Manufacturing", "Printing"], "post_time": "2022-01-05T06:20:45Z", "salary": {"currency": null, "max": null, "min": null, "period": "monthly", "term": null}, "salary_visible": false, "title_keywords": ["customer service"], "responsibilities": ["stock replenishment", "maintain quality", "monitoring", "monitor", "coordination with", "provide solutions", "system data", "communication", "reports", "coordination", "customer requests"], "requirements": {"degrees": ["diploma holder"], "majors": [], "languages": ["english", "mandarin"], "language_level": ["good command"], "hard_skills": ["outlook", "microsoft excel"], "soft_skills": ["detail-oriented"], "languages_combined": [{"language": "english", "language_level": ["good command"]}, {"language": "mandarin", "language_level": ["good command"]}]}, "experience_required": {"duration": ["2-3 years"], "field": []}}, {"job_id": "100003009022680", "location_code": "hk", "company": "Newsprint Production Group Ltd", "job_title": "Product Developer", "description": "APPLY NOW\u00a0\n\nDegree Holder or above with 2 years working experience;\nProficiency in Microsoft Excel; Good analytical skills;\nCapability to prioritize work and manage several projects at a time;\nCommunication ability in spoken and written English and Chinese (Mandarin is a MUST);\nPrior knowledge in labels and packaging industry will be a plus, but not necessary.\n\nTHE JOB\n\nGet brief from Sales team and study product's feasibility;\nSelect suitable materials and processes;\nCalculate costings through existing tools and maintenance of databases;\nMaintain relationship & smooth communication with suppliers;\nWork closely with HK other teams such Production, Logistic & Merchandising;\nEuropean customer oriented\nAd hoc assignments for communication and certification purpose (FSC, OEKO TEX, etc);\nBecome part of our dynamic team, bring your vision and your energy.\n\nWe work in a nice, modern and convenient office (only 3 minutes walk from Chai Wan MTR station).\n\nPlease visit our website: www.newsprintgroup.com\u00a0\n\nWe offer competitive remuneration package with comprehensive fringe benefits to the right candidate. Interested parties, please CLICK the \"APPLY NOW\" button,\u00a0and send your resume to us with your last and expected salary.\n\nAll personal data collected will be treated in strict confidence and used for recruitment only.", "employment_types": ["Full Time", "Permanent"], "selling_points": ["Proficiency in Microsoft Excel, Foreigner welcome", "Off-set Printing, paper, labels", "Spoken & Written English & Mandarin"], "locations": ["Chai Wan"], "categories": ["Manufacturing", "Garment / Textile", "Product Development / Management", "Printing"], "post_time": "2022-01-05T06:12:46Z", "salary": {"currency": null, "max": null, "min": null, "period": "monthly", "term": null}, "salary_visible": false, "title_keywords": ["product developer"], "responsibilities": ["maintenance", "teams", "merchandising", "website", "communication", "maintain", "sales team", "ad hoc assignments", "databases"], "requirements": {"degrees": ["degree holder"], "majors": [], "languages": ["english", "chinese", "mandarin"], "language_level": [], "hard_skills": ["plus", "maintenance", "tex", "nice", "analytical skills", "microsoft excel", "dynamic", "databases", "wan"], "soft_skills": ["prioritize", "analytical skills", "communication", "dynamic", "smooth"], "languages_combined": [{"language": "english", "language_level": []}, {"language": "chinese", "language_level": []}, {"language": "mandarin", "language_level": []}]}, "experience_required": {"duration": ["2 years"], "field": []}}, {"job_id": "100003009021603", "location_code": "hk", "company": "ConnectedGroup Limited", "job_title": "Project Manager - Printed Category, Global Retailers", "description": "Job Responsibilities\u00a0\n\n-\u00a0 \u00a0To work closely with Design Director and her team in creating contents, in both English and Chinese, for marketing materials and or publications including but not limit to press releases, catalogues and posts.\n\n-\u00a0 \u00a0 To deliver copywriting, translation, proofreads and/or edits, in both English and Chinese, in a timely manner and on schedule\n\n\u00a0Requirements\n\n-\u00a0 Experience working in art gallery most preferable\n\n-\u00a0 University graduate, preferable in art and design related subjects\n\n-\u00a0 \u00a0Min. 2 years of relevant copywriting experience, preferably in agency environment\n\n-\u00a0 \u00a0 Able to work under pressure and meet deadlines\n\n-\u00a0 \u00a0 Strong sense of responsibility, detail-minded with excellent communication skills\n\n-\u00a0 \u00a0 Hard-working, stable, motivated and detail minded\n\n\n\nWe offer competitive remuneration package to the right candidates. \u00a0Interest parties,\u00a0please e-mail detailed CV with current salary, expected salary and date of availability and the porfolio file to HR department by clicking\u00a0APPLY NOW\u00a0for interview arrangement.\u00a0\u00a0\n\nTo understand more of our company, please visit our website at\u00a0http://www.paperhouse.com.hk\u00a0or\u00a0http://www.offsetprinting.com.hk\n\nAll information received would be kept confidential and for recruitment use only.", "employment_types": ["Full Time", "Permanent"], "selling_points": ["Global Retailers", "Project Management", "Excellent Career path and Benefit"], "locations": ["Not Specified"], "categories": ["Manufacturing", "Production Planning / Control", "Merchandising & Purchasing", "Stationery", "Printing"], "post_time": "2022-01-05T04:19:20Z", "salary": {"currency": "HKD", "max": 54999, "min": 45000, "period": "monthly", "term": null}, "salary_visible": true, "title_keywords": ["project manager"], "responsibilities": ["a timely manner", "design", "schedule", "contents", "marketing materials"], "requirements": {"degrees": ["university graduate"], "majors": ["art", "design"], "languages": [], "language_level": [], "hard_skills": [], "soft_skills": ["detail-minded", "communication skills", "sense of responsibility", "motivated", "hard-working", "meet deadlines", "stable", "work under pressure"], "languages_combined": []}, "experience_required": {"duration": ["2 years"], "field": ["copywriting", "agency"]}}, {"job_id": "100003009019458", "location_code": "hk", "company": "Offset Printing Limited", "job_title": "Copywriter", "description": "Project Manager\n\nGlobal Retailer\nFast-Growing Company\nExcellent working Culture\nGlobal Exposure\n\nResponsibility:\n\nCoordinate internal resources and third parties/vendors for the flawless execution of multiple projects\nEstablish and maintain relationships with buyers, customers and internal stakeholders\nEnsure that all projects are delivered on time, within the scope and within budget\nAssist in the definition of project scope and objectives, involving all relevant internal stakeholders and ensuring technical feasibility\nEnsure resource availability and allocation\nDevelop a detailed project plan to monitor and track progress\nManage changes to the project scope, project schedule, and project costs using appropriate verification techniques\nMeet with clients to take detailed ordering briefs and clarify specific requirements of each project\nTrack project performance, specifically to analyze the successful completion of short and long-term goals\nReport and escalate to management as needed\nPerform risk management to minimize potential risks\n\nRequirement:\n\nMinimum 6 years working experience in project management\nBachelor's Degree\nExcellent client-facing and internal communication skills\nExcellent written and verbal communication skills\nSolid organizational skills including attention to detail and multitasking skills", "employment_types": ["Full Time"], "selling_points": [], "locations": ["North Point"], "categories": ["Design", "Graphics", "Manufacturing", "Printing", "Professional Services", "Translation"], "post_time": "2022-01-04T07:43:27Z", "salary": {"currency": null, "max": null, "min": null, "period": "monthly", "term": null}, "salary_visible": false, "title_keywords": ["copywriter"], "responsibilities": ["maintain relationships", "management", "budget", "monitor", "project plan", "develop", "coordinate", "schedule", "multiple projects", "costs", "report"], "requirements": {"degrees": ["degree", "bachelor"], "majors": [], "languages": [], "language_level": [], "hard_skills": ["project management"], "soft_skills": ["communication skills", "organizational skills", "project management", "attention to detail", "client-facing"], "languages_combined": []}, "experience_required": {"duration": ["minimum 6 years"], "field": ["project management"]}}, {"job_id": "100003009014407", "location_code": "hk", "company": "Unique Concepts Company Limited", "job_title": "Shift Digital Print Operator \u8f2a\u73ed\u6578\u78bc\u5674\u756b\u64cd\u4f5c\u54e1", "description": "\u8077\u8cac\n\n\n\u8ca0\u8cac\u6aa2\u67e5\u5ba2\u6236\u6a94\u6848\n\u4fee\u6539\u7a3f\u4ef6\n\u6838\u5c0d\u5167\u5bb9\u4ee5\u7b26\u5408\u5ba2\u6236\u9700\u6c42\n\u8981\u6c42\n\n\u4e2d\u4e09\u7a0b\u5ea6; 2\u5e74\u7d93\u9a57;\n\u826f\u597d\u7cb5\u8a9e\u512a\u5148; \u4e00\u822c\u666e\u901a\u8a71; \u4e00\u822c\u82f1\u8a9e; \u61c2\u8b80\u5beb\u4e2d\u6587; \u7565\u61c2\u8b80\u5beb\u82f1\u6587;\n\u61c2PhotoShop; \u61c2Macintosh; \u61c2Illustrator;\n\u80fd\u7368\u7acb\u8655\u7406\u5de5\u4f5c,\u5b88\u6642,\u6709\u8cac\u4efb\u611f,\n\u5177\u6578\u78bc\u5674\u756b\u5de5\u4f5c\u7d93\u9a57\u512a\u5148\n\u5f85\u9047 :\n\n\u6bcf\u6708$13,000 - $15,000\n\u6709\u52a0\u5de5\u8cbb\uff0c\u6642\u85aa\u5de5\u534a\n\u661f\u671f\u4e00\u81f3\u4e94: \u4e0a\u53489\u6642\u81f3\u4e0b\u53486\u6642/ \u4e0b\u53482\u6642\u81f3\u4e0b\u534811\u6642,\u8f2a\u73ed, \u6bcf\u5929\u5de5\u4f5c 8 \u5c0f\u6642\u53ca\u661f\u671f\u516d: \u4e0a\u53489\u6642\u81f3\u4e0b\u53486\u6642, \u661f\u671f\u516d\u9577\u77ed\u9031\uff0c\u77ed\u9031\u4f11\u5168\u65e5\n\u6c42\u8077\u8005\u53ef\u96fb\u90f5\u5c65\u6b77\u8868\u6216\u5f90\u5c0f\u59d0\u6d3d\u00a02519 2613", "employment_types": ["Full Time"], "selling_points": [], "locations": ["Cheung Sha Wan"], "categories": ["Media & Advertising", "Production", "Print Media", "Manufacturing", "Printing"], "post_time": "2022-01-03T03:23:10Z", "salary": {"currency": null, "max": null, "min": null, "period": "monthly", "term": null}, "salary_visible": false, "title_keywords": ["operator"], "responsibilities": [], "requirements": {"degrees": [], "majors": [], "languages": [], "language_level": [], "hard_skills": [], "soft_skills": [], "languages_combined": []}, "experience_required": {"duration": [], "field": []}}, {"job_id": "100003009022685", "location_code": "hk", "company": "Newsprint Production Group Ltd", "job_title": "Software Engineer / Developer", "description": "He/she is responsible for understanding business requirements, design, develop and test the implementations needed to existing or new systems.\n\nResponsibilities:\n\nUnderstand product requirements, participate in development, testing and implementation of applications based on our existing systems.\nDevelop existing modules for the existing in-house ERP\nTo investigate, troubleshoot and resolve production issues\nArchitect and build new features for the technical tools offered by the Company\nPrepare test scripts and data, and participate in system tests\nFocus on code quality and manage its evolution\nPerform functional enhancement, system deployment and testing\n\nRequirements\n\nBachelor\u2019s degree in Computer Science or related fields. Fresh graduates are welcome.\nKnowledge and experience in\u00a0C# programming with knowledge in Microsoft .NET Framework, WPF, MVVM, XAML, REST web services with ASP.NET MVC, Entity Framework and best practices in the industry\nExperience with relational databases, including SQL queries\nExperience in web application development, ERP system, database design and development are an advantage\nKnowledge/Experience of Agile software development lifecycle would be a plus\nOrganized and motivated, you have Good analytical and communication skills\nYou have good commands of both written and spoken English and Chinese\nWilling to learn and a good team player", "employment_types": ["Full Time", "Permanent"], "selling_points": ["Degree holder in Computer Science", "Knowledge and experience in C# programming", "Double pay, Performance Bonus, Medical/Dental Insu"], "locations": ["Chai Wan"], "categories": ["Information Technology (IT)", "Software Development", "Manufacturing", "Printing", "E-commerce", "Business Development"], "post_time": "2022-01-05T06:14:30Z", "salary": {"currency": null, "max": null, "min": null, "period": "monthly", "term": null}, "salary_visible": false, "title_keywords": ["software engineer", "developer"], "responsibilities": ["data", "systems", "quality", "implementation", "develop", "testing", "troubleshoot"], "requirements": {"degrees": ["degree", "bachelor"], "majors": ["computer science"], "languages": ["english", "chinese"], "language_level": ["good"], "hard_skills": ["plus", "web application development", "agile", "sql", "erp system", "databases", "programming", "web services", "c#"], "soft_skills": ["communication skills", "organized", "good team player", "agile", "willing to learn", "motivated"], "languages_combined": [{"language": "english", "language_level": ["good"]}, {"language": "chinese", "language_level": ["good"]}]}, "experience_required": {"duration": [], "field": ["software development", "development", "design", "sql", "erp system", "programming", "database", "application development"]}}, {"job_id": "100003009018629", "location_code": "hk", "company": "HB&P Limited", "job_title": "Graphic & Print Production Designer (\"Workshop Warrior\")", "description": "You\u2019ll get a chance to unleash your creativity in a team creating branding solutions for corporate clients and marketing projects. At the same you will have a good sense of practicality, as you design from initial concept, to proof of concept/prototype and even real production.\u00a0\n\n\nBrands are a bit like our clients' babies so this hands-on print production role requires thought, care and dedication to make each brand extension a successful and rewarding experience!\n\n\nThis role requires:\n\nA Degree, diploma or experience in any discipline (but ideally design or marketing related)\nProficiency in Adobe Illustrator and Photoshop (and other graphic design software)\nExcellent communication in English and Cantonese (spoken and written)\nExcellent time-management skills and dedication to meeting deadlines\nProduction using various printing and engraving machines\nResponsibility to perform routine equipment maintenance and liaise with equipment and product suppliers when needed\n\nThe ideal candidate also:\n\nWill be able to identify and grasp CONCEPTS and MOOD for each project\nIs a GOOD COMMUNICATOR that offers opinions but also respects and accepts differing points of view\nIs a PROBLEM SOLVER with a constant IMPROVEMENT MINDSET\nIs SELF-MOTIVATED to LEARN\nIs CONSIDERATE of others and COMMITTED to TEAM SUCCESS\n\nThe following skills/interests would be advantageous\n\nA geniune interest in print production\nDigital 3D rendering experience\nPhotography, digital media and web design experience\nFluency in spoken and written Mandarin\n\nWe recognize no-one is perfect straight-off-the-bat, so, if you can prove you are\n\nmeet most of the above criteria and are\ncommitted to coming up to speed on the rest\u2026.\n\n\u2026.then, have a go \u2013 we would love to hear from you!\n", "employment_types": ["Full Time", "Part Time", "Permanent", "Internship"], "selling_points": [], "locations": ["Tsuen Wan Area"], "categories": ["Design", "Graphics", "Media & Advertising", "Print Media", "Manufacturing", "Printing"], "post_time": "2022-01-04T04:07:54Z", "salary": {"currency": null, "max": null, "min": null, "period": "monthly", "term": null}, "salary_visible": false, "title_keywords": ["designer"], "responsibilities": ["management", "software", "maintenance", "3d rendering", "graphic design", "marketing projects", "design", "communication", "liaise with"], "requirements": {"degrees": ["diploma", "degree"], "majors": ["marketing", "design"], "languages": ["cantonese", "english", "mandarin"], "language_level": ["fluency", "excellent"], "hard_skills": ["web design", "no", "maintenance", "adobe illustrator", "make", "go", "photoshop"], "soft_skills": ["self-motivated", "problem solver", "communication", "committed", "hands-on", "communicator", "ideal"], "languages_combined": [{"language": "cantonese", "language_level": ["excellent"]}, {"language": "english", "language_level": ["excellent"]}, {"language": "mandarin", "language_level": ["fluency"]}]}, "experience_required": {"duration": [], "field": ["brand", "related", "print", "design", "marketing", "digital media", "digital"]}}, {"job_id": "100003009015937", "location_code": "hk", "company": "Lidl Asia Pte. Limited (Hong Kong Branch)", "job_title": "(Senior) Technical Writer", "description": "Summary\n\nLidl are hiring a (Senior) Technical Writer to support the Artwork and Packaging team in enhancing their technical writing capability. The successful candidate will create technical documentation based on product specifications and samples, and will also build up a database for process facilitation.\n\nWhat will you do?\nCreate technical documentations, including instruction manuals, safety / assembling manuals, and quick start guides for a wide variety of consumer goods.\nOrganise materials and complete writing assignments in accordance with all relevant product standards and countries regulations in the EU, UK, and US.\nCreate / edit line drawings, sketches, diagrams, OSD screenshots, table / charts to illustrate material.\nAlign with Merchandising and Quality Assurance teams during the documentation creation and finalisation phases. In terms of on-time delivery and ensuring accuracy of specifications, product assembly steps, and operating procedures of the products.\nUnderstand complex concepts and communicate the information in a way that is engaging and understood by end-users at various technical levels.\nGather feedback on instruction manuals from Quality Assurance team / Testing institutes to improve usability and marketability. Get alignment and execute final changes on instruction manuals to reduce correction loops before and after translations.\nAct as an editor to ensure terminology and style consistency in the documentation across product categories and organisation.\nPrepare / typeset and review instruction manuals for translation process.\nCooperate closely with Design, Translation and Artwork Team in the fields of graphics, artwork and packaging management based on internal quality requirements.\nBuild and maintain content / translation library and templates for standardisation purposes.\nAssist in proofreading, technical problem solving, reviewing test reports, and communicating with testing institutes if required.\nWork in ad-hoc project support and other duties as assigned.\n\nPlease note this is a 12-month contract with the potential to go permanent.\n\nWhat will you need?\n\nUniversity degree in Technical Communication, Technical Translation, or related fields or work experience as Technical Writer\u00a0\n\n2 - 4 years' work experience in the field of technical documentation\u00a0\n\nExperience with Power Tools, SDA, Lightings, and Hi-Tech (smart IoT) product groups will be an advantage\n\nExemplary attention to detail and time management skills\n\nWork independently on written assignments and be a dependable, strong team player with excellent interpersonal and organisational skills\n\nProficiency in Adobe InDesign, Adobe Illustrator, and Acrobat\u00a0\n\nExcellent writing skills in English, proficiency in German or other European languages will be an advantage\n\nAbility to work in a fast-paced environment whilst under pressure to meet tight deadlines\n\nWhat do we offer?\n\nWe are dedicated to fostering a family-friendly culture and work environment and we are an equal opportunities employer and welcome applications from all candidates with the required skills and experience.\n\n\u00a0\nMarket Leading Remuneration Package:\n\nDouble pay and discretionary bonus\n\nChoice of MPF provider\n\nLife Insurance\n\nMedical Insurance\n\nSupportive Environment:\n\nRental re-imbursement scheme\n\nFlexible work arrangements\n\nIn-house training courses\n\nTraining sponsorship scheme\n\nHealth Check\n\nVision Check\n\nSupporting your child\u2019s education with advice from a leading education consultant\n\nWork-Life Balance:\n\n5 day week\n\nCompetitive Annual Leave\n\nCharity, Community and Sporting Events\n\nWe are dedicated to fostering a family-friendly culture and work environment and we are an equal opportunities employer and welcome applications from all candidates with the required skills and experience.\n\n\u00a0\nMarket Leading Remuneration Package:\n\nDouble pay and discretionary bonus\n\nChoice of MPF provider\n\nLife Insurance\n\nMedical Insurance\n\nSupportive Environment:\n\nRental re-imbursement scheme\n\nFlexible work arrangements\n\nIn-house training courses\n\nTraining sponsorship scheme\n\nHealth Check\n\nVision Check\n\nSupporting your child\u2019s education with advice from a leading education consultant\n\nWork-Life Balance:\n\n5 day week\n\nCompetitive Annual Leave\n\nCharity, Community and Sporting Events", "employment_types": ["Contract"], "selling_points": ["2-4+ years exp. in technical documentation", "Must be fluent in English", "Office located in ICC building"], "locations": ["Tsim Sha Tsui"], "categories": ["Marketing / Public Relations", "Marketing - Marketing Communication", "Manufacturing", "Printing", "Others", "Technician"], "post_time": "2022-01-03T07:57:04Z", "salary": {"currency": null, "max": null, "min": null, "period": "monthly", "term": null}, "salary_visible": false, "title_keywords": [], "responsibilities": ["regulations", "ad-hoc", "merchandising", "quality", "design", "drawings", "communication", "maintain", "database", "product categories", "graphics", "other duties", "teams", "testing", "reports", "management", "review", "procedures", "sketches", "specifications", "proofreading", "documentation", "communicating with"], "requirements": {"degrees": ["university degree"], "majors": [], "languages": ["german", "english"], "language_level": ["advantage", "excellent", "proficiency"], "hard_skills": ["graphics", "acrobat", "adobe indesign", "writing skills", "adobe illustrator", "problem solving", "documentation", "translation", "go", "documentations"], "soft_skills": ["work independently", "meet tight deadlines", "under pressure", "time management skills", "fast-paced environment", "writing skills", "problem solving", "communication", "organisational skills", "attention to detail", "organisation", "team player", "interpersonal"], "languages_combined": [{"language": "german", "language_level": ["proficiency", "advantage", "excellent"]}, {"language": "english", "language_level": ["proficiency", "advantage", "excellent"]}]}, "experience_required": {"duration": ["2 - 4 years"], "field": ["related", "tech"]}}, {"job_id": "100003009014981", "location_code": "hk", "company": "", "job_title": "Purchasing clerk/ Trims Sales / Trims Coordinator -- Fabric/Garment/Trims", "description": "Takara Company\n\nPurchasing clerk/ Trims Sales / Trims Coordinator --\u00a0 Fabric/Garment/Trims/Zipper/label\n\u00a0\n-\u00a0F.5, IVE, Poly Graduate, Fresh Grad\u00a0\n- Good English & Mandarin\n- Factory experiences and advantage\n- Good knowledge of Sourcing, sampling and following orders\n\u00a0 - MUST Be immediate available\n\u00a0\n\u00a0\n\n\n\nPlease send your application with detailed resume and expected salary to\nhr@takara.hk\u00a0\u00a0\n**Personal data collected will be used for recruitment purpose only**\n", "employment_types": ["Full Time", "Permanent"], "selling_points": [], "locations": ["Cheung Sha Wan"], "categories": ["Manufacturing", "Garment / Textile", "Merchandising & Purchasing", "Fabrics", "Printing"], "post_time": "2022-01-03T04:46:15Z", "salary": {"currency": null, "max": null, "min": null, "period": "monthly", "term": null}, "salary_visible": false, "title_keywords": ["coordinator", "purchasing clerk", "sales"], "responsibilities": ["personal data", "recruitment"], "requirements": {"degrees": [], "majors": [], "languages": ["english", "mandarin"], "language_level": ["good"], "hard_skills": [], "soft_skills": ["detailed"], "languages_combined": [{"language": "english", "language_level": ["good"]}, {"language": "mandarin", "language_level": ["good"]}]}, "experience_required": {"duration": [], "field": []}}, {"job_id": "100003009020387", "location_code": "hk", "company": "FUJIFILM Data Management Solutions Asia Limited", "job_title": "Assistant Production Manager (Printing & Mailing Technologies)", "description": "The Job\n\nManage the team on day-to-day production, monitor the process of inbound and outbound services as well as the cost reporting\nResources planning with KPI capturing in order to optimize the productivity in every shift of performance\nLiaise with internal & external parties to achieve pre-defined agreed service level (SLA) in order to ensure quality & accuracy assurance and as the result to meet the customer requirements\nFollow through internal policy, working procedures with HKP, HKMA & HKIA requirements to complete each job order as required\nWell manage & allocate adequate resources and maximize the capacity to deal with any unexpected job orders and meet with the tight delivery schedule\nIdentifying areas of improvement and propose corrective and/or preventative action whenever required\nResponsible for the monthly reporting and participate internal review meeting for improvement & follow up\nPerform any ad-hoc tasks as assigned\n\n\u00a0The Person\n\nDiploma / Associate Degree holder or above in Business Management or related disciplines\nMinimum of 8 years manufacturing or BPO operations management or similar industry experience\nExperience in developing and implementing standard procedures and processes\nGood problems solving and proactively to look for alternatives and / improvement plan\nCommitted attitude and able to work under pressure to meet with client\u2019s SLA\nGood interpersonal skills and be a good team player\nGood in spoken and written Chinese (e.g. Cantonese) and English\nProficiency in using Microsoft Words, Excel and PowerPoint\nPrior experienced in ERP systems is essential\nCandidate with more experience can be considered as Production Manager\n\nWe are an equal opportunity employer, attractive incentive, shuttle bus service, training opportunity and medical benefits. Interested applicants shall submit a full resume indicating current and expected salary with soonest availability.\n\nAll information provided will be treated in strict confidence and used for recruitment purposes only. Applicants not hearing from us within six weeks may consider their applications unsuccessful. All data of unsuccessful applications will be destroyed after six months.\n", "employment_types": ["Full Time", "Permanent"], "selling_points": ["Monitor the process of inbound & outbound services", "Responsible for cost control & cost related report", "Excellent career exposure"], "locations": ["Chai Wan"], "categories": ["Engineering", "Manufacturing & Production", "Manufacturing", "Printing"], "post_time": "2022-01-04T10:49:41Z", "salary": {"currency": null, "max": null, "min": null, "period": "monthly", "term": null}, "salary_visible": false, "title_keywords": ["assistant production manager"], "responsibilities": ["reporting", "cost", "ad-hoc tasks", "external parties", "monitor", "quality", "procedures", "review", "delivery schedule", "liaise with", "planning"], "requirements": {"degrees": ["associate degree", "diploma"], "majors": ["related disciplines", "business"], "languages": ["cantonese", "english", "chinese"], "language_level": ["good"], "hard_skills": ["business management", "excel", "erp systems", "words", "powerpoint", "sla"], "soft_skills": ["committed", "good team player", "interpersonal skills", "work under pressure"], "languages_combined": [{"language": "cantonese", "language_level": []}, {"language": "english", "language_level": []}, {"language": "chinese", "language_level": ["good"]}]}, "experience_required": {"duration": ["minimum of 8 years"], "field": ["manufacturing", "operations management", "developing"]}}, {"job_id": "100003009009428", "location_code": "hk", "company": "Kobi Creative Products Limited", "job_title": "Purchasing Manager / Assistant Purchasing Manager", "description": "Responsibilities:\n\nResponsible for sourcing and procurement\nAssess/Evaluate potential suppliers from the perspective of (including but not limited to) Pricing, Quality, Capability, & Reliability\nManage entire procurement process from request for quotations, negotiations, bulk order management to shipment and logistics\nWork closely with Sales teams to understand customer needs, requirements and overall market trends\nConduct research and analysis on suppliers and industry / market trends\nConsolidate and present products update to sales and marketing teams\n\nRequirements:\nMinimum 3 years relevant experience in Gifts & Premiums / Printing is preferable\n\nAbility to work independently and aggressively\nKnowledge in Adobe, Photoshop and image design software are preferable\nMature, stable, self-motivated with excellent communication skill, positive attitude, able to work under pressure\nProficiency in speaking of English & Cantonese & Mandarin\nImmediate available is preferable\nCandidate with less experience will be considered as Purchasing Officer\n\nWe offer rewarding career with attractive remuneration package including 5-days week, Medical scheme, Study allowance to the right candidates.\u00a0Interested candidates should send\u00a0FULL RESUME\u00a0(IN WORD FORMAT)\u00a0with Current & Expected salary.\u00a0\n\nAll information provided by applicants will be treated in strict confidence and used only for recruitment purposes.", "employment_types": ["Full Time"], "selling_points": [], "locations": ["Kowloon Bay"], "categories": ["Merchandising & Purchasing", "Others", "Manufacturing", "Printing", "Procurement / Purchasing / Sourcing"], "post_time": "2021-12-31T01:03:13Z", "salary": {"currency": "HKD", "max": 24999, "min": 17000, "period": "monthly", "term": null}, "salary_visible": true, "title_keywords": ["purchasing manager", "assistant"], "responsibilities": ["understand customer needs", "order management", "analysis", "quality", "teams", "evaluate", "logistics", "conduct research"], "requirements": {"degrees": [], "majors": [], "languages": ["cantonese", "english", "mandarin"], "language_level": ["proficiency"], "hard_skills": ["adobe", "photoshop"], "soft_skills": ["self-motivated", "work independently", "communication skill", "mature", "positive attitude", "stable", "work under pressure"], "languages_combined": [{"language": "cantonese", "language_level": ["proficiency"]}, {"language": "english", "language_level": ["proficiency"]}, {"language": "mandarin", "language_level": ["proficiency"]}]}, "experience_required": {"duration": ["minimum 3 years"], "field": ["purchasing", "relevant experience"]}}, {"job_id": "100003009012566", "location_code": "hk", "company": "Start Way Limited", "job_title": "Assistant Merchandiser / Merchandiser (5 Days Work)", "description": "Job Highlights\n\n\nA Trading company in Kwun Tong\n5 days work\nDouble pay\nLunch offered\nBirthday Leave\n\nJob Description\nResponsibilities\n\n\n-\u00a0\u00a0Follow up seasonal decoration, home decoration and toys products,\n-\u00a0 Prepare quotations, samples\u00a0and orders\u00a0follow up\n-\u00a0 Product development\n-\u00a0 Assist in daily operational activities and provide supports to the merchandising\u00a0team members\n-\u00a0 Routine communication with factories and customers\n-\u00a0 Product sourcing in China or Far East countries\u00a0\n\nRequirements\n\n-\u00a0 Diploma or above\n-\u00a0 Minimum 1\u00a0year related working experience\n-\u00a0 Good in English and Mandarin\n-\u00a0 Proficiency in Illustrator\u00a0or\u00a0Photoshop\u00a0will be an advantage\n-\u00a0 Able to handle multi-tasks and cope with deadlines\n-\u00a0 Strong sense of responsibility, good communication skills and team work\u00a0\n\nInterested parties, please send full resume with current and expected salary via clicking \u2018Apply Now\u2019 for an interview.\n", "employment_types": ["Full Time", "Permanent"], "selling_points": [], "locations": ["Kwun Tong"], "categories": ["Merchandising & Purchasing", "Toy", "Sundries", "Manufacturing", "Printing"], "post_time": "2022-01-01T03:25:46Z", "salary": {"currency": null, "max": null, "min": null, "period": "monthly", "term": null}, "salary_visible": false, "title_keywords": ["merchandiser", "assistant merchandiser"], "responsibilities": ["routine communication", "merchandising"], "requirements": {"degrees": ["diploma or above"], "majors": [], "languages": ["english", "mandarin"], "language_level": ["good"], "hard_skills": ["illustrator", "photoshop"], "soft_skills": ["communication skills", "multi-tasks", "sense of responsibility"], "languages_combined": [{"language": "english", "language_level": ["good"]}, {"language": "mandarin", "language_level": ["good"]}]}, "experience_required": {"duration": ["minimum 1 year"], "field": ["related"]}}, {"job_id": "100003009009157", "location_code": "hk", "company": "East Asia Paper Products Company Limited", "job_title": "Graphic Designer", "description": "F.5, 2 yrs or above related exp, relevant Diploma or above,\nCreative\nIn-House design,\nExperience of products design\nFamiliar AI,Photoshop, Indesign", "employment_types": ["Full Time"], "selling_points": [], "locations": ["Kwun Tong"], "categories": ["Design", "Graphics", "Industrial / Product", "Manufacturing", "Printing"], "post_time": "2021-12-30T10:23:40Z", "salary": {"currency": null, "max": null, "min": null, "period": "monthly", "term": null}, "salary_visible": false, "title_keywords": ["graphic designer"], "responsibilities": ["design"], "requirements": {"degrees": ["diploma or above"], "majors": [], "languages": [], "language_level": [], "hard_skills": ["indesign", "photoshop", "ai"], "soft_skills": ["creative"], "languages_combined": []}, "experience_required": {"duration": [], "field": ["design"]}}, {"job_id": "100003009011371", "location_code": "hk", "company": "Q P Printing Ltd", "job_title": "Project Engineering Manager", "description": "What you will be doing:\nLead a Team to work with overseas customers in product development\nOversees and monitor progress of each project from product development to mass production to ensure schedules, costs and quality are well controlled\u00a0\nLiaise with customers and suppliers to ensure product design, quality, technical and functional requirements are properly fulfilled\nHandle customer\u2019s enquiries, propose and present to them the total solutions\nMaintain technical documents for reference and as compliance to audit requirement\nPerform ad hoc assignments by management\nWhat you need for this position:\nDiploma in Electrical/Mechanical/Manufacturing Engineering; Project Management; Business Management; or equivalent\nAt least 5 years relevant project management experience in Manufacturing environment, with minimum 2 years in managerial position\nExperience in paper product /printing/ toys industry is an advantage\nStrong leadership with good project management, problem solving and analytical skills\nGood presentation, communication, interpersonal skills\nGood command of written and spoken English, Cantonese and Mandarin\nWorkbase in Dongguan office, and travel in need\nApplication:\nPlease send your CV existing\u00a0salary & expected salary in WORD format to ghr @ qpp.com. \u00a0\nAll personal information collected will be kept for employment related purposes only.", "employment_types": ["Full Time", "Permanent"], "selling_points": ["Team leader to work on product development", "Electrical/Mechanical/Manufacturing Engineering", "Fast Growing Listed Company"], "locations": ["Others - China"], "categories": ["Engineering", "Engineering Project Management", "Manufacturing & Production", "Manufacturing", "Printing"], "post_time": "2021-12-31T16:58:03Z", "salary": {"currency": null, "max": null, "min": null, "period": "monthly", "term": null}, "salary_visible": false, "title_keywords": ["project engineering manager"], "responsibilities": ["management", "monitor progress", "schedules", "compliance", "quality", "audit", "communication", "lead a team", "project management", "product design", "maintain", "ad hoc assignments", "liaise with", "costs"], "requirements": {"degrees": ["diploma"], "majors": ["manufacturing", "engineering"], "languages": ["cantonese", "english", "mandarin"], "language_level": ["good command"], "hard_skills": ["business management", "word", "analytical skills", "problem solving", "project management"], "soft_skills": ["problem solving and analytical skills", "project management", "communication", "interpersonal skills", "controlled", "leadership", "presentation"], "languages_combined": [{"language": "cantonese", "language_level": ["good command"]}, {"language": "english", "language_level": ["good command"]}, {"language": "mandarin", "language_level": ["good command"]}]}, "experience_required": {"duration": ["at least 5 years", "minimum 2 years"], "field": ["toys", "project management", "manufacturing", "managerial"]}}, {"job_id": "100003009002547", "location_code": "hk", "company": "Elements Printing and Packaging Limited", "job_title": "Product Development Executive - Trims and Packaging (5-DAYS work)", "description": "Responsibilities\n\n\n\nFollow up quotation and sample development inquiry from local and overseas customers independently.\nLiaise with internal and external parties regarding the development process for new/revised products to ensure that the customer\u2019s requirements, quality standards.\nEnsure timely delivery of quotation and samplings\nQuality checking between sample and bulk sample\nSupport daily filing and reporting\n\nRequirements\n\n\n\n\u00a0\u00a0\u00a0\u00a0\u00a0\u00a0 F5 or above\n\u00a0\u00a0\u00a0\u00a0\u00a0\u00a0 2 years working experience in product development. Less experience would consider as junior level, fresh graduate is also considerable\n\u00a0\u00a0\u00a0\u00a0\u00a0\u00a0 Good team work and project management skills\n\u00a0\u00a0\u00a0\u00a0\u00a0\u00a0 Creative, self-motivated & detail-oriented can work under pressure and handle multiple tasks at the same time\n\u00a0 \u00a0 \u00a0 \u00a0Experience in Packaging products are preferred\n\u00a0 \u00a0 \u00a0 \u00a0 Proficiency in MS office application\n\u00a0\u00a0\u00a0\u00a0\u00a0\u00a0 Travel to China for follow up & working with manufacturer is necessary\nWe are offer:\n\n\u00a0\u00a0\u00a0\u00a0\u00a0\u00a0 Basic Salary + Team commission monthly\n\u00a0\u00a0\u00a0\u00a0\u00a0\u00a0 5 days work\n\u00a0\u00a0\u00a0\u00a0\u00a0\u00a0 Medical\u00a0allowance\n\u00a0\u00a0\u00a0\u00a0\u00a0\u00a0 Discretionary Bonus\n\u00a0\u00a0\u00a0\u00a0\u00a0\u00a0 Fast Track Promotion\n\u00a0\u00a0\u00a0\u00a0\u00a0\u00a0 14 days annual leave\n\n\nInterested parties please send the full resume with expected salary and available date by clicking\n\u201cAPPLY NOW\u201d.\n\nPersonal data will be used for recruitment purpose only.", "employment_types": ["Full Time"], "selling_points": ["2 years working experience in product development", "Experience in Packaging products are preferred", "Good communication skills"], "locations": ["Kwun Tong"], "categories": ["Manufacturing", "Product Development / Management", "Merchandising & Purchasing", "Others", "Printing"], "post_time": "2021-12-28T06:22:26Z", "salary": {"currency": null, "max": null, "min": null, "period": "monthly", "term": null}, "salary_visible": false, "title_keywords": ["product development", "executive"], "responsibilities": ["reporting", "quality checking", "quotation", "quality", "internal and external parties", "liaise with"], "requirements": {"degrees": ["fresh graduate"], "majors": [], "languages": [], "language_level": [], "hard_skills": ["project management", "basic", "ms office"], "soft_skills": ["good team work", "self-motivated", "project management skills", "detail-oriented", "handle multiple tasks", "creative", "work under pressure"], "languages_combined": []}, "experience_required": {"duration": ["2 years"], "field": ["product development"]}}, {"job_id": "100003009004373", "location_code": "hk", "company": "GenNex Financial Media Limited", "job_title": "Typesetter / Senior Typesetter \u6392\u7248\u54e1 / \u8cc7\u6df1\u6392\u7248\u54e1 (Shift allowance, 5-day)", "description": "Responsibilities\u8077\u8cac:\n\nTypesetting \u96fb\u8166\u6392\u7248\nCreate graphics and charts\u00a0 \u88fd\u4f5c\u7f8e\u5de5\u5716\u6848\u8207\u5716\u8868\nConversion of various file formats \u8f49\u63db\u5404\u7a2e\u6a94\u6848\u683c\u5f0f\nAble to complete assignments in an accurate and timely manner\n\u6e96\u78ba\u53ca\u5feb\u901f\u5b8c\u6210\u5de5\u4f5c\nRequirements\u8077\u4f4d\u8981\u6c42:\n\nForm 5 or above \u4e2d\u4e94\u7a0b\u5ea6\u6216\u4ee5\u4e0a\nFresh graduates will also be welcome \u6b61\u8fce\u61c9\u5c46\u7562\u696d\u751f\u61c9\u5fb5\nKnowledge of InDesign, Illustrator, Photoshop & MS Word is an advantage\n\u719f\u6089InDesign, Illustrator, Photoshop, MS Word\u7b49\u8edf\u4ef6\u512a\u5148\u8003\u616e\nKnowledge in typing (English & Chinese)\n\u719f\u6089\u4e2d\u82f1\u6587\u6253\u5b57\nFlexible working hours \u5f48\u6027\u5de5\u4f5c\u6642\u9593\u5236\u5ea6(shift allowance will be provided for the afternoon and overnight shift)\n\nWorking hours: 3 shifts (09:00 am \u2013 06:00 pm/ 2:00 pm \u2013 11:00 pm/ 09:00 pm \u2013 06:00 am)\n\nWe offer attractive packages to successful candidates. Salary will be commensurate with qualifications and experience.\u00a0\n\u6211\u5011\u5c07\u63d0\u4f9b\u5438\u5f15\u7684\u5de5\u8cc7\u798f\u5229\u7d66\u5408\u9069\u7684\u6c42\u8077\u8005\u3002 \u85aa\u6c34\u5c07\u8207\u8cc7\u6b77\u548c\u7d93\u9a57\u76f8\u7a31\u3002\n\nInterested parties please send your CV, existing salary, expected salary by clicking \u201cAPPLY NOW\u201d for application.\n\u6709\u610f\u8005\u8acb\u9ede\u64ca\u201c\u7acb\u5373\u7533\u8acb\u201d\u767c\u9001\u60a8\u7684\u7c21\u6b77\u3001\u73fe\u6709\u85aa\u6c34\u3001\u671f\u671b\u85aa\u6c34\u9032\u884c\u7533\u8acb\u3002\n\n** Personal data collected will be used for recruitment purposes only**\n** \u7533\u8acb\u8005\u6240\u63d0\u4f9b\u7684\u8cc7\u6599\u53ea\u63d0\u4f9b\u62db\u8058\u7528\u9014 **", "employment_types": ["Full Time", "Permanent"], "selling_points": [], "locations": ["Central"], "categories": ["Media & Advertising", "Print Media", "Manufacturing", "Printing", "Others", "Student / Fresh Graduate / No Experience"], "post_time": "2021-12-29T02:10:46Z", "salary": {"currency": null, "max": null, "min": null, "period": "monthly", "term": null}, "salary_visible": false, "title_keywords": ["typesetter"], "responsibilities": ["graphics"], "requirements": {"degrees": ["form 5 or above"], "majors": [], "languages": ["english", "chinese"], "language_level": [], "hard_skills": ["indesign", "illustrator", "typing", "photoshop", "ms word"], "soft_skills": ["flexible"], "languages_combined": [{"language": "english", "language_level": []}, {"language": "chinese", "language_level": []}]}, "experience_required": {"duration": [], "field": []}}, {"job_id": "100003009004367", "location_code": "hk", "company": "GenNex Financial Media Limited", "job_title": "Management Trainee - Financial Printing", "description": "Responsibilities:\n\nCoordinate and manage projects in the areas of typesetting, translation, design and printing\nInteract with clients, vendors and internal departments\nQuality assurance of projects delivery\n\nRequirements:\n\nMatriculation or Non Degree Tertiary\nFresh graduates will also be considered\nGood command of spoken and written English, Chinese\nFluent in spoken Mandarin is definitely an advantage\nCustomer-oriented with good communication skill\nSelf-motivated, willing to learn, able to work under pressure and a good team player\nFlexible working hours\nWilling to work overtime\n\nWe offer attractive package to successful candidates. Salary will be commensurate with qualifications and experience. Interested parties please contact Human Resources Department, Suite 901, Gloucester Tower, 15 Queen\u2019s Road Central, Hong Kong for enquiry.\n\n** Personal data collected will be used for recruitment purpose only**", "employment_types": ["Full Time", "Permanent"], "selling_points": [], "locations": ["Central"], "categories": ["Sales, CS & Business Devpt", "Customer Service - Supervisor / Officer", "Manufacturing", "Printing", "Account Servicing"], "post_time": "2021-12-29T02:09:48Z", "salary": {"currency": null, "max": null, "min": null, "period": "monthly", "term": null}, "salary_visible": false, "title_keywords": ["management trainee"], "responsibilities": ["coordinate", "quality", "manage projects", "design"], "requirements": {"degrees": ["degree"], "majors": [], "languages": ["english", "chinese", "mandarin"], "language_level": ["advantage", "good command", "fluent"], "hard_skills": [], "soft_skills": ["flexible", "self-motivated", "good team player", "work overtime", "communication skill", "willing to learn", "customer-oriented", "work under pressure"], "languages_combined": [{"language": "english", "language_level": ["good command"]}, {"language": "chinese", "language_level": ["good command"]}, {"language": "mandarin", "language_level": ["fluent", "advantage"]}]}, "experience_required": {"duration": [], "field": []}}, {"job_id": "100003009013813", "location_code": "hk", "company": "Bannershop Hong Kong Limited", "job_title": "(\u591c\u73ed)\u5370\u5237\u52a9\u7406", "description": "\n\u8077\u8cac :\u5354\u52a9\u5674\u756b/\u6578\u78bc\u5370\u5237\u5de5\u5834\u9032\u884c\u5ee3\u544a\u5370\u5237\u54c1\u751f\u7522\u6d3b\u52d5\uff0c\u5982\u4f7f\u7528\u5100\u5668\u751f\u7522\u8ca8\u54c1\uff0c\u5305\u88dd\u53ca\u8ddf\u9032\u8a02\u55ae\uff1b\u4e00\u822c\u5de5\u5834\u96dc\u52d9\uff1b\u914d\u5408\u4e0a\u53f8\u5206\u914d\u5de5\u4f5c\u3002\n\n\u8cc7\u6b77 :\u6c92\u6709\u5b78\u6b77\u8981\u6c42; \u826f\u597d\u7cb5\u8a9e; \u7565\u61c2\u8b80\u5beb\u4e2d\u6587; \u52e4\u596e\u6709\u6548\u7387\ufe50\u6709\u8cac\u4efb\u5fc3\ufe50\u5de5\u4f5c\u7d30\u5fc3\u3001\u6574\u9f4a\u3002\n\n\u5f85\u9047 :\u6bcf\u6708$12,000 - $16,000, \u6709\u5e74\u504710\u5929, \u9280\u884c\u5047\u671f, \u5728\u8077\u57f9\u8a13, \u91ab\u7642\u4fdd\u96aa \u53ca\u6649\u5347\u6a5f\u6703, \u661f\u671f\u4e00\u81f3\u516d: \u4e0b\u534811\u6642\u81f3\u4e0a\u53488\u6642, \u6bcf\u9031\u5de5\u4f5c5\u5929\u81f36\u5929, \u6bcf\u5929\u5de5\u4f5c 8 \u5c0f\u6642\n\n\u7533\u8acb\u9808\u77e5 :\u6c42\u8077\u8005\u53ef\u81f4\u96fb35003196(Ext.196)\u8207BANNERSHOP HONG KONG LIMITED\u5f35\u5c0f\u59d0\u806f\u7d61\u3002\n\n", "employment_types": ["Full Time"], "selling_points": [], "locations": ["Kwun Tong Area"], "categories": ["Manufacturing", "General / Production Workers", "Others", "Printing"], "post_time": "2022-01-03T02:45:29Z", "salary": {"currency": null, "max": null, "min": null, "period": "monthly", "term": null}, "salary_visible": false, "title_keywords": [], "responsibilities": [], "requirements": {"degrees": [], "majors": [], "languages": [], "language_level": [], "hard_skills": [], "soft_skills": [], "languages_combined": []}, "experience_required": {"duration": [], "field": []}}, {"job_id": "100003009014383", "location_code": "hk", "company": "Chong On Tong Health Co., Limited", "job_title": "\u64b0\u7a3f\u54e1", "description": "\n\u8077\u8cac :\u4e00\u822c\u7de8\u8f2f\u5de5\u4f5c, \u8ca0\u8cac\u793e\u4ea4\u5a92\u9ad4\u7db2\u7d61\u7684\u5167\u5bb9\u7de8\u64b0\u53ca\u65e5\u5e38\u4e92\u52d5, \u70ba\u5404\u7a2e\u5a92\u9ad4\u64b0\u5beb\u6e05\u6670\u4e14\u5f15\u4eba\u6ce8\u76ee\u7684\u7a3f\u4ef6, Create contents on digital platforms, Ad hoc duties as assigned by supervisor\n\n\u8cc7\u6b77 :\u5c08\u4e0a\u6559\u80b2\uff1a\u526f\u5b78\u4f4d; 1\u5e74\u7d93\u9a57; \u826f\u597d\u7cb5\u8a9e; \u4e00\u822c\u666e\u901a\u8a71; \u4e00\u822c\u82f1\u8a9e; \u61c2\u8b80\u5beb\u4e2d\u6587; \u7565\u61c2\u8b80\u5beb\u82f1\u6587; \u61c2\u4e2d\u82f1\u6587\u96fb\u8166\u64cd\u4f5c; \u61c2\u5009\u9821/\u901f\u6210\u8f38\u5165\u6cd5\n\n\u5f85\u9047 :\u6bcf\u6708$14,000 - $18,000, \u661f\u671f\u4e00\u81f3\u4e94: \u4e0a\u53489\u6642\u534a\u81f3\u4e0b\u53486\u6642\u534a\u53ca\u661f\u671f\u516d: \u4e0a\u53489\u6642\u534a\u81f3\u4e0b\u53481\u6642\u534a, \u6bcf\u9031\u5de5\u4f5c5\u5929\u534a, \u6bcf\u5929\u5de5\u4f5c 9 \u5c0f\u6642\n\n\u7533\u8acb\u9808\u77e5 :\u6c42\u8077\u8005\u53ef\u96fb\u90f5(Apply Now)\u5c65\u6b77\u8868\u7d66\u5275\u5b89\u5802\u4fdd\u5065\u6709\u9650\u516c\u53f8\u3002\u5982\u8981\u7d22\u53d6\u6536\u96c6\u500b\u4eba\u8cc7\u6599\u8072\u660e, \u8acb\u8207\u8b5a\u5148\u751f(Email)\u806f\u7d61\u3002\n\n", "employment_types": ["Full Time"], "selling_points": [], "locations": ["Tsim Sha Tsui"], "categories": ["Design", "Graphics", "Industrial / Product", "Manufacturing", "Printing"], "post_time": "2022-01-03T03:20:56Z", "salary": {"currency": null, "max": null, "min": null, "period": "monthly", "term": null}, "salary_visible": false, "title_keywords": [], "responsibilities": ["ad hoc duties", "contents"], "requirements": {"degrees": [], "majors": [], "languages": [], "language_level": [], "hard_skills": [], "soft_skills": [], "languages_combined": []}, "experience_required": {"duration": [], "field": []}}, {"job_id": "100003008104952", "location_code": "hk", "company": "Max Fortune Industrial Ltd", "job_title": "Sales & Marketing Executive / Senior Sales & Marketing Executive (5-day work)", "description": "Position highlights:\n\nUnique learning environment to develop your skills\nGreat opportunities, career path and C&B package\nA fun place to work\n\n\u00a0Responsibilities:\n\nAssist the team to prepare presentation materials\nIdentify client needs and promote business\nFollow-up sales order\nExplore potential clients in the market\nInitiate and participate in sales and marketing activities\nMaintain and enhance\u00a0business relationship with customers\nOccasionally overseas travelling is needed\n\nRequirements:\n\nDegree holder in any disciplines\nProactive, energetic, self-motivated and a good team player\nGood presentation and communication skills\nGood command of spoken & written English and Putonghua\nFamiliar with MS Word, Excel and Chinese typing\nCandidates with more experience will be considered as Senior Sales & Marketing Executive\n\nWe offer attractive remuneration package including 5-day work, 14-day annual leave, birthday leave to attract, retain and motivate talent.\u00a0\n\nInterest parties please submit your application with updated\u00a0resume\u00a0and current/ expected salary.\n\nPlease visit our web site\u00a0http://www.max-fortune.com\u00a0for company information.\n\nData collected will be used for recruitment purpose only.", "employment_types": ["Full Time"], "selling_points": [], "locations": ["Southern Area"], "categories": ["Manufacturing", "Printing", "Sales, CS & Business Devpt", "Sales - Sales Management", "Sales Administration"], "post_time": "2021-12-30T21:58:22Z", "salary": {"currency": null, "max": null, "min": null, "period": null, "term": null}, "salary_visible": false, "title_keywords": ["senior sales & marketing executive", "sales & marketing executive"], "responsibilities": ["maintain"], "requirements": {"degrees": ["degree holder"], "majors": ["any disciplines"], "languages": ["putonghua", "english", "chinese"], "language_level": ["good command"], "hard_skills": ["excel", "typing", "ms word"], "soft_skills": ["communication skills", "good team player", "proactive", "self-motivated", "energetic", "presentation"], "languages_combined": [{"language": "putonghua", "language_level": ["good command"]}, {"language": "english", "language_level": ["good command"]}, {"language": "chinese", "language_level": []}]}, "experience_required": {"duration": [], "field": ["marketing"]}}, {"job_id": "100003009003709", "location_code": "hk", "company": "FUJIFILM Business Innovation Hong Kong Limited", "job_title": "\u5370\u5237\u623f\u52a9\u7406", "description": "\u5de5\u4f5c\u6027\u8cea\n\u9700\u6d3e\u99d0\u5ba2\u6236\u8fa6\u516c\u5ba4\u5167\u5de5\u4f5c\n\u8ca0\u8cac\u64cd\u4f5c\u5370\u5237\u6a5f\u5b8c\u6210\u5404\u9805\u5370\u5237\u5de5\u4f5c\u4e26\u652f\u63f4\u647a\u4fe1\u3001\u5165\u4fe1\u53ca\u54c1\u8cea\u6aa2\u67e5\u7b49\u5de5\u5e8f\n\u8077\u4f4d\u8981\u6c42\n\n\u4e2d\u5b78\u7a0b\u5ea6\n\u52e4\u596e\u6709\u4e0a\u9032\u5fc3\u53ca\u8cac\u4efb\u611f\n\u6b61\u8fce\u61c9\u5c46\u7562\u696d\u751f\u7533\u8acb\n\n\u798f\u5229\n\n12\u65e5\u6709\u85aa\u5e74\u5047\n\u6bcf\u5e74\u984d\u5916\u53ef\u4eab\u9ad8\u905425\u65e5\u5e78\u798f\u5047\uff08\u5305\u62ec\uff1a\u751f\u65e5\u5047\u3001\u7fa9\u5de5\u5047\u3001\u7d50\u5a5a\u9031\u5e74\u7d00\u5ff5\u5047\u53ca\u5bf5\u7269\u5047\u7b49\uff09\n\u91ab\u7642\u53ca\u7259\u79d1\u4fdd\u5065\u798f\u5229\n\u6649\u5347\u6a5f\u6703\n\u5728\u8077\u57f9\u8a13\n\n\u6709\u610f\u61c9\u5fb5\u8005\uff0c\u6b61\u8fce\u628a\u500b\u4eba\u5c65\u6b77\u53ca\u671f\u671b\u85aa\u91d1\u96fb\u90f5\u81f3\u4eba\u529b\u8cc7\u6e90\u90e8\u3002\n\n\n", "employment_types": ["Full Time"], "selling_points": ["\u9700\u6d3e\u99d0\u5ba2\u6236\u8fa6\u516c\u5ba4\u5167\u5de5\u4f5c", "\u8ca0\u8cac\u64cd\u4f5c\u5370\u5237\u6a5f\u5b8c\u6210\u5404\u9805\u5370\u5237\u5de5\u4f5c", "\u6b61\u8fce\u61c9\u5c46\u7562\u696d\u751f\u7533\u8acb"], "locations": ["Hung Hom"], "categories": ["Admin & HR", "Clerical / Admin Staff", "Manufacturing", "Printing"], "post_time": "2021-12-28T10:13:11Z", "salary": {"currency": null, "max": null, "min": null, "period": "monthly", "term": null}, "salary_visible": false, "title_keywords": [], "responsibilities": [], "requirements": {"degrees": [], "majors": [], "languages": [], "language_level": [], "hard_skills": [], "soft_skills": [], "languages_combined": []}, "experience_required": {"duration": [], "field": []}}, {"job_id": "100003009000587", "location_code": "hk", "company": "Glory Moon Greeting Cards Co Ltd", "job_title": "Marketing Executive (Gift Exporter) (5 Days Work)", "description": "- Degree holder\n\n- Minimum 3 years experience in manufacturing firm\n\n- Follow up overseas orders\n\n- Product development coordination\n\n- Fluency in spoken and written Chinese and English\n\n- Good at MS office and Chinese WP\n\nPersonal data collected is for recruitment purpose only.", "employment_types": ["Full Time"], "selling_points": ["Min 3 years export sales exp Immediate Available", "Fluency in spoken and written English & Chinese", "Wiling to complete tasks before deadline"], "locations": ["Kowloon Bay"], "categories": ["Merchandising & Purchasing", "Sundries", "Others", "Manufacturing", "Printing"], "post_time": "2021-12-26T16:10:42Z", "salary": {"currency": null, "max": null, "min": null, "period": "monthly", "term": null}, "salary_visible": false, "title_keywords": ["marketing executive"], "responsibilities": ["personal data", "recruitment", "coordination"], "requirements": {"degrees": ["degree holder"], "majors": [], "languages": ["english", "chinese"], "language_level": ["fluency", "good"], "hard_skills": ["chinese wp", "ms office"], "soft_skills": ["coordination"], "languages_combined": [{"language": "english", "language_level": ["fluency"]}, {"language": "chinese", "language_level": ["fluency", "good"]}]}, "experience_required": {"duration": ["minimum 3 years"], "field": ["manufacturing"]}}, {"job_id": "100003009001053", "location_code": "hk", "company": "C & C Joint Printing Co (HK) Ltd", "job_title": "HR Management Trainee ( IANG Welcome)", "description": "Responsibilities\n\nAssist in HR project management.\nAssist in formulating and consolidating HR policy.\nAssist in other HR duties as assigned.\nOccasionally travel to Mainland is required.\n\nRequirements\n\n\nBachelor\u2019s degree or above; IANG and Fresh graduate are welcome.\nProficiency in Chinese and English, Mandarin is a MUST.\nGood written and verbal communication skills required.\nHard-working, fast learner, proactive and eager to learn.\n\nWe offer attractive salary package and five days work. Interested parties please send full resume with present and expected salary, available date, address and correspondence by clicking APPLY NOW.", "employment_types": ["Full Time", "Permanent"], "selling_points": [], "locations": ["Tai Po Area"], "categories": ["Admin & HR", "Personal / Executive Assistant", "HR Supporting Staff", "Manufacturing", "Printing"], "post_time": "2021-12-28T01:20:13Z", "salary": {"currency": null, "max": null, "min": null, "period": "monthly", "term": null}, "salary_visible": false, "title_keywords": ["management trainee", "hr"], "responsibilities": ["project management", "hr", "hr duties"], "requirements": {"degrees": ["degree or above", "bachelor", "fresh graduate"], "majors": [], "languages": ["english", "chinese", "mandarin"], "language_level": ["proficiency"], "hard_skills": [], "soft_skills": ["communication skills", "eager to learn", "hard-working", "proactive", "fast learner"], "languages_combined": [{"language": "english", "language_level": ["proficiency"]}, {"language": "chinese", "language_level": ["proficiency"]}, {"language": "mandarin", "language_level": ["proficiency"]}]}, "experience_required": {"duration": [], "field": []}}, {"job_id": "100003009001587", "location_code": "hk", "company": "1 Fast Print", "job_title": "Sales Coordinator / Account Service / Merchandiser", "description": "\n\u8077\u8cac\u00a0\n\n\u2022 \u70ba\u5ba2\u6236\u63d0\u4f9b\u670d\u52d9, \u7dad\u6301\u5ba2\u6236\u95dc\u4fc2\n\u2022 \u8ddf\u9032\u8a02\u55ae, \u5354\u8abf\u5ba2\u6236\u548c\u88fd\u4f5c\u90e8\n\u2022 \u8ddf\u9032\u8ca8\u7269, \u5b89\u6392\u9001\u8ca8\n\u2022 \u76f8\u95dc\u6587\u66f8\u5de5\u4f5c\n\n\u4efb\u8077\u8981\u6c42\n\n\u2022 5\u5e74\u4ee5\u4e0a\u76f8\u95dc\u5de5\u4f5c\u7d93\u9a57\uff0c\u6709\u5370\u5237\u3001\u8a2d\u8a08\u3001\u88fd\u4f5c\u7d93\u9a57\u8005\u512a\u5148\n\u2022 \u826f\u597d\u6e9d\u901a\u548c\u61c9\u8b8a\u80fd\u529b\uff0c\u53ef\u4ee5\u9069\u61c9\u4e0d\u540c\u5de5\u4f5c\n\u2022 \u6703\u7528Illustrator\u3001\u719f\u7528\u96fb\u8166\u3001\u80fd\u9069\u61c9\u4f7f\u7528\u964c\u751f\u5de5\u4f5c\u8edf\u4ef6\u512a\u5148\n\u2022 \u826f\u597d\u4e2d\u82f1\u6587\u512a\u5148\n\n", "employment_types": ["Full Time"], "selling_points": [], "locations": ["Chai Wan"], "categories": ["Sales, CS & Business Devpt", "Customer Service - Supervisor / Officer", "Manufacturing", "Printing", "Account Servicing"], "post_time": "2021-12-28T02:40:39Z", "salary": {"currency": null, "max": null, "min": null, "period": "monthly", "term": null}, "salary_visible": false, "title_keywords": ["sales coordinator", "merchandiser"], "responsibilities": [], "requirements": {"degrees": [], "majors": [], "languages": [], "language_level": [], "hard_skills": [], "soft_skills": [], "languages_combined": []}, "experience_required": {"duration": [], "field": []}}, {"job_id": "100003009004638", "location_code": "hk", "company": "FC Packaging (Hong Kong) Ltd.", "job_title": "\u5370\u52d9\u6a5f\u9577/\u526f\u6a5f\u9577", "description": "\n\u8077\u8cac :\u64cd\u4f5c\u5370\u5237\u53ca\u5857\u6599\u6a5f\u5668, \u63a7\u5236\u751f\u7522\u54c1\u8cea\n\n\u8cc7\u6b77 :\u6c92\u6709\u5b78\u6b77\u8981\u6c42; 3\u5e74\u7d93\u9a57; \u826f\u597d\u7cb5\u8a9e; \u61c2\u8b80\u5beb\u4e2d\u6587\n\n\u5f85\u9047 :\u6bcf\u6708$14,000 - $20,000,\u6709\u8d85\u6642\u5de5\u4f5c\u6d25\u8cbc,\u8f2a\u73ed\u6d25\u8cbc,\u52e4\u5de5\u734e\u91d1,\u914c\u60c5\u6027\u82b1\u7d05,\u4f9b\u81b3\u98df,\u7a7f\u68ad\u5df4\u58eb\u670d\u52d9\u53ca\u4e2d\u897f\u91ab\u7642\u798f\u5229, \u661f\u671f\u4e00\u81f3\u56db: \u4e0a\u53487\u6642\u81f3\u4e0b\u53487\u6642\u6216\u4e0b\u53487\u6642\u81f3\u4e0a\u53487\u6642, \u6bcf\u9031\u5de5\u4f5c4\u5929,\u8f2a\u73ed, \u6bcf\u5929\u5de5\u4f5c 12 \u5c0f\u6642\n\n\u7533\u8acb\u9808\u77e5 :\u6c42\u8077\u8005\u53ef\u81f4\u96fb26661172\u8207\u6c38\u5bcc\u5bb9\u5668(\u9999\u6e2f)\u6709\u9650\u516c\u53f8\u674e\u5c0f\u59d0\u806f\u7d61\u3002\n\n", "employment_types": ["Full Time"], "selling_points": [], "locations": ["Tai Po Area"], "categories": ["Manufacturing", "Manufacturing Management", "Others", "Printing"], "post_time": "2021-12-29T02:48:45Z", "salary": {"currency": null, "max": null, "min": null, "period": "monthly", "term": null}, "salary_visible": false, "title_keywords": [], "responsibilities": [], "requirements": {"degrees": [], "majors": [], "languages": [], "language_level": [], "hard_skills": [], "soft_skills": [], "languages_combined": []}, "experience_required": {"duration": [], "field": []}}, {"job_id": "100003008975176", "location_code": "hk", "company": "\u6674\u5929\u821e\u53f0\u88fd\u4f5c\u6709\u9650\u516c\u53f8", "job_title": "\u5674\u756b\u88fd\u4f5c\u5b78\u5f92/\u5e2b\u5085", "description": "Job Description\n\nGeneral duties of Printing Worker\nResponsible for general printing operations\nResponsible for typesetting and output printing\nOperating press machines\n\u8077\u8cac\u00a0\n\n\u5674\u756b\u88fd\u4f5c\n\u4e00\u822c\u5370\u5237\u5de5\u4f5c\n\u8ca0\u8cac\u4e00\u822c\u6253\u5370\u751f\u7522\u904b\u4f5c\n\u8ca0\u8cac\u5370\u5237\u6392\u7248\u53ca\u8f38\u51fa\n\u64cd\u4f5c\u5370\u5237\u6a5f\n\u5674\u756b\u5f8c\u671f\u88fd\u4f5c\uff0c\u5305\u62ec\u526a\u88c1\uff0c\u88dd\u88f1\uff0c\u904e\u819c\uff0c\u5305\u88dd\u7b49\n\nRequirements\n\n\n2 years\u2019 experiences in printing\nGood command of written and spoken Chinese, Fair of written English;\nGood interpersonal and communications skills;\nSelf-motivated, detail oriented, strong sense of responsibility and multi-tasked\n\u80fd\u529b\u9700\u6c42\n\n\n2\u5e74\u7d93\u9a57;\n\u826f\u597d\u7cb5\u8a9e; \u00a0\u4e00\u822c\u82f1\u8a9e; \u61c2\u8b80\u5beb\u4e2d\u6587; \u7565\u61c2\u8b80\u5beb\u82f1\u6587\n\u826f\u597d\u6e9d\u901a\u80fd\u529b\n\u80fd\u7368\u7acb\u5de5\u4f5c\u3001\u7d30\u5fc3\u3001\u6709\u8cac\u4efb\u611f\u3001\u80fd\u5728\u58d3\u529b\u4e0b\u5de5\u4f5c", "employment_types": ["Full Time", "Permanent"], "selling_points": [], "locations": ["Yuen Long"], "categories": ["Media & Advertising", "Production", "Design", "Others", "Manufacturing", "Printing"], "post_time": "2021-12-20T16:57:28Z", "salary": {"currency": null, "max": null, "min": null, "period": "monthly", "term": null}, "salary_visible": false, "title_keywords": [], "responsibilities": ["operations"], "requirements": {"degrees": [], "majors": [], "languages": ["english", "chinese"], "language_level": ["good command"], "hard_skills": [], "soft_skills": ["self-motivated", "sense of responsibility", "detail oriented", "multi-tasked", "interpersonal"], "languages_combined": [{"language": "english", "language_level": ["good command"]}, {"language": "chinese", "language_level": ["good command"]}]}, "experience_required": {"duration": ["2 years"], "field": []}}, {"job_id": "100003008996084", "location_code": "hk", "company": "Technoform Bautec Hong Kong Limited", "job_title": "QC \u54c1\u8cea\u6aa2\u67e5\u54e1", "description": "\nQC \u54c1\u8cea\u6aa2\u67e5\u54e1\n\u8077\u8cac\n\u2022 \u8ca0\u8cac\u539f\u6750\u6599\u9a57\u6536\u53ca\u751f\u7522\u7dda\u7522\u54c1\u8cea\u91cf\u6aa2\u67e5\n\u2022 \u8a18\u9304\u6e2c\u8a66\u6578\u64da\u8cc7\u6599\u53ca\u5236\u5b9a\u6e2c\u8a66\u5831\u544a\n\u2022 \u65e5\u5e38\u904b\u4f5c\u53ca\u4e0a\u7d1a\u6307\u6d3e\u5404\u9805\u5de5\u4f5c\u7b49\n\u8981\u6c42\n\u2022 \u4e2d\u4e94\u6216\u4ee5\u4e0a\n\u2022 \u80fd\u7368\u7acb\u5de5\u4f5c, \u61c2\u96fb\u8166\u61c9\u7528\u64cd\u4f5c\n\u2022 \u53ef\u5373\u6642\u4e0a\u73ed\u512a\u5148\n\u798f\u5229: \u514d\u8cbb\u81b3\u98df, \u5ee0\u8eca\u63a5\u9001, \u96d9\u7ce7, \u52a0\u73ed\u6d25\u8cbc1.5\u500d, \u54e1\u5de5\u53ca\u5b50\u5973\u91ab\u7642\u4fdd\u96aa, \u65b0\u4eba\u734e\u91d1$5000\n\u6709\u610f\u8005\u8acb\u628a\u5c65\u6b77\u8868 \u8acb\u6309Apply Now\u7533\u8acb\nAll personal data provided by applicants will be used for recruitment purposes only.\n\n", "employment_types": ["Full Time"], "selling_points": [], "locations": ["Not Specified"], "categories": ["Manufacturing", "Others", "Printing", "Quality Assurance, Control & Testing / ISO"], "post_time": "2021-12-23T05:27:47Z", "salary": {"currency": null, "max": null, "min": null, "period": "monthly", "term": null}, "salary_visible": false, "title_keywords": [], "responsibilities": ["personal data", "recruitment"], "requirements": {"degrees": [], "majors": [], "languages": [], "language_level": [], "hard_skills": [], "soft_skills": [], "languages_combined": []}, "experience_required": {"duration": [], "field": []}}, {"job_id": "100003008992141", "location_code": "hk", "company": "Adlib International Trading Limited", "job_title": "\u6210\u8863\u6578\u78bc\u5370\u82b1\u54e1", "description": "\n\u8077\u8cac :\u4e3b\u8981\u8ca0\u8cac\u64cd\u4f5c\u8f2a\u8f49\u5370\u5237\u6a5f\uff0c\u76e3\u63a7\u5370\u5237\u54c1\u8cea\n\n\u8cc7\u6b77 :\u4e2d\u4e00\u7a0b\u5ea6; 1\u5e74\u7d93\u9a57; \u826f\u597d\u7cb5\u8a9e; \u4e00\u822c\u666e\u901a\u8a71; \u4e00\u822c\u82f1\u8a9e; \u61c2\u8b80\u5beb\u4e2d\u6587; \u61c2\u95b1\u8b80\u82f1\u6587\n\n\u5f85\u9047 :\u6bcf\u6708$14,000 - $17,000, \u6709\u8d85\u6642\u5de5\u4f5c\u6d25\u8cbc, \u52e4\u5de5\u734e\u91d1, \u5728\u8077\u57f9\u8a13, \u91ab\u7642\u798f\u5229 \u53ca\u6bcf\u6708\u5176\u4ed6\u6d25\u8cbc/\u798f\u5229$300, \u661f\u671f\u4e00\u81f3\u516d: \u4e0a\u53488\u6642\u81f3\u4e0b\u53485\u6642, \u6bcf\u9031\u5de5\u4f5c6\u5929, \u6bcf\u5929\u5de5\u4f5c 8 \u5c0f\u6642\n\n\u7533\u8acb\u9808\u77e5 :\u6c42\u8077\u8005\u53ef\u81f4\u96fb26664956(Ext.4956)\u8207\u4e2d\u83ef\u5546\u52d9\u5b89\u5168\u5370\u52d9\u6709\u9650\u516c\u53f8\u83ab\u5c0f\u59d0\u806f\u7d61\u3002\n\n", "employment_types": ["Part Time"], "selling_points": [], "locations": ["Kwai Tsing Area"], "categories": ["Manufacturing", "Printing"], "post_time": "2021-12-22T04:25:16Z", "salary": {"currency": null, "max": null, "min": null, "period": "hourly", "term": null}, "salary_visible": false, "title_keywords": [], "responsibilities": [], "requirements": {"degrees": [], "majors": [], "languages": [], "language_level": [], "hard_skills": [], "soft_skills": [], "languages_combined": []}, "experience_required": {"duration": [], "field": []}}, {"job_id": "100003008995151", "location_code": "hk", "company": "C & C Security Printing Co Ltd", "job_title": "\u8f2a\u8f49\u5370\u5237\u6a5f\u8eca\u9577/\u6280\u5de5", "description": "\n\u8077\u8cac :\u8ca0\u8cac\u5674\u81a0\u53ca\u6578\u78bc\u5370\u82b1\n\n\u8cc7\u6b77 :\u4e2d\u4e09\u7a0b\u5ea6; \u826f\u597d\u7cb5\u8a9e\u512a\u5148; \u4e00\u822c\u82f1\u8a9e; \u61c2\u95b1\u8b80\u4e2d\u6587; \u7565\u61c2\u8b80\u5beb\u82f1\u6587; \u6709\u8cac\u4efb\u5fc3, \u52e4\u596e, \u5b88\u6642\n\n\u5f85\u9047 :\u6bcf\u5c0f\u6642$55.00, \u661f\u671f\u4e00\u81f3\u4e94: \u4e0a\u53489\u6642\u81f3\u4e0b\u53486\u6642, \u6bcf\u9031\u5de5\u4f5c5\u5929, \u5de5\u4f5c\u671f\u7531 20/12/2021 \u81f3 31/12/2021, \u6bcf\u5929\u5de5\u4f5c 8 \u5c0f\u6642\n\n\u7533\u8acb\u9808\u77e5 :\u6c42\u8077\u8005\u53ef\u81f4\u96fb63800381\u8207\u96c5\u529b\u570b\u969b\u8cbf\u6613\u6709\u9650\u516c\u53f8\u4f55\u5973\u58eb\u806f\u7d61\u3002\n\n", "employment_types": ["Full Time"], "selling_points": [], "locations": ["Tai Po Area"], "categories": ["Engineering", "Mechanical", "Manufacturing", "Others", "Printing"], "post_time": "2021-12-23T03:02:33Z", "salary": {"currency": null, "max": null, "min": null, "period": "monthly", "term": null}, "salary_visible": false, "title_keywords": ["\u6280\u5de5"], "responsibilities": [], "requirements": {"degrees": [], "majors": [], "languages": [], "language_level": [], "hard_skills": [], "soft_skills": [], "languages_combined": []}, "experience_required": {"duration": [], "field": []}}]