[{"job_id": "100003009055368", "location_code": "hk", "company": "Hung Fook Tong Holdings Limited", "job_title": "Product Marketing Officer (HRD-adv-22-001)", "description": "Responsibilities:\n\nTo support Product & Marketing Manager and work as a team to execute product plans and strategy with the ultimate objective of raising brand awareness, brand building and increasing sales;\nTo identify a continuous stream of commercially valuable new products;\nDrive product development, packaging and manage market analysis;\nProduct forecasting and inventory control and management;\nWork closely with internal and external production / QC teams to ensure accurate execution of product development with the right quality and time;\nSupport ad hoc projects when required.\n\nRequirements:\n\n\u00a0 Degree in marketing, business management, nutrition or food science background is preferable;\n\u00a0 Minimum 3 years product experience in retail / FMCG (bottled drinks preferred);\n\u00a0 Solid experience in product marketing is advantageous;\n\u00a0 Good communications skill in Cantonese, Mandarin and English\n\u00a0 Able to independently manage project and drive progress.\n\u00a0 Candidate with more experience will be considered as \"Senior Product Marketing Officer\"\n\n\n\nWe offer 5-day-work week with competitive remuneration and benefit packages to the right candidate. Interested parties please send your application letter, resume, expected salary (quoting Employer Ref:) and availability to\u00a0HR Department at Hung Fook Tong, 8/F, Chuan Kei Factory Building, Nos. 15-23 Kin Hon Street, Kwai Chung, NT., H.K. or e-mail or\u00a0browse our website:\u00a0www.hungfooktong.com\n\nPersonal Information Collection Statement-Applicants\u2019 personal information will be used for the recruitment and employment matters only; information will be kept in strict confidence; information of unsuccessful applicants will be shredded after recruitment process; subject to provisions under the Personal Data (Privacy) Ordinance, applicants have right to access and make corrections of their personal data", "employment_types": ["Full Time"], "selling_points": ["Execute product plans and strategy", "product experience in retail/FMCG", "5 day works,flexible working hour"], "locations": ["Kwai Hing"], "categories": ["Manufacturing", "Product Development / Management", "Marketing / Public Relations", "Marketing - Brand / Product Management", "Marketing - General / Support"], "post_time": "2022-01-18T02:21:03Z", "salary": {"currency": null, "max": null, "min": null, "period": "monthly", "term": null}, "salary_visible": false, "title_keywords": ["marketing officer"], "responsibilities": ["management", "teams", "quality", "inventory control", "market analysis", "ad hoc projects", "plans", "forecasting"], "requirements": {"degrees": ["degree"], "majors": ["business", "marketing", "food science"], "languages": ["cantonese", "english", "mandarin"], "language_level": ["good"], "hard_skills": ["business management"], "soft_skills": ["independently"], "languages_combined": [{"language": "cantonese", "language_level": ["good"]}, {"language": "english", "language_level": ["good"]}, {"language": "mandarin", "language_level": ["good"]}]}, "experience_required": {"duration": ["minimum 3 years"], "field": ["retail", "marketing", "fmcg"]}}, {"job_id": "100003009052731", "location_code": "hk", "company": "Just Play (HK) Limited", "job_title": "Project Engineer - Toys", "description": "We are a US Toys Company located in TST East.\u00a0 We are looking for a high caliber individual to fill in the following position:\n\nProject Engineer - Toys\n\nJob Specification:\n\nFollow up orders from initial product development to bulk production;\nCommunicate with US head office and designers;\nLiaise with vendors and internal departments for factory quotes and order commitments;\nEnsure good documentation and smooth transferring projects from engineering to manufacturing.\nAny ad-hoc job tasks and projects as assigned.\n\n\u00a0Job Requirements:\n\nDiploma or Degree holder in related engineering discipline is preferred;\nMinimum 5 years related working experiences in Toys field;\nComputer literacy with ERP experience;\nGood command of written and spoken English, able to speak Mandarin;\nProactive, good communication skills with suppliers and inter-departments;\nImmediate available is preferred.\n\nWe offer 5-day work week, medical, dental benefit and year end double paid.\u00a0\u00a0", "employment_types": ["Full Time"], "selling_points": [], "locations": ["Tsim Sha Tsui"], "categories": ["Manufacturing", "Product Development / Management"], "post_time": "2022-01-17T07:10:19Z", "salary": {"currency": null, "max": null, "min": null, "period": "monthly", "term": null}, "salary_visible": false, "title_keywords": ["project engineer"], "responsibilities": ["follow up orders", "ad-hoc", "communicate with", "documentation", "communication", "liaise with"], "requirements": {"degrees": ["diploma", "degree holder"], "majors": ["engineering"], "languages": ["english", "mandarin"], "language_level": ["good command"], "hard_skills": ["documentation", "erp"], "soft_skills": ["communication skills", "computer literacy", "proactive", "smooth"], "languages_combined": [{"language": "english", "language_level": ["good command"]}, {"language": "mandarin", "language_level": ["good command"]}]}, "experience_required": {"duration": ["minimum 5 years"], "field": ["related", "toys"]}}, {"job_id": "100003009053238", "location_code": "hk", "company": "Spin Master Toys Far East Limited", "job_title": "Senior Project Engineer", "description": "General\n\nAs a project lead to carry out project development, engineering support and debug to meet the product specifications, target cost and MAD.\n\nSpecific Responsibilities\n\nSupport and grow the product lines under Girls GBU.\nWork with internal North America teams, regional teams and vendors on product development to meet product specifications, target cost and MAD under projected PD milestones\nProvide effective technical supports, directions and ideas during debug.\nWork with designated suppliers for components sourcing, development, cost negotiation, as well as technical support.\nMonitor the PD schedule to ensure milestones happened on time, and provide appropriate on-site supports.\nProvide manufacturing supports and assist to evaluate production output issues after PS..\n\nRequired Qualifications & ExperienceSkill Set\n\n\nDegree or Higher Diploma in Mechanical/Manufacturing Engineering or related discipline.\nAt least 5 years experiences in toy industry with plastic, tooling, simple mechanism, fabric and softgoods knowledges.\nMultinational corporation (MNC) working experience is a must.\nKnowledges of Hard and Soft Toy quality standards of different countries.\nAble to make trips to PRC as required.\nExcellent project management skills in Girls items such as fashion dolls, playsets, and collectables.\nAble to work from prelim concept through development to MAD, in a fast-paced team setting\u00a0\u00a0\nA flexible, dedicated, independent and result-driven team player with attention to detail mindset and good communication skills.\nGood sense on design and aesthetics judgement.\nFamiliar with licensed items approval process.\nProficient English and Mandarin language skills.", "employment_types": ["Full Time", "Permanent"], "selling_points": ["Project Management", "Toys", "Engineering"], "locations": ["Tsim Sha Tsui"], "categories": ["Engineering", "Engineering Project Management", "Manufacturing", "Product Development / Management"], "post_time": "2022-01-17T06:30:44Z", "salary": {"currency": null, "max": null, "min": null, "period": "monthly", "term": null}, "salary_visible": false, "title_keywords": ["senior project engineer"], "responsibilities": ["cost", "technical supports", "ideas", "technical support", "teams", "monitor", "quality", "design", "evaluate", "project management", "communication", "specifications", "schedule"], "requirements": {"degrees": ["diploma", "degree"], "majors": ["manufacturing", "engineering"], "languages": ["english", "mandarin"], "language_level": ["proficient"], "hard_skills": ["simple", "make", "project management", "mad"], "soft_skills": ["flexible", "communication skills", "independent", "negotiation", "project management skills", "attention to detail", "team player", "driven"], "languages_combined": [{"language": "english", "language_level": ["proficient"]}, {"language": "mandarin", "language_level": ["proficient"]}]}, "experience_required": {"duration": ["at least 5 years"], "field": []}}, {"job_id": "100003009056287", "location_code": "hk", "company": "Sandbox VR Limited", "job_title": "Product Designer/ Senior Product Designer", "description": "Responsibilities\n\n\nResponsible for designing experience-related gears from concept to production stage\nDirect report to Product Design Manager\nUndertake detailed project work and mock-up sample presentation\nIdentifying the suitability and availability of materials\nMaking samples or working models by hand or using 3D prototyping equipment\nPerform product research, market analysis, generate new product ideas, rendering and presentation\nPlan and control schedule and quality of deliverable\nCollaborate with development teams in HK, China and US\n\nRequirements\n\n\nGraduating candidate in industrial design or related disciplines.\u00a0\nWith relevant experience, preferably in electronics, gaming goods, sporting goods, is an advantage. (Fresh graduates will be considered)\u00a0\nFamiliarity with plastics, metal applications and tooling manufacturing processes is an advantage.\nExperience in UX / Service design is an advantage.\nEngineering background is an advantage.\nExcellent in SolidWorks, KeyShot, Photoshop, Illustrator.\nAbility to work under tight schedules.\nGood communication skills with written and spoken English and Chinese.\nSelf-starter with a passion for innovation, development of new, better products and Industrial Design.\nGreat sketching skill, conceptualization, ideation, strong problem-solving ability, understanding of materials, human factors.\nCandidate with more experience will be considered as Senior Product Designer.\nPlease attach a full resume with the expected salary and portfolio for application.\nFresh Graduates with potential will be considered", "employment_types": ["Full Time"], "selling_points": ["Design Experience-related gears for active gaming", "Familiarity with manufacturing processes", "Excellent in SolidWorks, KeyShot, AI, PS, etc."], "locations": ["Tsim Sha Tsui"], "categories": ["Manufacturing", "Product Development / Management"], "post_time": "2022-01-18T03:52:15Z", "salary": {"currency": null, "max": null, "min": null, "period": "monthly", "term": null}, "salary_visible": false, "title_keywords": ["product designer", "senior product designer"], "responsibilities": ["collaborate with", "control", "ideas", "quality", "teams", "product design", "market analysis", "schedule", "plan", "designing", "report"], "requirements": {"degrees": [], "majors": [], "languages": ["english", "chinese"], "language_level": ["good"], "hard_skills": ["problem-solving", "solidworks", "illustrator", "photoshop"], "soft_skills": ["communication skills", "problem-solving", "passion for"], "languages_combined": [{"language": "english", "language_level": ["good"]}, {"language": "chinese", "language_level": ["good"]}]}, "experience_required": {"duration": [], "field": ["relevant experience", "designer", "design"]}}, {"job_id": "100003009054249", "location_code": "hk", "company": "Grown-Up Manufactory Limited", "job_title": "Senior Merchandising Manager / Senior Project Manager", "description": "OUR COMPANY\u00a0\n\nGROWN UP GROUP (Listed at the Hong Kong Stock Exchange, HKEX: 1842) is one of the world\u2019s leading companies within the bags and luggage industry.\n\nWe manufacture and design for a wide range of international brands, such as Adidas, Samsonite, Wilson and a strong portfolio of licensed and own brands like LEGO, Caterpillar, New Balance and Ellehammer.\n\nWe manufacture at both our own factories and at our numerous partner factories in \u00a0\u00a0Southeast Asia. We serve our customers from our global head office in Hong Kong, our R&D center in Shenzhen, our sales and design offices in Asia, Europe and the USA.\n\n\u00a0\nYOUR ROLE\n\nYou will be a member of our Merchandising Team and report directly to \u00a0 Head of Product Development, Merchandising, Sourcing and Design.\n\nYou have past record of successfully managing a small team.\n\nYou are leading a merchandising team in full merchandising duties from customer inquiry, product development, execute sourcing strategies, production and quality follow up, lab test submission, and handling incident etc., until shipment is completed, so as to ensure proper execution of schedule and timely delivery.\nYou are analyzing costing of products and materials, negotiating with suppliers for better price and target on company\u2019s cost improvement aim.\nYou are maintaining close communication with Brand & Licenses Team and customers\nYou are training the merchandising team on problem solving, product knowledge, merchandising skills and overall abilities\nThe post is based in Shenzhen Office. Frequent travelling is required.\n\n\nYOUR CHARACTER & COMPETENCES\n\nDiploma or above, in fashion, clothing or related discipline will be an advantage\nAt least 8 years of Merchandising experience, preferably in travel goods, garment, apparel, accessories or sports goods, and experience in order follow up and correspondence independently.\nDetailed-minded, flexible and be able to work well under pressure and meet strict deadlines.\nGood problem solving, interpersonal, communication and negotiation skills.\nGood command of both written and spoken English and Chinese, as well as Putonghua.\nAvailable by March 2022.\nWE OFFER YOU\nCompetitive salary\n5-day work week\nMedical insurance\nAnnual leave starting from 14 days\nWork experience with exposure to European markets\nA friendly work environment\n\nYOUR APPLICATION\n\n\u00a0\u00a0\u00a0\u00a0\u00a0 Please send us your application and CV with salary expected today.", "employment_types": ["Full Time", "Permanent"], "selling_points": [], "locations": ["Tai Po Area"], "categories": ["Manufacturing", "Product Development / Management", "Merchandising & Purchasing", "Handbag", "Procurement / Purchasing / Sourcing"], "post_time": "2022-01-17T09:06:51Z", "salary": {"currency": null, "max": null, "min": null, "period": "monthly", "term": null}, "salary_visible": false, "title_keywords": ["merchandising manager", "senior project manager"], "responsibilities": ["cost", "maintaining", "quality", "merchandising", "design", "communication", "schedule", "report"], "requirements": {"degrees": ["diploma or above"], "majors": [], "languages": ["putonghua", "english", "chinese"], "language_level": ["good command"], "hard_skills": ["r&d", "small", "problem solving", "exchange"], "soft_skills": ["flexible", "independently", "under pressure", "timely", "communication", "problem solving", "negotiation skills", "interpersonal", "detailed"], "languages_combined": [{"language": "putonghua", "language_level": ["good command"]}, {"language": "english", "language_level": ["good command"]}, {"language": "chinese", "language_level": ["good command"]}]}, "experience_required": {"duration": ["at least 8 years"], "field": ["garment", "merchandising"]}}, {"job_id": "100003009051745", "location_code": "hk", "company": "Amazin Consultants Limited", "job_title": "Merchandiser / Project Assistant", "description": "Our client is a reputable manufacturer of commercial furniture, supplying to multinational hospitality group and commercial industry.\u00a0 They are seeking for a merchandiser / project assistant to join the team.\n\n\nDevelopment project coordination\nChina factory liaison\nFollow up clients' order and\u00a0inquires\nResponsibilities:\n\nHandle inquiries from potential clients and prepare quotation as needed.\nFollow-up clients orders and development projects.\u00a0 Liaise with production unit in China to ensure projects deliver on a timely manner.\nBe a project owner and assist to resolve any issue during production when arise.\nWork closely with designers, production team, logistics team etc.\n\nRequirements:\n\nDiploma or above\nMinimum 3 years of working experience preferable in manufacturing or trading business.\nExposure furniture, fit-out project, interior design would be an advantage.\nExperience in Auto Cad is a plus.\nGood communication skills in English, Putonghua and Cantonese.\nResponsible, high-sense of ownership, good team work spirit.\n\n\n\nFor interested parties, please send your full resume\u00a0 to resume@ amazinhr.com\n\nPersonal information is collected and used for the purposes of recruitment only. We use your personal information to contact you for the position you apply and/or for the vacancy that matches with your profile.", "employment_types": ["Full Time"], "selling_points": ["Development project coordination", "Client and factory liaison", "Follow up clients order"], "locations": ["Not Specified"], "categories": ["Manufacturing", "Product Development / Management", "Merchandising & Purchasing", "Furniture"], "post_time": "2022-01-16T23:56:21Z", "salary": {"currency": "HKD", "max": 19999, "min": 17000, "period": "monthly", "term": null}, "salary_visible": true, "title_keywords": ["merchandiser", "project assistant"], "responsibilities": ["liaise with", "logistics", "quotation", "a timely manner"], "requirements": {"degrees": ["diploma or above"], "majors": [], "languages": ["cantonese", "putonghua", "english"], "language_level": ["good"], "hard_skills": ["plus", "auto cad"], "soft_skills": ["good team work", "communication skills", "responsible"], "languages_combined": [{"language": "cantonese", "language_level": ["good"]}, {"language": "putonghua", "language_level": ["good"]}, {"language": "english", "language_level": ["good"]}]}, "experience_required": {"duration": ["minimum 3 years"], "field": ["business", "manufacturing", "trading"]}}, {"job_id": "100003009054033", "location_code": "hk", "company": "Creative Concepts Manufacturing Limited", "job_title": "SENIOR MERCHANDISER", "description": "Liaise with overseas clients and factory independently\nHandle Orders from sampling to shipment in appropriate manner .\nAble to handle large quantity orders and Co-ordinate with colleagues in different departments\nTravel to China and Fluent Mandarin + English is a mandatory\nFollowing projects from sample collection to product development is a requirement\nExperience for minimum 5 years\nStrong negotiation, presentation, problem solving skill and able to work under pressure\nMake order status report on daily-weekly basis .\nExperience in Sundries , Novelties , Product Development , kitchen items , General Merchandise is a must .\nAble to source and find product through website and company database in 2 days maximum.\nWork with the sourcing and merchandising team on orders , queries , shipments, Quality Assurance Department.\nProficient in computers and Chinese typing is mandatory ( Excel , Word , PowerPoint , Outlook )\n5 DAY WORKS\u00a0\n\nInterested parties click \"APPLY NOW\" to submit your application.\n\nPersonal data collected will be used for recruitment purpose only.", "employment_types": ["Full Time", "Permanent"], "selling_points": [], "locations": ["Hung Hom"], "categories": ["Manufacturing", "Product Development / Management", "Merchandising & Purchasing", "Sundries", "Procurement / Purchasing / Sourcing"], "post_time": "2022-01-17T08:08:35Z", "salary": {"currency": null, "max": null, "min": null, "period": "monthly", "term": null}, "salary_visible": false, "title_keywords": ["senior merchandiser"], "responsibilities": ["co-ordinate with", "work under pressure", "merchandising", "website", "quality", "database", "liaise with", "report"], "requirements": {"degrees": [], "majors": [], "languages": ["english", "chinese", "mandarin"], "language_level": ["proficient", "fluent"], "hard_skills": ["excel", "word", "typing", "powerpoint", "problem solving", "make", "outlook"], "soft_skills": ["independently", "negotiation", "problem solving skill", "presentation", "work under pressure"], "languages_combined": [{"language": "english", "language_level": []}, {"language": "chinese", "language_level": ["proficient"]}, {"language": "mandarin", "language_level": ["fluent"]}]}, "experience_required": {"duration": ["minimum 5 years"], "field": ["product development"]}}, {"job_id": "100003009028244", "location_code": "hk", "company": "Creative China Creations Limited", "job_title": "Sourcing Coordinator/ Merchandiser /Sr. Merchandiser /Product Manager (Consumer Products/ Sundries)", "description": "Job Requirements:\u00a0\n\nMinimum 5 years merchandising or relevant experience in Trading or Manufacturing Company. (Sourcing, Product development experience)\nMotivated, Organized, and able to work efficiently to meet the deadlines of buyers\nEXCELLENT COMMAND IN WRITTEN & SPOKEN ENGLISH, CANTONESE & MANDARIN SKILLS\nAble to communicate with suppliers and overseas customers\nResponsible, willing to learn, exhibit a positive attitude and work overtime\nExcellent knowledge of product cost breakdown and production process.\nProficient in material sourcing and supplier evaluation and management.\nExcellent and successful in price negotiation and problem solving skills\nTravel to China for supplier evaluation, management, follow-up, and inspection.\nProficient in PC applications (Microsoft Word, Excel, Microsoft Office applications).\nAn analytical and strategic thinker who is efficient, organized, and attentive to details and able to motivate staff and work under time deadlines.\nStrong sourcing skills and network of potential suppliers that allows the company to source directly through the most cost efficient and competent factories.\nCommunicate clearly to suppliers, including lead time, capacity allocation, pricing and resource allocation to ensure reliable service, quality and low-cost procurement.\nCoordinate with factories for manufacturing process and ensure on time shipment\nSelf-motivated, detailed oriented, a team player and able to work under pressure.\u00a0\nExperienced to supervise merchandising team, & be a team leader.\nCustomer-oriented, effective interpersonal and communication skills\nAble to work independently or part of a team with overseas customers and vendors\nEffectively manage and review vendor base for optimal sourcing results and possess an extensive sourcing network and excellent relationships with vendors.\nProduct management including product development, product selection, Target Negotiation, placement order, pricing.\nAnalyze the marketplace, customers and competitors to determine the right features to bring to market\u00a0\u00a0\nDaily communications with buyers, laboratories and vendors, following through all samples, testing, production to shipments\nEnsuring an effective merchandising value chain which produces goods in good quality standard and meet tight delivery\nGood sourcing experience for USA and EU markets and are familiar with sourcing Websites such as Alibaba.com, globalsources.com, and other sourcing sites.\nA team leader who exhibits leadership qualities and is able to work under pressure and within time constraints.\nPermanent Hong Kong ID card Holder.\nFlexible working times and willing to work after hours if needed.\n\n\nKey responsibilities:\n\nTake the lead in the end-to-end product sourcing cycle from product development, price negotiation to production of consumer products\nWork with the buyers to understand the product and order requirement\nCommunicate with vendors and factories to ensure on-time delivery and resolve any potential problems\nExecute and review existing internal systems and policies to ensure smooth operations and meeting company standards\n\n\nKey requirements:\n\nDegree/Diploma holder, with at least 5 years of relevant experience\nGood understanding on global Markets\nExcellent command in Cantonese, English and Mandarin\nGood communication and interpersonal skills to work with counterparts\nAble to work independently and meet tight deadlines\nProficient in computer skills and MS Office Applications\n\n\nInterested applicants please send your English application along with cover letter and detailed resume with current and expected salary clearly stated to \u201cApply Now\u201d.\n\nAll Personal data collected will be used for recruitment purpose only.", "employment_types": ["Full Time", "Permanent"], "selling_points": ["double pay and performance bonus", "Good understanding on global markets", "With at least 5 years of relevant experience"], "locations": ["Ngau Tau Kok"], "categories": ["Manufacturing", "Product Development / Management", "Merchandising & Purchasing", "Sundries", "Procurement / Purchasing / Sourcing"], "post_time": "2022-01-17T16:20:53Z", "salary": {"currency": null, "max": null, "min": null, "period": "monthly", "term": null}, "salary_visible": false, "title_keywords": ["merchandiser", "product manager", "coordinator", "sr. merchandiser"], "responsibilities": ["communicate with", "price negotiation", "policies", "review", "communication", "recruitment", "ensure smooth operations", "personal data", "internal systems"], "requirements": {"degrees": [], "majors": [], "languages": ["cantonese", "english", "mandarin"], "language_level": ["excellent"], "hard_skills": ["excel", "microsoft word", "microsoft office", "id", "vendor", "pc applications", "problem solving skills"], "soft_skills": ["work overtime", "team player", "leadership", "work under pressure", "efficient", "customer-oriented", "reliable", "interpersonal", "organized", "communication skills", "work independently", "negotiation", "competent", "willing to learn", "extensive", "flexible", "self-motivated", "detailed oriented", "responsible", "attentive to details", "positive attitude", "motivated", "problem solving skills"], "languages_combined": [{"language": "cantonese", "language_level": ["excellent", "excellent"]}, {"language": "english", "language_level": ["excellent", "excellent"]}, {"language": "mandarin", "language_level": ["excellent", "excellent"]}]}, "experience_required": {"duration": ["minimum 5 years"], "field": ["manufacturing", "merchandising", "relevant experience", "product development", "trading"]}}, {"job_id": "100003009052355", "location_code": "hk", "company": "Sheenway (Hong Kong) Limited", "job_title": "Project Engineer (5-day week)", "description": "\u00a0\u5de5\u4f5c\u7bc4\u570d\uff1a\n\n\n\u8ca0\u8cac\u897f\u5f0f\u98df\u54c1\u88fd\u4f5c\n\u4e86\u89e3\u5e02\u5834\u52d5\u5411\u53ca\u8ca0\u8cac\u5b9a\u671f\u7814\u767c\u65b0\u7522\u54c1\u8fce\u5408\u5e02\u5834\u9700\u8981\n\u63a7\u5236\u98df\u7269\u6210\u672c\u53ca\u9810\u7b97\n\u6309\u516c\u53f8\u6a19\u6e96\u4f5c\u5168\u9762\u98df\u54c1\u88fd\u4f5c\u53ca\u76e3\u5bdf\u98df\u7269\u54c1\u8cea\n\u8a2d\u8a08\u71df\u904b\u6d41\u7a0b\n\u8ca0\u8cac\u90e8\u9580\u7ba1\u7406\u5de5\u4f5c\n\n\u00a0\u8077\u4f4d\u8981\u6c42\uff1a\n\n\u4e2d\u5b78\u7a0b\u5ea6\u4ee5\u4e0a\u53ca\u5341\u5e74\u6216\u4ee5\u4e0a\u5eda\u623f\u7ba1\u7406\u7d93\u9a57\n\n\u5177\u5099\u9152\u5e97\u3001\u6703\u6240\u3001\u9910\u98f2\u6216\u98df\u54c1\u88fd\u4f5c\u5eda\u52d9\u7ba1\u7406\u7d93\u9a57\n\u64c5\u9577\u897f\u3001\u65e5\u3001\u97d3\u53ca\u6771\u5357\u4e9e\u83dc\u98df\u54c1\u88fd\u4f5c\u53ca\u7814\u767c\u7d93\u9a57\n\u5177\u5099\u98df\u54c1\u5b89\u5168\u7ba1\u7406\u7d93\u9a57\u53ca\u6d41\u7a0b\u7cfb\u7d71\u7ba1\u7406\u7d93\u9a57\u66f4\u4f73\n\u826f\u597d\u4e2d\u6587\u66f8\u5beb\u53ca\u8aaa\u8a71\u80fd\u529b\n\nCompetitive remuneration package will be offered to the right candidate. Interested parties please click\u00a0\"Apply Now\"\u00a0or send full resume with expected salary by 1) email to\u00a0 recruitoffice@ fairwood.com.hk\u00a0or 2) direct mail to HR Manager, 2/F TRP Commercial Centre, 18 Tanner Road, North Point, Hong Kong.\n\n(Data collected will be used for recruitment purpose only)", "employment_types": ["Full Time", "Permanent"], "selling_points": [], "locations": ["Tsim Sha Tsui"], "categories": ["Engineering", "Electrical / Electronics", "Engineering Project Management", "Manufacturing", "Product Development / Management"], "post_time": "2022-01-17T02:50:45Z", "salary": {"currency": null, "max": null, "min": null, "period": "monthly", "term": null}, "salary_visible": false, "title_keywords": ["project engineer"], "responsibilities": [], "requirements": {"degrees": [], "majors": [], "languages": [], "language_level": [], "hard_skills": [], "soft_skills": [], "languages_combined": []}, "experience_required": {"duration": [], "field": []}}, {"job_id": "100003009052451", "location_code": "hk", "company": "Eternity Consultants (HK) Ltd", "job_title": "Assistant Project Manager / Project Manager - Toys", "description": "University degree, major\u00a0in Electrical & Electronic Engineering is preferred\n2 years or above experience in product development and project management of consumer electronic products\nCapability in understanding BOM, schematic diagram & 3D drawing will be an advantage\nSound communication & negotiation skills\nGood written and spoken English, Chinese & Mandarin\nProficiency in MS Office & other PC software\nResponsible, self-initiation, aggressive and work under pressure\nRequired to travel to China periodically\nImmediate available", "employment_types": ["Full Time", "Permanent"], "selling_points": ["5 days, 13 months+bonus, bank medical", "6-8 years in project follow up in toy, plastic", "project follow up"], "locations": ["Not Specified"], "categories": ["Engineering", "Engineering Project Management", "Manufacturing", "Manufacturing Management", "Product Development / Management"], "post_time": "2022-01-17T03:04:12Z", "salary": {"currency": null, "max": null, "min": null, "period": "monthly", "term": null}, "salary_visible": false, "title_keywords": ["assistant project manager", "project manager"], "responsibilities": ["communication", "project management", "work under pressure", "pc software"], "requirements": {"degrees": ["university degree"], "majors": ["engineering"], "languages": ["english", "chinese", "mandarin"], "language_level": ["good"], "hard_skills": ["pc", "project management", "ms office"], "soft_skills": ["responsible", "communication", "project management", "negotiation skills", "work under pressure"], "languages_combined": [{"language": "english", "language_level": ["good"]}, {"language": "chinese", "language_level": ["good"]}, {"language": "mandarin", "language_level": ["good"]}]}, "experience_required": {"duration": ["2 years"], "field": ["project management", "product development"]}}, {"job_id": "100003009054820", "location_code": "hk", "company": "Victoria\u2019s Secret", "job_title": "Contract Merchandiser (Product Development)", "description": "Job Duties:\n\nManage, monitor and enhance the efficiency and effectiveness of all aspects of engineering activities within an organization including sampling and product review\nEnsure all engineering projects, initiatives, and processes are in conformance with organization\u2019s established policies and objectives\nManage the daily operations of engineering team and deliver the KPI of company for engineering and technical functions\nTo lead the team member to drive the team structure and solve the problems in consistent way\nWork on product costing, budget and control repairing and maintenance costs\nTypically reports to top management\n\nJob Requirements:\n\nBachelor\u2019s degree in Industrial Engineering or equivalent\nMinimum 6 years plastic toys\n\nSolid experience in the manufacturing field with exposure in areas of production, quality, safety, logistics and maintenance\nGood understanding of production processes and manufacturing capabilities\nStrong knowledge of practices and procedures to effectively resolve workflow issues\nStrong ability to gather, analyze and interpret information and develop, recommend and implement solutions\nDemonstrate experience in leading, guiding, and mentoring teams and individuals; understand group dynamics and team development\nResult and quality focused; great attention to detail\nEffectively communicate, both verbally and written to all levels of the organization\nGood analytical and problem solving skills are essential\nFluency in both spoken and written English and Chinese (Mandarin & Cantonese)\nERP application experience is preferable\u00a0\n\n*Interested parties, please Email full resume with current & expected salary & date available in MS WORD FORMAT ONLY to us\u00a0\u00a0or fax to 3527 0634*\n\nWe are welcome applicants resend resumes to us even you have applied jobs in our company before.\n\nFor more jobs, please visit our website:\u00a0www.hketernity.com\n\n(Personal data submitted are for recruitment purpose only.)\u00a0\n\nFor more jobs, please visit our website:\u00a0www.hketernity.com\n\n\u00a0(Personal data submitted are for recruitment purpose only.)", "employment_types": ["Temporary", "Contract"], "selling_points": ["Renewable Contract", "Assess product construction - intimate and apparel", "5 days work week"], "locations": ["Kowloon Bay"], "categories": ["Manufacturing", "Garment / Textile", "Product Development / Management", "Merchandising & Purchasing", "Woven / Knit"], "post_time": "2022-01-17T11:22:08Z", "salary": {"currency": null, "max": null, "min": null, "period": "monthly", "term": null}, "salary_visible": false, "title_keywords": ["merchandiser", "product development"], "responsibilities": ["control", "management", "maintenance", "policies", "review", "monitor", "budget", "daily operations", "reports", "costs"], "requirements": {"degrees": ["degree", "bachelor"], "majors": ["engineering"], "languages": ["cantonese", "english", "chinese", "mandarin"], "language_level": ["fluency"], "hard_skills": ["problem solving skills", "maintenance", "erp"], "soft_skills": ["analytical and problem solving skills", "attention to detail", "focused"], "languages_combined": [{"language": "cantonese", "language_level": []}, {"language": "english", "language_level": ["fluency"]}, {"language": "chinese", "language_level": ["fluency"]}, {"language": "mandarin", "language_level": []}]}, "experience_required": {"duration": [], "field": ["manufacturing", "logistics", "maintenance"]}}, {"job_id": "100003009028237", "location_code": "hk", "company": "Creative China Creations Limited", "job_title": "Production & Quality Engineer (Consumer Products & Sundries)", "description": "PRINCIPAL DUTIES & RESPONSIBILITIES:\n\nAssess product construction based on fabrics, trims and treatments and to build the Smart product to achieve the aesthetics and margin goals\u00a0\nCall out any risks on quality, capability and capacity at the early development stage\u00a0and escalate to supervisor\u00a0\nAssess risks early to pull in CFT and QA expertise and work on\u00a0solutions\u00a0\nCome up with different cost options to achieve the business goals\u00a0\nManage tech pack in and out, work closely with vendors on meeting sample follow up.\u00a0\nFollow up costing with vendors to ensure costing to counterpart is provided in a timely manner.\u00a0\nCoordinate sample tracking\u00a0\nUpdate cost sheet per style\u00a0\nFollow up with vendors for the compliance questionnaires and check the completeness and accuracy for system update \u00a0\u00a0\nCo-ordinate with cross functional team including fit approval and style duplication per Senior Merchandiser direction\u00a0\u00a0\nLearn and work on enterprise software (e.g. Salesforce)\u00a0\n\nREQUIREMENTS:\n\n\n3+\u00a0years related experience\u00a0in\u00a0following up time and actions\u00a0\nProficient in Word, Excel and\u00a0Powerpoint\u00a0\u00a0\nCertificate/Diploma or equivalent\u00a0\nGood command of spoken and written English\nCandidates not invited for interview within 8 weeks may consider their applications unsuccessful. All personal information will be treated as confidential and be used for recruitment purposes only.", "employment_types": ["Full Time", "Permanent"], "selling_points": ["Good understanding on global markets", "Able to work independently & meet tight deadlines", "Preferable 5 years of work experience"], "locations": ["Ngau Tau Kok"], "categories": ["Manufacturing", "Product Development / Management", "Merchandising & Purchasing", "Sundries", "Procurement / Purchasing / Sourcing"], "post_time": "2022-01-17T16:20:53Z", "salary": {"currency": null, "max": null, "min": null, "period": "monthly", "term": null}, "salary_visible": false, "title_keywords": ["engineer"], "responsibilities": ["cost", "business goals", "software", "co-ordinate with", "system update", "compliance", "quality", "a timely manner", "coordinate", "assess risks", "tracking"], "requirements": {"degrees": ["certificate", "diploma"], "majors": [], "languages": ["english"], "language_level": ["good command"], "hard_skills": ["excel", "word", "powerpoint"], "soft_skills": [], "languages_combined": [{"language": "english", "language_level": ["good command"]}]}, "experience_required": {"duration": ["3+ years"], "field": ["related"]}}, {"job_id": "100003009052082", "location_code": "hk", "company": "TUMI Asia, Limited", "job_title": "Tumi - Product Development Assistant (4-month Contracted)", "description": "Job Requirements:\n\nDevelop and implement the Creative China Creations Limited (CCCL) Vendor Quality Management System across the supplier network in China as well as CCCL own facility in Mainland China in conjunction with the product development team at Hong Kong head office.\nFacilitate correspondence on internal Quality Control checks between Hong Kong office (Product Development Team) & CCCL factory in Mainland China as well as 3rd party suppliers\nCommunicate with Hong Kong team members on technical specifications & requirements through the product development process to ensure quality standards for both product functionality, safety and compliance are met.\nEstablish protocols with supplier production teams to develop high-volume and quick- turnaround manufacturing processes and capabilities for new product implementation (NPI)\nConduct quality audits (IQC, IPQC & OQC) for pre- and mass-production at suppliers.\nIntroduce protocols for final goods inspection with supplier QC team and third-party inspectors, and SOPs for in-time reporting and rapid corrective/preventive action plan (CAPA).\nSuggest quality control enhancements for both infrastructure & ERP systems as well as specific consumer products.\nUtilize inspection metrics and quality improvement/control tools (e.g., DOE & FMEA) to drive continuous quality improvement with suppliers.\nLiaise & coordinate 3rd party inspections with various companies such as SGS, Intertek, BV, etc and help establish inspection mandates & protocols to follow.\nMonitor market sale and return data and provide warning alerts to head office for quality risk management.\nLead company initiative to support overseas suppliers to attain C-TPAT validation (Customs \u2013 Trade Partnership against Terrorism - USA) as well as meet other audit or client specific audit standards such as ISO, ETL, UL, CE, BSCI, ICTI standards.\nEXCELLENT COMMAND IN WRITTEN & SPOKEN ENGLISH, CANTONESE & MANDARIN SKILLS\nAble to Travel to China for implementation and monitoring of Quality Control systems.\nCandidates with at least 5 years\u2019 experience is preferred but not a requirement.\nThe ability to work independent or part of a larger team, with the mentality & work ethic of a leader.\nFamiliarity with Quality control systems for consumer products is preferred.\nA team leader who exhibits leadership qualities and is able to work under pressure and within time constraints.\nPermanent Hong Kong ID card Holder.\nFlexible working times and willing to work after hours if needed.\n\n\u00a0Key requirements:\n\nDegree/Diploma holder, with at least 5 years of relevant experience\nGood understanding on US/UK/EU Markets\nExcellent command in Cantonese, English and Mandarin\nGood communication and interpersonal skills to work with counterparts\nAble to work independently and meet tight deadlines\nProficient in computer skills and MS Office Applications\nUnderstand electronic circuitry in component level.\nHands on experience in operating test equipment such as voltmeter, ammeter and oscilloscope\nCoordinate weekly customer complaint meeting.\n\nInterested applicants please send your English application along with cover letter and detailed resume with current and expected salary clearly stated to \u201cApply Now\u201d.\n\nAll Personal data collected will be used for recruitment purpose only.\n", "employment_types": ["Full Time", "Contract"], "selling_points": ["Five-day work week", "2 years of relevant experience", "Fresh Graduates are welcome to apply"], "locations": ["Tsim Sha Tsui"], "categories": ["Manufacturing", "Product Development / Management", "Others", "Merchandising & Purchasing", "Handbag"], "post_time": "2022-01-17T09:19:47Z", "salary": {"currency": null, "max": null, "min": null, "period": "monthly", "term": null}, "salary_visible": false, "title_keywords": ["product development assistant"], "responsibilities": ["liaise", "data", "quality", "audit", "communication", "plan", "personal data", "work under pressure", "control", "compliance", "teams", "implementation", "infrastructure", "develop", "monitor", "reporting", "management", "monitoring", "inspection", "specifications", "sops", "audits", "communicate with", "systems", "coordinate", "recruitment", "quality control"], "requirements": {"degrees": ["diploma holder", "degree"], "majors": [], "languages": ["cantonese", "english", "mandarin"], "language_level": ["excellent"], "hard_skills": ["erp systems", "id", "vendor", "c", "computer skills", "rapid", "ms office"], "soft_skills": ["flexible", "work independently", "meet tight deadlines", "independent", "detailed", "communication and interpersonal skills", "hands on", "work ethic", "creative", "leadership", "initiative", "work under pressure"], "languages_combined": [{"language": "cantonese", "language_level": ["excellent", "excellent"]}, {"language": "english", "language_level": ["excellent", "excellent"]}, {"language": "mandarin", "language_level": ["excellent", "excellent"]}]}, "experience_required": {"duration": ["at least 5 years"], "field": ["relevant experience"]}}, {"job_id": "100003009048296", "location_code": "hk", "company": "TIME Interconnect Limited", "job_title": "Project Engineer", "description": "Job Responsibilities:\u00a0\n\nAssist Product Development Manager on material development (prepare and send swatch cards to design, vendor and Tumi lab)\nPrepare weekly sample development status report\nHandle daily courier shipment\nTake sample photo, assist Product Development Manager\u00a0prepare sample evaluation report\nMaterial master filing\nJob Requirement:\u00a0\n\nDegree holder in any disciplines\nMinimum 2 years of relevant experience in administration/ operation and fresh graduates will be considered\nProficiency in Microsoft Office, Excel and Word\nGood spoken and written English and Cantonese/Chinese\nInterested parties please send your Full Resume with current and expected salary to us by clicking the \"Apply Now\" button below.\n\nTUMI is an equal opportunity employer and welcome applications from all qualified candidates. All information provided by candidates will be used solely for recruitment purposes. Candidates not notified within eight weeks may consider their application unsuccessful. Unsuccessful applications will be destroyed in strict confidence upon completion of recruitment process.", "employment_types": ["Full Time", "Permanent"], "selling_points": [], "locations": ["Shatin Area"], "categories": ["Manufacturing", "Product Development / Management"], "post_time": "2022-01-14T06:12:14Z", "salary": {"currency": null, "max": null, "min": null, "period": "monthly", "term": null}, "salary_visible": false, "title_keywords": ["project engineer"], "responsibilities": ["evaluation", "design", "report"], "requirements": {"degrees": ["degree holder"], "majors": ["any disciplines"], "languages": ["cantonese", "english", "chinese"], "language_level": ["good"], "hard_skills": ["excel", "word", "microsoft office"], "soft_skills": [], "languages_combined": [{"language": "cantonese", "language_level": ["good"]}, {"language": "english", "language_level": ["good"]}, {"language": "chinese", "language_level": ["good"]}]}, "experience_required": {"duration": ["minimum 2 years"], "field": ["operation", "relevant experience", "administration"]}}, {"job_id": "100003009054342", "location_code": "hk", "company": "MGA Entertainment (H.K.) Ltd", "job_title": "Costing Engineer / Industrial Engineer", "description": "Responsibilities:\u00a0\n\n\nResearch innovative design & technology for the new product development and evaluate the possibility for further product enhancement and\u00a0improvement\nMonitor and follow up product development, R&D Tasks for cabling accessories project from\u00a0design to production\nTrouble shoot by identifying root causes and communicate with parties concerned in order to\u00a0solve the problems\nProvide technical advice on design, production process and quality assurance\nDevelop new products to launch in tight timeframe\nOther duties as assigned\nRequirements\n\nBachelor Degree holder or above in Electronics Engineering / Material Science;\nSolid experience in product development, project follow up and management; experience in medical, automotive and/or electronics manufacturing industries is highly preferred;\nKnowledge in PCBA Design, Electronics Component Application, M.S. Project, Pro-E, SolidWork and AutoCad etc. will be an asset\nGood communication skills, self-initiative and teamwork characteristics;\nProficiency in both written and spoken English and Chinese (Cantonese and Mandarin);\nFrequent travel (including PRC) will be required.\nFresh graduate will also be considered\nWe offer competitive remuneration package including 5-day work, guaranteed 13 months' annual salary, discretionary bonus, training and insurance to the right candidate.\u00a0 Interested parties please apply by sending full resume including current and expected salaries, availability by email to our HR Department.\n\n(Personal data collected for recruitment purpose only)\n\n", "employment_types": ["Full Time", "Permanent"], "selling_points": [], "locations": ["Tsim Sha Tsui"], "categories": ["Engineering", "Manufacturing & Production", "Manufacturing", "Product Development / Management", "Merchandising & Purchasing", "Toy"], "post_time": "2022-01-17T09:12:34Z", "salary": {"currency": null, "max": null, "min": null, "period": "monthly", "term": null}, "salary_visible": false, "title_keywords": ["engineer"], "responsibilities": ["communicate with", "production process", "other duties", "technical advice", "monitor", "quality", "design", "develop", "evaluate"], "requirements": {"degrees": ["fresh graduate", "bachelor degree holder"], "majors": ["science", "engineering"], "languages": ["cantonese", "english", "chinese", "mandarin"], "language_level": ["proficiency"], "hard_skills": ["solidwork", "autocad"], "soft_skills": ["communication skills", "teamwork", "self-initiative"], "languages_combined": [{"language": "cantonese", "language_level": []}, {"language": "english", "language_level": ["proficiency"]}, {"language": "chinese", "language_level": ["proficiency"]}, {"language": "mandarin", "language_level": []}]}, "experience_required": {"duration": [], "field": ["product development", "manufacturing", "management", "medical"]}}, {"job_id": "100003009049481", "location_code": "hk", "company": "", "job_title": "Product Engineering Manager - Shenzhen", "description": "Diploma or above with minimum 5 years softgoods merchandising experience\nKnowledge of manufacturing processes is an added advantage\nAnalytical and attentive to details with good negotiation and problem solving skills\nSound computer knowledge, especially in Microsoft software\nGood communication skills in English and Chinese (both written and spoken), Putonghua speaking is an advantage\n\nInterested parties with relevant experience and qualification, please send detailed resume and expected salary to HR Department, MGA Entertainment,\u00a0Suite 301, Chinachem Golden Plaza, 77 Mody Road, TST East, Kowloon or via email.", "employment_types": ["Full Time", "Permanent"], "selling_points": ["Bachelor's Degree in Electronics Engineering", "Minimum 10 years engineering management exp.", "Handle Failure Analysis"], "locations": ["Others - China"], "categories": ["Engineering", "Electrical / Electronics", "Manufacturing & Production", "Manufacturing", "Product Development / Management"], "post_time": "2022-01-14T08:44:14Z", "salary": {"currency": null, "max": null, "min": null, "period": "monthly", "term": null}, "salary_visible": false, "title_keywords": ["engineering manager"], "responsibilities": ["communication", "merchandising", "software"], "requirements": {"degrees": ["diploma or above"], "majors": [], "languages": ["putonghua", "english", "chinese"], "language_level": ["advantage", "good"], "hard_skills": ["problem solving skills"], "soft_skills": ["communication skills", "problem solving skills", "negotiation", "attentive to details"], "languages_combined": [{"language": "putonghua", "language_level": ["advantage", "good"]}, {"language": "english", "language_level": ["advantage", "good"]}, {"language": "chinese", "language_level": ["advantage", "good"]}]}, "experience_required": {"duration": ["minimum 5 years"], "field": ["merchandising"]}}, {"job_id": "100003009054325", "location_code": "hk", "company": "SEB Asia Limited", "job_title": "Senior Merchandising Officer (Marketing)", "description": "Job Responsibilities:\u00a0\n\nServe as key technical interface with customer during the entire product life cycle from quotation, project transfer, NPI and mass production;\nServe as the technical coordinator for internal engineering departments including component, SMT, manufacturing, industrial, quality engineering and R&D;\nTake lead to resolve technical issues and perform failure analysis during NPI and at Mass Production;\nSupport Project Manager to communicate technically with customers\u00a0and internally with team members;\nPrepare, approve and maintain engineering documents, including BOM, ECN, DN, QPL, part drawing, first article evaluation report, etc.;\nSupport Purchasing Department and Quality Assurance Team for supplier selection;\nSupport Purchasing Department\u00a0to source the alternative materials;\nProvide training and support to the team members.\n\nQualification:\n\nBachelor\u2019s degree in Electronics Engineering;\nMinimum 10 years engineering management experience with circuit design knowledge in Industrial, Automotive, Telecommunication and/or RF Wireless; products;\nCapable to handle Failure Analysis;\nStrong communication skills in both verbal and written English;\nStation in Shenzhen plant is required.\n\nInterested candidates, please contact us at 65368175 for company details before applying.", "employment_types": ["Full Time", "Permanent"], "selling_points": ["The Global leader in Small Domestic Appliances", "MNC with International teams", "SDA background is an advantage"], "locations": ["Yau Tsim Mong Area"], "categories": ["Manufacturing", "Product Development / Management", "Merchandising & Purchasing", "Home Appliances", "Procurement / Purchasing / Sourcing"], "post_time": "2022-01-17T09:09:52Z", "salary": {"currency": null, "max": null, "min": null, "period": "monthly", "term": null}, "salary_visible": false, "title_keywords": ["officer", "merchandising"], "responsibilities": ["provide training", "management", "analysis", "quotation", "quality", "design", "communication", "maintain", "evaluation", "report"], "requirements": {"degrees": ["degree", "bachelor"], "majors": ["engineering"], "languages": ["english"], "language_level": [], "hard_skills": ["r&d", "analysis", "qpl"], "soft_skills": ["communication skills", "capable"], "languages_combined": [{"language": "english", "language_level": []}]}, "experience_required": {"duration": ["minimum 10 years"], "field": ["management", "engineering", "design"]}}, {"job_id": "100003009055329", "location_code": "hk", "company": "Computime Ltd", "job_title": "Manager / Senior Manager \u2013 Business", "description": "What\u2019s in it for you:\u00a0\u00a0\u00a0\u00a0\u00a0\u00a0\u00a0\u00a0\u00a0\u00a0\u00a0\u00a0\u00a0\u00a0\u00a0\u00a0\u00a0\u00a0\u00a0\u00a0\u00a0\u00a0\u00a0\u00a0\u00a0\u00a0\u00a0\u00a0\u00a0\u00a0\u00a0\u00a0\u00a0\u00a0\u00a0\u00a0\u00a0\u00a0\u00a0\u00a0\n\nMonitor process of product development projects by working closely with corresponding Sourcing teams\nHandle sample arrangement, follow up on packaging brief, artwork related documents in system\nSupport Product Manager to source potential suppliers / partners for the finished products including assist in analysis of product offer from manufacturers, benchmarking, short-listing potential suppliers etc\nConsolidate market information such as new products, new technologies and competitors\u2019 information\n\nWhat we are looking for:\n\nAssociate degree or above with at least 2 years of relevant working experience\nFamiliar with Small Domestic Appliances is an advantage\nGood command of both spoken and written English, Cantonese and Mandarin\nStrong sense of responsibility, well organized and good team player\nFamiliar with MS Office (Word, Excel, Powerpoint)\n\nWe offer attractive remuneration package to the right candidate including 5-day work, double pay, discretionary bonus,\u00a0family leave & birthday leave,\u00a0medical, dental / life insurance scheme, etc.\n\nInterested parties please apply with full resume with\u00a0expected salary\u00a0and current salary\u00a0to\u00a0Human Resources\u00a0Department. For company details, please visit our website.\n\nAll data collected is for recruitment purpose only. Candidates not invited for interview within 8 weeks from the date of this posting may consider their applications unsuccessful. Unsuccessful applications will be destroyed after 6 months.\u00a0", "employment_types": ["Full Time", "Permanent"], "selling_points": ["5 days work, double pay, and free shuttle coach", "Identify new OEM/ODM sales opportunities", "Knowledgeable of EMS process"], "locations": ["Shatin Area"], "categories": ["Sales, CS & Business Devpt", "Business Development", "Manufacturing", "Product Development / Management", "Account Servicing"], "post_time": "2022-01-18T02:12:47Z", "salary": {"currency": null, "max": null, "min": null, "period": "monthly", "term": null}, "salary_visible": false, "title_keywords": ["senior manager", "manager"], "responsibilities": ["related documents", "analysis", "teams", "monitor", "consolidate market information", "insurance", "listing"], "requirements": {"degrees": ["degree or above"], "majors": [], "languages": ["cantonese", "english", "mandarin"], "language_level": ["good command"], "hard_skills": ["small", "excel", "analysis", "word", "powerpoint", "scheme", "ms office"], "soft_skills": ["good team player", "well organized", "sense of responsibility"], "languages_combined": [{"language": "cantonese", "language_level": ["good command"]}, {"language": "english", "language_level": ["good command"]}, {"language": "mandarin", "language_level": ["good command"]}]}, "experience_required": {"duration": ["at least 2 years"], "field": ["relevant working experience"]}}, {"job_id": "100003009049845", "location_code": "hk", "company": "Aztech Systems (Hong Kong) Ltd", "job_title": "R&D Manager(IoT Product Development)", "description": "Major Responsibilities\n\nIdentify new OEM/ODM sales opportunities of US and Europe markets\nNurture customer networking relationship to grow strategic business partners\nConduct consultative solution sales by understanding customer\u2019s compelling needs\nFollow through in global account management by working closely with departments, e.g, Program Management, Customer Service, PMC, Test Engineering, and Purchasing, for RFQ kick off and quotation preparation up to product delivery\nGather market intelligence on technological product trends in specific markets\nProvide input to develop the marketing plan and chart product roadmap\nMeet and even exceed customer\u2019s expectation in service delivery\n\nRequirements\n\nPreferably degree level with related working experience\nMinimum 3-5 years' related sales and business development experiences in the electronic controls products\nKnowledgeable of EMS process and program management\nProven record in identifying new business opportunities by various means and turning\u00a0into strategic relationship or close business networking\nSolution driven mindset and collaborative manner to work with different level of teams\nProficiency in English and Chinese (including Putonghua)\nWilling to travel and stay China, plus overseas trips from time to time\nMore experience considered as Senior Manager \u2013 Business\n\nInterested parties, please apply together with a detailed resume, stating current and expected salary, and send it via APPLY NOW.\u00a0 Attractive remuneration will be offered in commensurate with qualification and experience.\u00a0\n\nAll personal information received will be treated in strict confidence for employment purpose only.\u00a0 Your application can be considered as unsuccessful if you have not been reached within 3 months.\u00a0 On the other hand, it may be transferred to other companies of our group for job openings.\u00a0 Unsuccessful applications will be destroyed for a period not more than 12 months.\u00a0\n\nhttps://www.computime.com/\nhttps://salus-controls.com/", "employment_types": ["Full Time", "Permanent"], "selling_points": [], "locations": ["Shatin Area"], "categories": ["Engineering", "Electrical / Electronics", "Manufacturing & Production", "Manufacturing", "Product Development / Management"], "post_time": "2022-01-14T09:19:00Z", "salary": {"currency": null, "max": null, "min": null, "period": "monthly", "term": null}, "salary_visible": false, "title_keywords": ["product development"], "responsibilities": ["service delivery", "management", "quotation", "develop", "marketing plan", "customer service"], "requirements": {"degrees": ["degree"], "majors": [], "languages": ["putonghua", "english", "chinese"], "language_level": ["proficiency"], "hard_skills": ["ems", "plus"], "soft_skills": ["solution driven", "collaborative"], "languages_combined": [{"language": "putonghua", "language_level": []}, {"language": "english", "language_level": ["proficiency"]}, {"language": "chinese", "language_level": ["proficiency"]}]}, "experience_required": {"duration": ["minimum 3-5 years"], "field": ["related", "business development", "business"]}}, {"job_id": "100003009052364", "location_code": "hk", "company": "JPC Texson Limited", "job_title": "ENGINEERING MANAGER (40K-50K) - HK listed toys manufacturer (station China Guangdong)", "description": "Responsibilities:\n\nLead a team of Engineers from product conceptualisation to mass production\nWork closely with the marketing team to define new products features and specifications\nLiase with technology partners and key component suppliers to give advice to the development team and conduct designs & review so as to ensure high standard product design integrity\nManage projects to ensure high quality results within defined time and budget schedules\n\nRequirements\n\nBachelor Degree in Electronics/ Electrical/Computer Engineering\nAt least 5 years of product development experience in data networking/communication-related designs\nGood command of English and Mandarin\nExcellent communication and interpersonal skills\nMature personality, proactive, pre-emptive, self-driven and able to work independently", "employment_types": ["Full Time", "Permanent"], "selling_points": ["Solid engineering exp in toys prf manufacturers", "Lead a team of China engineers", "Report to Technical & Quality Director"], "locations": ["Others - China"], "categories": ["Engineering", "Engineering Project Management", "Mechanical", "Manufacturing", "Product Development / Management"], "post_time": "2022-01-17T02:52:19Z", "salary": {"currency": null, "max": null, "min": null, "period": "monthly", "term": null}, "salary_visible": false, "title_keywords": ["engineering manager"], "responsibilities": ["schedules", "review", "quality", "budget", "lead a team", "specifications", "product design", "manage projects"], "requirements": {"degrees": ["degree", "bachelor"], "majors": ["computer engineering"], "languages": ["english", "mandarin"], "language_level": ["good command"], "hard_skills": [], "soft_skills": ["work independently", "mature", "communication", "communication and interpersonal skills", "proactive", "driven"], "languages_combined": [{"language": "english", "language_level": ["good command"]}, {"language": "mandarin", "language_level": ["good command"]}]}, "experience_required": {"duration": ["at least 5 years"], "field": ["related", "product development"]}}, {"job_id": "100003009050009", "location_code": "hk", "company": "SI HK Limited", "job_title": "Industrial / Product Design", "description": "\n\nTHE COMPANY :\nHK listed\n\nOEM/ODM toys manufacturer\nHong Kong office : 40-50 staff\n\nGuangdong factory : 3000-4000 workers\nMain markets : US, Europe and Japan\u00a0\nWe are looking\u00a0\u00a0\u00a0 ENGINEERING MANAGER\u00a0 -\u00a0 with details as follows :\u00a0\nTHE JOB :\nAt least 10 years\u2019 engineering experience in the toy industry\nHandle OEM/ODM projects with overseas and local customers\nResponsible for new product design and development, monitor development schedule and cost control\nSupervise a team of China engineers\nStrong mechanical design abilities, with knowledge in electronic / soft toy products\nReport to the Engineering & Quality Director\nTertiary education in Engineering / Manufacturing / Production related; or equivalent solid work experience\u00a0\nProficiency in English and Mandarin\u00a0\nGood interpersonal skills and experiences in supervising a team of China engineers\nWork based in Guangdong factory with some trips to HK office for meetings\u00a0\n13 months salary + performance bonus\u00a0\nAnnual leave : 10 days\nTax equalization\u00a0\nHong Kong Banking holidays\u00a0\u00a0\nAccommodations and meals provided\n\nChina allowances\n\nMedical benefits\u00a0\u00a0\u00a0\n\u00a0\nTO APPLY for this job or similar jobs :\u00a0\n\nFor secure and confidential job application, please click the below link to get our email address.\u00a0\nhttp://jpc.hk/confidential_apply.htm\u00a0\nWe provide free job hunting services to job seekers.\nTo speed up our process, please do NOT send us download links.\nPersonal data provided by job applicants will be used for recruitment purpose only.\nYour privacy is guaranteed. We will never give out, lease, or sell your personal information.\nJPC Recruiting Services was established in 1990.\nhttp://www.facebook.com/pages/JPC-Texson-Ltd/500356593325952\n\u00a0", "employment_types": ["Full Time"], "selling_points": [], "locations": ["Kowloon Bay"], "categories": ["Design", "Industrial / Product", "Manufacturing", "Product Development / Management"], "post_time": "2022-01-14T09:41:38Z", "salary": {"currency": null, "max": null, "min": null, "period": "monthly", "term": null}, "salary_visible": false, "title_keywords": [], "responsibilities": ["tax", "supervising", "monitor", "quality", "mechanical design", "product design", "schedule", "cost control", "banking", "report"], "requirements": {"degrees": [], "majors": [], "languages": ["english", "mandarin"], "language_level": ["proficiency"], "hard_skills": [], "soft_skills": ["interpersonal skills", "responsible"], "languages_combined": [{"language": "english", "language_level": ["proficiency"]}, {"language": "mandarin", "language_level": ["proficiency"]}]}, "experience_required": {"duration": ["at least 10 years"], "field": ["engineering", "team"]}}, {"job_id": "100003009050951", "location_code": "hk", "company": "Bank of Communications Hong Kong Branch", "job_title": "Deputy Chief Product Manager", "description": "Roles and Responsibilities.\u00a0\nFocus on product design for our lifestyle brands which primarily focusses on Electric Mobility, Robotics, Accessories and Smart devices.\nProduct research and market analysis for new ideas and inspiration.\u00a0\nProvide sketch ideas and 3D renderings to our marketing team\nGenerate design detailed concepts\nWork alongside with our mechanical and electrical engineers during the design process as well as during tooling stages to identify any issues that may arise.\nPrototyping\nGraphic design is required for packaging and digital marketing assets.\u00a0\n\nRequirements\n\nMinimum 5 years of Product / Industrial Design experience in Consumer Electronic and/or Toy development and manufacturing.\u00a0\nHigher diploma or above in Product Design and Mechanical Engineering is a preferred bonus\nDemonstrates successful experience in communicating with teams and having positive energy within the office environment.\nDemonstrates the ability to work under pressure and resolve issues while keeping projects on time.\nMature, well-organized, detail minded, with excellent written and oral communication skills.\u00a0\nExcellent communication skills in English, Cantonese and Mandarin.\u00a0\nExcellent Computer skills, high proficiency in MS Office, Excel and Project Management tools.\u00a0\nCAD: Rhino and/or Solid works,\u00a0CREO\nAdobe Illustrator, Photoshop and/or Coral Draw will be a plus\nLocation:\nThe position will be in our Hong Kong Office located in Kowloon Bay\n\nBenefits:\n\nPerformance bonus\nMedical & Travel allowance\u00a0\nPromotional opportunities\nCozy Working Environment\n5-day work\n\nTo apply the above position, please send us your\u00a0Resume and Portfolio\u00a0demonstrating relevant\u00a0 skills as required.", "employment_types": ["Full Time"], "selling_points": [], "locations": ["Not Specified"], "categories": ["Banking / Finance", "Credit Analysis / Approval", "Manufacturing", "Product Development / Management"], "post_time": "2022-01-14T11:56:46Z", "salary": {"currency": null, "max": null, "min": null, "period": "monthly", "term": null}, "salary_visible": false, "title_keywords": ["product manager"], "responsibilities": ["robotics", "ideas", "graphic design", "design", "product design", "market analysis", "digital marketing"], "requirements": {"degrees": ["higher diploma or above"], "majors": ["design", "mechanical engineering"], "languages": ["cantonese", "english", "mandarin"], "language_level": ["excellent"], "hard_skills": ["excel", "plus", "rhino", "cad", "adobe illustrator", "project management", "computer skills", "photoshop", "ms office"], "soft_skills": ["communication skills", "oral", "well-organized", "mature", "project management", "positive", "work under pressure"], "languages_combined": [{"language": "cantonese", "language_level": ["excellent"]}, {"language": "english", "language_level": ["excellent"]}, {"language": "mandarin", "language_level": ["excellent"]}]}, "experience_required": {"duration": ["minimum 5 years"], "field": ["development", "manufacturing", "design"]}}, {"job_id": "100003009050415", "location_code": "hk", "company": "Links International", "job_title": "Hardgoods Merchandiser - Product Developer", "description": "Provide one-stop services to line departments on manpower planning, talent acquisition, HR advisory and change management\nFormulate & implement HR policies & participate actively in various Human Resources events, functions and projects\nDegree holder or above in Human Resources Management or related disciplines\nMinimum 8 years\u2019 relevant experience in banking or financial sector, with supervisory or checker experience is preferred\nSelf-motivated, flexible, and strong in communication, analytical and project management skills\nProficient in written Chinese and English\n\nCandidate with less experience may be considered as Manager, Resources Planning\n\nThe above post requires proficiency in English, Cantonese and Putonghua.\n\nWe offer attractive remuneration package to the right candidates. Please send your full resume with expected salary to\u00a0The Human Resources Manager, Bank of Communications Co., Ltd., 10/F, Bank of\u00a0Communications\u00a0Tower,\u00a0231-235 Gloucester Road, Wan Chai,\u00a0Hong Kong, or fax to\u00a02838 9209, or e-mail to\u00a0APPLY NOW.", "employment_types": ["Full Time", "Permanent"], "selling_points": ["Toys, textile / bedding sourcing exp", "Sourcing office exp is preferable", "15days AL + 1 day birthday leave"], "locations": ["Kwun Tong Area"], "categories": ["Manufacturing", "Manufacturing Management", "Product Development / Management", "Merchandising & Purchasing", "Sundries"], "post_time": "2022-01-14T10:21:06Z", "salary": {"currency": "HKD", "max": 24999, "min": 20000, "period": "monthly", "term": null}, "salary_visible": true, "title_keywords": ["merchandiser", "product developer"], "responsibilities": ["management", "change management", "policies", "hr", "communication", "project management", "banking", "planning"], "requirements": {"degrees": ["degree holder"], "majors": ["related disciplines"], "languages": ["cantonese", "putonghua", "english", "chinese"], "language_level": ["proficiency", "proficient"], "hard_skills": ["project management"], "soft_skills": ["flexible", "project management skills", "self-motivated", "communication"], "languages_combined": [{"language": "cantonese", "language_level": ["proficiency"]}, {"language": "putonghua", "language_level": ["proficiency"]}, {"language": "english", "language_level": ["proficiency", "proficient"]}, {"language": "chinese", "language_level": ["proficient"]}]}, "experience_required": {"duration": ["minimum 8 years"], "field": ["supervisory", "financial", "relevant experience", "banking", "planning"]}}, {"job_id": "100003009052460", "location_code": "hk", "company": "Telford International Co Ltd", "job_title": "R&D Assistant/ R&D", "description": "Career Level\nSenior\nQualification\nDegree\nYears of Experience\n5 years\nJob Type\nFull Time, Permanent\nJob Functions\nBanking / Finance, Treasury, Financial Services, Others", "employment_types": ["Full Time", "Permanent"], "selling_points": ["Product Development/ Optimization", "Experience in QA/ R&D in F&B industry", "Knowledge in Microbiology Testing"], "locations": ["Yuen Long"], "categories": ["Manufacturing", "Product Development / Management", "Quality Assurance, Control & Testing / ISO", "Sciences, Lab, R&D", "Research & Development (R&D)"], "post_time": "2022-01-17T03:05:11Z", "salary": {"currency": null, "max": null, "min": null, "period": "monthly", "term": null}, "salary_visible": false, "title_keywords": ["assistant"], "responsibilities": ["banking"], "requirements": {"degrees": ["degree"], "majors": [], "languages": [], "language_level": [], "hard_skills": [], "soft_skills": [], "languages_combined": []}, "experience_required": {"duration": [], "field": []}}, {"job_id": "100003009056438", "location_code": "hk", "company": "Fairwood Fast Food Ltd", "job_title": "\u7522\u54c1\u767c\u5c55\u90e8\u7d93\u7406 Product Development Manager (Fast Food Chain)", "description": "\u00a0\u5de5\u4f5c\u7bc4\u570d\uff1a\n\n\n\u8ca0\u8cac\u897f\u5f0f\u98df\u54c1\u88fd\u4f5c\n\u4e86\u89e3\u5e02\u5834\u52d5\u5411\u53ca\u8ca0\u8cac\u5b9a\u671f\u7814\u767c\u65b0\u7522\u54c1\u8fce\u5408\u5e02\u5834\u9700\u8981\n\u63a7\u5236\u98df\u7269\u6210\u672c\u53ca\u9810\u7b97\n\u6309\u516c\u53f8\u6a19\u6e96\u4f5c\u5168\u9762\u98df\u54c1\u88fd\u4f5c\u53ca\u76e3\u5bdf\u98df\u7269\u54c1\u8cea\n\u8a2d\u8a08\u71df\u904b\u6d41\u7a0b\n\u8ca0\u8cac\u90e8\u9580\u7ba1\u7406\u5de5\u4f5c\n\n\u00a0\u8077\u4f4d\u8981\u6c42\uff1a\n\n\u4e2d\u5b78\u7a0b\u5ea6\u4ee5\u4e0a\u53ca\u5341\u5e74\u6216\u4ee5\u4e0a\u5eda\u623f\u7ba1\u7406\u7d93\u9a57\n\n\u5177\u5099\u9152\u5e97\u3001\u6703\u6240\u3001\u9910\u98f2\u6216\u98df\u54c1\u88fd\u4f5c\u5eda\u52d9\u7ba1\u7406\u7d93\u9a57\n\u64c5\u9577\u897f\u3001\u65e5\u3001\u97d3\u53ca\u6771\u5357\u4e9e\u83dc\u98df\u54c1\u88fd\u4f5c\u53ca\u7814\u767c\u7d93\u9a57\n\u5177\u5099\u98df\u54c1\u5b89\u5168\u7ba1\u7406\u7d93\u9a57\u53ca\u6d41\u7a0b\u7cfb\u7d71\u7ba1\u7406\u7d93\u9a57\u66f4\u4f73\n\u826f\u597d\u4e2d\u6587\u66f8\u5beb\u53ca\u8aaa\u8a71\u80fd\u529b\n\nCompetitive remuneration package will be offered to the right candidate. Interested parties please click\u00a0\"Apply Now\"\u00a0or send full resume with expected salary by 1) email to\u00a0 recruitoffice@ fairwood.com.hk\u00a0or 2) direct mail to HR Manager, 2/F TRP Commercial Centre, 18 Tanner Road, North Point, Hong Kong.\n\n(Data collected will be used for recruitment purpose only)", "employment_types": ["Full Time", "Permanent"], "selling_points": ["\u8ca0\u8cac\u897f\u5f0f\u98df\u54c1\u88fd\u4f5c\u3001\u8a2d\u8a08\u71df\u904b\u6d41\u7a0b\u53ca\u63a7\u5236\u98df\u54c1\u6210\u672c\u54c1\u8cea", "\u4e2d\u5b78\u7a0b\u5ea6\u53ca\u5341\u5e74\u4ee5\u4e0a\u5eda\u623f\u7ba1\u7406(\u9152\u5e97\u6703\u6240\u9910\u98f2\u696d)\u7d93\u9a57", "\u64c5\u9577\u897f\u65e5\u97d3\u53ca\u6771\u5357\u4e9e\u83dc\u98df\u54c1\u51e0\u88fd\u4f5c\u53ca\u7814\u767c"], "locations": ["Tai Po Area"], "categories": ["Hospitality / F & B", "Food & Beverage", "Manufacturing", "Product Development / Management", "Production Planning / Control"], "post_time": "2022-01-18T04:19:03Z", "salary": {"currency": null, "max": null, "min": null, "period": "monthly", "term": null}, "salary_visible": false, "title_keywords": ["product development manager"], "responsibilities": [], "requirements": {"degrees": [], "majors": [], "languages": [], "language_level": [], "hard_skills": [], "soft_skills": [], "languages_combined": []}, "experience_required": {"duration": [], "field": []}}, {"job_id": "100003009049616", "location_code": "hk", "company": "Smart Product Concepts Limited", "job_title": "Sourcing and Product Specialist", "description": "We experience rapid expansion and are looking for Talents in our merchandising teams to fill our newly created headcounts.\n\n\nJob Duties:\n\nHandle product enquiries, sourcing, product development, order processing, artwork, packaging, factory audit, testing compliance, production control\nResearch, liaise and identify capable factories from product sourcing to price negotiation\nNegotiate with suppliers on in-market products to achieve cost savings\nResearch and identify new products\nFunctional deep test on samples received\nEnsure shipment timeliness\nHandle special and ad-hoc projects as assigned\n\nRequirements:\n\nTertiary education in Engineering, Marketing, Purchasing and Supply, IT or equivalent is an advantage\n5+ years solid merchandizing experience plus project management experience from start to delivery\nMUST have experience in Small Domestic Appliances products. Familiar with EU / US markets and kitchen appliances are advantage\nStrong experiences in the relevant product field of the team concerned\nGood knowledge of EU / UL standards and regulations concerning product safety and requirements\nStrong sense of responsibility, good interpersonal and negotiation skills\nStrong analytical and problem-solving capabilities\nHighly self-motivated, able to work independent, creative, organized and with an eye for details\nAble to handle multi-tasks and work under pressure in a fast-moving environment\nFluent in spoken and written English, Cantonese and Mandarin\nWhat we offer:\n\nDouble pay and discretionary bonus\nMedical Insurance\nLearning and Development Opportunities\nNicely-decorated Office\n5 day work week\nCompetitive Annual Leave and Staff Benefit\nCharity, Community and Staff Recreational Activities\n\nCome and join us in a multi-cultural, dynamic and stable work environment, experience the opportunity to develop your career and to work in different exciting projects in an nicely decorated office.\n\nWe are an Equal Opportunity Employer. Interested parties, please send us your job application, the position you apply, together with Current and Expected Salary. We look forward to your application.", "employment_types": ["Full Time"], "selling_points": ["Guarantee 13th Month Salary", "Stable Work Environment", "International Company with Great Culture"], "locations": ["Hung Hom"], "categories": ["Manufacturing", "Product Development / Management", "Merchandising & Purchasing", "Electronics", "Home Appliances"], "post_time": "2022-01-14T08:58:25Z", "salary": {"currency": null, "max": null, "min": null, "period": "monthly", "term": null}, "salary_visible": false, "title_keywords": ["product specialist"], "responsibilities": ["liaise", "control", "price negotiation", "cost", "compliance", "audit", "testing", "order processing", "ad-hoc projects"], "requirements": {"degrees": [], "majors": [], "languages": ["cantonese", "english", "mandarin"], "language_level": ["fluent"], "hard_skills": ["small", "merchandizing", "plus", "problem-solving", "project management"], "soft_skills": ["organized", "self-motivated", "independent", "multi-tasks", "sense of responsibility", "problem-solving", "project management", "negotiation skills", "creative", "interpersonal", "work under pressure"], "languages_combined": [{"language": "cantonese", "language_level": ["fluent"]}, {"language": "english", "language_level": ["fluent"]}, {"language": "mandarin", "language_level": ["fluent"]}]}, "experience_required": {"duration": ["5+ years"], "field": ["project management", "team"]}}, {"job_id": "100003009056304", "location_code": "hk", "company": "Lam Soon (Hong Kong) Limited", "job_title": "Production Material Officer (\u751f\u7522\u90e8\u7269\u6599\u4e3b\u4efb) (Ref. JDB_21_037)", "description": "Career Level\nMiddle\nQualification\nDegree\nYears of Experience\n3 years\nJob Type\nFull Time, Permanent\nJob Functions\nBanking / Finance, Analyst, Corporate Banking, Credit Analysis / Approval", "employment_types": ["Full Time", "Permanent"], "selling_points": ["5\u5e74\u76f8\u95dc\u5de5\u4f5c\u7d93\u9a57 ; \u5c08\u4e0a\u6559\u80b2\uff1a\u6587\u6191/\u8b49\u66f8", "\u5177\u6709ISO9001\u53caISO22000\u77e5\u8b58", "\u98df\u54c1\u5ee0\u5de5\u4f5c\u7d93\u9a57\u512a\u5148 ; \u7269\u6599\u5de5\u4f5c\u7d93\u9a57\u512a\u5148"], "locations": ["Tai Po Area"], "categories": ["Manufacturing", "Manufacturing Management", "Product Development / Management", "Production Planning / Control"], "post_time": "2022-01-18T03:53:24Z", "salary": {"currency": null, "max": null, "min": null, "period": "monthly", "term": null}, "salary_visible": false, "title_keywords": ["officer"], "responsibilities": ["analysis", "banking"], "requirements": {"degrees": ["degree"], "majors": [], "languages": [], "language_level": [], "hard_skills": ["credit analysis"], "soft_skills": [], "languages_combined": []}, "experience_required": {"duration": [], "field": []}}, {"job_id": "100003009056078", "location_code": "hk", "company": "DFI Retail Group DFI\u96f6\u552e\u96c6\u5718", "job_title": "Product Development Manager (Beauty Care), Own Brand", "description": "Company Description\u00a0\n\nOur client is a fast expanding F&B group with business in cafe and coffee trading. Because of business expansion, they are looking for someone who is enthusiastic about coffee bean and coffee to join and main/enhance the coffee quality.\n\nResponsibilities\u00a0\n\nSourcing coffee beans globally and identify potential supplier\nEnsure the highest standard of coffee bean is purchased and the best coffee is served to customers.\nAct as quality control for the coffee made\nNegotiate with coffee suppliers to ensure the right price is offered\n\nRequirements\u00a0\n\nExperienced in coffee business\nAble to tell the difference of coffee beans, origins and different roast process\nConnection and network with coffee bean supplier is a plus\nStrong in communications with good working attitude\nFluency in Cantonese and English is a must.\n\nInterested parties please send your updated resume in WORD format with current and expected salaries (quoting Employer Ref:)", "employment_types": ["Permanent"], "selling_points": [], "locations": ["Quarry Bay"], "categories": ["Manufacturing", "Product Development / Management"], "post_time": "2022-01-18T03:15:09Z", "salary": {"currency": null, "max": null, "min": null, "period": "monthly", "term": null}, "salary_visible": false, "title_keywords": ["product development manager"], "responsibilities": ["quality control"], "requirements": {"degrees": [], "majors": [], "languages": ["cantonese", "english"], "language_level": ["fluency"], "hard_skills": ["plus"], "soft_skills": ["good working attitude"], "languages_combined": [{"language": "cantonese", "language_level": ["fluency"]}, {"language": "english", "language_level": ["fluency"]}]}, "experience_required": {"duration": [], "field": []}}, {"job_id": "100003009056206", "location_code": "hk", "company": "DFI Retail Group DFI\u96f6\u552e\u96c6\u5718", "job_title": "Product Development Officer, Own Brand H&B", "description": "The Job:\n\nManages end to end product life cycle management and new product development for designated areas\nPerforms market analysis to develop concepts that are differentiating from competitors (including product claims), partnering with Consumer Insights on market trends & consumer insights\nKeeps up to date with forthcoming trends, ensuring product is developed in the correct direction and is relevant in the market place\nPartners with Commercial team on Category Own Brand strategy and Range review to identify new Own Brand opportunities and develops compelling business case\nConceptualizes product ideas, develops and launches new Beauty Care product ranges (including ongoing improvements of existing products) in collaboration with Commercial teams\nCreates and manages Critical Path, mapping out activities, highlighting the critical path and dependencies, to achieve Critical Path timelines & on time launch\nPartners with Commercial Teams to drive sales & profit\nCoordinates with Design and Technical Teams, ensuring that design and regulatory guidelines are complied\nComplies to Own Brand Procurement process to ensure all legal obligations are met and in conjunction with Technical Team to ensure that all products are safe, reliable & meet quality requirements\nManages supplier base, identifying the best supplier for the category, optimizes costs, and overall supplier relationship management\nBuilds strategic partnership with key suppliers\nBuilds strong cross functional relationship with a variety of stakeholders in different markets, promoting collaboration and improvement plans\nReviews own work in order to derive learnings and apply these to future ways of working.\n\nThe role:\n\nBachelor degree in Business, Marketing or other related discipline\nMinimum 5 years of relevant experiences in FMCG brand management, product development, sales and merchandising or relevant experience in retail\nPreferred experience with Beauty Care products\nA sound understanding in product development and category management metrics and techniques\nStrong analytical mind and business planning abilities\nHighly independent, good interpersonal, communication and time-management skills\nOpen to travel to business units in the region\nAble to work under tight timeline and pressure\nGood team player\nFluent written and verbal English & Chinese\n\nDFI Retail Group is responsible for ensuring that all personal information collected from each Candidate presented to DFI Retail Group is used for recruitment purposes only and the data collection process is in accordance with all applicable laws and compliant with the Code of Practice on Human Resource Management.\n\nTo find out more about Our Businesses and Our People, please visit our website:\u00a0https://www.DFIretailgroup.com\n\nWe are an equal opportunity employer. Personal data collected will be kept and handled confidentially by authorised personnel for recruitment purposes only. We will retain the applications of candidates not selected for a period of no more than 24 months. A copy of our Privacy Policy can be accessed by visiting our Company website.\u201d\n\nIssued by The Dairy Farm Company, Limited", "employment_types": ["Permanent"], "selling_points": ["Support the end to end product development process", "Work closely with suppliers & retail banners", "Experience in retail, buying"], "locations": ["Quarry Bay"], "categories": ["Manufacturing", "Product Development / Management"], "post_time": "2022-01-18T03:32:30Z", "salary": {"currency": null, "max": null, "min": null, "period": "monthly", "term": null}, "salary_visible": false, "title_keywords": ["officer", "product development"], "responsibilities": ["ideas", "quality", "merchandising", "design", "website", "communication", "develop concepts", "plans", "personal data", "costs", "teams", "company website", "management", "consumer insights", "review", "market analysis", "data collection", "drive sales", "guidelines", "recruitment", "planning"], "requirements": {"degrees": ["degree", "bachelor"], "majors": ["business", "marketing"], "languages": ["english", "chinese"], "language_level": ["fluent"], "hard_skills": ["no", "code", "analysis", "safe"], "soft_skills": ["highly independent", "good team player", "responsible", "communication", "analytical mind", "reliable", "interpersonal"], "languages_combined": [{"language": "english", "language_level": ["fluent"]}, {"language": "chinese", "language_level": ["fluent"]}]}, "experience_required": {"duration": ["minimum 5 years"], "field": ["management", "fmcg", "brand", "merchandising", "relevant experience", "beauty", "product development", "retail"]}}, {"job_id": "100003009047363", "location_code": "hk", "company": "Cosmic Pet HK Limited", "job_title": "Project Coordinator / Assistant Merchandiser \u2013 Pet Products/Children Toys/Plastic Toys", "description": "Responsibilities:\u00a0\n\nAcquire the latest trends of the market, Develop and explore new business opportunities in overseas market\nConduct planning, execution and communication of a development strategy that meets and exceeds financial goal\nDevelop new customers for company, visit customers on a regular basis, maintain good relationship with customers\nDrive effective and efficient communication between fabric, development and production teams to ensure that contract, budgets and development schedules are targeted\nFormulating marketing and sales strategies, implementing action plans to achieve business KPI objectives\n\nRequirements:\u00a0\u00a0\n\nDegree / Diploma in Textiles and Clothing, Design or related disciplines\nRich customer resources, has ability to develop new customers and new market\n8+ year\u2019s solid experience in handling ladies high fashion or sporty fashion mainly in US or European market\nPresentable, pro-active, energetic, global vision, judgmental marketing insight, aggressive with good communication skills\nBase in HK, willing to travel occasionally\n\nWe offer an attractive package, good prospects and fringe benefits to the right candidate. Interested parties, please apply with full resume, current and expected salary to: Group Human Resources Manager of High Fashion Group. By click below \"APPLY NOW\"(in MS Word format), or by mail: 11/F., High Fashion Centre, 1-11 Kwai Hei Street, Kwai Chung, New Territories\n\n(The information received will be used for consideration of employment only and all personal data supplied will be destroyed within 6 months.)", "employment_types": ["Full Time"], "selling_points": ["Product Development, Merchandising, Sourcing", "Pet Products / Hard Toys / Gifts & Premium", "5-day work, Double Pay, Performance Bonus, Medical"], "locations": ["Lai Chi Kok"], "categories": ["Manufacturing", "Product Development / Management", "Merchandising & Purchasing", "Toy"], "post_time": "2022-01-14T02:54:46Z", "salary": {"currency": null, "max": null, "min": null, "period": "monthly", "term": null}, "salary_visible": false, "title_keywords": ["project coordinator", "assistant merchandiser"], "responsibilities": ["budgets", "explore new business opportunities", "schedules", "teams", "maintain good relationship", "communication", "develop", "plans", "planning"], "requirements": {"degrees": ["diploma", "degree"], "majors": ["related disciplines", "design"], "languages": [], "language_level": [], "hard_skills": [], "soft_skills": ["communication skills", "energetic", "pro-active", "presentable"], "languages_combined": []}, "experience_required": {"duration": ["8+ year"], "field": []}}, {"job_id": "100003009049973", "location_code": "hk", "company": "Hays", "job_title": "Supply Chain Project Specialist", "description": "Responsibilities:\n\nMaintain overall aspects of designs and engineering phase, while keeping the product development costs and timelines to market in focus;\nCollaborate with cross-functioning team including the US office, design team, project team, suppliers, to ensure multiple projects are being executed according to plan or timeline;\nProduct Sourcing and cost analysis;\nCoordinate, monitor the product design and project implementation;\nResponsible for product testing, packing design and package artwork handling.\n\n\u00a0Qualification & Requirements:\n\nDegree or above;\n2-year experiences in Children toys/Pet Products/Plastic items;\nFresh graduate will be considered;\nStrong PC skills and familiar with Project handling;\nKnowledge of manufacturing processes and molding processes will be an advantage;\nSelf-motivated, able to work under pressure, good problem-solving skills;\nGood interpersonal & communication skills;\nProficient in spoken & written English and Mandarin;\nOccasionally travel to overseas and China;", "employment_types": ["Full Time", "Permanent"], "selling_points": ["Largest chemical group", "SAP supply chain modules", "Up to 45K"], "locations": ["Not Specified"], "categories": ["Information Technology (IT)", "Product Management / Business Analyst", "Transportation & Logistics", "Supply Chain", "Manufacturing", "Product Development / Management"], "post_time": "2022-01-14T09:34:01Z", "salary": {"currency": null, "max": null, "min": null, "period": "monthly", "term": null}, "salary_visible": false, "title_keywords": ["specialist"], "responsibilities": ["collaborate with", "development costs", "monitor", "implementation", "design", "testing", "coordinate", "maintain", "product design", "plan", "multiple projects", "cost analysis"], "requirements": {"degrees": ["degree or above", "fresh graduate"], "majors": [], "languages": ["english", "mandarin"], "language_level": ["proficient"], "hard_skills": ["problem-solving skills", "pc skills"], "soft_skills": ["communication skills", "self-motivated", "problem-solving skills", "interpersonal", "work under pressure"], "languages_combined": [{"language": "english", "language_level": ["proficient"]}, {"language": "mandarin", "language_level": ["proficient"]}]}, "experience_required": {"duration": ["2-year"], "field": ["toys"]}}, {"job_id": "100003009046861", "location_code": "hk", "company": "Cloud Light Technology Limited", "job_title": "Project Management Executive (Job Ref. Apply-HK-2009-PM)", "description": "Your new company\nThis is one of the largest chemical group in the world which operates in over 120 countries. They are rapidly expanding the APAC office and is now inviting Supply Chain professional who base in Hong Kong.\n\nYour new role\n\nDrive improvements on the supply chain process in the group level to make significant performance improvements\nImplement and roll out projects for SAP supply chain management, planning or transportation modules\nLead the SAP implementation project from user requirement identification, analysis, testing to training.\nCoordinate with business stakeholders including Super Users, IT, Supply Chain Operations team\n\n\nWhat you'll need to succeed\n\nSolid understanding of Supply Chain Process from forecasting to delivery\nExperience in supporting SAP implementation such as APO, IBP, WM, TM etc\nGood analytic skills and able to communicate with cross team departments\nGood command of English and Mandarin\n\nWhat you need to do now\nIf you're interested in this role, click 'apply now' to forward an up-to-date copy of your CV, or call us now.\nIf this job isn't quite right for you but you are looking for a new position, please contact us for a confidential discussion on your career.", "employment_types": ["Full Time", "Permanent"], "selling_points": ["new product definition and development plan", "Product cost analysis, modeling and optimization", "familiar with optoelectronics, semiconductor packa"], "locations": ["Shatin Area"], "categories": ["Management", "General Management", "Manufacturing", "Product Development / Management", "Production Planning / Control"], "post_time": "2022-01-14T01:29:31Z", "salary": {"currency": null, "max": null, "min": null, "period": "monthly", "term": null}, "salary_visible": false, "title_keywords": ["project management executive"], "responsibilities": ["communicate with", "user requirement", "management", "operations", "analysis", "coordinate with", "implementation", "testing", "contact", "forecasting", "supply chain process", "planning"], "requirements": {"degrees": [], "majors": [], "languages": ["english", "mandarin"], "language_level": ["good command"], "hard_skills": ["make", "analysis", "analytic skills", "sap"], "soft_skills": ["interested in"], "languages_combined": [{"language": "english", "language_level": ["good command"]}, {"language": "mandarin", "language_level": ["good command"]}]}, "experience_required": {"duration": [], "field": []}}, {"job_id": "100003009050533", "location_code": "hk", "company": "TV Products (HK) Limited", "job_title": "Merchandiser", "description": "Responsibilities:\n\nThe successful candidates will join Hong Kong-based optical product development team and be involved in the development of high-speed fiber-optic transceiver and optical sensor products. He / she will be responsible for managing and scheduling new product development projects from conception through transfer to manufacturing, including: Management of the product development process, time-integrated planning for qualification and customer sampling, and transfer to production. This position will work closely with a cross-disciplinary team including engineering design, product verification and test, operations, and, sales & marketing to deliver a quality product.\n\nHis / Her job responsibilities will cover the following areas:\n\nCustomer support to collect customer forecast, sample schedule, specific requirement and manage customer requirement.\nFollow customer sample deliver and testing result.\nWork with technical leaders on new product definition and development plan\nDrive project execution to meet development milestones, schedule and budget\nPush project through development gates to ensure successful transfer to manufacturing\nProduct cost analysis, modeling and optimization.\nWorking with purchase team to continue the cost down plan.\nDrive continuous product/process design improvement\n\nRequirement:\n\n\nBachelor degree or above with > 2 years related project management experience.\nPreferred field(s) of study: Electrical or Mechanical Engineering, Physics, Applied Physics, Optical Engineering or equivalent.\nCandidate who are familiar with optoelectronics, semiconductor packaging and related disciplines are preferred.\nCandidate with previous experience in managing new technology development projects and government funded projects are preferred.\nStrong organization, leadership, and analytical skills.\nExcellent interpersonal and communication skills;\nFluent in English and Mandarin\nSelf-motivated, creative, innovative and responsible.\n\nRemunerations & Benefits:\n\n\nWork locations in Hong Kong and travel to the PRC may be required\nWork Hours from 9am to 6pm\n5-day work\nHong Kong Public Holidays\nChinese New Year Bonus\n\nApplication:\n\nTo apply, please email us\u00a0your resume, your availability to report duty and quote the Job Ref.\nOnly short-listed candidates will be notified. Personal data provided by applicants will be used for consideration of an application only.\n\nApplication Deadline:\n\nUntil this position is filled.\nResumes received will strictly be used for recruitment-related purpose.", "employment_types": ["Full Time", "Permanent"], "selling_points": ["Five-day week work, Performance bonus", "Near MTR Station", "Sizable and stable trading company"], "locations": ["Tsim Sha Tsui"], "categories": ["Manufacturing", "Product Development / Management", "Merchandising & Purchasing", "Sundries"], "post_time": "2022-01-14T10:38:57Z", "salary": {"currency": null, "max": null, "min": null, "period": "monthly", "term": null}, "salary_visible": false, "title_keywords": ["merchandiser"], "responsibilities": ["management", "cost", "engineering design", "operations", "budget", "quality", "design", "testing", "scheduling", "purchase", "schedule", "forecast", "plan", "cost analysis", "planning"], "requirements": {"degrees": ["degree or above", "bachelor"], "majors": ["project management"], "languages": ["english", "mandarin"], "language_level": ["fluent"], "hard_skills": ["project management", "analytical skills"], "soft_skills": ["communication skills", "self-motivated", "responsible", "analytical skills", "innovative", "project management", "creative", "leadership", "interpersonal"], "languages_combined": [{"language": "english", "language_level": ["fluent"]}, {"language": "mandarin", "language_level": ["fluent"]}]}, "experience_required": {"duration": ["2 years"], "field": ["related", "project management", "development projects"]}}, {"job_id": "100003009048696", "location_code": "hk", "company": "Gifi Asia Limited", "job_title": "Pack Engineer (Quality Department)", "description": "Job Responsibilities\n\n\nCreate and maintain the Company Pack policy and the Pack guidelines for related products\nIdentify the Pack tasks/projects and work with suppliers, service providers and internal team in planning and executing them\nValidate Pack tests and inspection plans designed to assure quality of product Pack based on a review of all applicable safety standards and industry requirements\nValidate marking related to storage/handling & recycling for Pack (Triman, green dot,\u2026)\n\u00a0Review and resolve Pack issues with suppliers, service providers and packaging vendors\n\u00a0Coordinate and liaise with internal & external parties, related to sample evaluations\n\u00a0Maintain good communication with the suppliers to make sure our Pack requirements and standards have been well informed and implemented\nWork with France Head office to make ecotax declaration\nDevelop and follow up Supplier Pack KPI\nOther duties as assigned by Management\n\nJob Requirement\n\n\nDiploma or above in Packaging or related disciplines\n\u00a0At least 3 years working experience in of packaging and printing related field\n\u00a0Knowledge about quality assurance and quality control, raw material and finish goods markets price levels\n\u00a0Able to perform price break down for analysis\n\u00a0Knowledge in Multiple packaging materials, packaging structure design & packaging test, Flexo, Offset litho, screen printing technology, conventional and digital pre-press technologies, color management experience, green pack alternative will be an advantage\nStrong project management experience and organization skills\n\u00a0Responsible, patient, self-motivated, detailed minded, professional integrity and trustworthiness]\n\u00a0Familiar with European market\n\u00a0Good command of English on writing & speaking\nRequire travelling occasionally\n\n*Office location: Few minutes walk from Whampoa station\n\u00a0\n\n*Please send your resume with your current & expected salary. Information provided by applicants will be treated in strict confidence and will be used for recruitment purpose only.*", "employment_types": ["Full Time"], "selling_points": ["3 yrs\u2019 experience in packaging field", "Flexible working hours, 5 working days", "13 months' salary plus discretionary bonus"], "locations": ["Hung Hom"], "categories": ["Manufacturing", "Product Development / Management", "Printing", "Quality Assurance, Control & Testing / ISO"], "post_time": "2022-01-14T07:03:57Z", "salary": {"currency": null, "max": null, "min": null, "period": "monthly", "term": null}, "salary_visible": false, "title_keywords": ["engineer"], "responsibilities": ["management", "other duties", "guidelines", "review", "quality", "external parties", "maintain good communication", "inspection", "coordinate", "develop", "maintain", "executing", "safety standards", "liaise with", "plans", "planning"], "requirements": {"degrees": ["diploma or above"], "majors": ["related disciplines"], "languages": ["english"], "language_level": ["good command"], "hard_skills": ["project management", "analysis"], "soft_skills": ["self-motivated", "confidence", "responsible", "integrity", "project management", "organization skills", "patient", "detailed"], "languages_combined": [{"language": "english", "language_level": ["good command"]}]}, "experience_required": {"duration": ["at least 3 years"], "field": ["management", "related", "design", "project management", "digital"]}}, {"job_id": "100003009056215", "location_code": "hk", "company": "Dick's Sporting Goods International, Limited", "job_title": "Senior Merchandiser (Sportswear)", "description": "Can work and handle project independently\nSupport the Manger in merchandising coordination from development to production\nHandle product development, sample arrangement\nMaintain and update production records and system data\nCoordinate with overseas clients and China factory for orders processing\nAssist other duties and ad hoc duties as required\n\nRequirements\n\nDiploma\u00a0or above\nMin 5 years\u2019 merchandising experience from product development to order finished in household products in overseas market\n\nGood command in written & spoken English, Mandarin & Cantonese\nKnowledge of MS Office\nA good learner\nImmediate available / Short notice is preferred\n\n\u00a0Benefits\n\nFive-day week work\nPerformance bonus\n14 days annual leave\nBank holidays\nMedical Insurance\nInterested parties please apply with full resume and expected salary by email to\u00a0Apply Now", "employment_types": ["Full Time"], "selling_points": ["US Fortune 500 Company", "Competitive package", "Exposure with sporting goods is highly preferred"], "locations": ["Kowloon Bay"], "categories": ["Manufacturing", "Product Development / Management", "Merchandising & Purchasing", "Woven / Knit", "Procurement / Purchasing / Sourcing"], "post_time": "2022-01-18T03:33:48Z", "salary": {"currency": null, "max": null, "min": null, "period": "monthly", "term": null}, "salary_visible": false, "title_keywords": ["senior merchandiser"], "responsibilities": ["ad hoc duties", "other duties", "coordinate with", "merchandising", "system data", "maintain", "coordination"], "requirements": {"degrees": ["diploma or above"], "majors": [], "languages": ["cantonese", "english", "mandarin"], "language_level": ["good command"], "hard_skills": ["processing", "ms office"], "soft_skills": ["good learner", "independently", "coordination"], "languages_combined": [{"language": "cantonese", "language_level": ["good command"]}, {"language": "english", "language_level": ["good command"]}, {"language": "mandarin", "language_level": ["good command"]}]}, "experience_required": {"duration": ["min 5 years"], "field": ["product development", "merchandising"]}}, {"job_id": "100003009043083", "location_code": "hk", "company": "William E Connor & Associates Ltd", "job_title": "Product Development Manager - Jewelries & Accessories", "description": "Responsibilities:\n\nLead activities in fabric/sample development, costing package coordination, preliminary screening and order tracking;\nWork with vendors to establish costing plans and follow-up on fit/lab dip approval status and ensure vendors meet the product development timeline, price, and bulk quality standards;\nProficiency on doing the costing analysis and evaluate the cost breakdown correctly;\nWith solid experience to deal with offshore vendors and proactively to communicate with them for all sampling development & production follow up;\nIs accountable to follow up on all details on production to achieve on-time delivery targets;\nProactive in price negotiation and sourcing of suppliers to meet requirements;\nDeal with production issues in efficient & proactive manner and having problem solving skillset;\nPerform any ad-hoc tasks/projects as assigned by the superior.\n\n\u00a0Qualifications:\n\nDiploma or Degree in Merchandising or textile-related discipline is an advantage;\nAt least\u00a05 years relevant experience in a merchandising and/or sourcing environment, exposure with\u00a0sportswear is highly preferred;\nExperience in dealing with off-shore factories;\nKnowledge of the U.S. retail market is an advantage;\nProficient in MS office;\nGood communication, analytical and problem solving skills;\nGood command of written and\u00a0spoken English and Chinese, Mandarin preferred;\nWillingness to Travel.\n\nInterested parties, please click the 'APPLY NOW' button for application. All information received will be used for recruitment purposes only.", "employment_types": ["Full Time", "Permanent"], "selling_points": ["Attractive package with good career development", "Familiar with merchandising in jewelry products", "Fashion & Jewelry design, product development"], "locations": ["Kowloon Bay"], "categories": ["Manufacturing", "Jewelry", "Product Development / Management", "Merchandising & Purchasing", "Procurement / Purchasing / Sourcing"], "post_time": "2022-01-12T09:45:30Z", "salary": {"currency": null, "max": null, "min": null, "period": "monthly", "term": null}, "salary_visible": false, "title_keywords": ["product development manager"], "responsibilities": ["communicate with", "order tracking", "cost", "price negotiation", "ad-hoc tasks", "quality", "merchandising", "evaluate", "communication", "coordination", "costing analysis", "plans"], "requirements": {"degrees": ["diploma", "degree", "dip"], "majors": [], "languages": ["english", "chinese", "mandarin"], "language_level": ["good command"], "hard_skills": ["problem solving", "analysis", "problem solving skills", "ms office"], "soft_skills": ["efficient", "negotiation", "accountable", "problem solving", "communication", "analytical and problem solving skills", "coordination", "proactive", "superior"], "languages_combined": [{"language": "english", "language_level": ["good command"]}, {"language": "chinese", "language_level": ["good command"]}, {"language": "mandarin", "language_level": ["good command"]}]}, "experience_required": {"duration": ["at least 5 years"], "field": ["development", "relevant experience", "merchandising"]}}, {"job_id": "100003009044840", "location_code": "hk", "company": "Kin Yat Industrial Co Ltd", "job_title": "Assistant Manager - Product Compliance", "description": "Job Accountabilities\n\nResponsible for execution of jewelry product development briefs and assist in formulating product strategies.\nCommunicate with clients on their upcoming needs & wants\nCoordinate with related parties to ensure new products from design stage to launch are effectively monitored.\nCollaborate with design team to develop seasonal concepts for jewelry\nStrong in research and development to assist in identifying a continuous stream of commercially valuable new products.\nResponsible for the evaluation of product sales and generate necessary analytical reports accordingly.\nPrepare client portfolios for upcoming trends design\nReview sales performance and formulate incentive programs in time to enhance it.\nConduct in-depth research on similar products among competitors in order to implement effective sales strategies for achievement of sales target.\nOther duties as assigned.\n\nJob Requirements\nUniversity degree or equivalent, in jewelry design & supply chain\nMinimum 8 years relevant working experience of which at least 4 years at managerial level, experience in Merchandising especially in Jewelry & Accessories\nPrevious experience in handling clients & meeting their requests is a must\nSound knowledge and experience in cost calculation, quality control, and jewelry production process, and be able to balance design with commercial constraints.\nExperience working directly with factories in China with knowledge of vendor base\nHave a good product eye and jewelry and accessories knowledge; familiar with US market will be a huge plus\nFamiliar with research resources & channels\nFluency in both written and spoken Cantonese, English and Mandarin.\nExcellent presentation skills\nResponsible, detail-minded, flexible, good team player while be able to work independently, able to cope with deadline.\nImmediate available is highly preferable.\nConnor provides excellent career opportunities & attractive fringe benefits to the right candidate. Further information about Connor and our career opportunities can be viewed on our website\u00a0 www.weconnor.com.\u00a0 If you are interested in joining our team, please send your resume with current and expected remuneration packages to us\u00a0by MS Word attachment.\n\n\nConnor is an equal opportunities employer. Personal data provided by applicants will be used strictly for recruitment purposes only. Only short-listed candidates will be notified. Applicants who are not invited for an interview within 8 weeks may consider their applications filed for future reference.", "employment_types": ["Full Time", "Permanent"], "selling_points": [], "locations": ["Others - China"], "categories": ["Engineering", "Engineering Project Management", "Manufacturing", "Product Development / Management", "Quality Assurance, Control & Testing / ISO"], "post_time": "2022-01-13T18:55:03Z", "salary": {"currency": null, "max": null, "min": null, "period": "monthly", "term": null}, "salary_visible": false, "title_keywords": ["assistant manager"], "responsibilities": ["communicate with", "collaborate with", "cost", "production process", "other duties", "sales performance", "sales target", "review", "coordinate with", "merchandising", "design", "develop", "reports", "quality control", "evaluation"], "requirements": {"degrees": ["university degree"], "majors": ["design"], "languages": ["cantonese", "english", "mandarin"], "language_level": ["fluency"], "hard_skills": ["plus", "vendor"], "soft_skills": ["detail-minded", "flexible", "good team player", "work independently", "responsible", "presentation skills"], "languages_combined": [{"language": "cantonese", "language_level": ["fluency"]}, {"language": "english", "language_level": ["fluency"]}, {"language": "mandarin", "language_level": ["fluency"]}]}, "experience_required": {"duration": ["minimum 8 years", "at least 4 years"], "field": ["managerial", "merchandising", "relevant working experience", "design", "commercial", "quality control"]}}, {"job_id": "100003009055963", "location_code": "hk", "company": "FWD Life Insurance Company (Bermuda) Limited", "job_title": "Assistant, Product Development & Management", "description": "Product Compliance Assistant Manager is responsible for ensuring that the design of a product operates within existing safety standards of different worldwide countries (USA, EU, CCC, SAA and so on), and complies with those product safety regulations (UL/CB/CE/CCC), testing standards (EN/IEC60335, UL982/1082/1026/CSA/GS/BSMI/JIS /SAA etc.) and environmental standards (RoHS, REACH, TPCH, etc.).\nHe or she will be expected to work closely with Marketing, R&D and NPI on all new and existing projects to ensure the product approbation and material environmental and safety standards are being met at the start and before handing the project over to mass production (PP stage).\u00a0 The Product Compliance Assistant Manger will report to the QA Mangers & QA Director on project bases.\n\nWhat You Will Achieve\nMaintain all the latest international testing standards and regulator specifications and approbation standards for all major product categories such as: Medical, Appliances, Floor Cleaning, Toys, Packaging\nReview design brief from Marketing and provide input and any risk with regards to the product approbation (Material standards and Test standards), for the destined markets (countries)\nCascade the complied information to the R&D & Project teams for alignment. Ensure the samples ordered by Engineering through Purchasing or customer supplied material is verified and meets the intended product safety approbation standards\nAlign with both Compliance Engineer and Project Manager to resolve any issues, during the R&D or NPI stages\nResponsible to reach out to third party agencies for product rescans and to obtain quotation and lead time on the approbation\nTo manage and maintain a tracking log for all the material regulatory safety certificates or an official declaration letter of compliance from all the supplier. To Meet RoHS, REACH and other environmental standards\nTo endorse and provide supporting certificates that is compiled in the CAF (Component Approval Form), for all parties to approved\nAttend project meetings and provide updates and any issues that need resolving\nMonitor and improve current systems\nReport the compliance progress to the QA / QA Director accordingly\nEstablish and manage testing regimes to ensure new products are able to meet the required international safety standards\nWhat You Will Need\n\nBachelor\u2019s or master\u2019s degree in a relevant Engineering field and 1-2 years of experience\nHave in-depth knowledge in the approbation process and various international standard for different countries and product safety standards or certificates\u00a0 \u00a0\u00a0\nFamiliar and experience in working with 3rd party agencies and within R&D and NPI Engineering environment\nStrong leadership, interpersonal and problem-solving skills\nHave Quality Management System (QMS) auditing skills have advantages\nWilling to station in Shenzhen\n\nWe are an equal opportunity employer and welcome applications from all qualified candidates. Any interest candidate, please send your resume with expected salary and availability by clicking\u00a0\u201cApply Now\u201d.\n\n(Data collected will be treated as strictly confidential and will be used for recruitment purpose only and will be destroyed after the recruitment exercise when no longer required.)", "employment_types": ["Full Time"], "selling_points": ["Assist in the product development projects", "Preparation of the product literatures", "Perform testing of the illustration system"], "locations": ["Wan Chai"], "categories": ["Insurance", "Manufacturing", "Product Development / Management"], "post_time": "2022-01-18T03:08:08Z", "salary": {"currency": null, "max": null, "min": null, "period": "monthly", "term": null}, "salary_visible": false, "title_keywords": ["product development", "assistant"], "responsibilities": ["regulations", "data", "quotation", "quality", "design", "maintain", "product categories", "compliance", "teams", "monitor", "testing", "report", "management", "review", "specifications", "cleaning", "third party", "tracking", "systems", "recruitment", "safety standards", "auditing"], "requirements": {"degrees": ["degree", "bachelor", "master"], "majors": ["engineering"], "languages": [], "language_level": [], "hard_skills": ["r&d", "problem-solving skills", "no"], "soft_skills": ["problem-solving skills", "leadership", "interpersonal", "responsible"], "languages_combined": []}, "experience_required": {"duration": ["1-2 years"], "field": ["engineering"]}}, {"job_id": "100003009043382", "location_code": "hk", "company": "Toy Options (Far East) Ltd", "job_title": "Project Engineering Manager - Hard & Soft Toys", "description": "Established in Asia in 2013 with a trailblazer mentality, FWD is the primary insurance business of investment group, Pacific Century Group (PCG), with minority shareholders Swiss Re Group, GIC Ventures, RRJ Capital and Hopu Investments.\n\nFWD spans 10 markets in Asia including Hong Kong SAR & Macau SAR, Thailand, Indonesia, the Philippines, Singapore, Vietnam, Japan, Malaysia and Cambodia. In Hong Kong, FWD offers life and medical insurance, general insurance, employee benefits, and financial planning. We focus on creating fresh customer experiences and making the insurance journey simpler, faster and smoother, with innovative propositions and easy-to-understand products, supported by digital technology. Through this customer-led approach, FWD aims to be a leading pan-Asian insurer by changing the way people feel about insurance.\n\nIf you are looking for a company where can fuel your inspiration and cultivate your expertise, join us on our exciting journey.\n\nThe Job:\n\nAssist in the product development projects at the design, implementation and launch stages\nPreparation of the product literatures and communications to customers for the launch or maintenance of products\nPerform testing of the illustration system, analyze problem area and communicate with relevant parties for fixing\nAssist in ad-hoc projects and other duties as required\n\u00a0\n\nThe Person:\n\nUniversity graduates from all disciplines. Majoring in Mathematics, Statistics, Actuarial Science or related subjects is an advantage\nGood computer skills in MS office and Chinese word processing\nStrong attention to details and good time management skills\nPreferably with 1-2 years of working experience in the insurance or banking industry\nFresh graduates are also welcomed\n\nWe offer 5-day work, 20-22 days annual leaves, excellent learning & development opportunities and an attractive package to the right candidate.\n\nInformation collected will be treated in strict confidence and used solely for recruitment purpose. The company will retain all applications no longer than 24 months of which will be destroyed thereafter. When there are vacancies in any of our subsidiaries, holding companies, associated or affiliated companies of, or companies controlled by, or under common control with the Company during that period, we may transfer your application to them for consideration of employment. We are an equal opportunity employer. We do not discriminate on the basis of race, sex, disability or family status in employment process.", "employment_types": ["Full Time", "Permanent"], "selling_points": [], "locations": ["Tsim Sha Tsui"], "categories": ["Manufacturing", "Product Development / Management"], "post_time": "2022-01-12T11:15:53Z", "salary": {"currency": null, "max": null, "min": null, "period": "monthly", "term": null}, "salary_visible": false, "title_keywords": ["project engineering manager"], "responsibilities": [], "requirements": {"degrees": [], "majors": [], "languages": [], "language_level": [], "hard_skills": [], "soft_skills": [], "languages_combined": []}, "experience_required": {"duration": [], "field": []}}, {"job_id": "100003009051837", "location_code": "hk", "company": "LAWSGROUP", "job_title": "Factory Manager (Stationed in Overseas)", "description": "Requirements:\nBachelor Degree in Engineering - Mechanical / Electronic / Production; other fields also considered with strong related experience;\nMinimum 8 years experience in managing OEM product design and development, preferably in both Plush toys and Hard toys;\nFamiliar with EU Toys Safety Regulation is a must;\nExperience in featured mechanism / motorized plush toys is definitely an advantage;\nStrong project management skill, strong analytical mind on problem solving;\nGood command of written and spoken English is a must.\u00a0\u00a0\u00a0\u00a0\u00a0\u00a0\u00a0\u00a0\u00a0\nCandidates without Toys Engineering experience will NOT be considered.\n\u00a0Job Duties:\n\nCommunicate with UK R&D colleagues on a daily basis on new product development;\nNew product concept evaluation, feasibility studies;\nProduct Costing analysis;\nDevelopment from conceptual stage through to production with OEM manufacturers;\nOccasional travel to China\nInterested parties, please send full resume with expected salary, present salary and available date by clicking \"Apply Now\"\u00a0or email to \" hr.hk @ thecharacter.com \" for interview.\n(Personal data collected will be used for recruitment purpose only.)", "employment_types": ["Full Time", "Permanent"], "selling_points": ["Degree holder with 8 yrs relevant work exp.", "Solid exp. in garment manufacturing factory", "Stationed in Overseas is required"], "locations": ["Overseas"], "categories": ["Manufacturing", "Garment / Textile", "Manufacturing Management", "Product Development / Management"], "post_time": "2022-01-17T01:22:45Z", "salary": {"currency": null, "max": null, "min": null, "period": "monthly", "term": null}, "salary_visible": false, "title_keywords": ["factory manager"], "responsibilities": ["communicate with", "product concept", "costing analysis", "evaluation"], "requirements": {"degrees": ["degree", "bachelor"], "majors": ["engineering"], "languages": ["english"], "language_level": ["good command"], "hard_skills": ["problem solving", "project management"], "soft_skills": ["problem solving", "analytical mind", "project management skill"], "languages_combined": [{"language": "english", "language_level": ["good command"]}]}, "experience_required": {"duration": ["minimum 8 years"], "field": ["toys", "engineering", "related", "development", "product design"]}}, {"job_id": "100003009048033", "location_code": "hk", "company": "Hornby Hobbies Limited", "job_title": "Senior Engineer", "description": "\n\nTHE COMPANY :\nEuropean owned company\nWatch design, develop & trading company\nWe are composed of engineers and technical experts.\u00a0 We are able to develop new projects and products which fulfill clients\u2019 specifications and international standards.\nWe offer rapid prototyping and salesman samples that clients have just drawn or proposed for ODM and OEM products.\nMain market : US and European watch brands and clients\nWe are looking for\u00a0 SENIOR\u00a0PROJECT COORDINATOR\u00a0\u00a0- with details as follows :\u00a0\nTHE JOB :\u00a0\u00a0\nOver 3 years work experience in watch field\nExperience in project or clients follow up is a plus\nExperience in European or US watch companies or watch brands is a plus\nProficient in English & Chinese; Mandarin is a plus\nReport to the Senior Project Manager\nParticipate in project management for assigned watch brands/projects\u00a0\nCoordinate with clients for project management details\nCollaborate with Design team of the developing product;\nLiaise and negotiate with suppliers regarding structure and possibility of Products;\nEnsure the product schedule on time;\nEnsure the products' structure and appearance match requirements\nMonitor the progress rate of each ongoing project;\nNo trips is required\n5 days work\n13 months salary + performance bonus\nAnnual leave : 14 days\nMedical benefits\nMore solid experience will be considered as\u00a0 Assistant Project Manager (2 posts)\nTO APPLY for this job or similar jobs :\n\u00a0\nFor secure and confidential job application, please click the below link to get our email address.\u00a0\nhttp://jpc.hk/confidential_apply.htm\u00a0\nWe provide free job hunting services to job seekers.\nTo speed up our process, please do NOT send us download links.\nPersonal data provided by job applicants will be used for recruitment purpose only.\nYour privacy is guaranteed. We will never give out, lease, or sell your personal information.\nJPC Recruiting Services was established in 1990.\u00a0\nhttp://www.facebook.com/pages/JPC-Texson-Ltd/500356593325952\n\u00a0", "employment_types": ["Full Time", "Permanent"], "selling_points": ["engineering", "Scalextric", "project management"], "locations": ["Kowloon Bay"], "categories": ["Manufacturing", "Product Development / Management"], "post_time": "2022-01-14T04:33:42Z", "salary": {"currency": null, "max": null, "min": null, "period": "monthly", "term": null}, "salary_visible": false, "title_keywords": ["senior engineer"], "responsibilities": ["specifications", "design", "develop"], "requirements": {"degrees": [], "majors": [], "languages": [], "language_level": [], "hard_skills": [], "soft_skills": [], "languages_combined": []}, "experience_required": {"duration": [], "field": []}}, {"job_id": "100003009047120", "location_code": "hk", "company": "Longshore Ltd", "job_title": "Senior Merchandiser / Merchandiser - Toys", "description": "Responsibilities:\n\nHandle and Coordinate Plastic & Paper product development cycle (including board games & puzzles) with factory\nResponsible in\u00a0managing suppliers, product development schedule,\u00a0costing comparison & calculation, sourcing material and vendors.\nFollow-up orders with factory, customers and internal parties to ensure customer satisfaction and on-time delivery\nHandle ad-hoc assignments as required\n\nRequirements:\n\nForm 7 or above\n3 years experiences in\u00a0OEM/ODM Plastic & Paper products (Experiences in Board game, Puzzle are preferred)\nStrong with plastic paper development cycle / schedule\u00a0is a definite advantage\nGood in English and good in PC/ERP knowledge\nExcellent communication skills with overseas customers and vendors are essential\nDetail-minded, well-organized, responsible and can work independently\nImmediately available is preferred\n\nAlternate Saturday, Double pay, Medical, Annual leave, Bonus\n\nWe offer attractive remuneration packages and excellent career opportunities. Interested parties please send resume states clearly expected salary by \"Apply Now\"", "employment_types": ["Full Time", "Permanent"], "selling_points": ["Whole merchandising procedure", "Excellent career prospect", "Immediate Available is preferred"], "locations": ["Hung Hom"], "categories": ["Manufacturing", "Product Development / Management", "Merchandising & Purchasing", "Electronics", "Toy"], "post_time": "2022-01-14T02:22:51Z", "salary": {"currency": null, "max": null, "min": null, "period": "monthly", "term": null}, "salary_visible": false, "title_keywords": ["merchandiser", "senior merchandiser"], "responsibilities": ["coordinate", "ad-hoc assignments", "schedule", "internal parties"], "requirements": {"degrees": [], "majors": [], "languages": ["english"], "language_level": ["good"], "hard_skills": ["pc", "erp"], "soft_skills": ["detail-minded", "communication skills", "work independently", "responsible", "well-organized"], "languages_combined": [{"language": "english", "language_level": ["good", "good"]}]}, "experience_required": {"duration": ["3 years"], "field": []}}, {"job_id": "100003009042384", "location_code": "hk", "company": "Plover Bay Technologies Limited", "job_title": "Senior Project Engineer", "description": "Join Plover Bay and become a part of this fast growing and energetic team! Plover Bay creates innovative networking technologies and solutions with customers in 70 countries. If you are a team player, creative, tech savvy and passionate, join our team and challenge yourself.\n\nMajor Responsibilities:\n\n\nAssist project management on maintain project plans and schedules\nProject documentation management, e.g. product/system design specification, schedule, meeting minutes, weekly project status update, etc.\nAssist the team on various ad-hoc projects as assigned\nRequirement:\n\n\nBachelor\u2019s degree in Electronics Engineering discipline is preferred\n3-5 years of experience with engineering equipment development is\u00a0preferable\nFluent in spoken and written English, Chinese and Mandarin\nAnalytical and problem-solving ability\nStrong interpersonal skills, with the ability to build positive working relationships with diverse teams\nBenefits:\n2-month discretionary bonus\nStock Options plan\n12-16 days annual leave\nFlexible working hours\nFive-day work\nJob\u00a0satisfaction is a key focus of the company culture\nExcellent career path in a fast growing technology company with global market\nWe offer challenging job opportunities, 5 days work, flexible working hours and attractive benefit to the right candidates. Please send your resume, present and expected salary\u00a0to\u00a0hr\u200b@ploverbay.com\n\nPersonal data collected will be treated in the strictest confidence and will only be used for employment-related purpose", "employment_types": ["Full Time", "Permanent"], "selling_points": ["5 days work, 2-month discretionary bonus", "Bachelor\u2019s degree in Electronics Engineering", "3+ exp. with engineering equipment development"], "locations": ["Lai Chi Kok"], "categories": ["Engineering", "Electrical / Electronics", "Engineering Project Management", "Manufacturing", "Product Development / Management"], "post_time": "2022-01-12T07:15:40Z", "salary": {"currency": null, "max": null, "min": null, "period": "monthly", "term": null}, "salary_visible": false, "title_keywords": ["senior project engineer"], "responsibilities": ["management", "schedules", "project management", "maintain", "system design", "schedule", "plans", "ad-hoc projects", "project documentation"], "requirements": {"degrees": ["degree", "bachelor"], "majors": ["engineering"], "languages": ["english", "chinese", "mandarin"], "language_level": ["fluent"], "hard_skills": ["problem-solving"], "soft_skills": ["diverse", "problem-solving", "interpersonal skills", "positive"], "languages_combined": [{"language": "english", "language_level": ["fluent"]}, {"language": "chinese", "language_level": ["fluent"]}, {"language": "mandarin", "language_level": ["fluent"]}]}, "experience_required": {"duration": ["3-5 years"], "field": ["development", "engineering"]}}, {"job_id": "100003009039195", "location_code": "hk", "company": "Ampd Energy Limited", "job_title": "Product Manager", "description": "Summary of the Position\n\nWe are seeking a talented and passionate Product Manager to support our rapidly growing team. Our products enable construction companies to eliminate the need for diesel and drive the transition toward fully electrified construction sites. Our engineering process is complex and involves elements of electronics, power electronics, high power systems, mechanical engineering, software, IoT, testing, all the way from the design stage to production deployment. Being part of a small, fast-moving team, this role will have a wide scope and there is lots of room to develop and learn.\n\nYou should be motivated, reliable, thorough, and excited about being among the first in the world to work with game-changing products. You will be expected to be able to operate with a degree of autonomy and be a clear, candid, and effective communicator in both spoken and written English.\n\nKnowledge, Qualifications and Skills\n\nBachelor\u2019s or Master\u2019s degree in Engineering or MBA, or equivalent in experience\n3+ years of experience in product management, product development and in shipping quality products that had customer impact with evidence of exceptional ability\nStrong ability to communicate, build relationship and influence others inside and outside the company.\nExperience in business case development and market and competitor analysis is a bonus.\nProven history of converting learnings from customer insights into tangible product features that customers like.\nAbility to successfully work cross functionally with people from engineering, design, business development, and others.\nGood understanding and working experience in technology development best practices and product management technologies.\nSolid product sense with the ability to understand product architecture.\nA passion for improving our environment.\nPermitted to work in Hong Kong.\n\nResponsibilities\n\nDrive and manage cross-functional Product Development. Contribute to the successful implementation and life cycle management of one or more products.\nInterface with all the stakeholders, inside and outside the organization to collect, analyse, and prioritize market requirements for a product.\nDefine and implement a product vision and product roadmap together with the Engineering team.\nMonitor market, competition, and technology trends closely, share knowledge and insights. Identify new product opportunities, as well as product improvement local environmental regulations.\nDefine a set of KPIs to measure business impact and utilize them in the decision-making processes.\nPrioritize between existing versus new customers, and between features, architectural improvements and operational excellence.\n\nHow to apply\n\nPlease submit your application via\u00a0https://www.linkedin.com/jobs/view/2874416036.\u00a0\n\nAll information provided will be treated in strict confidence and used solely for recruitment purposes. We regret that we are only able to notify short-listed candidates.\n\nAmpd Energy is an equal opportunity employer. All candidates will be assessed on merit without regard to age, race, gender, sexual orientation, religion, nationality, marital status, political affiliation or any other factor protected by law.", "employment_types": ["Full Time", "Permanent"], "selling_points": ["Rapidly Growing Startup Environment", "3+ Years of Experience in Product Management", "A Passion for Improving Our Environment"], "locations": ["Lai Chi Kok"], "categories": ["Engineering", "Electrical / Electronics", "Engineering Project Management", "Manufacturing", "Product Development / Management"], "post_time": "2022-01-11T08:58:17Z", "salary": {"currency": null, "max": null, "min": null, "period": "monthly", "term": null}, "salary_visible": false, "title_keywords": ["product manager"], "responsibilities": ["regulations", "management", "shipping", "software", "analysis", "systems", "quality", "customer insights", "design", "develop", "testing", "implementation", "monitor", "recruitment", "kpis", "architecture", "analyse"], "requirements": {"degrees": ["degree", "bachelor", "master"], "majors": ["engineering"], "languages": ["english"], "language_level": [], "hard_skills": ["small", "analysis", "factor", "deployment", "local environmental regulations"], "soft_skills": ["passionate", "confidence", "passion for", "prioritize", "clear", "motivated", "thorough", "communicator", "reliable"], "languages_combined": [{"language": "english", "language_level": []}]}, "experience_required": {"duration": ["3+ years"], "field": ["engineering", "development", "product management", "business", "product development"]}}, {"job_id": "100003009050481", "location_code": "hk", "company": "Arnhold & Co Ltd", "job_title": "Brand Executive", "description": "Position Summary:\n\nSupports the Branding and Exports Manager to grow company owned brand business, handles supplier sourcing and evaluation in assigned product categories, negotiate best prices, develop most appropriate packaging and ensure on-time shipment deliveries. \u00a0\n\nPrincipal Accountabilities:\n\n\nImplementing sanitary ware product sourcing strategies to support brand development\nDevelop, establish and cultivate vendor partnerships to meet current and future needs\nSelect, evaluate and manage suppliers to meet the company\u2019s price and quality standards\nWork with multiple suppliers for quotations in sanitary ware product categories review suppliers\u2019 strength, support and cooperation and determine reasonable quotations\nEvaluate factory to ensure that they can meet company clients\u2019 requirements as it relates to production output, packaging, quality and lead time\nManage pricing to secure the lowest cost options through effective negotiation and value improvement initiatives\nManage product execution from concept to delivery of quality product, in collaboration with Product Development, Sales & Marketing and Quality teams\nPrepare purchase orders and contract agreements, review packaging, follow up production and sample status with suppliers to ensure on-time deliveries\n\nQualifications and Experience:\n\nExperience:\n\n\n3+ years\u2019 in sourcing, supply chain or sales administration in relevant industry\nExperience in handling sales inquiries and providing customer after-sales services\nKnowledge of manufacturing process and sourcing practices / procedures\nKnowledge of global supplier base and supplier development experience\nExperience in sourcing bathroom products (ceramic and metal)\nDesire to developing a career in sourcing and branding\n\nEducation:\n\n\nBachelor\u2019s Degree in Business Administration, Supply Chain or related discipline\n\nSkills:\n\n\nGood presentation, interpersonal, organizing and communication\u00a0skills\nHighly self-motivated, able to work independently, responsible and reliable\nStrong negotiator and be able to achieve successful win-win negotiations\nStrong communication skills with fluency in Mandarin and predominate local language(s)\nGood computer operating skills, especially in MS Office\nAble to handle multi-tasks and work under pressure in a dynamic environment\nA team player\n\nWhat we offer?\n\nAttractive remuneration packages include variable bonus, retirement benefits with an option of ORSO and MPF and insurance scheme(s)\u00a0\nGood career prospects\n5-day work week\nBirthday Leave\nStaff Living Room\n\nInterested parties please send your resume together with your expected salary and date of availability to Human Resources Department via email by clicking \"Apply Now\".\n\n\nFor further information, please visit our company website: www.arnhold.com.hk\n\n(Personal data provided by job applicants will be used strictly in accordance with our personal data policy and guidelines which is available upon request. All related information will be retained for a maximum period of 6 months and all personal data will be destroyed afterwards.)", "employment_types": ["Full Time", "Permanent"], "selling_points": ["Good working environment", "5-day work with comprehensive fringe benefits", "We are the market leader and trendsetter"], "locations": ["North Point"], "categories": ["Manufacturing", "Product Development / Management", "Merchandising & Purchasing", "Procurement / Purchasing / Sourcing"], "post_time": "2022-01-14T10:29:26Z", "salary": {"currency": null, "max": null, "min": null, "period": "monthly", "term": null}, "salary_visible": false, "title_keywords": ["executive"], "responsibilities": ["product categories", "sales administration", "cost", "work under pressure", "review", "quality", "from concept to delivery", "teams", "develop", "evaluate", "procedures", "purchase", "developing", "communication", "evaluation", "administration"], "requirements": {"degrees": ["degree", "bachelor"], "majors": ["business administration"], "languages": ["mandarin"], "language_level": ["fluency"], "hard_skills": ["dynamic", "vendor", "ms office"], "soft_skills": ["communication skills", "self-motivated", "work independently", "dynamic environment", "negotiation", "responsible", "multi-tasks", "reliable", "team player", "interpersonal", "presentation", "work under pressure"], "languages_combined": [{"language": "mandarin", "language_level": ["fluency"]}]}, "experience_required": {"duration": [], "field": ["development"]}}, {"job_id": "100003009048554", "location_code": "hk", "company": "Tai Hing Zipper Factory Company Limited", "job_title": "SALES COORDINATOR", "description": "Benefit :\n\nMonthly Commission (Average 2K to 10K or above per month)\nGuarantee double pay\nAnnual bonus (Average 1-2 months of salary, subject to performance)\n\nJob Responsibilities:\n\nHandle customer enquiries\nProvide sales administration support to the sales team\nCoordinate with internal departments and factories for order processing and shipment arrangements\nHandle product development\n\nRequirements:\n\nForm 7 graduates or relevant certificate\n1 year relevant working experience\nGood interpersonal and communication skills in Chinese, English & Mandarin\nWell-organised, independent, and self motivated\nStrong PC skills\nImmediate available highly preferred\n\nWorking day: 5 days work\u00a0and Bank Holiday\n\n***All application email must be quote \"\u00a0Sales Coordinator\u00a0\" only on the subject line.\n\nInterested parties, please e-mail your resume with\u00a0EXPECTED SALARY\u00a0by clicking \"Apply Now\", or mail to TH Zipper Factory Company Ltd., Room 3003, 30/F, Enterprise Square Three, 39 Wang Chiu Road, Kowloon Bay, H.K\n\nAll information received will be kept in strict confidence and only for employment-related purposes.", "employment_types": ["Full Time", "Permanent"], "selling_points": [], "locations": ["Kowloon Bay"], "categories": ["Sales, CS & Business Devpt", "Customer Service - Supervisor / Officer", "Transportation & Logistics", "Documentary Credit / Bills Processing", "Manufacturing", "Product Development / Management"], "post_time": "2022-01-14T06:46:53Z", "salary": {"currency": null, "max": null, "min": null, "period": "monthly", "term": null}, "salary_visible": false, "title_keywords": ["sales coordinator"], "responsibilities": [], "requirements": {"degrees": [], "majors": [], "languages": [], "language_level": [], "hard_skills": [], "soft_skills": [], "languages_combined": []}, "experience_required": {"duration": [], "field": []}}, {"job_id": "100003009050450", "location_code": "hk", "company": "Links International", "job_title": "Sourcing Manager - Homeware & Kitchenware", "description": "Sourcing Manager - Houseware & Kitchenware\n\nOur client is a local trading company, looking for a Sourcing Manager to join their organisation.\n\nYour focus will be:\n\n\nSourcing, dealing with current suppliers, negotiate the right price and quality.\nProject coordination with our team and direct with our customers.\nCalculating cost pricing and arranging shipments.\nWork with other functional teams and manage the merchandising team for business migration from client's current operation to the company.\nFull ownership of the whole supply chain from factory sourcing, development till shipment with in-depth technical knowledge, proactive on problem precaution & strong decision maker.\nSearch new potential suppliers, having the desire to build up a network of suppliers within the packaging area, and a high level of service.\nDevelop a close relationship with existing suppliers and develop new suppliers through personal connections, trade fairs and sourcing trips\n\nYour profile and Experience:\n\n\nDiploma or above or related disciplines\nSelf-motivated and have strong sense of responsibility.\nPrevious experience in handling tabletop / kitchenware will be a plus. General hardgoods experience is a must.\nAble to perform price break down for analysis\nStrong project management experience and organization skills\nResponsible, patient, self-motivated, detailed minded, professional integrity and trustworthiness\nFamiliar with European / US market\nWilling to travel to China frequently\nGood command of English on writing & speaking", "employment_types": ["Full Time", "Permanent"], "selling_points": ["Solid exp. in houseware & kitchenware sourcing", "Work with wholesale / distributor clients", "18days AL, Double Pay + Bonus"], "locations": ["Others - China"], "categories": ["Manufacturing", "Manufacturing Management", "Product Development / Management"], "post_time": "2022-01-14T10:27:06Z", "salary": {"currency": "HKD", "max": 44999, "min": 30000, "period": "monthly", "term": null}, "salary_visible": true, "title_keywords": ["sourcing manager"], "responsibilities": ["cost", "project coordination", "analysis", "merchandising", "quality", "teams", "develop", "project management", "migration"], "requirements": {"degrees": ["diploma or above"], "majors": ["related disciplines"], "languages": ["english"], "language_level": ["good command"], "hard_skills": ["project management", "focus", "analysis", "plus"], "soft_skills": ["self-motivated", "responsible", "sense of responsibility", "integrity", "project management", "coordination", "organisation", "organization skills", "patient", "focus", "proactive", "detailed"], "languages_combined": [{"language": "english", "language_level": ["good command"]}]}, "experience_required": {"duration": [], "field": ["project management"]}}, {"job_id": "100003009041993", "location_code": "hk", "company": "Pearson Education Asia Limited", "job_title": "Assistant Project Management Manager", "description": "We create. We innovate. We reinvent.\u00a0\n\nWe are the world\u2019s leading learning company, with more than 22,500 employees working together to provide\u00a0high-quality\u00a0educational content and learning experiences, as well as assessments and qualifications to nearly 200 countries. We help people build their skills and grow with the world around them.\n\nWith an obsession to best support educators and learners worldwide, we never stop\u00a0perfecting\u00a0our educational products and services.\n\nWe now invite applications from passionate individuals to join the Pearson family:\n\nMain Responsibilities\n\n\nUnder direction of Manager, create budgets and plans resources for projects using both internal Project Support resources and external vendors\nDelegate work to internal Project Support team or external vendors as appropriate\nResponsible for creating and maintaining schedules for specific projects\nSchedule and track progress for specific projects with the support of internal Project Management & Support team\nEnsure all tracking systems are maintained and used effectively by the whole project team\nMonitor the on time delivery and distribution of assets for specific projects with the support of internal Project Support team\nResponsible for outsourcing and vendor contacts, including preparation of necessary agreements and processing of payments\nEnsure all content is developed and delivered in agreed formats/industrial standards, working with global teams and outside vendors as necessary\nProvide agreed communications and prepare reports for the project team\nMonitor all financial stages and controls, reporting regularly on financial status and forecasts for assigned projects to Department head and project team leads\nChampion for new tools and processes, coordinate with global and local teams as well as organize necessary training to ensure smooth and effective application\nJob Requirements\nUniversity/College degree in related subjects with relevant project management experience\nSelf-motivated, detailed-oriented and able to manage multiple projects under tight timeline\nA team player and able to work independently with good problem solving skills\nGood communication skills and proficient in written English and Chinese\nFluent and effective spoken English, Cantonese and Putonghua\n\nA competitive package including 5-day work, medical and dental benefits will also be offered to the right candidate.\n\nInterested parties may submit your\u00a0full resume via Apply Now.\n\nAll personal data provided will be treated in strict confidence and be used for recruitment purposes within the Pearson Group only. Information on unsuccessful candidates will be destroyed within 2 years.", "employment_types": ["Full Time", "Permanent"], "selling_points": ["5 days work", "13 months salary, performance bonus", "Flexible working hours"], "locations": ["Quarry Bay"], "categories": ["Media & Advertising", "Production", "Education", "Others", "Manufacturing", "Product Development / Management"], "post_time": "2022-01-12T05:01:22Z", "salary": {"currency": null, "max": null, "min": null, "period": "monthly", "term": null}, "salary_visible": false, "title_keywords": ["manager", "assistant"], "responsibilities": ["budgets", "reporting", "maintaining", "schedules", "systems", "monitor", "teams", "coordinate with", "project management", "payments", "schedule", "prepare reports", "plans", "tracking"], "requirements": {"degrees": ["degree"], "majors": ["project management"], "languages": ["cantonese", "putonghua", "english", "chinese"], "language_level": ["fluent", "proficient", "good"], "hard_skills": ["project management", "problem solving skills"], "soft_skills": ["communication skills", "self-motivated", "work independently", "project management", "problem solving skills", "team player", "detailed"], "languages_combined": [{"language": "cantonese", "language_level": ["fluent"]}, {"language": "putonghua", "language_level": ["fluent"]}, {"language": "english", "language_level": ["fluent", "proficient", "good"]}, {"language": "chinese", "language_level": ["proficient", "good"]}]}, "experience_required": {"duration": [], "field": ["related", "project management"]}}, {"job_id": "100003009047876", "location_code": "hk", "company": "Wright Life Pharmaceutical Limited", "job_title": "Merchandiser", "description": "\u8077\u4f4d\u8077\u8cac:\n\n\u8ca0\u8cacODM/OEM\u9805\u76ee\uff0c\u7368\u7acb\u8ddf\u9032\u6574\u500b\u6d41\u7a0b\n\u8a2d\u8a08\u53ca\u751f\u7522\u9032\u5ea6\u63a7\u5236\uff0c\u78ba\u4fdd\u7522\u54c1\u8cea\u91cf\n\u8ddf\u9032\u5ba2\u6236\u53ca\u4f9b\u61c9\u5546\u8a02\u55ae\uff0c\u8207\u5ba2\u6236\u4fdd\u6301\u826f\u597d\u95dc\u4fc2\n\u8655\u7406\u5831\u50f9\u548c\u767c\u7968\uff0c\u7269\u6d41\u5b89\u6392\n\u8077\u4f4d\u8981\u6c42:\n\n\u4e2d\u4e94\u6216\u4ee5\u4e0a\u7a0b\u5ea6\n3\u5e74\u6216\u4ee5\u4e0aODM/OEM\u9805\u76ee\u5de5\u4f5c\u7d93\u9a57\uff0c\u5177\u4fdd\u5065\u98df\u54c1\u6216\u4e2d\u6210\u85e5\u7d93\u9a57\u8005\u512a\u5148\u8003\u616e\n\u826f\u597d\u7cb5\u8a9e\u3001\u826f\u597d\u666e\u901a\u8a71\u53ca\u826f\u597d\u82f1\u8a9e\n\u5177\u6709\u57fa\u672c\u96fb\u8166\u64cd\u4f5c\u77e5\u8b58\uff0cMicrosoft Office\u53ca\u61c2\u5009\u9821/\u901f\u6210\u8f38\u5165\u6cd5\n\u826f\u597d\u6e9d\u901a\u6280\u5de7\u3001\u7d30\u5fc3\u53ca\u5177\u7d44\u7e54\u529b\n\u7d93\u9a57\u8f03\u5c11\u8005\u53ef\u8003\u616e\u70ba\u8ddf\u55ae\u6587\u54e1", "employment_types": ["Full Time"], "selling_points": ["5\u5929\u5de5\u4f5c+\u9280\u884c\u5047\u671f+\u96d9\u7ce7", "\u8ddf\u9032OEM\u53caODM\u5ba2\u6236\u53ca\u4f9b\u61c9\u5546\u8a02\u55ae", "\u5177\u4fdd\u5065\u98df\u54c1\u6216\u4e2d\u6210\u85e5\u7d93\u9a57\u8005\u512a\u5148"], "locations": ["Tsuen Wan Area"], "categories": ["Manufacturing", "Product Development / Management", "Production Planning / Control", "Merchandising & Purchasing", "Others"], "post_time": "2022-01-14T10:06:27Z", "salary": {"currency": null, "max": null, "min": null, "period": "monthly", "term": null}, "salary_visible": false, "title_keywords": ["merchandiser"], "responsibilities": [], "requirements": {"degrees": [], "majors": [], "languages": [], "language_level": [], "hard_skills": [], "soft_skills": [], "languages_combined": []}, "experience_required": {"duration": [], "field": []}}, {"job_id": "100003009046864", "location_code": "hk", "company": "Cloud Light Technology Limited", "job_title": "Technical Program Manager (Job Ref. Apply-HK-2107-TPM)", "description": "Responsibilities:\n\n\nSuccessful candidates will join Hong Kong-based optical product development team and lead development of high-speed fiber-optic transceiver and optical sensor products\nPlanning and managing new product development projects from conception through transfer to manufacturing, including management of the product development process, time-integrated planning for qualification and customer sampling, and transfer to production\nDefine new product architecture and technology / process requirements\nWork with a cross-disciplinary team including engineering design, product verification and test, operations, and sales & marketing to deliver a quality product\nDrive project execution to meet development milestones, schedule, and budget\nRequirement:\nMaster or PhD with > 2 years of related product development experience\nPreferred field(s) of study: Electrical or Mechanical Engineering, Physics, Applied Physics, Optical Engineering or equivalent\nFamiliar with fiber-optic communications, optoelectronics packaging or related disciplines\nCandidate with previous experience in managing new technology development projects and government funded projects are preferred\nStrong organization, leadership, and analytical skills\nExcellent interpersonal and communication skills\nFluent in English and Mandarin\nSelf-motivated, creative, innovative, and responsible\n\nApplication:\n\n\u00a0To apply, please email us\u00a0your resume, your availability to report duty and quote the Job Ref.\nOnly short-listed candidates will be notified. Personal data provided by applicants will be used for consideration of an application only.\n\nApplication Deadline:\n\nUntil this position is filled\nResumes received will strictly be used for recruitment-related purpose", "employment_types": ["Full Time", "Permanent"], "selling_points": ["Optical product development", "Transfer to Manufacturing", "Optoelectronics Packaging"], "locations": ["Shatin Area"], "categories": ["Engineering", "Electrical / Electronics", "Engineering Project Management", "Manufacturing", "Product Development / Management"], "post_time": "2022-01-14T01:29:31Z", "salary": {"currency": null, "max": null, "min": null, "period": "monthly", "term": null}, "salary_visible": false, "title_keywords": ["technical program manager"], "responsibilities": ["management", "engineering design", "operations", "budget", "quality", "schedule", "architecture", "planning"], "requirements": {"degrees": ["master"], "majors": [], "languages": ["english", "mandarin"], "language_level": ["fluent"], "hard_skills": ["analytical skills"], "soft_skills": ["communication skills", "self-motivated", "responsible", "analytical skills", "innovative", "creative", "leadership", "interpersonal"], "languages_combined": [{"language": "english", "language_level": ["fluent"]}, {"language": "mandarin", "language_level": ["fluent"]}]}, "experience_required": {"duration": ["2 years"], "field": ["related", "product development", "development projects"]}}, {"job_id": "100003009048268", "location_code": "hk", "company": "Kingsway Personnel Ltd", "job_title": "Japanese Speaking QA Assistant (Trading company) ~22K", "description": "Employer Ref: NR09467\nNature of Business: Japan based Trading Company\u00a0\u00a0\nWorking Days: 5 Days\nWorking Location: Tsing Yi Area\n\nBenefits:\n- Double pay\n- Discretionary Bonus\n- Transportation Allowance\n- OT Allowance\n- Attendance Allowance\n- Medical insurance\n\nRequirements:\n- Degree in Science related discipline (e.g.: Chemical / Medical / Biological) preferred\n- Min. 3yrs working exp., B to B business, FMCG products preferred\n- Business level in of Japanese and English\n\nDuties:\n- Handle QA duties for Consumer products\n- Assist in new product development\n\nInterested in the above vacancy?\u00a0 Send your resume to us NOW!\nOnly short-listed candidates will be notified. Personal data collected will be used for recruitment purpose only", "employment_types": ["Full Time", "Permanent"], "selling_points": ["Business level in Japanese and English Speaking", "Degree in Science related discipline", "~22K, double pay, bonus, transportation fee"], "locations": ["Tsing Yi"], "categories": ["Manufacturing", "Product Development / Management", "Quality Assurance, Control & Testing / ISO"], "post_time": "2022-01-16T21:50:20Z", "salary": {"currency": null, "max": null, "min": null, "period": "monthly", "term": null}, "salary_visible": false, "title_keywords": ["japanese speaking qa assistant"], "responsibilities": [], "requirements": {"degrees": [], "majors": [], "languages": [], "language_level": [], "hard_skills": [], "soft_skills": [], "languages_combined": []}, "experience_required": {"duration": [], "field": []}}, {"job_id": "100003009042091", "location_code": "hk", "company": "Green Paper Power Limited", "job_title": "Project Manager / Project Executive", "description": "Green Power Paper Limited Hong Kong (GPP HK),\u00a0an expert in Retail Window Display and Packaging production. In order to cope with our needs for business growth, we are looking for qualified candidate for the following position.\n\nResponsibilities\n\nTo report to the director and works toward ensuring a smooth business environment with the focus of optimal sales and marketing performance.\nTo work closely with the team to oversee daily business operations\nTo communicate with production support team and factories on capacity planning and order follow up.\nTo liaise with different parties to improve performance and work efficiency\nTo monitor sales orders and supplier relations\nTo attending to any correspondence and emails by customers, clients and contractors\n\nRequirements\n\n\nHigher Diploma or above with minimum 5 years experience in account servicing and project management in packaging and window display production; candidate with less experience will be considered as Project Executive.\nKnowledge of the industry and market trends\nGood project and time management control\nExcellent verbal (English & Putonghua) and written communication skills (English)\nProficiency in Microsoft Office applications\nKnowledge of Photoshop or Accounting is an advantage.\u00a0\u00a0\nAn eye for attention to detail\nAbility to work effectively in a fast-paced environment\nSolid customer service experience is preferable\nImmediately available is highly preferred\n\nWe offer 5-day-work and friendly working environment. Interested candidates please send your full resume and expected salary to us. If you're hard working and dedicated, apply today!\n\nTo apply online please click the Apply button below.", "employment_types": ["Full Time"], "selling_points": ["Good Project and Time Management Control", "Solid Account Servicing Experience", "Strong Organization Skills and Proactive"], "locations": ["Kwun Tong"], "categories": ["Manufacturing", "Product Development / Management", "Merchandising & Purchasing", "Others", "Sales, CS & Business Devpt", "Account Servicing"], "post_time": "2022-01-12T06:03:23Z", "salary": {"currency": null, "max": null, "min": null, "period": "monthly", "term": null}, "salary_visible": false, "title_keywords": ["project manager", "project executive"], "responsibilities": ["communicate with", "operations", "monitor", "liaise with", "report", "planning"], "requirements": {"degrees": ["higher diploma or above"], "majors": ["project management"], "languages": ["putonghua", "english"], "language_level": ["excellent"], "hard_skills": ["project management", "photoshop", "microsoft office"], "soft_skills": ["work effectively", "communication skills", "fast-paced environment", "project management", "customer service", "attention to detail", "time management"], "languages_combined": [{"language": "putonghua", "language_level": ["excellent"]}, {"language": "english", "language_level": ["excellent"]}]}, "experience_required": {"duration": ["minimum 5 years"], "field": ["project management", "customer service", "account servicing"]}}, {"job_id": "100003009043160", "location_code": "hk", "company": "Luxury Timepieces And Accessories Limited", "job_title": "Product Development Assistant (Watch)", "description": "\n\nWork with teams for the whole product development process for each season which includes product range development, target ex-factory price\nNegotiate and plan the ex-factory product cost, production and delivery schedules with contact manufacturers in accordance with the brand\u2019s marketing and sales programs\nCommunicate with vendors concerning Tech Packages and aesthetics to ensure alignment on development expectations\nProvide clerical and administrative support on daily operation of product development department\n\n\n\nRequirements:\n\nDiploma of Vocational Education (Watch and Clock) or equivalent\nWatch manufacturing knowledge, working experience in watch product development is an ADVANTAGE\nExcellent attention to details\nAbility to prioritize and meet essential deadlines\nGood written and verbal communication skills in English and Mandarin\n\n\n\nWe offer 5-day work and attractive package to the right candidate.\u00a0 Interested persons please send your full resume with expected salary and date available by clicking \u201cAPPLY NOW\".\n\n\n\n\n*personal data collected will be used for recruitment purpose only*", "employment_types": ["Full Time"], "selling_points": [], "locations": ["Kwun Tong"], "categories": ["Manufacturing", "Product Development / Management"], "post_time": "2022-01-12T09:58:46Z", "salary": {"currency": null, "max": null, "min": null, "period": "monthly", "term": null}, "salary_visible": false, "title_keywords": ["product development assistant"], "responsibilities": ["communicate with", "cost", "administrative support", "schedules", "teams", "daily operation", "communication", "contact", "plan"], "requirements": {"degrees": ["diploma"], "majors": [], "languages": ["english", "mandarin"], "language_level": ["good"], "hard_skills": [], "soft_skills": ["communication skills", "prioritize", "attention to details"], "languages_combined": [{"language": "english", "language_level": ["good"]}, {"language": "mandarin", "language_level": ["good"]}]}, "experience_required": {"duration": [], "field": ["product development", "manufacturing"]}}, {"job_id": "100003009050238", "location_code": "hk", "company": "Saint Honore Cake Shop Ltd", "job_title": "\u751f\u7522\u4e3b\u7ba1(\u901a\u5bb5\u73ed)", "description": "\u5de5\u4f5c\u7bc4\u570d\uff1a\n\n\u7ba1\u7406\u5de5\u5834\n\u78ba\u4fdd\u751f\u7522\u6d41\u7a0b\u6309\u6a19\u6e96\u7a0b\u5e8f\u9032\u884c\n\u78ba\u4fdd\u98df\u54c1\u5b89\u5168\u53ca\u885b\u751f\n\u5206\u914d\u751f\u7522\u5de5\u4f5c\n\u8ca0\u8cac\u76e3\u7763\u53ca\u8a13\u7df4\u54e1\u5de5\n\n\u5de5\u4f5c\u5730\u9ede\uff1a\u8475\u6d8c\u5340\n\n\u5de5\u4f5c\u6642\u9593\uff1a21:00 - 6:00 \uff0c\u6bcf\u6708\u4e94\u5929\u4f11\u606f\u65e5\uff0c\u8f2a\u4f11\n\n\u5de5\u4f5c\u8981\u6c42\uff1a\n\n5\u5e74\u6216\u4ee5\u4e0a\u98df\u54c1\u5ee0\u751f\u7522\u7dda\u7ba1\u7406\u7d93\u9a57\n\u6709\u76f8\u95dc\u98df\u54c1\u885b\u751f\u8b49\u66f8\u512a\u5148\n\u5b78\u6b77\u4e0d\u62d8\uff0c\u826f\u597d\u7cb5\u8a9e\u3001\u61c2\u8b80\u5beb\u4e2d\u6587\u3001\u7565\u61c2\u8b80\u5beb\u82f1\u6587\n\u5177\u5099\u826f\u597d\u6e9d\u901a\u6280\u5de7\uff0c\u6709\u8cac\u4efb\u5fc3\u53ca\u80fd\u7368\u7acb\u5de5\u4f5c\n\n\u54e1\u5de5\u798f\u5229\uff1a\u6bcf\u6708\u734e\u91d1\u3001\u00a0\u81b3\u98df\u6d25\u8cbc\u3001\u901a\u5bb5\u73ed\u6d25\u8cbc\u3001\u8d85\u6642\u6d25\u8cbc\u3001\u914c\u60c5\u6027\u82b1\u7d05\u3001\u91ab\u7642\u798f\u5229\u3001\u5f37\u7a4d\u91d1\u3001\u5bb6\u5ead\u53cb\u5584\u5047\u3001\u54e1\u5de5\u8cfc\u7269\u512a\u60e0\u3001\u826f\u597d\u6649\u5347\u6a5f\u6703\n\n\u61c9\u5fb5\u8005\u53ef\u900f\u904e\u4ee5\u4e0b\u9014\u5f91\u9810\u7d04\u9762\u8a66\u6216\u67e5\u8a62\uff1a\n\n\u96fb\u90f5\u500b\u4eba\u5c65\u6b77\u9023\u540c\u671f\u671b\u85aa\u91d1\u53ca\u53ef\u4e0a\u73ed\u65e5\u671f\u61c9\u5fb5\uff1b\u6216\n\u81f4\u96fb2991 6680\u9810\u7d04\u9762\u8a66\u6216\u67e5\u8a62\uff1b\u6216\n\u5c07(1)\u59d3\u540d\u3001(2)\u61c9\u5fb5\u8077\u4f4d\u3001(3)\u5c45\u4f4f\u5730\u5340\u3001(4)\u806f\u7d61\u96fb\u8a71 (5)\u76f8\u95dc\u5de5\u4f5c\u7d93\u9a57Whatsapp \u52306596 6174\n\n\u6240\u6709\u7533\u8acb\u5747\u7372\u56b4\u683c\u4fdd\u5bc6\u3002\u61c9\u5fb5\u8005\u6240\u63d0\u4f9b\u7684\u500b\u4eba\u8cc7\u6599\u53ea\u4f9b\u4f5c\u62db\u8058\u7528\u9014\u3002\u82e5\u99ae\u6c0f\u96c6\u5718\u7684\u5176\u4ed6\u6210\u54e1\u516c\u53f8\u6709\u985e\u4f3c\u8077\u4f4d\u7a7a\u7f3a\uff0c\u4fdd\u7559\u6b0a\u5229\u5c07\u7533\u8acb\u4eba\u6240\u63d0\u4f9b\u4e4b\u8cc7\u6599\u8f49\u4ea4\u5176\u4ed6\u6210\u54e1\u516c\u53f8\u4f5c\u62db\u8058\u7528\u9014\u3002\n\n\u61c9\u5fb5\u8005\u9700\u63d0\u4f9b\u5145\u8db3\u5b8c\u6574\u7684\u8cc7\u6599\u4ee5\u9032\u884c\u7504\u9078\u3002\u61c9\u5fb5\u8005\u6709\u6b0a\u67e5\u95b1\u53ca\u6539\u6b63\u6240\u63d0\u4f9b\u7684\u500b\u4eba\u8cc7\u6599\uff0c\u8acb\u4ee5\u66f8\u9762\u900f \u904e\u96fb\u90f5\u5411\u4eba\u529b\u8cc7\u6e90\u7d93\u7406\u63d0\u51fa\u3002", "employment_types": ["Full Time"], "selling_points": ["\u7ba1\u7406\u5de5\u5834\u78ba\u4fdd\u751f\u7522\u6d41\u7a0b\u6309\u6a19\u6e96\u7a0b\u5e8f\u9032\u884c", "5\u5e74\u6216\u4ee5\u4e0a\u98df\u54c1\u5ee0\u751f\u7522\u7dda\u7ba1\u7406\u7d93\u9a57", "\u5de5\u4f5c\u6642\u9593\uff1a21:00 - 6:00 \uff0c\u6bcf\u6708\u4e94\u5929\u4f11\u606f\u65e5"], "locations": ["Kwai Tsing Area"], "categories": ["Manufacturing", "Manufacturing Management", "Product Development / Management", "Production Planning / Control"], "post_time": "2022-01-14T09:59:59Z", "salary": {"currency": null, "max": null, "min": null, "period": null, "term": null}, "salary_visible": false, "title_keywords": [], "responsibilities": [], "requirements": {"degrees": [], "majors": [], "languages": [], "language_level": [], "hard_skills": [], "soft_skills": [], "languages_combined": []}, "experience_required": {"duration": [], "field": []}}, {"job_id": "100003009050955", "location_code": "hk", "company": "Bank of Communications Hong Kong Branch", "job_title": "Production Management Manager (Information Technology)", "description": "Career Level\nSenior\nQualification\nDegree\nYears of Experience\n5 years\nJob Type\nFull Time\nJob Functions\nManufacturing, Product Development / Management, Others", "employment_types": ["Full Time"], "selling_points": [], "locations": ["Not Specified"], "categories": ["Manufacturing", "Product Development / Management", "Others"], "post_time": "2022-01-14T12:01:10Z", "salary": {"currency": null, "max": null, "min": null, "period": "monthly", "term": null}, "salary_visible": false, "title_keywords": ["manager"], "responsibilities": ["management"], "requirements": {"degrees": ["degree"], "majors": [], "languages": [], "language_level": [], "hard_skills": [], "soft_skills": [], "languages_combined": []}, "experience_required": {"duration": [], "field": []}}, {"job_id": "100003009043917", "location_code": "hk", "company": "Charming Printing Limited", "job_title": "Product Development Manager (Printing/ Label/ Packaging/ Apparel Trims)", "description": "Printing/ Label/ Packaging/ Apparel Trims industry\n\nResponsibilities:\n\n\nConstant communication between China, local and oversea clients, sourcing teams and production lines regarding new products, design changes update and more.\nDrive and monitor the sampling process and quality to satisfy clients\u2019 requirement.\nProvide technical solution and trouble-shooting during sample making stage\nTo ensure new samples to be completed on time.\nCommunicates with CS team and production team after approval of a new programs or items, before launching it on production lines.\n\nRequirements:\n\nUniversity/Technical college graduate/ F.7 or above with 10 yrs + related working experience\n5 years + working experience in product development for Labels or Printing industry is required\nComprehensive knowledge of printing materials and their properties.\nGood communication & interpersonal skill\nExcellent time management, able to work under pressure & meet deadline\nFluent in English, Mandarin and Cantonese\nStation in China\n\nWe offer a competitive remuneration package to successful candidate.\u00a0 Interested parties please send your full resume and expected salary.\n\nThe right candidate may join our company before or after Lunar New Year Holiday.\n(All personal information will be treated in strict confidentiality)", "employment_types": ["Full Time"], "selling_points": ["Station in China", "Printing, Label, Packaging", "Product Development"], "locations": ["Others - China"], "categories": ["Manufacturing", "Product Development / Management", "Printing"], "post_time": "2022-01-13T02:27:11Z", "salary": {"currency": null, "max": null, "min": null, "period": "monthly", "term": null}, "salary_visible": false, "title_keywords": ["product development manager"], "responsibilities": ["quality", "monitor", "teams", "design", "constant communication"], "requirements": {"degrees": [], "majors": [], "languages": ["cantonese", "english", "mandarin"], "language_level": ["fluent"], "hard_skills": [], "soft_skills": ["interpersonal skill", "communication", "comprehensive", "time management", "work under pressure"], "languages_combined": [{"language": "cantonese", "language_level": ["fluent"]}, {"language": "english", "language_level": ["fluent"]}, {"language": "mandarin", "language_level": ["fluent"]}]}, "experience_required": {"duration": ["5 years +"], "field": ["related", "product development"]}}, {"job_id": "100003009048952", "location_code": "hk", "company": "Find Asia Limited", "job_title": "Procurement Manager (Electronics)", "description": "Our client, a Japanese electronics component company is looking for the candidate with the following details\n\nDuties\n\nUnderstand the needs and the workflow of the procurement processing\u00a0\nProcurement planning, research and analysis of the parts and finished goods production\u00a0\n\nReview the shipment schedule, monitor the delivery and shipment schedule\u00a0\nSupervise and control the production manufacturing, scheduling and operation\u00a0\nPO approval and shipment schedule review\u00a0\nProduct planning, re-modifying and market research to enhancement the product functions fit in different markets\u00a0\n\nRequirements\n\nUniversity graduate and with procurement/ purchasing/ SCM experience\nFluent English and Mandarin\nWith supervision and solid experience in procurement, production planning, good understand of product cycle, delivery processing\nExperience in project Management, processing review, industrial engineering review of production procedure\nGood sense of figure for data analysis\nGood knowledge of ISO 9001, 14001 and with knowledge/ experience working with compliance team\u00a0\nIndependent, persuasive and self-motivated", "employment_types": ["Full Time", "Permanent"], "selling_points": ["Japanese electronics components manufacturing", "procurement, purchasing", "5 days, Double Pay, Bonus"], "locations": ["Tsuen Wan Area"], "categories": ["Manufacturing", "Manufacturing Management", "Product Development / Management", "Merchandising & Purchasing", "Procurement / Purchasing / Sourcing"], "post_time": "2022-01-15T03:50:06Z", "salary": {"currency": null, "max": null, "min": null, "period": "monthly", "term": null}, "salary_visible": false, "title_keywords": ["manager"], "responsibilities": ["control", "analysis", "review", "monitor", "market research", "scheduling", "schedule", "planning"], "requirements": {"degrees": ["university graduate"], "majors": [], "languages": ["english", "mandarin"], "language_level": ["fluent"], "hard_skills": ["project management", "analysis", "processing"], "soft_skills": ["project management", "self-motivated", "persuasive", "independent"], "languages_combined": [{"language": "english", "language_level": ["fluent"]}, {"language": "mandarin", "language_level": ["fluent"]}]}, "experience_required": {"duration": [], "field": ["engineering", "purchasing", "compliance", "project management", "team", "procurement", "planning"]}}, {"job_id": "100003009036804", "location_code": "hk", "company": "r-pac Hong Kong Ltd", "job_title": "Product Developer", "description": "Key Responsibilities:\n\nDevelop and source solutions from concept through to production sampling.\nCollaborate with design and project management teams identifying technical solutions.\nYou will be required to be part delivering total customer service experience and ensuring the customer expectation are served.\nMonitor and actively participate in planning multiple fast moving production.\nParticipate in the fabric quality control/assurance during the concept and development stage outlining needs.\nYou should be able to participate in the development of product marketing activities and strategic implementation plans.\n\nRequirements:\n\nMinimum 3 years experiences in similar role within garment, trim and accessories manufacturing field.\nFamiliar with Soft-line items such as Paper tags, Woven & Printed labels.\nKnowledge of material sourcing will be an advantage\nAbility to organize, communicate with oversea colleagues and follow up sample development.\nStrong motivation, willing to take initiatives, and strong analytical skills\nFamiliarity with Microsoft applications\nGood command of English & Mandarin\nAggressive, willing to work under pressure and looking for job challenge\n\nWe offer excellent career development opportunities with a highly competitive salary supported by a benefits program including 5-days work, medical, MPF, and sales incentive plan. Interested parties please click \"APPLY NOW\" for application information.\n\n\u00a0**All information collected will be kept strictly confidential and solely for recruitment purposes**", "employment_types": ["Full Time"], "selling_points": ["Familiar with soft-line items eg. woven, paper tag", "Interface overseas staff, customer & factories", "Work in multinational company with 5 days workweek"], "locations": ["Kwai Hing"], "categories": ["Manufacturing", "Garment / Textile", "Product Development / Management"], "post_time": "2022-01-10T14:38:50Z", "salary": {"currency": null, "max": null, "min": null, "period": "monthly", "term": null}, "salary_visible": false, "title_keywords": ["product developer"], "responsibilities": ["collaborate with", "customer service experience", "teams", "monitor", "design", "develop", "implementation", "project management", "quality control", "plans", "planning"], "requirements": {"degrees": [], "majors": [], "languages": ["english", "mandarin"], "language_level": ["good command"], "hard_skills": ["microsoft applications", "analytical skills"], "soft_skills": ["work under pressure", "analytical skills"], "languages_combined": [{"language": "english", "language_level": ["good command"]}, {"language": "mandarin", "language_level": ["good command"]}]}, "experience_required": {"duration": ["minimum 3 years"], "field": ["garment", "manufacturing"]}}, {"job_id": "100003009042242", "location_code": "hk", "company": "Fairwood Fast Food Ltd", "job_title": "\u7522\u54c1\u767c\u5c55\u90e8\u7d93\u7406 Product Development Manager (Fast Food Chain)", "description": "Minimum 3 years' merchandising experience in sweater development and\u00a0Production follow up\nTI / Polytechnic graduate is preferable\nGood technical skill in sweater manufacturing and able to handle complicated\u00a0styles in both high fashion sweater and price conscious sweater\nExperience in factory manufacturing is an advantage\nAble to handle customer independently\nGood command of spoken and written English and able to communicate in Mandarin\nMature, self motivated, detail-minded, responsible and able to work under pressure\nWilling to travel to China (Dong Guan) when required\n\nInterested parties please apply with full resume and expected salary to us by clicking APPLY NOW.\u00a0\n\n", "employment_types": ["Full Time", "Permanent"], "selling_points": ["\u8ca0\u8cac\u897f\u5f0f\u98df\u54c1\u88fd\u4f5c\u3001\u8a2d\u8a08\u71df\u904b\u6d41\u7a0b\u53ca\u63a7\u5236\u98df\u54c1\u6210\u672c\u54c1\u8cea", "\u4e2d\u5b78\u7a0b\u5ea6\u53ca\u5341\u5e74\u4ee5\u4e0a\u5eda\u623f\u7ba1\u7406(\u9152\u5e97\u6703\u6240\u9910\u98f2\u696d)\u7d93\u9a57", "\u64c5\u9577\u897f\u65e5\u97d3\u53ca\u6771\u5357\u4e9e\u83dc\u98df\u54c1\u51e0\u88fd\u4f5c\u53ca\u7814\u767c"], "locations": ["Tai Po Area"], "categories": ["Hospitality / F & B", "Food & Beverage", "Manufacturing", "Product Development / Management", "Production Planning / Control"], "post_time": "2022-01-12T06:43:16Z", "salary": {"currency": null, "max": null, "min": null, "period": "monthly", "term": null}, "salary_visible": false, "title_keywords": ["product development manager"], "responsibilities": ["merchandising", "work under pressure"], "requirements": {"degrees": [], "majors": [], "languages": ["english", "mandarin"], "language_level": ["good command"], "hard_skills": [], "soft_skills": ["detail-minded", "independently", "responsible", "mature", "self motivated", "technical skill", "work under pressure"], "languages_combined": [{"language": "english", "language_level": ["good command"]}, {"language": "mandarin", "language_level": ["good command"]}]}, "experience_required": {"duration": ["minimum 3 years"], "field": ["development", "manufacturing", "merchandising"]}}, {"job_id": "100003009047965", "location_code": "hk", "company": "Solent Manufacturing Ltd", "job_title": "Merchandiser - Health & Beauty / Household / Bags", "description": "Job Highlights:\n\nThis is a challenging position for a high-calibre, energetic, and experienced personnel to oversee a manufacturing operation in China now with opportunities and potential growth to manage operations in multiple sites globally.\u00a0\n\nJob Responsibilities:\n\nOversee the operations of the manufacturing facilities in Dongguan, China\nManage production, quality control, planning and material control, procurement, supply chain, china customs, human resources and administration functions of the Dongguan facilities\nDevelop strategic operational planning and control, evaluates organizational efficiency, and makes necessary changes to increase and maximize productivity, reduce costs, and increase profit margins\nManage resources, maintain and execute existing operational policies, procedures, plans and systems in all aspects are carried out properly, compliance to established standards and requirements internally, externally, and legally and to develop new if required\nAssess the needs of the facilities and finds ways to contribute to the big picture by ensuring daily operations run smoothly and as efficiently and effectively as possible\nAssist Vice President, Operations in China to monitor operations maintained in South East Asia\nPosition based in Dongguan, China\nReport to Vice President, Operations in China.\n\nRequirement:\n\nBachelor or above, major in manufacturing, industrial engineering, supply chain, or related discipline is preferable;\nOver 10 years of solid relevant working experiences in similar position in managing operations of electronics component manufacturing facilities in China\nExperience in working with R&D team, optical component industry or similar field is an added advantage\nExperience in managing manufacturing operations in other South East Asian countries is an added advantage\nWell organized, detail minded, flexible and adaptable, ability to work independently and multi-tasks\nCommit to the job, strong sense of responsibility, capable of working under pressure and possess good problem-solving skills\nStrong data analytical and presentation skills and logical thinking\nStrong leadership, good team player with positive thinking, good coordination and inter-personal skills\nProficiency in Excel, MS Word, Power Point and Chinese word processing\nGood command of written and spoken English and Putonghua\n\nApplication:\n\nTo apply, please email us\u00a0your resume, your availability to report duty and quote the Job Ref.\nOnly short-listed candidates will be notified. Personal data provided by applicants will be used for consideration of an application only.\n\nApplication Deadline:\n\nUntil this position is filled.\nResumes received will strictly be used for recruitment-related purpose", "employment_types": ["Full Time", "Permanent"], "selling_points": ["Flexible Working Hour", "Hybrid Working", "Double Pay & Discretionary Bonus"], "locations": ["Hung Hom"], "categories": ["Manufacturing", "Manufacturing Management", "Product Development / Management", "Merchandising & Purchasing", "Procurement / Purchasing / Sourcing"], "post_time": "2022-01-14T04:23:58Z", "salary": {"currency": null, "max": null, "min": null, "period": "monthly", "term": null}, "salary_visible": false, "title_keywords": ["merchandiser"], "responsibilities": ["control", "operations", "policies", "systems", "procedures", "compliance", "monitor", "develop", "daily operations", "planning", "maintain", "quality control", "plans", "report", "costs", "administration"], "requirements": {"degrees": ["bachelor"], "majors": ["manufacturing", "engineering"], "languages": ["putonghua", "english", "chinese"], "language_level": ["proficiency", "good command"], "hard_skills": ["r&d", "excel", "chinese word processing", "power point", "problem-solving skills", "ms word"], "soft_skills": ["flexible", "work independently", "good team player", "under pressure", "capable", "multi-tasks", "sense of responsibility", "adaptable", "well organized", "inter-personal skills", "positive thinking", "presentation skills", "coordination", "problem-solving skills", "leadership"], "languages_combined": [{"language": "putonghua", "language_level": ["good command"]}, {"language": "english", "language_level": ["good command"]}, {"language": "chinese", "language_level": ["proficiency"]}]}, "experience_required": {"duration": ["10 years"], "field": ["manufacturing", "team"]}}, {"job_id": "100003009043302", "location_code": "hk", "company": "Chamtex Limited", "job_title": "Merchandiser", "description": "This role will be responsible for delivering B2B data products to solve supply chain issues and bring deficiencies to global trade.\n\nClient Details\n\nOur client create new solutions to shape the future of international trade.\n\nDescription\n\nYou will be involved in monitoring and achieving sustainability goals. You will be conduct user feedback sessions , product discovery and competitor analysis. You will be own the functionality on B2B platforms. You will explore potential data partnerships.\n\nProfile\n\nYou will have more than 4 years experience in delivering digital products and/or web-based software. You will be strong experience throughout the end-to-end product life-cycle. You will be master of the Scrum framework and agile methodologies using JIRA. If you are experience in Sustainability, B2B products, sustainable financing and/or supply chain product is an advantage.\n\nJob Offer\n\nAttractive package and great company culture are on the offer.\n\nTo apply online please click the 'Apply' button below. For a confidential discussion about this role please contact Christine Tsui on +852 2848 9584.", "employment_types": ["Full Time", "Permanent"], "selling_points": [], "locations": ["Kwun Tong"], "categories": ["Manufacturing", "Product Development / Management", "Merchandising & Purchasing", "Sweater", "Procurement / Purchasing / Sourcing"], "post_time": "2022-01-12T23:26:18Z", "salary": {"currency": null, "max": null, "min": null, "period": "monthly", "term": null}, "salary_visible": false, "title_keywords": ["merchandiser"], "responsibilities": ["software", "data", "analysis", "monitoring", "contact"], "requirements": {"degrees": ["master"], "majors": [], "languages": [], "language_level": [], "hard_skills": ["scrum framework", "analysis", "agile", "web"], "soft_skills": ["agile", "responsible"], "languages_combined": []}, "experience_required": {"duration": ["4 years"], "field": ["digital", "financing", "supply chain", "sustainability"]}}, {"job_id": "100003009046865", "location_code": "hk", "company": "Cloud Light Technology Limited", "job_title": "Director, China Operations (Job Ref. No. Apply-HK-2009-DCO)", "description": "Responsibilities:\n\nEngage development team to align supplier strategy.\nGauge progress of all relevant projects.\nCommunicate effectively between internal customers & manufacturers.\nCollaborate with the relevant teams to create new products.\nPropose suppliers for tooling projects.\nCreate reports to update progress on projects.\n\n\u00a0Qualifications:\n\nDegree in engineering preferred.\n5 to 10 years\u2019 experience in toys or related field with hand-on project management skills and problem-solving abilities.\nComputer literacy.\nExcellent interpersonal skills to work with different levels of people.\nAble to provide solutions and decision making on product developments.\nFrequent travel to factories required.\n\n\u00a0Benefits:\n\nWe offer 5-day work and attractive fringe benefits to the successful candidate.\nInterested parties please click apply now to submit your application.\nAll resumes will strictly be used for interview only and treated as confidential data upon disposal after completion.", "employment_types": ["Full Time", "Permanent"], "selling_points": ["Oversee operations of production plant in PRC", "Potential growth to manage sites in SE Asia", "10+ years solid experience in similar position"], "locations": ["Others - China"], "categories": ["Manufacturing", "Product Development / Management", "Production Planning / Control", "Quality Assurance, Control & Testing / ISO"], "post_time": "2022-01-14T01:29:32Z", "salary": {"currency": null, "max": null, "min": null, "period": "monthly", "term": null}, "salary_visible": false, "title_keywords": ["operations", "director"], "responsibilities": ["collaborate with", "teams", "provide solutions", "project management", "reports"], "requirements": {"degrees": ["degree"], "majors": ["engineering"], "languages": [], "language_level": [], "hard_skills": ["project management", "problem-solving"], "soft_skills": ["project management skills", "problem-solving", "computer literacy", "interpersonal skills", "decision making"], "languages_combined": []}, "experience_required": {"duration": ["5 to 10 years"], "field": ["toys", "project management", "related"]}}, {"job_id": "100003009044388", "location_code": "hk", "company": "Michael Page", "job_title": "Product Manager - Sustainability", "description": "Job Responsibilities\n\nNegotiate with multi suppliers on in-market products to achieve quality standard and cost efficiency\u00a0\nResponsible on product development from quotation to shipment in accordance with Company\u2019s procedures\nPreparation of export documents e.g. P/I, P/O\u2019s. and keep track on sample and order status\nHandle new inquiries including costing analysis, quote preparations, samples, and\u00a0 OEM developments\n\nJob Requirements:\n\nForm 5 or above\nGift Industry - export\nProficient in both written & spoken English\nMinimum 3 years of merchandiser & trading experience. Candidate with OEM product experience will be an advantage\u00a0\nWhat we offer:\n\n5 Days Work Week\nMedical Insurance\nAttractive Salary package plus commission\nAnnual Performance Bonus\nDouble Pay", "employment_types": ["Full Time", "Permanent"], "selling_points": ["Apparel Industry", "B2B Data Products", "Global Trade"], "locations": ["Not Specified"], "categories": ["Manufacturing", "Product Development / Management", "Others", "Trading", "E-commerce", "Supply Chain"], "post_time": "2022-01-13T03:56:50Z", "salary": {"currency": null, "max": null, "min": null, "period": "monthly", "term": null}, "salary_visible": false, "title_keywords": ["product manager"], "responsibilities": ["cost", "quotation", "quality", "procedures", "costing analysis"], "requirements": {"degrees": ["form 5 or above"], "majors": [], "languages": ["english"], "language_level": ["proficient"], "hard_skills": [], "soft_skills": [], "languages_combined": [{"language": "english", "language_level": ["proficient"]}]}, "experience_required": {"duration": ["minimum 3 years"], "field": ["trading"]}}, {"job_id": "100003009047756", "location_code": "hk", "company": "Kwong Chak Fat Manufactory Limited", "job_title": "Merchandiser / Senior Merchandiser", "description": "We are a local manufacturer focused on law enforcement customer (e.g. Fire Service, Police, Marine, Prison, Immigration, Custom, Military) around the world.\u00a0 Since our brand is just 3 years old, we are seeking a designer to help develop our products including but not limited to tactical vest & pouches, boots, helmet, uniform, gloves, bulletproof gears, backpacks, etc.\n\nThe candidate shall have\n1) Good knowledge of worldwide brand products such as 5.11, Crye Precision, SafariLand, etc\n2) Solid practical knowledge and experience in using the tactical gears. We need a serious gears lover\n3) Good knowledge of materials being used in all different products\n4) Work in detail\n5) Speak Mandarin, Cantonese and English.", "employment_types": ["Full Time"], "selling_points": [], "locations": ["Shatin Area"], "categories": ["Manufacturing", "Product Development / Management", "Merchandising & Purchasing", "Others", "Procurement / Purchasing / Sourcing"], "post_time": "2022-01-14T03:53:24Z", "salary": {"currency": null, "max": null, "min": null, "period": "monthly", "term": null}, "salary_visible": false, "title_keywords": ["merchandiser", "senior merchandiser"], "responsibilities": ["develop"], "requirements": {"degrees": [], "majors": [], "languages": ["cantonese", "english", "mandarin"], "language_level": [], "hard_skills": [], "soft_skills": ["focused"], "languages_combined": [{"language": "cantonese", "language_level": []}, {"language": "english", "language_level": []}, {"language": "mandarin", "language_level": []}]}, "experience_required": {"duration": [], "field": []}}, {"job_id": "100003009049883", "location_code": "hk", "company": "CK Life Sciences Limited", "job_title": "Manager, Technical Services (health supplement/product development/ regulatory affairs)", "description": "What\u2019s the role about?\nDrive the development process and product plans from the design concept to sample\u00a0approval.\nMonitor the works with vendors to ensure daily\u00a0operations run smoothly\nReview and provide recommendations for product improvement and valued\nengineering\nManage and contribute to design proposals, sourcing and pricing\nCollaborate with Supply Chain Management Team and Quality Assurance Team to\nensure production and quality standard.\u00a0Monitor product testing (including wear test)\nto meet product safety standard\nCommunicate effectively with key stakeholders locally and globally\nResponsible for accuracy of data setup attributes into the component materials\ninformation system\nWhat we are looking for:\n\nDiploma or above or any equivalent\nMinimum\u00a05 years of relevant experience\nFamiliar with product safety specification\nWell-organized, detail-oriented, have analytical mind and high sense of responsibility\nAble to work flexible, multi-task and under pressure\nKnowledge in both Watch and Jewelry fields is an advantage\nFamiliar with PLM system is a definite advantage\nGood command in both spoken and written English\n\nTogether, we make great things happen. Apply now and be part of our tomorrow.\n\nInterested parties please send us your full resume with contact details, preferably with your current and expected salary.\n\nFossil Group is an Equal Opportunity employer. All qualified applicants will receive consideration of employment without regard to race, disability, gender, religion, family status, marital status, national origin, sexual orientation, veteran status, gender identity or \u00a0expression or any other basis protected by local, state, or national law. Only short-listed candidates will be notified. All information received will be kept in strict confidence and only for employment-related purpose.", "employment_types": ["Full Time", "Permanent"], "selling_points": ["MSc /BSc in Food & Nutritional Science or Pharmacy", "8 years\u2019 experience in R&D(health supplement/food)", "5-day workweek"], "locations": ["Tai Po Area"], "categories": ["Sciences, Lab, R&D", "Food Science", "Beauty Care / Health", "Nutritionist", "Manufacturing", "Product Development / Management"], "post_time": "2022-01-14T09:23:24Z", "salary": {"currency": null, "max": null, "min": null, "period": "monthly", "term": null}, "salary_visible": false, "title_keywords": ["product development", "manager"], "responsibilities": ["collaborate with", "management team", "data", "design concept", "review", "monitor", "quality", "design", "testing", "daily operations", "provide recommendations", "plans", "setup"], "requirements": {"degrees": ["diploma or above"], "majors": [], "languages": ["english"], "language_level": ["good command"], "hard_skills": ["make", "information system"], "soft_skills": ["flexible", "multi-task", "under pressure", "responsible", "high sense of responsibility", "well-organized", "detail-oriented", "analytical mind"], "languages_combined": [{"language": "english", "language_level": ["good command"]}]}, "experience_required": {"duration": ["minimum 5 years"], "field": ["relevant experience"]}}, {"job_id": "100003009042045", "location_code": "hk", "company": "Fossil (East) Ltd", "job_title": "Senior Product Executive - Watch", "description": "Our client is an US Sourcing Office with 300+ stores. As of business expansion, they are now looking for a Senior Merchandiser to support end to end product development to sourcing functions.\u00a0\n\nJob Description:\n\nSource vendors and develop products according to the objectives and requirements from the buying team\nMonitor day to day operation including supplier management, product development, quote sheets, sample verification & order follow up\nResponsible for payment terms negotiation and vendor set up, on time shipment & Critical Path management\nMaintain vendor relationship and KPI measurements\nLiaise with buyers and vendors to ensure programs are delivered on time and as planned\nCoordinate the sourcing activates with various department such as QA, Supply chain and packaging team\nAbility to manage a team of 1-2 junior sourcing specialist and/or sourcing assistant\n\nExperience\n\nDegree holder or Higher Diploma in any discipline\n6+ years of experience in\u00a0any hardgood categories (Seasonal, General Merchandise, Arts & Crafts, Stationery, etc.)\u00a0\nFamiliar with sourcing landscape across Asia\u00a0", "employment_types": ["Full Time"], "selling_points": ["Drive the development process and product plans", "Monitor the works with vendors", "Manage design proposals, sourcing and pricing"], "locations": ["Tsuen Wan Area"], "categories": ["Manufacturing", "Jewelry", "Product Development / Management", "Others"], "post_time": "2022-01-12T05:40:41Z", "salary": {"currency": null, "max": null, "min": null, "period": "monthly", "term": null}, "salary_visible": false, "title_keywords": ["senior product executive"], "responsibilities": ["management", "terms negotiation", "monitor", "stationery", "develop", "coordinate", "payment", "maintain", "liaise with"], "requirements": {"degrees": ["diploma", "degree holder"], "majors": [], "languages": [], "language_level": [], "hard_skills": ["vendor"], "soft_skills": ["negotiation", "responsible"], "languages_combined": []}, "experience_required": {"duration": ["6+ years"], "field": []}}, {"job_id": "100003009046124", "location_code": "hk", "company": "Morgan Philips Hong Kong Limited", "job_title": "Senior Merchandiser - Hardgoods", "description": "Duties and Responsibilities\n\n-Define the project scope and direction\n\n-Ensuring an appropriate program or project management framework is in place, incorporating NPI, if required\n\n-Preparing the program brief, project initiation documents or equivalent\n\n-Prepare project schedule with internal/external alignment\n\n-Coordinating and directing end user input\n\n-Determining and managing risks to the program/project\n\n-Managing the program budget, including risk allowance\n\n-Coordinating and fostering teamwork\n\n-Receiving and reviewing detailed reports on the program or project from the stakeholder\n\n-Ensuring the development team or stakeholder decisions on time\n\n-Establishing a mechanism to ensure regular dialogue with contractors to promote problem\u00a0 \u00a0solving, team working and risk sharing\n\n-Traveling when needed for project following with supplier, CMS or corporate subsidiaries\n\n-Monitoring project schedule and alert management with delay and deviation of project\n\n-Require the project teams to build and maintain a project schedule and review progress in regular base\n\n-Report to the Executive Director any Project related issues on a timely basis, especially and critical safety issues that may arise during development\n\n-Work closely with related departments (R&D, Marketing, Manufacturing and Production)\u00a0 \u00a0ensuring all teams are collaborating and productively toward the project goals and objectives\n\n-Review all tooling plans, all applications for tooling quotations, and all part design for\u00a0 \u00a0manufacture review sessions\u00a0\n\n-Review all product test plans and test results during the project duration\n\n-Review all product cost against the project cost target\n\n-Provide training for staff to remove skill gaps as required\n\n-Chair a final project review meeting to discuss the project and lessons learning\n\n-PM may requested to support with proposal development, contract negotiation and monitor\u00a0 \u00a0supplier schedule. Proposal preparation may include assisting with plans, specifications and\u00a0 \u00a0financial terms of the contract.\n\n-Provide written progress report to the immediate next level and related parties in regular base\u00a0 \u00a0(TBD)\n\nJob Requirements\u00a0\n\nQualifications and Experience Levels:\u00a0\n\n-Educated to degree level (preferably Masters) in a relevant engineering discipline such as\u00a0 \u00a0Mechanical / Electronic / Electrical/Project Management)\n\n-Knowledge and technical understanding of Consumer Electronic and home appliance\u00a0 \u00a0processes,\u00a0 components and design techniques\n\n-Working Experience: 10 years in manufacturing environment\n\n- Proven leadership and management skills with the ability to optimise team performance and\u00a0 \u00a0development\n\n-Strong and confident negotiator with the ability to negotiate at all levels\n\n-Excellent communication, interpersonal and influencing skills\n\n-Excellent analytical and problem \u00a0solving abilities\n\n-Results orientated with ability to plan and deliver against project deadlines\u00a0\n\n-Excellent communication and presentation skills\n\n-Strong problem-solving and creative skills knowledge\n\n-An ability to work under pressure and keep to deadlines\n\n-Stay in Dong Guan, China", "employment_types": ["Full Time", "Permanent"], "selling_points": ["An US Sourcing Office", "No Sales Target", "Manage End to End Development Cycle"], "locations": ["Not Specified"], "categories": ["Manufacturing", "Product Development / Management", "Merchandising & Purchasing", "Stationery", "Procurement / Purchasing / Sourcing"], "post_time": "2022-01-13T09:40:00Z", "salary": {"currency": null, "max": null, "min": null, "period": "monthly", "term": null}, "salary_visible": false, "title_keywords": ["senior merchandiser"], "responsibilities": ["management", "cost", "budget", "teams", "review", "design", "monitor", "project management", "maintain", "reports", "schedule", "specifications", "plans", "report"], "requirements": {"degrees": ["degree"], "majors": ["project management", "engineering"], "languages": [], "language_level": [], "hard_skills": ["project management", "problem-solving"], "soft_skills": ["confident", "problem-solving", "communication", "project management", "presentation skills", "creative", "leadership", "interpersonal", "work under pressure"], "languages_combined": []}, "experience_required": {"duration": ["10 years"], "field": ["manufacturing"]}}, {"job_id": "100003009043023", "location_code": "hk", "company": "\u7279\u666e\u79d1\u6280\u6709\u9650\u516c\u53f8", "job_title": "Program Manager (Senior)", "description": "Responsibilities:\n\n\nResponsible for equipment selection for manufacturing and inspection\nDiagnosing problems in the production line and providing recommendations and training\nParticipate with process and design risk assessment\nAssist to design tools and machines use to manufacture products\nSupport validation activities for new equipment and prepare related documents (validation protocol, SOP, etc)\nPerforms other duties as assigned\n\nRequirements:\n\nAssociate\u2019s or Bachelor\u2019s degree in engineering discipline required\nStrong verbal and written communication skills are necessary\nSelf-motivated and able to work independently\nGood team player with high degree of integrity and responsibility\nExperience working in an ISO 13485 or related Quality Management System is a plus\nExperience with CAD software is a plus\nStrong verbal and written communication skills are necessary\n\nWe offer an attractive remuneration package including competitive salary, 5-day work, annual leave and medical insurance.\u00a0\u00a0If you are interested in this career opportunity,\u00a0please apply with your detailed resume, present and expected salary\u00a0by clicking \u201cApply Now\u201d\n\nPersonal data collected will be used for recruitment purpose only.", "employment_types": ["Full Time"], "selling_points": [], "locations": ["Others - China"], "categories": ["Manufacturing", "Product Development / Management"], "post_time": "2022-01-12T09:37:22Z", "salary": {"currency": null, "max": null, "min": null, "period": "monthly", "term": null}, "salary_visible": false, "title_keywords": ["manager"], "responsibilities": ["related documents", "other duties", "design", "inspection"], "requirements": {"degrees": ["degree", "bachelor"], "majors": ["engineering"], "languages": [], "language_level": [], "hard_skills": ["cad", "plus"], "soft_skills": ["communication skills", "self-motivated", "work independently", "good team player", "integrity"], "languages_combined": []}, "experience_required": {"duration": [], "field": ["related", "quality management"]}}, {"job_id": "100003009042268", "location_code": "hk", "company": "Sanwa Biotech Limited", "job_title": "Production Engineer", "description": "Global Product Manager - Hardware\n\nWe're partnering with a fast-growing networking & connectivity organization (with the plans for IPO) in finding a Global Product Manager for their hardware team.\n\nThe individual will need to be innovative and creative, coming up with new ideas to be a trend-setter and disrupt the market with never-seen-before products. You will be responsible in end-to-end development of the hardware for transmission device combined with developing tailored go-to-market strategies on a global scale. Collaborating closely with internal stakeholders, you will be a product owner with P&L responsibilities to ensure positive growth and timely execution of products in the market.\n\n\nJob responsibilities\n\nFormulate end-to-end product hardware to be able to integrate with software and service/solutions\nCollaborate with internal (sales, marketing, engineers, supply chain etc.) and external stakeholders (manufacturers, suppliers, design etc.) teams to develop products to be launched into the market\nFormulate personalized go-to market strategies for region/country to ensure positive growth and return\nCollaborate with senior management team on the vision of the product and present insights and recommendations for new product development and/or provide amendments to existing product portfolio\nResponsible for end-to-end product life cycle (from scratch to market launch to post-market launch follow ups) to ensure positive growth\nConduct market research and analysis to draw insights on the region's need and to bridge competition gap\nP&L ownership and management for responsible product category\n\nJob requirements:\n\nDegree holder in business related discipline\nMinimum 5 years experience in product management with global or APAC scope focusing either on B2B or B2C\nExperience managing hardware products, preferably in the networking or transmission category\nStrong in communication and negotiation\nTeam player, self-motivated, creative and detail minded\n\nInterested candidates, please send quest updated resume to Tommy Wong at tommy.wong@randstad.com.hk", "employment_types": ["Full Time", "Permanent"], "selling_points": [], "locations": ["Shatin Area"], "categories": ["Engineering", "Manufacturing & Production", "Mechanical", "Manufacturing", "Product Development / Management"], "post_time": "2022-01-12T06:47:11Z", "salary": {"currency": null, "max": null, "min": null, "period": "monthly", "term": null}, "salary_visible": false, "title_keywords": ["production engineer"], "responsibilities": ["collaborate with", "management", "software", "conduct market research", "analysis", "teams", "design", "develop", "p&l", "hardware", "senior management"], "requirements": {"degrees": ["degree holder"], "majors": ["business"], "languages": [], "language_level": [], "hard_skills": ["hardware"], "soft_skills": ["self-motivated", "negotiation", "communication", "team player", "creative"], "languages_combined": []}, "experience_required": {"duration": ["minimum 5 years"], "field": ["product management"]}}, {"job_id": "100003009038058", "location_code": "hk", "company": "Randstad Hong Kong Limited", "job_title": "Global Product Manager - Network Device (Hardware)", "description": "Job Duties:\n\nParticipate in a team for MDx product development and advancement;\nResponsible for planning, organizing and overseeing process or production trial and scale up, generating ideas for new products and researching feasibility in terms of profitability, resource availability and compliance with regulations;\nRecording and analyzing data, investigating and testing new equipment, technology transfer, documentation and filing;\nProvide technical support to cross-functional team for product quality control, validation and evaluation;\nLiaise with engineering, research, technical and/or production staff, vendors, academic researchers and external collaborators to coordinate research or commercialization projects;\nResponsible for writing and reading technical papers, reports, reviews and specifications, patent and grant applications; and\nReport findings and project update at group and departmental meetings.\n\n\u00a0Requirements:\n\nMPhil/Ph.D./Postdoc in Molecular Biology, Microbiology, Biomedical Engineering, or relevant disciplines;\nProficient and meticulous in Molecular techniques are preferable;\nHands-on experience in clinical research/ healthcare product, medical device or Point-Of-Care systems development, CE, FDA, or China NMPA application, ISO 9001 and ISO13485 process management will be beneficial;\nStrong team spirit, interpersonal and communication skills, good English writing and reading ability; and\nProactive, creative, positive attitude, result-oriented, capable of multi-tasking along with problem-solving expertise and capable of independent in-depth research.\n\nIf you are passionate, driven and looking for a new and exciting opportunity within a successful and growing company, this may be the right role for you.\n\nPlease click \u201cApply Now\u201d to submit your application.\n\nFor more info, please visit our web page at\u00a0http://www.diagcorlifescience.com/\n\n\nWe will only consider applicants who apply directly to our firm and not through recruitment agencies. All applications will be treated in strict confidence. Personal data collected will be used for recruitment purposes only. Applicants who do not hear from us within 4 weeks may consider their applications unsuccessful and the applications will be destroyed within 6 months.", "employment_types": ["Full Time", "Permanent"], "selling_points": [], "locations": ["Not Specified"], "categories": ["Engineering", "Electrical / Electronics", "Telecommunication / Wireless / Radio", "Manufacturing", "Product Development / Management"], "post_time": "2022-01-11T04:48:32Z", "salary": {"currency": "HKD", "max": 54999, "min": 45000, "period": "monthly", "term": null}, "salary_visible": true, "title_keywords": ["product manager"], "responsibilities": ["regulations", "ideas", "data", "technical support", "compliance", "testing", "coordinate", "liaise with", "commercialization", "specifications", "reports", "departmental meetings", "quality control", "evaluation", "documentation", "report", "planning"], "requirements": {"degrees": [], "majors": [], "languages": ["english"], "language_level": ["good"], "hard_skills": ["problem-solving", "web"], "soft_skills": ["result-oriented", "communication skills", "meticulous", "team spirit", "independent", "creative", "capable", "passionate", "confidence", "problem-solving", "driven", "positive attitude", "hands-on", "multi-tasking", "proactive", "interpersonal"], "languages_combined": [{"language": "english", "language_level": ["good"]}]}, "experience_required": {"duration": [], "field": ["healthcare", "management", "research", "development", "medical device", "clinical"]}}, {"job_id": "100003009042351", "location_code": "hk", "company": "DiagCor Life Science Limited", "job_title": "Scientist/ Research Scientist for Product development", "description": "My client is an US Buying Office with 200+ staff in Hong Kong. As of business expansion, they are now recruiting a Senior Merchandiser to join their team.\u00a0\n\n\n\nJob Duties :\n\n\nManage development to bulk production process\nWork with garment factories to achieve best prices\nWork to ensure a seamless co-ordination with internal colleagues related to development issues\nMonitor suppliers and the production market to update market situation.\nPartner with local and overseas technical teams to ensure Brand requirements are met\nReview tech packs and samples with fit tech to ensure the product requirements are followed\nLiaison with Fabric team to ensure on-time submission of quality and obtain approval\nEnsure clear and timeliness of the communication with all the counterparts\nProvide updated market information to customers in respect of style, fabrics, delivery etc.\nProvide information of competitors\u2019 activities within ability to access the market.\n\nRequirements:\u00a0\n\n\nCollege degree or equivalent work experience\n6-10 years related work experience in sourcing and production\nStrong technical knowledge in woven/knit/sweater\nDetail-oriented, strong planning and coordination skills\nExcellent verbal and written communication skills\u00a0\nAbility to work well within a team environment", "employment_types": ["Full Time", "Permanent"], "selling_points": [], "locations": ["Kowloon Bay"], "categories": ["Sciences, Lab, R&D", "Life Science", "Manufacturing", "Product Development / Management", "Research & Development (R&D)"], "post_time": "2022-01-12T07:09:06Z", "salary": {"currency": null, "max": null, "min": null, "period": "monthly", "term": null}, "salary_visible": false, "title_keywords": ["product development", "scientist", "research scientist"], "responsibilities": ["market information", "production process", "review", "quality", "monitor", "teams", "communication"], "requirements": {"degrees": ["degree"], "majors": [], "languages": [], "language_level": [], "hard_skills": [], "soft_skills": ["communication skills", "coordination skills", "detail-oriented"], "languages_combined": []}, "experience_required": {"duration": ["6-10 years"], "field": ["related"]}}, {"job_id": "100003009052626", "location_code": "hk", "company": "Morgan Philips Hong Kong Limited", "job_title": "Senior Merchandiser - Apparel (Woven)", "description": "Employer Ref: NR09468\nNature of Business: Japan based Trading Company\u00a0\u00a0\nWorking Days: 5 Days\nWorking Location: Tsing Yi Area\n\nBenefits:\n- Double pay\n- Discretionary Bonus\n- Transportation Allowance\n- OT Allowance\n- Attendance allowance\n- Medical insurance\n\nRequirements:\n- Degree holder\n- Min. 3 years exp. in Purchasing/Buying/Product development\n- Business level in Japanese and English\n\nDuties:\n- Handle daily purchasing and product development duties\n- Maintain good relationship with overseas suppliers\n- Responsible for data entry and managements\n\nInterested in the above vacancy?\u00a0 Send your resume to us NOW!\nOnly short-listed candidates will be notified. Personal data collected will be used for recruitment purpose only", "employment_types": ["Full Time", "Permanent"], "selling_points": ["An US Company", "Manage End to End PD to Production Cycle", "Woven & Knit"], "locations": ["Not Specified"], "categories": ["Manufacturing", "Product Development / Management", "Merchandising & Purchasing", "Woven / Knit", "Textiles"], "post_time": "2022-01-17T03:35:46Z", "salary": {"currency": null, "max": null, "min": null, "period": "monthly", "term": null}, "salary_visible": false, "title_keywords": ["senior merchandiser"], "responsibilities": [], "requirements": {"degrees": [], "majors": [], "languages": [], "language_level": [], "hard_skills": [], "soft_skills": [], "languages_combined": []}, "experience_required": {"duration": [], "field": []}}, {"job_id": "100003009048188", "location_code": "hk", "company": "Kingsway Personnel Ltd", "job_title": "Japanese Speaking Purchasing Executive ~22K", "description": "*NEW RECRUITMENT OFFER WITH $6,000 REFERRAL FEE!\nYou may invite your friends or family members to join us!\n\nWe offer:\n\nWell-structured and comprehensive mentoring program\nMonthly income from HK$15,000 + unlimited commission\nOne year fast track program to managerial level\n\u201cWork Hard, Play Hard\u201d working environment & lots of fun\nOpportunity to explore PRC business\nJob Description:\n\n1. Professional Investment plannings for clients\n\nWealth Management & Portfolio Advice\nInvestment Planning\u00a0\nRetirement Planning\nRisk Management Planning\n\n2. Management Level\n\nAttempt Planning Strategies for Constructing Team\nLearn from Recruiting & Managing Team\n\n3. Self Continuous Improvement\n\nAcquire Up-to-Date Financial Knowledge and News\nDevelop Better Interpersonal and Communication Skills\n\n4. Development Path and Work Benefit\n\nA structured career path and solid training in all aspects of management\nYou will work very closely with our District Director who will guide, train and mentor you\u00a0\nManagement trainee programme offers excellent training and a fast track career into management\nSponsored overseas traveling for achieving yearly targets\nResponsibilities:\n\nIdentifying needs of clients and providing professional financial advice\nManagement of wealth assets of clients through investment vehicles\nUpdating financial news to your clients\nProviding financial analyst, investment, saving, retirement, MPF and risk management services\nProvide quality after-sales services to maintain good customer relationship\nWe are looking for:\n\nDegree holder in all discipline\nEnergetic and outgoing\nMature, self-motivated, hardworking and willing to learn\nExperience in the banking industry or background in the Mainland will be an advantage\nUndergraduate in Hong Kong (Year 3 & 4 students are also welcome)", "employment_types": ["Full Time", "Permanent"], "selling_points": ["Business level in Japanese and English speaking", "Exp. in Purchasing/Buying/Product development", "~22K, double pay, bonus, transportation allowance"], "locations": ["Tsing Yi"], "categories": ["Manufacturing", "Product Development / Management", "Merchandising & Purchasing", "Others", "Procurement / Purchasing / Sourcing"], "post_time": "2022-01-15T19:11:34Z", "salary": {"currency": null, "max": null, "min": null, "period": "monthly", "term": null}, "salary_visible": false, "title_keywords": ["purchasing executive"], "responsibilities": ["recruitment"], "requirements": {"degrees": [], "majors": [], "languages": [], "language_level": [], "hard_skills": [], "soft_skills": [], "languages_combined": []}, "experience_required": {"duration": [], "field": []}}, {"job_id": "100003009045185", "location_code": "hk", "company": "Nova Group", "job_title": "Management Trainee/ Manager", "description": "We are a well-established watch manufacturer in Lai Chi Kok and looking for right candidates for the position of Product Development Executive. \u00a0The main job duties and requirements are :\n- Assist the Product Development Manager to coordinate product development projects\n- Evaluates and resolves technical feasibility, design optimization and production issues\n- 5 years related experience in watch manufacturing industries is preferred\n- F.5 graduate or above\n", "employment_types": ["Full Time", "Permanent", "Internship"], "selling_points": ["New recruitment offer of $6,000 referral fee", "Monthly income of $30K+ plus attractive commission", "Overseas convention trips & excellent career path"], "locations": ["Kwun Tong"], "categories": ["Transportation & Logistics", "Aviation Services", "Manufacturing", "Product Development / Management", "Sales, CS & Business Devpt", "Account Servicing"], "post_time": "2022-01-13T07:23:40Z", "salary": {"currency": null, "max": null, "min": null, "period": "monthly", "term": null}, "salary_visible": false, "title_keywords": ["management trainee", "manager"], "responsibilities": ["coordinate", "design"], "requirements": {"degrees": [], "majors": [], "languages": [], "language_level": [], "hard_skills": [], "soft_skills": [], "languages_combined": []}, "experience_required": {"duration": ["5 years"], "field": ["related", "manufacturing"]}}, {"job_id": "100003009035404", "location_code": "hk", "company": "AXA Hong Kong", "job_title": "Product Development Officer, General Insurance", "description": "The Cookware Company is a global company with a high expertise in innovative cookware. Our organization is vertically integrated, allowing us to manage both the production and distribution of our products. We have sales offices in Europe, the United States and Asia as well as state-of-the-art production facilities in Korea, China and Europe. We have high quality standards (e.g. ISO-certificates) and work hard to reduce our environmental impact.\nThe Cookware Company has always been a pioneer in healthy ceramic non-stick cookware. Over the years we have extended our scope in order to offer smart cookware solutions for everyone. Innovation, flexibility, creativity and social responsibility are our main focus. However, our most important asset are our people. They\u2019re the heart of our company.\nYou are responsible to make sure that our overall Quality plan is set up, managed and followed internally in the company and by all our external partners. The Quality Manager is responsible for managing all aspects of the Safety and Quality of products, to ensure products are available on time at the right quality level.\nMain Roles & Responsibilities:\n\nPrimary Responsibilities:\n\nPart of the project team to ensure Quality points are integrated in all new range development.\nImplement Quality Management Plans for all new ranges, manage supplier quality audits, product quality requirement and shipment inspections.\u00a0\nConduct on-site Quality Audits of all potential new suppliers and factories.\nManage the Quality relationship with suppliers, ensure all suppliers understand our requirements for quality management and product safety and product quality.\nMaintain up-to-date records for all Quality activity, including factory audit reports, test report and inspection reports, and share with other areas of the business as needed.\nCoordinate and supply all needed documents customers request in terms of Quality requirement.\nIdentify safety and quality requirements for new product ranges of new retail markets, record this information in Generic Global Protocols, and share with all relevant parties.\nConsult the organization on updated quality standards to ensure product compliance.\nReview all third service providers\u2019 reports and communicate to service provider(s) for any query (on-line, life test, lab testing, inspections and audits).\nProvide quality/Technical support to all needed departments; investigate product issues and work with suppliers to identify root causes and to take appropriate actions to prevent recurrence.\nManaging the performance of external service providers based on cost, service quality and value of technical support provided.\nManage the cost of Quality Management effectively, ensuring that all paid services deliver the maximum value for money in terms of Quality Management.\u00a0 Keep records of all Quality Management costs for periodic analysis.\nBuilding a strong relationship with our external service providers, licensor technical team and internal global clients to ensure timely and accurate technical support and communication of requirements.\nImprove the QA process, quality concept and quality control methods training guidance,\nLook for continuous improvements on the efficiency in the department and propose these to the organization.\nAnalyzes and manage Consumer Service Claims to identify root cause and identify corrective/preventive actions in product design, manufacturing and processes.\nOther Responsibilities\nReview brand-partner and client quality requirements to ensure they are understood by all parties and incorporated into Quality Management plans as required.\u00a0 \u00a0\nRequirements:\nBachelor degree with a minimum of 8 year experience in Quality Assurance or equivalent\nExtensive experience in Kitchenware, Cookware, household item\nGood communication and interpersonal skills, open-minded and willing to face challenges.\nAnalytical and problem-solving ability\nPersistence and the ability to influence others.\nSkills in numerical and statistical analysis\nAttention to detail.\nGood in English, Cantonese, and Mandarin, both spoken and written.", "employment_types": ["Full Time", "Permanent"], "selling_points": ["Corporate role in AXA", "General Insurance", "Product Development Team"], "locations": ["Southern Area"], "categories": ["Insurance", "Others", "Manufacturing", "Product Development / Management", "E-commerce", "Product Management / Business Analyst"], "post_time": "2022-01-10T07:03:19Z", "salary": {"currency": null, "max": null, "min": null, "period": "monthly", "term": null}, "salary_visible": false, "title_keywords": ["officer", "product development"], "responsibilities": ["inspection reports", "quality", "audit", "communication", "maintain", "plans", "costs", "compliance", "testing", "reports", "report", "continuous improvements", "guidance", "management", "cost", "review", "product design", "audits", "technical support", "analysis", "coordinate", "quality control"], "requirements": {"degrees": ["degree", "bachelor"], "majors": [], "languages": ["cantonese", "english", "mandarin"], "language_level": ["good"], "hard_skills": ["problem-solving", "statistical analysis"], "soft_skills": ["open-minded", "problem-solving", "communication and interpersonal skills", "attention to detail", "extensive"], "languages_combined": [{"language": "cantonese", "language_level": ["good"]}, {"language": "english", "language_level": ["good"]}, {"language": "mandarin", "language_level": ["good"]}]}, "experience_required": {"duration": ["minimum of 8 year"], "field": ["quality assurance"]}}, {"job_id": "100003009043295", "location_code": "hk", "company": "JAC Recruitment Hong Kong Co., Limited", "job_title": "Urgent - Japanese Speaking  Product Management(Japanese Trading Company)", "description": "Our client, a Japanese Trading company is looking for candidates Japanese Speaking\u00a0Product Management\u00a0roles.\u00a0\n\nResponsibilities:\n\n\u203b\u4e0b\u8a18\u696d\u52d9\u3092\u884c\u3046\u30c1\u30fc\u30e0\u3092\u30de\u30cd\u30b8\u30e1\u30f3\u30c8\u3057\u3066\u3044\u305f\u3060\u304d\u307e\u3059\u3002\n\n\n\n\u65b0\u898f\u53d6\u308a\u6271\u3044\u5546\u54c1\u306e\u793e\u5185\u30b7\u30b9\u30c6\u30e0\u3078\u306e\u767b\u9332\n\u60c5\u5831\u5909\u66f4\u6642\u306e\u793e\u5185\u30b7\u30b9\u30c6\u30e0\u306e\u30c7\u30fc\u30bf\u66f4\u65b0\n\u5728\u5eab\u30c7\u30fc\u30bf\u306e\u7ba1\u7406\n\u5165\u8377\u5546\u54c1\u306e\u691c\u54c1\u3068\u54c1\u8cea\u30c1\u30a7\u30c3\u30af\n\nRequirements:\n\n\n\u5e83\u6771\u8a9e\u30d3\u30b8\u30cd\u30b9\u30ec\u30d9\u30eb\u3001\u65e5\u672c\u8a9e\u30cd\u30a4\u30c6\u30a3\u30d6\u30ec\u30d9\u30eb\n\n\u30de\u30cd\u30b8\u30e1\u30f3\u30c8\u7d4c\u9a13\u8005\u3000\nPC\u3092\u4f7f\u3063\u305f\u4e8b\u52d9\u306b\u3042\u308b\u7a0b\u5ea6\u7cbe\u901a\u3057\u3066\u3044\u308b\u65b9\n\u65e5\u672c\u52e4\u52d9\u307e\u305f\u306f\u65e5\u7cfb\u4f01\u696d\u52e4\u52d9\u7d4c\u9a13\u8005\n\nInterested candidates, kindly send your detailed resume in MS Word including:\n\n\n1) Expected salary\n2) Current and last drawn salaries\n3) Reason for leaving current and past employments\n\u00a0\ndirectly to:\u00a0jac.hk\u00a0@jac-recruitment.com and CC to:\u00a0akihisa.watanabe\u00a0@jac-recruitment.com\n\nPersonal data collected will be used for employment-related purpose only. We regret to inform that only shortlisted candidates will be notified, thank you", "employment_types": ["Full Time", "Permanent"], "selling_points": ["Japanese company", "Expanding business", "Urgent Position"], "locations": ["Tsing Yi"], "categories": ["Manufacturing", "Product Development / Management"], "post_time": "2022-01-12T10:33:30Z", "salary": {"currency": null, "max": null, "min": null, "period": "monthly", "term": null}, "salary_visible": false, "title_keywords": [], "responsibilities": [], "requirements": {"degrees": [], "majors": [], "languages": [], "language_level": [], "hard_skills": [], "soft_skills": [], "languages_combined": []}, "experience_required": {"duration": [], "field": []}}, {"job_id": "100003009043446", "location_code": "hk", "company": "The Cookware Company Limited", "job_title": "QA Manager, Hardgoods", "description": "The Cookware Company is a global company with a high expertise in innovative cookware. Our organization is vertically integrated, allowing us to manage both the production and distribution of our products. We have sales offices in Europe, the United States and Asia as well as state-of-the-art production facilities in Korea, China and Europe. We have high quality standards (e.g. ISO-certificates) and work hard to reduce our environmental impact.\nThe Cookware Company has always been a pioneer in healthy ceramic non-stick cookware. Over the years we have extended our scope in order to offer smart cookware solutions for everyone. Innovation, flexibility, creativity and social responsibility are our main focus. However, our most important asset are our people. They\u2019re the heart of our company.\nYou are responsible to make sure that our overall Quality plan is set up, managed and followed internally in the company and by all our external partners. The Quality Manager is responsible for managing all aspects of the Safety and Quality of products, to ensure products are available on time at the right quality level.\nMain Roles & Responsibilities:\n\nPrimary Responsibilities:\n\nPart of the project team to ensure Quality points are integrated in all new range development.\nImplement Quality Management Plans for all new ranges, manage supplier quality audits, product quality requirement and shipment inspections.\u00a0\nConduct on-site Quality Audits of all potential new suppliers and factories.\nManage the Quality relationship with suppliers, ensure all suppliers understand our requirements for quality management and product safety and product quality.\nMaintain up-to-date records for all Quality activity, including factory audit reports, test report and inspection reports, and share with other areas of the business as needed.\nCoordinate and supply all needed documents customers request in terms of Quality requirement.\nIdentify safety and quality requirements for new product ranges of new retail markets, record this information in Generic Global Protocols, and share with all relevant parties.\nConsult the organization on updated quality standards to ensure product compliance.\nReview all third service providers\u2019 reports and communicate to service provider(s) for any query (on-line, life test, lab testing, inspections and audits).\nProvide quality/Technical support to all needed departments; investigate product issues and work with suppliers to identify root causes and to take appropriate actions to prevent recurrence.\nManaging the performance of external service providers based on cost, service quality and value of technical support provided.\nManage the cost of Quality Management effectively, ensuring that all paid services deliver the maximum value for money in terms of Quality Management.\u00a0 Keep records of all Quality Management costs for periodic analysis.\nBuilding a strong relationship with our external service providers, licensor technical team and internal global clients to ensure timely and accurate technical support and communication of requirements.\nImprove the QA process, quality concept and quality control methods training guidance,\nLook for continuous improvements on the efficiency in the department and propose these to the organization.\nAnalyzes and manage Consumer Service Claims to identify root cause and identify corrective/preventive actions in product design, manufacturing and processes.\nOther Responsibilities\nReview brand-partner and client quality requirements to ensure they are understood by all parties and incorporated into Quality Management plans as required.\u00a0 \u00a0\nRequirements:\nBachelor degree with a minimum of 8 year experience in Quality Assurance or equivalent\nExtensive experience in Small Domestic Appliances (cooking, kitchen)\nGood communication and interpersonal skills, open-minded and willing to face challenges.\nAnalytical and problem-solving ability\nPersistence and the ability to influence others.\nSkills in numerical and statistical analysis\nAttention to detail.\nGood in English, Cantonese, and Mandarin, both spoken and written.", "employment_types": ["Full Time", "Permanent"], "selling_points": ["Fast Growing MNC", "Young & Energetic Team", "Promising Career Opportunity"], "locations": ["Kowloon Bay"], "categories": ["Manufacturing", "Product Development / Management", "Merchandising & Purchasing", "Others", "Quality Assurance, Control & Testing / ISO"], "post_time": "2022-01-12T11:59:56Z", "salary": {"currency": null, "max": null, "min": null, "period": "monthly", "term": null}, "salary_visible": false, "title_keywords": ["manager"], "responsibilities": ["inspection reports", "quality", "audit", "communication", "maintain", "plans", "costs", "compliance", "testing", "reports", "report", "continuous improvements", "guidance", "management", "cost", "review", "product design", "audits", "technical support", "analysis", "coordinate", "quality control"], "requirements": {"degrees": ["degree", "bachelor"], "majors": [], "languages": ["cantonese", "english", "mandarin"], "language_level": ["good"], "hard_skills": ["small", "problem-solving", "statistical analysis"], "soft_skills": ["open-minded", "problem-solving", "communication and interpersonal skills", "attention to detail", "extensive"], "languages_combined": [{"language": "cantonese", "language_level": ["good"]}, {"language": "english", "language_level": ["good"]}, {"language": "mandarin", "language_level": ["good"]}]}, "experience_required": {"duration": ["minimum of 8 year"], "field": ["quality assurance"]}}, {"job_id": "100003009043439", "location_code": "hk", "company": "The Cookware Company Limited", "job_title": "QA Manager, SDA", "description": "Responsibilities:\n\nReview current production process flow and liaise continuous improvement activities with cross-functional parties;\nFormulate and maintain standard time of each production process;\nConduct Time and Motion Study on production processes;\nMonitor and enhance productivity of production lines and other related process;\nCoordinate Lean projects such as 5S, TPM etc. as required;\nAssist Production Training and maintain workers capability records;\nHandle ad hoc projects or other duties as assigned.\n\nRequirements:\n\nDegree holder in industrial engineering, manufacturing engineering or related disciplines;\n4 years or above working experience in Industrial Engineering or Food industry sector;\nSound experience in Pre-determined Motion Time System is an advantage;\nWork independently and prioritize work on hand;\nGood leadership, inter-personal skills and pro-active team player;\nStrong analytical thinking and problem solving skills;\nProficiency in MS Word, Excel, PowerPoint and English & Chinese word processing;\nGood command in written and spoken English and Cantonese;\nImmediate available is highly preferred.\n\nStaff Benefits\n\n5-day work week\nBirthday& Wedding Leave\nFree Meal & Shuttle Bus\nStaff Purchase Benefits\nMedical Insurance Coverage\n\nAll applications and data collected will be treated in strict confidence and used exclusively for recruitment purposes.\u00a0 Only short listed candidates will be invited for interview.\u00a0 The company will retain the applications for a maximum period of 6 months and may refer suitable candidates to other vacancies within the Group.", "employment_types": ["Full Time", "Permanent"], "selling_points": ["Fast Growing MNC", "Young & Energetic Team", "Promising Career Opportunity"], "locations": ["Kowloon Bay"], "categories": ["Manufacturing", "Product Development / Management", "Merchandising & Purchasing", "Home Appliances", "Quality Assurance, Control & Testing / ISO"], "post_time": "2022-01-12T11:52:18Z", "salary": {"currency": null, "max": null, "min": null, "period": "monthly", "term": null}, "salary_visible": false, "title_keywords": ["manager"], "responsibilities": ["liaise", "production process", "other duties", "review", "monitor", "coordinate", "maintain", "ad hoc projects"], "requirements": {"degrees": ["degree holder"], "majors": ["related disciplines", "manufacturing", "engineering"], "languages": ["cantonese", "english", "chinese"], "language_level": ["proficiency", "good command"], "hard_skills": ["excel", "chinese word processing", "powerpoint", "problem solving skills", "ms word"], "soft_skills": ["work independently", "determined", "inter-personal skills", "prioritize", "problem solving skills", "pro-active", "team player", "leadership"], "languages_combined": [{"language": "cantonese", "language_level": ["good command"]}, {"language": "english", "language_level": ["proficiency", "good command"]}, {"language": "chinese", "language_level": ["proficiency"]}]}, "experience_required": {"duration": ["4 years"], "field": ["food industry", "engineering"]}}, {"job_id": "100003009046657", "location_code": "hk", "company": "Maxim's Caterers Ltd", "job_title": "Assistant Industrial Engineering Manager (Cakes & Bakery Factory)", "description": "Key Responsibilities:\n\n\nBuilding strong cross-department links to ensure all aspects of the business are engaged in successful delivery of projects.\nManaging critical path from product sign off to shipment.\nWorking closely with UK commercial team on tracking the budgets.\nClosely tracking on the forecast and inventory management.\nDeveloping and managing project plans to ensure timescales are met and are clearly communicated to all manufacturers and suppliers.\nReviewing all completed projects to ensure that improvement actions are taken forward into new projects.\nDriving changes in response to business needs including continuous improvement to procedures governing all of the above\n\nKey Requirements:\n\n\nHigh diploma or above\u00a0with\u00a0merchandising\u00a0experience. Project management experience is a plus.\nSolid experience in product development & life cycle/product management of Health & Beauty/ Households/ Bags\nGood understanding\u00a0on manufacturing process.\nEffective business and personal skills to build relationships with all stakeholders\nGood knowledge of methodologies and techniques for planning, monitoring and controlling projects\nInnovative with strong passion in driving changes and continuous improvements\nSelf confidence in front of factories, oversea offices and customers\nAble to communicate and conduct presentation well in English\nEnjoy travelling to factories in Asia Regions\n\nPersonal data provided by applicants will be strictly used for recruitment purpose only.", "employment_types": ["Full Time", "Permanent"], "selling_points": ["Perform production planning and control production", "5 years or above experience in factory", "5-day work week, Free Meal & Shuttle Bus"], "locations": ["Tai Po Area"], "categories": ["Engineering", "Manufacturing & Production", "Manufacturing", "Product Development / Management", "Production Planning / Control"], "post_time": "2022-01-13T18:54:07Z", "salary": {"currency": null, "max": null, "min": null, "period": null, "term": null}, "salary_visible": false, "title_keywords": ["engineering manager", "assistant"], "responsibilities": ["budgets", "procedures", "developing", "inventory management", "forecast", "plans", "tracking"], "requirements": {"degrees": ["high diploma or above"], "majors": [], "languages": ["english"], "language_level": [], "hard_skills": ["project management", "plus"], "soft_skills": ["confidence", "passion in", "project management", "innovative", "presentation"], "languages_combined": [{"language": "english", "language_level": []}]}, "experience_required": {"duration": [], "field": ["merchandising", "product management", "project management", "beauty", "product development"]}}, {"job_id": "100003009042216", "location_code": "hk", "company": "Sanwa BioTech Limited", "job_title": "Production Clerk", "description": "Job Duty:\n\nEnsure that production work is performed by following SOPs and WIs\nMust be able to follow specific procedures and remain focused on exact and repetitive manufacturing tasks\nRecord data on production batch records and data entry to system\nAssist to maintain and calibrate on production equipment and tools\nEnsure that work areas are clean and maintained at all times\nEnsure that finished goods conform to quality and regulatory requirement\nWorks on individual projects as assigned\nPerforms other duties as assigned\n\nRequirement:\n\nHigher Diploma or above in Science, Chemistry, Biochemistry,\u00a0 Biotechnology or equivalent\nKnowledge in production or laboratory disciplines preferred\nKnowledge in regulatory such as ISO 13485 and GMP is a plus\nExperience with MS Office\nAbility to work in a logical, systematic manner\nAttention to detail to ensure high level of quality\nIndependent and self-motivation, willing to learn\nGood team player with high degree of integrity and responsibility\nAble to work in shift, overtime and weekend is required\n\nWe offer an attractive remuneration package including competitive salary, 5-day work, annual leave and medical insurance.\u00a0\u00a0If you are interested in this career opportunity,\u00a0please apply with your detailed resume, present and expected salary\u00a0by clicking \u201cApply Now\u201d\n\nPersonal data collected will be used for recruitment purpose only.", "employment_types": ["Full Time", "Permanent"], "selling_points": [], "locations": ["Shatin Area"], "categories": ["Sciences, Lab, R&D", "Laboratory", "Manufacturing", "Product Development / Management", "Production Planning / Control"], "post_time": "2022-01-12T06:39:06Z", "salary": {"currency": null, "max": null, "min": null, "period": "monthly", "term": null}, "salary_visible": false, "title_keywords": ["production clerk"], "responsibilities": ["other duties", "data entry", "data", "procedures", "quality", "maintain", "sops"], "requirements": {"degrees": ["higher diploma or above", "degree"], "majors": ["science", "chemistry"], "languages": [], "language_level": [], "hard_skills": ["clean", "batch", "ms office", "plus"], "soft_skills": ["good team player", "independent", "exact", "focused", "willing to learn", "integrity", "systematic", "self-motivation", "attention to detail"], "languages_combined": []}, "experience_required": {"duration": [], "field": []}}, {"job_id": "100003009046655", "location_code": "hk", "company": "Maxim's Caterers Ltd", "job_title": "Assistant Manager, Research and Development  (Cake & Bakery Factory)", "description": "Responsibilities:\n\nl\u00a0\u00a0 Manage and cooperate with R&D Chef and Marketing for the product development process of new products and the improvement process of existing products\n\nl\u00a0\u00a0 Handle raw materials / packaging materials testing, product trial quality testing and tasting\n\nl\u00a0\u00a0 Prepare recipes, F&P cost estimation, product specification and related documents\n\nl\u00a0\u00a0 Assist in new concept screening, product demonstration, photo shooting and workshop\n\nl\u00a0\u00a0 Liaise with internal and external parties relating to product research and development\n\nRequirements:\n\nl\u00a0\u00a0 Degree holder or above in Food Science or related disciplines\n\nl\u00a0\u00a0 Min. 6 years relevant working experience in food industry\n\nl\u00a0\u00a0 Creative, self-motivated and with good communication skill\n\nl\u00a0\u00a0 Proficient in PC applications and Chinese word processing\n\nl\u00a0\u00a0 Excellent command of spoken and written in English and Chinese \u00a0\n\nl\u00a0\u00a0 Work location: Tai Po Industrial Estate (with shuttle bus)\n\nStaff Benefits\n\nl\u00a0\u00a0 Medical Insurance Coverage\n\nl\u00a0\u00a0 Birthday& Wedding Leave\n\nl\u00a0\u00a0 Free Meal & Shuttle Bus\n\nl\u00a0\u00a0 Staff Purchase Benefits", "employment_types": ["Full Time"], "selling_points": ["Food Industry", "Food Science", "Research and Development"], "locations": ["Tai Po Area"], "categories": ["Manufacturing", "Product Development / Management"], "post_time": "2022-01-13T18:54:06Z", "salary": {"currency": null, "max": null, "min": null, "period": null, "term": null}, "salary_visible": false, "title_keywords": ["assistant manager,"], "responsibilities": ["cost estimation", "related documents", "workshop", "internal and external parties", "quality", "testing", "liaise with", "cooperate with"], "requirements": {"degrees": ["degree holder"], "majors": ["related disciplines", "food science"], "languages": ["english", "chinese"], "language_level": ["excellent", "proficient"], "hard_skills": ["chinese word processing", "pc applications"], "soft_skills": ["communication skill", "self-motivated", "creative"], "languages_combined": [{"language": "english", "language_level": ["excellent"]}, {"language": "chinese", "language_level": ["excellent", "proficient"]}]}, "experience_required": {"duration": ["6 years"], "field": ["food industry", "relevant working experience"]}}, {"job_id": "100003009045212", "location_code": "hk", "company": "Triple King Co Ltd", "job_title": "Merchandiser and Order Supervisor - Junior Candidates are also welcomed", "description": "TRIPLE KING CO. LTD.\n\nA foremost trading company is now expanding its teams.\u00a0\n\nTriple King \u2013 located in Kwun Tong \u2013 is expanding its activities and is seeking motivated smart people to perform and fill up below positions. We offer exciting opportunities for professional growth to all our employees.\u00a0\n\nOur values: Hard work, Integrity, Teamwork, Continuous Improvement and Professionalism.\n\n\u00a0Merchandiser (Junior) Position\nWe welcome fresh graduates!\u00a0Serious candidates only. This is a great opportunity to learn a craft, to deal with hundreds of exciting products and suppliers.\u00a0\n\nRequirements:\u00a0\n\nOrganized, highly-motivated, self-disciplined, energetic, willing to accept challenges and willing to learn\nAt least 2-year working experience\u00a0\nGood command of English & Mandarin\u00a0\nStrong computer skills including Microsoft Office (Excel, Word, Power Point). Photoshop is a plus.\u00a0\n\nResponsibilities:\u00a0\n\nAbility to deal with suppliers\u00a0\nAbility to follow missions and precise tasks\u00a0\nAbility to take in charge new projects development\u00a0\nAbility to actively build up and expand the company\u2019s database\u00a0\nAbility to make decisions independently and/or as part\u00a0of a team\n\nInterested parties, please send your resume with expected salary to \u201cApply Now\u201d.\n\nPersonal data collected will be used for recruitment purpose only.", "employment_types": ["Full Time"], "selling_points": ["Ability to deal with suppliers", "Ability to take in charge new projects", "Willing to learn and be committed"], "locations": ["Kwun Tong"], "categories": ["Manufacturing", "Product Development / Management", "Merchandising & Purchasing", "Sundries", "Procurement / Purchasing / Sourcing"], "post_time": "2022-01-13T07:26:37Z", "salary": {"currency": "HKD", "max": 19999, "min": 14000, "period": "monthly", "term": null}, "salary_visible": true, "title_keywords": ["merchandiser", "supervisor", "junior"], "responsibilities": [], "requirements": {"degrees": [], "majors": [], "languages": [], "language_level": [], "hard_skills": [], "soft_skills": [], "languages_combined": []}, "experience_required": {"duration": [], "field": []}}, {"job_id": "100003009045210", "location_code": "hk", "company": "Baum-Essex Manufacturing (HK) Ltd", "job_title": "Quality Assurance & Compliance Co-ordinator (5 Days Work)", "description": "Assist Quality Control Manager in various QC assignments including understanding of clients\u2019 product protocols, quality procedures, lab-tests and production schedule along with factory audits;\nQuality control knowledge and experience in consumable items, particularly Ceramic Table Top, Cutlery/Kitchenware, Beach products, Umbrella, Natural Fiber Storage is preferred;\nBe able to read client manuals outline, summarize important points for QA/QC/Merchandising and co-ordination with factories;\nGood organization and project management skills;\nGood command of written and spoken English / Chinese / Mandarin;\nDiploma or Degree Holder preferred;\nWorking experience: minimum 1-2 years.\n\n\n\nInterested parties, please send your resume, expected salary & the earliest available date by clicking \u201cAPPLY NOW\u201d.\n\nPersonal data collected will be used for recruitment purpose only.", "employment_types": ["Full Time", "Permanent"], "selling_points": ["Assist Quality Control Manager in various QC", "Diploma or Degree Holder preferred", "Working experience: minimum 1-2 years."], "locations": ["Not Specified"], "categories": ["Manufacturing", "Product Development / Management", "Merchandising & Purchasing", "Sundries", "Quality Assurance, Control & Testing / ISO"], "post_time": "2022-01-13T08:04:52Z", "salary": {"currency": null, "max": null, "min": null, "period": "monthly", "term": null}, "salary_visible": false, "title_keywords": [], "responsibilities": ["quality", "procedures", "merchandising", "project management", "schedule", "quality control", "audits"], "requirements": {"degrees": ["diploma", "degree holder"], "majors": [], "languages": ["english", "chinese", "mandarin"], "language_level": ["good command"], "hard_skills": ["project management"], "soft_skills": ["project management skills"], "languages_combined": [{"language": "english", "language_level": ["good command"]}, {"language": "chinese", "language_level": ["good command"]}, {"language": "mandarin", "language_level": ["good command"]}]}, "experience_required": {"duration": ["minimum 1-2 years"], "field": ["quality control"]}}, {"job_id": "100003009036645", "location_code": "hk", "company": "Links International", "job_title": "Hardgoods Merchandiser - Product Developer", "description": "Hardgoods Merchandiser - Product Development\n\nOur client is an international supplies retailer, focusing on pet products including food, toys, bedding, etc. They are looking for a Merchandiser to join their organization, responsible for sourcing, product development, and price negotiation process.\n\nJob Description\n\nDevelop and monitor sourcing strategies and procedures, ensure the vendors is fulfilling the sourcing plans\nSource potential suppliers within Asia to support the company's sourcing plans\nCollaborate with different teams to enhance brand identity and product features, keep track of projects' critical paths\nWork closely with UK Headquarter on category & supplier strategies\nUnderstand the product trends and market insight, develop competitive product ranges\nNegotiate and improve price competitiveness, deliver margin gains, improve payment terms and shipment date\nFollow up sourcing processes and help maintain sourcing systems\nTravel to factories /suppliers for buying trips & new product development\nManage any ad hoc projects, frequent travel to PRC\n\nRequirements\n\nDegree holder or above in the relevant discipline\nExperience of working in a sourcing/buying office is preferable\n2 - 5 years solid experience in developing or sourcing toys, textile or bedding products\nStrong negotiation and presentation skills, attention to details\nGood command of both spoken and written English, Cantonese & Mandarin\nWilling to travel to PRC\n", "employment_types": ["Full Time", "Permanent"], "selling_points": ["Toys, textile / bedding sourcing exp", "Sourcing office exp is preferable", "15days AL + 1 day birthday leave"], "locations": ["Kwun Tong Area"], "categories": ["Manufacturing", "Manufacturing Management", "Product Development / Management", "Merchandising & Purchasing", "Sundries"], "post_time": "2022-01-10T11:38:18Z", "salary": {"currency": "HKD", "max": 24999, "min": 20000, "period": "monthly", "term": null}, "salary_visible": true, "title_keywords": ["merchandiser", "product developer"], "responsibilities": ["collaborate with", "systems", "monitor", "procedures", "teams", "develop", "payment", "maintain", "ad hoc projects", "plans"], "requirements": {"degrees": ["degree holder"], "majors": [], "languages": ["cantonese", "english", "mandarin"], "language_level": ["good command"], "hard_skills": [], "soft_skills": ["presentation skills", "negotiation", "attention to details"], "languages_combined": [{"language": "cantonese", "language_level": ["good command"]}, {"language": "english", "language_level": ["good command"]}, {"language": "mandarin", "language_level": ["good command"]}]}, "experience_required": {"duration": ["2 - 5 years"], "field": ["toys", "developing", "textile"]}}, {"job_id": "100003009047037", "location_code": "hk", "company": "Vitasoy International Holdings Ltd", "job_title": "Group Assistant Regulatory Manager", "description": "Key Responsibilities:\n\n\nKeeps abreast of the updated labeling requirement for local and overseas market\nAssures that all product, packaging, labeling and claims are in regulatory compliance\n\nPrepares local and overseas product labels, declaration letters and product information to relevant departments\nHandles import registration of USA following FDA requirements\nliaisons with\u00a0 internal departments to handle the enquiries from customer related to regulatory requirement\nMaintains regular contact with local and overseas related regulatory authority\nExplains and interprets impact of new food regulations to other plants outside HK\nManages nutrition data base\nWork along with Nutritionist/Dietitian to maintain and develop virtual network of soy nutrition experts from University, research institutions and industries in HK/China, Sg, Aus, USA etc.\nPerforms ad hoc duties assigned\n\nKey Requirements:\n\n\nMinimum 5 years working experience on food/beverage rules and regulations monitoring experiences\nSolid experience in regulatory affairs.\u00a0 Established network with regulators and scientists in region a plus\nGood written and verbal communication skill in English, Cantonese and Putonghua\u00a0\nAbility to focus quickly on priorities and work under pressure with multiple deadlines.\nAbility to work both independently and as a team member.\nCan do attitude with creativity mind\nInterested parties please send your detailed resume stating your available date, current & expected salary to Human Resources Manager, by clicking the \u201cAPPLY NOW\u201d button below.\n\n\n\nAll information provided by applicants will be treated in strict confidence and used only for recruitment purposes. If you do not provide the information mentioned in the advertisement, we may not be able to assess your job application. You have the right to request access to, and correction of, your personal data held by us and you may lodge such request with our Data Protection Officer at pdpo@ vitasoy.com, but any such data access request will only be processed after the completion of the recruitment process.", "employment_types": ["Full Time"], "selling_points": ["5 days work with company shuttle bus", "Handles import registration of USA", "Updated labeling requirement"], "locations": ["Tuen Mun Area"], "categories": ["Sciences, Lab, R&D", "Food Science", "Manufacturing", "Product Development / Management", "Others"], "post_time": "2022-01-14T02:07:19Z", "salary": {"currency": "HKD", "max": 44999, "min": 30000, "period": "monthly", "term": null}, "salary_visible": true, "title_keywords": ["manager", "assistant"], "responsibilities": ["regulations", "ad hoc duties", "data", "compliance", "letters", "develop", "maintain", "contact"], "requirements": {"degrees": [], "majors": [], "languages": ["cantonese", "putonghua", "english"], "language_level": ["good"], "hard_skills": ["plus", "focus"], "soft_skills": ["independently", "communication skill", "focus", "team member", "work under pressure"], "languages_combined": [{"language": "cantonese", "language_level": ["good"]}, {"language": "putonghua", "language_level": ["good"]}, {"language": "english", "language_level": ["good"]}]}, "experience_required": {"duration": ["minimum 5 years"], "field": ["food", "regulatory affairs"]}}, {"job_id": "100003009041988", "location_code": "hk", "company": "Pearson Education Asia Limited", "job_title": "Senior Content Developer / Content Developer (Senior Editor / Editor) - ELT", "description": "We create. We innovate. We reinvent.\u00a0\n\nWe are the world\u2019s leading learning company, with more than 22,500 employees working together to provide\u00a0high-quality\u00a0educational content and learning experiences, as well as assessments and qualifications to nearly 200 countries. We help people build their skills and grow with the world around them.\n\nWith an obsession to best support educators and learners worldwide, we never stop\u00a0perfecting\u00a0our educational products and services.\n\nWe now invite applications from passionate individuals to join the Pearson family:\n\nMain Responsibilities\nReview and understand the approved instructional design, syllabus, course configuration, content map, budget, and schedule from supervisors\nReview quality of all contracted work; provide feedback to Content Developers, writers, freelancers or vendors on any recurring issues related to content creation; when necessary under deadline, bring quality of content up to standard through development and revision\nCollaborate closely with in-house designers, Project Management & Support team, photo and text researchers, rights managers before and during all phases of content production\nDevelop content for specific components including both print or digital products\nProvide continuous and consistent support to Content Developers, writers, freelancers or vendors throughout the writing and content development process\nJob Requirements\nUniversity/College degree in English Language, Linguistics or Translation, with relevant content development experience\nGood organisational and time management skills\nAbility to take on responsibility and work independently\nAbility to juggle multiple priorities and deadlines, remaining pragmatic and results-focused\nExcellent written and verbal communication skills and interpersonal skills\nA keen eye for detail\nFamiliar with local curriculum and public exams\n\nA competitive package including 5-day work, medical and dental benefits will also be offered to the right candidate.\n\nInterested parties may submit your\u00a0full resume via Apply Now.\n\nAll personal data provided will be treated in strict confidence and be used for recruitment purposes within the Pearson Group only. Information on unsuccessful candidates will be destroyed within 2 years.", "employment_types": ["Full Time", "Permanent"], "selling_points": ["5 days work, Flexible working hours", "13 months salary", "Performance bonus"], "locations": ["Quarry Bay"], "categories": ["Media & Advertising", "Editorial / Journalism", "Education", "Others", "Manufacturing", "Product Development / Management"], "post_time": "2022-01-12T05:00:56Z", "salary": {"currency": null, "max": null, "min": null, "period": "monthly", "term": null}, "salary_visible": false, "title_keywords": ["editor", "developer", "senior editor"], "responsibilities": ["collaborate", "configuration", "review", "budget", "quality", "design", "develop", "project management", "schedule"], "requirements": {"degrees": ["degree"], "majors": [], "languages": ["english"], "language_level": [], "hard_skills": ["translation"], "soft_skills": ["communication skills", "work independently", "focused", "time management skills", "keen", "interpersonal skills", "eye for detail"], "languages_combined": [{"language": "english", "language_level": []}]}, "experience_required": {"duration": [], "field": ["content development"]}}, {"job_id": "100003009042893", "location_code": "hk", "company": "JS Hometech Co Limited", "job_title": "Assistant Merchandiser / Merchandiser (Korean Speaking)", "description": "Job Description & Responsibilities:\n\n\nOrders follow up from product development, sampling, production orders to delivery\nLiaise with factories customers (mostly in Korea and Japan)\nWork closely with suppliers for issue settlement during production process\nMaintain and update production record\nTravel to China occasionally\nAd hoc job is required\n\nRequirements:\n\n\nDiploma or above in any disciplines\n\nAt least 3 years relevant experience in Electric Home Appliance industry is highly preferred\nProficiency in spoken and written Mandarin and Korean\nGood interpersonal and communication skills, well-organized, patient, self-initiative\nLess experience will be considered as Assistant Merchandiser\n\nInterested candidates please email full resume with CURRENT & EXPECTED SALARIES and AVAILABLE DATE by clicking \u201cApply Now\u201d button\n~No Agency Please\n~No phone calls to us about the application is appreciated\n~Our job ad is posted on JobsDB only", "employment_types": ["Full Time", "Permanent"], "selling_points": ["3 years experience in home appliances", "Korean Speaker", "Project follow up"], "locations": ["Hung Hom"], "categories": ["Manufacturing", "Product Development / Management", "Merchandising & Purchasing", "Home Appliances", "Sundries"], "post_time": "2022-01-12T09:10:05Z", "salary": {"currency": null, "max": null, "min": null, "period": "monthly", "term": null}, "salary_visible": false, "title_keywords": ["merchandiser", "assistant merchandiser"], "responsibilities": ["liaise with", "ad hoc", "maintain", "production process"], "requirements": {"degrees": ["diploma or above"], "majors": ["any disciplines"], "languages": ["mandarin", "korean"], "language_level": ["proficiency"], "hard_skills": [], "soft_skills": ["communication skills", "well-organized", "self-initiative", "patient", "interpersonal"], "languages_combined": [{"language": "mandarin", "language_level": ["proficiency"]}, {"language": "korean", "language_level": ["proficiency"]}]}, "experience_required": {"duration": ["at least 3 years"], "field": ["relevant experience"]}}, {"job_id": "100003009047412", "location_code": "hk", "company": "Hong Kong Applied Science and Technology Research Institute Company Limited (ASTRI)", "job_title": "Optics - Senior Engineer / Engineer", "description": "Reference #:\u00a0CTO/IOTSEN/15\nJob Responsibilities\n\n\nFor the research and development of advance optical system design and prototyping, including imaging / non-imaging optical design for machine vision, 3D reconstruction and medical imaging\nDefine optical specifications, design analyses, risk analysis with contingency plans, design reviews, manufacturability assessments, verification of design durability and reliability, vendor survey, schedule control and prototype verification\nEvaluating and implementing customer requirements in an optical engineering environment\nResolve technical problems related to optics. Optical system improvement; new optical technology research and development, IP development of core technologies\nAssist in optical testing, assembly, alignment, and debugging\nRequirements\nPh.D. holder or Master\u2019s degree in Optical Engineering, Applied Optics, Physics, Bio-optics or relevant disciplines with a minimum of 3 years of related experience. Candidate with fewer experience may also be considered.\nExperience of both imaging optical system and non-imaging optical system design and production\nKnowledge with optical design software tools such as Zemax, CodeV, LightTools or TracePro, etc.\nKnowledge with optical design for machine vision application, 3D reconstruction, medical imaging, confocal optical design, OCT, etc.\nGood command of written and spoken English, self-motivated and good communication skills\nApplication\n\nThe appointment will be on renewable contract terms with a competitive salary and performance-linked variable pay. Fringe benefits include paid leave, medical and dental benefits, insurance coverage and contribution to MPF. The incumbent will normally work\u00a0a five-day week.\n\nInterested candidates, please send an application (quoting Ref. No.) with a detailed resume, current and expected salary to\u00a0Talent Acquisition by clicking \"APPLY NOW\".\u00a0The resume should\u00a0not\u00a0include any sensitive personal information such as HKID or passport number, photo, etc.\u00a0\n\nPosition offer is subject to the applicant\u2019s experience and academic qualification. The application will be open until the position is filled. Only short-listed candidates will be notified. ASTRI reserves the right not to fill the position.\n\nASTRI is an Equal Opportunities Employer. Personal data provided by job applicants will be used\u00a0exclusively\u00a0for recruitment\u00a0only. For details, please refer to\u00a0Privacy - ASTRI - Hong Kong Applied Science and Technology Research Institute Company Limited, in particular section 9.", "employment_types": ["Full Time", "Contract"], "selling_points": ["Optics", "Define optical specifications, design analyses", "Advance optical system design"], "locations": ["Shatin Area"], "categories": ["Engineering", "Manufacturing & Production", "Information Technology (IT)", "Others", "Manufacturing", "Product Development / Management"], "post_time": "2022-01-14T03:01:34Z", "salary": {"currency": null, "max": null, "min": null, "period": "monthly", "term": null}, "salary_visible": false, "title_keywords": ["senior engineer", "engineer"], "responsibilities": ["control", "design", "testing", "specifications", "system design", "risk analysis", "schedule", "plans"], "requirements": {"degrees": ["degree", "master"], "majors": ["engineering", "physics"], "languages": ["english"], "language_level": ["good command", "good"], "hard_skills": ["system design"], "soft_skills": ["communication skills", "self-motivated"], "languages_combined": [{"language": "english", "language_level": ["good", "good command"]}]}, "experience_required": {"duration": ["minimum of 3 years"], "field": ["related", "system design", "engineering"]}}, {"job_id": "100003009044843", "location_code": "hk", "company": "FWD Life Insurance Company (Bermuda) Limited", "job_title": "Director, Product Development & Management", "description": "Established in Asia in 2013 with a trailblazer mentality, FWD is the primary insurance business of investment group, Pacific Century Group (PCG), with minority shareholders Swiss Re Group, GIC Ventures, RRJ Capital and Hopu Investments.\n\nFWD spans 10 markets in Asia including Hong Kong SAR & Macau SAR, Thailand, Indonesia, the Philippines, Singapore, Vietnam, Japan, Malaysia and Cambodia. In Hong Kong, FWD offers life and medical insurance, general insurance, employee benefits, and financial planning. We focus on creating fresh customer experiences and making the insurance journey simpler, faster and smoother, with innovative propositions and easy-to-understand products, supported by digital technology. Through this customer-led approach, FWD aims to be a leading pan-Asian insurer by changing the way people feel about insurance.\n\nIf you are looking for a company where can fuel your inspiration and cultivate your expertise, join us on our exciting journey.\n\nThe Job:\n\nDrive product development including the full project cycle from product idea generation to product launch implementation\nBe customer centric and provide business insight on the market trend to senior management on product decision\nManage various stakeholders, including distribution channels, IT, operations, risk and compliance to ensure successful product launch\nLead and coach teammates on product related duties Lead a d-hoc projects and other duties as required\n\nThe Person:\n\nUniversity degree\nAt least 10 years of work experience (with at least 5 years of experience in manager level or above) relating to insurance product development and/or marketing\nCandidates with less experience will be considered as Senior Manager / Associate Director\nStrong interpersonal skills to work with different parties\nGood command of English and Chinese language\nAttention to details and good time management skills\n\nWe offer 5-day work, 20-22 days annual leaves, excellent learning & development opportunities and an attractive package to the right candidate.\n\nInformation collected will be treated in strict confidence and used solely for recruitment purpose. The company will retain all applications no longer than 24 months of which will be destroyed thereafter. When there are vacancies in any of our subsidiaries, holding companies, associated or affiliated companies of, or companies controlled by, or under common control with the Company during that period, we may transfer your application to them for consideration of employment. We are an equal opportunity employer. We do not discriminate on the basis of race, sex, disability or family status in employment process.", "employment_types": ["Full Time"], "selling_points": ["Drive product development", "Be customer centric and provide business insight", "Lead and coach teammates on product related duties"], "locations": ["Wan Chai"], "categories": ["Manufacturing", "Product Development / Management"], "post_time": "2022-01-13T06:26:58Z", "salary": {"currency": null, "max": null, "min": null, "period": "monthly", "term": null}, "salary_visible": false, "title_keywords": ["product development", "director"], "responsibilities": [], "requirements": {"degrees": [], "majors": [], "languages": [], "language_level": [], "hard_skills": [], "soft_skills": [], "languages_combined": []}, "experience_required": {"duration": [], "field": []}}, {"job_id": "100003009041996", "location_code": "hk", "company": "Pearson Education Asia Limited", "job_title": "Senior Content Developer / Content Developer (Senior Editor / Editor) - BAFS/Econ", "description": "We create. We innovate. We reinvent.\u00a0\n\nWe are the world\u2019s leading learning company, with more than 22,500 employees working together to provide\u00a0high-quality\u00a0educational content and learning experiences, as well as assessments and qualifications to nearly 200 countries. We help people build their skills and grow with the world around them.\n\nWith an obsession to best support educators and learners worldwide, we never stop\u00a0perfecting\u00a0our educational products and services.\n\nWe now invite applications from passionate individuals to join the Pearson family:\n\nMain Responsibilities\n\nCarry out editorial work for print and digital products and ensures the highest quality of work is achieved.\nLiaise with authors, artists and designers to ensure timely production of assigned titles.\nCollaborate with marketing, sales and portfolio teams in market research, promotion and sales activities.\nJob Requirements\n\n\nUniversity degree in Economics, Finance, Business and Management Studies, Marketing, Accountancy or related disciplines\nExcellent command of both English and Chinese\nGood organisation, time management and communication skills\nStrong interest for a career in education and a keen eye for details\nExperience in textbook editing is preferred\nGood knowledge in IT and digital publishing is an advantage\nFamiliarity with the Senior Secondary Economics or BAFS curriculum is an advantage\nCandidates with better experience will be considered for the post of Senior Content Developer\n\nA competitive package including 5-day work, medical and dental benefits will also be offered to the right candidate.\n\nInterested parties may submit your\u00a0full resume via Apply Now.\n\nAll personal data provided will be treated in strict confidence and be used for recruitment purposes within the Pearson Group only. Information on unsuccessful candidates will be destroyed within 2 years.", "employment_types": ["Full Time", "Permanent"], "selling_points": ["5 days work, Flexible working hours", "13 months salary", "Performance bonus"], "locations": ["Quarry Bay"], "categories": ["Media & Advertising", "Editorial / Journalism", "Education", "Others", "Manufacturing", "Product Development / Management"], "post_time": "2022-01-12T05:05:04Z", "salary": {"currency": null, "max": null, "min": null, "period": "monthly", "term": null}, "salary_visible": false, "title_keywords": ["editor", "developer", "senior editor"], "responsibilities": ["collaborate with", "sales activities", "teams", "quality", "market research", "liaise with"], "requirements": {"degrees": ["university degree"], "majors": ["finance", "economics", "accountancy", "related disciplines", "business", "marketing"], "languages": ["english", "chinese"], "language_level": ["excellent"], "hard_skills": [], "soft_skills": ["communication skills", "time management", "organisation", "keen"], "languages_combined": [{"language": "english", "language_level": ["excellent"]}, {"language": "chinese", "language_level": ["excellent"]}]}, "experience_required": {"duration": [], "field": ["developer", "editing"]}}, {"job_id": "100003009047499", "location_code": "hk", "company": "Manulife (International) Limited", "job_title": "MPF Speicalist / Marketing Trainee", "description": "Manulife (International) Limited\n\n- On-the-Job training, friendly working environment\n- Flexible working hours, 5-days working week\n- Overseas travel incentives, excellent career development\n- 2 years working experience, fresh grad also welcome\n- Basic knowledge in MPF, interested in working with people\n\n", "employment_types": ["Full Time"], "selling_points": [], "locations": ["Ngau Tau Kok"], "categories": ["Accounting", "Accounting Clerk / Supervisor", "Manufacturing", "Product Development / Management", "Management", "Management Trainee"], "post_time": "2022-01-14T03:20:30Z", "salary": {"currency": null, "max": null, "min": null, "period": "monthly", "term": null}, "salary_visible": false, "title_keywords": ["trainee"], "responsibilities": ["mpf", "career development"], "requirements": {"degrees": [], "majors": [], "languages": [], "language_level": [], "hard_skills": ["basic"], "soft_skills": ["flexible", "interested in", "friendly"], "languages_combined": []}, "experience_required": {"duration": ["2 years"], "field": []}}, {"job_id": "100003009035694", "location_code": "hk", "company": "Newsprint Production Group Ltd", "job_title": "Product Developer", "description": "Roles & Responsibilities\n\n\nPerform day-to-day duties, such as following up on development and sample orders, work with customer & team to get the work done within a deadline.\nCoordinate - Maintain continuous and agile communication with design, production merchandising, Logistic & third-party partners to align and synchronize content.\nCoordinating Sample Development with factories to ensure final product is as per customer requirements.\nAssist on production planning with Sales / Merchandising for product style, quantity, delivery date etc. for factory planner to gauge the capacity for bulk production.\nCalculate costings through existing tools and maintenance of database.\nMaintain relationship & smooth communication with suppliers.\nAd hoc assignments for communication and certification purpose (FSC, OEKO TEX, etc)\n\nRequirements\n\n2-3 years of relevant experience working a R&D / Product Merchandiser.\nHigher Diploma in Textile Merchandising, Fashion Technology, or related discipline.\nGood communication skills in spoken and written English and Chinese (Mandarin preferably).\nProficiency in PC skills, such as MS Office (Excel, Word, PPT) - Chinese and English word processing.\nGood analytical skills.\nCapability to prioritize work and manage several projects at a time.\nPrior knowledge in printing, labels and/or packaging industry will be a plus, but not necessary.\nBe flexible and adaptable to a challenging working environment.\nImmediate availability is an advantage.", "employment_types": ["Full Time", "Permanent"], "selling_points": ["2-3 years of relevant experience working", "Spoken & Written English & Mandarin, PC Skill", "Double pay, medical, dental insurance"], "locations": ["Chai Wan"], "categories": ["Manufacturing", "Garment / Textile", "Product Development / Management", "Printing"], "post_time": "2022-01-10T08:11:48Z", "salary": {"currency": null, "max": null, "min": null, "period": "monthly", "term": null}, "salary_visible": false, "title_keywords": ["product developer"], "responsibilities": ["maintenance", "merchandising", "production planning", "design", "coordinate", "communication", "maintain", "ad hoc assignments", "database"], "requirements": {"degrees": ["diploma"], "majors": [], "languages": ["english", "chinese", "mandarin"], "language_level": ["proficiency", "good"], "hard_skills": ["r&d", "excel", "plus", "chinese and english word processing", "word", "analytical skills", "pc skills", "ms office"], "soft_skills": ["flexible", "communication skills", "adaptable", "prioritize", "analytical skills"], "languages_combined": [{"language": "english", "language_level": ["proficiency", "good"]}, {"language": "chinese", "language_level": ["proficiency", "good"]}, {"language": "mandarin", "language_level": ["good"]}]}, "experience_required": {"duration": ["2-3 years"], "field": ["relevant experience"]}}, {"job_id": "100003009043230", "location_code": "hk", "company": "Prime Group", "job_title": "Digital Content Marketing Officer", "description": "Our client\u00a0is a technology and IoT company changing the world with the most innovative smart home solutions, taking ordinary experiences and making them extraordinary. They are looking for Digital Content Marketing Officer.\u00a0\n\nHighlight:\n\nFlexible working hour and work from home arrangement\nChinese and English is required\nLocation: Central\n\n\nJob description:\n\nVisual content creation - photos / video shooting, production and edition for contents needed for the posting on websites, SEO, Ads copies, and different social media like FB; IG; Twitter and others.\nGenerating assets for print and digital mediums with deliverables including social media content, email marketing, pitch decks, ad copywriting, signage, product mockups for B2B & B2C clients and other branding communication materials\nWorking closely with our JAPAC and global marketing teams to support sales efforts in Australia and New Zealand\nDigital online marketing planning and execution for Internal Projects\nEnsuring brand consistency across all materials\nMaintaining the company's organization visual assets on social media channels\nDevelop content strategy across different channels\nManage major B2C e-commerce online platforms, e.g. list and update product listings, update price\nUpdate the information of sales platform, social media platforms\nCoordinate and support other countries as required\n\nRequirements:\n\n2 years related experience in content marketing/ copywriting\nExcellent languages in Chinese and English (Writing and reading)\nKnowledge of photoshop, illustrator and video editing\nProactive, result oriented, self-motivated, able to multi-task\nPassionate, creative and resourceful\nInterested parties please click \"apply now\" button.", "employment_types": ["Permanent"], "selling_points": ["Flexible working hour and work from home arrangeme", "Chinese and English is required", "Location: Central"], "locations": ["Central"], "categories": ["Manufacturing", "Product Development / Management"], "post_time": "2022-01-12T10:18:35Z", "salary": {"currency": null, "max": null, "min": null, "period": "monthly", "term": null}, "salary_visible": false, "title_keywords": ["marketing officer"], "responsibilities": ["social media", "seo", "maintaining", "social media platforms", "teams", "product listings", "develop", "communication", "coordinate", "video shooting", "social media content", "visual", "contents", "brand consistency", "planning"], "requirements": {"degrees": [], "majors": [], "languages": ["english", "chinese"], "language_level": ["excellent"], "hard_skills": ["video editing", "illustrator", "photoshop"], "soft_skills": ["passionate", "self-motivated", "multi-task", "creative", "resourceful", "result oriented", "proactive"], "languages_combined": [{"language": "english", "language_level": ["excellent"]}, {"language": "chinese", "language_level": ["excellent"]}]}, "experience_required": {"duration": ["2 years"], "field": ["related", "copywriting", "marketing"]}}, {"job_id": "100003009029709", "location_code": "hk", "company": "Creative China Creations Limited", "job_title": "Sourcing Coordinator/ Merchandiser /Sr. Merchandiser /Product Manager (Consumer Products/ Sundries)", "description": "Job Requirements:\u00a0\n\nMinimum 5 years merchandising or relevant experience in Trading or Manufacturing Company. (Sourcing, Product development experience)\nMotivated, Organized, and able to work efficiently to meet the deadlines of buyers\nEXCELLENT COMMAND IN WRITTEN & SPOKEN ENGLISH, CANTONESE & MANDARIN SKILLS\nAble to communicate with suppliers and overseas customers\nResponsible, willing to learn, exhibit a positive attitude and work overtime\nExcellent knowledge of product cost breakdown and production process.\nProficient in material sourcing and supplier evaluation and management.\nExcellent and successful in price negotiation and problem solving skills\nTravel to China for supplier evaluation, management, follow-up, and inspection.\nProficient in PC applications (Microsoft Word, Excel, Microsoft Office applications).\nAn analytical and strategic thinker who is efficient, organized, and attentive to details and able to motivate staff and work under time deadlines.\nStrong sourcing skills and network of potential suppliers that allows the company to source directly through the most cost efficient and competent factories.\nCommunicate clearly to suppliers, including lead time, capacity allocation, pricing and resource allocation to ensure reliable service, quality and low-cost procurement.\nCoordinate with factories for manufacturing process and ensure on time shipment\nSelf-motivated, detailed oriented, a team player and able to work under pressure.\u00a0\nExperienced to supervise merchandising team, & be a team leader.\nCustomer-oriented, effective interpersonal and communication skills\nAble to work independently or part of a team with overseas customers and vendors\nEffectively manage and review vendor base for optimal sourcing results and possess an extensive sourcing network and excellent relationships with vendors.\nProduct management including product development, product selection, Target Negotiation, placement order, pricing.\nAnalyze the marketplace, customers and competitors to determine the right features to bring to market\u00a0\u00a0\nDaily communications with buyers, laboratories and vendors, following through all samples, testing, production to shipments\nEnsuring an effective merchandising value chain which produces goods in good quality standard and meet tight delivery\nGood sourcing experience for USA and EU markets and are familiar with sourcing Websites such as Alibaba.com, globalsources.com, and other sourcing sites.\nA team leader who exhibits leadership qualities and is able to work under pressure and within time constraints.\nPermanent Hong Kong ID card Holder.\nFlexible working times and willing to work after hours if needed.\n\n\nKey responsibilities:\n\nTake the lead in the end-to-end product sourcing cycle from product development, price negotiation to production of consumer products\nWork with the buyers to understand the product and order requirement\nCommunicate with vendors and factories to ensure on-time delivery and resolve any potential problems\nExecute and review existing internal systems and policies to ensure smooth operations and meeting company standards\n\n\nKey requirements:\n\nDegree/Diploma holder, with at least 5 years of relevant experience\nGood understanding on global Markets\nExcellent command in Cantonese, English and Mandarin\nGood communication and interpersonal skills to work with counterparts\nAble to work independently and meet tight deadlines\nProficient in computer skills and MS Office Applications\n\n\nInterested applicants please send your English application along with cover letter and detailed resume with current and expected salary clearly stated to \u201cApply Now\u201d.\n\nAll Personal data collected will be used for recruitment purpose only.", "employment_types": ["Full Time", "Permanent"], "selling_points": ["double pay and performance bonus", "Good understanding on global markets", "With at least 5 years of relevant experience"], "locations": ["Ngau Tau Kok"], "categories": ["Manufacturing", "Product Development / Management", "Merchandising & Purchasing", "Sundries", "Procurement / Purchasing / Sourcing"], "post_time": "2022-01-10T16:52:34Z", "salary": {"currency": null, "max": null, "min": null, "period": "monthly", "term": null}, "salary_visible": false, "title_keywords": ["merchandiser", "product manager", "coordinator", "sr. merchandiser"], "responsibilities": ["communicate with", "price negotiation", "policies", "review", "communication", "recruitment", "ensure smooth operations", "personal data", "internal systems"], "requirements": {"degrees": [], "majors": [], "languages": ["cantonese", "english", "mandarin"], "language_level": ["excellent"], "hard_skills": ["excel", "microsoft word", "microsoft office", "id", "vendor", "pc applications", "problem solving skills"], "soft_skills": ["work overtime", "team player", "leadership", "work under pressure", "efficient", "customer-oriented", "reliable", "interpersonal", "organized", "communication skills", "work independently", "negotiation", "competent", "willing to learn", "extensive", "flexible", "self-motivated", "detailed oriented", "responsible", "attentive to details", "positive attitude", "motivated", "problem solving skills"], "languages_combined": [{"language": "cantonese", "language_level": ["excellent", "excellent"]}, {"language": "english", "language_level": ["excellent", "excellent"]}, {"language": "mandarin", "language_level": ["excellent", "excellent"]}]}, "experience_required": {"duration": ["minimum 5 years"], "field": ["manufacturing", "merchandising", "relevant experience", "product development", "trading"]}}, {"job_id": "100003009033157", "location_code": "hk", "company": "Lynns Limited", "job_title": "Product Development Manager", "description": "Responsibilities:\n\nIdentify and develop new products based on customers\u2019 perspective, products research and data analysis.\nLead the product team from the product development, order execution to shipment.\nCollaborate closely with internal parties to ensure the procurement of new potential products, the availability of products and the quality standard of content creation for global strategy.\nCollaborate with external suppliers, ensure business and creativity accurately reflected in our products.\nEvaluate and optimize the vendor base. Measure supplier performance and capacity in order to make the right sourcing decisions.\nOverall manage and follow up on responsible projects, make sure new product development and upgrading meet timely deliveries, with quality and cost effectiveness.\nEngage with customers to understand strategies and objectives.\nPerform and handle other ad hoc projects as assigned.\n\nRequirements:\n\nBachelor with a major in product designs / development / engineering / business preferred\nWork experience in product companies, especially in consumer products, preferably in product design / development / engineering\nKnowledge of photo software, 3D software, engineering management\nProficient in MS Office Suite, strong Excel skills\nExcellent interpersonal skills, communication as with global offices\nExcellent in written and spoken English, Mandarin and Cantonese\nIndependent work, decision making and comfortable with remote work\nImmediate availability or short notice will be an advantage", "employment_types": ["Full Time"], "selling_points": [], "locations": ["Wan Chai"], "categories": ["Manufacturing", "Manufacturing Management", "Product Development / Management", "Merchandising & Purchasing", "Procurement / Purchasing / Sourcing"], "post_time": "2022-01-08T11:30:50Z", "salary": {"currency": null, "max": null, "min": null, "period": "monthly", "term": null}, "salary_visible": false, "title_keywords": ["product development manager"], "responsibilities": ["collaborate", "collaborate with", "cost", "quality", "develop", "data analysis", "evaluate", "ad hoc projects", "products research", "internal parties"], "requirements": {"degrees": ["bachelor"], "majors": ["business", "engineering"], "languages": ["cantonese", "english", "mandarin"], "language_level": ["excellent"], "hard_skills": ["3d software", "excel", "ms office"], "soft_skills": ["communication", "independent", "interpersonal skills", "decision making"], "languages_combined": [{"language": "cantonese", "language_level": ["excellent"]}, {"language": "english", "language_level": ["excellent"]}, {"language": "mandarin", "language_level": ["excellent"]}]}, "experience_required": {"duration": [], "field": ["development", "product design", "engineering"]}}, {"job_id": "100003009035974", "location_code": "hk", "company": "Wolf 1834, Limited", "job_title": "Senior Merchandiser", "description": "Job Description\n\n- Job details are as follows:\n\nHandle hard goods including watch winder, jewellery box, small leather goods, watch box, tray and handbags\nLiaise between factories and overseas offices\nTravel to China for sourcing, factory visits, meetings and inspections\nRespond emails daily\nSource materials and factories\nHandle product development\nManage orders and paper work\nConduct pre-production document and meeting with factories\nMonitor factories to assure the quality level\nConduct inline inspection at the factories\nFollow up factory audit\n\n\n-\u00a0Candidate has to have about 5 years of relevant work experience\n\n- Candidate experiences in trading or manufacturing company is required. No experience in hard-lines will not be considered\n\n- Candidate has experience in branded leather goods as an advantage\n\n- Candidate has experience in inspection as an advantage\n\n- Candidate must have high proficiency in English, Mandarin & Cantonese\n\n- Proficient in MS Office is a must\n\n\n- Candidate has to be hardworking, independent, communicative, initiative, detail-minded and responsible\n\n- Candidate has to work with a small team closely", "employment_types": ["Full Time", "Permanent"], "selling_points": ["Double Pay & Performance bonus", "Travel to China often when there is no quarantine", "5-day work"], "locations": ["Lai Chi Kok"], "categories": ["Manufacturing", "Product Development / Management", "Merchandising & Purchasing", "Sundries", "Procurement / Purchasing / Sourcing"], "post_time": "2022-01-10T09:12:31Z", "salary": {"currency": "HKD", "max": 29999, "min": 20000, "period": "monthly", "term": null}, "salary_visible": true, "title_keywords": ["senior merchandiser"], "responsibilities": ["liaise", "monitor", "quality", "audit", "inspection", "pre-production"], "requirements": {"degrees": [], "majors": [], "languages": ["cantonese", "english", "mandarin"], "language_level": ["proficiency"], "hard_skills": ["small", "no", "ms office"], "soft_skills": ["detail-minded", "independent", "responsible", "initiative", "hardworking"], "languages_combined": [{"language": "cantonese", "language_level": ["proficiency"]}, {"language": "english", "language_level": ["proficiency"]}, {"language": "mandarin", "language_level": ["proficiency"]}]}, "experience_required": {"duration": ["5 years"], "field": ["manufacturing", "trading"]}}, {"job_id": "100003009048055", "location_code": "hk", "company": "Edwin McAuley Electronics Ltd", "job_title": "Senior Electronic Engineer/ Electronic Engineer (Welcome Fresh graduates)", "description": "This role is exceptionally challenging because it requires both technical knowledge of electronics manufacturing and the ability to communicate empathetically with internal and external parties.\u00a0\n\nJob Responsibilities:\u00a0\n\n\nResearch, design and development of electronics product\nWork cover the development process from product definition to product launch to the market\nResponsible to electronics hardware design\nProduct testing and evaluation\nParticipate in real production.\nOccasional travel in mainland or overseas may be required\n\nJob Requirements:\u00a0\n\nUniversity Degree in Electrical/Electronic Engineering or related disciplines\nUnderstanding electronic component and hardware circuitry is must\nKnowledge in test equipment and skills is must\nExperience in embedded design and microcontrollers application is preferred\nKnowledge of industrial quality requirements and safety standards is preferable\nGood command of Chinese and English\nCandidate with more experience will be considered as Senior Electronic Engineer\nFresh graduates are welcome\u00a0 \u00a0 \u00a0 \u00a0 \u00a0 \u00a0 \u00a0 \u00a0 \u00a0 \u00a0 \u00a0 \u00a0 \u00a0 \u00a0\n\nWe place much emphasis on the career development of our employees, respect the worthiness of individual contributions and expect strong commitment to performance excellence. We offer 5 days work per week, competitive remuneration package and fringe benefits including year-end and mid-year bonuses, medical scheme, life & accident insurance etc to the right candidate.\n\n\nInterested parties please send full resume stating current salary, expected salary and availability via JobsDB apply now.\n\nAll information received will strictly be kept confidential and be used for employment-related purposes only.", "employment_types": ["Full Time", "Permanent"], "selling_points": ["Knowledge in electronic component applications", "Experience in embedded software or MCU system", "5-day work week, mid-year bonus & double pay"], "locations": ["North Point"], "categories": ["Engineering", "Electrical / Electronics", "Manufacturing & Production", "Manufacturing", "Product Development / Management"], "post_time": "2022-01-14T04:37:08Z", "salary": {"currency": null, "max": null, "min": null, "period": "monthly", "term": null}, "salary_visible": false, "title_keywords": ["senior electronic engineer", "electronic engineer"], "responsibilities": ["hardware", "evaluation", "design", "testing"], "requirements": {"degrees": ["university degree"], "majors": ["related disciplines", "engineering"], "languages": ["english", "chinese"], "language_level": ["good command"], "hard_skills": ["hardware", "scheme"], "soft_skills": [], "languages_combined": [{"language": "english", "language_level": ["good command"]}, {"language": "chinese", "language_level": ["good command"]}]}, "experience_required": {"duration": [], "field": ["design"]}}, {"job_id": "100003009038368", "location_code": "hk", "company": "Samsung Electronics HK Co Ltd", "job_title": "Field Service Engineer", "description": "Responsibilities\u00a0\n\nManaging the implementation and delivery of enterprise business services and ongoing service account management for key B2B customers\nDevelop enterprise business services specification for customers and manage the analysis, proposition, and implementation of product roll out\nManage the services elements for enterprise business fulfillment - Investigate \u201cin field\u201d product technical faults to provide explanation of route cause, technical resolutions, escalation, and reporting to HQ\nSet performance criteria across Enterprise Business Service Partner network and ensure high performance at all time. Requirements\n\nRequirements\n\nDegree or above in Electronics/Electrical Engineering or equivalent\n5 years of experience in product supporting\nKnowledge in Printer/Monitor/TV/ AV product\nProficient in PC Skills (MS Excel and PowerPoint)\nHardworking and self-motivated\nGood command of both written and spoken English and Chinese\n\nWe offer attractive remuneration package to the right candidate. Interested parties please send us full resume in MS WORD format stating current and expected salary.\n\nOur company is an equal opportunities employer and welcome application from all qualified candidates. The data provide will only be used for consideration of the applied position or other suitable position in Samsung Electronics HK Co. Ltd. or other subsidiaries of Samsung Group.\n\nApplicants who are not invited for interview within 10 weeks should consider their applications unsuccessful. Personal data of unsuccessful applicant will be destroyed within 6 months.\n\n\"Personal data collected will be used for recruitment purpose only.\"", "employment_types": ["Full Time", "Permanent"], "selling_points": ["Field Service", "Printer/Monitor/TV/ AV product", "Product Engineer"], "locations": ["Wan Chai"], "categories": ["Engineering", "Electrical / Electronics", "Manufacturing", "Product Development / Management"], "post_time": "2022-01-11T06:41:48Z", "salary": {"currency": null, "max": null, "min": null, "period": "monthly", "term": null}, "salary_visible": false, "title_keywords": ["service engineer"], "responsibilities": ["reporting", "management", "fulfillment", "analysis", "implementation", "develop"], "requirements": {"degrees": ["degree or above"], "majors": ["electrical engineering"], "languages": ["english", "chinese"], "language_level": ["good command"], "hard_skills": ["ms excel", "pc skills", "powerpoint"], "soft_skills": ["self-motivated", "hardworking"], "languages_combined": [{"language": "english", "language_level": ["good command"]}, {"language": "chinese", "language_level": ["good command"]}]}, "experience_required": {"duration": ["5 years"], "field": []}}, {"job_id": "100003009037170", "location_code": "hk", "company": "ASM Technology Hong Kong Limited", "job_title": "Product/ Industrial Designer Engineer", "description": "Job description\nClosely interact with production on product cosmetic and fabrication process\nSupport on product usability and ergonomic design development\nDesign product graphic and logo\nEnable systematic approach to facilitate user experience, ergo and machine compliance.\nJob requirements\nDegree or above in Industrial/ Product Design/ Mechanical / Manufacturing engineer or relative disciplines\nRelevant working experience in industrial design on User-Centered Design approach\nProficient on SolidEdge/ SolidWorks and Keyshot rendering skill\nGeneral understanding of sheet metal fabrication process\nGeneral understanding in graphical and interface design will be an advantage\nGood problem-solving skill\n\nAttractive salary and fringe benefits package will be offered to the right candidates.\n\nInterested parties please submit your application with cover letter, resume, certificate and transcripts.\n\nData collected will be used for recruitment purpose only. Suitable candidates may be referred to other vacancies within our company.", "employment_types": ["Full Time", "Permanent"], "selling_points": ["Degree or higher in Industrial / Product Design", "Relevant working experience in industrial design", "Design product graphic and logo"], "locations": ["Tsing Yi"], "categories": ["Engineering", "Manufacturing & Production", "Others", "Manufacturing", "Product Development / Management"], "post_time": "2022-01-11T01:58:16Z", "salary": {"currency": null, "max": null, "min": null, "period": "monthly", "term": null}, "salary_visible": false, "title_keywords": ["industrial designer engineer"], "responsibilities": ["compliance", "user experience", "design"], "requirements": {"degrees": ["degree or above"], "majors": ["manufacturing", "design"], "languages": [], "language_level": [], "hard_skills": ["problem-solving", "solidworks"], "soft_skills": ["problem-solving"], "languages_combined": []}, "experience_required": {"duration": [], "field": ["relevant working experience", "design"]}}, {"job_id": "100003009039333", "location_code": "hk", "company": "Advance Pharmaceutical Company Limited", "job_title": "Production Officer", "description": "To assist in developing, implementing and maintaining the documentation system, including the Standard Operating Procedures (SOPs) and other production documents\nTo ensure and maintain the adequate and accurate records for controlling and monitoring conformity to specified GMP and statutory requirements\nTo assist monitor the production process according to the production plan\nTo assist in performing investigation to production deviation\nTo perform the daily operation and ad-hoc functions of Production Department\nTo assist the head of production to monitor the daily production workflow", "employment_types": ["Full Time"], "selling_points": [], "locations": ["Tai Po Area"], "categories": ["Manufacturing", "Manufacturing Management", "Product Development / Management", "Medical Services", "Pharmaceutical"], "post_time": "2022-01-11T09:27:01Z", "salary": {"currency": null, "max": null, "min": null, "period": "monthly", "term": null}, "salary_visible": false, "title_keywords": ["production officer"], "responsibilities": ["ad-hoc", "production process", "maintaining", "monitoring", "procedures", "developing", "monitor", "investigation", "daily operation", "statutory requirements", "maintain", "sops", "plan", "documentation"], "requirements": {"degrees": [], "majors": [], "languages": [], "language_level": [], "hard_skills": ["documentation"], "soft_skills": ["accurate"], "languages_combined": []}, "experience_required": {"duration": [], "field": []}}]