[{"job_id": "100003009052190", "location_code": "hk", "company": "Ceres Meat Packers Limited", "job_title": "Quality Assurance Manager / Assistant Quality Assurance Manager", "description": "Responsibility:\n\nLead a team of quality manager, engineers and inspectors to support activities from new product development NPI to mass production stages.\nInitiate activities and programs for continuous improvement on supplier management, process control and product quality.\nFollow directive from Top Management to manage quality and related functions.\nDefine and maintain quality standard and policy, align with corporate standard and customer's requirement.\nDevelop and provide quality guidelines to suppliers, enforce and ensure compliance.\nIn charge of supplier factory audit as well as company in-house audit.\nAct as the main point of contact on all quality matters, both internally and externally\n\n\u00a0Requirements:\n\nBachelor's degree in Engineering, Quality Management or Applied Science is a must\n10-15 years quality experience, with substantial exposure to electrical and electronic appliances manufacturing\nFamiliar with industry, national and international standards on quality management and product quality\nProficient in written and fluent spoken Mandarin and English\nStation Dongguan factory\u00a0\nOccasional trip to SE Asian countries for visiting factories of own group\u00a0\nInterested parties, please send your full resume stating your expected salary and date of availability to the Human Resources Department for application.\u00a0 We offer successful candidates an attractive remuneration packages (Basic salary + Bonus + Medical Scheme) and the opportunity to work in a dynamic and exciting environment.\u00a0 (Data collected will be used for recruitment purpose only)", "employment_types": ["Full Time"], "selling_points": ["QA", "ISO 22000 & HACCP", "Food Safety"], "locations": ["Kwai Fong"], "categories": ["Manufacturing", "Quality Assurance, Control & Testing / ISO"], "post_time": "2022-01-17T02:25:05Z", "salary": {"currency": null, "max": null, "min": null, "period": "monthly", "term": null}, "salary_visible": false, "title_keywords": ["manager", "assistant quality assurance manager"], "responsibilities": ["management", "control", "guidelines", "maintain quality", "quality", "audit", "develop", "ensure compliance", "lead a team", "contact"], "requirements": {"degrees": ["degree", "bachelor"], "majors": ["science", "engineering", "quality management"], "languages": ["english", "mandarin"], "language_level": ["fluent", "proficient"], "hard_skills": [], "soft_skills": [], "languages_combined": [{"language": "english", "language_level": ["fluent", "proficient"]}, {"language": "mandarin", "language_level": ["fluent", "proficient"]}]}, "experience_required": {"duration": ["10-15 years"], "field": ["manufacturing"]}}, {"job_id": "100003009052868", "location_code": "hk", "company": "Phase Scientific International Limited", "job_title": "Quality Control Technician", "description": "We are seeking an experienced\u00a0Quality Control Assistant\u00a0in the Art/Collectable Toy industry for our factory in Dongguan.\u00a0\n\nPrimary Responsibilities:\n\nDevelop implementation plans with the production team to ensure projects go smoothly\nEnsure production transitions smoothly from stage to stage so deadlines can be met\nAct as the key on-site person at the factories\nDaily check-ins with the production team outside of Dongguan\nDo quality checks on site at factories to ensure every toy is at the correct standard of quality\nIdentify and solve on-site production problems\n\nRequirements:\n\nMust be willing to live in Dongguan Full Time\nWork weekends during busy seasons\nFluent in spoken/written Cantonese, Mandarin\nStrong communication and interpersonal skills\nAt least 3 years experience in toy production\nExperience with PVC, ABS, Vinyl, and other toy production materials and standards\nMust be willing to work outside standard hours\nWell organized, self-motivated and have a strong sense of responsibility\nJob Location: Dongguan, China", "employment_types": ["Full Time", "Permanent"], "selling_points": ["Responsible for conduct product testing", "Perform some instrument calibration", "Perform any quality control duties"], "locations": ["Kwun Tong"], "categories": ["Manufacturing", "Quality Assurance, Control & Testing / ISO"], "post_time": "2022-01-17T04:20:34Z", "salary": {"currency": null, "max": null, "min": null, "period": "monthly", "term": null}, "salary_visible": false, "title_keywords": ["quality control technician"], "responsibilities": ["plans", "quality", "implementation", "develop"], "requirements": {"degrees": [], "majors": [], "languages": ["cantonese", "mandarin"], "language_level": ["fluent"], "hard_skills": [], "soft_skills": ["self-motivated", "communication and interpersonal skills", "well organized", "sense of responsibility"], "languages_combined": [{"language": "cantonese", "language_level": ["fluent"]}, {"language": "mandarin", "language_level": ["fluent"]}]}, "experience_required": {"duration": ["at least 3 years"], "field": []}}, {"job_id": "100003009054537", "location_code": "hk", "company": "Big W HK Procurement Pty Limited", "job_title": "Quality Specialist - Softline", "description": "\u00a0\u00a0\u00a0\u00a0\u00a0\u00a0\u00a0\u00a0Monitor the entire company QA team\n\u00a0\u00a0\u00a0\u00a0\u00a0\u00a0\u00a0\u00a0Handle all client complaints \u00a0and/or other issues related to production , quality .\n\u00a0\u00a0\u00a0\u00a0\u00a0\u00a0\u00a0\u00a0Travel to China office for QC Training whenever required\n\u00a0\u00a0\u00a0\u00a0\u00a0\u00a0\u00a0\u00a0\u00a0Create all order summary in excel sheet\n\u00a0\u00a0\u00a0\u00a0\u00a0\u00a0\u00a0\u00a0\u00a0Work with current QA team on production , quality , factory issues , etc\n\u00a0\u00a0\u00a0\u00a0\u00a0\u00a0\u00a0\u00a0\u00a0Work with factories on audits , inline , dupro , and final production for all orders\n\u00a0\u00a0\u00a0\u00a0\u00a0\u00a0\u00a0\u00a0\u00a0Maintain on time delivery schedule and streamline all order process is per our company standards\n\u00a0\u00a0\u00a0\u00a0\u00a0\u00a0\u00a0\u00a0\u00a0Create a Quality standard system for the company for easy process and handling\n\u00a0\u00a0\u00a0\u00a0\u00a0\u00a0\u00a0\u00a0\u00a0Monitor every project , order and with factories with a process in place for CCM quality standards\nFile and record all order status on server ( system ) for tracibility\nIssue weekly , monthly reports on orders vs quality status and create company protocols that must be followed .\nMust have experience of 15 years over in Inspection and Quality control - THIS IS MANDATORY \u2013\u00a0\u00a0\u00a0\u00a0\u00a0\u00a0\u00a0\u00a0\u00a0\u00a0\u00a0\u00a0\u00a0\u00a0\u00a0\u00a0\u00a0\u00a0\u00a0\u00a0\u00a0\u00a0\nMust be fluent in ENGLISH AND MANDARIN \u2013\n14. Experience in Consumer Products and General Merchandiser is MANDATORY", "employment_types": ["Full Time", "Permanent"], "selling_points": [], "locations": ["Lai Chi Kok"], "categories": ["Manufacturing", "Quality Assurance, Control & Testing / ISO"], "post_time": "2022-01-17T09:54:58Z", "salary": {"currency": null, "max": null, "min": null, "period": "monthly", "term": null}, "salary_visible": false, "title_keywords": ["specialist"], "responsibilities": ["monthly reports", "quality", "monitor", "inspection", "delivery schedule", "maintain", "quality control", "audits"], "requirements": {"degrees": [], "majors": [], "languages": ["english", "mandarin"], "language_level": ["fluent"], "hard_skills": ["server", "excel", "vs"], "soft_skills": [], "languages_combined": [{"language": "english", "language_level": ["fluent"]}, {"language": "mandarin", "language_level": ["fluent"]}]}, "experience_required": {"duration": ["of 15 years"], "field": ["quality control"]}}, {"job_id": "100003009054071", "location_code": "hk", "company": "Creative Concepts Manufacturing Limited", "job_title": "SENIOR QUALITY ASSURANCE & QUALITY PROJECT MANAGER", "description": "Our client is a recognized sourcing company with solid project pipelines, has arisen for Quality Assurance Officer to join their team.\n\n\nWe are now seeking for Quality Assurance Officer\n\n\nRESPONSIBILITIES\n\nWork closely with internal and external partners for testing needs and quality-related inquiries.\nPrepare and review technical documentation by standards and regulations throughout the product life cycle from new product development through production\nExamine the sample, do a product appraisal, and approve the sample\nProvide technical and quality assurance support for a variety of hard goods categories, including seasonal, home living, toys, and stationery\nWork with factories and producers to develop and implement corrective and preventive actions.\nEnsure that suppliers and producers are continually improving and undertake supplier evaluations.\nGathering and compiling high-quality data, as well as preparing, consolidating, updating, and filing reports\nConsistently conduct defined risk analyses for all products and suppliers.\nAssist with the implementation of new projects\nMaintain excellent and smooth interaction with all internal and external stakeholders and regular communication and data exchange.\n\nQUALIFICATIONS\n\nHigher Diploma or above on Mechanical, Industrial Engineering, Chemistry or related disciplines\nMinimum 2-5 years relevant experience in Quality Assurance\nExperience with an international sourcing company / European market is an advantage\nKnowledge of European safety standards and legal regulations\nDetail-minded with good time management, organizational and problem-solving skills\nSelf-motivated, proactive, able to work independently\nStrong communication, interpersonal and problem-solving skills, able to interact with all levels\nHardworking, self-motivated, proactive, independent, and attention to details\nA good team player as well as able to work independently\nFluent in spoken and written English, Cantonese, and Mandarin\nProficient in Microsoft Office applications (Excel, Word, Outlook, etc.) and Internet as well as other databases\nWilling to travel within Asia, focusing on Mainland China\n\n\n\nAPPLY FOR THIS JOB\nInterested candidate please CLICK apply button to apply online or send your resume in MS word format to Hillman Ross Recruitment Solution Professional\n\n\n\n\nPlease note that only shortlisted candidate will be notified. All information will be treated in strict confidence and solely used for recruitment purposes.", "employment_types": ["Full Time"], "selling_points": [], "locations": ["Hung Hom"], "categories": ["Manufacturing", "Quality Assurance, Control & Testing / ISO"], "post_time": "2022-01-17T08:18:34Z", "salary": {"currency": null, "max": null, "min": null, "period": "monthly", "term": null}, "salary_visible": false, "title_keywords": ["project manager"], "responsibilities": ["regulations", "management", "data", "review", "quality", "stationery", "implementation", "testing", "develop", "communication", "maintain", "reports", "recruitment", "databases", "safety standards", "documentation"], "requirements": {"degrees": ["higher diploma or above"], "majors": ["related disciplines", "chemistry", "engineering"], "languages": ["cantonese", "english", "mandarin"], "language_level": ["fluent"], "hard_skills": ["excel", "microsoft office", "pipelines", "ms word", "word", "outlook", "databases", "documentation", "problem-solving skills", "exchange"], "soft_skills": ["detail-minded", "self-motivated", "proactive", "work independently", "independent", "good team player", "confidence", "organizational", "communication", "attention to details", "smooth", "problem-solving skills", "time management", "interpersonal", "hardworking"], "languages_combined": [{"language": "cantonese", "language_level": ["fluent"]}, {"language": "english", "language_level": ["fluent"]}, {"language": "mandarin", "language_level": ["fluent"]}]}, "experience_required": {"duration": ["minimum 2-5 years"], "field": ["relevant experience", "quality assurance"]}}, {"job_id": "100003009052315", "location_code": "hk", "company": "Coffee Concepts (Hong Kong) Ltd", "job_title": "Assistant Quality Assurance Manager \u2013 Starbucks Hong Kong", "description": "Job Description:\n\n\u00a0\u00a0\u00a0\u00a0\u00a0\u00a0Implement, review and update food safety management system (ISO22000 & HACCP)\n\u00a0\u00a0\u00a0\u00a0\u00a0\u00a0Lead subordinates to conduct regular factory inspection\n\u00a0\u00a0\u00a0\u00a0\u00a0\u00a0Work closely with production, warehouse and sales team on quality issues\n\u00a0\u00a0\u00a0\u00a0\u00a0\u00a0Monitor incoming goods quality, returned goods handling\u00a0\n\u00a0\u00a0\u00a0\u00a0\u00a0\u00a0Conduct internal audits for production & warehouse\n\u00a0\u00a0\u00a0\u00a0\u00a0\u00a0Monitor pest control program\n\u00a0\u00a0\u00a0\u00a0\u00a0\u00a0Prepare product label with respective to comply HK labelling regulation\n\u00a0\u00a0\u00a0\u00a0\u00a0\u00a0Assist in ad-hoc projects as assigned\n\nRequirements:\n\nDegree holder in Food Science or other related discipline\nAt least 3 years in quality control / inspection experiences in food & catering industry\nKnowledge of ISO22000 & HACCP\u00a0\nGood problem solving and interpersonal skills\nGood PC skills especially Excel; Word and PowerPoint\nGood command of written and spoken English and Chinese\nWell organized, self-motivated and detail-oriented\n\n\n\nWe regret that only successful candidates will be notified.\nData collected will be used for recruitment purpose only.", "employment_types": ["Full Time", "Permanent"], "selling_points": ["Comply w/ F&B, ingredient, merchandise QA standard", "Product concern investigation & corrective action", "Develop digital tools to optimize QA  efficiency"], "locations": ["Not Specified"], "categories": ["Hospitality / F & B", "Food & Beverage", "Others", "Manufacturing", "Quality Assurance, Control & Testing / ISO"], "post_time": "2022-01-17T02:43:58Z", "salary": {"currency": null, "max": null, "min": null, "period": "monthly", "term": null}, "salary_visible": false, "title_keywords": ["assistant quality assurance manager"], "responsibilities": ["management", "control", "food safety", "lead subordinates", "review", "quality", "monitor", "inspection", "sales team", "audits", "ad-hoc projects"], "requirements": {"degrees": ["degree holder"], "majors": ["food science"], "languages": ["english", "chinese"], "language_level": ["good command"], "hard_skills": ["excel", "word", "powerpoint", "problem solving", "pc skills"], "soft_skills": ["self-motivated", "well organized", "detail-oriented", "problem solving", "interpersonal skills"], "languages_combined": [{"language": "english", "language_level": ["good command"]}, {"language": "chinese", "language_level": ["good command"]}]}, "experience_required": {"duration": ["at least 3 years"], "field": ["food", "quality control"]}}, {"job_id": "100003009052873", "location_code": "hk", "company": "Telford International Co Ltd", "job_title": "Quality Assurance Officer / Assistant", "description": "Summary\n\nLidl are hiring Quality Consultant in the Quality Assurance (Leisure - Furnitures, Sports Items, Pet Toys, Inflatables Items) team.The successful candidate will be responsible for liaising\u00a0on issues and product requirements related to the 3rd party laboratory testing in Europe, Asia and USA of related product groups.\u00a0Support the Quality Assurance and Production Team on all product and quality requirements of related products.\u00a0Provide support to the team.\n\nWhat will you do?\n\n\u2022\u00a0\u00a0 \u00a0Sample Inspection: Ensure sample inspections and \u00a0reports are completed within target time\n\u2022\u00a0\u00a0 \u00a0QA Warehouse\\samples: Responsible for arranging samples to be sent to external warehouse or testing laboratory once evaluation completed, ensure samples organized on shelves or allotted area\n\u2022\u00a0\u00a0 \u00a0To ensure all critical and major issues in own area being raised and discussed; seek further advice from appropriate team members\n\u2022\u00a0\u00a0 \u00a0Communication: Ensure more face to face discussion; reduce e-mails \u201cbombs\u201d, greater use of phone conference with related parties and agreed instant solution whenever possible.\n\u2022\u00a0\u00a0 \u00a0Laboratory test quotation issues and discuss with Technical Manager or Senior Quality Consultant for confirmation\n\u2022\u00a0\u00a0 \u00a0Attend Kick-off meetings\n\u2022\u00a0\u00a0 \u00a0Test failure analysis and recommendations to factory\u00a0\n\nArrange the retest once the improved sample available\nUpdate and recalculate the schedule and inform the merchandiser\nReview and discuss (where applicable) CAP report with Production\nClarify the testing issues with external laboratory\nUpdate Technical Manager or Senior Quality Consultant on safety/quality issues directly related to project particularly causing delays\n\n\u2022\u00a0\u00a0 \u00a0Monitor the schedule and review on the document/report (Test order, sample review report, DCL, Certification)\n\u2022\u00a0\u00a0 \u00a0Advise/discuss with Technical Manager& Senior Quality Consultant the critical and major issues related to projects\n\u2022\u00a0\u00a0 \u00a0Work with Technical Manager& Senior Quality Consultant on additional internal projects i.e. data analysis, SOP\u2019s, Guide for use by factory/production and within QA etc\n\u2022\u00a0\u00a0 \u00a0Prepare of applicable release shipment release documents\n\nWhat will you need?\n\n\u2022\u00a0\u00a0 \u00a0Degree holder or relevant level of experience\n\u2022\u00a0\u00a0 \u00a0Minimum 2 \u2013 5 years relevant experience in Quality Assurance / QC position and factory inspection practice in international sourcing company is an advantage. (Furnitures, Sports Items, Pet Toys, Inflatables Items)\n\u2022\u00a0\u00a0 \u00a0Possess strong technical expertise in hard-line or hard-goods products\n\u2022\u00a0\u00a0 \u00a0Detail orientated\n\u2022\u00a0\u00a0 \u00a0High degree of work ethics and integrity\n\u2022\u00a0\u00a0 \u00a0A can-do attitude is a must\n\u2022\u00a0\u00a0 \u00a0Proficiency in Mandarin, English and Cantonese, both spoken and written\n\u2022\u00a0\u00a0 \u00a0PC knowledge is essential\n\u2022\u00a0\u00a0 \u00a0Travel is required\n\nWhat do we offer?\n\nWe are dedicated to fostering a family-friendly culture and work environment and we are an equal opportunities employer and welcome applications from all candidates with the required skills and experience.\n\n\u00a0\nMarket Leading Remuneration Package:\n\nDouble pay and discretionary bonus\nChoice of MPF provider\nLife Insurance\nMedical Insurance\n\u00a0\n\nSupportive Environment:\n\nRental re-imbursement scheme\nFlexible work arrangements\nIn-house training courses\nTraining sponsorship scheme\nHealth Check\nVision Check\nSupporting your child\u2019s education with advice from a leading education consultant\n\u00a0\n\nWork-Life Balance:\n\n5 day week\nCompetitive Annual Leave\nCharity, Community and Sporting Events\n\nWe are dedicated to fostering a family-friendly culture and work environment and we are an equal opportunities employer and welcome applications from all candidates with the required skills and experience.\n\n\u00a0\nMarket Leading Remuneration Package:\n\nDouble pay and discretionary bonus\nChoice of MPF provider\nLife Insurance\nMedical Insurance\n\u00a0\n\nSupportive Environment:\n\nRental re-imbursement scheme\nFlexible work arrangements\nIn-house training courses\nTraining sponsorship scheme\nHealth Check\nVision Check\nSupporting your child\u2019s education with advice from a leading education consultant\n\u00a0\n\nWork-Life Balance:\n\n5 day week\nCompetitive Annual Leave\nCharity, Community and Sporting Events", "employment_types": ["Full Time", "Permanent"], "selling_points": ["Degree or above in Food Science", "1-2 years relevant work experiences", "Travel to Mainland if the circumstances permit"], "locations": ["Yuen Long"], "categories": ["Engineering", "Manufacturing & Production", "Sciences, Lab, R&D", "Food Science", "Manufacturing", "Quality Assurance, Control & Testing / ISO"], "post_time": "2022-01-17T04:23:01Z", "salary": {"currency": null, "max": null, "min": null, "period": "monthly", "term": null}, "salary_visible": false, "title_keywords": ["quality assurance officer", "assistant"], "responsibilities": ["provide support", "analysis", "quotation", "quality", "review", "monitor", "inspection", "testing", "communication", "data analysis", "reports", "schedule", "evaluation", "report"], "requirements": {"degrees": ["degree", "degree holder"], "majors": [], "languages": ["cantonese", "english", "mandarin"], "language_level": ["proficiency"], "hard_skills": ["dcl", "analysis", "inform", "pc knowledge"], "soft_skills": ["organized", "responsible", "can-do attitude", "integrity", "communication", "detail orientated"], "languages_combined": [{"language": "cantonese", "language_level": ["proficiency"]}, {"language": "english", "language_level": ["proficiency"]}, {"language": "mandarin", "language_level": ["proficiency"]}]}, "experience_required": {"duration": ["5 years"], "field": ["relevant experience", "quality assurance"]}}, {"job_id": "100003009054509", "location_code": "hk", "company": "PERSOL Hong Kong", "job_title": "QA Assistant (Pharmaceutical industry/ Kwai Tsing area/ Attractive package)", "description": "Our client, a Japanese company, is now seeking for a high caliber individual to join their team as\u00a0QA Assistant (Ref: #44478)\n\n\nJob Descriptions:\n\nSupport and communicate with the QA department to ensure smooth daily operations\nCheck and prepare testing reports for the management to review\nWork closely with Supervisor to monitor the lab testing progress\nMaintain close relationships with testing companies\u00a0\n\nRequirements:\n\nHigher Diploma or above, preferably in Chemistry or Biology related discipline\nAt least 2 years of QA/ QC related working experience\nWorking experience in pharmaceutical/ FMCG industry is a bonus\nSpeaks good command of English and Mandarin\nGood communication and time management skills\n\nBenefits:\n\n5 days work\nDouble pay\nDiscretionary bonus\nOT allowance\nTransportation allowance\nBanking holiday\nMedical insurance + body check\n\nInterested parties please quote\u00a0#44478\u00a0and send your application (please include your expected salary) via email to\u00a0Apply Now\u00a0or\u00a0gladys @persolhk.com.\u00a0For any enquiries, please do not hesitate to contact me at\u00a0(852) 2971-2551.\n\nPlease note that only short listed candidate will be notified.\n\nWe also have various job vacancies from our well-established clients in all kinds of fields, please feel free to contact us. We are always willing to give you support on your career development.\n\nOur company website:\u00a0http://www.persolhk.com\n\nAll information received will be treated in strict confidence and used for recruitment purpose only.", "employment_types": ["Full Time", "Permanent"], "selling_points": ["Quality Assurance", "Passionate in Pharmaceutical/ FMCG industry", "Double pay/ bonus/ allowances"], "locations": ["Tsing Yi"], "categories": ["Sciences, Lab, R&D", "Chemical", "Medical Services", "Pharmaceutical", "Manufacturing", "Quality Assurance, Control & Testing / ISO"], "post_time": "2022-01-17T09:49:24Z", "salary": {"currency": null, "max": null, "min": null, "period": "monthly", "term": null}, "salary_visible": false, "title_keywords": ["qa assistant"], "responsibilities": ["communicate with", "management", "review", "monitor", "testing", "daily operations", "maintain", "reports"], "requirements": {"degrees": ["higher diploma or above"], "majors": ["biology", "chemistry"], "languages": ["english", "mandarin"], "language_level": ["good command"], "hard_skills": ["fmcg industry"], "soft_skills": ["communication", "time management skills"], "languages_combined": [{"language": "english", "language_level": ["good command"]}, {"language": "mandarin", "language_level": ["good command"]}]}, "experience_required": {"duration": ["at least 2 years"], "field": ["related", "pharmaceutical", "fmcg", "qa"]}}, {"job_id": "100003009054291", "location_code": "hk", "company": "Vita Green Pharmaceutical (H.K.) Limited", "job_title": "Quality Assurance Assistant", "description": "Responsibilities:\n\nPerform routine on line and finished food products inspection at various stages on the production line to implement ISO/HACCP policy.\nAssist in implementing and maintain the documentation system and quality management system.\nSupport the implementation of food safety, hygiene and quality assurance operation policies, guidelines and procedures to ensure the entire production process is in compliance with the corporate standard.\nCoordinate and participate work safety, quality assurance and hygiene procedures training to related staff.\nAssist in other ad-hoc projects as assigned.\n\nRequirements:\n\nDiploma holder or above in biochemistry, Food Science or related disciplines;\nSelf-motivated, independent and with good communication skill;\nWell-organized with good analytical skill;\nProficient in PC applications including Chinese word processing;\nGood command of spoken and written English and Chinese / Cantonese;\nWorking location: Tai Po Industrial Estate (with shuttle bus)\nFresh graduate will also be considered.\n\nInterested parties please apply with full resume, state current and expected salaries via clicking \"Apply Now\".\n\n\nAll applications and data collected will be treated in strict confidence and used exclusively for recruitment purposes.\u00a0 Only short listed candidates will be invited for interview.\u00a0 The company will retain the applications for a maximum period of 6 months and may refer suitable candidates to other vacancies within the Group.", "employment_types": ["Full Time", "Permanent"], "selling_points": ["PIC/S GMP manufacturer", "Great career opportunity", "Inspection of production process"], "locations": ["Tai Po Area"], "categories": ["Manufacturing", "Quality Assurance, Control & Testing / ISO"], "post_time": "2022-01-17T09:04:42Z", "salary": {"currency": null, "max": null, "min": null, "period": "monthly", "term": null}, "salary_visible": false, "title_keywords": ["quality assurance assistant"], "responsibilities": ["management", "production process", "food safety", "guidelines", "policies", "compliance", "quality", "implementation", "procedures", "inspection", "coordinate", "hygiene", "maintain", "documentation", "ad-hoc projects"], "requirements": {"degrees": ["diploma holder", "fresh graduate"], "majors": ["related disciplines", "food science"], "languages": ["cantonese", "english", "chinese"], "language_level": ["good command", "proficient"], "hard_skills": ["analytical skill", "chinese word processing", "pc applications"], "soft_skills": ["self-motivated", "analytical skill", "independent", "communication skill", "well-organized"], "languages_combined": [{"language": "cantonese", "language_level": ["good command"]}, {"language": "english", "language_level": ["good command"]}, {"language": "chinese", "language_level": ["good command", "proficient"]}]}, "experience_required": {"duration": [], "field": []}}, {"job_id": "100003009051544", "location_code": "hk", "company": "Pucky Limited", "job_title": "Toy Production Quality Control Assistant / \u73a9\u5177\u751f\u7522\u54c1\u8cea\u7ba1\u7406\u52a9\u7406", "description": "Key Roles and Responsibilities\n\nPerform sampling and chemical testing on Purified water, Raw materials, intermediates, finished products and stability samples\nUndertake maintenance and calibration of related analytical instruments\nRevision of SOP documents\n\nQualifications and Experience\n\nIn Science subjects, preferably in Pharmaceutical Science/Chemistry related discipline\n1-2 years working experience in Quality Control of pharmaceutical or commercial laboratory is preferred\nFamiliar with pharmacopeia (BP/USP/CP) and GMP requirements as per FDA, PIC/S\nProficiency in MS Words and Excel\nSelf-motivated and responsible\nGood command of English and Chinese\nFresh graduates are also considered\n\nHow to Apply\n\nYou are invited to send in your application and CV stating the position\u00a0(with reference number)\u00a0you are applying for together with your current and expected salary, apply via JobsDB\u00a0on or before 17 February 2022.\n\nKaren Pharmaceutical Company Limited is an Equal Opportunities Employer. Personal data provided by job applicants will be used strictly in accordance with our personal data policy and for recruitment purposes only. We aim to respond to successful applicants within 8 weeks and related information will be kept in our file for up to 12 months for other suitable vacancies in our organization and thereafter destroyed.", "employment_types": ["Full Time", "Part Time", "Temporary", "Freelance"], "selling_points": [], "locations": ["Others - China"], "categories": ["Manufacturing", "Quality Assurance, Control & Testing / ISO"], "post_time": "2022-01-16T09:39:06Z", "salary": {"currency": null, "max": null, "min": null, "period": null, "term": null}, "salary_visible": false, "title_keywords": ["assistant"], "responsibilities": ["maintenance", "testing", "recruitment", "quality control", "personal data"], "requirements": {"degrees": [], "majors": [], "languages": ["english", "chinese"], "language_level": ["good command"], "hard_skills": ["excel", "maintenance", "ms words"], "soft_skills": ["self-motivated", "responsible"], "languages_combined": [{"language": "english", "language_level": ["good command"]}, {"language": "chinese", "language_level": ["good command"]}]}, "experience_required": {"duration": ["1-2 years"], "field": ["pharmaceutical", "quality control", "commercial laboratory"]}}, {"job_id": "100003009052305", "location_code": "hk", "company": "GrammyTech Ltd", "job_title": "Quality Director/ Senior Quality Manager (China Based)", "description": "Job Description\n\u00a0\u00a0\u00a0\u00a0\u00a0\u00a0\u00a0\u00a0 Responsible for conduct incoming, in-process and finished product testing.\n\u00a0\u00a0\u00a0\u00a0\u00a0\u00a0\u00a0\u00a0 Responsible to perform some instrument calibration and maintenance programs;\n\u00a0\u00a0\u00a0\u00a0\u00a0\u00a0\u00a0\u00a0 Assist and perform any quality control duties as assigned.\n\nQualifications and Experience\u00a0\n\n\u00a0\u00a0\u00a0\u00a0\u00a0\u00a0\u00a0\u00a0 Bachelor\u2019s degree in biomedical or equivalent\n\u00a0\u00a0\u00a0\u00a0\u00a0\u00a0\u00a0\u00a0 1-2 relevant working experience is preferable but fresh graduates are welcome;\n\u00a0\u00a0\u00a0\u00a0\u00a0\u00a0\u00a0\u00a0 Self-motivated, responsible and a good team player;\n\u00a0\u00a0\u00a0\u00a0\u00a0\u00a0\u00a0\u00a0 Hard working & being able to work under pressure;\n\u00a0\u00a0\u00a0\u00a0\u00a0\u00a0\u00a0\u00a0 Night shift is requested\n\u00a0\u00a0\u00a0\u00a0\u00a0\u00a0\u00a0\u00a0 Good computer knowledge is preferred (i.e. Microsoft Office); &\n\u00a0\u00a0\u00a0\u00a0\u00a0\u00a0\u00a0\u00a0 Immediate available is preferable.\n\nWe offer an attractive basic salary plus attractive commission, 5-day work, on-the-job training and career advancement opportunity to the right candidates.\u00a0 Please send full resume with availability, current and expected salary by clicking \"Apply Now\"\u00a0\n\nBenefits\n\n\u00a0\u00a0\u00a0\u00a0\u00a0\u00a0\u00a0\u00a0 Five-day work\n\u00a0\u00a0\u00a0\u00a0\u00a0\u00a0\u00a0\u00a0 Bank Holidays\n\u00a0\u00a0\u00a0\u00a0\u00a0\u00a0\u00a0\u00a0 Medical Insurance\n\u00a0\u00a0\u00a0\u00a0\u00a0\u00a0\u00a0\u00a0 12+ Days Annual leave\n\u00a0\u00a0\u00a0\u00a0\u00a0\u00a0\u00a0\u00a0 Paid Marriage Leave\n\u00a0\u00a0\u00a0\u00a0\u00a0\u00a0\u00a0\u00a0 Birthday Leave\n\n\u00a0(Personal data collected will be used for recruitment purpose only.)", "employment_types": ["Full Time", "Permanent"], "selling_points": ["Automotive Products", "Industrial Products", "Medical Products"], "locations": ["Others - China"], "categories": ["Engineering", "Manufacturing & Production", "Manufacturing", "Manufacturing Management", "Quality Assurance, Control & Testing / ISO"], "post_time": "2022-01-17T02:42:38Z", "salary": {"currency": null, "max": null, "min": null, "period": "monthly", "term": null}, "salary_visible": false, "title_keywords": ["quality manager", "director"], "responsibilities": ["work under pressure", "quality control", "maintenance", "testing"], "requirements": {"degrees": ["degree", "bachelor"], "majors": [], "languages": [], "language_level": [], "hard_skills": ["plus", "basic", "maintenance", "microsoft office"], "soft_skills": ["good team player", "self-motivated", "responsible", "hard working", "work under pressure"], "languages_combined": []}, "experience_required": {"duration": [], "field": ["relevant working experience"]}}, {"job_id": "100003009052834", "location_code": "hk", "company": "Panasonic Hong Kong Co., Limited", "job_title": "Purchasing Quality Officer (Japanese Speaking)", "description": "Job Responsibilities\n\n\nCreate and maintain the Company Pack policy and the Pack guidelines for related products\nIdentify the Pack tasks/projects and work with suppliers, service providers and internal team in planning and executing them\nValidate Pack tests and inspection plans designed to assure quality of product Pack based on a review of all applicable safety standards and industry requirements\nValidate marking related to storage/handling & recycling for Pack (Triman, green dot,\u2026)\n\u00a0Review and resolve Pack issues with suppliers, service providers and packaging vendors\n\u00a0Coordinate and liaise with internal & external parties, related to sample evaluations\n\u00a0Maintain good communication with the suppliers to make sure our Pack requirements and standards have been well informed and implemented\nWork with France Head office to make ecotax declaration\nDevelop and follow up Supplier Pack KPI\nOther duties as assigned by Management\n\nJob Requirement\n\n\nDiploma or above in Packaging or related disciplines\n\u00a0At least 3 years working experience in of packaging and printing related field\n\u00a0Knowledge about quality assurance and quality control, raw material and finish goods markets price levels\n\u00a0Able to perform price break down for analysis\n\u00a0Knowledge in Multiple packaging materials, packaging structure design & packaging test, Flexo, Offset litho, screen printing technology, conventional and digital pre-press technologies, color management experience, green pack alternative will be an advantage\nStrong project management experience and organization skills\n\u00a0Responsible, patient, self-motivated, detailed minded, professional integrity and trustworthiness]\n\u00a0Familiar with European market\n\u00a0Good command of English on writing & speaking\nRequire travelling occasionally\n\n*Office location: Few minutes walk from Whampoa station\n\u00a0\n\n*Please send your resume with your current & expected salary. Information provided by applicants will be treated in strict confidence and will be used for recruitment purpose only.*", "employment_types": ["Full Time", "Permanent"], "selling_points": ["Implement factory audit", "Monitor and provide guidance on quality standard", "Stable MNC in-house environment"], "locations": ["Tsim Sha Tsui"], "categories": ["Merchandising & Purchasing", "Electronics", "Manufacturing", "Quality Assurance, Control & Testing / ISO"], "post_time": "2022-01-17T04:13:27Z", "salary": {"currency": null, "max": null, "min": null, "period": "monthly", "term": null}, "salary_visible": false, "title_keywords": ["quality officer"], "responsibilities": ["management", "other duties", "guidelines", "review", "quality", "external parties", "maintain good communication", "inspection", "coordinate", "develop", "maintain", "executing", "safety standards", "liaise with", "plans", "planning"], "requirements": {"degrees": ["diploma or above"], "majors": ["related disciplines"], "languages": ["english"], "language_level": ["good command"], "hard_skills": ["project management", "analysis"], "soft_skills": ["self-motivated", "confidence", "responsible", "integrity", "project management", "organization skills", "patient", "detailed"], "languages_combined": [{"language": "english", "language_level": ["good command"]}]}, "experience_required": {"duration": ["at least 3 years"], "field": ["management", "related", "design", "project management", "digital"]}}, {"job_id": "100003009052460", "location_code": "hk", "company": "Telford International Co Ltd", "job_title": "R&D Assistant/ R&D", "description": "Our Client is a well-established multinational company, they are looking for a Senior Quality Assurance Engineer to join their expanding business.\n\nKey Job Responsibilities include:\n\nResponsible to handle all technical aspects of hardgoods product\nEnsure the technical process and quality manual are in line with customers requirement.\nResponsible to handle related testing documents and review all testing report.\nKeep up to date with new industry innovation and best practice to drive continuous improvement\nWork close with internal parties for testing requirements and customers enquires\nConduct factories audit and ensure the performance meet company standard.\nProvide training to newcomers and support on product areas\nMaintain a strong relationship with supplier\n\nOther requirements include:\n\nTertiary education with minimum 3 years' experience in Quality assurance/testing or other related discipline\nExperienced in hardgoods items\nAbility to conduct risk assessments\nFamiliar with Quality Management System.\nGood communication skills, self-motivated, proactive and open minded\nExcellent in English, Cantonese and Mandarin, both spoken and written", "employment_types": ["Full Time", "Permanent"], "selling_points": ["Product Development/ Optimization", "Experience in QA/ R&D in F&B industry", "Knowledge in Microbiology Testing"], "locations": ["Yuen Long"], "categories": ["Manufacturing", "Product Development / Management", "Quality Assurance, Control & Testing / ISO", "Sciences, Lab, R&D", "Research & Development (R&D)"], "post_time": "2022-01-17T03:05:11Z", "salary": {"currency": null, "max": null, "min": null, "period": "monthly", "term": null}, "salary_visible": false, "title_keywords": ["assistant"], "responsibilities": ["provide training", "review", "quality", "audit", "testing", "maintain", "internal parties", "report"], "requirements": {"degrees": [], "majors": [], "languages": ["cantonese", "english", "mandarin"], "language_level": ["excellent"], "hard_skills": [], "soft_skills": ["communication skills", "self-motivated", "proactive", "open minded"], "languages_combined": [{"language": "cantonese", "language_level": ["excellent"]}, {"language": "english", "language_level": ["excellent"]}, {"language": "mandarin", "language_level": ["excellent"]}]}, "experience_required": {"duration": ["minimum 3 years"], "field": ["related", "quality assurance", "testing", "education"]}}, {"job_id": "100003009048268", "location_code": "hk", "company": "Kingsway Personnel Ltd", "job_title": "Japanese Speaking QA Assistant (Trading company) ~22K", "description": "Responsibilities:\n\nLead a team of QC to ensure product quality is in compliance with company standard\n\nConduct online trouble-shooting activities, implement and monitor corrective and preventive actions on quality issues\nEnsure the implementation of quality management systems in production and related parties, and maintain relevant documentation\nMaintain and improve product quality, communicate and coordinate with internal parties on quality control issues\nHandle customers\u2019 complaints, investigate on the cause of problem and propose corrective actions and preventive measures\nConduct GMP audit and coordinate Pest Management activities\nConduct regular audits on suppliers to ensure their products are up to standard\nPrepare monthly reports and analysis and take up ad hoc assignments\n\nRequirements:\n\nHigher Diploma /\u00a0University degree in Food Science, Food Technology or related discipline\n\n3-4 years\u2019 relevant working experience in food related factory\nKnowledge of HACCP / BRC / ISO22000 will be required\nStrong analytical, communication and interpersonal skills\nDetail-minded with multiple-tasking capabilities, ability to work independently and willing to take up challenges\nProficiency in English and Mandarin as well as computer applications, knowledge of SAP will be an advantage\nImmediate available is highly preferred\n\nInterested parties please send your resume with current and expected salary and availability:\n\n- \u00a0by fax to 2666 6575\n- \u00a0by mail to\n\u00a0 \u00a0Human Resources Department\n\u00a0 \u00a0Amoy Food Limited\n\u00a0 \u00a011-15 Dai Fu Street,Tai Po Industrial Estate,Tai Po, N.T.\n- \u00a0by \u201cApply Now\u201d\n\nFor enquiries, please contact our Recruitment Hotline at 26603403.\u00a0Employment Application Form can be downloaded from the company website\u00a0www.amoy.com\u00a0\n\nAll applications will be treated in strict confidence and retained for 6 months for recruitment purposes only.\u00a0", "employment_types": ["Full Time", "Permanent"], "selling_points": ["Business level in Japanese and English Speaking", "Degree in Science related discipline", "~22K, double pay, bonus, transportation fee"], "locations": ["Tsing Yi"], "categories": ["Manufacturing", "Product Development / Management", "Quality Assurance, Control & Testing / ISO"], "post_time": "2022-01-16T21:50:20Z", "salary": {"currency": null, "max": null, "min": null, "period": "monthly", "term": null}, "salary_visible": false, "title_keywords": ["japanese speaking qa assistant"], "responsibilities": ["management", "monthly reports", "analysis", "compliance", "monitor", "quality", "implementation", "systems", "coordinate with", "lead a team", "audit", "maintain", "coordinate", "audits", "quality control", "ad hoc assignments", "documentation", "internal parties"], "requirements": {"degrees": ["diploma", "university degree"], "majors": ["food science"], "languages": ["english", "mandarin"], "language_level": ["advantage", "proficiency"], "hard_skills": ["sap"], "soft_skills": ["detail-minded", "work independently", "communication and interpersonal skills"], "languages_combined": [{"language": "english", "language_level": ["advantage", "proficiency"]}, {"language": "mandarin", "language_level": ["advantage", "proficiency"]}]}, "experience_required": {"duration": ["3-4 years"], "field": ["related", "food", "relevant working experience"]}}, {"job_id": "100003009053071", "location_code": "hk", "company": "Li Chung Shing Tong (Holdings) Limited", "job_title": "Assistant QA Officer/QA Assistant", "description": "Job Description\nNow Brewing \u2013 Talent Seekers!#tobeapartner\nSummary of Key Responsibilities\nReporting to the Group QA Manager, you will assist in the development, implementation and monitoring of QA systems & tools to manage the product safety risk; quality assurance and regulatory compliance strategy and programs to ensure the continuous supply of safe, wholesome, premium quality products throughout supply chain to customers.\nDevelop tools, implement, manage and monitor performance of the Retail Quality Assurance program to assure that food safety, store cleanliness and store conditions are maintained to Starbucks standards.\nReview performance and make recommendations utilizing consolidating quality matrix & reports to track progress and improvement opportunities.\nLead and manage investigations and troubleshooting of product concerns from retail stores and customers; and implements corrective action.\nTo assure that quality, product safety and regulatory compliance standards are met for food, beverage, ingredients, merchandise and supply items manufactured, distributed and sold by Starbucks.\nDrive and develop digital platform and tools to optimize efficiency and make accurate decisions.\nSummary of Experience\n5 yrs relevant QA experience, must have relevant experience in F&B retail chain store\nPreferably possess with 2 yr+ supervisory experience\nThose with less experience will be considered as Senior Quality Assurance Specialist\nRequired Knowledge, Skills and Abilities\nBachelor Degree in Quality Assurance / Food Science / Food Safety & Technology or related disciplines\nWell-organized with strong analytical and problem-solving skills\nExcellent interpersonal, communication and time management skills\nOpen and interest to explore new and innovative platform to elevate QA experience\nProficient in MS Word, Excel, and Power point and video-editing tool\nGood command of spoken and written English and Chinese\nInterest parties please send your application and resume including your current and expected salary to the Partner (Human) Resources Manager.\u00a0 Let us give you the opportunity to be part of something bigger than yourself.\u00a0 It is time for you #tobeapartner. Apply today!\nIt is our policy to retain the personal data of applicants for future recruitment purpose for a period of 24 months.\u00a0 When there are vacancies in our subsidiary or associate companies during the period, we may transfer your application to them for consideration of employment.\u00a0 Under the Personal Data (Privacy) Ordinance, you have a right to a request access to, and to request correction of, your personal data in relation to your application.\u00a0 If you wish to exercise these rights, please contact our Partner Resources Organization, Coffee Concepts (Hong Kong) Limited.", "employment_types": ["Full Time"], "selling_points": [], "locations": ["Tai Po Area"], "categories": ["Medical Services", "Pharmaceutical", "Manufacturing", "Quality Assurance, Control & Testing / ISO"], "post_time": "2022-01-17T05:34:57Z", "salary": {"currency": null, "max": null, "min": null, "period": null, "term": null}, "salary_visible": false, "title_keywords": ["assistant qa officer", "qa assistant"], "responsibilities": ["make recommendations", "reporting", "food safety", "monitor performance", "monitoring", "quality", "implementation", "systems", "compliance", "develop", "review", "troubleshooting", "digital platform", "reports"], "requirements": {"degrees": ["degree", "bachelor"], "majors": ["related disciplines", "food science"], "languages": ["english", "chinese"], "language_level": ["good command"], "hard_skills": ["power point", "problem-solving skills", "excel", "ms word"], "soft_skills": ["time management skills", "well-organized", "communication", "problem-solving skills", "innovative", "interpersonal"], "languages_combined": [{"language": "english", "language_level": ["good command"]}, {"language": "chinese", "language_level": ["good command"]}]}, "experience_required": {"duration": [], "field": ["qa"]}}, {"job_id": "100003009054811", "location_code": "hk", "company": "Hyakunousha International Limited", "job_title": "Production Supervisor/Assistant Production Supervisor  (New Headcount)", "description": "Roles and Responsibilities\n\n\nProvide technical support on food and beverage regulatory\nCommunicate with internal and external parties to ensure the product are compliance with regulation\nReview product label base on local and overseas regulatory requirements\nHandle routine QA duties, such as verify the raw materials / finished products whether comply with relevant regulations and have safety certifications\u00a0\nInvolve in new product development\nProduct specifications follow up and finished product check\nAssist in compliant investigation, root cause analysis and correction\nPerform other Ad hoc duties as assigned\nRequirements\n\nDegree or above in Food Science or related disciplines\n1-2 years work experience as quality assurance in food or beverage industry\nLiaise with food authority on food regulation/food labelling law\nGood communication skills and able to work independently\nSelf-motivated, well-organized with good analytical skill\nRegular travel to Mainland China if the circumstances permit\n\nWe offer attractive remuneration package and career prospects plus 5-day week to right candidate. Interest parties; please forward your full resume with expected salary to us.\n\nAll data collected shall be solely for recruitment purposes.\n\nWebsite: www.telford.com.hk", "employment_types": ["Full Time", "Permanent"], "selling_points": ["Manage daily operation to meet production schedule", "Collect and analyze production data", "Good communication skills"], "locations": ["Tsuen Wan Area"], "categories": ["Hospitality / F & B", "Food & Beverage", "Manufacturing", "Production Planning / Control", "Quality Assurance, Control & Testing / ISO"], "post_time": "2022-01-17T11:16:08Z", "salary": {"currency": null, "max": null, "min": null, "period": "monthly", "term": null}, "salary_visible": false, "title_keywords": ["supervisor", "assistant"], "responsibilities": ["communicate with", "regulations", "ad hoc duties", "technical support", "regulatory requirements", "analysis", "compliance", "review", "internal and external parties", "investigation", "specifications"], "requirements": {"degrees": ["degree or above"], "majors": ["related disciplines", "food science"], "languages": [], "language_level": [], "hard_skills": ["analytical skill"], "soft_skills": ["communication skills", "work independently", "self-motivated", "analytical skill", "well-organized"], "languages_combined": []}, "experience_required": {"duration": ["1-2 years"], "field": ["food or beverage industry", "quality assurance"]}}, {"job_id": "100003009043029", "location_code": "hk", "company": "Migros (Hong Kong) Ltd", "job_title": "Quality Assurance Officer", "description": "Responsibilities:\nPerform routine on line and finished food products inspection at various stages on the production line to implement ISO/HACCP policy.\nAssist in implementing and maintain the documentation system and quality management system.\nSupport the implementation of food safety, hygiene and quality assurance operation policies, guidelines and procedures to ensure the entire production process is in compliance with the corporate standard.\nCoordinate and participate work safety, quality assurance and hygiene procedures training to related staff.\nAssist in other ad-hoc projects as assigned.\nRequirements:\nDegree holder or above in biochemistry, Food Science or related disciplines;\nAt least 2 year laboratory working experience;\nSelf-motivated, independent and with good communication skill;\nWell-organized with good analytical skill;\nProficient in PC applications including Chinese word processing;\nGood command of spoken and written English and Chinese / Cantonese\nStaff Benefits\nMedical Insurance Coverage\nBirthday& Wedding Leave\nFree Meal & Shuttle Bus\nStaff Purchase Benefits\nAll applications and data collected will be treated in strict confidence and used exclusively for recruitment purposes.\u00a0 Only short listed candidates will be invited for interview.\u00a0 The company will retain the applications for a maximum period of 6 months and may refer suitable candidates to other vacancies within the Group.", "employment_types": ["Full Time", "Permanent"], "selling_points": [], "locations": ["Kowloon Bay"], "categories": ["Merchandising & Purchasing", "Others", "Manufacturing", "Quality Assurance, Control & Testing / ISO"], "post_time": "2022-01-12T09:35:02Z", "salary": {"currency": null, "max": null, "min": null, "period": "monthly", "term": null}, "salary_visible": false, "title_keywords": ["quality assurance officer"], "responsibilities": ["management", "production process", "food safety", "guidelines", "policies", "compliance", "quality", "implementation", "procedures", "inspection", "coordinate", "hygiene", "maintain", "documentation", "ad-hoc projects"], "requirements": {"degrees": ["degree holder"], "majors": ["related disciplines", "food science"], "languages": ["cantonese", "english", "chinese"], "language_level": ["good command", "proficient"], "hard_skills": ["analytical skill", "chinese word processing", "pc applications"], "soft_skills": ["self-motivated", "analytical skill", "independent", "communication skill", "well-organized"], "languages_combined": [{"language": "cantonese", "language_level": ["good command"]}, {"language": "english", "language_level": ["good command"]}, {"language": "chinese", "language_level": ["good command", "proficient"]}]}, "experience_required": {"duration": ["at least 2 year"], "field": ["laboratory"]}}, {"job_id": "100003009048696", "location_code": "hk", "company": "Gifi Asia Limited", "job_title": "Pack Engineer (Quality Department)", "description": "Requirements\n\n3- 5 years \u00a0in QA in hardgoods, Furniture, Toys, Seasonal, Kitchenware in Trading or buyign office\n\nPerform quality checks on general merchandizes and packaging through sample inspections and reviewing test reports/documents\n\nCategories of products for product testing according to international \u00a0regulations/standards and internal company requirements\n\nConduct test failure analysis and assist in the improvement of quality of samples and provide recommendation to factor\n\nOversee the production schedule and collaborate with both internal parties (merchandizing team, production team, artwork team) and external parties (factory, testing laboratory) for releasing product shipment\n\n*Interested parties, please send full resume with current & expected salary & date available in MS WORD FORMAT ONLY to our email address or fax to 3527 0634*\n\n\u00a0For more jobs, please visit our website: www.hketernity.com\n\n(Personal data submitted are for recruitment purpose only.)", "employment_types": ["Full Time"], "selling_points": ["3 yrs\u2019 experience in packaging field", "Flexible working hours, 5 working days", "13 months' salary plus discretionary bonus"], "locations": ["Hung Hom"], "categories": ["Manufacturing", "Product Development / Management", "Printing", "Quality Assurance, Control & Testing / ISO"], "post_time": "2022-01-14T07:03:57Z", "salary": {"currency": null, "max": null, "min": null, "period": "monthly", "term": null}, "salary_visible": false, "title_keywords": ["engineer"], "responsibilities": ["regulations", "collaborate with", "analysis", "external parties", "quality", "testing", "provide recommendation", "reports", "schedule", "internal parties"], "requirements": {"degrees": [], "majors": [], "languages": [], "language_level": [], "hard_skills": ["merchandizing", "analysis", "factor"], "soft_skills": [], "languages_combined": []}, "experience_required": {"duration": [], "field": []}}, {"job_id": "100003009054041", "location_code": "hk", "company": "Eternity Consultants (HK) Ltd", "job_title": "Assistant Compliance Specialist / Compliance Specialist - BSCI / SA8000 (Fresh graduate)", "description": "Summary\n\nLidl are hiring a\u00a0Manufacturing Excellence Specialist for our production and quality control\u00a0team. The successful candidate will ensures that factories/Mills are evaluated fairly and ethically, also support factories/Mills that do not meet our internal/ legal minimum requirements via monitoring on Corrective Action Plans, conducting the follow ups and re-assessment.\n\nWhat will you do?\n\n\u2022\u00a0\u00a0 \u00a0Ensure all FCE (Factory Social Compliance Evaluations) are in line with Lidl Asia defined SOP\u2019s\n\n\u2022\u00a0\u00a0 \u00a0Assist in development of Factory Evaluation plans and schedules. Communicate with the Shenzhen booking team to ensure all FCEs are arranged and conducted in line with the agreed company timelines and ensure CAPs are closed off.\n\n\u2022\u00a0\u00a0 \u00a0Conduct FCE (Factory Social Compliance Evaluation) of Lidl Asia\u2019s supplier base for factories/Mills to ensure they comply to Lidl\u2019s C&S (Compliance & Sustainability) requirements, inclusive of International & local labor regulations/ applicable laws.\n\n\u2022\u00a0\u00a0 \u00a0Review and verify the Critical Non-Compliance (CNC) found during an ongoing audit, by the ME audit team, authorized agencies or assigned 3rd parties.\n\n\u2022\u00a0\u00a0 \u00a0Perform the FCE audit report review, analyze and report compliance discrepancies and \u00a0follow up with ME audit team and authorized agencies or assigned 3rd parties.\n\n\u2022\u00a0\u00a0 \u00a0Perpare the FCE audit report to summarize the evaluation result, inclusive of non-compliance issues \u00a0and share internally to all internal stakeholders (Sourcing, Merchandising and Production) for new FCE assessments and Existing factories.\n\n\u2022\u00a0\u00a0 \u00a0Ensure all FCE data are accurate and updated in the LUP system by the Shenzhen booking team after completion of the latest compliance evaluations.\n\n\u2022\u00a0\u00a0 \u00a0 Prepare FCE data for the monthly/Quartely report.\n\n\u2022\u00a0\u00a0 \u00a0Monitor the CAP status and support factories deemed not meeting our evaluation criteria via CAPs, follow up meetings and or discussions and re-audits.\n\n\u2022\u00a0\u00a0 \u00a0Communicate with Lidl Asia Sourcing and Merchandizing teams, keep them up-to-date with factory compliance status, flag critical non-complaince issues immediately to the Sourcing teams to ensure they are updated on the social compliance risks in their supply base and work out a solution in a collaborative manner.\n\n\u2022\u00a0\u00a0 \u00a0Conduct Shadow audits when required to ensure integrity of Auditing program\n\n\u2022\u00a0\u00a0 \u00a0Prepare the notification letter and send out pre-alert notification letter to all internal stakeholders and Regulartory Compliance team\n\n\u2022\u00a0\u00a0 \u00a0Support Senior ME Manager in conducting process & system audits and make continual improvements in protocols/work procedures.\n\n\u2022\u00a0\u00a0 \u00a0Support Senior ME Manager in the creation of standard work documentation, visual work instructions and training material.\n\n\u2022\u00a0\u00a0 \u00a0Support in system upgrade and development to ensure end-state solutions meet all users\u2019 requirements in support of business strategic goals and objectives.\n\n\u2022\u00a0\u00a0 \u00a0Support in special investigation case or other tasks requested by Regulatory Compliance team\n\n\u2022\u00a0\u00a0 \u00a0Support in Monitoring Day to Day data management (CBX/LUP/DE) Liaise with relevant department and sourcing team for Factory Registration Form follow up.\n\n\u2022\u00a0\u00a0 \u00a0Monitor and ensure the distribution and communicate company Guidelines and Requirements to factories when required\n\nWhat will you need?\n\n\u2022\u00a0\u00a0 \u00a0Minimum Bachelor\u2019s degree holder in related field\n\n\u2022\u00a0\u00a0 \u00a0At least 3-5 years relevant experience in a sizeable organization with social compliance, BSCI/ SA8000, Better Work Factory, ACCORD or equivalent standards is a must\n\n\u2022\u00a0\u00a0 \u00a0leadership experience and preferably with remote team(s); leading remote team experience preferred.\n\n\u2022\u00a0\u00a0 \u00a0Experience with manufacturing environment, auditing and remediation\n\n\u2022\u00a0\u00a0 \u00a0Profound understanding on environment, health & safety regulations and international labour standard\n\n\u2022\u00a0\u00a0 \u00a0Sensitive to cultural differences with country / regional coverage\n\n\u2022\u00a0\u00a0 \u00a0Strong communication, interpersonal and problem-solving skills, able to interact with all levels\n\n\u2022\u00a0\u00a0 \u00a0Autonomous, proactive, detailed and commercially minded\n\n\u2022\u00a0\u00a0 \u00a0High degree of work ethics and integrity\n\n\u2022\u00a0\u00a0 \u00a0Good command of both in spoken & written English, \u00a0in spoken Cantonese and Mandarin.\n\n\u2022\u00a0\u00a0 \u00a0Good knowledge of Microsoft applications PowerPoint, Word & Excel\u00a0\n\n\u2022\u00a0\u00a0 \u00a0ISO14000 experience is also beneficial\n\n\u2022\u00a0\u00a0 \u00a0Willing to travel occasionally\n\nWhat do we offer?\n\nWe are dedicated to fostering a family-friendly culture and work environment and we are an equal opportunities employer and welcome applications from all candidates with the required skills and experience.\n\nMarket Leading Remuneration Package:\n\nDouble pay and discretionary bonus\n\nChoice of MPF provider\n\nLife Insurance\n\nMedical Insurance\n\n\n\n\u00a0\n\nSupportive Environment:\n\nRental re-imbursement scheme\n\nFlexible work arrangements\n\nIn-house training courses\n\nTraining sponsorship scheme\n\nHealth Check\n\nVision Check\n\nSupporting your child's education with advice from a leading education consultant\n\n\n\n\u00a0\n\nWork-Life Balance:\n\n5 day week\n\nCompetitive Annual Leave\n\nCharity, Community and Sporting Events", "employment_types": ["Full Time"], "selling_points": ["5 days, 13 months, bank, medical, 12 AL", "1-3 years in social compliance in trading", "buying office, factory audit, conflict mineral"], "locations": ["Not Specified"], "categories": ["Engineering", "Manufacturing & Production", "Manufacturing", "Manufacturing Management", "Quality Assurance, Control & Testing / ISO"], "post_time": "2022-01-17T08:11:05Z", "salary": {"currency": null, "max": null, "min": null, "period": "monthly", "term": null}, "salary_visible": false, "title_keywords": ["specialist", "assistant"], "responsibilities": ["regulations", "data", "schedules", "merchandising", "audit", "communication", "evaluation", "liaise with", "plans", "compliance", "monitor", "teams", "other tasks", "visual", "report", "management", "monitoring", "review", "procedures", "investigation", "booking", "audits", "documentation", "communicate with", "company guidelines", "quality control", "auditing"], "requirements": {"degrees": ["degree", "bachelor", "degree holder"], "majors": [], "languages": ["cantonese", "english", "mandarin"], "language_level": ["good command"], "hard_skills": ["merchandizing", "excel", "data management", "microsoft applications", "word", "powerpoint", "make", "documentation", "problem-solving skills"], "soft_skills": ["proactive", "integrity", "collaborative", "communication", "sensitive to", "autonomous", "problem-solving skills", "accurate", "leadership", "interpersonal", "detailed"], "languages_combined": [{"language": "cantonese", "language_level": ["good command"]}, {"language": "english", "language_level": ["good command"]}, {"language": "mandarin", "language_level": ["good command"]}]}, "experience_required": {"duration": ["at least 3-5 years"], "field": ["manufacturing", "compliance", "relevant experience", "team"]}}, {"job_id": "100003009052646", "location_code": "hk", "company": "Headsearch21 Consultancy Ltd", "job_title": "EHS Manager (5 days / Manufacturing / 30-40K)", "description": "Key Roles and Responsibilities\n\nPerform sampling and chemical testing on Purified water, Raw materials, intermediates, finished products and stability samples\nUndertake maintenance and calibration of related analytical instruments\nRevision of SOP documents\n\nQualifications and Experience\n\nIn Science subjects, preferably in Pharmaceutical Science/Chemistry related discipline\n1-2 years working experience in Quality Control of pharmaceutical or commercial laboratory is preferred\nFamiliar with pharmacopeia (BP/USP/CP) and GMP requirements as per FDA, PIC/S\nProficiency in MS Words and Excel\nSelf-motivated and responsible\nGood command of English and Chinese\nFresh graduates are also considered\n\nHow to Apply\n\nYou are invited to send in your application and CV stating the position\u00a0(with reference number)\u00a0you are applying for together with your current and expected salary, apply via JobsDB\u00a0on or before 17 February 2022.\n\nKaren Pharmaceutical Company Limited is an Equal Opportunities Employer. Personal data provided by job applicants will be used strictly in accordance with our personal data policy and for recruitment purposes only. We aim to respond to successful applicants within 8 weeks and related information will be kept in our file for up to 12 months for other suitable vacancies in our organization and thereafter destroyed.", "employment_types": ["Full Time", "Permanent"], "selling_points": ["Deg+4 yrs EHS exp (Environmental, Health & Safety)", "ISO14001 / Safety Management System", "Less experience --> Senior EHS Officer"], "locations": ["Not Specified"], "categories": ["Sciences, Lab, R&D", "Environmental Science / Waste Management", "Management", "General Management", "Manufacturing", "Quality Assurance, Control & Testing / ISO"], "post_time": "2022-01-17T03:43:11Z", "salary": {"currency": "HKD", "max": 44999, "min": 30000, "period": "monthly", "term": null}, "salary_visible": true, "title_keywords": ["manager"], "responsibilities": ["maintenance", "testing", "recruitment", "quality control", "personal data"], "requirements": {"degrees": [], "majors": [], "languages": ["english", "chinese"], "language_level": ["good command"], "hard_skills": ["excel", "maintenance", "ms words"], "soft_skills": ["self-motivated", "responsible"], "languages_combined": [{"language": "english", "language_level": ["good command"]}, {"language": "chinese", "language_level": ["good command"]}]}, "experience_required": {"duration": ["1-2 years"], "field": ["pharmaceutical", "quality control", "commercial laboratory"]}}, {"job_id": "100003009049211", "location_code": "hk", "company": "", "job_title": "(Senior) Quality Assurance Inspector - food labeling", "description": "Job Responsibilities\n\n\n\nEnsure product compliance with the bill of specifications and EU regulatory requirements\nPerform quality checking on product and packaging\nProvide assistance to sourcing department by monitoring and driving the improvement of quality of samples at all stages of product development\nEvaluate samples and recommend appropriate modifications in design of construction to achieve a high level of service quality and operation efficiency\nCollaborate with the sourcing merchandising department and related 3rd parties on quality development projects\nParticipate in after-sales service and take corrective and proactive action (CAPA) to follow up with customer\u2019s complaints and feedback\n\nJob Requirement\n\n\nDiploma or above in Mechanical, Engineering or related disciplines\nMinimum 3 years relevant experience in QA/QC and strong technical expertise in Toys\nWork Experience in European sourcing company and/or laboratory is an advantage\nSelf-motivated and detailed minded\nStrong communication and organization skills required, PC knowledge is essential\nGood command of English and Mandarin\nRequire travelling occasionally\n\n*Office location: Few minutes walk from Whampoa station\n\u00a0\n\n*Please send your resume with your current & expected salary. Information provided by applicants will be treated in strict confidence and will be used for recruitment purpose only.*", "employment_types": ["Full Time", "Permanent"], "selling_points": ["Good knowledge of food labeling", "Factory and stores audit", "Relevant experience in food/ retail /FMCG industry"], "locations": ["Sham Shui Po Area"], "categories": ["Hospitality / F & B", "Food & Beverage", "Sciences, Lab, R&D", "Food Science", "Manufacturing", "Quality Assurance, Control & Testing / ISO"], "post_time": "2022-01-14T09:30:05Z", "salary": {"currency": null, "max": null, "min": null, "period": "monthly", "term": null}, "salary_visible": false, "title_keywords": ["quality assurance inspector"], "responsibilities": ["collaborate with", "quality checking", "regulatory requirements", "compliance", "monitoring", "quality", "design", "merchandising", "evaluate", "after-sales service", "specifications", "provide assistance"], "requirements": {"degrees": ["diploma or above"], "majors": ["related disciplines", "engineering"], "languages": ["english", "mandarin"], "language_level": ["good command"], "hard_skills": ["pc knowledge"], "soft_skills": ["self-motivated", "confidence", "communication", "organization skills", "detailed"], "languages_combined": [{"language": "english", "language_level": ["good command"]}, {"language": "mandarin", "language_level": ["good command"]}]}, "experience_required": {"duration": ["minimum 3 years"], "field": ["toys", "laboratory", "relevant experience", "qa"]}}, {"job_id": "100003009054154", "location_code": "hk", "company": "aimHigher Consultancy Limited", "job_title": "Coffee Expert/ Master", "description": "Responsibilities:\nLead all quality assurance and control activities\nResponsible for food labeling checking and approval to ensure compliance with local regulations\nSupervise the quality assurance activities eg. product quality checking and conduct food sampling test\nConduct regular supplier audit and prepare reports\nRequirements:\n\nDegree or above in Nutritional Chemistry/ Food Science or related disciplines\n2\u00a0years\u2019\u00a0relevant experience in food/\u00a0retail / FMCG industry\nGood knowledge of food labeling\nDetail-minded, well-organized, self-motivated and willing to take up challenges\nTeam-player, willing to learn and with good communication and problem-solving skills\n\n\n\nInterested parties,\u00a0please send us an email to obtain an application form to Human Resources Department.\n\nWe are an equal opportunity employer. Applications from all qualified candidates are welcome.\n\nAll information collected will be used for recruitment related purpose only.\u00a0\n\nInterested candidates, please contact us at 67570958 for company details before applying.", "employment_types": ["Full Time"], "selling_points": ["Expanding business", "Coffee lover", "Fun and energetic team"], "locations": ["Not Specified"], "categories": ["Manufacturing", "Product Development / Management", "Merchandising & Purchasing", "Procurement / Purchasing / Sourcing", "Quality Assurance, Control & Testing / ISO"], "post_time": "2022-01-17T08:35:38Z", "salary": {"currency": null, "max": null, "min": null, "period": "monthly", "term": null}, "salary_visible": false, "title_keywords": [], "responsibilities": ["regulations", "control", "quality checking", "quality", "checking", "audit", "ensure compliance", "prepare reports"], "requirements": {"degrees": ["degree or above"], "majors": ["related disciplines", "nutritional chemistry", "food science"], "languages": [], "language_level": [], "hard_skills": ["problem-solving skills", "fmcg industry"], "soft_skills": ["detail-minded", "self-motivated", "team-player", "willing to learn", "well-organized", "communication", "problem-solving skills"], "languages_combined": []}, "experience_required": {"duration": ["2 years"], "field": ["food", "retail", "relevant experience", "fmcg"]}}, {"job_id": "100003009049900", "location_code": "hk", "company": "Paul Y. Engineering Group", "job_title": "(Assistant/ Senior) Quality Assurance Officer", "description": "A Hong Kong listed company with diversified business in industrial products is looking for Quality Director/ Senior Quality Manager (IATF 16949)\n\nQuality Director/\u00a0Senior Quality Manager (China Based)\n\n\u00a0Key Responsibilities:\n\nEnsure operations compliance to IATF16969 regulation standards\nLead advanced product quality planning (APQP) discipline\nDrive shop floor quality assurance planning and quality control\nDrive effective problem solving and a continuous improvement mindset culture\nDrive quality systematic KPI continuous improvement\n\nRequirements:\n\nEngineering Bachelor\u2019s degree, with 20 years or above relevant experience\nSkilled in advanced product quality planning (APQP) and quality tools; PPAP, SPC, MSA, FMEA\nExperienced in problem solving and continuous improvement tools; 8D, 5-Why,\u00a0Taguchi\u00a0DOE methods\nStrong practical experience, knowledge of relevant manufacturing systems and process technologies\nExtensive Shop Floor experience is a must\nFluency in English preferred\nCandidate with less experience will be considered a Quality Manager\nBased in China\n\nInterested parties please forward your CV in Word Format to anthonyko @grammytech.com", "employment_types": ["Full Time", "Permanent"], "selling_points": ["Implement Proj. Quality System on Const. Sites", "ISO9001 Implementation and Audit", "1 year of experience in Building Construction"], "locations": ["Not Specified"], "categories": ["Engineering", "Engineering Project Management", "Manufacturing", "Quality Assurance, Control & Testing / ISO", "Building & Construction", "Others"], "post_time": "2022-01-15T03:50:39Z", "salary": {"currency": null, "max": null, "min": null, "period": "monthly", "term": null}, "salary_visible": false, "title_keywords": ["quality assurance officer", "assistant"], "responsibilities": ["operations", "compliance", "quality", "quality control", "planning"], "requirements": {"degrees": ["degree", "bachelor"], "majors": ["engineering"], "languages": ["english"], "language_level": ["fluency"], "hard_skills": ["problem solving"], "soft_skills": ["problem solving", "extensive", "advanced"], "languages_combined": [{"language": "english", "language_level": ["fluency"]}]}, "experience_required": {"duration": ["20 years"], "field": ["manufacturing", "relevant experience", "engineering"]}}, {"job_id": "100003009049397", "location_code": "hk", "company": "ISS Facility Services Limited", "job_title": "Assistant Officer - Quality Assurance, Health and Safety and Environmental (Job Ref: ADV/22/015)", "description": "Employer Ref: NR09467\nNature of Business: Japan based Trading Company\u00a0\u00a0\nWorking Days: 5 Days\nWorking Location: Tsing Yi Area\n\nBenefits:\n- Double pay\n- Discretionary Bonus\n- Transportation Allowance\n- OT Allowance\n- Attendance Allowance\n- Medical insurance\n\nRequirements:\n- Degree in Science related discipline (e.g.: Chemical / Medical / Biological) preferred\n- Min. 3yrs working exp., B to B business, FMCG products preferred\n- Business level in of Japanese and English\n\nDuties:\n- Handle QA duties for Consumer products\n- Assist in new product development\n\nInterested in the above vacancy?\u00a0 Send your resume to us NOW!\nOnly short-listed candidates will be notified. Personal data collected will be used for recruitment purpose only", "employment_types": ["Full Time", "Permanent"], "selling_points": ["Conduct onsite inspections or investigation", "Comply accident/incident statistics and analysis", "Minimum 1 year\u2019 relevant experience"], "locations": ["Not Specified"], "categories": ["Building & Construction", "Building / Construction / QS", "Manufacturing", "Quality Assurance, Control & Testing / ISO", "Others", "Security / Safety Control"], "post_time": "2022-01-14T08:33:13Z", "salary": {"currency": null, "max": null, "min": null, "period": "monthly", "term": null}, "salary_visible": false, "title_keywords": ["assistant officer"], "responsibilities": [], "requirements": {"degrees": [], "majors": [], "languages": [], "language_level": [], "hard_skills": [], "soft_skills": [], "languages_combined": []}, "experience_required": {"duration": [], "field": []}}, {"job_id": "100003009054421", "location_code": "hk", "company": "Zeeva International Limited", "job_title": "Operations Manager", "description": "Responsibilities:\n\nImplement factory audit to suppliers located in mainland China/Asia Pacific Region\nProvide assistance on supplier selection on electronic/mechanical parts\nMonitor and provide guidance to suppliers on quality standard\nWork closely with vendors and internal teams in cost and quality monitoring\nPrepare quality monitoring and factory audit reports\nCoordinate and follow up quality related issues\n\nRequirements:\n\nHigh Diploma holder or above\nAt least 1 year work experience in manufacturing/electronic field\nKnowledge of ISO9000/IATF16949 is an advantage\nGood command of English, Cantonese and Mandarin\nFluent in Japanese (JLPT N2 or above)\nProficient in MS Office\nWell organized, multi-tasking, good communication skills and positive thinking\nFrequent travel is required for factory assessment/audit (mainly in PRC)\n\nRemuneration will be commensurate with qualification and experience. Interested parties, please send your application with detailed resume indicating both existing & expected salary and date of availability to us.\n\nWe are an equal opportunity employer. All information provided by applicants will be treated in strict confidence and used for recruitment purpose only.", "employment_types": ["Full Time"], "selling_points": [], "locations": ["Kowloon Bay"], "categories": ["Manufacturing", "Production Planning / Control", "Merchandising & Purchasing", "Electronics", "Quality Assurance, Control & Testing / ISO"], "post_time": "2022-01-17T09:28:51Z", "salary": {"currency": null, "max": null, "min": null, "period": "monthly", "term": null}, "salary_visible": false, "title_keywords": ["operations manager"], "responsibilities": ["cost", "monitoring", "quality", "provide assistance", "monitor", "audit", "teams", "coordinate", "reports", "provide guidance"], "requirements": {"degrees": ["high diploma"], "majors": [], "languages": ["cantonese", "japanese", "english", "mandarin"], "language_level": ["good command", "fluent"], "hard_skills": ["ms office"], "soft_skills": ["communication skills", "multi-tasking", "well organized", "positive thinking"], "languages_combined": [{"language": "cantonese", "language_level": ["good command"]}, {"language": "japanese", "language_level": ["fluent"]}, {"language": "english", "language_level": ["good command"]}, {"language": "mandarin", "language_level": ["good command"]}]}, "experience_required": {"duration": ["at least 1 year"], "field": ["manufacturing"]}}, {"job_id": "100003009054286", "location_code": "hk", "company": "Vita Green Pharmaceutical (H.K.) Limited", "job_title": "Senior Laboratory Technician", "description": "Key roles and Responsibilities:\n\nTo support the routine QA operations, includes the implementation, review and maintenance of the QA system\nTo prepare SOP and GMP documents for the compliance of GMP standard\nTo assist in product registration, GMP training and records implementation.\u00a0\nTo perform ad hoc projects as assigned\u00a0\n\nQualifications and Experience\n\nHigher Diploma or Degree in Chinese Medicine/ Pharmaceutical/Food Science or related disciplines \u00a0\n2-3 yeas relevant working experience preferably in Chinese medicine/health/ pharmaceutical industry\u00a0\nSelf- motivated, willing to learn and a good team player\nGood interpersonal and communication skills\u00a0\nGood command in spoken and written English and Chinese\nCandidate with less experience will be considered as QA Assistant", "employment_types": ["Full Time", "Permanent"], "selling_points": ["\u2022GMP manufacturer", "Welcome candidate from food, drug or related field", "Great career opportunity in a leading HK brand"], "locations": ["Tai Po Area"], "categories": ["Sciences, Lab, R&D", "Laboratory", "Manufacturing", "Production Planning / Control", "Quality Assurance, Control & Testing / ISO"], "post_time": "2022-01-17T09:03:02Z", "salary": {"currency": null, "max": null, "min": null, "period": "monthly", "term": null}, "salary_visible": false, "title_keywords": ["laboratory technician"], "responsibilities": ["maintenance", "operations", "review", "compliance", "implementation", "communication", "ad hoc projects", "prepare sop"], "requirements": {"degrees": ["diploma", "degree"], "majors": ["related disciplines", "food science"], "languages": ["english", "chinese"], "language_level": ["good command"], "hard_skills": ["maintenance"], "soft_skills": ["communication skills", "good team player", "willing to learn", "motivated", "interpersonal"], "languages_combined": [{"language": "english", "language_level": ["good command"]}, {"language": "chinese", "language_level": ["good command"]}]}, "experience_required": {"duration": [], "field": ["pharmaceutical", "relevant working experience", "qa"]}}, {"job_id": "100003009054727", "location_code": "hk", "company": "JAC Recruitment Hong Kong Co., Limited", "job_title": "Urgent - Japanese Speaking QA Assistant (Japanese Trading Company)", "description": "Our client, a Japanese Trading company is looking for candidates Japanese Speaking QA Assistant roles.\n\nCompany Location:\u00a0 \u00a0 \u00a0 \u00a0 \u00a0 \u00a0\u00a0Tsing Yi\n\nWorking Days: \u00a0\u00a0\u00a0\u00a0\u00a0\u00a0\u00a0\u00a0\u00a0\u00a0\u00a0\u00a0\u00a0\u00a0\u00a0\u00a0\u00a0\u00a0 Mon-Fri\n\nCompany Business:\u00a0 \u00a0 \u00a0 \u00a0 \u00a0 \u00a0\u00a0Japanese Trading Company\n\nLanguages Required:\u00a0 \u00a0 \u00a0 \u00a0 \u00a0Cantonese, English and Japanese\n\nJOB DUTIES:\n\n\u533b\u85ac\u54c1\u3001\u30b5\u30d7\u30ea\u30e1\u30f3\u30c8\u3001\u5316\u7ca7\u54c1\u306a\u3069\u306e\u54c1\u8cea\u7ba1\u7406\u3068\u54c1\u8cea\u4fdd\u8a3c\u306e\u30a2\u30b7\u30b9\u30bf\u30f3\u30c8\u696d\u52d9\n\nREQUIREMENTS:\n\n\u82f1\u8a9e\u30d3\u30b8\u30cd\u30b9\u30ec\u30d9\u30eb\u30fb\u65e5\u672c\u8a9e\u30b3\u30df\u30e5\u30cb\u30b1\u30fc\u30b7\u30e7\u30f3\u30ec\u30d9\u30eb\u4ee5\u4e0a\uff08\u672a\u7d4c\u9a13\u8005\u306f\u30d3\u30b8\u30cd\u30b9\u30ec\u30d9\u30eb\uff09\nBtoC\u30d3\u30b8\u30cd\u30b9\uff08\u6d88\u8cbb\u8ca1\u30fb\u98df\u54c1\u30fb\u5316\u7ca7\u54c1\u30fb\u65e5\u7528\u54c1\u30fb\u533b\u85ac\u54c1\u30fb\u96d1\u8ca8\u7b49\uff09\u4f01\u696d\u306b\u30662-3\u5e74\u306e\u5c31\u696d\u7d4c\u9a13\u304c\u3042\u308b\u65b9\n\u54c1\u8cea\u4fdd\u8a3c\u3001\u54c1\u8cea\u7ba1\u7406\u306e\u7d4c\u9a13\u8005\u6b53\u8fce\n\nPACKAGE:\n\nDouble Pay\nDiscretionary bonus\nMedical insurance\n\n\u00a0Interested candidates, kindly send your detailed resume in MS Word including:\n\n\n1) Expected salary\n2) Current and last drawn salaries\n3) Reason for leaving current and past employments\n\u00a0\ndirectly to:\u00a0jac.hk\u00a0@jac-recruitment.com and CC to:\u00a0akihisa.watanabe\u00a0@jac-recruitment.com\n\nPersonal data collected will be used for employment-related purpose only. We regret to inform that only shortlisted candidates will be notified, thank you", "employment_types": ["Full Time", "Permanent"], "selling_points": ["Japanese company", "Expanding business", "Urgent Position"], "locations": ["Tsing Yi"], "categories": ["Manufacturing", "Quality Assurance, Control & Testing / ISO"], "post_time": "2022-01-17T10:47:05Z", "salary": {"currency": null, "max": null, "min": null, "period": "monthly", "term": null}, "salary_visible": false, "title_keywords": ["japanese speaking qa assistant"], "responsibilities": [], "requirements": {"degrees": [], "majors": [], "languages": [], "language_level": [], "hard_skills": [], "soft_skills": [], "languages_combined": []}, "experience_required": {"duration": [], "field": []}}, {"job_id": "100003009053193", "location_code": "hk", "company": "Kwonnie Electrical Products Ltd", "job_title": "Senior Quality Manager (station Dongguan)", "description": "Responsibility:\n\nLead a team of quality manager, engineers and inspectors to support activities from new product development NPI to mass production stages.\nInitiate activities and programs for continuous improvement on supplier management, process control and product quality.\nFollow directive from Top Management to manage quality and related functions.\nDefine and maintain quality standard and policy, align with corporate standard and customer's requirement.\nDevelop and provide quality guidelines to suppliers, enforce and ensure compliance.\nIn charge of supplier factory audit as well as company in-house audit.\nAct as the main point of contact on all quality matters, both internally and externally\n\n\u00a0Requirements:\n\nBachelor's degree in Engineering, Quality Management or Applied Science is a must\n10-15 years quality experience, with substantial exposure to electrical and electronic appliances manufacturing\nFamiliar with industry, national and international standards on quality management and product quality\nProficient in written and fluent spoken Mandarin and English\nStation Dongguan factory\u00a0\nOccasional trip to SE Asian countries for visiting factories of own group\u00a0\nInterested parties, please send your full resume stating your expected salary and date of availability to the Human Resources Department for application.\u00a0 We offer successful candidates an attractive remuneration packages (Basic salary + Bonus + Medical Scheme) and the opportunity to work in a dynamic and exciting environment.\u00a0 (Data collected will be used for recruitment purpose only)", "employment_types": ["Full Time", "Permanent"], "selling_points": [], "locations": ["Others - China"], "categories": ["Manufacturing", "Quality Assurance, Control & Testing / ISO"], "post_time": "2022-01-17T06:22:56Z", "salary": {"currency": null, "max": null, "min": null, "period": "monthly", "term": null}, "salary_visible": false, "title_keywords": ["quality manager"], "responsibilities": ["management", "control", "guidelines", "maintain quality", "quality", "audit", "develop", "ensure compliance", "lead a team", "contact"], "requirements": {"degrees": ["degree", "bachelor"], "majors": ["science", "engineering", "quality management"], "languages": ["english", "mandarin"], "language_level": ["fluent", "proficient"], "hard_skills": [], "soft_skills": [], "languages_combined": [{"language": "english", "language_level": ["fluent", "proficient"]}, {"language": "mandarin", "language_level": ["fluent", "proficient"]}]}, "experience_required": {"duration": ["10-15 years"], "field": ["manufacturing"]}}, {"job_id": "100003009055815", "location_code": "hk", "company": "Hillman Ross", "job_title": "Quality Assurance Officer (Hardgoods)", "description": "Our client is a recognized sourcing company with solid project pipelines, has arisen for Quality Assurance Officer to join their team.\n\n\nWe are now seeking for Quality Assurance Officer\n\n\nRESPONSIBILITIES\n\nWork closely with internal and external partners for testing needs and quality-related inquiries.\nPrepare and review technical documentation by standards and regulations throughout the product life cycle from new product development through production\nExamine the sample, do a product appraisal, and approve the sample\nProvide technical and quality assurance support for a variety of hard goods categories, including seasonal, home living, toys, and stationery\nWork with factories and producers to develop and implement corrective and preventive actions.\nEnsure that suppliers and producers are continually improving and undertake supplier evaluations.\nGathering and compiling high-quality data, as well as preparing, consolidating, updating, and filing reports\nConsistently conduct defined risk analyses for all products and suppliers.\nAssist with the implementation of new projects\nMaintain excellent and smooth interaction with all internal and external stakeholders and regular communication and data exchange.\n\nQUALIFICATIONS\n\nHigher Diploma or above on Mechanical, Industrial Engineering, Chemistry or related disciplines\nMinimum 2-5 years relevant experience in Quality Assurance\nExperience with an international sourcing company / European market is an advantage\nKnowledge of European safety standards and legal regulations\nDetail-minded with good time management, organizational and problem-solving skills\nSelf-motivated, proactive, able to work independently\nStrong communication, interpersonal and problem-solving skills, able to interact with all levels\nHardworking, self-motivated, proactive, independent, and attention to details\nA good team player as well as able to work independently\nFluent in spoken and written English, Cantonese, and Mandarin\nProficient in Microsoft Office applications (Excel, Word, Outlook, etc.) and Internet as well as other databases\nWilling to travel within Asia, focusing on Mainland China\n\n\n\nAPPLY FOR THIS JOB\nInterested candidate please CLICK apply button to apply online or send your resume in MS word format to Hillman Ross Recruitment Solution Professional\n\n\n\n\nPlease note that only shortlisted candidate will be notified. All information will be treated in strict confidence and solely used for recruitment purposes.", "employment_types": ["Full Time", "Permanent"], "selling_points": ["Product life-cycle", "Hardgoods categories", "Willing to travel"], "locations": ["Not Specified"], "categories": ["Manufacturing", "Quality Assurance, Control & Testing / ISO"], "post_time": "2022-01-18T02:58:37Z", "salary": {"currency": null, "max": null, "min": null, "period": "monthly", "term": null}, "salary_visible": false, "title_keywords": ["quality assurance officer"], "responsibilities": ["regulations", "management", "data", "review", "quality", "stationery", "implementation", "testing", "develop", "communication", "maintain", "reports", "recruitment", "databases", "safety standards", "documentation"], "requirements": {"degrees": ["higher diploma or above"], "majors": ["related disciplines", "chemistry", "engineering"], "languages": ["cantonese", "english", "mandarin"], "language_level": ["fluent"], "hard_skills": ["excel", "microsoft office", "pipelines", "ms word", "word", "outlook", "databases", "documentation", "problem-solving skills", "exchange"], "soft_skills": ["detail-minded", "self-motivated", "proactive", "work independently", "independent", "good team player", "confidence", "organizational", "communication", "attention to details", "smooth", "problem-solving skills", "time management", "interpersonal", "hardworking"], "languages_combined": [{"language": "cantonese", "language_level": ["fluent"]}, {"language": "english", "language_level": ["fluent"]}, {"language": "mandarin", "language_level": ["fluent"]}]}, "experience_required": {"duration": ["minimum 2-5 years"], "field": ["relevant experience", "quality assurance"]}}, {"job_id": "100003009055787", "location_code": "hk", "company": "Lidl Asia Pte. Limited (Hong Kong Branch)", "job_title": "Quality Consultant (Leisure)", "description": "Summary\n\nLidl are hiring Quality Consultant in the Quality Assurance (Leisure - Furnitures, Sports Items, Pet Toys, Inflatables Items) team.The successful candidate will be responsible for liaising\u00a0on issues and product requirements related to the 3rd party laboratory testing in Europe, Asia and USA of related product groups.\u00a0Support the Quality Assurance and Production Team on all product and quality requirements of related products.\u00a0Provide support to the team.\n\nWhat will you do?\n\n\u2022\u00a0\u00a0 \u00a0Sample Inspection: Ensure sample inspections and \u00a0reports are completed within target time\n\u2022\u00a0\u00a0 \u00a0QA Warehouse\\samples: Responsible for arranging samples to be sent to external warehouse or testing laboratory once evaluation completed, ensure samples organized on shelves or allotted area\n\u2022\u00a0\u00a0 \u00a0To ensure all critical and major issues in own area being raised and discussed; seek further advice from appropriate team members\n\u2022\u00a0\u00a0 \u00a0Communication: Ensure more face to face discussion; reduce e-mails \u201cbombs\u201d, greater use of phone conference with related parties and agreed instant solution whenever possible.\n\u2022\u00a0\u00a0 \u00a0Laboratory test quotation issues and discuss with Technical Manager or Senior Quality Consultant for confirmation\n\u2022\u00a0\u00a0 \u00a0Attend Kick-off meetings\n\u2022\u00a0\u00a0 \u00a0Test failure analysis and recommendations to factory\u00a0\n\nArrange the retest once the improved sample available\nUpdate and recalculate the schedule and inform the merchandiser\nReview and discuss (where applicable) CAP report with Production\nClarify the testing issues with external laboratory\nUpdate Technical Manager or Senior Quality Consultant on safety/quality issues directly related to project particularly causing delays\n\n\u2022\u00a0\u00a0 \u00a0Monitor the schedule and review on the document/report (Test order, sample review report, DCL, Certification)\n\u2022\u00a0\u00a0 \u00a0Advise/discuss with Technical Manager& Senior Quality Consultant the critical and major issues related to projects\n\u2022\u00a0\u00a0 \u00a0Work with Technical Manager& Senior Quality Consultant on additional internal projects i.e. data analysis, SOP\u2019s, Guide for use by factory/production and within QA etc\n\u2022\u00a0\u00a0 \u00a0Prepare of applicable release shipment release documents\n\nWhat will you need?\n\n\u2022\u00a0\u00a0 \u00a0Degree holder or relevant level of experience\n\u2022\u00a0\u00a0 \u00a0Minimum 2 \u2013 5 years relevant experience in Quality Assurance / QC position and factory inspection practice in international sourcing company is an advantage. (Furnitures, Sports Items, Pet Toys, Inflatables Items)\n\u2022\u00a0\u00a0 \u00a0Possess strong technical expertise in hard-line or hard-goods products\n\u2022\u00a0\u00a0 \u00a0Detail orientated\n\u2022\u00a0\u00a0 \u00a0High degree of work ethics and integrity\n\u2022\u00a0\u00a0 \u00a0A can-do attitude is a must\n\u2022\u00a0\u00a0 \u00a0Proficiency in Mandarin, English and Cantonese, both spoken and written\n\u2022\u00a0\u00a0 \u00a0PC knowledge is essential\n\u2022\u00a0\u00a0 \u00a0Travel is required\n\nWhat do we offer?\n\nWe are dedicated to fostering a family-friendly culture and work environment and we are an equal opportunities employer and welcome applications from all candidates with the required skills and experience.\n\n\u00a0\nMarket Leading Remuneration Package:\n\nDouble pay and discretionary bonus\nChoice of MPF provider\nLife Insurance\nMedical Insurance\n\u00a0\n\nSupportive Environment:\n\nRental re-imbursement scheme\nFlexible work arrangements\nIn-house training courses\nTraining sponsorship scheme\nHealth Check\nVision Check\nSupporting your child\u2019s education with advice from a leading education consultant\n\u00a0\n\nWork-Life Balance:\n\n5 day week\nCompetitive Annual Leave\nCharity, Community and Sporting Events\n\nWe are dedicated to fostering a family-friendly culture and work environment and we are an equal opportunities employer and welcome applications from all candidates with the required skills and experience.\n\n\u00a0\nMarket Leading Remuneration Package:\n\nDouble pay and discretionary bonus\nChoice of MPF provider\nLife Insurance\nMedical Insurance\n\u00a0\n\nSupportive Environment:\n\nRental re-imbursement scheme\nFlexible work arrangements\nIn-house training courses\nTraining sponsorship scheme\nHealth Check\nVision Check\nSupporting your child\u2019s education with advice from a leading education consultant\n\u00a0\n\nWork-Life Balance:\n\n5 day week\nCompetitive Annual Leave\nCharity, Community and Sporting Events", "employment_types": ["Full Time"], "selling_points": ["2-5 years experience in Quality Assurance", "Quality Assurance (Furnitures, Sports Items, Pet Toys, Inflatables Items)", "5 days work. Office at ICC."], "locations": ["Others"], "categories": ["Manufacturing", "Quality Assurance, Control & Testing / ISO"], "post_time": "2022-01-18T02:57:02Z", "salary": {"currency": null, "max": null, "min": null, "period": "monthly", "term": null}, "salary_visible": false, "title_keywords": ["consultant"], "responsibilities": ["provide support", "analysis", "quotation", "quality", "review", "monitor", "inspection", "testing", "communication", "data analysis", "reports", "schedule", "evaluation", "report"], "requirements": {"degrees": ["degree", "degree holder"], "majors": [], "languages": ["cantonese", "english", "mandarin"], "language_level": ["proficiency"], "hard_skills": ["dcl", "analysis", "inform", "pc knowledge"], "soft_skills": ["organized", "responsible", "can-do attitude", "integrity", "communication", "detail orientated"], "languages_combined": [{"language": "cantonese", "language_level": ["proficiency"]}, {"language": "english", "language_level": ["proficiency"]}, {"language": "mandarin", "language_level": ["proficiency"]}]}, "experience_required": {"duration": ["5 years"], "field": ["relevant experience", "quality assurance"]}}, {"job_id": "100003009056256", "location_code": "hk", "company": "Maxim's Caterers Ltd", "job_title": "Part Time - Quality Assurance Assistant (Cakes & Bakery)", "description": "Responsibilities:\n\nPerform routine on line and finished food products inspection at various stages on the production line to implement ISO/HACCP policy.\nAssist in implementing and maintain the documentation system and quality management system.\nSupport the implementation of food safety, hygiene and quality assurance operation policies, guidelines and procedures to ensure the entire production process is in compliance with the corporate standard.\nCoordinate and participate work safety, quality assurance and hygiene procedures training to related staff.\nAssist in other ad-hoc projects as assigned.\n\nRequirements:\n\nDiploma holder or above in biochemistry, Food Science or related disciplines;\nSelf-motivated, independent and with good communication skill;\nWell-organized with good analytical skill;\nProficient in PC applications including Chinese word processing;\nGood command of spoken and written English and Chinese / Cantonese;\nWorking location: Tai Po Industrial Estate (with shuttle bus)\nFresh graduate will also be considered.\n\nInterested parties please apply with full resume, state current and expected salaries via clicking \"Apply Now\".\n\n\nAll applications and data collected will be treated in strict confidence and used exclusively for recruitment purposes.\u00a0 Only short listed candidates will be invited for interview.\u00a0 The company will retain the applications for a maximum period of 6 months and may refer suitable candidates to other vacancies within the Group.", "employment_types": ["Part Time", "Temporary", "Contract"], "selling_points": ["Implementing and maintain the documentation system", "Support the implementation of food safety, hygiene", "5-day work week and rotate day off"], "locations": ["Tai Po Area"], "categories": ["Sciences, Lab, R&D", "Food Science", "Laboratory", "Manufacturing", "Quality Assurance, Control & Testing / ISO"], "post_time": "2022-01-18T03:43:24Z", "salary": {"currency": null, "max": null, "min": null, "period": null, "term": null}, "salary_visible": false, "title_keywords": ["quality assurance assistant"], "responsibilities": ["management", "production process", "food safety", "guidelines", "policies", "compliance", "quality", "implementation", "procedures", "inspection", "coordinate", "hygiene", "maintain", "documentation", "ad-hoc projects"], "requirements": {"degrees": ["diploma holder", "fresh graduate"], "majors": ["related disciplines", "food science"], "languages": ["cantonese", "english", "chinese"], "language_level": ["good command", "proficient"], "hard_skills": ["analytical skill", "chinese word processing", "pc applications"], "soft_skills": ["self-motivated", "analytical skill", "independent", "communication skill", "well-organized"], "languages_combined": [{"language": "cantonese", "language_level": ["good command"]}, {"language": "english", "language_level": ["good command"]}, {"language": "chinese", "language_level": ["good command", "proficient"]}]}, "experience_required": {"duration": [], "field": []}}, {"job_id": "100003009055183", "location_code": "hk", "company": "Karen Pharmaceutical Company Limited", "job_title": "QC Technician", "description": "Key Roles and Responsibilities\n\nPerform sampling and chemical testing on Purified water, Raw materials, intermediates, finished products and stability samples\nUndertake maintenance and calibration of related analytical instruments\nRevision of SOP documents\n\nQualifications and Experience\n\nIn Science subjects, preferably in Pharmaceutical Science/Chemistry related discipline\n1-2 years working experience in Quality Control of pharmaceutical or commercial laboratory is preferred\nFamiliar with pharmacopeia (BP/USP/CP) and GMP requirements as per FDA, PIC/S\nProficiency in MS Words and Excel\nSelf-motivated and responsible\nGood command of English and Chinese\nFresh graduates are also considered\n\nHow to Apply\n\nYou are invited to send in your application and CV stating the position\u00a0(with reference number)\u00a0you are applying for together with your current and expected salary, apply via JobsDB\u00a0on or before 17 February 2022.\n\nKaren Pharmaceutical Company Limited is an Equal Opportunities Employer. Personal data provided by job applicants will be used strictly in accordance with our personal data policy and for recruitment purposes only. We aim to respond to successful applicants within 8 weeks and related information will be kept in our file for up to 12 months for other suitable vacancies in our organization and thereafter destroyed.", "employment_types": ["Full Time"], "selling_points": [], "locations": ["Tuen Mun Area"], "categories": ["Sciences, Lab, R&D", "Laboratory", "Medical Services", "Pharmaceutical", "Manufacturing", "Quality Assurance, Control & Testing / ISO"], "post_time": "2022-01-18T01:41:36Z", "salary": {"currency": null, "max": null, "min": null, "period": null, "term": null}, "salary_visible": false, "title_keywords": ["qc technician"], "responsibilities": ["maintenance", "testing", "recruitment", "quality control", "personal data"], "requirements": {"degrees": [], "majors": [], "languages": ["english", "chinese"], "language_level": ["good command"], "hard_skills": ["excel", "maintenance", "ms words"], "soft_skills": ["self-motivated", "responsible"], "languages_combined": [{"language": "english", "language_level": ["good command"]}, {"language": "chinese", "language_level": ["good command"]}]}, "experience_required": {"duration": ["1-2 years"], "field": ["pharmaceutical", "quality control", "commercial laboratory"]}}, {"job_id": "100003009055765", "location_code": "hk", "company": "ConnectedGroup Limited", "job_title": "Senior Quality Assurance Engineer", "description": "Our Client is a well-established multinational company, they are looking for a Senior Quality Assurance Engineer to join their expanding business.\n\nKey Job Responsibilities include:\n\nResponsible to handle all technical aspects of hardgoods product\nEnsure the technical process and quality manual are in line with customers requirement.\nResponsible to handle related testing documents and review all testing report.\nKeep up to date with new industry innovation and best practice to drive continuous improvement\nWork close with internal parties for testing requirements and customers enquires\nConduct factories audit and ensure the performance meet company standard.\nProvide training to newcomers and support on product areas\nMaintain a strong relationship with supplier\n\nOther requirements include:\n\nTertiary education with minimum 3 years' experience in Quality assurance/testing or other related discipline\nExperienced in hardgoods items\nAbility to conduct risk assessments\nFamiliar with Quality Management System.\nGood communication skills, self-motivated, proactive and open minded\nExcellent in English, Cantonese and Mandarin, both spoken and written", "employment_types": ["Full Time", "Permanent"], "selling_points": ["Well-established multinational company", "Attractive remuneration package", "Responsible for handling Hardgoods Products"], "locations": ["Not Specified"], "categories": ["Sciences, Lab, R&D", "Laboratory", "Manufacturing", "Quality Assurance, Control & Testing / ISO", "Others"], "post_time": "2022-01-18T02:55:47Z", "salary": {"currency": null, "max": null, "min": null, "period": "monthly", "term": null}, "salary_visible": false, "title_keywords": ["engineer"], "responsibilities": ["provide training", "review", "quality", "audit", "testing", "maintain", "internal parties", "report"], "requirements": {"degrees": [], "majors": [], "languages": ["cantonese", "english", "mandarin"], "language_level": ["excellent"], "hard_skills": [], "soft_skills": ["communication skills", "self-motivated", "proactive", "open minded"], "languages_combined": [{"language": "cantonese", "language_level": ["excellent"]}, {"language": "english", "language_level": ["excellent"]}, {"language": "mandarin", "language_level": ["excellent"]}]}, "experience_required": {"duration": ["minimum 3 years"], "field": ["related", "quality assurance", "testing", "education"]}}, {"job_id": "100003009055764", "location_code": "hk", "company": "Amoy Food Ltd", "job_title": "Assistant / QA Officer (Food Manufacturing)", "description": "Responsibilities:\n\nLead a team of QC to ensure product quality is in compliance with company standard\n\nConduct online trouble-shooting activities, implement and monitor corrective and preventive actions on quality issues\nEnsure the implementation of quality management systems in production and related parties, and maintain relevant documentation\nMaintain and improve product quality, communicate and coordinate with internal parties on quality control issues\nHandle customers\u2019 complaints, investigate on the cause of problem and propose corrective actions and preventive measures\nConduct GMP audit and coordinate Pest Management activities\nConduct regular audits on suppliers to ensure their products are up to standard\nPrepare monthly reports and analysis and take up ad hoc assignments\n\nRequirements:\n\nHigher Diploma /\u00a0University degree in Food Science, Food Technology or related discipline\n\n3-4 years\u2019 relevant working experience in food related factory\nKnowledge of HACCP / BRC / ISO22000 will be required\nStrong analytical, communication and interpersonal skills\nDetail-minded with multiple-tasking capabilities, ability to work independently and willing to take up challenges\nProficiency in English and Mandarin as well as computer applications, knowledge of SAP will be an advantage\nImmediate available is highly preferred\n\nInterested parties please send your resume with current and expected salary and availability:\n\n- \u00a0by fax to 2666 6575\n- \u00a0by mail to\n\u00a0 \u00a0Human Resources Department\n\u00a0 \u00a0Amoy Food Limited\n\u00a0 \u00a011-15 Dai Fu Street,Tai Po Industrial Estate,Tai Po, N.T.\n- \u00a0by \u201cApply Now\u201d\n\nFor enquiries, please contact our Recruitment Hotline at 26603403.\u00a0Employment Application Form can be downloaded from the company website\u00a0www.amoy.com\u00a0\n\nAll applications will be treated in strict confidence and retained for 6 months for recruitment purposes only.\u00a0", "employment_types": ["Full Time", "Permanent"], "selling_points": ["HD / University degree in Food Science/Nutrition", "3-4 year working experience,food science backgroud", "5-day work, Shuttle bus, Free lunch meal"], "locations": ["Tai Po Area"], "categories": ["Sciences, Lab, R&D", "Food Science", "Manufacturing", "Quality Assurance, Control & Testing / ISO", "Others"], "post_time": "2022-01-18T02:55:47Z", "salary": {"currency": null, "max": null, "min": null, "period": "monthly", "term": null}, "salary_visible": false, "title_keywords": ["officer", "assistant"], "responsibilities": ["management", "monthly reports", "analysis", "compliance", "monitor", "quality", "implementation", "systems", "coordinate with", "lead a team", "audit", "maintain", "coordinate", "audits", "quality control", "ad hoc assignments", "documentation", "internal parties"], "requirements": {"degrees": ["diploma", "university degree"], "majors": ["food science"], "languages": ["english", "mandarin"], "language_level": ["advantage", "proficiency"], "hard_skills": ["sap"], "soft_skills": ["detail-minded", "work independently", "communication and interpersonal skills"], "languages_combined": [{"language": "english", "language_level": ["advantage", "proficiency"]}, {"language": "mandarin", "language_level": ["advantage", "proficiency"]}]}, "experience_required": {"duration": ["3-4 years"], "field": ["related", "food", "relevant working experience"]}}, {"job_id": "100003009056222", "location_code": "hk", "company": "Maxim's Caterers Ltd", "job_title": "Senior / Quality Assurance Officer (Cakes & Bakery Factory)", "description": "Responsibilities:\nPerform routine on line and finished food products inspection at various stages on the production line to implement ISO/HACCP policy.\nAssist in implementing and maintain the documentation system and quality management system.\nSupport the implementation of food safety, hygiene and quality assurance operation policies, guidelines and procedures to ensure the entire production process is in compliance with the corporate standard.\nCoordinate and participate work safety, quality assurance and hygiene procedures training to related staff.\nAssist in other ad-hoc projects as assigned.\nRequirements:\nDegree holder or above in biochemistry, Food Science or related disciplines;\nAt least 2 year laboratory working experience;\nSelf-motivated, independent and with good communication skill;\nWell-organized with good analytical skill;\nProficient in PC applications including Chinese word processing;\nGood command of spoken and written English and Chinese / Cantonese\nStaff Benefits\nMedical Insurance Coverage\nBirthday& Wedding Leave\nFree Meal & Shuttle Bus\nStaff Purchase Benefits\nAll applications and data collected will be treated in strict confidence and used exclusively for recruitment purposes.\u00a0 Only short listed candidates will be invited for interview.\u00a0 The company will retain the applications for a maximum period of 6 months and may refer suitable candidates to other vacancies within the Group.", "employment_types": ["Full Time", "Permanent"], "selling_points": ["Food Factory", "Perform routine on line and finished food products", "At least 2 year laboratory working experience"], "locations": ["Tai Po Area"], "categories": ["Sciences, Lab, R&D", "Laboratory", "Life Science", "Manufacturing", "Quality Assurance, Control & Testing / ISO"], "post_time": "2022-01-18T03:38:21Z", "salary": {"currency": null, "max": null, "min": null, "period": null, "term": null}, "salary_visible": false, "title_keywords": ["quality assurance officer"], "responsibilities": ["management", "production process", "food safety", "guidelines", "policies", "compliance", "quality", "implementation", "procedures", "inspection", "coordinate", "hygiene", "maintain", "documentation", "ad-hoc projects"], "requirements": {"degrees": ["degree holder"], "majors": ["related disciplines", "food science"], "languages": ["cantonese", "english", "chinese"], "language_level": ["good command", "proficient"], "hard_skills": ["analytical skill", "chinese word processing", "pc applications"], "soft_skills": ["self-motivated", "analytical skill", "independent", "communication skill", "well-organized"], "languages_combined": [{"language": "cantonese", "language_level": ["good command"]}, {"language": "english", "language_level": ["good command"]}, {"language": "chinese", "language_level": ["good command", "proficient"]}]}, "experience_required": {"duration": ["at least 2 year"], "field": ["laboratory"]}}, {"job_id": "100003009054944", "location_code": "hk", "company": "Eternity Consultants (HK) Ltd", "job_title": "Assistant QA Engineer / QA Engineer - Hardgoods / Kitchenware / Ceramic / Household / Toy", "description": "Requirements\n\n3- 5 years \u00a0in QA in hardgoods, Furniture, Toys, Seasonal, Kitchenware in Trading or buyign office\n\nPerform quality checks on general merchandizes and packaging through sample inspections and reviewing test reports/documents\n\nCategories of products for product testing according to international \u00a0regulations/standards and internal company requirements\n\nConduct test failure analysis and assist in the improvement of quality of samples and provide recommendation to factor\n\nOversee the production schedule and collaborate with both internal parties (merchandizing team, production team, artwork team) and external parties (factory, testing laboratory) for releasing product shipment\n\n*Interested parties, please send full resume with current & expected salary & date available in MS WORD FORMAT ONLY to our email address or fax to 3527 0634*\n\n\u00a0For more jobs, please visit our website: www.hketernity.com\n\n(Personal data submitted are for recruitment purpose only.)", "employment_types": ["Full Time", "Permanent"], "selling_points": ["5 days, 13 months", "QA in household, Furniture, kitchenware, Toys", "toy, home decor, Tools, gardening"], "locations": ["Not Specified"], "categories": ["Engineering", "Manufacturing & Production", "Manufacturing", "Quality Assurance, Control & Testing / ISO"], "post_time": "2022-01-17T14:40:27Z", "salary": {"currency": null, "max": null, "min": null, "period": "monthly", "term": null}, "salary_visible": false, "title_keywords": ["engineer", "assistant"], "responsibilities": ["regulations", "collaborate with", "analysis", "external parties", "quality", "testing", "provide recommendation", "reports", "schedule", "internal parties"], "requirements": {"degrees": [], "majors": [], "languages": [], "language_level": [], "hard_skills": ["merchandizing", "analysis", "factor"], "soft_skills": [], "languages_combined": []}, "experience_required": {"duration": [], "field": []}}, {"job_id": "100003009056312", "location_code": "hk", "company": "Lidl Hong Kong Limited", "job_title": "Manufacturing Excellence Specialist", "description": "Summary\n\nLidl are hiring a\u00a0Manufacturing Excellence Specialist for our production and quality control\u00a0team. The successful candidate will ensures that factories/Mills are evaluated fairly and ethically, also support factories/Mills that do not meet our internal/ legal minimum requirements via monitoring on Corrective Action Plans, conducting the follow ups and re-assessment.\n\nWhat will you do?\n\n\u2022\u00a0\u00a0 \u00a0Ensure all FCE (Factory Social Compliance Evaluations) are in line with Lidl Asia defined SOP\u2019s\n\n\u2022\u00a0\u00a0 \u00a0Assist in development of Factory Evaluation plans and schedules. Communicate with the Shenzhen booking team to ensure all FCEs are arranged and conducted in line with the agreed company timelines and ensure CAPs are closed off.\n\n\u2022\u00a0\u00a0 \u00a0Conduct FCE (Factory Social Compliance Evaluation) of Lidl Asia\u2019s supplier base for factories/Mills to ensure they comply to Lidl\u2019s C&S (Compliance & Sustainability) requirements, inclusive of International & local labor regulations/ applicable laws.\n\n\u2022\u00a0\u00a0 \u00a0Review and verify the Critical Non-Compliance (CNC) found during an ongoing audit, by the ME audit team, authorized agencies or assigned 3rd parties.\n\n\u2022\u00a0\u00a0 \u00a0Perform the FCE audit report review, analyze and report compliance discrepancies and \u00a0follow up with ME audit team and authorized agencies or assigned 3rd parties.\n\n\u2022\u00a0\u00a0 \u00a0Perpare the FCE audit report to summarize the evaluation result, inclusive of non-compliance issues \u00a0and share internally to all internal stakeholders (Sourcing, Merchandising and Production) for new FCE assessments and Existing factories.\n\n\u2022\u00a0\u00a0 \u00a0Ensure all FCE data are accurate and updated in the LUP system by the Shenzhen booking team after completion of the latest compliance evaluations.\n\n\u2022\u00a0\u00a0 \u00a0 Prepare FCE data for the monthly/Quartely report.\n\n\u2022\u00a0\u00a0 \u00a0Monitor the CAP status and support factories deemed not meeting our evaluation criteria via CAPs, follow up meetings and or discussions and re-audits.\n\n\u2022\u00a0\u00a0 \u00a0Communicate with Lidl Asia Sourcing and Merchandizing teams, keep them up-to-date with factory compliance status, flag critical non-complaince issues immediately to the Sourcing teams to ensure they are updated on the social compliance risks in their supply base and work out a solution in a collaborative manner.\n\n\u2022\u00a0\u00a0 \u00a0Conduct Shadow audits when required to ensure integrity of Auditing program\n\n\u2022\u00a0\u00a0 \u00a0Prepare the notification letter and send out pre-alert notification letter to all internal stakeholders and Regulartory Compliance team\n\n\u2022\u00a0\u00a0 \u00a0Support Senior ME Manager in conducting process & system audits and make continual improvements in protocols/work procedures.\n\n\u2022\u00a0\u00a0 \u00a0Support Senior ME Manager in the creation of standard work documentation, visual work instructions and training material.\n\n\u2022\u00a0\u00a0 \u00a0Support in system upgrade and development to ensure end-state solutions meet all users\u2019 requirements in support of business strategic goals and objectives.\n\n\u2022\u00a0\u00a0 \u00a0Support in special investigation case or other tasks requested by Regulatory Compliance team\n\n\u2022\u00a0\u00a0 \u00a0Support in Monitoring Day to Day data management (CBX/LUP/DE) Liaise with relevant department and sourcing team for Factory Registration Form follow up.\n\n\u2022\u00a0\u00a0 \u00a0Monitor and ensure the distribution and communicate company Guidelines and Requirements to factories when required\n\nWhat will you need?\n\n\u2022\u00a0\u00a0 \u00a0Minimum Bachelor\u2019s degree holder in related field\n\n\u2022\u00a0\u00a0 \u00a0At least 3-5 years relevant experience in a sizeable organization with social compliance, BSCI/ SA8000, Better Work Factory, ACCORD or equivalent standards is a must\n\n\u2022\u00a0\u00a0 \u00a0leadership experience and preferably with remote team(s); leading remote team experience preferred.\n\n\u2022\u00a0\u00a0 \u00a0Experience with manufacturing environment, auditing and remediation\n\n\u2022\u00a0\u00a0 \u00a0Profound understanding on environment, health & safety regulations and international labour standard\n\n\u2022\u00a0\u00a0 \u00a0Sensitive to cultural differences with country / regional coverage\n\n\u2022\u00a0\u00a0 \u00a0Strong communication, interpersonal and problem-solving skills, able to interact with all levels\n\n\u2022\u00a0\u00a0 \u00a0Autonomous, proactive, detailed and commercially minded\n\n\u2022\u00a0\u00a0 \u00a0High degree of work ethics and integrity\n\n\u2022\u00a0\u00a0 \u00a0Good command of both in spoken & written English, \u00a0in spoken Cantonese and Mandarin.\n\n\u2022\u00a0\u00a0 \u00a0Good knowledge of Microsoft applications PowerPoint, Word & Excel\u00a0\n\n\u2022\u00a0\u00a0 \u00a0ISO14000 experience is also beneficial\n\n\u2022\u00a0\u00a0 \u00a0Willing to travel occasionally\n\nWhat do we offer?\n\nWe are dedicated to fostering a family-friendly culture and work environment and we are an equal opportunities employer and welcome applications from all candidates with the required skills and experience.\n\nMarket Leading Remuneration Package:\n\nDouble pay and discretionary bonus\n\nChoice of MPF provider\n\nLife Insurance\n\nMedical Insurance\n\n\n\n\u00a0\n\nSupportive Environment:\n\nRental re-imbursement scheme\n\nFlexible work arrangements\n\nIn-house training courses\n\nTraining sponsorship scheme\n\nHealth Check\n\nVision Check\n\nSupporting your child's education with advice from a leading education consultant\n\n\n\n\u00a0\n\nWork-Life Balance:\n\n5 day week\n\nCompetitive Annual Leave\n\nCharity, Community and Sporting Events", "employment_types": ["Full Time"], "selling_points": ["Social compliance, BSCI/ SA8000, Better Work Factory, ACCORD or equivalent standards is a must", "At least 3-5 years relevant experience in a sizeable organization", "Experience with manufacturing environment, auditing and remediation"], "locations": ["Others"], "categories": ["Manufacturing", "Manufacturing Management", "Quality Assurance, Control & Testing / ISO"], "post_time": "2022-01-18T03:56:27Z", "salary": {"currency": null, "max": null, "min": null, "period": "monthly", "term": null}, "salary_visible": false, "title_keywords": ["specialist"], "responsibilities": ["regulations", "data", "schedules", "merchandising", "audit", "communication", "evaluation", "liaise with", "plans", "compliance", "monitor", "teams", "other tasks", "visual", "report", "management", "monitoring", "review", "procedures", "investigation", "booking", "audits", "documentation", "communicate with", "company guidelines", "quality control", "auditing"], "requirements": {"degrees": ["degree", "bachelor", "degree holder"], "majors": [], "languages": ["cantonese", "english", "mandarin"], "language_level": ["good command"], "hard_skills": ["merchandizing", "excel", "data management", "microsoft applications", "word", "powerpoint", "make", "documentation", "problem-solving skills"], "soft_skills": ["proactive", "integrity", "collaborative", "communication", "sensitive to", "autonomous", "problem-solving skills", "accurate", "leadership", "interpersonal", "detailed"], "languages_combined": [{"language": "cantonese", "language_level": ["good command"]}, {"language": "english", "language_level": ["good command"]}, {"language": "mandarin", "language_level": ["good command"]}]}, "experience_required": {"duration": ["at least 3-5 years"], "field": ["manufacturing", "compliance", "relevant experience", "team"]}}, {"job_id": "100003009055239", "location_code": "hk", "company": "Karen Pharmaceutical Company Limited", "job_title": "Laboratory Assistant", "description": "Key Roles and Responsibilities\n\nPerform sampling and chemical testing on Purified water, Raw materials, intermediates, finished products and stability samples\nUndertake maintenance and calibration of related analytical instruments\nRevision of SOP documents\n\nQualifications and Experience\n\nIn Science subjects, preferably in Pharmaceutical Science/Chemistry related discipline\n1-2 years working experience in Quality Control of pharmaceutical or commercial laboratory is preferred\nFamiliar with pharmacopeia (BP/USP/CP) and GMP requirements as per FDA, PIC/S\nProficiency in MS Words and Excel\nSelf-motivated and responsible\nGood command of English and Chinese\nFresh graduates are also considered\n\nHow to Apply\n\nYou are invited to send in your application and CV stating the position\u00a0(with reference number)\u00a0you are applying for together with your current and expected salary, apply via JobsDB\u00a0on or before 17 February 2022.\n\nKaren Pharmaceutical Company Limited is an Equal Opportunities Employer. Personal data provided by job applicants will be used strictly in accordance with our personal data policy and for recruitment purposes only. We aim to respond to successful applicants within 8 weeks and related information will be kept in our file for up to 12 months for other suitable vacancies in our organization and thereafter destroyed.", "employment_types": ["Full Time"], "selling_points": [], "locations": ["Tuen Mun Area"], "categories": ["Sciences, Lab, R&D", "Laboratory", "Medical Services", "Pharmaceutical", "Manufacturing", "Quality Assurance, Control & Testing / ISO"], "post_time": "2022-01-18T01:54:32Z", "salary": {"currency": null, "max": null, "min": null, "period": null, "term": null}, "salary_visible": false, "title_keywords": ["laboratory assistant"], "responsibilities": ["maintenance", "testing", "recruitment", "quality control", "personal data"], "requirements": {"degrees": [], "majors": [], "languages": ["english", "chinese"], "language_level": ["good command"], "hard_skills": ["excel", "maintenance", "ms words"], "soft_skills": ["self-motivated", "responsible"], "languages_combined": [{"language": "english", "language_level": ["good command"]}, {"language": "chinese", "language_level": ["good command"]}]}, "experience_required": {"duration": ["1-2 years"], "field": ["pharmaceutical", "quality control", "commercial laboratory"]}}, {"job_id": "100003009048675", "location_code": "hk", "company": "Gifi Asia Limited", "job_title": "Quality Assurance Engineer (QA) - Toys", "description": "Job Responsibilities\n\n\n\nEnsure product compliance with the bill of specifications and EU regulatory requirements\nPerform quality checking on product and packaging\nProvide assistance to sourcing department by monitoring and driving the improvement of quality of samples at all stages of product development\nEvaluate samples and recommend appropriate modifications in design of construction to achieve a high level of service quality and operation efficiency\nCollaborate with the sourcing merchandising department and related 3rd parties on quality development projects\nParticipate in after-sales service and take corrective and proactive action (CAPA) to follow up with customer\u2019s complaints and feedback\n\nJob Requirement\n\n\nDiploma or above in Mechanical, Engineering or related disciplines\nMinimum 3 years relevant experience in QA/QC and strong technical expertise in Toys\nWork Experience in European sourcing company and/or laboratory is an advantage\nSelf-motivated and detailed minded\nStrong communication and organization skills required, PC knowledge is essential\nGood command of English and Mandarin\nRequire travelling occasionally\n\n*Office location: Few minutes walk from Whampoa station\n\u00a0\n\n*Please send your resume with your current & expected salary. Information provided by applicants will be treated in strict confidence and will be used for recruitment purpose only.*", "employment_types": ["Full Time"], "selling_points": ["3 yrs\u2019 experience in QA/ QC", "Flexible working hours, 5 working days", "13 months' salary plus discretionary bonus"], "locations": ["Hung Hom"], "categories": ["Manufacturing", "Manufacturing Management", "Production Planning / Control", "Quality Assurance, Control & Testing / ISO"], "post_time": "2022-01-14T07:01:21Z", "salary": {"currency": null, "max": null, "min": null, "period": "monthly", "term": null}, "salary_visible": false, "title_keywords": ["engineer"], "responsibilities": ["collaborate with", "quality checking", "regulatory requirements", "compliance", "monitoring", "quality", "design", "merchandising", "evaluate", "after-sales service", "specifications", "provide assistance"], "requirements": {"degrees": ["diploma or above"], "majors": ["related disciplines", "engineering"], "languages": ["english", "mandarin"], "language_level": ["good command"], "hard_skills": ["pc knowledge"], "soft_skills": ["self-motivated", "confidence", "communication", "organization skills", "detailed"], "languages_combined": [{"language": "english", "language_level": ["good command"]}, {"language": "mandarin", "language_level": ["good command"]}]}, "experience_required": {"duration": ["minimum 3 years"], "field": ["toys", "laboratory", "relevant experience", "qa"]}}, {"job_id": "100003009055762", "location_code": "hk", "company": "Amoy Food Ltd", "job_title": "Senior Production Officer / Production Officer (Food Industry)", "description": "Responsibilities:\n\nLaunch new product and closely work with QA and R&D department\nLead a team of operators and manage day-to-day operation of food production lines to achieve production schedules and targets\nAssist Manager in developing and implementing production and quality systems and ensure compliance of related requirements and standards with strong food safety sense\nPerform analysis on work flow and production efficiency regularly, collect and maintain accurate records and support month-end reports\nParticipate in regular factory audits and checks, and take up ad hoc assignments\n\nRequirements:\n\nHigher Diploma or above in Food Science,\u00a0Manufacturing, Industrial Engineering or related discipline\n2-4 years of relevant experience in manufacturing industry, preferably in food factory\nKnowledge of ISO22000 / HACCP / BRC will be an advantage\nDetail-minded, well-organized and sensitive to figures, self-motivated and willing to take up challenges\nTeam-player, willing to learn and with good communication and problem-solving skills\nProficient in both English and Mandarin as well as in computer applications, knowledge in SAP will be an advantage\nCandidate with more experience will be considered as Senior Production Officer\n\n\u00a0Interested parties please send your resume with current and expected salary and availability:\n\n- \u00a0by fax to 2666 6575\n- \u00a0by mail to\n\u00a0 \u00a0Human Resources Director\n\u00a0 \u00a0Amoy Food Limited\n\u00a0 \u00a011-15 Dai Fu Street,Tai Po Industrial Estate,Tai Po, N.T.\n- \u00a0by \u201cApply Now\u201d\n\nFor enquiries, please contact our Recruitment Hotline at 26603403.\u00a0Employment Application Form can be downloaded from the company website\u00a0www.amoy.com\n\nAll applications will be treated in strict confidence and retained for 6 months for recruitment purposes only.\u00a0\u00a0", "employment_types": ["Full Time", "Permanent"], "selling_points": ["Launch new product/revamp product with QA & R&D", "Higher diploma in Food Science / Nutrition", "Open-minded, seek for new challenges, passion"], "locations": ["Tai Po Area"], "categories": ["Manufacturing", "Manufacturing Management", "Production Planning / Control", "Quality Assurance, Control & Testing / ISO"], "post_time": "2022-01-18T02:55:46Z", "salary": {"currency": null, "max": null, "min": null, "period": "monthly", "term": null}, "salary_visible": false, "title_keywords": ["production officer"], "responsibilities": ["food safety", "schedules", "analysis", "systems", "quality", "developing", "month-end", "ensure compliance", "lead a team", "maintain", "reports", "ad hoc assignments", "audits", "day-to-day operation"], "requirements": {"degrees": ["higher diploma or above"], "majors": ["manufacturing", "engineering", "food science"], "languages": ["english", "mandarin"], "language_level": ["advantage", "proficient"], "hard_skills": ["problem-solving skills", "sap"], "soft_skills": ["detail-minded", "self-motivated", "team-player", "sensitive to figures", "well-organized", "willing to learn", "communication", "problem-solving skills"], "languages_combined": [{"language": "english", "language_level": ["advantage", "proficient"]}, {"language": "mandarin", "language_level": ["advantage", "proficient"]}]}, "experience_required": {"duration": ["2-4 years"], "field": ["food", "relevant experience", "manufacturing industry"]}}, {"job_id": "100003009048315", "location_code": "hk", "company": "DKSH Hong Kong Limited", "job_title": "Specialist, Quality Assurance - Healthcare", "description": "Job Responsibilities:\n\nSupport the design and development of quality assurance procedures, processes and standards to ensure alignment to global DKSH quality policy and local regulatory guidelines\nPrepare and assist in designing quality assurance systems, including the development of SOPs, quality checklists, supporting tools and techniques\nAssist in qualification, validation of equipment and facility\nAssist in handling of complaints, deviations, and change control\nAnalyze data to identify areas for improvement in practices and processes\nMaintain all controlled document files and quality records in a timely and accurate manner\nProvide training to employees on quality awareness and offer technical assistance to production on quality and process improvements as well as trouble shooting when necessary\n\nJob Requirements:\n\nDegree/Diploma holder in science related courses\nRegistered Authorized Person / Quality Assurance Officer (Secondary Packaging) would be an advantage\nExperience in working with pharmaceutical industry\u00a0\nCertificate in quality management system is preferred\nKnowledge in ISO 9001, ISO 13485, GDP and PIC/S GMP practices, standards\nGood communication skills in both English and Chinese\nProficient in MS Office applications\nCandidate with more experience will be considered as Senior Specialist\nWorking location:\u00a0Mapletree, Tsing Yi\n\n\nWe offer performance bonus and attractive benefits including medical insurance and company shuttle bus services to the right candidate. Interested parties please apply in full resume with current and expected salaries to Human Resources Department , DKSH Hong Kong Limited, 23rd Floor, Tower A, Southmark, 11 Yip Hing Street, Wong Chuk Hang, Hong Kong or by clicking \"Apply Now\"\n\nAll personal data collected will be used for recruitment purposes only. \u00a0Candidates will be contacted within 2 weeks if the background and experience are closely relevant to the job requirement.\n\nDrive Growth. Be the Difference. Join DKSH.\n\nDKSH\u2019s strength lies in our great diversity of services, industries, clients, products, regions and employees from various nationalities. We are proud of our people: they are the reason we are successful. Our people are the best in the industry. They are passionate about their career growth and about business success. They work as part of an energetic and committed team, positively impacting millions of lives through the products and services we provide.\u00a0Join us today if you are ready to \u201cDrive growth. Be the Difference.\u201d\u00a0With DKSH, you will experience a world of learning and development, own your career and take business responsibility and have a positive impact that touches people\u2019s lives.", "employment_types": ["Full Time", "Permanent"], "selling_points": ["Diploma or Degree holder in science related course", "Experience in working with pharmaceutical industry", "Registered AP / QAO (Secondary Packaging)"], "locations": ["Tsing Yi"], "categories": ["Medical Services", "Others", "Pharmaceutical", "Manufacturing", "Quality Assurance, Control & Testing / ISO"], "post_time": "2022-01-14T06:13:18Z", "salary": {"currency": null, "max": null, "min": null, "period": "monthly", "term": null}, "salary_visible": false, "title_keywords": ["specialist"], "responsibilities": ["provide training", "control", "guidelines", "systems", "quality", "procedures", "design", "maintain", "sops", "designing", "analyze data", "technical assistance"], "requirements": {"degrees": ["diploma holder", "certificate", "degree"], "majors": ["science", "quality management"], "languages": ["english", "chinese"], "language_level": ["good"], "hard_skills": ["ms office"], "soft_skills": ["communication skills"], "languages_combined": [{"language": "english", "language_level": ["good"]}, {"language": "chinese", "language_level": ["good"]}]}, "experience_required": {"duration": [], "field": ["pharmaceutical"]}}, {"job_id": "100003009055759", "location_code": "hk", "company": "Amoy Food Ltd", "job_title": "QC Inspector (Food Industry)", "description": "Responsibilities:\n\nPerform daily production on-line testing and analysis, review and decide the status of incoming\u00a0materials and finished products\nCompare lab results with specification standards and coordinate with internal and external parties for follow up and improvement actions\nPerform routine sampling, recording, and inspection\nParticipate in\u00a0quality inspections, audits, and other quality-related projects\n\nRequirements:\n\nHigher Diploma in Food Science/Nutrition or related discipline\n1-2 year working experience preferably gained\u00a0in the laboratory of food manufacturing industry (Fresh graduates will also be considered)\nDetail-minded with good analytical skills\nGood interpersonal and communication skills, ability to solve problems and work under pressure\nProficiency in both Chinese and English as well as computer applications\nImmediate available is highly preferred\n\nInterested parties please send your resume with current and expected salary and availability:\n\n- \u00a0by fax to 2666 6575\n- \u00a0by mail to\n\u00a0 \u00a0Human Resources Department\n\u00a0 \u00a0Amoy Food Limited\n\u00a0 \u00a011-15 Dai Fu Street,Tai Po Industrial Estate,Tai Po, N.T.\n- \u00a0by \u201cApply Now\u201d\n\nFor enquiries, please contact our Recruitment Hotline at 2660-3403 / 5545-8814.\u00a0Employment Application Form can be downloaded from the company website\u00a0www.amoy.com\u00a0\n\nAll applications will be treated in strict confidence and retained for 6 months for recruitment purposes only.\u00a0", "employment_types": ["Full Time", "Permanent"], "selling_points": ["Higher Diploma in Food Science/Nutrition", "1-2 year working experience / Fresh graduates", "Shuttle bus, Strong food safety awareness"], "locations": ["Tai Po Area"], "categories": ["Sciences, Lab, R&D", "Food Science", "Manufacturing", "Quality Assurance, Control & Testing / ISO", "Others"], "post_time": "2022-01-18T02:55:45Z", "salary": {"currency": null, "max": null, "min": null, "period": "monthly", "term": null}, "salary_visible": false, "title_keywords": ["qc inspector"], "responsibilities": ["analysis", "internal and external parties", "review", "coordinate with", "quality", "testing", "inspection", "audits"], "requirements": {"degrees": ["diploma"], "majors": ["food science"], "languages": ["english", "chinese"], "language_level": ["proficiency"], "hard_skills": ["analytical skills"], "soft_skills": ["detail-minded", "communication skills", "analytical skills", "solve problems", "interpersonal", "work under pressure"], "languages_combined": [{"language": "english", "language_level": ["proficiency"]}, {"language": "chinese", "language_level": ["proficiency"]}]}, "experience_required": {"duration": ["1-2 year"], "field": ["laboratory", "food manufacturing industry"]}}, {"job_id": "100003009055760", "location_code": "hk", "company": "Amoy Food Ltd", "job_title": "\u751f\u7522\u6280\u8853\u54e1 (\u4e0d\u9700\u8f2a\u73ed)", "description": "\u8077\u8cac\uff1a\n\n\u64cd\u4f5c\u751f\u7522\u6a5f\u5668 / \u9810\u5099\u539f\u6599\u00a0\n\u9810\u5099\u751f\u7522\u7269\u6599\uff0c\u914d\u5408\u751f\u7522\u8981\u6c42\n\u7dad\u6301\u751f\u7522\u7dda\u4e4b\u6b63\u5e38\u904b\u4f5c\n\u5165\u8077\u8981\u6c42\uff1a\n\u51771-2\u5e74\u7684\u98df\u54c1\u751f\u7522\n\u85aa\u91d1\u4e36\u798f\u5229\u53ca\u5de5\u4f5c\u6642\u9593\uff1a\n\n\n\u6bcf\u6708$15,000 - $18,000\n\u514d\u8cbb\u7a7f\u68ad\u5df4\u58eb\u670d\u52d9\n\u514d\u8cbb\u5348\u994d\u63d0\u4f9b\n\u914c\u60c5\u82b1\u7d05\n\u52a0\u73ed\u6d25\u8cbc\n\u5728\u8077\u57f9\u8a13\n\u54e1\u5de5\u8cfc\u7269\u512a\u60e0\n\u661f\u671f\u4e00\u81f3\u4e94\uff1a\u4e0a\u53488:15 \u81f3\u4e0b\u53486:20\n\n\u4e0d\u9700\u8f2a\u73ed\n\n\u7533\u8acb\u65b9\u6cd5\n1. \u81f4\u96fb 5545-8814 \u6216\n2. \u6309\u201cApply Now\u201d \u6216\n3. \u5c07\u500b\u4eba\u5c65\u6b77\u90f5\u5bc4\u81f3\u65b0\u754c\u5927\u57d4\u5de5\u696d\u90a8\u5927\u5bcc\u885711-15\u865f \u4eba\u529b\u8cc7\u6e90\u90e8\u6536 \u6216\n4. \u50b3\u771f\u81f32666-6575\n\n\uff08\u7533\u8acb\u4eba\u63d0\u4f9b\u4e4b\u8cc7\u6599\u5c07\u7d55\u5c0d\u4fdd\u5bc6\u53ca\u53ea\u4f5c\u62db\u8058\u7528\u9014\uff09\u00a0", "employment_types": ["Full Time", "Permanent"], "selling_points": ["\u64cd\u4f5c\u751f\u7522\u6a5f\u5668 / \u9810\u5099\u539f\u6599", "\u4e94\u5929\u5de5\u4f5c\uff0c \u5ee0\u8eca\u63a5\u9001\uff0c\u82b1\u7d05\uff0c\u91ab\u7642\u798f\u5229\uff0c\u5f37\u7a4d\u91d1", "\u9810\u5099\u751f\u7522\u7269\u6599\uff0c\u914d\u5408\u751f\u7522\u8981\u6c42\uff0c\u7dad\u6301\u751f\u7522\u7dda\u4e4b\u6b63\u5e38\u904b\u4f5c"], "locations": ["Tai Po Area"], "categories": ["Manufacturing", "Manufacturing Management", "Production Planning / Control", "Quality Assurance, Control & Testing / ISO"], "post_time": "2022-01-18T02:55:46Z", "salary": {"currency": null, "max": null, "min": null, "period": "monthly", "term": null}, "salary_visible": false, "title_keywords": ["\u751f\u7522\u6280\u8853\u54e1"], "responsibilities": [], "requirements": {"degrees": [], "majors": [], "languages": [], "language_level": [], "hard_skills": [], "soft_skills": [], "languages_combined": []}, "experience_required": {"duration": [], "field": []}}, {"job_id": "100003009049009", "location_code": "hk", "company": "Cathay Pacific Catering Services (H.K.) Limited", "job_title": "Quality Assurance Officer", "description": "Responsibilities\u00a0\n\nEnsure product quality is within the approved specification and in compliance with the corporate standards by performing daily quality assurance activities\nConduct hygiene audit and provide hygiene training\nAddress quality and hygiene issues and conduct problem solving\nImplement, monitor and improve quality and hygiene management systems\nMaintain and upgrade HACCP / hygiene programmes\nMaintain documentation system including various food safety records\nFood sample preparation, conduct the microbial test, lab result analysis and report preparation\nConduct equipment calibration\nAssist ad-hoc tasks as assigned\nShift duty is required\nRequirements\n\nHigher Diploma or Degree holder (or equivalent) in Food Science / Food Technology or related discipline\n1-year working experience in food processing QA role is preferred\nKnowledge and experience in setting up HACCP / ISO2200 for central kitchen would be an advantage\nExperience in laboratory tests particularly on microbiological testing is preferred\nGood knowledge in hygiene control and QA documentation\nSelf-motivated, hard-working and independent\nGood communication and interpersonal skills\nProficient in PC operations, including nutritional analysis software and Microsoft Office\nGood command of both written and spoken English and Chinese\nWe offer a competitive remuneration package and a full range of benefits. Interested parties please send your resume with your current and expected salary to Head of People,11 Catering Road East, Hong Kong International Airport, Lantau, Hong Kong or by clicking the \"Apply Now\" button\u00a0on or before 10 February 2022.\nPersonal data collected will be treated in the strictest confidence and only be used for recruitment-related purposes. Applicants who do not receive notification for an interview within six weeks may consider their application unsuccessful.", "employment_types": ["Full Time", "Permanent"], "selling_points": ["Maintain HACCP / hygiene programmes", "On job training provided", "Career advancement opportunities"], "locations": ["Airport Area"], "categories": ["Manufacturing", "Production Planning / Control", "Quality Assurance, Control & Testing / ISO"], "post_time": "2022-01-14T07:54:19Z", "salary": {"currency": null, "max": null, "min": null, "period": "monthly", "term": null}, "salary_visible": false, "title_keywords": ["quality assurance officer"], "responsibilities": ["management", "food safety", "sample preparation", "analysis", "compliance", "monitor", "quality", "audit", "systems", "ad-hoc tasks", "hygiene", "maintain", "maintain documentation", "report"], "requirements": {"degrees": ["diploma", "degree holder"], "majors": ["food science"], "languages": ["english", "chinese"], "language_level": ["good command"], "hard_skills": ["microsoft office", "analysis", "pc operations", "documentation", "processing"], "soft_skills": ["self-motivated", "communication and interpersonal skills", "hard-working", "independent"], "languages_combined": [{"language": "english", "language_level": ["good command"]}, {"language": "chinese", "language_level": ["good command"]}]}, "experience_required": {"duration": ["1-year"], "field": ["food", "laboratory", "qa", "testing"]}}, {"job_id": "100003009046456", "location_code": "hk", "company": "ConnectedGroup Limited", "job_title": "Head of Quality Assurance", "description": "Head of Quality Assurance\n\nA leading global retailer is looking for a true leader to join them as their highly successful HK sourcing office as the head of quality assurance. To be successful in this role, you will need to have the ability to lead a large team with over 10 direct reports, with strong product technical knowledge across hardgoods and softgoods, as well as carrying the ability to manage internal and external key-stakeholders.\n\nReporting to the COO, you will be responsible for:\n\nDefine and implement the quality management strategy, operations and processes to achieve the business goals\nWorking closely with the sourcing, PD, CSR teams, ensure that the common goals are achieved with optimal efficiency by lead-time and cost\nManage the performance of vendors such as third-party laboratory\nBe the technical expert to provide technical solutions and handle trouble-shooting scenarios\nContinuously reviewing and, when needed, improving the quality processes to align with the internal customer's standards and requirements\nWorking with the sourcing team, be involved in the development process in terms of managing the sample making and highlight potential risks, production feasibility, testing standards/requirements etc.\nManage, develop and lead the team to ensure continuous high performing levels and sustained development\n\nRequirements\n\nBachelor degree or above is a must\nMinimum of 15 years of relevant experience, with at least 3 years at director level\nStrong knowledge across multiple product categories particularly in hardgoods is a must\nExperience leading large teams of minimum of over 50 staffs is a must, whilst experience leading regional teams will be advantageous\nOutstanding communication skills with written and spoken English the priority\nCandidates who are currently located in Hong Kong will be highly preferred\nFrequent travelling (when allowed) will be needed\n\nInterested parties please send your CV to Vincent.chow@connectedgroup.com", "employment_types": ["Full Time", "Permanent"], "selling_points": ["Fast Growing Company", "Great Career Prospects & Opportunities", "International presence"], "locations": ["Not Specified"], "categories": ["Engineering", "Manufacturing & Production", "Manufacturing", "Quality Assurance, Control & Testing / ISO"], "post_time": "2022-01-13T11:20:53Z", "salary": {"currency": null, "max": null, "min": null, "period": "monthly", "term": null}, "salary_visible": false, "title_keywords": [], "responsibilities": ["product categories", "reporting", "management", "business goals", "cost", "operations", "quality", "teams", "testing", "develop", "communication", "reports"], "requirements": {"degrees": ["degree or above", "bachelor"], "majors": [], "languages": ["english"], "language_level": [], "hard_skills": [], "soft_skills": ["communication skills", "responsible"], "languages_combined": [{"language": "english", "language_level": []}]}, "experience_required": {"duration": ["at least 3 years", "minimum of 15 years"], "field": ["relevant experience"]}}, {"job_id": "100003009050214", "location_code": "hk", "company": "Saint Honore Cake Shop Ltd", "job_title": "Senior Quality Assurance Officer", "description": "Responsibilities:\nImplementation and maintenance of quality management system;\nPerform food safety, hygiene inspection and monitor in production floor to ensure the operation complies with all statutory requirements and in-house hygiene standard;\nFocus on quality enhancement;\nAssist in\u00a0ad hoc projects as assigned.\n\u00a0Requirements:\n\nBachelor Degree in Food & Nutritional Science or equivalent;\n5 years relevant experience in food manufacturing industry;\nKnowledge of GMP/ HACCP & ISO 9001 and food regulation would be an advantage;\nIndependent, responsible with good communication skill;\nProficient in Chinese Word, Excel and PowerPoint;\nCandidate with more experience could be considered as Assistant QA Manager\nInterested parties, please forward your resume stating salary expectation and available date to us.\n\nFor more information of Saint Honore Cake Shop, please visit www.cr-asia.com\nAll applications will be treated in the strictest confidence. Personal data provided will be used for recruitment purpose only. The information collected might also be disclosed to other associated companies of the Fung Group for job matching of similar vacancies.\nThe provision of full and complete information in support of your application is necessary for selection purposes. Applicant has the right to request access to and correction of personal data collected from him/her in writing to the Human Resource Manager by post to P.O. Box 92408, Tsim Sha Tsui Post Office, Hong Kong.", "employment_types": ["Full Time"], "selling_points": ["Focus on quality enhancement", "Implementation & maintenance of quality mgt system", "5 yrs exp. in food manufacturing industry"], "locations": ["Kwai Tsing Area"], "categories": ["Sciences, Lab, R&D", "Food Science", "Laboratory", "Manufacturing", "Quality Assurance, Control & Testing / ISO"], "post_time": "2022-01-14T09:57:02Z", "salary": {"currency": null, "max": null, "min": null, "period": null, "term": null}, "salary_visible": false, "title_keywords": ["senior quality assurance officer"], "responsibilities": ["management", "food safety", "maintenance", "quality", "implementation", "monitor", "inspection", "hygiene", "statutory requirements", "ad hoc projects"], "requirements": {"degrees": ["degree", "bachelor"], "majors": ["science"], "languages": ["chinese"], "language_level": ["proficient"], "hard_skills": ["excel", "word", "powerpoint"], "soft_skills": ["communication skill", "independent", "responsible"], "languages_combined": [{"language": "chinese", "language_level": ["proficient"]}]}, "experience_required": {"duration": ["5 years"], "field": ["food manufacturing industry", "relevant experience", "qa"]}}, {"job_id": "100003009050819", "location_code": "hk", "company": "Sky Manufacturing Services Limited", "job_title": "Senior Quality Engineer / Quality Engineer", "description": "Senior Quality Engineer / Quality Engineer\n\nJob Responsibilities:\n\nResponsible for overseeing day to day operations of all quality functions performed by our contract manufacturers and downstream suppliers.\nMonitor, analyze and drive continuous improvement in manufacturing process on quality issues to ensure demonstrated success in production yield and consistent good product quality performance.\nInvolve in conducting failure analysisand develop corrective and preventive measure.\nPerform regular factory quality assessment for suppliers and follow up their corrective actions.\nLiaise and work closely with Head-Quarter to handle quality related matters.\n\nJob Requirements:\n\nDegree\u00a0holder in Quality / Electronic / Production / Manufacturing Engineering or related discipline.\n5+ years\u00a0practical Quality Engineering experience in consumer electronic / wireless products manufacturing OR substantiate relevant work experience in Electronic Manufacturing services industry.\nSound Knowledge in international Safety & Regulatory Standards included RoHS and REACH requirements.\nFamiliar with Statistical Quality analysis tools such as six-sigma methodology.\nFrequent travel to PRC and oversea factories is necessary.\nGood command of written and spoken English and Chinese (include Putonghua).\nGood communication and presentation skills and able to work independently.", "employment_types": ["Full Time", "Permanent"], "selling_points": ["Perform regular factory quality assessment", "5+ years practical quality control experience", "5 days work, Bank holiday, Medical"], "locations": ["Wong Tai Sin Area"], "categories": ["Engineering", "Electrical / Electronics", "Manufacturing & Production", "Manufacturing", "Quality Assurance, Control & Testing / ISO"], "post_time": "2022-01-15T03:51:15Z", "salary": {"currency": null, "max": null, "min": null, "period": "monthly", "term": null}, "salary_visible": false, "title_keywords": ["engineer"], "responsibilities": ["liaise", "day to day operations", "monitor", "quality", "develop"], "requirements": {"degrees": ["degree holder"], "majors": ["manufacturing", "engineering"], "languages": ["putonghua", "english", "chinese"], "language_level": ["good command"], "hard_skills": ["analysis"], "soft_skills": ["communication", "presentation skills", "work independently"], "languages_combined": [{"language": "putonghua", "language_level": ["good command"]}, {"language": "english", "language_level": ["good command"]}, {"language": "chinese", "language_level": ["good command"]}]}, "experience_required": {"duration": ["5+ years"], "field": ["manufacturing", "engineering"]}}, {"job_id": "100003009055472", "location_code": "hk", "company": "API Lab Testing Limited", "job_title": "TCF Engineer (Textile)", "description": "Job Overview:\n\nAs a TCF Textile Engineer, he/she need to conduct the compliance and tracerabaility documentation check under the projects from fibre, style and final product accrording to the customer request. He/she need to contact and communicate with the worldwide suppliers for chasing the documents, reviewing the document, providing the status report to customer and joining the customer review meeting with KAM and other managmnent occasionally & regularly.\n\nEssential Duties and Responsibilities:\n\nCollecting, reviewing and validating certificates and test reports from suppliers reg. traceability.\nKeep clients and their suppliers updated and monitor the program status.\nUndertake any other duties in coping with the business growth.\nAssists in other duties as directed by the Manager.\n\nExperience & Competencies Required:\n\nAt least 2 years' experience in textile product testing or textile trading / manufacturing company,\nFamiliar with raw material / fabric/ garment compliance/ supply chain traceability\nExtensive knowledge of textile manufacturing processes will be strong plus.\nWorking experience in commercial testing laboratory/ in house testing laboratory will be an advantage\nFamiliar with EU/US regulation on Textile, knowledge on other categories such as toys, furniture, chemical and related regulations are highly preferable\nCandidate with more experience will be considered as Senior Engineer.\nHighly-organized, capable of working under pressure with multi-task assignments\nGood command of English and Chinese.\n\nEducation and Qualifications Required:\n\nHigh Diploma or above in Textile or related discipline\n\nTools Skills:\n\nProficient in Microsoft Programs, including Word, Excel, PowerPoint and Outlook.\n\nDisclaimer:\n\nJob duties and requirements are subject to change. The company reserves the right to modify position descriptions accordingly at any time with little or no prior notice.", "employment_types": ["Full Time"], "selling_points": ["TCF Engineer, Textile, Lai Chi Kok", "Material, Fabric, Garment Compliance, Supply chain", "Reviewing & Validating Certificates, Quality"], "locations": ["Kowloon City"], "categories": ["Manufacturing", "Garment / Textile", "Professional Services", "Legal & Compliance", "Quality Assurance, Control & Testing / ISO"], "post_time": "2022-01-18T02:38:04Z", "salary": {"currency": "HKD", "max": 24999, "min": 20000, "period": "monthly", "term": null}, "salary_visible": true, "title_keywords": ["engineer"], "responsibilities": ["communicate with", "any other duties", "regulations", "other duties", "compliance", "review", "monitor", "testing", "reports", "contact", "documentation", "report"], "requirements": {"degrees": ["high diploma or above"], "majors": [], "languages": ["english", "chinese"], "language_level": ["good command"], "hard_skills": ["excel", "plus", "no", "word", "powerpoint", "outlook", "documentation"], "soft_skills": ["organized", "under pressure", "capable", "multi-task", "extensive"], "languages_combined": [{"language": "english", "language_level": ["good command"]}, {"language": "chinese", "language_level": ["good command"]}]}, "experience_required": {"duration": ["at least 2 years"], "field": ["laboratory", "manufacturing", "senior engineer", "testing", "commercial", "textile", "trading"]}}, {"job_id": "100003009047065", "location_code": "hk", "company": "Vickmans Laboratories Limited", "job_title": "Quality Assurance Assistant", "description": "Key Roles and Responsibilities:\n\nAssist in developing, implementing and maintaining the documentation system and quality management system;\nPerform routine inspection on products at various stages on the production line to implement the GMP policy;\nAssist in performing ad hoc project and\u00a0other\u00a0QA-related duties.\n\nRequirements:\n\nHigher Diploma or Degree holder in Pharmaceutical Studies or other science related discipline;\nHands-on GMP experience in pharmaceutical industry will be an definite advantage;\nHardworking, initiative, self-motivated and fast learner;\nStrong communication skill, good command of English and Chinese;\nGood knowledge of MS Office and Chinese word processing;\nFresh graduates are\u00a0also considered.\n\n\n\nWe offer to the right candidates with competitive remuneration package including 12-16 day annual leave, marriage leave, maternity leave, paternity leave, compassionate leave, Public Holidays, medical and dental insurance, educational sponsorship, overtime allowance, performance bonus, MPF and other fringe benefits.\n\nHow to Apply\n\nYou are invited to send in your application and CV stating the position you are applying for together with your current and expected salary by clicking the \"apply button\".\n\n\u00a0\nVickmans LaboratoriesLimited is an Equal Opportunities Employer. Personal data provided by job applicants will be used strictly in accordance with our personal data policy and for recruitment purposes only. We aim to respond to successful applicants within 8 weeks and related information will be kept in our file for up to 12 months for other suitable vacancies in our organization and thereafter destroyed", "employment_types": ["Full Time", "Permanent"], "selling_points": [], "locations": ["Ngau Tau Kok"], "categories": ["Manufacturing", "Production Planning / Control", "Medical Services", "Pharmaceutical", "Quality Assurance, Control & Testing / ISO"], "post_time": "2022-01-14T02:13:31Z", "salary": {"currency": null, "max": null, "min": null, "period": null, "term": null}, "salary_visible": false, "title_keywords": ["quality assurance assistant"], "responsibilities": ["management", "ad hoc", "maintaining", "quality", "developing", "inspection", "documentation"], "requirements": {"degrees": ["diploma", "degree holder"], "majors": ["science"], "languages": ["english", "chinese"], "language_level": ["good command", "good"], "hard_skills": ["chinese word processing", "ms office"], "soft_skills": ["self-motivated", "communication skill", "hands-on", "fast learner", "initiative", "hardworking"], "languages_combined": [{"language": "english", "language_level": ["good command", "good"]}, {"language": "chinese", "language_level": ["good command", "good", "good"]}]}, "experience_required": {"duration": [], "field": ["pharmaceutical"]}}, {"job_id": "100003009051574", "location_code": "hk", "company": "A.S. Watson Industries", "job_title": "Production Manager", "description": "Responsible for the day-to-day operation of Production Department\nOversee overall production scheduling and material planning for all production lines\nOversee production lines performance to achieve departmental target\nCoordinate with Procurement, Warehouse and Sales teams to supply sufficient stock and meet sales requirement\nPrepare and control Departmental budget and expense\nAssist new capital investment and project implementation\n\n\u00a0Job Requirement\n\nDegree holder in Engineering or other related disciplines\nMinimum 8years relevant working experience in managing sizeable manufacturing companies, in which 4 years at managerial level. Experience in Food and Beverage and FMCG companies is an added advantage\nStrong leadership and problem-solving skills\nKnowledge in ISO22000 and GMP\nERP or Oracle knowledge is advanced\nEnergetic, well-organized, detail-minded, strong sense of responsibility, able to work independently & multi-task\nGood communication, presentation and interpersonal skill\nGood command of written and spoken English, Chinese and Mandarin\nPC knowledge in MS Excel, Word & PowerPoint and Chinese Processing\n\nWe offer competitive salary, discretionary performance bonus, medical and retirement benefits, free company coach services and excellent career prospects. Please send your resume together with salary expectation via\u00a0APPLY NOW\n\nFor more information, please visit our website at\u00a0www.aswatson.com\n\nAll information provided will be used for recruitment and other employment-related purposes by A.S. Watson & Company Limited (for and on behalf of the A.S. Watson Group of companies). It may be provided to companies/parties authorized to process the information for purposes relating to recruitment, e.g. qualifications assessment.\n\nWith the consent of applicant, all personal data of unsuccessful applicants will be retained for future consideration for two years. Otherwise, all personal data of unsuccessful applicants will be retained for twelve months.\n\nApplication will not be considered if the applicant does not provide all information as requested.\n\nAll information provided will be held in strict confidence.\n\nIf applicant request access to, and to request correction of personal data in relation to the application, please contact our People Department at 2660 1880.", "employment_types": ["Full Time", "Permanent"], "selling_points": ["Responsible for daily production operations", "Production scheduling and material planning", "Supply sufficient stock & meet sales requirements"], "locations": ["Tai Po Area"], "categories": ["Manufacturing", "Manufacturing Management", "Production Planning / Control", "Quality Assurance, Control & Testing / ISO"], "post_time": "2022-01-16T11:27:28Z", "salary": {"currency": null, "max": null, "min": null, "period": "monthly", "term": null}, "salary_visible": false, "title_keywords": ["production manager"], "responsibilities": ["control", "budget", "teams", "coordinate with", "implementation", "website", "communication", "scheduling", "recruitment", "contact", "personal data", "day-to-day operation", "planning"], "requirements": {"degrees": ["degree holder"], "majors": ["related disciplines", "engineering"], "languages": ["english", "chinese", "mandarin"], "language_level": ["good command"], "hard_skills": ["word", "erp", "powerpoint", "ms excel", "problem-solving skills", "pc knowledge", "processing", "oracle"], "soft_skills": ["detail-minded", "work independently", "confidence", "multi-task", "advanced", "responsible", "sense of responsibility", "well-organized", "interpersonal skill", "communication", "problem-solving skills", "energetic", "leadership", "presentation"], "languages_combined": [{"language": "english", "language_level": ["good command"]}, {"language": "chinese", "language_level": ["good command"]}, {"language": "mandarin", "language_level": ["good command"]}]}, "experience_required": {"duration": ["4 years"], "field": ["managerial", "manufacturing", "fmcg", "relevant working experience", "food"]}}, {"job_id": "100003009040322", "location_code": "hk", "company": "REWE Far East Limited", "job_title": "Field Technologist", "description": "Key Responsibilities:\n\n\nPerform factory inspections.\nPerform on site audits and supplier evaluation based on quality criteria.\nProvide training to suppliers on our quality requirements.\nPerform product evaluation on-site and in office.\nAccompany the production process on-site to ensure REWE quality requirements.\nAttend buying trips with buyers and merchandiser.\nPrepare weekly report on QA/factory audit/project progress.\n\n\nJob Requirements:\n\n\nDiploma or above in related discipline.\nMinimum of 3 years in quality management/quality control in consumer goods or testing laboratory.\nAble to have frequent travel.\nKnowledge of production processes is a plus.\nSelf-driven and solution oriented, and comfortable to work in cross-cultural environment.\nGood assertiveness and communication skills.\nGood command of both written and spoken English and Chinese (Cantonese and Mandarin).\nGood PC knowledge (Microsoft office suite).\n\nIf you are interested in the position, please submit your full resume with cover letter, current and expected salary and available date via JobsDB.\n\nAll\u00a0personal information is collected for recruitment purpose only and will be treated in strict confidentiality.\u00a0\u00a0", "employment_types": ["Full Time", "Permanent"], "selling_points": ["Factory Inspection & On Site Audits", "EU buying office, Mobile Working, Flex Working Hr", "13th Month Bonus, Discretionary Bonus"], "locations": ["Kwun Tong Area"], "categories": ["Merchandising & Purchasing", "Procurement / Purchasing / Sourcing", "Manufacturing", "Quality Assurance, Control & Testing / ISO"], "post_time": "2022-01-16T21:50:04Z", "salary": {"currency": null, "max": null, "min": null, "period": "monthly", "term": null}, "salary_visible": false, "title_keywords": [], "responsibilities": ["provide training", "production process", "quality", "audit", "project progress", "evaluation", "audits", "report"], "requirements": {"degrees": ["diploma or above"], "majors": [], "languages": ["cantonese", "english", "chinese", "mandarin"], "language_level": ["good command"], "hard_skills": ["microsoft office suite", "plus", "pc knowledge"], "soft_skills": ["communication skills", "interested in", "driven"], "languages_combined": [{"language": "cantonese", "language_level": ["good command"]}, {"language": "english", "language_level": ["good command"]}, {"language": "chinese", "language_level": ["good command"]}, {"language": "mandarin", "language_level": ["good command"]}]}, "experience_required": {"duration": [], "field": []}}, {"job_id": "100003009050387", "location_code": "hk", "company": "Fly King Transportation Company Ltd", "job_title": "Quality Assurance Officer", "description": "Responsibilities\nParticipate in internal / external audits\nProvide on-site coaching to frontline staff\nPrepare and review SOP and other quality related documents\nConduct quality control inspections and attend meetings\nAssist to identify operational deficiency and suggest corrective / preventive plans\nAssist in implementing and maintaining quality projects\nAny ad hoc duties as assigned by superior\nRequirements\nDiploma level or above\n1 years\u2019 relevant experience in air cargo industry is highly preferred\nWork independently and attention in detail\nStrong sense of responsibility and good interpersonal skills\nFluency in spoken and written Chinese and English\nProficient in MS applications including Word, Excel and Powerpoint\nCandidate with more relevant experience will be considered as Senior Quality Assurance Officer\nInterested parties, please send application with full particulars of qualifications, experience, current and expected salary by email via \"Apply Now\"\nAll information will be kept confidential and used for recruitment purpose only.", "employment_types": ["Full Time", "Permanent"], "selling_points": [], "locations": ["Airport Area"], "categories": ["Transportation & Logistics", "Others", "Manufacturing", "Others", "Quality Assurance, Control & Testing / ISO"], "post_time": "2022-01-14T10:15:56Z", "salary": {"currency": null, "max": null, "min": null, "period": "monthly", "term": null}, "salary_visible": false, "title_keywords": ["quality assurance officer"], "responsibilities": ["ad hoc duties", "conduct quality control", "maintaining", "related documents", "review", "quality", "attend meetings", "audits", "plans"], "requirements": {"degrees": ["diploma"], "majors": [], "languages": ["english", "chinese"], "language_level": ["fluency"], "hard_skills": ["excel", "ms applications", "word", "powerpoint"], "soft_skills": ["work independently", "interpersonal skills", "sense of responsibility"], "languages_combined": [{"language": "english", "language_level": ["fluency"]}, {"language": "chinese", "language_level": ["fluency"]}]}, "experience_required": {"duration": ["1 years"], "field": ["relevant experience", "quality assurance"]}}, {"job_id": "100003009050763", "location_code": "hk", "company": "Vita Green Pharmaceutical (H.K.) Limited", "job_title": "Quality Inspector", "description": "The Role:\n\nQuality Management plays a vital role in production while Vita Green Group is committed to serve our customers with the-highest-quality products in order to meet our customer satisfaction. We are now looking for candidates who are passionate in the discipline of quality control. You will be participating in the inspection of the whole production process, working closely with Production team and providing clerical support. Moreover, you are given opportunities to explore an international standard of food and drugs production by undertaking regular programs and calibrations.\n\u00a0\n\nIf you are ...\u00a0\n\na fresh graduate or the holder of Higher Diploma or above, preferably in Science, Chinese Medicine, Biotechnology, Biochemistry, Food Production, Manufacturing, Catering or Retail Industry.\nself motivated, flexible and interested in developing your career in a stable manufacturing environment and well known company.\na person who strives for renewal and improvement.\na team player\u00a0and willing to learn to develop yourself.\u00a0\n\n\n\nWe will offer you...\n\n\u00a0 \u00a0 \u00a0 \u00a0A career opportunity with the market leader in health product sector.\n\u00a0 \u00a0 \u00a0 \u00a0Casual wear everyday to enjoy your work.\n\u00a0 \u00a0 \u00a0 \u00a0Free shuttles from various locations.\n\u00a0 \u00a0 \u00a0 \u00a0Many opportunities\u00a0to learn and grow together.\n\u00a0 \u00a0 \u00a0 \u00a0Rapid growth opportunities for strong performers.\u202f\u00a0\n\u00a0 \u00a0 \u00a0 \u00a0Attractive staff purchase discount to experience our quality products.\n\nInterested parties, please send full resume with last & expected salary and date of available by clicking \u2018Apply\u2019.\n\nPersonal data collected is for recruitment purpose only.\n\nFor corporate information, please visit:\u00a0www.vitagreen.com", "employment_types": ["Full Time", "Permanent"], "selling_points": ["PIC/S GMP manufacturer", "Great career opportunity", "Performing inspection of production process"], "locations": ["Tai Po Area"], "categories": ["Medical Services", "Pharmaceutical", "Manufacturing", "Quality Assurance, Control & Testing / ISO", "Sciences, Lab, R&D", "Others"], "post_time": "2022-01-14T11:18:14Z", "salary": {"currency": null, "max": null, "min": null, "period": "monthly", "term": null}, "salary_visible": false, "title_keywords": [], "responsibilities": ["management", "production process", "quality", "clerical support", "developing", "inspection", "develop", "purchase", "quality control", "catering"], "requirements": {"degrees": ["higher diploma or above", "fresh graduate"], "majors": ["science", "manufacturing"], "languages": ["chinese"], "language_level": [], "hard_skills": ["rapid"], "soft_skills": ["passionate", "flexible", "interested in", "willing to learn", "self motivated", "committed", "team player", "stable"], "languages_combined": [{"language": "chinese", "language_level": []}]}, "experience_required": {"duration": [], "field": []}}, {"job_id": "100003009047352", "location_code": "hk", "company": "\u7f8e\u570b\u5bcc\u4fca\u570b\u969b\u6709\u9650\u8cac\u4efb\u516c\u53f8\u5ee3\u5dde\u4ee3\u8868\u8655", "job_title": "Supplier Quality Engineer", "description": "DUTIES & RESPONSIBILITIES:\u00a0\n\n*Review\u00a0and\u00a0disposition\u00a0PPAP\n\n*Verify\u00a01st\u00a0production\u00a0run\u00a0through\u00a0product\u00a0certification\n\n*Work\u00a0closely\u00a0with\u00a0the\u00a0Product\u00a0Development\u00a0teams\u00a0and\u00a0Business\u00a0Response\u00a0Teams\u00a0to\u00a0meet\u00a0quality,\u00a0delivery\u00a0and\u00a0cost\u00a0goals.\n\n*Coordinate\u00a03rd\u00a0party\u00a0conformance\u00a0testing.\n\n*Communicate\u00a0and\u00a0monitor\u00a0CARs\u00a0addressed\u00a0to\u00a0the\u00a0supplier.\n\n*Perform\u00a0product\u00a0audits.\n\n*Review\u00a0Supplier\u2019s\u00a0process\u00a0control\u00a0plans\u00a0&\u00a0process\u00a0FMEAs\u00a0periodically.\n\n*Assist\u00a0supplier\u00a0with\u00a0product\u00a0inspection\u00a0and\u00a0gauging\u00a0techniques.\n\n*Responsible\u00a0for\u00a0the\u00a0source\u00a0inspection\u00a0and\u00a0product\u00a0certification\u00a0at\u00a0each\u00a0supplier.\n\n*Perform\u00a0QSA,\u00a0Social\u00a0responsibility\u00a0and\u00a0Security\u00a0audit\u00a0in\u00a0supplier.\n\n*Assist\u00a0supplier\u00a0with\u00a0quality\u00a0improvements.\u00a0\n\n*Conduct\u00a0periodic\u00a0quality\u00a0review\u00a0meeting\u00a0with\u00a0supplier\u00a0to\u00a0motivate\u00a0and\u00a0sustain\u00a0supplier\u2019s\u00a0quality\u00a0performance.\n\n*Perform\u00a0other\u00a0tasks\u00a0assigned\u00a0by\u00a0line\u00a0manager.\n\nKEY\u00a0COMPETENCIES\u00a0&\u00a0QUALIFICATIONS\n\n*QMS\u00a0Auditing\u00a0experience,\u00a0preferably\u00a0ISO9001\u00a0and\u00a0ISO/TS\u00a016949.\u00a0\n\n*Prefer\u00a0Lean/6sigma\u00a0Green\u00a0Belt\u00a0or\u00a0Black\u00a0Belt\u00a0Certified.\n\n*Experience\u00a0with\u00a0identifying\u00a0gauging\u00a0needs\u00a0and\u00a0gauge\u00a0implementation\n\n*Fluent\u00a0written\u00a0and\u00a0spoken\u00a0English\u00a0and\u00a0Mandarin\u00a0required.\u00a0\n\n*Self-motivated\u00a0person\u00a0who\u00a0can\u00a0work\u00a0with\u00a0little\u00a0direction\u00a0and\u00a0handle\u00a0multiple\u00a0tasks\u00a0at\u00a0one\u00a0time.\u00a0\n\n*Accomplishments\u00a0that\u00a0reflect\u00a0teamwork,\u00a0accountability\u00a0and\u00a0speed.\n\n*Willing\u00a0to\u00a0travel\u00a0frequently\u00a0and\u00a0work\u00a0flexible\u00a0hours\n\n*Bachelor\u2019s\u00a0degree\u00a0with\u00a0at\u00a0least\u00a05\u00a0years\u00a0working\u00a0experience\u00a0\n\n*Experience\u00a0utilizing\u00a0statistical\u00a0techniques,\u00a0classifying\u00a0tools,\u00a0process\u00a0mapping,\u00a0Lean\u00a0Thinking,\u00a0and\u00a0Control\u00a0Plan\u00a0Knowledge.\u00a0\n\nEMPLOYMENT DETAILS & BENEFITS\n\n*Full time, permanent, 5 days working week\n\n*Initial probationary period of 3 months\n\n*Based in Kowloon, Hong Kong, with ad-hoc limited travel to APAC\n\n*Medical insurance benefit\n\nYou are welcome to visit our website :\u00a0www.masterlock.com\u00a0 \u00a0\n\nAll personal data provided by\u00a0applicants will be used\u00a0for recruitment purpose only.", "employment_types": ["Full Time"], "selling_points": ["Responsible for quality assurance", "Engineering background", "Team player"], "locations": ["Kowloon City Area"], "categories": ["Manufacturing", "Quality Assurance, Control & Testing / ISO"], "post_time": "2022-01-14T02:53:26Z", "salary": {"currency": null, "max": null, "min": null, "period": "monthly", "term": null}, "salary_visible": false, "title_keywords": ["engineer"], "responsibilities": ["cost", "control", "review", "quality", "teams", "monitor", "testing", "coordinate", "inspection", "audit", "other tasks", "implementation", "plan", "audits", "plans", "auditing"], "requirements": {"degrees": ["degree", "bachelor"], "majors": [], "languages": ["english", "mandarin"], "language_level": ["fluent"], "hard_skills": ["lean"], "soft_skills": ["flexible", "self-motivated", "accountability", "responsible", "teamwork", "handle multiple tasks"], "languages_combined": [{"language": "english", "language_level": ["fluent"]}, {"language": "mandarin", "language_level": ["fluent"]}]}, "experience_required": {"duration": ["at least 5 years"], "field": []}}, {"job_id": "100003009047425", "location_code": "hk", "company": "Tai Hing Catering Group Limited", "job_title": "Quality Assurance Technician (Food Hygiene)", "description": "Responsibilities\n\nConduct factory inspection in accordance with company standard and governmental regulations\nPerform equipment calibration and on-site sampling in food production center and shops\nConduct checking and testing of raw materials and final products\nAssist in developing, maintaining and monitoring of HACCP and ISO 22000 system\nDeal with quality and hygiene related documents\nHandle ad-hoc duties as specified by the superiors\n\nRequirements\n\nHigher Diploma or above in Food Science or other related discipline\n1 year relevant experience or above (Experience in F&B industry is preferred)\nBasic knowledge on GMP, HACCP and ISO 22000 system\nProficiency in MS Office (Word, Excel & PowerPoint)\nGood command of both spoken and written English and Chinese\nShift duty is required (including public holiday & lunar new year)\nFresh graduates are also welcome\nImmediately available is preferred\n\nWe offer\u00a0competitive\u00a0package and benefits:\n\nFive-Day work week\u00a0(Shift duties is required)\n3 Days Marriage Leave\n5 Days Full Pay Paternity Leave\nFamily-Friendly Leave\nBirthday Leave\nFree Duty Meal\nStaff Discount\nMedical Allowance\nInsurance Plan\nPromotion Opportunities\n\nFor more company information, please visit our web site at\u00a0www.taihing.com\n\nInterested parties please send\u00a0full resume with expected salary\u00a0and availability\u00a0to the\u00a0Human Resources Department via email.\n\nAll information received will be kept in strict confidence and only used for employment-related purposes. Applicants who are not invited for interview within 6 weeks may consider their applications unsuccessful.", "employment_types": ["Full Time", "Permanent"], "selling_points": [], "locations": ["Shatin Area"], "categories": ["Hospitality / F & B", "Food & Beverage", "Sciences, Lab, R&D", "Laboratory", "Manufacturing", "Quality Assurance, Control & Testing / ISO"], "post_time": "2022-01-14T03:03:05Z", "salary": {"currency": null, "max": null, "min": null, "period": "monthly", "term": null}, "salary_visible": false, "title_keywords": ["technician"], "responsibilities": ["regulations", "maintaining", "related documents", "monitoring", "quality", "developing", "checking", "testing", "inspection", "hygiene", "ad-hoc duties"], "requirements": {"degrees": ["higher diploma or above"], "majors": ["food science"], "languages": ["english", "chinese"], "language_level": ["good command"], "hard_skills": ["excel", "basic", "word", "powerpoint", "ms office"], "soft_skills": [], "languages_combined": [{"language": "english", "language_level": ["good command"]}, {"language": "chinese", "language_level": ["good command"]}]}, "experience_required": {"duration": ["1 year"], "field": ["f&b", "relevant experience"]}}, {"job_id": "100003009042211", "location_code": "hk", "company": "Vita Green Pharmaceutical (H.K.) Limited", "job_title": "Senior Quality Control Technician", "description": "The Role:\n\nQuality control is one of the most important processes for Vita Green Group to ensure all our production materials and finished products with the highest qualities to meet our customer satisfaction. We are looking for candidates with great interest in developing their career in quality control discipline. You will be participating in the role of conducting sample preparation and tests in both chemistry and microbiology laboratory. Moreover, you will be contributing to method validation, performance check, instrument calibration and maintenance in a reputable, stable local manufactory company.\n\nIf you are ...\u00a0\n\nthe holder of Bachelor Degree major in\u00a0Chemistry, Biochemistry, Biology or equivalent science discipline.\nhaving strong sense in science and familiar with GMP.\nhaving experience in microbial testing.\na team player and willing to learn to develop yourself.\nself-motivated, detail-oriented and multi-tasking.\nparticularly interested in growing yourself in a stable manufacturing environment.\n\nWe will offer you...\n\nA career opportunity with the market leader in health product sector.\nCasual wear everyday to enjoy your work.\nFree shuttles from various locations.\nChallenging jobs to learn and grow together.\u00a0\nRapid growth opportunities for strong performers.\u202f\u00a0\nAttractive staff purchase discount to experience our quality products.\n\nInterested parties, please send full resume with last & expected salary and date of available by clicking \u2018Apply\u2019.\n\nPersonal data collected is for recruitment purpose only.\n\nFor corporate information, please visit:\u00a0www.vitagreen.com", "employment_types": ["Full Time", "Permanent"], "selling_points": ["PIC/s GMP pharmaceutical manufacturer", "Welcome candidate from food, drug or related field", "Great career opportunity in a leading HK brand"], "locations": ["Tai Po Area"], "categories": ["Sciences, Lab, R&D", "Laboratory", "Manufacturing", "Production Planning / Control", "Quality Assurance, Control & Testing / ISO"], "post_time": "2022-01-14T11:21:08Z", "salary": {"currency": null, "max": null, "min": null, "period": "monthly", "term": null}, "salary_visible": false, "title_keywords": ["senior quality control technician"], "responsibilities": ["maintenance", "sample preparation", "quality", "developing", "testing", "develop", "purchase", "quality control"], "requirements": {"degrees": ["degree", "bachelor"], "majors": ["science", "biology", "chemistry"], "languages": [], "language_level": [], "hard_skills": ["maintenance", "rapid"], "soft_skills": ["self-motivated", "interested in", "willing to learn", "detail-oriented", "multi-tasking", "team player", "stable"], "languages_combined": []}, "experience_required": {"duration": [], "field": ["testing"]}}, {"job_id": "100003009042066", "location_code": "hk", "company": "", "job_title": "Quality Technologist / Senior Quality Technologist", "description": "We are an European sourcing office and are looking for motivated and talented candidates to join our Quality team.\n\nYour role:\n\nUndertake day to day technical duties at SKU level, providing technical advice to merchandisers to ensure products comply with the rules that apply in UK and\u00a0 throughout the EU\nLiaise with suppliers and testing labs to ensure all relevant products are tested appropriately and keep abreast of latest rules and regulations.\nEvaluate samples and recommend improvements to ensure products are safe and \u2018Fit for Purpose\u2019\nFully accountable for the quality, safety, integrity and legal compliance of products within assigned area of responsibility.\nWork closely with other team members and other technologists understanding of the product category, ensuring all quality safety legal and brand integrity requirements are met\nEnsure all product specifications (with test certification/material safety data sheets as appropriate) and supplier documentation are accurately maintenance and regularly reviewed for validity\nMonitor and measure supplier compliance through effective analysis of audits/visits, KPI\u2019s and complaints\nManage timeline effectively and make sure all lines hit launch date for technical and quality criteria, as per critical path\nUndertake in-process and pre-shipment inspections and incoming goods QC checks\nCarry out any other duties as requested by your line manager.\u00a0\n\nYour Profile:\n\nMin 2 years technical experience, preferably gained in sourcing / buying office.\nSelf-motivated individual with high level of integrity\nExcellent attention to detail with good planning and organizational\u00a0skills\nExperience in a broad range of Hardline consumer products. With recent knowledge of these product standards, legal requirements and manufacturing Technology and the ability to apply this in a commercial setting.\nDetailed knowledge of product labelling & testing requirements for the UK Independent and self-motivated\nQuality Systems and Social Compliance auditing experience.\nThe ability to work in a small team\nExcellent spoken and written English & Mandarin is essential.\n\nWe offer 5-day work and attractive compensation package.\u00a0 Please send us your application, together with current and expected salary.\n\u00a0\nAll information provided by applicants will be treated in strict confidence and used only for processing application.\u00a0 If you need further information, please contact us at 97648703.\u00a0", "employment_types": ["Full Time", "Permanent"], "selling_points": ["sourcing office, close to MTR", "QA for hardgoods", "5 days work week, flexi hours"], "locations": ["Kwun Tong"], "categories": ["Manufacturing", "Production Planning / Control", "Merchandising & Purchasing", "Procurement / Purchasing / Sourcing", "Quality Assurance, Control & Testing / ISO"], "post_time": "2022-01-12T06:02:56Z", "salary": {"currency": null, "max": null, "min": null, "period": "monthly", "term": null}, "salary_visible": false, "title_keywords": [], "responsibilities": ["regulations", "any other duties", "maintenance", "data", "technical advice", "compliance", "quality", "monitor", "analysis", "testing", "evaluate", "audits", "systems", "specifications", "documentation", "auditing", "liaise with suppliers", "planning"], "requirements": {"degrees": [], "majors": [], "languages": ["english", "mandarin"], "language_level": ["excellent"], "hard_skills": ["small", "maintenance", "analysis", "make", "safe", "documentation"], "soft_skills": ["organizational skills", "self-motivated", "independent", "integrity", "accountable", "motivated", "attention to detail", "detailed"], "languages_combined": [{"language": "english", "language_level": ["excellent"]}, {"language": "mandarin", "language_level": ["excellent"]}]}, "experience_required": {"duration": ["min 2 years"], "field": ["compliance"]}}, {"job_id": "100003009049232", "location_code": "hk", "company": "Arrow Asia Pac Ltd", "job_title": "Component Quality Specialist", "description": "What You'll Be Doing\n\nProvide detailed product inspection (level II) as mandated by corporate procedures and checklists to validate/verify product authenticity, markings, condition and offer documented, factual information for Sales and/or Commodity Management to determine disposition when applicable.\nInvestigate and inspect discrepant product from Purchase Orders, Sales orders, and Customer Returns (product ranges from Semiconductor, capacitors and passive type parts)\nInspect product under magnification to validate product markings, condition, and authenticity.\nResearch various websites or paid subscriptions to databases to find and read product datasheets.\nConfirm RoHS/Lead Free compliance via part markings, date codes, etc.\nTake photos to send with documented information as evidence and store, when applicable\nTake physical measurements of product to ensure authenticity, when applicable\nPerform marking permanency test as required.\nConfirms product Moisture Sensitivity level (MSL) when applicable.\nProvides technical guidance and testing for Corrective & Preventative Action\nAbility to travel on behalf of Converge as required and adheres to the specified travel policy.\nPerforms miscellaneous duties as assigned.\n\nWhat We Are Looking For\n\nHigher Diploma/ Degree holder in logistics, manufacturing or quality related disciplines\n2 years or above quality inspection experience, preferably from semiconductor industry\nFamiliar with ISO9001 and 14001\nGood command of spoken and written English and Chinese\nSelf-motivated, independent, good communication and able to work under pressure\nProficient in MS Office\n\nWhat\u2019s In It For You\nAt Arrow, we recognize that financial rewards and great benefits are important aspects of an ideal job. That\u2019s why we offer competitive financial compensation, including various compensation plans, and a solid benefits package.\n\nDouble Pay\nPerformance Bonus\nMedical & Dental\nLife Insurance\nMPF with additional employer contributions\nPaid Time Off\nFree Shuttle to HKSTP Office\n5-Day Work Week\nGrowth Opportunities\nAnd More!", "employment_types": ["Full Time", "Permanent"], "selling_points": ["Fortune 102 US Company", "Quality Inspection Specialist, ISO9001", "Steady Career Path and Attractive Salary Package"], "locations": ["Chai Wan"], "categories": ["Transportation & Logistics", "Inventory / Warehousing", "Supply Chain", "Manufacturing", "Quality Assurance, Control & Testing / ISO"], "post_time": "2022-01-14T08:17:52Z", "salary": {"currency": null, "max": null, "min": null, "period": "monthly", "term": null}, "salary_visible": false, "title_keywords": ["component quality specialist"], "responsibilities": ["guidance", "management", "compliance", "procedures", "quality", "inspection", "testing", "communication", "purchase", "logistics", "databases", "work under pressure"], "requirements": {"degrees": ["diploma", "degree holder"], "majors": ["related disciplines", "manufacturing"], "languages": ["english", "chinese"], "language_level": ["good command"], "hard_skills": ["codes", "databases", "msl", "converge", "ms office"], "soft_skills": ["self-motivated", "independent", "work under pressure", "sensitivity", "communication", "detailed"], "languages_combined": [{"language": "english", "language_level": ["good command"]}, {"language": "chinese", "language_level": ["good command"]}]}, "experience_required": {"duration": ["2 years"], "field": []}}, {"job_id": "100003009048762", "location_code": "hk", "company": "SD Electronic Materials (Hong Kong) Limited", "job_title": "Assistant QA Engineer", "description": "Responsibilities :\n\nHandle and feedback customer Ad-hoc inquiry which related to the quality management system, restricted chemical substance list, customer audit, and third-party testing\nAssist QA Manager to establish and implement ISO 9000 quality management system and document control system\nIssue the abnormal action ticket, MRB reports, and Process Deviation reports\nInitiate Corrective and Preventive Action Request (CAR) and analyze the defects when major defects/deviations are encountered in the course of production\nMaintain laboratory analyzing equipment in good condition\nHandle other projects and ad hoc assignments\nRequirements :\n\nFresh graduates are welcome\nMore experience will be considered as QA Engineer\nDegree holder/Diploma in Quality Management, Industrial engineering or chemistry or related disciplines\nGood command of written and spoken English, Cantonese, and Putonghua", "employment_types": ["Full Time"], "selling_points": ["5-day Work Week", "Competitive Remuneration and Benefits Package", "Year-end Bonus and Discretionary Performance Bonus"], "locations": ["Tai Po Area"], "categories": ["Manufacturing", "Quality Assurance, Control & Testing / ISO"], "post_time": "2022-01-14T07:14:15Z", "salary": {"currency": null, "max": null, "min": null, "period": "monthly", "term": null}, "salary_visible": false, "title_keywords": ["engineer", "assistant"], "responsibilities": ["ad-hoc", "management", "control", "quality", "audit", "testing", "maintain", "reports", "ad hoc assignments"], "requirements": {"degrees": ["diploma", "degree holder"], "majors": ["related disciplines", "chemistry", "engineering", "quality management"], "languages": ["cantonese", "putonghua", "english"], "language_level": ["good command"], "hard_skills": [], "soft_skills": [], "languages_combined": [{"language": "cantonese", "language_level": ["good command"]}, {"language": "putonghua", "language_level": ["good command"]}, {"language": "english", "language_level": ["good command"]}]}, "experience_required": {"duration": [], "field": ["qa"]}}, {"job_id": "100003009050104", "location_code": "hk", "company": "ALDI Services Asia Limited", "job_title": "Quality Consultant / Specialist (Hardgoods) (m/f)", "description": "We invite now high caliber talent to apply for Quality\u00a0Consultant / Quality Specialist (m/f)\u00a0to join our rapidly growing sourcing team in Hong Kong. This position supports product development and commercialization with a fast-paced successful team.\n\nResponsibilities.\n\nProduces regular communication updates for the Quality & Compliance Manager on developments within their categories and areas of responsibility\nResearches and investigates the relevant quality requirements in preparation for submissions, completing the submission process in line with company procedures\nFinalizes quality comparison documents and advises on the product quality of individual samples\nInstructs suppliers to conform to ALDI\u2019s Social Monitoring Programmes and implements relevant action plan\nManages and controls artwork creation and approval in line with department procedures\nFollows up after-sales service support for items within his/her commodity area including liaising with after sales service providers and national teams\n\n\n\u00a0Your Profile.\n\nAt least (Non-Degree) Tertiary education required.\nMinimum of 2 years' relevant working experience, preferably gained in sourcing/buying offices, working with consumer products.\nHands-on experience with QA topics and packaging follow-up highly advantageous.\nExcellent communication and interpersonal skills, team player.\nGood command of both verbal and written business English and fluency in Mandarin essential.\nAble to work independently, self-motivated, responsible, well-organized and willing to learn.\nAttention to detail and good organizing, coordination and planning skills.\nGeneral knowledge of MS office and Exchange essential.\nHigh level of maturity, integrity, trustworthiness.\n\nKey Benefits of working at ALDI.\n\nMarket leading remuneration package\n\nRewarding, attractive remuneration package.\nGroup Medical Insurance covering dental and maternity* benefits .\n\nWork-life balance\n\nFull time, permanent position, 5-day-work-week.\n20 days of paid Annual Leave.\n\nBeing part of a pleasant, successful, growing business\n\nALDI\u2019s business is expanding, same for the Hong Kong Office with lots of opportunities for growth and development.\nPleasant working atmosphere where proactive communication, teamwork and collaboration is highly valued.\n\nPeople Focused\n\nStructured, comprehensive orientation and on-the-job training.\nALDI empowers our people allowing staff ownership of their areas of responsibilities.\n\nTrust and Integrity\n\nWE DO WHAT WE SAY - \u00a0for us there is no grey area, we have robust business processes, procedures and strong governance in place.\nWe treat our staff members, customers, suppliers and service providers with trust and fairness as business partners.\n\n\u00a0* Maternity benefits only apply for female employees due to local Insurance policy\n\nHow to apply\u00a0\u00a0\n\nIf you are interested in applying for the job, we look forward to receiving your full application in English, including salary expectation and possible starting date. The application should be sent through JobsDB by clicking icon \u201cApply Now\u201d or addressed to ALDI HR Dept, 18/F, Millennium City 6, 392 Kwun Tong Road, Kwun Tong, Kowloon, Hong Kong.\n\nALDI is an Equal Opportunity employer. We are dedicated to create an equal opportunity throughout recruitment process and staff employment to build a diverse and inclusive workforce. We oppose all forms of unfair or unlawful discrimination in our selection process.\n\nAll personal data collected will be used for recruitment purposes only and be treated in strictest confidence and highest security level in accordance with Hong Kong Data (Privacy) Ordinance as well as ALDI internal Security Policy.\n\nNo part of this job content including but not limited to company information, logo and job description may be reproduced, presented, uploaded, transmitted, modified or distributed \u00a0in any form or by any means without prior permission of ALDI Services Asia Limited / ALDI Sourcing Asia Limited (\u201cthe Company\u201d). The Company reserves the right to take legal action on any unauthorized reproduction, presentation, upload, transmission, modification or distribution. Only applications submitted directly to the Company in response to this advertisement will be considered and any application received by the Company through unauthorized third party agents or via any other channels will not be considered.", "employment_types": ["Full Time", "Permanent"], "selling_points": ["Research & investigate quality requirement", "Finalize quality comparison documents", "Advise on the product quality of individual sample"], "locations": ["Kwun Tong"], "categories": ["Sciences, Lab, R&D", "Laboratory", "Manufacturing", "Quality Assurance, Control & Testing / ISO"], "post_time": "2022-01-14T09:47:15Z", "salary": {"currency": null, "max": null, "min": null, "period": "monthly", "term": null}, "salary_visible": false, "title_keywords": ["specialist", "consultant"], "responsibilities": ["compliance", "quality", "procedures", "monitoring", "liaising with", "communication", "teams", "commercialization", "after-sales service", "plan", "coordination", "planning"], "requirements": {"degrees": ["degree"], "majors": [], "languages": ["english", "mandarin"], "language_level": ["fluency", "good command"], "hard_skills": ["exchange", "submission process", "ms office"], "soft_skills": ["planning skills", "work independently", "self-motivated", "responsible", "well-organized", "willing to learn", "integrity", "communication", "hands-on", "communication and interpersonal skills", "attention to detail", "coordination", "team player"], "languages_combined": [{"language": "english", "language_level": ["fluency", "good command"]}, {"language": "mandarin", "language_level": ["good command"]}]}, "experience_required": {"duration": ["minimum of 2 years"], "field": ["buying offices", "relevant working experience", "qa"]}}, {"job_id": "100003009050110", "location_code": "hk", "company": "A.S. Watson Industries", "job_title": "QC Technician", "description": "Job Duties:\n\nMonitor production process and conduct hourly inspection for finished products\nConduct test and inspection for raw materials and imported products\nPerform physiochemical test\nSupport new product evaluation process\nHandle ad hoc projects assigned by Supervisor\n\nJob Requirements:\n\nIVE / Diploma holder in Science or related discipline\nMinimum\u00a01 year related experience in food industry or commercial laboratory\nKnowledge of HACCP / ISO22000 / Microbiological test are preferred\nEnergetic, well-organized, able to work independently and capable of working under pressure\nGood communication, presentation and interpersonal skill\nGood command of written and spoken English and Chinese\nPC Knowledge in MS Excel, Word & PowerPoint and Chinese Processing\nRequired to work on a roster basis including overnight\nFresh graduated / less experience will be considered as Assistant QC Technician\n\nWe offer competitive salary\u00a0discretionary performance bonus, medical and retirement benefits, free company coach services and excellent career prospects. Please send your resume together with salary expectation via APPLY NOW.\n\nFor more information, please visit our website at www.aswatson.com\u00a0\u00a0\n\nWe are an equal opportunity employer. The information provided will be treated in strict confidence and only be used for consideration of application for similar posts within the A.S. Watson Group of Companies.\n\nApplicants not hearing from us within 6 weeks from the date of advertisement may consider their application unsuccessful.\u00a0 All personal data of unsuccessful applicants will be destroyed within 12 months.\n\nAll information collected is for recruitment purpose only.", "employment_types": ["Full Time", "Permanent"], "selling_points": ["Free Shuttle Bus", "Discretionary bonus, Competitive pay", "QC for Water Production Line"], "locations": ["Tai Po Area"], "categories": ["Sciences, Lab, R&D", "Food Science", "Manufacturing", "Quality Assurance, Control & Testing / ISO", "Others"], "post_time": "2022-01-14T09:47:40Z", "salary": {"currency": null, "max": null, "min": null, "period": "monthly", "term": null}, "salary_visible": false, "title_keywords": ["qc technician"], "responsibilities": ["production process", "monitor", "evaluation process", "inspection", "ad hoc projects"], "requirements": {"degrees": ["diploma holder"], "majors": ["science"], "languages": ["english", "chinese"], "language_level": ["good command"], "hard_skills": ["word", "powerpoint", "ms excel", "pc knowledge", "processing"], "soft_skills": ["work independently", "confidence", "under pressure", "capable", "well-organized", "interpersonal skill", "communication", "energetic", "presentation"], "languages_combined": [{"language": "english", "language_level": ["good command"]}, {"language": "chinese", "language_level": ["good command"]}]}, "experience_required": {"duration": ["minimum 1 year"], "field": ["related", "food industry", "commercial laboratory"]}}, {"job_id": "100003009050106", "location_code": "hk", "company": "A.S. Watson Industries", "job_title": "\u53e3\u7f69\u54c1\u8cea\u76e3\u63a7\u54e1", "description": "\u5de5\u4f5c\u5167\u5bb9:\n\n\u7d00\u9304\u548c\u7ba1\u7406\u8ca8\u54c1\u6578\u91cf, \u78ba\u4fdd\u7522\u54c1\u7b26\u5408\u5b89\u5168\u8981\u6c42\n\u63a1\u96c6\u6a23\u672c\u548c\u6aa2\u6e2c\u53e3\u7f69\n\u8ca0\u8cac\u65e5\u5e38\u751f\u7522\u7dda\u4e0a\u534a\u6210\u54c1\u6216\u6210\u54c1\u4e4b\u6aa2\u67e5\u53ca\u70ba\u534a\u6210\u54c1\u5305\u88dd\u888b\u5c01\u53e3\n\u8a18\u9304\u6709\u95dc\u534a\u6210\u54c1\u6216\u6210\u54c1\u4e4b\u6aa2\u67e5\u5831\u544a\n\n\u5165\u8077\u8981\u6c42:\n\n\u6587\u6191\u7a0b\u5ea6\u6216\u4ee5\u4e0a\n\u6700\u5c11\u4e00\u5e74\u76f8\u95dc\u7d93\u9a57\n\u6709\u8cac\u4efb\u611f\u3001\u7a4d\u6975\u3001\u4e3b\u52d5\u3001\u80fd\u7368\u7acb\u8655\u7406\u5de5\u4f5c\n\u826f\u597d\u95b1\u8b80\u53ca\u66f8\u5beb\u4e2d\u6587\u53ca\u82f1\u6587\n\u61c2\u6587\u66f8\u8655\u7406\uff0c\u5982MS Excel\u3001Word\u53caPowerpoint\n\u9808\u8f2a\u73ed\u5de5\u4f5c\n\u7562\u696d\u751f\u6216\u8f03\u5c11\u7d93\u9a57\u8005\u6216\u88ab\u8003\u616e\u4f5c\u52a9\u7406\u53e3\u7f69\u54c1\u8cea\u76e3\u63a7\u54e1\n\n\u54e1\u5de5\u798f\u5229\u5305\u62ec:\n\n\u914c\u60c5\u6027\u82b1\u7d05\n\u52a0\u73ed\u6d25\u8cbc\n\u81b3\u98df\u6d25\u8cbc\n\u514d\u8cbb\u5ee0\u8eca\u63a5\u9001\n12\u5929\u6709\u85aa\u5e74\u5047\n\u91ab\u7642\u4fdd\u96aa(\u5305\u62ec\u5bb6\u5c6c)\n\u751f\u65e5/\u751f\u80b2\u79ae\u5238\n\u5a5a\u5047\u3001\u6069\u6064\u5047\n\u826f\u597d\u8077\u696d\u767c\u5c55\n\u54e1\u5de5\u6d3b\u52d5\n\u5728\u8077\u57f9\u8a13\u3001\u9032\u4fee\u8cc7\u52a9\n\u54e1\u5de5\u53ca\u5bb6\u5c6c\u8cfc\u7269\u512a\u60e0\n\n\u5de5\u4f5c\u5730\u9ede\uff1a\u5927\u57d4\u5de5\u696d\u90a8\n\n\u6709\u610f\u8005\u8acb\u81f4\u96fb\u62db\u8058\u7d44\u96fb\u8a71: 2660 1880\u6216\u6309 APPLY NOW \u7533\u8acb\u8077\u4f4d\u3002\n\n\u6240\u6709\u6c42\u8077\u8005\u4e4b\u8cc7\u6599\u53ea\u4f5c\u62db\u8058\u7528\u9014\u4e26\u7d55\u5c0d\u4fdd\u5bc6, \u82e5\u6c42\u8077\u8005\u65bc6\u661f\u671f\u5167\u4e26\u672a\u7372\u672c\u516c\u53f8\u63a5\u898b, \u672c\u516c\u53f8\u6703\u5c07\u5176\u8cc7\u659912\u500b\u6708\u5167\u6bc0\u6ec5\u3002", "employment_types": ["Full Time", "Permanent"], "selling_points": ["\u514d\u8cbb\u5ee0\u8eca\u63a5\u9001\u3001\u914c\u60c5\u6027\u82b1\u7d05", "\u63a1\u96c6\u6a23\u672c\u548c\u6aa2\u6e2c\u53e3\u7f69", "\u6587\u6191\u7a0b\u5ea6\u6216\u4ee5\u4e0a, \u7121\u9808\u7d93\u9a57"], "locations": ["Tai Po Area"], "categories": ["Sciences, Lab, R&D", "Laboratory", "Manufacturing", "Quality Assurance, Control & Testing / ISO", "Others", "Student / Fresh Graduate / No Experience"], "post_time": "2022-01-14T09:47:26Z", "salary": {"currency": null, "max": null, "min": null, "period": "monthly", "term": null}, "salary_visible": false, "title_keywords": ["\u53e3\u7f69\u54c1\u8cea\u76e3\u63a7\u54e1"], "responsibilities": [], "requirements": {"degrees": [], "majors": [], "languages": [], "language_level": [], "hard_skills": [], "soft_skills": [], "languages_combined": []}, "experience_required": {"duration": [], "field": []}}, {"job_id": "100003009049480", "location_code": "hk", "company": "John Lewis Hong Kong Limited", "job_title": "Product Development Technologist, Fashion (6-months contract) (contract to Perm)", "description": "As a Product Development Technologist, you are accountable for delivering John Lewis & Waitrose own label product to the agreed standard for safety, legality, quality, product development, sustainability and provenance aspects of the product life cycle.\u00a0\n\nThis role is potential to change to permanent role.\u00a0\u00a0\n\nMain role responsibilities\n\nSupplier and Factory Capability\n\nSharing results & working towards continuous improvement of suppliers performance on the sample rejection locally as well as with UK office\nAssess and screen new factory to ensure that they can\u00a0meet John Lewis and Waitrose brand standards\nManage a portfolio of factories to ensure the delivery of consistent technical & product quality and drive continuous improvement with the supply base\nQuality Assurance\n\nPerform garment fitting\u00a0\u00a0\nWhen required, screen initial product briefs received from the UK and check for appropriate technical information\nWhen required, pre-screen proto/offer samples, ensuring JL and Waitrose requirements are met before sending them to the UK teams\nResponsible for following up all red seal approvals in the UK,\nAct as a contact point between the UK team and suppliers for all quality/technical related topics\nApprove gold seal samples for mass production\nWorking closely with the UK Product Development Technologists\u00a0\nSkills and Experience\n\nEssential\n\nBachelor\u2019s degree in an Engineering / Fashion & Textile related field, or equivalent professional industrial, technical experience\n3-5 working experience in quality assurance (Less experience will also be considered)\nStrong communication and interpersonal skills.\nDesirable\n\nManagement of critical paths\nExperience of Branded and Own-brand products\nExperience in total product life cycle\nWe support agile working practices across the John Lewis Partnership. If you are looking for flexible working options please discuss this at your interview, as each role will have a differing level of flexibility.\n\nFor more details of how our Partners currently work flexibly\u00a0click here.\n\nInterested parties please click the \"APPLY\" button to submit your application with full resume including current and expected salary.\u00a0", "employment_types": ["Full Time", "Temporary", "Contract"], "selling_points": ["3-5 years working experience in QA", "UK sourcing office", "Potential to change to permanent role"], "locations": ["Kwun Tong"], "categories": ["Engineering", "Manufacturing & Production", "Others", "Manufacturing", "Quality Assurance, Control & Testing / ISO"], "post_time": "2022-01-14T08:44:20Z", "salary": {"currency": null, "max": null, "min": null, "period": "monthly", "term": null}, "salary_visible": false, "title_keywords": ["product development"], "responsibilities": ["management", "teams", "quality", "communication", "contact"], "requirements": {"degrees": ["degree", "bachelor"], "majors": ["engineering"], "languages": [], "language_level": [], "hard_skills": ["red", "agile"], "soft_skills": ["flexible", "agile", "responsible", "accountable", "communication and interpersonal skills"], "languages_combined": []}, "experience_required": {"duration": [], "field": ["brand", "engineering", "related", "textile", "quality assurance"]}}, {"job_id": "100003009050399", "location_code": "hk", "company": "Qima Limited", "job_title": "Laboratory Calibration Engineer (Fresh Grad is welcome)", "description": "Objective\n\nEnsure the equipment achieves the accuracy required at all time, support and perform calibration / verification for a wide range of Chemical, Physical and Optical laboratory equipment, as well as equipment purchasing, intermediate check, repair, and maintenance.\n\nYour Responsibilities\n\nSchedule and perform equipment calibration, verification, intermediate check, repair and maintenance, by following the calibration standards and requirement;\nPrepare and review calibration procedures, measurement uncertainty and internal calibration reports to fulfill ISO/IEC 17025 requirements;\nCo-ordinate with internal laboratory and calibration laboratory for internal/external calibration;\nManage the status and stock of laboratory\u2019s equipment. Co-ordinate with supplier for sourcing and purchasing new equipment;\nMaintain equipment record;\nSimple office facilities maintenance;\nHandle other equipment related tasks for quality assurance issues, such as internal/external auditing, document control, quality improvement projects, etc.\nMaintain document control system;\nHandle internal audit administration supporting tasks\n\nThe Skills We\u2019re Looking For\n\nHigher diploma / associate degree / degree holder of physics, mathematics or relevant engineering discipline;\nBasic understanding of ISO/IEC 17025 quality system document;\nGood communication skills and interpersonal skills;\nGood trouble shooting skills;\nExperiences of working in testing laboratory or toy industry is preferred;\nGood command of written and spoken English and Chinese;\nSelf-motivated and detail-minded;\nAnalytical mind and logical thinking;\nStrong technical knowledge;\nFresh graduate is also welcome.\nOther Benefits:\n\n5-day work, public holidays\nPerformance bonus and year-end bonus\nMedical and dental insurance\nOT allowance\nAnnual Leave, Compensation Leave, Compassionate Leave", "employment_types": ["Full Time", "Permanent"], "selling_points": ["5-day work", "Year end bonus and performance bonus", "Young and good work environment"], "locations": ["Kwun Tong"], "categories": ["Engineering", "Mechanical", "Sciences, Lab, R&D", "Laboratory", "Manufacturing", "Quality Assurance, Control & Testing / ISO"], "post_time": "2022-01-14T10:18:05Z", "salary": {"currency": null, "max": null, "min": null, "period": "monthly", "term": null}, "salary_visible": false, "title_keywords": ["engineer"], "responsibilities": ["control", "maintenance", "internal audit", "co-ordinate with", "review", "procedures", "measurement", "quality", "testing", "communication", "repair", "maintain", "reports", "schedule", "auditing", "administration"], "requirements": {"degrees": ["associate degree", "diploma", "fresh graduate", "degree holder"], "majors": ["mathematics", "engineering", "physics"], "languages": ["english", "chinese"], "language_level": ["good command"], "hard_skills": ["simple", "basic", "maintenance"], "soft_skills": ["detail-minded", "communication skills", "self-motivated", "analytical mind", "interpersonal skills"], "languages_combined": [{"language": "english", "language_level": ["good command"]}, {"language": "chinese", "language_level": ["good command"]}]}, "experience_required": {"duration": [], "field": ["laboratory", "testing"]}}, {"job_id": "100003009046875", "location_code": "hk", "company": "SYNCO (H.K.) Ltd", "job_title": "QA Assistant / Assistant QA Officer", "description": "Responsibilities:\n\nTo support in developing, implementing and maintaining the documentation and quality assurance system of the company, including the standard operating procedures (SOPs);\nTo ensure the adequate records are maintained for controlling and monitoring conformity to specified GMP and statutory requirements;\nTo support the routine QA Department functions, including GMP training, self-inspection, line clearance;\nKnowledge in Quality Management System (e.g change control, risk assessment and CAPA) is an advantage.\n\n\u00a0Requirements:\n\nHigher Diploma or University graduate in Pharmaceutical Studies / Food science/science related discipline;\nAttention to details, hard-working and being able to work under pressure;\nStrong communication skill, good command of English and Chinese;\n\nWe offer attractive remuneration package including medical scheme, discretionary year-end bonus etc. Interested parties please send\u00a0full resume\u00a0with\u00a0salary expectation\u00a0and\u00a0availability\u00a0by click \"Apply Now\". Only shortlisted candidates will be interviewed.\n\nSynco (H.K.) Ltd\u00a0is an Equal Opportunities Employer. Personal data provided by job applicants will be used strictly in accordance with our personal data policy and for recruitment purposes only. We aim to respond to successful applicants within 8 weeks and related information will be kept in our file for up to 12 months for other suitable vacancies in our organization and thereafter destroyed.\u00a0", "employment_types": ["Full Time", "Permanent"], "selling_points": [], "locations": ["Tai Po Area"], "categories": ["Hospitality / F & B", "Others", "Medical Services", "Pharmaceutical", "Manufacturing", "Quality Assurance, Control & Testing / ISO"], "post_time": "2022-01-14T01:33:41Z", "salary": {"currency": null, "max": null, "min": null, "period": null, "term": null}, "salary_visible": false, "title_keywords": ["qa assistant", "assistant qa officer"], "responsibilities": ["management", "control", "maintaining", "monitoring", "quality", "developing", "procedures", "inspection", "statutory requirements", "sops", "documentation"], "requirements": {"degrees": ["university graduate", "diploma"], "majors": ["science", "food science"], "languages": ["english", "chinese"], "language_level": ["good command"], "hard_skills": [], "soft_skills": ["communication skill", "hard-working", "attention to details", "work under pressure"], "languages_combined": [{"language": "english", "language_level": ["good command"]}, {"language": "chinese", "language_level": ["good command"]}]}, "experience_required": {"duration": [], "field": []}}, {"job_id": "100003009043446", "location_code": "hk", "company": "The Cookware Company Limited", "job_title": "QA Manager, Hardgoods", "description": "The Cookware Company is a global company with a high expertise in innovative cookware. Our organization is vertically integrated, allowing us to manage both the production and distribution of our products. We have sales offices in Europe, the United States and Asia as well as state-of-the-art production facilities in Korea, China and Europe. We have high quality standards (e.g. ISO-certificates) and work hard to reduce our environmental impact.\nThe Cookware Company has always been a pioneer in healthy ceramic non-stick cookware. Over the years we have extended our scope in order to offer smart cookware solutions for everyone. Innovation, flexibility, creativity and social responsibility are our main focus. However, our most important asset are our people. They\u2019re the heart of our company.\nYou are responsible to make sure that our overall Quality plan is set up, managed and followed internally in the company and by all our external partners. The Quality Manager is responsible for managing all aspects of the Safety and Quality of products, to ensure products are available on time at the right quality level.\nMain Roles & Responsibilities:\n\nPrimary Responsibilities:\n\nPart of the project team to ensure Quality points are integrated in all new range development.\nImplement Quality Management Plans for all new ranges, manage supplier quality audits, product quality requirement and shipment inspections.\u00a0\nConduct on-site Quality Audits of all potential new suppliers and factories.\nManage the Quality relationship with suppliers, ensure all suppliers understand our requirements for quality management and product safety and product quality.\nMaintain up-to-date records for all Quality activity, including factory audit reports, test report and inspection reports, and share with other areas of the business as needed.\nCoordinate and supply all needed documents customers request in terms of Quality requirement.\nIdentify safety and quality requirements for new product ranges of new retail markets, record this information in Generic Global Protocols, and share with all relevant parties.\nConsult the organization on updated quality standards to ensure product compliance.\nReview all third service providers\u2019 reports and communicate to service provider(s) for any query (on-line, life test, lab testing, inspections and audits).\nProvide quality/Technical support to all needed departments; investigate product issues and work with suppliers to identify root causes and to take appropriate actions to prevent recurrence.\nManaging the performance of external service providers based on cost, service quality and value of technical support provided.\nManage the cost of Quality Management effectively, ensuring that all paid services deliver the maximum value for money in terms of Quality Management.\u00a0 Keep records of all Quality Management costs for periodic analysis.\nBuilding a strong relationship with our external service providers, licensor technical team and internal global clients to ensure timely and accurate technical support and communication of requirements.\nImprove the QA process, quality concept and quality control methods training guidance,\nLook for continuous improvements on the efficiency in the department and propose these to the organization.\nAnalyzes and manage Consumer Service Claims to identify root cause and identify corrective/preventive actions in product design, manufacturing and processes.\nOther Responsibilities\nReview brand-partner and client quality requirements to ensure they are understood by all parties and incorporated into Quality Management plans as required.\u00a0 \u00a0\nRequirements:\nBachelor degree with a minimum of 8 year experience in Quality Assurance or equivalent\nExtensive experience in Kitchenware, Cookware, household item\nGood communication and interpersonal skills, open-minded and willing to face challenges.\nAnalytical and problem-solving ability\nPersistence and the ability to influence others.\nSkills in numerical and statistical analysis\nAttention to detail.\nGood in English, Cantonese, and Mandarin, both spoken and written.", "employment_types": ["Full Time", "Permanent"], "selling_points": ["Fast Growing MNC", "Young & Energetic Team", "Promising Career Opportunity"], "locations": ["Kowloon Bay"], "categories": ["Manufacturing", "Product Development / Management", "Merchandising & Purchasing", "Others", "Quality Assurance, Control & Testing / ISO"], "post_time": "2022-01-12T11:59:56Z", "salary": {"currency": null, "max": null, "min": null, "period": "monthly", "term": null}, "salary_visible": false, "title_keywords": ["manager"], "responsibilities": ["inspection reports", "quality", "audit", "communication", "maintain", "plans", "costs", "compliance", "testing", "reports", "report", "continuous improvements", "guidance", "management", "cost", "review", "product design", "audits", "technical support", "analysis", "coordinate", "quality control"], "requirements": {"degrees": ["degree", "bachelor"], "majors": [], "languages": ["cantonese", "english", "mandarin"], "language_level": ["good"], "hard_skills": ["problem-solving", "statistical analysis"], "soft_skills": ["open-minded", "problem-solving", "communication and interpersonal skills", "attention to detail", "extensive"], "languages_combined": [{"language": "cantonese", "language_level": ["good"]}, {"language": "english", "language_level": ["good"]}, {"language": "mandarin", "language_level": ["good"]}]}, "experience_required": {"duration": ["minimum of 8 year"], "field": ["quality assurance"]}}, {"job_id": "100003009039221", "location_code": "hk", "company": "Ampd Energy Limited", "job_title": "Director of Quality", "description": "Summary of the Position\n\nAmpd Energy is seeking a talented and passionate individual to plan, direct, coordinate, and implement a world class Quality Management System and develop a culture of Continuous Improvement at the company. You will be working closely with leaders and teams in R&D, Field Engineering, and Supply Chain to assess the current state and develop plans for improvement and then facilitate the implementation.\n\nWe are specifically looking for individuals who are organised, detail-oriented, dependable, and excited about Quality and process management. Ideally you have extensive experience in Quality Management and process management and a strong background in Lean-Six Sigma principles, Quality Tools, and best practices. This is a leadership role and so you must have specific leadership experience and outstanding leadership qualities. You will be expected to work well independently and to communicate clearly and effectively in English and preferably also Chinese. The company\u2019s quality management system shall span the entire range of the value chain from suppliers to end customers.\n\nKnowledge, Qualifications and Skills\n\nHigher diploma or bachelor\u2019s degree preferably in Engineering or related field. Master\u2019s degree preferred.\nMinimum 5 years of Quality Management experience, with progressive levels of responsibility.\nGreat planning skills, and excellent project and time management track record.\nExperience with Lean & Six Sigma principles. Experience with Quality Control in a manufacturing environment.\nKnowledge of and practice with the basic Quality Tools, 8D problem solving, SPC, ANOVA, GR&R, PPAP, Cpk analysis, and other common measurement and analytical tools. Experience teaching these concepts is preferred as well.\nGreat documentation, presentation, and report writing skills.\nBackground in industrial and/or electrical workplace safety is a huge plus.\nProficient in MS Office Applications (Word, Excel, Powerpoint).\nSelf-motivated, detailed oriented, organized.\nGood command of spoken and written English, and ideally Chinese.\n\nSpecific duties include:\n\nManage end to end Quality for the company and be responsible for reporting Quality Data, creating and maintaining the company\u2019s Quality Management Plan, and reporting status on the company\u2019s Quality Management efforts.\nEnsure internal and external documentation meets requirements for suppliers, customers, and other stakeholders.\nEstablish internal and external quality auditing procedures and report.\nEstablish and own Supplier Quality Management processes, and Customer Quality Management processes, including fulfilment chains in Europe, North America, and Asia-Pacific.\nContinue to keep up to date with latest developments in all relevant standards.\nProvide periodic training for the internal team and suppliers on Quality Management.\nParticipate in new product development to ensure Quality issues are addressed throughout the development process and all stakeholders understand requirements from the beginning.\n\nBenefits\n\nCompetitive cash package\nFull medical, dental & travel insurance coverage\nUber travel policy (for business travel & travel after 8pm)\n\nHow to apply\n\nPlease submit your application via https://www.linkedin.com/jobs/view/2868247652.\n\nAll information provided will be treated in strict confidence and used solely for recruitment purposes. We regret that we are only able to notify short-listed candidates.\n\nAmpd Energy is an equal opportunity employer. All candidates will be assessed on merit without regard to race, gender, sexual orientation, religion, nationality, marital status, political affiliation or any other factor protected by law.", "employment_types": ["Full Time", "Permanent"], "selling_points": ["Higher diploma or bachelor\u2019s degree", "5 years of Quality Management experience", "Self-motivated, detailed oriented, organized."], "locations": ["Lai Chi Kok"], "categories": ["Transportation & Logistics", "Others", "Supply Chain", "Manufacturing", "Quality Assurance, Control & Testing / ISO"], "post_time": "2022-01-11T09:04:40Z", "salary": {"currency": null, "max": null, "min": null, "period": "monthly", "term": null}, "salary_visible": false, "title_keywords": ["director"], "responsibilities": ["data", "quality", "plan", "maintaining", "teams", "implementation", "measurement", "develop", "develop plans", "report", "reporting", "management", "procedures", "documentation", "analysis", "coordinate", "quality control", "auditing", "planning"], "requirements": {"degrees": ["diploma", "degree", "bachelor", "master"], "majors": ["engineering"], "languages": ["english", "chinese"], "language_level": ["good command"], "hard_skills": ["r&d", "excel", "lean", "plus", "basic", "analysis", "word", "writing skills", "powerpoint", "problem solving", "six sigma", "documentation", "ms office"], "soft_skills": ["passionate", "planning skills", "self-motivated", "independently", "detailed oriented", "organized", "responsible", "writing skills", "detail-oriented", "problem solving", "leadership", "organised", "progressive", "time management", "extensive", "presentation"], "languages_combined": [{"language": "english", "language_level": ["good command"]}, {"language": "chinese", "language_level": ["good command"]}]}, "experience_required": {"duration": ["minimum 5 years"], "field": ["management", "manufacturing", "quality control", "quality management", "teaching"]}}, {"job_id": "100003009043439", "location_code": "hk", "company": "The Cookware Company Limited", "job_title": "QA Manager, SDA", "description": "The Cookware Company is a global company with a high expertise in innovative cookware. Our organization is vertically integrated, allowing us to manage both the production and distribution of our products. We have sales offices in Europe, the United States and Asia as well as state-of-the-art production facilities in Korea, China and Europe. We have high quality standards (e.g. ISO-certificates) and work hard to reduce our environmental impact.\nThe Cookware Company has always been a pioneer in healthy ceramic non-stick cookware. Over the years we have extended our scope in order to offer smart cookware solutions for everyone. Innovation, flexibility, creativity and social responsibility are our main focus. However, our most important asset are our people. They\u2019re the heart of our company.\nYou are responsible to make sure that our overall Quality plan is set up, managed and followed internally in the company and by all our external partners. The Quality Manager is responsible for managing all aspects of the Safety and Quality of products, to ensure products are available on time at the right quality level.\nMain Roles & Responsibilities:\n\nPrimary Responsibilities:\n\nPart of the project team to ensure Quality points are integrated in all new range development.\nImplement Quality Management Plans for all new ranges, manage supplier quality audits, product quality requirement and shipment inspections.\u00a0\nConduct on-site Quality Audits of all potential new suppliers and factories.\nManage the Quality relationship with suppliers, ensure all suppliers understand our requirements for quality management and product safety and product quality.\nMaintain up-to-date records for all Quality activity, including factory audit reports, test report and inspection reports, and share with other areas of the business as needed.\nCoordinate and supply all needed documents customers request in terms of Quality requirement.\nIdentify safety and quality requirements for new product ranges of new retail markets, record this information in Generic Global Protocols, and share with all relevant parties.\nConsult the organization on updated quality standards to ensure product compliance.\nReview all third service providers\u2019 reports and communicate to service provider(s) for any query (on-line, life test, lab testing, inspections and audits).\nProvide quality/Technical support to all needed departments; investigate product issues and work with suppliers to identify root causes and to take appropriate actions to prevent recurrence.\nManaging the performance of external service providers based on cost, service quality and value of technical support provided.\nManage the cost of Quality Management effectively, ensuring that all paid services deliver the maximum value for money in terms of Quality Management.\u00a0 Keep records of all Quality Management costs for periodic analysis.\nBuilding a strong relationship with our external service providers, licensor technical team and internal global clients to ensure timely and accurate technical support and communication of requirements.\nImprove the QA process, quality concept and quality control methods training guidance,\nLook for continuous improvements on the efficiency in the department and propose these to the organization.\nAnalyzes and manage Consumer Service Claims to identify root cause and identify corrective/preventive actions in product design, manufacturing and processes.\nOther Responsibilities\nReview brand-partner and client quality requirements to ensure they are understood by all parties and incorporated into Quality Management plans as required.\u00a0 \u00a0\nRequirements:\nBachelor degree with a minimum of 8 year experience in Quality Assurance or equivalent\nExtensive experience in Small Domestic Appliances (cooking, kitchen)\nGood communication and interpersonal skills, open-minded and willing to face challenges.\nAnalytical and problem-solving ability\nPersistence and the ability to influence others.\nSkills in numerical and statistical analysis\nAttention to detail.\nGood in English, Cantonese, and Mandarin, both spoken and written.", "employment_types": ["Full Time", "Permanent"], "selling_points": ["Fast Growing MNC", "Young & Energetic Team", "Promising Career Opportunity"], "locations": ["Kowloon Bay"], "categories": ["Manufacturing", "Product Development / Management", "Merchandising & Purchasing", "Home Appliances", "Quality Assurance, Control & Testing / ISO"], "post_time": "2022-01-12T11:52:18Z", "salary": {"currency": null, "max": null, "min": null, "period": "monthly", "term": null}, "salary_visible": false, "title_keywords": ["manager"], "responsibilities": ["inspection reports", "quality", "audit", "communication", "maintain", "plans", "costs", "compliance", "testing", "reports", "report", "continuous improvements", "guidance", "management", "cost", "review", "product design", "audits", "technical support", "analysis", "coordinate", "quality control"], "requirements": {"degrees": ["degree", "bachelor"], "majors": [], "languages": ["cantonese", "english", "mandarin"], "language_level": ["good"], "hard_skills": ["small", "problem-solving", "statistical analysis"], "soft_skills": ["open-minded", "problem-solving", "communication and interpersonal skills", "attention to detail", "extensive"], "languages_combined": [{"language": "cantonese", "language_level": ["good"]}, {"language": "english", "language_level": ["good"]}, {"language": "mandarin", "language_level": ["good"]}]}, "experience_required": {"duration": ["minimum of 8 year"], "field": ["quality assurance"]}}, {"job_id": "100003009045488", "location_code": "hk", "company": "DCH Logistics Co Ltd", "job_title": "Quality Assurance Assistant (Ref: LOG-QAA)", "description": "Job Responsibilities\n\nAssist in implementing and maintaining the documentation system and quality management system;\nAssist in 1st, 2nd and 3rd parties audit, qualification, validation of equipment and facility;\nAssist in handling customer complaints, conducting root cause analysis and following up corrective actions;\nProvide training to employees to raise their awareness on quality requirements from customers and company;\nRegular on site audit and checking\nAssist in other ad-hoc projects as assigned.\n\n\u00a0Job Requirements\n\nDiploma holder in Quality Assurance or Science related disciplines\nMinimum\u00a01 year\u2019s relevant experience, preferred in Logistics industry;\nKnowledge in ISO 9001 standards is a must;\nProfessional certification in quality management system will be an advantage;\nExcellent interpersonal and communication skills to be able to work well in a cross-functional team setting;\nDetail-minded, self-motivated and proactive;\nProficiency in MS Office applications and Chinese word processing;\nGood command of written and spoken English and Chinese;\nFresh graduates will also be considered if of high caliber\n\nWe offer competitive salary, discretionary bonus, medical insurance, life and personal accident insurance, annual leave and staff purchase discount to the successful candidate. Interested candidates please send your resume with salary expectation by clicking \"Apply Now\".\n\nWe are equal opportunities employer. Applicants who are not invited within 2 months may consider their application unsuccessful. All applicants may be considered for other suitable positions with DCH Group / CITIC Pacific Group and will be deleted from our files after 6 months from the date of application.\n\n.", "employment_types": ["Full Time", "Permanent"], "selling_points": [], "locations": ["Yuen Long"], "categories": ["Transportation & Logistics", "Inventory / Warehousing", "Manufacturing", "Quality Assurance, Control & Testing / ISO"], "post_time": "2022-01-13T07:56:45Z", "salary": {"currency": null, "max": null, "min": null, "period": "monthly", "term": null}, "salary_visible": false, "title_keywords": ["quality assurance assistant"], "responsibilities": ["provide training", "management", "maintaining", "customer complaints", "analysis", "quality", "audit", "checking", "documentation", "ad-hoc projects"], "requirements": {"degrees": ["diploma holder"], "majors": ["related disciplines", "science"], "languages": ["english", "chinese"], "language_level": ["proficiency", "good command"], "hard_skills": ["chinese word processing", "ms office"], "soft_skills": ["detail-minded", "communication skills", "self-motivated", "proactive", "interpersonal"], "languages_combined": [{"language": "english", "language_level": ["good command"]}, {"language": "chinese", "language_level": ["proficiency", "good command"]}]}, "experience_required": {"duration": ["minimum 1 year"], "field": ["logistics industry", "relevant experience"]}}, {"job_id": "100003009050536", "location_code": "hk", "company": "Celki Medical Company", "job_title": "Safety & Compliance Officer", "description": "Key Responsibilities:\n\nSafety & Security Compliance\nImplementation of the Group\u2019s/Company\u2019s industrial management system, quality management system, and safety & health policies and procedures\nMonitor regularly the staff compliance on the Safety & Security rules and carry out internal quality and safety check and audits\nDevelop and conduct training to staff and coach all staff to develop further awareness on health & safety work practices\nRisk and Accident Investigation and Prevention\nManage product recall and product registration according to regulatory and legal requirements\nMonitor and coordinate any accident investigation and proactively introduce preventive action\nQuality System & Audit Management\nConduct internal audit periodically and communication of audit findings to the relevant personnel for action\nEnsure the Company\u2019s quality system is properly implemented in accordance with ISO 9001:2015 and liaise with external parties on matters relating to the improvement the ISO system\nManage and improve ISO based Quality Management System documentation according to the group\u2019s guidelines and maintain proper quality records\nRequirements:\n\nDegree holder in Quality / Safety Management or related disciplines\n2 to 3 years solid experience in ISO Quality Management System; preferably with experience in healthcare industry\nSolid experience in handling medical device regulatory and product recall\nA certified internal auditor with experience in managing ISO internal audit\nGood planning, organization and project management skills\nStrong research, analytical, interpersonal and communication skills\nGood team player and able to work independently under tight deadlines\nFluent English and Chinese with strong computer skills\nImmediate available is highly preferred\nWe offer competitive remuneration and on-the-job coaching with a good career development to the right candidate.\u00a0Interested parties please send us a full resume stating current and expected salary and availability\u00a0for job application.\n\n\nPlease visit our website:\u00a0http://www.celki.com\u00a0for further information of our Company.\n\nData collected will be used for recruitment purpose only.", "employment_types": ["Full Time", "Permanent"], "selling_points": ["Responsible for overall Safety & Quality matters", "Certified internal auditor, manage ISO 9001:2015", "Exp. in medical device regulatory & product recall"], "locations": ["Cheung Sha Wan"], "categories": ["Medical Services", "Others", "Pharmaceutical", "Manufacturing", "Quality Assurance, Control & Testing / ISO"], "post_time": "2022-01-14T10:39:39Z", "salary": {"currency": null, "max": null, "min": null, "period": "monthly", "term": null}, "salary_visible": false, "title_keywords": ["compliance officer"], "responsibilities": ["internal audit", "external parties", "quality", "audit", "communication", "maintain", "liaise with", "system documentation", "compliance", "monitor", "implementation", "develop", "management", "procedures", "investigation", "audits", "guidelines", "policies", "coordinate"], "requirements": {"degrees": ["degree holder"], "majors": ["related disciplines"], "languages": ["english", "chinese"], "language_level": ["fluent"], "hard_skills": ["project management", "computer skills"], "soft_skills": ["communication skills", "good team player", "work independently", "project management skills", "interpersonal"], "languages_combined": [{"language": "english", "language_level": ["fluent"]}, {"language": "chinese", "language_level": ["fluent"]}]}, "experience_required": {"duration": ["2 to 3 years"], "field": ["healthcare industry", "audit", "quality management", "medical device"]}}, {"job_id": "100003009040111", "location_code": "hk", "company": "Vickmans Laboratories Limited", "job_title": "Quality Assurance Officer", "description": "Key Roles and Responsibilities:\n\nTo support in developing, implementing and maintaining the documentation and quality assurance system of the company;\nTo ensure the adequate records are maintained for controlling and monitoring conformity to specified GMP and statutory requirements;\nTo support the routine QA Department functions, including self-inspection, regulatory affairs, products complaints/returns/recalls, etc.\nTo assist ad-hoc projects and administrative tasks assigned by the Manager;\nKnowledge in Quality Management System (e.g change control, risk assessment and CAPA) is an advantage.\n\nQualifications and Experience:\n\nBachelor Degree or above in Pharmacy or related discipline;\nWork independently with good analytical skills and attention to detail;\nStrong communication skill, good command of English and Chinese;\nFresh graduates may also be considered.\n\nWe offer to the right candidates with competitive remuneration package including 12-16 day annual leave, marriage leave, maternity leave, paternity leave, compassionate leave, Public Holidays, medical and dental insurance, educational sponsorship, overtime allowance, performance bonus, MPF and other fringe benefits.\n\nHow to Apply\n\nYou are invited to send in your application and CV stating the position you are applying for together with your current and expected salary by clicking the \"apply button\".\n\n\u00a0\nVickmans LaboratoriesLimited is an Equal Opportunities Employer. Personal data provided by job applicants will be used strictly in accordance with our personal data policy and for recruitment purposes only. We aim to respond to successful applicants within 8 weeks and related information will be kept in our file for up to 12 months for other suitable vacancies in our organization and thereafter destroyed", "employment_types": ["Full Time", "Permanent"], "selling_points": [], "locations": ["Ngau Tau Kok"], "categories": ["Manufacturing", "Production Planning / Control", "Medical Services", "Pharmaceutical", "Quality Assurance, Control & Testing / ISO"], "post_time": "2022-01-12T01:27:55Z", "salary": {"currency": null, "max": null, "min": null, "period": null, "term": null}, "salary_visible": false, "title_keywords": ["quality assurance officer"], "responsibilities": ["management", "control", "mpf", "maintaining", "monitoring", "quality", "developing", "inspection", "communication", "statutory requirements", "recruitment", "insurance", "personal data", "documentation", "ad-hoc projects", "administrative tasks"], "requirements": {"degrees": ["degree or above", "bachelor"], "majors": [], "languages": ["english", "chinese"], "language_level": ["good command"], "hard_skills": ["documentation", "analytical skills"], "soft_skills": ["work independently", "communication skill", "attention to detail", "analytical skills"], "languages_combined": [{"language": "english", "language_level": ["good command"]}, {"language": "chinese", "language_level": ["good command"]}]}, "experience_required": {"duration": [], "field": []}}, {"job_id": "100003009047509", "location_code": "hk", "company": "JPC Texson Limited", "job_title": "QC MANAGER/QUALITY CONTROL MANAGER (33K-45K) - US distributor fastener/electro-mechanical components", "description": "\nTHE COMPANY :\nUS company over 50 years history\nLeading international distributor of industrial, commercial and military fasteners, electronic & electro-mechanical components.\nWe have a wide range of products to support the sheet metal/fabrication market\nWe serve customers from Asia, Central America, Europe and United Kingdom\u00a0\nWe possess rich experience supporting OEM's and Contract Manufacturers in both Commercial, Industrial and Military/Aerospace markets\nWe are looking for\u00a0 QUALITY CONTROL MANAGER\u00a0 - with details as follows :\n\nTHE JOB :\n\nFluency in English, Mandarin and Cantonese, both written and orally\nPrevious experience with metal fabrication and production of threaded products or others\nKnowledge of the Electronics Industry quality control process as relates to fasteners and sheet metal work\nFamiliarity with various secondary special processes such as heat treating and electroplating\nFamiliarity with the cold heading process, screw machine operations and other fabrication methods\nHave the qualifications for ISO9001 Lead Auditor or the possibility of becoming certified as such\nExcellent use of PowerPoint, Excel, Word, Outlook and other software programs\nFamiliarity with some or all of the following : ASTM, GBT, ISO, ANSI, DIN, JIS and other standards as relates to the manufacture, inspection, testing and acceptance of products.\nWork directly with manufacturers in the mainland to identify and resolve product rejections, including issuing Corrective Action Requests and analysis of the actions taken.\nVisit manufacturers on the mainland (normally 1-2 trips per month when free border) to perform on-site audits of facilities, including their sub-tier suppliers for special processes such as plating and heat treating.\nPerform as Lead ISO9001 Auditor for the Internal Audit of the Hong Kong facility and provide guidance to the other auditors involved in the same.\nHosting the annual ISO9001 registration and surveillance audits by our Registrar and responding to any findings\nMonitor the KPI for the Hong Kong facility, and spearheading efforts to meet the stated goals when those fall short.\nReport directly to the Quality Assurance Manager and Director of Operations in the USA Headquarters\nSupervision, guidance, review and mentoring of Hong Kong QC team of 4 members\n5 days work\nAnnual leave : 12 days\nMedical benefit\nDental benefit\nTO APPLY for this job or similar jobs :\n\n\u00a0\nFor secure and confidential job application, please click the below link to get our email address.\n\u00a0\nhttp://jpc.hk/confidential_apply.htm\n\u00a0\n\u00a0\nWe provide free job hunting services to job seekers.\n\u00a0\nTo speed up our process, please do NOT send us download links.\n\u00a0\nPersonal data provided by job applicants will be used for recruitment purpose only.\n\u00a0\nYour privacy is guaranteed. We will never give out, lease, or sell your personal information.\n\u00a0\nJPC Recruiting Services was established in 1990.\n\u00a0\nhttp://www.facebook.com/pages/JPC-Texson-Ltd/500356593325952\n\u00a0\n\n", "employment_types": ["Full Time", "Permanent"], "selling_points": ["Lead HK QC team of 4 members", "Report to US QA Manager & Operations Director", "Based in HK office with occasional China trip"], "locations": ["Kwun Tong Area"], "categories": ["Engineering", "Engineering Project Management", "Mechanical", "Manufacturing", "Quality Assurance, Control & Testing / ISO"], "post_time": "2022-01-14T03:21:29Z", "salary": {"currency": null, "max": null, "min": null, "period": "monthly", "term": null}, "salary_visible": false, "title_keywords": ["manager"], "responsibilities": ["guidance", "software", "internal audit", "operations", "analysis", "review", "monitor", "quality", "testing", "inspection", "quality control", "audits", "provide guidance", "report"], "requirements": {"degrees": [], "majors": [], "languages": ["cantonese", "english", "mandarin"], "language_level": ["fluency"], "hard_skills": ["excel", "analysis", "word", "powerpoint", "outlook"], "soft_skills": ["orally"], "languages_combined": [{"language": "cantonese", "language_level": ["fluency"]}, {"language": "english", "language_level": ["fluency"]}, {"language": "mandarin", "language_level": ["fluency"]}]}, "experience_required": {"duration": [], "field": ["commercial"]}}, {"job_id": "100003009043099", "location_code": "hk", "company": "Arup", "job_title": "Assistant Manager - Quality Assurance", "description": "Responsibilities:\nConduct internal audit on business units, projects and sites, report the audit findings and prepare audit report\nProvide support to local office in regard to the Quality, Environmental and Health & Safety Management System\nAssist the regional leader in establishing and improving of policies, systems, programs and initiatives to ensure compliance with relevant standards and requirements of Quality, Environmental and Health & Safety Management System\nEstablish and maintain statistical database for showing the trend of quality performance\nProvide in-house trainings to maintain high awareness on the requirements of related management system\nOccasional business travel is required\nQualifications & Experience required:\nDegree in Engineering with relevant qualifications in Quality, Environment and Health & Safety\nIRCA Lead Auditor or equivalent\n7 years of experience in development and implementation of Quality, Environmental and Health & Safety Management System and preferably in engineering field\nFamiliar with ISO9001, ISO14001 and OHSAS18001 / ISO45001 audits\nGood analytical, interpersonal and communication skills\nGood team player, strong self-motivated, independent and able to work under pressure\nProficiency in PC skills including MS Office and SharePoint\nProficiency in both written and spoken English and Chinese. Good command of Putonghua is an advantage\n\n\nCandidates with less experience will be considered for the position of Senior Officer - Quality Assurance.\n\nWe offer a competitive remuneration package commensurate with qualifications and experience to the right candidate including Global Profit Share scheme, additional fringe benefits of maternity/paternity leave and long-term career development opportunities.\u00a0\n\nFor interested applicants, please click \u201cApply Now\" to submit your online application.\n\nTo explore more job opportunities in Arup, please visit our website at http://www.arup.com/Careers/Experienced_Hires/ApplyForAJob\n\u00a0\nPersonal data collected will be used for recruitment purpose only. Applicants not contacted within 8 weeks may consider their applications unsuccessful.", "employment_types": ["Full Time", "Permanent"], "selling_points": [], "locations": ["Kowloon City Area"], "categories": ["Engineering", "Others", "Sciences, Lab, R&D", "Environmental Science / Waste Management", "Manufacturing", "Quality Assurance, Control & Testing / ISO"], "post_time": "2022-01-12T09:49:02Z", "salary": {"currency": null, "max": null, "min": null, "period": null, "term": null}, "salary_visible": false, "title_keywords": ["assistant manager"], "responsibilities": ["internal audit", "quality", "audit", "website", "communication", "maintain", "database", "personal data", "work under pressure", "implementation", "report", "provide support", "management", "career development", "audits", "policies", "systems", "ensure compliance", "recruitment"], "requirements": {"degrees": ["degree"], "majors": ["engineering"], "languages": ["putonghua", "english", "chinese"], "language_level": ["advantage", "proficiency", "good command"], "hard_skills": ["pc skills", "scheme", "ms office"], "soft_skills": ["communication skills", "good team player", "self-motivated", "independent", "interpersonal", "work under pressure"], "languages_combined": [{"language": "putonghua", "language_level": ["advantage", "good command"]}, {"language": "english", "language_level": ["proficiency"]}, {"language": "chinese", "language_level": ["proficiency"]}]}, "experience_required": {"duration": ["7 years"], "field": ["management", "engineering", "development", "environmental", "quality assurance"]}}, {"job_id": "100003009044048", "location_code": "hk", "company": "\u9999\u6e2f\u5370\u9214\u6709\u9650\u516c\u53f8", "job_title": "\u8cea\u91cf\u5be9\u67e5\u54e1 (Quality Examiner)", "description": "\u4e2d\u516d\u7a0b\u5ea6\u6216\u4ee5\u4e0a (\u6301\u5370\u5237\u6587\u6191 / \u5316\u9a57\u6587\u6191\u512a\u5148\u8003\u616e)\n\n\u9808\u5177\u6700\u5c11\u5169\u5e74\u8cea\u91cf\u5be9\u67e5/\u5be6\u9a57\u5ba4/\u5ee0\u623f\u5de5\u4f5c\u7d93\u9a57\n\u8ca0\u8cac\u65e5\u5e38\u8cea\u91cf\u5be9\u67e5/\u5316\u9a57/\u5100\u5668\u6821\u6e96\u53ca\u4fdd\u990a\u5de5\u4f5c\u7b49\n\u8ca0\u8cac\u64b0\u5beb\u6aa2\u6e2c\u5831\u544a\n\u6709\u8cac\u4efb\u5fc3\u548c\u826f\u597d\u6e9d\u901a\u6280\u5de7\n\u80fd\u66f8\u5beb\u4e2d\u82f1\u6587\u53ca\u64cd\u5ee3\u6771\u8a71\u3001\u57fa\u672c\u82f1\u8a9e\u53ca\u666e\u901a\u8a71\n\u5177\u6709\u826f\u597d\u96fb\u8166\u61c9\u7528\u77e5\u8b58\n\u9700\u8f2a\u73ed\u5de5\u4f5c\n\n(\u6b61\u8fce\u65b0\u7562\u696d\u4eba\u58eb\u7533\u8acb)\n\n\u00a0\u672c\u516c\u53f8\u63d0\u4f9b\u512a\u539a\u85aa\u916c\u53ca\u798f\u5229\uff0c\u5305\u62ec\u5e74\u7d42\u916c\u91d1\u3001\u91ab\u7642\u53ca\u4eba\u58fd\u4fdd\u96aa\u3001\u81b3\u98df\u53ca\u4ea4\u901a\u6d25\u8cbc\u7b49\uff0c\u52de\u5de5\u5047\u671f\u3002\u6709\u610f\u8005\u8acb\u5c07\u500b\u4eba\u5c65\u6b77\u3001\u5de5\u4f5c\u7d93\u9a57\u3001\u806f\u7d61\u5730\u5740\u53ca\u96fb\u8a71\uff0c\u51fd\u5bc4\u65b0\u754c\u5927\u57d4\u5de5\u696d\u90a8\u5927\u76db\u88572-4\u865f\u4eba\u4e8b\u53ca\u884c\u653f\u90e8\u6536\u6216\u6309\"APPLY NOW\"\u63d0\u4ea4\u7533\u8acb\u6216\u50b3\u771f\u81f32664 4882\u3002\n\n(\u7533\u8acb\u4eba\u6240\u63d0\u4f9b\u7684\u8cc7\u6599\u5c07\u4e88\u4fdd\u5bc6\u53ca\u53ea\u4f9b\u7533\u8acb\u6709\u95dc\u8077\u4f4d\u7528\u9014)\n\n*(\u6b61\u8fce\u65b0\u7562\u696d\u4eba\u58eb\u7533\u8acb)", "employment_types": ["Full Time"], "selling_points": [], "locations": ["Tai Po Area"], "categories": ["Manufacturing", "Others", "Printing", "Quality Assurance, Control & Testing / ISO"], "post_time": "2022-01-13T02:54:35Z", "salary": {"currency": null, "max": null, "min": null, "period": "monthly", "term": null}, "salary_visible": false, "title_keywords": [], "responsibilities": [], "requirements": {"degrees": [], "majors": [], "languages": [], "language_level": [], "hard_skills": [], "soft_skills": [], "languages_combined": []}, "experience_required": {"duration": [], "field": []}}, {"job_id": "100003009046807", "location_code": "hk", "company": "Wai Yuen Tong Medicine Co Ltd", "job_title": "Senior QA Officer / QA Officer", "description": "Responsibilities:\n\n\nHandle license application and renewal including certificate for manufacturer, wholesaler of Chinese herbal medicines, wholesaler of proprietary Chinese medicines, food factory\nHandle applications for license to import, introduce from the sea, export, re-export endangered species, import and export of Chinese medicines\nSupport application and renewal of HACCP certification\nAssist in audit and surprise check by government department\nManage the document control system, such as generating, filing and archiving of controlled documents for GMP/TGA/Food GMP/HACCP system\nEnsure the QA system and procedures are operated throughout quality system operations\nAssist in maintaining the training program\nUndertake routine quality assurance monitoring program\nAssist in handling and following up on quality incidents\nAssist in carrying out internal audits\nAssist in maintaining inspection readiness for external audits\n\nRequirements:\n\nHigher Diploma or above in science related subjects, e.g. Chinese Medicine, Food Science, Chemistry, Biochemistry, Chemical Engineering, Microbiology, Pharmacy, Pharmaceutical Science or related disciplines\nMinimum 3 year solid experience in food or pharmaceutical area\nProactive, attention to details, hard-working\nGood interpersonal and communication skills\nProficiency in computer application such as MS Office and Chinese word processing\nFamiliar with HACCP/Food GMP would be an advantage\nGood command in written and spoken English and Chinese, knowledge of Putonghua is an advantage\nProficiency in using Microsoft applications including Excel, PowerPoint and English & Chinese Word Processing\nApplicant with more experience will be considered as Senior QA Officer\n\nInterested parties please send full resume with present and expected salary to Human Resources Department by clicking \"APPLY NOW\".\n\n(Information provided will be treated in strict confidence and will only be used for recruitment-related purposes.)", "employment_types": ["Full Time", "Permanent"], "selling_points": ["Working Location: Yuen Long", "Handle license application and renewal", "experience in food or pharmaceutical area"], "locations": ["Yuen Long"], "categories": ["Medical Services", "Pharmaceutical", "Manufacturing", "Quality Assurance, Control & Testing / ISO"], "post_time": "2022-01-14T01:15:21Z", "salary": {"currency": null, "max": null, "min": null, "period": "monthly", "term": null}, "salary_visible": false, "title_keywords": ["officer"], "responsibilities": ["control", "maintaining", "operations", "monitoring", "quality", "procedures", "audit", "inspection", "license application", "audits"], "requirements": {"degrees": ["higher diploma or above"], "majors": ["science"], "languages": ["putonghua", "english", "chinese"], "language_level": ["advantage", "proficiency", "good command"], "hard_skills": ["excel", "chinese word processing", "microsoft applications", "powerpoint", "ms office"], "soft_skills": ["communication skills", "hard-working", "attention to details", "proactive", "interpersonal"], "languages_combined": [{"language": "putonghua", "language_level": ["good command"]}, {"language": "english", "language_level": ["advantage", "proficiency", "good command"]}, {"language": "chinese", "language_level": ["advantage", "proficiency", "proficiency", "good command"]}]}, "experience_required": {"duration": ["minimum 3 year"], "field": ["pharmaceutical", "food", "qa"]}}, {"job_id": "100003009039471", "location_code": "hk", "company": "Cornerstone Renewable Energy Limited", "job_title": "Assistant Quality Engineer", "description": "Responsibilities:\u00a0\n\nPerform outgoing quality inspection prior to the finished product delivery on site, analyse if any nonconformance for corrective action\nProduct/Part qualification test for final stage of design change prior to production launch\nProduct quality issue investigation from site and corrective action follow up\nPerform Incoming spare part inspection\nDeploy and sustain quality inspection plan and prepare report\nSupplier quality monitoring\n\nRequirements:\n\nHigher\u00a0Diploma or above in engineering or equivalent\nAt least 1-2\u00a0year working experience in Quality / Testing / Environmental / Manufacturing industrial sector\nGood problem-solving skills\nKnowledge of quality management system and quality tools\nProactive, willing to learn practical hand skills, and with can-do attitude\nGood command of both spoken and written English and Cantonese\nWell versed in Microsoft Word & Excel etc.\u00a0\nWilling to travel is preferable\nWe offer 5-day work and medical benefits to the successful candidates. Interested parties please send your full CV with current and expected salary in MS Word format to the Human Resources & Administration Manager.\nTo know more about us, please visit our website at\u00a0https://www.cstre.com.hk.\nWe are an equal opportunity employer and welcome applications from all qualified candidates.\nPersonal data collected will be treated in strict confidence and used only for recruitment-related purpose. Applicants who have not heard from us within four weeks may consider their applications unsuccessful. All personal data will be destroyed after 6 months.", "employment_types": ["Full Time", "Permanent"], "selling_points": ["Quality control prior to product delivery", "Sustain Quality Test and inspection plan", "Return part analysis for corrective action"], "locations": ["Wong Tai Sin Area"], "categories": ["Engineering", "Electrical / Electronics", "Manufacturing", "Quality Assurance, Control & Testing / ISO"], "post_time": "2022-01-11T09:53:06Z", "salary": {"currency": null, "max": null, "min": null, "period": "monthly", "term": null}, "salary_visible": false, "title_keywords": ["engineer", "assistant"], "responsibilities": ["prepare report", "monitoring", "quality", "product quality issue", "design", "inspection", "investigation", "plan", "deploy", "analyse"], "requirements": {"degrees": ["higher diploma or above"], "majors": ["engineering"], "languages": ["cantonese", "english"], "language_level": ["good command"], "hard_skills": ["problem-solving skills", "microsoft word", "excel"], "soft_skills": ["problem-solving skills", "proactive", "willing to learn", "can-do attitude"], "languages_combined": [{"language": "cantonese", "language_level": ["good command"]}, {"language": "english", "language_level": ["good command"]}]}, "experience_required": {"duration": ["at least 1-2 year"], "field": ["manufacturing", "environmental", "testing"]}}, {"job_id": "100003009042064", "location_code": "hk", "company": "Caf\u00e9 de Coral Group Limited", "job_title": "Quality Control Manager", "description": "Job Responsibilities:\n\nResponsible for ISO 22000 & HACCP System management and maintenance for a food manufacturing plant\nEnsure the food safety procedures outlined in the ISO system are communicated to all necessary parties and correctly implemented via training;\u00a0maintain up to date documentation, internal audit & follow up , oversee the certification renewal process, etc\nWorks with senior management on development and revision of policies and procedures pertaining to food quality and safety\nManage reporting and communication to prepare for audits and assessments, management meetings etc.\nCoordinate customer complaints incident investigation, report and analysis, develop plan for corrective & preventive actions\nCommunicate all Hold and Release activity to relevant department\nCollaborate with other related departments to assure timely and accurate reporting of food safety/ quality issues and or worker safety issues\nStay up to date on the latest regulatory requirements, and review company standards to ensure food safety & compliance\nLead and provide coaching to the team members\nPerform other duties as requested by Management\n\u00a0\nRequirements:\n\nBachelor\u2019s degree or above in Food Science/Nutrition or related discipline\nMinimum\u00a0 8 years\u2019 relevant experience in food industry QA or QC management, in which at least 5 years in supervisory/managerial roles\nSolid experience in Manufacturing industry, Quality & Food Safety Management System standard & setup; with ISO22000 lead auditor certification\nExperience with implementing ISO22000, HACCP system\nPassionate , details minded, self-motivated and able to work independently\nGood leadership and a good team player as well\nExcellent communication, training, and interpersonal skills\nProficient in MS Office applications\nGood command of both written and spoken English and Cantonese\n\nInterested parties please send full resume with\u00a0PRESENT & EXPECTED SALARY\u00a0to Human Resources Department by clicking \"APPLY NOW\".\n\nWe are an EQUAL OPPORTUNITIES EMPLOYER.\nAll information received will be kept in strict confidence and be used for employment related purpose only.", "employment_types": ["Full Time", "Permanent"], "selling_points": ["ISO 22000 & HACCP System management", "Ensure food safety & compliance", "Degree in Food Science/ Nutrition, with 8 yrs exp."], "locations": ["Shatin Area"], "categories": ["Hospitality / F & B", "Food & Beverage", "Sciences, Lab, R&D", "Food Science", "Manufacturing", "Quality Assurance, Control & Testing / ISO"], "post_time": "2022-01-12T05:49:32Z", "salary": {"currency": null, "max": null, "min": null, "period": "monthly", "term": null}, "salary_visible": false, "title_keywords": ["manager"], "responsibilities": ["collaborate with", "internal audit", "regulatory requirements", "quality", "communication", "maintain", "plan", "senior management", "perform other duties", "compliance", "develop", "report", "reporting", "management", "food safety", "customer complaints", "review", "procedures", "investigation", "audits", "documentation", "maintenance", "policies", "analysis", "coordinate"], "requirements": {"degrees": ["degree or above", "bachelor"], "majors": ["food science"], "languages": ["cantonese", "english"], "language_level": ["good command"], "hard_skills": ["ms office"], "soft_skills": ["passionate", "good team player", "self-motivated", "work independently", "communication", "interpersonal skills", "leadership"], "languages_combined": [{"language": "cantonese", "language_level": ["good command"]}, {"language": "english", "language_level": ["good command"]}]}, "experience_required": {"duration": ["at least 5 years", "8 years"], "field": ["managerial", "management", "supervisory", "qa", "food industry", "relevant experience", "food", "manufacturing industry"]}}, {"job_id": "100003009049963", "location_code": "hk", "company": "Vogue Laundry Service Limited", "job_title": "Senior Operations Support Officer", "description": "Successful candidates will be required to plan the best resource utilization in workflow and workforce to achieve the highest level of operations excellence and customer satisfaction.\n\nResponsibilities:\n\nLead a small team\u00a0to perform customer orders processing and handle inquiries or complaints from the corporate customers\nEnsure the daily production reports are delivered timely and accurately\nProvide satisfactory support services to operational teams\nPrepare and follow up on the progress of the system change request\nParticipate in ad-hoc projects and perform other duties as and when required\nRequirements:\n\nDiploma / Degree holder in Business, Logistics or Operations Management\nMinimum 3 years relevant experience in various operations support disciplines\nGood team player with strong interpersonal and communication skills\nStrong problem-solving capability, able to communicate effectively\nProficient in MS Office including Excel, PowerPoint, and Word\nWe offer competitive remuneration and benefits include:\nMedical & dental benefits\nDiscount air-tickets\nDiscount laundry service\nSwire Hong Kong Staff Association membership\nStaff activity\nEducation allowance\nChildren education scholarship\nVoluntary service leave\nOn-the job training\nOutperformer awards\nDiscretionary performance bonus\nInterested parties please click \u201cApply Now\u201d to submit your application.\u00a0\nMail: People Department, 95-99 Fuk Hi Street, Yuen Long Industrial\u00a0Estate, Yuen Long, N.T.\nFax: 2480 2432\n\nApplication details will be used only for recruitment purpose, and will be destroyed after 24 months.", "employment_types": ["Full Time"], "selling_points": ["Perform Customer Orders Processing", "Handle Corporate Customers' Inquiries", "Free Meal I Shuttle Bus I Medical"], "locations": ["Yuen Long"], "categories": ["Manufacturing", "Production Planning / Control", "Others", "Quality Assurance, Control & Testing / ISO"], "post_time": "2022-01-14T09:31:16Z", "salary": {"currency": null, "max": null, "min": null, "period": "monthly", "term": null}, "salary_visible": false, "title_keywords": ["officer", "senior operations"], "responsibilities": ["perform other duties", "lead a small team", "support services", "teams", "reports", "ad-hoc projects"], "requirements": {"degrees": ["diploma", "degree holder"], "majors": ["business"], "languages": [], "language_level": [], "hard_skills": ["excel", "problem-solving", "word", "powerpoint", "ms office"], "soft_skills": ["problem-solving", "communication skills", "good team player", "interpersonal"], "languages_combined": []}, "experience_required": {"duration": ["minimum 3 years"], "field": ["relevant experience"]}}, {"job_id": "100003009049022", "location_code": "hk", "company": "Randstad Hong Kong Limited", "job_title": "Product Compliance Specialist", "description": "about the company.\n\nOur client is a EU buying office with a strong presence in Hong Kong. With the rising awareness in social compliance and responsibility, they would like to invite a candidate to join their Hong Kong office as a Product Compliance Specialist.\n\nabout the job.\n\nAs a Product Compliance Specialist, you are required to\n\nEnsure all factory sociali complaince evaluations (FCE) are in line with company's SOP.\nHelp develop factory evaluation plans and schedules from social compliance perspetive, as well as ensure all FCEs are arranged and conducts in schedule.\nConduct FCE of Asia's supplier base for factories to ensure they comply with company requirements.\nReview and verify the critical non-compliance (CNC) found during audit as conducted by the ME audit team and third parties.\nReview FCE audit reports and report any compliance discrepancies and follow up with the corrective actions.\nUpdate and ensure all FCE data are accurate in the system.\nPrepare FCE audit report to summarize the evaluation results.\nPrepare FCE data for monthly and quarterly reports.\nAssist in system upgrade and development to ensure all requirements are met.\nSupport process & system audits, as well as standardization of work documentation.\nskills & experiences required.\n\nTo be successful at this position, you need\n\nBachelor degree or above, with good communication skills in both Chinese and English.\nAt least 3 year social compliance experience within a retail/ buying office field.\nKnowledge in BSCI/ SA8000, Better Work Factory, ACCORD and other social compliance standards.\nExperience in auditing within manufacturing environment.", "employment_types": ["Full Time", "Permanent"], "selling_points": ["EU Buying Office", "Product compliance", "Hardline and softline"], "locations": ["Not Specified"], "categories": ["Engineering", "Others", "Sciences, Lab, R&D", "Environmental Science / Waste Management", "Manufacturing", "Quality Assurance, Control & Testing / ISO"], "post_time": "2022-01-14T07:56:02Z", "salary": {"currency": "HKD", "max": 34999, "min": 30000, "period": "monthly", "term": null}, "salary_visible": true, "title_keywords": ["specialist"], "responsibilities": ["documentation", "data", "schedules", "compliance", "review", "audit", "develop", "communication", "reports", "schedule", "evaluation", "audits", "plans", "auditing", "report"], "requirements": {"degrees": ["degree or above", "bachelor"], "majors": [], "languages": ["english", "chinese"], "language_level": ["good"], "hard_skills": ["documentation"], "soft_skills": ["communication skills", "accurate"], "languages_combined": [{"language": "english", "language_level": ["good"]}, {"language": "chinese", "language_level": ["good"]}]}, "experience_required": {"duration": ["at least 3 year"], "field": ["manufacturing", "compliance", "retail"]}}, {"job_id": "100003009047386", "location_code": "hk", "company": "Advance Pharmaceutical Company Limited", "job_title": "Assistant QA Manager", "description": "Assist in inspection and supervision of the implementation of GMP throughout the company.\nResponsible for updating relevant GMP regulations (such as laws) and guidelines.\nHelp to maintain the Quality Management System. Monitor QA related works e.g. deviation, investigation, risk assessment, change control, periodic quality review and self-inspection, etc.\nMonitor and handle complaint and recall of products\nManage and Follow up with goods return and disposal\nAssist in the implementation of the training program and to provide related trainings to staff and review training records.\nReview maintenance records of critical utilities\nReview of SOP, Batch production record, validation report\nMaintain the documentation system\nAssist to monitor the suppliers and manufacturers of starting materials\nAssist to monitor the implementation of environmental monitoring\nConduct the tasks assigned by QA Manager", "employment_types": ["Full Time"], "selling_points": [], "locations": ["Tai Po Area"], "categories": ["Medical Services", "Pharmaceutical", "Manufacturing", "Quality Assurance, Control & Testing / ISO"], "post_time": "2022-01-14T02:57:08Z", "salary": {"currency": null, "max": null, "min": null, "period": "monthly", "term": null}, "salary_visible": false, "title_keywords": ["manager", "assistant"], "responsibilities": ["regulations", "management", "control", "guidelines", "maintenance records", "review", "quality", "implementation", "monitor", "inspection", "investigation", "monitoring", "maintain", "documentation", "report"], "requirements": {"degrees": [], "majors": [], "languages": [], "language_level": [], "hard_skills": ["documentation", "batch", "maintenance"], "soft_skills": ["responsible"], "languages_combined": []}, "experience_required": {"duration": [], "field": []}}, {"job_id": "100003009037812", "location_code": "hk", "company": "Hong Kong Regen Medtech Limited", "job_title": "Quality Control Manager", "description": "Job Responsibilities:\n\nPrepare and review protocols and other associated PIC/S GMP documentation.\nAnalysis of raw material, in-process and final bulk cell therapy/gene product samples according to Standard Operating Procedures (SOP) and test methods.\nExperience in one or more of the following analytical techniques: Flow Cytometry, Blood Culture test, Cell Culture, sterility test, endotoxin test, mycoplasma test, and tests specific to cell-based products.\nSupervise and perform the qualification, maintenance, and calibration for all QC equipment and instrument.\nReview and fine-tuning of quality control workflow.\nOther duties as assigned by Authorized Person and/or management team.\n\nQualification and Experience:\n\nBachelor\u2019s degree or above in biotechnology, biomedical engineering, medical laboratory science or science degree with relevant to cell therapy, gene therapy, regenerative medicines or tissue engineering, or other similar sciences disciplines;\nAt least 3 years of working experience at managerial or supervisory level in GMP manufacturing or quality control of ATPs;\nExperience for PIC/S GMP QC is highly preferred;\nWith practical experience in PIC/S GMP QC testing of sterile products is highly preferred;\nExcellent communication, problem-solving, time management, and prioritization skills.\nSelf-motivated and a good team player, attention to detail.\nProficiency in English and Chinese.\n\nWe offer an attractive remuneration package including group medical insurance, discretionary year-end performance bonus, and an energetic, fun work environment.\n\nInterested parties please send your resume with current, expected salary and availability to the HR Department.\n\n(All personal data provided will be treated in strict confidence and be used for recruitment purposes.)", "employment_types": ["Full Time"], "selling_points": [], "locations": ["Shatin Area"], "categories": ["Sciences, Lab, R&D", "Laboratory", "Medical Services", "Pharmaceutical", "Manufacturing", "Quality Assurance, Control & Testing / ISO"], "post_time": "2022-01-11T03:56:06Z", "salary": {"currency": null, "max": null, "min": null, "period": "monthly", "term": null}, "salary_visible": false, "title_keywords": ["manager"], "responsibilities": ["management team", "management", "year-end", "maintenance", "other duties", "analysis", "review", "procedures", "testing", "communication", "quality control", "documentation", "insurance"], "requirements": {"degrees": ["degree", "degree or above", "bachelor"], "majors": ["biomedical engineering", "engineering", "medical laboratory science", "science"], "languages": ["english", "chinese"], "language_level": ["proficiency"], "hard_skills": ["fun", "maintenance", "analysis", "problem-solving", "documentation"], "soft_skills": ["good team player", "self-motivated", "problem-solving", "communication", "energetic", "attention to detail", "time management"], "languages_combined": [{"language": "english", "language_level": ["proficiency"]}, {"language": "chinese", "language_level": ["proficiency"]}]}, "experience_required": {"duration": ["at least 3 years"], "field": ["managerial", "gmp manufacturing", "analytical", "testing", "quality control", "supervisory level"]}}, {"job_id": "100003009039300", "location_code": "hk", "company": "Giordano Limited", "job_title": "Assistant QA Manager", "description": "Responsibilities\n\nTo ensure products meet the quality requirements of our customers (especially newly developed markets)\nTo build quality concepts in the system and process to deliver consistency\nCoordinate with the corporate office and different teams to deliver results\u00a0\nUnderstand the quality requirement of newly developed markets & current standards to establish a suitable quality plan for those markets\nTo implement and communicate the plans to the vendors & all concerned parties\u00a0\nTo identify & evaluate risks in design, material & trims early in the process concerning the newly developed markets\nEnsure vendors conduct required tests and compliance with standards to ensure on-time delivery. Make proper filing records\u00a0\nTo audit vendors and arrange QC inspection\nConduct pre-production meetings, on-site inspections in the supplier's office or through zoom meetings\nIdentify and fix the ongoing quality problems and continuously identify areas of improvement\nCommunicate constantly with other teams to align goals and objectives\nProvide updated QA reports on a continued basis\n\n\u00a0\u00a0Qualifications:\n\nBachelor's degree in Industrial engineering/garment/textile\nExperience of at least five years in QA/QC in the garment/textile industry\nGood understanding of knitting and woven apparel\nGood English proficiency & hands-on knowledge of computer & QA statistics\nHaving analytical and logical thinking and must have good attention to detail\nWilling to travel\u00a0\nImmediate available are preferred", "employment_types": ["Full Time", "Permanent"], "selling_points": ["5 days work, 9:00 am to 5:00 pm", "5 years experience in QA/QC in garment industry", "Immediate available are preferred"], "locations": ["Lai Chi Kok"], "categories": ["Manufacturing", "Garment / Textile", "Quality Assurance, Control & Testing / ISO"], "post_time": "2022-01-11T09:23:11Z", "salary": {"currency": null, "max": null, "min": null, "period": "monthly", "term": null}, "salary_visible": false, "title_keywords": ["manager", "assistant"], "responsibilities": ["pre-production", "compliance", "teams", "quality", "coordinate with", "design", "evaluate", "audit", "inspection", "reports", "site inspections", "quality plan", "plans"], "requirements": {"degrees": ["degree", "bachelor"], "majors": ["engineering"], "languages": ["english"], "language_level": ["proficiency", "good"], "hard_skills": ["make"], "soft_skills": ["hands-on", "attention to detail"], "languages_combined": [{"language": "english", "language_level": ["proficiency", "good"]}]}, "experience_required": {"duration": ["at least five years"], "field": ["garment", "qa", "textile"]}}, {"job_id": "100003009042354", "location_code": "hk", "company": "DiagCor Life Science Limited", "job_title": "Senior Production Technologist/ Production Technologist/ Production Technician", "description": "Job Duties:\n\nParticipate in manufacturing & quality control of In-vitro diagnosis reagents;\nMonitor and review of manufacturing and quality control process;\nCoordinate with multi-functional teams for new product launching;\nPerform materials sourcing and quality control of incoming materials;\nReview and update standard operation procedure and documents;\nProvide technical training to ensure strictly follows to the approved SOP;\nAssist in QMS accreditation and product registration;\nPlan and perform stability study of new products;\nMonitor and maintenance production facility and equipment.\n\nRequirements:\n\nPostgraduate, degree or diploma holder in life science or related discipline with knowledge in molecular genetics / molecular biology;\n1 year of manufacturing experience in pharmaceutical, medical device or health care products;\nExperienced in PCR or molecular lab is preferred;\nExperience in handling equipment maintenance and calibration work;\nKnowledge in ISO 9001, ISO 13485 or GMP / six sigma is an advantage;\nGood written and verbal communication skills;\nGood problem solving skill and able to work under pressure;\nTeam player attitude, proactive and self-motivated.\n\nIf you are passionate, driven and looking for a new and exciting opportunity within a successful and growing company, this may be the right role for you.\n\nPlease click \u201cApply Now\u201d to submit your application.\n\nFor more info, please visit our web page at\u00a0http://www.diagcorlifescience.com/\n\nWe will only consider applicants who apply directly to our firm and not through recruitment agencies. All applications will be treated in strict confidence. Personal data collected will be used for recruitment purposes only. Applicants who do not hear from us within 4 weeks may consider their applications unsuccessful and the applications will be destroyed within 6", "employment_types": ["Full Time"], "selling_points": [], "locations": ["Kowloon Bay"], "categories": ["Sciences, Lab, R&D", "Life Science", "Manufacturing", "Production Planning / Control", "Quality Assurance, Control & Testing / ISO"], "post_time": "2022-01-12T07:10:03Z", "salary": {"currency": null, "max": null, "min": null, "period": "monthly", "term": null}, "salary_visible": false, "title_keywords": ["production technician"], "responsibilities": ["maintenance", "review", "teams", "monitor", "coordinate with", "quality control", "plan"], "requirements": {"degrees": ["diploma holder", "degree"], "majors": ["molecular biology", "science", "genetics"], "languages": [], "language_level": [], "hard_skills": ["problem solving", "six sigma", "web", "maintenance"], "soft_skills": ["passionate", "communication skills", "self-motivated", "confidence", "team player", "problem solving skill", "proactive", "driven", "work under pressure"], "languages_combined": []}, "experience_required": {"duration": ["1 year"], "field": ["manufacturing", "maintenance", "medical device", "pharmaceutical", "health care"]}}, {"job_id": "100003009046031", "location_code": "hk", "company": "Ocean Park Corporation", "job_title": "Food Technologist", "description": "(Long-Term Contract)\n\nThe incumbent will be responsible for implementing and maintain ISO22000 Food Safety Management System to ensure food safety. He/she will conduct microbiological testing on food/environmental samples collected at different food outlets. He/she will also conduct routine hygiene inspection and provide report to outlets to improve the outlet\u2019s hygiene. Besides, he/she will arrange third party services\u2019 for food outlets (Deep clean, Pest control etc.). In addition, he/she will assist in in or conduct food compliant investigation and regular internal and external audits including ISO22000 & Halal. S/he will also provide routine food safety training for staff and perform other ad hoc duties as assigned by manager.\n\n\n\n\u00a0Requirements:\n- Higher Diploma or above in Food Science or relevant disciplines\n- Relevant work experience in food manufacturing plant / catering industry is preferred\n- Hands-on experience in microbiological testing of food is preferred\n-\u00a0Familiar with HACCP / ISO22000, local food regulatory requirements and standards\n- Good communication and interpersonal skills\n- Good team player, hardworking and self-motivated\n-\u00a0Occasional travel in park area is required\n\nCandidates with more experience will be considered as Senior Food Technologist\n\nApplications including details of qualifications, working experience, expected salary, contact telephone number and address should be applied via: http://careers.oceanpark.com.hk --> Job opening --> Full time/ Long-term.\n\nApplicants not contacted within six weeks may consider their application unsuccessful. Personal data collected will be used for recruitment-related purpose only.", "employment_types": ["Full Time", "Contract"], "selling_points": ["Food Safety", "product testing", "hygiene inspection"], "locations": ["Aberdeen"], "categories": ["Sciences, Lab, R&D", "Food Science", "Manufacturing", "Quality Assurance, Control & Testing / ISO", "Others", "Others"], "post_time": "2022-01-13T09:27:38Z", "salary": {"currency": null, "max": null, "min": null, "period": "monthly", "term": null}, "salary_visible": false, "title_keywords": ["food technologist"], "responsibilities": ["ad hoc duties", "management", "control", "food safety", "regulatory requirements", "internal and external audits", "investigation", "testing", "inspection", "hygiene", "communication", "maintain", "recruitment", "contact", "catering", "personal data", "third party", "report"], "requirements": {"degrees": ["higher diploma or above"], "majors": ["food science"], "languages": [], "language_level": [], "hard_skills": ["clean"], "soft_skills": ["good team player", "self-motivated", "responsible", "deep", "hands-on", "communication and interpersonal skills", "hardworking"], "languages_combined": []}, "experience_required": {"duration": [], "field": ["food manufacturing", "food", "testing"]}}, {"job_id": "100003009044085", "location_code": "hk", "company": "Cargo Services Far East Ltd", "job_title": "Process and Quality Engineer", "description": "Responsibilities:\nTo work cross with respective departments to review current business and operational processes to identify areas of improvement and drive necessary changes for better efficiency and quality.\nTo assist in the implementation of new processes in an effective manner, that engages employees and stakeholders.\nTo assist in implementation of quality, process improvement, and compliance programs.\nTo perform inspection and measurement on business/operational processes (analyzing key performance indicators) and follow up on corrective actions\nOther duties as assigned by the Assistant General Manager \u2013 Process and Quality Assurance\nRequirements:\nDegree holder\nMinimum 1 year working experience in logistics/shipping field\nExperience in writing up procedure or work instruction is an advantage\nStrong communication, presentation, and computer skills, including knowledge of Microsoft Office in particular Visio, Excel, Powerpoint, Word, Outlook\nKnowledge related to ISO standard is an advantage but not essential\nAbility to work in a cross-functional environment, with good communication skill\nGood command of written and spoken English and Chinese\n\nBenefits:\nDouble Pay\nFive-day work week\nBirthday Leave\nMedical Insurance\nFree Shuttle Bus\nTraining Allowance\nAttractive remuneration package and excellent career development opportunities will be offered to the right candidates. For Interested parties, please apply with a detailed resume stating present and expected salary by clicking \"Apply Now\". You are welcome to visit our website at http://www.cargofe.com.\nPersonal data collected will be used for recruitment purposes only and kept confidential.\u00a0\u00a0", "employment_types": ["Full Time", "Permanent"], "selling_points": ["Process & QA role in Freight Forwarder", "1-year exp; Knowledge related to ISO standard", "5-day work week; Double Pay; Birthday Leave"], "locations": ["Kwai Tsing Area"], "categories": ["Transportation & Logistics", "Others", "Shipping", "Manufacturing", "Quality Assurance, Control & Testing / ISO"], "post_time": "2022-01-13T03:00:00Z", "salary": {"currency": null, "max": null, "min": null, "period": "monthly", "term": null}, "salary_visible": false, "title_keywords": ["engineer"], "responsibilities": ["other duties", "compliance", "review", "quality", "implementation", "inspection", "measurement"], "requirements": {"degrees": ["degree holder"], "majors": [], "languages": ["english", "chinese"], "language_level": ["good command"], "hard_skills": ["excel", "microsoft office", "word", "powerpoint", "computer skills", "outlook"], "soft_skills": ["communication", "communication skill", "presentation"], "languages_combined": [{"language": "english", "language_level": ["good command"]}, {"language": "chinese", "language_level": ["good command"]}]}, "experience_required": {"duration": ["minimum 1 year"], "field": ["logistics", "writing"]}}, {"job_id": "100003009049859", "location_code": "hk", "company": "Orient Overseas Container Line Ltd (OOCL)", "job_title": "Officer/Senior Officer, Traffic Control Center", "description": "Responsibilities:\nTo maximize vessel utilization of assigned services, and ensure full and down achievement\nTo optimize long-haul and double dipping opportunities for cost-effective slot utilization\nTo review the allocation of assigned services for yield improvement\nTo formulate and implement contingency plan for service recovery\nTo communicate with regions and planners in order to maximize vessel utilization\nTo communicate with business partners on day-to-day traffic matters in order to protect Company interests\nTo prepare regular traffic reports and slot settlement\nRequirements:\nUniversity graduate in Business or related disciplines\nAt least 3 years relevant work experience, preferably in shipping industry\nGood communication, analytical, decision making and problem solving skills\nSensitive to figures and details\nAble to work independently and under pressure; possess business sense\nProficient in spoken and written English and Chinese, spoken Mandarin preferred\nCompetent in Windows applications\nCandidate with less experience will also be considered for the position of Officer\nPlease send your application letter with detailed resume and expected salary by clicking \"Apply Now\" and quote the reference number on the subject\n(Data collected will be used for recruitment purpose only.)\nhttp://www.oocl.com/", "employment_types": ["Full Time", "Permanent"], "selling_points": ["To maximize vessel utilization of assigned service", "University graduate in Business or related", "At least 3 years relevant work experience"], "locations": ["Wan Chai"], "categories": ["Transportation & Logistics", "Shipping", "Manufacturing", "Others", "Quality Assurance, Control & Testing / ISO"], "post_time": "2022-01-14T09:19:28Z", "salary": {"currency": null, "max": null, "min": null, "period": "monthly", "term": null}, "salary_visible": false, "title_keywords": ["officer", "senior officer"], "responsibilities": ["communicate with", "cost", "review", "reports", "plan"], "requirements": {"degrees": ["university graduate"], "majors": ["related disciplines", "business"], "languages": ["english", "chinese", "mandarin"], "language_level": ["proficient"], "hard_skills": ["problem solving skills"], "soft_skills": ["work independently", "under pressure", "business sense", "competent", "sensitive to figures", "detailed", "communication", "problem solving skills", "decision making"], "languages_combined": [{"language": "english", "language_level": ["proficient"]}, {"language": "chinese", "language_level": ["proficient"]}, {"language": "mandarin", "language_level": ["proficient"]}]}, "experience_required": {"duration": ["at least 3 years"], "field": ["shipping industry"]}}, {"job_id": "100003009043584", "location_code": "hk", "company": "Maxim's Caterers Ltd", "job_title": "Quality Assurance Assistant (Cakes & Bakery)", "description": "Responsibilities:\n\nPerform routine on line and finished food products inspection at various stages on the production line to implement ISO/HACCP policy.\nAssist in implementing and maintain the documentation system and quality management system.\nSupport the implementation of food safety, hygiene and quality assurance operation policies, guidelines and procedures to ensure the entire production process is in compliance with the corporate standard.\nCoordinate and participate work safety, quality assurance and hygiene procedures training to related staff.\nAssist in other ad-hoc projects as assigned.\n\nRequirements:\n\nDiploma holder or above in biochemistry, Food Science or related disciplines;\nAt least 1 year laboratory working experience;\nSelf-motivated, independent and with good communication skill;\nWell-organized with good analytical skill;\nProficient in PC applications including Chinese word processing;\nGood command of spoken and written English and Chinese / Cantonese;\n5-day work week and rotate day off;\nWorking location: Tai Po Industrial Estate (with shuttle bus)\nFresh graduate will also be considered.\n\nInterested parties please apply with full resume, state current and expected salaries via clicking \"Apply Now\".\n\n\nAll applications and data collected will be treated in strict confidence and used exclusively for recruitment purposes.\u00a0 Only short listed candidates will be invited for interview.\u00a0 The company will retain the applications for a maximum period of 6 months and may refer suitable candidates to other vacancies within the Group.", "employment_types": ["Full Time", "Permanent"], "selling_points": ["Implementing and maintain the documentation system", "Support the implementation of food safety, hygiene", "5-day work week and rotate day off"], "locations": ["Tai Po Area"], "categories": ["Sciences, Lab, R&D", "Food Science", "Laboratory", "Manufacturing", "Quality Assurance, Control & Testing / ISO"], "post_time": "2022-01-12T23:19:09Z", "salary": {"currency": null, "max": null, "min": null, "period": null, "term": null}, "salary_visible": false, "title_keywords": ["quality assurance assistant"], "responsibilities": ["management", "production process", "food safety", "guidelines", "policies", "compliance", "quality", "implementation", "procedures", "inspection", "coordinate", "hygiene", "maintain", "documentation", "ad-hoc projects"], "requirements": {"degrees": ["diploma holder", "fresh graduate"], "majors": ["related disciplines", "food science"], "languages": ["cantonese", "english", "chinese"], "language_level": ["good command", "proficient"], "hard_skills": ["analytical skill", "chinese word processing", "pc applications"], "soft_skills": ["self-motivated", "analytical skill", "independent", "communication skill", "well-organized"], "languages_combined": [{"language": "cantonese", "language_level": ["good command"]}, {"language": "english", "language_level": ["good command"]}, {"language": "chinese", "language_level": ["good command", "proficient"]}]}, "experience_required": {"duration": ["at least 1 year"], "field": ["laboratory"]}}, {"job_id": "100003009042534", "location_code": "hk", "company": "Bravo Personnel Consultancy Limited", "job_title": "Shipping / Quality Control Assistant ($18K)", "description": "Job requirements:\nDiploma with 2 year relevant experience in shipping or quality control\nReceive production QC samples and perform inspections under the guidance of the QA/QC manager\nDocument internal processes and procedures\nAssist with AQL inspections as needed\nArchive all QC samples and documents\nInterested parties, please contact Ms LEE at 2881 6923 during office hours or email your CV by clicking \"Apply Now\" or fax your resume to 2576 8026. All the personal data collected will be used for recruitment purpose only.\u00a0", "employment_types": ["Full Time", "Permanent"], "selling_points": [], "locations": ["Tsuen Wan Area"], "categories": ["Transportation & Logistics", "Others", "Shipping", "Manufacturing", "Quality Assurance, Control & Testing / ISO"], "post_time": "2022-01-12T08:35:29Z", "salary": {"currency": null, "max": null, "min": null, "period": "monthly", "term": null}, "salary_visible": false, "title_keywords": ["shipping", "assistant"], "responsibilities": ["guidance", "shipping", "procedures", "quality control"], "requirements": {"degrees": ["diploma"], "majors": [], "languages": [], "language_level": [], "hard_skills": [], "soft_skills": [], "languages_combined": []}, "experience_required": {"duration": ["2 year"], "field": ["relevant experience", "quality control"]}}, {"job_id": "100003009038488", "location_code": "hk", "company": "Vita Green Pharmaceutical (H.K.) Limited", "job_title": "Quality Control Assistant", "description": "About the job:\n\nSampling and testing of raw materials and packaging materials.\u00a0\nPerform environmental monitoring tests\u00a0\nPerform instrument calibration and maintenance. \u00a0\nPrepare QC inventory control such as chemicals & working standard receiving and storage.\u00a0\nTo perform any other quality control activities assigned\n\nAbout the talent:\n\nDSE/ F.5 or above in Chemistry / Biology / Pharmaceutical or related discipline\u00a0\nFresh graduates are welcome\u00a0\nImmediate available is highly preferable\u00a0\n\nWhat we offer:\n\nCareer with the market leader in health product sector from Hong Kong\nDynamic working culture with great team spirit\nShuttle to/from Yau Tong, Kowloon Tong, Taipo, Tin Shui Wai, Tuen Mun, Tsuen Wan and Causeway Bay\nRapid growth opportunities for strong performers\nCasual attire at work\n\nInterested parties, please send full resume with last & expected salary and date of available by clicking \u2018Apply Now\u2019\n\nPersonal data collected is for recruitment purpose only. For corporate information, please visit: www.vitagreen.com", "employment_types": ["Full Time", "Permanent"], "selling_points": ["PIC/s GMP manufacturer", "Sampling and testing raw materials and packaging", "Great career opportunity"], "locations": ["Tai Po Area"], "categories": ["Manufacturing", "Quality Assurance, Control & Testing / ISO"], "post_time": "2022-01-11T07:04:56Z", "salary": {"currency": null, "max": null, "min": null, "period": "monthly", "term": null}, "salary_visible": false, "title_keywords": ["assistant"], "responsibilities": ["maintenance", "monitoring", "testing", "inventory control", "quality control"], "requirements": {"degrees": ["dse"], "majors": [], "languages": [], "language_level": [], "hard_skills": ["maintenance"], "soft_skills": [], "languages_combined": []}, "experience_required": {"duration": [], "field": []}}, {"job_id": "100003009045081", "location_code": "hk", "company": "\u9081\u672c\u9999\u6e2f\u91ab\u85e5\u79d1\u6280\u6709\u9650\u516c\u53f8", "job_title": "Validation Supervisor", "description": "Responsibilities\nRequire supervisor level for validation of pharmaceutical manufacturing equipment and controls.\nExperience working directly with manufacturing equipment.\nAbility to author / review / Modify Templates as required.\nAssess impact of process / equipment or procedural changes that can affect the validated state of the equipment.\nMust have an understanding of computer system validation including knowledge of cGMP, GAMP 5 and CFR 21 Part.\nMust have the ability to develop validation protocols (IQ/OQ/PQ), validation reports, and factory acceptance test documents.\nResponsible for supervising, reviewing, writing and execution of validation project and system qualifications, validations, re-qualifications and revalidation of manufacturing facilities, equipment, utilities, and processes.\nExcellent computer skills including knowledge of calibration management and environmental monitoring systems\nStrong problem-solving skills, strong verbal and written\nAble to initiate deviations, be responsible for CAPA investigation and closure as required.\nQualification and Requirements:\n\nBS in Engineering or Science related discipline preferred\nMinimum 4 years\u2019 experience in PIC/s or FDA regulated industry, preferably in a pharmaceutical manufacturing setting.", "employment_types": ["Full Time"], "selling_points": [], "locations": ["Kowloon Bay"], "categories": ["Manufacturing", "Quality Assurance, Control & Testing / ISO"], "post_time": "2022-01-13T07:15:32Z", "salary": {"currency": null, "max": null, "min": null, "period": "monthly", "term": null}, "salary_visible": false, "title_keywords": ["supervisor"], "responsibilities": ["management", "supervising", "review", "monitoring", "systems", "investigation", "develop", "reports"], "requirements": {"degrees": [], "majors": [], "languages": [], "language_level": [], "hard_skills": [], "soft_skills": [], "languages_combined": []}, "experience_required": {"duration": ["minimum 4 years"], "field": ["pharmaceutical", "manufacturing"]}}, {"job_id": "100003009035853", "location_code": "hk", "company": "Automatic Manufacturing Ltd", "job_title": "Quality Senior Manager / Quality Manager", "description": "\u00a0Job Requirements:\n\nMin BSc in Engineering\u00a0and Six Sigma Black Belt\nMin 8 yrs exp in medical devices manufacturing or pharmaceuticals\nExpertise in DFSS excellence, Design V&V, QFD, DOE, Failure Analysis, FMEA\nConversant in ISO-9001 / 13485 / 14971 / NMPA / FDA QSR\nConversant FDA GMP IOPQ\nExperience in CGMP and validation, labview virtual instrumentation and reliability engineering\nFluent communication skills in Mandarin and English\n\n\u00a0Job Description:\n\nManages, leads and mentors Quality Department and personnel\nSite Management Representative - liaison between staff and top management, assure maintenance and effectiveness of quality system and operation, ensure certification remains intact, escort for external audits\nPromotes, mentors and coaches staff for growth\nQA lead in Risk Management activities, including responses to complaints and recalls\nQuality lead in product development team meetings, technical design reviews, and phase gate design review meetings to ensure quality assurance requirements are met.\nIntegral member of new product development teams. Responsible for ensuring compliance during the design control and design transfer process\nRegularly reviews quality system standard operating procedures and work instructions, making changes as necessary to ensure compliant and efficient Quality Assurance processes.\nProvides input to the Management Review and Quality Review Board processes and monitors the Quality Management System (QMS), and provides training throughout the organization\nResponds to identified and potential nonconformities, complaints, deviations, and corrective/preventative actions assigned to Quality Assurance\nParticipates in Audits - internal and external. Responsible for all aspects of regulatory compliance and regulations, and being the key member of Review Boards as per Quality processes\nBachelor degree in Biomedical Engineering, life science or engineering discipline preferred, with minimum 8 years' work experience in a regulated / medical device industry required, and demonstrated knowledge of current industry quality practices under ISO 13485 & ISO 14971\nAbility to provide leadership to others in the organization through influence, innovative practices and coaching skills to foster a corporate culture of responsiveness, compliance awareness, self-regulation, quality system ownership, challenge of status quo, and continuous improvement in order to achieve the highest level of compliance\nExcellent problem solving methodology, using industry accepted concepts and tools to solve complex problems in creative and effective ways as they apply to compliance issues\nThorough knowledge of standards and regulations (cGMP, ISO 13485)\n\n\u00a0We offer 5 day week, attractive remuneration and fast promotion opportunities to aggressive talents. Interested parties please submit your full resume with qualifications, career history, availability, current and expected salary via e-mail to \"APPLY NOW\"", "employment_types": ["Full Time", "Permanent"], "selling_points": ["BSc in Engineering with 6 Sigma Black Belt", "8+yr exp in Medical Devices Mfg ISO13485 &ISO14971", "Exp in CGMP,validation, labview& reliability Engg"], "locations": ["Others - China"], "categories": ["Engineering", "Electrical / Electronics", "Manufacturing", "Production Planning / Control", "Quality Assurance, Control & Testing / ISO"], "post_time": "2022-01-10T08:32:37Z", "salary": {"currency": null, "max": null, "min": null, "period": "monthly", "term": null}, "salary_visible": false, "title_keywords": ["senior manager", "quality manager"], "responsibilities": ["regulations", "management", "control", "maintenance", "review", "quality", "site management", "design", "teams", "compliance", "procedures", "audits", "management review"], "requirements": {"degrees": ["bsc"], "majors": ["engineering"], "languages": ["english", "mandarin"], "language_level": ["fluent"], "hard_skills": ["six sigma", "analysis", "labview"], "soft_skills": ["communication skills"], "languages_combined": [{"language": "english", "language_level": ["fluent"]}, {"language": "mandarin", "language_level": ["fluent"]}]}, "experience_required": {"duration": [], "field": ["engineering"]}}, {"job_id": "100003009046810", "location_code": "hk", "company": "Luxembourg Medicine Co Ltd", "job_title": "QA Assistant", "description": "Responsibility\n\nTo support the routine QA activities, such as GMP training, self-inspection, line clearance, products complaints/returns/recalls, etc.\nTo support and maintain the documentation and quality assurance system of the company, such as standard operating procedures (SOPs) and record keeping system;\nTo provide clerical support for QA Department\nTo perform other tasks as assigned by supervisor\n\nRequirement\n\nHigher Diploma in science related discipline\nMature, well organized, independent, able to work under pressure with good communication and interpersonal skills\nProficiency in MS applications and Chinese word processing\n\nInterested parties please send full resumewith present and expected salary to Human Resources Department by clicking \"APPLY NOW\".\n\n(Information provided will be treated in strict confidence and will only be used for recruitment-related purposes.)", "employment_types": ["Full Time", "Permanent"], "selling_points": ["Provide clerical support for QA department", "Perform other tasks as assigned by supervisor", "Higher Diploma in science related discipline"], "locations": ["Yuen Long"], "categories": ["Manufacturing", "Quality Assurance, Control & Testing / ISO"], "post_time": "2022-01-14T01:16:22Z", "salary": {"currency": null, "max": null, "min": null, "period": "monthly", "term": null}, "salary_visible": false, "title_keywords": ["qa assistant"], "responsibilities": ["provide clerical support", "quality", "procedures", "inspection", "other tasks", "maintain", "sops", "documentation"], "requirements": {"degrees": ["diploma"], "majors": ["science"], "languages": ["chinese"], "language_level": ["proficiency"], "hard_skills": ["chinese word processing", "ms applications"], "soft_skills": ["independent", "well organized", "mature", "communication and interpersonal skills", "work under pressure"], "languages_combined": [{"language": "chinese", "language_level": ["proficiency"]}]}, "experience_required": {"duration": [], "field": []}}, {"job_id": "100003009038026", "location_code": "hk", "company": "Pricerite Home Ltd", "job_title": "Quality Assurance Engineer", "description": "Responsibilities:\n\nImplement quality assurance procedures and ensure full compliance of relevant policies\nImplement QA prevention-based strategies that ensure the highest quality, international regulatory compliance, safety and performance of products at the lowest possible cost\nLiaise with SCM and suppliers in design, development and production to provide quality related parameters\nConduct factory audits and evaluations and make sure all vendors meet international standards and company requirements\nMonitor cost and efficiencies of testing laboratories' services\nDetermine root cause analysis of process and product issues\nAssist in ad hoc projects assigned by supervisor\n\nRequirements:\n\nDegree in Manufacturing/ Quality Management/ Industrial Engineering or related discipline\n1 year quality assurance experience, preferably from Retail industry\nExperience in PRC manufacturing environments is preferable\nGood knowledge in quality standards, and/or consumer products\nAble to communicate effectively with internal parties and vendors on quality related issues\nGood command in spoken and written English and Mandarin\nWe offer attractive remuneration package including\u00a0comprehensive medical insurance scheme, birthday leave, full pay paternity leave, discretionary bonus, education subsidies & leave and job-related training etc.\nPlease apply in confidence with cover letter and full resume, quoting reference to the\u00a0Manager, Human Resources, Pricerite Home Limited,\u00a028/F, Manhattan Place, 23 Wang Tai Road, Kowloon Bay, Hong Kong\u00a0or\u00a0press below \"Apply Now\".\nThe information provided will be used for selection purpose only. All information of unsuccessful applicants will be destroyed within six months.", "employment_types": ["Full Time", "Permanent"], "selling_points": ["QA Experience", "Retail Industry", "Exp. in PRC manufacturing environments"], "locations": ["Kowloon Bay"], "categories": ["Engineering", "Manufacturing & Production", "Others", "Manufacturing", "Quality Assurance, Control & Testing / ISO"], "post_time": "2022-01-11T04:38:38Z", "salary": {"currency": null, "max": null, "min": null, "period": "monthly", "term": null}, "salary_visible": false, "title_keywords": ["engineer"], "responsibilities": ["cost", "policies", "analysis", "compliance", "quality", "procedures", "design", "audits", "monitor", "testing", "ad hoc projects", "liaise with"], "requirements": {"degrees": ["degree"], "majors": ["manufacturing", "engineering", "quality management"], "languages": ["english", "mandarin"], "language_level": ["good command"], "hard_skills": ["prc manufacturing", "scheme"], "soft_skills": ["comprehensive", "confidence"], "languages_combined": [{"language": "english", "language_level": ["good command"]}, {"language": "mandarin", "language_level": ["good command"]}]}, "experience_required": {"duration": ["1 year"], "field": ["retail industry", "manufacturing", "quality assurance"]}}, {"job_id": "100003009040083", "location_code": "hk", "company": "Sainsbury's Argos Asia Limited", "job_title": "Quality Technologist - Home , Home Accessories", "description": "In a nutshell\n\nManage assigned subcategory\u2019s full product life cycle\nDeliver all technical aspects of product development, in line with the Quality management system and Quality policy to ensure the business\u2019 products are fit for purpose and meet customer expectations\nEnsure products meet all quality, legal and safety requirements\nEnsure all responsible products are delivered on time shipments with no quality incidents at destination\nMaintain effective working relationship with related internal and external stakeholders in Asia and UK\n\nWhat I need to do\n\nEnsure suppliers understand Sainsbury's Technical Requirements\nAssist Technical Manager to implement QA/QC strategies to support the business growth\nEnsure technical approvals & timeliness adhere to the Critical Path coordinating hand in hand with UK, Merchandiser & supplier\nWorking closely with internal and external stakeholders to ensure supplier process capability is effective to meet product quality and process requirements\nSupport Merchandising and Compliance with supplier approval process\nManage root cause analysis and corrective action process of supplier quality issues\nPerform on-site supplier visits for root cause analysis and verification of corrective actions of supplier quality issues\nReview and evaluate supplier quality data to identify process improvement opportunities within the supply chain\nReview supplier manufacturing processes, collaborate with suppliers on process improvement and value enhancement opportunities\nEnsure all incidents, escalations and continuous improvements are diligently managed and followed up\nParticipation in buying trips, supplier selection & risk assessment\nDevelop and maintain relationship with external stakeholders including suppliers and third party inspection and testing service providers\n\nHow I will succeed\n\nEnsure product approvals are within Critical path deadline\nEnsure pre-shipment inspection pass rate is within the targets\nEnsure product return rate from consumer is within target\nEnsure technical cost within the agreed budget\n\nWhat I need to know\n\nRelevant manufacturing /engineering degree is preferred\n3-5\u00a0years related QA experience in sourcing, retail, manufacturing or product development environment\nExtensive knowledge of quality systems, ethical audits, testing requirements and manufacturing processes\nExcellent communication skills\nRobust personality able to work under pressure and make balanced decisions\nCompetent in problem solving\nCommercial awareness, experience in dealing with customer and suppliers\nExperience with manufacturing practices in Asia\nProven technical skills within the product area\nFamiliar with UK legislation and requirements\nFluently written and spoken English, Cantonese & Mandarin\nWillingness to travel within Asia\n\nWhat I need to show\n\nWe are trusting each other, working and winning as one team: Builds great working relationships with colleagues\nWe are making it simpler:\u00a0 Identifies opportunities to make the way we work simpler.\nWe are doing the right thing for our customers to grow sales: Looks for ways of improving service in the team and ensures colleagues understand how what they do influences the customer.\nWe are making it happen at pace: Encourages others to deliver results by making decisions and trying new approaches.\nWe are treating every pound as our own: Has a thorough understanding of the business performance and ensures colleagues understand the business impact of their decisions.\nWe are cheering on progress: Recognises when colleagues have made great progress and actively acknowledges this.\nWe offer a competitive package, including a 5 day week, 17 days Annual Leave, double pay, performance bonus,\u00a0MPF, a medical scheme, flexible working environment, plenty of work variety and a great team atmosphere. Interested candidates please go to the website below for application.\n\nDirect apply on our Job Portal to get your CV more visible", "employment_types": ["Full Time"], "selling_points": [], "locations": ["Ngau Tau Kok"], "categories": ["Merchandising & Purchasing", "Procurement / Purchasing / Sourcing", "Manufacturing", "Quality Assurance, Control & Testing / ISO"], "post_time": "2022-01-12T01:16:00Z", "salary": {"currency": null, "max": null, "min": null, "period": "monthly", "term": null}, "salary_visible": false, "title_keywords": [], "responsibilities": ["collaborate with", "data", "budget", "merchandising", "quality", "communication", "maintain", "work under pressure", "compliance", "develop", "testing", "continuous improvements", "management", "cost", "mpf", "review", "inspection", "audits", "third party", "analysis", "systems", "evaluate", "working relationships"], "requirements": {"degrees": ["degree"], "majors": ["manufacturing", "engineering"], "languages": ["cantonese", "english", "mandarin"], "language_level": [], "hard_skills": ["no", "analysis", "scheme", "problem solving", "make"], "soft_skills": ["flexible", "communication skills", "responsible", "competent", "robust", "problem solving", "ethical", "thorough", "technical skills", "extensive", "work under pressure"], "languages_combined": [{"language": "cantonese", "language_level": []}, {"language": "english", "language_level": []}, {"language": "mandarin", "language_level": []}]}, "experience_required": {"duration": ["3-5 years"], "field": ["manufacturing", "qa", "related", "commercial", "product development", "retail"]}}, {"job_id": "100003009046865", "location_code": "hk", "company": "Cloud Light Technology Limited", "job_title": "Director, China Operations (Job Ref. No. Apply-HK-2009-DCO)", "description": "Job Highlights:\n\nThis is a challenging position for a high-calibre, energetic, and experienced personnel to oversee a manufacturing operation in China now with opportunities and potential growth to manage operations in multiple sites globally.\u00a0\n\nJob Responsibilities:\n\nOversee the operations of the manufacturing facilities in Dongguan, China\nManage production, quality control, planning and material control, procurement, supply chain, china customs, human resources and administration functions of the Dongguan facilities\nDevelop strategic operational planning and control, evaluates organizational efficiency, and makes necessary changes to increase and maximize productivity, reduce costs, and increase profit margins\nManage resources, maintain and execute existing operational policies, procedures, plans and systems in all aspects are carried out properly, compliance to established standards and requirements internally, externally, and legally and to develop new if required\nAssess the needs of the facilities and finds ways to contribute to the big picture by ensuring daily operations run smoothly and as efficiently and effectively as possible\nAssist Vice President, Operations in China to monitor operations maintained in South East Asia\nPosition based in Dongguan, China\nReport to Vice President, Operations in China.\n\nRequirement:\n\nBachelor or above, major in manufacturing, industrial engineering, supply chain, or related discipline is preferable;\nOver 10 years of solid relevant working experiences in similar position in managing operations of electronics component manufacturing facilities in China\nExperience in working with R&D team, optical component industry or similar field is an added advantage\nExperience in managing manufacturing operations in other South East Asian countries is an added advantage\nWell organized, detail minded, flexible and adaptable, ability to work independently and multi-tasks\nCommit to the job, strong sense of responsibility, capable of working under pressure and possess good problem-solving skills\nStrong data analytical and presentation skills and logical thinking\nStrong leadership, good team player with positive thinking, good coordination and inter-personal skills\nProficiency in Excel, MS Word, Power Point and Chinese word processing\nGood command of written and spoken English and Putonghua\n\nApplication:\n\nTo apply, please email us\u00a0your resume, your availability to report duty and quote the Job Ref.\nOnly short-listed candidates will be notified. Personal data provided by applicants will be used for consideration of an application only.\n\nApplication Deadline:\n\nUntil this position is filled.\nResumes received will strictly be used for recruitment-related purpose", "employment_types": ["Full Time", "Permanent"], "selling_points": ["Oversee operations of production plant in PRC", "Potential growth to manage sites in SE Asia", "10+ years solid experience in similar position"], "locations": ["Others - China"], "categories": ["Manufacturing", "Product Development / Management", "Production Planning / Control", "Quality Assurance, Control & Testing / ISO"], "post_time": "2022-01-14T01:29:32Z", "salary": {"currency": null, "max": null, "min": null, "period": "monthly", "term": null}, "salary_visible": false, "title_keywords": ["operations", "director"], "responsibilities": ["control", "operations", "policies", "systems", "procedures", "compliance", "monitor", "develop", "daily operations", "planning", "maintain", "quality control", "plans", "report", "costs", "administration"], "requirements": {"degrees": ["bachelor"], "majors": ["manufacturing", "engineering"], "languages": ["putonghua", "english", "chinese"], "language_level": ["proficiency", "good command"], "hard_skills": ["r&d", "excel", "chinese word processing", "power point", "problem-solving skills", "ms word"], "soft_skills": ["flexible", "work independently", "good team player", "under pressure", "capable", "multi-tasks", "sense of responsibility", "adaptable", "well organized", "inter-personal skills", "positive thinking", "presentation skills", "coordination", "problem-solving skills", "leadership"], "languages_combined": [{"language": "putonghua", "language_level": ["good command"]}, {"language": "english", "language_level": ["good command"]}, {"language": "chinese", "language_level": ["proficiency"]}]}, "experience_required": {"duration": ["10 years"], "field": ["manufacturing", "team"]}}, {"job_id": "100003009037827", "location_code": "hk", "company": "Hong Kong Regen Medtech Limited", "job_title": "Quality Assurance Manager", "description": "\u00a0Job Responsibility\n\nResponsible for monitoring of QA Department's daily operations.\nApproval of cleanroom/utilities/equipment DQ/IQ/OQ/PQ protocols and reports, and various validation Protocols and reports.\nPerform initial assessment of Product Quality Review and Management Review Reports and submit to Authorized Person and management.\nBe a key member in conducting self-inspections and external audits.\nProvide coaching and training to QA staff, and advanced training on PIC/S GMP standards.\nApproval of SOPs related to the QA Department.\nPlan and provide practical and compliant solutions in change controls, deviation investigations, OOS investigation, CAPA, quality risk assessments, qualification and validation, supplier evaluations, and continual improvement.\nRaise quality issues to the Authorized Person and management in a timely manner.\nWork with the Authorized Person to develop and monitor quality KPI.\nOther duties as assigned by Authorized Person and/or management team.\n\nQualification and Experience\n\nBachelor's degree or above in biotechnology, biochemistry, chemistry, and medical laboratory science or science degree with relevant to cell therapy, gene therapy, regenerative medicines or tissue engineering, or other similar sciences disciplines;\nAt least 4 years of experience in a quality managerial role in a pharmaceutical GMP environment.\nKnowledge of PIC/S GMP and other quality system/quality assurance principles is highly preferred.\nReceived formal training on Quality Management System e.g. ISO 9001 Internal Auditor is highly preferred.\nWith knowledge and/or experience in GMP operations of sterile pharmaceutical products, biological substances or products, or cell-based products.\nExcellent communication, problem-solving, time management, and prioritization skills.\nSelf-motivated and a good team player, attention to detail.\nProficiency in English and Chinese.\n\nWe offer an attractive remuneration package including group medical insurance, discretionary year-end performance bonus, and an energetic, fun work environment.\n\nInterested parties please send your resume with current, expected salary and availability to the HR Department.\n\n(All personal data provided will be treated in strict confidence and be used for recruitment purposes.)", "employment_types": ["Full Time"], "selling_points": [], "locations": ["Shatin Area"], "categories": ["Medical Services", "Pharmaceutical", "Manufacturing", "Quality Assurance, Control & Testing / ISO"], "post_time": "2022-01-11T03:59:25Z", "salary": {"currency": null, "max": null, "min": null, "period": "monthly", "term": null}, "salary_visible": false, "title_keywords": ["manager"], "responsibilities": ["operations", "quality", "communication", "plan", "management review", "management team", "other duties", "monitor", "develop", "reports", "management", "review", "monitoring", "investigation", "daily operations", "sops", "audits", "year-end", "a timely manner", "insurance"], "requirements": {"degrees": ["degree", "degree or above", "bachelor"], "majors": ["science", "chemistry", "engineering", "medical laboratory science"], "languages": ["english", "chinese"], "language_level": ["proficiency"], "hard_skills": ["problem-solving", "fun"], "soft_skills": ["self-motivated", "good team player", "advanced", "responsible", "problem-solving", "timely", "communication", "energetic", "attention to detail", "time management"], "languages_combined": [{"language": "english", "language_level": ["proficiency"]}, {"language": "chinese", "language_level": ["proficiency"]}]}, "experience_required": {"duration": ["at least 4 years"], "field": ["pharmaceutical", "managerial"]}}, {"job_id": "100003009039774", "location_code": "hk", "company": "A.S. Watson Retail (HK) Limited", "job_title": "Quality Assurance Engineer - International Buying", "description": "Come and join a Winning Team\n\nWe are Awesome!\n\nWhy Should You Join Us?\n\nAt ASW, we believe in our people, in teamwork and the importance of your personal growth.\u00a0If you are looking for the opportunity to join our award-winning international family with 15,000+ stores across 25 markets in Asia and Europe, the ASW family welcomes you\u2026\u00a0 #BePartofMORE\n\nYou can enjoy:\n\nCompetitive compensation and benefits!\nComprehensive Medical and Life insurance coverage, including your spouse and children!\nFive-day work, plus casual wear every Friday, TGIF!\nProfessional training and career advancement opportunities!\nAttractive ACCA and CPA Australia Recognized Employer Partnership for F&A talents!\nExclusive company pension schemes for our people!\nMarriage, Maternity and Paternity Leave!\nConvenient office location, less than 5 min. walk from MTR!\nExclusive shopping discount!\nContemporary workplace, free drinks and chill out areas!\nWell-equipped Gym inside our office building!\nFitness and interest class packages!\nOnsite Clinic and Lactation Room!\nFree round-trip lunchtime shuttle bus services to Shatin!\nExclusive Bazaar Sales for our people only!\n\nRole Purpose:\nAs Quality Assurance Engineer\u00a0, you will be responsible for\u00a0mitigating risks associated with suppliers and products developed by Watsons International team and ASW International Buying team.\n\n\u00a0A typical day in this Role:\u00a0\n\n\nChecking cosmetic ingredients compliance against markets legislation and ASW Group QA Restricted Ingredients List\nDesigning product testing protocol to ensure the product safety, function & regulatory compliance.\nReviewing test reports, product specification and labels\nReviewing factory audit report and following up on any remediation plan\nApproving product evaluations and inspection controls ; Compiling product technical files; Maintaining the product library and database.\u00a0\n\nThis job is a good fit for You if:\u00a0\n\nYou are keen to join retail industry and have rich QA experience\nYou are self-motivated and able to work independently under pressures\nYou are a good team player\n\n\u00a0What we look for:\n\nDegree\u00a0 holder in Chemistry, Biochemistry/ Biology/ Cosmetic Science or related disciplines\nMinimum 2 years work experience in an accredited laboratory or in Cosmetic Industry. Fresh graduates will also be considered.\nWith good knowledge of cosmetic product requirement for EU, ASEAN ad CN markets\nA good communicator in both spoken and written English and Chinese, including Mandarin\nWith high proficiency in MS Office including Excel, Word and Outlook\n\nWhat is holding you back?\u00a0\n\nDon\u2019t miss out on this great chance to shape Your life!\u00a0\n\nApply now!\n\nInterested parties please e-mail your full resume in WORD FORMAT with expected salary to our company email (shown in our Company Profile).\n\n\nWe are an equal opportunity employer and welcome applications from all qualified candidates. The information provided will be treated in strict confidence and be used only for consideration of your application for relevant / similar posts within the A.S. Watson Group.\n\n\nApplicants not hearing from us within 6 weeks from the date of advertisement may consider their applications unsuccessful. All personal data of unsuccessful applicants will be destroyed within 12 months from the date of application.\u00a0", "employment_types": ["Full Time", "Permanent"], "selling_points": ["Quality Assurance for sourcing office", "Review testing lab reports", "Designing product testing protocol"], "locations": ["Shatin Area"], "categories": ["Merchandising & Purchasing", "Procurement / Purchasing / Sourcing", "Manufacturing", "Quality Assurance, Control & Testing / ISO"], "post_time": "2022-01-11T11:07:28Z", "salary": {"currency": null, "max": null, "min": null, "period": "monthly", "term": null}, "salary_visible": false, "title_keywords": ["engineer"], "responsibilities": [], "requirements": {"degrees": [], "majors": [], "languages": [], "language_level": [], "hard_skills": [], "soft_skills": ["teamwork"], "languages_combined": []}, "experience_required": {"duration": [], "field": []}}, {"job_id": "100003009038292", "location_code": "hk", "company": "Vita Green Pharmaceutical (H.K.) Limited", "job_title": "Senior Quality Assurance Officer", "description": "Key Highlights:\n\n\nPIC/s GMP manufacturer\nWork-life balance culture\nGreat career opportunity\n\n\nAbout the job:\n\nParticipate in quality systems processes including deviation control, change control, document control, internal and external audits and training programs\n\nCommunicate with other departments to improve quality systems processes.\n\nProvide training to the other departmental staff.\nPerform other duties assigned by the supervisor(s).\n\nAbout the talent:\n\nBachelor degree or above inScience subjects, preferably in Pharmaceutical Science, Chinese Medicine, Biotechnology, Biochemistry.\nAt least 3 years hands-on GMP experience in the pharmaceutical industry is highly preferable.\nPositive mindset, able to be a good team player.\nGood command of English and Chinese, both spoken and written.\n\nWhat we offer:\n\nCareer with Hong Kong market leader in health products.\nDynamic working culture and great team spirit.\nShuttle to/from Yau Tong, Kowloon Tong, Taiwan, Taipo, Tsuen Wan, Tuen Mun, Tin Shui Wai and Causeway Bay.\n\nRapid growth opportunities for strong performers.\nCasual attire at work.\n\nInterested parties, please send full resume with last & expected salary and date of available by clicking \u2018Apply Now\u2019\n\nPersonal data collected is for recruitment purpose only. For corporate information, please visit: www.vitagreen.com", "employment_types": ["Full Time", "Permanent"], "selling_points": ["PIC/s GMP pharmaceutical manufacturer", "Quality Assurance", "Quality Management System"], "locations": ["Tai Po Area"], "categories": ["Manufacturing", "Quality Assurance, Control & Testing / ISO"], "post_time": "2022-01-11T06:26:38Z", "salary": {"currency": null, "max": null, "min": null, "period": "monthly", "term": null}, "salary_visible": false, "title_keywords": ["senior quality assurance officer"], "responsibilities": ["communicate with", "provide training", "control", "perform other duties", "systems", "quality", "internal and external audits"], "requirements": {"degrees": ["degree or above", "bachelor"], "majors": ["science"], "languages": ["english", "chinese"], "language_level": ["good command"], "hard_skills": [], "soft_skills": ["good team player", "hands-on", "positive mindset"], "languages_combined": [{"language": "english", "language_level": ["good command"]}, {"language": "chinese", "language_level": ["good command"]}]}, "experience_required": {"duration": ["at least 3 years"], "field": ["pharmaceutical"]}}, {"job_id": "100003009033862", "location_code": "hk", "company": "Koon Chun Hing Kee Soy & Sauce Factory Limited", "job_title": "Head of Quality Assurance (QA)", "description": "- Double pay + bonus\n- 5 work days per week; 8:00am to 6:00pm (1 hour lunch time included)\n- Work location: Yuen Long, NT\n- 14 days annual leave + Hong Kong statutory holidays\n\nJob Description:\n- Manage and lead Quality Assurance (QA) department\n- Communicate professionally and work with different departments\n- Monitor operation performance and supply quality\n- Implement and ensure products and factory comply to meet local and international quality specifications, policies, and government regulations, including but not limited to food labels, nutritional tables, HACCP, ISO22000, and HALAL\n- Conduct trouble-shooting activities in a food factory setting\n- Implement and monitor corrective and preventive actions on quality-related issues\n- Provide technical support on production issues and ensure the final product are safe and meet the required standards\n- Maintain and improve product quality, procedures, specifications, food safety, and quality training\n-\u00a0Prepare team for local and international audit and inspections\n- Indoors and outdoors work setting\n\nRequirements:\n- Degree in Food Science or related disciplines\n- Work experience in the food industry\n- Management experience\n- In-depth knowledge of food safety/quality system such as HACCP, ISO22000, GMP, etc.\n- Good analytical, communication, and leadership skills with various levels on project/team management\n- Fluent in written and spoken Cantonese and English\n- Good knowledge of office computer apps (Excel, Word, etc.)\n- work experience in a food factory setting is advantageous\n\nInterested parties please send full resume with current and expected salary to us.\n\n\n\n\n", "employment_types": ["Full Time"], "selling_points": [], "locations": ["Yuen Long"], "categories": ["Hospitality / F & B", "Food & Beverage", "Sciences, Lab, R&D", "Food Science", "Manufacturing", "Quality Assurance, Control & Testing / ISO"], "post_time": "2022-01-10T01:59:00Z", "salary": {"currency": null, "max": null, "min": null, "period": "monthly", "term": null}, "salary_visible": false, "title_keywords": [], "responsibilities": [], "requirements": {"degrees": [], "majors": [], "languages": [], "language_level": [], "hard_skills": [], "soft_skills": [], "languages_combined": []}, "experience_required": {"duration": [], "field": []}}, {"job_id": "100003009039137", "location_code": "hk", "company": "Nine United China Limited", "job_title": "QA Assistant", "description": "Job Description\n\nassist and report to Lighting QA\nsupport the lighting team on product quality issues and quality documentations\nco-ordinate and follow-up product testings & certifications with 3rd party test labs / suppliers / customers to ensure all the customer requirements and timeline can be fulfilled\nmonitor the internal database of test reports & certifications\nassist for the new lighting directive & lighting test standard update process\nreview & comment the sample with development team during R&D process\nprepare quality manual for inspection check\ngolden sample / test sample checking, send to customer / 3rd party test lab\n\n\u00a0Requirements\n\nworking experience related to Product Quality / Lab Engineer / Technician of 1 year or more; experience in Lighting is an advantage\nbasic electronic and electricity knowledge\nknowledge of lighting EU directive / regulation is advantage\nreliable and proactive working attitude\ngood communication and presentation skills\nwilling to learn and deal with China factories & Oversea customer\nfluent in English, Mandarin, Cantonese", "employment_types": ["Full Time"], "selling_points": [], "locations": ["Tsim Sha Tsui"], "categories": ["Engineering", "Electrical / Electronics", "Manufacturing", "Quality Assurance, Control & Testing / ISO"], "post_time": "2022-01-11T08:49:09Z", "salary": {"currency": null, "max": null, "min": null, "period": "monthly", "term": null}, "salary_visible": false, "title_keywords": ["qa assistant"], "responsibilities": ["review", "monitor", "quality", "checking", "inspection", "reports", "database", "report"], "requirements": {"degrees": [], "majors": [], "languages": ["cantonese", "english", "mandarin"], "language_level": ["fluent"], "hard_skills": ["basic"], "soft_skills": ["proactive", "willing to learn", "communication", "presentation skills", "reliable"], "languages_combined": [{"language": "cantonese", "language_level": []}, {"language": "english", "language_level": ["fluent"]}, {"language": "mandarin", "language_level": ["fluent"]}]}, "experience_required": {"duration": ["of 1 year"], "field": ["related"]}}, {"job_id": "100003009046591", "location_code": "hk", "company": "Nestle Hong Kong Ltd", "job_title": "Laboratory Technician", "description": "Position Summary\n\n\nWorking Location: Yuen Long Industrial Estate\n\nDuty Pattern: 8:00am - 4:30pm or 11:00am - 7:30pm\n(5.5 days per week, alternative Saturday)\n\u00a0\u00a0Responsibilities:\n\nSampling and testing food and beverage raw materials and finished products\nAnalyze test data, verify results and prepare reports\nSAP system preparation work\nParcel packing, agar preparation and material purchasing\nConduct equipment maintenance and calibration\nMonitor factory environment and hygiene conditions\n\n\u00a0\u00a0Requirements:\u00a0\n\nHigher Diploma or above in Food Technology, Food Science, Chemistry, Biology or Biochemistry\nGood analytical and organizational skills\nGood communication skills in both written and spoken English and Chinese\nFresh graduates are also considered\n\nPlease submit\u00a0 application with your resume stating the employment history, present and expected salary by clicking \"Apply Now\".\n\nWe, at all levels, are strongly committed to the Company, its development and its culture. We practice what we preach and give great importance to training and development of people. We offer excellent career development opportunities, attractive remuneration package, comprehensive fringe benefits and wellness programs to the right candidates\n\nWe are an equal opportunity employer and committed to workforce diversity with opportunity for continuous development and growth to all employees.\n\n(All information will be treated in strict confidence and will be used exclusively for recruitment related purpose only. Information of unsuccessful applicants will be destroyed upon completion of the recruitment process.)", "employment_types": ["Full Time", "Permanent"], "selling_points": ["Great opportunity in FMCG/F&B", "World No.1 F&B company with collaborative culture", "Laboratory Testing"], "locations": ["Yuen Long"], "categories": ["Sciences, Lab, R&D", "Food Science", "Laboratory", "Manufacturing", "Quality Assurance, Control & Testing / ISO"], "post_time": "2022-01-13T15:29:27Z", "salary": {"currency": null, "max": null, "min": null, "period": "monthly", "term": null}, "salary_visible": false, "title_keywords": ["laboratory technician"], "responsibilities": ["maintenance", "data", "monitor", "testing", "hygiene", "prepare reports"], "requirements": {"degrees": ["higher diploma or above"], "majors": ["biology", "chemistry", "food science"], "languages": ["english", "chinese"], "language_level": ["good"], "hard_skills": [], "soft_skills": ["communication skills", "organizational skills", "confidence", "committed", "comprehensive"], "languages_combined": [{"language": "english", "language_level": ["good"]}, {"language": "chinese", "language_level": ["good"]}]}, "experience_required": {"duration": [], "field": []}}]