[{"job_id": "100003009053585", "location_code": "hk", "company": "OSMA Consulting Limited", "job_title": "Analyst \u5206\u6790\u5e08", "description": "Our client is an innovation and technology focus venture capital fund partnership with reputable universities in Hong Kong, the founder belongs a reputable local family office. They are currently looking for qualified individual to join the team assisting deal execution and fund operation.\u00a0\n\n\n\nResponsibilities:\nPerform fundamental, in-depth industry research analysis (TMT, Fin-tech);\n\nResearch involves spreadsheet modeling, interviewing management teams and extensive research with potential target companies;\nAssist senior members to perform DD and execution on potential deals;\nAssist in maintaining relations with existing LPs and pitching for new LPs;\nLiaise with councils and fund admin to monitor the fund operation.\n\n\u00a0Requirements:\n\nDegree or above;\nWork with passion, critical thinking and creativity;\nCFA/CPA is a plus\nCommand of Bloomberg or Wind is a plus\nHigh integrity, good communication skill", "employment_types": ["Full Time"], "selling_points": ["Venture capital", "Excellent deal exposure", "Attractive package"], "locations": ["Central"], "categories": ["Banking / Finance", "Analyst", "Financial Services", "Professional Services", "Business Analysis / Data Analysis"], "post_time": "2022-01-17T07:14:55Z", "salary": {"currency": null, "max": null, "min": null, "period": "monthly", "term": null}, "salary_visible": false, "title_keywords": ["analyst"], "responsibilities": ["management teams", "maintaining", "monitor", "liaise with", "research analysis"], "requirements": {"degrees": ["degree or above"], "majors": [], "languages": [], "language_level": [], "hard_skills": ["cfa", "plus", "bloomberg", "cpa"], "soft_skills": ["communication skill", "integrity"], "languages_combined": []}, "experience_required": {"duration": [], "field": []}}, {"job_id": "100003009054833", "location_code": "hk", "company": "Hong Kong Disneyland", "job_title": "Senior Analyst, Workforce Planning", "description": "OverviewOur client, a fast growing company in professional networking industry is looking for a Native Japanese speaking Research assocaite\n\nCompany Location:Central\n\nWorking Days:Mon-Fri\u00a0\n\nCompany Business: Professional networking\n\n\nLanguages Required:\u00a0English Japanese\n\nJOB DUTIES\n\nResearching industries in order to identify the most relevant individuals (C-level executives and practitioners working at the heart of their industries in Japan) to take part in conference calls / moderated interviews\nEngaging these individuals to participate in the interview, while assessing and ensuring that their insights are relevant and their fees are within budget\nDeveloping relationships with existing\u00a0contacts and build new ones with experts you have identified\u00a0\nWorking to tight deadlines alongside other members of the Forum team\n\nREQUIREMENTS\n\nInterest in financial markets, alternative investments and the public equity investment process\nExcellent communication skills and the ability to confidently interact with C-level industry experts on the phone\nDemonstrable skill in carrying out phone-based and desktop research with a logical and focused approach\nSelf-motivated; a resourceful nature, with a diligent and proactive approach to their work\nThe ability to work well within a team, in a fast-paced environment and under pressure. Positive and can-do attitude are essential\nFluent in spoken and written English and Japanese\nBachelor degree or above with strong academic record\nPrior work experience (0-2 years) is an advantage but not required; the level of experience may vary, but what matters is your curiosity, drive and ambition\u00a0\n\nPACKAGE\n\nCompetitive salary\nMedical insurance\nStudy support\n15 days annual leave (increasing with tenure)\u00a0\n2 days\u2019 off per year for community/corporate responsibility activity1) Expected salary\n\n2) Current and last drawn salaries\n3) Reason for leaving current and past employments\n\u00a0\ndirectly to:\u00a0jac.hk\u00a0@jac-recruitment.com and CC to:\u00a0daniel.ng\u00a0@jac-recruitment.com\n\n\u00a0\nPersonal data collected will be used for employment-related purpose only. We regret to inform that only shortlisted candidates will be notified, thank you", "employment_types": ["Full Time"], "selling_points": ["Develop & drive creative solutions for anticipate", "Bachelor Degree on a subject w/ strong analytical", "3-5 years of work experience in resources planning"], "locations": ["Lantau Island"], "categories": ["Admin & HR", "Others", "Banking / Finance", "Analyst", "Financial Services"], "post_time": "2022-01-17T11:27:39Z", "salary": {"currency": null, "max": null, "min": null, "period": "monthly", "term": null}, "salary_visible": false, "title_keywords": ["senior analyst"], "responsibilities": ["budget", "developing"], "requirements": {"degrees": ["degree or above", "bachelor"], "majors": [], "languages": ["japanese", "english"], "language_level": ["fluent"], "hard_skills": ["inform", "c", "reason"], "soft_skills": ["communication skills", "self-motivated", "under pressure", "resourceful", "focused", "fast-paced environment", "can-do attitude", "diligent", "proactive", "positive"], "languages_combined": [{"language": "japanese", "language_level": ["fluent"]}, {"language": "english", "language_level": ["fluent"]}]}, "experience_required": {"duration": ["0-2 years"], "field": []}}, {"job_id": "100003009045873", "location_code": "hk", "company": "Yue Xiu Securities Holdings Limited", "job_title": "Research Analyst , Consumer sector", "description": "OVERVIEW\nOur client is looking for a Logistics Manager for our client to work in Supply Chain & Operations team Main duties would include monitoring, improving the logistics workflows, driving projects, communicate with different parties including global customers, 3PLs, suppliers and our internal multi-functional teams. This role will be reporting to Supply Chain Director.\n\nJob Highlights\n>10 years working experience\nIn-house logistics experience preferred\n\nJOB RESPONSIBILITIES\nLead daily operational, ensure smooth order fulfilment, logistics planning, sales & purchase order creation, invoicing and import/export handling.\nOversees logistics workflows, cost improvements and benchmarking, lead a team in shipment planning & execution, import/export procedures & documentation,\u00a0\nManage and liaise with 3PLs\u00a0\nConstantly review existing workflows and provide improvement recommendations to enhance efficiency\n\nJOB REQUIREMENTS\nDegree holder, preferably in Business Administration, Supply Chain, Merchandising or related disciplines\n>10 years working experience in logistics sector, covering shipment planning & execution, as well as hands-on 3PLs management is preferable\nLead with strong sense of responsibility and ownership\nFluent command of spoken and written English, Cantonese and Mandarin is a MUST\nExcellent command of computer literacy in Word, Excel and PowerPoint\nA good team player, pro-active and with a mature mindset, outgoing, and self-motivated\nPositive, Confident and Smart\nImmediate availability is preferred\nPersonal data collected will be used for employment-related purpose only.\u00a0We\u00a0regret to inform that only shortlisted candidates will be notified, thank you.\n#LI-JACHK\n#countryhongkong", "employment_types": ["Full Time", "Part Time", "Permanent"], "selling_points": ["Investment and market reports,Consumer Sector", "1-2 years of research experience", "Bachelor degree or above"], "locations": ["Wan Chai"], "categories": ["Banking / Finance", "Analyst", "Financial Services", "Equities / Capital Markets"], "post_time": "2022-01-13T08:59:35Z", "salary": {"currency": null, "max": null, "min": null, "period": "monthly", "term": null}, "salary_visible": false, "title_keywords": ["research analyst"], "responsibilities": ["cost", "review", "procedures", "invoicing", "lead a team", "purchase", "liaise with", "logistics", "documentation", "planning"], "requirements": {"degrees": ["degree holder"], "majors": ["related disciplines", "business administration"], "languages": ["cantonese", "english", "mandarin"], "language_level": ["fluent"], "hard_skills": ["excel", "inform", "word", "powerpoint"], "soft_skills": ["outgoing", "confident", "good team player", "self-motivated", "sense of responsibility", "mature", "computer literacy", "hands-on", "pro-active", "positive"], "languages_combined": [{"language": "cantonese", "language_level": ["fluent"]}, {"language": "english", "language_level": ["fluent"]}, {"language": "mandarin", "language_level": ["fluent"]}]}, "experience_required": {"duration": ["10 years"], "field": ["management", "logistics", "planning"]}}, {"job_id": "100003009051276", "location_code": "hk", "company": "ZIM Integrated Shipping Services Ltd", "job_title": "Financial Analyst (BU)", "description": "Our client, a\u00a0Online Game company is looking for candidates\u00a0Japan Customer Support Team Leader.\n\nResponsibilities:\n\n\n\nEnsure that more complex customer issues are followed up and resolved\u3000in a timely manner / provide first line escalation support\nFacilitate resolutions to customer queries and issues brought forward while actively striving to achieve a \u201cone correct answer\u201d across all channels\nConduct induction training for new joiners in an informative and motivational fashion\nKeep induction training material / modules updated\nShow innovation by constantly improving the training program and tailoring it to the needs of the company and new joiners\nBe the first point of contact for the Customer Care Agent\nContribute to the ongoing improvement of the Customer Care team\u2019s performance\nPartake in the hiring process of new Customer Care Agents\nPartake in the development and quality of the Customer Care Agents\nActively pursuit and sharing of customer knowledge\nSupport and leverage our Customer Care infrastructure\nPartake in the planning of customer engagement initiatives\nImplement everyday improvement\nParticipate in quarterly assessments whereby various projects will be discussed and assigned\n\nRequirements:\n\n\n\nNative level of Japanese, fluent English\nStrong leadership skill\nStrong communication and interpersonal skills\n\n\u00a0Interested candidates, kindly send your detailed resume in MS Word including:\n\n\n1) Expected salary\n2) Current and last drawn salaries\n3) Reason for leaving current and past employments\n\u00a0\ndirectly to:\u00a0jac.hk\u00a0@jac-recruitment.com and CC to:\u00a0akihisa.watanabe\u00a0@jac-recruitment.com\n\nPersonal data collected will be used for employment-related purpose only. We regret to inform that only shortlisted candidates will be notified, thank you", "employment_types": ["Full Time", "Permanent"], "selling_points": ["Financial planning and analysis", "Ocean freight", "Work from home arrangement"], "locations": ["Kwun Tong"], "categories": ["Banking / Finance", "Analyst", "Corporate Finance"], "post_time": "2022-01-15T07:03:20Z", "salary": {"currency": null, "max": null, "min": null, "period": "monthly", "term": null}, "salary_visible": false, "title_keywords": ["financial analyst"], "responsibilities": ["infrastructure", "a timely manner", "quality", "contact", "customer queries", "customer issues", "planning"], "requirements": {"degrees": [], "majors": [], "languages": ["japanese", "english"], "language_level": ["native", "fluent"], "hard_skills": [], "soft_skills": ["leadership skill", "communication and interpersonal skills"], "languages_combined": [{"language": "japanese", "language_level": ["native"]}, {"language": "english", "language_level": ["fluent", "native"]}]}, "experience_required": {"duration": [], "field": []}}, {"job_id": "100003009052495", "location_code": "hk", "company": "China Development Bank Hong Kong Branch", "job_title": "Treasury Associate (Money Markets)   \u8cc7\u91d1\u4ea4\u6613", "description": "OverviewOur client, a prestigious Japanese bank, is looking for a\u00a0Analyst (Business Planning) - Global Markets Division for Asia\n\nCompany Location:Central\n\nWorking Days:Mon-Fri (9:00 am ~5:30pm)\n\nCompany Business:Japanese Bank\n\nLanguages Required:Cantonese, English, Mandarin, Japanese\n\nJOB DUTIES\n\nResponsible for coordinating and managing the day-to-day running of Global Markets business area, which may include budgeting, forecasting and review of internal control process.\nSupport the Planning Head on the development of business strategies, business promotion planning, operational efficiency improvement and implementation of regional projects for Global Markets Division for Asia;\nPartner with key stakeholders with overseas branches and Head Office to support in developing Global Markets business strategies;\nEnsure full compliance with the prevailing regulations showing examples of ethical behaviour and following all internal controls for the Team;\nSupport in developing and updating policies to ensure alignment with all relevant regulations;\n\nREQUIREMENTS\n\nUniversity graduate\nWith 1 to 3 years\u2019 relevant experience in banking or financial institutions is preferable\nGood command of written and spoken Japanese and English\n\nPACKAGE\n\nDiscretionary bonus\nMedical insurance\nBirthday leave\nWork from Home Policy\nExamination Leave\nVolunteer Leave\nPaid Sick Leave\nFlexible working Hour\nBonus\n\n1) Expected salary\n2) Current and last drawn salaries\n3) Reason for leaving current and past employments\n\u00a0\ndirectly to:\u00a0jac.hk\u00a0@jac-recruitment.com and CC to:\u00a0daniel.ng\u00a0@jac-recruitment.com\n\n\u00a0\nPersonal data collected will be used for employment-related purpose only. We regret to inform that only shortlisted candidates will be notified, thank you", "employment_types": ["Full Time", "Permanent"], "selling_points": ["Bachelor degree", "Minimum  3-5 years money market experience", "Suite 3307-3315, One IFC, No.1 Harbour View Street"], "locations": ["Central"], "categories": ["Banking / Finance", "Analyst", "Treasury", "Equities / Capital Markets"], "post_time": "2022-01-17T03:55:38Z", "salary": {"currency": null, "max": null, "min": null, "period": "monthly", "term": null}, "salary_visible": false, "title_keywords": ["associate"], "responsibilities": ["regulations", "budgeting", "policies", "review", "compliance", "implementation", "developing", "forecasting", "internal control", "planning"], "requirements": {"degrees": ["university graduate"], "majors": [], "languages": ["japanese", "english"], "language_level": ["good command"], "hard_skills": ["inform", "reason"], "soft_skills": ["flexible"], "languages_combined": [{"language": "japanese", "language_level": ["good command"]}, {"language": "english", "language_level": ["good command"]}]}, "experience_required": {"duration": ["1 to 3 years"], "field": ["financial institutions", "relevant experience", "banking"]}}, {"job_id": "100003009045929", "location_code": "hk", "company": "Wang On Financial Services Management Limited", "job_title": "Junior Investment / Research Analyst", "description": "Our client is a fast growing foreign bank. They are looking for someone to join as a\u00a0SRM / Team Head, Commercial Banking.\u00a0\n\nKey Responsibilities\n\n- Expand existing client portfolio and on-board new clients (client turnover size ranges from HKD500m to over HKD 12b)\n\n-\u00a0Work with / Lead a team to achieve profitable growth, identify risk, and opportunities\n\n-\u00a0Promote Commercial Banking products e.g. deposits (CASA ), trade/ working capital finance, factoring, supply chain financing, equipment finance, DCM, treasury products.\n\n-\u00a0Work closely with PRC Banking Branches to strategize business plans.\n\n-\u00a0Prepare banking facilities and credit proposal\n\n\n\n\nRequirements\n\n- Around 6-12 years (SRM) and over 10 years (Team Head) experience in commercial banking (mid-caps and large SMEs) with good deal records.\n\n-\u00a0Licensing Requirements: HKMA Type 1 & 4 is mandatory; HKFI (preferable)\n\n-\u00a0Fluent in English, Cantonese and Mandarin\n\n\n*We offer*\n\n\"Interested candidates, please send an updated CV to kelvin.lam @jac-recruitment.com and CC jac.hk @jac-recruitment.com\"\n\nPersonal data collected will be used for employment-related purpose only. We regret to inform that only shortlisted candidates will be notified.", "employment_types": ["Full Time", "Permanent"], "selling_points": [], "locations": ["Sheung Wan"], "categories": ["Banking / Finance", "Analyst", "Investment"], "post_time": "2022-01-13T09:10:28Z", "salary": {"currency": null, "max": null, "min": null, "period": "monthly", "term": null}, "salary_visible": false, "title_keywords": ["research analyst", "junior"], "responsibilities": ["lead a team", "business plans", "banking"], "requirements": {"degrees": [], "majors": [], "languages": ["cantonese", "english", "mandarin"], "language_level": ["fluent"], "hard_skills": ["hkma"], "soft_skills": [], "languages_combined": [{"language": "cantonese", "language_level": ["fluent"]}, {"language": "english", "language_level": ["fluent"]}, {"language": "mandarin", "language_level": ["fluent"]}]}, "experience_required": {"duration": ["6-12 years", "10 years"], "field": ["commercial", "banking", "team"]}}, {"job_id": "100003009039060", "location_code": "hk", "company": "The Hong Kong Jockey Club", "job_title": "Security Operations Support Manager", "description": "Our client, a\u00a0Online Game company is looking for candidates\u00a0Head of Japan VIP.\u00a0\n\n\n\nStrategy Execution:\n\nResponsible for developing, executing, and continuously improving the complete VIP strategy for the Japanese market. This plan needs to incorporate elements of all the areas listed below and to be achieved by liaising with senior stakeholders and the relevant teams of each:\n\nTranslate Commercial objectives into VIP Goals & KPI target setting\nConnect the VIP program across brands and setup a cohesive service & offering guideline\nAchieve and report on the overall performance of the VIP Team\nWork with other teams across the company to ensure alignment of respective strategies & implementation (Communications, Rewards, Product, Sustainability) and a seamless VIP enablement\u00a0\nDevelop VIP models to optimize the players performance, compensation & satisfaction\n\nOperational:\n\nOwnership of the VIP budget, target, and bonus costs\nCommunication - Coordinate with the VIP Team to handle any inquiries from the VIP players\nRelationship building with the VIP Players, both online and offline\nTake actions to secure excellent service level\nMonitor VIP players performance and report to senior stakeholders accordingly\nImprove the player profiling system & integrate results into the team\u2019s operational activities\nResponsible for the managed accounts pool including the addition/removal of managed accounts as per set criteria and to consistently report on and profile the players included\n\nTeam Management:\n\nManage & develop the VIP Team Specialists\nSupport team in maintaining relationships with the VIP players\nManage and resolve any VIP escalations from the team\nMaintain and explain VIP dashboards and reports\nDevelop and execute training programs for all new starters and Customer Service\n\nRequirements:\n\nMust:\n\n\nNative level Japanese, fluent English\nBachelor or higher educational degree\nAnalytical and detailed oriented\nSales driven\n2-3 years managerial experience\nAmbitious, goals-oriented, organized, proactive, communicative, big-picture view\n\nPreferred:\n\n2-3 years of Account Management experience\n2-3 years Customer Support experience\nInternational experience and mindset\nGood Excel & PPT skills\nSolid understanding of the psychology behind consumer behavior\n\n\u00a0Interested candidates, kindly send your detailed resume in MS Word including:\n\n1) Expected salary\n2) Current and last drawn salaries\n3) Reason for leaving current and past employments\n\u00a0\ndirectly to:\u00a0jac.hk\u00a0@jac-recruitment.com and CC to:\u00a0akihisa.watanabe\u00a0@jac-recruitment.com\n\nPersonal data collected will be used for employment-related purpose only. We regret to inform that only shortlisted candidates will be notified, thank you", "employment_types": ["Full Time"], "selling_points": ["Fluency in both English and Cantonese", "minimum of 5 years of leadership experience", "University degree or above in security management"], "locations": ["Shatin Area"], "categories": ["Banking / Finance", "Analyst", "Professional Services", "Legal & Compliance", "Others", "Security / Safety Control"], "post_time": "2022-01-17T09:42:04Z", "salary": {"currency": null, "max": null, "min": null, "period": null, "term": null}, "salary_visible": false, "title_keywords": ["operations", "manager"], "responsibilities": ["budget", "communication", "maintain", "customer service", "plan", "costs", "maintaining", "teams", "liaising with", "developing", "implementation", "develop", "monitor", "reports", "setup", "report", "management", "coordinate with", "executing"], "requirements": {"degrees": ["degree", "bachelor"], "majors": [], "languages": ["japanese", "english"], "language_level": ["native", "fluent"], "hard_skills": ["excel"], "soft_skills": ["organized", "detailed oriented", "responsible", "cohesive", "communication", "customer service", "proactive", "driven"], "languages_combined": [{"language": "japanese", "language_level": ["native"]}, {"language": "english", "language_level": ["fluent"]}]}, "experience_required": {"duration": ["2-3 years"], "field": ["managerial", "account management"]}}, {"job_id": "100003009051026", "location_code": "hk", "company": "The Wharf Group", "job_title": "Assistant Investment Research Officer", "description": "Our client is a top tier foreign bank. They are looking for someone to join as a\u00a0Team Head - Trade & Supply Chain Finance - Trade Finance Department\n\nKey Responsibilities\n\n- Manage Financial Institution clients for the Trade & Supply Chain Finance Team.\n\n- Lead and guide junior teammates to expand and maintain current trade and receivable finance portfolio of Chinese, APAC, and Western MNCs clients\n\n- Promote cross-regional collaboration and cross-selling of other bank products with strong focus in Greater China Region\n\n- Responsible for the credit quality\n\nRequirements\n\n- University Degree Holder in Business, Economics or related disciplines\n\n- Minimum of 10 years\u2019 relevant experience in trade finance with a preference with regional Trade Supply Chain Finance experience.\u00a0\n\n- Good credit\u00a0knowledge in Trade Finance\n\n- Fluent in English, Cantonese and Mandarin\n\n- Prior team management experience\n\n\n*We offer*\n\n\"Interested candidates, please send an updated CV to kelvin.lam @jac-recruitment.com\n\nPersonal data collected will be used for employment-related purpose only. We regret to inform that only shortlisted candidates will be notified.", "employment_types": ["Full Time", "Permanent"], "selling_points": [], "locations": ["Central"], "categories": ["Banking / Finance", "Analyst", "Investment", "Professional Services", "Business Analysis / Data Analysis"], "post_time": "2022-01-15T01:17:12Z", "salary": {"currency": null, "max": null, "min": null, "period": null, "term": null}, "salary_visible": false, "title_keywords": ["research officer", "assistant"], "responsibilities": ["maintain", "quality", "finance team"], "requirements": {"degrees": ["university degree"], "majors": ["related disciplines", "economics", "business"], "languages": ["cantonese", "english", "mandarin"], "language_level": ["fluent"], "hard_skills": [], "soft_skills": [], "languages_combined": [{"language": "cantonese", "language_level": ["fluent"]}, {"language": "english", "language_level": ["fluent"]}, {"language": "mandarin", "language_level": ["fluent"]}]}, "experience_required": {"duration": ["minimum of 10 years"], "field": ["management", "finance", "supply chain", "relevant experience", "team"]}}, {"job_id": "100003009049611", "location_code": "hk", "company": "KCG Securities Asia Limited", "job_title": "Research Analyst (5 Days)", "description": "Our client, a Japanese company is looking for candidates Sales Engineer roles.\u00a0\n\n\nCompany Location:\u00a0 \u00a0 \u00a0 \u00a0 \u00a0 \u00a0\u00a0Hung Hom\n\nWorking Days: \u00a0\u00a0\u00a0\u00a0\u00a0\u00a0\u00a0\u00a0\u00a0\u00a0\u00a0\u00a0\u00a0\u00a0\u00a0\u00a0\u00a0\u00a0 Mon-Fri\n\nCompany Business:\u00a0 \u00a0 \u00a0 \u00a0 \u00a0 \u00a0\u00a0Japanese Electronic Company\n\nLanguages Required:\u00a0 \u00a0 \u00a0 \u00a0 \u00a0Mandarin, English\n\n\nJOB DUTIES:\n\n\u5411\u5728\u6240\u8d1f\u8d23\u533a\u57df\u8303\u56f4\u5185\u63a8\u5e7f\n\u76f4\u63a5\u5bf9\u5e94\u6700\u7ec8\u7528\u6237\uff0c\u4e86\u89e3\u5ba2\u6237\u663e\u5728\u548c\u6f5c\u5728\u9700\u6c42\uff08B2B\u9500\u552e\uff09\n\u5206\u6790\u6240\u8d1f\u8d23\u533a\u57df\u7684\u884c\u4e1a\u52a8\u6001\u5e76\u5236\u5b9a\u76f8\u5e94\u7684\u6218\u7565\u8ba1\u5212\uff0c\u5b9e\u73b0\u6307\u5b9a\u533a\u57df\u9500\u552e\u4e1a\u7ee9\u6700\u5927\u5316\n\u5728\u6307\u5b9a\u533a\u57df\u8303\u56f4\u5185\u7ef4\u62a4\u5df2\u6709\u5ba2\u6237\u3001\u5f00\u53d1\u65b0\u5ba2\u6237\n\nREQUIREMENTS:\n\n\u6709\u9500\u552e\u7ecf\u9a8c\u4f18\u5148\uff0c\u53ef\u4ee5\u6d41\u5229\u7684\u8bf4\u666e\u901a\u8bdd\n\u9002\u5e94\u4e25\u8c28\u7684\u7ba1\u7406\u548c\u5feb\u8282\u594f\u7684\u5de5\u4f5c\u6c1b\u56f4\n\u826f\u597d\u7684\u6c9f\u901a\u80fd\u529b\uff0c\u70ed\u7231\u9500\u552e\u5de5\u4f5c\uff0c\u6709\u6fc0\u60c5\n\nPACKAGE:\n\nDiscretionary bonus\nMedical insurance\nTransportation Allowance\nBody Check\n\nInterested candidates, kindly send your detailed resume in MS Word including:\n\n1) Expected salary\n2) Current and last drawn salaries\n3) Reason for leaving current and past employments\n\u00a0\ndirectly to:\u00a0jac.hk\u00a0@jac-recruitment.com and CC to:\u00a0akihisa.watanabe\u00a0@jac-recruitment.com\n\nPersonal data collected will be used for employment-related purpose only. We regret to inform that only shortlisted candidates will be notified, thank you", "employment_types": ["Full Time", "Permanent"], "selling_points": [], "locations": ["Central"], "categories": ["Banking / Finance", "Analyst", "Investment", "Asset Management"], "post_time": "2022-01-14T08:57:51Z", "salary": {"currency": null, "max": null, "min": null, "period": "monthly", "term": null}, "salary_visible": false, "title_keywords": ["research analyst"], "responsibilities": [], "requirements": {"degrees": [], "majors": [], "languages": [], "language_level": [], "hard_skills": [], "soft_skills": [], "languages_combined": []}, "experience_required": {"duration": [], "field": []}}, {"job_id": "100003009050868", "location_code": "hk", "company": "Williams Lea (Hong Kong) Ltd", "job_title": "Data Analyst", "description": "Responsibilities:\n\nGather data from different internal platforms\u00a0\nTo collaborate with relationship managers and stakeholders to produce analysis,\u00a0dashboard\u00a0and reports for customers\nSupport for routine sales / business management activities\nPrepare internal and external presentations\nAssist in management of data,\u00a0databases\u00a0and the relevant system\nSupport other ad-hoc and administrative duties as required\n\nRequirements:\n\nDegree or above with at least one-year relevant experience in banking / financial sector\nGood communications skill to get inputs from stakeholders and prepare different presentation decks\nProficient in MS Excel for consolidating data, including formula and pivot table usage\nCapability to use MS PowerPoint to present findings with graphs / charts\nEnergetic, quick starter, good time-management and attention to detail\nStrong sense in data, detail-minded, organized, meticulous and responsible\n\nWe offer attractive remuneration package to the successful candidate.\u00a0 In addition, you will have an opportunity to work in a reputable company with excellent career exposure.\u00a0 Interested parties, please click \"APPLY NOW\" to submit your application.\n\nAll information provided will be treated confidentially and used solely for recruitment purpose.\u00a0", "employment_types": ["Full Time", "Permanent"], "selling_points": ["Banking Environment", "Monday to Friday 0900 - 1800", "AL 15 Days, Medical & Dental Coverage"], "locations": ["Mong Kok"], "categories": ["Banking / Finance", "Analyst", "Corporate Banking", "Financial Services"], "post_time": "2022-01-14T11:35:38Z", "salary": {"currency": null, "max": null, "min": null, "period": "monthly", "term": null}, "salary_visible": false, "title_keywords": ["data analyst"], "responsibilities": ["collaborate with", "ad-hoc", "management", "data", "analysis", "presentations", "reports", "administrative duties", "databases"], "requirements": {"degrees": ["degree or above"], "majors": [], "languages": [], "language_level": [], "hard_skills": ["pivot table", "ms excel", "ms powerpoint"], "soft_skills": ["detail-minded", "organized", "meticulous", "responsible", "attention to detail", "energetic", "presentation"], "languages_combined": []}, "experience_required": {"duration": [], "field": ["relevant experience", "financial", "banking"]}}, {"job_id": "100003009053769", "location_code": "hk", "company": "Taishin International Bank Co Ltd", "job_title": "Assistant Manager / Manager \u2013 Business Management Officer  (Private Banking)", "description": "Responsibilities:\n\n\nFormulate related management methods, rules, standard operating procedures and various forms of private banking and wealth management\nMake sure the system is working properly\nBudget preparation, control and production of performance reports (e.g. Management meeting reports, WM monthly meeting reports and etc.) for the business unit\nPerformance assessment on sales officers of private banking and wealth management business, and bonus calculating\nReferral process and rewarding campaign planning and execution\nMarketing campaign planning and execution\n\nRequirements:\n\nBachelor Degree or above, major in Economics, Finance or related disciplines\nMinimum 3 years\u2019 relevant experience in banking industry\nStrong analytical skills, able to prioritize multi-tasking and time management\nFluent in spoken and written English & Chinese (including Putonghua)\u00a0\n\nInterested parties please send your FULL RESUME with present & expected salary to\u00a0\n\nManager, Human Resource\nTaishin International Bank, Hong Kong Branch\n6/F,\u00a0Tower 5, The Gateway,\n15 Canton Road, Tsimshatsui.\n\n\nData from employment applications will be kept confidential and used only for the purpose of selection. Applications not being contacted within 2 months may consider their applications unsuccessful. Our Bank will retain the applications for a maximum of one year for future suitable openings.\u00a0", "employment_types": ["Full Time", "Permanent"], "selling_points": ["Formulate related management methods", "Budget preparation", "Performance assessment"], "locations": ["Yau Tsim Mong Area"], "categories": ["Banking / Finance", "Analyst", "Others"], "post_time": "2022-01-17T07:29:26Z", "salary": {"currency": null, "max": null, "min": null, "period": "monthly", "term": null}, "salary_visible": false, "title_keywords": ["assistant manager", "manager", "officer", "private banking"], "responsibilities": ["management", "control", "performance reports", "budget", "procedures", "reports", "banking", "planning"], "requirements": {"degrees": ["degree or above", "bachelor"], "majors": ["related disciplines", "finance", "economics"], "languages": ["putonghua", "english", "chinese"], "language_level": ["fluent"], "hard_skills": ["analytical skills"], "soft_skills": ["multi-tasking", "time management", "able to prioritize", "analytical skills"], "languages_combined": [{"language": "putonghua", "language_level": ["fluent"]}, {"language": "english", "language_level": ["fluent"]}, {"language": "chinese", "language_level": ["fluent"]}]}, "experience_required": {"duration": ["minimum 3 years"], "field": ["banking industry", "relevant experience"]}}, {"job_id": "100003009045797", "location_code": "hk", "company": "Goldhorse Capital Management (HK) Limited", "job_title": "Senior Equity Analyst", "description": "Responsibilities:\nConduct fundamental research analysis on assigned sectors and bottom up stock picking on Greater China stocks (Hong Kong and US listed);\nBe one of the key spokespersons on investments for client events and media;\nPrepare investment reports as well as research materials for internal and public presentation;\nProvide direction and expert advice on securities to buy, sell, or hold;\nCoach junior analysts on building financial models and valuation techniques.\n\nRequirements:\n\nAt least 5 years of equity research experience in buy side or sell side institutions;\nExperience in Chinese report writing skill is a must;\nStrong research background across all disciplines: Fundamental and Technical;\nStrong team player with excellent inter-personal skills is a must;\nPlease stated current and expected salary in the application.", "employment_types": ["Permanent"], "selling_points": [], "locations": ["Tsim Sha Tsui"], "categories": ["Banking / Finance", "Analyst", "Investment", "Equities / Capital Markets"], "post_time": "2022-01-13T08:43:55Z", "salary": {"currency": null, "max": null, "min": null, "period": "monthly", "term": null}, "salary_visible": false, "title_keywords": ["analyst"], "responsibilities": ["valuation", "fundamental research analysis", "provide direction", "financial models", "expert advice", "reports"], "requirements": {"degrees": [], "majors": [], "languages": ["chinese"], "language_level": [], "hard_skills": ["writing skill"], "soft_skills": ["team player", "inter-personal skills", "writing skill"], "languages_combined": [{"language": "chinese", "language_level": []}]}, "experience_required": {"duration": ["at least 5 years"], "field": ["equity research", "writing"]}}, {"job_id": "100003009046501", "location_code": "hk", "company": "AXA Hong Kong", "job_title": "Investment Analyst / Assistant Analyst", "description": "Job Responsibilities:\n\nSupport the AXA HK & Asia Head of Investment and AXA HK Investment Manager in various investment activities, including asset allocation, monitoring of investment activities, risk & limit consumption control, regular rebalancing, and liquidity management\nEnsure investments are done as per local investment policies and mandates while complying with AXA Group guidelines\nMonitor strategic and tactical investment positions\nEnsure the documentation of investment processes is updated on a regular basis\nPrepare reports for the local investment committees and board meetings\nAssist in producing presentations of investment-related projects\n\nJob Requirements:\n\nDegree holder from a reputable university specializing in finance, risk management, actuarial, accounting, or IT related disciplines\nIdeally 1 year working experience in investment, finance or insurance areas within a major financial institution\nStrong knowledge of Excel; programming skills is a bonus but not necessary\nTechnical competence in spreadsheet modelling and strong quantitative financial skills, including the use of financial information systems (e.g. Bloomberg)\nQualification or studying towards completion of recognized financial designations (e.g. CFA, FRM, CAIA) preferred\nAn independent individual and a team player\nFluent in both written and spoken English", "employment_types": ["Full Time", "Permanent"], "selling_points": ["entry level for Investment role", "prepare reports and manage process for investment", "Good working environment & culture"], "locations": ["Southern Area"], "categories": ["Banking / Finance", "Analyst", "Investment", "Insurance", "Others"], "post_time": "2022-01-13T12:16:59Z", "salary": {"currency": null, "max": null, "min": null, "period": "monthly", "term": null}, "salary_visible": false, "title_keywords": ["analyst", "assistant"], "responsibilities": ["control", "management", "prepare reports", "guidelines", "policies", "monitoring", "monitor", "presentations", "documentation"], "requirements": {"degrees": ["degree holder"], "majors": ["risk management", "finance", "related disciplines", "it", "accounting"], "languages": ["english"], "language_level": ["fluent"], "hard_skills": ["excel", "bloomberg", "cfa", "programming", "spreadsheet", "frm"], "soft_skills": ["team player", "independent"], "languages_combined": [{"language": "english", "language_level": ["fluent"]}]}, "experience_required": {"duration": ["1 year"], "field": ["finance", "insurance", "investment", "financial"]}}, {"job_id": "100003009054068", "location_code": "hk", "company": "MLC", "job_title": "Investor Relations Assistant  -  Innovative Fashion Design/Manufacturing Leader  (happy culture)", "description": "Working in a design driven, innovation & dynamic, and fast growing environment, you will support the Investor Relations Director on the full spectrum of investor relations functions for the organization, a top Innovative Design Manufacturer,\u00a0 relying on core technologies, innovative, research & development, and production capabilities to develop and\u00a0 produce top quality and creative fashion collections including seamless sports wear, yoga wear, functional body wear and bras, for global fashion brands.\n\nYou will partner with the Investor Relations Director and PR Agencies to organize all\u00a0Investor Relations corporate events including conference calls, meeting requests, and roadshows etc.\u00a0 You will assist in gathering company development information, market research, and industry trend research to develop IR materials, presentations, and communication strategies.\n\nYou will take lead on updating and maintaining company's website, industry news, and investors' database etc.\u00a0\n\nIf you have 1 years of relevant experience in investor relations, have a bachelor's degree in business administration, journalism, or related discipline,\u00a0and have strong communication ability in English and Chinese,\u00a0 then we would like to hear from you.\n\nPlease forward you resume to Ms. Lau of MLC by clicking the \"APPLY NOW\".\u00a0 Alternatively, you are welcome to call Ms. Lau at 27805232 to discuss your interest.\n\nAll data collected will be treated in strictest confidence and used only for recruitment purpose only.", "employment_types": ["Full Time", "Permanent"], "selling_points": ["PR events, Business Research & Administration", "Website Update, Executive Speech, Announcement", "Happy Work Place, Multi-Cultural Environment"], "locations": ["Others"], "categories": ["Banking / Finance", "Analyst", "Media & Advertising", "Editorial / Journalism", "Marketing / Public Relations", "Public Relations - Event Management"], "post_time": "2022-01-17T08:17:26Z", "salary": {"currency": null, "max": null, "min": null, "period": "monthly", "term": null}, "salary_visible": false, "title_keywords": ["assistant"], "responsibilities": ["maintaining", "data", "quality", "market research", "presentations", "design", "develop", "communication", "website", "recruitment", "database", "administration"], "requirements": {"degrees": ["degree", "bachelor"], "majors": ["journalism", "business administration"], "languages": ["english", "chinese"], "language_level": [], "hard_skills": ["dynamic", "presentations"], "soft_skills": ["confidence", "innovative", "communication", "dynamic", "creative", "driven"], "languages_combined": [{"language": "english", "language_level": []}, {"language": "chinese", "language_level": []}]}, "experience_required": {"duration": ["1 years"], "field": ["related", "relevant experience", "business administration"]}}, {"job_id": "100003009046403", "location_code": "hk", "company": "Wheelock Properties (Hong Kong) Ltd", "job_title": "Business Analyst / Business Analysis Manager (Property)", "description": "Responsibilities:\n\n\nConduct in-depth analysis and market research on property developments in Hong Kong\nReview and provide feasible solutions and scenarios\nConduct periodic and ad hoc health check on data integrity and risk management\nPresent findings of actionable business solutions to management\nMaintain Company\u2019s property-related operational databases\nKeep abreast and update record of market information and trends\nMonitor policy changes in relevant markets\nWork closely with sales team to monitor planned sales, turnover and profitability\nRequirements:\n\nDegree in Statistics/ Finance/ Applied Mathematics/ Real Estate or related disciplines\nCertification of taking VBA (Visual Basic for Applications) programming or intermediate/advanced excel courses is preferred\nMinimum 8 years of solid experience in building analytical models and market research, preferably experience gained in real estate/ retail/ banking/ insurance industries\nSupervisory/management level experience is preferred\nExtensive experience with research, data mining and statistical modeling tools\nStrong business acumen with analytical mindset\nGood communication and presentation skills\nProficient in written and spoken English and Chinese\nWe offer ample opportunities for career development and attractive salary package commensurate with experience and qualifications. \u00a0Interested parties please apply with full resume via\u00a0\u201cAPPLY NOW\u201d.\u00a0\n\n\nFor further information on Wheelock Properties (Hong Kong) Limited, please visit our website:\u00a0www.wheelockpropertieshk.com.\n\nWe are an equal opportunities employer and invite applications from all qualified candidates. Personal data collected will be treated in strict confidence and handled by authorized persons for recruitment-related purposes only within The Wheelock & Wharf Group. Applicants not hearing from us within 2 months may consider their applications unsuccessful.\u00a0", "employment_types": ["Full Time", "Permanent"], "selling_points": [], "locations": ["Central"], "categories": ["Banking / Finance", "Analyst", "Property / Real Estate", "Others", "Sales, CS & Business Devpt", "Sales - Real Estate"], "post_time": "2022-01-13T18:55:20Z", "salary": {"currency": null, "max": null, "min": null, "period": null, "term": null}, "salary_visible": false, "title_keywords": ["business analysis manager", "business analyst"], "responsibilities": ["management", "market information", "ad hoc", "data", "analysis", "review", "monitor", "market research", "maintain", "sales team", "databases"], "requirements": {"degrees": ["degree"], "majors": ["related disciplines", "finance", "statistics", "applied mathematics"], "languages": ["english", "chinese"], "language_level": ["proficient"], "hard_skills": ["vba", "excel", "visual basic", "programming", "data mining", "acumen"], "soft_skills": ["advanced", "communication", "presentation skills", "business acumen", "extensive"], "languages_combined": [{"language": "english", "language_level": ["proficient"]}, {"language": "chinese", "language_level": ["proficient"]}]}, "experience_required": {"duration": ["minimum 8 years"], "field": ["supervisory", "management", "research", "analytical", "market research", "banking", "insurance", "retail"]}}, {"job_id": "100003009049840", "location_code": "hk", "company": "Wang On Financial Services Management Limited", "job_title": "Investment Manager", "description": "We are looking for an investment manager to manage investment and deals on equities, bonds & funds, private equity fund, REIT, etc.\n\n\nResponsibilities:\n\n\nManage investment portfolio consisted of public and private equities, bonds, bond fund, Pre-IPO, PE Fund, REIT and alternative assets and prove portfolio performance. \u00a0\nTo collect market information and identify investment opportunities on the financial market;\nTo prepare in-depth market research & financial analysis on investment projects;\nTo perform quantitative and qualitative analysis;\nTo provide trading ideas and get involved in investment process;\nTo assist in origination and evaluation of investment deals\nTo prepare regular and update detailed financial models and to prepare investment research reports;\nTo monitor & evaluate investment performance, conduct returns analysis;\nTo provide timely analytical reports, updated information and investment recommendations to CC\u00a0\u00a0\n\nRequirements:\u00a0\n\nDirectly report to Credit Committee;\nDegree in investment/ finance related disciplines preferably with CFA & HKICPA;\nStrong analytical and presentation skills;\nSolid knowledge of financial modelling;\nDeep understanding of capital markets and fixed income products;\nHands-on experience in research, presentation preparation and data mining;\nAble to work under pressure;\nAt least 8 years\u2019 experience in financial field;\nStrong cognitive skills and highly adaptable;\nResult-oriented and concise communication\u00a0\n\n\n\nWe offer competitive remuneration package, our benefits include:\n\nPerformance bonus\nEducation subsidy\nProfessional membership fee sponsorship\nLife & medical insurance\nMarriage Leave, Compassionate Leave, Examination Leave etc.\nPublic holidays\nStaff purchase discount\n\nInterested parties please send full resume with present and expected salary to Human Resources Department by clicking\u00a0Apply Now.\n\n(Information provided will be treated in strict confidence and will only be used for recruitment-related purposes.)", "employment_types": ["Full Time", "Permanent"], "selling_points": [], "locations": ["Sheung Wan"], "categories": ["Banking / Finance", "Analyst", "Investment"], "post_time": "2022-01-14T09:18:44Z", "salary": {"currency": null, "max": null, "min": null, "period": "monthly", "term": null}, "salary_visible": false, "title_keywords": ["investment manager"], "responsibilities": ["market information", "ideas", "financial models", "analysis", "monitor", "market research", "financial analysis", "evaluate", "reports", "evaluation"], "requirements": {"degrees": ["degree"], "majors": ["related disciplines", "finance"], "languages": [], "language_level": [], "hard_skills": ["data mining", "cfa", "hkicpa"], "soft_skills": ["result-oriented", "adaptable", "deep", "communication", "presentation skills", "hands-on", "presentation", "work under pressure"], "languages_combined": []}, "experience_required": {"duration": ["at least 8 years"], "field": ["research", "financial"]}}, {"job_id": "100003009049217", "location_code": "hk", "company": "Shanghai Commercial Bank Ltd", "job_title": "Data Analyst - Assistant Manager/ Officer / Associate", "description": "Responsibilities:\n\nAnalyze structured and unstructured data in order to understand customer behavior, particularly for the Small Medium Enterprise and Retail customer segments.\nOffer assistance on developing analytics reports and visualization dashboard for business monitoring and delivering insights.\nSupport data-led experiments to continually refine our customer-led value proposition.\nSupport data maintenance and data management of a new implemented customer data platform and increase our data quality and accuracy of the data sources.\n\nRequirements\n\nDegree holder in Computer Science, Data Science, Mathematics, Statistics, IT or relevant disciplines.\n3-5 years experiences in data science or machine learning.\nGood knowledge on database and statistical software (such as SAS, Python) is preferred.\nSelf-motivated, presentable and analytical.\nTeam player and strong communication skill.\nGood command of both spoken and written English and Chinese. Mandarin is an advantage.\n\nAttractive remuneration package will be offered to the right candidates. Interested parties please click\u00a0\"Apply Now\"\u00a0to submit your full resume with current and expected salary to the\u00a0Human Resources Division.\n\nPlease visit us at\u00a0www.shacombank.com.hk\u00a0for more information about our Bank.\n\nAll personal data collected will be used for recruitment related purposes strictly in accordance with the Bank's personal data policies, a copy of which will be provided immediately upon request by contacting our Personal Data Compliance Officer. Applicants who are not contacted within two months may consider their applications unsuccessful and the personal data collected from the applicants will be retained for no longer than two years from the date of rejection during which the applicants may be considered for other suitable positions within the Bank.", "employment_types": ["Full Time", "Permanent"], "selling_points": ["Offer assistance on developing analytics reports", "Support data maintenance and data management", "Analyze structured and unstructured data"], "locations": ["Kwai Hing"], "categories": ["Banking / Finance", "Analyst", "Financial Services", "Others"], "post_time": "2022-01-15T03:50:12Z", "salary": {"currency": null, "max": null, "min": null, "period": "monthly", "term": null}, "salary_visible": false, "title_keywords": ["assistant manager", "associate", "data analyst", "officer"], "responsibilities": ["management", "visualization", "maintenance", "data", "monitoring", "quality", "developing", "reports", "customer data"], "requirements": {"degrees": ["degree holder"], "majors": ["data science", "mathematics", "statistics", "it", "computer science"], "languages": ["english", "chinese", "mandarin"], "language_level": ["advantage", "good command"], "hard_skills": ["python", "sas"], "soft_skills": ["self-motivated", "communication skill", "presentable", "learning", "team player"], "languages_combined": [{"language": "english", "language_level": ["good command"]}, {"language": "chinese", "language_level": ["good command"]}, {"language": "mandarin", "language_level": ["advantage"]}]}, "experience_required": {"duration": ["3-5 years"], "field": []}}, {"job_id": "100003009022593", "location_code": "hk", "company": "Peak Vision Appraisals Limited", "job_title": "Financial Analyst - Valuation", "description": "Financial Analyst - Valuation\u00a0\n\nLocation: Wanchai, Hong Kong\n\nJob Description and Responsibilities:\n\n\u00a0- Conduct company and industry research and analysis\n\u00a0- Assist in performing financial analysis and valuation including business and property valuations\n\u00a0- Draft valuation report\n\u00a0- Assist in organizing and monitoring project progress, liaise with internal and external parties\n\nRequirements:\n\n- Degree holder in Accounting, Finance, Surveying or related disciplines preferred\n- 1 to 2 years relevant experience in valuation or audit would be an advantage\n- Responsible, committed, details oriented, and willing to learn\n- Good computer skills (MS Office, Excel, PowerPoint)\n- Good command of both written and spoken English, Mandarin and Cantonese\n- Good team player with the ability to work independently\n- Able to work under pressure and meet deadline\n- Fresh graduates are welcome\n\nWhat we offer:\n\n- 5 working days per week\n- Attractive remuneration package\n- Good career prospect\n- Medical benefits\n- Friendly working environment\u00a0\n\nInterest parties, please send detailed resume with expected salary to us or by clicking \"Apply Now\"\n\nOur website : https://www.peakval.com\u00a0\n\n(Personal data collected would be used for recruitment purpose only)\n\nPeak Vision Appraisals Limited\n\nWe are a professional appraisal and advisory firm. We offer professional valuation services for M&A, IPO and accounting reference purposes, as well as advise on Environmental, Social and Governance (ESG) reporting. Our clients are mainly listed companies in Hong Kong.", "employment_types": ["Full Time"], "selling_points": ["Good career prospect", "Degree holder in Accounting, Finance, Surveying", "Friendly working environment"], "locations": ["Wan Chai Area"], "categories": ["Accounting", "Financial Analyst", "Banking / Finance", "Analyst", "Professional Services", "Business Analysis / Data Analysis"], "post_time": "2022-01-12T23:26:05Z", "salary": {"currency": null, "max": null, "min": null, "period": "monthly", "term": null}, "salary_visible": false, "title_keywords": ["financial analyst"], "responsibilities": ["valuation", "analysis", "monitoring", "internal and external parties", "project progress", "financial analysis", "liaise with", "report"], "requirements": {"degrees": ["degree holder"], "majors": ["related disciplines", "finance", "accounting", "surveying"], "languages": ["cantonese", "english", "mandarin"], "language_level": ["good command"], "hard_skills": ["excel", "computer skills", "powerpoint", "ms office"], "soft_skills": ["good team player", "work independently", "responsible", "willing to learn", "committed", "work under pressure"], "languages_combined": [{"language": "cantonese", "language_level": ["good command"]}, {"language": "english", "language_level": ["good command"]}, {"language": "mandarin", "language_level": ["good command"]}]}, "experience_required": {"duration": ["1 to 2 years"], "field": ["relevant experience", "audit"]}}, {"job_id": "100003009049253", "location_code": "hk", "company": "Shanghai Commercial Bank Ltd", "job_title": "Officer, Customer Analytics", "description": "Responsibilities:\n\nWith hands-on skills on advanced data tools including AI, machine learning and Big Data, help develop predictive models to support business in understanding customer needs better and improve customer experience\nWork closely with Technical and Product team in the implementation of advanced analytics tools and use the tool to deliver analytics results\nAnalyze online performance and sales data, provide review reports in customer portfolio / marketing campaign for performance evaluation, business recommendation and develop innovative marketing concepts\nProvide insights to business on defining new online acquisition opportunities, customer retention and assist different business units to apply predictive models to drive business\nSupport digital analytic development / transformation roadmap and initiatives\n\nRequirements:\n\nUniversity graduate in Quantitative Statistics, Analytics, or Business related discipline\nMinimum 3-5 years of experience in data analytics on customers, preferably in Banking, Financial Services or FinTech industry; non-bank industry is also welcome\nProficiency in big data / machine learning / predictive modelling using SAS, Python or other analytical tools for model development\nGood interpersonal skills with strong business sense so as to communicate analytical subjects effectively with various business units\nStrong analytical / project management skills\nGood command of both written and spoken English and Chinese. Knowledgeable on Mandarin is a plus.\n\n(Candidates with more experience will be considered as Assistant Manager, Customer Analytics)\n\nAttractive remuneration package will be offered to the right candidates. Interested parties please click\u00a0\"Apply Now\"\u00a0to submit your full resume with current and expected salary to the\u00a0Human Resources Division.\n\nPlease visit us at\u00a0www.shacombank.com.hk\u00a0for more information about our Bank.\n\nAll personal data collected will be used for recruitment related purposes strictly in accordance with the Bank's personal data policies, a copy of which will be provided immediately upon request by contacting our Personal Data Compliance Officer. Applicants who are not contacted within two months may consider their applications unsuccessful and the personal data collected from the applicants will be retained for no longer than two years from the date of rejection during which the applicants may be considered for other suitable positions within the Bank.", "employment_types": ["Full Time", "Permanent"], "selling_points": ["Work closely with Technical and Product team", "Analyze online performance and sales data", "Support digital analytic development"], "locations": ["Central"], "categories": ["Banking / Finance", "Analyst", "Others"], "post_time": "2022-01-15T03:50:15Z", "salary": {"currency": null, "max": null, "min": null, "period": "monthly", "term": null}, "salary_visible": false, "title_keywords": ["officer"], "responsibilities": ["analytics tools", "predictive models", "provide insights", "data", "review", "big data", "implementation", "develop", "reports", "evaluation"], "requirements": {"degrees": ["university graduate"], "majors": ["business", "statistics"], "languages": ["english", "chinese", "mandarin"], "language_level": ["good command"], "hard_skills": ["plus", "sas", "data analytics", "project management", "python"], "soft_skills": ["project management skills", "learning", "interpersonal skills", "business sense"], "languages_combined": [{"language": "english", "language_level": ["good command"]}, {"language": "chinese", "language_level": ["good command"]}, {"language": "mandarin", "language_level": []}]}, "experience_required": {"duration": ["minimum 3-5 years"], "field": ["financial services", "banking"]}}, {"job_id": "100003009041245", "location_code": "hk", "company": "Guosen Securities (HK) Financial Holdings Company, Limited", "job_title": "Research Analyst - Pharmaceutical & Healthcare", "description": "Responsibilities:\n\nResearch field: Analysis of researching industrial innovation development, closely follow up with industry trends, prepare in-depth research report\nIn-depth research on key companies/segmented fields: analysis of the specific industry of target companies\nAnalysis of business models, core competitiveness, field/company growth and risks, establish dynamic adjustment valuation models\nClosely follow up with the fundamental information of companies in target industries, and conduct researches on major announcements and important information\nConduct research and analysis of industries/companies independently and provide analysis reports\nTo perform ad hoc projects\n\nRequirements:\n\nMaster degree or above in science and engineering, biomedical background preferred\nMinimum 2 years of relevant experience in investment institutions or related relevant experience in the pharmaceutical industry, knowledge of key issues and developments in pharmaceutical industries\nPossess financial basic knowledge, familiar with various research methods, outstanding data processing ability\nWith strong analytical mind, strong ability of gathering information independently and logical thinking, research and analysis\nExcellent in written and spoken English and Chinese (Cantonese & Putonghua)\n\nAttractive remuneration will be offered to the right candidate.\u00a0 Interested parties please email your full resume with present & expected salary and date of availability to hrm @guosen.com.hk or via \"Apply Now\".\n\nPersonal data collected would be used for recruitment purpose only.", "employment_types": ["Full Time", "Permanent"], "selling_points": ["Pharmaceutical & Healthcare", "prepare in-depth research report", "follow up with the fundamental info of the company"], "locations": ["Admiralty"], "categories": ["Banking / Finance", "Analyst", "Others", "Medical Services", "Pharmaceutical"], "post_time": "2022-01-12T03:38:43Z", "salary": {"currency": null, "max": null, "min": null, "period": "monthly", "term": null}, "salary_visible": false, "title_keywords": ["research analyst"], "responsibilities": ["valuation", "analysis reports", "analysis", "ad hoc projects", "conduct research", "report"], "requirements": {"degrees": ["degree or above", "master"], "majors": ["science", "engineering"], "languages": ["cantonese", "putonghua", "english", "chinese"], "language_level": ["excellent"], "hard_skills": ["analysis", "processing", "basic"], "soft_skills": ["analytical mind", "independently"], "languages_combined": [{"language": "cantonese", "language_level": ["excellent"]}, {"language": "putonghua", "language_level": ["excellent"]}, {"language": "english", "language_level": ["excellent"]}, {"language": "chinese", "language_level": ["excellent"]}]}, "experience_required": {"duration": ["minimum 2 years"], "field": ["related", "pharmaceutical", "relevant experience", "investment"]}}, {"job_id": "100003009050026", "location_code": "hk", "company": "Genesis Block Limited", "job_title": "KYC/AML Specialist", "description": "Responsibilities\n\nHandle the end-to-end onboarding of new client accounts, collecting all relevant information and manage the client onboarding experience\nReview KYC (Know Your Client) documentation and perform customer due diligence (CDD) for new client accounts and periodic CDD review on existing client accounts\nProvide administrative support for the middle and back-office team\nMaintain and update database of all information and documents\nLiaise with internal teams to ensure a smooth onboarding experience\nOpportunities to know know your token (KYT, Crypto transaction monitoring)\n\nQualifications\n\nBachelor\u2019s degree\n1+ years experience in client onboarding, KYC/AML is preferred but fresh graduates are welcome\nExcellent written and verbal communication skills\nStrong analytical and problem-solving skills with excellent attention to detail\nFluency in written and spoken English; fluency in an Asian language is an advantage\nAbility to work independently in a fast-paced environment", "employment_types": ["Full Time", "Permanent"], "selling_points": ["Growing Digital Assets Brokerage firm", "Great exposure to blockchain and crypto industry", "Attractive package, Performance Driven bonus"], "locations": ["Wan Chai"], "categories": ["Banking / Finance", "Analyst", "Professional Services", "Legal & Compliance", "Risk Management"], "post_time": "2022-01-14T09:39:12Z", "salary": {"currency": "HKD", "max": 34999, "min": 20000, "period": "monthly", "term": null}, "salary_visible": true, "title_keywords": ["specialist"], "responsibilities": ["aml", "cdd", "review", "teams", "monitoring", "communication", "customer due diligence", "liaise with", "maintain", "database", "kyc", "documentation", "provide administrative support"], "requirements": {"degrees": ["degree", "bachelor"], "majors": [], "languages": ["english"], "language_level": ["fluency"], "hard_skills": ["crypto", "aml", "cdd", "customer due diligence", "kyc", "documentation", "problem-solving skills"], "soft_skills": ["communication skills", "work independently", "fast-paced environment", "attention to detail", "smooth", "problem-solving skills"], "languages_combined": [{"language": "english", "language_level": ["fluency"]}]}, "experience_required": {"duration": ["1+ years"], "field": []}}, {"job_id": "100003009050925", "location_code": "hk", "company": "Bank of Communications Hong Kong Branch", "job_title": "Analyst, Credit Policy & Quantitative Analysis", "description": "Assist in various credit risk management functions for the team\nCarry out risk data collection and analysis for monitoring and regular reporting\nExplore the changes and risk drivers of the bank\u2019s credit portfolio with reference to prevailing macro environment and market conditions\nPrepare credit portfolio analysis reports and presentation materials for senior management/ management committee\nEnhance and maintain credit related systems and database\nDegree holder or above in Statistics, Mathematics, IT / Computing, Risk Management, Finance or related disciplines\nMinimum 1 year\u2019s relevant experience in the banking or financial sector, with exposure on working with database and internal rating system.\nSound knowledge of Excel, Access, VBA, data warehouse and statistical tools (e.g. SAS)\nStrong interpersonal and communications skills\nStrong analytical skill and numerical sense\nConversant with Chinese word processing\nFluency in Mandarin is a plus\n\nCandidates with more experience will be considered as Senior Analyst, Credit Policy & Quantitative Analysis\n\n\u00a0\n\nThe above post requires proficiency in English, Cantonese and Putonghua.\n\nWe offer attractive remuneration package to the right candidates. Please send your full resume with expected salary to\u00a0The Human Resources Manager, Bank of Communications Co., Ltd., 10/F, Bank of Communications Tower, 231-235 Gloucester Road, Wan Chai, Hong Kong, or fax to\u00a02838 9209, or e-mail to APPLY NOW.", "employment_types": ["Full Time"], "selling_points": ["Degree holder or above in Statistics, Mathematics", "Strong interpersonal and communications skills", "1 year\u2019s relevant experience in the banking"], "locations": ["Not Specified"], "categories": ["Banking / Finance", "Analyst", "Financial Services", "Others"], "post_time": "2022-01-14T11:48:51Z", "salary": {"currency": null, "max": null, "min": null, "period": "monthly", "term": null}, "salary_visible": false, "title_keywords": ["analyst"], "responsibilities": ["reporting", "management", "data", "analysis", "monitoring", "portfolio analysis reports", "systems", "banking", "maintain", "data collection", "database", "senior management"], "requirements": {"degrees": ["degree holder"], "majors": ["mathematics", "risk management", "finance", "statistics", "related disciplines", "it"], "languages": ["cantonese", "english", "mandarin", "putonghua", "chinese"], "language_level": ["fluency", "proficiency"], "hard_skills": ["vba", "excel", "macro", "analytical skill", "chinese word processing", "plus", "sas", "data warehouse", "analysis"], "soft_skills": ["analytical skill", "interpersonal", "presentation"], "languages_combined": [{"language": "cantonese", "language_level": ["proficiency"]}, {"language": "english", "language_level": ["proficiency"]}, {"language": "mandarin", "language_level": ["fluency"]}, {"language": "putonghua", "language_level": ["proficiency"]}, {"language": "chinese", "language_level": []}]}, "experience_required": {"duration": ["minimum 1 year"], "field": ["database", "relevant experience", "financial", "banking"]}}, {"job_id": "100003009040254", "location_code": "hk", "company": "iFAST Financial (HK) Limited", "job_title": "Research Analyst", "description": "Responsibilities:\n\nAnalyze and research on mutual funds, portfolios, markets and other investment products;\nWrite original and timely articles on equity markets, mutual funds and investment-related products;\nInvolved in presenting to clients and financial advisors;\nTo contribute to senior member on materials and data preparation;\nTo support the research team to maintain database/research content & tools/portfolio monitoring.\n\nRequirements:\n\nA good degree in Economic/ Finance/ Mathematics or related discipline, fresh graduates are welcomed to apply;\nAdvanced knowledge in mutual fund and macro-economic analysis is preferred;\nExcellent writing and presentation skills in both English and Chinese;\nKeen interest in investments, financial markets and economics;\nMeticulous, precise and sensitive to numbers;\nStrong analytical ability with good communication and interpersonal skills;\nSense of urgency;\nSelf-motivated, mature and able to work independently as well as be a team player.\n\nOur offer:\u00a0\n\nCareer development prospect;\nAttractive remuneration;\n5-day working week;\n21+ days Annual Leave;\nMedical, Dental, Life Insurance;\nPerformance bonus and shares;\nEducation, sports allowance.\n\nInterested parties please send your full resume by clicking \"APPLY NOW\".\nOur company is an equal opportunities employer and welcome application from all qualified candidates.\u00a0Information provided will be treated with strict confidential and be used for the purpose of selection only.\u00a0Applicants who are not invited for interview within 10 weeks may consider their applications unsuccessful. Personal data of unsuccessful applicant will be destroyed within 12 months.", "employment_types": ["Full Time", "Permanent"], "selling_points": ["Focus on mutual funds, portfolios and markets", "Communicating via articles, presentations, videos", "21+ days Annual Leave"], "locations": ["Central"], "categories": ["Banking / Finance", "Analyst", "Investment", "Fund Management"], "post_time": "2022-01-12T02:02:07Z", "salary": {"currency": null, "max": null, "min": null, "period": "monthly", "term": null}, "salary_visible": false, "title_keywords": ["research analyst"], "responsibilities": ["monitoring", "maintain", "database", "data"], "requirements": {"degrees": ["degree"], "majors": ["finance", "mathematics"], "languages": ["english", "chinese"], "language_level": ["excellent"], "hard_skills": ["macro", "analysis"], "soft_skills": ["meticulous", "self-motivated", "work independently", "advanced", "urgency", "keen", "mature", "presentation skills", "communication and interpersonal skills", "team player", "precise", "sensitive to numbers"], "languages_combined": [{"language": "english", "language_level": ["excellent"]}, {"language": "chinese", "language_level": ["excellent"]}]}, "experience_required": {"duration": [], "field": []}}, {"job_id": "100003009043776", "location_code": "hk", "company": "Ethos BeathChapman Hong Kong Limited", "job_title": "Business Analyst (Equity Derivatives)", "description": "The Role:\n\nClient is a market-leading Global Bank, based here in Hong Kong. They are currently hiring into their Equity Derivatives Global Markets team.\n\nRequirements:\n\nExperience of working in the Equity Derivatives domain, especially within the Structured Products area.\nCandidate should have strong Business Analysis skills\nPowerful communicator \u2013 must be articulate and confident in interacting with senior stakeholders\nA team player, ability to work collaboratively and/or independently when required\n\nBeathChapman Pte Ltd", "employment_types": ["Full Time", "Permanent"], "selling_points": ["One of Hong Kong\u2019s leading banks", "Dynamic international working environment", "Attractive salary"], "locations": ["Central & Western Area"], "categories": ["Banking / Finance", "Analyst", "Equities / Capital Markets"], "post_time": "2022-01-13T01:59:27Z", "salary": {"currency": "HKD", "max": 69999, "min": 55000, "period": "monthly", "term": null}, "salary_visible": true, "title_keywords": ["business analyst"], "responsibilities": ["business analysis"], "requirements": {"degrees": [], "majors": [], "languages": [], "language_level": [], "hard_skills": ["analysis"], "soft_skills": ["confident", "independently", "team player", "articulate", "communicator", "structured"], "languages_combined": []}, "experience_required": {"duration": [], "field": []}}, {"job_id": "100003009043565", "location_code": "hk", "company": "Stratasys AP Limited", "job_title": "Financial Analyst, APJ", "description": "Summary\nThe person in this position will be critical to the delivery of meaningful financial reporting and analysis to internal and external recipients at varying levels. This person will be part of a team that lead multiple annual budget and forecast cycles, responsible for consolidating and interpreting inputs and for improving process for efficiency, accuracy and value added. This role requires an individual who possesses a high level of energy and is willing to take on a challenge and requires both detail-oriented and ability to see the bigger picture. This person will report to Financial Planning & Analysis Manager, APJ.\n\nRESPONSIBILITY:\n\nPerform consolidation, ensure accuracy and reasonableness, and provide analysis on APJ results for quarterly business review and budget meeting\nMonitor Opex and Capex closely and review regularly with country Finance for cost saving opportunities and quarterly forecast\nAnnual budget preparation, review country submission, systems upload and consolidation\nPrepare management reports for regional and country management, and various user departments\nPrepare quarterly revenue checklists for group reporting\nAs a business partner to facilitate to assigned regional user department, country, business units\nImplementing a new planning tool\nInvolved in building up and refine analysis template to facilitate region / management decision making\nTo be pilot user of BI projects and develop workflows to automate the existing manual processes\nProvide as needed support for Accounting team such as journal entry preparation, guidance on classification of entries\nAble to present reports to relevant Stakeholders\nAd-Hoc tasks / projects as required by management / other department\n\nQUALIFICATION\n\nAt least 3 years relevant working experience in FP&A or 3 years business analysis in MNC\nPrior regional experience with analysis, budget and forecast\nBachelor\u2019s degree, preferably accountancy or business related\nTechnical aptitude, proficient in handling large volume of data, with the ability to solve problems utilizing technology\nBe team-oriented, able to fulfill and adapt to requests of internal and external customers\nExcellent communication and interpersonal abilities, with influencing ability\nAble to work under high-pressure, fast paced and dynamic environment\nOpen minded, proactive, detail-minded and analytical thinking\nComfort dealing with ambiguity and the ability to work independently\nFluent in English, Cantonese and Mandarin\nExcellent computer skills in MS Excel and PowerPoint\nKnowledge with Qlik, Alteryx and IBM planning tools are an advantage, and experience on Oracle ERP", "employment_types": ["Full Time"], "selling_points": ["Regional experience with analysis, budget forecast", "Be team-oriented and problem solver", "Fluent in English, Cantonese and Mandarin"], "locations": ["Kwun Tong"], "categories": ["Banking / Finance", "Analyst"], "post_time": "2022-01-12T23:18:58Z", "salary": {"currency": null, "max": null, "min": null, "period": "monthly", "term": null}, "salary_visible": false, "title_keywords": ["financial analyst"], "responsibilities": ["data", "budget", "capex", "opex", "communication", "monitor", "develop", "reports", "forecast", "report", "reporting", "cost", "management", "guidance", "review", "annual budget preparation", "internal and external customers", "analysis", "systems", "ad-hoc tasks", "management reports", "financial reporting", "business analysis", "planning"], "requirements": {"degrees": ["degree", "bachelor"], "majors": ["business", "accountancy"], "languages": ["cantonese", "english", "mandarin"], "language_level": ["fluent"], "hard_skills": ["bi", "analysis", "powerpoint", "oracle erp", "management reports", "dynamic", "computer skills", "ms excel", "pilot", "alteryx"], "soft_skills": ["detail-minded", "dynamic environment", "work independently", "responsible", "detail-oriented", "communication", "solve problems", "open minded", "proactive", "interpersonal", "decision making"], "languages_combined": [{"language": "cantonese", "language_level": ["fluent"]}, {"language": "english", "language_level": ["fluent"]}, {"language": "mandarin", "language_level": ["fluent"]}]}, "experience_required": {"duration": ["3 years", "at least 3 years"], "field": ["business analysis", "relevant working experience", "planning"]}}, {"job_id": "100003009046293", "location_code": "hk", "company": "Ralph Lauren", "job_title": "Inventory Control Analyst, Accounting Operation", "description": "Position Overview\u00a0\n\nThe candidate\u2019s primary responsibility is to assist in the maintenance of inventory accuracy in our merchandising and financial systems and to oversee and approve the work of staff.\u00a0 This will require providing timely support to all divisions within Asia-Pacific. This candidate will also work toward development and implementation of standard policies, procedures and controls and will participate in strategy formulation, project management and execution, career development, benchmarking and reporting, ongoing process improvement, enhancing controls, and minimizing costs.\u00a0\n\nEssential Duties & Responsibilities\u00a0\n\nAssist in inventory related support efforts and ensure timely resolution of requests\nSchedule and coordinate physical inventories and cycle counts in all divisions including book cutoff (freeze), capturing counts and sales, research, reconciling, applying adjustments, and shrink reporting\nPrepare, review and approve inventory adjustments processed within Inventory Control department including, but not limited to RTV\u2019s, MOS, sell-offs, transfers, etc.\nEnsure store compliance with inventory related procedures including distributions, transfers, MOS, physical inventory prep and execution, etc.\nLiaison between Inventory Control, DC Operations, Planning & Buying, Store Operations, Asset Protection, and Stores to provide assistance with inventory related issues\nPartner with DC Transportation in administering and processing claims\nCoordinate and participate in reporting (Scorecard) and internal control documentation and testing\nPartnering with Accounting eg: \u00a0reconciliation of inventory data, inventory analysis of P&L and B/S accounts and audit questions.\nSupport year-end audit preparation with inventory related documentations\nExperience, Skills & Knowledge\nMinimum 2 years\u2019 of Inventory Control experience ideally within a Retail environment\nAccounting or Finance Degree\nExperience in working with various countries within Asia-Pacific region preferred\nEnglish required\nGood written and verbal communication skills\nKnowledge of Financial systems - Microsoft Dynamics AX or similar finance system\nProficient with Microsoft Applications (Excel, Word, PowerPoint, Access, Outlook)\nHighly organized with excellent time management skills\nPositive attitude and sound interpersonal skills", "employment_types": ["Full Time", "Permanent"], "selling_points": ["2+ years Inventory Control experience", "Maintain inventory accuracy within Asia-Pacific", "Accounting or Finance Degree"], "locations": ["Tsim Sha Tsui"], "categories": ["Banking / Finance", "Analyst"], "post_time": "2022-01-13T10:20:05Z", "salary": {"currency": null, "max": null, "min": null, "period": "monthly", "term": null}, "salary_visible": false, "title_keywords": ["analyst", "accounting"], "responsibilities": ["data", "operations", "inventory", "merchandising", "audit", "microsoft dynamics", "communication", "costs", "internal control", "compliance", "implementation", "p&l", "testing", "resolution", "schedule", "provide assistance", "reporting", "management", "review", "procedures", "inventory control", "career development", "documentation", "year-end", "maintenance", "policies", "analysis", "systems", "coordinate", "project management", "planning"], "requirements": {"degrees": ["degree"], "majors": ["finance", "accounting"], "languages": ["english"], "language_level": [], "hard_skills": ["excel", "documentation", "maintenance", "microsoft applications", "analysis", "word", "powerpoint", "project management", "outlook", "dc", "processing", "documentations", "internal control"], "soft_skills": ["communication skills", "organized", "time management skills", "timely", "positive attitude", "project management", "interpersonal skills"], "languages_combined": [{"language": "english", "language_level": []}]}, "experience_required": {"duration": ["minimum 2 years"], "field": ["inventory control", "retail"]}}, {"job_id": "100003009049214", "location_code": "hk", "company": "Shanghai Commercial Bank Ltd", "job_title": "Project Delivery (Customer Data Platform), Officer/ Associate", "description": "Responsibilities:\n\nProvide end to end project management support on customer data platform implementation.\nAssist in project planning, tracking, resourcing and execution.\nCoordinate with the selected vendors, Business, IT, and related departments to provide support on the implementation of data platform.\nSupport analyzing data on business needs across different functions.\nAssist to manage data quality, data analytic tools, data governance, and data migration.\n\nRequirements:\n\nDegree in Computer Science/IT or related discipline.\nMinimum 2 years of related working experience, preferably in banking industry.\nKnowledge in Big Data Platform tools with experience in managing hybrid Cloud IaaS environments is an advantage\nProactive with good communication skills.\nGood command of spoken and written English and Chinese. Mandarin is an advantage.\n\nAttractive remuneration package will be offered to the right candidates. Interested parties please click\u00a0\"Apply Now\"\u00a0to submit your full resume with current and expected salary to the\u00a0Human Resources Division.\n\nPlease visit us at\u00a0www.shacombank.com.hk\u00a0for more information about our Bank.\n\nAll personal data collected will be used for recruitment related purposes strictly in accordance with the Bank's personal data policies, a copy of which will be provided immediately upon request by contacting our Personal Data Compliance Officer. Applicants who are not contacted within two months may consider their applications unsuccessful and the personal data collected from the applicants will be retained for no longer than two years from the date of rejection during which the applicants may be considered for other suitable positions within the Bank.", "employment_types": ["Full Time", "Permanent"], "selling_points": ["Provide end to end project management support", "Coordinate with the selected vendors, Business, IT", "Support analyzing data on business needs"], "locations": ["Mong Kok"], "categories": ["Banking / Finance", "Analyst", "Others"], "post_time": "2022-01-15T03:50:12Z", "salary": {"currency": null, "max": null, "min": null, "period": "monthly", "term": null}, "salary_visible": false, "title_keywords": ["officer", "associate"], "responsibilities": ["project planning", "provide support", "data", "coordinate with", "implementation", "quality", "project management", "customer data", "migration", "tracking"], "requirements": {"degrees": ["degree"], "majors": ["it", "computer science"], "languages": ["english", "chinese", "mandarin"], "language_level": ["advantage", "good command"], "hard_skills": [], "soft_skills": ["communication skills", "proactive"], "languages_combined": [{"language": "english", "language_level": ["good command"]}, {"language": "chinese", "language_level": ["good command"]}, {"language": "mandarin", "language_level": ["advantage"]}]}, "experience_required": {"duration": ["minimum 2 years"], "field": ["related", "banking industry"]}}, {"job_id": "100003009049341", "location_code": "hk", "company": "Citibank (Hong Kong) Limited", "job_title": "Technology Business Analyst - Assistant Vice President", "description": "Job Description :\nThe IT Business Senior Analyst is an intermediate-level position responsible for liaising between business users and technologists to exchange information in a concise, logical and understandable way in coordination with the Technology team. The overall objective of this role is to contribute to continuous iterative exploration and investigation of business performance and other measures to gain insight and drive business planning.\nResponsibilities:\nFormulate and define systems scope and objectives for complex projects and foster communication between business leaders and IT\nConsult with users and clients to solve complex system issues/problems through in-depth evaluation of business processes, systems and industry standards and recommends solutions\nSupport system change processes from requirements through implementation and provide input based on analysis of information\nConsult with business clients to determine system functional specifications and provides user and operational support\nIdentify and communicate risks and impacts, considering business implications of the application of technology to the current business environment\nAct as advisor or coach to new or lower level analysts and work as a team to achieve business objectives, performing other duties and functions as assigned\nHas the ability to operate with a limited level of direct supervision.\nCan exercise independence of judgement and autonomy.\nActs as SME to senior stakeholders and /or other team members.\nAppropriately assess risk when business decisions are made, demonstrating particular consideration for the firm's reputation and safeguarding Citigroup, its clients and assets, by driving compliance with applicable laws, rules and regulations, adhering to Policy, applying sound ethical judgment regarding personal behavior, conduct and business practices, and escalating, managing and reporting control issues with transparency.\n\nQualifications:\n5-8 years of relevant experience\nProficiency in MS Office (Word, Excel, Visio, PowerPoint) with extensive experience using Excel for data analysis\nExperience in agile methodology, writing business and functional requirements document and driving user stories grooming sessions\nStrong domain knowledge on consumer/retail banking products and regulations\nExperience in reviewing and writing test cases\nCandidates with ITIL certification highly preferred\nExperience with all phases of Software Development Life Cycle (SDLC)\nComprehensive knowledge of the principles of business analysis\nIIBA certifications such as ECBA, CCBA and CBAP will be a strong advantage\nConsistently demonstrate clear and concise written and verbal communication in English\nFluency in Cantonese and/or Mandarin will be a plus\n\nEducation:\nBachelor's degree/University degree or equivalent experience\n\nInterested candidates, please click APPLY NOW \u00a0to apply.\n\n\n-------------------------------------------------\nJob Family Group:\u00a0Technology\n-------------------------------------------------\nJob Family:Business Analysis / Client Services\n------------------------------------------------------\nTime Type:\n------------------------------------------------------\nCiti is an equal opportunity and affirmative action employer.\nQualified applicants will receive consideration without regard to their race, color, religion, sex, sexual orientation, gender identity, national origin, disability, or status as a protected veteran.\nCitigroup Inc. and its subsidiaries (\"Citi\") invite all qualified interested applicants to apply for career opportunities. If you are a person with a disability and need a reasonable accommodation to use our search tools and/or apply for a career opportunity review .\nView the \"\" poster. View the .", "employment_types": ["Full Time"], "selling_points": ["Formulate and define systems scope and objectives", "Consult with users and clients", "5-8 years of relevant experience"], "locations": ["Not Specified"], "categories": ["Banking / Finance", "Analyst", "Others", "Information Technology (IT)", "Others"], "post_time": "2022-01-14T08:30:24Z", "salary": {"currency": null, "max": null, "min": null, "period": "monthly", "term": null}, "salary_visible": false, "title_keywords": ["business analyst", "assistant vice president"], "responsibilities": ["regulations", "operational support", "software", "coordination with", "communication", "evaluation", "sme", "control", "business analysis", "other duties", "compliance", "implementation", "banking", "reporting", "investigation", "data analysis", "specifications", "analysis", "systems", "demonstrating particular consideration", "assess risk", "planning"], "requirements": {"degrees": ["university degree", "degree", "bachelor"], "majors": [], "languages": ["cantonese", "english", "mandarin"], "language_level": ["fluency"], "hard_skills": ["itil", "excel", "plus", "agile", "analysis", "word", "powerpoint", "sdlc", "exchange", "ms office"], "soft_skills": ["agile", "work as a team", "responsible", "communication", "clear", "comprehensive", "ethical", "coordination", "business environment", "extensive"], "languages_combined": [{"language": "cantonese", "language_level": ["fluency"]}, {"language": "english", "language_level": []}, {"language": "mandarin", "language_level": ["fluency"]}]}, "experience_required": {"duration": ["5-8 years"], "field": ["data analysis", "business", "relevant experience", "writing", "software development"]}}, {"job_id": "100003009047769", "location_code": "hk", "company": "Public Bank (Hong Kong) Ltd", "job_title": "Officer \u2013 Risk Management (Ref: JD-RMO)", "description": "Assist in review of risk management framework, policies and procedures\nConduct risk analysis and assessment to identify and monitor major risks of the Bank\nPerform ad hoc tasks and projects assigned by supervisor\nUniversity Degree in Finance, Economics, Risk Management, Mathematics or other related disciplines with minimum 1 year relevant working experience\nExperience in asset and liability management will be an advantage\nSelf-motivated with good interpersonal and communication skill in both English and Chinese\nProficient in PC applications, including MS Excel\nCFA / FRM Level I or above is preferable\n\nTo apply, interested parties please follow the application methods available in the Bank\u2019s career website\u00a0https://www.publicbank.com.hk/en/aboutus/careeropportunities. You can send us your resume quoting our job reference number together with present &\u00a0expected salary (a must)\u00a0to the Human Resources Department by email or fax at\u00a02815 3157\u00a0or by post to\u00a0Human Resources Department, 12/F, Public Bank Centre, 120 Des Voeux Road Central, Hong Kong. You may also visit our career website for other career opportunities available within our Group.\n\nPersonal data collected will be used for recruitment purpose only and will be treated in accordance with the Bank\u2019s Personal Information Collection Statement, a copy of which has been available in the Bank\u2019s career website.", "employment_types": ["Full Time", "Permanent"], "selling_points": [], "locations": ["Not Specified"], "categories": ["Banking / Finance", "Analyst", "Professional Services", "Business Analysis / Data Analysis", "Risk Management"], "post_time": "2022-01-15T03:49:06Z", "salary": {"currency": null, "max": null, "min": null, "period": null, "term": null}, "salary_visible": false, "title_keywords": ["officer"], "responsibilities": ["management", "policies", "review", "procedures", "monitor", "ad hoc tasks", "communication", "risk analysis"], "requirements": {"degrees": ["university degree"], "majors": ["mathematics", "risk management", "finance", "economics", "related disciplines"], "languages": ["english", "chinese"], "language_level": ["good"], "hard_skills": ["cfa", "analysis", "pc applications", "ms excel", "frm"], "soft_skills": ["self-motivated", "communication skill", "interpersonal"], "languages_combined": [{"language": "english", "language_level": ["good"]}, {"language": "chinese", "language_level": ["good"]}]}, "experience_required": {"duration": ["minimum 1 year"], "field": ["risk management", "management", "related", "finance", "relevant working experience"]}}, {"job_id": "100003009051038", "location_code": "hk", "company": "Varitronix Ltd", "job_title": "Assistant Manager \u2013 Finance (Investment Team)", "description": "Responsibilities:\n\nSupport the Senior Manager to advice to the CEO, CFO and the Board on matters related to investment and IR matters\n\nFor investment:\n\n\nContinuously monitor new investment projects and provide analysis reports\nAssist the senior management team to draft business plans\nCorporate and communicate with various internal and external partners, handle industry research, due diligence, valuation and other associated tasks independently, Candidate with China Market knowledge and culture are strongly preferred\nPrepare investment memorandums, presentations and portfolio management reports\nIdentify investment target, perform due diligence, contract negotiation, financing strategic and post-investment management\nPost investment management, to provide advice to senior management team and make the best effort to contribute to the success of the investment\n\nFor Investor Relationship (IR):\n\n\nConduct regular market research and update top management with the latest market information\nPrepare corporate presentation for investor meeting\nOrganize roadshow or conference call with investor\n\n\nRequirements:\n\n\nDegree holder with 3 - 5 years\u2019 experience in corporate strategy, M&A, investment and PE experience\nProactive and good communication skills\nAble to work independently & with good time management to meet tight deadlines\nDetailed-minded. Strong research & financial modelling skills\nStrong numerical capabilities and problem-solving skills\nExcellent in PowerPoint, Excel and writing capabilities\nExcellent written and oral communication skills in English, Cantonese and Mandarin\nCandidates with higher experience will be considered as \u201cManager - Investment\u201d\nBig 4 candidates are also welcomed\n\nWe offer:\n\n5-day Work\nFull staff benefits including medical & life insurance coverage\nOngoing career development path\n\nInterested parties please send your full resume to the HR Department, Varitronix Group, Unit A-F Legend Tower, 7 Shing Yip Street, Kwun Tong, Kowloon, Hong Kong or email through \"Apply Now\". Our company information can be viewed at our website www.boevx.com.\n\nAll applications will be treated in the strictest confidence. Personal data provided will be used for recruitment purpose only and in accordance with the Code of Practice on Human Resource Management.", "employment_types": ["Full Time", "Permanent"], "selling_points": ["Advise Senior Manage, CEO, CFO on investment tasks", "Investment analysis, Investor relationship mgmt", "Degreee, 3-5 yrs M&A, investment & PE, 5 day week"], "locations": ["Kwun Tong Area"], "categories": ["Banking / Finance", "Analyst", "Investment", "Others"], "post_time": "2022-01-15T01:24:06Z", "salary": {"currency": null, "max": null, "min": null, "period": "monthly", "term": null}, "salary_visible": false, "title_keywords": ["assistant manager"], "responsibilities": ["communicate with", "due diligence", "valuation", "management", "market information", "analysis reports", "monitor", "market research", "business plans", "presentations", "management reports", "provide advice", "senior management"], "requirements": {"degrees": ["degree holder"], "majors": [], "languages": ["cantonese", "english", "mandarin"], "language_level": ["excellent"], "hard_skills": ["problem-solving skills", "excel", "pe", "powerpoint"], "soft_skills": ["communication skills", "work independently", "proactive", "meet tight deadlines", "oral", "problem-solving skills", "time management", "detailed"], "languages_combined": [{"language": "cantonese", "language_level": ["excellent"]}, {"language": "english", "language_level": ["excellent"]}, {"language": "mandarin", "language_level": ["excellent"]}]}, "experience_required": {"duration": ["3 - 5 years"], "field": ["investment"]}}, {"job_id": "100003009040255", "location_code": "hk", "company": "iFAST Financial (HK) Limited", "job_title": "Research Analyst, Fixed Income", "description": "Responsibilities\u00a0\n\nAnalyze and research on fixed income securities and markets, with a primary focus on Asian USD, CNY and HKD credits;\nProvide timely analytical reports, investment recommendations and updated information to clients;\nDevelop and enhance analysis tools to support investment recommendations;\nPrepare presentation materials and participate in presenting to clients and colleagues;\nPerform other ad-hoc projects as assigned.\n\n\u00a0Requirements\u00a0\n\nA good degree in Economic/ Finance/ Mathematics/ Accounting or related discipline. Fresh graduates are welcomed to apply;\n1 to 2 years of experience in investment research industry will be an advantage;\nKnowledge in bond and other fixed income products, fundamental credit and relative value analysis;\nExcellent writing and presentation skills in both English and Chinese;\nStrong analytical ability and sensitive to numbers, with enthusiasm in conducting investment research;\nCandidate should be able to think independently, willing to assert his/her views, and open-minded with disagreements and criticisms;\nDeep-seated belief in, and alignment with the iFAST Values, especially in empowering the investor community with the tools and education to make informed investment decisions;\n\nOur offer:\u00a0\n\nCareer development prospect;\nAttractive remuneration;\n5-day working week;\n21+ days annual leave for all staff;\nMedical, dental and life Insurance;\nPerformance bonus and company shares;\nEducation allowance and monthly sports allowance.\n\nInterested parties please send your full resume by clicking \"APPLY NOW\".\nOur company is an equal opportunities employer and welcome application from all qualified candidates.\u00a0Information provided will be treated with strict confidential and be used for the purpose of selection only.\u00a0Applicants who are not invited for interview within 10 weeks may consider their applications unsuccessful. Personal data of unsuccessful applicants will be destroyed within 12 months.", "employment_types": ["Full Time", "Permanent"], "selling_points": ["Provide analytical reports, investment information", "21+ days Annual Leave for all staff", "Performance bonus and company shares"], "locations": ["Central"], "categories": ["Banking / Finance", "Analyst"], "post_time": "2022-01-12T02:02:08Z", "salary": {"currency": null, "max": null, "min": null, "period": "monthly", "term": null}, "salary_visible": false, "title_keywords": ["research analyst"], "responsibilities": ["analysis", "ad-hoc projects", "reports", "develop"], "requirements": {"degrees": ["degree"], "majors": ["finance", "accounting", "mathematics"], "languages": ["english", "chinese"], "language_level": ["excellent"], "hard_skills": ["make", "analysis"], "soft_skills": ["independently", "open-minded", "deep", "presentation skills", "sensitive to numbers"], "languages_combined": [{"language": "english", "language_level": ["excellent"]}, {"language": "chinese", "language_level": ["excellent"]}]}, "experience_required": {"duration": ["1 to 2 years"], "field": ["research", "investment"]}}, {"job_id": "100003009044607", "location_code": "hk", "company": "Eclipse Trading", "job_title": "Junior Trading Analyst", "description": "Junior Trading Analyst\n\nAt Eclipse, we monitor thousands of listed derivatives every day. Strong trading automation and analytics are crucial to ensure we capitalise on profitable opportunities. Our trading analysts are responsible for providing valuable tools along with data driven insights to enhance our trading. The successful candidate will be a junior member of the team based in our headquarters in Hong Kong.\n\nResponsibilities and Duties\u00a0\n\nWork with traders to identify and solve technical trading problems, and implement automated solutions\nWork with quants to conduct detailed trading research by collecting and analysing data from various sources\nWork with developers to improve the efficiency and algorithms of our in-house trading software\n\nWhat you offer\n\nBachelor's degree or higher in Mathematics, Engineering, Computer Science, Finance, or similar discipline\nDemonstrated quantitative and problem-solving abilities\nIntellectual curiosity and a genuine interest in trading and financial markets\nExperience in a \u201cgeneral purpose\u201d programming language - Python (preferred), Julia, R or Matlab\nExcellent written and verbal communication skills\nPreferred:\nexperience in the trading division of a proprietary trading company or bank\nexperience in data analysis or statistics, and SQL\nexperience using Excel and writing VBA\nexperience working in Linux environment\n\nWhat we offer\n\nTraining in derivatives pricing, trading strategies and systems\nA multi-cultural environment with reasonable work hours\nAn innovative company, encouraging the exploration of new technologies and ideas\nA flat management structure, where everyone\u2019s voice is valued\nHands-on experience in the most exciting part of the financial industry, with a direct impact on trading\n\nAll information provided will be treated in strict confidence and used solely for recruitment purposes.\nDue to the high number of responses that we receive, we are only able to respond to successful applicants.", "employment_types": ["Full Time", "Permanent"], "selling_points": ["Bachelor\u2019s degree in a quantitative discipline", "Training in derivatives pricing", "Competitive salary and bonus"], "locations": ["Causeway Bay"], "categories": ["Banking / Finance", "Analyst", "Dealing & Trading", "Equities / Capital Markets"], "post_time": "2022-01-13T04:49:41Z", "salary": {"currency": null, "max": null, "min": null, "period": "monthly", "term": null}, "salary_visible": false, "title_keywords": ["analyst", "junior"], "responsibilities": ["software", "data"], "requirements": {"degrees": [], "majors": [], "languages": [], "language_level": [], "hard_skills": [], "soft_skills": [], "languages_combined": []}, "experience_required": {"duration": [], "field": []}}, {"job_id": "100003009050164", "location_code": "hk", "company": "Nanyang Commercial Bank", "job_title": "Economist (Ref: LB8003-00-JDB)", "description": "Write research reports and give presentations on macroeconomics and financial markets, provide forecasts of economic and financial markets indicators, concisely\u00a0 answer media\u2019s questions on economic issues, compile and analyze industry intelligence.\n\nRequirements:\n\nMaster\u2019s degree or above in Economics;\nAt least 3 years of experience in economic research, preferably in the banking sector;\nExcellent analytical and presentation skills;\nA critical thinker willing to challenge mainstream views;\nGood command of English, Chinese and Mandarin.\n\n\u00a0(Candidate with more experience will be considered as Senior Economist)\n\nIf you are flexible enough and zeal for a harmonious and supportive working environment where enables you to grow and succeed professionally, please send a full resume indicating your public examination results (HKCEE and HKALE / HKDSE), your present and expected salary and quoting reference number attention to\u00a0Talent Acquisition Division, Nanyang Commercial Bank, 151 Des Voeux Road Central, Hong Kong or apply through email. For details, please visit https://www.ncb.com.hk/ and select the page Recruit.\n\nWe are an Equal Opportunities Employer. Data collected would be used for recruitment purposes only. Applicants who do not hear from us within 8 weeks may consider their applications unsuccessful and their data will be destroyed within 12 months of receipt.", "employment_types": ["Full Time", "Permanent"], "selling_points": ["Write research reports on macroeconomics", "Provide forecasts for economic & financial markets", "Master\u2019s degree with at least 3 years relevant exp"], "locations": ["Central & Western Area"], "categories": ["Banking / Finance", "Analyst", "Retail Banking", "Equities / Capital Markets"], "post_time": "2022-01-15T03:50:52Z", "salary": {"currency": null, "max": null, "min": null, "period": "monthly", "term": null}, "salary_visible": false, "title_keywords": ["economist"], "responsibilities": ["data", "presentations", "recruitment", "reports", "banking"], "requirements": {"degrees": ["degree or above", "hkdse", "master"], "majors": ["economics"], "languages": ["english", "chinese", "mandarin"], "language_level": ["good command"], "hard_skills": ["presentations"], "soft_skills": ["flexible", "supportive", "presentation skills", "harmonious"], "languages_combined": [{"language": "english", "language_level": ["good command"]}, {"language": "chinese", "language_level": ["good command"]}, {"language": "mandarin", "language_level": ["good command"]}]}, "experience_required": {"duration": ["at least 3 years"], "field": ["research", "banking sector"]}}, {"job_id": "100003009049562", "location_code": "hk", "company": "Shanghai Commercial Bank Ltd", "job_title": "Assistant Vice President / Manager, Investment & Insurance Compliance", "description": "Responsibilities:\n\nProvide advisory services on Investment and Insurance businesses for compliance with relevant regulatory requirements\nProvide investment & insurance compliance development updates to Senior Management and assess the impact on the business and operation units\nParticipate in new product & service development project and advise on compliance matters\nReview staff sales script as well as marketing materials\nDevelop and review compliance policies and guidelines in relation to Investment and Insurance products\nDeliver investment compliance training to relevant Bank's staffs\nLiaise with external regulators and auditors on investment and insurance compliance matters\nHandle ad hoc projects assigned from management\n\nRequirements:\n\nDegree holder in Business Administration, Risk Management, Finance, Law or related disciplines\nMinimum 8 years of banking industry with compliance or related experience\nProficient with banking operations and solid knowledge of Investment & Insurance products\nStrong knowledge of regulatory requirements such as SFO, SFC's Code of Conduct and HKMA circulars etc.\nResponsible, detailed-mind, well-organized with good communication skills\n\n(Candidates with less experience will be considered for the position of Manager)\n\nAttractive remuneration package will be offered to the right candidates. Interested parties please click\u00a0\"Apply Now\"\u00a0to submit your full resume with current and expected salary to the\u00a0Human Resources Division.\n\nPlease visit us at www.shacombank.com.hk for more information about our Bank.\n\nAll personal data collected will be used for recruitment related purposes strictly in accordance with the Bank's personal data policies, a copy of which will be provided immediately upon request by contacting our Personal Data Compliance Officer at the above email address. Applicants who are not contacted within two months may consider their applications unsuccessful and the personal data collected will be destroyed within 12 months of receipt.", "employment_types": ["Full Time", "Permanent"], "selling_points": ["Provide advisory on I&I businesses for compliance", "Provide I&I compliance development updates", "New product & service development project"], "locations": ["Not Specified"], "categories": ["Banking / Finance", "Analyst", "Others", "Professional Services", "Legal & Compliance"], "post_time": "2022-01-15T03:50:32Z", "salary": {"currency": null, "max": null, "min": null, "period": "monthly", "term": null}, "salary_visible": false, "title_keywords": ["manager", "assistant vice president"], "responsibilities": ["management", "guidelines", "regulatory requirements", "policies", "review", "compliance", "develop", "liaise with", "ad hoc projects", "marketing materials", "senior management", "insurance"], "requirements": {"degrees": ["degree holder"], "majors": ["risk management", "business administration", "law", "finance", "related disciplines"], "languages": [], "language_level": [], "hard_skills": ["hkma", "code", "sfo"], "soft_skills": ["communication skills", "well-organized", "responsible", "detailed"], "languages_combined": []}, "experience_required": {"duration": ["minimum 8 years"], "field": ["related", "banking industry", "compliance"]}}, {"job_id": "100003009049424", "location_code": "hk", "company": "Shanghai Commercial Bank Ltd", "job_title": "Assistant Manager / Manager, Compliance Review", "description": "Responsibilities:\n\nAssist in developing a risk-based compliance review program\nConduct compliance reviews and on-site visits to business units, local and overseas branches, and subsidiaries\nPrepare compliance review reports to highlight exceptions and provide recommendations for ongoing improvement of the Bank's operations\nPrepare regular management reports on compliance updates and issues\nHandle enquiries from auditors and regulators\nPerform ad-hoc tasks assigned from time to time\nRequirements:\n\nDegree holder in Business Administration, Accounting, Risk Management, Law or related disciplines\nMinimum 3 years experience in areas related to\u00a0 Audit, Compliance or Control functions\nFair knowledge of compliance, AML and local regulations\nBasic understanding of compliance review and/or audit standard and methodology\nGood report writing, analytical and interpersonal skills\nResponsible, detailed-mind, well-organized with good communication skills\nOccasional travel to overseas countries required\n\nAttractive remuneration package will be offered to the right candidates. Interested parties please click \"Apply Now\" to submit your full resume with current and expected salary to the Human Resources Division.\n\nPlease visit us at www.shacombank.com.hk for more information about our Bank.\n\nAll personal data collected will be used for recruitment related purposes strictly in accordance with the Bank's personal data policies, a copy of which will be provided immediately upon request by contacting our Personal Data Compliance Officer. Applicants who are not contacted within two months may consider their applications unsuccessful and the personal data collected from the applicants will be retained for no longer than two years from the date of rejection during which the applicants may be considered for other suitable positions within the bank.", "employment_types": ["Full Time", "Permanent"], "selling_points": ["Develop a risk-based compliance review program", "Conduct compliance reviews and on-site visits", "Prepare compliance review reports"], "locations": ["North Point"], "categories": ["Banking / Finance", "Analyst", "Others"], "post_time": "2022-01-15T03:50:26Z", "salary": {"currency": null, "max": null, "min": null, "period": "monthly", "term": null}, "salary_visible": false, "title_keywords": ["assistant manager", "manager"], "responsibilities": ["operations", "ad-hoc tasks", "review", "compliance", "developing", "handle enquiries", "management reports", "reports", "provide recommendations"], "requirements": {"degrees": ["degree holder"], "majors": ["risk management", "business administration", "law", "related disciplines", "accounting"], "languages": [], "language_level": [], "hard_skills": ["aml", "basic"], "soft_skills": ["communication skills", "responsible", "well-organized", "interpersonal skills", "detailed"], "languages_combined": []}, "experience_required": {"duration": ["minimum 3 years"], "field": ["related", "compliance", "audit"]}}, {"job_id": "100003009042696", "location_code": "hk", "company": "Willis Towers Watson", "job_title": "Graduate Analyst, Retirement Consulting (Actuarial)", "description": "The Role\nOn all aspects of retirement programs, you will be responsible for providing technical support for delivering consulting services to existing and new clients.\n\nYou will have immediate exposure to real client assignments which will draw on your creativity as well as your ability to analyse data and elaborate observations. Such experience will help build your technical knowledge and overall industry expertise while you will also gain exposure from one of the industry\u2019s most comprehensive actuarial training and development programs.\n\nPerformance Objectives:\n\nPartner with consultants to provide actuarial support on client projects involving design, funding, pricing, implementation and management of a full array of retirement programs\nParticipate in projects that help our clients manage the risks of the retirement program of our clients\nPerform actuarial assessments in accordance with regulations and applicable accounting standards\nRecommend solutions to improve the management and governance of the retirement programs of our clients\nFollow best-practice work processes to ensure high quality of service and deliverables to clients and compliance to internal control process\nDevelop professional expertise by progressing towards qualification as an actuary\nProvide feedback to associates working within the project team\nSupport initiatives of Willis Towers Watson, including but not limited to inclusion and diversity\nThe Requirements\n\nBachelor\u2019s degree in actuarial science, mathematics, statistics or other mathematics-related degrees\nPrevious internship experience with an actuarial or a consulting firm is a plus\nExcellent project management and analytical skills\nStrong interpersonal, relationship building / management skills\nHigh energy individual looking for a dynamic, growth-oriented environment\nFlexibility and agility to work in an emerging market situation\nStrong computer software/programming skills\nBeing able to work well under pressure and tight timeline to meet client needs\nEffective written and verbal communication in English and Cantonese in a business context is essential. Fluent in Mandarin is a plus\nWillis Towers Watson is an equal opportunity employer. All qualified applicants will receive consideration for employment without regard to, among other things, race, colour, religion, sex, sexual orientation, gender identity, national origin, age, status as a protected veteran, or disability.\n\nWe are committed to equal employment opportunities at Willis Towers Watson.", "employment_types": ["Full Time", "Permanent"], "selling_points": ["Graduate Analyst", "Actuarial", "Open to  2021 Graduates"], "locations": ["Causeway Bay"], "categories": ["Banking / Finance", "Analyst", "Insurance", "Actuarial", "Others", "Student / Fresh Graduate / No Experience"], "post_time": "2022-01-12T08:25:44Z", "salary": {"currency": null, "max": null, "min": null, "period": "monthly", "term": null}, "salary_visible": false, "title_keywords": ["analyst"], "responsibilities": ["regulations", "management", "development programs", "consulting", "data", "technical support", "software", "compliance", "quality", "implementation", "design", "develop", "communication", "project management", "internal control", "analyse"], "requirements": {"degrees": ["degree", "bachelor"], "majors": ["mathematics", "statistics", "actuarial science"], "languages": ["cantonese", "english", "mandarin"], "language_level": ["fluent"], "hard_skills": ["plus", "analytical skills", "project management", "dynamic", "programming", "internal control"], "soft_skills": ["under pressure", "ability to analyse", "responsible", "analytical skills", "communication", "project management", "committed", "comprehensive", "dynamic", "interpersonal"], "languages_combined": [{"language": "cantonese", "language_level": []}, {"language": "english", "language_level": []}, {"language": "mandarin", "language_level": ["fluent"]}]}, "experience_required": {"duration": [], "field": ["development", "training", "consulting"]}}, {"job_id": "100003009047735", "location_code": "hk", "company": "Public Bank (Hong Kong) Ltd", "job_title": "Officer \u2013 Digital Transformation (Digital Marketing) (Ref: JD-ODTM)", "description": "Perform daily operations for social media platforms, websites and digital marketing campaigns\nManage relevant analytics and optimize various digital campaigns to drive sales\nConduct market survey on digital products and services offered by other financial institutions\nSupport marketing projects and perform ad-hoc duties as assigned\nSupport the hotline related to internet banking, mobile banking and digital banking\nDegree holder with minimum 1 year relevant experience\nGood communication skills in both English and Chinese\nGood interpersonal and coordination skills\n\nTo apply, interested parties please follow the application methods available in the Bank\u2019s career website https://www.publicbank.com.hk/en/aboutus/careeropportunities. You can send us your resume quoting our job reference number together with present & expected salary (a must) to the Human Resources Department by email or fax at 2815 3157 or by post to Human Resources Department, 12/F, Public Bank Centre, 120 Des Voeux Road Central, Hong Kong. You may also visit our career website for other career opportunities available within our Group.\n\nPersonal data collected will be used for recruitment purpose only and will be treated in accordance with the Bank\u2019s Personal Information Collection Statement, a copy of which has been available in the Bank\u2019s career website.", "employment_types": ["Full Time", "Permanent"], "selling_points": [], "locations": ["Not Specified"], "categories": ["Banking / Finance", "Analyst", "Order Processing & Operation / Settlement", "Marketing / Public Relations", "Digital Marketing"], "post_time": "2022-01-15T03:49:02Z", "salary": {"currency": null, "max": null, "min": null, "period": null, "term": null}, "salary_visible": false, "title_keywords": ["officer", "digital marketing"], "responsibilities": ["digital marketing campaigns", "social media platforms", "marketing projects", "banking", "communication", "daily operations", "digital campaigns", "ad-hoc duties", "coordination", "drive sales"], "requirements": {"degrees": ["degree holder"], "majors": [], "languages": ["english", "chinese"], "language_level": ["good"], "hard_skills": ["mobile"], "soft_skills": ["communication skills", "coordination skills", "interpersonal", "ad-hoc duties"], "languages_combined": [{"language": "english", "language_level": ["good"]}, {"language": "chinese", "language_level": ["good"]}]}, "experience_required": {"duration": ["minimum 1 year"], "field": ["relevant experience"]}}, {"job_id": "100003009049492", "location_code": "hk", "company": "Shanghai Commercial Bank Ltd", "job_title": "Manager, Risk Analytics", "description": "The successful candidate will be responsible for various analytical support in risk management related tasks, including model development, maintenance and governance, assist in keeping abreast of risk management regulatory requirements, review and establish policies and procedures in relation to the Bank's risk profile to comply with the regulatory or internal requirements.\n\nResponsibilities:\n\nDevelop, maintain, and enhance models for various risk initiatives (e.g., ICAAP pillar 2 capital, SDST, IRRBB, etc.) and relevant risk analytics methodologies\nDesign, review, enhance, implement, and maintain stress testing methodologies and procedures according to regulatory or internal requirements\nCollaborate with various internal and external units and stakeholders to collect essential information / data for model development and implementing latest risk projects\nAssume new risk management related projects and initiatives as required\nPerform other jobs and ad-hoc projects as assigned by supervisor\nRequirements:\n\nDegree holder or above in Risk Management, Statistics, Quantitative Analysis or related disciplines\nMinimum 5 years of relevant experience in risk analytics / risk management and familiar with banking business and products, with prior experience in risk modeling\nSelf-motivated and detail-oriented with a strong analytical mindset\nGood team player, with high level of curiosity as well as independent problem-solving and multi-tasking ability\nGood computer skills particularly in Excel and VBA, and proficiency in SAS or SQL programming skills would be an advantage\nGood command of both written and spoken English and Chinese\n(Candidates with less experience will be considered for the position of Assistant Manager)\n\n\nAttractive remuneration package will be offered to the right candidates. Interested parties please click \"Apply Now\" to submit your full resume with current and expected salary to the Human Resources Division.\n\nPlease visit us at www.shacombank.com.hk for more information about our Bank.\n\nAll personal data collected will be used for recruitment related purposes strictly in accordance with the Bank's personal data policies, a copy of which will be provided immediately upon request by contacting our Personal Data Compliance Officer. Applicants who are not contacted within two months may consider their applications unsuccessful and the personal data collected from the applicants will be retained for no longer than two years from the date of rejection during which the applicants may be considered for other suitable positions within the Bank.", "employment_types": ["Full Time", "Permanent"], "selling_points": ["Model development, maintenance and governance", "keep abreast of risk mgt regulatory requirement", "Review and establish policies and procedures"], "locations": ["North Point"], "categories": ["Banking / Finance", "Analyst", "Others", "Risk Management"], "post_time": "2022-01-15T03:50:28Z", "salary": {"currency": null, "max": null, "min": null, "period": "monthly", "term": null}, "salary_visible": false, "title_keywords": ["manager"], "responsibilities": ["collaborate with", "data", "review", "procedures", "risk management related projects", "design", "testing", "develop", "maintain", "ad-hoc projects"], "requirements": {"degrees": ["degree holder"], "majors": ["related disciplines", "risk management", "statistics"], "languages": ["english", "chinese"], "language_level": ["good command"], "hard_skills": ["excel", "vba", "sas", "problem-solving", "analysis", "sql", "computer skills", "programming"], "soft_skills": ["good team player", "self-motivated", "independent", "problem-solving", "detail-oriented", "multi-tasking"], "languages_combined": [{"language": "english", "language_level": ["good command"]}, {"language": "chinese", "language_level": ["good command"]}]}, "experience_required": {"duration": ["minimum 5 years"], "field": ["risk management", "business", "relevant experience", "banking"]}}, {"job_id": "100003009038710", "location_code": "hk", "company": "Chiron Management Company Ltd.", "job_title": "Analyst", "description": "\nWe are looking for an Analyst to help us with preparing in-depth market research on the topics related to decentralized finance and the digital asset industry as a whole.\n\nThe Analyst will have the opportunity to closely work with industry experts from leading companies such as Cointelegraph, Coin360, and Bequant, and learn about complex topics (DeFi, regulations, NFT etc.) in the blockchain & digital asset industry.\n\nApart from research, the Analyst will also have the chance to learn consulting best practices and execute strategic initiatives to grow our existing businesses. This will be a rare opportunity for a proactive individual to enter the blockchain industry and work with industry veterans directly.\n\u00a0Responsibilities\n\u2022 Compile research and market data under team leader guidance\n\u2022 Monitor market news and industry movement\n\u2022 Prepare research papers and presentation materials in management consulting standard\n\u2022 Work collaboratively with worldwide team members\n\u2022 Take initiatives to complete critical tasks with \"can-do\" attitude\n\nQualifications\n\u2022 Bachelor's degree in top tier university\n\u2022 Strong verbal and written English\n\u2022 Ability to self-learn new topics quickly\nExperienced in Microsoft Office suite (Excel, Word, PowerPoint)\n\u2022 Excellent communication skills\n\n", "employment_types": ["Full Time"], "selling_points": [], "locations": ["Not Specified"], "categories": ["Accounting", "Audit", "Banking / Finance", "Analyst", "Asset Management"], "post_time": "2022-01-11T07:40:00Z", "salary": {"currency": null, "max": null, "min": null, "period": "monthly", "term": null}, "salary_visible": false, "title_keywords": ["analyst"], "responsibilities": ["regulations", "guidance", "management", "consulting", "monitor", "market research", "communication", "market data"], "requirements": {"degrees": ["degree", "bachelor"], "majors": [], "languages": ["english"], "language_level": [], "hard_skills": ["blockchain", "excel", "word", "powerpoint", "microsoft office suite"], "soft_skills": ["communication skills", "proactive", "presentation", "can-do"], "languages_combined": [{"language": "english", "language_level": []}]}, "experience_required": {"duration": [], "field": []}}, {"job_id": "100003009041385", "location_code": "hk", "company": "China Chengxin (Asia Pacific) Credit Ratings Company Limited", "job_title": "Credit Analyst", "description": "The Job:\u00a0 successful candidates will conduct preliminary and on-going analysis of the credit profile of rated entities (debt issuers and debt securities), involve in formulating credit rating methodologies and industry research, and meet senior management of the rated entities and investors in Hong Kong, Mainland China and elsewhere.\n\nKey Responsibilities\uff1a\n\nPerform credit analysis of the rated entities\uff1b\nMonitor credit quality of issuers, engaging with issuers directly for follow-up clarification and information;\nWriting comprehensive rating reports and participate in management meetings with the rated entities;\nPublication of specific research and commentary;\nOccasional travel may be required\n\nQualifications and requirements:\n\nBachelor\u2019s degree or above holderin finance, accounting, management, economics, mathematics, financial engineering, statistics or related majors;\nOne to three years credit analysis experience or the like;\nStrong quantitative aptitude and qualitative sensitivity;\nHigh proficiency in both written and spoken English and Chinese (Putonghua and Cantonese);\nMature personality with good inter-personal skills;\nIndependent, self-motivated and able to work under pressure;\nWilling to travel to Mainland China and elsewhere.\n\nWe offer successful candidate(s) with attractive remuneration package andexcellent career prospects.\n\nInterested parties please submit application with full resume and expected salary by clicking \"Apply Now\" or by email to\"hr[at]ccxap.com\".\n\nAll information provided will be treated in strict confidence and used for recruitment purpose only.", "employment_types": ["Full Time"], "selling_points": ["Credit Analyst", "Degree holder in finance, accounting, economics", "Development opportunities"], "locations": ["Central"], "categories": ["Banking / Finance", "Analyst"], "post_time": "2022-01-12T03:50:01Z", "salary": {"currency": null, "max": null, "min": null, "period": "monthly", "term": null}, "salary_visible": false, "title_keywords": ["credit analyst"], "responsibilities": ["management", "analysis", "clarification", "quality", "monitor", "reports", "publication"], "requirements": {"degrees": ["degree or above", "bachelor"], "majors": ["mathematics", "engineering", "finance", "economics", "statistics", "accounting"], "languages": ["cantonese", "putonghua", "english", "chinese"], "language_level": ["proficiency"], "hard_skills": ["credit analysis"], "soft_skills": ["self-motivated", "independent", "sensitivity", "inter-personal skills", "mature", "work under pressure"], "languages_combined": [{"language": "cantonese", "language_level": []}, {"language": "putonghua", "language_level": []}, {"language": "english", "language_level": ["proficiency"]}, {"language": "chinese", "language_level": ["proficiency"]}]}, "experience_required": {"duration": ["one to three years"], "field": []}}, {"job_id": "100003009042865", "location_code": "hk", "company": "Modern Terminals Ltd", "job_title": "Financial Analyst (Contract)", "description": "The Role\n\nThe job holder\u2019s major responsibilities are to:\n\n\nSupport the Group Finance function including monthly financial and management reporting\nAnalyse and evaluate business performance\nPrepare and coordinate financial and tax planning, forecasting and budgeting\nParticipate in maintenance and development of Group financial policies and procedures\nAssist in annual audit, external reporting and compliance with shareholders requirements\nThe Person\n\n\u00a0The ideal candidate should have/be:\n\nUniversity degree in Finance/ Accounting\nQualified member of HKICPA or equivalent overseas leading professional accountant institutes is preferred but not essential\nMinimum 3 years relevant working experience\nExperience in group function accounting will be an advantage\nProficient in Microsoft Excel and financial modeling\nGood command of both written and spoken English and Chinese (including Putonghua)\nGood analytical, communication and presentation skills\nSelf motivated, able to work independently and take up challenges\nWe offer competitive remuneration package to the right candidate(s). Please apply in confidence with full resume, present and expected salary and contact telephone number, by clicking \"Apply Now\".\n\n\n\nWhatsApp Hotline: 6283 8297\n\nWe are an equal opportunity employer and welcome applications from all qualified candidates. Personal data collected will be treated in the strictest confidence and only be used for recruitment related purpose. Applicants not invited for interview in 6 weeks may consider their application unsuccessful and your personal data will be destroyed after a period of 6 months.", "employment_types": ["Full Time", "Contract"], "selling_points": [], "locations": ["Kwai Tsing Area"], "categories": ["Accounting", "Audit", "Financial Analyst", "Banking / Finance", "Analyst"], "post_time": "2022-01-12T09:18:30Z", "salary": {"currency": null, "max": null, "min": null, "period": "monthly", "term": null}, "salary_visible": false, "title_keywords": ["financial analyst"], "responsibilities": ["tax", "reporting", "maintenance", "annual audit", "budgeting", "financial policies", "procedures", "compliance", "evaluate", "coordinate", "planning", "management reporting", "forecasting", "analyse"], "requirements": {"degrees": ["university degree"], "majors": ["finance", "accounting"], "languages": ["putonghua", "english", "chinese"], "language_level": ["good command"], "hard_skills": ["microsoft excel", "hkicpa"], "soft_skills": ["work independently", "communication", "self motivated", "presentation skills", "ideal"], "languages_combined": [{"language": "putonghua", "language_level": ["good command"]}, {"language": "english", "language_level": ["good command"]}, {"language": "chinese", "language_level": ["good command"]}]}, "experience_required": {"duration": ["minimum 3 years"], "field": ["accounting", "relevant working experience"]}}, {"job_id": "100003009034289", "location_code": "hk", "company": "Zhongrong PT Securities Limited", "job_title": "Associate-Investment & Research Department", "description": "Responsibilities:\n\nAssist on drafting company and industry research reports;\nBuild valuation models on coverage companies;\nSupport financial modeling and database maintenance;\nProvide research services to institutional, corporate and high net-worth clients;\nAd-hoc research assignment upon management's request.\n\nRequirements:\n\nUniversity degree or above in Finance/Accounting or related disciplines;\nMinimum 2 years working experience in financial industry, prior experiences in Big-4 audit firms, sell-side or buy-side companies could be an advantage;\nQuick learner with an ability to work well under pressure;\nProficient financial analysis and business valuation techniques;\nGood communication, interpersonal and analytical skills;\nExcellent command of spoken and written English and Chinese (Mandarin is a must).\n\nInterest parties please send your\u00a0full resume\u00a0including your\u00a0current salary, expected salary\u00a0and\u00a0availability\u00a0by clicking \"APPLY NOW\".\n\n**Data collected will be used for recruitment purpose only.", "employment_types": ["Full Time", "Permanent"], "selling_points": ["Investment & Research", "Financial Background", "Good development opportunities"], "locations": ["Tsim Sha Tsui"], "categories": ["Banking / Finance", "Analyst", "Investment", "Others"], "post_time": "2022-01-10T03:05:47Z", "salary": {"currency": null, "max": null, "min": null, "period": "monthly", "term": null}, "salary_visible": false, "title_keywords": ["associate"], "responsibilities": ["ad-hoc", "valuation", "management", "maintenance", "financial modeling", "reports", "database"], "requirements": {"degrees": ["degree or above"], "majors": ["related disciplines", "finance", "accounting"], "languages": ["english", "chinese", "mandarin"], "language_level": ["excellent"], "hard_skills": ["financial analysis", "analytical skills"], "soft_skills": ["under pressure", "quick learner", "analytical skills", "communication", "interpersonal"], "languages_combined": [{"language": "english", "language_level": ["excellent"]}, {"language": "chinese", "language_level": ["excellent"]}, {"language": "mandarin", "language_level": ["excellent"]}]}, "experience_required": {"duration": ["minimum 2 years"], "field": ["financial industry", "audit"]}}, {"job_id": "100003009047736", "location_code": "hk", "company": "Public Bank (Hong Kong) Ltd", "job_title": "Officer \u2013 Digital Transformation (General) (Ref: SO-ODTG)", "description": "Coordinate the implementation of information and technological transformation solutions and initiatives.\nConduct market survey and product analysis in response to latest digital products and services features offered by other financial institutions via online media, engagement with customers\nCollaborate with I.T. Department and the relevant departments / business users pertaining to all digital transformation related projects\nSupport the hotline and handle customers\u2019 enquires related to digital banking services.\nSecondary education with minimum 3 years of relevant experience in banking industry\nGood communication skills in both English and Chinese (including Cantonese & Mandarin)\nGood interpersonal and coordination skills\nProficient in MS Office applications (MS Word and Excel)\n\nTo apply, interested parties please follow the application methods available in the Bank\u2019s career website https://www.publicbank.com.hk/en/aboutus/careeropportunities. You can send us your resume quoting our job reference number together with present & expected salary (a must) to the Human Resources Department by email or fax at 2815 3157 or by post to Human Resources Department, 12/F, Public Bank Centre, 120 Des Voeux Road Central, Hong Kong. You may also visit our career website for other career opportunities available within our Group.\n\nPersonal data collected will be used for recruitment purpose only and will be treated in accordance with the Bank\u2019s Personal Information Collection Statement, a copy of which has been available in the Bank\u2019s career website.", "employment_types": ["Full Time", "Permanent"], "selling_points": [], "locations": ["Not Specified"], "categories": ["Banking / Finance", "Analyst", "Others", "Marketing / Public Relations", "Marketing - Market Research"], "post_time": "2022-01-15T03:49:03Z", "salary": {"currency": null, "max": null, "min": null, "period": null, "term": null}, "salary_visible": false, "title_keywords": ["officer"], "responsibilities": ["collaborate with", "analysis", "implementation", "coordinate", "communication", "coordination", "banking"], "requirements": {"degrees": ["secondary education"], "majors": [], "languages": ["cantonese", "english", "chinese", "mandarin"], "language_level": ["good"], "hard_skills": ["ms word", "excel", "analysis", "ms office"], "soft_skills": ["communication skills", "coordination skills", "interpersonal"], "languages_combined": [{"language": "cantonese", "language_level": ["good"]}, {"language": "english", "language_level": ["good"]}, {"language": "chinese", "language_level": ["good"]}, {"language": "mandarin", "language_level": ["good"]}]}, "experience_required": {"duration": ["minimum 3 years"], "field": ["banking industry", "relevant experience", "education"]}}, {"job_id": "100003009047019", "location_code": "hk", "company": "Sinolink Securities (Hong Kong) Company Limited", "job_title": "Corporate Finance- Assistant Manager / Executive", "description": "Responsibilities:\n\n\u00a0\u00a0\u00a0\u00a0\u00a0\u00a0\u00a0\u00a0\u00a0\u00a0 Participate in the execution of corporate finance transactions\n\u00a0\u00a0\u00a0\u00a0\u00a0\u00a0\u00a0\u00a0\u00a0\u00a0 Perform sophisticated industry research and coverage\n\u00a0\u00a0\u00a0\u00a0\u00a0\u00a0\u00a0\u00a0\u00a0\u00a0 Perform due diligence and filing\n\u00a0\u00a0\u00a0\u00a0\u00a0\u00a0\u00a0\u00a0\u00a0\u00a0 Complete assigned task on time and meet tight deadlines\n\nRequirements:\n\n\u00a0\u00a0\u00a0\u00a0\u00a0\u00a0\u00a0\u00a0\u00a0\u00a0 Degree in Finance, Economics, Accounting\n\u00a0\u00a0\u00a0\u00a0\u00a0\u00a0\u00a0\u00a0\u00a0\u00a0 Professional qualification of CFA/CPA is preferred\n\u00a0\u00a0\u00a0\u00a0\u00a0\u00a0\u00a0\u00a0\u00a0\u00a0 1-2 years\u2019\u00a0relevant experience in corporate finance and/or auditing\n\u00a0 \u00a0 \u00a0 \u00a0 \u00a0Experience in accounting in big four is an advantage\n\u00a0 \u00a0 \u00a0 \u00a0 \u00a0\u00a0Candidates who are currently in China would also be considered", "employment_types": ["Full Time"], "selling_points": [], "locations": ["Sheung Wan"], "categories": ["Banking / Finance", "Analyst", "Corporate Banking", "Corporate Finance"], "post_time": "2022-01-14T02:03:18Z", "salary": {"currency": null, "max": null, "min": null, "period": "monthly", "term": null}, "salary_visible": false, "title_keywords": ["assistant manager", "executive", "corporate finance"], "responsibilities": ["due diligence", "transactions"], "requirements": {"degrees": ["degree"], "majors": ["finance", "economics", "accounting"], "languages": [], "language_level": [], "hard_skills": ["cfa", "cpa"], "soft_skills": [], "languages_combined": []}, "experience_required": {"duration": ["1-2 years"], "field": ["accounting", "relevant experience", "big four", "corporate finance"]}}, {"job_id": "100003009039310", "location_code": "hk", "company": "Nice Talent Asset Management Limited", "job_title": "Junior Analyst Program", "description": "Nice Talent Asset Management Limited\n\nNice Talent Asset Management Limited (NTAM) is a fast-growing asset management company with SFC Type 4 and Type 9 licenses. Our team comprised of seasoned bankers and investment advisors from international banks. We are now inviting ambitious talents to take part in the growth of our business.\n\nJunior Analyst Program\n\nWe offer a unique opportunity for high caliber and ambitious young talents who aspire to develop their career in asset management industry. You will have the opportunity to kick-start your career at our company with a well-defined development roadmap. Your on-job training experience will be enriched through a wide range of functions in an asset management firm as we continue to grow our business scale.\n\nOur 2-year Junior Analyst Program is offered in three major function streams: Investment, Operation and Compliance. You will first go through basic training as a junior analyst for the first 6 \u2013 12 months where you will learn about basic operation of an asset management firm. Then you will subsequently rotate through the three different function streams for the rest of the program:\n\nInvestment\n\nWork closely with our investment directors in identifying investment opportunities in a wide range of asset classes i.e. Equities, Fixed income, FX, etc.;\nAsset and support investment directors in monitoring investment portfolio and product development;\nProvide timely market update for our bankers / clients;\nConduct fundamental research with ultimate goal of generating tradable ideas\n\nOperation\n\nPerform pre-trade / post-trade checking with our counterparties;\nPerform back-office function on managing and monitoring our existing investment portfolio;\nSupport our bankers with client related tasks such as account reviews, investment proposal generation;\nDevelop and maintain our internal trade database, systems and various spreadsheets for daily operations\n\nCompliance\n\nLiaise with our external compliance consultant to handle regulatory filings to regulators;\nReview, revise and draft internal manuals, policies and procedures to ensure in compliance with rules and regulation of the SFC;\nAssist with internal risk monitoring, including but not limited to operational and investment risk monitoring\nAssist the team with bank account openings, conduct KYC/AML checking and other necessary investigations\n\nWho are we looking for?\n\nBachelor degree or above in Economics/ Finance/ Mathematics/ Risk management/ Computer engineering would be preferred but not necessary;\nRelevant industry experience is preferred. Recent graduates will also be considered;\nExcellent organization and communication skills;\nPassion and interest in financial market is a must;\nAbility to work under pressure and maintain quality of detailed work while meeting tight deadlines;\nProficient in English, Mandarin and Cantonese;\nKnowledge of VBA or any programming language is a plus", "employment_types": ["Full Time"], "selling_points": [], "locations": ["Wan Chai"], "categories": ["Banking / Finance", "Analyst"], "post_time": "2022-01-11T09:24:47Z", "salary": {"currency": null, "max": null, "min": null, "period": "monthly", "term": null}, "salary_visible": false, "title_keywords": ["analyst", "junior"], "responsibilities": ["asset management"], "requirements": {"degrees": [], "majors": [], "languages": [], "language_level": [], "hard_skills": ["nice"], "soft_skills": [], "languages_combined": []}, "experience_required": {"duration": [], "field": []}}, {"job_id": "100003009048578", "location_code": "hk", "company": "Hang Seng Bank Ltd", "job_title": "Business Performance Manager", "description": "Commercial Banking - Wholesale\u00a0Chief Operating Office\n\nHang Seng\u2019s Commercial Banking business provides customized one-stop financial solutions to our corporate customers, from prime small and medium-sized businesses to publicly listed companies.\u00a0\n\nFor customers conducting business locally or around the world, we offer a comprehensive range of services including corporate lending, trade and receivables finance, structured loan, cash management, investment, treasury services, insurance and e-Banking services.\u00a0 As a reliable financial partner, we attend to the specific business needs of our customers and provide efficient tailor-made banking solutions through our relationship managers and dedicated specialists.\n\nWe are currently seeking a high caliber professional to join our department as\u00a0Business Performance Manager.\n\nPrincipal responsibilities\n\nSupport the formulation of business forecast, financial resources plan and strategic plan to achieve the Bank\u2019s strategic direction and business focus\nPrepare timely and accurate management reports, analyze business trend and customer profitability\nConduct cost management to support implementation of business initiatives\nParticipate in stress testing\nCollaborate with FIN and relevant parties to ensure the accuracy and integrity of financial booking\nPerform various analysis on business operating results and handle enquiries from business users\nLead and participate in various sales MI projects, collaborate with various parties to ensure smooth launch of projects\nRequirements\nUniversity degree in Business Administration, Finance or a related discipline\nMinimum of 5 years\u2019 banking experience, preferably with knowledge of commercial banking products and bank operations\nSound analytical, problem solving, project management and presentation skills\nGreat sense of ownership and servicing mindset to ensure efficient and effective customer service processes\nStrong self-motivation, with ability to work independently and under pressure\nGood application of MS Office, with sound knowledge in MS Excel\nProficiency in both English and Chinese\n\nIf you would like to explore other opportunities at Hang Seng Hong Kong, please visit\u00a0www.hangseng.com/careers/\u00a0for details.\n\nThe health and safety of our employees and candidates is very important to us. Due to the current situation related to the Novel Coronavirus (2019-nCoV), we\u2019re leveraging our digital capabilities to ensure we can continue to recruit top talent at the HSBC Group. \u00a0As your application progresses, you may be asked to use one of our digital tools to help you through your recruitment journey.\u00a0 If so, one of our Resourcing colleagues will explain how our video-interviewing technology will be used throughout the recruitment process and will be on hand to answer any questions you might have.\n\nAll information provided by applicants will be used only for recruitment purposes and will be used strictly in accordance with the Bank's personal data policies, a copy of which may be obtained by the applicant upon request. Unless otherwise instructed in writing by the applicant concerned, applicants may be considered for other suitable positions within the Bank and its related companies. The personal data of unsuccessful job applicants may be retained for a maximum of two years from the date when the job application is rejected and such data may be retained for a longer period if there is a subsisting reason that obliges the Bank to do so, after which the personal data will be destroyed.", "employment_types": ["Full Time", "Permanent"], "selling_points": [], "locations": ["Not Specified"], "categories": ["Banking / Finance", "Analyst", "Corporate Banking"], "post_time": "2022-01-14T06:50:24Z", "salary": {"currency": null, "max": null, "min": null, "period": "monthly", "term": null}, "salary_visible": false, "title_keywords": ["manager"], "responsibilities": ["collaborate with", "cost", "management", "business initiatives", "analysis", "implementation", "testing", "handle enquiries", "management reports", "booking", "forecast", "plan"], "requirements": {"degrees": ["university degree"], "majors": ["finance", "business administration"], "languages": ["english", "chinese"], "language_level": ["proficiency"], "hard_skills": ["reason", "problem solving", "project management", "ms excel", "ms office"], "soft_skills": ["efficient", "work independently", "under pressure", "problem solving", "project management", "presentation skills", "customer service", "self-motivation", "novel"], "languages_combined": [{"language": "english", "language_level": ["proficiency"]}, {"language": "chinese", "language_level": ["proficiency"]}]}, "experience_required": {"duration": ["minimum of 5 years"], "field": ["commercial", "banking experience", "banking"]}}, {"job_id": "100003009049460", "location_code": "hk", "company": "Shanghai Commercial Bank Ltd", "job_title": "Assistant Vice President / Vice President - STR Investigation & Reporting", "description": "Responsibilities:\n\nAct as Money Laundering Report Officer of the Bank and main contact point with local and international law enforcement agencies\nEstablish, review and enhance suspicious transaction reporting, transaction monitoring, screening and sanctions framework including policies, guidelines, procedures, systems and workflows for ensuring their compliance with regulatory requirements as well as effectiveness and efficiency\nReview and approve assessments on internal disclosures, alerts or hits triggered by transaction monitoring and screening systems, and determine whether it is necessary to make a report to respective law enforcement agencies\nEnsure maintenance of all records related to submission, review and approval of investigation and reporting of suspicious transactions\nProvide guidance on how to avoid tipping off\nProvide advice to internal stakeholders in order to ensure clear understanding of any suspicious activity indicators with respect to customers, transactions, products and services\nEnsure adequate support as user role to the development, implementation, enhancement, review, tuning and validation of AML/CFT-related transaction monitoring and screening systems, as well as bank-wide projects involving the STR Investigation & Reporting function of AML Compliance Department\nWork closely with internal stakeholders for ensuring smooth and effective management of the function\nDesign and deliver training to all staff in relation to suspicious transaction reporting, transaction monitoring, screening and sanctions\nManage timely and accurate management reporting information for senior management as well as relevant board-level/ managerial committees\nHandle ad-hoc projects or tasks as assigned\n\nRequirements:\n\nDegree holder in Business Administration Risk Management, Law or related disciplines\nHolder of ACAMS, ECF on AML/CFT certification or equivalent\nMinimum 8 years of financial crime compliance experience\nStrong understanding of AML/CFT controls, procedures and regulations\nFamiliar with SAS transaction monitoring system, Fircosoft screening system and WorldCheck database considered as an advantage\nResponsible and detail-minded with excellent problem solving, analytical, writing and communication skills\nFluent in English, Cantonese and Mandarin\n\nAttractive remuneration package will be offered to the right candidates. Interested parties please click \"Apply Now\" to submit your full resume with current and expected salary to the Human Resources Division.\n\nPlease visit us at www.shacombank.com.hk for more information about our Bank.\n\nAll personal data collected will be used for recruitment related purposes strictly in accordance with the Bank's personal data policies, a copy of which will be provided immediately upon request by contacting our Personal Data Compliance Officer. Applicants who are not contacted within two months may consider their applications unsuccessful and the personal data collected from the applicants will be retained for no longer than two years from the date of rejection during which the applicants may be considered for other suitable positions within the Bank.", "employment_types": ["Full Time", "Permanent"], "selling_points": ["Act as Money Laundering Report Officer of the Bank", "Suspicious transaction reporting and monitoring", "Provide advice to internal stakeholders"], "locations": ["North Point"], "categories": ["Banking / Finance", "Analyst", "Others", "Professional Services", "Legal & Compliance"], "post_time": "2022-01-15T03:50:27Z", "salary": {"currency": null, "max": null, "min": null, "period": "monthly", "term": null}, "salary_visible": false, "title_keywords": ["vice president", "assistant vice president"], "responsibilities": ["regulatory requirements", "transactions", "design", "senior management", "ad-hoc projects", "compliance", "implementation", "report", "reporting", "management", "monitoring", "review", "procedures", "investigation", "contact", "management reporting", "provide guidance", "aml", "maintenance", "guidelines", "policies", "systems", "provide advice"], "requirements": {"degrees": ["degree holder"], "majors": ["related disciplines", "risk management", "business administration", "law"], "languages": ["cantonese", "english", "mandarin"], "language_level": ["fluent"], "hard_skills": ["aml", "sas", "problem solving", "cft", "acams"], "soft_skills": ["detail-minded", "communication skills", "problem solving", "responsible"], "languages_combined": [{"language": "cantonese", "language_level": ["fluent"]}, {"language": "english", "language_level": ["fluent"]}, {"language": "mandarin", "language_level": ["fluent"]}]}, "experience_required": {"duration": ["minimum 8 years"], "field": ["compliance", "financial"]}}, {"job_id": "100003009044302", "location_code": "hk", "company": "KPay Merchant Service Limited", "job_title": "Senior Research Analyst (Fintech/Digital Payment/SaaS)", "description": "About the Company: KPay (kpay-group.com) is a leading digital payment gateway company founded in 2020 by a team of serial entrepreneurs who have successful exited their previous ventures. We currently have a hundred-person team based in Hong Kong. We have aggressive plans to expand across Asia next year and are looking to build out the strategy and investments team, which reports directly to the founders.\n\nOur culture is nimble, entrepreneurial, and fun.\n\nJob Duties:\n\u2022 Conduct company, industry, market, and economic research and monitoring\n\u2022 Financial modelling and analysis\n\u2022 Develop presentation materials in both English and Chinese\n\nJob Requirements :\n\u2022 Relevant work experience (under 5 years) in financial services (PE/VC/hedge funds), investment banking, strategy / management consulting, accounting, digital assets (crypto), or internet start-ups (in particular, fintech involved with payments and/or lending), big data\n\u2022 Excellent communication and interpersonal skills\n\u2022 Excellent written and spoken English and Chinese\n\u2022 Proficiency in MS Word, Excel, PowerPoint, and Chinese word processing\n\u2022 Ability to interact and build relationships with senior management\n\n", "employment_types": ["Full Time", "Permanent"], "selling_points": ["Fast growing fintech firm", "Newly establish team", "Great employment package"], "locations": ["Kwun Tong"], "categories": ["Banking / Finance", "Analyst", "Investment", "Equities / Capital Markets"], "post_time": "2022-01-13T03:42:39Z", "salary": {"currency": null, "max": null, "min": null, "period": "monthly", "term": null}, "salary_visible": false, "title_keywords": ["research analyst"], "responsibilities": ["analysis", "monitoring", "develop"], "requirements": {"degrees": [], "majors": [], "languages": ["english", "chinese"], "language_level": ["excellent", "proficiency"], "hard_skills": ["excel", "crypto", "vc", "chinese word processing", "powerpoint", "pe", "ms word"], "soft_skills": ["communication and interpersonal skills"], "languages_combined": [{"language": "english", "language_level": ["excellent"]}, {"language": "chinese", "language_level": ["excellent", "proficiency"]}]}, "experience_required": {"duration": ["5 years"], "field": ["management", "consulting", "financial services", "investment", "banking", "digital", "accounting"]}}, {"job_id": "100003009045169", "location_code": "hk", "company": "Hang Seng Bank Ltd", "job_title": "Business Analytics Manager", "description": "Wholesale Banking \u2013 WSB Chief Operating Officer\u2019s Office\n\n\nHang Seng\u2019s Wholesale Banking (WSB) business provides customized one-stop financial solutions to our corporate customers, from prime small and medium-sized businesses to publicly listed companies. \u00a0\n\n\nFor customers conducting business locally or around the world, we offer a comprehensive range of services including corporate lending, trade and receivables finance, structured loan, cash management, investment, treasury services, insurance and e-Banking services. \u00a0As a reliable financial partner, we attend to the specific business needs of our customers and provide efficient tailor-made banking solutions through our relationship managers and dedicated specialists.\n\n\nWe are currently seeking a high caliber professional to join our department as\u00a0Business Analytics Manager.\n\n\nPrincipal responsibilities\n\nEnsure implementation of Sales and Services Composite Scorecard and work with IT to deliver the project according to the plan\nEnable visual analytics capability in CMB by deploying interactive dashboards across different business units\nSupport ad-hoc data analytics, sales MI & regular reporting and DataMart development\n\nRequirements\n\nUniversity degree in Quantitative Analysis, statistics, computing or a related discipline\u00a0\nAt least 5 years' data analysis, database management, sales performance analysis, software engineering, and system development\nWith experience on statistical modeling, or data/text mining is an added advantage\u00a0\nWith knowledge of commercial / digital banking preferred\u00a0\nHands-on experience of SAS, SQL, R, Python, MS Access or Excel VBA\nGreat sense of ownership and servicing mindset to ensure efficient and effective customer service processes\nStrong commitment in taking new challenges, self-motivation and creativity\u00a0\nGood communication, analytical and project management skills\nProficiency in both English and Chinese\n\n(Candidates with less experience will be considered for the position of Assistant Business Analytics Manager.)\n\nIf you would like to explore other opportunities at Hang Seng Hong Kong, please visit www.hangseng.com/careers/ for details.\n\nThe health and safety of our employees and candidates is very important to us. Due to the current situation related to the Novel Coronavirus (2019-nCoV), we\u2019re leveraging our digital capabilities to ensure we can continue to recruit top talent at the HSBC Group. As your application progresses, you may be asked to use one of our digital tools to help you through your recruitment journey. If so, one of our Resourcing colleagues will explain how our video-interviewing technology will be used throughout the recruitment process and will be on hand to answer any questions you might have.\n\nAll information provided by applicants will be used only for recruitment purposes and will be used strictly in accordance with the Bank's personal data policies, a copy of which may be obtained by the applicant upon request. Unless otherwise instructed in writing by the applicant concerned, applicants may be considered for other suitable positions within the Bank and its related companies. The personal data of unsuccessful job applicants may be retained for a maximum of two years from the date when the job application is rejected and such data may be retained for a longer period if there is a subsisting reason that obliges the Bank to do so, after which the personal data will be destroyed.", "employment_types": ["Full Time", "Permanent"], "selling_points": [], "locations": ["Not Specified"], "categories": ["Banking / Finance", "Analyst", "Corporate Banking"], "post_time": "2022-01-13T07:21:46Z", "salary": {"currency": null, "max": null, "min": null, "period": "monthly", "term": null}, "salary_visible": false, "title_keywords": ["manager"], "responsibilities": ["ad-hoc", "reporting", "data", "implementation", "plan", "visual"], "requirements": {"degrees": ["university degree"], "majors": ["statistics"], "languages": ["english", "chinese"], "language_level": ["proficiency"], "hard_skills": ["excel", "vba", "sas", "analysis", "reason", "sql", "project management", "python", "r"], "soft_skills": ["efficient", "project management skills", "communication", "hands-on", "customer service", "self-motivation", "novel"], "languages_combined": [{"language": "english", "language_level": ["proficiency"]}, {"language": "chinese", "language_level": ["proficiency"]}]}, "experience_required": {"duration": [], "field": ["sql", "business"]}}, {"job_id": "100003009044065", "location_code": "hk", "company": "Prince Group Holdings Limited", "job_title": "Investment Manager (Digital Assets)", "description": "Our subsidiary company is looking for a high calibre to join with our Company.\n\nJob Description\n\nScreen investment projects, to prepare analysis at various stages and be responsible for the project\u2019s execution\nConduct industry research including valuations, macro trends and comparisons, risk analysis etc.\nFundamental company and industry research include speaking with management teams, industry, and in-house experts\nFormulate investment strategies for the blockchain investments\n\nRequirements\n\nBachelor\u2019s degree or above, preferably in Finance, STEM or related\n3-8 years working experience in PE and investment firms\nIn-depth knowledge and experience in investment, especially TMT and blockchain sectors\nPrevious experience in cryptos is a distinct advantage\nProven track record in managing investment portfolio with returns\nExcellent analytical skills, with strong attention to detail\n\nPlease submit your CV (Chinese and English) online, including your current basic and expected salary. Also, remark the type of your visa and its status in your CV if you need a work permit in Hong Kong.", "employment_types": ["Full Time", "Permanent"], "selling_points": ["TMT and blockchain sectors", "3-8 years of experience in PE and investment firms", "5-day work week, attractive salary package"], "locations": ["Central"], "categories": ["Banking / Finance", "Analyst", "Investment", "Risk Management"], "post_time": "2022-01-13T02:57:02Z", "salary": {"currency": null, "max": null, "min": null, "period": "monthly", "term": null}, "salary_visible": false, "title_keywords": ["investment manager"], "responsibilities": ["management teams", "analysis", "investment strategies", "risk analysis"], "requirements": {"degrees": ["degree or above", "bachelor"], "majors": ["finance"], "languages": ["english", "chinese"], "language_level": ["basic"], "hard_skills": ["blockchain", "basic", "pe", "analytical skills"], "soft_skills": ["attention to detail", "analytical skills"], "languages_combined": [{"language": "english", "language_level": ["basic"]}, {"language": "chinese", "language_level": ["basic"]}]}, "experience_required": {"duration": ["3-8 years"], "field": ["investment"]}}, {"job_id": "100003009043997", "location_code": "hk", "company": "BUPA Asia Limited", "job_title": "Senior Actuarial Analyst", "description": "Responsibilities\u00a0\n\n\nAssist in using software model for actuarial valuation, including technical provision, capital adequacy and reinsurance activities.\nMaintain and enhance models to perform trend analysis and identify risks associated with the technical reserves.\nAssist in IFRS and Solvency II actuarial and financial reporting.\nDocument actuarial results with clear audit trail.\nEnsure compliance with regulations, guidelines, and enterprise policies.\nEnsure quality of data in database and reporting system.\nProvide guidance to junior staff\n\nQualifications\n\n\nAssociated or qualified member of internationally recognized actuarial body. Close to associated member will be considered.\nMinimum of 3 years\u2019 experience on technical reserving and valuation in an insurance company or consulting firm\nPeople management experience is a plus\nHighest levels of integrity and trust.\nGood communication and presentation skill, able to translate complex concepts and figures into story of business\nDisplay good stakeholder management skill which is pro-active and flexible depends on needs and concern of the stakeholder\nDemonstrate ability to identify area that is impactful to the business performance.\n\nBupa offers 5 days work per week and comprehensive remuneration packages including base salary, performance bonus, study assistance plan, non-contributory pension plan, life and medical benefit, dental benefit, annual leave, examination leave, etc.\n\nBupa is an equal opportunity employer and welcomes applications from qualified candidates. Information provided will be treated in strict confidence and only be used for consideration of application with Bupa.\n\nPersonal data collected will be used for recruitment purposes only. Only candidates selected for interviews will be contacted. Bupa will be in touch for any opportunities that matches your profile. All personal data of unsuccessful application will be destroyed 24 months from the date of receiving the application.", "employment_types": ["Full Time", "Permanent"], "selling_points": ["3+ years of relevant exp.", "Assist actuarial valuation", "IFRS and Solvency II report"], "locations": ["Not Specified"], "categories": ["Banking / Finance", "Analyst", "Insurance", "Actuarial", "Others"], "post_time": "2022-01-13T02:43:40Z", "salary": {"currency": null, "max": null, "min": null, "period": "monthly", "term": null}, "salary_visible": false, "title_keywords": ["senior actuarial analyst"], "responsibilities": ["regulations", "software", "consulting", "data", "quality", "audit", "communication", "maintain", "database", "plan", "personal data", "valuation", "reporting", "management", "provide guidance", "guidelines", "policies", "analysis", "ensure compliance", "recruitment", "financial reporting", "insurance"], "requirements": {"degrees": [], "majors": [], "languages": [], "language_level": [], "hard_skills": ["presentation skill", "analysis", "ifrs", "plus"], "soft_skills": ["presentation skill", "flexible", "confidence", "integrity", "clear", "communication", "comprehensive", "pro-active"], "languages_combined": []}, "experience_required": {"duration": ["minimum of 3 years"], "field": ["people management", "insurance", "consulting"]}}, {"job_id": "100003009037177", "location_code": "hk", "company": "Infocast Limited", "job_title": "Business Analyst / Solution Analyst", "description": "Responsibilities\u200b\u00a0\n\nTo conduct in depth requirement analysis, prepare functional specification, and support business testing\nTo lead medium sized project implementation from request initiation to completion\nTo propose, review business requirements and ensure they align with market standards\n\nRequirements\u00a0\u200b\u00a0\n\nDegree holder or above major in Business Administration or Finance\nSolid domain knowledge and business analysis experience in financial industry\nExperiences in software development is highly preferred\nExcellent communication skills, able to articulate and drive discussion across business functions and stakeholders\nExcellent problem solving and user support skills\nStrong customer focus and commitment to delivery\nMaintain can do attitude and stay positive towards challenges\n\nWe Offer\n\n5-day work week\nDiscretionary Bonus\nMedical Insurance\nVariety of Leaves (e.g. Birthday, Marriage Leave etc.)\nVariety of company activities and training\n\nTo Apply:\nWe offer attractive package including medical insurance scheme and good career prospects to the right candidate. Interested parties please send your application via \"Apply Now\" button.\n\nFor more Company information, please feel free to visit our website at www.infocast.com.hk.\n\nAll information received will be kept strictly confidential and only for employment-related purposes.", "employment_types": ["Full Time", "Permanent"], "selling_points": ["Conduct in depth requirement analysis", "Lead medium sized project implementation", "Review business requirements"], "locations": ["Hung Hom"], "categories": ["Banking / Finance", "Analyst", "Professional Services", "Business Analysis / Data Analysis", "Information Technology (IT)", "Product Management / Business Analyst"], "post_time": "2022-01-11T01:59:03Z", "salary": {"currency": null, "max": null, "min": null, "period": "monthly", "term": null}, "salary_visible": false, "title_keywords": ["business analyst", "solution analyst"], "responsibilities": ["analysis", "review", "implementation", "testing"], "requirements": {"degrees": ["degree holder"], "majors": ["finance", "business administration"], "languages": [], "language_level": [], "hard_skills": ["problem solving", "analysis", "focus"], "soft_skills": ["communication skills", "problem solving", "customer focus", "articulate", "positive"], "languages_combined": []}, "experience_required": {"duration": [], "field": ["business analysis", "financial industry", "software development"]}}, {"job_id": "100003009044987", "location_code": "hk", "company": "Hong Kong Aircraft Engineering Co Ltd", "job_title": "Accountant", "description": "HAECO Finance department is looking for candidate to cope with the operation expansion needs and to free up existing resources to deploy in several system development projects in the Company.\n\nHAECO leads in a broad range of aviation products and services that enable our customers to build and operate their aircraft, engines and components safely and efficiently and, in doing so, we seek to deliver sustainable value to all our stakeholders.\u00a0 Seize the opportunity and develop your career by applying to the HAECO today!\n\nScope of Duties:\u00a0\n\n\u00a0Month end closing of a subsidiary of HAECO Group\n\u00a0Prepare annual budget and quarterly forecast\n\u00a0Provide financial analysis on business performance for Business Units\n\u00a0Prepare business valuation model\n\u00a0Evaluate projects and investments opportunities and prepare relevant approval papers\n\u00a0Liaise with internal and external auditors\n\u00a0Perform other ad hoc reporting and projects\n\nRequirements:\u00a0\n\n\u00a0Recognized Degree in Accounting / Finance or related disciplines\n\u00a0Qualified accountant\n\u00a0Keen in developing career in or gaining exposure to management reporting and analysis\n\u00a0Detail-oriented and able to meet tight deadline\n\u00a0Able to manage multiple assignments\n\u00a0Good teamwork and supervisory skills\n\u00a0Good business acumen\n\u00a0Strong numerical sense, communication skills and analytical skills\n\u00a0Good command of English and Mandarin, both written and verbal\n\u00a0Proficient in the use of MS Excel, MS Word and MS PowerPoint\n\nHow to Apply:\n\nPlease send your resume with expected salary, quoting the employer's reference no., to: Human Resources Department - Talent & Partnership Team, Hong Kong Aircraft Engineering Company Limited, 80 South Perimeter Road, Hong Kong International Airport, Lantau, Hong Kong OR submit your application via\u00a0https://careers.haeco.com/hkg/job-openings/\n\nCandidates not contacted 4-6 weeks after submission of applications and/or interviews may consider their application unsuccessful.\n\nAll information provided by candidates will be treated in strict confidence and will be used for employment purpose only.", "employment_types": ["Full Time", "Permanent"], "selling_points": ["Prepare annual budget and quarterly forecast", "Provide financial analysis on business performance", "Qualified accountant, Degree in Accounting/Finance"], "locations": ["Airport Area"], "categories": ["Accounting", "Accountant", "Others", "Banking / Finance", "Analyst"], "post_time": "2022-01-13T06:49:19Z", "salary": {"currency": null, "max": null, "min": null, "period": "monthly", "term": null}, "salary_visible": false, "title_keywords": ["accountant"], "responsibilities": ["valuation", "month end closing", "reporting", "ad hoc", "budget", "financial analysis", "evaluate", "forecast", "liaise with", "external auditors"], "requirements": {"degrees": ["degree"], "majors": ["related disciplines", "finance", "accounting"], "languages": [], "language_level": [], "hard_skills": ["analysis"], "soft_skills": ["keen", "teamwork", "meet tight deadline", "detail-oriented"], "languages_combined": []}, "experience_required": {"duration": [], "field": []}}, {"job_id": "100003009042057", "location_code": "hk", "company": "Wise Ally Holdings Limited", "job_title": "Financial Analyst (Listed Company)", "description": "Responsibilities:\n\nResponsible for financial analysis and management report with commentary to support strategic business planning and monitor business performance;\nWork closely with various internal parties to investigate major variances aim at budgetary controls\nMake use of operational and financial data to enhance management reports and/or schedules and drive actions, i.e. cost savings and/or operational efficiencies\nConduct financial modeling, feasibility studies, returns on investments analysis to facilitate business decisions\nAssist in Listing rules compliance matters and ad-hoc projects as assigned\n\nRequirements:\n\nDegree holder in Accounting, Finance or equivalent discipline;\nQualifies accountant with HKICPA, ACCA or equivalent designations is preferred;\n\nAt least 4 to 5 years of solid audit and/or commercial experience in financial analysis , with electronics product manufacturing or Big 4 experience is an advantage;\nEnergetic; Strong analytical skills and business acumen;\nProficient in both spoken and written Chinese, Mandarin and English;\nExcellent Skills in Excel and Power point application.\n\nWe offer 5-DAY WORK WEEK plus long term career prospect with competitive remuneration package, 13th-month salary, and fringe benefits to the right candidate. Interested parties please apply in full resume including current and expected salary by clicking APPLY NOW.\n\nFor more information, please visit our website: http://www.wiseally.com.hk\n\nPersonal data collected will be used for recruitment purpose only.", "employment_types": ["Full Time", "Permanent"], "selling_points": ["Financial management and control functions", "Degree in Accounting, Finance", "5 days\u2019 work per week, double pay"], "locations": ["Kowloon Bay"], "categories": ["Accounting", "Financial Analyst", "Financial Controller", "Banking / Finance", "Analyst"], "post_time": "2022-01-12T05:46:01Z", "salary": {"currency": null, "max": null, "min": null, "period": "monthly", "term": null}, "salary_visible": false, "title_keywords": ["financial analyst"], "responsibilities": ["cost", "data", "schedules", "financial modeling", "analysis", "monitor", "compliance", "financial analysis", "management reports", "listing", "ad-hoc projects", "management report", "internal parties", "planning"], "requirements": {"degrees": ["degree holder"], "majors": ["finance", "accounting"], "languages": ["english", "chinese", "mandarin"], "language_level": ["proficient"], "hard_skills": ["excel", "acca", "plus", "analytical skills", "financial analysis", "hkicpa", "power point", "acumen"], "soft_skills": ["business acumen", "energetic", "analytical skills"], "languages_combined": [{"language": "english", "language_level": ["proficient"]}, {"language": "chinese", "language_level": ["proficient"]}, {"language": "mandarin", "language_level": ["proficient"]}]}, "experience_required": {"duration": ["at least 4 to 5 years"], "field": ["manufacturing", "big 4", "audit", "commercial", "financial"]}}, {"job_id": "100003009044276", "location_code": "hk", "company": "Pernod Ricard Hong Kong Ltd", "job_title": "Finance Intern (full time internship)", "description": "Position Summary:\n\nSupporting the Regional Business Analysis Director and the Regional Business Analysis team, the Finance Intern will:\n\nSupport the Regional Business Analysis team and affiliates to ensure timeously submission of financial scenarios, and be the gatekeeper of all PR Asia deadlines\nSupport the Regional Business Analysis Director in ad hoc task and requests\nConsolidate affiliates\u2019 submissions and prepare regular reports for management\u2019s review\nAssist other departments in retrieval of data for analysis purpose\n\nThe Finance Intern will obtain a sound understanding of how a multinational company works, through the lenses of a major regional finance department, by observing and exchanging with various stakeholders. He/she will also get a good grasp of underlying dynamics behind financial performance to understand better the Group and Business Model set up in Asia.\n\n\n\nKey Responsibilities:\n\nBusiness analysis\n\nManagement Reports and Reporting system:\nClosely monitor the submission status of affiliates and provide support when necessary\nConsolidate management reports for monthly reporting, estimates, annual budget and strategic plans\nProvide support to affiliates on reporting system functionalities\nMarkets Finance key contact:\nAct as the key contact with affiliates on all issues relating to management reports\nFollow up directly with affiliates to understand the financial submissions and the impact of the business situation\nInteraction with other stakeholders:\n\nAssist other departments in retrieval of financial data for presentation preparation and analysis purpose\nOther ad-hoc reports to top management or projects as assigned\n\n\n\nSkills / Qualifications / Experience:\n\n\nEssential:\n\nBachelor Degree in Finance or similar (In pursue)\nStrong communication, organisation and analytical skills to effectively work with internal and external stakeholders.\nExtremely rigorous\nExcellent Microsoft skills especially in Excel and Powerpoint\nSense of entrepreneurship / takes initiatives\nFluent in English\nWorking days: full time / 6 months\n\nDesirable:\n\nBachelor Degree in Finance or similar (completed)\nFinancial intern experience in Big 4 and/or MNC\nResults orientation, ability to work under pressure and meet tight deadlines\nKnowledge of Oracle/PRISMA/Essbase/Power BI\nOther Asian language", "employment_types": ["Full Time", "Contract", "Internship"], "selling_points": ["Business Analysis ; Regional Exposure", "Finance Intern / 6-month internship", "MNC; Wine & Spirit Industry"], "locations": ["Tsim Sha Tsui"], "categories": ["Banking / Finance", "Analyst", "Others", "Professional Services", "Business Analysis / Data Analysis"], "post_time": "2022-01-13T03:37:36Z", "salary": {"currency": null, "max": null, "min": null, "period": "monthly", "term": null}, "salary_visible": false, "title_keywords": ["internship", "intern"], "responsibilities": ["ad-hoc", "data", "budget", "communication", "regular reports for management", "work under pressure", "ad hoc", "monitor", "reports", "reporting", "provide support", "management", "review", "contact", "strategic plans", "power bi", "analysis", "management reports", "business analysis"], "requirements": {"degrees": ["degree", "bachelor"], "majors": ["finance"], "languages": ["english"], "language_level": ["fluent"], "hard_skills": ["excel", "bi", "analysis", "powerpoint", "analytical skills", "management reports", "oracle"], "soft_skills": ["meet tight deadlines", "analytical skills", "communication", "organisation", "presentation", "work under pressure"], "languages_combined": [{"language": "english", "language_level": ["fluent"]}]}, "experience_required": {"duration": [], "field": ["big 4", "financial"]}}, {"job_id": "100003009037321", "location_code": "hk", "company": "China CITIC Bank International Limited", "job_title": "Assistant Vice President, Business Analyst", "description": "Key Responsibilities\n\nEnsure that the product creates maximum value for its customers and users, and for the Bank\nOverseeing and finalizing business requirement with business units, drive process efficiency with improvement on quality for error and cost reduction.\nDrive and support the business transformation of PBG to a digital and e-savvy best-in-class business model\nProject and stakeholder management, work closely with digital transformation project stakeholders (Business, IT, Compliance, Risk, Legal and Solution providers) to define business objective, document requirement, track risks & issues and manage communications on project updates\nCoordinate and perform detailed business analysis; develop functional/business and technical specifications\nPerform data and business insights related activities including but not limited to mapping current processes, conducting customer journey research, analyzing business related data for insight recovery\nConstruct workflow charts and diagrams; studying system capabilities; writing specifications\nCreating, refining and maintaining user stories and associated deliverables\nAssist and participates in design, development and implementations\nManage multiple conflicting business / technology priorities\n\nRequirements\n\nUnderstandings in both the business opportunities and aspects of latest trend of technology.\nUnderstand industry and market developments relating to own function\nAwareness of both quality and risk, especially compliance-related risk and security issues\nFamiliar with modern prototyping tools\nHolder of Bachelor\u2019s degree in Business Administration, Information Technology, Information\u00a0 Management or related discipline with strong academic performance\nMinimum 6 years of working experience as Digital Business Analyst or similar capacity preferably in the Banking/Finance sector\nExcellent analytical and problem solving skills\nHighly proficient in Excel is a must\nExperience in data analytics software, Jira, Confluence and Tableau is a big plus\n\nFor more details about career opportunities with the Bank, please visit our website http://www.cncbinternational.com/careers/en/index.jsp.\u00a0 Please apply with full resume stating current and expected salaries.\n\nPersonal data collected will be used for recruitment related purposes only. Applicants not invited for interview within 6 weeks may consider their applications unsuccessful. However, applicants may be considered for other suitable positions within the Group for a period of not more than 2 years. Personal data will be destroyed at any time after 3 months.\n\nChina CITIC Bank International is committed to being an equal opportunities employer and intends to provide a work environment free of unlawful discrimination or harassment.\u00a0 All employment decisions will be made in a non-discriminatory manner.", "employment_types": ["Full Time", "Permanent"], "selling_points": ["Creates maximum value", "Drive process efficiency", "Minimum 6 years of experience"], "locations": ["Quarry Bay"], "categories": ["Banking / Finance", "Analyst", "Information Technology (IT)", "Product Management / Business Analyst", "Risk Management"], "post_time": "2022-01-11T02:28:16Z", "salary": {"currency": null, "max": null, "min": null, "period": "monthly", "term": null}, "salary_visible": false, "title_keywords": ["business analyst", "assistant vice president"], "responsibilities": ["cost", "management", "maintaining", "data", "compliance", "quality", "design", "develop", "project updates", "coordinate", "specifications", "business analysis"], "requirements": {"degrees": ["degree", "bachelor"], "majors": ["business administration", "information technology"], "languages": [], "language_level": [], "hard_skills": ["excel", "plus", "data analytics", "tableau", "problem solving skills"], "soft_skills": ["analytical and problem solving skills", "committed"], "languages_combined": []}, "experience_required": {"duration": ["minimum 6 years"], "field": ["finance", "digital", "business", "banking"]}}, {"job_id": "100003009049209", "location_code": "hk", "company": "Shanghai Commercial Bank Ltd", "job_title": "Assistant Vice President / Manager, Operation Efficiency", "description": "Responsibilities:\n\nSupport Team Lead to manage the project portfolio for the Operation Efficiency (OE) Workstream\nStreamline the end-to-end processes to deliver financial results\nCommunicate project progress, deliver recommendations and facilitate decisions with senior executives\nFacilitate continuous monitoring of projects after launch and evaluate the benefit realization achievement\nMeasure effectiveness of the improvement projects via the devised KPIs\nBesides delivering the operation efficiency projects in the OE Workstream, this role may also need to be involved in digital channel projects of the Customer Experiences Workstream to re-engineering the related back end processes\nAs a strong change advocate with \u2018customer focus\u2019 mind-set for process improvement\n\nRequirements:\n\nDegree holder with 8 years of experience in consulting / banking industry with at least 4 years of experiences in process analysis/process improvement/project management.\nSolid experience in managing projects of operation process improvement to enhance efficiency, service quality and customer experience.\nProven ability to build strong, cohesive partnerships and work effectively with the business, operations, technology and other key stakeholders.\nRecognized qualification in project management is desirable, with Six Sigma Black Belt is an advantage.\nGood knowledge of process improvement methodologies is preferred.\nOwnership mind-set, analytical and open-minded with strong communication, facilitation and interpersonal skills.\nGood command of both spoken and written English and Chinese. Mandarin is an advantage.\n\n(Candidate with less experience will be considered as Manager)\n\nAttractive remuneration package will be offered to the right candidates. Interested parties please click \"Apply Now\" to submit your full resume with current and expected salary to the Human Resources Division.\n\nPlease visit us at www.shacombank.com.hk for more information about our Bank.\n\nAll personal data collected will be used for recruitment related purposes strictly in accordance with the Bank's personal data policies, a copy of which will be provided immediately upon request by contacting our Personal Data Compliance Officer. Applicants who are not contacted within two months may consider their applications unsuccessful and the personal data collected from the applicants will be retained for no longer than two years from the date of rejection during which the applicants may be considered for other suitable positions within the Bank.", "employment_types": ["Full Time", "Permanent"], "selling_points": ["End-to-end processes to deliver financial results", "Facilitate continuous monitoring of projects", "Measure effectiveness of the improvement projects"], "locations": ["Kwun Tong"], "categories": ["Banking / Finance", "Analyst", "Others", "Order Processing & Operation / Settlement"], "post_time": "2022-01-15T03:50:11Z", "salary": {"currency": null, "max": null, "min": null, "period": "monthly", "term": null}, "salary_visible": false, "title_keywords": ["manager", "assistant vice president"], "responsibilities": ["project progress", "evaluate", "continuous monitoring", "kpis", "re-engineering"], "requirements": {"degrees": ["degree holder"], "majors": ["project management"], "languages": ["english", "chinese", "mandarin"], "language_level": ["advantage", "good command"], "hard_skills": ["six sigma", "project management", "analysis"], "soft_skills": ["work effectively", "open-minded", "cohesive", "communication", "project management", "interpersonal skills"], "languages_combined": [{"language": "english", "language_level": ["good command"]}, {"language": "chinese", "language_level": ["good command"]}, {"language": "mandarin", "language_level": ["advantage"]}]}, "experience_required": {"duration": ["at least 4 years", "8 years"], "field": ["banking industry", "project management", "operation", "consulting"]}}, {"job_id": "100003009034461", "location_code": "hk", "company": "Pineal Ai Limited", "job_title": "Investment Analyst (Blockchain/Crypto)", "description": "Responsibilities:\n\n1. Conduct market research on market trend, industry index, impact from the policy update, etc.\n\n2. Conduct research and analysis of industries/companies independently and provide analysis reports\n\n3. Strong interest in equity investments and motivation of discovering investment opportunities\n\nRequirements:\n\n1. Bachelor Degree holder or above in Business Administration, Finance, Medical, Computer Science or related disciplines;\n\n2. Minimum 2 years of relevant working experience gained in Dot-com or blockchain industry;\n\n3. Excellent interpersonal skills and be able to work under pressure with minimal supervision;\n\n4. Excellent command of written and spoken English and Chinese", "employment_types": ["Full Time", "Permanent"], "selling_points": [], "locations": ["Central"], "categories": ["Banking / Finance", "Analyst", "Investment", "E-commerce", "Business Development"], "post_time": "2022-01-10T03:26:23Z", "salary": {"currency": null, "max": null, "min": null, "period": "monthly", "term": null}, "salary_visible": false, "title_keywords": ["analyst"], "responsibilities": ["analysis reports", "conduct market research", "analysis", "conduct research"], "requirements": {"degrees": ["bachelor degree holder"], "majors": ["related disciplines", "finance", "business administration", "computer science"], "languages": ["english", "chinese"], "language_level": ["excellent"], "hard_skills": ["blockchain"], "soft_skills": ["interpersonal skills", "work under pressure"], "languages_combined": [{"language": "english", "language_level": ["excellent"]}, {"language": "chinese", "language_level": ["excellent"]}]}, "experience_required": {"duration": ["minimum 2 years"], "field": ["relevant working experience"]}}, {"job_id": "100003009034291", "location_code": "hk", "company": "Zhongrong PT Securities Limited", "job_title": "Analyst/Associate \u2013 Capital Markets", "description": "Job Description:\n\n\nA general capital markets role covering both investment banking and deal-driven investment, and with products exposure to both fixed income and equity.\nSector focus will be mainly in energy (renewable energy, new infrastructure and ESG) and real estate.\nAssess potential deals, prepare pitch book and conduct\u00a0financial\u00a0due diligence.\nConduct fundamental analysis on potential investment opportunities and prepare investment memo.\nVisualize data and present analytical insights to business team and management to facilitate business decisions.\nHandle other ad-hoc projects per senior management request.\n\nRequirements:\n\n\nBachelor\u2019s degree in Accounting and Finance or related disciplines are preferred. Other disciplines should be able to demonstrate competency in financial analysis.\n1-2 years\u2019 experience in financial industry is preferable\nSelf-motivated and proactive\nStrong team spirit and good communication skills\nSolid in corporate finance and accounting analysis\nAnalytical and logical thinking\nCandidate with more experience will be considered as Associate", "employment_types": ["Full Time", "Permanent"], "selling_points": ["Analysis on potential investment opportunities", "Analytical and logical thinking", "Self-motivated and proactive"], "locations": ["Tsim Sha Tsui"], "categories": ["Banking / Finance", "Analyst", "Investment", "Equities / Capital Markets"], "post_time": "2022-01-10T03:05:47Z", "salary": {"currency": null, "max": null, "min": null, "period": "monthly", "term": null}, "salary_visible": false, "title_keywords": ["analyst", "associate"], "responsibilities": ["due diligence", "management", "memo", "data", "analysis", "infrastructure", "banking", "ad-hoc projects", "senior management"], "requirements": {"degrees": ["degree", "bachelor"], "majors": ["related disciplines", "finance", "accounting"], "languages": [], "language_level": [], "hard_skills": ["financial analysis", "analysis"], "soft_skills": ["communication skills", "self-motivated", "proactive", "team spirit"], "languages_combined": []}, "experience_required": {"duration": ["1-2 years"], "field": ["financial industry"]}}, {"job_id": "100003009043306", "location_code": "hk", "company": "Swire Coca-Cola HK Ltd", "job_title": "Commercial Manager (Business Analytics/ Analyst)", "description": "Responsibilities:\n\n\nLead customer performance functions for the Commercial Leadership department including trade promotional management, category management, market, product & customer analysis, customer pricings and customer projects\nDrive company business by conducting market analysis, business forecast, category and brand specific review to identify business opportunities and support fact-based decisions\nTake lead in Trade Promotion Management (TPM) process and own internal TPM tool, evaluate promotion effectiveness and share recommendation key stakeholders\nWork closely with sales teams, take a lead in driving the business performance, identifying opportunities and addressing shortfalls from analysis perspective\nProvide leadership and coaching to the team, upskilling the team on category management and trade promotion management and value-added analytical contribution\nProvide leadership, market insights, analytics, and collaborate with key stakeholders to strategize & deliver core commercial strategies, practices and innovative solutions, to grow SCCHK profitability\nDeliver routine performance tracking and trend analysis by key channels, packs, category & brands to internal stakeholders and business partners\nSupport Commercial Leadership team to manage ad-hoc commercial projects and analysis to drive business priorities\n\nRequirements:\n\nDegree in Business / Marketing or equivalent\nMinimum 8-10 years of working experience, preferably in FMCG but not a must\nExperience in FMCG Sales and Marketing functions, with a focus on Category Management/ Shopper Insights/ Business Intelligence is highly preferred\nExperience in Project Management is preferred\nStrong commercial acumen and attention to details with agile delivery\nUnderstand competitive landscapes, products, and consumer trends with insights to identify business opportunities or risks\u00a0\nAnalytics skillset with the ability to translate data into commercial strategies and solutions to complex problems\nSolid data analysis experience with good numeric sense, and able to work with data in different format from various sources\nStrong presentation skills and able to articulate analysis insights to audience from different backgrounds\nStrong sense of responsibility, self-motivated and result oriented\nKnowledge in Power BI or other data visualization tool is a plus\nProficient in Nielsen NAD and other statistical software is preferred but not a must\nExcellent MS Excel and PowerPoint skills\nExcellent command of spoken and written English and Chinese\n\nPlease apply with full resume, current and expected salary and availability to:\u00a0The Human Resources Manager, Swire Coca-Cola HK, 17-19 Yuen Shun Circuit, Siu Lek Yuen, Shatin, or by clicking \"Apply Now\".\u00a0\n\n*Personal data provided are treated in strictest confidence and for recruitment purposes only. All information will be destroyed after the process completed.*\u00a0", "employment_types": ["Full Time", "Permanent"], "selling_points": ["Market analysis, business forecast, pricing mgt", "FMCG background, strong analytical skills", "Nielsen data handling, Power BI report"], "locations": ["Shatin Area"], "categories": ["Banking / Finance", "Analyst", "Professional Services", "Business Analysis / Data Analysis", "Sales, CS & Business Devpt", "Others"], "post_time": "2022-01-12T10:40:55Z", "salary": {"currency": null, "max": null, "min": null, "period": null, "term": null}, "salary_visible": false, "title_keywords": ["analyst", "manager"], "responsibilities": ["collaborate with", "ad-hoc", "management", "identify business opportunities", "analysis", "review", "teams", "evaluate", "market analysis", "forecast", "tracking"], "requirements": {"degrees": ["degree"], "majors": ["business", "marketing"], "languages": ["english", "chinese"], "language_level": ["excellent"], "hard_skills": ["plus", "bi", "agile", "analysis", "powerpoint", "project management", "ms excel", "data visualization", "focus", "business intelligence", "acumen"], "soft_skills": ["self-motivated", "confidence", "agile", "sense of responsibility", "project management", "presentation skills", "result oriented", "attention to details", "articulate", "focus"], "languages_combined": [{"language": "english", "language_level": ["excellent"]}, {"language": "chinese", "language_level": ["excellent"]}]}, "experience_required": {"duration": ["minimum 8-10 years"], "field": ["management", "fmcg", "data analysis", "project management", "business", "marketing"]}}, {"job_id": "100003009044642", "location_code": "hk", "company": "HKT Consumer Group", "job_title": "Business Analysis Officer / Executive", "description": "Your role\n\nThe jobholder will assist\u00a0in supporting the management accounting and business performance management functions of Consumer Group.\u00a0 Major responsibilities include:\n\nAssist in the evaluation of capex funding cases and post implementation checking\nAssist in the preparation of AOP, BU financial forecast and cost analysis\nProvide support for the preparation of KPI analysis & reports, month-end closing, etc.\nPerform other ah-hoc assignments and projects\n\nTo succeed in this role\n\nHolder of University Degree in Finance, Accounting or related discipline\nAt least\u00a01 years\u2019 relevant working experience in accounting/auditing/business planning\nExperience in building financial models, preparing financial reports and presentations\nStrong numerical sense and analytical mind\nProactive, initiative and able to work independently with minimal supervision\nAble to handle and manage multi-tasks to meet deadlines\nGood interpersonal & communication skills\nGood command of written and spoken English and Chinese\nProficiency in PC\u00a0applications, especially EXCEL spreadsheets\nCandidates with more experience will be considered as Business Analysis Executive\n\nIf you have the desire for an exciting and rewarding career, please send us your resume immediately, quoting the reference number, your present and expected salary via email to Human Resources.\n\nEmail: Shirley.ny.ho@pccw.com", "employment_types": ["Full Time"], "selling_points": [], "locations": ["Quarry Bay"], "categories": ["Accounting", "Audit", "Banking / Finance", "Analyst", "Professional Services", "Business Analysis / Data Analysis"], "post_time": "2022-01-13T04:58:15Z", "salary": {"currency": null, "max": null, "min": null, "period": "monthly", "term": null}, "salary_visible": false, "title_keywords": ["officer", "executive"], "responsibilities": ["management", "provide support", "financial reports", "financial models", "analysis", "capex", "checking", "implementation", "presentations", "communication", "month-end closing", "reports", "forecast", "evaluation", "business analysis", "cost analysis", "auditing", "planning"], "requirements": {"degrees": ["university degree"], "majors": ["finance", "accounting"], "languages": ["english", "chinese"], "language_level": ["good command"], "hard_skills": ["excel", "analysis", "presentations", "pc applications"], "soft_skills": ["communication skills", "work independently", "multi-tasks", "interpersonal", "analytical mind", "meet deadlines", "proactive", "initiative"], "languages_combined": [{"language": "english", "language_level": ["good command"]}, {"language": "chinese", "language_level": ["good command"]}]}, "experience_required": {"duration": ["at least 1 years"], "field": ["relevant working experience", "business", "planning", "business analysis", "accounting", "financial"]}}, {"job_id": "100003009042469", "location_code": "hk", "company": "Bank of Communications Trustee Limited", "job_title": "Contract Business Analyst", "description": "Responsibilities:\nAnalyze user requirement document and review system design documentations to ensure that the functionalities meet the user requirement document\nLead testers to execute UAT including planning, prepare or review test plan and results\nCo-ordinate and monitor UAT progress to ensure development team\u2019s deliverables meet user requirements.\nIdentify key issues and risks throughout the project cycle\nBuild and maintain application/ system documentations and procedures\nPrepare training materials and provide training to business users\nPerform ad-hoc assignment as required\nRequirements:\nDegree holder or above in Business Administration, Information Systems or Actuarial\nMinimum 2 years\u2019 experience in financial industry and business analyst role\nGood understanding of MPF & SFC regulated activities with license preferred\nStrong communication, analytical and problem solving skills\nProficient in both spoken and written English and Chinese, Putonghua a plus\nImmediately available is highly preferred\nCandidates with less experience will be considered as lower position\nPlease click \"Apply Now\" to submit your application.\nPersonal data collected will be used for recruitment purpose only.", "employment_types": ["Contract"], "selling_points": ["Analyze user requirement document and review", "Degree holder or above in Business Administration", "Minimum 2 years\u2019 experience in financial industry"], "locations": ["Not Specified"], "categories": ["Banking / Finance", "Analyst", "Financial Services", "Professional Services", "Business Analysis / Data Analysis"], "post_time": "2022-01-12T07:37:35Z", "salary": {"currency": null, "max": null, "min": null, "period": "monthly", "term": null}, "salary_visible": false, "title_keywords": ["business analyst"], "responsibilities": ["provide training", "user requirement", "ad-hoc", "uat", "review", "monitor", "procedures", "system design", "maintain", "plan", "planning"], "requirements": {"degrees": ["degree holder"], "majors": ["business administration"], "languages": ["putonghua", "english", "chinese"], "language_level": ["proficient"], "hard_skills": ["problem solving skills", "plus"], "soft_skills": ["communication", "analytical and problem solving skills"], "languages_combined": [{"language": "putonghua", "language_level": ["proficient"]}, {"language": "english", "language_level": ["proficient"]}, {"language": "chinese", "language_level": ["proficient"]}]}, "experience_required": {"duration": ["minimum 2 years"], "field": ["business", "financial industry"]}}, {"job_id": "100003009045939", "location_code": "hk", "company": "CACEIS Hong Kong Trust Company Limited", "job_title": "Transfer Agent - Investor Services Officer/ Senior Officer", "description": "The successful candidate will be reporting to the Head of Fund Distribution Services team.\n\nJob responsibilities:\n\n\nReceipt, check & control of investor instruction to ensure compliance of funds dealing procedures with fund documentation- including Prospectus and Operating Memorandums\u00a0\nProcess subscription, redemption, switches and transfer for a range of onshore and offshore funds\nFollow up on trade outstanding issues (e.g. settlement, confirmation etc.)\nMaintain shareholder register and investor files\nEnsuring compliance with KYC/AML procedures\nResolve dealing related enquiries by email and by telephone from investor and distributors\nPrepare internal and external report\n\nRequirements:\n\nUniversity degree with finance major\u00a0\nAt least 2 years Transfer Agent KYC experience or similar position\nPreferably strong knowledge of PC based applications, including Microsoft Excel, Word and Outlook (VBA is one appreciated skill)\nStrong KYC knowledge\nPositive attitude and mature behaviour\nStrong analytical skills\u00a0\nGood communication and inter-personal skills\u00a0\nExcellent organization and time management skills\u00a0\nAble to work well under pressure and produce quality work according to deadline\u00a0\nAble to perform multi-tasking as well as additional duties\nFluent in English and Mandarin. Knowledge in French/ Japanese/ Korean and other Asian/ foreign languages would be an advantage\n\nCandidates with more relevant experience\u00a0will be considered for\u00a0more senior position.\n\nCompetitive remuneration package will be offered to the successful applicant. We offer an environment that encourages diversity and continuous professional development. Aspiring talents please send your resume via JobsDB. Personal data provided in job applications will be used strictly in accordance with our personal data policy, a copy of which is available upon request.\n\nFor more information about the Group, please visit www.caceis.com", "employment_types": ["Full Time", "Permanent"], "selling_points": [], "locations": ["Admiralty"], "categories": ["Banking / Finance", "Analyst", "Financial Services", "Fund Management"], "post_time": "2022-01-13T09:11:46Z", "salary": {"currency": null, "max": null, "min": null, "period": "monthly", "term": null}, "salary_visible": false, "title_keywords": ["officer", "senior officer"], "responsibilities": ["control", "aml", "compliance", "procedures", "ensure compliance", "maintain", "kyc", "report"], "requirements": {"degrees": ["university degree"], "majors": ["finance"], "languages": ["english", "french", "mandarin", "japanese", "korean"], "language_level": ["advantage", "fluent"], "hard_skills": ["vba", "word", "microsoft excel", "analytical skills", "outlook", "kyc", "pc"], "soft_skills": ["under pressure", "time management skills", "inter-personal skills", "mature", "analytical skills", "positive attitude", "communication", "multi-tasking"], "languages_combined": [{"language": "english", "language_level": ["fluent"]}, {"language": "french", "language_level": ["advantage"]}, {"language": "mandarin", "language_level": ["fluent"]}, {"language": "japanese", "language_level": ["advantage"]}, {"language": "korean", "language_level": ["advantage"]}]}, "experience_required": {"duration": ["at least 2 years"], "field": ["relevant experience"]}}, {"job_id": "100003009044270", "location_code": "hk", "company": "KPay Merchant Service Limited", "job_title": "Business Strategy Manager (Fintech/Digital Payment/SaaS)", "description": "About the Company:\nKPay (kpay-group.com) is a leading digital payment gateway company founded in 2020 by a team of serial entrepreneurs who have successful exited their previous ventures. We currently have a hundred-person team based in Hong Kong. We have aggressive plans to expand across Asia next year and are looking to build out the strategy and investments team, which reports directly to the founders.\n\nOur culture is nimble, entrepreneurial, and fun.\n\nJob Duties:\n\u2022 Conduct company, industry, market, and economic research and monitoring\n\u2022 Financial modelling and analysis\n\u2022 Develop presentation materials in both English and Chinese\n\nJob Requirements :\n\u2022 Relevant work experience (under 5 years) in financial services (PE/VC/hedge funds), investment banking, strategy / management consulting, accounting, digital assets (crypto), or internet start-ups (in particular, fintech involved with payments and/or lending), big data\n\u2022 Excellent communication and interpersonal skills\n\u2022 Excellent written and spoken English and Chinese\n\u2022 Proficiency in MS Word, Excel, PowerPoint, and Chinese word processing\n\u2022 Ability to interact and build relationships with senior management\n\n", "employment_types": ["Full Time", "Permanent"], "selling_points": ["Fast growing fintech firm", "Newly establish team", "Great employment package"], "locations": ["Kwun Tong"], "categories": ["Banking / Finance", "Analyst", "Professional Services", "Business Analysis / Data Analysis", "Business Consultancy"], "post_time": "2022-01-13T03:36:42Z", "salary": {"currency": null, "max": null, "min": null, "period": "monthly", "term": null}, "salary_visible": false, "title_keywords": ["manager"], "responsibilities": ["analysis", "monitoring", "develop"], "requirements": {"degrees": [], "majors": [], "languages": ["english", "chinese"], "language_level": ["excellent", "proficiency"], "hard_skills": ["excel", "crypto", "vc", "chinese word processing", "powerpoint", "pe", "ms word"], "soft_skills": ["communication and interpersonal skills"], "languages_combined": [{"language": "english", "language_level": ["excellent"]}, {"language": "chinese", "language_level": ["excellent", "proficiency"]}]}, "experience_required": {"duration": ["5 years"], "field": ["management", "consulting", "financial services", "investment", "banking", "digital", "accounting"]}}, {"job_id": "100003009035594", "location_code": "hk", "company": "Access Investment Management (HK) Ltd", "job_title": "Analyst - Asset Management", "description": "Responsibilities\n\n\nReview global news and other sources and prepare market briefing notes with added analysis.\nCollect, organize and analyze data to support investment thesis.\nPrepare financial models and forecasts. Construct a valuation of a company.\nGenerate, write and present positive return investment ideas to pitch to senior analysts and portfolio managers.\nCoverage of either healthcare, consumer or renewables sector.\nCompile a universe of companies for benchmarking.\nUpdate databases.\n\n\u00a0Requirements\n\n\nUniversity Degree in Finance or Economics preferred. Other degrees will be considered if financial proficiency can be demonstrated.\n1-2 years of experience as an analyst in a licensed entity or family office\nHigh proficiency in spoken and written English is a must; solid command of Mandarin will be advantageous.\nPossess good analytical skills both in the qualitative and quantitative methods with the ability to appreciate macro-economic trends.\nHave an innate curiosity and an ability to be creative with your work. Be able to present complex ideas and concepts in an understandable form\nHolder of SFC\u2019s license or CFA is preferred.\u00a0\n\nOur company provide:\n\nMedical insurance (including spouse and children)\nDental insurance\nLife insurance\nPerformance bonus\nStudy leave\nBank Holiday\n\n\n\nWe offer competitive compensation package to the right candidate.\u00a0 Please click 'Apply Now' and apply with a detailed resume with current & expected salary to us.\u00a0\n\nAll applications will be treated in strictly confidential.\u00a0 Applicants who are not invited for an\u00a0interview within 2 months may consider that their applications are unsuccessful.", "employment_types": ["Full Time", "Permanent"], "selling_points": [], "locations": ["Central"], "categories": ["Banking / Finance", "Analyst", "Financial Services", "Asset Management"], "post_time": "2022-01-10T07:48:38Z", "salary": {"currency": null, "max": null, "min": null, "period": "monthly", "term": null}, "salary_visible": false, "title_keywords": ["analyst", "asset management"], "responsibilities": ["valuation", "ideas", "financial models", "analysis", "review", "databases", "analyze data"], "requirements": {"degrees": ["university degree"], "majors": ["finance", "economics"], "languages": ["english", "mandarin"], "language_level": ["proficiency"], "hard_skills": ["cfa", "macro", "analytical skills"], "soft_skills": ["creative", "analytical skills"], "languages_combined": [{"language": "english", "language_level": ["proficiency"]}, {"language": "mandarin", "language_level": []}]}, "experience_required": {"duration": ["1-2 years"], "field": []}}, {"job_id": "100003009041234", "location_code": "hk", "company": "Links International", "job_title": "Finance Analyst -  iBank, Welcome Auditors!", "description": "Responsibilities:\n\nPrepare monthly management accounts and month-end procedures\nMonitor trading activities, highlight and report unusual transactions\nTo be fully informed of all developments and issues in their trading areas\nAssess risk inherent in trading positions, whether market, compliance or reputational risk and etc.\nPrepare daily P&L's for trading desks, involving pricing reviews to ensure reasonable valuation of inventory, and substantial use of the firm's accounting systems\nPerform independent price verification on trading inventories\nRequirements:\nBachelor Degree in accounting, finance or related disciplines\nHKICPA/ ACCA/ CPAA Qualified Accountant is preferable\nMinimum 1 year of solid working experience in audit firm\nStrong report writing skill (both English and Chinese)\nGood command of spoken English and Mandarin", "employment_types": ["Full Time", "Permanent"], "selling_points": ["Well-established and sizeable business", "Fast track career path", "All rounded and dynamic role"], "locations": ["Not Specified"], "categories": ["Accounting", "Financial Analyst", "Banking / Finance", "Analyst", "Financial Services"], "post_time": "2022-01-12T03:37:35Z", "salary": {"currency": "HKD", "max": 24999, "min": 20000, "period": "monthly", "term": null}, "salary_visible": true, "title_keywords": ["analyst"], "responsibilities": ["valuation", "management", "inventory", "compliance", "monitor", "procedures", "month-end", "transactions", "p&l", "systems", "assess risk", "report"], "requirements": {"degrees": ["degree", "bachelor"], "majors": ["related disciplines", "finance", "accounting"], "languages": ["english", "chinese", "mandarin"], "language_level": ["good command"], "hard_skills": ["acca", "writing skill", "hkicpa"], "soft_skills": ["writing skill"], "languages_combined": [{"language": "english", "language_level": ["good command"]}, {"language": "chinese", "language_level": []}, {"language": "mandarin", "language_level": ["good command"]}]}, "experience_required": {"duration": ["minimum 1 year"], "field": ["audit"]}}, {"job_id": "100003009038634", "location_code": "hk", "company": "Hang Seng Bank Ltd", "job_title": "Index Research Manager", "description": "HANG SENG INDEXES COMPANY LTD\n\nHang Seng Indexes Company Limited (\u2018Hang Seng Indexes Company\u2019) manages and compiles the Hang Seng Family of Indexes, which cover stocks listed in Hong Kong and Mainland China. Our index series includes the Hang Seng Index, the Hang Seng China Enterprises Index and the Hang Seng TECH Index, as well as Stock Connect, Greater Bay Area and sector-related indexes. As at the end of 2020, assets under management in products passively tracking indexes in the Hang Seng Family of Indexes had reached a total of about US$38 billion.\n\nHang Seng Indexes Company is a wholly owned subsidiary of Hang Seng Bank. Our company is a team of professionals who strives for delivering quality, efficient and world-class index complier services to customers and financial institutions around the world.\n\nTo support our business growth, we are currently seeking high calibre professionals to join our Research team as\u00a0Index\u00a0Research Manager.\u00a0\n\n\n\nPrincipal responsibilities\n\nUpkeep the methodology and integrity of HSIL\u2019s key products (HSI, HSCEI and HSTECH) through addressing regulatory changes and market developments and consulting necessary stakeholders;\nConduct periodic constituent review on HSI, HSCEI, HSTECH and some other indexes;\nPerform quantitative research for the development of HSIL's Smart Beta and Strategy Indexes;\nResearch of new and innovative techniques employed in new index development;\nReview the methodologies of Hang Seng Family of Indexes to ensure they are up to standard and managed with the necessary governance; and\nSupport new index development and research such as preparing new index proposals and backtesting calculation\nRequirements\nUniversity degree in Finance, Economics, Quantitative Analysis, Statistics or related disciplines;\nMinimum 4 years of relevant work experience;\nFamiliar with the Hong Kong / China A stock market;\nDemonstrate good understanding of the financial markets and derivatives strategies;\nStrength in quantitative skills.\u00a0 Factor modelling is an advantage;\nKnowledge in machine learning and NLP techniques is a plus;\nExperience with Excel / VBA / Python / SQL and Bloomberg / Reuters / Factset / Wind;\nStrong research writing, presentation and communication skills;\nResilient, able to work responsibly in a dynamic environment;\nProficiency in English, Cantonese and Putonghua;\nGreat sense of ownership and servicing mindset to ensure efficient and effective customer service processes\n\nIf you would like to explore other opportunities at Hang Seng Hong Kong, please visit www.hangseng.com/careers/ for details.\n\nThe health and safety of our employees and candidates is very important to us. Due to the current situation related to the Novel Coronavirus (2019-nCoV), we\u2019re leveraging our digital capabilities to ensure we can continue to recruit top talent at the HSBC Group. As your application progresses, you may be asked to use one of our digital tools to help you through your recruitment journey. If so, one of our Resourcing colleagues will explain how our video-interviewing technology will be used throughout the recruitment process and will be on hand to answer any questions you might have.\n\nAll information provided by applicants will be used only for recruitment purposes and will be used strictly in accordance with the Bank's personal data policies, a copy of which may be obtained by the applicant upon request. Unless otherwise instructed in writing by the applicant concerned, applicants may be considered for other suitable positions within the Bank and its related companies. The personal data of unsuccessful job applicants may be retained for a maximum of two years from the date when the job application is rejected and such data may be retained for a longer period if there is a subsisting reason that obliges the Bank to do so, after which the personal data will be destroyed.", "employment_types": ["Full Time", "Permanent"], "selling_points": [], "locations": ["Not Specified"], "categories": ["Banking / Finance", "Analyst", "Others", "Others", "Others"], "post_time": "2022-01-12T02:11:06Z", "salary": {"currency": null, "max": null, "min": null, "period": "monthly", "term": null}, "salary_visible": false, "title_keywords": ["manager"], "responsibilities": ["review", "consulting"], "requirements": {"degrees": ["university degree"], "majors": ["related disciplines", "finance", "economics", "statistics"], "languages": ["cantonese", "putonghua", "english"], "language_level": ["proficiency"], "hard_skills": ["vba", "excel", "plus", "bloomberg", "analysis", "reason", "sql", "dynamic", "factor", "python"], "soft_skills": ["efficient", "communication skills", "dynamic environment", "learning", "customer service", "novel", "presentation"], "languages_combined": [{"language": "cantonese", "language_level": ["proficiency"]}, {"language": "putonghua", "language_level": ["proficiency"]}, {"language": "english", "language_level": ["proficiency"]}]}, "experience_required": {"duration": ["minimum 4 years"], "field": ["sql"]}}, {"job_id": "100003009042502", "location_code": "hk", "company": "Bank of China (Hong Kong) Limited", "job_title": "Assistant Manager - Financial and Data Management Team", "description": "Responsibilities:\n\nPerform management reporting including financial budget and forecast, and variances analysis to ensure effective budgetary control;\nPerform cost allocation reporting including monthly allocation ratio, standard cost variances analysis and actual operating cost analysis for providing management information of operation efficiency in financial\nPerform monthly service billing to inter-companies\nReview and develop cost allocation methodology for business unit\nSupport the management by preparing regular and ad-hoc financial analysis for decision making\nImplement efficient internal control for the business units\nPerform ad-hoc projects or assignments as required\n\nRequirements:\n\nBachelor Degree in Accounting, Finance or Business Administration\nStudent member of HKICPA or equivalent\nAt least 2 years of experience in accounting or auditing field , preferably in auditing or management accounting\nKnowledge in Banking Operation or Internal Control function is an advantage\nDetail-oriented with excellent analytical skill\nIndependent, proactive, and able to work in a challenging and dynamic environment\nCapable to work under pressure and willing to work overtime with strong sense of urgency to meet deadlines\nExcellent negotiation, communication and interpersonal skills\nSound PC knowledge including MS Office and Chinese word processing,\nAdvanced knowledge in Excel, knowledge of Macro and VBA is an advantage.\nProficient in both spoken and written English, Cantonese and Mandarin\nImmediate available preferred", "employment_types": ["Full Time"], "selling_points": ["Operation", "Auditing", "Financial analysis"], "locations": ["Others"], "categories": ["Banking / Finance", "Analyst"], "post_time": "2022-01-12T07:48:47Z", "salary": {"currency": null, "max": null, "min": null, "period": "monthly", "term": null}, "salary_visible": false, "title_keywords": ["assistant manager"], "responsibilities": ["ad-hoc", "reporting", "control", "cost", "management", "ad-hoc projects", "analysis", "budget", "review", "develop", "financial analysis", "management reporting", "forecast", "cost analysis", "internal control"], "requirements": {"degrees": ["degree", "bachelor"], "majors": ["finance", "accounting", "business administration"], "languages": ["cantonese", "english", "chinese", "mandarin"], "language_level": ["proficient"], "hard_skills": ["excel", "analytical skill", "macro", "chinese word processing", "vba", "hkicpa", "dynamic", "pc knowledge", "ms office", "internal control"], "soft_skills": ["analytical skill", "dynamic environment", "independent", "capable", "work overtime", "negotiation", "urgency", "advanced", "detail-oriented", "communication and interpersonal skills", "meet deadlines", "proactive", "work under pressure"], "languages_combined": [{"language": "cantonese", "language_level": ["proficient"]}, {"language": "english", "language_level": ["proficient"]}, {"language": "chinese", "language_level": []}, {"language": "mandarin", "language_level": ["proficient"]}]}, "experience_required": {"duration": ["at least 2 years"], "field": ["management accounting", "accounting"]}}, {"job_id": "100003009045007", "location_code": "hk", "company": "Hang Seng Bank Ltd", "job_title": "WPB CDD Project Manager", "description": "WPB Chief Operating Office\n\nWe are currently seeking a high caliber professional to join our team as\u00a0WPB CDD Project Manager.\u00a0\n\u00a0\n\nPrincipal responsibilities\n\nPlan and Deliver CDD initiatives and relevant governance works in relations to HSBC Group\u2019s Business Financial Crime Risks Programmes and Anti-Money Laundering (AML) Regulatory Policies, by working with Group and Regional stakeholders to formulate and deploy WPB CDD governance frameworks and workflows across different HASE WPB business units and functions, per Group\u2019s Functional Instruction Manuals (FIM), Target Operating Model (TOM), CDD Line of Business Procedures (LoBPs) and other relevant guidelines / requirements\nDrive and lead continuous improvement initiatives within onshore and offshore HASE WPB Know-Your-Customer (KYC) New-to-Bank / Existing-to-Bank processes, by identifying pain-points within processes, developing improvement plan and driving the implementations, both operational-wise and technology-wise\nDrive business financial crime risks mitigation projects and remediation exercises for HASE WPB, by working with Global/ Regional/ local counterparts in Chief Data Office, Data and Analytics, Technologies and Operations to deploy and/or localize CDD solutions per evolvement of financial crime typologies and business risk appetites.\nSupport HASE WPB business initiatives as CDD Control Owner and CDD System SME, by working with HASE WPB Business Units, Financial Crime Compliance, Legal, Regulatory Compliance, Transformation, Technologies and Operations in delivering various HASE WPB projects on product development, customer journey digitalization/ enhancement and operational process streamlining.\nRequirements\nUniversity Graduate in Business, Finance, Accounting and Technology disciplines\nAt least 5 years of experience in financial services industry preferably in the capacity of regulatory, compliance and operational risk related areas, with proven track record of managing and delivering banking policies/ products/ processes projects\nFunctional domain knowledge on AML policies and CDD within the Wealth & Personal Banking environment\nProficient in written and verbal English. And able to formulate and articulate solutions to ambiguous and complex issues to senior stakeholders\nProject management qualifications (e.g., PMP) and proved sophisticated project delivery would be an advantage\nSkills on data analysis and analytics (e.g., SQL, MS Macro script competence) would be an advantage\nAbility to communicate effectively, embrace change and overcome challenges\nStrong desire to learn and able to work in Agile environment\nGreat sense of ownership and servicing mindset to ensure efficient and effective deliverables\n\nIf you would like to explore other opportunities at Hang Seng Hong Kong, please visit\u00a0www.hangseng.com/careers/\u00a0for details.\n\nThe health and safety of our employees and candidates is very important to us. Due to the current situation related to the Novel Coronavirus (2019-nCoV), we\u2019re leveraging our digital capabilities to ensure we can continue to recruit top talent at the HSBC Group. \u00a0As your application progresses, you may be asked to use one of our digital tools to help you through your recruitment journey.\u00a0 If so, one of our Resourcing colleagues will explain how our video-interviewing technology will be used throughout the recruitment process and will be on hand to answer any questions you might have.\u00a0\n\nAll information provided by applicants will be used only for recruitment purposes and will be used strictly in accordance with the Bank's personal data policies, a copy of which may be obtained by the applicant upon request. Unless otherwise instructed in writing by the applicant concerned, applicants may be considered for other suitable positions within the Bank and its related companies. The personal data of unsuccessful job applicants may be retained for a maximum of two years from the date when the job application is rejected and such data may be retained for a longer period if there is a subsisting reason that obliges the Bank to do so, after which the personal data will be destroyed.", "employment_types": ["Full Time", "Permanent"], "selling_points": [], "locations": ["Not Specified"], "categories": ["Banking / Finance", "Analyst", "Project Finance", "Risk Management"], "post_time": "2022-01-13T06:53:06Z", "salary": {"currency": null, "max": null, "min": null, "period": "monthly", "term": null}, "salary_visible": false, "title_keywords": ["project manager"], "responsibilities": ["control", "business initiatives", "aml", "data", "guidelines", "cdd", "policies", "kyc", "procedures", "developing", "operations", "compliance", "plan", "deploy", "sme"], "requirements": {"degrees": ["university graduate"], "majors": ["finance", "business", "accounting"], "languages": ["english"], "language_level": ["proficient"], "hard_skills": ["macro", "aml", "agile", "cdd", "analysis", "reason", "sql", "project management", "pmp"], "soft_skills": ["sophisticated", "efficient", "agile", "project management", "articulate", "novel"], "languages_combined": [{"language": "english", "language_level": ["proficient"]}]}, "experience_required": {"duration": ["at least 5 years"], "field": ["related", "financial services industry", "compliance", "banking"]}}, {"job_id": "100003009039283", "location_code": "hk", "company": "Gravitas Recruitment Group", "job_title": "PBMO Analyst", "description": "Our client is expanding the middle office with increasing volume in the prime brokerage business.\n\nRole & requirements:\n\nManage trade lifecycle for ETF/Equity Derivatives/Exotics in HK and other Asia markets\nWork with trading, trader assistant, product control and market risk on resolving any queries\nKnowledgeable of Asia Equities markets and equity derivatives products\nPreferably min. 2-3 years of relevant experience in trade support/middle office function\nStrong mindset of continuous process improvement\nStrong communication skill, especially to speak fluently in English\n\nWHY APPLY?\n\nThis supporting team playing function will be sitting on the trading floor. The scope and exposure is broad in the fast pace business.", "employment_types": ["Full Time", "Permanent"], "selling_points": ["Globally leading investment bank", "Perm", "Competitive career prospect"], "locations": ["Not Specified"], "categories": ["Banking / Finance", "Analyst", "Equities / Capital Markets", "Order Processing & Operation / Settlement"], "post_time": "2022-01-11T09:17:35Z", "salary": {"currency": "HKD", "max": 54999, "min": 35000, "period": "monthly", "term": null}, "salary_visible": true, "title_keywords": ["analyst"], "responsibilities": ["communication", "brokerage", "control"], "requirements": {"degrees": [], "majors": [], "languages": ["english"], "language_level": [], "hard_skills": [], "soft_skills": ["communication skill"], "languages_combined": [{"language": "english", "language_level": []}]}, "experience_required": {"duration": ["2-3 years"], "field": ["relevant experience"]}}, {"job_id": "100003009038015", "location_code": "hk", "company": "Manpower Services (Hong Kong) Limited", "job_title": "On-Site with Hang Seng Bank - Analyst, Investment Operations (6 Month Contract, Up to 18K)", "description": "Title Analyst, Investment Operations\nContract Period 6months\nSalary Range max. 18,000 per month\n\nWe are currently seeking a high caliber professional to join our team as Analyst, Investment Operations\n\nPrincipal responsibilities\n\u2022 Handling investment operations processes include trade management and support, monitor life cycle management and settlement, and oversight treasury positions.\n\u2022 Act as a point of escalation for business as usual (BAU) queries where required.\n\u2022 Maintaining positive relationships with all investment office team members and key staff at, to support the creation of a collaborative working environment in keeping with the clients values and mission.\n\u2022 Assist to manage the relationship with middle office service providers, custodian banks, auditors, and internal/external counterparties to monitor the quality of services and ensure the agreements with relevant service providers are being appropriately applied.\n\u2022 Participate in new product enablement coordinate with middle office service providers and custodian banks on change requirements.\n\nRequirements\n\u2022 University degree in a related discipline OR other relevant qualifications\n\u2022 Previous experience of operations/ accounting management, ideally in an investment setting would be valuable.\n\u2022 Computer literacy with common PC applications (i.e. word, excel, power point). VBA and Bloomberg knowledge is preferred.\n\u2022 Proactive / can-do approach and attitude. Thorough attention to detail and accuracy of delivery.\n\u2022 Good command of written and spoken English and Cantonese\n\nIf you are interested in this role, click \u201cApply Now\u201d, else, you may also directly send your updated resume and expected salary to Anson Li at anson.li@manpowergrc.hk.", "employment_types": ["Contract"], "selling_points": ["Previous experience of ops/ accounting management", "Familiar with VBA and Bloomberg knowledge", "Computer literacy with MS office is preferred"], "locations": ["Mong Kok"], "categories": ["Banking / Finance", "Analyst", "Corporate Banking", "Investment"], "post_time": "2022-01-11T04:35:26Z", "salary": {"currency": null, "max": null, "min": null, "period": "monthly", "term": null}, "salary_visible": false, "title_keywords": ["analyst", "operations"], "responsibilities": ["management", "maintaining", "operations", "monitor", "quality", "coordinate with"], "requirements": {"degrees": ["university degree"], "majors": [], "languages": ["cantonese", "english"], "language_level": ["good command"], "hard_skills": ["excel", "vba", "bloomberg", "word", "pc applications", "power point"], "soft_skills": ["interested in", "computer literacy", "thorough", "attention to detail", "can-do", "proactive"], "languages_combined": [{"language": "cantonese", "language_level": ["good command"]}, {"language": "english", "language_level": ["good command"]}]}, "experience_required": {"duration": [], "field": ["management", "accounting", "investment"]}}, {"job_id": "100003009040034", "location_code": "hk", "company": "Lidl Asia Pte. Limited (Hong Kong Branch)", "job_title": "(Senior) Analytics Specialist", "description": "Summary\n\nLidl Asia are hiring for a (Senior) Analytics Specialist in our Business Controlling team who will provide analytics driven solutions by adopting analytical models and data science methods.\n\nWhat will you do?\nBe responsible for the quality of your solutions and results, while accounting for best practices from our Global Analytics team during implementation.\nStructure and derive results of the analyses in creating targeted and understandable presentations.\nSupport Analytics in the country roll out and localisation of Analytics data products.\nProvide first-level support to stakeholders related to analytics questions.\nParticipate in deriving and solving analytical questions, either through deep-dive analyses or the development of local analytical solutions for the business.\nOperationalise the solutions by applying analytics methods, including processing and visualisation of results; the implementation can range from simple methods (e.g. exploratory data analysis, linear regression, cluster algorithms) to complex models (e.g. XGBoost, KNN). Usage and development of data sources and feature engineering are also part of the task.\nWhere applicable, be involved in the development of solution templates with other countries.\nImplement separate projects upon request which may result from operational requirements.\nWhat will you need?\n\nStrong knowledge in big-data technologies, machine learning, optimisation, and data mining methods (e.g. with Python, R)\n\nStatistical knowledge and predictive modelling\n\nProven experience of applying time-series / regression analysis, clustering-methods, and effectiveness testing (A-/B-hypotheses testing) to solve diverse business problems\n\nStrong ability to understand complex problems and scenarios, and analysing them in detail\n\nAble to work to tight deadlines and to deliver accurate results\n\nExcellent communication skills and teamwork\n\nSelf-motivated and proactive individual with a can-do attitude and the ability to work on projects and solve problems independently\n\nWhat do we offer?\n\nWe are dedicated to fostering a family-friendly culture and work environment and we are an equal opportunities employer and welcome applications from all candidates with the required skills and experience.\nMarket Leading Remuneration Package:\n\nDouble pay and discretionary bonus\nChoice of MPF provider\nLife Insurance\nMedical Insurance\n\nSupportive Environment:\n\nRental re-imbursement scheme\nFlexible work arrangements\nIn-house training courses\nTraining sponsorship scheme\nHealth Check\nVision Check\nSupporting your child\u2019s education with advice from a leading education consultant\n\nWork-Life Balance:\n\n5 day week\nCompetitive Annual Leave\nCharity, Community and Sporting Events\n\nWe are dedicated to fostering a family-friendly culture and work environment and we are an equal opportunities employer and welcome applications from all candidates with the required skills and experience.\nMarket Leading Remuneration Package:\n\nDouble pay and discretionary bonus\nChoice of MPF provider\nLife Insurance\nMedical Insurance\n\nSupportive Environment:\n\nRental re-imbursement scheme\nFlexible work arrangements\nIn-house training courses\nTraining sponsorship scheme\nHealth Check\nVision Check\nSupporting your child\u2019s education with advice from a leading education consultant\n\nWork-Life Balance:\n\n5 day week\nCompetitive Annual Leave\nCharity, Community and Sporting Events", "employment_types": ["Full Time"], "selling_points": ["Must have strong data analytics knowledge", "Office located in ICC building", "Flexible work arrangements"], "locations": ["Tsim Sha Tsui"], "categories": ["Accounting", "Consulting", "Banking / Finance", "Analyst", "Professional Services", "Business Analysis / Data Analysis"], "post_time": "2022-01-12T00:56:47Z", "salary": {"currency": null, "max": null, "min": null, "period": "monthly", "term": null}, "salary_visible": false, "title_keywords": ["specialist"], "responsibilities": ["clustering", "data", "analysis", "quality", "implementation", "presentations", "testing", "data analysis", "communication", "data mining"], "requirements": {"degrees": [], "majors": [], "languages": [], "language_level": [], "hard_skills": ["simple", "analysis", "presentations", "python", "data mining", "r", "processing"], "soft_skills": ["communication skills", "self-motivated", "proactive", "independently", "responsible", "can-do attitude", "deep", "teamwork", "diverse", "solve problems", "learning", "accurate", "driven"], "languages_combined": []}, "experience_required": {"duration": [], "field": ["business", "testing"]}}, {"job_id": "100003009039723", "location_code": "hk", "company": "Guotai Junan International Holdings Limited", "job_title": "Investment Strategist (Wealth Management)", "description": "Responsibilities:\n\nResponsible for equity market commentary\nResponsible for investment research and analysis of both equity and fixed income markets;\nPrepare market update, investment proposals and presentations; and\nJoin client meeting on request.\n\nRequirements:\n\nBachelor degree or abovein Finance, Accountancy or related disciplines;\nMinimum 10 year of relevant experiences in financial field;\nGood communication skills and well-organized;\nSelf-motivated, responsible, good analytical and problem solving skills;\nGood command of written and spoken English and Chinese, proficiency in Putonghua is preferred.\n\nWe offer an attractive remuneration package to the right candidate. Interested parties please forward your full resume with availability, expected salary by pressing \"Apply now\"\u00a0or send it to 27/F., Low Block, Grand Millennium Plaza, 181 Queen\u2019s Road, Central, Hong Kong.\n\n(Data collected will be kept strictly confidential and used for recruitment purpose only.)", "employment_types": ["Full Time", "Permanent"], "selling_points": ["Responsible for equity market commentary", "Responsible for investment research and analysis", "Minimum 10 year of relevant experiences"], "locations": ["Central & Western Area"], "categories": ["Banking / Finance", "Analyst", "Financial Services", "Wealth Management"], "post_time": "2022-01-11T10:41:16Z", "salary": {"currency": null, "max": null, "min": null, "period": "monthly", "term": null}, "salary_visible": false, "title_keywords": ["wealth management"], "responsibilities": ["analysis", "presentations"], "requirements": {"degrees": ["degree", "bachelor"], "majors": ["related disciplines", "finance", "accountancy"], "languages": ["putonghua", "english", "chinese"], "language_level": ["proficiency", "good command"], "hard_skills": ["problem solving skills"], "soft_skills": ["communication skills", "self-motivated", "responsible", "well-organized", "analytical and problem solving skills"], "languages_combined": [{"language": "putonghua", "language_level": ["proficiency", "good command"]}, {"language": "english", "language_level": ["proficiency", "good command"]}, {"language": "chinese", "language_level": ["proficiency", "good command"]}]}, "experience_required": {"duration": ["minimum 10 year"], "field": ["financial"]}}, {"job_id": "100003009050286", "location_code": "hk", "company": "Nanyang Commercial Bank", "job_title": "Risk Management Manager - Credit Risk Modelling (Ref: OG8007-CRM-JDB)", "description": "Responsible for the development, implementation and enhancement of credit risk rating models and systems. Monitor and report model performance. Formulate policies and procedures to facilitate the credit risk models implementation.\n\nRequirements:\n\n\nBachelor Degree holder or above in Risk Management, Statistics, Quantitative Finance or related disciplines preferably with professional qualification in ACCA / CPA / CFA / FRM / PRM;\nIn-depth knowledge in Basel regulatory requirements and banking practices in credit risk management is essential;\nAt least 4 years experience in the development of credit risk internal ratings-based system is preferred;\nSound knowledge in statistical and quantitative analysis and familiar with SAS, Excel VBA, SQL and MS office;\n\u00a0Analytical, independent, possession of good communication and interpersonal skills;\nProficient in both spoken and written English and Chinese, fluent in Putonghua is preferable.\n\nCandidate with less relevant experience will be considered as Assistant\u00a0Risk Management Manager.)\n\nIf you are flexible enough and zeal for a harmonious and supportive working environment where enables you to grow and succeed professionally, please send a full resume indicating your public examination results (HKCEE and HKALE / HKDSE), your present and expected salary and quoting reference number attention to Talent Acquisition Division, Nanyang Commercial Bank, 151 Des Voeux Road Central, Hong Kong or apply through email. For details, please visit https://www.ncb.com.hk/ and select the page Recruit.\n\nWe are an Equal Opportunities Employer. Data collected would be used for recruitment purposes only. Applicants who do not hear from us within 8 weeks may consider their applications unsuccessful and their data will be destroyed within 12 months of receipt.", "employment_types": ["Full Time", "Permanent"], "selling_points": ["Responsible for the development, implementation", "Monitor and report model performance", "At least 4 years relevant experience"], "locations": ["Central & Western Area"], "categories": ["Banking / Finance", "Analyst", "Credit Analysis / Approval"], "post_time": "2022-01-15T03:50:56Z", "salary": {"currency": null, "max": null, "min": null, "period": "monthly", "term": null}, "salary_visible": false, "title_keywords": ["risk management manager"], "responsibilities": ["management", "data", "policies", "regulatory requirements", "systems", "monitor", "implementation", "procedures", "analysis", "communication", "recruitment", "banking", "report"], "requirements": {"degrees": ["hkdse", "bachelor degree holder"], "majors": ["finance", "risk management", "related disciplines", "statistics"], "languages": ["putonghua", "english", "chinese"], "language_level": ["fluent", "proficient"], "hard_skills": ["excel", "acca", "vba", "sas", "cfa", "analysis", "sql", "cpa", "frm", "ms office"], "soft_skills": ["flexible", "supportive", "independent", "harmonious", "responsible", "communication and interpersonal skills"], "languages_combined": [{"language": "putonghua", "language_level": ["fluent", "proficient"]}, {"language": "english", "language_level": ["fluent", "proficient"]}, {"language": "chinese", "language_level": ["fluent", "proficient"]}]}, "experience_required": {"duration": ["at least 4 years"], "field": ["development", "relevant experience", "credit risk", "risk management"]}}, {"job_id": "100003009037771", "location_code": "hk", "company": "Oliver James Associates Limited", "job_title": "AML Analyst (Fraud/FCC) - renewable contract (18K-28K)", "description": "Job Description\n\u2022Principal point of referral for all relevant investigations, which may originate from various internal or external sources.\n\u2022Continuously monitor and action requests that arrive in the regional enquiries inbox.\n\u2022The provision of timely and reliable assessment and triage on potential financial crime risks to improve risk management decisions within FCI.\n\u2022Completion of initial case intake assessment and all associated logging to determine action status of request.\n\u2022To adhere to the globally defined triage procedures or approved country variances across FCI Investigation, which are designed to support the operational effectiveness of the investigative capability.\n\u2022Ensure that all cases are correctly entered onto the case management system.", "employment_types": ["Contract"], "selling_points": ["attractive package", "long term role", "AML exposure"], "locations": ["Mong Kok"], "categories": ["Banking / Finance", "Analyst"], "post_time": "2022-01-11T03:47:26Z", "salary": {"currency": null, "max": null, "min": null, "period": "monthly", "term": null}, "salary_visible": false, "title_keywords": ["analyst"], "responsibilities": ["management", "monitor", "investigation", "procedures"], "requirements": {"degrees": [], "majors": [], "languages": [], "language_level": [], "hard_skills": [], "soft_skills": ["timely", "reliable"], "languages_combined": []}, "experience_required": {"duration": [], "field": []}}, {"job_id": "100003009050669", "location_code": "hk", "company": "China Construction Bank (Asia) Corporation Limited", "job_title": "Relationship Manager, Corporate Banking (China Corporate)", "description": "Responsibilities:\n\nManage and grow a portfolio of clients who need financial services and customized products to meet their financial needs and builds solid, profitable relationships with clients characterized by mutual respect, understanding and trust; works to establish his/her role as a trusted advisor\nExecute strategies to meet individual revenue targets set by the Bank and maximise the Bank\u2019s profitability\nProspect and generate new business by expanding the customer portfolio and enhancing existing relationships through identifying opportunities for cross-selling and up-tiering\nConduct credit analysis and review credit proposals with persuasive and objective arguments\nPerform credit due diligence and ensure credit and regulatory compliance\nFollow up with clients to complete loan administration work in the post credit monitoring process\nSystematically acquire relevant information to support key decisions; is particularly resourceful in securing information from a variety of sources and integrates new information into planning and/or decision-making\nDemonstrate broad knowledge of the client\u2019s industry; is aware of its benchmarks, standards, methodologies and structures; has up-to-date knowledge of client industry practices and processes and keep abreast of trends and developments\nUse analytical skills and knowledge of credit policies required to evaluate the financial condition of the clients and make recommendations for credit approval\nIdentify risks and draws conclusions from financial data for the purpose of decision-making\nConsistently applies established procedures/ practices to make financial decisions\nPerform routine account monitoring and maintain good credit quality\nDemonstrate dedication and passion for exceeding the expectations of internal / external clients, earns client loyalty through accuracy, efficiency and courtesy\nTake ownership for solving problems, engaging the appropriate associates and addressing client issues in a timely and accurate manner\nDevelop strong interpersonal alliances at appropriate levels and positively represents the company in the communities we serve\nConduct regular KYC assessment on a timely basis and to ensure client onboarding activity is complied with the AML policy and procedures\nMaintain regular visit with the clients\nIdentify, investigate and report any suspicious activities and transactions to respective units on a timely manner\n\n\u00a0Requirements:\n\nUniversity degree or equivalent, preferably in Business or Economics\nMinimum 5 years relevant banking experience in trade financing and corporate lending\nStrong business development skills and sound knowledge of banking products and services with proven analytical skills and creative problem solving skills\nProficiency in the financial services/products offered to PRC clients\nExcellent communication and interpersonal skills\nGood business acumen with good knowledge of credit and lending policies and standard\nGood command of both English and Chinese, including Putonghua\n\nApplicants who are not contacted within 8 weeks may consider their applications unsuccessful and their personal data will be retained by the bank for a period up to two years.\n\nAll information provided by applicants will be used for recruitment purposes only and will be used strictly in accordance with the bank's personal data policies, a copy of which will be provided upon request.\u00a0", "employment_types": ["Full Time", "Permanent"], "selling_points": ["Minimum 5 years banking experience (trade finance)", "Banking products and services with proven analytic", "University degree or equivalent, Business or Econ"], "locations": ["Central"], "categories": ["Banking / Finance", "Analyst", "Corporate Banking", "Credit Analysis / Approval"], "post_time": "2022-01-14T11:09:20Z", "salary": {"currency": null, "max": null, "min": null, "period": "monthly", "term": null}, "salary_visible": false, "title_keywords": ["relationship manager"], "responsibilities": ["data", "quality", "transactions", "maintain", "administration", "make recommendations", "due diligence", "compliance", "develop", "kyc", "report", "review", "monitoring", "procedures", "aml", "policies", "analysis", "a timely manner", "evaluate", "planning"], "requirements": {"degrees": ["university degree"], "majors": ["economics", "business"], "languages": ["putonghua", "english", "chinese"], "language_level": ["good command"], "hard_skills": ["problem solving skills", "acumen", "analytical skills"], "soft_skills": ["analytical skills", "communication and interpersonal skills", "business acumen", "problem solving skills", "creative"], "languages_combined": [{"language": "putonghua", "language_level": ["good command"]}, {"language": "english", "language_level": ["good command"]}, {"language": "chinese", "language_level": ["good command"]}]}, "experience_required": {"duration": ["minimum 5 years"], "field": ["financing", "banking experience"]}}, {"job_id": "100003009049763", "location_code": "hk", "company": "Chiyu Banking Corp Ltd", "job_title": "Credit Risk Model Validation Manager", "description": "Responsibilities:\n\nExecute validation of risk data aggregation and risk reporting against the regulatory requirements, identify any compliance gap, and prioritize a roadmap for the gap-closing activities.\nConduct qualitative validation by examining itemized criteria for risk data aggregation and risk reporting to comply with the regulatory validation requirements.\nConduct quantitative validation with standardized tools and templates.\nAssess whether responsible personnel follows the policies and procedures established for risk data aggregation and risk reporting.\nExecute qualitative and quantitative validation of credit scorecards, PD/LGD/EAD models, or other credit risk models (e.g. portfolio risk stress testing, IFRS9) across retail and non-retail exposures in accordance with regulatory requirements\nManage validation process including planning and executing project activities, coordinating, and liaising with different parties in the Bank.\nPrepare reports and make recommendations to senior management or related stakeholders.\nReview policies and procedural guidelines regularly\n\n\u00a0\nRequirements:\n\nBachelor degree holder or above in Data (or Business) Analytics, Engineering, Risk Management, Statistics/ Applied Mathematics, Quantitative Finance or equivalent discipline.\nAt least 3 years\u2019working experience in data quality control, data report and monitoring, data quality management\nProficiency in data analysis tools such as SAS, Excel VBA, SQL\nGood command of written and spoken Chinese and English. Fluent Mandarin will be an advantage\n\n\n\nWe offer competitive packages and promising career opportunities to the right candidates. Please send your full resume with current salary, expected salary and the date of availability to The Human Resources Department, Chiyu Banking Corporation Ltd, 12/F, Chiyu Bank Building, No. 78 Des Voeux Road Central, Hong Kong or fax to 2986-3233 or by clicking Apply Now.\n\nInformation provided will be treated in strict confidence and only be used for recruitment purposes. All personal data of unsuccessful applicants will be destroyed after the recruitment exercise. A copy of Personal Information Collection Statement is available upon request.", "employment_types": ["Full Time", "Permanent"], "selling_points": [], "locations": ["Central"], "categories": ["Banking / Finance", "Analyst", "Credit Analysis / Approval", "Risk Management"], "post_time": "2022-01-14T09:12:14Z", "salary": {"currency": null, "max": null, "min": null, "period": "monthly", "term": null}, "salary_visible": false, "title_keywords": ["model", "manager"], "responsibilities": ["make recommendations", "reporting", "data", "guidelines", "policies", "regulatory requirements", "compliance", "procedures", "liaising with", "review", "testing", "executing", "prepare reports", "senior management", "planning"], "requirements": {"degrees": ["bachelor degree holder"], "majors": ["risk management", "engineering", "finance", "statistics", "business", "applied mathematics"], "languages": ["english", "chinese", "mandarin"], "language_level": ["advantage", "good command", "fluent"], "hard_skills": ["vba", "excel", "sas", "analysis", "sql"], "soft_skills": [], "languages_combined": [{"language": "english", "language_level": ["good command"]}, {"language": "chinese", "language_level": ["good command"]}, {"language": "mandarin", "language_level": ["fluent", "advantage"]}]}, "experience_required": {"duration": [], "field": ["quality management", "quality control"]}}, {"job_id": "100003009044105", "location_code": "hk", "company": "WilliamSELECT", "job_title": "Assistant Financial Analyst (APAC) - Retail", "description": "My client is a well known retail brand. To expand their finance team, they are looking for an Assistant Financial Analyst to join their team.\n\nResponsibilties:\n\nPrepare annual and monthly management reports for APAC\nPrepare budget and forecast reports to identify risks and improve efficient\u00a0\nConduct P&L variance analysis\nGive analytical support for business decisions\nParticipate in system/process improvement project\nReport to FP&A Manager and assist on ad hoc duties\u00a0\n\nRequirements:\n\nBachelor Degree in Accounting/Finance\u00a0\n1 years relevant experience in accounting/financial analysis, preferably from retail industry\nStrong analytical mind, good communication skill and business sense\nProactive and self motivated\u00a0\nGood command of spoken and written English and Chinese", "employment_types": ["Full Time", "Permanent"], "selling_points": ["FP&A focus", "Budget & Forecast", "Fresh Graduate welcome"], "locations": ["Not Specified"], "categories": ["Accounting", "Accounting Clerk / Supervisor", "Financial Analyst", "Banking / Finance", "Analyst"], "post_time": "2022-01-13T03:04:48Z", "salary": {"currency": null, "max": null, "min": null, "period": "monthly", "term": null}, "salary_visible": false, "title_keywords": ["assistant", "financial analyst"], "responsibilities": ["ad hoc duties", "budget", "p&l", "variance analysis", "management reports", "reports", "forecast", "report"], "requirements": {"degrees": ["degree", "bachelor"], "majors": ["finance", "accounting"], "languages": ["english", "chinese"], "language_level": ["good command"], "hard_skills": ["financial analysis"], "soft_skills": ["business sense", "communication skill", "self motivated", "analytical mind", "proactive"], "languages_combined": [{"language": "english", "language_level": ["good command"]}, {"language": "chinese", "language_level": ["good command"]}]}, "experience_required": {"duration": ["1 years"], "field": ["retail industry", "accounting", "relevant experience", "financial"]}}, {"job_id": "100003009035631", "location_code": "hk", "company": "HKT Enterprise Solutions", "job_title": "Market Analyst (SQL, Python focus)", "description": "To support our continuous development, we are looking for a candidate who is strong at database marketing and data manipulation\u00a0\n\nYour new role\n\nDevelop end to end marketing campaign automation using SQL Server SSIS and other automation tools\nPerform regular data cleansing or other tasks necessary to avoid redundant constituent record and to ensure data integrity\nWorking with counterparts on marketing campaign preparation\nPrepare campaign performance analysis and monthly reports of related LOBs for management review\u00a0\n\nTo succeed in this role\n\nUniversity graduate in Computer Science, IT, Data Management, Statistic or related disciplines\nMinimum 2 years' experience in database marketing or data manipulation\nSolid experience in using SQL (or similar software package) and with ability to design complex series of queries to interrogate data\nExcellent analytical skills to evaluate opportunities from cross-platforms\u2019 data\nAble to work independently but also a good team player", "employment_types": ["Full Time"], "selling_points": [], "locations": ["Quarry Bay"], "categories": ["Banking / Finance", "Analyst", "Professional Services", "Business Analysis / Data Analysis", "Marketing / Public Relations", "Marketing - Market Research"], "post_time": "2022-01-10T07:56:23Z", "salary": {"currency": null, "max": null, "min": null, "period": "monthly", "term": null}, "salary_visible": false, "title_keywords": ["analyst"], "responsibilities": ["manipulation", "management", "software", "data", "monthly reports", "cleansing", "analysis", "design", "develop", "evaluate", "other tasks", "database", "management review"], "requirements": {"degrees": ["university graduate"], "majors": ["related disciplines", "it", "computer science"], "languages": [], "language_level": [], "hard_skills": ["data management", "analysis", "analytical skills", "sql", "server", "data manipulation"], "soft_skills": ["good team player", "work independently", "integrity", "analytical skills"], "languages_combined": []}, "experience_required": {"duration": ["minimum 2 years"], "field": ["sql", "marketing", "database", "design"]}}, {"job_id": "100003009050668", "location_code": "hk", "company": "China Construction Bank (Asia) Corporation Limited", "job_title": "VP / AVP, Credit Policies", "description": "Responsibilities:\n\n\n\nFormulate and review bank-wide credit policies, procedures and guidelines in line with statutory and regulatory requirements as well as the Group\u2019s standard\nKeep close update of the new guidelines / regulations / policies released by the regulatory bodies and Head Office applicable to the Bank\u2019s credit risk management\nParticipate in bank-wide projects and formulate / enhance related credit policies & guidelines to support business initiatives\nCoordinate responses and follow-up actions of the findings / recommendations by the auditors and regulators and conduct policy enhancement\nHandle regular/ad-hoc reporting and bank projects\n\n\u00a0Requirements:\n\nUniversity degree holder in banking, finance or related disciplines\n\nMinimum 6-8 years\u2019 banking experience\n\nGood knowledge of general banking products / workflow, lending principles / credit approval process as well as awareness of credit risk issues\n\nPreferable with experience in formulating credit policies for corporate, commercial and treasury / institutional banking related areas\n\nKnowledge in BELR, IRB & corporate governance would be an added advantage\n\nProactive, detailed-oriented, good analytical and communication skills\n\nMulti-tasked and able to work independently under tight timelines\n\nGood command of written and spoken English and Chinese (Putonghua is a must)\n\nApplicants who are not contacted within 8 weeks may consider their applications unsuccessful and their personal data will be retained by the bank for a period up to two years.\n\nAll information provided by applicants will be used for recruitment purposes only and will be used strictly in accordance with the bank's personal data policies, a copy of which will be provided upon request.\u00a0", "employment_types": ["Full Time", "Permanent"], "selling_points": ["Formulate/review/update bank-wide credit policies", "Review & update new guidelines/regulations", "Degree with 6-8 yrs exp in banking industry"], "locations": ["Kowloon Bay"], "categories": ["Banking / Finance", "Analyst", "Financial Services", "Risk Management"], "post_time": "2022-01-14T11:09:19Z", "salary": {"currency": null, "max": null, "min": null, "period": "monthly", "term": null}, "salary_visible": false, "title_keywords": [], "responsibilities": ["regulations", "ad-hoc", "management", "business initiatives", "reporting", "guidelines", "policies", "regulatory requirements", "review", "procedures", "coordinate"], "requirements": {"degrees": ["university degree"], "majors": ["related disciplines", "finance"], "languages": ["putonghua", "english", "chinese"], "language_level": ["good command"], "hard_skills": [], "soft_skills": ["communication skills", "work independently", "multi-tasked", "proactive", "detailed"], "languages_combined": [{"language": "putonghua", "language_level": ["good command"]}, {"language": "english", "language_level": ["good command"]}, {"language": "chinese", "language_level": ["good command"]}]}, "experience_required": {"duration": ["minimum 6-8 years"], "field": ["related", "commercial", "banking experience", "banking"]}}, {"job_id": "100003009038364", "location_code": "hk", "company": "Nautilus Technology Limited", "job_title": "Junior Quantitative Developer", "description": "Job Responsibilities:\n\nResponsible for integrating data from various back-end services and databases\nWorking with Senior Management and real traders to design, model and generate algorithm ideas.\nAnalyze unique proprietary data sets.\n\nRequirements:\n\nBachelor Degree in Math, CS, Stats, Physics, or related field\n1-3 years of coding experience\nOutstanding programming ability in C++ and Python\nStrong command of both written and spoken English and Chinese (Especially in Mandarin)\n\nNice to have:\n\nKnowledge of UNIX operating systems (we use Linux), system/processor performance, and network communication\nExperience with low latency programming", "employment_types": ["Full Time", "Permanent"], "selling_points": [], "locations": ["Tsim Sha Tsui"], "categories": ["Banking / Finance", "Analyst", "Corporate Finance", "Equities / Capital Markets"], "post_time": "2022-01-11T06:44:20Z", "salary": {"currency": null, "max": null, "min": null, "period": "monthly", "term": null}, "salary_visible": false, "title_keywords": ["developer", "junior"], "responsibilities": ["ideas", "data", "design", "databases", "senior management"], "requirements": {"degrees": ["degree", "bachelor"], "majors": ["math", "physics"], "languages": ["english", "chinese", "mandarin"], "language_level": [], "hard_skills": ["linux", "c++", "nice", "programming", "python", "math"], "soft_skills": ["communication"], "languages_combined": [{"language": "english", "language_level": []}, {"language": "chinese", "language_level": []}, {"language": "mandarin", "language_level": []}]}, "experience_required": {"duration": ["1-3 years"], "field": ["programming"]}}, {"job_id": "100003009035368", "location_code": "hk", "company": "HKT Enterprise Solutions", "job_title": "Senior Market Analyst", "description": "Your\u00a0role\n\nYou will work in the Marketing Data Analytic Team.\u00a0 The major responsibility of this role is to provide high quality insight and facilitate decision making process on business side through data mining and analysis. Major responsibilities include but not limited to the following:\n\nHandle large sets of data to analysis the customer behavior and identify new market opportunities and retention strategies\nPrepare regular management report & dashboards on business performance metrics\nAnalyze marketing trend and identify customer needs by building data-driven attribution models\nConduct market research projects to analyze competitors, determine brand perceptions evaluate market penetration; understand customer satisfaction\nProvide ROI analysis of all marketing campaigns and sales activities (maximize effectiveness)\nPerform UAT, data testing and monitor project execution to maintain data integrity of marketing data mart\nSupport ad-hoc projects as assigned\n\nTo succeed this role\n\nDegree holder in Marketing or Statistics related discipline\n3 years\u2019 solid experience in data analytics, data mining and customer segmentation with strong programming skill in SQL and Python\nFamiliar in Datamart, BI Dashboard and visualization tool such as Qliksense and Tableau\nWorking experience in telecommunication / mobile / Banking/ IT industry is preferred\nA marketing expert who possesses a core strength of strategic thinking\nGood analytical skill and detail-oriented\nExcellent interpersonal and communication skills as well as good command of both written and spoken English and Cantonese", "employment_types": ["Full Time"], "selling_points": [], "locations": ["Quarry Bay"], "categories": ["Banking / Finance", "Analyst", "Information Technology (IT)", "DBA", "Marketing / Public Relations", "Marketing - Market Research"], "post_time": "2022-01-10T06:56:23Z", "salary": {"currency": null, "max": null, "min": null, "period": "monthly", "term": null}, "salary_visible": false, "title_keywords": ["analyst"], "responsibilities": ["visualization", "data", "conduct market research", "quality", "communication", "data mining", "ad-hoc projects", "uat", "monitor", "testing", "marketing campaigns", "banking", "management report", "maintain data", "sales activities", "analyze marketing trend", "analysis", "performance metrics", "evaluate"], "requirements": {"degrees": ["degree holder"], "majors": ["marketing", "statistics"], "languages": ["cantonese", "english"], "language_level": ["excellent", "good command"], "hard_skills": ["analytical skill", "bi", "data analytics", "analysis", "tableau", "python", "sql", "mobile", "programming", "data mining"], "soft_skills": ["communication skills", "analytical skill", "strategic thinking", "integrity", "detail-oriented", "interpersonal", "driven", "decision making"], "languages_combined": [{"language": "cantonese", "language_level": ["excellent", "good command"]}, {"language": "english", "language_level": ["excellent", "good command"]}]}, "experience_required": {"duration": ["3 years"], "field": ["sql", "it", "programming", "banking"]}}, {"job_id": "100003009040317", "location_code": "hk", "company": "Taiping Reinsurance Company Limited", "job_title": "Senior Manager/Manager, Group Financial and Regulatory Reporting", "description": "To cope with the continuous growing business needs, we are actively looking for Senior Manager/Manager to join the Group financial and regulatory reporting team.\n\nKey Responsibilities\n\nPrepare and ensure month-end, quarter-end, interim and annual financial closing and reporting processes with good quality in a timely manner;\nLiaise with finance teams of the Group\u2019s subsidiaries and external auditors for any issues related to financial and accounting;\nParticipate in the property valuation matters;\nSupport the deliverables for the Audit Committee and the Board of Directors;\nProvide analytical review on the consolidated financial results;\nWork closely with IT department to support continuous process and system enhancements to drive efficiency and effectiveness of the closing process and\u00a0 the production of deliverables;\nParticipate in the implementation of IFRS 9, IFRS 17, and other new accounting standards;\nAchieve assigned functions accurately and efficiently;\nProvide guidance and technical advice to subsidiaries;\nPerform ad-hoc financial management tasks and duties as assigned.\n\n\u00a0Requirements\n\nBachelor\u2019s Degree in Accounting/Finance or above;\nCPA or equivalent qualification is a MUST;\nMin 10 (for Senior Manager)/ min 5 (for Manager) years strong and solid\u00a0 experience in financial reporting from Big 4 or listed companies;\nSolid experience in complex group consolidation preparation and group\u00a0 financial reporting;\nExcellent problem solving and analytical skills;\nExcellent multi-tasking skills;\nStrong communication skills in written and spoken English, Cantonese and Mandarin;\nStrong leadership skills, sound business acumen and able to work under pressure;\nAbility to support multi stakeholder information needs;\nProficiency in HFM, IFRS and PRC GAAP a plus;\nWork in Hong Kong with occasional travelling to Mainland is required.\n\nRecruitment statement\n\nThis position is posted by China Taiping Insurance Group Ltd (The parent company of Taiping Reinsurance Co., Ltd.) .\n\nFor qualified and interested candidates, please click the following job application link to apply.", "employment_types": ["Full Time", "Permanent"], "selling_points": ["Insurance Group, a HK listed company", "Min 10/min 5 years relevant accounting experience", "CPA, Big 4 candidates"], "locations": ["North Point"], "categories": ["Accounting", "Consulting", "Financial Analyst", "Banking / Finance", "Analyst"], "post_time": "2022-01-12T02:17:40Z", "salary": {"currency": null, "max": null, "min": null, "period": "monthly", "term": null}, "salary_visible": false, "title_keywords": ["senior manager", "manager"], "responsibilities": ["ad-hoc", "reporting", "valuation", "management", "technical advice", "review", "a timely manner", "quality", "month-end", "teams", "audit", "implementation", "liaise with", "provide guidance", "external auditors"], "requirements": {"degrees": ["degree", "bachelor"], "majors": ["finance", "accounting"], "languages": ["cantonese", "english", "mandarin"], "language_level": [], "hard_skills": ["ifrs", "plus", "analytical skills", "problem solving", "cpa", "acumen"], "soft_skills": ["communication skills", "multi-tasking skills", "leadership skills", "problem solving and analytical skills", "business acumen", "work under pressure"], "languages_combined": [{"language": "cantonese", "language_level": []}, {"language": "english", "language_level": []}, {"language": "mandarin", "language_level": []}]}, "experience_required": {"duration": [], "field": ["consolidation", "big 4", "financial"]}}, {"job_id": "100003009042959", "location_code": "hk", "company": "Chong Hing Bank Ltd", "job_title": "Assistant Vice President \u2013 Regulatory Compliance (Investment & Insurance focused)", "description": "Responsibilities:\n\nFollow up latest regulatory requirements and provide advisory services on compliance related issues in order to ensure business units in compliance with regulatory requirements;\nPerform review on general compliance issues and monitor business compliance with relevant external regulatory requirements;\nAssist in the formulating and executing compliance assurance projects;\nIdentify any deficiencies in business activities & operations during assurance reviews; and make recommendations to business units in improving & reinforcing compliance standards accordingly;\nMonitor the implementation status of assurance review recommendations as agreed with units;\nCompile compliance review reports and manage the reporting /escalation of review result to management;\nCoordinate with Regulators and relevant internal stakeholders in handling Regulatory examination related requests;\nConduct compliance training when necessary; and\nPerform other ad hoc projects or assignments.\nRequirements:\nUniversity degree in Law, Business Administration, Finance or related discipline;\nMinimum of 5 years\u2019 solid experience in general regulatory compliance of which 4 years in investment and insurance compliance;\nSound knowledge of investment products such as securities, funds and bonds;\nConversant with banking rules and regulations including Banking Ordinance and Securities & Futures Ordinance;\nKeep abreast of HKMA circulars, industry news and market information;\nExcellent communication and interpersonal skills, able to work with stakeholders at different levels; and\nWell-versed in spoken and written English and Chinese, including Putonghua.\nWe offer competitive remuneration package and promising career opportunities to the successful candidates. Interested parties, please send full resume with current & expected salary and the date of availability to\u00a0The HR Division by clicking \"Apply Now\" button below. Please quote reference on your application. Information provided will be treated in strict confidence and only be used for recruitment purposes. Personal data of unsuccessful applications will be destroyed 24 months after the completion of the recruitment and selection exercise.", "employment_types": ["Full Time", "Permanent"], "selling_points": ["I & I Compliance Advisory and Updates", "Policy, Procedural Manuals and Projects", "Regular/ Ad-hoc Review, Testing Programs & Self-As"], "locations": ["Central"], "categories": ["Banking / Finance", "Analyst", "Professional Services", "Legal & Compliance", "Risk Management"], "post_time": "2022-01-12T09:18:49Z", "salary": {"currency": null, "max": null, "min": null, "period": "monthly", "term": null}, "salary_visible": false, "title_keywords": ["assistant vice president"], "responsibilities": ["make recommendations", "reporting", "management", "regulatory requirements", "operations", "review", "compliance", "monitor", "implementation", "coordinate with", "executing", "reports", "ad hoc projects", "business activities"], "requirements": {"degrees": ["university degree"], "majors": ["finance", "business administration", "law"], "languages": ["putonghua", "english", "chinese"], "language_level": [], "hard_skills": ["hkma", "investment products"], "soft_skills": ["communication and interpersonal skills"], "languages_combined": [{"language": "putonghua", "language_level": []}, {"language": "english", "language_level": []}, {"language": "chinese", "language_level": []}]}, "experience_required": {"duration": ["4 years", "minimum of 5 years"], "field": ["compliance", "investment", "insurance"]}}, {"job_id": "100003009043370", "location_code": "hk", "company": "KPay Merchant Service Limited", "job_title": "Senior Product Manager (Fintech)", "description": "Job Requirements:\u00a0\n\n\nManage the product development process including conceptualization, design,\u00a0structuring, and developing product propositions for payment products to serve\u00a0underserved segments\nLead project to enhance financial inclusion for both SME merchants using\u00a0new technologies and partnerships\nManage end to end management of product initiatives including product documentation, coordination of internal and external parties/resources to ensure an effective implementation of initiatives and post-launch management\nConduct market research and customer segmentation for both HK with internal parties and group stakeholders to drive product/service development strategies\nManage business requirements and system testing on new products/services\n\nJob Requirements:\u00a0\n\nBachelor degree or above in Information Technology, Information System, or other relevant discipline\nExperience in product lifecycle management, preferably in agile framework lines\nProduct management experience gained from personal lending business, credit card business or BFSI consulting will be a plus.\nExcellent communication, interpersonal and presentation skills\nProblem-solving aptitude, Well-organized, self-motivated and able to work under pressure\nProficiency in Chinese Mandarin and English, both written and verbal communications", "employment_types": ["Full Time", "Permanent"], "selling_points": ["Fast growing FinTech company", "5-days work week plus birthday & Anniversary leave", "Attractive Remuneration Package"], "locations": ["Kwun Tong"], "categories": ["Banking / Finance", "Analyst", "Information Technology (IT)", "IT Project Management / Team Lead", "Product Management / Business Analyst"], "post_time": "2022-01-12T11:05:07Z", "salary": {"currency": null, "max": null, "min": null, "period": "monthly", "term": null}, "salary_visible": false, "title_keywords": ["senior product manager"], "responsibilities": ["management", "documentation", "consulting", "conduct market research", "internal and external parties", "developing", "design", "implementation", "testing", "communication", "payment", "coordination", "sme", "internal parties", "work under pressure"], "requirements": {"degrees": ["degree or above", "bachelor"], "majors": ["information technology"], "languages": ["english", "chinese", "mandarin"], "language_level": ["proficiency"], "hard_skills": ["plus", "agile", "problem-solving", "information system", "documentation"], "soft_skills": ["self-motivated", "agile", "problem-solving", "well-organized", "communication", "presentation skills", "coordination", "interpersonal", "work under pressure"], "languages_combined": [{"language": "english", "language_level": ["proficiency"]}, {"language": "chinese", "language_level": ["proficiency"]}, {"language": "mandarin", "language_level": ["proficiency"]}]}, "experience_required": {"duration": [], "field": ["management", "consulting", "credit card", "product management", "business"]}}, {"job_id": "100003009036090", "location_code": "hk", "company": "YF Life Insurance International Limited", "job_title": "Strategic Planning and Analysis", "description": "Responsibilities:\n\n\nResponsible for regularly analyzing the economic and financial environment and the development trend of the insurance industry.\n\nOrganize the preparation of mid - and long-term development strategic plans of the company, inspect the implementation of the strategic plans, revise the strategic plans periodically or irregularly as required by the company, and supervise the formulation and implementation of the strategic development plans of each business segment;\nGuide and support each business segment of the company to develop business plans. Support to set KPI according to the annual business objectives, and supervise the implementation of the plans. Regularly analyze and feedback problems and shortcomings, and submit improvement plans and suggestions\nResponsible for the analysis of the company's overall business situation, forecast the achievement of the company's business objectives, and regularly issue planning and analysis reports.\nRequirements:\n\n\nBachelor degree or above, major in economics, management, statistical analysis or related.\n\nMore than 10 years working experience in life insurance;\nProficient in enterprise strategic management, operation management, project management and other theoretical knowledge;\nProficient in business analysis of life insurance, customer data analysis and other data analysis ability;\nExcellent report writing skills in Both Chinese and English, capable of completing analysis reports independently and could find and analyze hidden changes and problems.\nFluent in Cantonese is preferred.\n\nAttractive salary and fringe benefits, including 5-day work week, medical, life insurance, annual leave, pension scheme and training subsidies, etc. will be offered to this permanent appointment. Interested parties please send\u00a0full resume, with academic results, current and expected salary\u00a0to\u00a0Human Resources and Administration Manager by clicking\u00a0\"Apply Now\".\u00a0\u00a0All information received will be used for recruitment purposes only.", "employment_types": ["Full Time", "Permanent"], "selling_points": [], "locations": ["Wan Chai"], "categories": ["Banking / Finance", "Analyst", "Insurance", "Others", "Others", "Others"], "post_time": "2022-01-10T09:19:22Z", "salary": {"currency": null, "max": null, "min": null, "period": null, "term": null}, "salary_visible": false, "title_keywords": [], "responsibilities": ["strategic plans", "analysis reports", "analysis", "implementation", "business plans", "develop", "forecast", "plans", "insurance", "planning"], "requirements": {"degrees": ["degree or above", "bachelor"], "majors": ["economics"], "languages": ["cantonese", "english", "chinese"], "language_level": ["excellent", "fluent"], "hard_skills": ["project management", "analysis", "statistical analysis", "writing skills"], "soft_skills": ["project management", "independently", "capable", "writing skills"], "languages_combined": [{"language": "cantonese", "language_level": ["fluent"]}, {"language": "english", "language_level": ["excellent"]}, {"language": "chinese", "language_level": ["excellent"]}]}, "experience_required": {"duration": ["10 years"], "field": ["insurance"]}}, {"job_id": "100003009038884", "location_code": "hk", "company": "Welab Bank Limited", "job_title": "Manager, Fraud Investigation (Virtual Bank)", "description": "WeLab is a leading fintech company in Asia, \u00a0which operates one of first licensed digital banks in Asia \u2013 WeLab Bank, as well as multiple leading online financial services businesses including WeLend and WeLab Bank in Hong Kong, WeLab Digital (\u6211\u6765\u6570\u79d1), Taoxinji (\u6dd8\u65b0\u673a), Wallet Gugu (\u94b1\u5939\u8c37\u8c37) and Tianmian Tech (\u5929\u5195\u79d1\u6280)\u00a0in Mainland China and Maucash in Indonesia. WeLab aims to bring joy to everyone\u2019s financial journey. We strive to improve people\u2019s lives by reinventing financial services through game-changing technology. We put our people first, whether it\u2019s our customers or our employees.\n\nAs the only homegrown Hong Kong fintech to receive a virtual banking license, we aim to reinvent and redefine the banking experience by building a bank we love.\n\nWe are an energetic and passionate team that can deliver and execute. We are looking for other intellectually curious, open-minded and smart-working individuals who are just as passionate as we are about making financial services enjoyable. Now you have the opportunity to join us on our journey to achieve our vision and be part of building a better financial future for everyone.\n\nAbout you:\n\nYou're a go-getter with mad juggling skills (or multiple hats) who can thrive in a fast-paced, agile environment\nYou have a strong thirst for knowledge and are driven to find solutions that don't exist yet\nYou are comfortable with ambiguity and extremely resourceful (in your past life you could've been a detective)\nYou always find a way to get things done without sacrificing the quality of your work, integrity and values. No task is off limits for you.\nYou are humble and prioritize the success of the team over your own with an eagerness to help those around you\nYou don't shy away from challenges and have the ability to bounce back from setbacks\n\nWhat you\u2019ll do and what success looks like in this role\n\nPrepare management information reports related to fraud / ML for senior management\u2019s oversight\nContact point between the Bank and LEA\nInvestigating the alerts generated by fraud detection and AML transaction monitoring systems and external intelligence from outsider and financial crime risk related matter raised by the business, filling STR to JFIU where necessary\nPerform data analysis and prepare intelligence/crime trend analysis report for management\u2019s review\nMonitor and analysis the performance of fraud monitoring rules for improvement\nPrepare and submit clear, concise, factual, unbiased, thorough and timely investigation reports\nWork closely with relevant business and function units and act as a Subject Matter Expert in fraud / ML\nAssist in implementing the Bank policy and procedure with respect to ensuring effective review of TM alerts and fraud investigations\nHandle ad-hoc projects or tasks as assigned\n\nWhat is required and what we\u2019re looking for\n\nDegree holder preferably in Finance, Law, Accounting, Information Technology or business-related disciplines\n4 years\u2019 or above experience in fraud and/or financial crime investigations, preferable with fraud investigation experience from banks\nWith knowledge of relevant laws, regulations and guidelines\nExposure in SAS programming and project experience/ technical support in implementing financial crime monitoring or investigation system and digital forensic tools is preferable\nProfessional training and qualifications in investigations techniques\nIndependent, good team player, analytical mind with sound communication and interpersonal skills\nProficient in both spoken and written English and Chinese, fluent in Putonghua is preferable\nHolder of AAMLP or CAMS would be an advantage\n\nWeLab perks:\n\nCompetitive salary\nLearning and development stipend, because we value lifelong learning and believe the best way to invest in our employees is to encourage them to continue to learn\nWork hard and laugh lots (chicken wings and french toast, etc.) with a high-performing, fun and diverse team\nHappiness Dollars for spending on anything that makes you happy\nCoffee stipend\nConveniently located office surrounded by diverse and delicious lunch options\nLively office with gaming consoles and a ping pong table\nFun extracurricular activities with your colleagues like hiking, yoga, badminton, wine tasting, dragon boat racing, rock climbing, etc.\nEmployee referral bonuses\n\nAwards & recognition:\n\nFinancial Times (FT) 2020 Asia-Pacific High-Growth Companies \u2013 #2 ranked company\n2020 CNBC Disruptor 50 List \u2013 #11, only company included from Hong Kong and just one of five from Asia\n\nWe offer competitive salary package to the successful candidate.\u00a0 If you are interested in joining this exciting team, please apply with resume via the \"Apply\" button.\n\nAll information provided by applicants will be used for recruitment purposes only. Information of unsuccessful applicants will be destroyed within 24 months of receipt.", "employment_types": ["Full Time", "Permanent"], "selling_points": ["Prepare management information reports", "Contact point between the Bank and LEA", "Perform data analysis"], "locations": ["Quarry Bay"], "categories": ["Banking / Finance", "Analyst", "Financial Services", "Professional Services", "Legal & Compliance"], "post_time": "2022-01-11T08:02:41Z", "salary": {"currency": null, "max": null, "min": null, "period": "monthly", "term": null}, "salary_visible": false, "title_keywords": ["manager"], "responsibilities": ["regulations", "analysis report", "quality", "communication", "ad-hoc projects", "senior management", "monitor", "reports", "banking", "management", "monitoring", "review", "investigation", "data analysis", "contact", "aml", "guidelines", "technical support", "analysis", "systems", "subject matter expert"], "requirements": {"degrees": ["degree holder"], "majors": ["law", "finance", "information technology", "related disciplines", "business", "accounting"], "languages": ["putonghua", "english", "french", "chinese"], "language_level": ["fluent", "proficient"], "hard_skills": ["no", "joy", "agile", "aml", "sas", "fun", "analysis", "ml", "programming", "aamlp", "go", "mad"], "soft_skills": ["passionate", "good team player", "independent", "agile", "resourceful", "open-minded", "timely", "integrity", "prioritize", "clear", "diverse", "analytical mind", "communication and interpersonal skills", "thorough", "learning", "energetic", "driven"], "languages_combined": [{"language": "putonghua", "language_level": ["fluent", "proficient"]}, {"language": "english", "language_level": ["fluent", "proficient"]}, {"language": "french", "language_level": []}, {"language": "chinese", "language_level": ["fluent", "proficient"]}]}, "experience_required": {"duration": ["4 years"], "field": ["banking experience", "programming", "banking", "digital", "financial"]}}, {"job_id": "100003009038496", "location_code": "hk", "company": "Financial Services Development Council", "job_title": "Manager (Policy Research)", "description": "\u00a0Key Responsibilities\n\n\nThe manager will work closely with FSDC Members to conceptualise, manage and coordinate the development of policy research initiatives and other initiatives aligned with FSDC\u2019s mission, vision and strategic objectives.\n\nTo conduct in-depth policy research and studies in relation to economic and financial market developments;\nTo drive and deliver policy research initiatives of one of the FSDC Committees and its working groups;\nTo facilitate cross-team collaboration so as to maximise the impact of FSDC\u2019s research efforts;\nTo prepare research proposals, papers, reports, speeches, presentation materials and briefing materials; and;\nTo perform any other duties as and when required.\n\n\u00a0Requirements\n\n\nPreferably with 5 years\u2019 post-qualification experience in the financial services industry, with experiences in financial market, economic and/or regulatory development research and analysis;\nSolid report writing and analytical skills;\nBachelor\u2019s degree or equivalent, preferably in law, business, finance, economics or related disciplines; a postgraduate degree will be preferably viewed;\nFluent command of both written and spoken English and Chinese; good command of Putonghua; and\nProficiency in computer knowledge and skills, including MS Office. Knowledge of economic and financial databases, including Bloomberg and CEIC, required.\n\nTerms of Appointment & Package\n\nAppointment will be offered on 3 years fixed-term contract.\u00a0 Fringe benefits include paid leave, medical insurance and MPF.\n\nHow to Apply\n\nInterested candidates please send, in not more than four pages altogether, a letter of application and a curriculum vitae setting out the details of qualifications, previous work experience, current and expected salary\u00a0by clicking Apply Now\u00a0on or before 24 January 2022. Shortlisted candidates will be invited to participate in a 1.5 hour written assessment. Applicants not invited for an interview within 8 weeks from the closing date may consider their applications unsuccessful.\u00a0 For enquiries, please call 2493 1313.\n\nAll applications will be handled in strict confidence and the information collected will only be used for recruitment related purposes. All information on unsuccessful candidates will be destroyed after 6 months from the close of application.", "employment_types": ["Full Time", "Contract"], "selling_points": ["Conduct policy research in economics & finance", "Drive policy research initiatives in Committees", "Prepare research proposals, speeches, presentation"], "locations": ["Central"], "categories": ["Banking / Finance", "Analyst", "Financial Services", "Public / Civil", "Others"], "post_time": "2022-01-11T07:06:50Z", "salary": {"currency": null, "max": null, "min": null, "period": "monthly", "term": null}, "salary_visible": false, "title_keywords": ["manager"], "responsibilities": ["coordinate", "any other duties", "reports"], "requirements": {"degrees": ["degree", "bachelor"], "majors": ["law", "finance", "economics", "related disciplines", "business"], "languages": ["putonghua", "english", "chinese"], "language_level": ["good command", "fluent"], "hard_skills": ["bloomberg", "analysis", "analytical skills", "databases", "ms office"], "soft_skills": ["analytical skills"], "languages_combined": [{"language": "putonghua", "language_level": ["good command"]}, {"language": "english", "language_level": ["fluent"]}, {"language": "chinese", "language_level": ["fluent"]}]}, "experience_required": {"duration": ["5 years"], "field": ["research", "post-qualification", "development", "financial services industry", "financial"]}}, {"job_id": "100003009037764", "location_code": "hk", "company": "Oliver James Associates Limited", "job_title": "Bank, Settlement Associate (up to 55K, renewable contract)", "description": "Job Responsibilities:\n\n\u2022 Experience of Settlement function and a good understanding of trade life cycle and settlement end-to-end flow for fixed income products.\n\u2022 Good communication skills in both English and Cantonese.\n\u2022 Maintain a high level of accuracy and be vigilant when validating the settlement instructions and authorizing payments. The candidate also needs to have high control awareness and be flexible in handling exception in case of system problems. A high degree of judgment is required in handling non-routine/irregular issues. Instant response and quick decisions are perpetually required to meet deadlines. As the global settlement activities stretch across all different settlement systems, the candidate must get himself familiarized with operations of the different systems.\n\u2022 To cope with the rapidly changing environment, the candidate must keep himself up-to-date for the skill and knowledge of the securities industry and be conversant with the special market practices, rules and regulations in order to comply with and avoid any breaching of the regulations.\n\u2022 The candidate needs to rigorously enforce dual control in Settlements area and put in place the appropriate level of segregation of duties in processing settlement capability within the authorized limits.\n\u2022 The candidate needs to ensure all trading activities need to adhere to and comply with the Securities Ordinance as well as the Rules and Regulations of Securities and Futures Commission \u201cSFC\u201d.\n\u2022 The candidate must have a clear understanding of the market regulations and have to ensure that any irregularities are reported to the manager. If necessary, the candidate should further clarify with Compliance before processing, to avoid breaching of the regulations.", "employment_types": ["Contract"], "selling_points": ["temp to perm", "attractive benefit", "banking exposure"], "locations": ["Mong Kok"], "categories": ["Banking / Finance", "Analyst"], "post_time": "2022-01-11T03:46:06Z", "salary": {"currency": null, "max": null, "min": null, "period": "monthly", "term": null}, "salary_visible": false, "title_keywords": ["associate"], "responsibilities": ["regulations", "control", "irregularities", "operations", "systems", "compliance", "communication", "maintain", "payments"], "requirements": {"degrees": ["degree"], "majors": [], "languages": ["cantonese", "english"], "language_level": ["good"], "hard_skills": ["processing"], "soft_skills": ["flexible", "communication skills", "meet deadlines", "clear"], "languages_combined": [{"language": "cantonese", "language_level": ["good"]}, {"language": "english", "language_level": ["good"]}]}, "experience_required": {"duration": [], "field": []}}, {"job_id": "100003009042870", "location_code": "hk", "company": "Chong Hing Bank Ltd", "job_title": "SRM / RM - Hong Kong Corporates/ Mainland Corporates", "description": "Responsibilities:\n\n\nBuild and manage a corporate customer portfolio of the Bank by providing financial solutions and cross-selling suitable products/services to them\nSolicit new customer prospects to enlarge the Bank\u2019s customer portfolio\nProvide quality and value-added services to the customers for building a long- term trusted relationship\nPrepare comprehensive credit proposals and reviews for assessing customers\u2019 credit worthiness and react to the market changes from time to time\nRequirements:\n\n\nUniversity graduate in Business Administration, Accounting, Finance, Economics or a related discipline\nMinimum 3 years' solid experience in corporate/commercial banking\nGood credit analysis, report writing and communication skills\nSelf-motivated, independent and able to work under pressure\nProficient in both spoken and written English and Chinese,\u00a0Putonghua is preferred\n\n\nWe offer competitive remuneration package and promising career opportunities to the successful candidates. Interested parties, please send full resume with current & expected salary and the date of availability to\u00a0The HR Division, G.P.O. Box 2535, HK\u00a0, or by clicking Apply Now. Please quote reference on your application. Information provided will be treated in strict confidence and only be used for recruitment purposes. Personal data of unsuccessful applications will be destroyed 24 months after the completion of the recruitment and selection exercise.", "employment_types": ["Full Time", "Permanent"], "selling_points": ["Build and manage a customer portfolio", "Prepare comprehensive credit proposals", "Discretionary performance bonus, Life insurance"], "locations": ["Central"], "categories": ["Banking / Finance", "Analyst", "Credit Analysis / Approval", "Corporate Finance"], "post_time": "2022-01-12T09:04:45Z", "salary": {"currency": null, "max": null, "min": null, "period": null, "term": null}, "salary_visible": false, "title_keywords": [], "responsibilities": ["quality"], "requirements": {"degrees": ["university graduate"], "majors": ["economics", "finance", "accounting", "business administration"], "languages": ["putonghua", "english", "chinese"], "language_level": ["proficient"], "hard_skills": ["credit analysis"], "soft_skills": ["communication skills", "self-motivated", "independent", "work under pressure"], "languages_combined": [{"language": "putonghua", "language_level": ["proficient"]}, {"language": "english", "language_level": ["proficient"]}, {"language": "chinese", "language_level": ["proficient"]}]}, "experience_required": {"duration": ["minimum 3 years"], "field": ["commercial", "banking"]}}, {"job_id": "100003009033785", "location_code": "hk", "company": "APAC Asset Valuation and Consulting Limited", "job_title": "(Fresh Graduates Welcomed) Assistant Valuer / Valuer", "description": "Responsibilities:\n\nTo perform valuation exercises for public listed companies and private institutions in Asia Pacific, mainly involving the valuations of businesses and financial derivatives (including but not limited to convertible bonds, equity options, futures, currency forwards / swaps, etc.);\nTo perform market research, industry and comparable analysis, and to prepare reports on the results of valuations;\nTo conduct site inspections (when necessary) and collect information from various market and company specific sources relating to the valuation exercises;\nTo perform analyses and valuation tasks on an individual basis, and to be able to work in a team-oriented environment; and\nTo understand characteristics of the valuation subjects, draw connections between said characteristics and the intrinsic values of the underlying assets, and provide justifications for the valuation opinions.\n\nRequirements\n\nDiploma or above in corporate finance / quantitative finance/ financial engineering / economics / business administration / accounting / mathematics / computing related disciplines;\nMinimum 1 years working experience in valuation/ accounting / finance / business/ banking related field is preferred, but applications from fresh graduates are welcomed and would be sincerely considered;\nGood computer proficiencies and sound analytical skills;\nDiligent, self-motivated, good team player, and able to work independently within a tight schedule; and\nProficiencies in both written and spoken English and Chinese (including Mandarin).\n\nInterested parties, please send Full Resume with Expected Salary by Clicking\u00a0\"Apply Now\"\n**Personal data collected will be used for recruitment\u00a0", "employment_types": ["Full Time", "Permanent", "Temporary", "Contract", "Internship"], "selling_points": [], "locations": ["Sheung Wan"], "categories": ["Accounting", "Financial Analyst", "Banking / Finance", "Analyst", "Professional Services", "Business Consultancy"], "post_time": "2022-01-10T01:47:58Z", "salary": {"currency": null, "max": null, "min": null, "period": "monthly", "term": null}, "salary_visible": false, "title_keywords": ["valuer", "assistant valuer"], "responsibilities": ["valuation", "analysis", "market research", "site inspections", "prepare reports"], "requirements": {"degrees": ["diploma or above"], "majors": ["mathematics", "business administration", "engineering", "finance", "economics", "related disciplines", "accounting"], "languages": ["english", "chinese", "mandarin"], "language_level": [], "hard_skills": ["analytical skills"], "soft_skills": ["good team player", "self-motivated", "work independently", "diligent", "analytical skills"], "languages_combined": [{"language": "english", "language_level": []}, {"language": "chinese", "language_level": []}, {"language": "mandarin", "language_level": []}]}, "experience_required": {"duration": ["minimum 1 years"], "field": ["related", "finance", "business", "banking", "accounting"]}}, {"job_id": "100003009039277", "location_code": "hk", "company": "Deloitte Touche Tohmatsu", "job_title": "Manager / Senior Manager (Actuarial) - Human Capital - Hong Kong", "description": "At Deloitte China, we are on a mission to nurture and empower our people to become deep subject matter experts. We offer the perfect platform to unleash your full potential and equip you to thrive on challenges, and partner with our clients to solve their most complex problems. A world of opportunities awaits. Start your adventure and journey with us.\n\nAbout The Business\n\nDeloitte\u2019s\u00a0Human Capital\u00a0professionals help organizations drive productivity, value and impact through the organization, Human Resources and the workforce. Our professionals leverage research, analytics, technology solutions and industry insights to help:\n\nCreate an organization that is adaptable to change that can respond to the increasing need for transparency in the era of the Social Enterprise\nCompose a workforce that drives productivity and value\u2014today and in the future\nDesign all aspects of work in a way that allows the worker to find meaning and esteem in the work they perform\nProvide business & people insights through data analytic & actuarial consulting\nActuarial & Insurance\u00a0: The actuarial function is a core component of any insurance operation. Retirement benefit is also typically part of an essential package of employee benefits. In these areas, actuarial capability is required. Actuaries also expand their quantitative skills into the advanced data analytics to provide insights into underwriting, claims management, risk management and human resources management.\n\nWork you'll do\nManage own work against the project plan to ensure a superior client experience\nUnderstand the client\u2019s business, follow sector trends and learn leading practices\nDiagnose a problem, conduct analysis, and develop solutions for client problems\nArticulate thoughts and ideas in a clear and composed manner to instill confidence in team and clients\nEffectively interact with colleagues and clients of varying backgrounds to effectively serve clients\nWork with our practice leaders and professional consultants as a team to solve complex business problems and deliver high quality solutions to our clients on areas including but not limited to:\nFinancial reporting\nSolvency II / Economic Capital\nIFRS 17\nEmbedded value\nActuarial modeling\nMerger & Acquisition\nMarket entry strategy\nAsset-liability management\nProduct pricing\nRisk management\nActuarial audit\nMarket research\nWork and collaborate with our professionals in the actuarial practice and other consulting service lines in different geographical locations including the United Kingdom, Australia, China, Singapore and Taiwan\nA fit for the role? Let's talk about you.\n\nBachelor degree or above with strong academic credentials\nQualified or committed to obtaining fellowship qualification of an internationally recognized actuarial organization\n6 years or above relevant insurance and actuarial experience in life and general insurance markets\nSound analytical and problem-solving skills with strong attention to detail\nExcellent communication skills, both written and oral\nA team player with great interpersonal skills\n\n\n\u6709\u610f\u7533\u8acb\u8005\u8acb\u6309 APPLY NOW\u7533\u8acb", "employment_types": ["Full Time"], "selling_points": [], "locations": ["Not Specified"], "categories": ["Banking / Finance", "Analyst", "Sales, CS & Business Devpt", "Business Development", "Management", "Top Executives (CEO, CFO, CTO, GM, MD etc.)"], "post_time": "2022-01-11T09:16:05Z", "salary": {"currency": null, "max": null, "min": null, "period": "monthly", "term": null}, "salary_visible": false, "title_keywords": ["senior manager", "manager"], "responsibilities": ["consulting", "insurance", "design", "data"], "requirements": {"degrees": [], "majors": [], "languages": [], "language_level": [], "hard_skills": [], "soft_skills": ["adaptable", "deep"], "languages_combined": []}, "experience_required": {"duration": [], "field": []}}, {"job_id": "100003009038225", "location_code": "hk", "company": "Teki'Spire Limited", "job_title": "Project Manager (Sr Manager - Associate Director Level)", "description": "Duties:\nManage Projects covering Payment, New Product, and Compliance and make sure projects are in line with company's project management methodology\nWork collaboratively and build relationships with internal stakeholders to elicit requirements to ensure the business objectives and product vision is being delivered\u00a0\nDetermine the strategic direction of products and ensure they align with the needs of the business, market and stakeholders\nAnalyse complex issues and identify root causes\u00a0\nDevelop requirements and produce high-quality process flows\u00a0\nValidate business cases to ensure all benefits are measurable\u00a0\nPresent analysis and process reviews to stakeholders and project teams\u00a0\nManage workshops and meetings with business and technology\u00a0\nIdentify risks and track through to resolution\u00a0\nSupport the business to ensure readiness for change (e.g. UAT, Training, documentation etc.)\u00a0\nImplement process improvements and system deployments\u00a0\nWork to agreed deadlines and coordinate others accordingly\u00a0\nPerform data analysis and generate proper reports to major stakeholders\u00a0\nJudge to design and implement effective changes which address business needs\u00a0\nShares information and ideas with others, has good listening skills\u00a0\nProvide coaching and support to other team members as needed\nRequirements:\n10+ years in a project manager/ business analyst or similar role, preferable with exposure to Financial Services\nStrong experience in managing and leading projects or programs, preferably within a Business Improvement environment\u00a0\nStrong experience in preparing process and requirement documentation as well as technical/software development\u00a0\nAbility to elicit product requirements from stakeholder requests and feedback\nGood communication skill with proven ability to tailor communications to suit different levels of audiences\u00a0\nConfident to deal with senior management and executives across all areas of the business\u00a0\nProactive approach to work, willing to take initiative and follow through with delivery\u00a0\nProficient in MS Office Suite of products including MS Visio, Excel (macro), MS PowerPoint and MS Word\u00a0\nKeen attention to detail and problem-solving capabilities\u00a0\nProven track record of dealing with multiple projects of work and effective prioritization\u00a0\nAbility to transfer the knowledge gained throughout various parts of the organization\u00a0\nAble to analyse requirements, risks and issues and can prioritise requirements based on priority and benefits\u00a0\nMust be able to adapt to change, work well under pressure and be open to new ideas\u00a0\nPrevious experience in leading a small team\u00a0\nFluency in Cantonese and English\nPlease hit \"Apply now\" to attach your CV with your current & expected salary for these specific roles. We will contact you shortly. Or simply\u00a0email your CV to careers(a)tekispire.com\u00a0and we will link you up to suitable opportunities.\u00a0", "employment_types": ["Full Time", "Permanent"], "selling_points": ["Financial Service, In-house, Perm", "Payment, New Product, Compliance", "Business Analyst, Project Manager, Product Manager"], "locations": ["Not Specified"], "categories": ["Banking / Finance", "Analyst", "Information Technology (IT)", "Others"], "post_time": "2022-01-11T06:13:21Z", "salary": {"currency": null, "max": null, "min": null, "period": "monthly", "term": null}, "salary_visible": false, "title_keywords": ["associate director", "project manager", "manager"], "responsibilities": ["compliance", "quality", "develop", "project management", "payment", "manage projects", "analyse"], "requirements": {"degrees": [], "majors": [], "languages": [], "language_level": [], "hard_skills": [], "soft_skills": [], "languages_combined": []}, "experience_required": {"duration": [], "field": []}}, {"job_id": "100003009050912", "location_code": "hk", "company": "Bank of Communications Co., Ltd. Hong Kong Branch", "job_title": "Relationship Manager (Corporate Banking)", "description": "Career Level\nMiddle\nQualification\nDegree\nYears of Experience\n3 years\nJob Type\nFull Time, Permanent\nJob Functions\nBanking / Finance, Analyst, Corporate Banking, Credit Analysis / Approval", "employment_types": ["Full Time", "Permanent"], "selling_points": [], "locations": ["Wan Chai Area"], "categories": ["Banking / Finance", "Analyst", "Corporate Banking", "Credit Analysis / Approval"], "post_time": "2022-01-14T11:45:25Z", "salary": {"currency": null, "max": null, "min": null, "period": null, "term": null}, "salary_visible": false, "title_keywords": ["relationship manager"], "responsibilities": ["analysis", "banking"], "requirements": {"degrees": ["degree"], "majors": [], "languages": [], "language_level": [], "hard_skills": ["credit analysis"], "soft_skills": [], "languages_combined": []}, "experience_required": {"duration": [], "field": []}}, {"job_id": "100003009034267", "location_code": "hk", "company": "Zebra Strategic Outsource Solution Ltd", "job_title": "Research Assistant, China Research Team (Banking)", "description": "Responsibilities:\n\nSupport Head of China Research in providing research coverage in the China sector\nCreate, update and maintain company models, company valuation, and industry databases\nPerform regular tasks promptly and provide regular reports to the analyst including analysis of periodically released industry statistics, sector news, etc.\nHandle ad-hoc client requests\n\nRequirements:\n\nDegree holder with related research experience\nStrong communication skills\nFlexibility to handle multiple research assignments simultaneously\nPassion for in-depth analysis and stock picking\nGenerate creative research ideas and ability to write clear and concise research notes\nAble to prioritize\u00a0and work well under pressure\n\nThis position will be under the employment of Zebra Strategic Outsource Solution Ltd.\nTo find out more about Zebra, visit us at\u00a0www.zebragroup.com\nAll personal data collected will be kept in strict confidence and would only be used for recruitment purpose.", "employment_types": ["Full Time", "Temporary", "Contract"], "selling_points": [], "locations": ["Kwun Tong"], "categories": ["Banking / Finance", "Analyst", "Investment", "Others"], "post_time": "2022-01-10T03:03:26Z", "salary": {"currency": null, "max": null, "min": null, "period": "monthly", "term": null}, "salary_visible": false, "title_keywords": ["research assistant"], "responsibilities": ["ad-hoc", "valuation", "analysis", "maintain", "reports", "databases"], "requirements": {"degrees": ["degree holder"], "majors": [], "languages": [], "language_level": [], "hard_skills": ["analysis"], "soft_skills": ["communication skills", "confidence", "under pressure", "able to prioritize", "passion for", "clear", "creative"], "languages_combined": []}, "experience_required": {"duration": [], "field": ["related", "research"]}}, {"job_id": "100003009036773", "location_code": "hk", "company": "Industrial and Commercial Bank of China (Asia) Limited", "job_title": "Senior Officer or Manager, Bond Syndication and Research, Global Capital Financing", "description": "Job Responsibilities\nExecute bond transaction in the primary market as a member of syndicate\nProvide information and insight on global and local macroeconomic conditions, market sentiment and pricing rationale for sovereign, financial and corporate names\nAnalyze company\u2019s financial status and using comparable data to provide price guidance to both internal and external clients\nWork with a senior member of the team on bond transaction execution, including Book building, allocating and pricing transactions which includes hosting, preparing and participating in market update, IPG, FPG calls. Support DCM in their materials including bond structure recommendations for clients (i.e. tenor, size aspirations, etc) as well as supplementing market information.\nWork under a senior member of the team to write thematic research reports on the Asian bond market and daily summaries, as well as forward-looking thematic pieces on market trends and outlook\nFormulate recommendation and present insight to both internal and external stakeholders based on market conditions and specific needs of the transactions, both orally and in writing\nObtain market information and investor views by speaking to investors directly or through liaising with the sales team in the department\nJob Requirements\nUniversity degree in Economics, Finance or related disciplines\n2 year to 5 year working experience with sound knowledge of the debt market in Asia\nIntrinsic curiosity on macro or market trends, impacts of geopolitical events on the market\nHighly self-motivated, attention to details\nsound knowledge of fixed income market or financial modelling\nFluent in Chinese (Putonghua) and English, both written and spoken\nStrong interpersonal, communication, and analytical skills with a can-do attitude\nStrong skillset on excel, Bloomberg charts, and necessary statistics for data interpretation", "employment_types": ["Permanent"], "selling_points": [], "locations": ["Central"], "categories": ["Banking / Finance", "Analyst", "Investment", "Corporate Finance"], "post_time": "2022-01-10T13:56:19Z", "salary": {"currency": null, "max": null, "min": null, "period": "monthly", "term": null}, "salary_visible": false, "title_keywords": ["senior officer", "manager"], "responsibilities": ["guidance", "market information", "data", "liaising with", "transactions", "reports", "sales team"], "requirements": {"degrees": ["university degree"], "majors": ["related disciplines", "finance", "economics"], "languages": ["putonghua", "english", "chinese"], "language_level": ["fluent"], "hard_skills": ["excel", "macro", "bloomberg", "analytical skills"], "soft_skills": ["self-motivated", "can-do attitude", "analytical skills", "communication", "attention to details", "interpersonal"], "languages_combined": [{"language": "putonghua", "language_level": ["fluent"]}, {"language": "english", "language_level": ["fluent"]}, {"language": "chinese", "language_level": ["fluent"]}]}, "experience_required": {"duration": ["5 year", "2 year"], "field": []}}, {"job_id": "100003009028494", "location_code": "hk", "company": "Manulife (International) Limited", "job_title": "Junior Business Analyst", "description": "Job Duties:\u00a0\n\nProvide comprehensive financial and investment advice to clients\nIdentify and recommend the high profitable segments\u00a0\nMonitor and review investment portfolios\nPromote our professional services and existing projects to clients\nMaintain a high quality standard relationship with our existing clients\n\nRequirements:\n\nHong Kong citizens or work permit holder is a must\nUniversity graduate in any discipline (preferably in finance discipline)\nFresh graduates and IANG holders will also be considered\nCandidates with oversea study or work experience are welcome\nSelf-motivate, independent, excellent presentation skills with the ability to work effectively under pressure\nFluent in spoken Cantonese, Putonghua and English\nOutgoing and willing to work in a team-oriented atmosphere\n\nWe offer:\n\n5-days work and attractive remuneration package ($20K above with attractive bonuses)\nProfessional training programme including mentorship support and leadership workhouse\nMedical scheme and other allowance\nSponsorship for professional qualifications (CFP, CFA, RFP)\nIncentive Trips & Overseas Conferences\nExcellent career path and fast-track advancement opportunities\n\nApplications:\n\nInterested parties please send your resume with current and expected salaries by clicking\u00a0Apply Now\n\nPersonal data collected will be used for recruitment purpose only.\u00a0Interview will be arranged by the employer for suitable candidates.", "employment_types": ["Full Time", "Part Time", "Permanent", "Internship", "Freelance"], "selling_points": ["$20K above with attractive remuneration bonuses", "5-days work & medical scheme and other allowance", "Professional training programme & mentor support"], "locations": ["Ngau Tau Kok"], "categories": ["Banking / Finance", "Analyst", "Financial Services", "Wealth Management"], "post_time": "2022-01-07T02:25:44Z", "salary": {"currency": "HKD", "max": 24999, "min": 20000, "period": "monthly", "term": null}, "salary_visible": true, "title_keywords": ["business analyst", "junior"], "responsibilities": ["review", "quality", "monitor", "investment portfolios", "maintain"], "requirements": {"degrees": ["university graduate"], "majors": ["finance"], "languages": ["cantonese", "putonghua", "english"], "language_level": ["fluent"], "hard_skills": [], "soft_skills": ["work effectively", "outgoing", "independent", "under pressure", "presentation skills"], "languages_combined": [{"language": "cantonese", "language_level": ["fluent"]}, {"language": "putonghua", "language_level": ["fluent"]}, {"language": "english", "language_level": ["fluent"]}]}, "experience_required": {"duration": [], "field": []}}, {"job_id": "100003009036625", "location_code": "hk", "company": "Welab Bank Limited", "job_title": "Assistant Manager, Finance Projects (Virtual Bank)", "description": "WeLab is a leading fintech company in Asia, \u00a0which operates one of first licensed digital banks in Asia \u2013 WeLab Bank, as well as multiple leading online financial services businesses including WeLend and WeLab Bank in Hong Kong, WeLab Digital (\u6211\u6765\u6570\u79d1), Taoxinji (\u6dd8\u65b0\u673a), Wallet Gugu (\u94b1\u5939\u8c37\u8c37) and Tianmian Tech (\u5929\u5195\u79d1\u6280)\u00a0in Mainland China and Maucash in Indonesia. WeLab aims to bring joy to everyone\u2019s financial journey. We strive to improve people\u2019s lives by reinventing financial services through game-changing technology. We put our people first, whether it\u2019s our customers or our employees.\n\nAs the only homegrown Hong Kong fintech to receive a virtual banking license, we aim to reinvent and redefine the banking experience by building a bank we love.\n\nWe are an energetic and passionate team that can deliver and execute. We are looking for other intellectually curious, open-minded and smart-working individuals who are just as passionate as we are about making financial services enjoyable. Now you have the opportunity to join us on our journey to achieve our vision and be part of building a better financial future for everyone.\n\nAbout you:\n\nYou're a go-getter with mad juggling skills (or multiple hats) who can thrive in a fast-paced, agile environment\nYou have a strong thirst for knowledge and are driven to find solutions that don't exist yet\nYou are comfortable with ambiguity and extremely resourceful (in your past life you could've been a detective)\nYou always find a way to get things done without sacrificing the quality of your work, integrity and values. No task is off limits for you.\nYou are humble and prioritize the success of the team over your own with an eagerness to help those around you\nYou don't shy away from challenges and have the ability to bounce back from setbacks\n\nWhat you\u2019ll do and what success looks like in this role\n\nReporting to Deputy Chief Financial Officer to manage strategic projects of the Bank and cross teams projects within Finance\nPerform periodic reviews to monitor progress of ongoing initiatives, demonstrate good understanding of existing deficiencies of the business and process, and articulate the pain points and bottlenecks\nServe as a result-oriented project manager working across various functions with internal and external stakeholders to drive business and operational improvement efforts and to ensure the successful delivery of business objectives and strategy\nSupport the overall team management of the Finance and Treasury department\nProvide support different finance teams for ad-hoc tasks\nAct as one of the communication point with different teams across business units and/or Group functions\n\nWhat is required and what we\u2019re looking for\n\nDegree holder in Business Administration, Economics, Management or equivalent disciplines\nMinimum 3 years of experience in management consulting, investment banking, private equity, corporate strategy or equivalent project management experience in finance / technology company\nImpeccable business judgment and demonstrated analytical and problem-solving skills\nExcellent communication and interpersonal skills with an ability to distil complex issues into structured frameworks and concrete action plans. Precision and composure are key\nAlways focused on the bigger picture but also possesses an eagle eye for details\nEntrepreneurial self-starter who can work in a fast-paced environment with minimal supervision\nSpoken and written fluency in English, Cantonese\nExcellent in Excel and PowerPoint\n\nWeLab perks:\n\nCompetitive salary\nLearning and development stipend, because we value lifelong learning and believe the best way to invest in our employees is to encourage them to continue to learn\nWork hard and laugh lots (chicken wings and french toast, etc.) with a high-performing, fun and diverse team\nHappiness Dollars for spending on anything that makes you happy\nCoffee stipend\nConveniently located office surrounded by diverse and delicious lunch options\nLively office with gaming consoles and a ping pong table\nFun extracurricular activities with your colleagues like hiking, yoga, badminton, wine tasting, dragon boat racing, rock climbing, etc.\nEmployee referral bonuses\n\nAwards & recognition:\n\nFinancial Times (FT) 2020 Asia-Pacific High-Growth Companies \u2013 #2 ranked company\n2020 CNBC Disruptor 50 List \u2013 #11, only company included from Hong Kong and just one of five from Asia\n\nWe offer competitive salary package to the successful candidate.\u00a0 If you are interested in joining this exciting team, please apply with resume via the \"Apply\" button.\n\nAll information provided by applicants will be used for recruitment purposes only. Information of unsuccessful applicants will be destroyed within 24 months of receipt.", "employment_types": ["Full Time"], "selling_points": ["Manage strategic projects of the Bank", "Perform periodic reviews to monitor progress", "Ensure the successful delivery of objectives"], "locations": ["Quarry Bay"], "categories": ["Accounting", "Financial Analyst", "Banking / Finance", "Analyst", "Professional Services", "Business Analysis / Data Analysis"], "post_time": "2022-01-10T11:24:55Z", "salary": {"currency": null, "max": null, "min": null, "period": "monthly", "term": null}, "salary_visible": false, "title_keywords": ["assistant manager,"], "responsibilities": ["reporting", "management", "provide support", "monitor progress", "consulting", "ad-hoc tasks", "teams", "quality", "communication", "project management", "banking", "plans", "administration"], "requirements": {"degrees": ["degree holder"], "majors": ["economics", "business administration"], "languages": ["cantonese", "english", "french"], "language_level": ["fluency"], "hard_skills": ["excel", "no", "joy", "agile", "fun", "powerpoint", "project management", "problem-solving skills", "go", "private equity", "mad"], "soft_skills": ["agile", "focused", "fast-paced environment", "communication", "articulate", "integrity", "diverse", "passionate", "open-minded", "prioritize", "communication and interpersonal skills", "problem-solving skills", "energetic", "result-oriented", "driven", "resourceful", "project management", "learning", "structured"], "languages_combined": [{"language": "cantonese", "language_level": []}, {"language": "english", "language_level": ["fluency"]}, {"language": "french", "language_level": []}]}, "experience_required": {"duration": ["minimum 3 years"], "field": ["management", "consulting", "banking experience", "finance", "project management", "investment", "banking"]}}, {"job_id": "100003009023234", "location_code": "hk", "company": "Realord Asia Pacific Securities Limited", "job_title": "Research Analyst", "description": "Job Description\n\nConduct research and analysis of industries/stocks, especially IPO listed in HK\nAnalyze economic data and trends in China and Hong Kong using mathematical models and statistical techniques\nCompile daily stock commentary, research reports, publications, presentations, periodic reports and other materials to provide supportive information\nProvide research services to institutional, corporate and high net-worth clients\nUndertake investment research under supervision of the management\nParticipate in market activities including roadshows and investment forums\nHandle ad-hoc projects as assigned\n\nJob Requirements\n\nBachelor degree or above in Finance, Economics, Accounting or related disciplines\nHolder of SFC Type 4 licence and at least 2 years equity research experience with a focus in China and Hong Kong market\nOutstanding analytical skills with good grasp of statistics, and familiarity with global and regional economies\nStrong conceptual and critical thinking skills, able to identify and access key issues rather than simply filtering and reprocessing information\nSelf-motivated, responsible and able to work independently under pressure and tight deadlines\nExcellent interpersonal and communication skills\nFamiliar with MS Excel Marco, PowerPoint and experience in handling Bloomberg is an advantage\nExcellent command of written and spoken English and Chinese(including Mandarin)\n\n\n\nWe offer attractive remuneration and benefits to the right candidates. Interested parties, please send your application with full resume stating your CURRENT and EXPECTED salary\u00a0by email or click \"APPLY Now\".\n\nAll information collected will be kept in strictly confidential and will be used for recruitment purpose only.", "employment_types": ["Full Time"], "selling_points": ["Equity research", "At least 2 years of research experience", "IANG Holder is also welcome"], "locations": ["Central"], "categories": ["Banking / Finance", "Analyst", "Fund Management", "Others"], "post_time": "2022-01-05T07:51:47Z", "salary": {"currency": null, "max": null, "min": null, "period": "monthly", "term": null}, "salary_visible": false, "title_keywords": ["research analyst"], "responsibilities": ["management", "data", "analysis", "presentations", "reports", "ad-hoc projects", "conduct research"], "requirements": {"degrees": ["degree or above", "bachelor"], "majors": ["related disciplines", "finance", "economics", "accounting"], "languages": ["english", "mandarin"], "language_level": ["excellent"], "hard_skills": ["bloomberg", "powerpoint", "analytical skills", "marco", "ms excel", "focus"], "soft_skills": ["communication skills", "work independently", "self-motivated", "under pressure", "responsible", "analytical skills", "focus", "interpersonal"], "languages_combined": [{"language": "english", "language_level": ["excellent"]}, {"language": "mandarin", "language_level": ["excellent"]}]}, "experience_required": {"duration": ["at least 2 years"], "field": ["equity research"]}}, {"job_id": "100003009031354", "location_code": "hk", "company": "Eve Asia Co., Ltd", "job_title": "Junior Research Analyst (\u521d\u7d1a\u7814\u7a76\u54e1)", "description": "Job Description\n\nGathering public information through numerous sources and assisting in execution of deals\nDeveloping and maintaining various databases;\nAnalysing company performance on an absolute and relative basis\nGenerating models for valuation metrics;\nAssist ad-hoc assignment as required\n\nRequirement\n\nUniversity degree or equivalent, preferably in Business or Finance\n2 years of financial analysis experience with strong research skills, fresh graduates are also welcome.\nExcellent communication skills with good command in both written and spoken English and Chinese\nProficient in Excel, Word and PowerPoint\nWilling to travel\nImmediate availability is preferred\nWe offer an attractive package and good career development for the right candidate.", "employment_types": ["Full Time", "Permanent"], "selling_points": ["Conducting research", "Proficient in MS Office", "2 years of financial analysis experience"], "locations": ["Kwun Tong"], "categories": ["Banking / Finance", "Analyst"], "post_time": "2022-01-07T09:14:16Z", "salary": {"currency": null, "max": null, "min": null, "period": "monthly", "term": null}, "salary_visible": false, "title_keywords": ["research analyst", "junior"], "responsibilities": ["ad-hoc", "valuation", "maintaining", "developing", "databases"], "requirements": {"degrees": ["university degree"], "majors": ["finance", "business"], "languages": ["english", "chinese"], "language_level": ["excellent", "good command"], "hard_skills": ["financial analysis", "excel", "word", "powerpoint"], "soft_skills": ["communication skills", "research skills"], "languages_combined": [{"language": "english", "language_level": ["excellent", "good command"]}, {"language": "chinese", "language_level": ["excellent", "good command"]}]}, "experience_required": {"duration": ["2 years"], "field": ["research", "financial"]}}]