[{"job_id": "100003009054278", "location_code": "hk", "company": "Inspire Executive Limited", "job_title": "Fund of Funds Investment Analyst - VP", "description": "Our client is a newly set up Chinese asset management firm, they are looking for a FoF investment analyst - VP level to join their firm.\n\nResponsibilities:\n\nCreating and executing financial analysis to support the investment process for both third-party fund investment and direct investment\nConducting insight research on both private and public Fund in Hong Kong Market\nConduct and Support in due diligence procedures, research and financial modelling\nMonitor the existing investments for consistency to stated strategy, performance, trends and other quantitative and qualitative aspects\nHandle end-to-end investment execution and liaise with both internal and external stake holdersRequirements:\n2-5 years of experience in financial markets with strong analytical skills, less experience will be considered as Junior Postion\nIdeally from a FoF background, but also open to consider candidates from top tier consulting houses, advisory firms like Big 4, Investment Banking Divisions, Equity Research\nAbility to interpret qualitative and quantitative data, and add own judgment to the investment process\nStrong analytical, writing and oral communication skills\nFluent in\u00a0spoken and written Mandarin & English", "employment_types": ["Full Time"], "selling_points": ["Fund of Fund", "asset management", "Investment"], "locations": ["Central & Western Area"], "categories": ["Banking / Finance", "Asset Management"], "post_time": "2022-01-17T09:01:10Z", "salary": {"currency": null, "max": null, "min": null, "period": "monthly", "term": null}, "salary_visible": false, "title_keywords": ["analyst"], "responsibilities": ["due diligence", "consulting", "data", "procedures", "monitor", "financial analysis", "communication", "executing", "banking", "liaise with", "asset management"], "requirements": {"degrees": [], "majors": [], "languages": ["english", "chinese", "mandarin"], "language_level": ["fluent"], "hard_skills": ["financial analysis", "analytical skills"], "soft_skills": ["communication skills", "oral", "analytical skills"], "languages_combined": [{"language": "english", "language_level": ["fluent"]}, {"language": "chinese", "language_level": []}, {"language": "mandarin", "language_level": ["fluent"]}]}, "experience_required": {"duration": ["2-5 years"], "field": ["financial markets", "analytical"]}}, {"job_id": "100003009054303", "location_code": "hk", "company": "Infinity Asset Management Limited", "job_title": "Analyst", "description": "Please submit CV in both Chinese & English with your current and expected salary.\n\n\nResponsibilities:\n\nCreating and executing financial analysis to support the investment process for both third-party fund investment and direct investment\nConducting insight research on both private and public Fund in Hong Kong Market\nConduct and Support in due diligence procedures, research and financial modelling\nMonitor the existing investments for consistency to stated strategy, performance, trends and other quantitative and qualitative aspects\nHandle end-to-end investment execution and liaise with both internal and external stake holders\n\nRequirements:\n\n2-5 years of experience in financial markets with strong analytical skills, less experience will be considered as Junior Postion\nIdeally from a FoF background, but also open to consider candidates from top tier consulting houses, advisory firms like Big 4, Investment Banking Divisions, Equity Research\nAbility to interpret qualitative and quantitative data, and add own judgment to the investment process\nStrong analytical, writing and oral communication skills\nFluent in\u00a0spoken and written Mandarin & English\nRemuneration and Benefits:\nSalary will be commensurate with qualifications and experience. Friendly culture, competitive remuneration, meal allowance, group medical and other benefits based on policy will be offered.", "employment_types": ["Full Time"], "selling_points": ["-\tInvestment Career Opportunity", "-\tBachelor Degree", "-\tGood command in English and Chinese"], "locations": ["Admiralty"], "categories": ["Banking / Finance", "Analyst", "Asset Management"], "post_time": "2022-01-17T09:05:35Z", "salary": {"currency": null, "max": null, "min": null, "period": "monthly", "term": null}, "salary_visible": false, "title_keywords": ["analyst"], "responsibilities": ["due diligence", "monitor", "procedures", "financial analysis", "executing", "liaise with"], "requirements": {"degrees": [], "majors": [], "languages": ["english", "mandarin"], "language_level": ["fluent"], "hard_skills": ["analytical skills"], "soft_skills": ["communication skills", "oral", "analytical skills"], "languages_combined": [{"language": "english", "language_level": ["fluent"]}, {"language": "mandarin", "language_level": ["fluent"]}]}, "experience_required": {"duration": ["2-5 years"], "field": ["financial markets", "analytical"]}}, {"job_id": "100003009053282", "location_code": "hk", "company": "South China Financial Holdings Limited", "job_title": "Director, Asset Management (Sole RO 9)", "description": "Please submit CV in both Chinese & English with your current and expected salary.\n\nJob Descriptions\nPerform deep-dive fundamental research and financial analysis on related companies in New Economy related sectors, such as metaverse, blockchain, EV, etc.\nFollow sector, company and macroeconomic developments in TMT industry to generate investment ideas and contribute investment recommendations to senior management\nKeep abreast of TMT industry-related development\nProvide investment ideas on TMT sectors and seek for PE stage, pre-ipo, ipo, and secondary equity market opportunities.\nConduct research framework and business models assessment, develop and maintain sector-specific databases\nProvide hands-on research support for the evaluation of potential investment opportunities/projects, as well as the existing investments\nProvide support for evaluation and execution of direct investments and equity funds on both primary and secondary markets\n\n\u00a0Requirement\n\n2-5 years of research experience covering TMT industry with a focus on New Economy sector stocks at a reputable investment bank is preferred\nPrefer solid research, quantitative and financial analysis/modeling skills\nBachelor's degree or above\nDemonstrate interest/enthusiasm and insights in New Economy-related investing\nExcellent interpersonal and communication skills with fluency in written and spoken English and Mandarin\nAttention to detail, intellectual curiosity, motivated and a team player\nCandidate with more experience with be considered as Senior Position\n\nRemuneration and Benefits:\nSalary will be commensurate with qualifications and experience. Friendly culture, competitive remuneration, meal allowance, group medical and other benefits based on policy will be offered.", "employment_types": ["Full Time", "Permanent"], "selling_points": [], "locations": ["Central"], "categories": ["Banking / Finance", "Asset Management"], "post_time": "2022-01-17T06:40:11Z", "salary": {"currency": null, "max": null, "min": null, "period": "monthly", "term": null}, "salary_visible": false, "title_keywords": ["director", "asset management"], "responsibilities": ["provide support", "ideas", "develop", "financial analysis", "maintain", "research support", "databases", "evaluation", "senior management", "conduct research"], "requirements": {"degrees": ["degree or above", "bachelor"], "majors": [], "languages": ["english", "mandarin"], "language_level": ["fluency", "excellent"], "hard_skills": ["financial analysis", "focus"], "soft_skills": ["communication skills", "motivated", "team player", "attention to detail", "focus", "interpersonal"], "languages_combined": [{"language": "english", "language_level": ["fluency", "excellent"]}, {"language": "mandarin", "language_level": ["fluency", "excellent"]}]}, "experience_required": {"duration": ["2-5 years"], "field": ["research", "investment bank"]}}, {"job_id": "100003009053504", "location_code": "hk", "company": "Ping An of China Asset Management (HK) Co., Ltd.", "job_title": "Intern (Institutional Business Development Department)", "description": "\u5d17\u4f4d\u8077\u8cac\uff1a\n\n\u5efa\u7acb\u548c\u8655\u7406\u516c\u53f8\u65e5\u5e38\u6cd5\u5f8b\u4e8b\u52d9\u5de5\u4f5c\u3001\u696d\u52d9\u5408\u898f\u6027\u5de5\u4f5c\u4ee5\u53ca\u5176\u4ed6\u76f8\u95dc\u5185\u63a7\u5236\u5ea6\uff1b\n\u8ca0\u8cac\u516c\u53f8\u5408\u540c\u7ba1\u7406\uff1a\u8d77\u8349\u3001\u5be9\u6838\u5404\u985e\u6cd5\u5f8b\u6587\u66f8/\u5408\u540c\uff0c\u4fdd\u8b49\u5408\u540c\u7684\u5408\u6cd5\u6027\uff1b\n\u70ba\u516c\u53f8\u6c7a\u7b56\u548c\u5404\u9805\u91d1\u878d\u696d\u52d9\u63d0\u4f9b\u6cd5\u5f8b\u53ef\u884c\u6027\u3001\u5408\u6cd5\u6027\u53ca\u98a8\u96aa\u65b9\u9762\u7684\u5206\u6790\uff1b\n\u8ca0\u8cac\u5167\u90e8\u6cd5\u5f8b\u77e5\u8b58\u57f9\u8a13\uff1b\n\u5354\u52a9\u4e0d\u540c\u90e8\u9580\u3001\u5916\u90e8\u5f8b\u5e2b\u6240\u53ca\u653f\u5e9c\u6709\u95dc\u90e8\u9580\u7684\u6e9d\u901a\u5408\u4f5c\uff1b\n\u6838\u8b49\u516c\u53f8\u8cc7\u8cea\u6a94\u53ca\u76f8\u95dc\u4eba\u58eb\u8eab\u4efd\u8b49\u4ef6\u526f\u672c\uff1b\n\u5176\u4ed6\u4e0a\u7d1a\u4ea4\u8fa6\u7684\u5de5\u4f5c\u3002\n\n\u4efb\u8077\u8981\u6c42\uff1a\n\n\u719f\u6089\u4e2d\u6e2f\u7d93\u6fdf\u91d1\u878d\u9818\u57df\u3001\u5982\u9999\u6e2f\u516c\u53f8\u6cd5\u3001\u8b49\u5238\u53ca\u671f\u8ca8\u689d\u4f8b\u7b49\uff1b\n\u64c1\u6709\u9999\u6e2f\u57f7\u696d\u5f8b\u5e2b(\u4e8b\u52d9\u5f8b\u5e2b)\u8cc7\u683c\uff1b\n\u81f3\u5c11\u4e00\u5e74\u5f8b\u5e2b\u6240\u6216\u516c\u53f8\u6cd5\u52d9\u5de5\u4f5c\u7d93\u9a57\uff1b\n\u6d41\u5229\u7684\u4e2d\u6587(\u5305\u62ec\u7cb5\u8a9e\u53ca\u666e\u901a\u8a71)\u3001\u82f1\u6587\u8b80\u89e3\u3001\u66f8\u5beb\u53ca\u53e3\u8a9e\u80fd\u529b\uff0c\u80fd\u5920\u8d77\u8349\u3001\u5be9\u6838\u4e2d\u82f1\u6587\u5408\u540c\uff1b\n\u5177\u6709\u5718\u968a\u5408\u4f5c\u7cbe\u795e\u548c\u7368\u7acb\u5de5\u4f5c\u3002\n\n\nResponsibilities:\n\nEstablish and handle the daily operation of legal, compliance and other relevant internal procedures/ policies;\nDraft, review, and approve different official letters/ agreements to ensure the legality;\nProvide professional consultation for management regarding legal, compliance and risk control affairs;\nAssisting in internal legal trainings;\nLiaise with internal departments or external stakeholders when necessary;\nProvide attestation services (CTC) for documents\nAssist in any ad hoc duties delegated.\n\nRequirements:\n\nSound knowledge about economics, financial products, and other relevant compliance rules, e.g. Securities and Futures Ordinance;\nQualified as solicitor.\nAt least 1 year working experience from reputable law firms or\u00a0in-house roles ;\nStrong reading, writing and oral ability in English and Chinese (Putonghua and Cantonese), able to draft and review legal documents in Chinese and English;\nSense of teamwork and work independently.", "employment_types": ["Part Time", "Internship"], "selling_points": ["Mandarin is a must", "Able to work at least 2 days per week", "Solid knowledge of MS office"], "locations": ["Central"], "categories": ["Banking / Finance", "Asset Management"], "post_time": "2022-01-17T07:04:25Z", "salary": {"currency": null, "max": null, "min": null, "period": "hourly", "term": null}, "salary_visible": false, "title_keywords": ["intern"], "responsibilities": ["ad hoc duties", "management", "control", "policies", "review", "compliance", "daily operation", "procedures", "letters", "liaise with"], "requirements": {"degrees": [], "majors": [], "languages": ["cantonese", "putonghua", "english", "chinese"], "language_level": [], "hard_skills": ["securities and futures ordinance"], "soft_skills": ["oral", "teamwork", "work independently"], "languages_combined": [{"language": "cantonese", "language_level": []}, {"language": "putonghua", "language_level": []}, {"language": "english", "language_level": []}, {"language": "chinese", "language_level": []}]}, "experience_required": {"duration": ["at least 1 year"], "field": []}}, {"job_id": "100003009053378", "location_code": "hk", "company": "Hang Seng Bank Ltd", "job_title": "Head of Data", "description": "Hang Seng Indexes Company Ltd\n\nHang Seng Indexes Company Limited (\u2018Hang Seng Indexes Company\u2019) manages and compiles the Hang Seng Family of Indexes, which cover stocks listed in Hong Kong and Mainland China. Our index series includes the Hang Seng Index, the Hang Seng China Enterprises Index and the Hang Seng TECH Index, as well as Stock Connect, Greater Bay Area and sector-related indexes. As at the end of 2020, assets under management in products passively tracking indexes in the Hang Seng Family of Indexes had reached a total of about US$38 billion.\n\nHang Seng Indexes Company is a wholly owned subsidiary of Hang Seng Bank. Our company is a team of professionals who strives for delivering quality, efficient and world-class index complier services to customers and financial institutions around the world.\n\nWe are currently seeking a high caliber professional to join our department as\u00a0Head of Data.\n\n\nPrincipal responsibilities\n\nCollaborate with business stakeholders to align the data strategy with business strategy;\nUplift the data driven culture and data maturity for the organization, Promote data as an asset;\nDefine and Own the data roadmap that creates a best-in-class data and analytic capability which enable identification of new products and market opportunities to drive innovation;\u00a0\nEstablish and execute the mechanism of data governance (Data standard, Single source of Truth and Data quality assurance);\nOversee the Team for data BAU operation that empowers Hang Seng Indexes with trusted data;\nEstablish Proactive Data Quality Management and Data Quality Monitoring solution;\nEnhance data accessibility across the teams to stand up the self-service model;\nChair Data Steering Committee to drive the strategic discussion for the future state of the firm\u2019s data capability\n\nRequirements\n\nUniversity degree or above in Information System, Finance, Business Admin, or a related discipline;\n15+ years\u2019 experience, preferably with financial data management background;\nSound understanding of Data Lake, Master Data Management technology landscape, processes and design principles;\nSound understanding of financial data (Equity market data) from data vendors (eg. Bloomberg, Refinitiv, Factset, WIND);\nStrong Experience in Data Governance, establishing and enforcing data operating model and standardized operating procedure; with no less than 7 years of experience in managing data warehouse on Cloud and performing data cleansing;\nDemonstrated knowledge in using cloud, data management platforms and tools, e.g. GCP, AWS, AI/ML, Collibra and other data management utilities etc.;\nExperiences on data dictionary, business glossary, data catalog and data quality solutions is preferred;\nStrong project management and business analysis experience with excellent problem solving and interpersonal skill;\nAcute communicator with proven track record in influencing senior stakeholders;\nProven team coaching and expansion experience;\nProficiency in Python, Tableau a plus\nProficiency in both English and Chinese\nGreat sense of ownership and servicing mindset to ensure efficient and effective customer service processes\n\nIf you would like to explore other opportunities at Hang Seng Hong Kong, please visit www.hangseng.com/careers/ for details.\n\nThe health and safety of our employees and candidates is very important to us. Due to the current situation related to the Novel Coronavirus (2019-nCoV), we\u2019re leveraging our digital capabilities to ensure we can continue to recruit top talent at the HSBC Group. As your application progresses, you may be asked to use one of our digital tools to help you through your recruitment journey. If so, one of our Resourcing colleagues will explain how our video-interviewing technology will be used throughout the recruitment process and will be on hand to answer any questions you might have.\n\nAll information provided by applicants will be used only for recruitment purposes and will be used strictly in accordance with the Bank's personal data policies, a copy of which may be obtained by the applicant upon request. Unless otherwise instructed in writing by the applicant concerned, applicants may be considered for other suitable positions within the Bank and its related companies. The personal data of unsuccessful job applicants may be retained for a maximum of two years from the date when the job application is rejected and such data may be retained for a longer period if there is a subsisting reason that obliges the Bank to do so, after which the personal data will be destroyed.", "employment_types": ["Full Time", "Permanent"], "selling_points": [], "locations": ["Not Specified"], "categories": ["Banking / Finance", "Others", "Others", "Others", "Asset Management"], "post_time": "2022-01-17T06:53:26Z", "salary": {"currency": null, "max": null, "min": null, "period": "monthly", "term": null}, "salary_visible": false, "title_keywords": [], "responsibilities": ["collaborate with", "management", "data", "monitoring", "quality", "teams"], "requirements": {"degrees": ["degree or above", "master"], "majors": ["finance", "business", "design"], "languages": ["english", "chinese"], "language_level": ["proficiency"], "hard_skills": ["no", "plus", "data management", "bloomberg", "ai", "data warehouse", "analysis", "information system", "tableau", "aws", "ml", "project management", "problem solving", "reason", "python"], "soft_skills": ["efficient", "novel", "interpersonal skill", "problem solving", "project management", "customer service", "communicator"], "languages_combined": [{"language": "english", "language_level": ["proficiency"]}, {"language": "chinese", "language_level": ["proficiency"]}]}, "experience_required": {"duration": ["7 years", "15+ years"], "field": ["management", "project management", "business", "team", "business analysis", "financial"]}}, {"job_id": "100003009049305", "location_code": "hk", "company": "Be Myjob Company Limited", "job_title": "Head of Fund Operations ( Primary Market + Secondary Market )", "description": "Responsibilities :\n\nManaging the team to ensure daily fund operations performing\nVerifying/confirming the correctness of fund NAV which is calculated by the fund service provider (e.g. fund administration team of Custodian Bank) for equity funds, fixed income, private fund, and discretionary accounts.\nManaging the team to perform good operations support for Private Equity and Structured Finance product\nWork closely with Prime Brokers, Executing Brokers, Custodian Bank, and other service providers\nMaintaining accuracy and on-time fund valuation reconciliation & settlement\nAssist in custodian and brokerage trading accounting opening\nRequirement :\n\nDegree Holder in Accounting, Finance or any related disciplines\nCandidates with CPA qualifications will be an advantage\n8 years of experience in Fund Operations support\nFluent in English and proficient in Mandarin", "employment_types": ["Full Time"], "selling_points": ["Attractive Package + 8 Months Bonus", "Asset Management", "PE Fund + Hedge Fund"], "locations": ["Wan Chai"], "categories": ["Banking / Finance", "Asset Management"], "post_time": "2022-01-14T08:24:41Z", "salary": {"currency": null, "max": null, "min": null, "period": "monthly", "term": null}, "salary_visible": false, "title_keywords": ["operations"], "responsibilities": ["valuation", "prime brokers", "maintaining", "operations", "brokerage", "executing", "administration"], "requirements": {"degrees": ["degree holder"], "majors": ["related disciplines", "finance", "accounting"], "languages": ["english", "mandarin"], "language_level": ["proficient", "fluent"], "hard_skills": ["cpa"], "soft_skills": [], "languages_combined": [{"language": "english", "language_level": ["fluent", "proficient"]}, {"language": "mandarin", "language_level": []}]}, "experience_required": {"duration": ["8 years"], "field": []}}, {"job_id": "100003009053897", "location_code": "hk", "company": "Hang Seng Bank Ltd", "job_title": "Senior Treasury Solution Dealer II", "description": "Global Banking and Markets \u2013 Global Markets\n\nHang Seng's Global Markets business provides superior service, fully integrated solutions and 24-hour global markets coverage. Our support framework is substantial. Our advanced technologies deliver quick access to key markets. Our capital strength allows us to tailor competitively-priced solutions for specific client business around the world. We provide a full spectrum of treasury services to our customers, including foreign exchange, interest rate risk management, derivatives products, capital markets instruments, as well as market intelligence on global trends and key developments.\n\nWe are currently seeking a high caliber professional to join our department as\u00a0Senior Treasury Solution Dealer II.\n\u00a0\u00a0\n\nPrincipal responsibilities\n\nServe and provide treasury solutions / products to the Bank\u2019s client with focus on corporate clients;\nIndentify sales opportunities or initiatives that address clients\u2019 need;\nMaintain business relationships with clients in assigned area of responsibility;\nSupport the Head of Treasury Solution on business initiatives;\nCollaborate with internal stakeholders, including Relationship Managers and other product groups to maximise cross-selling opportunities for the Bank;\nDealing of treasury vanilla products and structure derivatives\nRequirements\nUniversity degree holder;\nMinimum of five\u00a0years\u2019 working experience as treasury sales with strong connection of corporate clients;\nStrong treasury product knowledge especially in FX and interest rate derivatives;\nStrong communication and interpersonal skills;\nCreative, with growth mindset and highly adaptable to changes and transformation;\nProficiency in both English and Chinese, fluency in Putonghua an advantage;\nHigh level of customer centricity mindset with dedication to deliver exceptional quality services for customers\n\nIf you would like to explore other opportunities at Hang Seng Hong Kong, please\u00a0visit\u00a0www.hangseng.com/careers/\u00a0for details.\n\nThe health and safety of our employees and candidates is very important to us. Due to the current situation related to the Novel Coronavirus (2019-nCoV), we\u2019re leveraging our digital capabilities to ensure we can continue to recruit top talent at the HSBC Group. \u00a0As your application progresses, you may be asked to use one of our digital tools to help you through your recruitment journey.\u00a0 If so, one of our Resourcing colleagues will explain how our video-interviewing technology will be used throughout the recruitment process and will be on hand to answer any questions you might have.\u00a0\n\nAll information provided by applicants will be used only for recruitment purposes and will be used strictly in accordance with the Bank's personal data policies, a copy of which may be obtained by the applicant upon request. Unless otherwise instructed in writing by the applicant concerned, applicants may be considered for other suitable positions within the Bank and its related companies. The personal data of unsuccessful job applicants may be retained for a maximum of two years from the date when the job application is rejected and such data may be retained for a longer period if there is a subsisting reason that obliges the Bank to do so, after which the personal data will be destroyed.", "employment_types": ["Full Time", "Permanent"], "selling_points": [], "locations": ["Not Specified"], "categories": ["Banking / Finance", "Treasury", "Asset Management"], "post_time": "2022-01-17T07:43:05Z", "salary": {"currency": null, "max": null, "min": null, "period": "monthly", "term": null}, "salary_visible": false, "title_keywords": ["dealer"], "responsibilities": ["business initiatives", "maintain", "collaborate with"], "requirements": {"degrees": ["university degree"], "majors": [], "languages": ["putonghua", "english", "chinese"], "language_level": ["fluency", "advantage", "proficiency"], "hard_skills": ["reason"], "soft_skills": ["adaptable", "novel", "communication and interpersonal skills", "creative"], "languages_combined": [{"language": "putonghua", "language_level": ["fluency"]}, {"language": "english", "language_level": ["proficiency", "fluency", "advantage"]}, {"language": "chinese", "language_level": ["proficiency", "fluency", "advantage"]}]}, "experience_required": {"duration": ["minimum of five years"], "field": []}}, {"job_id": "100003009053694", "location_code": "hk", "company": "", "job_title": "Customer service manager", "description": "Discover New Possibilities at FinStyle Family Office\u00a0\n\nFinStyle Family Office is a place that provide comprehensive training and excellent career development opportunities.\n\nWe are an integrated platform that we deliver bespoke wealth preservation solutions and all around investment, asset management and risk protection for families.\n\nWant a dynamic career with a difference? Come and join us!\n\n\n\n\u00a0Core responsibilities:\u00a0\n\nlAble to provide market insights, investment opportunities in the corresponding market\n\nlProvide professional financial service to every individual client for their purposes of wealth management, retirement plan and investment\n\nlManage relationships with individual clients and corporate accounts\n\n\nWe are offer:\n\nlClient Base provided\u00a0\n\nlQuarterly Bonus and Year End Bonus\n\nlInitial training and On-Job training provided\n\nlTransparent Career Path to Management Level\n\nlLife and Medical Insurance\n\n\n\nWe offer attractive benefits packages and excellent career development opportunities.\u00a0\nApply now by send\u00a0sending your updated resume to us .\u00a0\nPlease mention your expected salary and the earliest availability in the resume.", "employment_types": ["Full Time", "Permanent", "Contract"], "selling_points": ["25k-50k", "21 days annual leave", "5 days work"], "locations": ["Tsim Sha Tsui"], "categories": ["Admin & HR", "Administration / Operation Manager", "Sales, CS & Business Devpt", "Business Development", "Banking / Finance", "Asset Management"], "post_time": "2022-01-17T07:21:54Z", "salary": {"currency": null, "max": null, "min": null, "period": "monthly", "term": null}, "salary_visible": false, "title_keywords": ["customer service manager"], "responsibilities": ["asset management", "career development"], "requirements": {"degrees": [], "majors": [], "languages": [], "language_level": [], "hard_skills": [], "soft_skills": ["comprehensive"], "languages_combined": []}, "experience_required": {"duration": [], "field": []}}, {"job_id": "100003009051176", "location_code": "hk", "company": "Cheuk Hang Growth", "job_title": "Fund Management Intern / Assistant / Trainee", "description": "Job Description\n\nOur clients are leading financial institutions in Hong Kong. They are currently looking for who interest in Finance to join their investment team as:\n\nResponsibilities:\n\nTo provide tailor-made financial advices to clients\nTo monitor & analyze clients\u2019 investment portfolio\nTo maintain good relationship with clients\n\nRequirements:\n\nUniversity graduate in any discipline\u00a0\nWilling to work with others\nExcellent interpersonal, communications and presentation skills\nAggressive, self-motivated, passionate for better career development\n\n\n\nBenefits:\n\n5 days work\nOn job training\nTraining allowance\nMedical Insurance, competitive salary and attractive bonus\n\nHK residents will only be considered.\nPersonal data will be used for recruitment purpose only.", "employment_types": ["Full Time"], "selling_points": [], "locations": ["Central & Western Area"], "categories": ["Banking / Finance", "Private Banking", "Management", "Management Trainee", "Asset Management"], "post_time": "2022-01-15T04:05:34Z", "salary": {"currency": "HKD", "max": 24999, "min": 20000, "period": "monthly", "term": null}, "salary_visible": true, "title_keywords": ["trainee", "assistant", "intern"], "responsibilities": ["monitor", "maintain good relationship"], "requirements": {"degrees": ["university graduate"], "majors": [], "languages": [], "language_level": [], "hard_skills": [], "soft_skills": ["passionate", "presentation skills", "interpersonal", "self-motivated"], "languages_combined": []}, "experience_required": {"duration": [], "field": []}}, {"job_id": "100003009044189", "location_code": "hk", "company": "Trinity Search Limited", "job_title": "Investment Analyst \u2013 Real Estate Private Equity", "description": "Key Responsibilities\n\nLiaise with investment managers, fund administrators and any other related parties in relation to trading activity as required for transaction and NAV preparation and controls\nSupport calculation of capital call/distribution and preparation of correspondence in accordance with the legal documents of the funds and discretionary accounts\nDeal with invoicing and payment process, collection of receivables, and maintain books and records\nSupport fund valuation and review, ensure transaction are properly recorded in valuations process\nProvide ongoing support in financial and regulatory reporting and filing to ensure compliance with regulatory requirements\nPerform cash & security reconciliations and projections\nHandle annual audits and regulatory filings\nPerform other job-related duties and special projects as required\n\nKey Requirements\n\nDegree holder, with a major in accounting or finance or related discipline, qualified accountant/professional qualifications\nMinimum 5 years\u2019 experience in fund accounting, preferably in regulated asset management firm\nSound knowledge of SFC regulations and familiar with products and operations of fund management\nTeam spirit combined with the ability to work autonomously and pro-actively\nExcellent communication and interpersonal skills, and well organized\nGood command of written and spoken English and Mandarin", "employment_types": ["Full Time"], "selling_points": ["Real Estate Private Equity", "Excellent Deal Flow and Pipeline", "Strong Financial Modelling Skills Required"], "locations": ["Not Specified"], "categories": ["Accounting", "Financial Analyst", "Property / Real Estate", "Property Consultancy", "Banking / Finance", "Asset Management"], "post_time": "2022-01-13T03:20:40Z", "salary": {"currency": null, "max": null, "min": null, "period": "monthly", "term": null}, "salary_visible": false, "title_keywords": ["analyst"], "responsibilities": ["valuation", "reporting", "regulatory requirements", "review", "ensure compliance", "invoicing", "reconciliations", "audits", "maintain", "payment process", "liaise with"], "requirements": {"degrees": ["degree holder"], "majors": ["finance", "accounting"], "languages": ["english", "mandarin"], "language_level": ["good command"], "hard_skills": ["professional qualifications"], "soft_skills": ["team spirit", "well organized", "communication and interpersonal skills"], "languages_combined": [{"language": "english", "language_level": ["good command"]}, {"language": "mandarin", "language_level": ["good command"]}]}, "experience_required": {"duration": ["minimum 5 years"], "field": ["accounting", "asset management"]}}, {"job_id": "100003009047512", "location_code": "hk", "company": "Jinluo Securities Limited", "job_title": "Responsible Officer 1", "description": "Job Highlights\nFormulate and update the operations procedure\nParticipate in investment products launch\nConduct investment research and analysis\nJob Description\n\nResponsibilities\n\nAct as Responsible Officer for SFC Type 1\u00a0\nFormulate, review and update the operations procedures\nParticipate in investment products launch\nDeliver investment performances according to established risk and return targets of each portfolio\nConduct investment research and analysis\nConduct fund management and periodic review of investment portfolio\nMonitor daily asset management business operations to ensure the workflow is complied with the relevant rules and regulations\nAssist senior management on the Firm\u2019s investment function\n\nRequirements\n\nMust be a current SFC Type 1 Responsible Officer License holder.\u00a0 \u00a0\nMinimum 3 years of trading experience in HK and US stocks is required\nAt least 3~5 years relevant fund management working experience\nUnderstanding of settlement of Hong Kong and US stocks\nFamiliar with portfolio construction and performance measurement\nStrong business sense and in-depth knowledge of the asset management industry\nProactive, good interpersonal skill and able to work under pressure\nFluent in speaking and writing skills in both English and Chinese languages.", "employment_types": ["Full Time", "Part Time"], "selling_points": [], "locations": ["Central"], "categories": ["Banking / Finance", "Asset Management"], "post_time": "2022-01-14T03:21:40Z", "salary": {"currency": null, "max": null, "min": null, "period": "monthly", "term": null}, "salary_visible": false, "title_keywords": ["responsible officer"], "responsibilities": ["regulations", "management", "operations", "analysis", "review", "procedures", "monitor", "senior management", "asset management"], "requirements": {"degrees": [], "majors": [], "languages": ["english", "chinese"], "language_level": ["fluent"], "hard_skills": ["writing skills"], "soft_skills": ["responsible", "business sense", "writing skills", "interpersonal skill", "proactive", "work under pressure"], "languages_combined": [{"language": "english", "language_level": ["fluent"]}, {"language": "chinese", "language_level": ["fluent"]}]}, "experience_required": {"duration": ["at least 3~5 years", "minimum 3 years"], "field": ["management", "trading"]}}, {"job_id": "100003009051427", "location_code": "hk", "company": "ACT Company", "job_title": "Young\u300aCEO\u300bTraining Program x Trainee 15K - 25K", "description": "\u500b\u500b\u90fd\u60f3\u5165\u5927\u516c\u53f8/\u5927\u6a5f\u69cb\u505a\uff0c\u4f46\u70ba\u4ec0\u9ebc\u8981\u8acb\u4f60\uff1f\n\u4f60\u61c2\u92b7\u552e\uff1f\u4f60\u61c2\u7ba1\u7406\uff1f\u4f60\u6709\u7d93\u9a57\uff1f\u4f60\u6709\u4eba\u8108\uff1f\n\u5982\u679c\u6c92\u6709\uff0c\u7b2c\u4e00\u6b65\u61c9\u5f9e\u4f4e\u505a\u8d77\uff01\n\n\u4f60\u4e00\u4efd\u9858\u610f\u6bd4\u4f60\u53bb\u5b78\u7fd2\uff0c\u53bb\u70ba\u4f60\u589e\u503c\uff0c\u70ba\u4f60\u524d\u9014\u53bb\u92ea\u8def\u7684\u5de5\uff01\n\u6216\u4e00\u500b\u53ef\u4ee5\u4ee4\u4f60\u505a\u4e00\u8f29\u7684\u884c\u696d\uff01\n\n\u70ba\u4e86\u57f9\u80b2\u65b0\u4eba\uff0c\u70ba\u4f60\u5011\u5efa\u7acb\u6700\u597d\u7684CV \uff0c\u5982\u4f60\u5408\u9069\u5c07\u6703\u5f97\u5230\u4ee5\u4e0bBenefit \uff1a\n\n\n\u6bcf\u6708\u6708\u85aa\uff1aHKD15,000 \u6d25\u8cbc\u8d77\u6b65\n\u76ee\u6a19\uff1a1\u5e74\u5167\u52a9\u65b0\u540c\u4e8b\u9054\u5230\u5206\u7d44\u7d93\u7406\n\u81ea\u4e3b\u81ea\u7531\u7684\u5de5\u4f5c\uff0c\u8a2d30\u65e5\u5927\u5047\n\u8868\u73fe\u826f\u597d\uff0c\u516c\u53f8\u6703\u6709\u6bcf\u6708Bonus\u00a0\n\u8a2d\u7279\u5feb\u6649\u5347\uff0c\u9810\u671f3\u5e74\u6649\u5347\u70ba\u5206\u884c\u7d93\u7406(Branch Manger\uff09\u00a0\n\u5c0a\u91cd\u540c\u4e8b\uff0c\u81ea\u7531\u767c\u5c55\u4e8b\u696d\u53bb\u5411/\u5b78\u7fd2\u7a7a\u9593\n\u5c08\u696d\u4e0a\u5802\u5b78\u7fd2\u57f9\u8a13\uff1a 1)\u9ad8\u7aef\u91d1\u878d\u77e5\u8b58 2) \u5546\u696d\u79ae\u5100 3)\u91ab\u5b78\u77e5\u8b58 4) \u4fe1\u8a175)\u5b78\u7fd2\u5982\u4f55\u5e6b\u5bcc\u4eba\u8cc7\u7522\u7ba1\u7406 / \u8cc7\u7522\u5206\u914d / \u6295\u8cc7\u77e5\u8b58/\u00a0\u92b7\u552e\u6280\u5de7\n\u4e0a\u53f81 \u5c0d 1 \u5de5\u4f5c\u57f9\u8a13\uff0c\u9577\u671f\u5de5\u4f5c\u5354\u52a9\n\u6bcf\u6708\u5b63\u4e00\u6b21Team Building \uff08\u884c\u5c71/BBQ/\u72fc\u4eba\u6bba\uff09\u00a0\n\n\u5de5\u4f5c\u7bc4\u7587\uff1a\n\n\u5b9a\u7279\u5de5\u4f5c\u6642\u9593Mon - Fri 830 am - 11:45 am\u00a0\nReview \u5ba2\u6236\u6295\u8cc7\u7d44\u5408 / \u4ecb\u7d39\u6295\u8cc7\u5e73\u53f0\n\u5354\u52a9\u968a\u54e1\u8ddf\u9032\u6bcf\u65e5\u9032\u5ea6\n\u63d0\u4f9b\u57f9\u8a13\uff0c\u52a0\u5f37\u968a\u54e1\u92b7\u552e\u80fd\u529b\uff0c\u7522\u54c1\u77e5\u8b58\n\n\u798f\u5229\uff1a\n\n\u6700\u9ad849% commission rate\u00a0\u00a0\n\u63d0\u4f9b\u843d\u5be6\u65b9\u6cd5\u3001\u6307\u5f15\u3001\u8cc7\u6e90\u3002\n\u53e6\u4eab\u8c50\u539a\u4f63\u91d1\uff0c\u6bcf\u6708\u734e\u91d1\u53ca\u5e74\u5c3e\u82b1\u7d05\n\u4e0d\u5b9a\u6642\u6709\u61c9\u5fb5\u8005\u63d0\u4f9b\uff0c\u9577\u9060\u5efa\u7acb\u88ab\u52d5\u6536\u5165\n\u5718\u968a\u6709Cold Market\u00a0\u63fe\u5ba2\u7cfb\u7d71\u4f5c\u652f\u63f4\n\u5c08\u5c6c\u5168\u65b9\u4f4d\u6709\u6548\u57f9\u8a13\n\u5728\u8077\u92b7\u552e\u53ca\u7522\u54c1\u57f9\u8a13\n\u4e0d\u8a2d\u4efb\u4f55\u696d\u7e3e\u58d3\u529b\n\u89c0\u5858\u7532\u7d1a\u5546\u5834\u5beb\u5b57\u6a13\u5de5\u4f5c\n\u5730\u65b9\u5bec\u8eba\uff0c\u64c1\u6709\u8212\u9069\u4f11\u606f\u7a7a\u9593\n\u65c5\u884c\u734e\u8cde\uff0c\u5982\u9054\u6a19\u8005\u53ef\u4ee5\u4e00\u5e74\u53bb\u4e00\u6b21\u4e9e\u6d32\u8207\u6b50\u6d32\uff08\u6a5f\u7968\uff0b\u9152\u5e97)\u00a0\n\n\u8981\u6c42\uff1a\n\n\u4e2d\u4e94\u7562\u696d\u53ca\u4e94\u79d1\u5408\u683c\n\u6709\u5fc3\u60f3\u5728\u7406\u8ca1\u884c\u696d\u8a8d\u771f\u767c\u5c55\u7684\u4eba \uff0c\u4e0d\u6703\u534a\u9014\u800c\u5ee2\n\u6709\u826f\u597d\u7684\u4eba\u969b\u95dc\u4fc2\uff0c\u597d\u52d5\uff0c\u6709\u5275\u610f\uff0c\u611b\u8207\u4eba\u4ea4\u969b\n\u611b\u6e9d\u901a\uff0c\u4e3b\u52d5\uff0c\u6562\u65bc\u63a5\u53d7\u6311\u6230\n\u7d93\u9a57\u4e0d\u62d8\uff0c\u7562\u696d\u5927\u5b78\u751f\u70ba\u4e3b\n\n*******\u6709\u610f\u8005\u8acb\u7acb\u523b\u9ede\u64caApply Now\u4ee5\u5b89\u6392\u9762\u8a66\u00a0**********", "employment_types": ["Full Time", "Part Time", "Permanent", "Temporary", "Contract", "Internship", "Freelance"], "selling_points": ["\u6b61\u8fce\u6562\u640f\u3001\u5e74\u8f15\u3001\u6709\u6d3b\u529b\u7684\u5e74\u8f15\u4eba\u52a0\u5165", "\u7528\u5fc3\u5be6\u8e10\u5c08\u696d\uff0c\u4ee5\u611b\u6210\u5c31\u4eba\u751f", "\u6642\u9593\u81ea\u4e3b\uff0c\u62db\u52df\u6210\u5c31\u4e8b\u696d\uff01"], "locations": ["Kwun Tong"], "categories": ["Others", "Student / Fresh Graduate / No Experience", "Sales, CS & Business Devpt", "Direct Sales", "Banking / Finance", "Asset Management"], "post_time": "2022-01-15T16:21:40Z", "salary": {"currency": "HKD", "max": 29999, "min": 17000, "period": "monthly", "term": null}, "salary_visible": true, "title_keywords": ["trainee"], "responsibilities": ["review"], "requirements": {"degrees": [], "majors": [], "languages": [], "language_level": [], "hard_skills": [], "soft_skills": [], "languages_combined": []}, "experience_required": {"duration": [], "field": []}}, {"job_id": "100003009048694", "location_code": "hk", "company": "Henderson Land Development Company Limited", "job_title": "MANAGER - ASSET MANAGEMENT", "description": "Ref. No.: JDB/HLD22/MAM-PLD\n\u00a0Responsibilities:\n\nConsolidating revenue and expenses of leasing portfolio against budgets set\nMonitoring the leasing portfolio and reviewing asset positioning to maximize usage of resources\nPreparing periodic business plans, asset management reports to management for review\nDeveloping financial and operational assumptions\nPreparing financial model analysis for leasing portfolio\nAnalyzing financial information, industry data and economic statistics, developing financial models and preparing research reports\n\nRequirements:\n\nACCA / HKICPA, Chartered Financial Analyst (CFA) or equivalent\nMinimum 5 years\u2019 commercial real estate analysis / asset management experience with an emphasis on retail properties, preferably gained from real estate industry\nProficiency in consolidating accounts and well versed in using Excel for financial modeling\nStrong analytical, interpersonal, presentation and leadership skills\nGood command of written & spoken English and Chinese (including Putonghua)\nCandidates with less experience will be considered for the post of Assistant Manager\nAttractive salary and fringe benefits will be offered to the successful candidates. Please apply with full resume, including CURRENT and EXPECTED salary by mail to\u00a0Human Resources Department, Henderson Land Development Co. Ltd., 71/F, Two International Finance Centre, 8 Finance Street, Central, Hong Kong\u00a0or by fax at\u00a02905 1855\u00a0or visit our homepage at\u00a0http://www.hld.com\u00a0or\u00a0by clicking \"Apply Now\".\n(Please quote the ref. no. on letter)\nPersonal data provided by job applicants will be used for recruitment purpose only.", "employment_types": ["Full Time", "Permanent"], "selling_points": ["Medical Allowance", "Education Allowance", "Free Lunch"], "locations": ["Central"], "categories": ["Accounting", "Others", "Property / Real Estate", "Others", "Banking / Finance", "Asset Management"], "post_time": "2022-01-14T07:03:29Z", "salary": {"currency": null, "max": null, "min": null, "period": "monthly", "term": null}, "salary_visible": false, "title_keywords": ["manager", "asset management"], "responsibilities": ["budgets", "management", "data", "financial models", "analysis", "monitoring", "expenses", "review", "business plans", "developing", "reports", "asset management"], "requirements": {"degrees": [], "majors": [], "languages": ["putonghua", "english", "chinese"], "language_level": ["good command"], "hard_skills": ["chartered financial analyst", "acca", "excel", "cfa", "analysis", "hkicpa"], "soft_skills": ["leadership skills", "presentation", "interpersonal"], "languages_combined": [{"language": "putonghua", "language_level": ["good command"]}, {"language": "english", "language_level": ["good command"]}, {"language": "chinese", "language_level": ["good command"]}]}, "experience_required": {"duration": ["minimum 5 years"], "field": ["commercial", "retail", "asset management"]}}, {"job_id": "100003009050611", "location_code": "hk", "company": "Safe Investment Company Limited", "job_title": "Risk Associate", "description": "Responsibilities\n\nOverseeing, coordinating and taking the lead role in providing compliance and market risk advice and support to the investment teams on various day to day matters;\nDeveloping and maintaining various programs to ensure adherence to investment mandate and risk control policies;\nEnsure achievement of all requirements for risk and compliance reporting and escalation of risks as required;\nEnsure adherence to risk management frameworks through effective implementation of a consistent enterprise risk and control management regime across the company;\nBuilding strong relationships with portfolio managers to have risk discussions and facilitate risk management framework implementation including:- promoting awareness of risk and risk management best practices, and as needed, working with and advising portfolio managers in developing effective mitigation steps and controls, analyzing and reporting firm level risk themes, risk levels and focus action items.\n\nRequirement\n\nMaster or above with good school/academic records;\nWorking experience in financial industry would be an advantage;\nA good team player with good communication and interpersonal skill;\nStrong analytical minds with solid execution skills;\nExcellent command of written and spoken English and Putonghua;\nPossess of programing skills of at least one of following: SQL, Python, R, C, C#;\nFresh graduate will also be considered.\n\nWe offer an attractive remuneration with excellent opportunities to the right candidate. Interested parties please apply with detailed resume. (All personal information received will be kept in strictly confidential and only for recruitment purpose only.)", "employment_types": ["Full Time"], "selling_points": [], "locations": ["Central"], "categories": ["Banking / Finance", "Investment", "Risk Management", "Asset Management"], "post_time": "2022-01-14T10:56:18Z", "salary": {"currency": null, "max": null, "min": null, "period": "monthly", "term": null}, "salary_visible": false, "title_keywords": ["associate"], "responsibilities": ["reporting", "control", "management", "maintaining", "policies", "ensure adherence", "compliance", "teams", "developing", "implementation"], "requirements": {"degrees": ["fresh graduate", "master"], "majors": [], "languages": ["putonghua", "english"], "language_level": ["excellent"], "hard_skills": ["sql", "c", "python", "r", "c#"], "soft_skills": ["communication", "good team player", "interpersonal skill"], "languages_combined": [{"language": "putonghua", "language_level": ["excellent"]}, {"language": "english", "language_level": ["excellent"]}]}, "experience_required": {"duration": [], "field": ["financial industry"]}}, {"job_id": "100003009049142", "location_code": "hk", "company": "Conners Consulting Limited", "job_title": "Team Head, Investment Analysis & Product Development ***Attractive Package**", "description": "Our client, a well-known MPF Trustee in Hong Kong, is hiring Senior Manager, Investment Analysis & Product Development to join the group.\n\nResponsibilities:\n\nSelect, analyze and monitor the performance of fund managers for both MPF and ORSO\nPrepare Performance reports, marketing materials and presentations for acquiring new business / regular meeting and publications\nCollaborate\u00a0with marketing functions (including the conduct of presentations and product promotion and project management)\nKeep abreast of market update and conduct research and analysis on macroeconomic trends and other issues in global economics and / or funds & pension investments\nProvide training to teammates and frontline sales staff and produce monthly investment house view to be used at client presentations\nTake lead in developing and implementing investment products / services, investor education programmes / materials\n\nRequirements:\n\nUniversity graduate in Investment / Finance / Economics\u00a0\u00a0\nAt least 8-10 years of experience in fund management or wealth management industry\u00a0\u00a0\nGood knowledge in financial markets and pension products is preferable\nHolder of MPFI License and HKSFC License (Type 4) is highly desirable\nCFA / CFP finalist is highly preferable\nExperience in using financial data providers has an advantage\nStrong presentation and people management skills\nGood product development and management skills\nExcellent command of written, spoken and presentation skill in English and Chinese\nSelf-driven and strong problem solving skills\n\nTo apply, please send your detailed resume to eppie[at]connersconsulting[dot]com or contact Ms. Eppie Lee at 3997 3928 for a confidential discussion.\u00a0\n\nOnly shortlisted candidates will be notified.\u00a0\n\nApplicants who are not contacted within two weeks may consider their applications unsuccessful.\n\nAll data collected will be used for recruitment purpose only & will be used strictly confidential.\n\nConners Consulting Limited\n\n2005 Kai Tak Commercial Building 317 Des Voeux Road Central Hong Kong\n\nTel: (852) 3996 8090\u00a0\u00a0\u00a0\u00a0\u00a0\u00a0\u00a0\u00a0\n\nWebsite:\u00a0http://www.connersconsulting.com/", "employment_types": ["Full Time", "Permanent"], "selling_points": ["8 yrs exp in fund management or wealth management", "CFA with strong investment knowledge", "Attractive Package"], "locations": ["Sheung Wan"], "categories": ["Banking / Finance", "Investment", "Fund Management", "Asset Management"], "post_time": "2022-01-15T03:50:07Z", "salary": {"currency": null, "max": null, "min": null, "period": "monthly", "term": null}, "salary_visible": false, "title_keywords": ["product development"], "responsibilities": ["collaborate with", "provide training", "mpf", "performance reports", "analysis", "developing", "presentations", "project management", "monitor the performance", "marketing materials", "conduct research"], "requirements": {"degrees": ["university graduate"], "majors": ["finance", "economics"], "languages": ["english", "chinese"], "language_level": ["excellent"], "hard_skills": ["presentation skill", "cfa", "problem solving skills", "hksfc"], "soft_skills": ["presentation skill", "presentation", "problem solving skills", "driven", "detailed"], "languages_combined": [{"language": "english", "language_level": ["excellent"]}, {"language": "chinese", "language_level": ["excellent"]}]}, "experience_required": {"duration": ["at least 8-10 years"], "field": ["management", "financial"]}}, {"job_id": "100003009045910", "location_code": "hk", "company": "Inspire Executive Limited", "job_title": "Equity Portfolio Manager-Leading Chinese Financial Group", "description": "Our client is a leading Chinese financial group, now they are looking for an Equity PM to join their firm.\n\nResponsibilities\n\nPortfolio construction and risk management of equity portfolio\nTo conduct investment research for equity investments including both A/H and US Shares\nTo establish portfolio allocation criteria and process\n\nRequirements:\n\nBachelor Degree above of any discipline, with 5 or more years working experience,\u00a0with independent\u00a0equity portfolio management experience (3+ years).\nExcellent quantitative, analytical and communication skills, able to work well under pressure and tight deadlines, and have the aptitude to synthesize large amounts of information and develop innovative solutions\nMandarin and English is a must", "employment_types": ["Full Time"], "selling_points": ["Portfolio Manager", "Equity Investment", "5+ Years Experience"], "locations": ["Central & Western Area"], "categories": ["Banking / Finance", "Asset Management"], "post_time": "2022-01-13T09:05:08Z", "salary": {"currency": null, "max": null, "min": null, "period": "monthly", "term": null}, "salary_visible": false, "title_keywords": ["manager"], "responsibilities": ["management"], "requirements": {"degrees": ["degree", "bachelor"], "majors": [], "languages": ["english", "mandarin"], "language_level": [], "hard_skills": [], "soft_skills": ["communication skills", "innovative", "independent", "under pressure"], "languages_combined": [{"language": "english", "language_level": []}, {"language": "mandarin", "language_level": []}]}, "experience_required": {"duration": ["3+ years"], "field": ["management"]}}, {"job_id": "100003009050430", "location_code": "hk", "company": "Apex Fund Services (HK) Limited", "job_title": "Hedge Fund Administration \u2013 Supervisor", "description": "Job Description:\n\nThe successful applicant will be responsible for day-to-day operations of accounting and administration of hedge funds and will strive to be the one point contact to investment managers and funds\u2019 investors. To carry out these duties, the successful applicant will carry out and coordinate with and lead relevant support team, and to deliver timely and accurate fund administration services to our clients. This role will report to Senior Account Manager.\n\n\nResponsibilities:\n\nAssist Senior Manager and/or Manager to lead a team in HK office and oversee the work done by oversea offices\nProvide CRM client relationship management\u00a0\nEnsure that necessary controls are in place and adhered to in order to provide complete, accurate and timely fund administration services to our clients.\nEnsure all deliverables are delivered to our clients as per service level agreement.\nAssist in pre-launch phase of new client fund vehicles; launching of new fund and review operational procedure. Review net asset value calculation for the fund on a monthly, weekly or daily basis as per engagement requirements\nReview and process subscription and redemption activity in a timely manner\nReview financial statements and liaise with auditors to ensure timely completion of audits\nMonitor accuracy of fund expenses (management fee, performance fee etc.).\nReview portfolio of investment position and ensure independent pricing.\nKnowledge of financial products.\nReview funds\u2019 share registry dealing orders and ensure all are processed in high accuracy and timely manner.\nPerform AML checks for investors.\nImplement FATCA and CRS programme to ensure client funds\u2019 compliance with regulatory requirements.\nReview, manage and liaise with auditors for audits of client funds.\n\n\u00a0Requirements:\n\nUniversity degree in Accounting, Finance or a related discipline\nProfessional qualified accountant,\nMinimum 3 years of work experience in fund administration\nGood communications, interpersonal and problem solving skills\nExcellent verbal and written communication skills \u2013 Cantonese, English and Mandarin.\nFlexibility and ability to multi-task\nProficient in the use of Microsoft Excel and Microsoft Word\nKnowledge in PAXUS is an advantage\nCandidate with less working experience may be considered as Supervisor, Fund Administration\n\nTo be successful in this role it is envisaged you are a motivated and self-driven individual eager to contribute and grow with the organization.\u00a0\u00a0\n\nWe offer a modern and progressive work environment, and offer a path towards future career growth.\u00a0Interested parties please send your full resume\u00a0with your expected salary and availability by clicking \"Apply Now\" below.\n\n\nPersonal data provided by job applicants will be used for recruitment purposes only and will be treated in strictly confidential.\u00a0", "employment_types": ["Full Time", "Permanent"], "selling_points": [], "locations": ["Central & Western Area"], "categories": ["Banking / Finance", "Financial Services", "Fund Management", "Asset Management"], "post_time": "2022-01-14T10:24:13Z", "salary": {"currency": null, "max": null, "min": null, "period": "monthly", "term": null}, "salary_visible": false, "title_keywords": ["supervisor"], "responsibilities": ["administration", "management", "aml", "regulatory requirements", "review", "coordinate with", "day-to-day operations", "a timely manner", "financial statements", "audits", "lead a team", "monitor", "expenses", "compliance", "contact", "liaise with", "report"], "requirements": {"degrees": ["university degree"], "majors": ["finance", "accounting"], "languages": ["cantonese", "english", "mandarin"], "language_level": ["excellent"], "hard_skills": ["problem solving skills", "microsoft word", "microsoft excel"], "soft_skills": ["communication skills", "multi-task", "driven", "motivated", "problem solving skills", "interpersonal"], "languages_combined": [{"language": "cantonese", "language_level": ["excellent"]}, {"language": "english", "language_level": ["excellent"]}, {"language": "mandarin", "language_level": ["excellent"]}]}, "experience_required": {"duration": ["minimum 3 years"], "field": ["administration"]}}, {"job_id": "100003009051468", "location_code": "hk", "company": "Zext intelligence Limited", "job_title": "Graduate Trainee Program (20K+, Finance)", "description": "The Employer:\n\nOur client is one of the major financial institution in Hong Kong. They are aggressive and innovative, and fast growing.\u00a0 They would like to expand the market share by investing their resources on the right talents.\n\nThe Role and Responsibilities:\n\nComprehensive on-the-job training regarding professional investment and asset management expertise.\nPreparing investment portfolio and global market analysis.\nTo develop investment strategies to achieve client\u2019s short-term and long-term financial objectives.\nOn going manage client\u2019s portfolios according to client\u2019s financial goals.\nPreparing different scheme of investment proposal and portfolio review report.\nIdentify client objectives and offer appropriate financial consultancy.\n\nRequirements:\n\nBachelor degree holder or above in all disciplines\nInitiative, sincere and a good team player\nProficiency in Chinese and English\nGood communication and interpersonal skills\nArticulate and detail oriented, ability to multitask in a fast paced environment.\u00a0\n\n\n\nWe offer a competitive salary and benefits package and the professional advantages of a dynamic environment that supports your development and recognizes your achievements.\n\nInterested individuals please send your detailed resume and expected salary by clicking\u00a0\"Apply Now\". Only candidates who are authorized to work in Hong Kong will be considered.\n\nAll personal data provided will only be used for recruitment purpose only.\nInformation of candidates not selected will be destroyed in 3 months.", "employment_types": ["Full Time", "Permanent"], "selling_points": ["on the job training, continuous studying subsidy", "portfolio/ asset management experience is a plus", "To be a future leader"], "locations": ["Quarry Bay"], "categories": ["Marketing / Public Relations", "Others", "Management", "Management Trainee", "Banking / Finance", "Asset Management"], "post_time": "2022-01-16T03:20:07Z", "salary": {"currency": null, "max": null, "min": null, "period": "monthly", "term": null}, "salary_visible": false, "title_keywords": ["graduate trainee"], "responsibilities": ["investment strategies", "preparing investment portfolio", "global market analysis", "develop", "investment proposal", "portfolio review report", "manage client\u2019s portfolios", "asset management"], "requirements": {"degrees": ["bachelor degree holder"], "majors": [], "languages": ["english", "chinese"], "language_level": ["proficiency"], "hard_skills": ["dynamic"], "soft_skills": ["good team player", "dynamic environment", "sincere", "detail oriented", "communication and interpersonal skills", "articulate", "ability to multitask", "initiative", "detailed"], "languages_combined": [{"language": "english", "language_level": ["proficiency"]}, {"language": "chinese", "language_level": ["proficiency"]}]}, "experience_required": {"duration": [], "field": []}}, {"job_id": "100003009043985", "location_code": "hk", "company": "Avenue Family Office Limited", "job_title": "Graduate Trainee (For 2021 graduates) / Full-time Intern (For 2022 graduates)", "description": "Responsibilities\n\nPractice on asset management, project, research, operation and analysis skills\nWork with colleagues in different departments\nLiaise with professional counterparties and execute deals\nDeal with ad hoc tasks as assigned by supervisors\nRequirements\n\nDegree Holder graduated from\u00a0the world's Top 100 universities\u00a0\nPossess less than 1 year working experience, Fresh Graduates are welcomed\nDetermined to advance in asset and fund management\nExcellent in analytical and critical thinking\nStrong in communications skills (spoken & written) in both English & Chinese\nBe a good team player, proactive and highly motivated\nPositive and can-do attitude\nDetailed mind, committed and willing to work in a fast pace environment and excited to learn new things\nProficient in Microsoft Office applications\n\nAVENUE is an Equal Opportunity Employer. We respect and seek to empower each individual and support the diverse cultures, perspectives, skills and experiences within our workforce. Personal data provided by job applicants will be used strictly in accordance with the employer\u2019s personal data policies, a copy of which will be provided immediately upon request.\n", "employment_types": ["Full Time", "Permanent"], "selling_points": ["A young team with happy & relaxing working culture", "Fast learner and keen to develop career in Finance", "Comprehensive exposure to Fund, Bond, Equity, etc."], "locations": ["Central"], "categories": ["Banking / Finance", "Private Banking", "Fund Management", "Asset Management"], "post_time": "2022-01-13T02:40:59Z", "salary": {"currency": null, "max": null, "min": null, "period": "monthly", "term": null}, "salary_visible": false, "title_keywords": ["graduate trainee", "intern"], "responsibilities": ["liaise with", "analysis", "ad hoc tasks", "asset management"], "requirements": {"degrees": ["degree holder"], "majors": [], "languages": ["english", "chinese"], "language_level": [], "hard_skills": ["microsoft office"], "soft_skills": ["good team player", "determined", "can-do attitude", "committed", "diverse", "motivated", "proactive", "detailed mind", "positive"], "languages_combined": [{"language": "english", "language_level": []}, {"language": "chinese", "language_level": []}]}, "experience_required": {"duration": ["1 year"], "field": []}}, {"job_id": "100003009043689", "location_code": "hk", "company": "A-Jex Investment Limited", "job_title": "Managing Director / Executive Director - Asset Management", "description": "Responsibilities\nAccording to the company's strategy, develop and implement business plans address the potential threats and opportunities.\nOverall management of asset management, mainly fixed income, including full responsibility of the P&L and operations.\nServe as RO\u00a0of SFC Type 1,\u00a04, and 9 activities.\u00a0Lead a small investment team and develop investment strategies,\u00a0including fixed incomed, project financing, LBO, private equity, PIPE, etc.\nExplore investment opportunities in fixed income areas, such as public bond, structured products, as well as private products.\nMonitor the managers\u2019 portfolio risks, participate in risk policies formulation and execution.\nCommunicate with stakeholders and outside parties in facilitating from sourcing to closing deal.\nAd hoc assignments as assigned.\n\nRequirement\n\nMaster Degree holder or above in Finance, Economics, MBA or related discipline.\nOver 12 years solid experience in fix income, project financing, LBO, private equity, PIPE with at least 8 years\u2019 managerial experience.\u00a0Excellent track record\u00a0is an advantage.\u00a0\nExperience in a Chinese firm is highly preferred. Experience in Wealth Management in preferred.\nResponsible Officer without conditions of SFC Type 9 activities is required. Responsible Officer of\u00a0SFC Type 1, 4 activities\u00a0is preferred.\nStrong leadership, flexible team player equipped with excellent communication, presentation, problem solving, negotiation and analytical skills.\nProactive, result-oriented, can-do attitude and ability to work in a start-up entity.\nExcellent command of written and spoken English and Chinese. Fluency in Mandarin is a must and essential for this role.\nWe offer competitive remuneration package & benefits to the right candidate. Interested parties please send your English & Chinese\u00a0Resume\u00a0with availability, current and expected salary to to us by clicking Apply Now.\u00a0Personal data will be used for recruitment purpose only.", "employment_types": ["Full Time", "Permanent"], "selling_points": ["Responsible Officer of 1, 4, 9", "Fixed Income, Asset Management", "Rapid Growing Chinese Investment Firm"], "locations": ["Wan Chai"], "categories": ["Banking / Finance", "Financial Services", "Wealth Management", "Asset Management"], "post_time": "2022-01-13T01:30:35Z", "salary": {"currency": null, "max": null, "min": null, "period": "monthly", "term": null}, "salary_visible": false, "title_keywords": ["executive director", "director", "asset management"], "responsibilities": ["communicate with", "management", "investment strategies", "operations", "policies", "monitor", "p&l", "business plans", "develop", "ad hoc assignments", "asset management"], "requirements": {"degrees": ["master degree"], "majors": ["finance", "economics"], "languages": ["english", "chinese", "mandarin"], "language_level": ["fluency", "excellent"], "hard_skills": ["problem solving", "private equity", "analytical skills"], "soft_skills": ["flexible", "result-oriented", "negotiation", "responsible", "can-do attitude", "analytical skills", "communication", "problem solving", "team player", "proactive", "leadership", "presentation"], "languages_combined": [{"language": "english", "language_level": ["excellent"]}, {"language": "chinese", "language_level": ["excellent"]}, {"language": "mandarin", "language_level": ["fluency"]}]}, "experience_required": {"duration": ["at least 8 years", "12 years"], "field": ["managerial", "management", "financing"]}}, {"job_id": "100003009046121", "location_code": "hk", "company": "Guotai Junan International Holdings Limited", "job_title": "Fund Operation Analyst, Asset Management", "description": "Ref: SAFS/AM/140122DB/223\n\nResponsibilities\n\nDevelop and identify potential clients, build and maintain strong relationship with institutional clients, family offices and retail channels, schedule and arrange conference calls, clients meeting, roadshows and investor events\nMaintain excellent clients relationship, handle client communication and queries in a professional manner\nHandle all product evaluation processes and distribution marketing including RFP, DDQ and pitch books, etc.\nWork closely with team to serve clients and provide solution to a broad range of investment-related need, prepare and execute client on-boarding with the operations team\nProvide regular reporting to the Group and Headquarter to support the business on a timely manner\n\nRequirements\n\n\nBachelor's Degree or above with SFC licenses 1, 4 & 9\n3-5 years of sales experience with proven sales record\nStrong knowledge in funds, investment products and asset management\nHighly self-motivated, responsible and good team player\nExceptional attention to detail, multiple-task capability\nGood interpersonal, presentation and communication skills\nFluent in both written and verbal English and Mandarin. Cantonese is desirable\n\nWe offer a competitive remuneration package to the right candidate. If you are interested in the post, please send your resume together with your present and expected salaries by clicking \u201cApply Now\u201d.\u00a0\n\n\nFor more information about China Everbright Securities International Company Limited, please visit www.ebshk.com.\n\n\n\nWe are an equal opportunity employer and welcome applications from all qualified candidates. All applications will be treated in the strictest confidence. Personal data provided will be used for recruitment purposes only. The job applicant will assume all or any risks arising out of or in connection with the job application transmission process prior to our actual receipt of the same including but not limited to accidental or unauthorized loss or disclosure of personal information, to which we will not be responsible in any way.\n\nUnder the Personal Data (Privacy) Ordinance, you may request access to, and / or correction of your personal data in relation to your application. If you wish to do so, please email to us.", "employment_types": ["Full Time", "Permanent"], "selling_points": ["Support daily operation duties for all asset types", "Process operational activity in accounting system", "Immediately Available is highly preferred"], "locations": ["Central & Western Area"], "categories": ["Banking / Finance", "Dealing & Trading", "Order Processing & Operation / Settlement", "Asset Management"], "post_time": "2022-01-13T09:39:55Z", "salary": {"currency": null, "max": null, "min": null, "period": "monthly", "term": null}, "salary_visible": false, "title_keywords": ["analyst", "asset management"], "responsibilities": ["reporting", "operations", "professional manner", "a timely manner", "develop", "communication", "maintain", "schedule", "evaluation"], "requirements": {"degrees": ["degree or above", "bachelor"], "majors": [], "languages": ["cantonese", "english", "mandarin"], "language_level": ["fluent"], "hard_skills": ["investment products"], "soft_skills": ["communication skills", "good team player", "self-motivated", "responsible", "presentation", "attention to detail", "interpersonal"], "languages_combined": [{"language": "cantonese", "language_level": []}, {"language": "english", "language_level": ["fluent"]}, {"language": "mandarin", "language_level": ["fluent"]}]}, "experience_required": {"duration": ["3-5 years"], "field": []}}, {"job_id": "100003009047132", "location_code": "hk", "company": "JPMorgan Chase Bank, N.A.", "job_title": "Asset Management, Client Platform & Controls, Vice President", "description": "Team Background - Client Platform & Controls\n\nThe Client Platform & Controls team is dedicated to support business development of the APAC Client Services team. Our vision is to deliver industry-leading client service, support growth and change in a seamless manner, add value and efficiency to drive business results. The successful candidate will be partnering with an extensive network of stakeholders across front offices and supporting functions to deliver innovative solutions to business problems and maintain a robust control framework for Client Services team.\n\nKey Responsibilities\n\nBusiness Management\n\nSource and analyze regional data including Client Services activities, resource utilization and issue trend\nPrepare metrics, dashboards and business representations for management\nSupport thematic business data analysis for management\nIdentify process inefficiency and formulate problem statements with Client Services data and feedback\nCollaborate with stakeholders to design solutions to business problems\nRisk & Controls\n\nAssist analysis on critical issues, identify control gaps and drive execution of remediation\nDesign controls and facilitate procedure uplift to address business change and control requirement\nConduct periodic control testing on Client Services processes, procedures and documentation\nArrange trainings for awareness to emerging risks, process deficiencies and remediation\nMain liaison for audit requests and compliance testing\nProjects & Coordination\n\nFacilitate prioritization, budget and benefit tracking of strategic projects\nPartner with Technology and stakeholders to support projects for process improvement and digitalization\nPartner with Legal, Compliance and stakeholders to assess client impact on regulatory change\nQualifications\n\nUnderstanding of business and project management functions in Asset Management and/or related financial services industries\nAbility to work independently and comfortable with ambiguity and dynamically shifting priorities, strict timelines, and demands\nStrong analytic capabilities, confident in solving complex operational challenges with sound control acumen; ability to articulate and address critical risks and issues\nHighly accurate with attention to details\nProficiency in MS Excel, Powerpoint and Visio; knowledge on data analytical tools would be an advantage\nExcellent command in both spoken and written English and Cantonese. Fluency in Mandarin preferred\nWe recognize that our people are our strength and the diverse talents they bring to our global workforce are directly linked to our success. We are an equal opportunity employer and place a high value on diversity and inclusion at our company. We do not discriminate on the basis of any protected attribute, including race, religion, color, national origin, gender, sexual orientation, gender identity, gender expression, age, marital or veteran status, pregnancy or disability, or any other basis protected under applicable law. In accordance with applicable law, we make reasonable accommodations for applicants' and employees' religious practices and beliefs, as well as any mental health or physical disability needs.\n\nInterested parties please click \u201cApply Now\u201d to apply job.\n\nAll applications applied through our system will be delivered directly to the advertiser and privacy of personal data of the applicant will be ensured with security.", "employment_types": ["Full Time"], "selling_points": [], "locations": ["Not Specified"], "categories": ["Banking / Finance", "Others", "Management", "General Management", "Asset Management"], "post_time": "2022-01-14T02:25:01Z", "salary": {"currency": null, "max": null, "min": null, "period": "monthly", "term": null}, "salary_visible": false, "title_keywords": ["vice president", "asset management"], "responsibilities": ["collaborate with", "data", "design solutions", "budget", "audit", "design", "maintain", "support projects", "control", "compliance", "testing", "management", "procedures", "data analysis", "documentation", "tracking", "analysis", "project management", "coordination", "asset management"], "requirements": {"degrees": [], "majors": [], "languages": ["cantonese", "english", "mandarin"], "language_level": ["fluency", "excellent"], "hard_skills": ["business management", "analysis", "powerpoint", "project management", "ms excel", "make", "documentation", "acumen"], "soft_skills": ["confident", "work independently", "accurate", "robust", "project management", "diverse", "coordination", "attention to details", "articulate", "innovative", "extensive"], "languages_combined": [{"language": "cantonese", "language_level": ["excellent"]}, {"language": "english", "language_level": ["excellent"]}, {"language": "mandarin", "language_level": ["fluency"]}]}, "experience_required": {"duration": [], "field": []}}, {"job_id": "100003009047050", "location_code": "hk", "company": "HANSEL INTERNATIONAL Executive Search Limited", "job_title": "Head of Middle Office, Asset Management", "description": "Our client is the asset management arm of a Chinese investment bank listed on HK stock exchange. They are looking for a Head of Middle Office to lead their internal control, investment risk management, & compliance functions, details are as follow:\n\nResponsibilities:\n\n\nImplement and review internal control procedures to ensure smooth operations of the Asset Management business\nMonitor investment and operational risk exposure of the fund business, design relevant mitigation measures and follow-up action plan\nReview, streamline and enhance daily processes and operations to ensure control effectiveness\nConduct quantitative analysis on portfolio risk and performance attributions, perform periodic reporting on findings\nDesign workflow and facilitate implementation of operational flows according to new or revised regulations and ordinances\nPrepare and consolidate information for internal and external parties for audit, financial and regulatory reporting, and other relevant purposes\nAs project manager for system enhancement projects\u00a0\nSupervise and train junior staffs\u00a0\n\nRequirements:\n\n8+ years of experience in risk management, operational control, and middle office support. Worked in reputable asset management firms and fund houses\nWorking knowledge in SFO requirements relevant to Asset Management business\nCFA/FRM/CPA Holder is a plus\u00a0\nStrong communication skills, enjoys working with other teams to achieve results together.\nSpeaking and writing in Mandarin Chinese is a must, fluency in English is preferred.\nFor interested candidate please send us your CV with current and expected salary.\u00a0 All personal information collected will be strictly used for recruitment purpose only.\u00a0", "employment_types": ["Full Time", "Permanent"], "selling_points": ["Risk & Internal Control, Asset Management", "At least 8 years of experience, management role", "Operational risk & investment risk management"], "locations": ["Central"], "categories": ["Banking / Finance", "Others", "Risk Management", "Asset Management"], "post_time": "2022-01-14T02:10:45Z", "salary": {"currency": null, "max": null, "min": null, "period": "monthly", "term": null}, "salary_visible": false, "title_keywords": ["asset management"], "responsibilities": ["regulations", "reporting", "control", "operations", "analysis", "review", "procedures", "monitor", "design", "implementation", "internal and external parties", "audit", "ensure smooth operations", "plan", "enhancement projects", "internal control", "asset management"], "requirements": {"degrees": [], "majors": [], "languages": ["mandarin chinese", "english"], "language_level": ["fluency"], "hard_skills": ["plus", "cfa", "cpa", "sfo", "frm"], "soft_skills": ["communication skills"], "languages_combined": [{"language": "mandarin chinese", "language_level": []}, {"language": "english", "language_level": ["fluency"]}]}, "experience_required": {"duration": ["8+ years"], "field": ["risk management"]}}, {"job_id": "100003009050832", "location_code": "hk", "company": "Bank of Communications Trustee Limited", "job_title": "Manager / Senior Officer - Private Trust Administration", "description": "Responsibilities\nLead a small team effectively for preparing trust documents and handle daily trust administration\nResponsible for the preparation and documentation of trust establishment and transfer\nHandle all related trust documents including trust deeds, letter of wishes and board resolutions\nPerform annual review on trust and meet up clients to understand their needs and expectation and changes of their status\nLiaise with both internal and external stakeholders such as banks, lawyers, accountants, all partners and investment managers or advisors regarding distribution, management and distributions of trust assets\nPrepare and review due diligence/ KYC documents according to internal procedures\nPerform ad-hoc assignments as required\nRequirements\nDegree in Law, Accounting, business related disciplines or possess relevant professional qualifications such as TEP, CPA or ACIS are preferred\n4 year or above relevant experience in handling private trust administration work\nExcellent communication and organization skills with positive learning attitude\nGood knowledge in PC skills (MS Word, Excel and PowerPoint), Chinese typing an advantage\nProficient in both spoken and written English and Chinese (Putonghua an advantage)\nImmediately available is highly preferred\nCandidate with more experience will be considered for the senior position\n\n\nPlease click \"Apply Now\" to submit your application.\nPersonal data collected will be used for recruitment purpose only.\n\n", "employment_types": ["Full Time", "Permanent"], "selling_points": ["Responsible for the preparation and documentation", "Degree in Law, Accounting, business related", "4 year or above relevant experience"], "locations": ["Not Specified"], "categories": ["Banking / Finance", "Private Banking", "Asset Management"], "post_time": "2022-01-14T11:31:02Z", "salary": {"currency": null, "max": null, "min": null, "period": "monthly", "term": null}, "salary_visible": false, "title_keywords": ["senior officer", "manager"], "responsibilities": ["due diligence", "management", "ad-hoc assignments", "lead a small team", "review", "procedures", "liaise with", "kyc", "documentation", "administration"], "requirements": {"degrees": ["degree"], "majors": ["business", "related disciplines", "accounting", "law"], "languages": ["putonghua", "english", "chinese"], "language_level": ["advantage", "proficient", "good"], "hard_skills": ["excel", "professional qualifications", "typing", "powerpoint", "cpa", "pc skills", "ms word"], "soft_skills": ["communication", "learning", "organization skills", "positive"], "languages_combined": [{"language": "putonghua", "language_level": ["advantage"]}, {"language": "english", "language_level": ["proficient"]}, {"language": "chinese", "language_level": ["proficient", "good"]}]}, "experience_required": {"duration": ["4 year"], "field": ["relevant experience", "administration"]}}, {"job_id": "100003009043680", "location_code": "hk", "company": "Bank of China (Hong Kong) Limited", "job_title": "Contract - Middle Office", "description": "Responsibilities\nProvide trade support for fund managers including fixed income, equity and alternative investments\nSupport fund managers from pre-trade compliance monitoring, deal booking to post trade checking\nMaintenance of investment system data and update when necessary\nPrepare regular investment reports for clients\nPrepare analytical reports related to portfolio returns and statistics data for senior management\nRequirements\nUniversity graduated in Finance, Business Administration or relevant disciplines\n2+ years\u2019 experience in Middle Office or trade support\nProficiency in Excel, Bloomberg\nDetail-oriented, proactive and team player", "employment_types": ["Contract"], "selling_points": ["Middle Office", "Trade Support", "Compliance"], "locations": ["Central"], "categories": ["Banking / Finance", "Asset Management"], "post_time": "2022-01-13T01:27:52Z", "salary": {"currency": null, "max": null, "min": null, "period": "monthly", "term": null}, "salary_visible": false, "title_keywords": [], "responsibilities": ["maintenance", "data", "monitoring", "compliance", "checking", "system data", "reports", "booking", "senior management"], "requirements": {"degrees": [], "majors": [], "languages": [], "language_level": [], "hard_skills": ["excel", "bloomberg"], "soft_skills": ["team player", "proactive", "detail-oriented"], "languages_combined": []}, "experience_required": {"duration": ["2+ years"], "field": []}}, {"job_id": "100003009050588", "location_code": "hk", "company": "China Life Insurance (Overseas) Company Limited", "job_title": "Senior Accounting Officer", "description": "Responsibilities\n\nHandle daily accounting function and month end closing\nPerform inter-company reconciliation and fixed asset recording\nPrepare accurate schedules/ reports for management reporting and auditing requirements as designated by the supervisor\nParticipate in annual budgeting, monitoring and cash projecting\nDealing with auditors in both external and internal audit\nAssist in annual filing of tax return and reply tax queries from IRD\nHandle ad hoc assignments as required\n\nRequirements\n\nDegree holder in Accounting discipline\nMinimum four years of related working experience\nIndependent and\u00a0self-motivated ,with good problem solving skills and strong sense of responsibility\nAble to work under pressure and meet tight deadlines\nProficient in MS office application; familiar with Chinese word processing\nGood written and spoken English and Mandarin\nExperience in using\u00a0SAP,\u00a0SUN\u00a0or Hiportfolio system\u00a0is highly preferred\nCandidates with less relevant working experience may be considered the post of Accounting Officer", "employment_types": ["Full Time", "Permanent"], "selling_points": ["Month end closing", "Inter-co reconciliation & fixed asset recording", "Annual budgeting, monitoring and cash projecting"], "locations": ["Wan Chai"], "categories": ["Accounting", "Accountant", "Accounting Clerk / Supervisor", "Banking / Finance", "Asset Management"], "post_time": "2022-01-14T10:50:45Z", "salary": {"currency": null, "max": null, "min": null, "period": "monthly", "term": null}, "salary_visible": false, "title_keywords": ["senior accounting officer"], "responsibilities": ["tax", "month end closing", "internal audit", "schedules", "annual budgeting", "monitoring", "reports", "management reporting", "ad hoc assignments", "daily accounting", "auditing"], "requirements": {"degrees": ["degree holder"], "majors": ["accounting"], "languages": ["english", "chinese", "mandarin"], "language_level": ["good"], "hard_skills": ["problem solving skills", "chinese word processing", "sap", "ms office"], "soft_skills": ["self-motivated", "meet tight deadlines", "independent", "sense of responsibility", "problem solving skills", "work under pressure"], "languages_combined": [{"language": "english", "language_level": ["good"]}, {"language": "chinese", "language_level": []}, {"language": "mandarin", "language_level": ["good"]}]}, "experience_required": {"duration": ["minimum four years"], "field": ["related", "accounting", "relevant working experience"]}}, {"job_id": "100003009035594", "location_code": "hk", "company": "Access Investment Management (HK) Ltd", "job_title": "Analyst - Asset Management", "description": "Responsibilities\n\n\nReview global news and other sources and prepare market briefing notes with added analysis.\nCollect, organize and analyze data to support investment thesis.\nPrepare financial models and forecasts. Construct a valuation of a company.\nGenerate, write and present positive return investment ideas to pitch to senior analysts and portfolio managers.\nCoverage of either healthcare, consumer or renewables sector.\nCompile a universe of companies for benchmarking.\nUpdate databases.\n\n\u00a0Requirements\n\n\nUniversity Degree in Finance or Economics preferred. Other degrees will be considered if financial proficiency can be demonstrated.\n1-2 years of experience as an analyst in a licensed entity or family office\nHigh proficiency in spoken and written English is a must; solid command of Mandarin will be advantageous.\nPossess good analytical skills both in the qualitative and quantitative methods with the ability to appreciate macro-economic trends.\nHave an innate curiosity and an ability to be creative with your work. Be able to present complex ideas and concepts in an understandable form\nHolder of SFC\u2019s license or CFA is preferred.\u00a0\n\nOur company provide:\n\nMedical insurance (including spouse and children)\nDental insurance\nLife insurance\nPerformance bonus\nStudy leave\nBank Holiday\n\n\n\nWe offer competitive compensation package to the right candidate.\u00a0 Please click 'Apply Now' and apply with a detailed resume with current & expected salary to us.\u00a0\n\nAll applications will be treated in strictly confidential.\u00a0 Applicants who are not invited for an\u00a0interview within 2 months may consider that their applications are unsuccessful.", "employment_types": ["Full Time", "Permanent"], "selling_points": [], "locations": ["Central"], "categories": ["Banking / Finance", "Analyst", "Financial Services", "Asset Management"], "post_time": "2022-01-10T07:48:38Z", "salary": {"currency": null, "max": null, "min": null, "period": "monthly", "term": null}, "salary_visible": false, "title_keywords": ["analyst", "asset management"], "responsibilities": ["valuation", "ideas", "financial models", "analysis", "review", "databases", "analyze data"], "requirements": {"degrees": ["university degree"], "majors": ["finance", "economics"], "languages": ["english", "mandarin"], "language_level": ["proficiency"], "hard_skills": ["cfa", "macro", "analytical skills"], "soft_skills": ["creative", "analytical skills"], "languages_combined": [{"language": "english", "language_level": ["proficiency"]}, {"language": "mandarin", "language_level": []}]}, "experience_required": {"duration": ["1-2 years"], "field": []}}, {"job_id": "100003009039059", "location_code": "hk", "company": "Michael Page", "job_title": "ESG Analyst - PE Fund", "description": "This role will work closely with senior management team in the fund, conducting ESG analysis and research for portfolio companies.\n\nClient Details\n\nAsia focused Private Equity Fund\n\nDescription\n\nEmbed ESG and Impact into organisations through strategy development, ESG research and ESG policy development.\nDrive ESG initiatives in the region, including engagements with portfolio companies and global management team.\nStrengthen internal ESG capacity and enable ESG collaboration across functions and locations;\nPublish research paper of thematic research;\nCollaborate with investment team to make informed decision through ESG research\nActively engage with regulators on ESG and responsible investment related topics and themes.\n\nProfile\n\nFamiliar with ESG initiatives in the region\n4-8 years of working experience\nUnderstand corporate governance in the context of business and ESG\nFluency in English and Chinese is must\n\nJob Offer\n\nGlobal team\n\nTo apply online please click the 'Apply' button below. For a confidential discussion about this role please contact Chris Yang on +852 2848 4716", "employment_types": ["Full Time", "Permanent"], "selling_points": ["Asia-focused Buyout Fund", "ESG research and analysis", "Portfolio Management"], "locations": ["Central & Western Area"], "categories": ["Banking / Finance", "Corporate Banking", "Corporate Finance", "Asset Management"], "post_time": "2022-01-11T08:33:26Z", "salary": {"currency": null, "max": null, "min": null, "period": "monthly", "term": null}, "salary_visible": false, "title_keywords": ["analyst"], "responsibilities": ["collaborate with", "management team", "analysis", "policy development", "contact", "senior management"], "requirements": {"degrees": [], "majors": [], "languages": ["english", "chinese"], "language_level": ["fluency"], "hard_skills": ["make", "analysis", "private equity"], "soft_skills": ["focused", "responsible"], "languages_combined": [{"language": "english", "language_level": ["fluency"]}, {"language": "chinese", "language_level": ["fluency"]}]}, "experience_required": {"duration": ["4-8 years"], "field": []}}, {"job_id": "100003009051088", "location_code": "hk", "company": "Hong Kong Job Consulting", "job_title": "(Senior) Risk Manager", "description": "A full Licensed Corporation, covering RA1, 2, 4, 5 & 9, is looking for a professional Risk Manager handling risk & control function.\n\nResponsibilities:\n\nHandle risk management related issues covering securities, futures and asset management\nMeasure and monitor risks portfolios, include but not limited to investment, liquidity and counterparty risks\nReview and update on risk management policies and procedures\nEnsure the internal control policies and business activities procedures are complied with the Hong Kong laws included SFC codes and guidelines\nHandle ad-hoc projects assigned by senior management\n\nRequirements:\n\nBachelor\u2019s degree or above in Risk Management, Risk Control or Finance relevant discipline\nProfessional qualification such as CPA, CFA and FRM\n5-7 years of related working experience in risk management in financial services industry\nKnowledge and experience in handling Margin Trading related is must\nHands-on experience in risk management development\nKnowledge in fund management and financial product operations in SFC regulated activities, candidate with experience in fund companies, asset management companies, securities companies are preferred\nExcellent communication skills at both spoken and written in English and Putonghua\nCandidate with less experience will be considered as Manager\n\n\u00a0 \u00a0 Interested parties please send your resume to \"APPLY NOW\u201d\n\n\u00a0***Personal data collected will be used for recruitment purposes only***", "employment_types": ["Full Time", "Permanent"], "selling_points": ["Risk & Control of a SFC Licensed Corporation", "Monitor Risk Portfolios,such as Counterparty Risks", "Experience in Handling Margin Trading related"], "locations": ["Not Specified"], "categories": ["Banking / Finance", "Others", "Risk Management", "Asset Management"], "post_time": "2022-01-15T02:04:16Z", "salary": {"currency": null, "max": null, "min": null, "period": "monthly", "term": null}, "salary_visible": false, "title_keywords": ["manager"], "responsibilities": ["management", "guidelines", "policies", "review", "monitor", "procedures", "senior management", "ad-hoc projects", "internal control", "business activities", "asset management"], "requirements": {"degrees": ["degree or above", "bachelor"], "majors": ["finance", "risk management"], "languages": ["putonghua", "english"], "language_level": ["excellent"], "hard_skills": ["cfa", "cpa", "frm"], "soft_skills": ["communication skills", "hands-on"], "languages_combined": [{"language": "putonghua", "language_level": ["excellent"]}, {"language": "english", "language_level": ["excellent"]}]}, "experience_required": {"duration": ["5-7 years"], "field": ["risk management", "management", "related", "development", "securities", "asset management", "financial services industry", "trading", "financial"]}}, {"job_id": "100003009046312", "location_code": "hk", "company": "China Taiping Life Insurance (Hong Kong) Company Limited", "job_title": "Investment Reporting-Head / Senior Manager", "description": "Job Responsibility\n\nManage the investment system maintenance and development process, which are consist of\nInvestment report system: generate regular report to fulfill various internal and external reporting requirements.\nInvestment performance system: able to store and extract all historical performance related data for all portfolio and also the benchmark.\nInvestment risk management system: able to store and extract quantitative financial risk data and parameters.\nFundamental analysis database: able to store and extract fundamental data for various market and securities.\nMacau Investment Operation: Assisting external asset management companies and the company's internal financial department to prepare regular reports, formulate investment agreements in accordance with Macau regulatory requirements and supervise the implementation of entrusted investment guidelines\nRequirement\n\nDegree in Data Science, Computer Science, Financial Engineering, Math, Physics or other quantitative fields.\nMinimum 5 years of solid working experiences from asset management system development, IT consulting, banking or financial advisory firm.\nExcellent capability in data mining and quantitative modeling.\nIn depth knowledge of at least one mainstream programming languages such as C++/Java/Python and basic database design and SQL knowledge are desired.\nGood time management skills, independent problem-solving skills and ability to multitask and work under pressure to meet tight deadlines,.\n\n", "employment_types": ["Full Time"], "selling_points": ["Investment system reporting", "Data mining and quantitative modeling", "Attractive remuneration package"], "locations": ["North Point"], "categories": ["Banking / Finance", "Asset Management", "Information Technology (IT)", "Data Scientist"], "post_time": "2022-01-13T10:25:05Z", "salary": {"currency": null, "max": null, "min": null, "period": "monthly", "term": null}, "salary_visible": false, "title_keywords": ["senior manager"], "responsibilities": ["reporting", "management", "maintenance", "data", "guidelines", "regulatory requirements", "analysis", "implementation", "asset management", "reports", "database", "report"], "requirements": {"degrees": ["degree"], "majors": ["data science", "engineering", "physics", "computer science", "math"], "languages": [], "language_level": [], "hard_skills": ["java", "basic", "c++", "python", "sql", "programming", "data mining", "problem-solving skills", "math"], "soft_skills": ["meet tight deadlines", "independent", "time management skills", "problem-solving skills", "ability to multitask", "work under pressure"], "languages_combined": []}, "experience_required": {"duration": ["minimum 5 years"], "field": ["consulting", "financial", "system development", "it", "banking", "asset management"]}}, {"job_id": "100003009037329", "location_code": "hk", "company": "Haitong International Securities Group Limited", "job_title": "Senior Multi-Asset Strategist, Asset Management (Ref.: JDB/AM/SMAS/HC)", "description": "The Job:\n\nCreate and maintain the scorecard for tactical global multi-asset allocation framework, including both fundamental and market technical drivers\nPerform back-testing to ensure the factors provide promising predictive power for assets to deliver a statistically significant outperformance against benchmark over the defined investment horizon\nProduce the long-term capital market returns assumptions, which underpin the strategic asset allocation process\nConduct fundamental research on the global, in particular China, macroeconomic environment and generate insights on the economic trends, market developments, and cross-asset implications\nProduce routine analytics on asset allocation, macroeconomics, and core drivers of asset prices to support investment decisions\nCommunicate the market outlook and multi-asset investment views both internally and externally\nAssist business development team and portfolio manager to develop new / tailored multi-asset investment solutions and model portfolios\nWork closely with fund managers and team members on ad hoc research projects.\n\nRequirements:\n\nWe support local hire with solid relevant working experience in HK.\n\nBachelor Degree or above in finance, economics, quantitative finance, financial engineering, statistics or related majors. Advanced degree or CFA preferred\nGood understanding in the financial market and various asset classes, spanning equities, fixed income, and multi-asset solutions\nStrong statistical, analytical and financial modeling skills.\nInquisitive, organized, self-motivated, and able to work independently\nGood written, presentation, and verbal communication skills\nProficient in market data terminals (e.g. Bloomberg, Wind), and Microsoft Office applications\nProficient in both Mandarin and English\nAt least 5 to 7 years of relevant experience in multi-asset investment, asset allocation, macroeconomic or quantitative research or portfolio management role\n\nWe are committed to build a team of competence individuals who have acquired relevant local solid working experience and with diversified exposure to work together with us. Applicants who do not hear from us within 6 weeks may consider their applications unsuccessful.\n\nWe provide attractive remuneration package and fringe benefits for the right candidate.\u00a0Interested parties please send detailed resume with current and expected salaries to\u00a0Human Resources Department\u00a0i) by mail: 22/F, Li Po Chun Chambers, 189 Des Voeux Road Central, HK;\u00a0ii) by fax:2537 5431; or\u00a0iii) by using\u00a0\u201cApply Now\u201d.\n\nPlease quote the reference in the application.If application is submitted in hard copy format, it should be placed in a sealed envelope marked \u201cConfidential\u201d.\u00a0 All applications will be treated in strict confidence and personal data provided by job applications will be used for recruitment purposes only.\u00a0 A copy of our Personal Information Collection Statement will be available upon request.", "employment_types": ["Full Time", "Permanent"], "selling_points": [], "locations": ["Central"], "categories": ["Banking / Finance", "Asset Management"], "post_time": "2022-01-11T02:30:18Z", "salary": {"currency": null, "max": null, "min": null, "period": null, "term": null}, "salary_visible": false, "title_keywords": ["asset management"], "responsibilities": ["ad hoc", "research projects", "develop", "testing", "maintain"], "requirements": {"degrees": ["degree", "degree or above", "bachelor"], "majors": ["finance", "economics", "statistics", "engineering"], "languages": ["english", "mandarin"], "language_level": ["proficient"], "hard_skills": ["cfa", "bloomberg", "microsoft office"], "soft_skills": ["organized", "self-motivated", "work independently", "communication skills", "advanced", "committed", "presentation"], "languages_combined": [{"language": "english", "language_level": ["proficient"]}, {"language": "mandarin", "language_level": ["proficient"]}]}, "experience_required": {"duration": ["at least 5 to 7 years"], "field": ["management", "research", "relevant working experience", "relevant experience", "investment", "team"]}}, {"job_id": "100003009047906", "location_code": "hk", "company": "KPMG Executive Recruitment Limited", "job_title": "Financial Controller", "description": "Our client is a private investment group with a large portfolio of retail outlets and other real estate assets.\n\nKPMG is a global network of professional services firms providing Audit, Tax and Advisory services. KPMG Executive Search and Recruitment is a business unit of KPMG China and is one of the few recruitment consultancy firms in Hong Kong that is part of a large professional organisation.\u00a0 We work alongside a group of professionals and advisors who provide us with a high level of insights and awareness about a wide range of businesses and professions. We support the clients and aim to provide a pleasant working experience for the clients and candidates.\u00a0 \u00a0\n\nResponsibilities\n\nTo be responsible for all the accounting and finance functions\nDrive strategic initiatives for continuous business growth\nTake a lead role in financial planning and analysis, procurement, and investment activities\nPrepare Group consolidation, enhance consolidation process to increase efficiency and strengthen account analysis and monitoring\nAssist in financial analysis and budget tracking\nIdentify risks and ensure compliance with the rules including the preparation of annual report, interim report\nImplement finance policies and procedures, and reporting system\nWork closely with business heads on data analysis and provide financial related advice\n\nRequirements:\n\nA degree or above in Accounting or Finance or relevant discipline\nProfessional Certificate holder, e.g., CPA, ACCA etc.\nAt least 12 years in financial planning and analysis with minimum 5 years managerial experience preferably from property industry with Big 4 background\nPrevoius experience in driving business process improvement and investment analysis\nExcellent analytical skills\nGood interpersonal and communication skills\nGood command of written and spoken English and Cantonese\n\nApplications\n\nTo apply, please send your CV with expected salary to Ms. Aris Lee by clicking below \"APPLY NOW\" button or 8th\u00a0Floor, Prince\u2019s Building, 10 Chater Road, Central, Hong Kong. By submitting your application, you agree to receive communications from us and agree our Personal Information Collection Statement in the following link:\u00a0www.kpmg.com.cn/KER-opportunities\n\u00a92022 KPMG Executive Recruitment Limited, a Hong Kong limited liability company and a member firm of the KPMG network of independent member firms affiliated\u00a0", "employment_types": ["Full Time"], "selling_points": ["responsible for all accounting&finance functions", "Professional Certificate holder, e.g., CPA, ACCA", "12+years in financial planning and analysis"], "locations": ["Not Specified"], "categories": ["Banking / Finance", "Asset Management"], "post_time": "2022-01-14T04:22:33Z", "salary": {"currency": null, "max": null, "min": null, "period": "monthly", "term": null}, "salary_visible": false, "title_keywords": ["financial controller"], "responsibilities": ["reporting", "tracking", "policies", "analysis", "monitoring", "budget", "procedures", "ensure compliance", "financial analysis", "data analysis", "report", "planning"], "requirements": {"degrees": ["certificate", "degree or above"], "majors": ["finance", "accounting"], "languages": ["cantonese", "english"], "language_level": ["good command"], "hard_skills": ["cpa", "acca", "analysis", "analytical skills"], "soft_skills": ["communication skills", "independent", "interpersonal", "analytical skills"], "languages_combined": [{"language": "cantonese", "language_level": ["good command"]}, {"language": "english", "language_level": ["good command"]}]}, "experience_required": {"duration": ["at least 12 years", "minimum 5 years"], "field": ["managerial", "financial", "big 4", "business", "investment", "planning"]}}, {"job_id": "100003009045701", "location_code": "hk", "company": "Inspire Executive Limited", "job_title": "Institutional sales/Channel Sales/ETF Sales - Top Chinese-based Asset Management", "description": "Job Description\nBuild, manage, and grow our institutional and distribution team in Greater China region.\nDevelop and maintain a strong relationship with investors - private banks, family offices and HNWIs.\nEstablish local and global channels and expand our institutional customer base efficiently\nHave a clear understanding of customer needs and channel feedback to our internal teams effectively\n\n\nThe Successful Applicant\n\n\n\u00a0\u00a0\u00a0\u00a0\u00a0\u00a0\u00a0\u00a0 3+ years of experience in fund sales, distribution sales or business development or relevant experiences in financial services\n\u00a0\u00a0\u00a0\u00a0\u00a0\u00a0\u00a0\u00a0 Proven track record of developing relationships, negotiating, and problem-solving with both internal and external partners and stakeholders\n\u00a0\u00a0\u00a0\u00a0\u00a0\u00a0\u00a0\u00a0 Have existing relationships with PB, family offices, HNW, and other sophisticated investors\n\u00a0\u00a0\u00a0\u00a0\u00a0\u00a0\u00a0\u00a0 Strong interpersonal skills, self-driven and a good team player\n\u00a0\u00a0\u00a0\u00a0\u00a0\u00a0\u00a0\u00a0 Excellent command of spoken and written Chinese and English (Mandarin is a must)", "employment_types": ["Full Time"], "selling_points": ["Top 3 Chinese Asset Management", "Institutional Sales", "ETF Sales"], "locations": ["Central & Western Area"], "categories": ["Banking / Finance", "Asset Management"], "post_time": "2022-01-13T08:23:46Z", "salary": {"currency": null, "max": null, "min": null, "period": "monthly", "term": null}, "salary_visible": false, "title_keywords": ["sales", "asset management"], "responsibilities": ["maintain", "teams", "developing", "develop"], "requirements": {"degrees": [], "majors": [], "languages": ["english", "chinese", "mandarin"], "language_level": ["excellent"], "hard_skills": ["problem-solving"], "soft_skills": ["sophisticated", "good team player", "problem-solving", "clear", "interpersonal skills", "driven"], "languages_combined": [{"language": "english", "language_level": ["excellent"]}, {"language": "chinese", "language_level": ["excellent"]}, {"language": "mandarin", "language_level": ["excellent"]}]}, "experience_required": {"duration": ["3+ years"], "field": ["business development", "financial services"]}}, {"job_id": "100003009049040", "location_code": "hk", "company": "Frontier Financial Group Limited", "job_title": "Sr. Compliance Manager / Head of Compliance", "description": "Responsibilities:\n\nDevelop and implement the compliance framework to ensure company policies and regulations are met\nOversee and review all business operations relating to compliance including policies, investments, and procedures\nCommunicate applicable risks, costs, progress, and results to all relevant partners and regulators\nDesign and monitor control systems to deal with violations of legal rules and internal policies\nRegularly assess the efficiency of control systems and recommend effective improvements\nPerform periodic audits on company procedures and processes\nConduct employee training sessions on compliance issues\nProvide compliance advisory to the business\nAdvise on new product launch or revamp, relevant sale and marketing materials, training materials\nHandle inquiries from regulatory bodies and compile periodical reports for management, steer for ad hoc compliance project or investigation when required\n\nRequirements:\n\n\n\nDegree or above qualification in Business, Finance, Legal or related discipline\nAt least 8 years of solid relevant experience\nExposure to compliance monitoring and testing work or experience working regulatory bodies, consultancies or advisory firms will be an advantage\nExperience in policy and procedures development and implementation is required\nGood understanding of Hong Kong AML/ CFT\nGood spoken and written English and Chinese (including Putonghua) is required\n\nWe offer excellent remuneration package and career development to the right candidate.\u00a0 Fringe benefits include medical insurance, free lunch and 5-days work.\n\n(All personal information received will be kept in strictly confidential and only for\u00a0recruitment purpose only.)", "employment_types": ["Full Time"], "selling_points": ["Develop and implement the compliance framework", "Degree or above in Accounting, Laws or related", "Min. 8 yrs of working experience"], "locations": ["Central"], "categories": ["Banking / Finance", "Financial Services", "Professional Services", "Legal & Compliance", "Asset Management"], "post_time": "2022-01-14T07:57:50Z", "salary": {"currency": null, "max": null, "min": null, "period": "monthly", "term": null}, "salary_visible": false, "title_keywords": ["compliance manager"], "responsibilities": ["regulations", "operations", "design", "costs", "control", "ad hoc", "compliance", "monitor", "develop", "reports", "management", "review", "procedures", "investigation", "audits", "revamp", "policies", "systems", "marketing materials"], "requirements": {"degrees": ["degree or above"], "majors": ["finance", "business"], "languages": ["putonghua", "english", "chinese"], "language_level": ["good"], "hard_skills": ["cft", "aml"], "soft_skills": [], "languages_combined": [{"language": "putonghua", "language_level": ["good"]}, {"language": "english", "language_level": ["good"]}, {"language": "chinese", "language_level": ["good"]}]}, "experience_required": {"duration": ["at least 8 years"], "field": ["development", "compliance", "relevant experience", "testing"]}}, {"job_id": "100003009045044", "location_code": "hk", "company": "Robert Walters (HK)", "job_title": "Business Analyst- Back Office System", "description": "My client is looking a business analyst to participate in the back-office application replacement project. The analyst is in the implementation team focused to oversight and responsible for the implementation of the back office system, in replacement of their legacy fund account system. The team will also need to own the system (purchased package) skills for on-going support and maintenance purpose\n\nPrincipal Responsibilities:\n* Implement the back-office application replacement project.\n* Working with business users to understand their requirements\n* Ongoing application support to the daily operation, after launch.\n* Liaise with different teams, but not limited to, front office and data team, for redesigning key process flows.\n* Maintain client relationships and manage client expectations.\n* Development of test strategies, test plans, test cases and expected results with users to ensure the applications are meeting expected deliverables.\n\nTechnical Requirements:\n* Over 3 years of experience on the buy-side fund administration domain.\n* Implementation experience of back-office system within the asset management industry is a definite plus.\n* Vendor management skills and project management experience on implementation of packaged solutions is a definite plus.\n* Experience with investment accounting system including SimCorp Dimension, Portia, FIS Global, Eagle Star, HiPort, is a definite plus.\n* Strong interpersonal skills, communications and presentation skills, positive, can-do attitude, meticulous are essential.\n* Good Excel and SQL skills\n* Fluent in English, Mandarin and Cantonese", "employment_types": ["Full Time", "Permanent"], "selling_points": ["Buy side/Asset Management/Fund Mgt Experience", "Fluent in English, Mandarin and Cantonese", "Offer Double Pay Salary"], "locations": ["Not Specified"], "categories": ["Banking / Finance", "Asset Management"], "post_time": "2022-01-13T06:59:51Z", "salary": {"currency": null, "max": null, "min": null, "period": "monthly", "term": null}, "salary_visible": false, "title_keywords": ["business analyst"], "responsibilities": ["data", "teams", "daily operation", "maintain", "liaise with", "plans"], "requirements": {"degrees": [], "majors": [], "languages": ["cantonese", "english", "mandarin"], "language_level": ["fluent"], "hard_skills": ["excel", "plus", "vendor", "sql", "project management", "accounting system"], "soft_skills": ["meticulous", "can-do attitude", "project management", "presentation skills", "interpersonal skills", "positive"], "languages_combined": [{"language": "cantonese", "language_level": ["fluent"]}, {"language": "english", "language_level": ["fluent"]}, {"language": "mandarin", "language_level": ["fluent"]}]}, "experience_required": {"duration": ["3 years"], "field": ["administration", "management", "project management", "investment", "accounting", "asset management"]}}, {"job_id": "100003009046488", "location_code": "hk", "company": "Randstad Hong Kong Limited", "job_title": "Asset Management - Sales Associate", "description": "about the company.\n\nMy client is an asset management firm in Hong Kong. Due to expansion, they are looking for a sales assistant to join their team.\n\nabout the team.\n\nJoin this firm with great team culture and supportive environment to stably develop your own career and expand market share for the asset management\n\nabout the job.\n\nAs a member of the team, you will cover all aspects in\n\nAssist Head of Asset Management for identifying business opportunities of mutual fund, private equity fund or other products for corporate or financial institutional clients\nProvide support on business plan and marketing seminars and activities to develop more business opportunities\nFollow and maintain relationship with clients and provide investors' feedback to fund managers\nExecute business development plan to expand fund resources\n\nskills & experiences required.\n\nYour previous experience as client services, sales or business development in banking or asset management and familiarity with fund products will help you succeed in this role. You will have 1+ years of experience in client services or ARM. Qualifying in HKSI LE exam/ License type 9 would be an advantage. Due to the targeted client segment, you will be proficient in Mandarin and English on a daily basis.\n\nIf you're interested in this role, click 'apply now' or for more information and a confidential discussion on this role or to find out more opportunities contact Anthony Chan at +852 2232 3425 or email anthony.chan@randstad.com.hk", "employment_types": ["Full Time", "Permanent"], "selling_points": ["Asset Management - Fund", "Sales Support", "Attractive salary package"], "locations": ["Not Specified"], "categories": ["Banking / Finance", "Investment", "Fund Management", "Asset Management"], "post_time": "2022-01-13T11:54:51Z", "salary": {"currency": "HKD", "max": 19999, "min": 17000, "period": "monthly", "term": null}, "salary_visible": true, "title_keywords": ["sales associate", "asset management"], "responsibilities": ["provide support", "business opportunities", "develop", "maintain", "contact", "plan", "banking", "business plan", "asset management"], "requirements": {"degrees": [], "majors": [], "languages": ["english", "mandarin"], "language_level": ["proficient"], "hard_skills": ["private equity", "hksi"], "soft_skills": ["supportive", "interested in"], "languages_combined": [{"language": "english", "language_level": ["proficient"]}, {"language": "mandarin", "language_level": ["proficient"]}]}, "experience_required": {"duration": ["1+ years"], "field": ["business development", "asset management", "banking"]}}, {"job_id": "100003009034409", "location_code": "hk", "company": "Hip Shing Hong (Holdings) Company Limited", "job_title": "INVESTMENT ANALYST", "description": "Responsibilities:\nAssist Investment Manager on research and financial modelling\nPrepare investment proposals\nConduct portfolio valuations\nExpand market coverage and deal origination\nRequirements:\n\nBachelor\u2019s Degree in Real Estate, Surveying or related discipline\nAt least 2 year\u2019s property analyst, asset management, valuations or consultancy experience\nSelf-motivated, able to work independently\nAdvanced MS Excel and PowerPoint\nProficiency in both written and spoken English and Chinese with excellent communication skills\n\nBenefits:\u00a0\u00a0\n\nMedical insurance\nDental insurance\nDiscretionary year-end bonus\nEducation and training allowance\nPaid marriage leave & gift\nPaid emergency leave\nPaid children's birthday leave\nPaid compassionate leave\nAcademic scholarship\nWe are constantly looking for talents who are proactive and dedicated to be part of our Hip Shing Hong\u2019s family.\u00a0 If you are ready for the next challenge, please apply now!\n\nFor more information, please visit our Company's website\u00a0https://www.hshd.com.hk/en/career/.\n\nAll information provided by applicants will be treated in strict confidence and be used for recruitment purpose only.", "employment_types": ["Full Time", "Permanent"], "selling_points": ["Handle research on policies, real estate market", "Prepare investment proposals", "2 year\u2019s property analyst experiences"], "locations": ["Central"], "categories": ["Banking / Finance", "Investment", "Professional Services", "Business Analysis / Data Analysis", "Asset Management"], "post_time": "2022-01-10T03:23:07Z", "salary": {"currency": null, "max": null, "min": null, "period": "monthly", "term": null}, "salary_visible": false, "title_keywords": ["analyst"], "responsibilities": [], "requirements": {"degrees": ["degree", "bachelor"], "majors": ["surveying"], "languages": ["english", "chinese"], "language_level": ["proficiency", "excellent"], "hard_skills": ["ms excel", "powerpoint"], "soft_skills": ["communication skills", "advanced", "self-motivated", "work independently"], "languages_combined": [{"language": "english", "language_level": ["proficiency", "excellent"]}, {"language": "chinese", "language_level": ["proficiency", "excellent"]}]}, "experience_required": {"duration": ["at least 2 year"], "field": ["asset management"]}}, {"job_id": "100003009041162", "location_code": "hk", "company": "ARTA TechFin Corporation Limited", "job_title": "Operation Assistant, Asset Management", "description": "At ARTA TechFin, our vision is to transform financial services using technology. We have ambitious yet achievable goals, from transforming a local brokerage to global, from building up a China cross-border business from ground zero, and from building a One-Stop-Shop financial experience for our customers. We aim to enrich everyone\u2019s financial experience via Virtual Reality, Metaverse, Blockchain Technology and many more. Things we dream one day can happen, ARTA TechFin will make it happen.\n\nARTA TechFin is constantly in the look-out for like-minded exceptional talents to come on this exciting journey with us. If this sounds exciting for you, read on\u2026\n\nTODAY, we are actively looking for a skilled and experienced Operation Assistant \u2013 Asset Management to support the rapidly growing and changing business.\n\nThis position is awaiting a candidate who possesses good knowledge in Asset Management, keen to explore and learn. The right talent will support the team and assist in back-office tasks.\n\nInsights from the top\n\nAre you the \u201cExceptional\u201d talent for this position?\n\nWell, if you\u2026\n\nLove Asset Management. You will take the initiative to get involved in product development projects and support the team to achieve amazing result. You desire to explore the knowledge of Fund of Funds, Private Equity, Private Credit, etc. You love it so much that you will always try to find optimal solutions, drive necessary changes and even go beyond the unimaginable.\n\nYou Love to be Challenged. You respect processes but it\u2019s also why you don\u2019t like corporate structure. You want to be part of a start-up that is nimble but stable, innovative but not too risky, you want to be the change driver, to contribute and not just follow the standards and copy what everyone else is doing.\n\nYou Love to Influence Others. You want to make a difference. You understand that everyone has their desires and needs, but you also believe that in order to make things happen, excellent relationship building and stakeholder management are essential.\n\nYou Love Learning New Things (especially in Technology). If you don\u2019t know it, you wanna learn it. Part of your time, you love to research new tech and driving forward your knowledge, always moving to figure things out and improve your experience.\n\nYou Love Challenges and Able to Balance Lots of Concerns. ARTA TechFin is an advanced innovation hub, like any innovation, you will encounter lots of challenges, hicks ups, unpredictable problems, etc\u2026 You have to love the roller coaster experience with the rapidly changing ecosystem of the technological world. You are able to effectively manage your time. You can balance a lot of demands and requests without getting overwhelmed and keep to ball rolling. At the end of the day, we are a startup.\n\nExciting things that you will be involved in\u2026\n\nOpportunity to participate in product development projects related to AI, blockchain, cloud, data and ESG in the long run.\nSupport the Asset Management team to set up new products.\nAssist in daily reconciliations, trade matching, booking, NAV valuation, and license applications.\nParticipate in Portfolio Management System and Risk Management System implementation.\nPrepare product development documents and filing.\nArrange internal and external meetings and relevant documentation.\nAd hoc duties as assigned by the team leaders.\n\nHow will you be qualified?\n\nPassionate about applying technology in financial services industry.\nBachelor\u2019s Degree in Business, Economics, Finance or related disciplines.\nKnowledge in financial market and instruments such as equities, fixed income, derivatives and structured investments.\nUnderstanding of Hong Kong SFC regulatory requirements is an advantage.\nFluent in both English and Chinese.\nStrong engagement at work and a team player.\n\nStill believe you have got what it takes to be part of the transformation?\n\nStop thinking, just ACT.\n\nWe offer competitive salary package to the successful candidate. If you are interested in joining this exceptional opportunity, please apply by sending your resume with expected salary.\n\nAll information provided by applicants will be used for recruitment purposes only. Information of unsuccessful applicants will be destroyed within 24 months of receipt.", "employment_types": ["Full Time", "Permanent"], "selling_points": ["Opportunity to participate in TechFin project", "Support the Asset Management team", "Participate PMS and RMS implementation"], "locations": ["Wan Chai"], "categories": ["Banking / Finance", "Analyst", "Fund Management", "Asset Management"], "post_time": "2022-01-12T03:32:32Z", "salary": {"currency": null, "max": null, "min": null, "period": "monthly", "term": null}, "salary_visible": false, "title_keywords": ["operation assistant", "asset management"], "responsibilities": ["ad hoc duties", "valuation", "management", "data", "brokerage", "regulatory requirements", "implementation", "reconciliations", "booking", "documentation", "license applications", "support the team", "asset management"], "requirements": {"degrees": ["degree", "bachelor"], "majors": ["finance", "economics", "related disciplines", "business"], "languages": ["english", "chinese"], "language_level": ["fluent"], "hard_skills": ["blockchain", "documentation", "ai", "make", "system implementation", "go", "private equity"], "soft_skills": ["advanced", "keen", "learning", "team player", "structured", "stable", "innovative", "initiative", "passionate about"], "languages_combined": [{"language": "english", "language_level": ["fluent"]}, {"language": "chinese", "language_level": ["fluent"]}]}, "experience_required": {"duration": [], "field": ["research", "brokerage", "tech", "business", "financial"]}}, {"job_id": "100003009043972", "location_code": "hk", "company": "Osmium Consulting Group Limited", "job_title": "Fixed Income Trader", "description": "Reporting to the Fund Manager, you will:\n\nBe responsible for fixed income and equity trading for funds and client accounts\nWork as part of the investment team to provide real-time market colour, identify investment opportunities, and implement effective trades to derive profits\nAssist in the portfolio management of funds and client accounts\nAssist in client marketing and day to day client communication\nMaintain and develop new trading instruments and other relevant products to enhance investment returns\n\nRequirements:\n\n3 - 5 years of relevant trading experience in fixed income or equity\nPrefer degree in business, finance or any similar field;\nFamiliar with the fixed income and equity markets ecosystem\nSolid understanding of investment products, trading strategies and risk management\nAbility to work accurately under stress;\nFast learner, proactive and quick reaction to market changes\nFluent in English and Mandarin", "employment_types": ["Full Time", "Permanent"], "selling_points": ["Fixed Income Trader", "Buy-side FI", "SFC License Type 9"], "locations": ["Central & Western Area"], "categories": ["Banking / Finance", "Dealing & Trading", "Equities / Capital Markets", "Asset Management"], "post_time": "2022-01-13T02:38:15Z", "salary": {"currency": null, "max": null, "min": null, "period": "monthly", "term": null}, "salary_visible": false, "title_keywords": [], "responsibilities": ["reporting", "management", "develop", "communication", "maintain", "investment returns"], "requirements": {"degrees": ["degree"], "majors": ["finance", "business"], "languages": ["english", "mandarin"], "language_level": ["fluent"], "hard_skills": ["investment products"], "soft_skills": ["communication", "proactive", "fast learner", "responsible"], "languages_combined": [{"language": "english", "language_level": ["fluent"]}, {"language": "mandarin", "language_level": ["fluent"]}]}, "experience_required": {"duration": ["3 - 5 years"], "field": ["trading"]}}, {"job_id": "100003009038710", "location_code": "hk", "company": "Chiron Management Company Ltd.", "job_title": "Analyst", "description": "\nWe are looking for an Analyst to help us with preparing in-depth market research on the topics related to decentralized finance and the digital asset industry as a whole.\n\nThe Analyst will have the opportunity to closely work with industry experts from leading companies such as Cointelegraph, Coin360, and Bequant, and learn about complex topics (DeFi, regulations, NFT etc.) in the blockchain & digital asset industry.\n\nApart from research, the Analyst will also have the chance to learn consulting best practices and execute strategic initiatives to grow our existing businesses. This will be a rare opportunity for a proactive individual to enter the blockchain industry and work with industry veterans directly.\n\u00a0Responsibilities\n\u2022 Compile research and market data under team leader guidance\n\u2022 Monitor market news and industry movement\n\u2022 Prepare research papers and presentation materials in management consulting standard\n\u2022 Work collaboratively with worldwide team members\n\u2022 Take initiatives to complete critical tasks with \"can-do\" attitude\n\nQualifications\n\u2022 Bachelor's degree in top tier university\n\u2022 Strong verbal and written English\n\u2022 Ability to self-learn new topics quickly\nExperienced in Microsoft Office suite (Excel, Word, PowerPoint)\n\u2022 Excellent communication skills\n\n", "employment_types": ["Full Time"], "selling_points": [], "locations": ["Not Specified"], "categories": ["Accounting", "Audit", "Banking / Finance", "Analyst", "Asset Management"], "post_time": "2022-01-11T07:40:00Z", "salary": {"currency": null, "max": null, "min": null, "period": "monthly", "term": null}, "salary_visible": false, "title_keywords": ["analyst"], "responsibilities": ["regulations", "guidance", "management", "consulting", "monitor", "market research", "communication", "market data"], "requirements": {"degrees": ["degree", "bachelor"], "majors": [], "languages": ["english"], "language_level": [], "hard_skills": ["blockchain", "excel", "word", "powerpoint", "microsoft office suite"], "soft_skills": ["communication skills", "proactive", "presentation", "can-do"], "languages_combined": [{"language": "english", "language_level": []}]}, "experience_required": {"duration": [], "field": []}}, {"job_id": "100003009048659", "location_code": "hk", "company": "Rich Loyal Consultants Limited", "job_title": "HK/ China Business Investment Advisor", "description": "Duties / Responsibilities:\u00a0\nActively explore the new business leads by offering services in order to meet the customers' satisfaction\u202f\u00a0\nAssist director in analyzing HK and China market growth.\u00a0\nLiaise with the committee to plan and execute various types of marketing events, in HK or in China.\u00a0\nBuild systematic training and marketing programs and systems.\u00a0\nPrepare proposal and presentation materials\u202fto best fit the client's needs\u00a0\nActively explore the new business leads by offering services in order to meet the customers' satisfaction\u00a0\n\n\n\nRequirements:\u00a0\n\nA Bachelor\u2019s degree holder with 1-2 years or above of working experience will be considered firstly.\u00a0\nGood interpersonal and communication skills, good in both Cantonese and English; fluent in Mandarin is an\u00a0advantage.\u00a0\nBusiness mindset, self-motivated, confident, and a team player will be preferred.\u00a0\nDetailed-oriented with good analytical and problem-solving skills.\u00a0\nStrong PRC connection and exposure is a definite advantage\u00a0\nFresh graduates and IANG holders will also consider trainee posts.\u00a0", "employment_types": ["Full Time", "Permanent"], "selling_points": ["Excellent Career Path", "Professional training", "Attractive salary package"], "locations": ["Quarry Bay"], "categories": ["Banking / Finance", "Investment", "Sales, CS & Business Devpt", "Business Development", "Asset Management"], "post_time": "2022-01-14T06:58:19Z", "salary": {"currency": "HKD", "max": 29999, "min": 20000, "period": "monthly", "term": null}, "salary_visible": true, "title_keywords": ["advisor"], "responsibilities": ["liaise with", "marketing events", "systems", "plan"], "requirements": {"degrees": ["bachelor", "degree holder"], "majors": [], "languages": ["cantonese", "english", "mandarin"], "language_level": ["advantage", "fluent", "good"], "hard_skills": ["problem-solving skills"], "soft_skills": ["confident", "communication skills", "self-motivated", "problem-solving skills", "team player", "interpersonal", "detailed"], "languages_combined": [{"language": "cantonese", "language_level": ["good"]}, {"language": "english", "language_level": ["good"]}, {"language": "mandarin", "language_level": ["fluent", "advantage"]}]}, "experience_required": {"duration": ["1-2 years"], "field": []}}, {"job_id": "100003009039963", "location_code": "hk", "company": "MCP Asset Management Company Limited", "job_title": "Associate Director / Director \u2013 Legal & Compliance", "description": "Job description: An excellent legal and compliance opportunity in a global asset management firm.\n\n\nRequirements:\n\nWe\u2019re looking for a mature and independent team-player. The ideal candidate should:\nhave degree or higher diploma majoring in law or related discipline;\nhave about 10-15 years\u2019 experience gained in the field of financial laws, asset management, corporate administration or related financial services;\nbe proficient in English and Chinese;\npossess strong analytical and communication skills;\nwell-organised and is able to multi-tasks at the same time; and\nbe proactive and a good team-player.\nApplicant with less experience may also be considered.\n\n\n\nJob duties:\n\nAssist in the creation and maintenance of investment funds documentation database;\nWork closely with back office, front office and service providers on corporate administration and compliance matters;\nWork closely with compliance consultants to support the SFC licensing, continuous professional training monitoring and other compliance process;\nAssist in the preparation of basic corporate and/or legal documents (e.g. board resolutions);\nAssist in the implementation of compliance policies and controls applicable to the Group;\nProvide administrative support to the team;\nHandle ad hoc projects and duties.\n\n\n\nInterested candidates please send full resume with expected salary by clicking \"Apply Now\".\n\nPersonal data provided by job applicants will be used for recruitment purposes only and will be treated in strict confidential.", "employment_types": ["Full Time"], "selling_points": [], "locations": ["Causeway Bay"], "categories": ["Banking / Finance", "Fund Management", "Professional Services", "Legal & Compliance", "Asset Management"], "post_time": "2022-01-11T16:02:22Z", "salary": {"currency": null, "max": null, "min": null, "period": "monthly", "term": null}, "salary_visible": false, "title_keywords": ["associate director", "director"], "responsibilities": ["maintenance", "policies", "compliance", "monitoring", "back office", "implementation", "ad hoc projects", "database", "documentation", "provide administrative support", "administration"], "requirements": {"degrees": ["diploma", "degree"], "majors": ["law"], "languages": ["english", "chinese"], "language_level": ["proficient"], "hard_skills": [], "soft_skills": ["communication skills", "independent", "multi-tasks", "team-player", "mature", "well-organised", "proactive", "ideal"], "languages_combined": [{"language": "english", "language_level": ["proficient"]}, {"language": "chinese", "language_level": ["proficient"]}]}, "experience_required": {"duration": ["10-15 years"], "field": ["financial", "related", "asset management", "financial services", "administration"]}}, {"job_id": "100003009038459", "location_code": "hk", "company": "Asia Progress Executive Limited", "job_title": "Fund Operation, AVP  -PRC  Asset Management firm", "description": "Our client is PRC\u00a0Asset\u00a0Management. They\u00a0are inviting\u00a0high\u00a0caliber talents to develop and take part in the growth of their business:\n\nFund Operation ,AVP - PRC Asset Management firm\u00a0\n\nResponsibilities\n\nResponsible for performing the daily operations work, such as cash & security holding reconciliation, preparing cash forecast reporting\nMonitor the completeness of daily trade execution and matching performed by back office team\nLiaise with fund administrators, custodians and prime brokers on a daily basis\nParticipate in new fund launch\nClose communication with internal departments, such as Legal & Compliance, Sales & Marketing etc\nProvide support to senior management for new project implementation\n\nRequirements:\n\nDegree holder in Finance or related disciplines\nAt least 5years hands on fund operation experience in\u00a0 Asset Management\u00a0\nFamiliar with investment operation flow and with strong experience in QFII, RQFII or QDII products\nGood PC skills is a definite advantage\nGood command of written and spoken English & Chinese including Putonghua\nGood team player with good communication and interpersonal skills\n\nPlease send full resume with\u00a0present & expected\u00a0salary to expedite sourcing\u00a0in\u00a0MS-WORD\u00a0format by clicking \u201cAPPLY NOW\u201d\n\nPlease quote our reference in your application\n\nPersonal data provided by job applicants will be used strictly in accordance with the employer\u2019s personal data policies, a copy of which will be provided upon request\n\nAll information provided will be used for recruitment purpose only", "employment_types": ["Full Time"], "selling_points": ["Degree 2-3yrs fund operation exp Asset Management", "products cash equities, QFII RQFII QDII , bonds", "Trade execution, trade processing & fund admin"], "locations": ["Central & Western Area"], "categories": ["Banking / Finance", "Fund Management", "Order Processing & Operation / Settlement", "Asset Management"], "post_time": "2022-01-11T06:57:39Z", "salary": {"currency": null, "max": null, "min": null, "period": "monthly", "term": null}, "salary_visible": false, "title_keywords": ["asset management"], "responsibilities": ["reporting", "provide support", "prime brokers", "compliance", "monitor", "back office", "implementation", "communication", "daily operations", "forecast", "liaise with", "senior management"], "requirements": {"degrees": ["degree holder"], "majors": ["related disciplines", "finance"], "languages": ["putonghua", "english", "chinese"], "language_level": ["good command"], "hard_skills": ["ms-word", "qfii", "qdii", "pc skills", "rqfii"], "soft_skills": ["good team player", "hands on", "communication and interpersonal skills"], "languages_combined": [{"language": "putonghua", "language_level": ["good command"]}, {"language": "english", "language_level": ["good command"]}, {"language": "chinese", "language_level": ["good command"]}]}, "experience_required": {"duration": [], "field": ["operation", "investment", "asset management"]}}, {"job_id": "100003009035251", "location_code": "hk", "company": "Tampa Stone Co.", "job_title": "Portfolio Manager (30K above) (Full Time)", "description": "Job Description\n\nA golden opportunity to experience the investment platform with full range of investment products. Tailor-made industry training, coaching and mentoring by a team of experienced mentors.\n\nJob Duties:\n\n\u00a0Promote full range of financial products.\n\u00a0Practice on asset management, research and analysis skills\u00a0\n\u00a0Identify and develop client business relationships\n\u00a0Organize and participate in sales visits with existing and potential clients.\n\nRequirements:\n\nBachelor Degree or equivalent experience\nCandidates with lower academic qualifications or inexperienced will consider Investment Trainee position\nProficient in both written and spoken English, Chinese and Mandarin\nExcellent interpersonal, communications and presentation skills\u00a0 \u00a0\n\n#Candidates must be permitted to work in Hong Kong#\n\nInterested parties please\u00a0click\u00a0Apply with CV and business\u00a0photo", "employment_types": ["Full Time", "Permanent"], "selling_points": ["Flexible hours", "Basic allowance + Commission + Performance Bonus", "Training allowance"], "locations": ["Wan Chai"], "categories": ["Accounting", "Financial Analyst", "Property / Real Estate", "Property Consultancy", "Banking / Finance", "Asset Management"], "post_time": "2022-01-12T02:23:47Z", "salary": {"currency": null, "max": null, "min": null, "period": "monthly", "term": null}, "salary_visible": false, "title_keywords": ["manager"], "responsibilities": ["develop", "analysis", "asset management"], "requirements": {"degrees": ["degree", "bachelor"], "majors": [], "languages": ["english", "chinese", "mandarin"], "language_level": ["proficient"], "hard_skills": [], "soft_skills": ["presentation skills", "interpersonal"], "languages_combined": [{"language": "english", "language_level": ["proficient"]}, {"language": "chinese", "language_level": ["proficient"]}, {"language": "mandarin", "language_level": ["proficient"]}]}, "experience_required": {"duration": [], "field": []}}, {"job_id": "100003009033797", "location_code": "hk", "company": "AEM Asset Management Limited", "job_title": "Junior Associate, Client Services", "description": "Responsibilities\n\n\u00a0\u00a0\u00a0\u00a0\u00a0\u00a0\u00a0\u00a0 Products covered include equities, fixed income, investment/mutual funds,\u00a0 \u00a0 \u00a0 \u00a0 \u00a0 \u00a0 \u00a0 \u00a0 \u00a0 \u00a0 \u00a0private equity\n\u00a0\u00a0\u00a0\u00a0\u00a0\u00a0\u00a0\u00a0 Conduct research on various markets and products\n\u00a0 \u00a0 \u00a0 \u00a0 \u00a0Assist in establishing and maintaining strong business relationships with clients\n\u00a0\u00a0\u00a0\u00a0\u00a0\u00a0\u00a0\u00a0 Occasionally travel to other countries for site visits\n\u00a0\u00a0\u00a0\u00a0\u00a0\u00a0\u00a0\u00a0 Perform ad-hoc assignments\n\nRequirements\n\n\u00a0\u00a0\u00a0\u00a0\u00a0\u00a0\u00a0\u00a0 Good command of spoken and written English, Mandarin and Cantonese\n\u00a0\u00a0\u00a0\u00a0\u00a0\u00a0\u00a0\u00a0 Proficiency in MS Office and Chinese word processing\n\u00a0\u00a0\u00a0\u00a0\u00a0\u00a0\u00a0\u00a0 Team player with strong sense of responsibility and self-motivation\n\u00a0 \u00a0 \u00a0 \u00a0 \u00a0Good interpersonal and communication skills\n\u00a0 \u00a0 \u00a0 \u00a0 \u00a0Outgoing and energetic personality\n\u00a0 \u00a0 \u00a0 \u00a0 \u00a0Fresh graduates are also welcomed\n\nWe offer\n\n\u00a0\u00a0\u00a0\u00a0\u00a0\u00a0\u00a0\u00a0 5 Days\u2019 work\n\u00a0\u00a0\u00a0\u00a0\u00a0\u00a0\u00a0\u00a0 Performance bonus\n\u00a0 \u00a0 \u00a0 \u00a0 \u00a0Study and examination leaves\n\nPlease click \"Apply Now\" to submit your application.\nAll personal data collected will be used for recruitment purpose only.", "employment_types": ["Full Time", "Permanent"], "selling_points": [], "locations": ["Causeway Bay"], "categories": ["Accounting", "Financial Analyst", "Banking / Finance", "Fund Management", "Asset Management"], "post_time": "2022-01-10T01:49:04Z", "salary": {"currency": null, "max": null, "min": null, "period": "monthly", "term": null}, "salary_visible": false, "title_keywords": ["associate", "junior"], "responsibilities": ["ad-hoc assignments", "conduct research", "maintaining"], "requirements": {"degrees": [], "majors": [], "languages": ["cantonese", "english", "chinese", "mandarin"], "language_level": ["proficiency", "good command"], "hard_skills": ["chinese word processing", "ms office"], "soft_skills": ["outgoing", "communication skills", "sense of responsibility", "self-motivation", "team player", "energetic", "interpersonal"], "languages_combined": [{"language": "cantonese", "language_level": ["good command"]}, {"language": "english", "language_level": ["good command"]}, {"language": "chinese", "language_level": ["proficiency"]}, {"language": "mandarin", "language_level": ["good command"]}]}, "experience_required": {"duration": [], "field": []}}, {"job_id": "100003009046110", "location_code": "hk", "company": "Guotai Junan International Holdings Limited", "job_title": "Compliance Manager, Asset Management", "description": "Responsibilities\n\nAdvise on a full range of compliance function (SFC 1,4,9)to ensure full compliance with regulatory requirements include UCITS/HK authorized fund/Cayman fund\nReview and approve marketing communications, materials, disclaimer consistency with applicable regulatory standards and provide guidance to writers and others involved\nConduct process for monitoring and tracking of remedial actions derived from Compliance Monitoring activity under regulatory or internal requirement.\nMaintain and review company\u2019s policies, procedures and practices to ensure compliance with all applicable laws and regulations\u00a0\nPerform Gap Analysis upon regulatory changes\nPrepare and respond to inquiries and audits from regulatory authorities\nResponsible on pre-trade and post-trade monitoring across multi asset guideline restrictions on Bloomberg CMGR and VMGR.\nIn-depth and comprehensive knowledge of KYC and AML, in particular onboarding entities, present AML & KYC view of cases\nPerform ad-hoc assignments as required.\nBackup each other in the team.\n\nRequirements\n\nHolds a\u00a0degree or professional qualification in Legal, Business, Finance, Accounting or related disciplines\nMinimum 5 years compliance experience in asset management, preferably in SFC regulated institutions\nWorking knowledge of securities laws and regulations in Hong Kong, Cayman and Luxemburg with a good understanding of Asset management business compliance tasks\nFamiliar with Bloomberg, MS Office applications and Chinese word processing\nA good team player, mature, responsible, detail minded, with the ability to handle multiple tasks independently under pressure\nGood communication and organization skills\nGood command in written and spoken English, Cantonese and Chinese\n\nWe offer an attractive remuneration package to the right candidate. Interested parties please forward your full resume with availability, expected salary by pressing \"Apply now\" or send it to 27/F., Low Block, Grand Millennium Plaza, 181 Queen\u2019s Road, Central, Hong Kong.\n\n(Data collected will be kept strictly confidential and used for recruitment purpose only.)", "employment_types": ["Full Time", "Permanent"], "selling_points": ["Strengthen regulatory compliance in fund level", "Corporate with risk and compliance department", "Advise on full range of compliance function"], "locations": ["Central & Western Area"], "categories": ["Professional Services", "Legal & Compliance", "Banking / Finance", "Risk Management", "Asset Management"], "post_time": "2022-01-13T09:38:31Z", "salary": {"currency": null, "max": null, "min": null, "period": "monthly", "term": null}, "salary_visible": false, "title_keywords": ["compliance manager", "asset management"], "responsibilities": ["regulations", "aml", "regulatory requirements", "policies", "review", "compliance", "monitoring", "procedures", "ensure compliance", "analysis", "ad-hoc assignments", "maintain", "kyc", "audits", "provide guidance", "tracking"], "requirements": {"degrees": ["degree"], "majors": ["related disciplines", "finance", "business", "accounting"], "languages": ["cantonese", "english", "chinese"], "language_level": ["good command"], "hard_skills": ["securities laws", "chinese word processing", "bloomberg", "ms office"], "soft_skills": ["good team player", "independently", "under pressure", "responsible", "mature", "handle multiple tasks", "communication", "organization skills"], "languages_combined": [{"language": "cantonese", "language_level": ["good command"]}, {"language": "english", "language_level": ["good command"]}, {"language": "chinese", "language_level": ["good command"]}]}, "experience_required": {"duration": ["minimum 5 years"], "field": ["compliance", "asset management"]}}, {"job_id": "100003009043174", "location_code": "hk", "company": "Cheuk Hang Growth", "job_title": "Fund Management Intern / Assistant / Trainee", "description": "Job Description\n\nOur clients are leading financial institutions in Hong Kong. They are currently looking for who interest in Finance to join their investment team as:\n\nResponsibilities:\n\nTo provide tailor-made financial advices to clients\nTo monitor & analyze clients\u2019 investment portfolio\nTo maintain good relationship with clients\n\nRequirements:\n\nUniversity graduate in any discipline\u00a0\nWilling to work with others\nExcellent interpersonal, communications and presentation skills\nAggressive, self-motivated, passionate for better career development\n\n\n\nBenefits:\n\n5 days work\nOn job training\nTraining allowance\nMedical Insurance, competitive salary and attractive bonus\n\nHK residents will only be considered.\nPersonal data will be used for recruitment purpose only.", "employment_types": ["Full Time"], "selling_points": [], "locations": ["Central & Western Area"], "categories": ["Banking / Finance", "Private Banking", "Management", "Management Trainee", "Asset Management"], "post_time": "2022-01-12T10:00:53Z", "salary": {"currency": "HKD", "max": 24999, "min": 20000, "period": "monthly", "term": null}, "salary_visible": true, "title_keywords": ["trainee", "assistant", "intern"], "responsibilities": ["monitor", "maintain good relationship"], "requirements": {"degrees": ["university graduate"], "majors": [], "languages": [], "language_level": [], "hard_skills": [], "soft_skills": ["passionate", "presentation skills", "interpersonal", "self-motivated"], "languages_combined": []}, "experience_required": {"duration": [], "field": []}}, {"job_id": "100003009046472", "location_code": "hk", "company": "Randstad Hong Kong Limited", "job_title": "Compliance Advisory, Asset Management/Funds", "description": "about the company\n\nOur client is a leading Investment Management Firm, headquartered in the United States\n\nabout the team\n\nFast paced working environment\nIndependent and self-motivated individuals\n\nabout the job\n\nAssist/advise business on all-rounded compliance issues, including registering/licensing new investment advisers, investment management structures, licensing individuals with the SFC, SFC applications etc\nConducting compliance reviews, maintaining and updating policies and procedures, including drafting new processes to streamline compliance initiatives\nCommunicate with internal stakeholders on potential risk and provide solutions/recommendations\nAssist with compliance protocols and training\n\nskills & experiences required\n\nUniversity Degree in Law, Finance, Accounting, Economics or relevant discipline\nAt least 3 to 7 years of relevant compliance experience in buy-side (hedge funds/private equity/asset management).\nCandidates with Audit/Advisory/Consultancy experience would be considered\nBasic knowledge of private funds\nStrong language skills in written and spoken English and Chinese\n\nTo apply online, please click on the link. Alternatively, for a confidential discussion please contact Joanne Lo on + 852 2232 3421 or email: joanne.lo@randstad.com.hk", "employment_types": ["Full Time", "Permanent"], "selling_points": ["Private Funds Experience is a must", "Big 4 / SFC Candidates Are Welcome", "Rewarding Culture and Promising Career Progression"], "locations": ["Not Specified"], "categories": ["Banking / Finance", "Financial Services", "Professional Services", "Legal & Compliance", "Asset Management"], "post_time": "2022-01-13T11:35:55Z", "salary": {"currency": "HKD", "max": 69999, "min": 35000, "period": "monthly", "term": null}, "salary_visible": true, "title_keywords": ["asset management"], "responsibilities": ["communicate with", "management", "maintaining", "policies", "compliance", "procedures", "audit", "provide solutions", "contact", "asset management"], "requirements": {"degrees": ["university degree"], "majors": ["finance", "accounting", "economics", "law"], "languages": ["english", "chinese"], "language_level": [], "hard_skills": ["basic", "private equity"], "soft_skills": ["self-motivated", "independent"], "languages_combined": [{"language": "english", "language_level": []}, {"language": "chinese", "language_level": []}]}, "experience_required": {"duration": ["at least 3 to 7 years"], "field": ["compliance", "audit", "asset management"]}}, {"job_id": "100003009041225", "location_code": "hk", "company": "Principal Asset Management Company (Asia) Limited", "job_title": "Manager, Investment Governance & Control", "description": "Job Summary\n\nBeing part of the Product Strategy & Development team, the Manager, Investment Governance & Control will play a critical role in the link between Investment Management team and Compliance & Risk departments at the group level with respect of three primary areas of focus: Investment compliance monitoring, risk management and internal policies monitoring.\u00a0\n\nWe are looking for a talent individual who can work independently in overseeing the investment compliance and risk management functions for asset management business with the primary focuses in mutual funds and MPF funds in Hong Kong.\u00a0 The role also plays an important part to collaborate with different business functions in various oversea offices within the group in performing risk oversight on funds.\u00a0 As one of the key members of the asset management family in Hong Kong, the Manager will also work alongside with other teammates under a small team environment regarding any new product development initiatives.\u00a0\n\nOther responsibilities include:\n\nEnsure that the investment management activities operate in compliance with applicable laws and regulations in relation to SFC and MPFA\nMonitor service providers by reviewing regular reports, conducting due diligence, on-site visit, including but not limited to fund administrator, transfer agency, etc.\nMaintain an oversight mechanism to strengthen the first line of defense for investment management activities\nInvestigate potential breaches and ensure remediate actions are executed\nDesign, implement and review the internal governance frameworks, internal control measures and policies of the investment management activities and initiatives\nReview and advise on internal work process and practices to identify, assess, report and mitigate the risks in a proactive manner\nKeep abreast of regulatory updates and accommodate the relevant regulatory changes in a timely and prudent manner\nPerform periodic monitoring/ surveillance according to relevant regulations and internal policies.\nMonitor the activities of investment managers and investment delegates by setting, reviewing relevant indicators and reports\nProvide support and perform other related duties and special projects as required from time to time.\n\nEssential Skills, Experience and Competencies\n\nThe Manager will act as an oversight role of the investment compliance and risk management functions in relation to asset management business, which requires strong analytical-mind, excellent problems solving skills and always keep an eye on details.\n\n\nProven experience as first line of defense or compliance experience gained within asset management, investment and/or pension industry; Well-versed in SFO codes and other regulatory requirements, for example AML/CFT, FATCA and CRS will be a strength of the role.\n\nOther key skills required for the role:\n\nDegree holder in Law, Business, Finance, Accounting or related disciplines\nExperience in ESG fund products and Climate Related Risk will be an advantage\nSelf-motivated, well-organized, able to work under pressure and multi-tasks with tight deadlines\nExcellent communication and interpersonal skills\nProficiency in both written and spoken English and Chinese\n\nWhat We Offer\n\nPrincipal offers employees a competitive package and a comprehensive range of benefits to help meeting your needs now and in the future, including:\n\n5-Day Work Week\nYear-end Payment\nDiscretionary Bonus\nBirthday Leave\nMedical Plan\nLife Insurance\nPension Scheme\nEmployee Stock Purchase Plan\nAnd Growth Opportunities!", "employment_types": ["Full Time", "Permanent"], "selling_points": ["Oversee investment compliance for asset management", "Work closely with group compliance & risk and BUHs", "Well versed in SFC, MPFA & regulatory requirements"], "locations": ["Kwun Tong"], "categories": ["Banking / Finance", "Financial Services", "Professional Services", "Legal & Compliance", "Asset Management"], "post_time": "2022-01-12T03:36:57Z", "salary": {"currency": null, "max": null, "min": null, "period": null, "term": null}, "salary_visible": false, "title_keywords": ["manager"], "responsibilities": ["regulations", "due diligence", "management", "provide support", "problems solving", "aml", "policies", "regulatory requirements", "compliance", "monitor", "review", "design", "monitoring", "maintain", "reports", "asset management", "report", "internal control"], "requirements": {"degrees": ["degree holder"], "majors": ["law", "finance", "related disciplines", "business", "accounting"], "languages": ["english", "chinese"], "language_level": ["proficiency"], "hard_skills": [], "soft_skills": ["self-motivated", "multi-tasks", "well-organized", "communication and interpersonal skills", "work under pressure"], "languages_combined": [{"language": "english", "language_level": ["proficiency"]}, {"language": "chinese", "language_level": ["proficiency"]}]}, "experience_required": {"duration": [], "field": ["related"]}}, {"job_id": "100003009040245", "location_code": "hk", "company": "Pathos Consultancy Limited", "job_title": "Fund Accountant", "description": "The Company\nOur client is Chinese based private equity company. They are looking for a junior Fund Accountant Associate to join the team.\n\nThe Role\n\nPreparing and review financial statements of SPVs;\nProviding day-to-day fund accounting;\nPreparing of Management Accountants and Financial Statements;\nReviewing monthly NAV calculation;\nAssisting asset management team with compilation and analysis for investment budgets and business plans;\nCompleting portfolio and client analysis;\nAssisting to provide KYC documents for bank opening purpose;\nActing as liaison support between asset management, joint venture partners, and fund clients ;\nReviewing capital call and distribution calculations prepared by subordinates.\n\nYour Profile\n\n\nGood interpersonal skills and ability to cooperate\nGood analytical and problem solving skills\nAble to work under pressure in meeting deadlines\nAt least 4+ years of experience in asset management / buy-side companies / big 4\nDegree holding in Accounting, Finance or Economics\nQualification in HKICPA/ACCA or similar qualifications are highly preferred\n\nApply Today\nTo apply online (Word attachment only), please click the 'Apply' button. Interested parties please apply with the most updated CV with expected salary and available date via JobsDB. Applicants who do not hear from us within 2 weeks may consider their applications unsuccessful.\u00a0\n\nAbout Pathos\nWe are Pathos Consultancy Limited, a boutique recruitment firm based in Hong Kong strategically placing our candidates across all levels in permanent, temporary and contract roles.\u00a0 We specialize in IT and finance roles for banking, financial services and listed MNC sectors.", "employment_types": ["Full Time", "Permanent"], "selling_points": ["Fund Accounting", "Private Equity / Hedge Fund", "Open to big 4 candidates"], "locations": ["Central"], "categories": ["Banking / Finance", "Financial Services", "Fund Management", "Asset Management"], "post_time": "2022-01-12T01:59:37Z", "salary": {"currency": null, "max": null, "min": null, "period": "monthly", "term": null}, "salary_visible": false, "title_keywords": ["accountant"], "responsibilities": ["budgets", "management", "work under pressure", "analysis", "review", "financial statements", "business plans", "kyc", "asset management"], "requirements": {"degrees": ["degree"], "majors": ["finance", "accounting", "economics"], "languages": ["chinese"], "language_level": [], "hard_skills": ["acca", "analysis", "word", "kyc", "problem solving skills", "private equity", "hkicpa"], "soft_skills": ["analytical and problem solving skills", "interpersonal skills", "work under pressure"], "languages_combined": [{"language": "chinese", "language_level": []}]}, "experience_required": {"duration": ["at least 4+ years"], "field": ["big 4", "asset management"]}}, {"job_id": "100003009045796", "location_code": "hk", "company": "Goldhorse Capital Management (HK) Limited", "job_title": "Business Development", "description": "Responsibilities\nSearch and identify new business opportunities to engage new clients, grow wallet share, increase revenue channels and maintain existing relationship\nBe the product owner, coordinate with cross-functional teams (Product, IT, Ops, Marketing) to execute business strategies and rollout new derivatives business products\nDevelop market-fit and innovative strategies to broaden business product offerings to meet institutional client needs and improved client experiences\nProactively monitor KPIs, competitor landscape, VIP clients and community feedback to iterate overall product, marketing and business strategy\n\nRequirements\n\nSharp and fast learner, thinking out of the box\n2 to 5 years of experience in business development, product or sales function at financial institutions, preferably with buyside connections such as PB, EAM, PWM\nPassionate about fintech industry, Experience on high/low-touch execution service, derivatives trading would be advantageous but not essential\nDetail-oriented, Entrepreneurship, Excellent oral and written communication skills\nFluent in English and Cantonese, Mandarin is advantageous\n\nConditions\n\nFast moving, challenging and unique business problems\nGreat career development opportunities in a growing company\nCompetitive salary", "employment_types": ["Full Time"], "selling_points": [], "locations": ["Tsim Sha Tsui"], "categories": ["Banking / Finance", "Financial Services", "Asset Management"], "post_time": "2022-01-13T08:43:29Z", "salary": {"currency": null, "max": null, "min": null, "period": "monthly", "term": null}, "salary_visible": false, "title_keywords": [], "responsibilities": ["business opportunities", "coordinate with", "monitor", "develop", "maintain", "kpis", "cross-functional teams"], "requirements": {"degrees": [], "majors": [], "languages": ["cantonese", "english", "mandarin"], "language_level": ["fluent"], "hard_skills": [], "soft_skills": ["communication skills", "oral", "unique", "detail-oriented", "fast learner", "passionate about"], "languages_combined": [{"language": "cantonese", "language_level": ["fluent"]}, {"language": "english", "language_level": ["fluent"]}, {"language": "mandarin", "language_level": ["fluent"]}]}, "experience_required": {"duration": ["2 to 5 years"], "field": ["financial institutions", "business development", "trading", "pb"]}}, {"job_id": "100003009033977", "location_code": "hk", "company": "China Shandong International Asset Management Limited", "job_title": "SFC Type 1, 4 & 9 RO Responsible Officer", "description": "Job Description\n\nAct as a Responsible Officer to supervise Type 1, 4 & 9 regulated activities in compliance with SFC regulations, including fund management;\nAssist in SFC license RA1 application;\u00a0\nProvide advice and support to management on strategic activities and daily operations;\nPrepare materials and present for Investment Committee meeting;\nDevelop and maintain compliance manual and corresponding workflows to ensure compliance with internal policies and external legislation and regulations.; and\nPerform other ad-hoc projects and assignments as required.\n\nRequirements\n\n\n\nSound knowledge of SFO, regulations and guidelines of relevant regulatory authorities and risk management control;\nDegree holder in Finance, Economics or a business-related discipline;\nLicensed SFC Responsible Officer for Type 1, 4 & 9 regulated activities (without conditions);\nExperience in application of SFC licensing;\nMinimum 3-year relevant experience as a Responsible Officer in Type 1, 4 & 9 regulated activities including at least 1 year of Type 1 and Type 9 experience; and\nGood command of written & spoken English and Chinese, proficiency in Mandarin Chinese is preferred.\nPlease state your current and expected salary in your CV.\u00a0", "employment_types": ["Full Time", "Permanent"], "selling_points": [], "locations": ["Wan Chai"], "categories": ["Banking / Finance", "Asset Management"], "post_time": "2022-01-10T02:19:06Z", "salary": {"currency": "HKD", "max": 54999, "min": 45000, "period": "monthly", "term": null}, "salary_visible": true, "title_keywords": ["responsible officer"], "responsibilities": ["regulations", "management", "policies", "compliance", "develop", "ensure compliance", "daily operations", "provide advice", "maintain", "ad-hoc projects"], "requirements": {"degrees": ["degree holder"], "majors": ["business", "finance", "economics"], "languages": ["mandarin chinese", "english", "chinese"], "language_level": ["proficiency", "good command"], "hard_skills": ["sfo"], "soft_skills": ["responsible"], "languages_combined": [{"language": "mandarin chinese", "language_level": ["good command"]}, {"language": "english", "language_level": ["proficiency", "good command"]}, {"language": "chinese", "language_level": ["proficiency", "good command"]}]}, "experience_required": {"duration": ["minimum 3-year", "at least 1 year"], "field": ["relevant experience"]}}, {"job_id": "100003009037407", "location_code": "hk", "company": "CHINA INDUSTRIAL SECURITIES INTERNATIONAL FINANCIAL GROUP LIMITED", "job_title": "Asset Management, Operations/ Fund Operations", "description": "Job Duties and Responsibilities\n\nSupport daily operational duties of the funds, discretionary accounts and investment products (equities, fixed income, repo, private equity. etc)\nReconcile the fund/accounts\u2019 cash management, trade booking, position reconciliation and corporate action support\nOversee the fund NAV process ensuring full reconciliation of the fund administrator\u2019s NAV calculation as part of an internal maker-checker review\nOversee and review the operational support to the client onboarding process as pertains to AML/KYC in conjunction with the transfer agency\nOversee unmatched trades for timely settlement and liaise with custodians to reconcile any trade matching issues\nMaintain reasonable fund expenses and improve the fund expense ratio across all funds\nOversee the funds\u2019 financial audit and in conjunction with the fund\u2019s auditors, tax consultant and fund administrator\nWork with external Advisor to ensure FATCA and CRS reporting\u2019s processes adhere to the respective regulatory guidelines.\nWork with the platform development to streamline the operational process of the firm\u2019s products and assist in preparing and executing test cases and new systems support\n\nRequirements\n\nUniversity degree holder in business administration, Accountancy, Finance or related discipline are preferable\nMinimum 1-2years of experience in relevant asset management /fund administrator experience\nProduct knowledge of the fund operations workflow\nExperience in handling NAV calculations\nAble to take initiative and good at time management\nProficiency in Chinese (including Mandarin) and English are required\nImmediate Available is highly preferred", "employment_types": ["Full Time"], "selling_points": ["Immediate Available is highly preferred", "Support daily operation duties for asse management", "Securities"], "locations": ["Sheung Wan"], "categories": ["Banking / Finance", "Fund Management", "Order Processing & Operation / Settlement", "Asset Management"], "post_time": "2022-01-11T02:43:24Z", "salary": {"currency": null, "max": null, "min": null, "period": "monthly", "term": null}, "salary_visible": false, "title_keywords": ["operations", "asset management"], "responsibilities": ["tax", "reporting", "management", "operational support", "aml", "guidelines", "review", "expenses", "trade booking", "audit", "systems", "maintain", "executing", "kyc", "liaise with", "operational duties", "timely settlement"], "requirements": {"degrees": ["university degree"], "majors": ["finance", "business administration", "accountancy"], "languages": ["english", "chinese", "mandarin"], "language_level": ["proficiency"], "hard_skills": [], "soft_skills": ["time management", "initiative"], "languages_combined": [{"language": "english", "language_level": ["proficiency"]}, {"language": "chinese", "language_level": ["proficiency"]}, {"language": "mandarin", "language_level": ["proficiency"]}]}, "experience_required": {"duration": [], "field": ["asset management"]}}, {"job_id": "100003009035611", "location_code": "hk", "company": "Kata Gj Palm Company", "job_title": "Assistant Relationship Manager", "description": "Our client is the leading financial advisory firm in Hong Kong with thousands of professional financial consultants in the Asia Pacific region. They focus on three core businesses: financial advisory, financial product manufacturing and FinTech. They are looking a Assistant Relationship Manager within their Wealth Management team.\n\nResponsibilities:\n\nSupporting Investment Representatives in financial and maintaining successful relationships with clients\nTo provide comprehensive financial strategies to clients including on financial planning, insurance and securities service\u00a0\nTo manage clients\u2019 financial portfolios periodically\nTo provide quality after-sales services to maintain relationship with clients Engage in team management and related activities Markets analysis and market event\nTo explore oversea property, asset management and risk management solution to individual and corporate clients\nQualifications:\n\nBachelor degree from University (Preferably in Finance, Business Management, Economics or related discipline)\nat least 1 years of relevant financial services experience\nDedicated team player with keen interest in financial industry\n\nJob Offer:\n\nWealth Management team\nSteep learning curve\nExcellent career development\nAttractive bonus package", "employment_types": ["Full Time", "Part Time", "Permanent", "Internship"], "selling_points": [], "locations": ["Admiralty"], "categories": ["Banking / Finance", "Fund Management", "Marketing / Public Relations", "Marketing - Market Research", "Asset Management"], "post_time": "2022-01-11T16:01:36Z", "salary": {"currency": "HKD", "max": 29999, "min": 20000, "period": "monthly", "term": null}, "salary_visible": true, "title_keywords": ["assistant relationship manager"], "responsibilities": ["management team", "management", "maintaining", "analysis", "quality", "maintain", "asset management", "career development", "insurance", "planning"], "requirements": {"degrees": ["degree", "bachelor"], "majors": ["finance", "business", "economics"], "languages": [], "language_level": [], "hard_skills": ["business management", "focus", "analysis"], "soft_skills": ["keen", "comprehensive", "team player", "learning", "focus"], "languages_combined": []}, "experience_required": {"duration": ["at least 1 years"], "field": ["financial services"]}}, {"job_id": "100003009048778", "location_code": "hk", "company": "Global Job Consulting Co.", "job_title": "Asset Management Consultant / Wealth Management Consultant / IFA", "description": "Responsibilities:\n\n-Provide comprehensive financial and banking advice to clients on\u00a0risk-and wealth-management products, Insurance, MPF and employee-benefits products\n\n-Analyze and compare products of different service providers/ insurance companies\n\n-Constant monitoring of investment portfolios\n\n-Develop and expand existing network through relationship management\n\nRequirements:\n\n-Fresh graduates/ IANG will also be considered\n\n-Mature, self-motivated, hardworking and willing to learn\n\n-Aggressive, Energetic and outgoing\n\n-Good interpersonal and communication skills\n\n-Explore PRC and Hong Kong market\n\n-Interest in Investment\u00a0\n\nIncentive:\n\n-Attractive basic +\u00a0commission with allowance package\n\n-Fast-track promotion to managerial position\n\n-Overseas trips & conventions plus excellent career path\n\n-Excellent and comprehensive in-house training programs\n\n-Professional training to become a\u00a0Millionaires", "employment_types": ["Full Time"], "selling_points": ["$25000 - $40000", "Work balance and be Professional", "Happy working atmosphere"], "locations": ["Sheung Wan"], "categories": ["Banking / Finance", "Asset Management"], "post_time": "2022-01-14T07:16:36Z", "salary": {"currency": null, "max": null, "min": null, "period": "monthly", "term": null}, "salary_visible": false, "title_keywords": ["wealth management consultant", "consultant", "asset management"], "responsibilities": [], "requirements": {"degrees": [], "majors": [], "languages": [], "language_level": [], "hard_skills": [], "soft_skills": [], "languages_combined": []}, "experience_required": {"duration": [], "field": []}}, {"job_id": "100003009042966", "location_code": "hk", "company": "Chong Hing Bank Ltd", "job_title": "Treasury and Markets Trainee", "description": "We are looking for high calibre individuals to join our Treasury and Markets for developing a long-term career with us.\u00a0 Treasury and Markets Trainees are provided with development and learning opportunities comprising on-the-job training, job rotation and coaching which equip you with relevant knowledge and skills for career advancement. \u00a0We also offer support to you to pursue relevant professional qualifications in order to enhance your professionalism.\n\nWe now offer development opportunities in following professional teams:\n\nSales and Marketing\nAsset Management\nProduct Structuring\n\nWe welcome all young talents who meet the following requirements:\n\nUniversity graduate in Computer Science, Finance, Economics, Mathematics, Business or related disciplines (strong technical / numerical background is preferred)\nExcellent analytical, interpersonal and communication skills\nStrong self-motivation and drive to achieve excellence\nPassionate, committed and a good team player\nSelf-disciplined and able to work under pressure\u00a0\u00a0\nGood computer knowledge in VBA and Macros\n\n\nWe offer competitive remuneration package and promising career opportunities to the successful candidates. Interested parties, please send full resume with current & expected salary and the date of availability to\u00a0The HR Division, G.P.O. Box 2535, HK\u00a0, or by clicking Apply Now. Please quote reference on your application. Information provided will be treated in strict confidence and only be used for recruitment purposes. Personal data of unsuccessful applications will be destroyed 24 months after the completion of the recruitment and selection exercise.", "employment_types": ["Full Time", "Permanent"], "selling_points": ["Provided w/ development & learning opportunities", "University graduate in Computer Science, Finance", "Strong technical /numerical background is prefer"], "locations": ["Central"], "categories": ["Banking / Finance", "Treasury", "Equities / Capital Markets", "Asset Management"], "post_time": "2022-01-12T09:19:34Z", "salary": {"currency": null, "max": null, "min": null, "period": "monthly", "term": null}, "salary_visible": false, "title_keywords": ["trainee"], "responsibilities": ["teams", "developing", "communication", "asset management", "work under pressure"], "requirements": {"degrees": ["university graduate"], "majors": ["mathematics", "finance", "economics", "related disciplines", "business", "computer science"], "languages": [], "language_level": [], "hard_skills": ["vba", "professional qualifications"], "soft_skills": ["passionate", "communication skills", "good team player", "committed", "learning", "self-motivation", "interpersonal", "work under pressure"], "languages_combined": []}, "experience_required": {"duration": [], "field": []}}, {"job_id": "100003009040340", "location_code": "hk", "company": "Pathos Consultancy Limited", "job_title": "Fund Accounting Manager", "description": "The Company\nOur client is a sizable financial services company based in Hong Kong. They are currently looking for a Fund Accounting Manager to join the Fund Services team.\u00a0\n\nThe Role\n\n\nAssist to supervise a team in performing portfolio valuation NAV prices computation and other fund administration works daily\nCheck valuation reports and other fund administration works to ensure that they are correctly prepared\nMaintaining a high degree of accuracy and consistency in preparation of daily reporting and ensure that the pricing/valuation process are adhered to audit procedures and ensure service standards are met.\nDeal with issues and queries from clients in a professional and timely manner\nFollow and perform control as specified in the Procedure Manual and ensure comply with in all relevant work processes. Prompt escalation to Team Head or Department Head for any issues identified.\nStrong sense on risk awareness and supervise the team members to ensure they always comply with regulation and company\u2019s policy and procedures.\nParticipate in UAT for any new system enhancement prior to production\nParticipate in those tasks or projects as assigned by Department Head from time to time and take accountability.\u00a0\n\nYour Profile\n\n\nDegree holder in accountancy or Diploma in Business related discipline etc\nMinimum 8 years\u2019 experience in fund accounting and administration, with substantial\u00a0experience in regulated mutual funds / MPF / ORSO schemes operations\nGood command of spoken and written English and Chinese.\nBe flexible and an open-minded team player\nStrong adaptability to change\n\nApply Today\nTo apply online (Word attachment only), please click the 'Apply' button. Interested parties please apply with the most updated CV with expected salary and available date via JobsDB. Applicants who do not hear from us within 2 weeks may consider their applications unsuccessful.\n\nAbout Pathos\nWe are Pathos Consultancy Limited, a boutique recruitment firm based in Hong Kong strategically placing our candidates across all levels in permanent, temporary and contract roles.\u00a0 We specialize in IT and finance roles for banking, financial services and listed MNC sectors.", "employment_types": ["Full Time", "Permanent"], "selling_points": ["Financial Services", "Mutual Fund / Pension Fund", "Fund administration / Fund accounting"], "locations": ["Central"], "categories": ["Banking / Finance", "Financial Services", "Fund Management", "Asset Management"], "post_time": "2022-01-12T02:21:13Z", "salary": {"currency": null, "max": null, "min": null, "period": "monthly", "term": null}, "salary_visible": false, "title_keywords": ["accounting manager"], "responsibilities": ["reporting", "valuation", "control", "uat", "maintaining", "mpf", "operations", "procedures", "audit", "service standards", "reports", "administration"], "requirements": {"degrees": ["diploma", "degree", "degree holder"], "majors": ["business", "accountancy"], "languages": ["english", "chinese"], "language_level": ["good command"], "hard_skills": ["word"], "soft_skills": ["flexible", "accountability", "prompt", "open-minded", "timely", "adaptability", "team player"], "languages_combined": [{"language": "english", "language_level": ["good command"]}, {"language": "chinese", "language_level": ["good command"]}]}, "experience_required": {"duration": ["minimum 8 years"], "field": ["accounting", "mpf", "administration"]}}, {"job_id": "100003009045852", "location_code": "hk", "company": "Superfund Financial (Hong Kong) Limited", "job_title": "Sales Support Associate", "description": "Job Responsibilities\n1. To make warm calls for setting up the appointments with the company\u2019s sales managers.\n\n2\u00b7 Support the company\u2019s sales managers in new business sales and retention activities.\n\n3\u00b7 Handle customer\u2019s calls, facilitate the enrollment process, follow up financial documents and enquires.\n\nJob Requirements\n\n\u00b7 Undergraduate Degree, Finance or Economics degree preferred\n\n\u00b7 At least 1 year of experience in the financial services industry.\n\n\u00b7 Strong Proficiency in computer skills including Microsoft office suites\n\n\u00b7 Excellent attention to detail\n\n\u00b7 Self-motivated with great optimistic mind. (must be an excellent team player with a strong work ethic and willing to learn)\n\n\u00b7 Strong interpersonal, relationship building and communication skills with the ability to remain highly professional.\n\n\u00b7 Fluent in English, Cantonese and Mandarin", "employment_types": ["Full Time", "Permanent"], "selling_points": ["Support in new sales and retention activities", "At least 1 year work experience in financial field", "Fluent in English, Cantonese and Mandarin"], "locations": ["Tsim Sha Tsui"], "categories": ["Banking / Finance", "Financial Services", "Sales, CS & Business Devpt", "Sales - Sales Management", "Asset Management"], "post_time": "2022-01-13T10:21:01Z", "salary": {"currency": null, "max": null, "min": null, "period": "monthly", "term": null}, "salary_visible": false, "title_keywords": ["associate", "sales"], "responsibilities": ["enrollment"], "requirements": {"degrees": ["degree"], "majors": ["finance", "economics"], "languages": ["cantonese", "english", "mandarin"], "language_level": ["fluent"], "hard_skills": ["computer skills", "microsoft office"], "soft_skills": ["communication skills", "self-motivated", "willing to learn", "work ethic", "attention to detail", "team player", "interpersonal"], "languages_combined": [{"language": "cantonese", "language_level": ["fluent"]}, {"language": "english", "language_level": ["fluent"]}, {"language": "mandarin", "language_level": ["fluent"]}]}, "experience_required": {"duration": ["at least 1 year"], "field": ["financial services industry"]}}, {"job_id": "100003009040708", "location_code": "hk", "company": "CEB International Investment Corporation Limited", "job_title": "Credit Sales", "description": "Responsibilities:\n\n\u2022 To support institutional sales coverage for all fixed income products;\n\n\u2022 To facilitate client on-boarding for existing and prospective institutional clients;\n\n\u2022 To support new business development and new product roll-out;\n\n\u2022 To support marketing efforts such organizing and participating in conferences, corporate access events etc;\n\n\u2022 To carry out other duties which may be given by the Supervisor, in which such assignments are consistent with the scope of employment.\u00a0\n\nRequirements:\n\n\u2022 A Bachelor's degree and qualified to be a licensed person under SFC;\n\n\u2022 3-5 year of sales-related work experience;\n\n\u2022 Strong interpersonal and presentation skills;\n\n\u2022 Highly independent and strong problem-solving ability;\n\n\u2022 Language skills required include Mandarin and English. Proficiency in Cantonese will be a plus.", "employment_types": ["Full Time", "Permanent"], "selling_points": ["Institutional sales for fixed income products", "3-5 year of sales-related work experience", "Strong interpersonal and presentation skills"], "locations": ["Central"], "categories": ["Banking / Finance", "Asset Management"], "post_time": "2022-01-12T02:58:24Z", "salary": {"currency": null, "max": null, "min": null, "period": "monthly", "term": null}, "salary_visible": false, "title_keywords": ["sales"], "responsibilities": ["conferences", "other duties"], "requirements": {"degrees": ["degree", "bachelor"], "majors": [], "languages": ["cantonese", "english", "mandarin"], "language_level": ["proficiency"], "hard_skills": ["problem-solving", "plus"], "soft_skills": ["problem-solving", "highly independent", "presentation skills", "interpersonal"], "languages_combined": [{"language": "cantonese", "language_level": ["proficiency"]}, {"language": "english", "language_level": []}, {"language": "mandarin", "language_level": []}]}, "experience_required": {"duration": ["3-5 year"], "field": ["related"]}}, {"job_id": "100003009040010", "location_code": "hk", "company": "Hays", "job_title": "Assistant Manager/Finance Manager | Private Equity", "description": "HOT JOB: Fund House seeking an Assistant Manager to support their Finance team | ~$50K + Bonus\n\nYour new company\n\nThis multinational financial institution is currently hiring for an Assistant Manager/Finance Manager position. Its office in Hong Kong offers a word-class working environment with great exposure to the private equity and buy-side industry.\n\nYour new role\n\nYour responsibilities include:\n\n\nProvide support in preparing financial reports, tax and regulatory returns;\nAssist fund operation procedure, e.g. capital call, distribution, management fee, bank transactions and ad-hoc tasks (for responding to investors' requests)\nHandle full set of accounts, invoice payments, staff claims and bank reconciliations, etc.;\nLiaise with auditors to ensure smooth year end closing for group related entities;\nProvide general administration, company secretarial and compliance support;\nWork with Management for regular review and enhancement of accounting workflow\n\n\nWhat you'll need to succeed\n\n\nCPA or equivalent qualification\nExperience in handling PE/Venture Capital Fund\nExperience of working in SFC licensed corporations, FRR reporting is a plus\nBachelor's degree in Accounting or related field\nIndependent with strong analytical, communication, and computer skills (e.g. QuickBooks)\nProficiency in spoken and written English and Chinese\n\n\nWhat you'll get in return\n\n\nStrong exposure to the Buy-Side and Private Equity industry\nUnlimited Career Development Opportunities\nGood Work Life Balance\nAttractive Bonus\nFamily Like Culture\n\n\nWhat you need to do now\nIf you are interested in this position or other Accounting positions in the Financial Services industry, please send your Resume to Veronica.Lin@hays.com.hk\n\nAt Hays, we value diversity and are passionate about placing people in a role where they can flourish and succeed. We actively encourage people from diverse backgrounds to apply.", "employment_types": ["Full Time", "Permanent"], "selling_points": ["Exposure to the Buy-Side & Private Equity Industry", "Unlimited Career Development Opportunities", "Good Work Life Balance"], "locations": ["Not Specified"], "categories": ["Accounting", "Finance / Accounting Manager", "Banking / Finance", "Fund Management", "Asset Management"], "post_time": "2022-01-12T00:00:36Z", "salary": {"currency": "HKD", "max": 54999, "min": 45000, "period": "monthly", "term": null}, "salary_visible": true, "title_keywords": ["assistant manager", "finance manager"], "responsibilities": ["work with management", "transactions", "regular review", "communication", "liaise with", "administration", "full set of accounts", "compliance", "bank reconciliations", "finance team", "reporting", "provide support", "management", "invoice", "career development", "tax", "financial reports", "ad-hoc tasks", "payments"], "requirements": {"degrees": ["degree", "bachelor"], "majors": ["accounting"], "languages": ["english", "chinese"], "language_level": ["proficiency"], "hard_skills": ["plus", "quickbooks", "word", "cpa", "computer skills", "pe", "venture capital", "private equity", "frr"], "soft_skills": ["independent", "interested in", "communication", "diverse", "smooth", "passionate about"], "languages_combined": [{"language": "english", "language_level": ["proficiency"]}, {"language": "chinese", "language_level": ["proficiency"]}]}, "experience_required": {"duration": [], "field": ["venture capital"]}}, {"job_id": "100003009039146", "location_code": "hk", "company": "Oriental Ever Investment Limited", "job_title": "Operation Officer / Manager", "description": "Responsibilities:\n\nVerify clients' account opening/AML documents to proceed account opening process and handle clients\u2019 enquiries;\nAssist trade execution and settlement for mutual funds;\nProvide administrative support including data input, document filing and generate reports from computing system;\nPrepare client/transactions reports and conduct periodical reviews to meet regulatory requirements;\nPerform other ad-hoc projects such as system enhancement, user acceptance testing, etc.\n\nRequirements:\n\n2 years or above in relevant experience, preferably in asset management\nKnowledgeable on mutual fund operations preferably\nEligible for SFC Type 1 representative license\u00a0\nGood command in English, Cantonese and Mandarin\nGood communication skill and proficiency in MS Office\nImmediate available is preferred", "employment_types": ["Full Time", "Permanent", "Contract"], "selling_points": ["Discretionary bonus", "Work Life balance, NO work overtime", "Opportunity to work at technology platform"], "locations": ["Central"], "categories": ["Banking / Finance", "Financial Services", "Wealth Management", "Asset Management"], "post_time": "2022-01-11T08:50:27Z", "salary": {"currency": null, "max": null, "min": null, "period": "monthly", "term": null}, "salary_visible": false, "title_keywords": ["operation officer", "manager"], "responsibilities": ["document filing", "aml", "account opening", "regulatory requirements", "data input", "transactions", "testing", "reports", "provide administrative support", "ad-hoc projects"], "requirements": {"degrees": [], "majors": [], "languages": ["cantonese", "english", "mandarin"], "language_level": ["good command"], "hard_skills": ["ms office"], "soft_skills": ["communication skill"], "languages_combined": [{"language": "cantonese", "language_level": ["good command"]}, {"language": "english", "language_level": ["good command"]}, {"language": "mandarin", "language_level": ["good command"]}]}, "experience_required": {"duration": ["2 years"], "field": ["relevant experience", "asset management"]}}, {"job_id": "100003009042335", "location_code": "hk", "company": "Talmud Management Consulting Company", "job_title": "Corporate Partnership Trainee", "description": "Job Highlights\n- Fast-track Promotion Program From Entry to Middle Level\n- Welcome Fresh Graduates candidates\n\nRequirements\n- Degree holder in all discipline\n- Energetic, self-motivated, hard-working and willing to learn\n- Good communication skills and interpersonal skills\n- Experience in sales industry (B2B or B2C) will be an advantage\n- Fluent in Cantonese, English and Mandarin\n\nJob Duties\n\nProvide professional corporate solutions to clients including (but not limited to):\n- Reduce cost of the corporate\n- Increase corporate's reputation in the industry\n- Assist corporate to raise colleagues' loyalty\n- Maintain corporate's sustainability\n\nProvide professional financial advices to employees and private wealth clients including:\n- Wealth Management & Portfolio Advices\n- Risk Management Planning\n- PRC Business & CIES (Capital Investment Entrant Scheme) Planning\n- Quality after-sales services\n\nRecruitment Timeline:\nApplication >>> Short-listing >>> Offer >>> On-Boarding\n\nAll personal data collected will be used for recruitment purpose only and will be treated in accordance with our Personal Data Policy, which is available immediately upon request. All applications will be destroyed after 12 months.\n\n2021 Record (as per 31 Dec 2021)\n100% Retention Ratio\nLowest Fresh Graduate Salary Benchmark - $26,000/month\nLowest Staff Salary Benchmark - 50% increment vs. previous job\n\nWe believe these records would be a critical reason why you should join us.\n\n", "employment_types": ["Full Time", "Permanent"], "selling_points": [], "locations": ["Yau Tsim Mong Area"], "categories": ["Banking / Finance", "Corporate Finance", "Financial Services", "Asset Management"], "post_time": "2022-01-12T07:06:28Z", "salary": {"currency": null, "max": null, "min": null, "period": "monthly", "term": null}, "salary_visible": false, "title_keywords": ["trainee"], "responsibilities": ["cost", "management", "quality", "maintain", "recruitment", "personal data", "listing", "planning"], "requirements": {"degrees": ["degree holder"], "majors": [], "languages": ["cantonese", "english", "mandarin"], "language_level": ["fluent"], "hard_skills": [], "soft_skills": ["communication skills", "self-motivated", "willing to learn", "hard-working", "interpersonal skills", "energetic"], "languages_combined": [{"language": "cantonese", "language_level": ["fluent"]}, {"language": "english", "language_level": ["fluent"]}, {"language": "mandarin", "language_level": ["fluent"]}]}, "experience_required": {"duration": [], "field": []}}, {"job_id": "100003009048128", "location_code": "hk", "company": "AIA International Limited", "job_title": "Management Trainee - Branch Office", "description": "Our wealth management trainee position aims to develop your talents and experience in various functional areas including but not limited to Wealth Management Business Development, Customer Relationships, Retail Client Expansion and Operations Administration.\n\nOutstanding candidates will have the opportunity to join management level and become an independent team leader.\nYou will:\nRealize your talents and fully Unleash your\u00a0potential by working on a diverse range of projects with High-Net-Worth (HNW) customers, bank and retail shop\nSupport by ample guidance \u2013 work directly with senior management executives\nAssist in planning and executing HNW customers\u00a0projects of Premium financing and global investment allocation\nCommunicate with customers to assist in managing relationships and expanding new networks\nAcquire Mainland China / Overseas training opportunities\nQualifications:\nBachelor degree in Economics, Business, Marketing, Finance or any related field\nAt least 1 year working experience\nEnable to deal with multi-tasks and strive in an energetic and fast-paced environment\nPossess an entrepreneurial mindset with an acumen for analyzing and interpreting numbers\nExcellent presentation and communication skills\nMature with good interpersonal skills, detail-minded, self-motivated, dedicated, enthusiastic, out-going and independent\nGood command of written and spoken English and Chinese (Cantonese & Mandarin)\nStrong computer skills including Word, Excel, and PowerPoint, etc\u2026\n\nWe offer competitive remuneration package to the right candidate.\u00a0 For interested candidates, please send your CV by clicking \"Apply\" button", "employment_types": ["Full Time"], "selling_points": ["Attractive Income & Fast track to Management level", "Ability to handle multiple tasks concurrently", "Mature with good interpersonal skills"], "locations": ["Quarry Bay"], "categories": ["Banking / Finance", "Financial Services", "Wealth Management", "Asset Management"], "post_time": "2022-01-14T05:06:57Z", "salary": {"currency": null, "max": null, "min": null, "period": "monthly", "term": null}, "salary_visible": false, "title_keywords": ["management trainee"], "responsibilities": ["communicate with", "guidance", "management", "operations", "develop", "communication", "planning", "executing", "senior management", "administration"], "requirements": {"degrees": ["degree", "bachelor"], "majors": ["business", "finance", "economics", "marketing"], "languages": ["cantonese", "english", "chinese", "mandarin"], "language_level": ["good command"], "hard_skills": ["excel", "word", "powerpoint", "computer skills", "acumen"], "soft_skills": ["detail-minded", "communication skills", "self-motivated", "independent", "multi-tasks", "fast-paced environment", "mature", "diverse", "interpersonal skills", "enthusiastic", "energetic", "presentation"], "languages_combined": [{"language": "cantonese", "language_level": ["good command"]}, {"language": "english", "language_level": ["good command"]}, {"language": "chinese", "language_level": ["good command"]}, {"language": "mandarin", "language_level": ["good command"]}]}, "experience_required": {"duration": ["at least 1 year"], "field": ["management", "business development", "retail", "administration"]}}, {"job_id": "100003009040958", "location_code": "hk", "company": "Pong Yuen Holdings Ltd", "job_title": "Assistant Officer, Accounting & Administration", "description": "Responsibilities\n\nHandle all general accounting and office administrative works;\nPrepare monthly and annual financial and management reports for the management and audit purpose;\nMonitoring cash flow and assist in budgeting;\nAssist in HR & Co Secretary affairs\nHandle any ad hoc projects assigned by the management\nRequirements\n\nDegree holder in Finance, Accounting / Qualification of LCC higher or above\n3+ years' experience in handling the full sets of accounting\nKnowledge in using MYOB accounting software preferably;\nWith strong sense of responsibility and able to meet tight deadline with high accuracy;\nAbility to handle ad-hoc requests;\nProficiency PC skills in Microsoft Word and Excel;\nFluent in Mandarin and good command of\u00a0English;\nImmediate availability is advantage;\u00a0", "employment_types": ["Full Time"], "selling_points": [], "locations": ["Shatin Area"], "categories": ["Accounting", "Accountant", "Admin & HR", "Clerical / Admin Staff", "Banking / Finance", "Asset Management"], "post_time": "2022-01-12T10:07:32Z", "salary": {"currency": null, "max": null, "min": null, "period": "monthly", "term": null}, "salary_visible": false, "title_keywords": ["assistant officer", "accounting"], "responsibilities": ["management", "budgeting", "hr", "monitoring", "audit", "management reports", "cash flow", "ad hoc projects"], "requirements": {"degrees": ["degree holder"], "majors": ["finance", "accounting"], "languages": ["english", "mandarin"], "language_level": ["good command", "fluent"], "hard_skills": ["excel", "microsoft word", "accounting software", "lcc", "pc skills", "myob"], "soft_skills": ["meet tight deadline", "sense of responsibility"], "languages_combined": [{"language": "english", "language_level": ["good command"]}, {"language": "mandarin", "language_level": ["fluent", "good command"]}]}, "experience_required": {"duration": ["3+ years"], "field": ["accounting"]}}, {"job_id": "100003009038605", "location_code": "hk", "company": "Asia Progress Executive Limited", "job_title": "VP, Fund Operation - Assest Management/Private Equity Firm", "description": "Our client is PRC Asset Management Company/Private Equity Firm .\u00a0To cope with the rapid business expansion, they are now inviting high caliber candidates to join the team\n\n\u00a0VP,Fund Operation- Assest Management /Private Equity Firm\n\nResponsibilities:\n\nPrepare and validate daily and monthly NAV\nPrepare and check regular and ad hoc reports\nPerform settlement preparation and validation including but not limited to securities & fixed income, Private Equity & Structured Financing\nPrepare and validate including cash reconciliation, trades matching, holding reconciliation, client deposits / withdrawal instructions, other settlement duties and return calculation etc\nLiaise with executing brokers, prime brokers, custodians, fund administrators and system vendors to resolve trade breaks and/or other relative issues\nWork closely with cross departments such as Investment & Trading, Finance, Compliance, Risk & IT, etc. to ensure operational process is smooth and compliant with internal and external regulation and policy\nReview fund capital activity to ensure it is properly processed and recorded\nReview of client on boarding, and prepare account opening with external counter parties\nAssist team head to perform operation relevant projects including but not limited to workflow enhancement, system flow improvement, external vendors performance review\n\nRequirements:\n\nBachelor degree or above in Finance, Accounting or related discipline\nCFA would be an advantage\nat 5 years or above experience in PE Operation\u00a0 /\u00a0 fund accounting/operations with asset management firm\u00a0\nRelevant experience in PE and/or structure financing is preferred\nProficient in Excel. Microsoft VBA macro skill would be beneficial\nFamiliar with operations of Fund Accounting system\nFluency in written/oral English, Cantonese and Putonghua\nAble to work independently & strong interpersonal skills to deal effectively with internal and\u00a0 external parties\nProactive / can-do approach and attitude; thorough attention to detail and accuracy of delivery\nAble to multi-task, prioritise and meet deadlines and the flexibility to work in a fast changing environment\nStrong problem solving skills with the ability to research issues where the resolution is not readily apparent\nGood teamwork spirit and creative thinking\n\nPlease send full resume with\u00a0present & expected\u00a0salary to expedite sourcing\u00a0in\u00a0MS-WORD\u00a0format by clicking \u201cAPPLY NOW\u201d\nPlease quote our reference in your application\nPersonal data provided by job applicants will be used strictly in accordance with the employer\u2019s personal data policies, a copy of which will be provided upon request\nAll information provided will be used for recruitment purpose only", "employment_types": ["Full Time"], "selling_points": ["Deg 8yr Fund operation in Asset management PRc co", "NAv Calculation, NAV Valuation,PE funds /RQFII", "structure finance,Equities fund& Fixed income fund"], "locations": ["Central & Western Area"], "categories": ["Banking / Finance", "Fund Management", "Order Processing & Operation / Settlement", "Asset Management"], "post_time": "2022-01-11T07:30:26Z", "salary": {"currency": null, "max": null, "min": null, "period": "monthly", "term": null}, "salary_visible": false, "title_keywords": [], "responsibilities": ["prime brokers", "ad hoc", "account opening", "compliance", "review", "reports", "executing", "liaise with"], "requirements": {"degrees": ["degree or above", "bachelor"], "majors": ["finance", "accounting"], "languages": ["cantonese", "putonghua", "english"], "language_level": ["fluency"], "hard_skills": ["vba", "macro", "excel", "ms-word", "cfa", "pe", "accounting system", "problem solving skills"], "soft_skills": ["oral", "work independently", "multi-task", "creative", "prioritise", "problem solving skills", "interpersonal skills", "thorough", "can-do", "attention to detail", "teamwork spirit", "meet deadlines", "proactive"], "languages_combined": [{"language": "cantonese", "language_level": ["fluency"]}, {"language": "putonghua", "language_level": ["fluency"]}, {"language": "english", "language_level": ["fluency"]}]}, "experience_required": {"duration": ["at 5 years"], "field": ["financing", "operation", "relevant experience", "accounting", "asset management"]}}, {"job_id": "100003009035415", "location_code": "hk", "company": "China Tonghai Asset Management Limited", "job_title": "Fund Administrative Officer / Senior Fund Administrative Officer", "description": "Job Responsibilities: \u00a0\n\nResponsible for daily reconciliation of NAV, trade and positions of UCITS and hedge funds\nHandle FX, cash management and trade settlement of investment funds including Cayman and UCITS products\nHandling enquiries related to trade & settlement, corporate action\nEnsure timely delivery and upload of trade and position reports to custodians\nCalculation and reconciliation of fee payment to investment manager and distributors\nLiaise with internal parties for operations related reports\nHandle enquiries from auditors in preparing for financial statements of UCITS and Cayman funds\nHandling enquiries from clients in relations to operational related issues and in particularly the account opening of UCITS and Cayman products as well as FATCA and CRS reporting requirements\n\nJob Requirements:\n\nBachelor degree in Accounting, Finance or relevant discipline\nMinimum 2 \u2013 5 years of experience in fund administration or fund accounting and operation experiences\nGood knowledge in fund administration and accounting of UCITS and / or hedge Fund\nProficient in Microsoft Office, MS Excel. Good knowledge on Bloomberg usage would be an added advantage\nProficiency in both written and spoken in English, Cantonese and Mandarin\nGood communication skills and team player\nCandidates with more experience and qualifications will be considered as Senior Fund Administration Officer\nImmediate available is an advantage\u00a0\n\nWe offer attractive salary, benefits and 5-day workweek to the successful applicant.\u00a0 Please send your resume with\u00a0present\u00a0and\u00a0expected salary\u00a0to the Group Human Resources Manager. (Please quote the job reference number on the email subject line.)\u00a0\n\nPersonal Data collected will be used for recruitment purposes only.", "employment_types": ["Full Time", "Permanent"], "selling_points": ["5 days work week at Central", "Education allowance, medial, dental and insurance", "Asset Management"], "locations": ["Central"], "categories": ["Banking / Finance", "Fund Management", "Order Processing & Operation / Settlement", "Asset Management"], "post_time": "2022-01-10T07:04:29Z", "salary": {"currency": null, "max": null, "min": null, "period": "monthly", "term": null}, "salary_visible": false, "title_keywords": ["administrative officer"], "responsibilities": ["reporting", "management", "operations", "account opening", "financial statements", "handle enquiries", "payment", "reports", "liaise with", "internal parties"], "requirements": {"degrees": ["degree", "bachelor"], "majors": ["finance", "accounting"], "languages": ["cantonese", "english", "mandarin"], "language_level": ["proficiency"], "hard_skills": ["ms excel", "bloomberg", "microsoft office"], "soft_skills": ["communication skills", "team player"], "languages_combined": [{"language": "cantonese", "language_level": ["proficiency"]}, {"language": "english", "language_level": ["proficiency"]}, {"language": "mandarin", "language_level": ["proficiency"]}]}, "experience_required": {"duration": ["5 years"], "field": ["operation", "accounting", "administration"]}}, {"job_id": "100003009044591", "location_code": "hk", "company": "Future Leader Recruitment Agency", "job_title": "Investment Consultant Trainee (Graduates are welcome, 20K+)", "description": "Comprehensive Trainee Program for graduates\nPromising career path\nCompetitive compensation and benefit package\n\n\nJob Description\n\nOur client is one of the major financial institution in Asia. They are young, energetic and innovative, that nurture many youngsters to be part of their management team. Now they offer highly professional trainee program to\u00a0caliber candidates:\n\nTraining program:\n\nStructured and comprehensive training to build the professional base on finance and investment market knowledge and strategies\nExtensive initial training covering\u00a0professional and comprehensive\u00a0soft skills consulting, negotiation, presentation and communication\u00a0 \u00a0\nWeekly mentor-ship training sessions hold\u00a0by experienced Managers of firm\u00a0\nRotation of job duties in order to acquire experience in management and leadership\n\nJob responsibilities:\n\nTrained to be able to provide investment advice for clients, especially high net worth asset clients, manage their account and improve their investment return\n\nAssist senior managers in presenting investment portfolio and market outlook to clients\n\nWork as a team to organize business development events, such as, investment seminars, marketing events and road shows regarding investment\n\nDevelop your own client servicing skills, and make use of your professional knowledge to maintain a good relationship with clients\n\nDevelop your interpersonal skills and management skills to be a part of the management team in the later stage of your career\n\nRequirements:\n\nUniversity graduate\u00a0in any discipline\nMainland China\u00a0Fresh graduates with IANG visa are welcome\nProficiency in Chinese and English\nProactive to learn\nExcellent interpersonal, communications and presentation skills\nAggressive, self-motivated, customer orientation\u00a0\u00a0\n\nInterested parties please\u00a0click\u00a0Apply Now\n\nPlease note: Short listed candidates will be notified within eight (8) weeks of the date of this advertisement. All personal data collected will be kept confidential and used for recruitment purposes only.\n\n\n\n", "employment_types": ["Full Time", "Permanent"], "selling_points": ["Comprehensive Trainee Program for graduates", "Promising career path", "Promising career path"], "locations": ["Causeway Bay"], "categories": ["Others", "Student / Fresh Graduate / No Experience", "Management", "Management Trainee", "Banking / Finance", "Asset Management"], "post_time": "2022-01-13T04:42:26Z", "salary": {"currency": null, "max": null, "min": null, "period": "monthly", "term": null}, "salary_visible": false, "title_keywords": ["investment consultant trainee"], "responsibilities": ["management team", "management", "marketing events", "consulting", "develop", "communication", "good relationship", "maintain"], "requirements": {"degrees": ["university graduate"], "majors": [], "languages": ["english", "chinese"], "language_level": ["proficiency"], "hard_skills": [], "soft_skills": ["presentation skills", "proactive", "interpersonal", "self-motivated"], "languages_combined": [{"language": "english", "language_level": ["proficiency"]}, {"language": "chinese", "language_level": ["proficiency"]}]}, "experience_required": {"duration": [], "field": []}}, {"job_id": "100003009039211", "location_code": "hk", "company": "", "job_title": "Investment Manager/Director", "description": "A listed company principally engaged in principal investment business, financial services business, money lending business and real property business. Through respective subsidiaries, company also have obtained type 1, 2, 4, 5, 6, 9 regulated activities under the Securities and Futures Ordinance. Our SFC full license financial institution is now looking for the a professional talent to be part of our professional team.\nThe job:\n\nDevelop the investment and asset management business\nSource new sales opportunities and generate revenue\nExpand the client network and bring in new client with AUM\nIdentify the investment opportunities to gain excellent return\nFormulate relevant investment strategies to achieve sales target\n\nRequirements:\nDegree in business, finance or accountancy or above related academic qualifications\n3 years\u2019 relevant experience in asset management / investment in Hong Kong\nHolder of SFC responsible officer/ representative type 9\nCompetent and capable in business development and can generate revenue independently\nFlexible, proactive, tactful and analytical mindset\nGood command of written and spoken English and Chinese\n\nWe offer competitive remuneration package and excellent career prospect to the right candidate. You may contact us at 5349 2418 for company details.", "employment_types": ["Full Time", "Permanent"], "selling_points": [], "locations": ["Wan Chai Area"], "categories": ["Banking / Finance", "Investment", "Financial Services", "Asset Management"], "post_time": "2022-01-11T09:01:52Z", "salary": {"currency": null, "max": null, "min": null, "period": "monthly", "term": null}, "salary_visible": false, "title_keywords": ["investment manager", "director"], "responsibilities": ["investment strategies", "sales target", "asset management", "develop"], "requirements": {"degrees": ["degree"], "majors": ["finance", "business", "accountancy"], "languages": ["english", "chinese"], "language_level": ["good command"], "hard_skills": [], "soft_skills": ["flexible", "independently", "capable", "responsible", "competent", "proactive", "tactful"], "languages_combined": [{"language": "english", "language_level": ["good command"]}, {"language": "chinese", "language_level": ["good command"]}]}, "experience_required": {"duration": ["3 years"], "field": ["relevant experience", "investment", "asset management"]}}, {"job_id": "100003009043681", "location_code": "hk", "company": "Bank of China (Hong Kong) Limited", "job_title": "Contract (AMC Admin Team)", "description": "Responsibilities\n\nProvide daily Administration and Clerical support\n\nProvide Accounting assistance to the team\n\nPerform other duties as assigned by supervisors\n\n\u00a0Requirements\n\nHKCEE / HKDSE graduates or above\n\nWilling to learn, independent, detail-oriented and strong sense of responsibility\n\nGood command of PC software including\u00a0 Microsoft Office Word, Excel and Powerpoint\n\nGood command of spoken and written English and Chinese\n\nImmediate available is highly preferred", "employment_types": ["Contract"], "selling_points": ["AMC", "Admin", "Contract"], "locations": ["Others"], "categories": ["Banking / Finance", "Asset Management"], "post_time": "2022-01-13T01:27:57Z", "salary": {"currency": null, "max": null, "min": null, "period": "monthly", "term": null}, "salary_visible": false, "title_keywords": ["admin"], "responsibilities": ["perform other duties", "clerical support", "administration"], "requirements": {"degrees": ["hkdse"], "majors": [], "languages": ["english", "chinese"], "language_level": ["good command"], "hard_skills": ["excel", "microsoft office", "word", "powerpoint", "pc"], "soft_skills": ["independent", "sense of responsibility", "willing to learn", "detail-oriented"], "languages_combined": [{"language": "english", "language_level": ["good command"]}, {"language": "chinese", "language_level": ["good command"]}]}, "experience_required": {"duration": [], "field": []}}, {"job_id": "100003009038197", "location_code": "hk", "company": "Noah International (Hong Kong) Limited", "job_title": "Operations Specialist, Investment Operations (Asset Management\uff09", "description": "Scope of Responsibilities:\n\n\nResponsible for fund operations, including managing board meeting minutes, investor notices, payment applications, KYC and bank account maintenance;\nManage internal and external key stakeholders; fund administrators, nominee agents, legal counsel and compliance and other related parties;\nCoordinate work with product managers, fund managers, legal consultants, accountants and other relevant units;\nResponsible to perform fund operations / accounting and administrative works related to all funds\nAd hoc tasks as required.\n\nSkills & Qualifications:\n\n\nDegree holder in BBA or related areas;\n1 year experience in Investment Management, Fund Operations, Accounting or Banking;\nExposure in operations and all rounded middle-to-back office support duties is preferred;\nGood command of the use of Excel, Word, PowerPoint and operation systems;\nExcellent verbal and written communication skills \u2013 Mandarin and English;\nTeam player and strong ability to multi-tasks;\nIndependent, attentive to details, self-motivated, keen to learn, ability to adapt new challenges/changes;\n\nWe offer:\n\nCompetitive\u00a0package + year-end bonus + insurance benefit\nFull range of professional training program\nBright\u00a0career path to every\u00a0successful candidate\nCompany sponsors selected professional qualification\n\nIf you are ready to challenge yourself in a performance-driven and dynamic culture that recognizes and rewards talent, we would like to meet you. We are an equal opportunity employer. Our application process is completely secure and confidential. When you submit your credentials, we will review your application, examine your qualifications. We will contact you to pursue a conversation if your background and skills align with our firm\u2019s needs.\n\n***Please provide your current and expected salary, thank you.", "employment_types": ["Full Time", "Permanent"], "selling_points": ["Discretionary bonus & Medical insurance", "Knowledge of Fund of Funds and Private Equity", "1 year experience"], "locations": ["Causeway Bay"], "categories": ["Banking / Finance", "Order Processing & Operation / Settlement", "Wealth Management", "Asset Management"], "post_time": "2022-01-11T06:00:56Z", "salary": {"currency": null, "max": null, "min": null, "period": "monthly", "term": null}, "salary_visible": false, "title_keywords": ["specialist", "operations", "asset management"], "responsibilities": ["management", "operations", "compliance", "ad hoc tasks", "banking", "back office", "systems", "coordinate", "communication", "payment", "kyc", "account maintenance"], "requirements": {"degrees": ["degree holder"], "majors": ["bba"], "languages": ["english", "mandarin"], "language_level": ["excellent"], "hard_skills": ["excel", "maintenance", "word", "powerpoint", "kyc"], "soft_skills": ["communication skills", "self-motivated", "independent", "multi-tasks", "responsible", "attentive to details", "keen", "team player"], "languages_combined": [{"language": "english", "language_level": ["excellent"]}, {"language": "mandarin", "language_level": ["excellent"]}]}, "experience_required": {"duration": ["1 year"], "field": ["management", "accounting", "investment", "banking"]}}, {"job_id": "100003009035128", "location_code": "hk", "company": "China CITIC Bank International Limited", "job_title": "(Contract) Associate, Risk Management (Asset Management)", "description": "Key Responsibilities\n\nAssist the Risk Management team to handle daily fund operations and risk monitoring\nAssist in developing and maintaining risk models covering all trading businesses across the Company, providing exposure to a wide range of businesses, products and asset classes globally (focus on market risk, credit risk and liquidity risk)\nAssist in monitoring the limit of each trade and escalate the incidents if necessary\nAssist in facilitating internal control and ensure the process/ deliverable are in compliance with the local regulatory requirements\nConduct statistical analysis\nPrepare periodic risk reports to the internal stakeholders\n\nRequirements\n\n\nUniversity degree holder or above in Business Administration, Risk Management or related disciplines\nMinimum 2 years\u2019 of working experience in fund operations and risk management in asset management company is preferred\nUnderstand industry and market developments relating to market risk, liquidity risk, credit risk, model validation and/or fair value\nUnderstand the features and benefits of asset management e.g. fixed income, funds etc.\nSound knowledge in statistical and quantitative analysis and familiar with VBA\nStrong analytical skills, self-motivated with high degree of initiatives\nGood interpersonal and communication skills\nGood command of written and spoken English and Chinese (including Putonghua)\n\nFor more details about career opportunities with the Bank, please visit our website\u00a0http://www.cncbinternational.com/careers/en/index.jsp.\u00a0; Please apply with full resume stating current and expected salaries.\n\nPersonal data collected will be used for recruitment related purposes only. Applicants not invited for interview within 6 weeks may consider their applications unsuccessful. However, applicants may be considered for other suitable positions within the Group for a period of not more than 2 years. Personal data will be destroyed at any time after 3 months.\n\nChina CITIC Bank International is committed to being an equal opportunities employer and intends to provide a work environment free of unlawful discrimination or harassment.\u00a0 All employment decisions will be made in a non-discriminatory manner.", "employment_types": ["Full Time", "Temporary", "Contract"], "selling_points": ["Assist the Risk Management team", "Assist in developing and maintaining risk models", "Assist in monitoring the limit of each trade"], "locations": ["Tsim Sha Tsui"], "categories": ["Banking / Finance", "Others", "Risk Management", "Asset Management"], "post_time": "2022-01-10T06:06:29Z", "salary": {"currency": null, "max": null, "min": null, "period": "monthly", "term": null}, "salary_visible": false, "title_keywords": ["associate", "asset management"], "responsibilities": ["management team", "maintaining", "operations", "regulatory requirements", "monitoring", "compliance", "developing", "analysis", "risk monitoring", "reports", "internal control"], "requirements": {"degrees": ["university degree"], "majors": ["related disciplines", "risk management", "business administration"], "languages": [], "language_level": [], "hard_skills": [], "soft_skills": [], "languages_combined": []}, "experience_required": {"duration": ["minimum 2 years"], "field": ["risk management", "asset management"]}}, {"job_id": "100003009043750", "location_code": "hk", "company": "Aston Carter", "job_title": "Business Analyst - Regional Transformation Programme - MNC", "description": "Looking for your next big project to work on?\u00a0 Join us - a top tier multinational Investments company, great exposure towards working on regional projects. Open to candidates with less experience but with great attitude to develop more as a Business Analyst.\n\nResponsibilities:\n\nLead the requirements gathering/definition sessions to clarify functionality requirements and ensure that any solution can be supported\nPrepare relevant documentation to capture the user requirements\u00a0\nDraft user stories\u00a0\nWork with IT teams\u00a0\nParticipate in daily Agile activities\n\nRequirements\n\n1-2 years of experience in Business Analysis\nFinancial Services experience is a MUST\u00a0\nGood understanding of investment products\u00a0\nGood communication skills in English and Cantonese", "employment_types": ["Full Time"], "selling_points": ["Business Analyst", "Investment Products", "Regional Project"], "locations": ["Kwun Tong Area"], "categories": ["Banking / Finance", "Asset Management"], "post_time": "2022-01-13T01:48:58Z", "salary": {"currency": null, "max": null, "min": null, "period": "monthly", "term": null}, "salary_visible": false, "title_keywords": ["business analyst"], "responsibilities": ["documentation", "teams"], "requirements": {"degrees": [], "majors": [], "languages": ["cantonese", "english"], "language_level": ["good"], "hard_skills": ["analysis", "investment products"], "soft_skills": ["communication skills"], "languages_combined": [{"language": "cantonese", "language_level": ["good"]}, {"language": "english", "language_level": ["good"]}]}, "experience_required": {"duration": ["1-2 years"], "field": ["business analysis", "financial services"]}}, {"job_id": "100003009046451", "location_code": "hk", "company": "Ambition", "job_title": "Quant Developer", "description": "Responsibilities\n\nDesign, build and maintain high performance, high availability and high scalability platform and tools for:\n\n\n\nAutomatic execution of proprietary trading orders\nTrading signals generation and notification\nTrading data visualisation\nMarket-making platform enhancement\nDevelop portfolio optimisation models and systematic investment strategies\nDesign, develop, and deploy elegant software solutions across research, alpha & signal generation, systematic and non-systematic trading\nBuild automated ETL pipelines to support rapid but controlled transition from research to live trading\nSupport the team in operations workflow\n\nJob Requirements\n\n\n\nBachelor's, Master's or PhD degree in Computer Science, Mathematics, Statistics, or equivalent field\nPrevious experience in blockchain / cryptos are preferred but not required\nProficiency with one or more programming languages (e.g. C++, Python, or Java)\nHands-on experience analysing complex data and building statistical models\nGood knowledge of data-structures and algorithms\nGood command in spoken and written English and Chinese\n\nReach out to Louis Hui (Louis.Hui@Ambition.com.hk) if you are interested.\n\n\n\nIf this job isn't quite right for you, but you know someone who would be great at this role, why not take advantage of our referral scheme? We offer HKD1000 in Apple gift cards for every referred candidate who we place in a role. Terms & Conditions Apply. https://www.ambition.com.hk/refer-a-friend", "employment_types": ["Full Time", "Permanent"], "selling_points": ["Hedge Fund - Digital Assets", "Algorithm Trading", "Python / C++ / C# / Java"], "locations": ["Not Specified"], "categories": ["Information Technology (IT)", "Software Development", "Banking / Finance", "Asset Management", "Data Scientist"], "post_time": "2022-01-13T11:17:53Z", "salary": {"currency": "HKD", "max": null, "min": 70000, "period": "monthly", "term": null}, "salary_visible": true, "title_keywords": ["developer"], "responsibilities": ["investment strategies", "software", "data", "operations", "design", "develop", "maintain", "deploy", "support the team"], "requirements": {"degrees": ["degree", "bachelor", "master"], "majors": ["mathematics", "statistics", "computer science"], "languages": ["english", "chinese"], "language_level": ["good command"], "hard_skills": ["blockchain", "java", "c++", "scheme", "programming", "python"], "soft_skills": ["hands-on"], "languages_combined": [{"language": "english", "language_level": ["good command"]}, {"language": "chinese", "language_level": ["good command"]}]}, "experience_required": {"duration": [], "field": []}}, {"job_id": "100003009029604", "location_code": "hk", "company": "Michael Page", "job_title": "Investment Research Analyst - Crypto", "description": "This role will work closely with senior management team to conduct digital asset market research for investment purpose.\n\nClient Details\n\nOur client is a family office with heavy investments on digital asset world. To expand their business, they are currently seeking a research analyst to focus on digital asset investment research.\n\nDescription\n\nConduct research for various relevant aspects of digital asset industry\nLead diligence and investment execution for investments (funds, early stage and liquid tokens, venture equity, staking/yield farming)\nPerform data analysis, visualization, econometric studies etc.\nWork across teams to help manage and build content calendars\n\nProfile\n\nBachelor's degree in any discipline. Master's and PhD are highly welcome\n3+ years of experience in IBD, buyside firms, or crypto research firms, ideally as an analyst, strategist, or specialist.\nPassionate about digital assets, with curiosity to deep dive into its technology and industry with 3+ years of experience in digital assets world (can be as a personal pursuit)\nExceptional critical thinking skills and analytical skills\nFluency in English and Chinese is a must\n\nJob Offer\n\ncompetitive salary package\n\nTo apply online please click the 'Apply' button below. For a confidential discussion about this role please contact Chris Yang on +852 2848 4716", "employment_types": ["Full Time", "Permanent"], "selling_points": ["Family Office", "Investment research for digital assets/crypto", "Fluency in English is a must"], "locations": ["Central & Western Area"], "categories": ["Banking / Finance", "Investment", "Fund Management", "Asset Management"], "post_time": "2022-01-07T05:38:41Z", "salary": {"currency": null, "max": null, "min": null, "period": "monthly", "term": null}, "salary_visible": false, "title_keywords": ["research analyst"], "responsibilities": ["visualization", "teams", "market research", "data analysis", "contact", "senior management", "conduct research"], "requirements": {"degrees": ["degree", "bachelor", "master"], "majors": [], "languages": ["english", "chinese"], "language_level": ["fluency"], "hard_skills": ["focus", "analysis", "crypto", "analytical skills"], "soft_skills": ["focus", "deep", "passionate about", "analytical skills"], "languages_combined": [{"language": "english", "language_level": ["fluency"]}, {"language": "chinese", "language_level": ["fluency"]}]}, "experience_required": {"duration": ["3+ years"], "field": ["digital", "research"]}}, {"job_id": "100003009049939", "location_code": "hk", "company": "Amethyst Asia Partners Pte. Ltd.", "job_title": "Private Equity Fund Accountant", "description": "Our client is an International fund accounting and administration service provider to private equity and real estate funds. They emphasize on career growth and invests in employees with training. Due to business expansion, they are looking for Fund Accountant and the role is based in Hong Kong.\n\nKey responsibilities:\n\nWork closely with other team members to support the financial statements preparation and other reports\nCompiling and analysis of financial information underlying the financial statements, including the treatment of business transactions\nPrepared fund correspondence and notices, ensure permanent files are adequately maintained for new and existing clients\nSupport the team and clients on other reports such as fund correspondence and notices etc\nRecord transactions such as bookkeeping of invoices, bank reconciliations, fund transactions analysis etc\nLiaise with clients to request accounting documents and enquiries\n\nKey requirements\n\n2-5 years of accounting experience.\u00a0 Open for candidates coming from corporate accounting or audit background\nAccounting degree or qualification from a recognized professional accounting body\nDiligent, self-motivated and positive attitude\nExcellent communication skills in English", "employment_types": ["Full Time"], "selling_points": ["International firm with strong track record", "One of the market leaders in the industry", "Good career development"], "locations": ["Central"], "categories": ["Accounting", "Accountant", "Banking / Finance", "Fund Management", "Asset Management"], "post_time": "2022-01-14T09:27:59Z", "salary": {"currency": null, "max": null, "min": null, "period": "monthly", "term": null}, "salary_visible": false, "title_keywords": ["accountant"], "responsibilities": ["liaise with clients", "invoices", "analysis", "bank reconciliations", "transactions", "financial statements", "reports", "support the team"], "requirements": {"degrees": ["degree"], "majors": ["accounting"], "languages": ["english"], "language_level": ["excellent"], "hard_skills": [], "soft_skills": ["positive attitude", "communication skills", "self-motivated", "diligent"], "languages_combined": [{"language": "english", "language_level": ["excellent"]}]}, "experience_required": {"duration": ["2-5 years"], "field": ["accounting experience"]}}, {"job_id": "100003009046178", "location_code": "hk", "company": "Wellesley Associates Limited", "job_title": "Investment Advisor-Primer Banking", "description": "My client is a prominent bank with robust commercial activities and expansion especially in Asian region. With undoubted commitment in the business, they are currently looking to hire a senior professional to join them.\n\nResponsibilities:\n\nGive advice on portfolio issues and meet clients on\u00a0a regular basis.\nRecommend tailor-made, individually-optimized, investment portfolio for clients\nMonitor and oversee portfolio quality\nMonitor portfolio performance of the business as a whole\nProvide training to internal staff on portfolio-related matters\nGive regular presentation to clients\n\u00a0\n\nQualifications:\n\n5+ years of experience working as relationship manager, portfolio counselor, fund manager, financial advisor, etc\nPreferably a CFA holder\nStrong communication and interpersonal skills\nSound knowledge of investment products\nProficiency in both English, Cantonese, Mandarin would be an advantage\n\nIf you're interested in this role, forward an up-to-date copy of your CV via email, or call directly on +852 2847 9962. If this job isn't quite right for you but you are opened for a new position within banking / wealth management side, please contact me for a confidential discussion on your career.", "employment_types": ["Full Time", "Permanent"], "selling_points": ["Join a team with great dynamics", "Attractive compensation package", "Strong support from management"], "locations": ["Not Specified"], "categories": ["Banking / Finance", "Retail Banking", "Wealth Management", "Asset Management"], "post_time": "2022-01-13T09:51:38Z", "salary": {"currency": null, "max": null, "min": null, "period": "monthly", "term": null}, "salary_visible": false, "title_keywords": ["advisor"], "responsibilities": ["provide training", "management", "quality", "monitor", "communication", "contact", "banking"], "requirements": {"degrees": [], "majors": [], "languages": ["cantonese", "english", "mandarin"], "language_level": ["advantage", "proficiency"], "hard_skills": ["cfa", "investment products"], "soft_skills": ["interested in", "communication and interpersonal skills", "presentation", "robust"], "languages_combined": [{"language": "cantonese", "language_level": ["proficiency"]}, {"language": "english", "language_level": ["proficiency"]}, {"language": "mandarin", "language_level": ["advantage", "proficiency"]}]}, "experience_required": {"duration": ["5+ years"], "field": ["financial"]}}, {"job_id": "100003009044842", "location_code": "hk", "company": "HSBC Group", "job_title": "Senior Mortgage Service Officer - Wealth & Personal Banking", "description": "The health and safety of our employees and candidates is very important to us. Due to the current situation related to the Novel Coronavirus (2019-nCoV), we\u2019re leveraging our digital capabilities to ensure we can continue to recruit top talent at HSBC. \u00a0As your application progresses, you may be asked to use one of our digital tools to help you through your recruitment journey.\u00a0\u00a0If so, one of our Resourcing colleagues will explain how our video-interviewing technology will be used throughout the recruitment process and will be on hand to answer any questions you might have.\n\nSome careers have more impact than others.\n\nIf you\u2019re looking for a career where you can make a real impression, join HSBC and discover how valued you\u2019ll be. Whether you want a career that could take you to the top, or simply take you in an exciting new direction, HSBC offers opportunities, support and rewards that will take you further.\n\nSales, Distribution and Business Development plays a vital role in understanding and meeting customer needs by offering the right solutions through the right channels to the right customer segments.\u00a0 The team is responsible for implementing distribution strategy, driving the delivery of market leading personal banking customer experiences and thereby maximising customer satisfaction.\n\nWe are currently seeking a high calibre professional to join our team as a Senior Mortgage Service Officer.\n\nPrincipal Responsibilities\n\nImpact on the Business/Function\n\nGrow the Bank\u2019s mortgage lending business by supporting the end-to-end mortgage process and application referred by branch and mortgage outreach sales team\nProvide privilege mortgage solutions and services to customer. Identify customer other banking needs such as protection, financial and follow through mortgage application journey\nCommunicate closely and timely with frontline on mortgage approval result and counter offer to secure the mortgage drawdown and raise Bank\u2019s mortgage penetration\nLiaise with internal and external department to ensure mortgage documents are in compliance with the Bank\u2019s policies, guidelines and regulatory requirements as well as service standards\nEnsure proper execution of mortgage documents and fulfilment of loan conditions before drawdown\nEstablish effective working relationships with different teams within the Branch and build a positive team culture, through ensuring quality business referrals and referral skills among team members\nCollaborate with outreach mortgage sales team during on-site activities and provide instant support to them\nProvide feedback and support of current application and approval process for streamlining opportunities to enhance work efficiency and customer experience in sales journey\n\nCustomers / Stakeholders\n\nDeliver privilege customer experience and act as fulfilment expertise to handle the mortgage applications\nCollaborate with Branch Managers and team leaders to ensure quality mortgage application, excellent service delivery, uplift application to drawdown conversion rate and minimize number of pending cases\nConsolidate feedback from branch staff and customer on process streamlining so to reduce unnecessary back and forth procedure, simplify workflow and enhance customer experience\nProvide professional mortgage advice to both internal and external stakeholders\nWork closely with other stakeholders \u2013 MLU, solicitor, frontline etc. to ensure smooth operations and excellent customer experience delivery\nMeet the standard lead time of each case assigned\n\nLeadership & Teamwork\n\nCollaborate with various branch streams and outreach sales teams to fulfill customers\u2019 property and financial needs with the Bank and uplift the application to drawdown ratio\nShare best practices among mortgage team, so as to contribute value to team and deliver superb customer service\nDemonstrates professionalism and confidence\nMaintain best place to bank principles through coaching and training\n\nOperational Effectiveness & Control\n\nKeep abreast with present and forthcoming regulatory requirements\nKnowledge of Group compliance, Operational Risk and other control guidelines for RBWM\nMaintain HSBC internal control standards\nContinually review work practices to improve productivity, whilst identifying activity that compromises ability to spend time with individuals or your team\n\nRequirements\n\nMinimum 3 years\u2019 retail banking experience with at least 2 years\u2019 in mortgage related position\nKnowledgeable in Mortgage products and credit guidelines\nAble to work independently and at the same time can collaborate well with team and staff from frontline and internal department\nGood communication, interpersonal and analytical skills\nGreat sense of responsibility and servicing mind-set to ensure efficient and quality customer service processes\n\nYou\u2019ll achieve more when you join HSBC.\u00a0\nhttp://www.hsbc.com/careers\n\nHSBC is committed to building a culture where all employees are valued, respected and opinions count. We take pride in providing a workplace that fosters continuous professional development, flexible working and opportunities to grow within an inclusive and diverse environment. Personal data held by the Bank relating to employment applications will be used in accordance with our Privacy Statement, which is available on our website.\n\nIssued by The Hongkong and Shanghai Banking Corporation Limited.", "employment_types": ["Full Time"], "selling_points": ["Impact on the Business/Function", "Customers / Stakeholders", "Operational Effectiveness & Control"], "locations": ["Kowloon City"], "categories": ["Media & Advertising", "Account Servicing", "Banking / Finance", "Asset Management"], "post_time": "2022-01-13T06:26:53Z", "salary": {"currency": null, "max": null, "min": null, "period": "monthly", "term": null}, "salary_visible": false, "title_keywords": ["officer", "personal"], "responsibilities": ["collaborate with", "site activities", "regulatory requirements", "quality", "service standards", "customer service", "maintain", "liaise with", "internal control", "service delivery", "control", "compliance", "teams", "banking", "review", "ensure smooth operations", "bank\u2019s policies", "guidelines", "sales team", "working relationships"], "requirements": {"degrees": [], "majors": [], "languages": [], "language_level": [], "hard_skills": ["analytical skills"], "soft_skills": ["efficient", "flexible", "work independently", "sense of responsibility", "analytical skills", "communication", "committed", "diverse", "customer service", "interpersonal"], "languages_combined": []}, "experience_required": {"duration": ["at least 2 years", "minimum 3 years"], "field": ["related", "retail banking"]}}, {"job_id": "100003009035712", "location_code": "hk", "company": "Superb Talent Limited", "job_title": "Fund Accountant", "description": "Client Description\n\nOur client, a Hong Kong SFC licensed asset management advisory company (Type 4, 9 license). It helps to manage several hedge funds, from equity, commodity to multi-strategies. The company is now inviting an energetic person to join their growing team.\n\nKey Responsibilities\nTo compile daily operation work, such as cash & security holding reconciliation\nResponsible for the settlement for clients and fund transactions\nCalculation and ensure accurate of NAV, including monthly expenses accrual, preparation of month-end balance sheet reconciliations and to conduct valuation analysis\nResponsible to prepare cash forecast report cash, fund valuation reports & FRR to SFC\nTo ensure compliance with all the relevant external regulations and internal codes and policies to regulated activities type 9 under HKSFC\nLiaise with fund administrators, custodians and prime broker on a daily basic\nParticipate in new fund launch\n\nThe ideal candidate should process the following qualities:\n\nDegree holder in Finance or related disciplines\nMinimum 3-5 years direct compliance working experience\nIn-depth knowledge of HKSFC regulations\nFamiliar with products and operations of fund management\nGood command of written and spoken English and Cantonese\n\nInterested parties please send your resume together with present and expected salary (quoting ref. STL/2022/1001/JD) by e-mail to us.\n\nShortlisted candidates will be invited to attend an interview within one month. Data collected will be used by Superb Talent Limited and its associates for recruitment purpose only.\n\n", "employment_types": ["Full Time"], "selling_points": ["5-day Fund Accountant", "New fund set up", "All rounded Fund Accouting exposure"], "locations": ["Central"], "categories": ["Accounting", "Accountant", "Banking / Finance", "Asset Management"], "post_time": "2022-01-10T08:14:43Z", "salary": {"currency": null, "max": null, "min": null, "period": "monthly", "term": null}, "salary_visible": false, "title_keywords": ["accountant"], "responsibilities": ["regulations", "operations", "transactions", "liaise with", "expenses", "compliance", "month-end", "reports", "forecast", "balance sheet", "report", "valuation", "management", "reconciliations", "accrual", "policies", "analysis", "daily operation", "ensure compliance", "asset management"], "requirements": {"degrees": ["degree holder"], "majors": ["related disciplines", "finance"], "languages": ["cantonese", "english"], "language_level": ["good command"], "hard_skills": ["basic", "analysis", "frr", "hksfc", "codes"], "soft_skills": ["energetic", "accurate", "responsible", "ideal"], "languages_combined": [{"language": "cantonese", "language_level": ["good command"]}, {"language": "english", "language_level": ["good command"]}]}, "experience_required": {"duration": ["minimum 3-5 years"], "field": ["compliance"]}}, {"job_id": "100003009040068", "location_code": "hk", "company": "The Bank of East Asia, Limited", "job_title": "Risk Manager (Product Control & Reporting Section)", "description": "Risk Manager (Product Control & Reporting Section) (Job ID: 3373)\n\nResponsibilities\n\nTo be a team member of Product Control & Reporting Section of Asset & Liability Management Department\nTo conduct price verification on financial products\nTo conduct profit & loss analyses / attribution on financial products\nTo be responsible for the assessment of the valuation adjustment, off-market rate checking\nTo participate in various projects on financial products\nTo assist in system maintenance / implementation\n\nRequirements\n\nUniversity graduate in Risk Management, Statistics, Economics, Quantitative Analysis, Finance, Accounting\nProficiency in VBA, SQL related analytic tools\nKnowledge in the banking industry and financial product analytical skill is preferred\nPro-active and mature\nGood attention to details, able to work under pressure and independently\nExcellent command of both spoken and written English and Chinese, Putonghua preferable\n\nPlease apply online via the BEA Careers website at https://careers.hkbea.com/psp/hcmprd/EMPLOYEE/HRMS/c/HRS_HRAM.HRS_APP_SCHJOB.GBL?Page=HRS_APP_JBPST&Action=U&FOCUS=Applicant&SiteId=1&JobOpeningId=3373&PostingSeq=1 or by clicking the Apply Now button. Kindly note that if you are a new user, you have to first create your User Profile before you can apply.\n\nPersonal data provided by job applicants will be used for recruitment purposes only and will be treated in accordance with the Bank's Personal Data Policy, which is available upon request. Applicants who are not invited for interviews within six weeks may consider their applications unsuccessful and the personal data collected will be destroyed after six months.", "employment_types": ["Full Time", "Permanent"], "selling_points": ["Conduct price verification on financial products", "Conduct profit & loss analyses/attribution", "Assess valuation adjustment"], "locations": ["Kwun Tong"], "categories": ["Banking / Finance", "Others", "Risk Management", "Asset Management"], "post_time": "2022-01-12T01:17:46Z", "salary": {"currency": null, "max": null, "min": null, "period": null, "term": null}, "salary_visible": false, "title_keywords": ["manager"], "responsibilities": ["reporting", "control", "valuation", "management", "maintenance", "checking", "implementation"], "requirements": {"degrees": ["university graduate"], "majors": ["risk management", "finance", "economics", "statistics", "accounting"], "languages": ["putonghua", "english", "chinese"], "language_level": ["excellent"], "hard_skills": ["vba", "analytical skill", "analysis", "sql", "c"], "soft_skills": ["analytical skill", "independently", "mature", "attention to details", "pro-active", "work under pressure"], "languages_combined": [{"language": "putonghua", "language_level": ["excellent"]}, {"language": "english", "language_level": ["excellent"]}, {"language": "chinese", "language_level": ["excellent"]}]}, "experience_required": {"duration": [], "field": []}}, {"job_id": "100003009036172", "location_code": "hk", "company": "Amber Hill Holdings Limited", "job_title": "Fund Operation Manager", "description": "Amber Hill Group is an asset management institution based on financial science and technology. We aimed to provide intelligent and scientific asset management services for high-net-worth customers around the world and determined to become the world's well-known and integrated financial services group.\n\nWe are currently looking for talent to join our team as Fund Operation Manager.\n\nAs a Fund Operation Manager, you will:-\n\nChecking hedge fund valuations prepared by the external fund administrator\nAccurately prepare trade tickets and keep track of trade settlements\nProcess and review subscriptions, redemptions, and anti-money laundering application\nHandle month-end closing, vouchers, and office administration for the licensed corporation\nResponsible for routine operation and related secretarial work\nAssist accounts opening for client, brokerage, and banking services\nAssist in ad-hoc assignments and duties as required\nIt would be wonder if you are/have:-\n\nUniversity degree or above in Business Administration, Accounting, Finance, or related disciplines.\nMinimum of 5 years\u2019 working experience in fund operations and administration.\nGood interpersonal skills and presentation skills.\nFlexible and detailed minded.\nGood command of spoken and written English & Chinese, including Mandarin.\nImmediately available is highly preferred.\nYour application shall contain your resume stating your current & expected salary.\nYour application will go through severe screening & consideration; only qualified candidates will be contacted within two weeks after application.\nAll personal data collected will be strictly prohibited for recruitment purposes only; personal data of unsuccessful candidates will be destroyed within 12 months after the date of application.", "employment_types": ["Full Time", "Permanent"], "selling_points": ["Fund Operation, Hedged Fund, Fund valuation", "Fund accounting, subscriptions, redemption, AML", "Listed Company, Fintec, Grade A office"], "locations": ["Wan Chai"], "categories": ["Banking / Finance", "Fund Management", "Order Processing & Operation / Settlement", "Asset Management"], "post_time": "2022-01-10T09:33:18Z", "salary": {"currency": null, "max": null, "min": null, "period": "monthly", "term": null}, "salary_visible": false, "title_keywords": ["fund operation manager"], "responsibilities": ["administration", "office administration", "brokerage", "review", "ad-hoc assignments", "checking", "operations", "month-end closing", "recruitment", "banking", "personal data", "asset management"], "requirements": {"degrees": ["degree or above"], "majors": ["related disciplines", "finance", "accounting", "business administration"], "languages": ["english", "chinese", "mandarin"], "language_level": ["good command"], "hard_skills": ["go", "anti-money laundering"], "soft_skills": ["flexible", "determined", "responsible", "presentation skills", "interpersonal skills", "detailed"], "languages_combined": [{"language": "english", "language_level": ["good command"]}, {"language": "chinese", "language_level": ["good command"]}, {"language": "mandarin", "language_level": ["good command"]}]}, "experience_required": {"duration": ["minimum of 5 years"], "field": ["administration"]}}, {"job_id": "100003009038290", "location_code": "hk", "company": "AXA China Region Insurance Company Limited", "job_title": "MPF Sales Officer", "description": "Career with a Difference\n\n\nWe offer flexible working hours, comprehensive training and excellent career development opportunities.\n\nWe deliver professional MPF services and retirement planning to our clients. Working in our young and joyful international team including native Cantonese and English speakers, we respect every teammate and have equal opportunities. Want a dynamic career with a difference? Come and join us!\n\n\u00a0Core responsibilities:\u00a0\n\nProvide professional MPF service to every individual client for their purposes of wealth management, retirement plan and investment\nProvide corporate benefits to company accounts like MPF schemes, Group Medical Plans and General Business Insurance\nManage relationships with individual clients and corporate accounts\nHandle incoming inquiries from scheme members\nEnjoy our benefits:\n\nClient Base provided\u00a0\nFlexible working hours\u00a0\nMonthly salary ranging from HK$22000 to $30000\nQuarterly Bonus and Year End Bonus\nInitial training and On-Job training provided\nTransparent Career Path to Management Level\nLife and Medical Insurance\nAs a MPF service officer, you should possess the following qualities:\n\nDegree or Diploma holders would be preferred\nExperienced in sales or customer service field as an advantage\nFluent in Cantonese, English, and Mandarin as an advantage\nStrong interpersonal and communication skills with the ability to manage client relationships\nProactive, self-motivated, and customer-oriented\nResponsible team player with strong desire for success\nHKID card holder is a MUST\nFresh graduates would also be considered\n\nWe offer attractive benefits packages and excellent career development opportunities.\u00a0 Please mention your expected salary and the earliest availability in the resume.", "employment_types": ["Full Time", "Permanent", "Contract"], "selling_points": ["4 Days Working", "22k-30k (stable income)", "Long term business development"], "locations": ["Tsim Sha Tsui"], "categories": ["Admin & HR", "Administration / Operation Manager", "Sales, CS & Business Devpt", "Sales - Sales Management", "Banking / Finance", "Asset Management"], "post_time": "2022-01-11T06:26:37Z", "salary": {"currency": "HKD", "max": 34999, "min": 20000, "period": "monthly", "term": null}, "salary_visible": true, "title_keywords": ["sales officer"], "responsibilities": [], "requirements": {"degrees": [], "majors": [], "languages": [], "language_level": [], "hard_skills": [], "soft_skills": [], "languages_combined": []}, "experience_required": {"duration": [], "field": []}}, {"job_id": "100003009040818", "location_code": "hk", "company": "Profile Search and Selection", "job_title": "Manager, Marketing Compliance, Asset Manager", "description": "Responsibilities:\n\nManage AML, COE and ABC process in relation to promotional activities for their institutional business.\nManage budget and ensure expenses are spent within budget.\nManage the compliance clearance process for marketing materials across the region.\n\nRequirements:\n\nAt least 5-6 years of relevant experience in asset management, finance or banking is preferred.\nCompliance related experience is a plus.\nStrong team player with excellent communications skills.\nStrong computer skills - MS Word, PowerPoint, MS Outlook, Excel, Chinese typing.", "employment_types": ["Full Time", "Permanent"], "selling_points": ["compliance", "marketing", "marketing material"], "locations": ["Not Specified"], "categories": ["Professional Services", "Legal & Compliance", "Marketing / Public Relations", "Others", "Banking / Finance", "Asset Management"], "post_time": "2022-01-12T03:06:38Z", "salary": {"currency": null, "max": null, "min": null, "period": "monthly", "term": null}, "salary_visible": false, "title_keywords": ["manager"], "responsibilities": ["aml", "expenses", "budget", "compliance", "promotional activities", "marketing materials"], "requirements": {"degrees": [], "majors": [], "languages": ["chinese"], "language_level": [], "hard_skills": ["excel", "plus", "typing", "powerpoint", "computer skills", "outlook", "ms word"], "soft_skills": ["team player"], "languages_combined": [{"language": "chinese", "language_level": []}]}, "experience_required": {"duration": ["at least 5-6 years"], "field": ["related", "finance", "compliance", "relevant experience", "banking", "asset management"]}}, {"job_id": "100003009036403", "location_code": "hk", "company": "Solomon Capital Management Limited", "job_title": "Assistant Compliance Officer/ Compliance Officer/ Assistant Manager", "description": "Responsibilities:\n\nGeneral SFC compliance coverage for Type 1, 4 & 9 licensed corporation, including AML/CTF\nExposure to fund administration compliance\nUpdate, review and draft manuals, policies and procedures\nPerform compliance checking and reviews\nHandle the implementation of compliance procedures and polices\nAdditional exposure to other related duties and new fund structures, LPF, OFC, QFII and potentially alternative assets such as crypto\n\nRequirements:\n\nDegree holder in Law, Accounting or other related disciplines\u00a0\nAt least 1-3 years compliance experience in the financial services industry or with regulatory bodies\nExperience in brokerage, advisory and asset management\nGood knowledge of SFC regulatory requirements and market practices for Type 1, 4 & 9 licensed corporation\nProactive, detail oriented, responsible, good interpersonal skills and willing to learn and to work under pressure\nPrevious experience with banking ordinance and with futures contract an advantage but not necessary\nGood command of written and spoken English and Chinese, Putonghua is optional\nExcellent command of Microsoft Office\nPosition is also open for candidates with more experience to be considered for a more senior role and responsibilities\n\nInterested parties please apply with your resume, with current and expected salary.", "employment_types": ["Full Time"], "selling_points": [], "locations": ["Wan Chai"], "categories": ["Banking / Finance", "Financial Services", "Professional Services", "Legal & Compliance", "Asset Management"], "post_time": "2022-01-10T10:17:59Z", "salary": {"currency": null, "max": null, "min": null, "period": "monthly", "term": null}, "salary_visible": false, "title_keywords": ["assistant manager", "compliance officer", "assistant"], "responsibilities": ["aml", "policies", "review", "compliance", "procedures", "checking", "implementation", "administration"], "requirements": {"degrees": ["degree holder"], "majors": ["related disciplines", "accounting", "law"], "languages": ["putonghua", "english", "chinese"], "language_level": ["good command"], "hard_skills": ["microsoft office"], "soft_skills": ["responsible", "detail oriented", "willing to learn", "interpersonal skills", "proactive", "work under pressure"], "languages_combined": [{"language": "putonghua", "language_level": ["good command"]}, {"language": "english", "language_level": ["good command"]}, {"language": "chinese", "language_level": ["good command"]}]}, "experience_required": {"duration": ["at least 1-3 years"], "field": ["brokerage", "compliance", "banking", "financial services industry", "asset management"]}}, {"job_id": "100003009035277", "location_code": "hk", "company": "\u78d0\u6fa4\u8cc7\u7522\u7ba1\u7406(\u9999\u6e2f)\u6709\u9650\u516c\u53f8", "job_title": "Fund Operation Associate", "description": "Fund Operation Associate\n\nA top performing fund manager (AUM 1bn USD +) is looking for a Junior Fund Operation expert to expand their business in Hong Kong. This candidate is expected to be fluent in Mandarin & English and have solid Fund Accounting experience in Hedge Funds, Private Equity, Asset Managements or Fund Admins\n\nWe are looking for young & high calibers candidate to join our professional team.\n\nResponsibilities\n\nResponsible for the oversight of fund operation;\n\nHandle trade booking, settlement, NAV review & reconciliation;\n\nLiaise with fund administrators, brokers, custodians, auditors on various fund operations task; Provide support to different parties;\n\nHandle investors\u2019 subscriptions/redemptions and address related enquires;\n\nResponsible for regulatory reporting;\n\nEnsure adherence to compliance & regulation, review & enhancement on internal control, etc.\n\nUpdate marketing materials and other investors' related reports;\n\nProvide supports and ad hoc tasks which assigned in the team.\n\nRequirements\n\nUniversity graduates in business related disciplines;\n\nMinimum 1 years of Operation experience; both buy side or sell side is welcome; Experiences in audit firm is preferred.\n\nExperience in hedge fund operation & EQ & series accounting is a must;\n\nGood command of written and spoken English and Chinese and Mandarin;\n\nOutstanding negotiation, planning, analytical, problem solving and decision-making skills.", "employment_types": ["Full Time", "Permanent"], "selling_points": [], "locations": ["Central"], "categories": ["Banking / Finance", "Asset Management"], "post_time": "2022-01-10T06:38:38Z", "salary": {"currency": null, "max": null, "min": null, "period": "monthly", "term": null}, "salary_visible": false, "title_keywords": ["associate"], "responsibilities": ["marketing materials", "reporting", "provide support", "operations", "ensure adherence", "review", "compliance", "trade booking", "ad hoc tasks", "reports", "liaise with", "internal control"], "requirements": {"degrees": [], "majors": [], "languages": ["english", "chinese", "mandarin"], "language_level": ["good command"], "hard_skills": ["problem solving"], "soft_skills": ["problem solving", "negotiation"], "languages_combined": [{"language": "english", "language_level": ["good command"]}, {"language": "chinese", "language_level": ["good command"]}, {"language": "mandarin", "language_level": ["good command"]}]}, "experience_required": {"duration": ["minimum 1 years"], "field": ["operation", "audit", "accounting"]}}, {"job_id": "100003009042983", "location_code": "hk", "company": "\u601d\u62db\u8058\u516c\u53f8", "job_title": "Financial Consultant 17k+", "description": "Responsibilities\n\nProvide professional financial services to individual and corporate clients\nCustomize personal financial plan to suit clients\u2019 needs\nPresent professional analysis and business solutions\n\nRequirements\n\n\n\nUniversity Degree/Associate-degree/High-Diploma holder\nJob experiences in Customer Services would definitely be an advantage\nWell-spoken and Presentable\nOptimistic and Result-driven\n\nWe offer\n\n\n\nAttractive Remunerations : Starting monthly based salary ( $15,000 - $25,000+ depending on experience),\u00a0 Commission and Year-end Bonus\nTraining & Support : Professional on-the-job training\nBroaden Your Horizon : Overseas conventions and Travel bonus\u00a0\nComprehensive Benefits : MPF, ORSO , Medical allowance\u00a0", "employment_types": ["Full Time", "Permanent"], "selling_points": ["Fast track advancement", "5 days work", "on-job training in financial sector"], "locations": ["Tsim Sha Tsui"], "categories": ["Banking / Finance", "Investment", "Management", "Management Trainee", "Asset Management"], "post_time": "2022-01-12T09:25:00Z", "salary": {"currency": null, "max": null, "min": null, "period": "monthly", "term": null}, "salary_visible": false, "title_keywords": ["consultant"], "responsibilities": ["analysis", "plan"], "requirements": {"degrees": ["diploma holder", "university degree", "degree"], "majors": [], "languages": [], "language_level": [], "hard_skills": [], "soft_skills": ["driven", "presentable"], "languages_combined": []}, "experience_required": {"duration": [], "field": ["customer services"]}}, {"job_id": "100003009043408", "location_code": "hk", "company": "Ambition", "job_title": "Associate / Senior Associate, Trade Support", "description": "Convenient Working location\nExcellent career path\nWork life balance\n\nOur client is a well-established investment bank with strong global presence. In order to cope with the company growth, they are currently looking for a Trade Support to join the Operations team.\n\nAs a Trade Support, you are responsible for the following but not limited to:\n\nPerform trade matching and reconciliation for Equities products for APAC market\nResolve any trade breaks with internal stakeholders such as Traders and settlement team\nHandle trade-related clients' enquiries\nParticipate in system enhancement such as UAT testing if necessary\n\nTo qualify, individual must possess:\n\nUniversity degree holder in Accounting or equivalent disciplines\nOver 2 years of middle office operations experience in financial services industry\nExperience in Stock connect would be an advantage\nA good team player, willing to learn and able to work under high pressure\nStrong interpersonal, communication and presentation skills\nExcellent communication skills with fluency in Cantonese and English\n\nInterested parties, send your updated resume to rita.lee@ambition.com.hk or click \"Apply Now\" .\n\nOnly shortlisted candidates would be notified.\n\nIf this job isn't quite right for you, but you know someone who would be great at this role, why not take advantage of our referral scheme? We offer HKD1000 in Apple gift cards for every referred candidate who we place in a role. Terms & Conditions Apply. https://www.ambition.com.hk/refer-a-friend", "employment_types": ["Full Time", "Permanent"], "selling_points": ["Convenient Working location", "Excellent career path", "Work life balance"], "locations": ["Not Specified"], "categories": ["Banking / Finance", "Equities / Capital Markets", "Others", "Asset Management"], "post_time": "2022-01-12T11:32:41Z", "salary": {"currency": null, "max": null, "min": null, "period": "monthly", "term": null}, "salary_visible": false, "title_keywords": ["senior associate", "associate"], "responsibilities": ["communication", "operations", "uat testing"], "requirements": {"degrees": ["university degree"], "majors": ["accounting"], "languages": ["cantonese", "english"], "language_level": ["fluency", "excellent"], "hard_skills": [], "soft_skills": ["communication skills", "good team player", "responsible", "willing to learn", "communication", "presentation skills", "work under high pressure", "interpersonal"], "languages_combined": [{"language": "cantonese", "language_level": ["fluency", "excellent"]}, {"language": "english", "language_level": ["fluency", "excellent"]}]}, "experience_required": {"duration": ["2 years"], "field": ["financial services industry"]}}, {"job_id": "100003009042569", "location_code": "hk", "company": "Recruitment Intelligence Consultants Ltd", "job_title": "SENIOR INSTITUTIONAL SALES", "description": "International Asset Management House\nBased in Hong Kong\nOur client is an international asset management house with an unparalleled reputation across the Asia Pacific region. With the continued growth of the organization, the need has arisen to recruit high calibers to join them.\nResponsible for sales generation and client relationship management in Hong Kong, Taiwan, Philippines and Macau for complex institutional accounts. Identifies new business opportunities with new client relationships. Creates, monitors, and revises lead generation plans for the development of sustainable and diversified sales pipelines. Maintains significant industry experience and proactively researches trends, competitor services/offerings, and clients' business environment. Oversees existing complex client relationships. Maintains good relationship with all internal stakeholders but at the same time drive changes to cater for client needs. Evaluates the strategic potential of prospects; develops and executes a plan for capitalizing on those opportunities in the near and long term. Develops in-depth knowledge of institutional clients, their sensitivities, and their business needs to effectively influence their decision-making. \u00a0Partners with marketing team and other sales teams to develop promotional and pitch materials. Analyzes highly complex data, trends, plan changes, and strategies to keep up to date with sales/relationship performance. Engages the appropriate internal stakeholders to ensure contract requirements are in alignment with organizational policies and standards; maintains good relationship with internal stakeholders.\nTo be considered, you should be a Degree holder with a minimum of 10 years of relevant work experience. Sound knowledge and experience of institutional clients in Hong Kong, Taiwan, Philippines and Macau. Excellent communication skills in written and spoken, in both English and Chinese (Cantonese and Mandarin). Good interpersonal skills to work with all levels of internal stakeholders. Well organized and results focused.\u00a0\u00a0\n\nInterested applicants should send a detailed resume to Kelly Kam quoting reference jdb-4576\u00a0via email.\u00a0 Please click \u201cAPPLY NOW\u201d button below.\n\n(Applicants not contacted within 4 weeks should consider their application unsuccessful.)\n", "employment_types": ["Full Time", "Permanent"], "selling_points": [], "locations": ["Not Specified"], "categories": ["Banking / Finance", "Financial Services", "Fund Management", "Asset Management"], "post_time": "2022-01-12T08:04:34Z", "salary": {"currency": null, "max": null, "min": null, "period": "monthly", "term": null}, "salary_visible": false, "title_keywords": ["sales"], "responsibilities": ["management", "data", "policies", "business opportunities", "teams", "develop", "good relationship", "communication", "plan", "sensitivities", "plans", "asset management"], "requirements": {"degrees": ["degree holder"], "majors": [], "languages": ["cantonese", "english", "chinese", "mandarin"], "language_level": ["excellent"], "hard_skills": ["pipelines"], "soft_skills": ["communication skills", "responsible", "focused", "organizational", "well organized", "interpersonal skills", "business environment", "detailed"], "languages_combined": [{"language": "cantonese", "language_level": ["excellent"]}, {"language": "english", "language_level": ["excellent"]}, {"language": "chinese", "language_level": ["excellent"]}, {"language": "mandarin", "language_level": ["excellent"]}]}, "experience_required": {"duration": ["minimum of 10 years"], "field": ["business"]}}, {"job_id": "100003009043080", "location_code": "hk", "company": "Find Asia Limited", "job_title": "Sales VP, Investment Funds Services Product", "description": "Our client, a banking & finance co. is looking for the candidate with the following details:\n\nDuties\n\nEnhance sales opportunities for potential clients and penetrated with existing clients for full investment Funds Services Products\nWell-prepare the sales presentation, liaise and set up meetings\nLiaise with internal client relationship team to explore all sales opportunities\nIdentify product enhancement and product management\nSupport and liaise with Regional Head of Sales and the team for business development in North Asia and Regional Asia\nEnsure smooth delivery of the products and work closely with other teams\nParticipate in any conferences, seminars to maintain professional knowledge, update market, industry developments and competitors\u2019 activities\n\n\u00a0Requirements\n\nBachelor degree of Economics, Business Administration, Finance or relevant disciplines\nFluent in English and Mandarin\nWith relevant experience in finance, asset management in sales or business development\nSolid experience in clients handling, marketing and promotion\nExcellent skills of organization, communication, customer-focused\nAble to work independently and proactively", "employment_types": ["Full Time", "Permanent"], "selling_points": ["Finance, Investment Funds Services", "Asset Management, Sales, Business Development", "Proactive, independent"], "locations": ["Central & Western Area"], "categories": ["Banking / Finance", "Corporate Banking", "Equities / Capital Markets", "Asset Management"], "post_time": "2022-01-12T09:45:01Z", "salary": {"currency": null, "max": null, "min": null, "period": "monthly", "term": null}, "salary_visible": false, "title_keywords": ["sales"], "responsibilities": ["liaise", "management", "teams", "conferences", "maintain", "liaise with"], "requirements": {"degrees": ["degree", "bachelor"], "majors": ["finance", "economics", "business administration"], "languages": ["english", "mandarin"], "language_level": ["fluent"], "hard_skills": [], "soft_skills": ["communication", "work independently", "customer-focused"], "languages_combined": [{"language": "english", "language_level": ["fluent"]}, {"language": "mandarin", "language_level": ["fluent"]}]}, "experience_required": {"duration": [], "field": ["finance", "business development", "marketing", "relevant experience", "asset management"]}}, {"job_id": "100003009028083", "location_code": "hk", "company": "First Prosperous Financial Holdings Co., Limited", "job_title": "Analyst, Private Equity", "description": "Job Purpose\n\nReporting to a Private Equity Director, the candidate is taking a major execution role from preparing pitchbook to deal execution.\n\nKey Responsibilities\n\nPreparing company pitchbooks in Chinese and English;\nConducting research in health care / technology / blockchain related sectors, providing insights and generating investment views;\nWork independently in carrying out investment analysis and investment report to the investment target through investigating the financial reports and market information, etc;\nBuilding financial models and valuation analysis of the target investment;\nParticipating in due diligence for active deals and possible portfolio company monitoring in the after-investment stage.\n\nRequirements\n\nBachelor's degree or above, with major in Economics, Finance, Accounting, Business Administration or related discipline(s); CPA or CFA is a plus;\n2-3 years of working experience in Private Equity and related investment nature;\nWell versed in DCF modelling, corporate valuations and due diligence;\nUnderstanding the whole process of running a PE fund from deal sourcing to deal execution;\nHighly skilled in using MS Office especially power point to make pitchbook presentation in Chinese and English;\nGood writing, analytical and quantitative skills;\nSelf-motivated, independent and pleasant personality with good communication skills\nGood command of written and spoken English and Chinese (including Putonghua)", "employment_types": ["Full Time"], "selling_points": [], "locations": ["Central"], "categories": ["Banking / Finance", "Asset Management"], "post_time": "2022-01-07T01:29:00Z", "salary": {"currency": null, "max": null, "min": null, "period": "monthly", "term": null}, "salary_visible": false, "title_keywords": ["analyst"], "responsibilities": ["valuation", "financial reports", "market information", "due diligence", "investment analysis", "financial models", "analysis", "monitoring", "report"], "requirements": {"degrees": ["degree or above", "bachelor"], "majors": ["finance", "economics", "business administration", "accounting"], "languages": ["putonghua", "english", "chinese"], "language_level": ["good command"], "hard_skills": ["plus", "cfa", "cpa", "make", "pe", "power point", "private equity", "ms office"], "soft_skills": ["communication skills", "self-motivated", "independent", "pleasant", "presentation"], "languages_combined": [{"language": "putonghua", "language_level": ["good command"]}, {"language": "english", "language_level": ["good command"]}, {"language": "chinese", "language_level": ["good command"]}]}, "experience_required": {"duration": ["2-3 years"], "field": ["related", "investment"]}}, {"job_id": "100003009034629", "location_code": "hk", "company": "Links International", "job_title": "Fund Operations Associate - Welcome Fund Admin!", "description": "Responsibilities:\n\nPrepare daily and monthly reconciliation, NAV estimates\nPreparing monthly fund valuation, return attribution and investor reporting\nMonitor various fund operation issues including settlements, collateral, and cash management\nPerform trade bookings, trade matching, daily and P&L reconciliations, failed trade investigations\nLiaise with prime brokers and fund administrator on break resolutions\nPerform automation and process review to streamline and document workflow\nSupport the trading team and assist in back office tasks\nHandle ad-hoc projects assigned by management\n\nRequirements:\n\nUniversity degree in Accounting, Finance or other related disciplines\nMinimum of 1 year fund/ accounting related experience\nKnowledge of financial derivative products is an advantage\nExcellent communication skills in English and Mandarin, mature mindset and confident personality in order to interact with Trading teams and senior management to address business issues\nGood attention to details, able to adapt and work well under pressure\nProficiency in Excel and SQL are preferable\nA positive attitude, a sense of satisfaction from doing your best, and self-discipline are all essential", "employment_types": ["Full Time", "Permanent"], "selling_points": ["Guaranteed 13 months salary", "Work life balance", "All rounded and dynamic role"], "locations": ["Not Specified"], "categories": ["Accounting", "Accountant", "Banking / Finance", "Fund Management", "Asset Management"], "post_time": "2022-01-10T03:50:17Z", "salary": {"currency": null, "max": null, "min": null, "period": "monthly", "term": null}, "salary_visible": false, "title_keywords": ["admin", "fund operations associate"], "responsibilities": ["valuation", "reporting", "management", "prime brokers", "review", "monitor", "back office", "p&l", "reconciliations", "liaise with", "ad-hoc projects"], "requirements": {"degrees": ["university degree"], "majors": ["related disciplines", "finance", "accounting"], "languages": ["english", "mandarin"], "language_level": ["excellent"], "hard_skills": ["sql", "excel"], "soft_skills": ["confident", "communication skills", "under pressure", "mature", "positive attitude", "attention to details"], "languages_combined": [{"language": "english", "language_level": ["excellent"]}, {"language": "mandarin", "language_level": ["excellent"]}]}, "experience_required": {"duration": ["minimum of 1 year"], "field": ["related", "accounting"]}}, {"job_id": "100003009041559", "location_code": "hk", "company": "Leader Marine Products Trading Limited", "job_title": "\u8eca\u968a\u7d44\u9577\u517c\u53f8\u6a5f (5.5\u5678 / 9.5\u5678)", "description": "\n\u8077\u8cac :\u8ca0\u8cac\u7ba1\u7406\u8eca\u968a, \u5b89\u6392\u53f8\u6a5f\u65e5\u7a0b, \u65bc\u5de5\u5834\u53d6\u8ca8\u4e26\u6d3e\u9001\u6e2f\u4e5d\u65b0\u754c\u5404\u5e97\u92ea; \u65bc\u516c\u53f8\u5009\u5eab\u53d6\u8ca8\u5f8c\u9001\u8ca8\u5230\u5404\u5927\u51cd\u5009 (\u5305\u62ec\u8d85\u5e02); \u5b89\u6392\u8eca\u8f1b\u4fdd\u990a\u7dad\u4fee\u53ca\u65e5\u5e38\u6e05\u6f54\u7b49; \u9577\u6c99\u7063\u53d6\u8eca\n\n\u8cc7\u6b77 :\u4e2d\u4e94\u7a0b\u5ea6; 3\u5e74\u7d93\u9a57; \u4e00\u822c\u7cb5\u8a9e\u512a\u5148; \u4e00\u822c\u666e\u901a\u8a71; \u4e00\u822c\u82f1\u8a9e\u512a\u5148; \u61c2\u8b80\u5beb\u4e2d\u6587; \u61c2\u8b80\u5beb\u82f1\u6587; \u6301\u6709\u4e2d\u578b\u8ca8\u8eca\u99d5\u99db\u57f7\u7167; \u6301\u6709\u8f15\u578b\u8ca8\u8eca\u99d5\u99db\u57f7\u7167\n\n\u5f85\u9047 :\u6bcf\u6708$20,000 - $28,000, \u6709\u914c\u60c5\u6027\u82b1\u7d05, \u54e1\u5de5\u8cfc\u7269\u512a\u60e0 \u53ca\u8d85\u6642\u5de5\u4f5c\u6d25\u8cbc, \u661f\u671f\u4e00\u81f3\u516d: \u4e0a\u53488\u6642\u81f3\u4e0b\u53486\u6642, \u6bcf\u9031\u5de5\u4f5c6\u5929, \u6bcf\u5929\u5de5\u4f5c 10 \u5c0f\u6642\n\n\u7533\u8acb\u9808\u77e5 :\u6c42\u8077\u8005\u53ef\u81f4\u96fb36561388(Ext.315)\u8207\u5229\u9054\u6d77\u7522\u8cbf\u6613\u6709\u9650\u516c\u53f8\u66fe\u5c0f\u59d0\u806f\u7d61\u3002\n\n", "employment_types": ["Full Time"], "selling_points": [], "locations": ["Cheung Sha Wan"], "categories": ["Banking / Finance", "Asset Management"], "post_time": "2022-01-12T04:02:28Z", "salary": {"currency": null, "max": null, "min": null, "period": "monthly", "term": null}, "salary_visible": false, "title_keywords": [], "responsibilities": [], "requirements": {"degrees": [], "majors": [], "languages": [], "language_level": [], "hard_skills": [], "soft_skills": [], "languages_combined": []}, "experience_required": {"duration": [], "field": []}}, {"job_id": "100003009042907", "location_code": "hk", "company": "Global Job Consulting Co.", "job_title": "Asset Management Consultant / Wealth Management Consultant / IFA", "description": "Responsibilities:\n\n-Provide comprehensive financial and banking advice to clients on\u00a0risk-and wealth-management products, Insurance, MPF and employee-benefits products\n\n-Analyze and compare products of different service providers/ insurance companies\n\n-Constant monitoring of investment portfolios\n\n-Develop and expand existing network through relationship management\n\nRequirements:\n\n-Fresh graduates/ IANG will also be considered\n\n-Mature, self-motivated, hardworking and willing to learn\n\n-Aggressive, Energetic and outgoing\n\n-Good interpersonal and communication skills\n\n-Explore PRC and Hong Kong market\n\n-Interest in Investment\u00a0\n\nIncentive:\n\n-Attractive basic +\u00a0commission with allowance package\n\n-Fast-track promotion to managerial position\n\n-Overseas trips & conventions plus excellent career path\n\n-Excellent and comprehensive in-house training programs\n\n-Professional training to become a\u00a0Millionaires", "employment_types": ["Full Time"], "selling_points": ["$25000 - $40000", "Work balance and be Professional", "Happy working atmosphere"], "locations": ["Sheung Wan"], "categories": ["Banking / Finance", "Asset Management"], "post_time": "2022-01-12T09:12:22Z", "salary": {"currency": null, "max": null, "min": null, "period": "monthly", "term": null}, "salary_visible": false, "title_keywords": ["wealth management consultant", "consultant", "asset management"], "responsibilities": [], "requirements": {"degrees": [], "majors": [], "languages": [], "language_level": [], "hard_skills": [], "soft_skills": [], "languages_combined": []}, "experience_required": {"duration": [], "field": []}}, {"job_id": "100003009036815", "location_code": "hk", "company": "Noah International (Hong Kong) Limited", "job_title": "Risk Manager", "description": "\u00a0Job Description\n\nA career in our Financial Services / Commercial Department will provide you with the opportunity to advise financial services clients, and in particular fund managers, in relation to their Hong Kong SFC licensing requirements and to handle the preparation, processing and follow up of SFC licence applications. Secretarial support will be available for the position.\n\nResponsibilities:\n\n\nAs a Licensing, Compliance & Regulatory Executive, you will need to be able to manage relationships with clients and contacts as a \u201ctrusted compliance advisor\u201d and to develop and maintain good relationships with relevant persons at the SFC. Specific responsibilities include but are not limited to:\nPreliminary assessments on the proposed activities of companies and individuals and provide advice on the type of SFC licence required\nNew individual and corporate SFC licence applications\nSubsequent applications (e.g. additional regulated activity, modification of licensing conditions, FRR return authorised signatories)\nSubstantial shareholder (associate) analysis and new substantial shareholder applications\nAssistance in responding to SFC enquiries\nNotifications to and on-going regulatory filings with the SFC\nAdvice on on-going regulatory requirements and business compliance related matters\nMaintain a flexible approach and be able to accommodate new and varied work flows\nMay be required to assist with other regulatory and compliance matters within the compliance unit or the funds group as a whole\n\nRequirements:\n\n\nA degree holder (in law or other business related discipline)\nAt least two years of financial industry experience and preferably with an asset manager\nWide range of experience including, but not limited to the following areas:\nSFC licence applications\nSFC licence maintenance including ongoing filings\nKnowledge of how the securities, futures and asset management industries operate\nFamiliarity with the relevant regulatory requirements\nPreferably have worked at the Licensing Department of the SFC and ideally at assistant manager level 1 or higher\nA good communicator with good interpersonal communication skills\nA good team player with good team spirit\nThe ability to handle direct client communications and meetings professionally and competently, while always keeping their supervisors fully involved and informed\nAble to speak, read and write English, Cantonese and Mandarin fluently\n\nAttractive salary and fringe benefits will be offered to the right candidate. Please visit\u00a0www.deacons.com\u00a0for more information about the firm.\u00a0 If you are interested, please click \"Apply Now\".\n\nWe would only consider applicants who apply directly to our firm and not through recruitment agencies.\u00a0 All applications will be treated in strict confidence.\u00a0 Personal data collected will be used for recruitment purposes only.\u00a0 Information on unsuccessful candidates will be kept up to 2 years after the recruitment process.", "employment_types": ["Full Time", "Permanent"], "selling_points": ["Min. of 2-3 years\u2019 experience in risk management", "Knowledge of fund management", "Professional Qualification (FRM/ CFA) is an adv"], "locations": ["Causeway Bay"], "categories": ["Banking / Finance", "Fund Management", "Risk Management", "Asset Management"], "post_time": "2022-01-10T15:11:08Z", "salary": {"currency": null, "max": null, "min": null, "period": "monthly", "term": null}, "salary_visible": false, "title_keywords": ["manager"], "responsibilities": ["regulatory requirements", "analysis", "compliance", "develop", "maintain", "provide advice", "secretarial support"], "requirements": {"degrees": ["degree holder"], "majors": ["business", "law"], "languages": ["cantonese", "english", "mandarin"], "language_level": [], "hard_skills": ["maintenance"], "soft_skills": ["communication skills", "good team player", "team spirit", "communicator", "interpersonal"], "languages_combined": [{"language": "cantonese", "language_level": []}, {"language": "english", "language_level": []}, {"language": "mandarin", "language_level": []}]}, "experience_required": {"duration": ["at least two years"], "field": ["financial industry"]}}, {"job_id": "100003009036980", "location_code": "hk", "company": "Deacons", "job_title": "Licensing, Compliance & Regulatory Executive", "description": "We invite applications for the position of Senior Legal Counsel / Legal Counsel. Candidates should have the following qualifications:\n\nFor the position of Senior Legal Counsel, not less than 10 years\u2019 PQE gained at a well-recognized law firm, fund house or financial institution.\u00a0 Candidates with less experience may be considered for the position of Legal Counsel.\u00a0 Legal qualifications and experience gained from jurisdictions outside Hong Kong will also be considered.\nStrong advisory experience in banking, securities and futures, investment funds, derivatives or capital market products, with a sound knowledge of the ISDA Master Agreement and other market standard agreements used in the international financial markets.\nGood legal drafting, advisory and analytical skills, in both Chinese and English.\nA self-motivated team-player with the ability to work under pressure and independently and impeccable integrity.\nGood academic background.\nProficiency in Putonghua and English.\n\n\u00a0Personal data collected will be used for recruitment related purposes only.", "employment_types": ["Full Time", "Permanent"], "selling_points": ["Degree holder", "At least 2 years of financial experiences", "Fluent in English, Chinese & Mandarin"], "locations": ["Central"], "categories": ["Professional Services", "Legal & Compliance", "Banking / Finance", "Asset Management"], "post_time": "2022-01-11T01:12:11Z", "salary": {"currency": null, "max": null, "min": null, "period": "monthly", "term": null}, "salary_visible": false, "title_keywords": ["executive"], "responsibilities": ["work under pressure", "personal data", "recruitment", "banking"], "requirements": {"degrees": ["master"], "majors": [], "languages": ["putonghua", "english", "chinese"], "language_level": ["proficiency", "good"], "hard_skills": ["analytical skills"], "soft_skills": ["self-motivated", "independently", "team-player", "integrity", "analytical skills", "work under pressure"], "languages_combined": [{"language": "putonghua", "language_level": ["proficiency"]}, {"language": "english", "language_level": ["proficiency", "good"]}, {"language": "chinese", "language_level": ["proficiency", "good"]}]}, "experience_required": {"duration": [], "field": ["legal", "financial markets", "investment", "banking", "securities"]}}, {"job_id": "100003009036130", "location_code": "hk", "company": "Deacons", "job_title": "Junior Compliance & Regulatory Executive", "description": "Job Description\nA career in our Financial Services / Commercial Department will provide you with the opportunity to provide support to members of our compliance and regulatory team with work for financial services clients, and in particular fund managers, in connection with handling the preparation and processing of SFC licence applications. Secretarial support will not usually be available for the position.\nResponsibilities:\nAs a Junior Compliance & Regulatory Executive, you will need to maintain a flexible approach and be able to accommodate new and varied work flows. At times the individual may be required to assist with other regulatory and compliance matters within the compliance team or the funds group as a whole. Specific responsibilities include but are not limited to:\nDetails of the main duties are set out below:\nTo prepare routine/simple Applications for Licensed Representatives, monitor the application process by checking the SFC's Register and with approval of the Supervisor, follow up with the case officer, prepare reports to the client once the application is approved, seek input from the client, obtain copies of licensing exam results for persons that need to pass the exam papers within the grace period and submit to the SFC\nTo prepare routine/simple Applications for Transfer of Accreditation and to monitor the application process by checking the SFC's Register and with approval of the Supervisor, follow up with the case officer and prepare a draft report to the client once the application is approved\nTo prepare routine/simple Applications for Addition of Accreditation, monitor the application process by checking the SFC's Register and with approval of the Supervisor follow up with the case officer and prepare a draft report to the client once the application is approved\nThe individual will also be expected to:\nPrepare other routine/simple applications from time to time for review by the Supervisor\nPrepare routine/simple notifications to the SFC for review and approval by the Supervisor\nConduct licensing and other administrative tasks from time to time\nPrepare soft copies of licensing application forms for clients\nNote that all verbal and written communications with the SFC and the client and other relevant parties have to be pre-approved in accordance with our standard external communications approval procedures\nAble to manage relationships with clients and contacts as a \u201ctrusted compliance advisor\u201d and to develop and maintain good relationships with relevant persons at the SFC\nRequirements:\nA degree holder (in law or other business related discipline)\nKnowledge of how the securities and asset management industries operate\nA confident communicator with effective interpersonal communication skills\nA good team player with team spirit\nThe ability to handle direct client communications and meetings professionally and competently, while always keeping supervisor fully involved and informed\nAble to speak, read and write English, Cantonese and Mandarin fluently\n\nAttractive salary and fringe benefits will be offered to the right candidate. Please visit\u00a0www.deacons.com\u00a0for more information about the firm.\u00a0 If you are interested, please click \"Apply Now\".\n\nWe would only consider applicants who apply directly to our firm and not through recruitment agencies.\u00a0 All applications will be treated in strict confidence.\u00a0 Personal data collected will be used for recruitment purposes only.\u00a0 Information on unsuccessful candidates will be kept up to 2 years after the recruitment process.", "employment_types": ["Full Time", "Permanent"], "selling_points": ["Degree holder", "Knowledge of securities and asset management", "Fluent in English, Chinese & Mandarin"], "locations": ["Central"], "categories": ["Professional Services", "Legal & Compliance", "Banking / Finance", "Asset Management"], "post_time": "2022-01-10T09:25:40Z", "salary": {"currency": null, "max": null, "min": null, "period": "monthly", "term": null}, "salary_visible": false, "title_keywords": ["executive", "junior"], "responsibilities": ["provide support", "communications with", "compliance", "monitor", "checking", "review", "procedures", "develop", "maintain", "secretarial support", "prepare reports", "administrative tasks", "report"], "requirements": {"degrees": ["degree holder"], "majors": ["business", "law"], "languages": ["cantonese", "english", "mandarin"], "language_level": [], "hard_skills": [], "soft_skills": ["confident", "communication skills", "good team player", "team spirit", "communicator", "interpersonal"], "languages_combined": [{"language": "cantonese", "language_level": []}, {"language": "english", "language_level": []}, {"language": "mandarin", "language_level": []}]}, "experience_required": {"duration": [], "field": []}}, {"job_id": "100003009036182", "location_code": "hk", "company": "Fubon Bank (Hong Kong) Limited", "job_title": "Assistant Manager / Supervisor, Capital Management & ALCO Support, Financial Control Division", "description": "Responsibilities\n\n\nCoordinate and involve in activities and events with external business partners\nTo conduct related research and presentation\nTo prepare marketing materials where necessary\nTo support operations of business\nFormulate strategic development planning to management\nTo assist in any ad hoc assignments\n\n\u00a0Requirements\n\n\u00a0\u00a0\u00a0\u00a0\u00a0\u00a0\u00a0\u00a0 Bachelor\u2019s degree holder in relevant disciplines;\n\u00a0\u00a0\u00a0\u00a0\u00a0\u00a0\u00a0\u00a0 At least 2-3 years relevant experience in financial institutions;\n\u00a0\u00a0\u00a0\u00a0\u00a0\u00a0\u00a0\u00a0 Sound knowledge of the financial markets, investment products;\n\u00a0\u00a0\u00a0\u00a0\u00a0\u00a0\u00a0\u00a0 Commercial savvy on family office market trends;\n\u00a0\u00a0\u00a0\u00a0\u00a0\u00a0\u00a0\u00a0 Analytical-thinking and outgoing;\n\u00a0\u00a0\u00a0\u00a0\u00a0\u00a0\u00a0\u00a0 Willing to work as part of a team, where interdependencies and communication across external parties will be common and ongoing;\n\u00a0\u00a0\u00a0\u00a0\u00a0\u00a0\u00a0\u00a0 Excellent command of spoken and written Chinese and English (including Mandarin)", "employment_types": ["Permanent"], "selling_points": ["13 Month Pay", "Medical Benefits", "Insurance Benefits"], "locations": ["Central"], "categories": ["Banking / Finance", "Financial Services", "Equities / Capital Markets", "Asset Management"], "post_time": "2022-01-10T09:35:45Z", "salary": {"currency": null, "max": null, "min": null, "period": "monthly", "term": null}, "salary_visible": false, "title_keywords": ["assistant manager", "supervisor"], "responsibilities": ["management", "operations", "coordinate", "ad hoc assignments", "prepare marketing materials", "planning"], "requirements": {"degrees": ["bachelor", "degree holder"], "majors": [], "languages": ["english", "chinese", "mandarin"], "language_level": ["excellent"], "hard_skills": ["investment products"], "soft_skills": ["outgoing", "communication"], "languages_combined": [{"language": "english", "language_level": ["excellent"]}, {"language": "chinese", "language_level": ["excellent"]}, {"language": "mandarin", "language_level": ["excellent"]}]}, "experience_required": {"duration": ["at least 2-3 years"], "field": ["financial institutions", "relevant experience"]}}, {"job_id": "100003009030363", "location_code": "hk", "company": "Wisdom Asset Management Limited", "job_title": "Management Officer (Multi-Family Office, Asset Management)", "description": "Responsibilities\nEstablish a comprehensive retirement plan to the clients.\nProactively manage accounts and maintain solid relationships with existing clients.\nLeading regular client meetings and communications to deliver exceptional service.\nProvide comprehensive wealth management services to clients.\n\nBenefits\nProfessional training program including mentorship support and leadership workhouse.\nMedical scheme and Start-up allowance\u00a0 + performance bonus\nStudy allowance for professional qualifications (CFP, QRA).\n\nRequirements\nStrong interpersonal skills, team spirit, proactive and independent.\nSales-oriented, strong organization and problem-solving skills.\nImmediately available is preferred.\n\n", "employment_types": ["Full Time"], "selling_points": [], "locations": ["Tsim Sha Tsui"], "categories": ["Banking / Finance", "Asset Management"], "post_time": "2022-01-07T07:19:25Z", "salary": {"currency": null, "max": null, "min": null, "period": "monthly", "term": null}, "salary_visible": false, "title_keywords": ["officer", "asset management"], "responsibilities": ["management", "maintain", "plan"], "requirements": {"degrees": [], "majors": [], "languages": [], "language_level": [], "hard_skills": [], "soft_skills": [], "languages_combined": []}, "experience_required": {"duration": [], "field": []}}, {"job_id": "100003009047554", "location_code": "hk", "company": "AIA International Limited", "job_title": "Wealth Management Manager / Trainee, Financial Planning (Fresh Grad / Candidates w IANG are welcome)", "description": "Our Client\nA top Trustee in HK\n\n\nRole Overview\n\nPrepare for private trust establishment and transfer documentations\nEnsure accuracy of onboarding documents inclusive but not limited to trust deeds, letter of wishes\nPerform client annual review\nConduct due diligence/ KYC\nLiaise with internal and external stakeholders such as banks, lawyers, accountants, all partners a nd investment manager s or advisors regarding distribution, management and distributions of trust assets\n\nIdeal Profile\n\nBachelor degree or above\n3 years or above experience in handling private trust administration\nGood command of Chinese and English (Putonghua is preferred)\nProfessional qualifications such as TEP, CPA or ACIS preferable\u00a0", "employment_types": ["Full Time", "Part Time", "Permanent", "Internship"], "selling_points": ["Management Trainee", "Financial Planning", "investment"], "locations": ["Causeway Bay"], "categories": ["Insurance", "Insurance Agent / Broker", "Sales, CS & Business Devpt", "Account Servicing", "Banking / Finance", "Asset Management"], "post_time": "2022-01-14T03:27:02Z", "salary": {"currency": null, "max": null, "min": null, "period": "monthly", "term": null}, "salary_visible": false, "title_keywords": ["wealth management manager", "trainee"], "responsibilities": ["due diligence", "management", "review", "kyc", "liaise with", "administration"], "requirements": {"degrees": ["degree or above", "bachelor"], "majors": [], "languages": ["putonghua", "english", "chinese"], "language_level": ["good command"], "hard_skills": ["cpa", "professional qualifications", "documentations", "kyc"], "soft_skills": ["ideal"], "languages_combined": [{"language": "putonghua", "language_level": ["good command"]}, {"language": "english", "language_level": ["good command"]}, {"language": "chinese", "language_level": ["good command"]}]}, "experience_required": {"duration": ["3 years"], "field": ["administration"]}}, {"job_id": "100003009034608", "location_code": "hk", "company": "Cornerstone Global Partners", "job_title": "Private Trust Admin Manager / Senior Officer (KYC, Legal Documents, Top Trustee)", "description": "Responsibilities:-\n\nManaging and monitoring the performance of Individual and Corporate clients\n\nHandling investment portfolios, premium financing, asset management\nMaintain customer relationships by providing regular market information and updates on local and international investment instruments\nDevelop and implement digital and social media plans\nRequirements:-\n\nUniversity\u00a0 graduates (FRESH GRADUATES ARE ALSO WELCOMED)\nExcellent communication and interpersonal skills\u00a0\nGood decision making skills within fast-paced environments\nAttention to detail, able to work and cope with people\nSocial events and networking\nProvide Good client service and professional financial advice;\nWe offer:-\n\nFast-track advancement opportunities to management level\nA structured career path and solid training in all aspects of management\n5-days work week, MPF, medical and dental insurance package\nOversea trips and convention\nSponsorship in professional qualifications\nSalary, Commission, Year end Bonus\u00a0", "employment_types": ["Permanent"], "selling_points": ["private trust transfer", "private trust establishment", "due diligence/ KYC"], "locations": ["Central & Western Area"], "categories": ["Banking / Finance", "Private Banking", "Fund Management", "Asset Management"], "post_time": "2022-01-10T03:47:48Z", "salary": {"currency": "HKD", "max": 44999, "min": 25000, "period": "monthly", "term": null}, "salary_visible": true, "title_keywords": ["senior officer", "admin", "manager"], "responsibilities": ["social media", "market information", "monitoring", "investment portfolios", "develop", "maintain", "plans", "asset management"], "requirements": {"degrees": [], "majors": [], "languages": [], "language_level": [], "hard_skills": [], "soft_skills": ["decision making skills", "communication and interpersonal skills", "attention to detail"], "languages_combined": []}, "experience_required": {"duration": [], "field": []}}, {"job_id": "100003008671594", "location_code": "hk", "company": "King's Cross Recruitment", "job_title": "Management Trainee (17k+)", "description": "Well established international Asset Management Firm\nExcellent Career Opportunity\nOur client is an international asset management firm with an unparalleled reputation across the Asia Pacific region. With the continued growth of the organization, the need has arisen to recruit a high calibre candidate to join them.\nAs the Subject Matter Expertise (SME) of Operations team to provide subject matter expertise and best practice advice to support daily trade management processes.\u00a0 Participating project meetings, monitoring of various project timelines to secure the respective funding requirements. Oversight and managing of investment funding process including bank account opening, funding communication and settlement for various investment projects, resolve and escalate any funding issues in a timely manner. Manage funds flow schedule with effect payments/disbursements and associated investor notices for internal Capital Calls and Distributions. Perform cash reconciliation and monitor the daily cash flows for individual Fund, include monitoring of cash calculation of Capital Call, Distribution and Return of Capital. Liaison with both internal and external key stakeholders to involve daily work for ensuring the smoothness of fund operations. Manage the relationship with fund managers, custodian banks, brokers, auditors, and internal/external counterparties to monitor the quality of services and ensure market standard practices are in place. Liaise with or oversee Fund Administrator for subscription, redemption and other requests for investors as well as assist in documents preparation for setting up or closure of private funds. Develop and maintain enhanced procedures and controls.\u00a0\u00a0\n\nTo be considered, you should be a degree holder in with a minimum of 4 years experience in asset management, private industry investment operations. Experienced with private market and real estate custodial operations, fund accounting and settlement processes.\u00a0 Direct experience working in a Private Company is an advantage. Experience and knowledge of Middle Office, Investment Operations\u2019 policies and procedures, including o oversighting of cash flow, funding processing, corporate actions and fund operations. Knowledge and experience with cash management, cash flow forecast, reconciliations, reporting and fund operations.\nInterested applicants should send a detailed resume to Kelly Kam quoting reference jdb-4571\u00a0via email.\u00a0 Please click \u201cAPPLY NOW\u201d button below\n(Applicants not contacted within 4 weeks should consider their application unsuccessful.)", "employment_types": ["Full Time", "Permanent"], "selling_points": ["Young and Fun working atmosphere", "Fast track promotion", "Work life balance"], "locations": ["Tsim Sha Tsui"], "categories": ["Banking / Finance", "Investment", "Management", "Management Trainee", "Asset Management"], "post_time": "2022-01-11T09:09:45Z", "salary": {"currency": "HKD", "max": 34999, "min": 17000, "period": "monthly", "term": null}, "salary_visible": true, "title_keywords": ["management trainee"], "responsibilities": ["operations", "quality", "communication", "maintain", "liaise with", "sme", "disbursements", "account opening", "monitor", "develop", "schedule", "forecast", "reporting", "management", "monitoring", "procedures", "reconciliations", "cash flow", "policies", "a timely manner", "payments", "asset management"], "requirements": {"degrees": ["degree holder"], "majors": [], "languages": [], "language_level": [], "hard_skills": ["account opening", "processing"], "soft_skills": ["communication", "timely", "detailed"], "languages_combined": []}, "experience_required": {"duration": ["minimum of 4 years"], "field": ["management", "investment", "asset management"]}}]