[{"job_id": "100003009054200", "location_code": "hk", "company": "First Commercial Bank, Ltd", "job_title": "Deposit / Remittance Clerk", "description": "\u4e00\u822c\u5b58\u6b3e\u6216\u532f\u514c\u90e8\u9580\u6587\u54e1\n\nMain Responsibilities:\n\nHandle\u00a0counter transactions and opening accounts etc\nPerform inward/outward remittance and document\nHandle other duties as assigned by supervisors\n\n\nRequirements:\n\nAssociate Diploma or equivalent\nGood command in written & spoken Mandarin is a must, fluent in English and Cantonese\nProficient in MS Office applications including Chinese word processing\nFresh graduates are also welcomed\n\n\nWe offer competitive salary & attractive fringe benefits package to the right candidates. Please send your full resume, expected salary to us.\n", "employment_types": ["Full Time", "Permanent"], "selling_points": ["general duties of deposit or remittance clerk", "5 days work week, double pay & bonus", "Fresh graduates are also welcome"], "locations": ["Tsim Sha Tsui"], "categories": ["Banking / Finance", "Corporate Banking", "Private Banking", "Retail Banking"], "post_time": "2022-01-17T08:47:27Z", "salary": {"currency": null, "max": null, "min": null, "period": "monthly", "term": null}, "salary_visible": false, "title_keywords": ["clerk"], "responsibilities": ["other duties", "transactions"], "requirements": {"degrees": ["diploma"], "majors": [], "languages": ["cantonese", "english", "chinese", "mandarin"], "language_level": ["proficient", "good command", "fluent"], "hard_skills": ["chinese word processing", "ms office"], "soft_skills": [], "languages_combined": [{"language": "cantonese", "language_level": ["good command", "fluent"]}, {"language": "english", "language_level": ["good command", "fluent"]}, {"language": "chinese", "language_level": ["proficient"]}, {"language": "mandarin", "language_level": ["good command", "fluent"]}]}, "experience_required": {"duration": [], "field": []}}, {"job_id": "100003009054846", "location_code": "hk", "company": "Cathay United Bank Company, Limited", "job_title": "Associate, Relationship Management - Corporate Banking", "description": "Responsibilities:\u00a0\n\n\nDeal with day-to-day clients\u2019 loan / credit applications including prepare credit analysis needed for loan origination\nPerform credit analysis and prepare credit proposals for Credit Risk Management Committee approval\nResponsible for client-on-boarding, account openings were properly controlled to fulfill all local/overseas regulations, conduct customer due diligence and conduct regular credit review\nProvide support to Relationship Managers on client management, transaction execution and key business initiatives\n\n\u00a0Ideal candidates are expected to possess:\u00a0\n\n\nUniversity degree in Banking / Finance or related discipline\nAt least 2 years\u2019 experience in Corporate Banking, with proven track record in handling syndicated loans / project finance / trade finance\nHolder of HKSFC type 1 license, prior AML/KYC experience in banking would be an advantage\nAssociate Credit Risk Management Professional (ACRP) holder an added advantage\nSelf-motivation, able to work independently with good organization skills\nGood communication skills with strong customer-focused mindset\nWe offer attractive remuneration package and comprehensive fringe benefits. Interested parties please e-mail your full resume with current and expected salary by clicking\u00a0\"Apply Now\".\u00a0\n\nPersonal information collected will be used for considering suitability for the post and strictly in accordance with our personal data policies.\u00a0 It is our policy to retain the personal data of unsuccessful applicants for future recruitment purposes for a period of maximum two years.", "employment_types": ["Full Time", "Permanent"], "selling_points": ["Bachelor\u2019s degree or above", "At least 2 years\u2019 relevant work experience", "Holder of HKSFC type 1 license"], "locations": ["Causeway Bay"], "categories": ["Banking / Finance", "Corporate Banking"], "post_time": "2022-01-17T11:42:30Z", "salary": {"currency": null, "max": null, "min": null, "period": "monthly", "term": null}, "salary_visible": false, "title_keywords": ["associate"], "responsibilities": ["regulations", "management", "provide support", "business initiatives", "aml", "kyc", "analysis", "review", "communication", "customer due diligence", "banking"], "requirements": {"degrees": ["university degree"], "majors": ["finance"], "languages": [], "language_level": [], "hard_skills": ["aml", "customer due diligence", "kyc", "credit analysis", "hksfc"], "soft_skills": ["communication skills", "work independently", "responsible", "organization skills", "customer-focused mindset", "self-motivation", "controlled", "ideal"], "languages_combined": []}, "experience_required": {"duration": ["at least 2 years"], "field": ["finance", "banking"]}}, {"job_id": "100003009054301", "location_code": "hk", "company": "OCBC Wing Hang Bank Limited", "job_title": "2022 OCBC Wing Hang Graduate Talent Programme", "description": "2022 OCBC Wing Hang Graduate\u00a0Talent Programme\n\nDesigned for graduates with up to two years of working experience who aspire to carve a career in banking, you will get a head start with our OCBC Wing Hang Graduate\u00a0Talent Programme. We have carefully designed a 24-month structured programme with an opportunity to gain exposure from front to back office of the bank to help you build a strong banking foundation to achieve your career goals in the banking industry.\n\n\n\nBy joining the Graduate Talent Programme, you will:\n\nGet onboard our 24-month accelerated career programme\nAchieve a head-start through job rotations\nDevelop broad-based banking knowledge\nBe guided by career coach / mentor\nWork on business projects\nBuild your regional network with graduates and businesses across the OCBC Group\n\n\nHere in OCBC Wing Hang Bank, we value the growth of every individual. We are here to help you take on the future of banking with us. We say that there's no better investment than the one in your own skills and growth.\n\nJoin us to become the next Graduate Talent of the future!\n\nWe seek passionate go-getters with high levels of motivation and drive, those who are interested in an accelerated career in the banking industry.\n\nRequirements\n\nA Bachelor\u2019s Degree with second upper class or above in any discipline\nLess than 2 years of working experience\nOutstanding extracurricular/internship achievements\nHighly motivated and analytical\nStrong leadership and open to new challenges and problem-solving\nTeam player with strong interpersonal and communication skills\nOpen-minded and able to work with colleagues from diverse cultures\nKeen interest in the latest development of global economy, including the Greater-Bay-Area (GBA)\nExcellent written and spoken English and Chinese, with proficiency in Putonghua would be an advantage\nIndividuals holding IANG visa are welcomed\n\nFor the 2022 Graduate Talent Programme, we are hiring for the following divisions:\n\nRetail Banking Group\nWholesale Banking Group\nTreasury\nOCBC Wing Hang Credit\nInformation Technology\nCompliance\n\nApply Now\n\nPlease submit your application\u00a0by providing your full resume, expected GPA and stating your top 3 choices of divisions.\n\nApplication ends on 3 February 2022.\n\nSelection Process\n\nOnline Application\nVideo Assessment\nOnline Aptitude & Numerical Tests\nAssessment Centre\nFinal Panel Interview\n\nProgramme Commencement Date\n\nJuly 2022", "employment_types": ["Full Time", "Permanent"], "selling_points": ["24-month accelerated career programme", "Achieve a head-start through job rotations", "Less than 2 years of working experience"], "locations": ["Sheung Wan"], "categories": ["Banking / Finance", "Corporate Banking", "Retail Banking", "Others"], "post_time": "2022-01-17T09:05:35Z", "salary": {"currency": null, "max": null, "min": null, "period": "monthly", "term": null}, "salary_visible": false, "title_keywords": [], "responsibilities": ["business projects", "compliance", "back office", "develop", "communication", "banking"], "requirements": {"degrees": ["degree", "bachelor"], "majors": [], "languages": ["putonghua", "english", "chinese"], "language_level": ["advantage", "excellent", "proficiency"], "hard_skills": ["problem-solving", "no", "go"], "soft_skills": ["passionate", "communication skills", "open-minded", "problem-solving", "interested in", "keen", "diverse", "motivated", "team player", "structured", "leadership", "interpersonal"], "languages_combined": [{"language": "putonghua", "language_level": ["proficiency", "advantage", "excellent"]}, {"language": "english", "language_level": ["advantage", "excellent"]}, {"language": "chinese", "language_level": ["advantage", "excellent"]}]}, "experience_required": {"duration": ["2 years", "two years"], "field": ["banking"]}}, {"job_id": "100003009053095", "location_code": "hk", "company": "OCBC Wing Hang Bank Limited", "job_title": "Business Compliance Manager, Corporate & Commercial Banking", "description": "Career Level\nSenior\nQualification\nDegree\nYears of Experience\n8 years\nJob Type\nFull Time\nJob Functions\nAccounting, Others, Banking / Finance, Fund Management, Professional Services, Legal & Compliance", "employment_types": ["Full Time", "Permanent"], "selling_points": ["Conduct customer due diligence reviews", "Provide advisory support", "Participate in project/ system enhancement"], "locations": ["Sheung Wan"], "categories": ["Banking / Finance", "Corporate Banking", "Others", "Professional Services", "Legal & Compliance"], "post_time": "2022-01-17T05:46:57Z", "salary": {"currency": null, "max": null, "min": null, "period": "monthly", "term": null}, "salary_visible": false, "title_keywords": ["compliance manager"], "responsibilities": ["management", "compliance", "banking"], "requirements": {"degrees": ["degree"], "majors": [], "languages": [], "language_level": [], "hard_skills": [], "soft_skills": [], "languages_combined": []}, "experience_required": {"duration": [], "field": []}}, {"job_id": "100003009053456", "location_code": "hk", "company": "Hang Seng Bank Ltd", "job_title": "Proposition Manager", "description": "Career Level\nEntry Level\nQualification\nDegree\nYears of Experience\n2 years\nJob Type\nFull Time\nJob Functions\nBanking / Finance, Corporate Banking, Others, Others, Student / Fresh Graduate / No Experience", "employment_types": ["Full Time", "Permanent"], "selling_points": [], "locations": ["Not Specified"], "categories": ["Banking / Finance", "Corporate Banking", "Loan", "Sales, CS & Business Devpt", "Business Development"], "post_time": "2022-01-17T07:00:19Z", "salary": {"currency": null, "max": null, "min": null, "period": "monthly", "term": null}, "salary_visible": false, "title_keywords": ["manager"], "responsibilities": ["banking"], "requirements": {"degrees": ["degree", "fresh graduate"], "majors": ["finance"], "languages": [], "language_level": [], "hard_skills": ["no"], "soft_skills": [], "languages_combined": []}, "experience_required": {"duration": [], "field": ["finance", "banking"]}}, {"job_id": "100003009050669", "location_code": "hk", "company": "China Construction Bank (Asia) Corporation Limited", "job_title": "Relationship Manager, Corporate Banking (China Corporate)", "description": "Responsibilities:\n\nManage and grow a portfolio of clients who need financial services and customized products to meet their financial needs and builds solid, profitable relationships with clients characterized by mutual respect, understanding and trust; works to establish his/her role as a trusted advisor\nExecute strategies to meet individual revenue targets set by the Bank and maximise the Bank\u2019s profitability\nProspect and generate new business by expanding the customer portfolio and enhancing existing relationships through identifying opportunities for cross-selling and up-tiering\nConduct credit analysis and review credit proposals with persuasive and objective arguments\nPerform credit due diligence and ensure credit and regulatory compliance\nFollow up with clients to complete loan administration work in the post credit monitoring process\nSystematically acquire relevant information to support key decisions; is particularly resourceful in securing information from a variety of sources and integrates new information into planning and/or decision-making\nDemonstrate broad knowledge of the client\u2019s industry; is aware of its benchmarks, standards, methodologies and structures; has up-to-date knowledge of client industry practices and processes and keep abreast of trends and developments\nUse analytical skills and knowledge of credit policies required to evaluate the financial condition of the clients and make recommendations for credit approval\nIdentify risks and draws conclusions from financial data for the purpose of decision-making\nConsistently applies established procedures/ practices to make financial decisions\nPerform routine account monitoring and maintain good credit quality\nDemonstrate dedication and passion for exceeding the expectations of internal / external clients, earns client loyalty through accuracy, efficiency and courtesy\nTake ownership for solving problems, engaging the appropriate associates and addressing client issues in a timely and accurate manner\nDevelop strong interpersonal alliances at appropriate levels and positively represents the company in the communities we serve\nConduct regular KYC assessment on a timely basis and to ensure client onboarding activity is complied with the AML policy and procedures\nMaintain regular visit with the clients\nIdentify, investigate and report any suspicious activities and transactions to respective units on a timely manner\n\n\u00a0Requirements:\n\nUniversity degree or equivalent, preferably in Business or Economics\nMinimum 5 years relevant banking experience in trade financing and corporate lending\nStrong business development skills and sound knowledge of banking products and services with proven analytical skills and creative problem solving skills\nProficiency in the financial services/products offered to PRC clients\nExcellent communication and interpersonal skills\nGood business acumen with good knowledge of credit and lending policies and standard\nGood command of both English and Chinese, including Putonghua\n\nApplicants who are not contacted within 8 weeks may consider their applications unsuccessful and their personal data will be retained by the bank for a period up to two years.\n\nAll information provided by applicants will be used for recruitment purposes only and will be used strictly in accordance with the bank's personal data policies, a copy of which will be provided upon request.\u00a0", "employment_types": ["Full Time", "Permanent"], "selling_points": ["Minimum 5 years banking experience (trade finance)", "Banking products and services with proven analytic", "University degree or equivalent, Business or Econ"], "locations": ["Central"], "categories": ["Banking / Finance", "Analyst", "Corporate Banking", "Credit Analysis / Approval"], "post_time": "2022-01-14T11:09:20Z", "salary": {"currency": null, "max": null, "min": null, "period": "monthly", "term": null}, "salary_visible": false, "title_keywords": ["relationship manager"], "responsibilities": ["data", "quality", "transactions", "maintain", "administration", "make recommendations", "due diligence", "compliance", "develop", "kyc", "report", "review", "monitoring", "procedures", "aml", "policies", "analysis", "a timely manner", "evaluate", "planning"], "requirements": {"degrees": ["university degree"], "majors": ["economics", "business"], "languages": ["putonghua", "english", "chinese"], "language_level": ["good command"], "hard_skills": ["problem solving skills", "acumen", "analytical skills"], "soft_skills": ["analytical skills", "communication and interpersonal skills", "business acumen", "problem solving skills", "creative"], "languages_combined": [{"language": "putonghua", "language_level": ["good command"]}, {"language": "english", "language_level": ["good command"]}, {"language": "chinese", "language_level": ["good command"]}]}, "experience_required": {"duration": ["minimum 5 years"], "field": ["financing", "banking experience"]}}, {"job_id": "100003009046568", "location_code": "hk", "company": "DBS Bank Ltd", "job_title": "KYC/CDD Specialist, Centralized Onboarding, Institutional Banking", "description": "Our client is a top tier foreign bank. They are looking for someone to join as a\u00a0Team Head - Trade & Supply Chain Finance - Trade Finance Department\n\nKey Responsibilities\n\n- Manage Financial Institution clients for the Trade & Supply Chain Finance Team.\n\n- Lead and guide junior teammates to expand and maintain current trade and receivable finance portfolio of Chinese, APAC, and Western MNCs clients\n\n- Promote cross-regional collaboration and cross-selling of other bank products with strong focus in Greater China Region\n\n- Responsible for the credit quality\n\nRequirements\n\n- University Degree Holder in Business, Economics or related disciplines\n\n- Minimum of 10 years\u2019 relevant experience in trade finance with a preference with regional Trade Supply Chain Finance experience.\u00a0\n\n- Good credit\u00a0knowledge in Trade Finance\n\n- Fluent in English, Cantonese and Mandarin\n\n- Prior team management experience\n\n\n*We offer*\n\n\"Interested candidates, please send an updated CV to kelvin.lam @jac-recruitment.com\n\nPersonal data collected will be used for employment-related purpose only. We regret to inform that only shortlisted candidates will be notified.", "employment_types": ["Full Time"], "selling_points": ["See job description.", "See job description.", "See job description."], "locations": ["Quarry Bay"], "categories": ["Banking / Finance", "Corporate Banking"], "post_time": "2022-01-13T14:25:55Z", "salary": {"currency": null, "max": null, "min": null, "period": "monthly", "term": null}, "salary_visible": false, "title_keywords": ["specialist"], "responsibilities": ["maintain", "quality", "finance team"], "requirements": {"degrees": ["university degree"], "majors": ["related disciplines", "economics", "business"], "languages": ["cantonese", "english", "mandarin"], "language_level": ["fluent"], "hard_skills": [], "soft_skills": [], "languages_combined": [{"language": "cantonese", "language_level": ["fluent"]}, {"language": "english", "language_level": ["fluent"]}, {"language": "mandarin", "language_level": ["fluent"]}]}, "experience_required": {"duration": ["minimum of 10 years"], "field": ["management", "finance", "supply chain", "relevant experience", "team"]}}, {"job_id": "100003009050215", "location_code": "hk", "company": "Nanyang Commercial Bank", "job_title": "Product Management Manager (Corporate Banking Product) (Ref: UA8020 -CB-JDB)", "description": "Our client, a\u00a0Online Game company is looking for candidates\u00a0Japanese Customer Support Agent.\n\nResponsibilities:\n\n\n\nNurture and support player relationships via phone, e-mail, and live chat.\nSeek resolutions to customer queries and issues whilst maintaining a personalized and caring attitude.\nAssist in the alignment of promotions across all customer communication channels.\nReceive, handle, and translate customers\u2019 KYC documents.\nAssist in English to Japanese translation work for new games and promotions.\nAssist in various ad-hoc projects and tasks.\n\nRequirements:\n\n\n\nNative level of written and spoken Japanese.\nIntermediate to fluent level of written and spoken English.\nAbility to listen and come up with solutions to customer problems.\nStrong communication and interpersonal skills.\nAbility to work independently and as part of a team.\nWork well under pressure.\nGeneral PC skills (Microsoft Word and Excel).\nBe flexible when it comes to working hours and able to work on a five day a week shift basis.\u00a0\n\n\u00a0Interested candidates, kindly send your detailed resume in MS Word including:\n\n1) Expected salary\n2) Current and last drawn salaries\n3) Reason for leaving current and past employments\n\u00a0\ndirectly to:\u00a0jac.hk\u00a0@jac-recruitment.com and CC to:\u00a0akihisa.watanabe\u00a0@jac-recruitment.com\n\nPersonal data collected will be used for employment-related purpose only. We regret to inform that only shortlisted candidates will be notified, thank you", "employment_types": ["Full Time", "Permanent"], "selling_points": ["Participate in workflow design", "Manage product development and enhancement", "At least 5 years banking experience"], "locations": ["Central & Western Area"], "categories": ["Banking / Finance", "Corporate Banking", "Investment", "Marketing / Public Relations", "Marketing - Brand / Product Management"], "post_time": "2022-01-15T03:50:56Z", "salary": {"currency": null, "max": null, "min": null, "period": "monthly", "term": null}, "salary_visible": false, "title_keywords": ["manager"], "responsibilities": ["maintaining", "communication", "kyc", "customer queries", "ad-hoc projects"], "requirements": {"degrees": [], "majors": [], "languages": ["japanese", "english"], "language_level": ["native", "fluent", "intermediate"], "hard_skills": ["excel", "pc skills", "microsoft word"], "soft_skills": ["flexible", "work independently", "communication and interpersonal skills", "under pressure"], "languages_combined": [{"language": "japanese", "language_level": ["native"]}, {"language": "english", "language_level": ["fluent", "intermediate"]}]}, "experience_required": {"duration": [], "field": []}}, {"job_id": "100003009050345", "location_code": "hk", "company": "Nanyang Commercial Bank", "job_title": "Senior Clerk (Accounting) (Secondment Contract) (Ref: HC8031-00-JDB)", "description": "OverviewOur client, a prestigious Japanese bank, is looking for a\u00a0Analyst (Market Support)\n\nCompany Location:Central\n\nWorking Days:Mon-Fri (9:00 am ~5:30pm)\n\nCompany Business:Japanese Bank\n\nLanguages Required:Cantonese, English, Mandarin, Japanese\n\nJOB DUTIES\n\nTo handle instructions and enquires in relation to client transactions in a timely and orderly manner to ensure quality service is delivered.\nTo work closely with clients, relationship managers and Operations Departments to ensure client transactions are completed efficiently and accurately.\nTo follow up pending items by contacting clients regularly to avoid overdue of tasks.\nTo prepare control sheet for unprocessed documents and follow up the settlement in a timely manner.\nTo act as the 1st line of defense and ensure all transactions are in compliance with internal policies, AML, sanctions and other regulatory requirements.\nTo prepare AML related reports and relevant documents to facilitate KYC and transaction monitoring processes.\nTo support the implementation and delivery of enhancement initiatives of the Business Unit according to the predetermined schedule.\nTo maintain good working knowledge of procedural changes, products, relevant rules and regulations.\n\nREQUIREMENTS\n\nUniversity graduate\nWith 1 to 3 years\u2019 relevant experience in banking or financial institutions is preferable\nGood command of written and spoken Japanese and English\n\nPACKAGE\n\nDiscretionary bonus\nMedical insurance\nBirthday leave\nWork from Home Policy\nExamination Leave\nVolunteer Leave\nPaid Sick Leave\nFlexible working Hour\nBonus\n\n1) Expected salary\n2) Current and last drawn salaries\n3) Reason for leaving current and past employments\n\u00a0\ndirectly to:\u00a0jac.hk\u00a0@jac-recruitment.com and CC to:\u00a0daniel.ng\u00a0@jac-recruitment.com\n\n\u00a0\nPersonal data collected will be used for employment-related purpose only. We regret to inform that only shortlisted candidates will be notified, thank you", "employment_types": ["Full Time", "Contract"], "selling_points": ["General accounting duties", "Eager to learn and able to work independently", "Diploma holder or above in any disciplines"], "locations": ["Not Specified"], "categories": ["Accounting", "Accounting Clerk / Supervisor", "Banking / Finance", "Corporate Banking"], "post_time": "2022-01-15T03:51:00Z", "salary": {"currency": null, "max": null, "min": null, "period": "monthly", "term": null}, "salary_visible": false, "title_keywords": ["accounting", "senior clerk"], "responsibilities": ["regulations", "control", "aml", "operations", "policies", "compliance", "a timely manner", "quality", "transactions", "regulatory requirements", "monitoring", "implementation", "maintain", "reports", "schedule", "kyc"], "requirements": {"degrees": ["university graduate"], "majors": [], "languages": ["japanese", "english"], "language_level": ["good command"], "hard_skills": ["inform", "reason"], "soft_skills": ["flexible"], "languages_combined": [{"language": "japanese", "language_level": ["good command"]}, {"language": "english", "language_level": ["good command"]}]}, "experience_required": {"duration": ["1 to 3 years"], "field": ["financial institutions", "relevant experience", "banking"]}}, {"job_id": "100003009045157", "location_code": "hk", "company": "Hang Seng Bank Ltd", "job_title": "Assistant CDD Approval Manager (New-to-Bank)", "description": "Responsibilities:\nPerform customer segmentation and profile analysis through advanced statistical modeling / data mining / AI & ML technologies to provide insight for segment strategy and identify business opportunities\nDevelop and enhance propensity / predictive models to support CRM strategies related to change of customer behavior or specific event trigger, eg. customer acquisition, upgrade and retention\nCompile MIS reports and conduct analysis across customer, product and channel perspectives to identify potential customer and deliver actionable insights and recommendations to business units for developing portfolio and product strategy\nAssist business units in applying propensity / predictive model and customer segmentation model in marketing campaign to drive business performance, evaluate and enhance model effectiveness to improve campaign efficiency\nDevelop and enhance MIS report automation to help improve campaign efficiency\nRequirements:\nDegree or above with major in quantitative, numerical science or related discipline\n3+ years' experience relating to data analytics\nProficiency in SAS, Python, R or similar analytically oriented programming languages,\u00a0 experience in model development covering segmentation, acquisition, attrition, cross-selling and related applications\nExperience in Banking, Financial Services or FinTech industry preferred\nA mature self-starter with strong drive, motivation, committed with good business sense and strong understanding of the personal banking market\nExcellent interpersonal and communication skills with excellent written and spoken English and Chinese, knowledge of Mandarin would be a definite advantage\nLess experience will be considered as our Deputy/Assistant Customer Analytics & Data Science Manager", "employment_types": ["Full Time", "Permanent"], "selling_points": [], "locations": ["Not Specified"], "categories": ["Banking / Finance", "Corporate Banking", "Risk Management"], "post_time": "2022-01-13T07:20:11Z", "salary": {"currency": null, "max": null, "min": null, "period": "monthly", "term": null}, "salary_visible": false, "title_keywords": ["manager", "assistant"], "responsibilities": ["predictive models", "identify business opportunities", "analysis", "developing", "develop", "evaluate", "reports", "data mining", "report"], "requirements": {"degrees": ["degree or above"], "majors": ["science"], "languages": ["english", "chinese", "mandarin"], "language_level": ["advantage", "excellent"], "hard_skills": ["sas", "data analytics", "programming", "python", "r"], "soft_skills": ["communication skills", "business sense", "mature", "committed", "interpersonal"], "languages_combined": [{"language": "english", "language_level": ["advantage", "excellent"]}, {"language": "chinese", "language_level": ["advantage", "excellent"]}, {"language": "mandarin", "language_level": ["advantage", "excellent"]}]}, "experience_required": {"duration": ["3+ years"], "field": ["related", "development", "financial services", "programming", "banking"]}}, {"job_id": "100003009038637", "location_code": "hk", "company": "Bangkok Bank Public Co Ltd", "job_title": "Counter Service Assistant / Teller (Ref: CS-26/185/240-DB)", "description": "Responsibilities\n\nFormulate effective cross-border strategies and plans based on management\u2019s direction\nPerform project management from planning to executing different project plans, especially for projects in both China and overseas regions, and ensure that all projects are implemented on schedule with defined quality standards\nAssist management to evaluate the results of different cross-border programs, prepare relevant reports and proposals with professional recommendations and workable solutions for management to improve the overall business performance, and to manage cross-border customer segment and drive marketing programs to build customer portfolio\nLiaise with product managers to come up with suitable training materials and to make enhancement with feedback from sales team\nConduct regular review & analysis on sales performance in order to provide advice or suggestion for sales team to improve as well as to achieve the targets\nEnsure all works are complied with internal and external policies and rules\nBuild the relationship of business linkage with Mother Bank, Act as a key coordinator for both external and internal business partners\n\nRequirements\n\nDegree or above with major in Business Administration, Marketing, Economics, Finance or related discipline\nAt least 3- 5 years working experience in segment management and business strategy management, including 2 years of which in managerial level and retail banking business\nProfound knowledge and experience in Business development / Marketing planning\nKnowledge in projects about China financial industry and experience in China project management\nWith good people network in China and ability to communicate with Chinese financial entities independently\nExcellent communication and negotiation skills with good command of English and Chinese. Proficiency in Mandarin is a must\nProficient in using Microsoft Office ( Excel, PowerPoint and Word)\nLess experience will be considered as Business Development Manager", "employment_types": ["Full Time"], "selling_points": [], "locations": ["Central"], "categories": ["Banking / Finance", "Corporate Banking", "Retail Banking", "Financial Services"], "post_time": "2022-01-14T09:36:05Z", "salary": {"currency": null, "max": null, "min": null, "period": "monthly", "term": null}, "salary_visible": false, "title_keywords": ["assistant"], "responsibilities": ["relevant reports", "management", "sales performance", "analysis", "policies", "quality", "evaluate", "project management", "regular review", "provide advice", "executing", "schedule", "sales team", "liaise with", "plans", "planning"], "requirements": {"degrees": ["degree or above"], "majors": ["finance", "economics", "marketing", "business administration"], "languages": ["english", "chinese", "mandarin"], "language_level": ["excellent", "good command", "proficiency", "good"], "hard_skills": ["excel", "microsoft office", "word", "powerpoint", "project management"], "soft_skills": ["communication", "project management", "negotiation skills", "independently"], "languages_combined": [{"language": "english", "language_level": ["excellent", "good command", "good"]}, {"language": "chinese", "language_level": ["excellent", "good command", "good", "good"]}, {"language": "mandarin", "language_level": ["proficiency"]}]}, "experience_required": {"duration": ["2 years", "at least 3- 5 years"], "field": ["managerial", "management", "retail banking", "business development", "financial industry", "project management", "business", "marketing", "planning"]}}, {"job_id": "100003009050453", "location_code": "hk", "company": "Industrial Bank of Korea", "job_title": "Remittance Clerk", "description": "Responsibilities:\nDevelop and maintain group-wide human resources strategies, HR budget, C&B schemes and\u00a0 remuneration policies, and especially participate in the management of Southeast Asia subsidiaries, including:\nReview, analyze, and co-ordinate the manpower planning of the Southeast Asia subsidiaries\nAnnual HR budgeting and allocation in accordance with the group\u2019s manpower strategy, bonus and salary review plans, and annual bonus and salary review budgeting and allocation\nStudy, formulate and execute the HR budget control mechanism\nStudy, establish and maintain rewards management policies and staff wellness programs\nConduct due diligence on Southeast Asia subsidiaries\u2019 C&B policies and management initiatives\nConduct job matching and participate various compensation and benefits surveys in both HK and Southeast Asia\nStudy, establish and maintain human resources management mechanism\nOther ad-hoc projects\nRequirements:\nDegree with major in Human Resources Management, Finance and Economics, Accounting, Business Administration or relevant discipline\nAt least 3-4 years working experience in C&B, preferably in regional bank\nFamiliar with statutory and compliance requirements including Employment Ordinance and other relevant laws and regulations for Hong Kong and Southeast Asia\nGood analytical, presentation and communication skills required\nExcellent Chinese and English writing skills required and preferably fluent in Mandarin and English speaking", "employment_types": ["Full Time", "Permanent"], "selling_points": [], "locations": ["Admiralty"], "categories": ["Banking / Finance", "Corporate Banking", "Others", "Order Processing & Operation / Settlement"], "post_time": "2022-01-14T10:27:17Z", "salary": {"currency": null, "max": null, "min": null, "period": "monthly", "term": null}, "salary_visible": false, "title_keywords": ["clerk"], "responsibilities": ["due diligence", "management", "policies", "hr", "budget", "review", "budgeting", "develop", "maintain", "plans", "budget control", "planning"], "requirements": {"degrees": [], "majors": [], "languages": [], "language_level": [], "hard_skills": [], "soft_skills": [], "languages_combined": []}, "experience_required": {"duration": [], "field": []}}, {"job_id": "100003009049748", "location_code": "hk", "company": "China Construction Bank (Asia) Corporation Limited", "job_title": "Assistant Manager, Transaction Monitoring (1-year Contract)", "description": "Responsibilities:\nAssist Business Strategy Manager to achieve responsible tasks\nWork closely with IT and Business Managers for Omni Channel / O2O / Fintech application development initiatives\nAnalyse users initiatives and recommend best practice solutions to achieve excellent customer experience\nSupport project manager to manage project schedule, deliverables and reporting\nPrepare documentation on user requirements, operating procedures and operating guideline\nDevelop the user acceptance test plan and test details and carry out the user acceptance test\nSupport system management as system owner\nConduct feasibility studies, industry benchmarking whenever necessary\nRequirements:\nDegree holder or above with major in Business Administration, e-Commerce, Information Technology or related disciplines\nAt least 1 year of experience in banking industry and e-banking development areas with exposure to project management on Personal & Corporate Banking online channels or fintech application is highly desirable\nBe a good team player and self-motivated with strong analytical mindset\nGreat Chinese and English writing skills\nProficient in both spoken English and Chinese (Cantonese and Mandarin)\nCandidates with less experience will be considered as Assistant Business Strategy Manager", "employment_types": ["Full Time", "Permanent"], "selling_points": ["AML Compliance", "Transaction Monitoring", "customer due diligence assessment / reassessment"], "locations": ["Kowloon Bay"], "categories": ["Banking / Finance", "Corporate Banking", "Retail Banking", "Professional Services", "Legal & Compliance"], "post_time": "2022-01-14T09:11:29Z", "salary": {"currency": null, "max": null, "min": null, "period": "monthly", "term": null}, "salary_visible": false, "title_keywords": ["assistant manager,"], "responsibilities": ["reporting", "management", "procedures", "develop", "schedule", "plan", "documentation", "application development", "analyse"], "requirements": {"degrees": ["degree holder"], "majors": ["related disciplines", "business administration", "information technology", "e-commerce"], "languages": ["cantonese", "english", "chinese", "mandarin"], "language_level": ["proficient"], "hard_skills": ["project management", "writing skills", "e-commerce"], "soft_skills": ["project management", "good team player", "self-motivated", "writing skills"], "languages_combined": [{"language": "cantonese", "language_level": ["proficient"]}, {"language": "english", "language_level": ["proficient"]}, {"language": "chinese", "language_level": ["proficient"]}, {"language": "mandarin", "language_level": ["proficient"]}]}, "experience_required": {"duration": ["at least 1 year"], "field": ["banking industry", "development", "project management", "business", "banking"]}}, {"job_id": "100003009049902", "location_code": "hk", "company": "HSBC Group", "job_title": "Assistant Manager, Customer Care - Wealth & Personal Banking", "description": "Responsibilities\n\nAssist the District with implementation of sales strategies in order to achieve the insurance business target\nAssist the branch sales staff in provision of professional wealth management services, strengthening customer relationship and providing support on insurance business\n\nAssist in enhancing insurance business productivity of the District by sharing experience and cooperating with branch sales staff\n\nRequirements\n\nDegree holder or above, with 2-year relevant experience in insurance industry (candidates with more experience would be considered for Senior Insurance Specialist)\nQualifications in IIQE\nHolders of CB Professional Qualifications and/or Awards will be preferred\nQualifications in CFA / CFP / CFMP / LMI / other financial or life-insurance related international qualifications preferred\nSensitive to market trend and sound knowledge in insurance business, with experience in working with sales teams in banking industry an advantage\nGood command of spoken and written English, Cantonese and Putonghua\nStrong communication, presentation and interpersonal skills\nGood PC skills and Chinese input", "employment_types": ["Full Time"], "selling_points": ["One of the world's leading international banks.", "Excellent Career Progression.", "Team Based Work Culture."], "locations": ["Kowloon City"], "categories": ["Banking / Finance", "Corporate Banking", "Private Banking"], "post_time": "2022-01-14T09:26:15Z", "salary": {"currency": null, "max": null, "min": null, "period": "monthly", "term": null}, "salary_visible": false, "title_keywords": ["personal", "assistant manager,"], "responsibilities": ["management", "insurance", "implementation", "providing support"], "requirements": {"degrees": ["degree holder"], "majors": ["insurance"], "languages": ["cantonese", "putonghua", "english", "chinese"], "language_level": ["good command", "good"], "hard_skills": ["chinese input", "iiqe", "professional qualifications", "cfa", "pc skills"], "soft_skills": ["communication", "sensitive to", "interpersonal skills", "presentation"], "languages_combined": [{"language": "cantonese", "language_level": ["good command", "good"]}, {"language": "putonghua", "language_level": ["good command", "good"]}, {"language": "english", "language_level": ["good command", "good"]}, {"language": "chinese", "language_level": ["good"]}]}, "experience_required": {"duration": ["2-year"], "field": ["banking industry", "insurance industry", "business", "relevant experience", "insurance"]}}, {"job_id": "100003009043492", "location_code": "hk", "company": "DBS Bank Ltd", "job_title": "Analyst/ Senior Officer/ Officer, Custody Operations", "description": "Responsibilities:\nConduct analysis on a regular basis, analyze customer demand for banking products and services, collect market information, gain insight into market trends, plan and manage strategies for each customer segment\nAssist in regular customer behavior and business analysis of each customer segment, including but not limited to using various analytical tools to provide information on the segmentation and customer behavior changes\nAssist in formulating and implementing the high and mid customer segment strategies, including sales scripts and training material, to achieve the business targets\nAssist in the launch of various marketing promotions such as customer acquisition, cross-selling, up-selling, aiming to develop potential/high value customer segmentation, and to monitor the target achievement for each promotion on a regular basis\nAccording to customer's needs and deepening of the product penetration, establish and recommend the product portfolio and pricing strategy for specific customer segment\nConduct post campaign evaluation and analysis; deliver timely and right cross-sell plan, closely align with external partner to maximize business result\nEnsure the effective communication between departments in order to achieve targets for each initiative\nProactively working with product managers and channel management, aiming to improve customer revenue contribution, and ensure marketing management strategies are properly implemented\nWorking along the bank strategy and cross collaboration with partners, proactively recommend and review effective measures to improve revenue and achieve targets for the Bank\nRequirements:\nDegree or above in Business Administration, Marketing, Finance, Statistics or related disciplines\n8\u00a0years or above experience in financial industry\nA mature self-starter with strong drive, motivation and committed with good business sense and problem solving skills\nExcellent communication and presentation skills with good command of both written and spoken English and Chinese, knowledge of Mandarin would be a definite advantage\nProficiency in MS Excel and Access\nLess experience will be considered as Segment Management Manager", "employment_types": ["Full Time"], "selling_points": ["Experience in custody Operation is an advantage", "Fresh Graduate are also welcome", "See job description."], "locations": ["Admiralty"], "categories": ["Banking / Finance", "Corporate Banking", "Order Processing & Operation / Settlement"], "post_time": "2022-01-12T14:25:43Z", "salary": {"currency": null, "max": null, "min": null, "period": "monthly", "term": null}, "salary_visible": false, "title_keywords": ["analyst", "senior officer", "officer", "operations"], "responsibilities": ["achieve targets", "management", "market information", "evaluation", "analysis", "review", "monitor", "develop", "communication", "marketing promotions", "plan", "banking", "business analysis"], "requirements": {"degrees": ["degree or above"], "majors": ["business administration", "finance", "statistics", "related disciplines", "marketing"], "languages": ["english", "chinese", "mandarin"], "language_level": ["advantage", "excellent", "good command"], "hard_skills": ["problem solving skills", "ms excel"], "soft_skills": ["business sense", "mature", "communication", "committed", "presentation skills", "problem solving skills"], "languages_combined": [{"language": "english", "language_level": ["advantage", "excellent", "good command"]}, {"language": "chinese", "language_level": ["advantage", "excellent", "good command"]}, {"language": "mandarin", "language_level": ["advantage", "excellent", "good command"]}]}, "experience_required": {"duration": ["8 years"], "field": ["management", "financial industry"]}}, {"job_id": "100003009048735", "location_code": "hk", "company": "Hang Seng Bank Ltd", "job_title": "Assistant Manager, Control Office", "description": "Responsibilities:\nLead the team to design and implement talent acquisition plans, manage and implement end-to-end recruitment processes, including but not limited to campus and experienced hires recruitment\nProvide consultation to hiring managers on all aspects of the hiring process, including hiring strategies, recruitment cycle timing, coaching and guidance on best practices and sourcing trends\nManage and work with recruitment agencies for specialist and secondment placements\nDevelop and utilize different channels / platforms for employer branding and talent sourcing\nProvide advice and support on the talent sourcing and onboarding exercises of Southeast Asian entities\nManage projects related to recruitment process streamlining, assessment tools review and revamp, workflow digitalization and automation, etc.\nRequirements:\u00a0\u00a0\nDegree in Human Resources Management, Business Administration or related disciplines\nAt least 7 years\u2019 relevant experience, preferably in banking or financial institutions\nFamiliar with candidate assessments, hiring intelligence and technology application\nSound knowledge of Employment Ordinance and other relevant laws and regulations\nStrong analytical, interpersonal and communication skills\nProficient in computer applications (MS Word, Excel, PowerPoint, etc)\nProficient in both spoken and written English and Chinese, proficiency in Putonghua is a plus", "employment_types": ["Full Time", "Permanent"], "selling_points": [], "locations": ["Not Specified"], "categories": ["Banking / Finance", "Corporate Banking", "Risk Management"], "post_time": "2022-01-14T08:35:17Z", "salary": {"currency": null, "max": null, "min": null, "period": "monthly", "term": null}, "salary_visible": false, "title_keywords": ["assistant manager,"], "responsibilities": ["guidance", "revamp", "review", "design", "develop", "provide advice", "recruitment", "manage projects", "plans", "recruitment process"], "requirements": {"degrees": ["degree"], "majors": ["related disciplines", "business administration"], "languages": ["putonghua", "english", "chinese"], "language_level": ["proficiency", "proficient"], "hard_skills": ["excel", "plus", "powerpoint", "ms word"], "soft_skills": ["communication skills", "interpersonal"], "languages_combined": [{"language": "putonghua", "language_level": ["proficiency", "proficient"]}, {"language": "english", "language_level": ["proficient"]}, {"language": "chinese", "language_level": ["proficient"]}]}, "experience_required": {"duration": ["at least 7 years"], "field": ["financial institutions", "relevant experience", "banking"]}}, {"job_id": "100003009046004", "location_code": "hk", "company": "DBS Bank Ltd", "job_title": "Product Sales, Securities & Fiduciary Services, GTS", "description": "\u5d17\u4f4d\u8077\u8cac\n\nDeliver quality customer services through counter transactions\n\u6253\u9020\u5206\u884c\u4e00\u7ad9\u5f0f\u5c08\u696d\u91d1\u878d\u7406\u8ca1\u670d\u52d9\nSupport back-end branch operations\n\u8655\u7406\u5ba2\u6236\u6bcf\u65e5\u6ac3\u53f0\u4ea4\u6613(\u5305\u62ec\u73fe\u91d1\u6536\u4ed8\u3001\u5165\u7968\u3001\u8f49\u5e33\u3001\u5b9a\u671f\u3001\u532f\u6b3e\u7b49\u7684\u5de5\u4f5c)\u3001\u5ba2\u6236\u67e5\u8a62\u53ca\u5167\u90e8\u6587\u66f8\u5de5\u4f5c\nCross-sell retail banking products\n\u92b7\u552e\u53ca\u8f49\u4ecb\u5de5\u4f5c\n\u5d17\u4f4d\u8981\u6c42\n\nSecondary School graduate or above\n\u4e2d\u5b78\u6587\u6191\u6216\u4ee5\u4e0a\u7a0b\u5ea6\nStrong sales and service orientation with outgoing personality and good communication skills\n\u5177\u826f\u597d\u7684\u6e9d\u901a\u6280\u5de7\u53ca\u5ba2\u6236\u670d\u52d9\u610f\u8b58\nProficiency in English and Cantonese as well as fluency in Putonghua\n\u5177\u826f\u597d\u7684\u4e2d\u3001\u82f1\u6587\u95b1\u8b80\u3001\u66f8\u5beb\u53ca\u666e\u901a\u8a71\u8868\u9054\u80fd\u529b", "employment_types": ["Full Time"], "selling_points": ["See job description.", "See job description.", "See job description."], "locations": ["Central"], "categories": ["Banking / Finance", "Corporate Banking", "Fund Management"], "post_time": "2022-01-13T09:25:54Z", "salary": {"currency": null, "max": null, "min": null, "period": "monthly", "term": null}, "salary_visible": false, "title_keywords": ["sales"], "responsibilities": ["operations", "quality", "transactions", "customer services", "communication", "banking"], "requirements": {"degrees": [], "majors": [], "languages": ["cantonese", "putonghua", "english"], "language_level": ["fluency", "proficiency"], "hard_skills": [], "soft_skills": ["outgoing personality", "communication skills"], "languages_combined": [{"language": "cantonese", "language_level": ["proficiency"]}, {"language": "putonghua", "language_level": ["fluency", "proficiency"]}, {"language": "english", "language_level": ["fluency", "proficiency"]}]}, "experience_required": {"duration": [], "field": []}}, {"job_id": "100003009049313", "location_code": "hk", "company": "China Merchants Securities International Company Limited", "job_title": "Vice President, Compensation & Benefits", "description": "Job Responsibilities\uff1a\n\nManage full spectrum of C&B functions including\u00a0monthly payroll, MPF, overtime allowances, annual tax returns, leave administration, benefits administration, employee termination, final payment reports and other C&B related matters\nProvide strategic advice and assist department head to drive and implement C&B cycles - \u00a0reviewing and enhancing the incentive/bonus scheme, performing the annual salary review, promotion, salary survey, grading structure review, headcount planning and budgeting, etc\nAssist to formulate, review and implement C&B related policies and strategies from time to time\nCompile HR reports on a regular basis for management review\nWork closely with Mainland Headquarter and involve in relevant projects\nPerform ad-hoc projects as assigned\n\nJob Requirements:\n\nDegree holder in Human Resources, Business Administration, or equivalent disciplines\n8-12 years of C&B experience gained from reputable financial institutions with sound experience on working with Mainland headquarter\nFamiliar with labour ordinances or other relevant ordinance and regulatory requirements\nDetailed minded, with good communication and analytical skills\nEnjoy teamwork, responsible and proactive, with pleasant personality\nAble to complete tasks within required time frame and respond effectively under pressure\nExcellent communication in both written and spoken Chinese (Mandarin a MUST) and English\n\nWe offer attractive remuneration and benefits including 5-day working week to the right candidates. Interested parties, please send your full resume including your\u00a0CURRENT\u00a0and\u00a0EXPECTED\u00a0salary to us by email.\u00a0\n\nPersonal data provided will be used by us for recruitment and related purposes, which is strictly in accordance with the Personal Data (Privacy) Ordinance (Cap. 486 of the Laws of Hong Kong) for Applicants for Employment. Applicants who are not contacted within 6 weeks may consider your applications unsuccessful and the personal data collected will be destroyed after 2 years or such other period as prescribed by the applicable laws.\n\n\u6709\u610f\u7533\u8acb\u8005\u8acb \u6309 APPLY NOW\u7533\u8acb\n\n", "employment_types": ["Full Time"], "selling_points": [], "locations": ["Kwun Tong"], "categories": ["Banking / Finance", "Corporate Banking", "Admin & HR", "Compensation & Benefits", "Management", "Top Executives (CEO, CFO, CTO, GM, MD etc.)"], "post_time": "2022-01-14T08:27:35Z", "salary": {"currency": null, "max": null, "min": null, "period": "monthly", "term": null}, "salary_visible": false, "title_keywords": ["vice president"], "responsibilities": ["tax", "mpf", "budgeting", "policies", "review", "hr reports", "payment", "planning", "reports", "ad-hoc projects", "payroll", "management review", "administration"], "requirements": {"degrees": ["degree holder"], "majors": ["business administration"], "languages": ["english", "chinese", "mandarin"], "language_level": ["excellent"], "hard_skills": ["analytical skills"], "soft_skills": ["under pressure", "responsible", "teamwork", "analytical skills", "communication", "pleasant", "proactive", "detailed"], "languages_combined": [{"language": "english", "language_level": ["excellent"]}, {"language": "chinese", "language_level": ["excellent"]}, {"language": "mandarin", "language_level": ["excellent"]}]}, "experience_required": {"duration": ["8-12 years"], "field": ["financial institutions"]}}, {"job_id": "100003009049921", "location_code": "hk", "company": "Nanyang Commercial Bank", "job_title": "Anti-Money Laundering Manager \u2013 Advisory and Compliance Review (Ref: KC8022-AC-JDB)", "description": "Assist in developing and implementing an effective AML/CFT compliance framework across the bank;\nProvide advisory support to business units and relevant stakeholders in both Hong Kong and China on the implementation and regular review of AML/CFT policies and procedures;\nProvide technical support to the Bank\u2019s AML system/ customer risk assessment model such as handling of user enquiries, collaboration with Business Analyst and troubleshooting application incident;\nReview enhanced due diligence for high risk customers;\nEnsure compliance with relevant AML regulations and continuous improvement of AML/CFT controls through compliance reviews;\nHandle AML-related inquiries from regulators and other stakeholders;\nParticipate in AML/CFT related ad-hoc projects as assigned.\n\nRequirements:\n\nDegree holder in Finance, Law, Accounting, Business Administration or related disciplines;\nA minimum of 5 years of relevant experience in AML/CFT compliance with good understanding and application of regulatory requirements in both Hong Kong and China;\nExposure in project experience/ technical support in implementing and maintaining customer risk assessment model;\nIndependent, good team player, analytical mind with sound communication and interpersonal skills;\nProficient in both spoken and written English and Chinese, fluent in Putonghua is preferable;\nHolder of AAMLP or CAMS would be an advantage.\n\n(Candidate with less experience will be considered as\u00a0Assistant Anti-Money Laundering Manager \u2013 Advisory and Compliance Review.)\n\nIf you are flexible enough and zeal for a harmonious and supportive working environment where enables you to grow and succeed professionally, please send a full resume indicating your public examination results (HKCEE and HKALE / HKDSE), your present and expected salary and quoting reference number attention to\u00a0Talent Acquisition Division, Nanyang Commercial Bank, 151 Des Voeux Road Central, Hong Kong or apply through email. For details, please visit https://www.ncb.com.hk/ and select the page Recruit.\n\nWe are an Equal Opportunities Employer. Data collected would be used for recruitment purposes only. Applicants who do not hear from us within 8 weeks may consider their applications unsuccessful and their data will be destroyed within 12 months of receipt.", "employment_types": ["Full Time", "Permanent"], "selling_points": ["developing and implementing an effective AML/CFT", "Provide technical support to the Bank\u2019s AML system", "5 years of relevant experience in AML/CFT"], "locations": ["Central & Western Area"], "categories": ["Banking / Finance", "Corporate Banking", "Retail Banking", "Professional Services", "Legal & Compliance"], "post_time": "2022-01-15T03:50:40Z", "salary": {"currency": null, "max": null, "min": null, "period": "monthly", "term": null}, "salary_visible": false, "title_keywords": ["manager"], "responsibilities": ["regulations", "data", "regulatory requirements", "troubleshooting", "regular review", "communication", "ad-hoc projects", "administration", "due diligence", "maintaining", "compliance", "developing", "implementation", "review", "procedures", "aml", "technical support", "policies", "ensure compliance", "recruitment"], "requirements": {"degrees": ["hkdse", "degree holder"], "majors": ["business administration", "law", "finance", "related disciplines", "accounting"], "languages": ["putonghua", "english", "chinese"], "language_level": ["fluent", "proficient"], "hard_skills": ["cft", "aml", "anti-money laundering", "aamlp"], "soft_skills": ["flexible", "good team player", "supportive", "independent", "harmonious", "troubleshooting", "analytical mind", "communication and interpersonal skills"], "languages_combined": [{"language": "putonghua", "language_level": ["fluent", "proficient"]}, {"language": "english", "language_level": ["fluent", "proficient"]}, {"language": "chinese", "language_level": ["fluent", "proficient"]}]}, "experience_required": {"duration": ["minimum of 5 years"], "field": ["compliance", "relevant experience"]}}, {"job_id": "100003009050666", "location_code": "hk", "company": "China Construction Bank (Asia) Corporation Limited", "job_title": "Credit Support Specialist, Limits Control & Services", "description": "Responsibilities:\n\n\n- Perform maker function of data capture for approved customer credit facilities and credit related information to\u00a0various banking\u00a0systems.\n- Control and monitor risk limits for complying with internal/regulatory requirements.\n- Implement credit related projects, e.g. credit risk system enhancement, etc.\n- Perform user acceptance tests for\u00a0new systems.\n- Respond to business units\u2019 inquiries on credit limit-related issue.\n- Prepare credit portfolio management reports.\n\nRequirements:\n- Higher\u00a0Diploma / \u00a0DSE graduate or above.\n- Familiarize with data input of banking systems, ideally covering commercial, consumer banking & treasury businesses.\n- Knowledge of PC software application preferably Excel, Access.\n- Minimum 3 years' relevant experience in banking industry.\n- Strong communication & interpersonal skills.\n- Proactive, hard-working\u00a0and self-motivated.\n- Good command of written and spoken English and Chinese, preferably proficiency with Putonghua.\n\n\nAll information provided by applicants will be used for recruitment purposes only and will be used strictly in accordance with the bank's personal data policies, a copy of which will be provided upon request.\u00a0", "employment_types": ["Full Time", "Permanent"], "selling_points": ["Data capture in banking system & perform maker", "Prepare credit portfolio management reports", "HD / DSE holder, 3-year working experience"], "locations": ["Kowloon Bay"], "categories": ["Banking / Finance", "Corporate Banking", "Retail Banking", "Risk Management"], "post_time": "2022-01-14T11:09:19Z", "salary": {"currency": null, "max": null, "min": null, "period": "monthly", "term": null}, "salary_visible": false, "title_keywords": ["specialist"], "responsibilities": ["control", "data", "regulatory requirements", "systems", "monitor", "management reports", "banking"], "requirements": {"degrees": ["diploma", "dse"], "majors": [], "languages": ["putonghua", "english", "chinese"], "language_level": ["proficiency", "good command"], "hard_skills": ["pc", "excel"], "soft_skills": ["self-motivated", "communication", "interpersonal skills", "hard-working", "proactive"], "languages_combined": [{"language": "putonghua", "language_level": ["proficiency", "good command"]}, {"language": "english", "language_level": ["proficiency", "good command"]}, {"language": "chinese", "language_level": ["proficiency", "good command"]}]}, "experience_required": {"duration": ["minimum 3 years"], "field": ["banking industry", "relevant experience"]}}, {"job_id": "100003009050868", "location_code": "hk", "company": "Williams Lea (Hong Kong) Ltd", "job_title": "Data Analyst", "description": "Responsibilities:\n\nGather data from different internal platforms\u00a0\nTo collaborate with relationship managers and stakeholders to produce analysis,\u00a0dashboard\u00a0and reports for customers\nSupport for routine sales / business management activities\nPrepare internal and external presentations\nAssist in management of data,\u00a0databases\u00a0and the relevant system\nSupport other ad-hoc and administrative duties as required\n\nRequirements:\n\nDegree or above with at least one-year relevant experience in banking / financial sector\nGood communications skill to get inputs from stakeholders and prepare different presentation decks\nProficient in MS Excel for consolidating data, including formula and pivot table usage\nCapability to use MS PowerPoint to present findings with graphs / charts\nEnergetic, quick starter, good time-management and attention to detail\nStrong sense in data, detail-minded, organized, meticulous and responsible\n\nWe offer attractive remuneration package to the successful candidate.\u00a0 In addition, you will have an opportunity to work in a reputable company with excellent career exposure.\u00a0 Interested parties, please click \"APPLY NOW\" to submit your application.\n\nAll information provided will be treated confidentially and used solely for recruitment purpose.\u00a0", "employment_types": ["Full Time", "Permanent"], "selling_points": ["Banking Environment", "Monday to Friday 0900 - 1800", "AL 15 Days, Medical & Dental Coverage"], "locations": ["Mong Kok"], "categories": ["Banking / Finance", "Analyst", "Corporate Banking", "Financial Services"], "post_time": "2022-01-14T11:35:38Z", "salary": {"currency": null, "max": null, "min": null, "period": "monthly", "term": null}, "salary_visible": false, "title_keywords": ["data analyst"], "responsibilities": ["collaborate with", "ad-hoc", "management", "data", "analysis", "presentations", "reports", "administrative duties", "databases"], "requirements": {"degrees": ["degree or above"], "majors": [], "languages": [], "language_level": [], "hard_skills": ["pivot table", "ms excel", "ms powerpoint"], "soft_skills": ["detail-minded", "organized", "meticulous", "responsible", "attention to detail", "energetic", "presentation"], "languages_combined": []}, "experience_required": {"duration": [], "field": ["relevant experience", "financial", "banking"]}}, {"job_id": "100003009049920", "location_code": "hk", "company": "Nanyang Commercial Bank", "job_title": "Anti-Money Laundering Manager \u2013 Transaction Monitoring (Ref: KC8022-TM- JDB)", "description": "Investigate/ review suspicious transactions in accordance with relevant statutory and regulatory requirements.\nProvide timely advice to business units on AML/CFT related regulations and matters;\nProvide technical support to the Bank\u2019s transaction monitoring system such as handling of user enquiries, collaboration with Business Analyst and troubleshooting application incident;\nHandle AML-related inquiries from regulators and law enforcement agencies;\nParticipate in AML/CFT related ad-hoc projects as assigned.\n\u00a0Requirements:\n\nDegree holder in Finance, Law, Accounting, Business Administration, Information Technology or related disciplines;\nA minimum of 5 years of relevant experience in AML/CFT compliance, preferably in transaction monitoring from banks;\nSound knowledge in AML/CFT related regulations, guidelines and practices;\nExposure in SAS programming and project experience/ technical support in transaction monitoring system and regtech solution;\nIndependent, good team player, analytical mind with sound communication and interpersonal skills;\nProficient in both spoken and written English and Chinese, fluent in Putonghua is preferable;\nHolder of AAMLP or CAMS would be an advantage.\n\n(Candidate with less experience will be considered as Assistant Anti-Money Laundering Manager \u2013 Transaction Monitoring.)\n\nIf you are flexible enough and zeal for a harmonious and supportive working environment where enables you to grow and succeed professionally, please send a full resume indicating your public examination results (HKCEE and HKALE / HKDSE), your present and expected salary and quoting reference number attention to\u00a0Talent Acquisition Division, Nanyang Commercial Bank, 151 Des Voeux Road Central, Hong Kong or apply through email. For details, please visit https://www.ncb.com.hk/ and select the page Recruit.\n\nWe are an Equal Opportunities Employer. Data collected would be used for recruitment purposes only. Applicants who do not hear from us within 8 weeks may consider their applications unsuccessful and their data will be destroyed within 12 months of receipt.", "employment_types": ["Full Time", "Permanent"], "selling_points": ["Investigate/ review suspicious transactions", "Handle AML-related inquiries", "A minimum of 5 years of relevant experience"], "locations": ["Central & Western Area"], "categories": ["Banking / Finance", "Corporate Banking", "Retail Banking", "Professional Services", "Legal & Compliance"], "post_time": "2022-01-15T03:50:40Z", "salary": {"currency": null, "max": null, "min": null, "period": "monthly", "term": null}, "salary_visible": false, "title_keywords": ["manager"], "responsibilities": ["regulations", "aml", "data", "technical support", "regulatory requirements", "guidelines", "review", "monitoring", "troubleshooting", "transactions", "compliance", "communication", "recruitment", "ad-hoc projects", "administration"], "requirements": {"degrees": ["hkdse", "degree holder"], "majors": ["business administration", "law", "finance", "information technology", "related disciplines", "accounting"], "languages": ["putonghua", "english", "chinese"], "language_level": ["fluent", "proficient"], "hard_skills": ["aml", "sas", "cft", "programming", "aamlp", "anti-money laundering"], "soft_skills": ["flexible", "good team player", "supportive", "independent", "harmonious", "timely", "troubleshooting", "analytical mind", "communication and interpersonal skills"], "languages_combined": [{"language": "putonghua", "language_level": ["fluent", "proficient"]}, {"language": "english", "language_level": ["fluent", "proficient"]}, {"language": "chinese", "language_level": ["fluent", "proficient"]}]}, "experience_required": {"duration": ["minimum of 5 years"], "field": ["compliance", "relevant experience", "programming"]}}, {"job_id": "100003009046510", "location_code": "hk", "company": "Page Personnel", "job_title": "Transaction Monitoring Senior Officer - Top HK Bank!", "description": "Our client is a leading public bank in Hong Kong that provides tailor-made financing solutions and services to their customers. They are currently looking for a role of transaction monitoring senior officer to join the financial crime compliance department to conduct AML/ case investigations and transaction monitoring. The candidate should have 2-3 years of working experience in transaction monitoring within banking industry.\n\nClient Details\n\nOur client is one of Hong Kong's largest listed banks and they are now seeking a position of transaction monitoring senior officer to join the financial crime compliance department to investigate assigned cases including transaction monitoring, unusual activity reports and customer screening alerts. The department is responsible for investigating cases, checking suspicious activity and reporting to the authorities according to the agreed standard reporting requirements and guidance.\n\nDescription\n\nResponsible for conducting effective and timely investigations including transaction monitoring cases from FCC operations, unusual activity reports from various business units and customer screening alerts suggesting risk\nComplete level 2 case analysis and identify suspicious activity or possible violations of regulation in business transaction documented in CDD according to regulatory reporting requirements\nWrite high quality reports to identify risks and escalate investigations to the line of business or the authorities\nProvide telephone or email guidance to line of business or relevant stakeholders in accordance with reporting standards\nProvide timely and accurate management information as required\n\nProfile\n\nBachelor's Degree with major in Business Administration/ Finance or relevant discipline\n2-3 years of working experience in AML investigation, transaction monitoring within banking industry\nExperience in identifying risk activity, investigating customer activity and writing reports for escalation. Regulatory investigation experience is an advantage\nExcellent English spoken and written communication skills\nStrong interpersonal skills and strong organization skills\n\nJob Offer\n\nStimulating and challenging work\nDynamic working environment\nCompetitive remuneration and benefit packages\n\nTo apply online please click the 'Apply' button below. For a confidential discussion about this role please contact Esther Liu on +852 2258 3537", "employment_types": ["Full Time", "Permanent"], "selling_points": ["Stimulating and challenging work", "Dynamic working environment", "Competitive remuneration and benefit packages"], "locations": ["Not Specified"], "categories": ["Banking / Finance", "Corporate Banking", "Financial Services", "Others"], "post_time": "2022-01-13T12:37:55Z", "salary": {"currency": null, "max": null, "min": null, "period": "monthly", "term": null}, "salary_visible": false, "title_keywords": ["senior officer"], "responsibilities": ["reporting", "guidance", "management", "aml", "operations", "analysis", "compliance", "monitoring", "checking", "cdd", "quality", "investigation", "communication", "reports", "contact", "banking", "administration"], "requirements": {"degrees": ["degree", "bachelor"], "majors": ["finance", "business administration"], "languages": ["english"], "language_level": ["excellent"], "hard_skills": ["cdd", "analysis", "dynamic", "aml"], "soft_skills": ["communication skills", "responsible", "timely", "dynamic", "interpersonal skills", "organization skills", "accurate"], "languages_combined": [{"language": "english", "language_level": ["excellent"]}]}, "experience_required": {"duration": ["2-3 years"], "field": ["banking industry", "writing"]}}, {"job_id": "100003009049747", "location_code": "hk", "company": "China Construction Bank (Asia) Corporation Limited", "job_title": "Manager/AVP, Transaction Monitoring", "description": "Main Responsibilities\n- Review alerts / cases escalated and draft STRs, sourcing from system generated alerts, internal and external parties\n- Review cases escalated or investigate complicated cases as assigned\n- Coach junior staff and closely monitor the progress and quality of cases reviewed by junior staff\n- Quality checking on closed alerts\n- Advise the transaction monitoring related inquiries\n- Prepare management information reports\n- Participate in transaction monitoring system/Regtech projects\n- Handle ad-hoc tasks as assigned by supervisor\n\nRequirements\n- Degree holder or equivalent\n- At least 4 years AML experience in financial institutions and/or regulatory bodies\n- Qualification in ECF is preferred\n- Possession of good knowledge on banking operations, products and services and experience to communicate with law enforcement agent and regulators will be an advantage\n- AAMLP/CAMLP or ACAMS qualification preferred\n- Self-motivated, independent with good communication and interpersonal skills\n- Good command of both written and spoken English and Chinese\n- Proficient in PC skills including MS Word and Excel\n- Attentive to details, compliance and control oriented, diligent and proactive\n\nCandidates with more experience will be considered as Assistant Vice President\n\nPlease send your application with both current and expected salary for reference.\u00a0\u00a0\n\nApplicants who are not contacted within 8 weeks may consider their applications unsuccessful and their personal data will be retained by the bank for a period up to two years.\n\nAll information provided by applicants will be used for recruitment purposes only and will be used strictly in accordance with the bank\u2019s personal data policies, a copy of which will be provided upon request.", "employment_types": ["Full Time", "Permanent"], "selling_points": ["AML Compliance", "Transaction Monitoring", "Review alerts / cases escalated and draft STRs"], "locations": ["Kowloon Bay"], "categories": ["Banking / Finance", "Corporate Banking", "Retail Banking", "Professional Services", "Legal & Compliance"], "post_time": "2022-01-14T09:11:29Z", "salary": {"currency": null, "max": null, "min": null, "period": "monthly", "term": null}, "salary_visible": false, "title_keywords": ["manager"], "responsibilities": ["quality checking", "management", "ad-hoc tasks", "review", "quality", "monitor", "internal and external parties", "monitoring", "reports"], "requirements": {"degrees": ["degree holder"], "majors": [], "languages": ["english", "chinese"], "language_level": ["good command"], "hard_skills": ["excel", "aml", "acams", "aamlp", "pc skills", "ms word"], "soft_skills": ["self-motivated", "independent", "attentive to details", "diligent", "communication and interpersonal skills", "proactive"], "languages_combined": [{"language": "english", "language_level": ["good command"]}, {"language": "chinese", "language_level": ["good command"]}]}, "experience_required": {"duration": ["at least 4 years"], "field": ["financial institutions", "banking"]}}, {"job_id": "100003009050444", "location_code": "hk", "company": "China Construction Bank (Asia) Corporation Limited", "job_title": "Syndication Professional", "description": "Job Descriptions:\n\nSupport the Head of Syndication on pitching and execution of syndication mandates\nSolicit potential clients for syndicated loan\nAssess the credit worthiness of prospective borrowers, conduct market comparable analysis, due diligence, prepare syndication risk analysis and perform cashflow analysis\nPrepare information memorandum and presentation materials by obtaining relevant market information and liaison with customers directly\nFormulate syndication strategy based on research on market appetite, competing deal(s) and market depth analysis\nNegotiate with borrower, legal counsel and lenders on loan agreement\nPerform special duties as assigned by the Head of Syndication from time to time\nSupport co-marketing with Head Office / other branches as needed\n\nRequirements:\n\nBachelor degree or above in leading university\nMinimum 4 years relevant experience in loan syndication. Candidate with less experience in loan syndication will be considered as Assistant Vice President\nProven financial, commercial and business acumen\nStrong analytical skills and highly numerate and articulate\nGood presentation skills. A team player with strong communication, interpersonal and project management skills\nCan work efficiently and independently under minimal supervision. Able to work under pressure and meet tight deadlines\nKnowledge of MS applications including Excel and Power Point and good PC skills\nExcellent command of written and spoken English and Chinese including Putonghua\nWilling to travel occasionally\n\nTo apply, please send the detailed resume to the designated email address.\n\nApplicants who are not contacted within 8 weeks may consider their applications unsuccessful and their personal data will be retained by the bank for a period up to two years.\n\nAll information provided by applicants will be used for recruitment purposes only and will be used strictly in accordance with the bank\u2019s personal data policies, a copy of which will be provided upon request.", "employment_types": ["Full Time", "Permanent"], "selling_points": ["Loan syndication", "Prepare information memorandum & loan agreement", "Pitching and execution of syndication mandates"], "locations": ["Central"], "categories": ["Banking / Finance", "Corporate Banking", "Credit Analysis / Approval", "Corporate Finance"], "post_time": "2022-01-14T10:26:38Z", "salary": {"currency": null, "max": null, "min": null, "period": "monthly", "term": null}, "salary_visible": false, "title_keywords": [], "responsibilities": ["due diligence", "analysis", "market information", "risk analysis"], "requirements": {"degrees": ["degree or above", "bachelor"], "majors": [], "languages": ["putonghua", "english", "chinese"], "language_level": ["excellent"], "hard_skills": ["excel", "ms applications", "analytical skills", "project management", "power point", "pc skills", "acumen"], "soft_skills": ["meet tight deadlines", "independently", "project management skills", "detailed", "analytical skills", "communication", "presentation skills", "business acumen", "articulate", "team player", "interpersonal", "work under pressure"], "languages_combined": [{"language": "putonghua", "language_level": ["excellent"]}, {"language": "english", "language_level": ["excellent"]}, {"language": "chinese", "language_level": ["excellent"]}]}, "experience_required": {"duration": ["minimum 4 years"], "field": ["relevant experience"]}}, {"job_id": "100003009042527", "location_code": "hk", "company": "ADECCO", "job_title": "Assistant Manager, Investigation (Fraud, 6-month contract, bank)", "description": "Our client is one of the leading bank and they are looking for Assistant Manager, Investigation to join their Financial Crime team.\n\nJob\u00a0Responsibilities :\nAnalyze alerts and cases generated by TM system, investigate further and disclose suspicious transactions to relevant authority, such as JFIU, in a speedy and professional manner\nReview fraud-related cases reported by victim or law enforcement agencies (LEAs), investigate further and report suspicious cases to LEAs\nProvide advice to Business Units on handling suspicious transactions and AML/CFT-related matters\nDisseminate AML/CFT related information or regulatory notification to Business Units and/or functions\nSupport the Bank\u2019s AML/CTF related tasks or projects, such as the periodic review and enhancement of TM to ensure their ongoing effectiveness\nSupport the senior manager of Financial Crime Risk in any matter relating to financial crime risk, TM and STR reporting\nJob Requirements :\n\nUniversity degree in related discipline\nAt least 3 years\u2019 experience in banking industry with exposure to Financial Crime Compliance, audit or general compliance\nKnowledge and practical experience in FCC and STR reporting is an advantage\nAAMLP / ACAMS certification is preferred\nGood command of both written and spoken in English and Chinese\nStrong analytical skills and PC Knowledge\nImmediate available preferred\nIf you're interested in this role, please\u00a0CLICK HERE\u00a0to apply the position via Adecco website with your CV.\n\nPlease note that only shortlisted candidates will be notified. All information gathered will be treated in strict confidence and solely used for recruitment purposes.", "employment_types": ["Full Time", "Temporary", "Contract"], "selling_points": [], "locations": ["Mong Kok"], "categories": ["Banking / Finance", "Corporate Banking"], "post_time": "2022-01-12T07:52:20Z", "salary": {"currency": null, "max": null, "min": null, "period": "monthly", "term": null}, "salary_visible": false, "title_keywords": ["assistant manager,"], "responsibilities": ["reporting", "aml", "review", "professional manner", "transactions", "provide advice", "report"], "requirements": {"degrees": ["university degree"], "majors": [], "languages": ["english", "chinese"], "language_level": ["good command"], "hard_skills": ["pc knowledge", "acams", "analytical skills", "aamlp"], "soft_skills": ["interested in", "confidence", "analytical skills"], "languages_combined": [{"language": "english", "language_level": ["good command"]}, {"language": "chinese", "language_level": ["good command"]}]}, "experience_required": {"duration": ["at least 3 years"], "field": ["banking industry", "compliance", "audit", "general compliance", "financial"]}}, {"job_id": "100003009050759", "location_code": "hk", "company": "China Construction Bank (Asia) Corporation Limited", "job_title": "VP/ AVP, Internal Control (Corporate Banking)", "description": "Responsibilities\n\nProvide advice on various codes such as loan purpose and non-bank Mainland China exposure (NBMCE) etc. in credit application and MIS reporting are able to fulfill regulatory standard\nParticipate in Risk remediation projects to address control issue\nAssist & quality assure all Risk & Control Self-Assessments\nIndependently assess governances, internal controls and business activities effectiveness and commensuration with operational / credit risk appetite set by the bank / Management\nOversee daily excess & credit monitoring on assigned portfolios\nIdentify key risk and material control issues and timely escalate to Management; conduct independent risk reviews complementing other functions\u2019 assessment\nPropose adequate risk mitigating measures to close gaps\nFoster strong collaboration with Business and peers for carrying out daily administrative / credit monitoring and control process\nProvide compliance / audit related support as assigned by management\nAlign, develop and fine tune existing / new process and procedures\nRegular review the policy and procedure to ensure all business activities are complied with the Bank policy and regulatory requirement\nCoordinate FATCA and CRS customers remediation project\nHandle ad hoc project as assigned by Management, not limited to AML CDD issue, IT / system related enhancement, Compliance, internal / external regulatory issue etc\n\nRequirements\n\n\nDegree holder or above with major in Risk Management, Economics, Business Administration, Corporate Governance or related discipline\nQualifications in CPA, FRM or law related areas are preferable\nAt least 7 years banking experience with not less than 5 years in Risk Management, control, Compliance or audit related functions, with good knowledge in credit products and business practices. Candidates with less experience could be considered for the position of AVP\nUnderstand supervisory requirements, banking law / rules in Hong Kong and Mainland China\n\u00a0Demonstrated communication and interpersonal skills, including, the capacity to articulate the case for risk management in the language of business\nAbility to work and thrive in a fast changing, results driven environment\nIndependent, committed, proactive and responsible\nUnderstand and interpret complex business requirements and prioritize competing demands\nVery good demand of English; fluency in Putonghua is an advantage\nFamiliarize with Microsoft Office i.e. Word, Excel & PowerPoint\nApplicants who are not contacted within 8 weeks may consider their applications unsuccessful and their personal data will be retained by the bank for a period up to two years.\n\n\n\nAll information provided by applicants will be used for recruitment purposes only and will be used strictly in accordance with the bank's personal data policies, a copy of which will be provided upon request.\u00a0", "employment_types": ["Full Time", "Permanent"], "selling_points": ["Provide advice on credit appln & MIS Reporting", "Participate in Risk remediation projects", "7 yr banking exp, 5 yrs in Risk/Control/Compliance"], "locations": ["Central"], "categories": ["Banking / Finance", "Corporate Banking", "Financial Services", "Risk Management"], "post_time": "2022-01-14T11:17:21Z", "salary": {"currency": null, "max": null, "min": null, "period": "monthly", "term": null}, "salary_visible": false, "title_keywords": [], "responsibilities": ["reporting", "control", "management", "ad hoc", "aml", "cdd", "monitoring", "quality", "compliance", "audit", "develop", "procedures", "regular review", "coordinate", "provide advice", "business activities"], "requirements": {"degrees": ["degree holder"], "majors": ["risk management", "economics", "business administration"], "languages": ["putonghua", "english"], "language_level": ["fluency", "advantage", "good"], "hard_skills": ["excel", "microsoft office", "word", "powerpoint", "cpa", "frm"], "soft_skills": ["independent", "responsible", "prioritize", "committed", "communication and interpersonal skills", "articulate", "proactive", "driven"], "languages_combined": [{"language": "putonghua", "language_level": ["fluency", "advantage"]}, {"language": "english", "language_level": ["good"]}]}, "experience_required": {"duration": ["5 years", "at least 7 years"], "field": ["risk management", "banking experience", "related", "compliance", "audit", "business"]}}, {"job_id": "100003009033715", "location_code": "hk", "company": "Bank of Communications Co., Ltd. Hong Kong Branch", "job_title": "Corporate Management Trainee Programme (Corporate Banking)", "description": "Career Level\nEntry Level\nQualification\nDegree\nYears of Experience\n2 years\nJob Type\nFull Time\nJob Functions\nBanking / Finance, Corporate Banking, Others, Others, Student / Fresh Graduate / No Experience", "employment_types": ["Full Time"], "selling_points": [], "locations": ["Not Specified"], "categories": ["Banking / Finance", "Corporate Banking", "Others", "Others", "Student / Fresh Graduate / No Experience"], "post_time": "2022-01-10T01:38:48Z", "salary": {"currency": null, "max": null, "min": null, "period": null, "term": null}, "salary_visible": false, "title_keywords": ["management trainee"], "responsibilities": ["banking"], "requirements": {"degrees": ["degree", "fresh graduate"], "majors": ["finance"], "languages": [], "language_level": [], "hard_skills": ["no"], "soft_skills": [], "languages_combined": []}, "experience_required": {"duration": [], "field": ["finance", "banking"]}}, {"job_id": "100003009044231", "location_code": "hk", "company": "JAC Recruitment Hong Kong Co., Limited", "job_title": "Japanese speaking Analyst (Market Support) Up to 24K,knowledge in AML and KYC", "description": "OverviewOur client, a prestigious Japanese bank, is looking for a\u00a0Analyst (Market Support)\n\nCompany Location:Central\n\nWorking Days:Mon-Fri (9:00 am ~5:30pm)\n\nCompany Business:Japanese Bank\n\nLanguages Required:Cantonese, English, Mandarin, Japanese\n\nJOB DUTIES\n\nTo handle instructions and enquires in relation to client transactions in a timely and orderly manner to ensure quality service is delivered.\nTo work closely with clients, relationship managers and Operations Departments to ensure client transactions are completed efficiently and accurately.\nTo follow up pending items by contacting clients regularly to avoid overdue of tasks.\nTo prepare control sheet for unprocessed documents and follow up the settlement in a timely manner.\nTo act as the 1st line of defense and ensure all transactions are in compliance with internal policies, AML, sanctions and other regulatory requirements.\nTo prepare AML related reports and relevant documents to facilitate KYC and transaction monitoring processes.\nTo support the implementation and delivery of enhancement initiatives of the Business Unit according to the predetermined schedule.\nTo maintain good working knowledge of procedural changes, products, relevant rules and regulations.\n\nREQUIREMENTS\n\nUniversity graduate\nWith 1 to 3 years\u2019 relevant experience in banking or financial institutions is preferable\nGood command of written and spoken Japanese and English\n\nPACKAGE\n\nDiscretionary bonus\nMedical insurance\nBirthday leave\nWork from Home Policy\nExamination Leave\nVolunteer Leave\nPaid Sick Leave\nFlexible working Hour\nBonus\n\n1) Expected salary\n2) Current and last drawn salaries\n3) Reason for leaving current and past employments\n\u00a0\ndirectly to:\u00a0jac.hk\u00a0@jac-recruitment.com and CC to:\u00a0daniel.ng\u00a0@jac-recruitment.com\n\n\u00a0\nPersonal data collected will be used for employment-related purpose only. We regret to inform that only shortlisted candidates will be notified, thank you", "employment_types": ["Full Time"], "selling_points": ["experienced in KYC,AML is preferable", "Good benefits, 20days AL", "Location: Central"], "locations": ["Central"], "categories": ["Banking / Finance", "Corporate Banking"], "post_time": "2022-01-13T03:29:00Z", "salary": {"currency": null, "max": null, "min": null, "period": "monthly", "term": null}, "salary_visible": false, "title_keywords": ["analyst"], "responsibilities": ["regulations", "control", "aml", "operations", "policies", "compliance", "a timely manner", "quality", "transactions", "regulatory requirements", "monitoring", "implementation", "maintain", "reports", "schedule", "kyc"], "requirements": {"degrees": ["university graduate"], "majors": [], "languages": ["japanese", "english"], "language_level": ["good command"], "hard_skills": ["inform", "reason"], "soft_skills": ["flexible"], "languages_combined": [{"language": "japanese", "language_level": ["good command"]}, {"language": "english", "language_level": ["good command"]}]}, "experience_required": {"duration": ["1 to 3 years"], "field": ["financial institutions", "relevant experience", "banking"]}}, {"job_id": "100003009049679", "location_code": "hk", "company": "Bangkok Bank Public Co Ltd", "job_title": "Chief Officer - Credit Administration (Ref: CAS-10/181/240-DB)", "description": "We are now seeking a high caliber candidate to join our Hong Kong Branch.\n\nResponsibilities:\n\n\nManage and review facility letter, loan and security documents\nReview and comment facility and security documentation prepared by legal counsel\nEnsure security and facility documents are executed in accordance with the Bank's prevailing policies and guidelines\nReview credit limit of borrowers and other relevant information to ensure proper input in the system\nPerform supervisor release of the transactions completed by the users in the system\nMonitor the submission of credit data of SME borrowers to CCRA and CRA\nPrepare, update\u00a0and check reports (monthly/quarterly) for the relevant department/management\nParticipate in the development and enhancement of work processes and system functions\nCollaborate with internal stakeholders, project team and external vendor for system development and enhancement\nRationalize work procedure and monitoring reports compiling of the section and update CAS guidelines\nPerform ad-hoc duties as and when required\n\nRequirements:\u00a0\u00a0\n\nDegree holder or equivalent\nMinimum 8 years of credit administration / loan documentation experience with at least 5 years at supervisory level\nIn-depth knowledge of banking products and non-standard loan documentations is a\u00a0MUST\nHands-on experience in credit control and monitoring functions\nExperience in participating in work process / system enhancement projects as a Subject Matter Expert is an advantage\nAble to work independently and under pressure to meet tight deadlines\nTeam player with good interpersonal and communication skills\nProficient in MS Office\nGood command of spoken and written English and Chinese\n\nWe offer excellent career prospects to the right candidate. Salary will be commensurate with qualifications and experience. Interested parties please apply with\u00a0full resume, stating\u00a0current / expected salary and availability\u00a0to\u00a0The Human Resources Manager, Bangkok Bank Public Co. Ltd., Bangkok Bank Building, 28 Des Voeux Road Central, Hong Kong.\n\nPersonal data provided by job applicants will be used solely for considering suitability for the post and strictly in accordance with our personal data policies which are available on request.\n\n(Only shortlisted candidates will be contacted.)", "employment_types": ["Full Time"], "selling_points": [], "locations": ["Central"], "categories": ["Banking / Finance", "Corporate Banking", "Others"], "post_time": "2022-01-14T09:05:19Z", "salary": {"currency": null, "max": null, "min": null, "period": "monthly", "term": null}, "salary_visible": false, "title_keywords": ["officer"], "responsibilities": ["collaborate with", "management", "data", "guidelines", "policies", "review", "monitor", "monitoring", "transactions", "reports", "ad-hoc duties", "documentation", "sme"], "requirements": {"degrees": ["degree holder"], "majors": [], "languages": ["english", "chinese"], "language_level": ["good command"], "hard_skills": ["documentation", "documentations", "ms office"], "soft_skills": ["communication skills", "work independently", "meet tight deadlines", "under pressure", "hands-on", "team player", "interpersonal"], "languages_combined": [{"language": "english", "language_level": ["good command"]}, {"language": "chinese", "language_level": ["good command"]}]}, "experience_required": {"duration": ["minimum 8 years", "at least 5 years"], "field": ["supervisory level", "administration"]}}, {"job_id": "100003009045169", "location_code": "hk", "company": "Hang Seng Bank Ltd", "job_title": "Business Analytics Manager", "description": "Wholesale Banking \u2013 WSB Chief Operating Officer\u2019s Office\n\n\nHang Seng\u2019s Wholesale Banking (WSB) business provides customized one-stop financial solutions to our corporate customers, from prime small and medium-sized businesses to publicly listed companies. \u00a0\n\n\nFor customers conducting business locally or around the world, we offer a comprehensive range of services including corporate lending, trade and receivables finance, structured loan, cash management, investment, treasury services, insurance and e-Banking services. \u00a0As a reliable financial partner, we attend to the specific business needs of our customers and provide efficient tailor-made banking solutions through our relationship managers and dedicated specialists.\n\n\nWe are currently seeking a high caliber professional to join our department as\u00a0Business Analytics Manager.\n\n\nPrincipal responsibilities\n\nEnsure implementation of Sales and Services Composite Scorecard and work with IT to deliver the project according to the plan\nEnable visual analytics capability in CMB by deploying interactive dashboards across different business units\nSupport ad-hoc data analytics, sales MI & regular reporting and DataMart development\n\nRequirements\n\nUniversity degree in Quantitative Analysis, statistics, computing or a related discipline\u00a0\nAt least 5 years' data analysis, database management, sales performance analysis, software engineering, and system development\nWith experience on statistical modeling, or data/text mining is an added advantage\u00a0\nWith knowledge of commercial / digital banking preferred\u00a0\nHands-on experience of SAS, SQL, R, Python, MS Access or Excel VBA\nGreat sense of ownership and servicing mindset to ensure efficient and effective customer service processes\nStrong commitment in taking new challenges, self-motivation and creativity\u00a0\nGood communication, analytical and project management skills\nProficiency in both English and Chinese\n\n(Candidates with less experience will be considered for the position of Assistant Business Analytics Manager.)\n\nIf you would like to explore other opportunities at Hang Seng Hong Kong, please visit www.hangseng.com/careers/ for details.\n\nThe health and safety of our employees and candidates is very important to us. Due to the current situation related to the Novel Coronavirus (2019-nCoV), we\u2019re leveraging our digital capabilities to ensure we can continue to recruit top talent at the HSBC Group. As your application progresses, you may be asked to use one of our digital tools to help you through your recruitment journey. If so, one of our Resourcing colleagues will explain how our video-interviewing technology will be used throughout the recruitment process and will be on hand to answer any questions you might have.\n\nAll information provided by applicants will be used only for recruitment purposes and will be used strictly in accordance with the Bank's personal data policies, a copy of which may be obtained by the applicant upon request. Unless otherwise instructed in writing by the applicant concerned, applicants may be considered for other suitable positions within the Bank and its related companies. The personal data of unsuccessful job applicants may be retained for a maximum of two years from the date when the job application is rejected and such data may be retained for a longer period if there is a subsisting reason that obliges the Bank to do so, after which the personal data will be destroyed.", "employment_types": ["Full Time", "Permanent"], "selling_points": [], "locations": ["Not Specified"], "categories": ["Banking / Finance", "Analyst", "Corporate Banking"], "post_time": "2022-01-13T07:21:46Z", "salary": {"currency": null, "max": null, "min": null, "period": "monthly", "term": null}, "salary_visible": false, "title_keywords": ["manager"], "responsibilities": ["ad-hoc", "reporting", "data", "implementation", "plan", "visual"], "requirements": {"degrees": ["university degree"], "majors": ["statistics"], "languages": ["english", "chinese"], "language_level": ["proficiency"], "hard_skills": ["excel", "vba", "sas", "analysis", "reason", "sql", "project management", "python", "r"], "soft_skills": ["efficient", "project management skills", "communication", "hands-on", "customer service", "self-motivation", "novel"], "languages_combined": [{"language": "english", "language_level": ["proficiency"]}, {"language": "chinese", "language_level": ["proficiency"]}]}, "experience_required": {"duration": [], "field": ["sql", "business"]}}, {"job_id": "100003009039900", "location_code": "hk", "company": "HSBC Group", "job_title": "Vice President, Business Relationship Manager - Commercial Banking", "description": "The health and safety of our employees and candidates is very important to us. Due to the current situation related to the Novel Coronavirus (2019-nCoV), we\u2019re leveraging our digital capabilities to ensure we can continue to recruit top talent at HSBC. \u00a0As your application progresses, you may be asked to use one of our digital tools to help you through your recruitment journey. \u00a0If so, one of our \u00a0Resourcing colleagues will explain how our video-interviewing technology will be used throughout the recruitment process and will be on hand to answer any questions you might have.\n\nSome careers open more doors than others.\u00a0\n\nIf you\u2019re looking for a career that will unlock new opportunities, join HSBC and experience the possibilities. Whether you want a career that could take you to the top, or simply take you in an exciting new direction, HSBC offers opportunities, support and rewards that will take you further.\n\nThrough Business Banking our global network offers comprehensive support and services to businesses in the SME market. From expanding overseas to managing the cash and trade flows of an established enterprise, the Business Banking team of Relationship Managers and Product Specialists provides a range of end-to-end solutions designed to help small and large businesses reach their potential.\n\nWe are currently seeking a high calibre professional to join our team as a\u00a0Vice President, Business Relationship Manager.\n\nPrincipal Responsibilities\n\nGrow sustainable revenues from existing relationships and expand portfolio through proactive marketing effort\nIncrease profitability and relationship depth by anticipating customer needs and providing superior quality services resulting in a profitable portfolio in line with business appetite\nManaging risks of the portfolio. Proactively develop effective strategies to manage and de-risk relationships, in line with the Global Standards requirements\nOffer value-added advice and guidance to customers and placing their needs at the forefront of all that we do, setting world class standards. Keep abreast of external factors influencing international and domestic business e.g. economic, cultural, geographical, procedural and regulatory requirements\n\nRequirements\n\nWith strong customer facing experience, preferably in financial service industry with knowledge of wealth management products\nPrior experience in commercial lending will be an advantage\nAbility to identify, analyse, and with effective presentation skills. Be fluent in both English and Cantonese, with knowledge in Mandarin preferred\nSelf-motivated and driven to succeed in building strong relationships with clients\nAbility to manage a variety of assignments simultaneously\nShould possess investment and insurance license\nPossess strong organizational, analytical, negotiation, communication, teamwork and influencing skills\nGood level of business acumen and international commercial awareness, including economic, cultural, procedural and regulatory issues\nCandidates with less expereince will also be considered for a junior postion\nCandidate will be assigned to relevant RM team subject to business needs\n\nYou\u2019ll achieve more when you join HSBC.\nwww.hsbc.com/careers\n\nHSBC is committed to building a culture where all employees are valued, respected and opinions count. We take pride in providing a workplace that fosters continuous professional development, flexible working and opportunities to grow within an inclusive and diverse environment. Personal data held by the Bank relating to employment applications will be used in accordance with our Privacy Statement, which is available on our website.\u00a0\n\nIssued by The Hongkong and Shanghai Banking Corporation Limited.", "employment_types": ["Full Time"], "selling_points": ["Excellent Career Progression", "Stable working environment", "Dynamic working environment"], "locations": ["Kowloon City"], "categories": ["Banking / Finance", "Corporate Banking", "Private Banking"], "post_time": "2022-01-11T14:26:31Z", "salary": {"currency": null, "max": null, "min": null, "period": "monthly", "term": null}, "salary_visible": false, "title_keywords": ["vice president", "relationship manager"], "responsibilities": ["guidance", "quality", "regulatory requirements", "develop"], "requirements": {"degrees": [], "majors": [], "languages": ["cantonese", "english", "mandarin"], "language_level": ["fluent"], "hard_skills": ["acumen"], "soft_skills": ["flexible", "self-motivated", "negotiation", "organizational", "teamwork", "communication", "committed", "presentation skills", "diverse", "business acumen", "driven"], "languages_combined": [{"language": "cantonese", "language_level": ["fluent"]}, {"language": "english", "language_level": ["fluent"]}, {"language": "mandarin", "language_level": ["fluent"]}]}, "experience_required": {"duration": [], "field": ["commercial", "management", "service industry", "financial"]}}, {"job_id": "100003009043865", "location_code": "hk", "company": "Manulife (International) Limited", "job_title": "MPF Sales Assistant (Part-time 6K-10K,2-3 days work)", "description": "Job Description:\n\n-Manage personal and corporate MPF / personal accounts\n-Provide sales and after-sales services and protection services\n\n\u00a0\nWe offer:\n\n$6,000- $10,000 (with month allowance, performance bonus, annual bonus)\n\n-2-3 days work and flexible working hours\n-Overseas conferences & travel allowance\n-Excellent career development and promotion opportunities\n-Professional\u00a0training program and mentorship program (CFP, CFA, RFP)\n-Medical scheme & study allowance\n\n\nRequirement:\n\n-Fresh graduate will be considered\n-No relevant experience is required\n-Self-motivated, positive attitude, and customer-oriented", "employment_types": ["Full Time", "Part Time", "Permanent", "Internship"], "selling_points": [], "locations": ["Not Specified"], "categories": ["Accounting", "Accountant", "Banking / Finance", "Corporate Banking", "Financial Services"], "post_time": "2022-01-13T02:14:03Z", "salary": {"currency": null, "max": null, "min": null, "period": "monthly", "term": null}, "salary_visible": false, "title_keywords": ["sales assistant"], "responsibilities": ["mpf"], "requirements": {"degrees": [], "majors": [], "languages": [], "language_level": [], "hard_skills": [], "soft_skills": [], "languages_combined": []}, "experience_required": {"duration": [], "field": []}}, {"job_id": "100003009037907", "location_code": "hk", "company": "Ambition", "job_title": "Senior Relationship Manager, Corporate Banking", "description": "Responsibilities:\n\nDevelop new business and maintain existing customer portfolio, by providing professional financial solutions in areas of cross-border financing, project financing, syndication loans, overseas property financing or investments etc.\nExplore business opportunities with prospective customers (corporate clients or PRC local institutional clients like government, media, charitable institutions, etc.).\nPromote the bank's broad range of financial services products.\nImplement agreed business plan to achieve pre-set sales/revenue targets.\nReview credit facilities, conduct credit analysis and prepare credit proposals.\n\nJob Requirement:\n\nBachelor's degree or above in related discipline\nSolid experience in Corporate Banking in Relationship Management\nNative Mandarin speaker is preferred\nProduct knowledge in syndication finance with experience in whole deal flow, origination and documentation\nSolid credit analysis and application proposal writing skills in English\nCustomer-oriented with passion to cultivate business relationship\nProficiency in spoken and written Chinese, Mandarin and English\n\nContact Winnie Cheung on (852) 3103 4369/ winnie.cheung@ambition.com.hk quoting reference number or APPLY NOW here\nhttp://www.ambition.com.hk\nData provided is for recruitment purposes only\n\nIf this job isn't quite right for you, but you know someone who would be great at this role, why not take advantage of our referral scheme? We offer HKD1000 in Apple gift cards for every referred candidate who we place in a role. Terms & Conditions Apply. https://www.ambition.com.hk/refer-a-friend", "employment_types": ["Full Time", "Permanent"], "selling_points": ["Competitive salary package with good benefit", "top tier global bank with good reputation", "Experience of handling large corporate segments"], "locations": ["Not Specified"], "categories": ["Banking / Finance", "Corporate Banking", "Loan", "Retail Banking"], "post_time": "2022-01-11T04:12:29Z", "salary": {"currency": "HKD", "max": 159999, "min": 45000, "period": "monthly", "term": null}, "salary_visible": true, "title_keywords": ["senior relationship manager"], "responsibilities": ["develop new business", "business opportunities", "review", "analysis", "maintain", "business plan"], "requirements": {"degrees": ["degree or above", "bachelor"], "majors": [], "languages": ["english", "chinese", "mandarin"], "language_level": ["native", "proficiency"], "hard_skills": ["documentation", "credit analysis", "scheme", "writing skills"], "soft_skills": ["customer-oriented", "writing skills"], "languages_combined": [{"language": "english", "language_level": ["proficiency"]}, {"language": "chinese", "language_level": ["proficiency"]}, {"language": "mandarin", "language_level": ["native", "proficiency"]}]}, "experience_required": {"duration": [], "field": ["finance", "management", "banking"]}}, {"job_id": "100003009047779", "location_code": "hk", "company": "Michael Page", "job_title": "RO 1, 4 & 9 - PE Investment", "description": "This role will be work closely with the founder of the company, leading the investment activities.\n\nClient Details\n\nOur client is a Chinese asset management firm with focus on alternative investments across Asia region.\n\nDescription\n\nFormulate business strategies and business plans\nMonitor the investment platform, portfolio performance to achieve investment goals\nManage daily operations, portfolio valuations, risk control, implement investment policies and processes\nProvide investment advice to the top management\nLiaise with Hong Kong regulatory authorities to ensure that business development to comply with the Hong Kong Securities Regulatory Commission\nHandle ad-hoc tasks as requested\n\nProfile\n\nDegree or above in Finance, Economics, Business or related discipline\nCurrent holder of SFC Responsible Officer license Type 1, 4 and 9 regulated activities\nMinimum 10 year of related experience with solid managerial exposure including not limited to investment\nSeasoned candidates with track record in managing HK & China PE portfolios\nGood command of written and spoken English and Mandarin\n\nJob Offer\n\nGood pay\n\nTo apply online please click the 'Apply' button below. For a confidential discussion about this role please contact Chris Yang on +852 2848 4716", "employment_types": ["Full Time", "Permanent"], "selling_points": ["RO 1, 4 & 9", "PE investment activities across Asia", "Chinese Asset Management firm"], "locations": ["Central & Western Area"], "categories": ["Banking / Finance", "Corporate Banking"], "post_time": "2022-01-14T03:53:06Z", "salary": {"currency": null, "max": null, "min": null, "period": "monthly", "term": null}, "salary_visible": false, "title_keywords": [], "responsibilities": ["control", "management", "policies", "ad-hoc tasks", "monitor", "business plans", "contact", "liaise with", "manage daily operations", "asset management"], "requirements": {"degrees": ["degree or above"], "majors": ["business", "finance", "economics"], "languages": ["english", "chinese", "mandarin"], "language_level": ["good command"], "hard_skills": ["focus", "pe"], "soft_skills": ["focus", "responsible"], "languages_combined": [{"language": "english", "language_level": ["good command"]}, {"language": "chinese", "language_level": []}, {"language": "mandarin", "language_level": ["good command"]}]}, "experience_required": {"duration": ["minimum 10 year"], "field": ["related", "managerial", "investment"]}}, {"job_id": "100003009037591", "location_code": "hk", "company": "The Bank of East Asia, Limited", "job_title": "Assistant Risk & Compliance Manager (AML & Compliance)", "description": "Assistant Risk & Compliance Manager (AML & Compliance) (Job ID3098)\nResponsibilities\nTo be a team member of Corporate Risk and Compliance Department\nTo conduct CDD/KYC review of Corporate Banking customers\nTo conduct AML transactions monitoring\nTo provide advice to frontline staff on AML/CFT and compliance requirements\nTo prepare, review and enhance business workflows and procedure manuals\nTo prepare control and MIS reports\nTo handle internal compliance reviews and audits\nTo perform other duties under risk and compliance functions of the Department as assigned\nRequirements\nHKCEE Form 7/HKDSE or above\nAt least 2 years of experience in banking/finance sector\nBasic knowledge of the principle of risks and compliance\nBasic knowledge of the Bank\u2019s lending policies and standards\nStrong Analytical and problem solving skills\nProficient with Microsoft Office application including Word and Excel\nGood command of both spoken and written English and Chinese\nPlease apply online via the BEA Careers website at\u00a0https://careers.hkbea.com/psp/hcmprd/EMPLOYEE/HRMS/c/HRS_HRAM.HRS_APP_SCHJOB.GBL?Page=HRS_APP_JBPST&Action=UFOCUS=Applicant&SiteId=1&JobOpeningId=3098&PostingSeq=1 or by clicking the \"Apply Now\" button below. Kindly note that if you are a new user, you have to first create your User Profile before you can apply.\nPersonal data provided by job applicants will be used for recruitment purposes only and will be treated in accordance with the Bank's Personal Information Collection (Employees) Statement and Privacy Policy Statement. Applicants who are not invited for interviews within six weeks may consider their applications unsuccessful and the personal data collected will be destroyed after six months.", "employment_types": ["Full Time", "Permanent"], "selling_points": ["To conduct AML transactions monitoring", "To prepare control and MIS reports", "HKCEE Form 7/HKDSE or above"], "locations": ["Not Specified"], "categories": ["Banking / Finance", "Analyst", "Corporate Banking", "Risk Management"], "post_time": "2022-01-11T03:14:20Z", "salary": {"currency": null, "max": null, "min": null, "period": null, "term": null}, "salary_visible": false, "title_keywords": ["compliance manager", "assistant"], "responsibilities": ["control", "perform other duties", "aml", "cdd", "compliance", "monitoring", "review", "transactions", "provide advice", "reports", "banking", "audits", "kyc review"], "requirements": {"degrees": ["hkdse"], "majors": [], "languages": ["english", "chinese"], "language_level": ["good command"], "hard_skills": ["excel", "basic", "microsoft office", "word", "c", "problem solving skills"], "soft_skills": ["analytical and problem solving skills"], "languages_combined": [{"language": "english", "language_level": ["good command"]}, {"language": "chinese", "language_level": ["good command"]}]}, "experience_required": {"duration": ["at least 2 years"], "field": ["finance", "banking"]}}, {"job_id": "100003009043451", "location_code": "hk", "company": "Page Personnel", "job_title": "Assistant Investigation Manager - Top HK Bank!", "description": "Our client is a leading public bank in HK that provides tailor-made financing solutions and services to their customers. They are looking for a role of Assistant Investigation Manager to join the Financial Crime Threat Mitigation team to conduct all types of fraud and financial crime investigation. The candidate should have 2-3 years of working experience in fraud/ financial crime investigation within banking industry.\n\nClient Details\n\nOur client is one of Hong Kong's largest listed banks and they are now seeking a position of Assistant Investigation Manager to join the Investigation team within Financial Crime Threat Mitigation Department to conduct all types of financial crime investigation. The department is responsible for investigating complex and serious cases across all types of fraud and financial crime risk, including AML, Sanctions, Anti-bribery and corruption.\n\nDescription\n\nResponsible for conducting all types of financial crime investigation originating from IASD, law enforcement, business, HR, AML investigations or other relevant referrals\nProvide guidance and solutions, recommendations for process improvement, control weaknesses and trends identified in each identified cases to the business\nIdentify, plan and execute best practices and procedures for the investigations, maximise loss recovery and minimise risk exposure\nProvide oversight of intelligence/ case files being shared with law enforcement/ government agencies\nPrepare and submit clear, concise and timely investigation reports\nProvide advice and support on investigations of all types of fraud and financial crime to other countries within the region when required and complete other ad hoc duties given by Senior Investigations Manager\n\nProfile\n\nBachelor's Degree with major in Business Administration/ Finance or relevant discipline\n2-3 years of working experience in financial crime investigation experience or fraud experience within banking industry\nExperience in managing a team of experienced senior clerical staff\nExcellent English spoken and written communication skills\nStrong interpersonal skills and strong organization skills\n\nJob Offer\n\nStimulating and challenging work\nDynamic working environment\nCompetitive remuneration and benefit packages\n15 days AL\n\nTo apply online please click the 'Apply' button below. For a confidential discussion about this role please contact Esther Liu on +852 2258 3537", "employment_types": ["Full Time", "Permanent"], "selling_points": ["Stimulating and challenging work", "Dynamic working environment", "Competitive remuneration and benefit packages"], "locations": ["Not Specified"], "categories": ["Banking / Finance", "Corporate Banking", "Financial Services"], "post_time": "2022-01-12T12:23:42Z", "salary": {"currency": null, "max": null, "min": null, "period": "monthly", "term": null}, "salary_visible": false, "title_keywords": ["manager", "assistant"], "responsibilities": ["ad hoc duties", "control", "aml", "hr", "procedures", "investigation", "communication", "provide advice", "reports", "contact", "plan", "banking", "managing a team", "provide guidance", "administration"], "requirements": {"degrees": ["degree", "bachelor"], "majors": ["finance", "business administration"], "languages": ["english"], "language_level": ["excellent"], "hard_skills": ["dynamic", "aml", "anti-bribery"], "soft_skills": ["communication skills", "responsible", "timely", "clear", "dynamic", "interpersonal skills", "organization skills"], "languages_combined": [{"language": "english", "language_level": ["excellent"]}]}, "experience_required": {"duration": ["2-3 years"], "field": ["banking industry", "managing a team", "clerical", "financial"]}}, {"job_id": "100003009039795", "location_code": "hk", "company": "Sin Chiao Limited", "job_title": "Account Officer", "description": "Location\u00a0\u00a0\u00a0\u00a0\u00a0\u00a0\u00a0\u00a0 \u00a0\u00a0\u00a0\u00a0 : Within Hong Kong\nEmployment type: Full Time Permanent\n\nIndustry\u00a0\u00a0\u00a0\u00a0\u00a0\u00a0\u00a0\u00a0\u00a0\u00a0\u00a0\u00a0\u00a0\u00a0 : Shipping related business\n\n\nJob Responsibilities:\nResponsible for the full spectrum of accounting activities. This includes books keeping, full set of accounts and reporting.\nPerform all accounting functions in accounts receivable and accounts payable\nPayroll, MPF Contributions\nLiaising with auditor, tax agent, secretarial and bankers\nOversee Treasury & Banking operations\nOrganizes and maintains up to date financial records / cash flow\nPerform account reconciliations\nMonitor customer account details for non-payments, delayed payments and other irregularities\nMonth-end closing reports\nCheck Incoming Funds through Internet Banking\nReview and verify invoices and cheque requests, prepare receiving & payment vouchers\n\n\nRequirements:\n\nA-level or Diploma in Accountancy\nAt least 3 years of working experience in the related field is required\nComputer skills (Outlook, Excel, Word) and Accounting software\nBilingual in English and Mandarin to liaise with staffs in China for accounts matters\nAbility to work independently with minimum supervision\nGood team player with a positive attitude and aptitude\nProactive and able to work in a fast-paced environment\nAttention to detail, accuracy, planning, organizing, scheduling and monitoring\n\nBenefits:\n\nDouble Pay or called 13th month\nPerformance bonus\nAnnual salary increment", "employment_types": ["Full Time", "Permanent"], "selling_points": [], "locations": ["Sheung Wan"], "categories": ["Accounting", "Accounting Clerk / Supervisor", "Banking / Finance", "Corporate Banking", "Admin & HR", "HR Supporting Staff"], "post_time": "2022-01-12T05:37:35Z", "salary": {"currency": null, "max": null, "min": null, "period": "monthly", "term": null}, "salary_visible": false, "title_keywords": ["officer"], "responsibilities": ["operations", "payment", "invoices", "accounts receivable", "full set of accounts", "monitor", "liaising with", "reports", "banking", "reporting", "mpf", "review", "reconciliations", "cash flow", "payroll", "tax", "irregularities", "month-end closing", "payments", "accounts payable"], "requirements": {"degrees": ["diploma"], "majors": ["accountancy"], "languages": ["english", "mandarin"], "language_level": [], "hard_skills": ["excel", "accounting software", "word", "computer skills", "outlook"], "soft_skills": ["good team player", "work independently", "fast-paced environment", "positive attitude", "attention to detail", "proactive"], "languages_combined": [{"language": "english", "language_level": []}, {"language": "mandarin", "language_level": []}]}, "experience_required": {"duration": ["at least 3 years"], "field": ["related"]}}, {"job_id": "100003009039275", "location_code": "hk", "company": "KBC Bank N. V.", "job_title": "Local Operational Risk Manager / Assistant Operations Manager", "description": "\u00a0\n\n\u201cWe\u201d are the largest Belgian bank with Asian activities in Singapore, Shanghai and Hong Kong.\u00a0 Each and every day our team in Asia strives to become the Preferred European Banking Partner of our domestic and European customers. To do so, we combine high professional standards and a pleasant working environment and we put our customers in the center point in everything we do. Also our internal customers!\n\nWe are looking for an enthusiastic and self-motivating talent to join our team as the Operational Risk Manager. With risk management being essential for long term sustainable operations, you can direct access to senior management via periodic or ad hoc reporting. You are also the focal person to supervise the branch\u2019s performance of control functions in relation to operational risk.\n\nAbout the job\n\nAs a Local Operational Risk Manager / Assistant Operations Manager you are in the lead for identifying, assessing and remediating operational risks;\u00a0\nYou closely work together with department heads in the branch to ensure the operations run smoothly and all risks are duly managed;\u00a0\nYou are supported and receive input from colleagues in head office and other international branches. This helps you to ensure operations comply with regulations , with KBC guidelines and with best international practices;\u00a0\nYou are involved in various challenging global projects that aim to enhance the efficiency and effectiveness of branch\u2019s operations;\u00a0\nYou contribute to implement changes to the day to day operations of the branch. You look for efficiency gains, for digitization and for increased operational collaboration between the international branches of KBC.\u00a0\n\nAbout you\n\nTo join the KBC team, you need to be a good team player, with ability to communicate clearly and concisely. You must\u00a0 be strong in analytical and problem-solving skills with great self-motivation and self-starting ability. You need to be familiar with regulatory requirements in banking industry and have minimum 5 years\u2019 experience in operational risk management. Finally, need to be eager to learn and continuously develop yourself to remain future proof in a swiftly changing environment..\n\nWe offer an attractive remuneration package in line with your relevant experience and the importance of the position.\u00a0\u00a0\n\nIf you feel like this position is a fit with your skill-set and expectations, please apply with a cover letter and CV (indicating your salary expectation) by email via \"Apply Now\". For any questions with regards to the position you can give us a call on\u00a0 (852) 2879 3363.\n\nAll information received will be used for recruitment purpose only. Applicants not being invited to interview within 6 weeks may consider their applications unsuccessful. All information on unsuccessful candidates will be deleted from our files within 12 months.", "employment_types": ["Full Time", "Permanent"], "selling_points": ["Operational Risk in banking", "Exposure in international banking", "Challenging global projects"], "locations": ["Wan Chai"], "categories": ["Banking / Finance", "Corporate Banking", "Professional Services", "Legal & Compliance", "Risk Management"], "post_time": "2022-01-11T09:15:52Z", "salary": {"currency": null, "max": null, "min": null, "period": "monthly", "term": null}, "salary_visible": false, "title_keywords": ["manager", "assistant operations manager"], "responsibilities": ["regulations", "reporting", "management", "control", "ad hoc", "day to day operations", "guidelines", "operations", "regulatory requirements", "develop", "banking", "senior management"], "requirements": {"degrees": [], "majors": [], "languages": [], "language_level": [], "hard_skills": ["problem-solving skills", "focal"], "soft_skills": ["good team player", "pleasant", "eager to learn", "self-motivation", "enthusiastic", "problem-solving skills"], "languages_combined": []}, "experience_required": {"duration": ["minimum 5 years"], "field": ["banking industry", "risk management"]}}, {"job_id": "100003009045777", "location_code": "hk", "company": "JAC Recruitment Hong Kong Co., Limited", "job_title": "SRM / Team Head, Commercial Banking - Foreign Bank - Budget HKD 60 - 100k", "description": "Our client is a fast growing foreign bank. They are looking for someone to join as a\u00a0SRM / Team Head, Commercial Banking.\u00a0\n\nKey Responsibilities\n\n- Expand existing client portfolio and on-board new clients (client turnover size ranges from HKD500m to over HKD 12b)\n\n-\u00a0Work with / Lead a team to achieve profitable growth, identify risk, and opportunities\n\n-\u00a0Promote Commercial Banking products e.g. deposits (CASA ), trade/ working capital finance, factoring, supply chain financing, equipment finance, DCM, treasury products.\n\n-\u00a0Work closely with PRC Banking Branches to strategize business plans.\n\n-\u00a0Prepare banking facilities and credit proposal\n\n\n\n\nRequirements\n\n- Around 6-12 years (SRM) and over 10 years (Team Head) experience in commercial banking (mid-caps and large SMEs) with good deal records.\n\n-\u00a0Licensing Requirements: HKMA Type 1 & 4 is mandatory; HKFI (preferable)\n\n-\u00a0Fluent in English, Cantonese and Mandarin\n\n\n*We offer*\n\n\"Interested candidates, please send an updated CV to kelvin.lam @jac-recruitment.com and CC jac.hk @jac-recruitment.com\"\n\nPersonal data collected will be used for employment-related purpose only. We regret to inform that only shortlisted candidates will be notified.", "employment_types": ["Full Time"], "selling_points": ["A fast growing Foreign Bank", "Trade/ working capital finance, factoring", "Client turnover size ranges from HKD500m to over"], "locations": ["Central & Western Area"], "categories": ["Banking / Finance", "Corporate Banking", "Credit Analysis / Approval", "Loan"], "post_time": "2022-01-13T08:39:35Z", "salary": {"currency": null, "max": null, "min": null, "period": "monthly", "term": null}, "salary_visible": false, "title_keywords": [], "responsibilities": ["lead a team", "business plans", "banking"], "requirements": {"degrees": [], "majors": [], "languages": ["cantonese", "english", "mandarin"], "language_level": ["fluent"], "hard_skills": ["hkma"], "soft_skills": [], "languages_combined": [{"language": "cantonese", "language_level": ["fluent"]}, {"language": "english", "language_level": ["fluent"]}, {"language": "mandarin", "language_level": ["fluent"]}]}, "experience_required": {"duration": ["6-12 years", "10 years"], "field": ["commercial", "banking", "team"]}}, {"job_id": "100003009049749", "location_code": "hk", "company": "China Construction Bank (Asia) Corporation Limited", "job_title": "AVP/VP, Big Data Analytics and Machine Learning (Business Implementation)", "description": "Responsibilities:\n\n\nDevelop an analytical and insight-driven customer-centric communication framework based on customer needs to deliver personalized and relevant communications in fulfilling their financial goals\nEstablish an end-to-end implementation process of customer journey via omni-channels\nEvaluate and monitor business results to enable close-loop learning\nLeverage on the integration of internal bank data and external data to drive effective customer targeting\nCollaborate with key internal stakeholders and effectively manage agency/ vendor relationships\nBring in new ideas and suggestions to continually enhance customer experience and improve cost effectiveness through driving innovation, system/ process improvement and refining standardized operating procedure to streamline manual support\nEnsure all communications/ programs/ projects are strictly adhered to banking practices, compliance and regulatory requirements\n\nRequirements:\n\n\n\nUniversity degree in Business Administration, Statistics or other related discipline\nA minimum of 10 years marketing or campaign management experience in financial service industry\nWith hands-on experience in developing and executing large scale CRM solutions / campaign management/ customer lifecycle marketing is an advantage\nStrong in transforming analytical concepts and developments into business strategies and applications for the uplift of business value\nAbility to build strong stakeholders relationships through thorough understanding of business requirements and the ability to analyse issues to find effective solutions\nGreat sense of ownership and servicing mindset to ensure efficient and effective customer service processes\nStrong project management, people and negotiations skills; able to motivate others to strike for excellence; capable of working independently as well as in a team\nSelf-motivated, result oriented, attentive to details and able to work under pressure\nProficiency in English and Chinese (both Cantonese and Putonghua)\nPlease specify your current and expected package in your application for reference.\u00a0\n\n\nApplicants who are not contacted within 8 weeks may consider their applications unsuccessful and their personal data will be retained by the bank for a period up to two years.\n\nAll information provided by applicants will be used for recruitment purposes only and will be used strictly in accordance with the bank\u2019s personal data policies, a copy of which will be provided upon request.", "employment_types": ["Full Time"], "selling_points": ["A minimum of 10 years experience", "Degree in BA, Statistic/ other related discipline", "With exp in CRM solution/ campaign management, etc"], "locations": ["Not Specified"], "categories": ["Banking / Finance", "Corporate Banking", "Retail Banking", "Professional Services", "Business Analysis / Data Analysis"], "post_time": "2022-01-14T09:11:30Z", "salary": {"currency": null, "max": null, "min": null, "period": "monthly", "term": null}, "salary_visible": false, "title_keywords": [], "responsibilities": ["collaborate with", "cost", "ideas", "data", "regulatory requirements", "compliance", "monitor", "implementation", "develop", "communication", "evaluate", "banking"], "requirements": {"degrees": ["university degree"], "majors": ["statistics", "business administration"], "languages": ["cantonese", "putonghua", "english", "chinese"], "language_level": ["proficiency"], "hard_skills": ["project management"], "soft_skills": ["efficient", "self-motivated", "independently", "ability to analyse", "capable", "attentive to details", "project management", "hands-on", "customer service", "result oriented", "thorough", "work under pressure"], "languages_combined": [{"language": "cantonese", "language_level": []}, {"language": "putonghua", "language_level": []}, {"language": "english", "language_level": ["proficiency"]}, {"language": "chinese", "language_level": ["proficiency"]}]}, "experience_required": {"duration": ["minimum of 10 years"], "field": ["management", "developing", "service industry", "marketing", "financial"]}}, {"job_id": "100003009044824", "location_code": "hk", "company": "DBS Bank Ltd", "job_title": "AVP / Senior Associate, IBG Marketing", "description": "Business Function\n\nCorporate and Investment Banking provides corporate customers with a full range of commercial banking products and services, including cash management services, current accounts, time deposits, trade finance, working capital finance, term loans and foreign exchange. Through our continued commitment, DBS has cultivated long-standing relationships with its customers in the region that are based on account relationship management, service differentiation, product development and rigorous credit standards.\n\nResponsibilities\n\nReporting to VP, IBG Marketing. This role will focus on marketing activities related to Greater Bay Area, sustainability, and large corporates.\nGreater Bay Area \u2013 work closely with stakeholders (including China onshore and offshore teams) on brand building, lead acquisition and customer engagement marketing activities.\nSustainability \u2013 engage with relationship managers and dial up the bank's sustainability image via various initiatives including thought leadership contents.\nLarge corporate \u2013 prepare and deliver \u2018insight-led\u2019 programs such as events, webinars, sponsorship, content marketing amplifications, etc.\nUtilize digital marketing and social media to drive awareness, acquisition and advocacy, including WeChat and LinkedIn.\nPartner with Group Strategic Marketing and Communications to shape external perception through interviews and press statements, and to ensure marketing programs are executed in line with regional brand standards.\nDrive the Awards strategy across the business, amplifying wins both externally and internally.\nUndertake continuous analysis of competitive environment and customer trends to ensure effectiveness of branding and product marketing strategy.\nAble to make use of data to make informed decisions in optimizing marketing effectiveness across channels (including own media, paid media, online & offline) to maximize marketing ROI.\nCollaborate with different partners and marketing agencies to enhance the branding of DBS IBG.\n\nRequirements\n\nDegree holder in Marketing / Business Administration or other related discipline.\nAt least 8+ years of experience in B2B marketing, preferably in the financial services industry.\nA successful track record of developing and delivering successful marketing strategies and customer-centric campaigns.\nFluent written and spoken English and Chinese, and an eye for design. Mandarin fluency is an advantage.\nProven analytical capabilities and a \u201cdata-driven\u201d mindset.\nPositive personality with the ability to work towards challenging deadlines while paying attention to details.\nSpecific experience in content marketing, digital marketing and social media.\nProven ability to plan and manage budgets.\nCandidates with less experience will be considered for the role as Senior Associate.\n\nCore Competencies\n\nStrategic mindset with can-do attitude.\nConfident with good command of both written and spoken English and Chinese (including Mandarin).\nStrong interpersonal and communication skills to work with various internal and external stakeholders.\nProblem-solving and project management capabilities; manage concurrent tasks independently with high accuracy and efficiency.", "employment_types": ["Full Time"], "selling_points": ["See job description.", "See job description.", "See job description."], "locations": ["Central"], "categories": ["Banking / Finance", "Corporate Banking", "Marketing / Public Relations", "Marketing - General / Support", "Marketing - Marketing Communication"], "post_time": "2022-01-13T06:25:53Z", "salary": {"currency": null, "max": null, "min": null, "period": "monthly", "term": null}, "salary_visible": false, "title_keywords": ["senior associate"], "responsibilities": ["collaborate with", "reporting", "social media", "data", "analysis", "teams", "digital marketing", "contents"], "requirements": {"degrees": ["degree holder"], "majors": ["marketing", "business administration"], "languages": ["english", "chinese", "mandarin"], "language_level": ["fluency", "advantage", "good command", "fluent"], "hard_skills": ["project management", "problem-solving"], "soft_skills": ["confident", "communication skills", "independently", "can-do attitude", "problem-solving", "project management", "attention to details", "interpersonal", "driven", "positive"], "languages_combined": [{"language": "english", "language_level": ["good command", "fluent"]}, {"language": "chinese", "language_level": ["good command", "fluent"]}, {"language": "mandarin", "language_level": ["fluency", "advantage", "good command"]}]}, "experience_required": {"duration": ["at least 8+ years"], "field": ["social media", "financial services industry", "marketing", "digital marketing"]}}, {"job_id": "100003009049579", "location_code": "hk", "company": "China Construction Bank (Asia) Corporation Limited", "job_title": "AVP / VP, Big Data Analytics & Machine Learning", "description": "Responsibilities:\n\n\nExplore the availability, access and transformation/ use of unstructured data (browsing data, voice, email, picture, videos) for analytics and customer contact purpose\nHands-on develop advanced analytics/ Machine Learning-based solutions to uplift effectiveness of analytics, modelling and customer contact riding on (i) supervised/ unsupervised Machine Learning techniques (ii) unstructured data e.g. digital footprint\nStudy and develop the business implementation of speech and text analytics\nIntegrate customer external and internal data, structured and unstructured\nDevelop close-loop learning path and ensure insights and learnings are carried out for continuous customer interactions\nAs the Subject Matter Expert, trainer and advocate to uplift the machine learning skillset and culture of existing analysts pool\n\nRequirements:\n\nBachelor\u2019s / Master's degree in Computer Science, Data and Information Management or a related discipline\nA data scientist with minimum 8 years of hands-on experience in developing and executing large scale analytics deliverables/ projects in the Financial Services Industry\nDeep experience in applying artificial intelligence and machine learning techniques/algorithms, infused with industry knowledge, to enhance business strategies\nStrong in transforming analytical concepts and developments into business strategies and applications for the uplift of business value\nAbility to build strong stakeholders\u2019 relationships through thorough understanding of business requirements and the ability to analyse issues to find effective solutions\nSolid experience in training analysts on machine learning techniques\nEffective presentation, communication and interpersonal skills\nGreat sense of ownership and servicing mindset to ensure efficient and effective customer service processes\nProficiency in English and Chinese (both Cantonese and Mandarin)\nCandidate with less experience will be considered for the AVP position\n\nPlease specify your current and expected package in your application for reference.\u00a0\n\nApplicants who are not contacted within 8 weeks may consider their applications unsuccessful and their personal data will be retained by the bank for a period up to two years.\n\nAll information provided by applicants will be used for recruitment purposes only and will be used strictly in accordance with the bank\u2019s personal data policies, a copy of which will be provided upon request.", "employment_types": ["Full Time", "Permanent"], "selling_points": ["Data Management", "Big Data", "Machine Learning"], "locations": ["Not Specified"], "categories": ["Banking / Finance", "Corporate Banking", "Retail Banking", "Professional Services", "Business Analysis / Data Analysis"], "post_time": "2022-01-14T08:54:13Z", "salary": {"currency": null, "max": null, "min": null, "period": "monthly", "term": null}, "salary_visible": false, "title_keywords": [], "responsibilities": ["data", "implementation", "subject matter expert", "develop", "contact"], "requirements": {"degrees": ["degree", "bachelor", "master"], "majors": ["computer science"], "languages": ["cantonese", "english", "chinese", "mandarin"], "language_level": ["proficiency"], "hard_skills": [], "soft_skills": ["efficient", "ability to analyse", "deep", "hands-on", "learning", "communication and interpersonal skills", "thorough", "customer service", "presentation"], "languages_combined": [{"language": "cantonese", "language_level": []}, {"language": "english", "language_level": ["proficiency"]}, {"language": "chinese", "language_level": ["proficiency"]}, {"language": "mandarin", "language_level": []}]}, "experience_required": {"duration": ["minimum 8 years"], "field": ["financial services industry", "business", "training", "developing"]}}, {"job_id": "100003009049948", "location_code": "hk", "company": "DBS Bank (Hong Kong) Limited", "job_title": "Team Lead, Technology, Project Management, Corporate Banking", "description": "See job description for detailsBusiness Function\nTechnology and Operations (T&O) enables and empowers the bank with an efficient, nimble and resilient infrastructure through a strategic focus on productivity, quality & control, technology, people capability and innovation. In T&O, we manage the majority of the Bank's operational processes and inspire to delight our business partners through our multiple banking delivery channels.\n\nResponsibilities\nWork as Application Team Lead to maintain and support applications on Risk Platform to provide good functionality, availability, performance and security\nWriting scalable, robust, testable, efficient and easily maintainable code\nPerform user requirement analysis, to identify and recommend technology solutions for continuous improvement of the systems\nDeliver solution for a system or systems within a platform on time, within budget and aligned with appropriate change framework while maintaining quality and stability\nSupport users in User Acceptance Tests, prepare application system documentations and conduct user training on application systems\nAcquire new technologies and propose appropriate solutions for solving business requirements as well as improving system efficiency and control\nWork closely with release managers and other stakeholders to forward plan the release windows and cycles across the platform, including putting together release calendars and scheduling environments usage.\nEnsure development documentations and artefacts (such as release notes, build procedures etc.) are current, relevant and correct\nEnsure that software packages and programs are well documented and has reasonable test cover\nResolve technical problems and to provide application support to users\nRequirements\nDegree holder in Information Technology or related discipline\nMinimum 5 years of relevant experiences in financial IT system analysis, design, development and implementation.\nExperience in Scrum/Agile/DevOps would be required.\nSound knowledge of Java technology would be required\nExperience in Python would be an advantage.\nProven knowledge on API, micro-services, and development framework for enterprise environment would be a plus\nExperience in Confluence/Jira/SonarQ would be a plus\nStrong awareness of application security, technology risk and source control\nStrong analytical and problem-solving skill\nTeam player, ability to work under pressure, handle multiple tasks, self-motivated, able to learn quickly, with good communication and interpersonal skills\nAble to communicate between local and regional team.\nReliable, intelligent, diligent and good problem-solving skills\nApply Now\n\n\nInterested candidates, please click APPLY NOW \u00a0to apply.\n\nWe offer a competitive salary and benefits package and the professional advantages of a dynamic environment that supports your development and recognises your achievements.\n\nWe regret only shortlisted candidates will be notified.", "employment_types": ["Full Time"], "selling_points": ["maintain and support applications on Risk Platform", "5 years of relevant experiences", "Experience in Scrum/Agile/DevOps"], "locations": ["Not Specified"], "categories": ["Banking / Finance", "Corporate Banking", "Project Finance", "Others"], "post_time": "2022-01-14T09:29:08Z", "salary": {"currency": null, "max": null, "min": null, "period": "monthly", "term": null}, "salary_visible": false, "title_keywords": ["lead"], "responsibilities": ["user requirement", "control", "software", "maintaining", "operations", "analysis", "infrastructure", "quality", "systems", "budget", "application system", "procedures", "scheduling", "maintain", "plan", "banking", "application systems"], "requirements": {"degrees": ["degree holder"], "majors": ["information technology"], "languages": [], "language_level": [], "hard_skills": ["java", "plus", "agile", "devops", "analysis", "problem-solving", "python", "problem-solving skills"], "soft_skills": ["self-motivated", "agile", "problem-solving", "diligent", "handle multiple tasks", "communication and interpersonal skills", "problem-solving skills", "team player", "reliable", "work under pressure"], "languages_combined": []}, "experience_required": {"duration": ["minimum 5 years"], "field": ["development", "devops", "design", "it", "financial"]}}, {"job_id": "100003009043639", "location_code": "hk", "company": "Page Personnel", "job_title": "Compliance Advisory - Top Tier Asian Corporate Bank", "description": "Our client is a leading International bank with operations in both banking and treasury services.\n\n\n\nPerform financial reporting functions and handle monthly, quarterly and year-end reporting e.g. preparation of financial reports, interim and annual reports\nEffective control on the operations, structure and workflow of financial data and general ledger production of the Group\nFormulate changes in accounting policies and practices or the adoption of new accounting policies and the monitoring of their subsequent implementations\nAssist in enhancements to financial controls and reporting process including automation and UAT\nLiaise with external auditors for annual audit and tax matters\n\n\nRequirements:\n\nBachelor's Degree in Accounting, Finance or relevant discipline\nMinimum 3 years' experience in banking and financial accounting /financial reporting functions\nMember of CPA is an added advantage\nHigh level of multi-tasking and time management skill are required\nA team-player with excellent working attitude; willing to take on multiple functions\nExcellent verbal and written communication skills\n\n\nApply Today\n\nTo apply online (Word attachment only), please click the 'Apply' button. Please note that only short-listed candidates will be contacted.", "employment_types": ["Full Time", "Permanent"], "selling_points": ["Exposure of Regional General Compliance", "Stable Working Hours", "Competitive Salary and Fringe Benefits"], "locations": ["Not Specified"], "categories": ["Banking / Finance", "Corporate Banking", "Financial Services", "Professional Services", "Legal & Compliance"], "post_time": "2022-01-13T01:11:50Z", "salary": {"currency": null, "max": null, "min": null, "period": "monthly", "term": null}, "salary_visible": false, "title_keywords": [], "responsibilities": ["data", "operations", "general ledger", "communication", "accounting policies", "liaise with", "tax matters", "control", "uat", "reports", "banking", "reporting", "management", "annual audit", "monitoring", "year-end", "financial reports", "financial reporting", "external auditors"], "requirements": {"degrees": ["degree", "bachelor"], "majors": ["finance", "accounting"], "languages": [], "language_level": [], "hard_skills": ["cpa", "word"], "soft_skills": ["team-player", "communication skills", "multi-tasking", "time management skill"], "languages_combined": []}, "experience_required": {"duration": ["minimum 3 years"], "field": ["accounting", "financial", "banking"]}}, {"job_id": "100003009044257", "location_code": "hk", "company": "OCBC Wing Hang Bank Limited", "job_title": "VP/AVP, China Offshore Institutional Sales", "description": "Our client is currently providing a position of Deposit and Remittance VP for the Payment & Remittance Team. The major responsibility is to handling cash, deposits and remittance functions including cash/cheques transactions, foreign currency exchange, time deposits, remittance and correspondent banking.\n\nClient Details\n\nOur client is a leading Japanese bank which provides financial products and services to a wide range of clients, including individuals, small and medium-sized enterprises, large corporations, financial institutions and public sector entities. With a long history and a comprehensive service set providing commercial, corporate and investment banking. It leads our client to become the world's leading financial group.\n\nDescription\n\nProcess and control the deposits/remittance related operations which include, but not limited to, account related services, pooling services, cash deposit/withdrawal, inward/outward cheque clearing, time deposits, inward/outward remittance, corresponding banking, and etc.\nIdentify/review the risk factors and apply effective risks mitigating measures/treatments\nReport to the superiors of any operations irregularities, incidents, anti-money laundering and drug trafficking events\nProvide inputs and participate in the Section's improvement/development targets which should be in line with the Bank's objectives and direction\nAssist to work out, update and execute the disaster recovery plan, business continuity plan, split operations plan, the Work-from-Home plan and etc.\nProvide inputs and participate in the Bank's infrastructure, new products, services standard and operation excellence projects\n\nProfile\n\nBachelor's Degree or above, preferably in Business, Accounting, Finance or related disciplines\nMinimum 8 years' experience in banking with exposure in deposit and remittance related operations; operation experience in trade services, loan operations or treasury settlements is an advantage\nHand on experience in SWIFT, CHATS, FPS operations and project management is preferred; knowledge in IT applications and solutions is an advantage\nProficiency in English and Mandarin\n\nJob Offer\n\nExposure working in international bank\nGood learning environment\nWell-established platform\nCompetitive Package + Benefits\nProfessional Growth and Solid Training\n\nTo apply online please click the 'Apply' button below. For a confidential discussion about this role please contact Michael K. Lee on +852 3602 2441", "employment_types": ["Full Time", "Permanent"], "selling_points": ["Distribute FICC derivatives", "Solicit new business opportunities", "Actively identify potential business"], "locations": ["Sheung Wan"], "categories": ["Banking / Finance", "Corporate Banking", "Corporate Finance", "Treasury"], "post_time": "2022-01-13T03:34:34Z", "salary": {"currency": null, "max": null, "min": null, "period": "monthly", "term": null}, "salary_visible": false, "title_keywords": ["sales"], "responsibilities": ["business continuity", "control", "irregularities", "operations", "review", "infrastructure", "transactions", "project management", "payment", "cheques", "plan", "banking", "report"], "requirements": {"degrees": ["degree or above", "bachelor"], "majors": ["related disciplines", "finance", "business", "accounting"], "languages": ["japanese", "english", "mandarin"], "language_level": ["proficiency"], "hard_skills": ["small", "project management", "anti-money laundering", "swift", "exchange"], "soft_skills": ["project management", "comprehensive", "learning"], "languages_combined": [{"language": "japanese", "language_level": []}, {"language": "english", "language_level": ["proficiency"]}, {"language": "mandarin", "language_level": ["proficiency"]}]}, "experience_required": {"duration": ["minimum 8 years"], "field": ["related", "project management", "operation", "banking"]}}, {"job_id": "100003009039895", "location_code": "hk", "company": "DBS Bank Ltd", "job_title": "Senior Associate, Operations, Structured Trade", "description": "Our client is a globally renowned Asian bank with over 600 employees in Hong Kong. They are looking for candidate with at least 2 years of experience in general compliance/advisory to join them.\n\nClient Details\n\nOur client is a globally renowned Asian bank. With over 600 people in Hong Kong, they provide corporate banking services including transaction banking, financial advisory, financing services, merger and acquisition etc.\n\nTo cope with its business growth, they are looking for candidate with at least 2 years of experience in general compliance/advisory to join them. Candidate would be expected to perform advisory regarding the regional general compliance. Candidate would enjoy great regional exposure and travelling experience.\n\nDescription\n\nPerform advisory and coordination task regarding the regional general compliance policy\nEnhance compliance management framework on regional general compliance area\nMonitor the regional oversea office's compliance status by conducting off-site or on-site monitoring\nRespond to individual cases and issues instructed by the divisions in Compliance Group\nConduct tasks in cooperation with AML team in the department\n\nProfile\n\nBachelor degree holder, preferably finance or other related discipline\n2 years+ experience in general compliance/compliance advisory, preferably from corporate bank\nExcellent command both written and spoken English\nResponsible, proactive and strong in problem solving\n\nJob Offer\n\nStrong Reputation\nExposure of Regional General Compliance\nConvenient Location\nAnnual Leave: 18 days\nMedical Benefit Cover Spouse and Dependences\nDental Benefits Cover Spouse and Dependences\n\nTo apply online please click the 'Apply' button below. For a confidential discussion about this role please contact Janet CHang on +852 3602 2459.", "employment_types": ["Full Time"], "selling_points": ["With structured trade operations experience", "Knowledge in import/ export/  LC", "See job description."], "locations": ["Kwun Tong"], "categories": ["Banking / Finance", "Corporate Banking", "Order Processing & Operation / Settlement"], "post_time": "2022-01-11T14:25:41Z", "salary": {"currency": null, "max": null, "min": null, "period": "monthly", "term": null}, "salary_visible": false, "title_keywords": ["senior associate", "operations"], "responsibilities": ["management", "aml", "compliance", "monitor", "monitoring", "coordination", "banking"], "requirements": {"degrees": ["bachelor degree holder"], "majors": ["finance"], "languages": ["english"], "language_level": ["excellent"], "hard_skills": ["problem solving", "aml"], "soft_skills": ["problem solving", "proactive", "coordination", "responsible"], "languages_combined": [{"language": "english", "language_level": ["excellent"]}]}, "experience_required": {"duration": ["at least 2 years"], "field": ["compliance", "business", "general compliance"]}}, {"job_id": "100003009012276", "location_code": "hk", "company": "National Bank of Pakistan", "job_title": "Credit & Trade Finance Officer", "description": "\u00a0\nResponsibilities\n\n- Distribute FICC derivatives, structured products, and cross boarder solutions to Chinese institutional clients\n- Solicit new business opportunities and continue to grow and strengthen existing relationship and institutional client networks\n- Work closely with bond syndicate and onshore China team to drive the Fixed Income business\n- Actively identify potential business by working with trading and structuring to deliver tailor-made solutions to institutional clients\n\nRequirements\n\n- Bachelor degree in business or related disciplines\n- A minimum of 5 to 7 years' of relevant experience in FICC sales, covering China-based bank and non-bank financial institutional clients\n- Demonstrated track record in developing and implementing strategies to achieve sales results\n- Strong knowledge in global financial markets, fixed income products, derivatives, and structured products\n- Native in Mandarin is a MUST. Proficiency in both spoken and written Chinese and English\n- Excellent interpersonal and communication skills, self-driven and a good team player\n- Strong work ethic, attention to details and willing to learn\n- Well versed in Bloomberg, MS Excel/Word/Powerpoint\n\nAttractive remuneration package will be offered to the right candidate. Please apply with full resume stating present & expected salary and contact phone number\u00a0to\u00a0The Human Resources Manager, 10/F, 161 Queen\u2019s Road Central, Hong Kong.\u00a0Please quote the reference.\n\nPersonal data collected will be used for recruitment purpose only. For more information, please visit our website:\u00a0http://www.ocbcwhhk.com.", "employment_types": ["Contract"], "selling_points": [], "locations": ["Not Specified"], "categories": ["Banking / Finance", "Corporate Banking"], "post_time": "2022-01-11T04:56:31Z", "salary": {"currency": null, "max": null, "min": null, "period": "monthly", "term": null}, "salary_visible": false, "title_keywords": ["finance officer"], "responsibilities": ["business opportunities"], "requirements": {"degrees": ["degree", "bachelor"], "majors": ["related disciplines", "business"], "languages": ["english", "chinese", "mandarin"], "language_level": ["native", "proficiency"], "hard_skills": ["powerpoint", "ms excel", "bloomberg", "word"], "soft_skills": ["communication skills", "good team player", "interpersonal", "willing to learn", "work ethic", "attention to details", "structured", "driven"], "languages_combined": [{"language": "english", "language_level": ["proficiency"]}, {"language": "chinese", "language_level": ["proficiency"]}, {"language": "mandarin", "language_level": ["native"]}]}, "experience_required": {"duration": ["minimum of 5 to 7 years"], "field": ["relevant experience", "financial"]}}, {"job_id": "100003009039752", "location_code": "hk", "company": "Page Personnel", "job_title": "KYC/ CDD Analyst - International Corporate Bank!", "description": "Business Function\n\nTechnology and Operations (T&O) enables and empowers the bank with an efficient, nimble and resilient infrastructure through a strategic focus on productivity, quality & control, technology, people capability and innovation. In T&O, we manage the majority of the Bank's operational processes and inspire to delight our business partners through our multiple banking delivery channels.\n\nResponsibilities\n\nHandle multi releasing functions in Structured Trade Operations\nHandling Front-to-Back Documentary Credit and Back-to-Back Documentary Credit on Commodities Trade for serving Structured Trade Finance (\u201cSTF\u201d) clients\nAnswering in-scope enquiry from Structured Trade clients on Commodities Trade.\nPerform supervisor and checker functions assigned by Section Manager including people management, data and information verification, screening application etc.\nSupport on STF projects assigned by team managers\n\nRequirements:\n\nMinimum 5 years experience in trade related banking operations\nExperience in structured trade operations in an advantage\nIn-depth trade operations experience and knowledge on trade related international rules, regulations and practices.\nStrong sense of risk and fraud control\nCapable to work effectively under pressure and tight deadlines.\nGood written English and Chinese.\n\nApply Now\n\nWe offer a competitive salary and benefits package and the professional advantages of a dynamic environment that supports your development and recognises your achievements.\n\nWe regret only shortlisted candidates will be notified", "employment_types": ["Full Time", "Permanent"], "selling_points": ["International working environment", "Generous package and benefits", "Rewarding and stimulating job tasks"], "locations": ["Not Specified"], "categories": ["Banking / Finance", "Corporate Banking", "Financial Services", "Order Processing & Operation / Settlement"], "post_time": "2022-01-11T10:55:29Z", "salary": {"currency": null, "max": null, "min": null, "period": "monthly", "term": null}, "salary_visible": false, "title_keywords": ["analyst"], "responsibilities": ["data and information verification", "operations", "management", "screening application"], "requirements": {"degrees": [], "majors": [], "languages": ["english", "chinese"], "language_level": ["good"], "hard_skills": ["dynamic"], "soft_skills": ["work effectively", "dynamic environment", "under pressure", "capable", "structured"], "languages_combined": [{"language": "english", "language_level": ["good"]}, {"language": "chinese", "language_level": ["good"]}]}, "experience_required": {"duration": ["minimum 5 years"], "field": ["related", "banking"]}}, {"job_id": "100003009038653", "location_code": "hk", "company": "China Construction Bank (Asia) Corporation Limited", "job_title": "General Clerk \u2013 Commercial Banking (6 month or 1 year Contract)", "description": "Responsibilities:\n\nProcessing Import/Export i.e. Documentary Credit and Collection\nL/C Negotiations, Confirmation & Discounting.\nDocumentary Credits/Amendments in line with the latest UCP 600\nScrutinizing & Examining of documents received under Letters of Credit and or Collection/Payment basis in timely manner as per URC, UCP & internal guidelines\nOther tasks assigned by Management.\n\n\u00a0Requirements:\n\nMinimum 3 to 5 years hands on Trade Finance related experience in banking environment.\nWell versed with UCP 600.\u00a0 Formal ICC Certification (CDCS) would be considered as an added qualification.\nWith knowledge in T24 will be preferred\n\nWe offer competitive salary and other fringe benefits including Mandatory Provident Fund, Medical etc.\n\nInterested candidates may send detailed resume stating present and expected salary to HR Department.\n\nNational Bank of Pakistan, Hong Kong by e-mail by clicking \u201c Apply Now\u201d\n\nAll collected information only for recruitment purpose.", "employment_types": ["Full Time", "Permanent"], "selling_points": ["Assist RM in performing the documents, A/C opening", "KYC, AML", "High Diploma or above in any discipline"], "locations": ["Kowloon Bay"], "categories": ["Admin & HR", "Clerical / Admin Staff", "Banking / Finance", "Corporate Banking", "Order Processing & Operation / Settlement"], "post_time": "2022-01-11T07:40:20Z", "salary": {"currency": null, "max": null, "min": null, "period": "monthly", "term": null}, "salary_visible": false, "title_keywords": ["general clerk"], "responsibilities": ["management", "guidelines", "letters", "other tasks", "payment"], "requirements": {"degrees": [], "majors": [], "languages": [], "language_level": [], "hard_skills": [], "soft_skills": ["hands on"], "languages_combined": []}, "experience_required": {"duration": ["minimum 3 to 5 years"], "field": ["related", "finance", "banking"]}}, {"job_id": "100003009049141", "location_code": "hk", "company": "Bangkok Bank Public Co Ltd", "job_title": "Senior Project Analyst / Project Analyst (Ref: HKC-21/175/240-DB)", "description": "Our client is one of the top international corporate banks in the world. They are currently looking for a KYC Analyst to join their KYC team to handle KYC/ CDD, customer onboarding for corporate clients. The candidate should have 2-3 years of working experience in KYC/ CDD within corporate banking.\n\nClient Details\n\nOur client is one of the top international corporate banks in the world and they are now opening an exciting role for a KYC analyst to perform KYC/CDD, customer onboarding and periodic review for corporate clients. They have a diverse and complex portfolio in serving their multiproduct clients in their APAC strategy.\n\nDescription\n\nResponsible for performing KYC/ CDD procedures at both customer onboarding and periodic review, covering end to end process as both maker and checker roles as a support function within first line of defence\nLiaise with customers for obtaining updated KYC documents when requested by relationships managers\nManager KYC/ CDD trigger events and reviews and ensure appropriate actions are taken accordance with the AML/ KYC policies and procedures\nPerform name screening and searches on prospective customers and existing customer base\nMaintain customer lists and records, archive documents etc.\nManage weekly/ monthly MIS and issue reporting\nAssist the supervisor in any ad hoc tasks\n\nProfile\n\nBachelor's degree with major in Business Administration, Management, Accounting, Finance or relevant discipline\n2-3 years of working experience in KYC/CDD within corporate banking\nWorking experience in credit administration team would be an advantage\nFamiliar with internal control, banking operation and AML function\nStrong knowledge in regulatory compliance guidelines and requirements\nStrong English and Chinese communications skills both verbally and written\nStrong interpersonal skills, good team player and able to multi-task and work under pressure\n\nJob Offer\n\nInternational working environment\nGenerous package and benefits\nRewarding and stimulating job tasks\nMedical benefits\n21 days annual leave\n\nTo apply online please click the 'Apply' button below. For a confidential discussion about this role please contact Esther Liu on +852 2258 3537", "employment_types": ["Full Time"], "selling_points": [], "locations": ["Central"], "categories": ["Banking / Finance", "Corporate Banking", "Others", "E-commerce", "Product Management / Business Analyst"], "post_time": "2022-01-14T08:13:43Z", "salary": {"currency": null, "max": null, "min": null, "period": "monthly", "term": null}, "salary_visible": false, "title_keywords": ["analyst"], "responsibilities": ["reporting", "management", "aml", "guidelines", "cdd", "kyc", "review", "procedures", "policies", "ad hoc tasks", "compliance", "work under pressure", "maintain", "banking", "liaise with", "internal control", "administration"], "requirements": {"degrees": ["degree", "bachelor"], "majors": ["finance", "accounting", "business administration"], "languages": ["english", "chinese"], "language_level": [], "hard_skills": ["cdd", "internal control", "aml", "kyc"], "soft_skills": ["good team player", "multi-task", "responsible", "diverse", "interpersonal skills", "work under pressure"], "languages_combined": [{"language": "english", "language_level": []}, {"language": "chinese", "language_level": []}]}, "experience_required": {"duration": ["2-3 years"], "field": ["administration", "team", "banking"]}}, {"job_id": "100003009046508", "location_code": "hk", "company": "Page Personnel", "job_title": "Business Risk and Control Senior Associate - Top US Bank", "description": "Job Descriptions:\n\n\n\nProvide basic clerical and administrative support\nAssist front line to complete KYC re-assessment and monitor completion of KYC re-assessment\nCompile regular KYC statistic including but not limited to validating data for reporting to AML CC and management\nHandle enquiries from KYC Support Center and front lines on KYC reassessment matter\nHandle account opening documentations, conducting different kinds of background search\nHandle any tasks as assigned by Team Head\n\n\u00a0Job Requirements:\n\n\nHigh Diploma or above, Undergraduate preferable\nMinimum 1 year banking experience in KYC re-assessment field\nStrong customer service orientation\nGood command of written and spoken English, Cantonese and Mandarin\nHave experience in banking industry will be an advantage\nGood knowledge of AML Compliance policy and guidelines\nTo apply, please send your detailed resume\u00a0stating present and expected salary\u00a0to one of the following channels:-\nBy Email\nBy Fax: 3718 2910\n\nApplicants who are not contacted within 8 weeks may consider their applications unsuccessful and their personal data will be retained by the bank for a period up to two years.\n\nAll information provided by applicants will be used for recruitment purposes only and will be used strictly in accordance with the bank's personal data policies, a copy of which will be provided upon request.", "employment_types": ["Full Time", "Permanent"], "selling_points": ["International and dynamic working environment", "Rewarding and stimulating job tasks", "Exposure to APAC regional business"], "locations": ["Not Specified"], "categories": ["Banking / Finance", "Corporate Banking", "Order Processing & Operation / Settlement", "Risk Management"], "post_time": "2022-01-13T12:33:55Z", "salary": {"currency": null, "max": null, "min": null, "period": "monthly", "term": null}, "salary_visible": false, "title_keywords": ["senior associate"], "responsibilities": ["reporting", "management", "aml", "data", "administrative support", "account opening", "monitor", "handle enquiries", "kyc"], "requirements": {"degrees": ["high diploma or above"], "majors": [], "languages": ["cantonese", "english", "mandarin"], "language_level": ["good command"], "hard_skills": ["aml", "kyc"], "soft_skills": ["customer service", "detailed"], "languages_combined": [{"language": "cantonese", "language_level": ["good command"]}, {"language": "english", "language_level": ["good command"]}, {"language": "mandarin", "language_level": ["good command"]}]}, "experience_required": {"duration": ["minimum 1 year"], "field": ["banking industry", "banking experience"]}}, {"job_id": "100003009039028", "location_code": "hk", "company": "KBC Bank N. V.", "job_title": "Junior Officer, Remittance & Settlement", "description": "We are now seeking a high caliber candidate to join our Hong Kong Branch.\n\nResponsibilities:\n\nAssist project manager in liaising between various business units and implementing project management to achieve business goal\nPerform business analysis through working with different stakeholders to document requirements and associated use cases, outline problems and identify stakeholders' needs so as to thoroughly define and represent the mandated functionality and results\nAnalyse business requirements and design solutions/new process flows to address business problems\nIdentify, document and communicate possible gaps in business requirements, and at times collaborate with other Analysts to provide appropriate recommendation / solution options\nPrepare test plan and execute cases for SIT and provide support to users in UAT test execution\nPerform ad-hoc duties as and when required\n\nRequirements:\n\nDegree holder in Business Management, Finance or other related disciplines\nMinimum 5 years of business analysis experience in the banking industry\nHands-on experience or previously worked in a capacity of Customer Service or Loans Service, especially in the field of Current Account / Saving Account; Time Deposit and Clearing processes with HKICL\nExcellent communication, presentation and interpersonal skills\nSelf-motivated, strong sense of responsibility, accountability and willing to learn\nInterested in transitioning career into project based environment\nStrong analytical and problem-solving skills\nStrong PC skills, including Microsoft Word, Excel and PowerPoint\n\n(Candidate with more experience will be considered as Senior Project Analyst.)\n\nWe offer excellent career prospects to the right candidate. Salary will be commensurate with qualifications and experience. Interested parties please apply with\u00a0full resume, stating current / expected salary and availability to The Human Resources Manager, Bangkok Bank Public Co. Ltd., Bangkok Bank Building, 28 Des Voeux Road Central, Hong Kong.\n\nPersonal data provided by job applicants will be used solely for considering suitability for the post and strictly in accordance with our personal data policies which are available on request.\n\n(Only shortlisted candidates will be contacted.)", "employment_types": ["Full Time", "Permanent"], "selling_points": ["3 years' relevant experience", "Exposure in international banking", "Perform inward & outward remittance"], "locations": ["Wan Chai"], "categories": ["Banking / Finance", "Corporate Banking", "Others", "Order Processing & Operation / Settlement"], "post_time": "2022-01-11T08:26:15Z", "salary": {"currency": null, "max": null, "min": null, "period": "monthly", "term": null}, "salary_visible": false, "title_keywords": ["officer", "junior"], "responsibilities": ["collaborate with", "provide support", "uat", "design solutions", "project management", "plan", "ad-hoc duties", "business analysis", "analyse"], "requirements": {"degrees": ["degree holder"], "majors": ["related disciplines", "finance", "business"], "languages": [], "language_level": [], "hard_skills": ["business management", "excel", "microsoft word", "analysis", "powerpoint", "problem-solving skills", "pc skills"], "soft_skills": ["self-motivated", "accountability", "sense of responsibility", "interested in", "willing to learn", "communication", "hands-on", "customer service", "interpersonal skills", "problem-solving skills", "presentation"], "languages_combined": []}, "experience_required": {"duration": ["minimum 5 years"], "field": ["business analysis", "banking industry", "customer service"]}}, {"job_id": "100003009039872", "location_code": "hk", "company": "Page Personnel", "job_title": "Credit Admin Senior Officer - International Corporate Bank!", "description": "Our client is one of the largest financial services firms in the United States. They are currently looking for a high calibre as business risk and control senior associate to join the APAC Regional Business Risk and Control team to handle risk and control self assessment in APAC. The candidate should have at least 5 years of working experience in risk management within FS industry.\n\nClient Details\n\nOur client is one of the largest US financial services firms in the world, headquartered in San Francisco and founded in 1852. They are now opening an exciting role for business risk and control Senior Associate to join the APAC Regional Business Risk and Control team to manage front line control responsibilities for Business Process Management and Risk and Control Self Assessment for APAC. They identify, assess and mitigate risks across financial crimes, regulatory and operational risk types as well as designing and implementing controls to ensure work effectiveness by managing risk across corporate investment group.\n\nDescription\n\nResponsible for completing RCSA for the legal entity in APAC for the business and work with different business stakeholders for risk and control processes\nHandle frontline line responsibilities for the Regional International Business Process Management (BPM), Integrated Process Risk and Control (IPRC) programs and the business process risk ranking effort for APAC\nImplement Risk and Control Self-Assessments (RCSA) framework, identify and document RCSA activities associated with business processes\nDeliver Line of Business (LoB) RSCA, remediate RCSA quality assurance, identify control gaps and improvement opportunities in IPRC exercise\nWork closely with different stakeholders including international compliance, international operational risk, independent risk management, frontline business groups and business process subject matter experts for the RSCA program\nProvide guidance and advice on developing, implementing and monitoring business processes to identify, assess and mitigate risk\nDesign and implement risk mitigation strategies and controls, risk monitoring and risk reporting processes\n\nProfile\n\nBachelor's degree with major in risk management, business administration or relevant discipline\nAt least 5 years of working experience in risk management/ compliance (including operational risk, compliance, financial crimes, legal, credit risk, market risk, IT system security, business process management) within corporate investment banking/ risk and advisory role\nExperience in RCSA is a must\nStrong knowledge in excel, VLOOKUP and PPT\nExcellent stakeholder management skills with the ability to work with geographically dispersed teams and to communicate with all levels of stakeholders\nStrong analytical skills and data management skills\nExcellent English communication skills and interpersonal skills\n\nJob Offer\n\nInternational and dynamic working environment\nRewarding and stimulating job tasks\nExposure to APAC regional business\nMedical benefits\nCompetitive packages\n\nTo apply online please click the 'Apply' button below. For a confidential discussion about this role please contact Esther Liu on +852 2258 3537", "employment_types": ["Full Time", "Permanent"], "selling_points": ["Dynamic working environment", "Competitive package and generous benefits", "Work life balance"], "locations": ["Not Specified"], "categories": ["Banking / Finance", "Corporate Banking", "Credit Analysis / Approval", "Order Processing & Operation / Settlement"], "post_time": "2022-01-11T13:07:29Z", "salary": {"currency": null, "max": null, "min": null, "period": "monthly", "term": null}, "salary_visible": false, "title_keywords": ["senior officer", "admin"], "responsibilities": ["data", "quality", "design", "communication", "business process", "designing", "administration", "control", "compliance", "teams", "developing", "banking", "reporting", "management", "monitoring", "risk monitoring", "provide guidance", "communicate with", "system security"], "requirements": {"degrees": ["degree", "bachelor"], "majors": ["risk management", "business administration"], "languages": ["english"], "language_level": ["excellent"], "hard_skills": ["excel", "data management", "analytical skills", "dynamic", "vlookup"], "soft_skills": ["communication skills", "independent", "responsible", "analytical skills", "dynamic", "interpersonal skills"], "languages_combined": [{"language": "english", "language_level": ["excellent"]}]}, "experience_required": {"duration": ["at least 5 years"], "field": ["risk management", "management", "legal", "compliance", "it", "business", "security", "investment", "banking", "market risk", "credit risk", "financial"]}}, {"job_id": "100003009050670", "location_code": "hk", "company": "China Construction Bank (Asia) Corporation Limited", "job_title": "Manager, Credit Risk Quantitative Modeling", "description": "\u00a0\n\n\u201cWe\u201d are the largest Belgian bank with Asian activities in Singapore, Shanghai and Hong Kong.\u00a0 Each and every day our team in Asia strives to become the Preferred European Banking Partner of our domestic and European customers. To do so, we combine high professional standards and a pleasant working environment and we put our customers in the center point in everything we do. Also our internal customers!\n\nWe are looking for an enthusiastic and self-motivating talent to join our team as the Junior Officer of Remittance and Settlement Team. You can have the exposure in full remittance and settlement process in the international banking.\n\n\u00a0About the job\n\nAs the Junior Officer of Remittance and Settlement team, you process inward and outward remittance;\nYou handle and respond to inquiries / requests from inter-department, customers, on transaction processing and related matters;\nYou perform customer FX transactions, as well as participating in AML screening on incoming & outgoing swift payments;\nYou manage the daily operations through SWIFT/ RTGS system;\nYou manage the general administrative duties of your team and assist in ad hoc duties as assigned by superiors.\n\nAbout you\n\nTo join the KBC team, you need to be a good team player, with ability to communicate clearly and concisely. You are with good command of spoken and written English, Chinese & Mandarin, as well as great self-motivation and self-starting ability. You need to be familiar AML screening and SWIFT/ RTGS system. You should also attain tertiary qualification and have minimum 3 years\u2019 relevant experience. Finally, need to be eager to learn and continuously develop yourself to remain future proof in a swiftly changing environment. If you are having less experience, we may also considered you as Senior Clerk.\n\nWe offer an attractive remuneration package in line with your relevant experience and the importance of the position.\u00a0\u00a0\n\nIf you feel like this position is a fit with your skill-set and expectations, please apply with a cover letter and CV (indicating your salary expectation) by email via \"Apply Now\". For any questions with regards to the position you can give us a call on\u00a0 (852) 2879 3363.\n\n\nAll information received will be used for recruitment purpose only. Applicants not being invited to interview within 6 weeks may consider their applications unsuccessful. All information on unsuccessful candidates will be deleted from our files within 12 months.", "employment_types": ["Full Time", "Permanent"], "selling_points": ["Oversee credit risk model development", "Ongoing credit risk model validation & governance", "Degree & 3 years exp in credit risk / risk mgt"], "locations": ["Kowloon Bay"], "categories": ["Banking / Finance", "Analyst", "Corporate Banking", "Risk Management"], "post_time": "2022-01-14T11:09:20Z", "salary": {"currency": null, "max": null, "min": null, "period": "monthly", "term": null}, "salary_visible": false, "title_keywords": ["manager"], "responsibilities": ["ad hoc duties", "settlement process", "banking", "transactions", "develop", "daily operations", "payments", "aml screening", "administrative duties", "transaction processing"], "requirements": {"degrees": [], "majors": [], "languages": ["english", "chinese", "mandarin"], "language_level": ["good command"], "hard_skills": ["swift", "processing", "aml screening"], "soft_skills": ["outgoing", "good team player", "pleasant", "eager to learn", "self-motivation", "enthusiastic"], "languages_combined": [{"language": "english", "language_level": ["good command"]}, {"language": "chinese", "language_level": ["good command"]}, {"language": "mandarin", "language_level": ["good command"]}]}, "experience_required": {"duration": ["minimum 3 years"], "field": ["relevant experience"]}}, {"job_id": "100003009045021", "location_code": "hk", "company": "Odin Partners Asia Limited", "job_title": "Corporate Sales", "description": "Responsibilities:\nBe responsible for the development, implementation, monitoring and enhancement of credit risk rating models and systems\nPrepare MI reports relating to credit risk analytics\nProvide support to model governance, model validation, internal and external audit\nWork closely with regulators and internal stakeholders on credit risk model development and other data management exercise to ensure compliance of regulatory requirements\nSupport the Banks development, enhancement and implementation of IRB models\nAssist in performing system enhancement UAT\nObtain a high-level understanding on the internal rating-based approach requirements from various regulatory bodies, such as CBIRC and HKMA\nRequirements:\nBachelor degree in Business Administration or other related disciplines\nAdvanced degree/ FRM / CFA qualification is an advantage\nMinimum 3 years\u2019 relevant experience in credit risk management or related risk management field\nStrong programming skill (SAS / VBA) is an advantage\nStrong communication and writing skills in Chinese and English,\u00a0excellent command of Mandarin is an advantage\nApplicants who are not contacted within 8 weeks may consider their applications unsuccessful and their personal data will be retained by the bank for a period up to two years.\n\nAll information provided by applicants will be used for recruitment purposes only and will be used strictly in accordance with the bank's personal data policies, a copy of which will be provided upon request.\u00a0", "employment_types": ["Full Time"], "selling_points": [], "locations": ["Central & Western Area"], "categories": ["Banking / Finance", "Corporate Banking"], "post_time": "2022-01-13T06:55:13Z", "salary": {"currency": null, "max": null, "min": null, "period": "monthly", "term": null}, "salary_visible": false, "title_keywords": ["sales"], "responsibilities": ["provide support", "management", "uat", "data", "monitoring", "systems", "implementation", "audit", "compliance of regulatory", "reports"], "requirements": {"degrees": ["degree", "bachelor"], "majors": ["related disciplines", "business administration"], "languages": ["english", "chinese", "mandarin"], "language_level": ["advantage", "excellent"], "hard_skills": ["vba", "sas", "cfa", "writing skills", "programming", "frm"], "soft_skills": ["communication", "advanced", "writing skills"], "languages_combined": [{"language": "english", "language_level": ["advantage", "excellent"]}, {"language": "chinese", "language_level": ["advantage", "excellent"]}, {"language": "mandarin", "language_level": ["advantage", "excellent"]}]}, "experience_required": {"duration": ["minimum 3 years"], "field": ["risk management", "management", "related", "relevant experience", "credit risk"]}}, {"job_id": "100003009044183", "location_code": "hk", "company": "JAC Recruitment Hong Kong Co., Limited", "job_title": "Japanese speaking Business Planning-Analyst", "description": "Position:\u00a0Corporate Sales\u00a0\n\nLocation:\u00a0Hong Kong\u00a0\n\nDuration:\u00a0Permanent, Full-Time\n\nSalary:\u00a0Negotiable\n\nCompany Background\n\nWorld renowned Global Markets Sell Side firm with operations across the globe. The business has a very substantial customer base and has achieved high growth by capitalizing on the globalization and innovation opportunities in APAC.\u00a0\n\nPosition Summary\n\nThe business is looking for Corporate Sales (Director level) to spearhead the cross-asset Corporate Sales business, working closely with the Head of all Sales and Head of Fixed Income.\u00a0\n\n\u00a0It is essential that the candidate has:\n\nMore than 10 years of experience in Corporate Sales, Global Markets\u00a0\nExperience in flow sales\u00a0\nExperience with Chinese/HK/MNC corporates", "employment_types": ["Full Time"], "selling_points": ["Good command in English,Mandarin,Japanese", "Good benefits, 20days AL", "Location: Central"], "locations": ["Central"], "categories": ["Banking / Finance", "Corporate Banking"], "post_time": "2022-01-13T03:19:34Z", "salary": {"currency": null, "max": null, "min": null, "period": "monthly", "term": null}, "salary_visible": false, "title_keywords": ["analyst"], "responsibilities": ["operations"], "requirements": {"degrees": [], "majors": [], "languages": ["chinese"], "language_level": [], "hard_skills": [], "soft_skills": [], "languages_combined": [{"language": "chinese", "language_level": []}]}, "experience_required": {"duration": ["10 years"], "field": ["corporate sales"]}}, {"job_id": "100003009036751", "location_code": "hk", "company": "Industrial and Commercial Bank of China (Asia) Limited", "job_title": "Senior Relationship Manager, Non-Bank Business", "description": "OverviewOur client, a prestigious Japanese bank, is looking for a\u00a0Analyst (Business Planning) - Global Markets Division for Asia\n\nCompany Location:Central\n\nWorking Days:Mon-Fri (9:00 am ~5:30pm)\n\nCompany Business:Japanese Bank\n\nLanguages Required:Cantonese, English, Mandarin, Japanese\n\nJOB DUTIES\n\nResponsible for coordinating and managing the day-to-day running of Global Markets business area, which may include budgeting, forecasting and review of internal control process.\nSupport the Planning Head on the development of business strategies, business promotion planning, operational efficiency improvement and implementation of regional projects for Global Markets Division for Asia;\nPartner with key stakeholders with overseas branches and Head Office to support in developing Global Markets business strategies;\nEnsure full compliance with the prevailing regulations showing examples of ethical behaviour and following all internal controls for the Team;\nSupport in developing and updating policies to ensure alignment with all relevant regulations;\n\nREQUIREMENTS\n\nUniversity graduate\nWith 1 to 3 years\u2019 relevant experience in banking or financial institutions is preferable\nGood command of written and spoken Japanese and English\n\nPACKAGE\n\nDiscretionary bonus\nMedical insurance\nBirthday leave\nWork from Home Policy\nExamination Leave\nVolunteer Leave\nPaid Sick Leave\nFlexible working Hour\nBonus\n\n1) Expected salary\n2) Current and last drawn salaries\n3) Reason for leaving current and past employments\n\u00a0\ndirectly to:\u00a0jac.hk\u00a0@jac-recruitment.com and CC to:\u00a0daniel.ng\u00a0@jac-recruitment.com\n\n\u00a0\nPersonal data collected will be used for employment-related purpose only. We regret to inform that only shortlisted candidates will be notified, thank you", "employment_types": ["Full Time", "Permanent"], "selling_points": [], "locations": ["Central & Western Area"], "categories": ["Banking / Finance", "Corporate Banking", "Credit Analysis / Approval", "Corporate Finance"], "post_time": "2022-01-10T13:34:07Z", "salary": {"currency": null, "max": null, "min": null, "period": null, "term": null}, "salary_visible": false, "title_keywords": ["senior relationship manager"], "responsibilities": ["regulations", "budgeting", "policies", "review", "compliance", "implementation", "developing", "forecasting", "internal control", "planning"], "requirements": {"degrees": ["university graduate"], "majors": [], "languages": ["japanese", "english"], "language_level": ["good command"], "hard_skills": ["inform", "reason"], "soft_skills": ["flexible"], "languages_combined": [{"language": "japanese", "language_level": ["good command"]}, {"language": "english", "language_level": ["good command"]}]}, "experience_required": {"duration": ["1 to 3 years"], "field": ["financial institutions", "relevant experience", "banking"]}}, {"job_id": "100003009045901", "location_code": "hk", "company": "Robert Half", "job_title": "AVP/VP - Asset & Liability Management/ALCO", "description": "Job Responsibilities\n\nResponsible for promoting and marketing banking products\nEnlarge business scope via cross-selling banking products\nMaintain close relationship and have good customer services to clients\nComply with all internal procedures and all external regulations\nIdentify and report any policy breaches to supervisors\nJob Requirements\n\nBachelor Degree Holder, in Finance, Accounting, Economics, Commerce and Marketing disciplines.\nRelevant Individuals of RA Type 1 and 4.\nAt least 5 years\u2019 experience in Banking / Securities Firms / Asset Management Firms. Experience in handling sales and marketing to Non-bank Fis is preferable\nGood relationship management skills\nFamiliar with Banking products and market\nGood team spirit and cooperative\nOpen minded, patient and able to work under pressure\nExcellent in written and spoken English and Chinese, including Putonghua", "employment_types": ["Full Time", "Permanent"], "selling_points": ["A leading retail banking and corporate banking", "Fringe benefit with decent bonus", "Good exposure with career progression"], "locations": ["Central & Western Area"], "categories": ["Banking / Finance", "Corporate Banking", "Private Banking", "Retail Banking"], "post_time": "2022-01-13T09:03:52Z", "salary": {"currency": null, "max": null, "min": null, "period": "monthly", "term": null}, "salary_visible": false, "title_keywords": [], "responsibilities": ["regulations", "procedures", "customer services", "maintain", "banking", "report"], "requirements": {"degrees": ["bachelor degree holder"], "majors": ["finance", "accounting", "economics", "marketing"], "languages": ["putonghua", "english", "chinese"], "language_level": ["excellent"], "hard_skills": ["ra type"], "soft_skills": ["team spirit", "cooperative", "open minded", "patient", "work under pressure"], "languages_combined": [{"language": "putonghua", "language_level": ["excellent"]}, {"language": "english", "language_level": ["excellent"]}, {"language": "chinese", "language_level": ["excellent"]}]}, "experience_required": {"duration": ["at least 5 years"], "field": ["asset management", "marketing", "securities firms", "banking"]}}, {"job_id": "100003009042425", "location_code": "hk", "company": "PERSOLKELLY Hong Kong Limited", "job_title": "Banking Operations Team Lead (up to 60k p/m + bonus + benefits)", "description": "Snapshot\n\nAn exciting opportunity to join a sizeable foreign bank as an Operations Team Lead, to be responsible for process monitoring of banking operations.\n\nCompany Profile\n\nOur client, a sizeable foreign bank is looking for an Operations Team Lead to join the team\n\nExciting new role for you\n\nResponsible for monitoring and managing daily banking operation flows\nIdentity and minimize relevant operational risk in product, processing and transaction\nSpearhead risk and compliance related projects\n\nRequirements\n\nDegree holder in Accounting, Finance, Risk Management or related discipline\nAt least 10 years of experience in banking operations\nExperience in team management is required\nGood command of English and Chinese\nSolid reporting skills by using MS Excel and PowerPoint\n\nRewards\n\nInternational platform with stable career growth and attractive renumeration package", "employment_types": ["Full Time", "Permanent"], "selling_points": ["Foreign Banking Operations Team Lead", "Well versed in banking operations and compliance", "Stable career growth, up to 60k p/m"], "locations": ["Yau Tsim Mong Area"], "categories": ["Banking / Finance", "Corporate Banking", "Order Processing & Operation / Settlement", "Risk Management"], "post_time": "2022-01-12T07:28:25Z", "salary": {"currency": null, "max": null, "min": null, "period": "monthly", "term": null}, "salary_visible": false, "title_keywords": ["operations", "lead"], "responsibilities": ["reporting", "management", "operations", "monitoring", "compliance", "banking"], "requirements": {"degrees": ["degree holder"], "majors": ["finance", "accounting", "risk management"], "languages": ["english", "chinese"], "language_level": ["good command"], "hard_skills": ["ms excel", "processing", "powerpoint"], "soft_skills": ["stable", "responsible"], "languages_combined": [{"language": "english", "language_level": ["good command"]}, {"language": "chinese", "language_level": ["good command"]}]}, "experience_required": {"duration": ["at least 10 years"], "field": ["management", "team", "banking"]}}, {"job_id": "100003009036816", "location_code": "hk", "company": "Ignite Recruitment Hong Kong Limited", "job_title": "Assistant Manager, Trade Finance Operation-Regional Corporate & Investment Bank(Work life balance)", "description": "Career Level\nMiddle\nQualification\nDegree\nYears of Experience\n3 years\nJob Type\nFull Time, Permanent\nJob Functions\nBanking / Finance, Analyst, Corporate Banking, Credit Analysis / Approval", "employment_types": ["Full Time", "Permanent"], "selling_points": ["Stable Bank with Excellent Work-Life Balance", "Strong Financial Performance with Decent Bonus", "Prestigious Location & Friendly Working Culture"], "locations": ["Central & Western Area"], "categories": ["Banking / Finance", "Corporate Banking", "Financial Services", "Order Processing & Operation / Settlement"], "post_time": "2022-01-10T15:19:30Z", "salary": {"currency": "HKD", "max": 34999, "min": 25000, "period": "monthly", "term": null}, "salary_visible": true, "title_keywords": ["assistant manager,"], "responsibilities": ["analysis", "banking"], "requirements": {"degrees": ["degree"], "majors": [], "languages": [], "language_level": [], "hard_skills": ["credit analysis"], "soft_skills": [], "languages_combined": []}, "experience_required": {"duration": [], "field": []}}, {"job_id": "100003009038537", "location_code": "hk", "company": "Asia Pacific Data Technology Limited", "job_title": "Assistant Manager, Payments", "description": "Our client is a stable and well-established regional corporate & investment bank in Hong Kong. They are currently looking for an Assistant Manager, Trade Finance to join their Trade Finance Operation\u00a0Team.\n\nResponsibilities\n\n\n\nProcess all Trade Finance Applications and Documents\u00a0including Import LC Opening, Import Document checking and payment, Import Collection Bills handling, Trust Receipt loan granting and retirement, Export LC Advising, Export LC Transfer, Export LC Bills checking and negotiation, Export LC collection bills handling, Export DA DP Bills handling, LC Reimbursement Authorization and Claims, LC Refinancing and Forfaiting.\nProcess Remittance Applications & Payments, LC Reimbursement Authorization & Claims and\u00a0 Revolving Loan Application & Retirement\nWork as a team to enter transaction details and pass G/L entries into system\nPrepare all outgoing LC & Payment SWIFT messages\nCollaborate closely with front line staff on handling customer enquiries & customers transaction approvals\nAssist on handling corporate client account opening & time deposits\nPerform loan administration duties\nRequirements\n\nHKCEE/DSE passed\n4 years + working experience in Commercial/ Corporate Banking Trade Finance\nGood knowledge in UCP600, ISBP, URC522, URR725 would be an advantage\nSolid experience in preparing MT700, MT202 & MT103\u00a0would be preferable\nGood in both written and spoken English\u00a0& Chinese\nCandidate with less experience would be consider for senior officer title\u00a0\n\nTo apply online please click the 'Apply' button.\u00a0For a confidential discussion about this role & other openings please contact Alex CHEUNG at +852 2121 1418 .", "employment_types": ["Full Time", "Permanent"], "selling_points": [], "locations": ["Tsim Sha Tsui"], "categories": ["Banking / Finance", "Corporate Banking", "Loan", "Order Processing & Operation / Settlement"], "post_time": "2022-01-11T07:17:30Z", "salary": {"currency": "HKD", "max": 34999, "min": 30000, "period": "monthly", "term": null}, "salary_visible": true, "title_keywords": ["assistant manager,"], "responsibilities": ["collaborate", "account opening", "checking", "handling customer enquiries", "payment", "payments", "administration"], "requirements": {"degrees": ["dse"], "majors": [], "languages": ["english", "chinese"], "language_level": ["good"], "hard_skills": [], "soft_skills": [], "languages_combined": [{"language": "english", "language_level": ["good"]}, {"language": "chinese", "language_level": ["good"]}]}, "experience_required": {"duration": ["4 years +"], "field": ["finance", "commercial", "banking"]}}, {"job_id": "100003009022461", "location_code": "hk", "company": "Asia Progress Executive Limited", "job_title": "Senior Remittance Officer \u2013 Corporate Banking /Banking", "description": "What shall this Job responsible for?\n\nHandle payment operations and remittance as well as loan administration\nPerform daily reconciliation\nPrepare internal and external management reports\nEnsure operational processes are in full compliance with internal policies and regulatory requirements if any\nSupport systems implementation by participating in user acceptance tests\nPerform other ad hoc duties as assigned\n\n\u00a0\u00a0Who can perform this Job?\n\nHigh diploma or above education\nAt least 5 years solid experience in commercial payments/ remittance processes or loan administration\nSound knowledge on commercial products\nGood command of English and Chinese", "employment_types": ["Full Time"], "selling_points": ["Post-Sec,6 yrs in Remittance Corporate Banking", "Trade Transaction;cross border Renminbi settlement", "Conduct customer contact and handle customer enqui"], "locations": ["Central & Western Area"], "categories": ["Banking / Finance", "Corporate Banking", "Retail Banking", "Order Processing & Operation / Settlement"], "post_time": "2022-01-10T05:02:37Z", "salary": {"currency": null, "max": null, "min": null, "period": "monthly", "term": null}, "salary_visible": false, "title_keywords": ["officer"], "responsibilities": ["ad hoc duties", "operations", "policies", "compliance", "regulatory requirements", "systems", "implementation", "payment", "management reports", "payments", "administration"], "requirements": {"degrees": ["high diploma or above"], "majors": [], "languages": ["english", "chinese"], "language_level": ["good command"], "hard_skills": ["management reports"], "soft_skills": ["responsible"], "languages_combined": [{"language": "english", "language_level": ["good command"]}, {"language": "chinese", "language_level": ["good command"]}]}, "experience_required": {"duration": ["at least 5 years"], "field": ["commercial", "administration"]}}, {"job_id": "100003009049282", "location_code": "hk", "company": "Bangkok Bank Public Co Ltd", "job_title": "Head of Audit (Ref: AU-08/176/240-DB)", "description": "One of our clients (an overseas bank) is now looking for high calibre candidates to fill the following positions:\nExperience in corporate banking/ finance is preferred;\nMain job duty is to handle Japanese or Korean corporate clients;\nAble to achieve annual sales target;\nGood communication skills, aggressive and able to build up good relationship with new clients;\nNative in either Japanese or Korean speaking is a must;\nWork visa can be arranged for right candidates.\n\nRemarks:\n\nMonthly salary:\u00a0Attractive salary will be offered to right candidate + discretionary bonus;\n5-day work;\nWorking location: Kowloon;\nCompany background: A well-known overseas bank;\nGood fringe benefits e.g. 22-day annual leave, medical, dental (including spouse), bank holiday, etc\n\nIf the above position is not suitable for you, please also feel free to send your CV to us for our job matching.\n\nInterested parties please click \"APPLY NOW\"\u00a0or send to\u00a0OUR EMAIL\u00a0and attach your updated resume with expected salary in \"MS WORD\" format.\n\nPlease quote the\u00a0Job Ref. No.\u00a0and\u00a0Applied Post\u00a0on the subject of your application.\n\nInterest to know our candidates' and clients' comments about our service? Please click\u00a0HERE.\n\n\nCompany website: www.kek.com.hk\n\nThe information provided will only be used for recruitment related purposes.", "employment_types": ["Full Time"], "selling_points": [], "locations": ["Central"], "categories": ["Accounting", "Audit", "Banking / Finance", "Corporate Banking", "Others"], "post_time": "2022-01-14T08:23:30Z", "salary": {"currency": null, "max": null, "min": null, "period": "monthly", "term": null}, "salary_visible": false, "title_keywords": [], "responsibilities": ["communication", "sales target", "good relationship", "banking"], "requirements": {"degrees": [], "majors": [], "languages": ["japanese", "korean"], "language_level": ["native"], "hard_skills": [], "soft_skills": ["communication skills"], "languages_combined": [{"language": "japanese", "language_level": ["native"]}, {"language": "korean", "language_level": ["native"]}]}, "experience_required": {"duration": [], "field": ["finance", "banking"]}}, {"job_id": "100003009038942", "location_code": "hk", "company": "Asia Progress Executive Limited", "job_title": "Manager/Team Lead - Credit Documentation/Loan Documentation (Corporate Banking/Retail Banking )", "description": "Responsibilities:\n\nPerform daily inward and outward remittance transaction\nHandle cheque clearing, FPS and fixed deposit\nCommunicate with in-house department i.e. RM or Finance dept.\nHandle investigate cases for remittance\nPerform Drill test for HKICL\n\nRequirements:\n\nTertiary education or above\nAt least 1 year banking experience\nKnowledge on SWIFT/RTGS payment system\nProficient in both spoken and written English and Chinese including Putonghua\nGood PC knowledge including MS Word, Excel and Chinese word processing\nStrong team player\nCandidates with less experience will be considered as Assistant Officer\n\nApply Method\n\nInterested parties, please send full resume (both in English and Chinese) with current and expected salary and the date of availability\u00a0via \"Apply Now\". Please quote your name and the job position in your application.\u00a0\n\nInformation provided will be treated in strict confidence and only be used for recruitment purpose.\u00a0\n\nWelcome to learn more about China Minsheng Bank at\u00a0www.cmbc.com.cn", "employment_types": ["Full Time"], "selling_points": ["Credit Doc&Loan Doc,Syndication & Bilateral loan", "draft standard & non-standard credit & collateral", "Corporate Banking & Retail banking exp"], "locations": ["Central & Western Area"], "categories": ["Banking / Finance", "Corporate Banking", "Loan", "Order Processing & Operation / Settlement"], "post_time": "2022-01-11T08:10:32Z", "salary": {"currency": null, "max": null, "min": null, "period": "monthly", "term": null}, "salary_visible": false, "title_keywords": ["manager", "lead"], "responsibilities": ["communicate with", "fixed deposit"], "requirements": {"degrees": [], "majors": [], "languages": ["putonghua", "english", "chinese"], "language_level": ["good", "proficient"], "hard_skills": ["excel", "chinese word processing", "swift", "pc knowledge", "ms word"], "soft_skills": ["team player"], "languages_combined": [{"language": "putonghua", "language_level": []}, {"language": "english", "language_level": ["proficient"]}, {"language": "chinese", "language_level": ["proficient", "good"]}]}, "experience_required": {"duration": ["at least 1 year"], "field": ["banking experience"]}}, {"job_id": "100003009046327", "location_code": "hk", "company": "Randstad Hong Kong Limited", "job_title": "Market Risk Manager, Corporate and Investment Bank", "description": "Job Purpose\n\nHandle debt recovery and minimize impairment loss for the designated accounts.\n\nResponsibilities\n\nAssist to formulate and perform daily execution of collection strategies.\nHandle debt recovery for the designated accounts through cash/ assets recovery, debt restructuring and security enforcement.\nSustain positive working relationship with key internal customers to enhance recoverability of problem loans.\nMaximize debt recovery for the designated accounts including cash/ assets recovery, debt restructuring, security enforcement, obtaining additional securities etc.\nLiaise with solicitors and collection agents on problem loans management.\nSupervise and execute the repossession and sale of collaterals.\nAchieve annual business targets, for instances, provision balance, impairment loss ratio, bad debt recoveries etc.\u00a0\u00a0\nSupport bank-wide new business initiatives by providing timely advice from risk management perspective.\nMonitor the output quality from team members to ensure their compliance with the regulatory requirements and provide timely coaching to team members.\n\nRequirements\n\nSecondary education or above. Bachelor degree holder in business or risk management is a plus.\nMinimum 10 years\u2019 relevant experience in bank, credit or related field in which 3 years\u2019 experience at supervisory level is highly preferred.\nProfessional Qualification of Certified Credit Risk Management Professional (Credit Portfolio Management) is preferred.\nKnowledge of litigation process in HKSAR and PRC with focus on collaterals repossession.\nGood knowledge of regulatory requirements such as relevant ordinances and supervisory guidelines and in-depth knowledge on banking and investment products.\nSolid experience in Corporate Banking collection is preferable.\nStrong analytical and credit assessment skills with excellent understanding of lending principles.\nSelf-motivated, independent and able to communicate effectively at all levels.\nGood command of written and spoken English and Chinese including Putonghua.", "employment_types": ["Full Time", "Permanent"], "selling_points": ["Well-established Corporate Bank", "Bank-wide coverage", "Sizeable team"], "locations": ["Not Specified"], "categories": ["Banking / Finance", "Corporate Banking", "Financial Services", "Risk Management"], "post_time": "2022-01-13T10:30:59Z", "salary": {"currency": "HKD", "max": 54999, "min": 30000, "period": "monthly", "term": null}, "salary_visible": true, "title_keywords": ["manager"], "responsibilities": ["management", "business initiatives", "regulatory requirements", "compliance", "quality", "monitor", "liaise with"], "requirements": {"degrees": ["secondary education", "bachelor degree holder"], "majors": ["risk management", "business"], "languages": ["putonghua", "english", "chinese"], "language_level": ["good command"], "hard_skills": ["litigation process", "plus", "focus", "investment products"], "soft_skills": ["focus", "independent", "self-motivated"], "languages_combined": [{"language": "putonghua", "language_level": ["good command"]}, {"language": "english", "language_level": ["good command"]}, {"language": "chinese", "language_level": ["good command"]}]}, "experience_required": {"duration": ["3 years", "minimum 10 years"], "field": ["related", "supervisory level", "relevant experience", "banking"]}}, {"job_id": "100003009038998", "location_code": "hk", "company": "O-Bank Co., Ltd", "job_title": "Compliance Deputy Manager", "description": "We are now seeking a high caliber candidate to join our Hong Kong Branch.\n\nResponsibilities:\n\nReport directly to Head Office Audit and manage the audit function\nDevelop annual risk-based audit plan\nDesign audit programs for operational, financial, IT-related, compliance audits and regulatory assessments\nCoach and supervise audit staff in completing audit assignments\nFollow up with auditees on the rectification completion progress\nProvide consultancy to departments and management\u00a0\nLiaise with regulatory bodies, Head Office auditors and external auditors\nPerform special reviews, investigation and ad hoc assignments requested by local and Head Office management\nRequirements:\n\nDegree in Accounting/Finance/Business or equivalent\nMember of CPA and/or CIA\nMinimum 8\u00a0years' solid internal audit experience from banking industry\nExcellent command of written and spoken English and Chinese\nWe offer excellent career prospects to the right candidate. Salary will be commensurate with qualifications and experience. Interested parties please apply with\u00a0full resume, stating current / expected salary and availability to The Human Resources Manager, Bangkok Bank Public Co. Ltd., Bangkok Bank Building, 28 Des Voeux Road Central, Hong Kong.\nPersonal data provided by job applicants will be used solely for considering suitability for the post and strictly in accordance with our personal data policies which are available on request.\n(Only shortlisted candidates will be contacted.)", "employment_types": ["Full Time", "Permanent"], "selling_points": [], "locations": ["Tsim Sha Tsui"], "categories": ["Banking / Finance", "Corporate Banking", "Professional Services", "Legal & Compliance"], "post_time": "2022-01-11T16:01:47Z", "salary": {"currency": null, "max": null, "min": null, "period": "monthly", "term": null}, "salary_visible": false, "title_keywords": ["deputy manager"], "responsibilities": ["management", "compliance", "rectification", "audit", "design", "develop", "external auditors", "liaise with", "investigation", "ad hoc assignments", "plan", "audits", "report"], "requirements": {"degrees": ["degree"], "majors": ["business", "finance", "accounting"], "languages": ["english", "chinese"], "language_level": ["excellent"], "hard_skills": ["cpa"], "soft_skills": [], "languages_combined": [{"language": "english", "language_level": ["excellent"]}, {"language": "chinese", "language_level": ["excellent"]}]}, "experience_required": {"duration": ["minimum 8 years"], "field": ["banking industry", "audit experience"]}}, {"job_id": "100003009051070", "location_code": "hk", "company": "IT Solutions Ltd.", "job_title": "IT Business Analyst / Senior Business Analyst (Life Insurance) - Major Bank", "description": "Our client a well-known PRC bank in Hong Kong is looking for a high caliber to join the group\nfor Corporate Banking business.\u00a0\n\nManager/Team Lead \u2013 Credit Documentation/Loan Documentation\u00a0(Corporate Banking/ Retail Banking )\u00a0\n\nResponsibilities\u00a0\n\n\u00a0To review and draft both standard and non-standard credit and collateral documentation\nTo\u00a0support the the Loan Document Operations to achieve the agreed objectives on the balanced scorecard for the division\nTo perform regular monitoring and tracking on the quality of the deliverable and produce monthly report for senior management review\nTo participate in system enhancement project\u00a0\n\nRequirements\n\nDegree holder\u00a0or related disciplines\nAround 5-10 years of Corporate banking experience in credit documentation and loan documentation operations\u00a0\nBroad knowledge and experience in monitoring end to end process from loan documentation Syndication loan Bilateral loan limit dispatch and credit documentation for corporate loan facilities and have solid experience in project management\nGood command of spoken and written English & Chinese\n\nPlease send full resume with\u00a0present & expected\u00a0salary to expedite sourcing\u00a0in\u00a0MS-WORD\u00a0format by clicking \u201cAPPLY NOW\u201d\n\nPlease quote our reference in your application\n\nPersonal data provided by job applicants will be used strictly in accordance with the employer\u2019s personal data policies, a copy of which will be provided upon request\n\nAll information provided will be used for recruitment purpose only", "employment_types": ["Full Time"], "selling_points": ["Business Analysis + Project Management", "Various Insurance System Project Exposure", "Good Career Prospect in Major Bank"], "locations": ["Tai Koo"], "categories": ["Banking / Finance", "Corporate Banking", "Information Technology (IT)", "IT Project Management / Team Lead", "Product Management / Business Analyst"], "post_time": "2022-01-15T01:44:49Z", "salary": {"currency": "HKD", "max": 54999, "min": 20000, "period": "monthly", "term": null}, "salary_visible": true, "title_keywords": ["senior business analyst", "business analyst"], "responsibilities": ["operations", "monitoring", "review", "quality", "monthly report", "documentation", "senior management", "tracking"], "requirements": {"degrees": ["degree holder"], "majors": ["related disciplines"], "languages": ["english", "chinese"], "language_level": ["good command"], "hard_skills": ["documentation", "project management", "ms-word"], "soft_skills": ["project management"], "languages_combined": [{"language": "english", "language_level": ["good command"]}, {"language": "chinese", "language_level": ["good command"]}]}, "experience_required": {"duration": ["5-10 years"], "field": ["project management", "banking experience"]}}, {"job_id": "100003009042130", "location_code": "hk", "company": "China Construction Bank (Asia) Corporation Limited", "job_title": "AVP/VP, Internal Control, Commercial Banking (Ref no: AVPIC/CMB/JDB)", "description": "about the company\n\n\n\n\n\nOur client is a well-established corporate bank.\n\nabout the team\n\n\nThe team is hands-on and expanding.\n\nabout the job\n\n\nYou will be:\n\n\nDesigning, developing and performing market risk management and monitoring\nIdentify, monitor, manage, and control the market risk of business and products\nMonitor key risk measures (e.g. Greeks and PV01) and risk metrics (e.g. VaR, ES and Stress Test) against limits mandates\nProvide analysis and commentaries on the key drivers affecting risk metrics / stress testing results\n\nabout the requirements\n\n\n\n\nBachelor's degree holder in risk management, finance, accounting, or business discipline\n3+ years of experience in market risk, product control or valuation in corporate banks\nFamiliar with financial products of fixed income, FX, and other related derivatives\nGood command in both Chinese and English languages\nTo apply online, please click on the link. Alternatively, for a confidential discussion please contact Cheryl Tsang on + 852 2232 3470 or email: cheryl.tsang@randstad.com.hk", "employment_types": ["Full Time", "Permanent"], "selling_points": ["Perform quality assurance on I&I products", "Monitoring KYC reassessment task", "Diploma with min. 5 yrs of experience"], "locations": ["Kowloon Bay"], "categories": ["Accounting", "Audit", "Banking / Finance", "Corporate Banking", "Professional Services", "Legal & Compliance"], "post_time": "2022-01-12T06:19:34Z", "salary": {"currency": null, "max": null, "min": null, "period": "monthly", "term": null}, "salary_visible": false, "title_keywords": [], "responsibilities": ["management", "control", "analysis", "monitoring", "monitor", "developing", "testing", "designing"], "requirements": {"degrees": ["bachelor", "degree holder"], "majors": ["finance", "risk management", "accounting", "business"], "languages": ["english", "chinese"], "language_level": ["good command"], "hard_skills": [], "soft_skills": [], "languages_combined": [{"language": "english", "language_level": ["good command"]}, {"language": "chinese", "language_level": ["good command"]}]}, "experience_required": {"duration": ["3+ years"], "field": ["market risk"]}}, {"job_id": "100003009038280", "location_code": "hk", "company": "DBS Bank Ltd", "job_title": "Associate/Senior Associate, Business Process Engineer, Transaction Banking", "description": "Business Function\nGlobal Transaction Services (GTS) comprises of Cash & Trade, Securities Services and Fiduciary Services. In an increasingly borderless world marked by burgeoning trade flow, expertise in trade finance services is an invaluable asset. With cash the lifeblood of every company, so too, is a good understanding of how to manage these cashflows. Trade Finance, together with Cash Management, is the mainstay of GTS, and is extended to SME and corporate clients for their local and cross-border financial transaction needs.\n\nThis role focuses on the End-to-End process analysis and improvement in different areas, in order to increase both employee and customers\u2019 satisfaction.\n\nResponsibilities\n\nUnderstand and map out processes end to end, including client touch points, product handling, Operation processing.\nConduct deep dive process data analysis, insight generations and improvements proposals.\nPropose continuous process improvement ideas, eliminate \u201cwaste\u201d, increase end-to-end efficiency.\nDeliver and implement improvement projects.\nFacilitate strategic transformation agenda.\nContinuously build capability in the Process Engineering Practice.\n\nRequirements\n\nBachelor\u2019s degree in areas of Industrial Engineering, Information System Engineering, Operational Management, or related majors preferred.\nAt least 4+ years'\u00a0process improvement related working experience required.\nData analysis, Business requirement analysis experience required.\nExperience in workshop/ hackathon facilitation preferred.\nSix-sigma black belt, Agile Scrum Master, Design Thinking certification preferred.\nStrong communication skills, strong data analytics mindset\nOpen minded, team-oriented, high efficiency, multi-tasking\n\nApply Now\n\nWe offer a competitive salary and benefits package and the professional advantages of a dynamic environment that supports your development and recognises your achievements.\n\nWe regret only shortlisted candidates will be notified.", "employment_types": ["Full Time"], "selling_points": ["See job description.", "See job description.", "See job description."], "locations": ["Central"], "categories": ["Banking / Finance", "Corporate Banking", "Professional Services", "Business Analysis / Data Analysis"], "post_time": "2022-01-11T06:25:45Z", "salary": {"currency": null, "max": null, "min": null, "period": "monthly", "term": null}, "salary_visible": false, "title_keywords": ["senior associate", "associate", "process engineer"], "responsibilities": ["data analysis", "ideas"], "requirements": {"degrees": ["degree", "bachelor", "master"], "majors": ["system engineering", "engineering", "design"], "languages": [], "language_level": [], "hard_skills": ["agile", "data analytics", "analysis", "information system", "dynamic"], "soft_skills": ["communication skills", "dynamic environment", "agile", "multi-tasking", "open minded"], "languages_combined": []}, "experience_required": {"duration": ["at least 4+ years"], "field": ["related", "data analysis", "business"]}}, {"job_id": "100003009037294", "location_code": "hk", "company": "Manulife (International) Limited", "job_title": "MPF Customer Service Officer", "description": "Responsibilities\n\nMaintain good relationship with existing or potential customers\nHandle customer enquiries in a professional manner\nCoach junior team member on customer service skills\nFollow up and liaise with relevant parties\u00a0\nRequirements\n\nExperience at customer services/ insurance/ medical industry with 2 years or above\nExcellent customer services skill experience; self-motivated and good team player\nBe proactive and able to work independently,Strong communication skills\u00a0\nGood command of written and spoken English/ Mandarin\u00a0\nDiploma or above in any discipline, Insurance Studies and Qualification of IIQE Paper 1, 2 & 3 will be an advantage", "employment_types": ["Full Time", "Permanent"], "selling_points": ["20k up Income", "Customer Service Experience will be an advantage", "Coach junior team member"], "locations": ["Ngau Tau Kok"], "categories": ["Banking / Finance", "Corporate Banking", "Hospitality / F & B", "Hospitality / Hotel Services", "Property / Real Estate", "Property Consultancy"], "post_time": "2022-01-11T02:21:39Z", "salary": {"currency": null, "max": null, "min": null, "period": "monthly", "term": null}, "salary_visible": false, "title_keywords": ["customer service officer"], "responsibilities": ["handle customer enquiries", "professional manner", "maintain good relationship", "customer service", "liaise with"], "requirements": {"degrees": ["diploma or above"], "majors": ["insurance"], "languages": ["english", "mandarin"], "language_level": ["good command"], "hard_skills": ["iiqe paper"], "soft_skills": ["communication skills", "good team player", "self-motivated", "customer services skill", "work independently", "proactive"], "languages_combined": [{"language": "english", "language_level": ["good command"]}, {"language": "mandarin", "language_level": ["good command"]}]}, "experience_required": {"duration": ["2 years"], "field": ["medical", "insurance", "customer services"]}}, {"job_id": "100003009035919", "location_code": "hk", "company": "Hang Seng Bank Ltd", "job_title": "Assistant Project Manager", "description": "Wholesale Banking \u2013 Chief Operating Officer\u2019s Office\n\nHang Seng\u2019s Wholesale Banking (WSB) business provides customized one-stop financial solutions to our corporate customers, from prime small and medium-sized businesses to publicly listed companies.\n\nFor customers conducting business locally or around the world, we offer a comprehensive range of services including corporate lending, trade and receivables finance, structured loan, cash management, investment, treasury services, insurance and e-Banking services.\u00a0\u00a0As a reliable financial partner, we attend to the specific business needs of our customers and provide efficient tailor-made banking solutions through our relationship managers and dedicated specialists.\n\nWe are currently seeking a high caliber professional to join our department as\u00a0Assistant Project Manager.\n\nPrincipal responsibilities\n\nProvide project management, business analysis and consultancy services on strategic change project / system implementation, workflow design, automation and process re-engineering in Wholesale Banking\nAssist project manager in monitoring project scope and resources to meet project schedule & budget\nWork closely with various stakeholders including business users, operations, IT, audit, legal and compliance to ensure effective project governance\nSupport project manager in managing all the potential risks on projects and recommend mitigating measures if required\nKeep abreast on latest technology/ best practices in banking industry and deliver changes to current processes with efficiency and cost improvement\nRequirements\nUniversity degree in a related discipline or other relevant qualifications\nMinimum of 3 years\u2019 banking experience with participation in banking projects, preferably with knowledge in project management and product delivery lifecycle\nKnowledge of light automation solution such as Blue Prism, Power Platform and VBA, hands-on experience in RPA development will be a plus\nAbility to overcome challenges, create innovative solutions and work in an agile environment\nSelf-initiative, ability to communicate effectively and create connection with others\nProficiency in both spoken and written English and Chinese (Mandarin & Chinese)\nGreat sense of ownership and servicing mindset to ensure efficient and effective customer service processes\n\n\nIf you would like to explore other opportunities at Hang Seng Hong Kong, please visit\u00a0www.hangseng.com/careers/\u00a0for details.\n\nThe health and safety of our employees and candidates is very important to us. Due to the current situation related to the Novel Coronavirus (2019-nCoV), we\u2019re leveraging our digital capabilities to ensure we can continue to recruit top talent at the HSBC Group. As your application progresses, you may be asked to use one of our digital tools to help you through your recruitment journey. If so, one of our Resourcing colleagues will explain how our video-interviewing technology will be used throughout the recruitment process and will be on hand to answer any questions you might have.\n\nAll information provided by applicants will be used only for recruitment purposes and will be used strictly in accordance with the Bank's personal data policies, a copy of which may be obtained by the applicant upon request. Unless otherwise instructed in writing by the applicant concerned, applicants may be considered for other suitable positions within the Bank and its related companies. The personal data of unsuccessful job applicants may be retained for a maximum of two years from the date when the job application is rejected and such data may be retained for a longer period if there is a subsisting reason that obliges the Bank to do so, after which the personal data will be destroyed.", "employment_types": ["Full Time", "Permanent"], "selling_points": [], "locations": ["Not Specified"], "categories": ["Banking / Finance", "Corporate Banking", "Information Technology (IT)", "IT Project Management / Team Lead"], "post_time": "2022-01-11T01:17:31Z", "salary": {"currency": null, "max": null, "min": null, "period": "monthly", "term": null}, "salary_visible": false, "title_keywords": ["assistant project manager"], "responsibilities": ["cost", "operations", "monitoring", "budget", "implementation", "design", "audit", "compliance", "project management", "schedule", "banking", "business analysis", "re-engineering"], "requirements": {"degrees": ["university degree"], "majors": [], "languages": ["english", "chinese", "mandarin"], "language_level": ["proficiency"], "hard_skills": ["vba", "plus", "agile", "reason", "rpa", "project management"], "soft_skills": ["efficient", "agile", "project management", "hands-on", "customer service", "self-initiative", "novel", "innovative"], "languages_combined": [{"language": "english", "language_level": ["proficiency"]}, {"language": "chinese", "language_level": ["proficiency"]}, {"language": "mandarin", "language_level": ["proficiency"]}]}, "experience_required": {"duration": ["minimum of 3 years"], "field": ["project management", "development", "banking experience", "banking"]}}, {"job_id": "100003009036354", "location_code": "hk", "company": "KeeReal Consulting Limited", "job_title": "Corporate Loan - Senior Officer", "description": "Our client is a well-established MNC bank and recently seeking a flexible candidate for the Corporate Loan - Senior Officer position to join their newly expanded branch.\u00a0\n\nResponsibilities:\n\nPerform Syndication Agency function and loan administration as an officer;\u00a0\nReview structured & syndicated loan documentation drafts, and to ensure all terms and conditions are align with the bank\u2019s policy.\nTo work closely with internal and external parties for loan draw down and credit administration work;\nPerform customer due diligent (KYC);\nMonitor & follow up documentation deficiency and outstanding loan documents;\nRequirements:\n\nDegree holder or above\nSelf-motivating, flexible and can-do attitude preferred\nAt least 3 years\u2019 experience in credit process / monitoring of Corporate Banking industry\nProficient in English\u00a0", "employment_types": ["Full Time", "Permanent"], "selling_points": ["Well-established MNC bank in Asia", "At least 3 years\u2019 experience in credit monitoring", "Directly reporting to Senior Manager"], "locations": ["Central & Western Area"], "categories": ["Banking / Finance", "Corporate Banking", "Credit Analysis / Approval", "Loan"], "post_time": "2022-01-10T16:27:23Z", "salary": {"currency": null, "max": null, "min": null, "period": "monthly", "term": null}, "salary_visible": false, "title_keywords": ["senior officer"], "responsibilities": ["syndicated loan documentation", "review", "internal and external parties", "monitor", "kyc", "documentation", "administration"], "requirements": {"degrees": ["degree holder"], "majors": [], "languages": ["english"], "language_level": ["proficient"], "hard_skills": [], "soft_skills": ["flexible", "can-do attitude"], "languages_combined": [{"language": "english", "language_level": ["proficient"]}]}, "experience_required": {"duration": ["at least 3 years"], "field": ["banking industry"]}}, {"job_id": "100003009036758", "location_code": "hk", "company": "-", "job_title": "Relationship Manager, Foreign Enterprises Finance, Asia-Pacific Business", "description": "Job Responsibilities\nAssist senior marketing officers on customer portfolio accounts management to contribute to the sustained, profitable growth of our Bank\nAssist senior marketing officers to solicit and establish new customer relationship\nStrengthen, broaden and protect existing customer relationships\nPractise sound credit risk management\nManage development of self and staff\nImplement improvement initiatives\nJob Requirements\nUniversity graduate\nAt least 2 years' relevant experience\nGood credit analysis and marketing skills with knowledge of Asian markets\nSound knowledge on credit and banking products as well as proven cashflow modeling skill\nSound business sense with good interpersonal and communication skills\nGood computer skills\nGood command of both written and spoken English & Chinese (including Putonghua)\nCandidates with less experience will also be considered", "employment_types": ["Full Time", "Permanent"], "selling_points": [], "locations": ["Central"], "categories": ["Banking / Finance", "Corporate Banking", "Corporate Finance", "Financial Services"], "post_time": "2022-01-10T13:36:19Z", "salary": {"currency": null, "max": null, "min": null, "period": "monthly", "term": null}, "salary_visible": false, "title_keywords": ["relationship manager"], "responsibilities": ["management"], "requirements": {"degrees": ["university graduate"], "majors": [], "languages": ["putonghua", "english", "chinese"], "language_level": ["good command"], "hard_skills": ["credit analysis", "marketing skills", "computer skills"], "soft_skills": ["communication skills", "interpersonal", "business sense"], "languages_combined": [{"language": "putonghua", "language_level": ["good command"]}, {"language": "english", "language_level": ["good command"]}, {"language": "chinese", "language_level": ["good command"]}]}, "experience_required": {"duration": ["at least 2 years"], "field": ["relevant experience"]}}, {"job_id": "100003009034950", "location_code": "hk", "company": "\u5fc5\u9ad8\u4eba\u4e8b\u9867\u554f\u6709\u9650\u516c\u53f8", "job_title": "Junior Relationship Manager - SME Team", "description": "Our client is a Global Bank and due to its steady business growth, they are now seeking high caliber Junior Relationship Manager to join their SME Team.\n\nJob Responsibilities\n\nBuild and growth SME clients to sell SME product;\nProvide professional advice/service to clients on SME business financial needs;\nConduct periodic reviews of portfolio customers to ensure proper due diligence and KYC.\n\nRequirements\n\nUniversity degree in Business, Finance or related disciplines;\nMinimum 3 years of relevant experiences in banking; with 1 years of SME/corporate customer relationship management;\nKnowledgeable of Credit writing is preferable;\nArticulate with strong communication skills;\nSales driven and result oriented;\nYoung, energetic, and self-motivation;\nProficiency in both written and spoken English, Cantonese and Putonghua;\nCompleted and passed HKSI and IIQE licensing exams is a must;\nCandidates with more experience will be considered for Relationship Manager/Senior Relationship Manager.\n\nInterested parties please forward your CV in word format with current and expected salaries to PICCO Bent Consultancy Limited.\n\n[All applications will be treated with strict confidential and will be used for recruitment purposes only]", "employment_types": ["Full Time"], "selling_points": ["Build and growth SME clients to sell SME product", "Completed and passed HKSI and IIQE licensing exams", "Sales driven, result oriented, self-motivation"], "locations": ["Central"], "categories": ["Banking / Finance", "Corporate Banking", "Retail Banking", "Sales, CS & Business Devpt", "Customer Service - Supervisor / Officer"], "post_time": "2022-01-10T04:48:42Z", "salary": {"currency": null, "max": null, "min": null, "period": "monthly", "term": null}, "salary_visible": false, "title_keywords": ["relationship manager", "junior"], "responsibilities": ["sme", "due diligence", "kyc"], "requirements": {"degrees": ["university degree"], "majors": ["related disciplines", "finance", "business"], "languages": ["cantonese", "putonghua", "english"], "language_level": ["proficiency"], "hard_skills": ["iiqe", "hksi"], "soft_skills": ["communication skills", "result oriented", "self-motivation", "articulate", "energetic", "driven"], "languages_combined": [{"language": "cantonese", "language_level": ["proficiency"]}, {"language": "putonghua", "language_level": ["proficiency"]}, {"language": "english", "language_level": ["proficiency"]}]}, "experience_required": {"duration": ["minimum 3 years"], "field": ["banking"]}}, {"job_id": "100003009039893", "location_code": "hk", "company": "DBS Bank Ltd", "job_title": "Associate/Analyst, Custody Settlement", "description": "Business Function\n\nTechnology and Operations (T&O) enables aand empowers the bank with an efficient, nimble and resilient infrastructure through a strategic focus on productivity, quality & control, technology, people capability and innovation. In T&O, we manage the majority of the Bank's operational processes and inspire to delight our business partners through our multiple banking delivery channels.\n\nResponsibilties\u00a0\n\nMonitor and execute stock settlement instructions efficiently and accurately\nMonitor and process physical scrip deposit and withdrawal to provide efficient services to our customers and maintain the record in a timely and accurate manner.\nMonitor day-to-day settlement on equities, fixed income and other types of instruments.\nPerform check and control on processes including static data maintenance, customer position update and pricing information update, and handle reconciliation of General Ledger accounts, preparation of transaction and miscellaneous reports, etc\nFollow up with brokers and custodians to clean up any unmatched/ unsettled instructions\nSupport the process of monthly fee billings and collections.\nProvide second level client services.\u00a0\u00a0Handle customer inquiries and resolve / escalate problems in an efficient manner\nParticipate in project initiatives and UAT for system enhancements\n\nRequirements\n\n1\u00a0years of relevant working experience in securities settlement in the banking environment\nSolid knowledge in investment product and end to end settlement process.\nBe conversant with CCASS, SFC rules, SFO and HKICL\nBe familiar with the market trend and new product / system development of Hong Kong securities market\nAccuracy and thoroughness in work\nGood problem-solving skills and ability to handle difficult customers\nGood team player, supportive and flexible to take up team tasks\nGood communication skills and good command in English and Chinese (both spoken & written)\n\nApply Now\n\nWe offer a competitive salary and benefits package and the professional advantages of a dynamic environment that supports your development and recognises your achievements.\n\nWe regret only shortlisted candidates will be notified.", "employment_types": ["Full Time"], "selling_points": ["With securities settlement experience preferable", "Currently holding a checker role is an advantage", "See job description."], "locations": ["Kwun Tong"], "categories": ["Banking / Finance", "Corporate Banking", "Order Processing & Operation / Settlement"], "post_time": "2022-01-11T14:25:31Z", "salary": {"currency": null, "max": null, "min": null, "period": "monthly", "term": null}, "salary_visible": false, "title_keywords": ["analyst", "associate"], "responsibilities": ["control", "uat", "maintenance", "data", "customer inquiries", "general ledger", "billings", "monitor", "maintain", "reports"], "requirements": {"degrees": [], "majors": [], "languages": ["english", "chinese"], "language_level": ["good command", "good"], "hard_skills": ["sfc rules", "dynamic", "ccass", "problem-solving skills", "sfo"], "soft_skills": ["flexible", "communication skills", "supportive", "good team player", "dynamic environment", "problem-solving skills"], "languages_combined": [{"language": "english", "language_level": ["good command", "good"]}, {"language": "chinese", "language_level": ["good command", "good"]}]}, "experience_required": {"duration": ["1 years"], "field": ["securities", "relevant working experience", "banking"]}}, {"job_id": "100003009046337", "location_code": "hk", "company": "Randstad Hong Kong Limited", "job_title": "Liquidity Risk Manager, Corporate Bank", "description": "about the company\n\nOur client is a well-established corporate bank\n\nabout the team\n\nThe team is sizable and focuses on treasury market exposure\n\nabout the job\n\nYou will:\n\nSupport to establish and maintain liquidity risk management framework of limits and controls, policies & procedures and governance\nMonitor and manage liquidity risk and conduct daily liquidity ratios management and projection\nConduct regular liquidity risk regulatory and internal stress testing\nSupport to implement strategies over Bank's asset and liabilities, balance sheet growth and projection, with an on-going monitoring of the result\nFormulate and enhance the corresponding policies and guidelines to ensure internal risk controls are adequate and appropriate\n\nskills & experiences required\n\nDegree holder or above in financial subjects, professional qualification in CFA or FRM is preferable\nAt least 2-3 years liquidity risk experience in banking institutions and familiar with treasury products\nGood understanding on corresponding regulatory requirements\nGood command of both written and spoken English and Mandarin\nTo apply online, please click on the link. Alternatively, for a confidential discussion please contact Cheryl Tsang on + 852 2232 3470 or email: cheryl.tsang@randstad.com.hk", "employment_types": ["Full Time", "Permanent"], "selling_points": ["Well-established Corporate Bank", "Bank-wide coverage", "Hong Kong Island location"], "locations": ["Not Specified"], "categories": ["Banking / Finance", "Corporate Banking", "Financial Services", "Risk Management"], "post_time": "2022-01-13T10:34:59Z", "salary": {"currency": "HKD", "max": 54999, "min": 30000, "period": "monthly", "term": null}, "salary_visible": true, "title_keywords": ["manager"], "responsibilities": ["management", "guidelines", "policies", "regulatory requirements", "monitoring", "procedures", "monitor", "testing", "maintain", "contact", "banking", "balance sheet"], "requirements": {"degrees": ["degree holder"], "majors": [], "languages": ["english", "mandarin"], "language_level": ["good command"], "hard_skills": ["cfa", "frm"], "soft_skills": [], "languages_combined": [{"language": "english", "language_level": ["good command"]}, {"language": "mandarin", "language_level": ["good command"]}]}, "experience_required": {"duration": ["at least 2-3 years"], "field": ["banking"]}}, {"job_id": "100003009042202", "location_code": "hk", "company": "Manpower Services (Hong Kong) Limited", "job_title": "Onsite with HSBC- Fund Accountant (12 Month Contract, Up to 25K)", "description": "Title: Fund Accountant ( equivalent to GCB7)\nMax Salary : 20 -25K per month ( 1 year exp)\nDuration: 12 months\nLocation: 5/F Tower 1 HSBC Centre, 1 Sham Mong Road, Kowloon, Hong Kong\nDepartment : Securities Services GBMC\n\nPrincipal responsibilities :\n\nAssist in the day to day administration, valuation, custody, compliance and accounting of the assigned\nfund portfolios\nReview Net Asset Value reports and reconciliation prepared by servicing team and train the servicing\nteam in preparing such reports\nProvide support in preparing relevant reports to clients on a regular basis and ensure the operations are\nin compliance with relevant guidelines and governance\nEvaluate the fund operation procedures with the team to improve efficiency\nPerform operational and administrative works and assist in answering stakeholders enquiries\nEscalate and report any issues in accordance with internal incident management reporting requirements\nParticipate in ad-hoc projects as required\n\nRequirements :\n\nUniversity graduate majoring in accounting or finance related disciplines\nBasic understanding of accounting and experience in fund or banking industry is desired\nExcellent written and spoken English\nStrong team player, attention to details\nGood computer and interpersonal skills\n\nIf you are interested in this role, click \u201cApply Now\u201d, else, you may also directly send your updated resume and expected salary to Anson Li at anson.li@manpowergrc.hk.", "employment_types": ["Contract"], "selling_points": ["Uni graduate majoring in accounting or Commerce", "Experience in fund or banking industry is desired", "Working Location: HSBC Centre"], "locations": ["Kowloon City Area"], "categories": ["Accounting", "Accountant", "Banking / Finance", "Corporate Banking", "Fund Management"], "post_time": "2022-01-12T06:35:36Z", "salary": {"currency": null, "max": null, "min": null, "period": "monthly", "term": null}, "salary_visible": false, "title_keywords": ["accountant"], "responsibilities": ["valuation", "provide support", "relevant reports", "guidelines", "operations", "review", "compliance", "procedures", "evaluate", "reports", "management reporting", "report", "ad-hoc projects", "administration"], "requirements": {"degrees": ["university graduate"], "majors": ["related disciplines", "finance", "accounting"], "languages": ["english"], "language_level": ["excellent"], "hard_skills": ["basic"], "soft_skills": ["team player", "interested in", "interpersonal skills", "attention to details"], "languages_combined": [{"language": "english", "language_level": ["excellent"]}]}, "experience_required": {"duration": [], "field": ["banking industry", "accounting"]}}, {"job_id": "100003009039324", "location_code": "hk", "company": "DBS Bank Ltd", "job_title": "Senior Associate, Operations, Sec Svcs-Clrnc/Setlmnt/Invstgn, Private Banking (Payment, Loans & TRE Admin)", "description": "Business Function\n\nGroup Technology and Operations (T&O) enables and empowers the bank with an efficient, nimble and resilient infrastructure through a strategic focus on productivity, quality & control, technology, people capability and innovation. In Group T&O, we manage the majority of the Bank's operational processes and inspire to delight our business partners through our multiple banking delivery channels.\n\nResponsibilities:\n\nCash Related Transaction processing\nRemittance Out and In\nFund Transfer\nIssuance of Cashier Order & Demand Draft\nCheque & Time Deposit\nHandle RM & CS\u2019 enquiries\nInsufficient fund and collateral check\nDay-end reconciliation on deal ticket & incomplete order verification\nSystem enhancement & development\nReport and escalate any issue and exceptions\nComplete transaction such as remittance & issuance of CO & DD by cut-off time\nEnsure TT Out and 3rd\u00a0Party Fund Transfer with sufficient funds and collateral\nEnsure no error detected with control of day-end reconciliation\nOther clerical administration\n\nRequirements:\n\nUniversity Degree Holder\nMinimum 7-year experience in banking cash related products with 4-year in leader level\u00a0\u00a0\nGood experience and knowledge in banking cash products and remittance\nAble to work independently, excellent interpersonal and communication skills\nDigital mindset would be advantage\nProficient in MS Office\nProficiency in spoken / writing skills in both English and Chinese\nCandidate with more experience may consider for a senior position\n\nApply Now\n\nWe offer a competitive salary and benefits package and the professional advantages of a dynamic environment that supports your development and recognises your achievements.\n\nWe regret only shortlisted candidates will be notified.", "employment_types": ["Full Time"], "selling_points": ["Pension Fund Scheme", "Medical Coverage for Family", "Career Development"], "locations": ["Kwun Tong"], "categories": ["Banking / Finance", "Corporate Banking", "Private Banking", "Retail Banking"], "post_time": "2022-01-11T09:25:45Z", "salary": {"currency": null, "max": null, "min": null, "period": "monthly", "term": null}, "salary_visible": false, "title_keywords": ["senior associate", "admin", "operations", "private banking"], "responsibilities": ["administration", "report", "control", "transaction processing"], "requirements": {"degrees": ["university degree"], "majors": [], "languages": ["english", "chinese"], "language_level": ["proficiency"], "hard_skills": ["dynamic", "writing skills", "ms office"], "soft_skills": ["communication skills", "work independently", "dynamic environment", "writing skills", "interpersonal"], "languages_combined": [{"language": "english", "language_level": ["proficiency"]}, {"language": "chinese", "language_level": ["proficiency"]}]}, "experience_required": {"duration": ["4-year", "minimum 7-year"], "field": ["related", "banking"]}}, {"job_id": "100003009038319", "location_code": "hk", "company": "Asia Pacific Data Technology Limited", "job_title": "Assistant Manager, Credit Administration", "description": "What shall this Job responsible for?\n\nManage loan document processing\nOversee and maintain commercial credit hygiene\nProvide corporate services to our client by issuing customized commercial loan contracts and corresponding documentation\nMonitor and generate reports for internal control requirement and conditions\nManage and participate in process improvement projects to streamline work flows and procedures\nPerform other ad hoc duties as assigned\n\n\u00a0\u00a0Who can perform this Job?\n\nHigh diploma or above education\nAt least 5 years solid experience in commercial loan documents administration\nSound knowledge on commercial products and related documents requirement\nGood command of English and Chinese", "employment_types": ["Full Time", "Permanent"], "selling_points": [], "locations": ["Tsim Sha Tsui"], "categories": ["Banking / Finance", "Corporate Banking", "Loan", "Order Processing & Operation / Settlement"], "post_time": "2022-01-11T06:33:37Z", "salary": {"currency": "HKD", "max": 44999, "min": 30000, "period": "monthly", "term": null}, "salary_visible": true, "title_keywords": ["assistant manager,"], "responsibilities": ["ad hoc duties", "administration", "related documents", "contracts", "monitor", "procedures", "hygiene", "maintain", "reports", "documentation", "internal control"], "requirements": {"degrees": ["high diploma or above"], "majors": [], "languages": ["english", "chinese"], "language_level": ["good command"], "hard_skills": ["documentation", "processing", "internal control"], "soft_skills": ["responsible"], "languages_combined": [{"language": "english", "language_level": ["good command"]}, {"language": "chinese", "language_level": ["good command"]}]}, "experience_required": {"duration": ["at least 5 years"], "field": ["commercial", "administration"]}}, {"job_id": "100003009036984", "location_code": "hk", "company": "Manulife (International) Limited", "job_title": "MPF Sales Assistant (Part-time 6K-10K,2-3 days work)", "description": "Job Description:\n\n-Manage personal and corporate MPF / personal accounts\n-Provide sales and after-sales services and protection services\n\n\u00a0\nWe offer:\n\n$6,000- $10,000 (with month allowance, performance bonus, annual bonus)\n\n-2-3 days work and flexible working hours\n-Overseas conferences & travel allowance\n-Excellent career development and promotion opportunities\n-Professional\u00a0training program and mentorship program (CFP, CFA, RFP)\n-Medical scheme & study allowance\n\n\nRequirement:\n\n-Fresh graduate will be considered\n-No relevant experience is required\n-Self-motivated, positive attitude, and customer-oriented", "employment_types": ["Full Time", "Part Time", "Permanent", "Internship"], "selling_points": [], "locations": ["Not Specified"], "categories": ["Accounting", "Accountant", "Banking / Finance", "Corporate Banking", "Financial Services"], "post_time": "2022-01-11T01:13:33Z", "salary": {"currency": null, "max": null, "min": null, "period": "monthly", "term": null}, "salary_visible": false, "title_keywords": ["sales assistant"], "responsibilities": ["mpf"], "requirements": {"degrees": [], "majors": [], "languages": [], "language_level": [], "hard_skills": [], "soft_skills": [], "languages_combined": []}, "experience_required": {"duration": [], "field": []}}, {"job_id": "100003009048252", "location_code": "hk", "company": "Charterhouse Partnership", "job_title": "Internal Audit - VP/AVP, Corporate Banking", "description": "Job Specification:\n\nSupport the Head of Audit to establish and implement strategies and departmental audit activities\nReview, supervise and monitor job assignments performed by other staff in ensuring all audit assignments and projects objectives are achieved\nPlan and/or conduct job assignments; follow up on the auditees\u2019 corrective actions and prepare audit documentation\nProvide constructive advice to appropriate levels of management\nSupervise the Regulatory Research and Compliance Team\u2019s activities\nManage key relationships with external stakeholders e.g. regulators, auditors, etc., as well as internal stakeholders e.g. Branch Management, other control functions, etc.\nEnhance and ensure the standard of internal audit process to be in line with professional practice\n\nRequirements:\n\nUniversity graduate with relevant professional qualification e.g. CPA, CIA, CAMS, CISA, CISM, CISSP etc.\nAt least 5 to 6 years\u2019 experience in auditing, with solid exposure to internal audit in banking field\nSound knowledge in controls and risk management of banking products e.g. corporate banking, structured finance and treasury, etc., related controls and banking systems\nGood planning, project management and organizing skills\nEffective leadership, communication and planning skills and ability to work independently\nProficiency in English, Cantonese and Mandarin.\u00a0\n\nIf you are interested in finding out more about this career opportunity, please email your resume to Nestor Roldan, nestor.roldan@ charterhouse.com.hk Web: www.charterhouse.com.hk\n\nCharterhouse Partnership Hong Kong is here to assist you in your job search. Our experienced recruitment consultants will provide you with career advice and assist you to develop a tailored job search strategy.", "employment_types": ["Full Time"], "selling_points": ["Audit VP/AVP, team head position", "A leading international corporate bank", "At least 5 to 6 years\u2019 experience in auditing"], "locations": ["Not Specified"], "categories": ["Accounting", "Audit", "Banking / Finance", "Corporate Banking", "Project Finance"], "post_time": "2022-01-14T06:07:51Z", "salary": {"currency": null, "max": null, "min": null, "period": "monthly", "term": null}, "salary_visible": false, "title_keywords": [], "responsibilities": ["management", "control", "internal audit", "review", "monitor", "audit", "compliance", "systems", "communication", "project management", "develop", "recruitment", "plan", "banking", "documentation", "auditing", "planning"], "requirements": {"degrees": ["university graduate"], "majors": [], "languages": ["cantonese", "english", "mandarin"], "language_level": ["proficiency"], "hard_skills": ["documentation", "cpa", "project management", "web"], "soft_skills": ["planning skills", "work independently", "interested in", "communication", "project management", "structured", "leadership", "constructive"], "languages_combined": [{"language": "cantonese", "language_level": ["proficiency"]}, {"language": "english", "language_level": ["proficiency"]}, {"language": "mandarin", "language_level": ["proficiency"]}]}, "experience_required": {"duration": ["at least 5 to 6 years"], "field": ["audit", "banking"]}}, {"job_id": "100003009043080", "location_code": "hk", "company": "Find Asia Limited", "job_title": "Sales VP, Investment Funds Services Product", "description": "Our client, a banking & finance co. is looking for the candidate with the following details:\n\nDuties\n\nEnhance sales opportunities for potential clients and penetrated with existing clients for full investment Funds Services Products\nWell-prepare the sales presentation, liaise and set up meetings\nLiaise with internal client relationship team to explore all sales opportunities\nIdentify product enhancement and product management\nSupport and liaise with Regional Head of Sales and the team for business development in North Asia and Regional Asia\nEnsure smooth delivery of the products and work closely with other teams\nParticipate in any conferences, seminars to maintain professional knowledge, update market, industry developments and competitors\u2019 activities\n\n\u00a0Requirements\n\nBachelor degree of Economics, Business Administration, Finance or relevant disciplines\nFluent in English and Mandarin\nWith relevant experience in finance, asset management in sales or business development\nSolid experience in clients handling, marketing and promotion\nExcellent skills of organization, communication, customer-focused\nAble to work independently and proactively", "employment_types": ["Full Time", "Permanent"], "selling_points": ["Finance, Investment Funds Services", "Asset Management, Sales, Business Development", "Proactive, independent"], "locations": ["Central & Western Area"], "categories": ["Banking / Finance", "Corporate Banking", "Equities / Capital Markets", "Asset Management"], "post_time": "2022-01-12T09:45:01Z", "salary": {"currency": null, "max": null, "min": null, "period": "monthly", "term": null}, "salary_visible": false, "title_keywords": ["sales"], "responsibilities": ["liaise", "management", "teams", "conferences", "maintain", "liaise with"], "requirements": {"degrees": ["degree", "bachelor"], "majors": ["finance", "economics", "business administration"], "languages": ["english", "mandarin"], "language_level": ["fluent"], "hard_skills": [], "soft_skills": ["communication", "work independently", "customer-focused"], "languages_combined": [{"language": "english", "language_level": ["fluent"]}, {"language": "mandarin", "language_level": ["fluent"]}]}, "experience_required": {"duration": [], "field": ["finance", "business development", "marketing", "relevant experience", "asset management"]}}, {"job_id": "100003009039837", "location_code": "hk", "company": "Hays", "job_title": "Senior Officer, Cash Management", "description": "Foreign Corporate Bank is looking for a Cash Management Officer. Amazing culture and Great Exposure\n\nYour new company\nA Foreign Corporate Bank is looking for a Cash Management Senior Officer\n\nYour new role\n\nProcess money transfer instruction from customer\nHandle customer enquiry and make quote to customer for deposit and foreign exchange\nTransaction input, filing\nCheque Clearings\n\n\nWhat you'll need to succeed\n\n3+ years of experience in remittance\nExperience in FlexCube preferable\nFluent in English and Mandarin\nSound knowledge in international payment system\nSWIFT knowledge\n\n\n\nWhat you need to do now\nIf you're interested in this role, click 'apply now' to forward an up-to-date copy of your CV, or reach out to Christopher Cheung via phone 2230 7916 or via email christopher.cheung@hays.com.hk now.\nIf this job isn't quite right for you but you are looking for a new position, please contact us for a confidential discussion on your career.", "employment_types": ["Full Time", "Permanent"], "selling_points": ["Foreign Corporate Bank", "Cash Management Senior Officer", "3+ years of experience"], "locations": ["Not Specified"], "categories": ["Banking / Finance", "Corporate Banking", "Others", "Order Processing & Operation / Settlement"], "post_time": "2022-01-11T11:52:28Z", "salary": {"currency": null, "max": null, "min": null, "period": "monthly", "term": null}, "salary_visible": false, "title_keywords": ["senior officer", "cash management"], "responsibilities": ["management", "payment", "contact"], "requirements": {"degrees": [], "majors": [], "languages": ["english", "mandarin"], "language_level": ["fluent"], "hard_skills": ["swift", "make", "exchange"], "soft_skills": ["interested in"], "languages_combined": [{"language": "english", "language_level": ["fluent"]}, {"language": "mandarin", "language_level": ["fluent"]}]}, "experience_required": {"duration": ["3+ years"], "field": []}}, {"job_id": "100003009038472", "location_code": "hk", "company": "SALT Consulting International Company Limited", "job_title": "Bank Complaint Handling - Manager / Assistant Manager / Officer", "description": "Our Banking client is hiring Complaint Handling Customer Service Manager / AM / Officer.\n\nResponsibilities:\n\nHandle verbal, in person or written complaint\n\nGive verbal / written reply for customer complaints\n\nAssign complaints to relevant ownership departments for further investigation\n\nPrepare management reports for reviewing complaints on a regular basis\n\nMonitor complaint resolution satisfaction\n\nProvide counseling and training when needed\n\n\nInterested parties pls send us your CV in MS Word format.", "employment_types": ["Full Time"], "selling_points": ["Investigate customer complaint", "Complaint handling", "Reengineering customer service workflow"], "locations": ["Central"], "categories": ["Banking / Finance", "Corporate Banking", "Retail Banking"], "post_time": "2022-01-11T07:02:04Z", "salary": {"currency": null, "max": null, "min": null, "period": "monthly", "term": null}, "salary_visible": false, "title_keywords": ["assistant manager", "manager", "officer"], "responsibilities": ["customer complaints", "monitor", "investigation", "resolution", "management reports", "customer service", "banking"], "requirements": {"degrees": [], "majors": [], "languages": [], "language_level": [], "hard_skills": ["management reports"], "soft_skills": ["customer service"], "languages_combined": []}, "experience_required": {"duration": [], "field": []}}, {"job_id": "100003009025603", "location_code": "hk", "company": "Shanghai Pudong Development Bank Co., Ltd., Hong Kong Branch", "job_title": "Assistant / Relationship Manager, China Corporate - Corporate Banking (Ref.: CV_CBD_RMC_202201)", "description": "Responsibilities:\n\nAchieve business and management targets effectively\nSolicit new business and deepen existing relationship with corporate clients, focusing on China Corporates\nDevelop the portfolio by cross selling on loan, deposit, treasury and DCM products\nWork closely with Mainland branches for referral business\nAnalyze, formulate, propose and execute financial solutions and client relationship management efficiently\nMonitor customer portfolio and conduct credit risk analysis\nContribute in product development and re-engineering\n\nRequirements:\n\nUniversity graduated with at least 2 years of experience in Corporate Banking who are currently working as Relationship Manager, with focus in China Corporates\nStrong track record in business development skills, familiar with financial markets\nStrong analytical thinking and negotiation skills\nSolid experience in conducting credit analysis and preparing credit proposals\nTeam player with good interpersonal and communication skills\nGood command of spoken and written Chinese and English, fluent Putonghua is a must\nQualification of SFC license 1 and 4 will be preferred\n\nPlease quote the Reference No.: CV_CBD_RMC_202201 in your application.\n\nOur Bank offers attractive remuneration package to chosen candidates. Interested parties please apply with full resume stating expected salary and contact phone number via Apply Now.\n\nAll applications will be treated in the strictest confidence and personal data collected will be used for recruitment purpose only.", "employment_types": ["Full Time", "Permanent"], "selling_points": ["Focus in China corporates", "Excellent career path in growing platform", "Bonus, medical plan, staff canteen facility, etc."], "locations": ["Wan Chai"], "categories": ["Banking / Finance", "Corporate Banking", "Others"], "post_time": "2022-01-06T16:08:04Z", "salary": {"currency": null, "max": null, "min": null, "period": "monthly", "term": null}, "salary_visible": false, "title_keywords": ["relationship manager", "assistant"], "responsibilities": ["management", "monitor", "develop", "risk analysis", "re-engineering"], "requirements": {"degrees": [], "majors": [], "languages": ["putonghua", "english", "chinese"], "language_level": ["good command", "fluent"], "hard_skills": ["credit analysis", "focus", "no", "sfc license"], "soft_skills": ["communication skills", "negotiation skills", "team player", "focus", "interpersonal"], "languages_combined": [{"language": "putonghua", "language_level": ["fluent", "good command"]}, {"language": "english", "language_level": ["good command"]}, {"language": "chinese", "language_level": ["good command"]}]}, "experience_required": {"duration": ["at least 2 years"], "field": ["banking"]}}, {"job_id": "100003009038015", "location_code": "hk", "company": "Manpower Services (Hong Kong) Limited", "job_title": "On-Site with Hang Seng Bank - Analyst, Investment Operations (6 Month Contract, Up to 18K)", "description": "Title Analyst, Investment Operations\nContract Period 6months\nSalary Range max. 18,000 per month\n\nWe are currently seeking a high caliber professional to join our team as Analyst, Investment Operations\n\nPrincipal responsibilities\n\u2022 Handling investment operations processes include trade management and support, monitor life cycle management and settlement, and oversight treasury positions.\n\u2022 Act as a point of escalation for business as usual (BAU) queries where required.\n\u2022 Maintaining positive relationships with all investment office team members and key staff at, to support the creation of a collaborative working environment in keeping with the clients values and mission.\n\u2022 Assist to manage the relationship with middle office service providers, custodian banks, auditors, and internal/external counterparties to monitor the quality of services and ensure the agreements with relevant service providers are being appropriately applied.\n\u2022 Participate in new product enablement coordinate with middle office service providers and custodian banks on change requirements.\n\nRequirements\n\u2022 University degree in a related discipline OR other relevant qualifications\n\u2022 Previous experience of operations/ accounting management, ideally in an investment setting would be valuable.\n\u2022 Computer literacy with common PC applications (i.e. word, excel, power point). VBA and Bloomberg knowledge is preferred.\n\u2022 Proactive / can-do approach and attitude. Thorough attention to detail and accuracy of delivery.\n\u2022 Good command of written and spoken English and Cantonese\n\nIf you are interested in this role, click \u201cApply Now\u201d, else, you may also directly send your updated resume and expected salary to Anson Li at anson.li@manpowergrc.hk.", "employment_types": ["Contract"], "selling_points": ["Previous experience of ops/ accounting management", "Familiar with VBA and Bloomberg knowledge", "Computer literacy with MS office is preferred"], "locations": ["Mong Kok"], "categories": ["Banking / Finance", "Analyst", "Corporate Banking", "Investment"], "post_time": "2022-01-11T04:35:26Z", "salary": {"currency": null, "max": null, "min": null, "period": "monthly", "term": null}, "salary_visible": false, "title_keywords": ["analyst", "operations"], "responsibilities": ["management", "maintaining", "operations", "monitor", "quality", "coordinate with"], "requirements": {"degrees": ["university degree"], "majors": [], "languages": ["cantonese", "english"], "language_level": ["good command"], "hard_skills": ["excel", "vba", "bloomberg", "word", "pc applications", "power point"], "soft_skills": ["interested in", "computer literacy", "thorough", "attention to detail", "can-do", "proactive"], "languages_combined": [{"language": "cantonese", "language_level": ["good command"]}, {"language": "english", "language_level": ["good command"]}]}, "experience_required": {"duration": [], "field": ["management", "accounting", "investment"]}}, {"job_id": "100003009039710", "location_code": "hk", "company": "Manpower Services (Hong Kong) Limited", "job_title": "Manager Process Re-engineering - Global Banking", "description": "Onsite with HSBC \u2013\u00a0Manager Process Re-engineering - Global Banking\n\nAs one of the world\u2019s largest banking and financial services organisations, HSBC has been connecting customers to opportunities since 1865. With operations in 64 countries and territories, HSBC\u2019s unparalleled international network links developed and emerging markets, and spans the world\u2019s largest and fastest-growing trade corridors. The bank serves more than 40 million customers through its commercial, retail, investment and private banking businesses, which are supported by operational and functional teams around the world.\n\n\u00a0We\u2019re currently seeking an experienced professional to join the HSBC\u00a0CTA Client Coverage Resizing team.\n\nTitle: Process Re-engineering\nMax Salary : 60 -70K per month\nDuration: 6 months contract\nLocation: Hong Kong\nDepartment: WCOO\n\nJob Responsibilities:\n\n\uf0b7 Conduct detailed assessment of frontline improvement opportunities assessing their viability and benefit they will bring to the business\n\uf0b7 Work closely with Global stakeholders to understand current state processes, identify wastes / inefficiencies in\na process, use a proven framework to understand the root causes for the waste in the process and identify opportunities to improve the process\n\uf0b7 Through collaborating with stakeholders and gathering data, you will be required to present opportunities to stakeholders of all levels, and where applicable to senior/ executive level stakeholders; who can use the information presented to make informed decisions\n\uf0b7 Facilitate co-creation sessions/workshops with a wide group of stakeholders\nTo be successful in this role you should meet the following requirements:\n\n\uf0b7 Knowledge and experience of process mapping, identifying process improvements, designing\nsimplified, streamlined processes and delivering process improvements is essential\n\uf0b7 Lean / Lean Six Sigma training and experience is essential. The DMAIC framework, combined with Design Thinking and Agile experience will be useful in the day to day role\n\uf0b7 Certified Lean practitioner / Lean Six Sigma Belt is desirable\n\uf0b7 Global Banking, Commercial Banking, knowledge and experience is desirable\n\uf0b7 Must have experience using Visio, as this will be the main tool used for process mapping\n\n\uf0b7 The role would suit someone who has worked in /experience in Consulting, Change Delivery,\nTransformation, Simplification, Operations, Lean /Process Improvement roles\n\uf0b7 Understand Agile ways of working\n\uf0b7 Proven ability to solve problems and drive a continuous improvement culture\n\uf0b7 Excellent interpersonal and communication skills with a proven ability to engage stakeholders, facilitate workshops and work well independently / in a team environment\n\uf0b7 Experience in gathering voice of the customer and voice of the business, to identify pain points and identify opportunities to solve for the pain points\n\uf0b7 Design Thinking training or experience is an advantage\n\nIf you are interested in this role, click \u201capply\u201d, else, you may also directly send your updated resume to Shwetha at shwetha.vineeth@manpowergrc.hk\n\nHSBC is committed to building a work culture where everyone is valued, respected and opinions count. They take pride in providing a workplace that fosters continuous professional development, collaboration and supporting people to be at their best in an inclusive and diverse environment.", "employment_types": ["Contract"], "selling_points": ["Manager Process Re-engineering", "Onsite with HSBC", "Contract Position"], "locations": ["Central"], "categories": ["Banking / Finance", "Corporate Banking", "Financial Services"], "post_time": "2022-01-11T10:35:57Z", "salary": {"currency": null, "max": null, "min": null, "period": "monthly", "term": null}, "salary_visible": false, "title_keywords": ["manager"], "responsibilities": ["consulting", "data", "operations", "teams", "designing", "design", "communication", "banking", "re-engineering"], "requirements": {"degrees": [], "majors": [], "languages": [], "language_level": [], "hard_skills": ["lean", "agile", "voice of the customer", "make", "six sigma", "workshops", "max"], "soft_skills": ["communication skills", "independently", "agile", "interested in", "solve problems", "committed", "diverse", "interpersonal", "detailed"], "languages_combined": []}, "experience_required": {"duration": [], "field": ["training", "consulting", "design", "commercial", "business", "banking"]}}, {"job_id": "100003009037940", "location_code": "hk", "company": "Tradewind International Factoring Ltd.", "job_title": "VP / AVP, Sales", "description": "Key responsibilities as follow:\n\nDevelop and promote the Tradewind brand and advance Factoring and Trade Finance Business throughout the region.\u00a0\nIndependently maintain, develop and expand customer relationships by providing trade finance products/solutions and general banking services.\nMeet sales targets and help establish the company\u2019s business plan.\nAssist in presentations, negotiations, project evaluations and obtaining final approvals from management as required.\nOrganize, coordinate and complete the client due diligence process including recommendation to management for on boarding certain target prospects\nMaintain effective communication with clients/prospects; establish long-term working relations with clients and spearhead close interaction with all Tradewind offices to develop synergies across the Tradewind franchise\nAttend trade shows to network with exhibitors and other participants and to identify new sales opportunity\nDevelop referral network with business partners\nTravel required\nOther jobs assigned by the immediate supervisor.\n\nHere is your opportunity to broaden your career exposure with Tradewind and to develop your specialized skill set in factoring and financing as a subject matter expert in this particular line of business.\u00a0\u00a0\n\nWe are looking for candidates with outgoing personality, connect well with prospects/clients and articulate professionally in client meetings/presentations.\u00a0 Most importantly strong passion to succeed in a dynamic sales environment.\n\nQualifications:\n\nBachelor degree or above, degree in Finance, Accounting or Business is a plus;\nMinimum 5 years' working experience in business development;\nCandidate with lesser experience will be considered as\u00a0Assistant Vice President, Sales;\nStrong ability in market development, communication and coordination;\nEntrepreneurial mindset, accountability, ability to work under pressure;\nDetailed-oriented with good organizational and interpersonal skills;\nGood level of business acumen and commercial awareness;\nFluent in spoken and written English and Chinese (Cantonese and Mandarin).", "employment_types": ["Full Time"], "selling_points": [], "locations": ["Tsim Sha Tsui"], "categories": ["Banking / Finance", "Corporate Banking", "Financial Services", "Sales, CS & Business Devpt", "Direct Sales"], "post_time": "2022-01-11T04:20:39Z", "salary": {"currency": null, "max": null, "min": null, "period": "monthly", "term": null}, "salary_visible": false, "title_keywords": ["sales"], "responsibilities": ["due diligence", "management", "subject matter expert", "presentations", "develop", "coordinate", "communication", "maintain", "coordination", "banking", "business plan", "work under pressure"], "requirements": {"degrees": ["degree", "degree or above", "bachelor"], "majors": ["business", "finance", "accounting"], "languages": ["cantonese", "english", "chinese", "mandarin"], "language_level": ["fluent"], "hard_skills": ["plus", "dynamic", "presentations", "acumen"], "soft_skills": ["outgoing personality", "independently", "accountability", "organizational", "detailed", "communication", "dynamic", "interpersonal skills", "coordination", "business acumen", "articulate", "work under pressure"], "languages_combined": [{"language": "cantonese", "language_level": ["fluent"]}, {"language": "english", "language_level": ["fluent"]}, {"language": "chinese", "language_level": ["fluent"]}, {"language": "mandarin", "language_level": ["fluent"]}]}, "experience_required": {"duration": ["minimum 5 years"], "field": ["business development"]}}, {"job_id": "100003009039458", "location_code": "hk", "company": "ADECCO", "job_title": "Clerk (Chinese Bank) (12-month renewable contract)", "description": "Our client is a Chinese Bank and they are looking for clerk to join their winning team.\n\n\n\n\nResponsibilities:\n\nHandle the documentation for customer onboarding and data maintenance of existing customer in compliance with the related procedures and service standard\nEnsure completion and correctness of all Legal & Supporting documentation for execution\nLiaise with various stakeholders to complete the task\nEnsure all transactions are handled in compliance with regulatory requirements and internal procedures/guidelines\nProvide advisory supports and assistance to BU relating to customer onboarding and data maintenance\nSupport ad hoc tasks\nReview and prepare daily or monthly reports for internal or regulatory purpose\n\nExperience:\n\nWith 1 or 2 years\u2019 experience in handling corporate customer onboarding is preferable\nCustomer-oriented, attentive to details, compliance and control oriented, diligent, proactive and able to\u00a0work under pressure\nGood command of spoken English, Cantonese and Putonghua\nProficient in MS Office including Word, Excel and Chinese word processing.\u00a0\nUAT experience is preferable\u00a0\n\nEducation\n\n5 subjects at Grade E/Level 2 or above in HKCEE/HKDSE, including English, Chinese and Mathematics\n\nIf you're interested in this role, please \"CLICK HERE\"\u00a0to apply the position via Adecco website with your CV.\n\nPlease note that only shortlisted candidates will be notified. All information gathered will be treated in strict confidence and solely used for recruitment purposes.", "employment_types": ["Full Time", "Contract"], "selling_points": [], "locations": ["Kowloon Bay"], "categories": ["Banking / Finance", "Corporate Banking"], "post_time": "2022-01-11T09:50:00Z", "salary": {"currency": null, "max": null, "min": null, "period": "monthly", "term": null}, "salary_visible": false, "title_keywords": ["clerk"], "responsibilities": ["control", "service standard", "maintenance", "data", "guidelines", "regulatory requirements", "monthly reports", "compliance", "procedures", "ad hoc tasks", "transactions", "review", "website", "liaise with", "uat", "recruitment", "documentation", "work under pressure"], "requirements": {"degrees": ["hkdse"], "majors": ["mathematics"], "languages": ["cantonese", "putonghua", "english", "chinese"], "language_level": ["good command", "proficient"], "hard_skills": ["excel", "chinese word processing", "maintenance", "word", "documentation", "ms office"], "soft_skills": ["confidence", "attentive to details", "interested in", "diligent", "customer-oriented", "proactive", "work under pressure"], "languages_combined": [{"language": "cantonese", "language_level": ["good command"]}, {"language": "putonghua", "language_level": ["good command"]}, {"language": "english", "language_level": ["good command"]}, {"language": "chinese", "language_level": ["proficient"]}]}, "experience_required": {"duration": ["2 years"], "field": []}}, {"job_id": "100003009037503", "location_code": "hk", "company": "Robert Half", "job_title": "AVP/VP - Regulatory Reporting, Leading Bank", "description": "Our client is a leading International bank with operations in both banking and treasury services. To cope with their business expansion, they are looking for a caliber to join their team.\n\n\n\nResponsible for the HKMA regulatory reporting process, and to ensure the compilation of banking returns and surveys are in compliance with the completion instructions and relevant guidelines as set out by the HKMA\nEnsure proper control checking and review procedures are in place so as to minimize errors in reporting\nAssist in the implementation of system enhancement projects relating to banking return reporting and other ad hoc tasks as required by the management from time to time\n\n\n\nRequirements:\n\nBachelor's Degree in Accounting, Finance or relevant discipline\nMinimum 3 years' experience in banking and financial accounting / regulatory reporting functions\nMember of CPA is an added advantage\nHigh level of multi-tasking and time management skill are required\nA team-player with excellent working attitude; willing to take on multiple functions\nExcellent verbal and written communication skills\n\n\nApply Today\n\nTo apply online (Word attachment only), please click the 'Apply' button. Please note that only short-listed candidates will be contacted.", "employment_types": ["Full Time", "Permanent"], "selling_points": ["A leading retail banking and corporate banking", "Fringe benefit with decent bonus", "Good exposure with career progression"], "locations": ["Central & Western Area"], "categories": ["Banking / Finance", "Corporate Banking", "Private Banking", "Retail Banking"], "post_time": "2022-01-11T02:58:22Z", "salary": {"currency": null, "max": null, "min": null, "period": "monthly", "term": null}, "salary_visible": false, "title_keywords": [], "responsibilities": ["reporting", "control", "management", "guidelines", "operations", "compliance", "review", "checking", "procedures", "implementation", "ad hoc tasks", "communication", "banking", "enhancement projects"], "requirements": {"degrees": ["degree", "bachelor"], "majors": ["finance", "accounting"], "languages": [], "language_level": [], "hard_skills": ["hkma", "cpa", "word", "hkma regulatory reporting"], "soft_skills": ["communication skills", "responsible", "team-player", "multi-tasking", "time management skill"], "languages_combined": []}, "experience_required": {"duration": ["minimum 3 years"], "field": ["accounting", "financial", "banking"]}}, {"job_id": "100003009030320", "location_code": "hk", "company": "Hang Seng Bank Ltd", "job_title": "Contact Centre Transformation Manager", "description": "Digital, Business Services \u2013 Transformation\n\nHang Seng\u2019s Transformation under Digital, Business, Services a team of professionals dedicated to design and deliver change initiatives for the Bank and various business functions.\n\nThe Contact Centre Transformation programme involves various projects under Contact Center covering both Commercial Bank and Wealth & Personal Bank. The transformation includes omni-channel collaboration, process re-engineering, customer experience enhancement, staff capability improvement, and ultimately facilitate business growth.\n\nWe are currently seeking high caliber professional to join the Contact Centre Transformation team as\u00a0Contact Centre Transformation Manager.\n\nPrincipal responsibilities\n\nOrchestrate customer journeys across channels and touch points giving customers an integral and seamless omni-channel experience\u00a0\nCreate compelling and engaging Contact Centre experience\nDrive and deliver changes in operational and revenue performance of Contact Centre through initiatives which are fully aligned to business strategy\nUtilize data to come up with insights for business decisions\nEstablish effective project governance, lead changes to transform businesses, facilitate project initiation for cost / benefit analysis\u00a0\nManage programme / project cost and schedule, monitor progress and report to stakeholders and senior management.\u00a0\nProactively manage all the potential risks and issues on projects and ensure all relevant control measures are undertaken to minimize the risk exposure of the Bank\nNurture a collaborative, agile and supportive team culture through constant data driven feedback and constructive discussions\nSeek opportunities to create sustainable cost savings and operational efficiencies\nKeep abreast of best practices in banking industry when planning and delivering changes\nRequirements\nUniversity graduate in related disciplines or other relevant qualifications\nMinimum of 5 years\u2019 relevant experience in contact centre management and transformation projects\nKnowledge on data analytics, customer experience would be an advantage\nStrong understanding of Agile methodologies and tools is preferred\nStrong customer and people orientation, able to come up with solutions to improve staff and customer experience\nSound business acumen, able to make commercial judgment balancing the costs and benefits\nHighly organized with attention to details\nStrong communication and interpersonal skills\nAble to work independently with strong self-initiative, able to spot or pre-empt issues, recommend business solutions and escalate as required\nProficiency in both spoken and written English and Chinese\nGreat sense of ownership and servicing mindset to ensure efficient and effective customer service processes\u00a0\n\n\nIf you would like to explore other opportunities at Hang Seng Hong Kong, please visit\u00a0www.hangseng.com/careers/ for details.\n\nThe health and safety of our employees and candidates is very important to us. Due to the current situation related to the Novel Coronavirus (2019-nCoV), we\u2019re leveraging our digital capabilities to ensure we can continue to recruit top talent at the HSBC Group. \u00a0As your application progresses, you may be asked to use one of our digital tools to help you through your recruitment journey. \u00a0If so, one of our \u00a0Resourcing colleagues will explain how our video-interviewing technology will be used throughout the recruitment process and will be on hand to answer any questions you might have\nAll information provided by applicants will be used only for recruitment purposes and will be used strictly in accordance with the Bank's personal data policies, a copy of which may be obtained by the applicant upon request. Unless otherwise instructed in writing by the applicant concerned, applicants may be considered for other suitable positions within the Bank and its related companies. The personal data of unsuccessful job applicants may be retained for a maximum of two years from the date when the job application is rejected and such data may be retained for a longer period if there is a subsisting reason that obliges the Bank to do so, after which the personal data will be destroyed.", "employment_types": ["Full Time", "Permanent"], "selling_points": [], "locations": ["Not Specified"], "categories": ["Banking / Finance", "Corporate Banking", "Retail Banking", "Financial Services"], "post_time": "2022-01-10T02:29:26Z", "salary": {"currency": null, "max": null, "min": null, "period": "monthly", "term": null}, "salary_visible": false, "title_keywords": ["manager"], "responsibilities": ["cost", "control", "monitor progress", "data", "analysis", "planning", "schedule", "contact", "banking", "senior management", "report"], "requirements": {"degrees": ["university graduate"], "majors": ["related disciplines"], "languages": [], "language_level": [], "hard_skills": ["data analytics", "agile"], "soft_skills": ["agile"], "languages_combined": []}, "experience_required": {"duration": ["minimum of 5 years"], "field": ["management", "relevant experience"]}}, {"job_id": "100003009036756", "location_code": "hk", "company": "Industrial and Commercial Bank of China (Asia) Limited", "job_title": "Assistant Internal Control Manager, Asia-Pacific Business", "description": "Job Responsibilities\nPrepare credit-related data (rating, annual audit, etc.) data collection, feedback, and regular reporting\nAssist in preparing and responding to internal control and Internal audit-related tasks\nResponsible for departmental operational risk measures, complaint handling case and BCP\nPerform ad-hoc tasks as assigned\nJob Requirements\nBachelor Degree or above\nMinimum 3 years administrative support experience, preferably in banking or financial institution\nDown-to-earth work attitude\nGood PC and Chinese typing skills\nGood interpersonal and communication skills\nGood command of written and spoken English and Chinese, including Putonghua\nFresh graduate will also be considered\n\n-\n\n-", "employment_types": ["Full Time"], "selling_points": [], "locations": ["Central"], "categories": ["Admin & HR", "Administration / Operation Manager", "Banking / Finance", "Corporate Banking", "Professional Services", "Legal & Compliance"], "post_time": "2022-01-10T13:35:56Z", "salary": {"currency": null, "max": null, "min": null, "period": "monthly", "term": null}, "salary_visible": false, "title_keywords": ["manager", "assistant"], "responsibilities": ["reporting", "internal audit", "annual audit", "data", "ad-hoc tasks", "data collection", "internal control"], "requirements": {"degrees": ["degree or above", "bachelor", "fresh graduate"], "majors": [], "languages": ["putonghua", "english", "chinese"], "language_level": ["good command", "good"], "hard_skills": ["pc", "typing"], "soft_skills": ["communication skills", "interpersonal"], "languages_combined": [{"language": "putonghua", "language_level": ["good command", "good"]}, {"language": "english", "language_level": ["good command", "good"]}, {"language": "chinese", "language_level": ["good command", "good", "good"]}]}, "experience_required": {"duration": ["minimum 3 years"], "field": ["administrative", "financial", "banking"]}}, {"job_id": "100003009038452", "location_code": "hk", "company": "Asia Progress Executive Limited", "job_title": "Credit Analyst (Corporate banking /Commercial Banking) - $30K-50K", "description": "Our client is PRC Corporate Bank\u00a0to cope with the rapid business expansion, they are now inviting high caliber candidates to join the team\n\nCredit Analyst (Corporate banking /Commercial Banking) - $30K-50K\n\nResponsibilities:-\n\nConduct analysis, assessment and evaluation on credit proposals for commercial clients and make recommendations for approval\nAssist to ensure the proper handling of credit request and to monitor a high credit quality of the bank\u2019s portfolio of commercial clients\u00a0\nReview and validate risk rating scorecards\u00a0\nMonitor credit limit excess, credit ratings/loan classification changes, adverse news release, credit events and developments relating to counterparties\u00a0\nPerform regular reporting, portfolio analysis and research duties\u00a0\nParticipate in bank projects relating to commercial credit risk and ad-hoc duties\n\nRequirements:-\n\nUniversity degree holder, major in Business/Finance/Accounting or other related disciplines\nAt least 3 - 4 years' credit analysis experience on Commercial banking credits; experience in handling FI / NBFI / Chinese & local large corporates\u00a0\n\u00a0Detailed-oriented, good analytical, interpersonal and communication skills\nGood command of written and spoken English and Chinese (Putonghua is a must)\nProficient in PC applications, including Microsoft Word and Excel\nMulti-tasked and able to work under tight timelines\u00a0\n\nPlease send full resume with\u00a0present & expected\u00a0salary to expedite sourcing\u00a0in\u00a0MS-WORD\u00a0format by clicking \u201cAPPLY NOW\u201d\nPlease quote our reference in your application\nPersonal data provided by job applicants will be used strictly in accordance with the employer\u2019s personal data policies, a copy of which will be provided upon request\nAll information provided will be used for recruitment purpose only", "employment_types": ["Full Time"], "selling_points": ["Deg 3-4 yrs credit analyst/credit proposal in bank", "credit analyst corporate Bank/FI/ Commercial BK", "Credit proposal large corporate clients in banking"], "locations": ["Central & Western Area"], "categories": ["Banking / Finance", "Corporate Banking", "Credit Analysis / Approval", "Loan"], "post_time": "2022-01-11T06:55:02Z", "salary": {"currency": null, "max": null, "min": null, "period": "monthly", "term": null}, "salary_visible": false, "title_keywords": ["credit analyst"], "responsibilities": ["make recommendations", "reporting", "ad-hoc duties", "analysis", "review", "quality", "monitor", "evaluation"], "requirements": {"degrees": ["university degree"], "majors": ["related disciplines", "finance", "business", "accounting"], "languages": ["putonghua", "english", "chinese"], "language_level": ["good command"], "hard_skills": ["excel", "ms-word", "microsoft word", "pc applications", "credit analysis"], "soft_skills": ["communication skills", "multi-tasked", "interpersonal", "detailed"], "languages_combined": [{"language": "putonghua", "language_level": ["good command"]}, {"language": "english", "language_level": ["good command"]}, {"language": "chinese", "language_level": ["good command"]}]}, "experience_required": {"duration": ["at least 3 - 4 years"], "field": ["commercial", "banking"]}}, {"job_id": "100003009038726", "location_code": "hk", "company": "China Construction Bank (Asia) Corporation Limited", "job_title": "Credit Control and Business Administration Manager \u2013 Commercial Banking (Ref. no.: BACA/CMB/JDB)", "description": "Job Descriptions:\n\n\nFacilitate the credit and transaction streamline projects\nEnsure the Division is following the Bank\u2019s governing credit policies and regulatory requirements\nCoordinate and conduct on-going monitoring on credit-& transactional control related reports to ensure they are within credit and operational risk framework\nTake part in ad-hoc projects as required (portfolio reviews)\nHandle the internal and external audit\n\nJob Requirements:\n\n\nDegree holder or equivalent\nMinimum 5 years\u2019 commercial banking and credit experience\nSolid understanding of credit/loan documentation as well as credit, operational and compliance\u00a0risk control concept\nStrong analytical and communication skills\nDetails-minded, logical and responsible\nGood command of both written and spoken English and Chinese, including Putonghua\nProficient in PC applications, including Microsoft Word and Excel\n\nTo apply, please send your detailed resume\u00a0stating present and expected salary\u00a0to one of the following channels:-\n\nBy Email\nBy Fax: 3718 2910\n\nApplicants who are not contacted within 8 weeks may consider their applications unsuccessful and their personal data will be retained by the bank for a period up to two years.\n\nAll information provided by applicants will be used for recruitment purposes only and will be used strictly in accordance with the bank's personal data policies, a copy of which will be provided upon request.", "employment_types": ["Full Time", "Permanent"], "selling_points": ["internal and external audit", "credit and transaction streamline projects", "Degree + 5 yrs commercial banking and credit"], "locations": ["Kowloon Bay"], "categories": ["Banking / Finance", "Corporate Banking", "Order Processing & Operation / Settlement", "Risk Management"], "post_time": "2022-01-11T07:41:23Z", "salary": {"currency": null, "max": null, "min": null, "period": "monthly", "term": null}, "salary_visible": false, "title_keywords": ["administration manager"], "responsibilities": ["control", "policies", "regulatory requirements", "monitoring", "audit", "coordinate", "reports", "ad-hoc projects"], "requirements": {"degrees": ["degree holder"], "majors": [], "languages": ["putonghua", "english", "chinese"], "language_level": ["good command"], "hard_skills": ["documentation", "excel", "microsoft word", "pc applications"], "soft_skills": ["communication skills", "responsible", "detailed"], "languages_combined": [{"language": "putonghua", "language_level": ["good command"]}, {"language": "english", "language_level": ["good command"]}, {"language": "chinese", "language_level": ["good command"]}]}, "experience_required": {"duration": ["minimum 5 years"], "field": ["commercial", "banking"]}}, {"job_id": "100003009033711", "location_code": "hk", "company": "Bank of Communications Co., Ltd. Hong Kong Branch", "job_title": "Relationship Manager (Financial Institutions Department)", "description": "Career Level\nMiddle\nQualification\nDegree\nYears of Experience\n8 years\nJob Type\nFull Time, Permanent\nJob Functions\nBanking / Finance, Corporate Banking, Treasury, Dealing & Trading", "employment_types": ["Full Time", "Permanent"], "selling_points": [], "locations": ["Not Specified"], "categories": ["Banking / Finance", "Corporate Banking", "Treasury", "Dealing & Trading"], "post_time": "2022-01-10T01:37:58Z", "salary": {"currency": null, "max": null, "min": null, "period": null, "term": null}, "salary_visible": false, "title_keywords": ["relationship manager"], "responsibilities": ["banking"], "requirements": {"degrees": ["degree"], "majors": [], "languages": [], "language_level": [], "hard_skills": [], "soft_skills": [], "languages_combined": []}, "experience_required": {"duration": [], "field": []}}, {"job_id": "100003009036759", "location_code": "hk", "company": "Industrial and Commercial Bank of China (Asia) Limited", "job_title": "Assistant Manger to Manager, Business Management, Corporate Banking", "description": "Job Responsibilities\nPerform AML, CDD & Internal Control Reviews and inspections, conduct risk based on-site or off-site interviews and inspections to assess the effectiveness of internal control framework\nIdentify, inspect, and report internal control weaknesses and recommend corrective actions or enhancements for implementation, monitor and evaluate the effectivess and efficiency of the remediation implemented\nPromote and monitor the effective implementation of external regulatory rules and the Bank\u2019s internal policies and procedures\nPerform gap analysis to fulfill regulatory requirements, formulate and improve the department\u2019s operation manual and operating procedures\nTimely report non-compliance risk incidents to the Internal Control and Compliance Department of the Bank\nCooperate with regulatory authorities and the Bank to carry out internal and external inspections\nCarry out compliance risk monitoring of various products, businesses and management activities. Conduct self-checking for the departments\u2019 business activities and operation processes\nOrganize and provide training, guidance and operation procedures to the Department\nIdentify and determine the compliance risk points and compliance risk data indicators of the department. Perform key risk assessment of the department\nJob Requirements\nUniversity graduate\n3\u00a0 to 8 years of corporate banking or legal and compliance department experience\nFamiliar with regulatory requirements including but not limited to the HKMA, SFC and PRC related guidelines\nA good command of written and spoken English, Cantonese and Mandarin\nFamiliar with corporate banking\u2019s operation procedures and customer due diligence is preferred", "employment_types": ["Permanent"], "selling_points": [], "locations": ["Central"], "categories": ["Banking / Finance", "Corporate Banking", "Others", "Professional Services", "Legal & Compliance"], "post_time": "2022-01-10T13:37:10Z", "salary": {"currency": null, "max": null, "min": null, "period": "monthly", "term": null}, "salary_visible": false, "title_keywords": ["manager", "assistant"], "responsibilities": ["provide training", "data", "regulatory requirements", "self-checking", "cooperate with", "internal control", "cdd", "compliance", "monitor", "implementation", "business activities", "report", "guidance", "management", "procedures", "risk monitoring", "aml", "policies", "analysis", "evaluate"], "requirements": {"degrees": ["university graduate"], "majors": [], "languages": ["cantonese", "english", "mandarin"], "language_level": ["good command"], "hard_skills": ["hkma", "customer due diligence"], "soft_skills": [], "languages_combined": [{"language": "cantonese", "language_level": ["good command"]}, {"language": "english", "language_level": ["good command"]}, {"language": "mandarin", "language_level": ["good command"]}]}, "experience_required": {"duration": ["8 years"], "field": ["compliance", "legal", "banking"]}}, {"job_id": "100003009036154", "location_code": "hk", "company": "Page Personnel", "job_title": "Leading Bank Group - Transaction Monitoring Investigator", "description": "Our client is one of Hong Kong's largest banks and they are now looking for a Transaction Monitoring Investigator to join their team. The successful candidate will have 2+ years of experience in transaction monitoring and investigations within banking.\n\nClient Details\n\nOur client is one of the most reputable banks in Hong Kong, with 3000+ offices across the world. They are currently one of the leaders in the market and has built a great reputation across the globe. Their Hong Kong business provides retail banking, private banking, commercial banking and global banking services to their clients.\n\nDescription\n\nConduct transaction monitoring, customer screening and AML investigations\nResponsible for writing a high-quality investigative reports\nIdentify possible violations of regulation according to documented red flags\nConduct Unusual Activity Reports (UARs) and escalate investigations to Financial Crime Investigators (FCC)\n\nProfile\n\nConduct transaction monitoring, customer screening and AML investigations\nResponsible for writing a high-quality investigative reports\nIdentify possible violations of regulation according to documented red flags\nConduct Unusual Activity Reports (UARs) and escalate investigations to Financial Crime Investigators and\n\nJob Offer\n\nWorking days and time: Mon - Fri, 0900 - 180\nWork location: Mongkok\nLeading bank group\nStimulating and challenging work\nExcellent exposure and learning curve\n\nTo apply online please click the 'Apply' button below. For a confidential discussion about this role please contact Kira Tang on +852 2258 3538.", "employment_types": ["Full Time", "Permanent"], "selling_points": ["Leading bank group", "Stimulating and challenging work", "Excellent exposure and learning curve"], "locations": ["Not Specified"], "categories": ["Banking / Finance", "Corporate Banking", "Retail Banking", "Financial Services"], "post_time": "2022-01-10T09:30:16Z", "salary": {"currency": null, "max": null, "min": null, "period": "monthly", "term": null}, "salary_visible": false, "title_keywords": [], "responsibilities": ["aml", "monitoring", "quality", "reports", "banking"], "requirements": {"degrees": [], "majors": [], "languages": [], "language_level": [], "hard_skills": ["red", "aml"], "soft_skills": ["responsible"], "languages_combined": []}, "experience_required": {"duration": ["2+ years"], "field": ["banking"]}}, {"job_id": "100003009034812", "location_code": "hk", "company": "China Construction Bank (Asia) Corporation Limited", "job_title": "e-Banking Professional (Corporate E-Channel)", "description": "Main Responsibilities\n- Manage Corporate E-Channel project development, be able to raise user requirement, monitor the progress and ensure new services/ initiatives are effectively implemented, benchmark with best market practice and excellent customer experience\n- Work closely with internal and external stakeholders on planning and execution\n- Perform regular business management\n- Communicate with Hotline and online customer services of Online Enterprise Banking, follow-up online channel related production problems\n\nRequirements\n- Degree holder in Information Technology, Business Administration, Economics, Finance or other related disciplines\n- Minimum 3-4 years experience on eBanking / Channel project management in sizable multi-national financial institutions\n- Self-motivated, result oriented, meticulous and able to work under pressure\n- Keen interest in new digital technologies and trends\n- Good communication skills with team spirit\n- Proficiency in English and Chinese (both Cantonese and Putonghua)\n- Sound knowledge of corporate banking products and operations will be an advantage", "employment_types": ["Full Time", "Permanent"], "selling_points": ["e-Banking", "Corporate E-Channel", "Customer service"], "locations": ["Kowloon Bay"], "categories": ["Banking / Finance", "Corporate Banking", "E-commerce", "Business Development"], "post_time": "2022-01-10T04:18:42Z", "salary": {"currency": null, "max": null, "min": null, "period": "monthly", "term": null}, "salary_visible": false, "title_keywords": [], "responsibilities": ["communicate with", "user requirement", "management", "monitor", "customer services", "banking", "planning"], "requirements": {"degrees": ["degree holder"], "majors": ["business administration", "finance", "economics", "information technology", "related disciplines"], "languages": ["cantonese", "putonghua", "english", "chinese"], "language_level": ["proficiency"], "hard_skills": ["project management"], "soft_skills": ["meticulous", "self-motivated", "communication skills", "team spirit", "keen", "project management", "result oriented", "work under pressure"], "languages_combined": [{"language": "cantonese", "language_level": []}, {"language": "putonghua", "language_level": []}, {"language": "english", "language_level": ["proficiency"]}, {"language": "chinese", "language_level": ["proficiency"]}]}, "experience_required": {"duration": ["minimum 3-4 years"], "field": ["project management", "financial institutions"]}}, {"job_id": "100003009039679", "location_code": "hk", "company": "Randstad Hong Kong Limited", "job_title": "Regional General Compliance", "description": "about the company\n\nOur client is a regional corporate and investment bank with strong presence in HK and other APAC region\n\nabout the team\n\nA team of 3 in Regional General Compliance Department\nWork-life balance and stable team\n\nabout the job\n\nAssist in performing general compliance duties, including policies review, conducting on/off-site monitoring, preparing compliance training etc\nAssist in enhancing regional compliance framework and updating procedures and policies to ensure compliance with latest regulations/group policies\nCollect and review overseas offices compliance reports\nCommunicate with local Compliance teams on compliance initiatives and regional projects\nProvide advice to local/overseas office on general compliance matters\n\nskills & experiences required\n\nUniversity Degree in Finance, Law, Accounting or Economics\nAt least 2 years compliance experience\nGood command in spoken and written English and Chinese\n\nTo apply online, please click on the link. Alternatively, for a confidential discussion please contact Joanne Lo on + 852 2232 3421 or email: joanne.lo@randstad.com.hk", "employment_types": ["Full Time", "Permanent"], "selling_points": [], "locations": ["Not Specified"], "categories": ["Banking / Finance", "Corporate Banking", "Others", "Junior Executive", "Professional Services", "Legal & Compliance"], "post_time": "2022-01-11T10:27:26Z", "salary": {"currency": "HKD", "max": 29999, "min": 20000, "period": "monthly", "term": null}, "salary_visible": true, "title_keywords": [], "responsibilities": ["regulations", "communicate with", "policies", "review", "compliance", "procedures", "monitoring", "ensure compliance", "teams", "provide advice", "reports", "contact"], "requirements": {"degrees": ["university degree"], "majors": ["finance", "accounting", "economics", "law"], "languages": ["english", "chinese"], "language_level": ["good command"], "hard_skills": [], "soft_skills": ["stable"], "languages_combined": [{"language": "english", "language_level": ["good command"]}, {"language": "chinese", "language_level": ["good command"]}]}, "experience_required": {"duration": ["at least 2 years"], "field": ["compliance"]}}]