[{"job_id": "100003009053978", "location_code": "hk", "company": "Hang Seng Bank Ltd", "job_title": "Director Signature/ Associate Director Signature", "description": "Retail Distribution\n\nHang Seng's Retail Distribution focuses on personal wealth management and financial services. Our one-stop wealth management initiatives are designed for both our affluent and mass integrated account customers. With more than 290 branches and automated banking centers, including around 60 Prestige Banking Centers for our high-end personal customers, we serve over half of the adult population in Hong Kong while offering an extensive range of products to our valued customers.\n\nWe are currently seeking high caliber professionals to join our department as\u00a0Director Signature/\u00a0Associate Director Signature\n\nPrincipal responsibilities\nProvide professional financial planning services to high-net-worth / top-tier Prestige Signature customers\nProvide personalized and all-rounded wealth management service for this segment of customers to build and maintain good relationships\nPromote holistic wealth management service for optimizing new business opportunities\nAssist the team head in providing coaching to Relationship Managers\nManage operational risk and observe the relevant policies / guidelines and compliance requirements\n\u00a0\u00a0\n\n\nHang Seng Bank Relationship Manager Virtual Recruitment Talk\u00a0\n\nIf you are keen to find out more about the working culture and how we nurture our Relationship Managers for their success at Hang Seng Bank, please join our Virtual Recruitment Talk\u00a0to hear the candid sharing from our Branch Networks business leaders and also our RMs. You will also find out our progressive career ladder for RMs from entry-level RM Trainee to Signature and Executive RM.\n\nDate:\u00a026 January 2022 (Wed)\n\nTime: 6:00 - 7:00 PM\n\nLocation:\u00a0Virtual Session \u2013 Dial in details will be provided upon registration\n\nRegister your place before 26 Jan 2022 by clicking\u00a0https://hsbc.zoom.us/webinar/register/WN_KABEhwC-RJqmSR07NkIS2g\u00a0\u00a0\n\nRequirements\nUniversity degree in a related discipline OR professional qualifications such as CFA, CFP or CFMP is preferred\nPasses in the Insurance Intermediaries Qualifying Examinations / Hong Kong Securities Institute Licensing Examinations\nFulfilment of the competency requirements to carry out relevant regulated activities as defined under the Securities and Futures Ordinance\nMinimum of five years' experience in selling investment, insurance and banking products\nStrong sales and customer orientation, with good communication and interpersonal skills\nStrong self-motivation and ability to work under pressure\nProficiency in both English and Chinese, with proficiency in Putonghua an advantage\nHigh level of customer centricity mindset and ability to manage complex interactions effectively\nShown strong situation awareness, strong desire to learn and able to work in Agile environment\nBe curious and with passion to think deeply and rationally\n\nIf you would like to explore other opportunities at Hang Seng Hong Kong, please visit\u00a0www.hangseng.com/careers/\u00a0for details.\n\nThe health and safety of our employees and candidates is very important to us. Due to the current situation related to the Novel Coronavirus (2019-nCoV), we\u2019re leveraging our digital capabilities to ensure we can continue to recruit top talent at the HSBC Group.\u00a0 As your application progresses, you may be asked to use one of our digital tools to help you through your recruitment journey.\u00a0 If so, one of our\u00a0 Resourcing colleagues will explain how our video-interviewing technology will be used throughout the recruitment process and will be on hand to answer any questions you might have.\nAll information provided by applicants will be used only for recruitment purposes and will be used strictly in accordance with the Bank's personal data policies, a copy of which may be obtained by the applicant upon request. Unless otherwise instructed in writing by the applicant concerned, applicants may be considered for other suitable positions within the Bank and its related companies. The personal data of unsuccessful job applicants may be retained for a maximum of two years from the date when the job application is rejected and such data may be retained for a longer period if there is a subsisting reason that obliges the Bank to do so, after which the personal data will be destroyed.", "employment_types": ["Full Time", "Permanent"], "selling_points": [], "locations": ["Not Specified"], "categories": ["Banking / Finance", "Credit Analysis / Approval", "Retail Banking", "Credit Collection"], "post_time": "2022-01-17T07:54:17Z", "salary": {"currency": null, "max": null, "min": null, "period": "monthly", "term": null}, "salary_visible": false, "title_keywords": ["associate director", "director"], "responsibilities": ["management", "guidelines", "policies", "business opportunities", "compliance", "maintain", "recruitment", "planning"], "requirements": {"degrees": ["university degree"], "majors": [], "languages": ["putonghua", "english", "chinese"], "language_level": ["advantage", "proficiency"], "hard_skills": ["agile", "professional qualifications", "cfa", "securities and futures ordinance", "reason"], "soft_skills": ["agile", "communication and interpersonal skills", "self-motivation", "novel", "work under pressure"], "languages_combined": [{"language": "putonghua", "language_level": ["proficiency", "advantage"]}, {"language": "english", "language_level": ["proficiency", "proficiency", "advantage"]}, {"language": "chinese", "language_level": ["proficiency", "proficiency", "advantage"]}]}, "experience_required": {"duration": ["minimum of five years"], "field": ["insurance", "investment", "banking"]}}, {"job_id": "100003008929495", "location_code": "hk", "company": "\u9ad8\u67cf(\u4e9e\u6d32)\u8cc7\u7522\u7ba1\u7406\u6709\u9650\u516c\u53f8", "job_title": "\u8cec\u52d9\u5354\u5546\u4e3b\u4efb \u2013 \u9280\u884c/\u96fb\u8a0a\u670d\u52d9", "description": "\u8077\u8cac\u00a0\n\n\u904b\u7528\u5408\u9069\u5354\u5546\u6280\u5de7\uff0c\u8ddf\u9032\u9280\u884c/\u96fb\u8a0a\u5ba2\u6236\u903e\u671f\u8cec\u9805\u6848\u4ef6\n\u89e3\u7b54\u903e\u671f\u5e33\u9805\u7528\u6236\u6709\u95dc\u67e5\u8a62\u53ca\u5546\u8a0e\u9084\u6b3e\u65b9\u6848\n\n\u00a0\u8981\u6c42\n\n\u4e2d\u4e94\u6216\u4ee5\u4e0a\u5b78\u6b77\uff0c\u00a0\u5de5\u4f5c\u7d93\u9a57\u53ca\u884c\u696d\u4e0d\u9650\n\u826f\u597d\u6e9d\u901a\u6280\u5de7\uff0c\u9748\u6d3b\u4e3b\u52d5\uff0c\u7a4d\u6975\u9032\u53d6\n\u5177\u92b7\u552e/\u5ba2\u6236\u670d\u52d9\u7d93\u9a57\uff0c\u53ef\u512a\u5148\u8003\u616e\n\n\u00a0\u85aa\u91d1\u798f\u5229\n\n\u56fa\u5b9a\u5e95\u85aa+\u52e4\u5de5\u6d25\u8cbc+\u696d\u7e3e\u4f63\u91d1+\u5718\u968a\u734e\u91d1\n\u512a\u8d8a\u53ca\u8212\u9069\u5de5\u4f5c\u74b0\u5883\n\u91ab\u7642\u798f\u5229\u3001\u9280\u884c\u5047\u671f\u3001\u6709\u85aa\u5e74\u5047\u53ca\u8d85\u6642\u5de5\u4f5c\u6d25\u8cbc\n\u826f\u597d\u6649\u5347\u6a5f\u6703\u53ca\u63d0\u4f9b\u5b8c\u5584\u5165\u8077\u5728\u8077\u57f9\u8a13\n\n\u6211\u5011\u63d0\u4f9b:\n\n12\u5929\u6709\u85aa\u5e74\u5047\n\u91ab\u7642\u6d25\u8cbc\n\u7259\u79d1\u6d25\u8cbc\n\u5e74\u7d42\u734e\u91d1\n\u5176\u4ed6\u54e1\u5de5\u95dc\u61f7\u8914\u5229\uff0c\u4f8b\u5982\uff1a\u7bc0\u65e5\u6d3b\u52d5\u3001\u6fc0\u52f5\u734e\u91d1\u7b49\u2026\n\u6b61\u8fce\u65b0\u79fb\u6c11\u00a0/\u00a0\u8f49\u8077\u00a0/\u00a0\u8f49\u696d\u4eba\u58eb\u52a0\u5165\n\n\n\u6709\u610f\u8005\u8acb\u5c07\u500b\u4eba\u5c65\u6b77\u3001\u5de5\u4f5c\u7d93\u9a57\u3001\u8981\u6c42\u85aa\u91d1\u53ca\u53ef\u5230\u8077\u65e5\u671f\u50b3\u771f\u81f381616498\u4eba\u529b\u8cc7\u6e90\u90e8\u6536\u6216\u6309\"Apply Now\"\u3002\u6709\u610f\u8005\u4ea6\u53ef\u81f4\u96fb\u62db\u52df\u71b1\u7dda8200 2738\u6216Whatsapp 5116 9625 \u67e5\u8a62\u3002\n\n\u6b32\u4e86\u89e3\u672c\u516c\u53f8\u8cc7\u6599\u53ef\u700f\u7060\u7db2\u5740www.goldpartners.com.hk\n\n\u6240\u6709\u8077\u4f4d\u7533\u8acb\u904e\u7a0b\u4e2d\u6240\u6536\u96c6\u7684\u500b\u4eba\u8cc7\u6599\u53ea\u6703\u7528\u4f5c\u62db\u8058\u7528\u9014\u3002\u00a0\u4e0d\u5408\u9069\u7684\u7533\u8acb\u8005\u7684\u500b\u4eba\u8cc7\u6599\u5c07\u88ab\u8f49\u4ecb\u81f3\u96c6\u5718\u5c6c\u4e0b\u6a5f\u69cb\u76f8\u95dc\u8077\u4f4d\u7a7a\u7f3a\uff0c\u4e26\u4fdd\u7559\u4e0d\u591a\u65bc1\u5e74\u4f5c\u65e5\u5f8c\u62db\u8058\u7528\u9014\u3002", "employment_types": ["Full Time", "Permanent"], "selling_points": [], "locations": ["Kowloon Bay"], "categories": ["Sales, CS & Business Devpt", "Call Centre", "Banking / Finance", "Credit Collection", "Customer Service - Supervisor / Officer"], "post_time": "2022-01-15T03:51:06Z", "salary": {"currency": null, "max": null, "min": null, "period": "monthly", "term": null}, "salary_visible": false, "title_keywords": [], "responsibilities": [], "requirements": {"degrees": [], "majors": [], "languages": [], "language_level": [], "hard_skills": [], "soft_skills": [], "languages_combined": []}, "experience_required": {"duration": [], "field": []}}, {"job_id": "100003009053354", "location_code": "hk", "company": "Hang Seng Bank Ltd", "job_title": "Executive Customer Relationship Manager", "description": "Retail Distribution\n\nHang Seng's Retail Distribution focuses on personal wealth management and financial services. Our one-stop wealth management initiatives are designed for both our affluent and mass integrated account customers. With more than 170 branches and automated banking centres, including over 50 Prestige Banking Centres for our high-end personal customers, we serve over half of the adult population, offering an extensive range of products.\n\nWe are currently seeking a high caliber professional to join our team as\u00a0Executive Customer Relationship Manager.\n\nPrincipal responsibilities\n\nProvide financial planning services to high-net-worth customers\nProvide personalised service for this segment of customers to build and maintain good relationships\nPromote investment, insurance and banking products for optimising new business opportunities\nAssist the team head in providing coaching to Relationship Managers\nManage operational risk and observe the relevant policies /guidelines and compliance requirements\n\nHang Seng Bank Relationship Manager Virtual Recruitment Talk\u00a0\n\nIf you are keen to find out more about the working culture and how we nurture our Relationship Managers for their success at Hang Seng Bank, please join our Virtual Recruitment Talk\u00a0to hear the candid sharing from our Branch Networks business leaders and also our RMs. You will also find out our progressive career ladder for RMs from entry-level RM Trainee to Signature and Executive RM.\n\nDate:\u00a026 January 2022 (Wed)\n\nTime: 6:00 - 7:00 PM\n\nLocation:\u00a0Virtual Session \u2013 Dial in details will be provided upon registration\n\nRegister your place before 26 Jan 2022 by clicking\u00a0https://hsbc.zoom.us/webinar/register/WN_KABEhwC-RJqmSR07NkIS2g\u00a0\u00a0\n\n\n\nRequirements\n\nUniversity degree in a related discipline OR professional qualifications such as CFA, CFP or CFMP is preferred\nPasses in the Insurance Intermediaries Qualifying Examinations / Hong Kong Securities Institute Licensing Examinations\nFulfilment of the competency requirements to carry out relevant regulated activities as defined under the Securities and Futures Ordinance\nMinimum of five years' experience in selling investment, insurance and banking products\nStrong sales and customer orientation, with good communication and interpersonal skills\nStrong self-motivation and ability to work under pressure\nProficiency in both English and Chinese, with proficiency in Putonghua an advantage\nHigh level of customer centricity mindset with dedication to deliver exceptional quality services for customers\nIf you would like to explore other opportunities at Hang Seng Hong Kong, please visit\u00a0www.hangseng.com/careers/\u00a0for details.\n\n\n\n\nThe health and safety of our employees and candidates is very important to us. Due to the current situation related to the Novel Coronavirus (2019-nCoV), we\u2019re leveraging our digital capabilities to ensure we can continue to recruit top talent at the HSBC Group.\u00a0 As your application progresses, you may be asked to use one of our digital tools to help you through your recruitment journey.\u00a0 If so, one of our\u00a0 Resourcing colleagues will explain how our video-interviewing technology will be used throughout the recruitment process and will be on hand to answer any questions you might have.\n\n\n\nAll information provided by applicants will be used only for recruitment purposes and will be used strictly in accordance with the Bank's personal data policies, a copy of which may be obtained by the applicant upon request. Unless otherwise instructed in writing by the applicant concerned, applicants may be considered for other suitable positions within the Bank and its related companies. The personal data of unsuccessful job applicants may be retained for a maximum of two years from the date when the job application is rejected and such data may be retained for a longer period if there is a subsisting reason that obliges the Bank to do so, after which the personal data will be destroyed.", "employment_types": ["Full Time", "Permanent"], "selling_points": [], "locations": ["Not Specified"], "categories": ["Banking / Finance", "Credit Analysis / Approval", "Retail Banking", "Credit Collection"], "post_time": "2022-01-17T06:49:50Z", "salary": {"currency": null, "max": null, "min": null, "period": "monthly", "term": null}, "salary_visible": false, "title_keywords": ["executive", "relationship manager"], "responsibilities": ["guidelines", "policies", "business opportunities", "compliance", "maintain", "recruitment", "banking", "insurance", "planning"], "requirements": {"degrees": ["university degree"], "majors": [], "languages": ["putonghua", "english", "chinese"], "language_level": ["advantage", "proficiency"], "hard_skills": ["cfa", "reason", "securities and futures ordinance", "professional qualifications"], "soft_skills": ["novel", "communication and interpersonal skills", "self-motivation", "work under pressure"], "languages_combined": [{"language": "putonghua", "language_level": ["proficiency", "advantage"]}, {"language": "english", "language_level": ["proficiency", "proficiency", "advantage"]}, {"language": "chinese", "language_level": ["proficiency", "proficiency", "advantage"]}]}, "experience_required": {"duration": ["minimum of five years"], "field": ["insurance", "investment", "banking"]}}, {"job_id": "100003009049527", "location_code": "hk", "company": "Mitsubishi HC Capital (Hong Kong) Limited", "job_title": "Credit Control Officer (Collection Department)", "description": "Responsibilities:\n\nTo perform dunning calls and follow-up actions on overdue accounts\nTo liaise with account manager to follow up with customer enquiries\nTo daily report progress of the collection to the manager\nTo provide general administration and clerical support to the team\nTo provide monthly progress report\nTo perform other ad-hoc assignments as required\n\nRequirements:\n\nHKDSE or above\nAt least 3 years working experience in collection field; Candidate with less experience will be considered as Assistant Credit Control Officer\nGood command of spoken and written in Chinese and English\nAble to work independently and under pressure\nMature and pleasant personality with good communication skill\nFresh graduate is also welcome\n\nWe offer competitive remuneration package including 5-day work, double pay, discretionary bonus and medical & group life insurance to the right candidate. Interested parties, please send full resume with present and expected salary, as well as availability to Talent Management & General Affairs Department, Mitsubishi HC Capital (Hong Kong) Limited by clicking \u201cAPPLY NOW\u201d.\n\nPersonal data collected will be used for recruitment purpose only. Applicants who do not hear from us within 8 weeks may consider their applications unsuccessful and their data will be destroyed within 12 months of receipt.\n\nWe are an Equal Opportunity Employer provides equal employment opportunities to all qualified applicants.", "employment_types": ["Full Time", "Permanent"], "selling_points": [], "locations": ["Mong Kok"], "categories": ["Banking / Finance", "Financial Services", "Credit Collection"], "post_time": "2022-01-15T03:50:30Z", "salary": {"currency": null, "max": null, "min": null, "period": "monthly", "term": null}, "salary_visible": false, "title_keywords": ["credit control officer"], "responsibilities": ["daily report", "customer enquiries", "ad-hoc assignments", "clerical support", "liaise with", "report", "administration"], "requirements": {"degrees": ["hkdse", "fresh graduate"], "majors": [], "languages": ["english", "chinese"], "language_level": ["good command"], "hard_skills": [], "soft_skills": ["work independently", "under pressure", "communication skill", "mature", "pleasant"], "languages_combined": [{"language": "english", "language_level": ["good command"]}, {"language": "chinese", "language_level": ["good command"]}]}, "experience_required": {"duration": ["at least 3 years"], "field": []}}, {"job_id": "100003009044984", "location_code": "hk", "company": "Hang Seng Bank Ltd", "job_title": "Assistant Collections Officer (Unsecured Collections)", "description": "WPB\u00a0Chief Operating Office \u2013\u00a0Fraud and Credit Control Services\n\nWe are currently seeking a high caliber professional to join our department as\u00a0Assistant Collections Officer.\n\nPrincipal responsibilities\n\nPerform dunning calls to arrange delinquent account balances and minimize credit losses.\nNegotiate with customers of delinquent accounts for debt repayment\nAssist in the process of debt collection activities\u00a0\u00a0\nAssist in compiling MIS reports and performing User Acceptance Test on system enhancement and development\nProvide administrative support to debt collection operations\n\nRequirements\n\nCompleted HKCEE / HKDSE with at least five subjects at Grade E / Level 2 / \"Attained\" or above including Chinese, English and Mathematics\nStrong self-motivation, with ability to work independently and under pressure\nGood interpersonal, negotiation and problem solving skills\nAbility to be resilient in face of difficult situations\nGood knowledge of application software such as MS Word, Excel and Access\nProficiency in both English and Chinese, with fluency in Putonghua an advantage\nCandidates with prior telemarketing or call centre exposure are welcome to apply\nGreat sense of ownership and servicing mindset to ensure efficient and effective customer service processes\n\nIf you would like to explore other opportunities at Hang Seng Hong Kong, please visit\u00a0www.hangseng.com/careers/\u00a0for details.\n\nThe health and safety of our employees and candidates is very important to us. Due to the current situation related to the Novel Coronavirus (2019-nCoV), we\u2019re leveraging our digital capabilities to ensure we can continue to recruit top talent at the HSBC Group. \u00a0As your application progresses, you may be asked to use one of our digital tools to help you through your recruitment journey.\u00a0 If so, one of our Resourcing colleagues will explain how our video-interviewing technology will be used throughout the recruitment process and will be on hand to answer any questions you might have.\n\nAll information provided by applicants will be used only for recruitment purposes and will be used strictly in accordance with the Bank's personal data policies, a copy of which may be obtained by the applicant upon request. Unless otherwise instructed in writing by the applicant concerned, applicants may be considered for other suitable positions within the Bank and its related companies. The personal data of unsuccessful job applicants may be retained for a maximum of two years from the date when the job application is rejected and such data may be retained for a longer period if there is a subsisting reason that obliges the Bank to do so, after which the personal data will be destroyed.", "employment_types": ["Full Time", "Permanent"], "selling_points": [], "locations": ["Not Specified"], "categories": ["Banking / Finance", "Retail Banking", "Credit Collection"], "post_time": "2022-01-13T06:48:55Z", "salary": {"currency": null, "max": null, "min": null, "period": "monthly", "term": null}, "salary_visible": false, "title_keywords": ["officer", "assistant"], "responsibilities": ["provide administrative support", "debt collection", "reports", "operations"], "requirements": {"degrees": ["hkdse"], "majors": ["mathematics"], "languages": ["putonghua", "english", "chinese"], "language_level": ["fluency", "advantage", "proficiency"], "hard_skills": ["excel", "problem solving skills", "reason", "ms word"], "soft_skills": ["efficient", "novel", "work independently", "under pressure", "negotiation", "self-motivation", "customer service", "problem solving skills", "interpersonal"], "languages_combined": [{"language": "putonghua", "language_level": ["fluency", "advantage"]}, {"language": "english", "language_level": ["proficiency", "fluency", "advantage"]}, {"language": "chinese", "language_level": ["proficiency", "fluency", "advantage"]}]}, "experience_required": {"duration": [], "field": []}}, {"job_id": "100003009045561", "location_code": "hk", "company": "Hang Seng Bank Ltd", "job_title": "Assistant Collections Manager (Unsecured Collections)", "description": "WPB Chief Operating Office\u00a0-\u00a0Fraud and Credit Control Services\n\n\nWe are currently seeking a high caliber professional to join our department as\u00a0Assistant Collections Manager (Unsecured Collections).\n\n\n\nPrincipal responsibilities\n\nLead a team of staff to manage delinquent accounts of the retail unsecured loan portfolios; to perform account maintenance and prepare statistical reports for management review.\nHandle restructured application approval and monitor the turnaround time of application process.\nTake legal proceedings against debtors by instructing external legal firms; represent the Bank to attend court hearing and liaison with Official Receiver\u2019s Office /Outside Trustee on bankruptcy related matters.\nFollow up and manage deceased, bankruptcy accounts and other accounts with court orders.\nConduct risk account review and propose mitigation actions through regular or ad hoc review.\nHandle customer complaints and perform necessary investigation.\nCarry out ad hoc tasks and conduct UAT for program / system enhancement.\nEnsure adherence to legal and Group regulatory requirements, operating procedures and practices.\nRequirements\nUniversity degree in a related discipline OR other relevant qualifications\nMinimum 2 years' experience in debt recovery / unsecured lending and mortgage business with exposure to credit control / administration\nStrong self-motivation, good interpersonal, communication, credit analytic and supervisory skills\nGood knowledge of PC application software such as MS Word, Excel and Access\nProficiency in both English and Chinese, fluency in Putonghua and advantage\nGreat sense of ownership and servicing mindset to ensure efficient and effective customer service processes\n\nIf you would like to explore other opportunities at Hang Seng Hong Kong, please visit\u00a0www.hangseng.com/careers/\u00a0for details.\n\nThe health and safety of our employees and candidates is very important to us. Due to the current situation related to the Novel Coronavirus (2019-nCoV), we\u2019re leveraging our digital capabilities to ensure we can continue to recruit top talent at the HSBC Group. \u00a0As your application progresses, you may be asked to use one of our digital tools to help you through your recruitment journey.\u00a0 If so, one of our Resourcing colleagues will explain how our video-interviewing technology will be used throughout the recruitment process and will be on hand to answer any questions you might have.\u00a0\n\nAll information provided by applicants will be used only for recruitment purposes and will be used strictly in accordance with the Bank's personal data policies, a copy of which may be obtained by the applicant upon request. Unless otherwise instructed in writing by the applicant concerned, applicants may be considered for other suitable positions within the Bank and its related companies. The personal data of unsuccessful job applicants may be retained for a maximum of two years from the date when the job application is rejected and such data may be retained for a longer period if there is a subsisting reason that obliges the Bank to do so, after which the personal data will be destroyed.", "employment_types": ["Full Time", "Permanent"], "selling_points": [], "locations": ["Not Specified"], "categories": ["Admin & HR", "Administration / Operation Manager", "Banking / Finance", "Financial Services", "Credit Collection"], "post_time": "2022-01-13T08:04:57Z", "salary": {"currency": null, "max": null, "min": null, "period": "monthly", "term": null}, "salary_visible": false, "title_keywords": ["manager", "assistant"], "responsibilities": ["ad hoc", "uat", "customer complaints", "regulatory requirements", "ensure adherence", "review", "monitor", "ad hoc tasks", "investigation", "procedures", "lead a team", "reports", "account maintenance", "management review"], "requirements": {"degrees": ["university degree"], "majors": [], "languages": ["putonghua", "english", "chinese"], "language_level": ["fluency", "advantage", "proficiency"], "hard_skills": ["pc", "reason", "excel", "ms word"], "soft_skills": ["efficient", "communication", "self-motivation", "customer service", "novel", "interpersonal"], "languages_combined": [{"language": "putonghua", "language_level": ["fluency", "advantage"]}, {"language": "english", "language_level": ["proficiency", "fluency"]}, {"language": "chinese", "language_level": ["proficiency", "fluency"]}]}, "experience_required": {"duration": ["minimum 2 years"], "field": ["business", "administration"]}}, {"job_id": "100003009044993", "location_code": "hk", "company": "Hang Seng Bank Ltd", "job_title": "Assistant Collections Manager (Legal and Monitoring Team)", "description": "WPB Chief Operating Office\u00a0-\u00a0Fraud and Credit Control Services\n\nWe are currently seeking a high caliber professional to join our department as\u00a0Assistant Collections Manager (Legal and Monitoring Team).\n\n\n\nPrincipal responsibilities:\n\nLead a team of staff to manage delinquent accounts of the retail unsecured loan portfolios; to perform account\nmaintenance and provide administration support\nTake legal proceedings against debtors by instructing external legal firms; representing the Bank to attend court hearing and liaison with Official Receiver\u2019s Office /Outside Trustee on bankruptcy related matters\nFollow up and manage deceased, bankruptcy accounts and other accounts with court orders\nConduct risk account review and propose mitigation actions through regular or ad hoc review\nAssist in the process of Supplier Risk Management and prepare statiscal repots for management review\nHandle customer complaints and perform necessary investigation\n\nRequirements:\n\nUniversity degree in a related discipline OR other relevant qualifications\nMinimum 2 years' experience in debt recovery / unsecured lending and mortgage business with exposure to credit control / administration\nStrong self-motivation, good interpersonal, communication, credit analytic and supervisory skills\nGood knowledge of PC application software such as MS Word, Excel and Access\nProficiency in both English and Chinese, fluency in Putonghua and advantage\nGreat sense of ownership and servicing mindset to ensure efficient and effective customer service processes\nIf you would like to explore other opportunities at Hang Seng Hong Kong, please visit\u00a0www.hangseng.com/careers/\u00a0for details.\n\nThe health and safety of our employees and candidates is very important to us. Due to the current situation related to the Novel Coronavirus (2019-nCoV), we\u2019re leveraging our digital capabilities to ensure we can continue to recruit top talent at the HSBC Group. \u00a0As your application progresses, you may be asked to use one of our digital tools to help you through your recruitment journey.\u00a0 If so, one of our Resourcing colleagues will explain how our video-interviewing technology will be used throughout the recruitment process and will be on hand to answer any questions you might have.\u00a0\nAll information provided by applicants will be used only for recruitment purposes and will be used strictly in accordance with the Bank's personal data policies, a copy of which may be obtained by the applicant upon request. Unless otherwise instructed in writing by the applicant concerned, applicants may be considered for other suitable positions within the Bank and its related companies. The personal data of unsuccessful job applicants may be retained for a maximum of two years from the date when the job application is rejected and such data may be retained for a longer period if there is a subsisting reason that obliges the Bank to do so, after which the personal data will be destroyed.", "employment_types": ["Full Time", "Permanent"], "selling_points": [], "locations": ["Not Specified"], "categories": ["Banking / Finance", "Retail Banking", "Financial Services", "Credit Collection"], "post_time": "2022-01-13T06:50:14Z", "salary": {"currency": null, "max": null, "min": null, "period": "monthly", "term": null}, "salary_visible": false, "title_keywords": ["manager", "assistant"], "responsibilities": ["management", "ad hoc", "maintenance", "customer complaints", "review", "investigation", "lead a team", "management review", "administration"], "requirements": {"degrees": ["university degree"], "majors": [], "languages": ["putonghua", "english", "chinese"], "language_level": ["fluency", "advantage", "proficiency"], "hard_skills": ["pc", "reason", "excel", "ms word"], "soft_skills": ["efficient", "communication", "self-motivation", "customer service", "novel", "interpersonal"], "languages_combined": [{"language": "putonghua", "language_level": ["fluency", "advantage"]}, {"language": "english", "language_level": ["proficiency", "fluency"]}, {"language": "chinese", "language_level": ["proficiency", "fluency"]}]}, "experience_required": {"duration": ["minimum 2 years"], "field": ["business", "administration"]}}, {"job_id": "100003009044861", "location_code": "hk", "company": "Hang Seng Bank Ltd", "job_title": "Assistant Collections Manager (OPS Supports Team)", "description": "WPB Chief Operating Office\u00a0-\u00a0Fraud and Credit Control Services\n\n\nWe are currently seeking a high caliber professional to join our department as\u00a0Assistant Collections Manager (OPS Supports Team).\n\n\n\nPrincipal responsibilities:\n\nParticipate in the project planning, testing and system conversion, enhancement and development\nPropose and implement quality enhancement and control strengthening initiatives in response to the review findings and business needs\u00a0\nPrepare statistical and ad-hoc managment information reports for management review\nProvide prompt responses and recommendations on collection strategies and workflow to adapt to the fast and changing market\nLiaise and communicate with counterparts in both internal and external to keep abreast of new and advance system requirements\n\nRequirements:\n\nUniversity degree in a related discipline OR other relevant qualifications\nMinimum 2 years' experience in debt recovery / unsecured lending and mortgage business, with exposure to credit control / administration\nKnowledge of relevant credit system of personal finance such as Credit Bureau System, Credit Decision System etc an advantage\nStrong self-motivation, good interpersonal, communication, credit analytic and supervisory skills\nGood knowledge of application software (Skills in SAS, MS Word, Excel, PowerPoint and Access)\nGreat sense of ownership and servicing mindset to ensure efficient and effective customer service processes\nProficiency in both English and Chinese, fluency in Putonghua and advantage\n\nIf you would like to explore other opportunities at Hang Seng Hong Kong, please visit\u00a0www.hangseng.com/careers/\u00a0for details.\n\nThe health and safety of our employees and candidates is very important to us. Due to the current situation related to the Novel Coronavirus (2019-nCoV), we\u2019re leveraging our digital capabilities to ensure we can continue to recruit top talent at the HSBC Group. \u00a0As your application progresses, you may be asked to use one of our digital tools to help you through your recruitment journey.\u00a0 If so, one of our Resourcing colleagues will explain how our video-interviewing technology will be used throughout the recruitment process and will be on hand to answer any questions you might have.\u00a0\n\nAll information provided by applicants will be used only for recruitment purposes and will be used strictly in accordance with the Bank's personal data policies, a copy of which may be obtained by the applicant upon request. Unless otherwise instructed in writing by the applicant concerned, applicants may be considered for other suitable positions within the Bank and its related companies. The personal data of unsuccessful job applicants may be retained for a maximum of two years from the date when the job application is rejected and such data may be retained for a longer period if there is a subsisting reason that obliges the Bank to do so, after which the personal data will be destroyed.\n", "employment_types": ["Full Time", "Permanent"], "selling_points": [], "locations": ["Not Specified"], "categories": ["Banking / Finance", "Retail Banking", "Financial Services", "Credit Collection"], "post_time": "2022-01-13T06:28:19Z", "salary": {"currency": null, "max": null, "min": null, "period": "monthly", "term": null}, "salary_visible": false, "title_keywords": ["manager", "assistant"], "responsibilities": ["ad-hoc", "liaise", "project planning", "control", "communicate with", "review", "quality", "testing", "reports", "management review"], "requirements": {"degrees": ["university degree"], "majors": [], "languages": ["putonghua", "english", "chinese"], "language_level": ["fluency", "advantage", "proficiency"], "hard_skills": ["excel", "sas", "powerpoint", "reason", "ms word"], "soft_skills": ["efficient", "communication", "self-motivation", "customer service", "novel", "interpersonal"], "languages_combined": [{"language": "putonghua", "language_level": ["fluency", "advantage"]}, {"language": "english", "language_level": ["proficiency", "fluency"]}, {"language": "chinese", "language_level": ["proficiency", "fluency"]}]}, "experience_required": {"duration": ["minimum 2 years"], "field": ["business", "administration"]}}, {"job_id": "100003009045548", "location_code": "hk", "company": "Hang Seng Bank Ltd", "job_title": "Manager, Collections OPS", "description": "WPB Chief Operating Office \u2013 Fraud and Credit Control Services\n\nWe are currently seeking a high caliber professional to join our department as\u00a0Manager, Collections OPS.\n\n\nPrinciple responsibilities\n\nLead a team of staff to manage all activities related to project management, system development and implementation.\nPlan, direct and manage the development and production of quality MIs.\nProvide prompt responses and recommendations on credit policies and collections strategy to adapt to the fast and changing market.\nLead and drive new initiatives / projects including process streamlining, system enhancement and service migration to improve operational efficiencies and copy with business needs.\nRequirements\nUniversity degree in Business or a related discipline OR other relevant qualifications/experience\nMinimum 5 years' relevant experience in project management, analytics, debt collections or credit risk.\nSound knowledge of retail banking, operational risk management, financial crime compliance or other related areas an advantage\nGood knowledge of application software (Skills in SAS, MS Word, Excel, Powerpoint and Access)\nStrong business acumen with good problem solving, communication and analytical skills\nGreat sense of ownership and servicing mindset to ensure efficient and effective customer service processes\nProficiency in both English and Chinese, fluency in Putonghua an advantage\n\u00a0\n\nIf you would like to explore other opportunities at Hang Seng Hong Kong, please visit\u00a0www.hangseng.com/careers/\u00a0for details.\n\nThe health and safety of our employees and candidates is very important to us. Due to the current situation related to the Novel Coronavirus (2019-nCoV), we\u2019re leveraging our digital capabilities to ensure we can continue to recruit top talent at the HSBC Group. \u00a0As your application progresses, you may be asked to use one of our digital tools to help you through your recruitment journey. \u00a0If so, one of our Resourcing colleagues will explain how our video-interviewing technology will be used throughout the recruitment process and will be on hand to answer any questions you might have.\n\nAll information provided by applicants will be used only for recruitment purposes and will be used strictly in accordance with the Bank's personal data policies, a copy of which may be obtained by the applicant upon request. Unless otherwise instructed in writing by the applicant concerned, applicants may be considered for other suitable positions within the Bank and its related companies. The personal data of unsuccessful job applicants may be retained for a maximum of two years from the date when the job application is rejected and such data may be retained for a longer period if there is a subsisting reason that obliges the Bank to do so, after which the personal data will be destroyed.", "employment_types": ["Full Time", "Permanent"], "selling_points": [], "locations": ["Not Specified"], "categories": ["Banking / Finance", "Credit Analysis / Approval", "Retail Banking", "Credit Collection"], "post_time": "2022-01-13T08:03:46Z", "salary": {"currency": null, "max": null, "min": null, "period": "monthly", "term": null}, "salary_visible": false, "title_keywords": ["manager"], "responsibilities": ["policies", "quality", "implementation", "lead a team", "project management", "plan", "migration"], "requirements": {"degrees": ["university degree"], "majors": ["business"], "languages": ["putonghua", "english", "chinese"], "language_level": ["fluency", "advantage", "proficiency"], "hard_skills": ["excel", "sas", "powerpoint", "acumen", "problem solving", "project management", "analytical skills", "reason", "ms word"], "soft_skills": ["efficient", "analytical skills", "communication", "project management", "problem solving", "customer service", "business acumen", "novel"], "languages_combined": [{"language": "putonghua", "language_level": ["fluency"]}, {"language": "english", "language_level": ["proficiency", "fluency", "advantage"]}, {"language": "chinese", "language_level": ["proficiency", "fluency", "advantage"]}]}, "experience_required": {"duration": ["minimum 5 years"], "field": ["related", "project management", "business", "relevant experience", "credit risk"]}}, {"job_id": "100003009049038", "location_code": "hk", "company": "Industrial and Commercial", "job_title": "Manager to Assistant Vice President, Workout and Recovery", "description": "Job Responsibilities\nManage and monitor problem corporate loans portfolio and formulate action plan to maximize financial recovery\nEnsure appropriate and updated risk rating is provided for non-performing loans\nAdvise and coordinate on collection/litigation/bankruptcy cases\nNegotiate with customers and manage foreclose actions\nCompile reports on special assets\nSome travel to Mainland China may be required\nJob Requirements\nUniversity graduate\nMinimum 8 years banking experience, at least 5 years of experience in commercial lending, credit or debt recovery function\nGood knowledge of banking products and services and banking regulations\nGood communication and negotiation skills\nGood command of Chinese and English with knowledge of Putonghua\nLess experienced candidates will be considered for Manager/Senior Manager position", "employment_types": ["Full Time"], "selling_points": [], "locations": ["Ngau Tau Kok"], "categories": ["Banking / Finance", "Credit Collection"], "post_time": "2022-01-14T07:57:38Z", "salary": {"currency": null, "max": null, "min": null, "period": "monthly", "term": null}, "salary_visible": false, "title_keywords": ["manager", "assistant vice president"], "responsibilities": ["coordinate", "monitor", "plan", "compile reports"], "requirements": {"degrees": ["university graduate"], "majors": [], "languages": ["putonghua", "english", "chinese"], "language_level": ["good command"], "hard_skills": [], "soft_skills": ["communication", "negotiation skills"], "languages_combined": [{"language": "putonghua", "language_level": ["good command"]}, {"language": "english", "language_level": ["good command"]}, {"language": "chinese", "language_level": ["good command"]}]}, "experience_required": {"duration": ["minimum 8 years", "at least 5 years"], "field": ["commercial", "banking experience"]}}, {"job_id": "100003009047550", "location_code": "hk", "company": "OCBC Wing Hang Bank Limited", "job_title": "Manager/ Senior Manager, Planning & Operations, Branch Credit", "description": "Responsibilities\n\nTo lead the team and project workgroup to implement the credit planning and achieve operational efficiency.\nMaintain close collaboration with different stakeholders in the credit process to drive and maintain an optimized strategic network planning in order to ensure best banking experience and meeting customer\u2019s need\nTo lead a workforce to provide a wide spectrum of support to Retail Banking Group to meet customer needs, improve client engagement and maximize operational efficiency\nDevelop and enhance relevant tools to streamline workflow and to identify and mitigate risk\nRequirements\n\nUniversity degree in Finance and Accounting, Economics, Banking, Business Management and related discipline.\nProfessional qualification or higher educational level is an advantage.\nMinimum 7 years of relevant experience with good knowledge of retail or SME business an advantage\nStrong leadership and management skills with relevant experience in managing a team or workgroup in a hands-on manner\nStrong interpersonal, analytical and communication skills with customer concentricity mindset\nProficient in spoken and written Chinese and English", "employment_types": ["Full Time", "Permanent"], "selling_points": ["University graduate", "Experienced in retail credit", "Good knowledge in retail/ SME business"], "locations": ["Central"], "categories": ["Banking / Finance", "Retail Banking", "Credit Collection"], "post_time": "2022-01-14T03:26:52Z", "salary": {"currency": null, "max": null, "min": null, "period": "monthly", "term": null}, "salary_visible": false, "title_keywords": ["senior manager", "operations", "manager"], "responsibilities": ["develop", "maintain", "banking", "planning"], "requirements": {"degrees": ["university degree"], "majors": ["business", "finance", "accounting", "economics"], "languages": ["english", "chinese"], "language_level": ["proficient"], "hard_skills": ["business management"], "soft_skills": ["communication skills", "hands-on", "leadership", "interpersonal"], "languages_combined": [{"language": "english", "language_level": ["proficient"]}, {"language": "chinese", "language_level": ["proficient"]}]}, "experience_required": {"duration": ["minimum 7 years"], "field": ["management", "sme business", "relevant experience", "managing a team", "retail"]}}, {"job_id": "100003009048202", "location_code": "hk", "company": "Chope Group Limited", "job_title": "Finance Executive (AR)", "description": "At a Glance\n\nReporting to the Finance & Admin Manager, you will provide general accounting, clerical and administrative services to ensure efficiency, timely and accuracy in the below scope, as well as ensure compliance with statutory and company accounting policies and procedure.\n\nYou will also continually look into and participate in process improvement and play an important role in sharing best practices with your team and functional colleagues.\n\nAbout the Role\n\nMaintain accounts receivable customer files and records\nMonitor customer account details for non-payments, delayed payments and other irregularities, develop a recovery system and initiate collection efforts\nFollow up on collection and allocate receipts, investigate and resolve customer billing/collection queries\nCommunicate with customers via phone, email, mail or personally\nPrepare balance sheet reconciliation related to Accounts Receivable accounts for Finance Manager\nEnsure that all internal and external finance-related requests are responded to promptly and accurately\nImplement B2B A/R, Invoicing, and Collection processes\nWork closely with Sales team to maintain up-to-date billing system\nHelp in the implementation of new CRM / ERP system\nAny other ad-hoc duties as assigned by Manager\n\nSkills & Experiences Required\n\nHigher Diploma or above in Accounting/Business Administration or similar discipline\nAt least 2 years of relevant accounting/finance experience in E-commerce/Banking/F&B industry\nGood knowledge of AR collection is preferred\nProficient in PC applications including MS Word and Chinese Word processing, advanced proficiency in MS Excel will be an advantage\nExperience with these or similar tools: NetSuite, Xero, G-sheet & Tableau\nWilling to work hard in a fast-pace environment\nA team player with high stress tolerance and sense of urgency, able to meet tight deadlines and produce accurate and detail work with quick turnaround\nAttention to detail and accuracy\nGood verbal and written communication skills in English and Chinese\nCandidates with less experience will be consider as Assistant Finance Executive\nImmediate available is an advantage\n\nWhy Chope?\n\nMeaningful work - you\u2019ll have ownership over and the ability to make a direct impact on the experience we\u2019re delivering to our customers (You\u2019re not here \u201cjust to execute\u201d)\nAutonomy - you\u2019ll be in an environment that enables you to challenge yourself, challenge team members, learn new skills, and try out new things\nCollaborative and an open culture that values receiving and giving feedback\nA competitive salary\nFlexible work arrangements that provide you the balance you deserve", "employment_types": ["Full Time", "Permanent"], "selling_points": ["Maintain accounts receivable customer files/record", "Monitor customer account details for non-payments", "Follow up on collection and allocate receipts"], "locations": ["Sheung Wan"], "categories": ["Banking / Finance", "Credit Collection"], "post_time": "2022-01-14T05:51:37Z", "salary": {"currency": null, "max": null, "min": null, "period": "monthly", "term": null}, "salary_visible": false, "title_keywords": ["executive"], "responsibilities": ["receipts", "communication", "accounting policies", "maintain", "administration", "accounts receivable", "monitor", "implementation", "develop", "banking", "balance sheet", "reporting", "ar", "ad-hoc duties", "communicate with", "irregularities", "ensure compliance", "invoicing", "payments", "sales team"], "requirements": {"degrees": ["higher diploma or above"], "majors": ["accounting", "business administration"], "languages": ["english", "chinese"], "language_level": ["advantage", "good", "proficiency", "proficient"], "hard_skills": ["chinese word processing", "ar", "e-commerce", "xero", "tableau", "pc applications", "make", "erp system", "billing system", "ms excel", "r", "ms word"], "soft_skills": ["flexible", "communication skills", "meet tight deadlines", "advanced", "urgency", "timely", "collaborative", "attention to detail", "ad-hoc duties", "team player", "accurate"], "languages_combined": [{"language": "english", "language_level": ["good"]}, {"language": "chinese", "language_level": ["advantage", "good", "proficiency", "proficient"]}]}, "experience_required": {"duration": ["at least 2 years"], "field": ["e-commerce", "finance", "f&b", "banking", "accounting"]}}, {"job_id": "100003009042648", "location_code": "hk", "company": "CUHK Medical Centre Limited", "job_title": "Shroff Service Officer", "description": "Key Responsibilities\n\nPerform cashier counter duties and day-end procedures;\nHandle patients and next-of-kin enquiries;\nHandle patient billing issues and ensure accuracy of all chargeable items when issuing invoice;\nFollow up payment with patients and corporates;\nPerform general clerical duties, including filing, data entry and record keeping; and\nPerform any other duties as assigned by supervisor(s) from time to time.\n\nJob Requirements\n\nCompletion of Secondary Education\nAt least 2 years\u2019 relevant work experience\nExperience in hospital, hotel, airline or insurance company and area of billing and cashier is preferred\nCustomer-oriented with excellent communication and interpersonal skills\nShift duty (night shift) is required\nTeam player and able to work independently and under pressure\nGood command of written and spoken English and Chinese\nProficient in MS Office applications\n\nCompensation and Employment Terms\n\nWe provide a unique employment experience for people seeking careers in hospital and healthcare industry; and offer competitive remuneration packages to the successful candidates. Appointment will be made on a 3-year contract with contract-end gratuity, renewable subject to good performance and mutual agreement.\n\nApplication Closing Date\n\n25 January 2022\n\n\n\nPersonal Information Collection Statement\n\nData collected will only be used for job application processing. Applicants not contacted by CUHK Medical Centre Limited within eight weeks from the application closing date may assume their applications unsuccessful. All personal data collected will be kept for a period of 12 months from the application closing date, and will be destroyed thereafter.", "employment_types": ["Full Time", "Contract"], "selling_points": ["2 years\u2019 relevant work experience", "Hospital, hotel, airline or insurance co. exp", "Shift duty (night shift) is required"], "locations": ["Shatin Area"], "categories": ["Accounting", "Treasurer", "Banking / Finance", "Credit Collection", "Hospitality / F & B", "Hospitality / Hotel Services"], "post_time": "2022-01-12T08:15:56Z", "salary": {"currency": null, "max": null, "min": null, "period": "monthly", "term": null}, "salary_visible": false, "title_keywords": ["officer"], "responsibilities": ["any other duties", "data entry", "invoice", "procedures", "payment"], "requirements": {"degrees": ["secondary education"], "majors": [], "languages": ["english", "chinese"], "language_level": ["good command"], "hard_skills": ["airline", "ms office"], "soft_skills": ["work independently", "under pressure", "customer-oriented", "communication and interpersonal skills", "team player"], "languages_combined": [{"language": "english", "language_level": ["good command"]}, {"language": "chinese", "language_level": ["good command"]}]}, "experience_required": {"duration": ["at least 2 years"], "field": ["billing", "insurance"]}}, {"job_id": "100003009044710", "location_code": "hk", "company": "UOB Kay Hian (Hong Kong) Limited", "job_title": "Credit Officer/ Credit Assistant", "description": "Responsibilities:\n\nAssist in automating existing credit risk report production through Excel visual basic enhancement\nAssist in IPO booking, manage trade confirmations and allotment result notification process\nInvolve in preparation of group exposure risk analysis\nCoordinate risk management projects for credit departments\nTake up ad-hoc assignments and related tasks as required\nRequirements:\n\n\nUniversity graduate with a degree in science, finance or accounting\nProficient in programming skills (Python, VBA)\nPrior experience in financial services industry is preferred\nKeen interest in developing a career in financial risk management\nMin. 2 years\u00a0relevant experience preferred\n*Candidates with less experience will be considered as Credit Assistant\n\nInterested candidates are invited to send a comprehensive resume stating current and expected salaries to\u00a0Head of Human Resources, UOB Kay Hian (Hong Kong) Limited, 6/F Harcourt House, 39 Gloucester Road, Hong Kong\u00a0or email by clicking the below\u00a0\"Apply Now\"\u00a0button", "employment_types": ["Full Time", "Permanent"], "selling_points": [], "locations": ["Wan Chai"], "categories": ["Banking / Finance", "Credit Analysis / Approval", "Financial Services", "Credit Collection"], "post_time": "2022-01-13T05:40:41Z", "salary": {"currency": null, "max": null, "min": null, "period": "monthly", "term": null}, "salary_visible": false, "title_keywords": ["officer", "assistant"], "responsibilities": ["management", "ad-hoc assignments", "coordinate", "booking", "risk analysis", "visual", "report"], "requirements": {"degrees": ["university graduate", "degree"], "majors": ["finance", "science", "accounting"], "languages": [], "language_level": [], "hard_skills": ["python", "vba", "programming"], "soft_skills": ["keen"], "languages_combined": []}, "experience_required": {"duration": ["2 years"], "field": ["financial services industry", "relevant experience"]}}, {"job_id": "100003009037243", "location_code": "hk", "company": "CMB Wing Lung Bank Limited", "job_title": "Senior Officer/Assistant Vice President (Retail Finance and Credit Card Department)", "description": "Responsibilities:\n\nMonitor and take appropriate collection actions on delinquent unsecured loans and credit card accounts\nMonitor the performance of external debt collection agencies\nPrepare reports on delinquent accounts and debt collection agencies performance to internal or external parties\nAssist the management to review internal policies and procedure manual, ensure all internal guidelines are in alignment and compliance with regulatory requirements\n\nRequirements:\n\nDegree holder\nMinimum 5 years\u2019 related working experience\nProficient in both English and Chinese; fluency in Putonghua an advantage\nGood communication and negotiation skills", "employment_types": ["Full Time", "Permanent"], "selling_points": ["Credit Card Operations", "Collection", "Minimum 2 years' experience"], "locations": ["Not Specified"], "categories": ["Banking / Finance", "Credit Collection"], "post_time": "2022-01-11T02:11:02Z", "salary": {"currency": null, "max": null, "min": null, "period": "monthly", "term": null}, "salary_visible": false, "title_keywords": ["senior officer", "assistant vice president"], "responsibilities": ["management", "guidelines", "policies", "regulatory requirements", "external parties", "monitor", "review", "compliance", "debt collection", "monitor the performance", "prepare reports"], "requirements": {"degrees": ["degree holder"], "majors": [], "languages": ["putonghua", "english", "chinese"], "language_level": ["fluency", "advantage", "proficient"], "hard_skills": [], "soft_skills": ["communication", "negotiation skills"], "languages_combined": [{"language": "putonghua", "language_level": ["fluency", "advantage"]}, {"language": "english", "language_level": ["proficient"]}, {"language": "chinese", "language_level": ["proficient"]}]}, "experience_required": {"duration": ["minimum 5 years"], "field": ["related"]}}, {"job_id": "100003009050873", "location_code": "hk", "company": "Manpower Services (Hong Kong) Limited", "job_title": "Bank Security and Facility Specialist", "description": "Responsibilities and duties of the role:\n\nWork with front office and in-house legal to review facility and security agreements and ensure terms and conditions are in compliance with credit approval.\nMonitor underwriting commitment and assist front office on pre-signing administrative tasks.\nTo ensure all conditions precedent documents are fulfilled before approving the BO team to proceed funding and loan payment.\nMonitor facility closing, initial drawdown, fees settlement and conditions subsequent, if any.\nCheck and verify facility and security documentation signed and returned by customers with relevant supporting documentation.\nEnsure the perfection on security documents and monitor periodical revaluation and the expiry of ongoing collateral and securities.\nHandle credit matters and daily portfolio monitoring and covenant checking for designated portfolio across all Business Lines.\nHandle facility limits, collateral, covenants set up, modification and deletion timely in system.\nHandle other tasks assigned by the Team Lead &/or Manager.\n\nJob Requirements\n\nUniversity degree, minimum of 3-5 years relevant experiences with an international bank.\nKnowledge and experience in handling covenant monitoring is essential.\nExperience in handling Specialized Lending or Structured Finance Facilities.\nGood interpersonal and communication skills are required and able to work under pressure.\nWritten and Spoken English, Spoken Mandarin & Cantonese\n\nInterested parties please send your full resume with expected salary to yan.chan@manpowergrc.hk\u00a0or by clicking \"Apply Now\".", "employment_types": ["Contract"], "selling_points": ["Covenant monitoring", "Specialized Lending/Structured Finance Facilities", "3-5 years relevant experiences"], "locations": ["Yau Tsim Mong Area"], "categories": ["Banking / Finance", "Credit Analysis / Approval", "Others", "Credit Collection"], "post_time": "2022-01-14T11:36:17Z", "salary": {"currency": null, "max": null, "min": null, "period": "monthly", "term": null}, "salary_visible": false, "title_keywords": ["specialist"], "responsibilities": ["documentation", "compliance", "review", "monitor", "monitoring", "checking", "other tasks", "payment", "administrative tasks"], "requirements": {"degrees": ["university degree"], "majors": [], "languages": ["cantonese", "english", "mandarin"], "language_level": [], "hard_skills": [], "soft_skills": ["communication skills", "structured", "interpersonal", "work under pressure"], "languages_combined": [{"language": "cantonese", "language_level": []}, {"language": "english", "language_level": []}, {"language": "mandarin", "language_level": []}]}, "experience_required": {"duration": ["minimum of 3-5 years"], "field": ["finance"]}}, {"job_id": "100003009042761", "location_code": "hk", "company": "ExcelNet Total HR Solutions", "job_title": "Bank Credit Facilities Specialist", "description": "Our client is looking for a high-caliber candidate to fill up the captioned position.\n\nJob Responsibilities :\n\n\nWork with the front office and in-house legal to review facility and security agreements and ensure terms and conditions are in compliance with credit approval\nMonitor underwriting commitment and assist front office on pre-signing administrative tasks\nTo ensure all conditions precedent documents are fulfilled before approval the Back Office team to proceed with funding and loan payment\nMonitor facility closing, initial drawdown fees settlement, and conditions subsequent, if any\nCheck and verify facility and security documents signed and returned by customers with relevant supporting documentation\nEnsure the perfection on security documents and monitor periodical revaluation and the expiry of ongoing collateral and securities\nHandle credit matters and daily portfolio monitoring and covenant checking for designated portfolio across all business lines\nHandle facility limits, collateral, covenants set up, modification and deletion timely in the system\nJob Requirements :\n\nUniversity graduate\nMinimum 3-5 years relevant experience with an International Bank\nKnowledge and experience covenant monitoring is essential\nExperience in handling specialized lending or structured finance facilities\nGood interpersonal and communications skills and able to work under pressure\nInterested parties, please click \"APPLY NOW\" or refer to the Company Overview below to submit your application.", "employment_types": ["Full Time", "Contract"], "selling_points": ["Exp in Lending or Structured Finance Facilities", "Familiar with handle covenant monitoring", "Attractive salary"], "locations": ["Not Specified"], "categories": ["Banking / Finance", "Credit Analysis / Approval", "Others", "Credit Collection"], "post_time": "2022-01-12T08:47:19Z", "salary": {"currency": null, "max": null, "min": null, "period": "monthly", "term": null}, "salary_visible": false, "title_keywords": ["specialist"], "responsibilities": ["documentation", "compliance", "review", "monitor", "back office", "monitoring", "checking", "payment", "administrative tasks"], "requirements": {"degrees": ["university graduate"], "majors": [], "languages": [], "language_level": [], "hard_skills": [], "soft_skills": ["structured", "interpersonal", "work under pressure"], "languages_combined": []}, "experience_required": {"duration": ["minimum 3-5 years"], "field": ["finance", "relevant experience"]}}, {"job_id": "100003009040263", "location_code": "hk", "company": "AXA Hong Kong", "job_title": "Senior Customer Service Officer", "description": "Responsibilities:\n\nHandle daily incoming premium collection with service vendors' coordination\nConduct reconciliation and maintain accurate payment records of transactions\nHandle payment related enquiries and answer emails in a timely and professional manner\nProvide administrative supports to the Customer Payment team\nConduct regular AML checking\nLiaise closely with other functional teams (e.g. Finance, Policy Admin., CS) to deliver quality and excellent customer payment services\nAssist the manager to streamline payment process to improve efficiency\n\nRequirements:\n\nDiploma holder or above in any discipline\nMinimum 2 years relevant working experience, preferably in Insurance and Financial Industry\nResponsible, logical, accuracy and attentive to details\nProficiency in Microsoft Word and Excel\nGood command of spoken and written English and Chinese\nCustomer-oriented, flexible and able to work independently\nCandidates with less experience will be considered as Customer Service Officer", "employment_types": ["Full Time", "Permanent"], "selling_points": ["Handle daily incoming premium collection", "Reconciliation and back office support", "Detail-minded, with good numeric sense"], "locations": ["Not Specified"], "categories": ["Accounting", "Accountant", "Banking / Finance", "Credit Collection", "Insurance", "Others"], "post_time": "2022-01-12T02:02:37Z", "salary": {"currency": null, "max": null, "min": null, "period": "monthly", "term": null}, "salary_visible": false, "title_keywords": ["senior customer service officer"], "responsibilities": ["liaise", "aml", "professional manner", "checking", "transactions", "teams", "quality", "payment", "maintain", "coordination", "payment process"], "requirements": {"degrees": ["diploma holder"], "majors": [], "languages": ["english", "chinese"], "language_level": ["good command"], "hard_skills": ["excel", "microsoft word"], "soft_skills": ["flexible", "work independently", "attentive to details", "responsible", "customer-oriented", "customer service"], "languages_combined": [{"language": "english", "language_level": ["good command"]}, {"language": "chinese", "language_level": ["good command"]}]}, "experience_required": {"duration": ["minimum 2 years"], "field": ["customer service", "insurance", "financial industry", "relevant working experience"]}}, {"job_id": "100003009044454", "location_code": "hk", "company": "Kin Yat Industrial Co Ltd", "job_title": "Accounting Clerk (Welcome Fresh Graduates)", "description": "Responsibilities\n\nResponsible for daily Sales and AR operation\nLiaise closely with customers and internal parties to resolve credit and billing issues\nReconcile shipment and invoices\nSettlement of invoices\u00a0\nMaintaining accounts receivable files and records\nHandle ad-hoc duties as assigned\n\nRequirements\n\nDiploma or above in Accounting / Finance or related disciplines\nMinimum\u00a01 year of relevant experience\nSelf-motivated, independent, responsible, able to work under pressure and meet tight deadlines\nGood command in English and Chinese\nGood PC skills in MS Word, Excel and Power Point\nImmediate availability is preferred\n\nWe are an equal opportunity employer and welcome applications from all qualified candidates. Any interest candidate, please send your resume with expected salary and availability by clicking\u00a0\u201cApply Now\u201d.\n\n(Data collected will be treated as strictly confidential and will be used for recruitment purpose only and will be destroyed after the recruitment exercise when no longer required.)\n", "employment_types": ["Full Time", "Permanent"], "selling_points": [], "locations": ["Wong Tai Sin Area"], "categories": ["Accounting", "Accounting Clerk / Supervisor", "Banking / Finance", "Credit Collection"], "post_time": "2022-01-15T03:49:17Z", "salary": {"currency": null, "max": null, "min": null, "period": "monthly", "term": null}, "salary_visible": false, "title_keywords": ["accounting clerk"], "responsibilities": ["liaise", "invoices", "maintaining", "ar", "accounts receivable", "ad-hoc duties", "internal parties"], "requirements": {"degrees": ["diploma or above"], "majors": ["related disciplines", "finance", "accounting"], "languages": ["english", "chinese"], "language_level": ["good command"], "hard_skills": ["excel", "no", "power point", "pc skills", "ms word"], "soft_skills": ["self-motivated", "meet tight deadlines", "independent", "responsible", "work under pressure"], "languages_combined": [{"language": "english", "language_level": ["good command"]}, {"language": "chinese", "language_level": ["good command"]}]}, "experience_required": {"duration": ["minimum 1 year"], "field": ["relevant experience"]}}, {"job_id": "100003009039843", "location_code": "hk", "company": "Page Personnel", "job_title": "Collection/ Credit Control, Associate-MNC Platform", "description": "Our client is an European insurance company set up for more than 100 years. They are now looking for candidate who is with at least 2 years Collection/Credit Control experience with corporate clients to join them. They also welcome candidate coming from non-insurance background.\n\nClient Details\n\nOur client is an European based insurance company. They have set up for more than 100 years, specialising in general insurance business with corporate clients globally. They operate as a very strong MNC business with global footprint covering more than 200 regions. Setting their Asian hub in Hong Kong for more than 20 years, they have been providing competitive insurance services and products to their corporate clients.\n\nTo support their business growth, they are looking for candidate with Collection or Credit Control experience to join them. Candidate would be expected to negotiate with external counterpart from different countries to manage their collection status. Therefore, they would like to look for candidate who is strong in interpersonal skills and could communicate clearly in both Chinese and English. The company culture is very stable and friendly. They emphasise the career development of their staff by providing ample internal mobility opportunities.\n\nDescription\n\nPerform daily collection activities to manage the debt collection status meeting the assigned target.\nFollow up collection issues with suppliers and provide updated report to clients.\nWork closely with internal risk team for collection management\nHandle all enquiries related to collection issues.\nLiaise and maintain positive relationship with policy holders and brokers.\n\nProfile\n\nBachelor degree holder.\nAt least 2 years Collection/Credit Control experience with corporate clients.\nSolid experience of negotiation or client facing from previous job experiences.\nCandidate with experience of negotiating with regional counterpart would be a plus.\nExcellent command in both English and Chinese.\nSociable and self-motivated teamplayer who is with excellent interpersonal skills.\n\nJob Offer\n\nMNC Platform\nWell-established Business\nAnnual Leave: 14 days Up\nMedical Benefits\nDental Benefits\nBody Check\nExcellent Training\nInternal Mobility/ International Mobility\n\nTo apply online please click the 'Apply' button below. For a confidential discussion about this role please contact Ellen Fung on +852 3602 2447.", "employment_types": ["Full Time", "Permanent"], "selling_points": ["MNC Insurance Platform", "Collection Experience", "Excellent Internal Mobility"], "locations": ["Not Specified"], "categories": ["Accounting", "Credit Control", "Banking / Finance", "Credit Collection", "Risk Management"], "post_time": "2022-01-11T11:57:28Z", "salary": {"currency": "HKD", "max": 34999, "min": 20000, "period": "monthly", "term": null}, "salary_visible": true, "title_keywords": ["associate"], "responsibilities": ["liaise", "control", "management", "debt collection", "maintain", "career development", "insurance", "report"], "requirements": {"degrees": ["bachelor degree holder"], "majors": [], "languages": ["english", "chinese"], "language_level": ["excellent"], "hard_skills": ["plus"], "soft_skills": ["self-motivated", "negotiation", "sociable", "interpersonal skills", "friendly", "stable", "mobility", "positive"], "languages_combined": [{"language": "english", "language_level": ["excellent"]}, {"language": "chinese", "language_level": ["excellent"]}]}, "experience_required": {"duration": ["at least 2 years"], "field": ["business"]}}, {"job_id": "100003009037738", "location_code": "hk", "company": "China CITIC Bank International Limited", "job_title": "Assistant Vice President, Risk Assets Management", "description": "Job Purpose\n\nHandle debt recovery and minimize impairment loss for the designated accounts.\n\nResponsibilities\n\nAssist to formulate and perform daily execution of collection strategies.\nHandle debt recovery for the designated accounts through cash/ assets recovery, debt restructuring and security enforcement.\nSustain positive working relationship with key internal customers to enhance recoverability of problem loans.\nMaximize debt recovery for the designated accounts including cash/ assets recovery, debt restructuring, security enforcement, obtaining additional securities etc.\nLiaise with solicitors and collection agents on problem loans management.\nSupervise and execute the repossession and sale of collaterals.\nAchieve annual business targets, for instances, provision balance, impairment loss ratio, bad debt recoveries etc.\u00a0\u00a0\nSupport bank-wide new business initiatives by providing timely advice from risk management perspective.\nMonitor the output quality from team members to ensure their compliance with the regulatory requirements and provide timely coaching to team members.\n\nRequirements\n\nSecondary education or above. Bachelor degree holder in business or risk management is a plus.\nMinimum 10 years\u2019 relevant experience in bank, credit or related field in which 3 years\u2019 experience at supervisory level is highly preferred.\nProfessional Qualification of Certified Credit Risk Management Professional (Credit Portfolio Management) is preferred.\nKnowledge of litigation process in HKSAR and PRC with focus on collaterals repossession.\nGood knowledge of regulatory requirements such as relevant ordinances and supervisory guidelines and in-depth knowledge on banking and investment products.\nSolid experience in Corporate Banking collection is preferable.\nStrong analytical and credit assessment skills with excellent understanding of lending principles.\nSelf-motivated, independent and able to communicate effectively at all levels.\nGood command of written and spoken English and Chinese including Putonghua.", "employment_types": ["Full Time", "Permanent"], "selling_points": ["Handle debt recovery", "10 years\u2019 collection experience in bank", "Solid experience on Corporate Banking collection"], "locations": ["Quarry Bay"], "categories": ["Banking / Finance", "Corporate Banking", "Credit Collection", "Risk Management"], "post_time": "2022-01-11T03:41:45Z", "salary": {"currency": null, "max": null, "min": null, "period": "monthly", "term": null}, "salary_visible": false, "title_keywords": ["assistant vice president"], "responsibilities": ["management", "business initiatives", "regulatory requirements", "compliance", "quality", "monitor", "liaise with"], "requirements": {"degrees": ["secondary education", "bachelor degree holder"], "majors": ["risk management", "business"], "languages": ["putonghua", "english", "chinese"], "language_level": ["good command"], "hard_skills": ["litigation process", "plus", "focus", "investment products"], "soft_skills": ["focus", "independent", "self-motivated"], "languages_combined": [{"language": "putonghua", "language_level": ["good command"]}, {"language": "english", "language_level": ["good command"]}, {"language": "chinese", "language_level": ["good command"]}]}, "experience_required": {"duration": ["3 years", "minimum 10 years"], "field": ["related", "supervisory level", "relevant experience", "banking"]}}, {"job_id": "100003009035147", "location_code": "hk", "company": "Mouser Electronics (Hong Kong) Limited", "job_title": "Customer Accounts Representative / Billing Officer (Assistant)", "description": "Scope:\n\nCustomer Account Representative is responsible for assisting with day to day operations of credit and collections in a manner that ensures total quality and customer service.\n\nAccountabilities:\n\nCommunicates with customers and internal departments to resolve account issues, pending orders, and invoice discrepancies within specified guidelines.\nPerforms order releases, new account set-ups, credit investigations.\nWorks effectively with customers to collect outstanding accounts and communicates with appropriate personnel regarding potential and existing problem accounts.\nPerforms assigned research activities to reconcile wire payments and/or resolve payment discrepancies.\nProvides company credit services within specified guidelines via U/V, phone, internet, email & mail, and fax.\nPossesses working knowledge of company policies, procedures, and systems.\nOther duties as assigned.\n\nRequirements:\n\nUniversity or Tertiary College graduate.\nGood command of English and Mandarin.\nFresh graduate welcome, applicant with min 1 year working experience will be an advantage.\nUnderstands and able to correctly work with multiple currencies.\nTeam player, Trustworthy and maintains confidentiality.\nPlease mention salary history and expectations in\u00a0your resume.\n\n\nWe are an equal opportunity employer; personal data collected will be treated in strictest confidence and handled confidentially by authorized personnel for recruitment-related purposes.\n", "employment_types": ["Full Time", "Permanent"], "selling_points": ["Customer Service Oriented", "Regional Exposure", "Welcome Fresh Graduate"], "locations": ["Kwun Tong"], "categories": ["Accounting", "Accounting Clerk / Supervisor", "Banking / Finance", "Credit Collection", "Sales, CS & Business Devpt", "Customer Service - Supervisor / Officer"], "post_time": "2022-01-10T06:10:20Z", "salary": {"currency": null, "max": null, "min": null, "period": "monthly", "term": null}, "salary_visible": false, "title_keywords": ["representative", "billing officer", "assistant"], "responsibilities": ["day to day operations", "other duties", "invoice", "guidelines", "policies", "systems", "quality", "procedures", "payment", "customer service", "payments", "recruitment", "personal data"], "requirements": {"degrees": ["fresh graduate"], "majors": [], "languages": ["english", "mandarin"], "language_level": ["good command"], "hard_skills": [], "soft_skills": ["confidence", "responsible", "trustworthy", "customer service", "team player"], "languages_combined": [{"language": "english", "language_level": ["good command"]}, {"language": "mandarin", "language_level": ["good command"]}]}, "experience_required": {"duration": ["min 1 year"], "field": []}}, {"job_id": "100003009041292", "location_code": "hk", "company": "Belos Capital (Asia) Limited", "job_title": "Customer Service Officer (5-Day Work) (Fresh Graduates Welcome)", "description": "Responsibilities:\n\n\nAssist manager in executing the merchant banking solutions, including cold call, negotiation, client relationship management, client due diligence and client audit;\nProvide general office administration support including purchasing and procurement, document management, etc;\nRecording and review of vendor invoices in the system;\nConduct other ad-hoc supporting duties.\n\nRequirements:\n\nDiploma/ Associate Degree or above;\nAt least 1 year of working experience, fresh graduates are also welcomed;\nExperiences in customer service of banking are preferred;\nStrong sense of maturity, responsibility, integrity and attention to detail;\nStrong interpersonal and communication skills with fluency in English, Cantonese and Mandarin. Other Asian language is a plus.\n\nApplications:\n\nInterested parties please send your full resume giving details of current & expected salary and availability by clicking \"Apply Now\".\n\n\u00a0*Personal data collected will be used for recruitment purpose only.", "employment_types": ["Full Time"], "selling_points": [], "locations": ["Wan Chai"], "categories": ["Banking / Finance", "Financial Services", "Credit Collection", "Sales, CS & Business Devpt", "Customer Service - Supervisor / Officer"], "post_time": "2022-01-12T03:42:04Z", "salary": {"currency": null, "max": null, "min": null, "period": "monthly", "term": null}, "salary_visible": false, "title_keywords": ["customer service officer"], "responsibilities": ["ad-hoc", "due diligence", "management", "office administration support", "invoices", "review", "audit", "executing", "banking"], "requirements": {"degrees": ["diploma", "degree or above"], "majors": [], "languages": ["cantonese", "english", "mandarin"], "language_level": ["fluency"], "hard_skills": ["plus"], "soft_skills": ["communication skills", "integrity", "customer service", "attention to detail", "interpersonal"], "languages_combined": [{"language": "cantonese", "language_level": ["fluency"]}, {"language": "english", "language_level": ["fluency"]}, {"language": "mandarin", "language_level": ["fluency"]}]}, "experience_required": {"duration": ["at least 1 year"], "field": ["customer service", "banking"]}}, {"job_id": "100003009035085", "location_code": "hk", "company": "Potus Medical (Hong Kong) Limited", "job_title": "Administrative Assistant / Officer, Generic, 5-day work, Open Career Paths", "description": "Career Growth\n\nA career within Administrative Assistant can be highly rewarding, and open to the opportunity across different departments like Product Support, Purchasing, General Admin. Start in an entry-level/graduate and a generic position, before moving through the ranks of Administrative Officer, Senior Administrative Officer, Team leader before reaching Department Manager level of dedicated departments\u00a0\n\nJob Description & Responsibilities\nCandidates could follow one of the following routes according to skill sets as determined by HR.\n\nProduct Support\n\nProvide pre-sales & follow after-sales clerical support.\nAssist Team leader in pricing model: setting price levels, managing price discounts and establishing price structure.\nResponsible for issuing quotations, following up on delivery status to customer satisfaction\nProvide backend support to Product Team infield.\nPerform interdisciplinary ad-hoc projects assigned by the director.\n\nPurchasing\n\nSupport warehouse department: inbound and outbound material movement (transfer, storage, staging and retrieval), parts inspection and stock checking.\nAssist Team leader in inventory management model: setting stock levels, establishing economic order quantity and classifying stock-keeping unit.\nIssue Purchase Order to vendors according to pre-set rules\nCoordinate with vendors, factories, and internal parties\u00a0for day-to-day logistics operations\nPerform interdisciplinary ad-hoc projects assigned by the director.\n\nGeneral Administration\n\nManage account receivables activities include issuing the monthly statement, the collection of due payment, performing bookkeeping through ERP, reconciling amounts\nManage account payable activities include issuing cheques, the review and audit of reimbursement requests.\nAssist Team Leader with HR function:\u00a0\u00a0monitor KPI, benchmark salary by position,\u00a0organize\u00a0company events and talent\u00a0acquisition.\nPerform interdisciplinary ad-hoc projects assigned by the director.\n\nRequirement\n\n\nUniversity graduate or above with 1-2 years of experience, previous experience in merchandising, retail, or bank preferred.\u00a0\nFresh graduate is also welcome. Candidate with >2 years of experience will be considered as Senior Administrative Officer /Team Leader, AO / Department Manager. Candidate with Diploma will be considered as trainee.\nAble to work under pressure, responsible and willing to learn\nGood command of spoken and written English, Cantonese and Mandarin.\u00a0\nSelf-motivated, detail-oriented and multi-tasking\n\nRemuneration\u00a0\n\nWe offer attractive remuneration package\n5-day work week, bank holidays, medical scheme and MPF\n\nInterested parties please send your resume with expected salary, contact telephone number by clicking 'Apply Now' for an interview.\u00a0\nAll personal data collected will be used for recruitment purpose only.\nPlease visit our website at\u00a0http://www.potus.com.hk\u00a0for more information about us.", "employment_types": ["Full Time", "Permanent"], "selling_points": ["Admin Assistant / Officer, Generic, 5-day work", "Dynamic 80/90s generation Team, Clear Career Path", "Opportunity in Support, Purchasing, General Admin"], "locations": ["Kwai Hing"], "categories": ["Admin & HR", "Clerical / Admin Staff", "Banking / Finance", "Credit Collection", "Merchandising & Purchasing", "Procurement / Purchasing / Sourcing"], "post_time": "2022-01-10T09:09:35Z", "salary": {"currency": null, "max": null, "min": null, "period": "monthly", "term": null}, "salary_visible": false, "title_keywords": ["administrative assistant", "officer"], "responsibilities": ["operations", "hr", "review", "coordinate with", "checking", "clerical support", "inspection", "inventory management", "audit", "purchase", "payment", "logistics", "cheques", "ad-hoc projects", "monitor", "internal parties", "administration"], "requirements": {"degrees": ["university graduate or above", "diploma", "fresh graduate"], "majors": [], "languages": ["cantonese", "english", "mandarin"], "language_level": ["good command"], "hard_skills": [], "soft_skills": ["self-motivated", "responsible", "willing to learn", "detail-oriented", "multi-tasking", "work under pressure"], "languages_combined": [{"language": "cantonese", "language_level": ["good command"]}, {"language": "english", "language_level": ["good command"]}, {"language": "mandarin", "language_level": ["good command"]}]}, "experience_required": {"duration": ["2 years", "1-2 years"], "field": ["retail", "merchandising", "team", "administrative"]}}, {"job_id": "100003009036216", "location_code": "hk", "company": "BOCOM International Holdings Company Limited", "job_title": "Associate/ Senior Associate, Credit Risk", "description": "Responsibilities:\n\nConduct daily report review and account monitoring and liaise with Account Executives (AE) to obtain relevant information for credit due diligence\nCommunicate effectively with sales team on the follow-up action on credit control related issues\nConduct and comment assessments on credit limit proposals and act as a maker to adjust the client approved limit in the trading system\nObtain the proper approval for those accounts in accordance with credit policies and procedures\nSet up or create templates for reporting\nCollect the statistical data on credit risk analysis\nPerform ad hoc assignments and handle special projects with credit related issues from time to time required by management\nCompile daily, weekly and monthly reports on time and perform clerical duty\n\nRequirement\n\nUniversity degree in Finance / Risk Management / other related disciplines (FRM or CFA preferred). Minimum 5-6 years relevant working experience is required if the candidate is not a degree holder\nMinimum 3 years experience in credit risk management, preferably in financial institutions\nGood knowledge in equity market and derivatives products\nPossess strong credit analytical skills\nStrong proficiency in VBA and Excel-Macro\nProficient in MS Office application and Chinese word processing\nGood communication skills and good telephone manner\nGood command of written and spoken English and Chinese with fluency in Mandarin; knowledge of Simplified Chinese a plus\nEfficient, self-motivated, independent and able to work under pressure\nMore experience will be offered as Senior Associate\nImmediate Available is highly preferred\n\nApplication:\n\nWe offer an attractive remuneration package including a performance bonus, medical insurance covering dependants, MPF, Life and AD&D insurance, annual leave, birthday leave, marriage leave and training subsidy, etc. to the right candidate.\u00a0\n\nIf you are interested in this opportunity, please send your application with a detailed resume including current and expected salary, latest bonus and availability by clicking \"Apply Now\". Applications without required information will NOT be considered.\n\n*Information provided by applicants will be treated in the strictest confidence and will be solely used for recruitment purposes.", "employment_types": ["Full Time", "Permanent"], "selling_points": ["Credit Risk", "Strong in Excel (VBA, Macro)", "Margin Financing"], "locations": ["Central"], "categories": ["Banking / Finance", "Credit Analysis / Approval", "Credit Collection", "Risk Management"], "post_time": "2022-01-10T09:40:28Z", "salary": {"currency": null, "max": null, "min": null, "period": "monthly", "term": null}, "salary_visible": false, "title_keywords": ["senior associate", "associate"], "responsibilities": ["due diligence", "control", "reporting", "management", "data", "policies", "monitoring", "review", "procedures", "liaise with", "sales team", "risk analysis", "ad hoc assignments", "daily report", "weekly and monthly reports"], "requirements": {"degrees": ["university degree", "degree holder"], "majors": ["related disciplines", "finance", "risk management"], "languages": ["english", "chinese", "mandarin"], "language_level": ["fluency", "good command", "proficient"], "hard_skills": ["vba", "excel", "macro", "chinese word processing", "plus", "cfa", "credit analytical skills", "frm", "ms office"], "soft_skills": ["efficient", "communication skills", "self-motivated", "confidence", "independent", "interested in", "detailed", "analytical skills", "telephone manner", "work under pressure"], "languages_combined": [{"language": "english", "language_level": ["fluency", "good command"]}, {"language": "chinese", "language_level": ["fluency", "good command", "proficient"]}, {"language": "mandarin", "language_level": ["fluency", "good command"]}]}, "experience_required": {"duration": ["minimum 5-6 years", "minimum 3 years"], "field": ["financial institutions", "management", "relevant working experience", "credit risk"]}}, {"job_id": "100003009020935", "location_code": "hk", "company": "OCBC Wing Hang Bank Limited", "job_title": "Assistant Manager / Associate \u2013 Consumer Credit Recovery (Collection)", "description": "Responsibility:\nMake telephone calls, issue demand notice and conduct outdoor visit to follow up repayment in respect of past due loans\nAssist in training and coaching of junior colleagues to achieve KPIs from time to time given by the Bank\nFile Small Claims and attend Tribunal hearings as delegated\nCommunicate with and assist to monitor performance of appointed external parties including solicitors, valuation agencies and debt collection agencies, etc.\nProvide prepare operational reports\nOther ad hoc duties as assigned by superior\nRequirement:\nPost-secondary education or above\nAround 3 years of relevant working experience in banking industry\nGood knowledge of debt collection is preferred\nFamiliar with vehicle financing will be an advantage\nProficient in MS Office, including Word, Excel and Chinese Word Processing\nHard working, self-motivated and able to work under pressure\nFresh graduates will also be considered\nAttractive remuneration package will be offered to the right candidate. Please apply with full resume stating present & expected salary and contact phone number\u00a0to\u00a0The Human Resources Manager, 10/F, 161 Queen\u2019s Road Central, Hong Kong.\u00a0Please quote the reference.\n\nPersonal data collected will be used for recruitment purpose only. For more information, please visit our website:\u00a0http://www.ocbcwhhk.com.", "employment_types": ["Full Time", "Permanent"], "selling_points": ["3 years experience", "Debt collection", "vehicle financing"], "locations": ["Shau Kei Wan"], "categories": ["Banking / Finance", "Loan", "Retail Banking", "Credit Collection"], "post_time": "2022-01-05T02:35:49Z", "salary": {"currency": null, "max": null, "min": null, "period": "monthly", "term": null}, "salary_visible": false, "title_keywords": ["assistant manager", "associate"], "responsibilities": ["communicate with", "valuation", "ad hoc duties", "monitor performance", "external parties", "debt collection", "reports", "kpis"], "requirements": {"degrees": ["secondary education"], "majors": [], "languages": ["chinese"], "language_level": ["proficient"], "hard_skills": ["excel", "chinese word processing", "word", "ms office"], "soft_skills": ["hard working", "self-motivated", "work under pressure"], "languages_combined": [{"language": "chinese", "language_level": ["proficient"]}]}, "experience_required": {"duration": ["3 years"], "field": ["banking industry", "relevant working experience"]}}, {"job_id": "100003009043380", "location_code": "hk", "company": "ADECCO", "job_title": "Credit Monitoring Specialist (12-month Contract Renewable)", "description": "Our client is a leading bank; they are looking for a Credit Monitoring Specialist to join their team\n\nResponsibilities:\n\n\u2022 Contact clients to gather financial data and documentation\n\u2022 Perform impairment assessment\n\u2022 Analyze potential credit risks and market information\n\u2022 Analyze risks and approve or reject loan requests\n\nRequirements:\n\n\u2022 Analytical, independent with good communication skills\n\u2022 Bachelor\u2019s degree in related disciplines or relevant qualifications\n\u2022 Any relevant working experiences is preferred, but not necessary\n\u2022 Ability to create and process financial spreadsheets (MS Excel)\n\u2022 Familiar with general banking and the financial institution will be an advantage\n\nIf you're interested in this role, please CLICK HERE or click 'Apply Now' to apply the position via the Adecco website with your CV.\n\nPlease note that only shortlisted candidates will be notified. All information gathered will be treated in strict confidence and solely used for recruitment purposes.", "employment_types": ["Contract"], "selling_points": [], "locations": ["Kowloon Bay"], "categories": ["Accounting", "Credit Control", "Banking / Finance", "Credit Analysis / Approval", "Credit Collection"], "post_time": "2022-01-12T11:11:45Z", "salary": {"currency": null, "max": null, "min": null, "period": "monthly", "term": null}, "salary_visible": false, "title_keywords": ["specialist"], "responsibilities": ["documentation", "market information", "contact", "data"], "requirements": {"degrees": ["degree", "bachelor"], "majors": ["related disciplines"], "languages": [], "language_level": [], "hard_skills": ["ms excel"], "soft_skills": ["communication skills", "interested in", "independent", "confidence"], "languages_combined": []}, "experience_required": {"duration": [], "field": []}}, {"job_id": "100003009053338", "location_code": "hk", "company": "Hang Seng Bank Ltd", "job_title": "Customer Relationship Manager", "description": "Retail Distribution\n\nHang Seng's Retail Distribution focuses on personal wealth management and financial services. Our one-stop wealth management initiatives are designed for both our affluent and mass integrated account customers.\u00a0With more than\u00a0290\u00a0branches\u00a0and automated banking centres, including\u00a0around 60\u00a0Prestige\u00a0Banking Centres\u00a0for our high-end personal customers, we serve over half of the adult population in Hong Kong while offering an extensive range of products to our valued customers.\n\nWe are currently seeking a high caliber professional to join our team as\u00a0Customer Relationship Manager.\n\nPrincipal responsibilities\n\nProvide financial planning services to high-net-worth customers\nProvide personalised service for this segment of customers to build and maintain good relationships\nPromote investment, insurance and banking products for optimising new business opportunities\nManage operational risk and observe the relevant policies /guidelines and compliance requirements\u00a0\n\u00a0\n\nHang Seng Bank Relationship Manager Virtual Recruitment Talk\u00a0\n\nIf you are keen to find out more about the working culture and how we nurture our Relationship Managers for their success at Hang Seng Bank, please join our Virtual Recruitment Talk\u00a0to hear the candid sharing from our Branch Networks business leaders and also our RMs. You will also find out our progressive career ladder for RMs from entry-level RM Trainee to Signature and Executive RM.\n\nDate:\u00a026 January 2022 (Wed)\n\nTime: 6:00 - 7:00 PM\n\nLocation:\u00a0Virtual Session \u2013 Dial in details will be provided upon registration\n\nRegister your place before 26 Jan 2022 by clicking\u00a0https://hsbc.zoom.us/webinar/register/WN_KABEhwC-RJqmSR07NkIS2g\u00a0\u00a0\n\n\n\nRequirements\n\nUniversity level education is an advantage OR\nHKCEE / HKDSE (with at least passes in Chinese and Mathematics OR English and Mathematics at Grade E / Level 2 / \"Attained\" or above) plus relevant work experience\nPasses in the Insurance Intermediaries Qualifying Examinations / Hong Kong Securities Institute Licensing Examinations\u00a0\nFulfilment of the competency requirements to carry out relevant regulated activities as defined under the Securities and Futures Ordinance\nMinimum of two years' experience in selling investment, insurance and banking products\nStrong sales and customer orientation, with good communication and interpersonal skills\nStrong self-motivation and ability to work under pressure\nProficiency in both English and Chinese, with proficiency in Putonghua an advantage\nHigh level of customer centricity mindset and ability to manage complex interactions effectively\nShown strong situation awareness, strong desire to learn and able to work in Agile environment\nBe curious and with passion to think deeply and rationally\n\n(Candidates with less experience will be considered for the position of\u00a0Senior Customer Relationship Officer)\n\nIf you would like to explore other opportunities at Hang Seng Hong Kong, please visit www.hangseng.com/careers/ for details.\n\nThe health and safety of our employees and candidates is very important to us. Due to the current situation related to the Novel Coronavirus (2019-nCoV), we\u2019re leveraging our digital capabilities to ensure we can continue to recruit top talent at the HSBC Group.\u00a0 As your application progresses, you may be asked to use one of our digital tools to help you through your recruitment journey.\u00a0 If so, one of our\u00a0 Resourcing colleagues will explain how our video-interviewing technology will be used throughout the recruitment process and will be on hand to answer any questions you might have.\n\nAll information provided by applicants will be used only for recruitment purposes and will be used strictly in accordance with the Bank's personal data policies, a copy of which may be obtained by the applicant upon request. Unless otherwise instructed in writing by the applicant concerned, applicants may be considered for other suitable positions within the Bank and its related companies. The personal data of unsuccessful job applicants may be retained for a maximum of two years from the date when the job application is rejected and such data may be retained for a longer period if there is a subsisting reason that obliges the Bank to do so, after which the personal data will be destroyed.", "employment_types": ["Full Time", "Permanent"], "selling_points": [], "locations": ["Not Specified"], "categories": ["Banking / Finance", "Credit Analysis / Approval", "Retail Banking", "Credit Collection"], "post_time": "2022-01-17T06:48:17Z", "salary": {"currency": null, "max": null, "min": null, "period": "monthly", "term": null}, "salary_visible": false, "title_keywords": ["relationship manager"], "responsibilities": ["guidelines", "policies", "business opportunities", "compliance", "maintain", "recruitment", "banking", "insurance", "planning"], "requirements": {"degrees": ["hkdse"], "majors": ["mathematics"], "languages": ["putonghua", "english", "chinese"], "language_level": ["advantage", "proficiency"], "hard_skills": ["plus", "securities and futures ordinance", "agile", "reason"], "soft_skills": ["agile", "communication and interpersonal skills", "self-motivation", "novel", "work under pressure"], "languages_combined": [{"language": "putonghua", "language_level": ["proficiency", "advantage"]}, {"language": "english", "language_level": ["proficiency", "proficiency", "advantage"]}, {"language": "chinese", "language_level": ["proficiency", "proficiency", "advantage"]}]}, "experience_required": {"duration": ["minimum of two years"], "field": ["insurance", "investment", "banking"]}}, {"job_id": "100003009049262", "location_code": "hk", "company": "Shanghai Commercial Bank Ltd", "job_title": "Associate, Merchant Support", "description": "Responsibilities:\n\nProvide administrative support to the Merchant Service Team and Payment Facilitators, including data input and verification of new account opening of VISA, Mastercard, UnionPay, FPS and online merchants; handling cases received from Payment Facilitators; preparation of merchant agreement and arrangement of POS terminal deployment\nHandle telephone enquiry and provide quality services to the card merchants\nHandle ah-hoc project assigned\n\nRequirements:\n\nPost-secondary education or above with at least 1 year\u2019s relevant experience in banking industry or credit card merchant business preferred\nPossess basic knowledge of related Codes of regulatory bodies, such as Code of Banking Practice, HKMA Supervisory Policy manual (SPM), AML/CTF guidelines and PDPO, etc.\nDetailed oriented, good interpersonal skills and PC knowledge\nProficient in Cantonese and English\nWork Location: Kwai Hing\n\nAttractive remuneration package will be offered to the right candidates. Interested parties please click \"Apply Now\" to submit your full resume with current and expected salary to the Human Resources Division.\n\nPlease visit us at www.shacombank.com.hk for more information about our Bank.\n\nAll personal data collected will be used for recruitment related purposes strictly in accordance with the Bank's personal data policies, a copy of which will be provided immediately upon request by contacting our Personal Data Compliance Officer. Applicants who are not contacted within two months may consider their applications unsuccessful and the personal data collected from the applicants will be retained for no longer than two years from the date of rejection during which the applicants may be considered for other suitable positions within the Bank.", "employment_types": ["Full Time", "Permanent"], "selling_points": ["Provide support to the Merchant Service Team", "Handling cases received from Payment Facilitators", "Preparation of merchant agreement"], "locations": ["Kwai Hing"], "categories": ["Banking / Finance", "Others", "Credit Collection"], "post_time": "2022-01-15T03:50:16Z", "salary": {"currency": null, "max": null, "min": null, "period": "monthly", "term": null}, "salary_visible": false, "title_keywords": ["associate"], "responsibilities": ["account opening", "quality", "data input", "payment", "provide administrative support"], "requirements": {"degrees": ["secondary education"], "majors": ["business"], "languages": ["cantonese", "english"], "language_level": ["proficient"], "hard_skills": ["basic", "aml", "hkma", "banking practice", "code", "pc knowledge", "codes"], "soft_skills": ["detailed oriented", "interpersonal skills"], "languages_combined": [{"language": "cantonese", "language_level": ["proficient"]}, {"language": "english", "language_level": ["proficient"]}]}, "experience_required": {"duration": ["at least 1 year"], "field": ["banking industry", "credit card", "education", "business", "relevant experience"]}}, {"job_id": "100003009037424", "location_code": "hk", "company": "The Hong Kong And China Gas Co Ltd", "job_title": "Credit Control Officer", "description": "The Role:\n\nPerform credit management and debt collection actions\nFollow up delinquent accounts via demand letters, telephone calls and on-site visits\nNegotiate with customers on settlement arrangement, such as payment by instalments, taking over of account with previous unsettled balance, tenancy dispute, etc.\nAssign delinquent accounts to Credit Agency for further dunning actions\nManage Credit Agency on issues arising from delinquent accounts\nInitiate legal actions against delinquent accounts\nCarry out on-site visit and cap-off gas supply\nHandle customers' enquiries and complaints regarding Credit Control operation\nHandle other credit control matters and ad hoc assignments\n\nThe Person:\n\nDiploma or above in Accounting, Finance or related disciplines\n\nAt least 2 years\u2019 solid experiences in commercial credit management functions\nHolder of valid driving license Class 1 is an advantage\nProficiency in MS Office applications\n\nGood command of spoken and written English and Chinese, proficiency in Putonghua will be an advantage\n\nCustomer-oriented with good communication and telephone skills\n\nSelf-motivated and able to work independently\n\nApplication with full details stating current and expected salary to: APPLY NOW\u00a0\n\nPlease quote the reference number (CFMD/CCO/JDB01/22) in your application.\n\n(All personal data provided will be treated in strict confidence and used for recruitment purposes only.)", "employment_types": ["Permanent"], "selling_points": ["Credit Control Officer", "Negotiate with customers", "Handle customers' enquiries"], "locations": ["Quarry Bay"], "categories": ["Banking / Finance", "Others", "Credit Collection"], "post_time": "2022-01-11T02:47:02Z", "salary": {"currency": null, "max": null, "min": null, "period": "monthly", "term": null}, "salary_visible": false, "title_keywords": ["credit control officer"], "responsibilities": ["management", "control", "letters", "communication", "debt collection", "payment", "recruitment", "ad hoc assignments", "personal data"], "requirements": {"degrees": ["diploma or above"], "majors": ["related disciplines", "finance", "accounting"], "languages": ["putonghua", "english", "chinese"], "language_level": ["advantage", "proficiency", "good command"], "hard_skills": ["ms office"], "soft_skills": ["work independently", "confidence", "self-motivated", "communication", "customer-oriented"], "languages_combined": [{"language": "putonghua", "language_level": ["proficiency", "good command"]}, {"language": "english", "language_level": ["advantage", "proficiency", "good command"]}, {"language": "chinese", "language_level": ["advantage", "proficiency", "good command"]}]}, "experience_required": {"duration": ["at least 2 years"], "field": ["commercial", "management"]}}, {"job_id": "100003009038917", "location_code": "hk", "company": "CMB International Capital Corporation Limited", "job_title": "Associate / Vice President, Operations (Middle Office)", "description": "Responsibilities:\n\nPerform daily trade processing on various products including equity, fixed income, structured products etc.\nLiaise with counterparties/external clients on trade matching/confirmations\nManage static data/closing prices in trade booking systems\nResolve trade breaks\nLiaise with Settlement Team/Business/clients to ensure successful trade settlement\nCoordinate with other internal stakeholders including Compliance, Legal & Finance on the status of trades and ensure the completion of tasks\nProvide senior management with updates on the status of trades\nSupport new products and business initiatives. Provide inputs to trade flow and booking model\nProvide user requirements and perform UAT for system enhancements/migration\nRequirements:\n\n4-5 years of solid banking experience in middle office or related role\nKnowledge of front to back process in investment bank/brokerage firms\nProven ability to work under the pressure of tight timelines\nExtremely strong problem solving skills to create workarounds to ensure successful settlement\nTeam player who can also take on responsibility for transactions front to back\nAbility to think ahead and anticipate issues in advance so they can be mitigated\nA good understanding of banking operations, clearing systems and payments\nExcellent organisational skills and communication skills in English and Chinese", "employment_types": ["Full Time", "Permanent"], "selling_points": ["Familiar with daily trade processing", "Knowledge of front to back process", "Internal stakeholder coordination"], "locations": ["Central"], "categories": ["Banking / Finance", "Credit Collection", "Order Processing & Operation / Settlement", "Risk Management"], "post_time": "2022-01-11T08:08:51Z", "salary": {"currency": null, "max": null, "min": null, "period": "monthly", "term": null}, "salary_visible": false, "title_keywords": ["vice president", "operations", "associate"], "responsibilities": ["business initiatives", "uat", "data", "systems", "coordinate with", "trade booking", "compliance", "booking", "liaise with", "senior management", "migration"], "requirements": {"degrees": [], "majors": [], "languages": ["english", "chinese"], "language_level": ["excellent"], "hard_skills": ["problem solving skills"], "soft_skills": ["communication skills", "problem solving skills", "team player", "organisational skills"], "languages_combined": [{"language": "english", "language_level": ["excellent"]}, {"language": "chinese", "language_level": ["excellent"]}]}, "experience_required": {"duration": ["4-5 years"], "field": ["related", "banking experience"]}}, {"job_id": "100003009037965", "location_code": "hk", "company": "Cheil Hong Kong Limited", "job_title": "Billing Assistant (2-3 days per week)", "description": "Responsibilities:\n\nEnsure bill payment records are updated in the system accurately and timely\nWork with internal parties to clarify and resolve any discrepancy\nVerify accuracy of billing data and work with external parties to revise any error\nProcess and verify billing data and monthly invoices\nPerform ad hoc tasks as assigned\n\n\u00a0Requirement:\n\nDiploma holder in Business Administration, Finance, Information Systems or other related discipline with minimum 1 year of relevant working experience\nWell-organized, detail-minded and proactive\nIndependent, self-motivated, analytical and able to work under tight deadlines\nGood communication skills, interpersonal skills and problem-solving skills\nGood command of spoken and written English and Chinese\nProficient in Microsoft Office applications", "employment_types": ["Part Time", "Contract"], "selling_points": ["2-3 days per week", "Detail-minded", "Experience in billing handling"], "locations": ["Sheung Wan"], "categories": ["Accounting", "Credit Control", "Others", "Banking / Finance", "Credit Collection"], "post_time": "2022-01-11T04:27:14Z", "salary": {"currency": null, "max": null, "min": null, "period": "monthly", "term": null}, "salary_visible": false, "title_keywords": ["assistant"], "responsibilities": ["invoices", "data", "external parties", "ad hoc tasks", "payment", "internal parties"], "requirements": {"degrees": ["diploma holder"], "majors": ["finance", "business administration"], "languages": ["english", "chinese"], "language_level": ["good command"], "hard_skills": ["problem-solving skills", "microsoft office"], "soft_skills": ["detail-minded", "communication skills", "self-motivated", "independent", "well-organized", "interpersonal skills", "problem-solving skills", "proactive"], "languages_combined": [{"language": "english", "language_level": ["good command"]}, {"language": "chinese", "language_level": ["good command"]}]}, "experience_required": {"duration": ["minimum 1 year"], "field": ["related", "finance", "business administration", "relevant working experience"]}}, {"job_id": "100003009028253", "location_code": "hk", "company": "Dah Sing Financial Group", "job_title": "Senior Manager, Credit", "description": "Reporting to the Head of Commercial Credit Approval, you will be responsible for providing an independent assessment of credit proposals originated from the bank\u2019s Commercial Banking Division, ensuring that they adhere to regulatory and policy guidelines and meet the bank\u2019s credit standards, before approving or supporting to higher levels for approval. You will also be responsible for post-approval monitoring of the relevant client portfolio and other credit-related duties.\nTo meet the challenge, you should have the following qualifications and attributes:\nDegree holder with minimum 8 years of credit related experience in commercial banking\nSelf-motivated and independent with an analytical mindset\nComfortable to deal with details\nGood credit assessment skill, with sound knowledge in commercial banking loan products and proficiency in analyzing complex groups\nGood verbal and written communication skills, and good team player\nPlease note that only shortlisted candidates will be notified.", "employment_types": ["Permanent"], "selling_points": ["Providing an independent assessment of credit", "Degree holder", "8 years of credit related experience"], "locations": ["North Point"], "categories": ["Banking / Finance", "Credit Analysis / Approval", "Others", "Credit Collection"], "post_time": "2022-01-07T01:53:55Z", "salary": {"currency": null, "max": null, "min": null, "period": "monthly", "term": null}, "salary_visible": false, "title_keywords": ["senior manager"], "responsibilities": ["reporting", "guidelines", "monitoring", "communication", "banking"], "requirements": {"degrees": ["degree holder"], "majors": [], "languages": [], "language_level": [], "hard_skills": ["loan products"], "soft_skills": ["communication skills", "self-motivated", "good team player", "independent", "responsible"], "languages_combined": []}, "experience_required": {"duration": ["minimum 8 years"], "field": ["related", "commercial", "banking"]}}, {"job_id": "100003009027979", "location_code": "hk", "company": "Construction Industry Council", "job_title": "Officer - Finance (Levy Section)", "description": "The applicant must possess\n\na recognised degree in legal / accounting / finance or other related discipline;\na minimum of 3 years\u2019 post-qualification work experience, preferably in law enforcement or finance and accounting or quantity surveying duties;\nexperience in NGOs or handling levy reporting or law enforcement is an advantage;\ntrack record in system implementation is a plus;\nbe proactive with strong critical mind to continuously improve levy operation;\nhigh level of integrity and sense of responsibility;\nexcellent analytical, communication and leadership skills with detailed mind;\nproficiency in Microsoft application software (including Word, Excel and PowerPoint, etc.) as well as Chinese word processing; and\ngood command of both written and spoken English and Chinese.\n(Applicants who do not possess the required qualifications and / or experience may be considered for other positions within the organisation.)\nDuties include\n\nReport to the Manager \u2013 Finance, the incumbent is expected:\n\nto perform levy inspection and prepare documents on potential offence cases;\nto collect evidence, take statements for investigation of non-compliant cases and to serve as prosecution witness in legal proceedings;\nto prepare and continuously improve reports to maintain strong corporate governance on levy;\nto work with IT and other parties for system upgrade;\nto handle levy related documents including levy forms, eForms, eServices accounts and web submissions;\nto prepare levy assessment to contractors;\nto follow up levy issues with contractors and authorized persons;\nto answer enquiries from levy payers and relevant parties;\nto perform data input and payment receipts in levy collection system; and\nto carry out any other duties as assigned from time to time by the Executive Director.\nApplications:\nThe position is on a renewable fixed-term contract (subject to performance and operational needs) for a period of 2 years.\u00a0\nPlease click the below \u201cApply Online\u201d to complete the application form and upload the updated curriculum vitae, the results of English and Chinese Language obtained in public examinations, current and expected salary together with a covering letter stating one\u2019s suitability for the job on or before 21 January 2022.\u00a0\nFor further details on CIC please refer to website: http://www.cic.hk.", "employment_types": ["Full Time", "Contract"], "selling_points": ["recognised degree in legal / accounting / finance", "minimum of 3 years\u2019 post-qualification work exp.", "perform levy inspection and prepare documents"], "locations": ["Not Specified"], "categories": ["Banking / Finance", "Corporate Finance", "Credit Collection", "Professional Services", "Legal & Compliance"], "post_time": "2022-01-07T00:47:49Z", "salary": {"currency": null, "max": null, "min": null, "period": null, "term": null}, "salary_visible": false, "title_keywords": ["officer"], "responsibilities": ["reporting", "any other duties", "software", "receipts", "related documents", "implementation", "investigation", "inspection", "communication", "data input", "payment", "maintain", "reports", "website", "prepare documents", "report"], "requirements": {"degrees": ["degree"], "majors": ["finance", "accounting"], "languages": ["english", "chinese"], "language_level": ["good command"], "hard_skills": ["excel", "plus", "chinese word processing", "web", "word", "powerpoint", "system implementation"], "soft_skills": ["sense of responsibility", "leadership skills", "integrity", "communication", "organisation", "proactive", "detailed mind"], "languages_combined": [{"language": "english", "language_level": ["good command"]}, {"language": "chinese", "language_level": ["good command"]}]}, "experience_required": {"duration": ["minimum of 3 years"], "field": ["finance", "accounting", "post-qualification"]}}, {"job_id": "100003009026296", "location_code": "hk", "company": "Hang Seng Bank Ltd", "job_title": "Director Signature/ Associate Director Signature", "description": "Retail Distribution\n\nHang Seng's Retail Distribution focuses on personal wealth management and financial services. Our one-stop wealth management initiatives are designed for both our affluent and mass integrated account customers. With more than 290 branches and automated banking centers, including around 60 Prestige Banking Centers for our high-end personal customers, we serve over half of the adult population in Hong Kong while offering an extensive range of products to our valued customers.\n\nWe are currently seeking high caliber professionals to join our department as\u00a0Director Signature/\u00a0Associate Director Signature\n\nPrincipal responsibilities\nProvide professional financial planning services to high-net-worth / top-tier Prestige Signature customers\nProvide personalized and all-rounded wealth management service for this segment of customers to build and maintain good relationships\nPromote holistic wealth management service for optimizing new business opportunities\nAssist the team head in providing coaching to Relationship Managers\nManage operational risk and observe the relevant policies / guidelines and compliance requirements\n\u00a0\u00a0\n\n\nHang Seng Bank Relationship Manager Virtual Recruitment Talk\u00a0\n\nIf you are keen to find out more about the working culture and how we nurture our Relationship Managers for their success at Hang Seng Bank, please join our Virtual Recruitment Talk\u00a0to hear the candid sharing from our Branch Networks business leaders and also our RMs. You will also find out our progressive career ladder for RMs from entry-level RM Trainee to Signature and Executive RM.\n\nDate:\u00a026 January 2022 (Wed)\n\nTime: 6:00 - 7:00 PM\n\nLocation:\u00a0Virtual Session \u2013 Dial in details will be provided upon registration\n\nRegister your place before 26 Jan 2022 by clicking\u00a0https://hsbc.zoom.us/webinar/register/WN_KABEhwC-RJqmSR07NkIS2g\u00a0\u00a0\n\nRequirements\nUniversity degree in a related discipline OR professional qualifications such as CFA, CFP or CFMP is preferred\nPasses in the Insurance Intermediaries Qualifying Examinations / Hong Kong Securities Institute Licensing Examinations\nFulfilment of the competency requirements to carry out relevant regulated activities as defined under the Securities and Futures Ordinance\nMinimum of five years' experience in selling investment, insurance and banking products\nStrong sales and customer orientation, with good communication and interpersonal skills\nStrong self-motivation and ability to work under pressure\nProficiency in both English and Chinese, with proficiency in Putonghua an advantage\nHigh level of customer centricity mindset and ability to manage complex interactions effectively\nShown strong situation awareness, strong desire to learn and able to work in Agile environment\nBe curious and with passion to think deeply and rationally\n\nIf you would like to explore other opportunities at Hang Seng Hong Kong, please visit\u00a0www.hangseng.com/careers/\u00a0for details.\n\nThe health and safety of our employees and candidates is very important to us. Due to the current situation related to the Novel Coronavirus (2019-nCoV), we\u2019re leveraging our digital capabilities to ensure we can continue to recruit top talent at the HSBC Group.\u00a0 As your application progresses, you may be asked to use one of our digital tools to help you through your recruitment journey.\u00a0 If so, one of our\u00a0 Resourcing colleagues will explain how our video-interviewing technology will be used throughout the recruitment process and will be on hand to answer any questions you might have.\nAll information provided by applicants will be used only for recruitment purposes and will be used strictly in accordance with the Bank's personal data policies, a copy of which may be obtained by the applicant upon request. Unless otherwise instructed in writing by the applicant concerned, applicants may be considered for other suitable positions within the Bank and its related companies. The personal data of unsuccessful job applicants may be retained for a maximum of two years from the date when the job application is rejected and such data may be retained for a longer period if there is a subsisting reason that obliges the Bank to do so, after which the personal data will be destroyed.", "employment_types": ["Full Time", "Permanent"], "selling_points": [], "locations": ["Not Specified"], "categories": ["Banking / Finance", "Credit Analysis / Approval", "Retail Banking", "Credit Collection"], "post_time": "2022-01-06T07:55:05Z", "salary": {"currency": null, "max": null, "min": null, "period": "monthly", "term": null}, "salary_visible": false, "title_keywords": ["associate director", "director"], "responsibilities": ["management", "guidelines", "policies", "business opportunities", "compliance", "maintain", "recruitment", "planning"], "requirements": {"degrees": ["university degree"], "majors": [], "languages": ["putonghua", "english", "chinese"], "language_level": ["advantage", "proficiency"], "hard_skills": ["agile", "professional qualifications", "cfa", "securities and futures ordinance", "reason"], "soft_skills": ["agile", "communication and interpersonal skills", "self-motivation", "novel", "work under pressure"], "languages_combined": [{"language": "putonghua", "language_level": ["proficiency", "advantage"]}, {"language": "english", "language_level": ["proficiency", "proficiency", "advantage"]}, {"language": "chinese", "language_level": ["proficiency", "proficiency", "advantage"]}]}, "experience_required": {"duration": ["minimum of five years"], "field": ["insurance", "investment", "banking"]}}, {"job_id": "100003009024616", "location_code": "hk", "company": "Dah Chong Hong Holdings Limited", "job_title": "Assistant / Accounting Officer (Contract) (Ref: GFN_CON-OTC)", "description": "The incumbent will be responsible for monitoring receivable aging and ensure timely collection of outstanding debts, performing credit assessment to existing and new credit applications with the established guidelines, ensure timely and efficient resolution of all queries, both internal and external, Issue monthly debtors' statements and subsequent demand letters, preparing AR aging reports and ad hoc assignment.\n\nHigh Diploma or Graduated in Accounting, Business Administration, or related disciplines;\n3-4 years of solid working experience in Account Receivable;\nCustomer oriented with good inter-personal and communication skills;\nGood Command of written and spoken English and Chinese.\nIndependent, proactive, detail-oriented and able to work under pressure\nProficiency in MS applications, especially MS Office and Excel & VBA;\n\nInterested candidates please send your resume by email or clicking \u201cApply Now\u201d.\n\nWe are equal opportunities employer. Applicants who are not invited within 2 months may consider their application unsuccessful. All applicants may be considered for other suitable positions with DCH Group / CITIC Pacific Group and will be deleted from our files after 6 months from the date of application.", "employment_types": ["Contract"], "selling_points": [], "locations": ["Kowloon Bay"], "categories": ["Accounting", "Accounting Clerk / Supervisor", "Credit Control", "Banking / Finance", "Credit Collection"], "post_time": "2022-01-06T01:58:27Z", "salary": {"currency": null, "max": null, "min": null, "period": "monthly", "term": null}, "salary_visible": false, "title_keywords": ["accounting officer", "assistant"], "responsibilities": ["ar", "guidelines", "work under pressure", "ad hoc assignment", "monitoring", "letters", "resolution", "communication", "reports", "administration"], "requirements": {"degrees": ["high diploma"], "majors": ["related disciplines", "accounting", "business administration"], "languages": ["english", "chinese"], "language_level": ["good command"], "hard_skills": ["excel", "vba", "ms applications", "ar", "ms office"], "soft_skills": ["efficient", "communication skills", "independent", "responsible", "inter-personal", "timely", "detail-oriented", "proactive", "work under pressure"], "languages_combined": [{"language": "english", "language_level": ["good command"]}, {"language": "chinese", "language_level": ["good command"]}]}, "experience_required": {"duration": ["3-4 years"], "field": []}}, {"job_id": "100003009019450", "location_code": "hk", "company": "PrimeCredit Ltd", "job_title": "Collection Clerk (Contract)", "description": "Responsibilities\n\nPerform collection duties on delinquent accounts\nContact customer and handle billing or overdue repayment with appropriate manner\nNegotiate with borrower for repayment schedule\nHandle enquiries related to collection matters\nPerform daily duties in compliance with the internal code of conduct and external regulations\n\nRequirements\n\nForm 5 / DSE graduates or above\nAt least 1-2 years of debt collection experience in banks or financial company is preferable\nWorking experience in customer services / telemarketing is an advantage\nFluentin spoken and written English and Cantonese\nProficient in MS applications including MS Word and Excel\nCandidate with less experience will be considered as Collection Clerk (Contract)\n\nThis is a very rewarding and exciting opportunity. We offer an attractive remuneration to the successful candidates. Please forward your resume with present and expected salary by clicking \u201cAPPLY NOW\u201d or complete the online application form at https://www.primecredit.com/career/en/jobs.\n\n\u00a0To know more about PrimeCredit, please visit our websites https://www.primecredit.com/career/en/.\n\n\u00a0All applications will be treated in strict confidence and only be used for recruitment related purpose.", "employment_types": ["Full Time", "Contract"], "selling_points": ["Perform collection duties on delinquent accounts", "Negotiate with borrower for repayment schedule", "At least 1-2 years of debt collection experience"], "locations": ["Wan Chai"], "categories": ["Admin & HR", "Clerical / Admin Staff", "Banking / Finance", "Loan", "Credit Collection"], "post_time": "2022-01-04T07:43:20Z", "salary": {"currency": null, "max": null, "min": null, "period": "monthly", "term": null}, "salary_visible": false, "title_keywords": ["clerk"], "responsibilities": ["regulations", "compliance", "handle enquiries", "contact", "schedule"], "requirements": {"degrees": ["form 5", "dse"], "majors": [], "languages": ["cantonese", "english"], "language_level": [], "hard_skills": ["excel", "ms applications", "ms word"], "soft_skills": [], "languages_combined": [{"language": "cantonese", "language_level": []}, {"language": "english", "language_level": []}]}, "experience_required": {"duration": ["at least 1-2 years"], "field": ["customer services", "financial"]}}, {"job_id": "100003009019891", "location_code": "hk", "company": "OCBC Wing Hang Credit Limited", "job_title": "Collection Associate - Consumer Loans", "description": "Responsibilities\n\u200bMonitor loans accounts and carry out appropriate actions for delinquent or problematic accounts\nPrepare and check proposals, monitoring reports and statistic reports\nTake legal action against debtors according to instructions from managers and make recommendations / suggestions on actions against debtors\nPrepare relevant documents for legal actions\nAssist managers to monitor overall performance of delinquent accounts and control delinquent ratio\nPerform administrative duties and provide clerical support\nRequirements\n\u200bHigher Diploma or above\nMinimum 2 years\u2019 relevant experience in consumer loans collection\nGood telephone manner, mature and able to work independently\nGood communication skill and emotional control\nGood concept on debt collection\nGood PC skills\n\n\n\nAttractive remuneration package will be offered to the right candidate. Please apply with full resume stating present & expected salary and contact phone number to\u00a0The Human Resources Manager, 10/F, 161 Queen\u2019s Road Central, Hong Kong.\u00a0Please quote the reference.\n\nPersonal data collected will be used for recruitment purpose only. For more information, please visit our website:\u00a0http://www.ocbcwhhk.com.", "employment_types": ["Full Time", "Permanent"], "selling_points": ["Monitor loan accounts", "Carry out actions for delinquent / problematic ac", "Prepare monitoring reports"], "locations": ["Wan Chai"], "categories": ["Accounting", "Credit Control", "Banking / Finance", "Loan", "Credit Collection"], "post_time": "2022-01-04T09:28:56Z", "salary": {"currency": null, "max": null, "min": null, "period": "monthly", "term": null}, "salary_visible": false, "title_keywords": ["associate"], "responsibilities": ["make recommendations", "provide clerical support", "control", "monitoring", "monitor", "assist managers", "reports", "administrative duties"], "requirements": {"degrees": ["diploma or above"], "majors": [], "languages": [], "language_level": [], "hard_skills": ["pc skills"], "soft_skills": ["work independently", "communication skill", "telephone manner", "mature"], "languages_combined": []}, "experience_required": {"duration": ["minimum 2 years"], "field": ["relevant experience"]}}, {"job_id": "100003009026328", "location_code": "hk", "company": "Hang Seng Bank Ltd", "job_title": "Customer Relationship Manager", "description": "Retail Distribution\n\nHang Seng's Retail Distribution focuses on personal wealth management and financial services. Our one-stop wealth management initiatives are designed for both our affluent and mass integrated account customers.\u00a0With more than\u00a0290\u00a0branches\u00a0and automated banking centres, including\u00a0around 60\u00a0Prestige\u00a0Banking Centres\u00a0for our high-end personal customers, we serve over half of the adult population in Hong Kong while offering an extensive range of products to our valued customers.\n\nWe are currently seeking a high caliber professional to join our team as\u00a0Customer Relationship Manager.\n\nPrincipal responsibilities\n\nProvide financial planning services to high-net-worth customers\nProvide personalised service for this segment of customers to build and maintain good relationships\nPromote investment, insurance and banking products for optimising new business opportunities\nManage operational risk and observe the relevant policies /guidelines and compliance requirements\u00a0\n\u00a0\n\nHang Seng Bank Relationship Manager Virtual Recruitment Talk\u00a0\n\nIf you are keen to find out more about the working culture and how we nurture our Relationship Managers for their success at Hang Seng Bank, please join our Virtual Recruitment Talk\u00a0to hear the candid sharing from our Branch Networks business leaders and also our RMs. You will also find out our progressive career ladder for RMs from entry-level RM Trainee to Signature and Executive RM.\n\nDate:\u00a026 January 2022 (Wed)\n\nTime: 6:00 - 7:00 PM\n\nLocation:\u00a0Virtual Session \u2013 Dial in details will be provided upon registration\n\nRegister your place before 26 Jan 2022 by clicking\u00a0https://hsbc.zoom.us/webinar/register/WN_KABEhwC-RJqmSR07NkIS2g\u00a0\u00a0\n\n\n\nRequirements\n\nUniversity level education is an advantage OR\nHKCEE / HKDSE (with at least passes in Chinese and Mathematics OR English and Mathematics at Grade E / Level 2 / \"Attained\" or above) plus relevant work experience\nPasses in the Insurance Intermediaries Qualifying Examinations / Hong Kong Securities Institute Licensing Examinations\u00a0\nFulfilment of the competency requirements to carry out relevant regulated activities as defined under the Securities and Futures Ordinance\nMinimum of two years' experience in selling investment, insurance and banking products\nStrong sales and customer orientation, with good communication and interpersonal skills\nStrong self-motivation and ability to work under pressure\nProficiency in both English and Chinese, with proficiency in Putonghua an advantage\nHigh level of customer centricity mindset and ability to manage complex interactions effectively\nShown strong situation awareness, strong desire to learn and able to work in Agile environment\nBe curious and with passion to think deeply and rationally\n\n(Candidates with less experience will be considered for the position of\u00a0Senior Customer Relationship Officer)\n\nIf you would like to explore other opportunities at Hang Seng Hong Kong, please visit www.hangseng.com/careers/ for details.\n\nThe health and safety of our employees and candidates is very important to us. Due to the current situation related to the Novel Coronavirus (2019-nCoV), we\u2019re leveraging our digital capabilities to ensure we can continue to recruit top talent at the HSBC Group.\u00a0 As your application progresses, you may be asked to use one of our digital tools to help you through your recruitment journey.\u00a0 If so, one of our\u00a0 Resourcing colleagues will explain how our video-interviewing technology will be used throughout the recruitment process and will be on hand to answer any questions you might have.\n\nAll information provided by applicants will be used only for recruitment purposes and will be used strictly in accordance with the Bank's personal data policies, a copy of which may be obtained by the applicant upon request. Unless otherwise instructed in writing by the applicant concerned, applicants may be considered for other suitable positions within the Bank and its related companies. The personal data of unsuccessful job applicants may be retained for a maximum of two years from the date when the job application is rejected and such data may be retained for a longer period if there is a subsisting reason that obliges the Bank to do so, after which the personal data will be destroyed.", "employment_types": ["Full Time", "Permanent"], "selling_points": [], "locations": ["Not Specified"], "categories": ["Banking / Finance", "Credit Analysis / Approval", "Retail Banking", "Credit Collection"], "post_time": "2022-01-06T07:58:27Z", "salary": {"currency": null, "max": null, "min": null, "period": "monthly", "term": null}, "salary_visible": false, "title_keywords": ["relationship manager"], "responsibilities": ["guidelines", "policies", "business opportunities", "compliance", "maintain", "recruitment", "banking", "insurance", "planning"], "requirements": {"degrees": ["hkdse"], "majors": ["mathematics"], "languages": ["putonghua", "english", "chinese"], "language_level": ["advantage", "proficiency"], "hard_skills": ["plus", "securities and futures ordinance", "agile", "reason"], "soft_skills": ["agile", "communication and interpersonal skills", "self-motivation", "novel", "work under pressure"], "languages_combined": [{"language": "putonghua", "language_level": ["proficiency", "advantage"]}, {"language": "english", "language_level": ["proficiency", "proficiency", "advantage"]}, {"language": "chinese", "language_level": ["proficiency", "proficiency", "advantage"]}]}, "experience_required": {"duration": ["minimum of two years"], "field": ["insurance", "investment", "banking"]}}, {"job_id": "100003009026354", "location_code": "hk", "company": "Hang Seng Bank Ltd", "job_title": "Executive Customer Relationship Manager", "description": "Retail Distribution\n\nHang Seng's Retail Distribution focuses on personal wealth management and financial services. Our one-stop wealth management initiatives are designed for both our affluent and mass integrated account customers. With more than 170 branches and automated banking centres, including over 50 Prestige Banking Centres for our high-end personal customers, we serve over half of the adult population, offering an extensive range of products.\n\nWe are currently seeking a high caliber professional to join our team as\u00a0Executive Customer Relationship Manager.\n\nPrincipal responsibilities\n\nProvide financial planning services to high-net-worth customers\nProvide personalised service for this segment of customers to build and maintain good relationships\nPromote investment, insurance and banking products for optimising new business opportunities\nAssist the team head in providing coaching to Relationship Managers\nManage operational risk and observe the relevant policies /guidelines and compliance requirements\n\nHang Seng Bank Relationship Manager Virtual Recruitment Talk\u00a0\n\nIf you are keen to find out more about the working culture and how we nurture our Relationship Managers for their success at Hang Seng Bank, please join our Virtual Recruitment Talk\u00a0to hear the candid sharing from our Branch Networks business leaders and also our RMs. You will also find out our progressive career ladder for RMs from entry-level RM Trainee to Signature and Executive RM.\n\nDate:\u00a026 January 2022 (Wed)\n\nTime: 6:00 - 7:00 PM\n\nLocation:\u00a0Virtual Session \u2013 Dial in details will be provided upon registration\n\nRegister your place before 26 Jan 2022 by clicking\u00a0https://hsbc.zoom.us/webinar/register/WN_KABEhwC-RJqmSR07NkIS2g\u00a0\u00a0\n\n\n\nRequirements\n\nUniversity degree in a related discipline OR professional qualifications such as CFA, CFP or CFMP is preferred\nPasses in the Insurance Intermediaries Qualifying Examinations / Hong Kong Securities Institute Licensing Examinations\nFulfilment of the competency requirements to carry out relevant regulated activities as defined under the Securities and Futures Ordinance\nMinimum of five years' experience in selling investment, insurance and banking products\nStrong sales and customer orientation, with good communication and interpersonal skills\nStrong self-motivation and ability to work under pressure\nProficiency in both English and Chinese, with proficiency in Putonghua an advantage\nHigh level of customer centricity mindset with dedication to deliver exceptional quality services for customers\nIf you would like to explore other opportunities at Hang Seng Hong Kong, please visit\u00a0www.hangseng.com/careers/\u00a0for details.\n\n\n\n\nThe health and safety of our employees and candidates is very important to us. Due to the current situation related to the Novel Coronavirus (2019-nCoV), we\u2019re leveraging our digital capabilities to ensure we can continue to recruit top talent at the HSBC Group.\u00a0 As your application progresses, you may be asked to use one of our digital tools to help you through your recruitment journey.\u00a0 If so, one of our\u00a0 Resourcing colleagues will explain how our video-interviewing technology will be used throughout the recruitment process and will be on hand to answer any questions you might have.\n\n\n\nAll information provided by applicants will be used only for recruitment purposes and will be used strictly in accordance with the Bank's personal data policies, a copy of which may be obtained by the applicant upon request. Unless otherwise instructed in writing by the applicant concerned, applicants may be considered for other suitable positions within the Bank and its related companies. The personal data of unsuccessful job applicants may be retained for a maximum of two years from the date when the job application is rejected and such data may be retained for a longer period if there is a subsisting reason that obliges the Bank to do so, after which the personal data will be destroyed.", "employment_types": ["Full Time", "Permanent"], "selling_points": [], "locations": ["Not Specified"], "categories": ["Banking / Finance", "Credit Analysis / Approval", "Retail Banking", "Credit Collection"], "post_time": "2022-01-06T08:01:33Z", "salary": {"currency": null, "max": null, "min": null, "period": "monthly", "term": null}, "salary_visible": false, "title_keywords": ["executive", "relationship manager"], "responsibilities": ["guidelines", "policies", "business opportunities", "compliance", "maintain", "recruitment", "banking", "insurance", "planning"], "requirements": {"degrees": ["university degree"], "majors": [], "languages": ["putonghua", "english", "chinese"], "language_level": ["advantage", "proficiency"], "hard_skills": ["cfa", "reason", "securities and futures ordinance", "professional qualifications"], "soft_skills": ["novel", "communication and interpersonal skills", "self-motivation", "work under pressure"], "languages_combined": [{"language": "putonghua", "language_level": ["proficiency", "advantage"]}, {"language": "english", "language_level": ["proficiency", "proficiency", "advantage"]}, {"language": "chinese", "language_level": ["proficiency", "proficiency", "advantage"]}]}, "experience_required": {"duration": ["minimum of five years"], "field": ["insurance", "investment", "banking"]}}, {"job_id": "100003009027232", "location_code": "hk", "company": "DBS Bank Ltd", "job_title": "VP, Team Lead, Credit Risk Management, Consumer Banking", "description": "Business Function\u00a0\n\nRisk Management Group (RMG) is responsible for the development and maintenance of risk management and internal control frameworks. We provide independent review and challenge to business to ensure that appropriate balance is considered in risk/return decisions. In addition, RMG is responsible for the monitoring and reporting on key risk issues of the Bank. To manage risk effectively and deliver strong financial performance, we invest significantly in our people and infrastructure.\n\nResponsibilities\n\nDevelop resource plan and streamline operating process and procedure to maintain and enhance various application turnaround\nMonitor quality control report to improve credit quality and data accuracy in credit approval process\nAssess and approve new secured / unsecured product applications, portfolio credit limit management and recommend deviation in credit underwriting process\nCoordinate and conduct UAT test for system / project development\nEnhance existing risk governance framework such as improving quality assurance framework and monitoring critical trigger.\nEnsure and maintain good credit quality and data accuracy in credit underwriting process\nMaintain and enhance various application service turnaround\n\nRequirement\n\nBachelor Degree or above major in Statistics / Finance / Business Administration\nMinimum 12 years on credit underwriting process / risk management / policy formulation in major financial institutions\nProven working experience as credit underwriting manager or credit risk manager\nStrong credit sense and judgment skills with good product knowledge in consumer lending product, with additional knowledge on investment lending product is preferred.\nStrong analytical skills with the ability to collect, organize, analyze, and disseminate information with attention to detail and accuracy\nA team player to work with other credit units / other departments in result delivery\n\nApply Now\n\nWe offer a competitive salary and benefits package and the professional advantages of a dynamic environment that supports your development and recognises your achievements.\n\nWe regret only shortlisted candidates will be notified.", "employment_types": ["Full Time"], "selling_points": ["Pension Fund Scheme", "Medical Coverage for Family", "Extra Day Off"], "locations": ["Quarry Bay"], "categories": ["Accounting", "Credit Control", "Banking / Finance", "Credit Analysis / Approval", "Credit Collection"], "post_time": "2022-01-06T09:26:01Z", "salary": {"currency": null, "max": null, "min": null, "period": "monthly", "term": null}, "salary_visible": false, "title_keywords": ["credit risk management", "lead"], "responsibilities": [], "requirements": {"degrees": [], "majors": [], "languages": [], "language_level": [], "hard_skills": [], "soft_skills": [], "languages_combined": []}, "experience_required": {"duration": [], "field": []}}, {"job_id": "100003009020707", "location_code": "hk", "company": "Hang Seng Bank Ltd", "job_title": "Onboarding Specialist", "description": "Retail Distribution\n\nHang Seng's Retail Distribution focuses on personal wealth management and financial services. Our one-stop wealth management initiatives are designed for both our affluent and mass integrated account customers.\u00a0With more than\u00a0290\u00a0branches\u00a0and automated banking centres, including\u00a0around 60\u00a0Prestige\u00a0Banking Centres\u00a0for our high-end personal customers, we serve over half of the adult population in Hong Kong while offering an extensive range of products to our valued customers.\n\nWe are currently seeking a high caliber professional to join our team as\u00a0Onboarding Specialist.\n\n\n\nPrincipal responsibilities\n\nSupport the team to achieve service excellence in account opening,\u00a0 account maintenance and transactions follow-up for offshore and mainland customers, conduct Risk Profiling Questionnaires, resolve customer enquiries on transactional needs and provide operational support in customer servicing\nCollaborate closely with other departments to ensure that customer instructions are executed accurately and in a timely manner\nImprove customer experience by collating customer feedback, identifying areas to improve such as operational, administrative, processes and competitiveness of products and services\nResolve operational issues and ensure smooth daily administration and operation in the team\u00a0\n\nRequirements\n\nAssociate degree or Higher diploma or HKCEE / HKDSE holder,\u00a0less academically qualified candidates with relevant work experience will also be considered\nHKCEE / HKDSE (with at least passes in Chinese and Mathematics OR English and Mathematics at Grade E / Level 2 / \"Attained\" or above) plus relevant work experience\nPasses in the\u00a0Hong Kong Securities Institute Licensing Examinations\u00a0and fulfil the competency requirements to carry out regulated activities as defined under the Regulator\nMinimum 2 years of work experience including 1 year of financial services work experience\nGood knowledge of wealth management products, both investment and insurance\nGood understanding of branch services and operations\nCustomer oriented with strong language skills and service mindset, ability to capture customer financial needs and make referrals where appropriate\nHigh proficiency in Mandarin is a MUST\u00a0Good command of Cantonese and English is an advantage.\u00a0\n\n(Candidates with less experience will be considered for the\u00a0lower level position)\n\nIf you would like to explore other opportunities at Hang Seng Hong Kong, please visit www.hangseng.com/careers/ for details.\n\n\n\nThe health and\u00a0safety of our employees and candidates is very important to us. Due to the current situation\u00a0related to the Novel Coronavirus (2019-nCoV), we're leveraging our digital capabilities to ensure we can continue to recruit top talent at the HSBC Group. As your application progresses, you may be asked to use one of our digital tools to help you through your recruitment journey. If so, one\u00a0of our Resourcing colleagues will explain how our video interviewing technology will be used throughout the recruitment process and will be on hand to answer any questions you might have.\u00a0\u00a0\n\n\nAll information provided by applicants will be used only for recruitment purposes and will be used strictly in accordance with the Bank's personal data policies, a copy of which may be obtained by the applicant upon request. Unless otherwise instructed in writing by the applicant concerned, applicants may be considered for other suitable positions within the Bank and its related companies. The personal data of unsuccessful job applicants may be retained for a maximum of two years from the date when the job application is rejected and such data may be retained for a longer period if there is a subsisting reason that obliges the Bank to do so, after which the personal data will be destroyed.", "employment_types": ["Full Time", "Permanent"], "selling_points": [], "locations": ["Not Specified"], "categories": ["Banking / Finance", "Credit Analysis / Approval", "Retail Banking", "Credit Collection"], "post_time": "2022-01-05T01:15:55Z", "salary": {"currency": null, "max": null, "min": null, "period": "monthly", "term": null}, "salary_visible": false, "title_keywords": ["specialist"], "responsibilities": ["collaborate", "operational support", "customer enquiries", "account opening", "a timely manner", "transactions", "resolve operational issues", "account maintenance", "support the team", "administration"], "requirements": {"degrees": ["associate degree", "diploma", "hkdse"], "majors": ["mathematics"], "languages": ["cantonese", "english", "chinese", "mandarin"], "language_level": ["advantage", "proficiency", "good command"], "hard_skills": ["make", "plus", "reason"], "soft_skills": ["novel"], "languages_combined": [{"language": "cantonese", "language_level": ["advantage", "good command"]}, {"language": "english", "language_level": ["advantage", "good command"]}, {"language": "chinese", "language_level": []}, {"language": "mandarin", "language_level": ["proficiency", "advantage", "good command"]}]}, "experience_required": {"duration": ["1 year", "minimum 2 years"], "field": ["financial services"]}}, {"job_id": "100003009029859", "location_code": "hk", "company": "Shenwan Hongyuan Securities (H.K.) Ltd.", "job_title": "Associate, Credit (Ref: C/AC/01-22)", "description": "Duties & responsibilities:\n\nPrepare credit proposal for management review and approval;\nPrepare reports for Credit Committee meeting;\nMonitor client positions on wide range of products, including securities and derivatives products;\nConduct margin calls and ensure all trades transacted comply with the credit control policies;\nParticipate in various system enhancements and projects implementation to meet business demands.\n\nRequirements:\n\nBachelor Degree holder in Finance, Business or related discipline;\nPossess good knowledge in financial products, such as Bonds, Equity and index / commodities future etc.;\nRelevant experience, preferably in banking / Financial institution;\nA good team player, quick learner, self-motivated with strong sense of responsibility and discipline;\nGood command of written and spoken English, Chinese and Mandarin;\n\nWe offer attractive remuneration package and fringe benefits including 5-day week to the right candidate.\u00a0 Interested parties please send your application letter with resume stating present and expected salary to Human Resources Department by clicking\u00a0\"Apply Now\", or mail to Level 17, 28 Hennessy Road, Hong Kong. (Please quote the reference of the post on the envelope)\u00a0.\nAll information received will be kept in strict confidence and only for recruitment-related purposes.\n\nAll information received will be kept in strict confidence and only for recruitment-related purposes.", "employment_types": ["Full Time", "Permanent"], "selling_points": [], "locations": ["Admiralty"], "categories": ["Banking / Finance", "Others", "Credit Collection"], "post_time": "2022-01-07T06:18:38Z", "salary": {"currency": null, "max": null, "min": null, "period": null, "term": null}, "salary_visible": false, "title_keywords": ["associate"], "responsibilities": ["control", "policies", "monitor", "implementation", "prepare reports", "management review"], "requirements": {"degrees": ["bachelor degree holder"], "majors": ["finance", "business"], "languages": ["english", "chinese", "mandarin"], "language_level": ["good command"], "hard_skills": [], "soft_skills": ["good team player", "self-motivated", "quick learner", "sense of responsibility"], "languages_combined": [{"language": "english", "language_level": ["good command"]}, {"language": "chinese", "language_level": ["good command"]}, {"language": "mandarin", "language_level": ["good command"]}]}, "experience_required": {"duration": [], "field": ["relevant experience", "financial", "banking"]}}, {"job_id": "100003009015059", "location_code": "hk", "company": "Servcorp HK Central Limited", "job_title": "Credit Control & Customer Service Officer", "description": "Job Highlights\n\u00a0Competitive Salary\n\u00a0Opportunities for regional role\n\u00a0Can-do attitude\nJob Description\n\nCredit Control & Customer Service Officer\n\nGreat job, great offices, global company!\n\nServcorp provides the highest quality workspace solutions and 5-star services to start-ups, SME\u2019s and multinational corporations. Our Hong Kong offices has been operating for twenty years with branches located in prime positions.\u00a0\n\nWe are an international company, market leader in its field, with offices worldwide. We are currently recruiting for a Credit Control Officer to be based at our prestigious offices in Central. This is a Full Time Permanent Position, working Monday - Friday from 9am - 6pm\n\nJob Details:\nAs a dedicated and motivated team player your duties will include but not be limited to:\n\nFollowing procedures and policies that ensure timely payments, while maintaining a high level of client retention\nPosting and allocation of all customer daily payments in line with daily time lines\nReconciling unallocated payments\nHandling Small Claims litigation matters for defaulted payments\nWork with Management to improve on existing credit control system\nEnsuring credit and collection policies and procedures are followed within the team\nAssisting with new account applications by obtaining AML documents\nLiaising with clients, as well as internal personnel including the sales team\nPreparing reports and working closely with the accounts team\nBenefits:\nWork in a five-star environment located in Central and Tsim Sha Tsui\nAttractive salary\u00a0\nFull and professional training provided\nMedical scheme\nSkills development and growth opportunities for promotion and advancement\n\nRequirements:\n\nHigher diploma or above\nMinimum 1 - 2 years\u2019 experience in a similar role\nGood command of written and spoken English and Chinese, including Cantonese & Mandarin\nGood MS Office and Chinese word processing skills\nGood communication skills with the ability to deal with people at all levels\nAn eye for detail\nWorks well under pressure with the ability to prioritise\nWorks independently with minimum supervision, as well as a team player", "employment_types": ["Full Time"], "selling_points": ["Salary", "Career Development", "International Company"], "locations": ["Central"], "categories": ["Banking / Finance", "Credit Collection", "Sales, CS & Business Devpt", "Customer Service - Supervisor / Officer", "Account Servicing"], "post_time": "2022-01-03T20:52:10Z", "salary": {"currency": null, "max": null, "min": null, "period": "monthly", "term": null}, "salary_visible": false, "title_keywords": ["customer service officer"], "responsibilities": ["control", "work with management", "aml", "maintaining", "policies", "quality", "procedures", "liaising with", "customer service", "payments", "sales team", "preparing reports", "sme"], "requirements": {"degrees": [], "majors": [], "languages": [], "language_level": [], "hard_skills": [], "soft_skills": [], "languages_combined": []}, "experience_required": {"duration": [], "field": []}}, {"job_id": "100003009023409", "location_code": "hk", "company": "Rise Associates Asia Limited", "job_title": "Accounting Officer - AR & Credit Control (Property Developer)", "description": "Our client is one of the largest property developers in Hong Kong with an extensive portfolio in Mainland China. Due to continuous development, they are looking for an Accounting Officer to assist in AR functions.\n\u00a0\nJob Descriptions:\n\nMainly perform Accounts Receivables duties\nAssist in daily accounting operations and month-end / year-end closing\nAssist in monitoring outstanding accounts and perform debt collection actions via telephone or email\nHandle customers inquires and complaints on billing issues\nAssist in\u00a0preparing analysis reports for the review of management\nLiaise with other departments in resolving disputes and outstanding accounts\nParticipate in ad hoc projects\nRequirements:\n\nHigher Diploma / Degree holder in Business Administration or Accounting or related disciplines\n5 years or above accounting experience, preferably in credit administration, credit control and debt collection\nGood reporting and coordinating skills for credit control\nGood communication skills\nProficiency in Microsoft Word and Excel Applications", "employment_types": ["Permanent"], "selling_points": ["Perform AR duties & monitor outstanding A/C", "Good communication skill", "Stable platform with good career prospect"], "locations": ["Not Specified"], "categories": ["Accounting", "Accounting Clerk / Supervisor", "Credit Control", "Banking / Finance", "Credit Collection"], "post_time": "2022-01-05T08:35:25Z", "salary": {"currency": null, "max": null, "min": null, "period": "monthly", "term": null}, "salary_visible": false, "title_keywords": ["developer", "accounting officer"], "responsibilities": ["management", "analysis reports", "monitoring", "review", "month-end", "daily accounting operations", "debt collection", "ad hoc projects", "year-end closing", "liaise with"], "requirements": {"degrees": ["diploma", "degree holder"], "majors": ["related disciplines", "accounting", "business administration"], "languages": [], "language_level": [], "hard_skills": ["excel", "microsoft word"], "soft_skills": ["communication skills"], "languages_combined": []}, "experience_required": {"duration": ["5 years"], "field": ["accounting experience", "administration"]}}, {"job_id": "100003009027226", "location_code": "hk", "company": "DBS Bank Ltd", "job_title": "VP, Specialist, Credit Risk Management, SME Banking", "description": "Business Function\u00a0\n\nRisk Management Group (RMG) is responsible for the development and maintenance of risk management and internal control frameworks. We provide independent review and challenge to business to ensure that appropriate balance is considered in risk/return decisions. In addition, RMG is responsible for the monitoring and reporting on key risk issues of the Bank. To manage risk effectively and deliver strong financial performance, we invest significantly in our people and infrastructure.\n\nResponsibilities\n\nReview and approve credit applications\nEnsure and maintain good credit quality and data accuracy in credit underwriting process\nEnsure adherence to credit process and regulatory requirement\nWork closely with partners in building, implementing digital lending strategies\nCollaborates with stakeholders to ensure project scope definition meets business objectives\nMaintain and enhance various application service turnaround\n\nRequirement\n\nBachelor Degree or above major in Statistics / Finance / Business Administration\nHolder of Enhanced Competency Framework on\u00a0Credit Risk Management (ECF-CRM) is preferred\nMinimum 10 years on credit underwriting process / risk management / policy formulation in major financial institutions\nProven working experience as credit risk manager\nStrong credit sense and judgment skills with good product knowledge in commercial lending product, additional knowledge on digital lending product, credit modeling is preferred.\nStrong analytical skills with the ability to collect, organize, analyze, and disseminate information with attention to detail and accuracy\nA team player to work with other credit units / other departments in result delivery\nStrong written and verbal communication skills with the ability to present analysis in a succinct manner\n\nApply Now\n\nWe offer a competitive salary and benefits package and the professional advantages of a dynamic environment that supports your development and recognises your achievements.\n\nWe regret only shortlisted candidates will be notified.", "employment_types": ["Full Time"], "selling_points": ["Pension Fund Scheme", "Medical Coverage for Family", "Flexible Working Arrangement"], "locations": ["Others"], "categories": ["Accounting", "Credit Control", "Banking / Finance", "Credit Analysis / Approval", "Credit Collection"], "post_time": "2022-01-06T09:25:41Z", "salary": {"currency": null, "max": null, "min": null, "period": "monthly", "term": null}, "salary_visible": false, "title_keywords": ["specialist", "credit risk management"], "responsibilities": [], "requirements": {"degrees": [], "majors": [], "languages": [], "language_level": [], "hard_skills": [], "soft_skills": [], "languages_combined": []}, "experience_required": {"duration": [], "field": []}}, {"job_id": "100003009020694", "location_code": "hk", "company": "Hang Seng Bank Ltd", "job_title": "Relationship Manager", "description": "Retail Distribution\n\n\nHang Seng's Retail Distribution focuses on personal wealth management and financial services. Our one-stop wealth management initiatives are designed for both our affluent and mass integrated account customers.\u00a0With more than\u00a0290\u00a0branches\u00a0and automated banking centres, including\u00a0around 60\u00a0Prestige\u00a0Banking Centres\u00a0for our high-end personal customers, we serve over half of the adult population in Hong Kong while offering an extensive range of products to our valued customers.\n\nWe are currently seeking a high caliber professional to join our team as\u00a0Relationship Manager.\n\n\n\nPrincipal responsibilities\n\nAcquire, maintain and develop sustainable relationships with mainlander customer through account servicing and focus on retail banking products\nProvide dedicated support to offshore and mainland customers by identifying their financial and other banking needs, then making referrals to Branch RM\nProvide personalized account services to promote HASE\u2019s brand, handle customers\u2019 account opening matters and coordinate with other relevant departments for completing account opening procedures\nCollaborate closely with other departments to ensure that customer instructions are executed accurately and in a timely manner\u00a0\n\n\n\nRequirements\n\nUniversity level education is an advantage\u00a0preferably in finance, business or a related discipline\u00a0OR\nHKCEE / HKDSE (with at least passes in Chinese and Mathematics OR English and Mathematics at Grade E / Level 2 / \"Attained\" or above) plus relevant work experience\nPasses in the\u00a0Hong Kong Securities Institute Licensing Examinations\u00a0and fulfil the competency requirements to carry out regulated activities as defined under the Regulator\nMinimum 2 years direct sales experience in banking industry\nGood knowledge of wealth management products, both investment and insurance\nGood understanding of branch services and operations\nCustomer oriented with strong language skills and service mindset, ability to capture customer financial needs and make referrals where appropriate\nHigh proficiency in Mandarin is a MUST. Good command of Cantonese and English is an advantage\n\n(Candidates with less experience will be considered for the\u00a0lower level position)\n\nIf you would like to explore other opportunities at Hang Seng Hong Kong, please visit www.hangseng.com/careers/ for details.\n\nThe health and safety of our employees and candidates is very important to us. Due to the current situation related to the Novel Coronavirus (2019-nCoV), we\u2019re leveraging our digital capabilities to ensure we can continue to recruit top talent at the HSBC Group. \u00a0As your application progresses, you may be asked to use one of our digital tools to help you through your recruitment journey.\u00a0 If so, one of our Resourcing colleagues will explain how our video-interviewing technology will be used throughout the recruitment process and will be on hand to answer any questions you might have.\u00a0\n\nAll information provided by applicants will be used only for recruitment purposes and will be used strictly in accordance with the Bank's personal data policies, a copy of which may be obtained by the applicant upon request. Unless otherwise instructed in writing by the applicant concerned, applicants may be considered for other suitable positions within the Bank and its related companies. The personal data of unsuccessful job applicants may be retained for a maximum of two years from the date when the job application is rejected and such data may be retained for a longer period if there is a subsisting reason that obliges the Bank to do so, after which the personal data will be destroyed.", "employment_types": ["Full Time", "Permanent"], "selling_points": [], "locations": ["Not Specified"], "categories": ["Banking / Finance", "Credit Analysis / Approval", "Retail Banking", "Credit Collection"], "post_time": "2022-01-05T01:08:43Z", "salary": {"currency": null, "max": null, "min": null, "period": "monthly", "term": null}, "salary_visible": false, "title_keywords": ["relationship manager"], "responsibilities": ["collaborate", "account opening", "coordinate with", "procedures", "a timely manner", "develop", "maintain", "banking"], "requirements": {"degrees": ["hkdse"], "majors": ["mathematics"], "languages": ["cantonese", "english", "chinese", "mandarin"], "language_level": ["advantage", "proficiency", "good command"], "hard_skills": ["make", "plus", "reason"], "soft_skills": ["novel"], "languages_combined": [{"language": "cantonese", "language_level": ["advantage", "good command"]}, {"language": "english", "language_level": ["advantage", "good command"]}, {"language": "chinese", "language_level": []}, {"language": "mandarin", "language_level": ["proficiency"]}]}, "experience_required": {"duration": ["minimum 2 years"], "field": ["banking industry"]}}, {"job_id": "100003009013011", "location_code": "hk", "company": "DHL EXPRESS (HONG KONG) LIMITED", "job_title": "Credit Agent / Accounts Receivable Assistant", "description": "Working Location: Ngau Tau Kok\nReporting to Credit Supervisor, you will be responsible for managing credit control and payment collection of corporate customers.\nResponsibilities:\nParticipate in payment collection plan formulation\nCommunicate with corporate customers for overdue payment collection\nCoordinate with customers and internal parties to resolve credit and billing issues\nMaintain daily payment collection records and prepare regular reports\nMaintain good relationship with customers while meeting business targets\nRequirements:\nDiploma holder with 2 years\u2019 experience in credit control or accounting field with customer interface exposure\nEffective communication and telephone handling skills\nCustomer-oriented and able to solve customer problems independently\nSelf-initiative, able to work with tight deadlines and under pressure\nExperience in using accountings systems is an advantage\nGood command in spoken and written English and Chinese (Cantonese and Mandarin)\nProficient with MS Office applications, especially Excel\nApplication:\nClick \"Apply Now\" or apply on line via the following link: https://dhlexpress.taleo.net/careersection/ex/jobdetail.ftl?job=2100CSO&iniurl.src=CWS-10001&tz=GMT%2B08%3A00&tzname=\nalso indicating your current and expected salary, and availability.\u00a0 For more job opportunities, please visit our website at https://www.dpdhl.jobs/\nPersonal Information Collection Statement pertaining to Recruitment\nDHL Express (Hong Kong) Limited / DHL Aviation (Hong Kong) Limited (\u201cDHL\u201d) is committed to protecting and respecting your privacy in accordance with the Personal Data (Privacy) Ordinance of Hong Kong (the \u201cOrdinance\u201d) and DHL\u2019s Personal Data Protection Policy (the \u201cPolicy\u201d) at\u00a0https://www.dhl.com/hk-en/home/footer/local-privacy-notice.html\nBy proceeding to respond to this recruitment advertisement, you consent that we may use, retain, process, transfer or otherwise handle the personal data that we collect from you for recruitment,\u00a0 application processing, assessment and communication purposes (including any other purposes directly related thereto) in accordance with the Policy.\nAll personal data of unsuccessful applicants will be retained for future recruitment purposes for a period of not more than two (2) years after which such data will be destroyed.\nYou have the right at any time to make a data access or correction request concerning your personal data held by us. In addition, you may request us to delete your personal data that is no longer required for the relevant purposes which you have given consent. Should you wish to exercise such rights or have any question in relation to your personal data or the Policy, please contact our Human Resources Division in writing.\n", "employment_types": ["Full Time"], "selling_points": ["Participate in payment collection plan", "Diploma holder with 2 years\u2019 experience", "Experience in using accountings systems"], "locations": ["Ngau Tau Kok"], "categories": ["Accounting", "Accounting Clerk / Supervisor", "Credit Control", "Banking / Finance", "Credit Collection"], "post_time": "2022-01-03T01:07:56Z", "salary": {"currency": null, "max": null, "min": null, "period": "monthly", "term": null}, "salary_visible": false, "title_keywords": ["assistant"], "responsibilities": ["communicate with", "payment collection", "coordinate with", "maintain good relationship", "maintain", "reports", "plan", "internal parties"], "requirements": {"degrees": ["diploma holder"], "majors": ["accounting"], "languages": ["cantonese", "english", "chinese", "mandarin"], "language_level": ["good command"], "hard_skills": ["excel", "no", "html", "make", "processing", "ms office"], "soft_skills": ["independently", "under pressure", "communication", "committed", "customer-oriented", "self-initiative"], "languages_combined": [{"language": "cantonese", "language_level": ["good command"]}, {"language": "english", "language_level": ["good command"]}, {"language": "chinese", "language_level": ["good command"]}, {"language": "mandarin", "language_level": ["good command"]}]}, "experience_required": {"duration": ["2 years"], "field": ["accounting"]}}, {"job_id": "100003009025333", "location_code": "hk", "company": "China Construction Bank (Asia) Corporation Limited", "job_title": "Assistant Officer, Authorization (Credit Card Focus)", "description": "Responsibilities:\n\nDeal with authorization requests related to cardholders up to the credit limit set for purchases and cash advances.\nHandle reporting lost card for VISA, MasterCard and UnionPay Card.\nMonitor account\u2019s activities to detect possible fraud transaction.\nRequirements:\n\nDiploma graduate with minimum 3 years\u2019 relevant experience in credit card authorization field\u00a0\nGood credit sense and sound knowledge of VISA, MasterCard and UnionPay operation.\nBe customer oriented with good negotiation, communication and interpersonal skills.\nWilling to work off-hours / shift duty.\nGood command of written and spoken English and Chinese, preferably proficiency in Putonghua\nKnowledge of PC software application (Word, Excel)", "employment_types": ["Full Time", "Permanent"], "selling_points": ["Credit card authorization & lost reporting", "Fraud transaction monitoring", "3 years\u2019 relevant experience in credit card"], "locations": ["Kowloon Bay"], "categories": ["Accounting", "Credit Control", "Admin & HR", "Administration / Operation Manager", "Banking / Finance", "Credit Collection"], "post_time": "2022-01-06T04:09:56Z", "salary": {"currency": null, "max": null, "min": null, "period": "monthly", "term": null}, "salary_visible": false, "title_keywords": ["assistant officer"], "responsibilities": ["reporting", "monitor"], "requirements": {"degrees": ["diploma"], "majors": [], "languages": ["putonghua", "english", "chinese"], "language_level": ["proficiency", "good command"], "hard_skills": ["pc", "word", "excel"], "soft_skills": ["communication and interpersonal skills", "negotiation"], "languages_combined": [{"language": "putonghua", "language_level": ["proficiency", "good command"]}, {"language": "english", "language_level": ["proficiency", "good command"]}, {"language": "chinese", "language_level": ["proficiency", "good command"]}]}, "experience_required": {"duration": ["minimum 3 years"], "field": ["credit card", "relevant experience"]}}, {"job_id": "100003009019264", "location_code": "hk", "company": "Hang Seng Bank Ltd", "job_title": "Prestige Sales Leader/Manager (Offshore)", "description": "Retail Distribution\n\nHang Seng's Retail Distribution focuses on personal wealth management and financial services. Our one-stop wealth management initiatives are designed for both our affluent and mass integrated account customers.\u00a0With more than\u00a0290\u00a0branches\u00a0and automated banking centres, including\u00a0around 60\u00a0Prestige\u00a0Banking Centres\u00a0for our high-end personal customers, we serve over half of the adult population in Hong Kong while offering an extensive range of products to our valued customers.\n\nWe are currently seeking a high caliber professional to join our team as\u00a0Prestige Sales Leader/Manager (Offshore)\n\nPrincipal responsibilities\n\nFormulate and implement localized sales and marketing plans for the offshore centre to achieve the assigned business targets, as well as direct and manage the operation of the centre to maximize service quality and productivity\nSupport the section head to manage the RM team to acquire, retain and develop sustainable relationships of high-net-worth, mainlander and offshore customers to achieve assigned KPIs\nSolicit new business to identify opportunities for wealth management penetration and grow revenue\nDevelop relationship management systems and implement various customer loyalty programs to maximize customer loyalty and monitor customer attrition rate\nMaintain close working relationships with different stakeholders and product owners to execute strategy, sales and service model for offshore banking business\nOrganize product briefing, experience sharing and role play sessions to enhance team members\u2019 product/ investment knowledge and selling skills\nManage operational risk, including its identification, assessment, mitigation and controls, loss identification and reporting by observing the relevant policies and guidelines issued by the Bank and the Group\n\nRequirements\n\nUniversity degree in Business Administration or other relevant qualifications such as CFP, CFMP or CRWP\nMinimum 10 years of sales experience including 5 years in managing the portfolio of high net worth customers\nExposure to Mainland market segment and have solid experience in handling mainlander and offshore customers will be an advantage\nGood communication, interpersonal and analytical skills\nStrong self-motivation and drive to succeed, with ability to work under pressure\nHigh proficiency in Mandarin is a MUST, Proficiency in both English and Chinese\nHigh level of customer centricity mindset with dedication to deliver exceptional quality services for customers and manage complex interactions effectively\nShown strong situation awareness, strong desire to learn and able to work in Agile environment\nAble to inspire others to achieve their goals/ambitions in a variety of situations\n\nIf you would like to explore other opportunities at Hang Seng Hong Kong, please visit www.hangseng.com/careers/ for details.\n\nThe health and safety of our employees and candidates is very important to us. Due to the current situation related to the Novel Coronavirus (2019-nCoV), we\u2019re leveraging our digital capabilities to ensure we can continue to recruit top talent at the HSBC Group. As your application progresses, you may be asked to use one of our digital tools to help you through your recruitment journey. If so, one of our Resourcing colleagues will explain how our video-interviewing technology will be used throughout the recruitment process and will be on hand to answer any questions you might have.\n\nAll information provided by applicants will be used only for recruitment purposes and will be used strictly in accordance with the Bank's personal data policies, a copy of which may be obtained by the applicant upon request. Unless otherwise instructed in writing by the applicant concerned, applicants may be considered for other suitable positions within the Bank and its related companies. The personal data of unsuccessful job applicants may be retained for a maximum of two years from the date when the job application is rejected and such data may be retained for a longer period if there is a subsisting reason that obliges the Bank to do so, after which the personal data will be destroyed.", "employment_types": ["Full Time", "Permanent"], "selling_points": [], "locations": ["Not Specified"], "categories": ["Banking / Finance", "Credit Analysis / Approval", "Retail Banking", "Credit Collection"], "post_time": "2022-01-04T07:09:10Z", "salary": {"currency": null, "max": null, "min": null, "period": "monthly", "term": null}, "salary_visible": false, "title_keywords": ["manager", "sales"], "responsibilities": ["reporting", "management", "marketing plans", "policies", "guidelines", "systems", "quality", "monitor", "banking", "develop", "maintain", "working relationships", "kpis"], "requirements": {"degrees": ["university degree"], "majors": ["business administration"], "languages": ["english", "chinese", "mandarin"], "language_level": ["proficiency"], "hard_skills": ["reason", "agile", "analytical skills"], "soft_skills": ["agile", "analytical skills", "communication", "self-motivation", "novel", "interpersonal", "work under pressure"], "languages_combined": [{"language": "english", "language_level": ["proficiency"]}, {"language": "chinese", "language_level": ["proficiency"]}, {"language": "mandarin", "language_level": ["proficiency"]}]}, "experience_required": {"duration": ["5 years", "minimum 10 years"], "field": []}}, {"job_id": "100003009006790", "location_code": "hk", "company": "Hays", "job_title": "Deputy Department Head of Retail Credit, Chinese Bank", "description": "As an Accounting Assistant/ Officer, you are responsible for:\n\nSupporting the Account Receivable/ Payable and debt collection process;\nProcessing payment requisition by inputting data into system accurately;\n\nCommunicating effectively with customers about billing questions to collect payment;\nMaintaining accurate and current records/ reports of daily operations;\nPerforming routine accounting functions, such as data entry, invoice and Delivery Note checking;\nHandling Ad hoc duties as assigned\n\n\nIn order to succeed in this role, you:\n\na holder of Diploma or above in Accounting or related discipline\n\nhave good command of English and Chinese (Mandarin and Cantonese)\nare competent in PC knowledge, MS Windows applications, including Outlook, Excel and Chinese word processing\n\nare attentive to detail, planning, organisation and daily delivery requirements\nare articulate, adaptable, collaborative and resilient\n\nWe offer:\n\n\nHealth Insurance: Medical and Dental, Annual Health Checkup\n\nDouble Pay\n\nBonuses: \u00a0Twice per year\nPaid Time Off:\u00a0 7 \u2013 14 days of Annual Leave, in addition to paid company holidays each year etc.\nPaid Sick Days\nOffice perks: 5-days work, unlimited coffee and tea, excellent working location (5 mins walk from Hung Hom station), stable working hours (09:00-17:45), etc.\n\nDid we catch your interest? Interested candidates please email your resume with expected salary to us.\n\nAll applications will be treated in strict confidence and used solely for recruitment purpose. Applicants who are not invited to an interview within four weeks may consider their applications unsuccessful. All personal data of unsuccessful applicants will be destroyed after two years.", "employment_types": ["Full Time", "Permanent"], "selling_points": ["Rare Vacancy", "Competitive salary and discretionary bonus", "Managerial role"], "locations": ["Not Specified"], "categories": ["Banking / Finance", "Credit Analysis / Approval", "Credit Collection", "Risk Management"], "post_time": "2021-12-29T10:28:08Z", "salary": {"currency": null, "max": null, "min": null, "period": "monthly", "term": null}, "salary_visible": false, "title_keywords": ["department head"], "responsibilities": ["ad hoc duties", "maintaining", "data", "data entry", "invoice", "checking", "debt collection", "payment", "daily operations", "reports", "planning"], "requirements": {"degrees": ["diploma or above"], "majors": ["accounting"], "languages": ["cantonese", "english", "chinese", "mandarin"], "language_level": ["good command"], "hard_skills": ["excel", "chinese word processing", "ms windows", "outlook", "pc knowledge", "processing"], "soft_skills": ["attentive to detail", "responsible", "competent", "adaptable", "collaborative", "organisation", "articulate", "accurate"], "languages_combined": [{"language": "cantonese", "language_level": ["good command"]}, {"language": "english", "language_level": ["good command"]}, {"language": "chinese", "language_level": ["good command"]}, {"language": "mandarin", "language_level": ["good command"]}]}, "experience_required": {"duration": [], "field": []}}, {"job_id": "100003008988706", "location_code": "hk", "company": "OCBC Wing Hang Bank Limited", "job_title": "Manager/Assistant Manager, Special Asset Management", "description": "Responsibilities:\n\nNegotiate with the corporate customers for loans workout plans.\nHandle a portfolio of loan accounts.\nLiaise with external parties (including lawyers, accountants, insolvency practitioners) during the workout process.\nAnalyze the root causes of the problem credits and devise appropriate account strategies / action plans.\nTo understand and prepare the provisioning of the problem credits by individual assessment through discounted cashflow models.\nHandling various reporting for problem credit management.\nTo assist in various data management projects.\n\nRequirements:\n\nDegree in Business/ Banking or Accounting is preferred.\nMinimum 5 years of relevant experience in loan recovery/ business restructuring and commercial collection.\nSolid skills in data management including data analysis.\nProficient in Excel.\nGood interpersonal and communication skills.\nApplicants with less relevant experience will be considered for the role as Senior Officer\n\nAttractive remuneration package will be offered to the right candidate. Please apply with full resume stating present & expected salary and contact phone number to The Human Resources Manager, 10/F, 161 Queen\u2019s Road Central, Hong Kong. Please quote the reference.\n\nPersonal data collected will be used for recruitment purpose only. For more information, please visit our website: http://www.ocbcwhhk.com.", "employment_types": ["Full Time", "Permanent"], "selling_points": ["Handle a portfolio of loan accounts", "Knowledge in data management", "5 years of relevant experience"], "locations": ["Sheung Wan"], "categories": ["Banking / Finance", "Loan", "Others", "Credit Collection"], "post_time": "2021-12-20T17:02:19Z", "salary": {"currency": null, "max": null, "min": null, "period": "monthly", "term": null}, "salary_visible": false, "title_keywords": ["manager", "assistant manager,", "asset management"], "responsibilities": ["reporting", "management", "data", "external parties", "liaise with", "plans"], "requirements": {"degrees": ["degree"], "majors": ["business", "accounting"], "languages": [], "language_level": [], "hard_skills": ["excel", "analysis", "data management"], "soft_skills": ["communication skills", "interpersonal"], "languages_combined": []}, "experience_required": {"duration": ["minimum 5 years"], "field": ["commercial", "business", "relevant experience"]}}, {"job_id": "100003008999710", "location_code": "hk", "company": "Industrial and Commercial Bank of China (Asia) Limited", "job_title": "Officer to Assistant Manager - Credit System Management, CMD", "description": "Job Responsibilities\nWork as the administrator of the Credit Management System, support and coordinate the development and implementation of credit approval & monitoring system\nPerform the credit data governance, monitor the credit data quality\nPrepare the credit risk analysis reports\nOther administration affairs including IT management and official documents system management\nParticipate in ad hoc work and projects\nJob Requirements\nBachelor Degree or above with major in Finance, Computer or related field.\nMinimum 1 year of banking experience with knowledge of credit or system project management.\nFamiliar with Microsoft office software (Excel, Access) and SQL is preferred.\nGood analytical and communication skills.\nProficient in spoken and written English & Chinese (including Putonghua)", "employment_types": ["Full Time"], "selling_points": [], "locations": ["Central"], "categories": ["Banking / Finance", "Credit Analysis / Approval", "Credit Collection"], "post_time": "2021-12-24T08:38:26Z", "salary": {"currency": null, "max": null, "min": null, "period": "monthly", "term": null}, "salary_visible": false, "title_keywords": ["officer", "assistant manager"], "responsibilities": ["management", "ad hoc", "data", "monitoring", "monitor", "implementation", "quality", "coordinate", "reports", "risk analysis", "it management", "administration"], "requirements": {"degrees": ["degree or above", "bachelor"], "majors": ["finance"], "languages": ["putonghua", "english", "chinese"], "language_level": ["proficient"], "hard_skills": ["sql", "project management", "excel", "microsoft office software"], "soft_skills": ["communication skills", "project management"], "languages_combined": [{"language": "putonghua", "language_level": ["proficient"]}, {"language": "english", "language_level": ["proficient"]}, {"language": "chinese", "language_level": ["proficient"]}]}, "experience_required": {"duration": ["minimum 1 year"], "field": ["project management", "banking experience"]}}, {"job_id": "100003008993797", "location_code": "hk", "company": "i-CABLE Communications Limited", "job_title": "Credit Service Officer", "description": "Credit Collection Dept\n\nTo be responsible for handling payment enquiries; executing routine dunning actions for non-payment accounts\nForm 5 or above with minimum 1 year relevant working experience in telecommunication industry is preferred\nProficient in PC applications including MS office\nExcellent command of spoken and written English, Cantonese and Mandarin\nStrong communication and presentation skills, good telephone manner and able\u00a0 to work under pressure and meet tight deadlines\nIndependent, well-organized, customer oriented with analytical mind\nWe offer 5-day work week, competitive remuneration packages and advancement opportunities. Interested parties, please write with full resume to\u00a0Director, Human Resources, Human Resources Department, i-CABLE Communications Limited, 4/F Cable TV Tower, 9 Hoi Shing Road Tsuen Wan, N.T. or fax to 2112 7841 or via Apply Now (Please quote reference number and position applied for). For other information, please visit our website\u00a0http://www.i-cable.com.\nYour application may be forwarded to any affiliate companies and successful applicant may be seconded to work at any office as assigned.\u00a0 The information received will be used for consideration of employment only and all personal data supplied will be destroyed within 3 months.\nWe are an equal opportunity employer.", "employment_types": ["Full Time", "Permanent"], "selling_points": [], "locations": ["Not Specified"], "categories": ["Banking / Finance", "Credit Collection", "Sales, CS & Business Devpt", "Customer Service - Supervisor / Officer", "Others"], "post_time": "2021-12-22T09:23:23Z", "salary": {"currency": null, "max": null, "min": null, "period": "monthly", "term": null}, "salary_visible": false, "title_keywords": ["officer"], "responsibilities": ["communication", "payment", "executing", "work under pressure"], "requirements": {"degrees": ["form 5 or above"], "majors": [], "languages": ["cantonese", "english", "mandarin"], "language_level": ["excellent"], "hard_skills": ["ms office", "pc applications"], "soft_skills": ["meet tight deadlines", "independent", "responsible", "well-organized", "communication", "presentation skills", "analytical mind", "telephone manner", "work under pressure"], "languages_combined": [{"language": "cantonese", "language_level": ["excellent"]}, {"language": "english", "language_level": ["excellent"]}, {"language": "mandarin", "language_level": ["excellent"]}]}, "experience_required": {"duration": ["minimum 1 year"], "field": ["relevant working experience"]}}, {"job_id": "100003008998465", "location_code": "hk", "company": "Shenwan Hongyuan Securities (H.K.) Ltd.", "job_title": "Analyst, Settlement (Futures & Options) (Ref: C/ASFO/07-21)", "description": "Duties & responsibilities:\n\nHandle daily operations and settlement of derivatives products;\nMonitor client positions on wide range of products, including derivatives products;\nConduct margin calls and ensure all trades transacted comply with the credit control policies;\nParticipate in various system enhancements and projects implementation to meet business demands;\nNight Shift required.\n\nRequirements:\n\nBachelor Degree holder in Finance, Business or related discipline;\nAt least 2 years work experiences in operations and settlement of futures and options products including HKFE and Global Futures products;\nA good team player, quick learner, self-motivated with strong sense of responsibility and discipline;\nGood command of written and spoken English, Chinese and Mandarin;\n\nWe offer attractive remuneration package and fringe benefits including 5-day week to the right candidate.\u00a0 Interested parties please send your application letter with resume stating present and expected salary to Human Resources Department by clicking\u00a0\"Apply Now\", or mail to Level 17, 28 Hennessy Road, Hong Kong. (Please quote the reference of the post on the envelope)\u00a0.\nAll information received will be kept in strict confidence and only for recruitment-related purposes.\n\nAll information received will be kept in strict confidence and only for recruitment-related purposes.", "employment_types": ["Full Time", "Permanent"], "selling_points": [], "locations": ["Admiralty"], "categories": ["Banking / Finance", "Others", "Credit Collection"], "post_time": "2021-12-24T03:36:09Z", "salary": {"currency": null, "max": null, "min": null, "period": null, "term": null}, "salary_visible": false, "title_keywords": ["analyst"], "responsibilities": ["control", "policies", "monitor", "implementation", "daily operations"], "requirements": {"degrees": ["bachelor degree holder"], "majors": ["finance", "business"], "languages": ["english", "chinese", "mandarin"], "language_level": ["good command"], "hard_skills": [], "soft_skills": ["good team player", "self-motivated", "quick learner", "sense of responsibility"], "languages_combined": [{"language": "english", "language_level": ["good command"]}, {"language": "chinese", "language_level": ["good command"]}, {"language": "mandarin", "language_level": ["good command"]}]}, "experience_required": {"duration": ["at least 2 years"], "field": []}}, {"job_id": "100003008986749", "location_code": "hk", "company": "The Hong Kong And China Gas Co Ltd", "job_title": "Credit Control Officer", "description": "The Role:\n\nPerform credit management and debt collection actions\nFollow up delinquent accounts via demand letters, telephone calls and on-site visits\nNegotiate with customers on settlement arrangement, such as payment by instalments, taking over of account with previous unsettled balance, tenancy dispute, etc.\nAssign delinquent accounts to Credit Agency for further dunning actions\nManage Credit Agency on issues arising from delinquent accounts\nInitiate legal actions against delinquent accounts\nCarry out on-site visit and cap-off gas supply\nHandle customers' enquiries and complaints regarding Credit Control operation\nHandle other credit control matters and ad hoc assignments\n\nThe Person:\n\nDiploma or above in Accounting, Finance or related disciplines\n\nAt least 2 years\u2019 solid experiences in commercial credit management functions\nHolder of valid driving license Class 1 is an advantage\nProficiency in MS Office applications\n\nGood command of spoken and written English and Chinese, proficiency in Putonghua will be an advantage\n\nCustomer-oriented with good communication and telephone skills\n\nSelf-motivated and able to work independently\n\nApplication with full details stating current and expected salary to: APPLY NOW\u00a0\n\nPlease quote the reference number (CFMD/CCO/JDB01/21) in your application.\n\n(All personal data provided will be treated in strict confidence and used for recruitment purposes only.)", "employment_types": ["Permanent"], "selling_points": ["Credit Control Officer", "Negotiate with customers", "Handle customers' enquiries"], "locations": ["Quarry Bay"], "categories": ["Banking / Finance", "Others", "Credit Collection"], "post_time": "2021-12-20T03:48:17Z", "salary": {"currency": null, "max": null, "min": null, "period": "monthly", "term": null}, "salary_visible": false, "title_keywords": ["credit control officer"], "responsibilities": ["management", "control", "letters", "communication", "debt collection", "payment", "recruitment", "ad hoc assignments", "personal data"], "requirements": {"degrees": ["diploma or above"], "majors": ["related disciplines", "finance", "accounting"], "languages": ["putonghua", "english", "chinese"], "language_level": ["advantage", "proficiency", "good command"], "hard_skills": ["ms office"], "soft_skills": ["work independently", "confidence", "self-motivated", "communication", "customer-oriented"], "languages_combined": [{"language": "putonghua", "language_level": ["proficiency", "good command"]}, {"language": "english", "language_level": ["advantage", "proficiency", "good command"]}, {"language": "chinese", "language_level": ["advantage", "proficiency", "good command"]}]}, "experience_required": {"duration": ["at least 2 years"], "field": ["commercial", "management"]}}, {"job_id": "100003008986532", "location_code": "hk", "company": "Michael Page", "job_title": "Team Head - Credit Policy", "description": "Our client is currently looking for a Team Head to join their growing Credit team. The ideal candidate will have at least 10 years of solid experience in banking industry, of which 5 years at managerial level.\n\nClient Details\n\nOur client is one of the largest and leading banking group in Asia with more than 10,000 domestic branches and overseas branches in Asia and Europe. They provide a wide array of banking products and services to customers, including consumer banking services, commercial banking services, corporate banking services, private banking services, treasury business and cross-border financial services, etc.\n\nDescription\n\nManage a team of professionals to formulate, review and updatecredit policies, procedures, guidelines and underwriting standards in support of the overall business and risk management needs\nReview the new policies/regulations/practices released by the regulatory bodies or Head Office which are applicable to the Bank's risk management framework and policies, and update the Bank's policies and procedures to cater for the new requirements\nDrive the implementation of credit risk related modules within the overall Basel plan\nDrive/participate in special projects from the credit risk management angle\nLiaise with Head Office for the proper usage and maintenance of the corporate scorecards\nLiaise with Internal Control, Regional Audit and regulatory bodies on relevant audits/examinations and coordinate the relevant responses on findings for Credit Risk Management where appropriate.\nInitiate and drive the annual review process on risk appetite statement of the Bank\n\nProfile\n\nUniversity Degree in Business Administration or related disciplines\nMinimum 10 years' relevant experience in banking industry with no less than 5 years at managerial level\nIn-depth knowledge of lending principles/credit process and a keen awareness of credit issues\nExcellent knowledge of general banking products, including trade finance, mortgage and treasury products\nKnowledge of bank regulations and supervisory manuals\nFront-line marketing experience is preferred\nStrong communication, negotiation and people management skills\nProficient in written English and Chinese\n\nJob Offer\n\nStable company culture\nSupervisory exposure\nMedical coverage\nCompetitive Package + Benefits\nWork life balance\n\nTo apply online please click the 'Apply' button below. For a confidential discussion about this role please contact Michael K. Lee on +852 3602 2441", "employment_types": ["Full Time", "Permanent"], "selling_points": ["Credit Risk Management & Policies", "Minimum 10 years' relevant experience", "Well-established Platform"], "locations": ["Not Specified"], "categories": ["Banking / Finance", "Corporate Banking", "Credit Analysis / Approval", "Credit Collection"], "post_time": "2021-12-20T03:25:20Z", "salary": {"currency": "HKD", "max": 89999, "min": 70000, "period": "monthly", "term": null}, "salary_visible": true, "title_keywords": [], "responsibilities": ["regulations", "credit issues", "audit", "communication", "plan", "liaise with", "administration", "internal control", "implementation", "banking", "liaise with head office", "management", "review", "procedures", "audits", "maintenance", "guidelines", "policies", "coordinate"], "requirements": {"degrees": ["university degree"], "majors": ["related disciplines", "business administration"], "languages": ["english", "chinese"], "language_level": ["proficient"], "hard_skills": ["no", "maintenance", "internal control"], "soft_skills": ["negotiation", "keen", "communication", "stable", "ideal"], "languages_combined": [{"language": "english", "language_level": ["proficient"]}, {"language": "chinese", "language_level": ["proficient"]}]}, "experience_required": {"duration": ["at least 10 years", "5 years", "minimum 10 years"], "field": ["banking industry", "marketing", "relevant experience", "managerial"]}}, {"job_id": "100003008993533", "location_code": "hk", "company": "\u9ad8\u67cf(\u4e9e\u6d32)\u8cc7\u7522\u7ba1\u7406\u6709\u9650\u516c\u53f8", "job_title": "\u5ba2\u6236\u806f\u7d61\u4e3b\u4efb \u2013 \u9280\u884c/\u96fb\u8a0a\u670d\u52d9 (\u591a\u540d) (\u53ef\u9054$18K\u4ee5\u4e0a)", "description": "\u5de5\u4f5c\u8077\u8cac\n\n\u900f\u904e\u96fb\u8a71\u8ddf\u9032\u5ba2\u6236\u903e\u671f\u6b20\u6b3e\u8cec\u9805\u4f86\u6848\uff0c\u9032\u884c\u63d0\u9192\u5354\u5546\n\u89e3\u7b54\u903e\u671f\u6b20\u6b3e\u5e33\u9805\u4f86\u6848\u7528\u6236\u76f8\u95dc\u67e5\u8a62\u53ca\u5546\u8a0e\u9084\u6b3e\u65b9\u6848\n\u5b9a\u671f\u8f38\u5165\u53ca\u66f4\u65b0\u96fb\u8166\u7cfb\u7d71\u5167\u903e\u671f\u6b20\u6b3e\u5e33\u9805\u4f86\u6848\u9032\u7a0b\n\n\u8077\u4f4d\u8981\u6c42\n\n\u4e2d\u4e94\u6216\u4ee5\u4e0a\u5b78\u6b77\uff0c\u00a0\n1\u5e74\u6216\u4ee5\u4e0a\u5de5\u4f5c\u7d93\u9a57\uff0c\u884c\u696d\u4e0d\u9650\n\u826f\u597d\u6e9d\u901a\u6280\u5de7\n\u9748\u6d3b\u7a4d\u6975\uff0c\u8aa0\u5be6\u53ca\u5bcc\u8cac\u4efb\u611f\n\u5177\u9280\u884c\u96fb\u8a71\u806f\u7d61\u4e2d\u5fc3\u3001\u501f\u8cb8\u92b7\u552e\u6216\u5ba2\u6236\u670d\u52d9\u7d93\u9a57\uff0c\u53ef\u512a\u5148\u8003\u616e\n\n\u85aa\u91d1\u798f\u5229\n\n\u56fa\u5b9a\u5e95\u85aa + \u696d\u7e3e\u4f63\u91d1 + \u591a\u9805\u6d25\u8cbc\n\u6bcf\u54685.5\u5929\u5de5\u4f5c\ufe5d\u661f\u671f\u516d\u9577\u77ed\u5468\ufe5e\uff0c\u661f\u671f\u65e5\u53ca\u516c\u773e\u5047\u671f\u4f11\u606f\n\u91ab\u7642\u798f\u5229\u3001\u7259\u79d1\u798f\u5229\u3001\u5168\u52e4\u734e\u91d1\u53ca\u8d85\u6642\u5de5\u4f5c\u6d25\u8cbc\u7b49\n\u4e5d\u9f8d\u7063\u7532\u7d1a\u5546\u5ec8\u5de5\u4f5c\u3001\u74b0\u5883\u512a\u8d8a\u3001\u7a7f\u68ad\u5df4\u58eb\u63d0\u4f9b\n\u826f\u597d\u6649\u5347\u6a5f\u6703\u53ca\u63d0\u4f9b\u5b8c\u5584\u5165\u8077\u5728\u8077\u57f9\u8a13\u00a0\n\n\u6b61\u8fce\u8f49\u8077 / \u8f49\u696d\u4eba\u58eb / \u7562\u696d\u751f\u52a0\u5165\n\n\u6709\u610f\u8005\u8acb\u5c07\u500b\u4eba\u5c65\u6b77\u3001\u8981\u6c42\u85aa\u91d1\u53ca\u53ef\u5230\u8077\u65e5\u671f\u50b3\u771f\u81f38161 6498\u4eba\u529b\u8cc7\u6e90\u90e8\u6536\u6216\u6309\"Apply Now\"\u3002\u6709\u610f\u8005\u4ea6\u53ef\u81f4\u96fb\u62db\u52df\u71b1\u7dda8200 2738\u6216Whatsapp 5116 9625\u4f5c\u67e5\u8a62\u3002\n\n\u6b32\u4e86\u89e3\u672c\u516c\u53f8\u8cc7\u6599\u53ef\u700f\u7060\u7db2\u5740www.goldpartners.com.hk\n\n\u6240\u6709\u8077\u4f4d\u7533\u8acb\u904e\u7a0b\u4e2d\u6240\u6536\u96c6\u7684\u500b\u4eba\u8cc7\u6599\u53ea\u6703\u7528\u4f5c\u62db\u8058\u7528\u9014\u3002\u00a0\u4e0d\u5408\u9069\u7684\u7533\u8acb\u8005\u7684\u500b\u4eba\u8cc7\u6599\u5c07\u88ab\u8f49\u4ecb\u81f3\u96c6\u5718\u5c6c\u4e0b\u6a5f\u69cb\u76f8\u95dc\u8077\u4f4d\u7a7a\u7f3a\uff0c\u4e26\u4fdd\u7559\u4e0d\u591a\u65bc1\u5e74\u4f5c\u65e5\u5f8c\u62db\u8058\u7528\u9014\u3002", "employment_types": ["Full Time", "Permanent"], "selling_points": [], "locations": ["Kowloon Bay"], "categories": ["Sales, CS & Business Devpt", "Call Centre", "Banking / Finance", "Credit Collection", "Customer Service - Supervisor / Officer"], "post_time": "2021-12-22T09:18:51Z", "salary": {"currency": null, "max": null, "min": null, "period": "monthly", "term": null}, "salary_visible": false, "title_keywords": [], "responsibilities": [], "requirements": {"degrees": [], "majors": [], "languages": [], "language_level": [], "hard_skills": [], "soft_skills": [], "languages_combined": []}, "experience_required": {"duration": [], "field": []}}]