[{"job_id": "100003009049330", "location_code": "hk", "company": "Shanghai Commercial Bank Ltd", "job_title": "Credit Manager / Assistant Manager", "description": "Responsibilities:\n\nPrepare credit facility review and to identify and assess potential problematic credit accounts\nConduct risk evaluation and make recommendation on credit facilities\nEnsure compliance of bank policy and regulatory requirements\nAssist in formulating credit policies, guidelines and procedures of credit activities undertaken by the bank\nHandle ad-hoc credit tasks as assigned\nCollaborate with business units and assess various market information/event and internal & external early warning signal to detect potential problem accounts for close & early management\nTake immediate action to manage & mitigate account irregularity and credit risk\n\nRequirements:\n\nDegree holder in Business Administration, Finance, Risk Management or related disciplines\nMinimum 5 years of experience of solid experience in commercial / corporate/ listed companies' credit analysis (in terms of credit risk aspects and financial viability) and credit risk management in banking industry\nStrong understanding of legal and regulatory requirements and banking practices on credit risk management\nSelf-motivated with good analytical skill and risk control knowledge\nGood command of written and spoken English and Chinese\n\nAttractive remuneration package will be offered to the right candidates. Interested parties please click \"Apply Now\" to sumbit your full resume with current and expected salary to the Human Resources Division.\n\nPlease visit us at www.shacombank.com.hk for more information about our Bank.\n\nAll personal data collected will be used for recruitment related purposes strictly in accordance with the Bank's personal data policies, a copy of which will be provided immediately upon request by contacting our Personal Data Compliance Officer. Applicants who are not contacted within two months may consider their applications unsuccessful and the personal data collected from the applicants will be retained for no longer than two years from the date of rejection during which the applicants may be considered for other suitable positions within the Bank.", "employment_types": ["Full Time", "Permanent"], "selling_points": ["Prepare credit facility review", "Conduct risk evaluation and make recommendation", "Formulate credit policies, guidelines & procedures"], "locations": ["North Point"], "categories": ["Banking / Finance", "Analyst", "Credit Analysis / Approval", "Others"], "post_time": "2022-01-15T03:50:18Z", "salary": {"currency": null, "max": null, "min": null, "period": "monthly", "term": null}, "salary_visible": false, "title_keywords": ["assistant manager", "manager"], "responsibilities": ["ad-hoc", "collaborate with", "management", "market information", "make recommendation", "guidelines", "regulatory requirements", "policies", "review", "procedures", "ensure compliance", "evaluation", "credit facility"], "requirements": {"degrees": ["degree holder"], "majors": ["related disciplines", "finance", "business administration", "risk management"], "languages": ["english", "chinese"], "language_level": ["good command"], "hard_skills": ["credit analysis", "analytical skill"], "soft_skills": ["self-motivated", "analytical skill"], "languages_combined": [{"language": "english", "language_level": ["good command"]}, {"language": "chinese", "language_level": ["good command"]}]}, "experience_required": {"duration": ["minimum 5 years"], "field": ["banking industry", "management", "commercial", "credit risk", "financial"]}}, {"job_id": "100003009053188", "location_code": "hk", "company": "Konew Financial Express Limited \u5eb7\u696d\u4fe1\u8cb8\u5feb\u905e", "job_title": "Officer, Credit Approval", "description": "Main Duties & Responsibilities:\n\nConduct credit approvals on all applications including property loans, personal loans and SME loans in accordance with authority\nAssist to ensure that credit activities are conducted in accordance with requirements as stipulated in the credit policies\nEnsure appropriate infrastructure, resources and systems are in place for credit risk management\nCollaborate with Sales Department for the criteria of credit approval\nReview and prepare various reports of credit risk management\n\nRequirements:\n\nBachelor Degree in Risk Management, Mathematics, Economics or related discipline\nAt least 1\u00a0year relevant working experience\nExcellent analytical, communication and interpersonal skills\nIndependent, proactive, detail-oriented and able to work under pressure\nCandidates with more experience will be considered as\u00a0Senior Officer\n\nWe offer:\n\nDiscretionary bonus\nMedical insurance\nDental insurance\nHardship allowance\nCompetitive annual leave days\nBirthday leave\nAnniversary leave\nStudy leave\nMarriage leave\nCompassionate leave\n\nHow to apply:\n\nInterested parties, please send your resume stating your expected salary to Human Capital Department\u00a0by clicking \"APPLY NOW\".\n\n(We are an equal opportunity employer.\u00a0 Personal data collected will be used for recruitment purpose only.\u00a0 The unsuccessful applications will be destroyed after 6 months.)\u00a0", "employment_types": ["Full Time", "Permanent"], "selling_points": ["Conduct credit approvals on all loan applications", "Collaborate for the criteria of credit approval", "5 days work, birthday leave, anniversary leave"], "locations": ["Central"], "categories": ["Banking / Finance", "Credit Analysis / Approval", "Loan", "Mortgage"], "post_time": "2022-01-17T06:22:00Z", "salary": {"currency": null, "max": null, "min": null, "period": "monthly", "term": null}, "salary_visible": false, "title_keywords": ["officer"], "responsibilities": ["collaborate with", "management", "policies", "infrastructure", "systems", "review", "reports", "sme"], "requirements": {"degrees": ["degree", "bachelor"], "majors": ["risk management", "economics", "mathematics"], "languages": [], "language_level": [], "hard_skills": [], "soft_skills": ["independent", "detail-oriented", "communication and interpersonal skills", "proactive", "work under pressure"], "languages_combined": []}, "experience_required": {"duration": ["at least 1 year"], "field": ["relevant working experience"]}}, {"job_id": "100003009050665", "location_code": "hk", "company": "China Construction Bank (Asia) Corporation Limited", "job_title": "Corporate Credit Analyst / Approver (FI/NBFI/PRC & Local Corp)", "description": "Responsibilities:\n\nConduct analysis, assessment and evaluation on credit proposals for commercial clients and make recommendations for approval\nAssist to ensure the proper handling of credit request and to monitor a high credit quality of the bank\u2019s portfolio of commercial clients\nReview and validate risk rating scorecards\nMonitor credit limit excess, credit ratings/loan classification changes, adverse news release, credit events and developments relating to counterparties\nPerform regular reporting, portfolio analysis and research duties\nParticipate in bank projects relating to commercial credit risk and ad-hoc duties\nVisit Commercial clients with relationship managers\n\n\u00a0 \u00a0 \u00a0 \u00a0Requirements:\n\nUniversity degree holder, major in Business/Finance/Accounting or other related disciplines\nMinimum 5 years\u2019 credit analysis experience on Commercial banking credits; experience in handling FI / NBFI / Chinese & local large corporates is preferred\nCandidates with more experience or prior approval authority can be considered as Credit approver\nDetailed-oriented, good analytical, interpersonal and communication skills\nGood command of written and spoken English and Chinese (Putonghua is a must)\nProficient in PC applications, including Microsoft Word and Excel\nMulti-tasked and able to work under tight timelines\n\nApplicants who are not contacted within 8 weeks may consider their applications unsuccessful and their personal data will be retained by the bank for a period up to two years.\n\nAll information provided by applicants will be used for recruitment purposes only and will be used strictly in accordance with the bank's personal data policies, a copy of which will be provided upon request.\u00a0", "employment_types": ["Full Time", "Permanent"], "selling_points": ["Analyse & evaluate on credit application/proposal", "Risk rating scorecards, Give credit judegement", "Degree with 5 years' of exp in credit analysis"], "locations": ["Central"], "categories": ["Banking / Finance", "Credit Analysis / Approval", "Financial Services"], "post_time": "2022-01-14T11:09:18Z", "salary": {"currency": null, "max": null, "min": null, "period": "monthly", "term": null}, "salary_visible": false, "title_keywords": ["credit analyst"], "responsibilities": ["make recommendations", "reporting", "ad-hoc duties", "analysis", "review", "quality", "monitor", "evaluation"], "requirements": {"degrees": ["university degree"], "majors": ["related disciplines", "finance", "business", "accounting"], "languages": ["putonghua", "english", "chinese"], "language_level": ["good command"], "hard_skills": ["credit analysis", "excel", "microsoft word", "pc applications"], "soft_skills": ["communication skills", "multi-tasked", "interpersonal", "detailed"], "languages_combined": [{"language": "putonghua", "language_level": ["good command"]}, {"language": "english", "language_level": ["good command"]}, {"language": "chinese", "language_level": ["good command"]}]}, "experience_required": {"duration": ["minimum 5 years"], "field": ["commercial", "banking"]}}, {"job_id": "100003009049334", "location_code": "hk", "company": "Shanghai Commercial Bank Ltd", "job_title": "Manager / Assistant Manager, Credit Appraisal (Corporate / Commercial)", "description": "Responsibilities:\n\nAnalyse and review complex and sizeable loans in HK and the Mainland to ensure that they adhere to existing policy guidelines\nLiaise with lending units to resolve credit issues and expedite the process\nAssist in collecting market intelligence through various channels\nPrepare various MIS reports for the management\u2019s review\nEnsure credit facilities adhere to the Bank's internal credit policies/guidelines as well as external regulatory requirements\n\nRequirements:\n\nDegree holder in Finance, Risk Management or related disciplines. Professional qualifications, such as CFA, CPA, ECF-CRM, etc., are preferred.\nMinimum 5 years of experience in credit review and analysis in Corporate/Commercial accounts, preferably in banking industry\nSound knowledge of lending and hedging products\nGood understanding in credit risk management and regulatory compliance\nSelf-motivated and detail-minded with strong risk control senses and analytical skills\n(Candidates with less experience will be considered for the position of Assistant Manager)\n\n\nAttractive remuneration package will be offered to the right candidates. Interested parties please click \"Apply Now\" to submit your full resume with current and expected salary to the Human Resources Division.\n\nPlease visit us at www.shacombank.com.hk for more information about our Bank.\n\nAll personal data collected will be used for recruitment related purposes strictly in accordance with the Bank's personal data policies, a copy of which will be provided immediately upon request by contacting our Personal Data Compliance Officer. Applicants who are not contacted within two months may consider their applications unsuccessful and the personal data collected from the applicants will be retained for no longer than two years from the date of rejection during which the applicants may be considered for other suitable positions within the Bank.", "employment_types": ["Full Time", "Permanent"], "selling_points": ["Analyse and review complex and sizeable loans", "Liaise with lending units to resolve credit issues", "Assist in collecting market intelligence"], "locations": ["Central"], "categories": ["Banking / Finance", "Credit Analysis / Approval", "Others", "Risk Management"], "post_time": "2022-01-15T03:50:18Z", "salary": {"currency": null, "max": null, "min": null, "period": "monthly", "term": null}, "salary_visible": false, "title_keywords": ["manager", "assistant manager,"], "responsibilities": ["management", "guidelines", "credit issues", "policies", "review", "regulatory requirements", "reports", "liaise with", "analyse"], "requirements": {"degrees": ["degree holder"], "majors": ["related disciplines", "finance", "risk management"], "languages": [], "language_level": [], "hard_skills": ["professional qualifications", "cfa", "analysis", "analytical skills", "cpa"], "soft_skills": ["detail-minded", "self-motivated", "analytical skills"], "languages_combined": []}, "experience_required": {"duration": ["minimum 5 years"], "field": ["commercial", "banking industry"]}}, {"job_id": "100003009050291", "location_code": "hk", "company": "Nanyang Commercial Bank", "job_title": "Senior Credit Risk Manager / Credit Risk Manager   (Ref: OE8014-00-JDB)", "description": "Conduct independent credit assessment and validation of credit applications, including internal ratings, compliance of policies and regulations and make recommendations for approval. The portfolio of clients mainly covers PRC large corporate clients and NBFI, as well as those in the New Economy industries.Conduct on-going monitoring over large exposure, credit rating, early warning and risk concentration.Contribute to the formulation and review of credit risk policies and guidelines to cope with regulatory changes. Perform ad hoc projects or assignments.\n\nRequirements:\n\nMinimum 10 years\u2019 experience in corporate / structured credits and cross border transactions for PRC corporate clients and NBFI, either within a credit risk function or business line in banking industry.\nUniversity graduate with major in Accounting, Finance, Economics, Risk Management or related disciplines\nGood understanding in key market and industry dynamics as well as regulatory changes, especially that of PRC\nStrong expertise in risk and financial analysis, cash flow projections and banking products\nCFA, FRM, Accountant or HKIB ECF-CRM would be an advantage\nProficiency in written Chinese and English, fluency in Putonghua is preferred\nGood PC skills in MS Word and Excel\n\n(Candidate with less relevant experience will be considered as Credit Risk Manager)\n\nIf you are flexible enough and zeal for a harmonious and supportive working environment where enables you to grow and succeed professionally, please send a full resume indicating your public examination results (HKCEE and HKALE / HKDSE), your present and expected salary and quoting reference number attention to\u00a0Talent Acquisition Division, Nanyang Commercial Bank, 151 Des Voeux Road Central, Hong Kong or apply through email. For details, please visit https://www.ncb.com.hk/ and select the page Recruit.\n\nWe are an Equal Opportunities Employer. Data collected would be used for recruitment purposes only. Applicants who do not hear from us within 8 weeks may consider their applications unsuccessful and their data will be destroyed within 12 months of receipt.", "employment_types": ["Full Time", "Permanent"], "selling_points": ["Conduct independent credit assessment", "Conduct on-going monitoring over large exposure", "Minimum 10 years\u2019 experience"], "locations": ["Central & Western Area"], "categories": ["Accounting", "Credit Control", "Banking / Finance", "Credit Analysis / Approval"], "post_time": "2022-01-15T03:50:58Z", "salary": {"currency": null, "max": null, "min": null, "period": "monthly", "term": null}, "salary_visible": false, "title_keywords": ["manager"], "responsibilities": ["regulations", "make recommendations", "management", "data", "guidelines", "policies", "compliance", "monitoring", "review", "transactions", "financial analysis", "cash flow", "ad hoc projects", "recruitment", "banking"], "requirements": {"degrees": ["university graduate", "hkdse"], "majors": ["risk management", "finance", "economics", "related disciplines", "accounting"], "languages": ["putonghua", "english", "chinese"], "language_level": ["fluency", "proficiency"], "hard_skills": ["excel", "cfa", "financial analysis", "make", "pc skills", "frm", "ms word"], "soft_skills": ["make recommendations", "flexible", "supportive", "independent", "harmonious", "structured"], "languages_combined": [{"language": "putonghua", "language_level": ["fluency", "proficiency"]}, {"language": "english", "language_level": ["proficiency"]}, {"language": "chinese", "language_level": ["fluency", "proficiency"]}]}, "experience_required": {"duration": ["minimum 10 years"], "field": ["banking industry", "business", "relevant experience", "credit risk"]}}, {"job_id": "100003009042883", "location_code": "hk", "company": "Industrial and Commercial Bank of China (Asia) Limited", "job_title": "Credit Analyst (Institutional Credit)", "description": "Responsibilities:\nResponsible for processing evaluation on Financial Institutions (banks and non-bank FI) credit applications and preparing credit opinion/ recommendation to the credit approvers\nEnsure credit request is duly assessed with respect to all internal and external requirements including approval of credit applications within delegated authority\nParticipate in cross department projects and provide guidance as a subject matter expert on credit risk issues\nRequirements:\nUniversity graduate with major in Accounting, Finance or related disciplines\nMinimum 3 years of banking experience in relationship management, credit review, analysis or approval for FI/ large corporate / middle-market sector. The experience on FI credit review is preferred.\nSolid knowledge in financial analysis, banking law and practice\nSelf-motivated, independent with an analytical mindset and ability to work under pressure\nStrong interpersonal, communication, negotiation and presentation skills with experience in working with senior management level\nStrong command of both written and spoken English and Chinese, including Putonghua\nMore experienced candidates will be considered for Manager positions", "employment_types": ["Full Time", "Permanent"], "selling_points": [], "locations": ["Central"], "categories": ["Banking / Finance", "Credit Analysis / Approval", "Corporate Finance", "Financial Services"], "post_time": "2022-01-12T09:07:14Z", "salary": {"currency": null, "max": null, "min": null, "period": null, "term": null}, "salary_visible": false, "title_keywords": ["credit analyst"], "responsibilities": ["provide guidance", "subject matter expert", "evaluation"], "requirements": {"degrees": ["university graduate"], "majors": ["related disciplines", "finance", "accounting"], "languages": ["putonghua", "english", "chinese"], "language_level": [], "hard_skills": ["financial analysis", "analysis"], "soft_skills": ["self-motivated", "independent", "negotiation", "communication", "presentation skills", "interpersonal", "work under pressure"], "languages_combined": [{"language": "putonghua", "language_level": []}, {"language": "english", "language_level": []}, {"language": "chinese", "language_level": []}]}, "experience_required": {"duration": ["minimum 3 years"], "field": ["management", "banking experience"]}}, {"job_id": "100003009054838", "location_code": "hk", "company": "Cathay United Bank Company, Limited", "job_title": "Credit Administration Manager, Operations", "description": "Responsibilities:\n\nPrepare and review facility and security documentation\n\nCheck and comment on loan documents\nFollow up precedent/subsequent loan conditions, financial covenants, etc.\nIdentify documentation and workflow deficiencies, report and follow-up\nParticipate and contribute to projects and conduct UAT\nPrepare, review and update SOP\n\nCandidates are expected to possess:\n\nBachelor\u2019s Degree\u00a0with minimum 8 years of experience in Credit Administration, with well qualified supervisory experience\nIn-depth knowledge of processing bilateral loans, syndicated loans, Lombard lending, etc., especially in areas of banking practice and legal aspects\nStrong management skills with positive attitude and team spirit\nStrong communication and organization skills\nProficiency in MS Office application like WORD and EXCEL\nExcellent command of written and spoken English and Chinese, including Mandarin\n\nWe offer attractive salary and comprehensive fringe benefits. Interested parties please e-mail your full resume with current and expected salary by clicking 'Apply Now'.\n\nPersonal information collected will be used for considering suitability for the post and strictly in accordance with our personal data policies.\u00a0 It is our policy to retain the personal data of unsuccessful applicants for future recruitment purposes for a period of maximum two years.\u00a0", "employment_types": ["Full Time", "Permanent"], "selling_points": ["University graduate", "At least 8 years of Credit Admin experience", "Well qualified supervisory experience"], "locations": ["Causeway Bay"], "categories": ["Banking / Finance", "Credit Analysis / Approval", "Loan", "Others"], "post_time": "2022-01-17T11:37:24Z", "salary": {"currency": null, "max": null, "min": null, "period": "monthly", "term": null}, "salary_visible": false, "title_keywords": ["administration manager", "operations"], "responsibilities": ["management", "uat", "review", "communication", "banking", "documentation", "report", "administration"], "requirements": {"degrees": ["degree", "bachelor"], "majors": [], "languages": ["english", "chinese", "mandarin"], "language_level": ["excellent"], "hard_skills": ["excel", "word", "banking practice", "documentation", "processing", "ms office"], "soft_skills": ["positive attitude", "team spirit", "organization skills", "communication"], "languages_combined": [{"language": "english", "language_level": ["excellent"]}, {"language": "chinese", "language_level": ["excellent"]}, {"language": "mandarin", "language_level": ["excellent"]}]}, "experience_required": {"duration": ["minimum 8 years"], "field": ["supervisory experience", "administration"]}}, {"job_id": "100003009046311", "location_code": "hk", "company": "China Taiping Life Insurance (Hong Kong) Company Limited", "job_title": "Investment Analyst (Credit Analyst)", "description": "Responsibilities:\n\nPerform credit research, and recommend internal rating for investment counterparties using both quantitative and qualitative assessments\nConduct due diligence on investments providers and products and present to managements\nAssess the instrument ratings for fixed-income investment, alternative investment and structured products\nConduct annual counterparty credit rating reviews as well as ad-hoc credit investments review, alert on significant credit deteriorations\nMaintain and advise the internal rating methodology for different investment products and industries periodically\nAssist in developing and maintaining internal credit rating policies and procedures\nOther relevant ad-hoc projects and duties as assigned\n\nRequirements:\n\nBachelor\u2019s degree in Business/ Economics/ Finance/ Accounting or related discipline a plus\nPreferably 1 to 3 years of credit analysis experience in international credit rating agencies or relevant roles in financial industry, experience in leading bond rating agencies of China is also welcomed\nDeep understanding of international credit rating agency\u2019s rating methodologies\nStrong credit analytical skill and good understanding of financial analysis and financial modelling\nProactive, analytical minded with attention to details and market sense\nExcellent communication skills with fluency in written and spoken English and Mandarin\n\nApplication\nInterested parties please send a detailed resume, stating current and expected salary to Human Resources Department.\n\nInformation supplied will be treated in strict confidence and used in accordance with the Personal Data (Privacy) Ordinance.\u00a0 Applicants not invited for interview within 6 weeks may consider their applications unsuccessful.", "employment_types": ["Full Time", "Permanent"], "selling_points": ["1 to 3 years of credit analysis experience", "Growing Company with rapid expansion", "Attractive remuneration package"], "locations": ["Causeway Bay"], "categories": ["Banking / Finance", "Credit Analysis / Approval", "Investment", "Insurance", "Others"], "post_time": "2022-01-13T10:25:05Z", "salary": {"currency": null, "max": null, "min": null, "period": "monthly", "term": null}, "salary_visible": false, "title_keywords": ["analyst", "credit analyst"], "responsibilities": ["ad-hoc", "due diligence", "maintaining", "policies", "review", "procedures", "developing", "maintain", "fixed-income investment", "ad-hoc projects"], "requirements": {"degrees": ["degree", "bachelor"], "majors": ["finance", "economics", "business", "accounting"], "languages": ["english", "mandarin"], "language_level": ["fluency", "excellent"], "hard_skills": ["credit analysis", "plus", "financial analysis", "analytical skill"], "soft_skills": ["communication skills", "analytical skill", "deep", "attention to details", "proactive"], "languages_combined": [{"language": "english", "language_level": ["fluency", "excellent"]}, {"language": "mandarin", "language_level": ["fluency", "excellent"]}]}, "experience_required": {"duration": ["1 to 3 years"], "field": ["financial industry"]}}, {"job_id": "100003009049982", "location_code": "hk", "company": "The Bank of East Asia, Limited", "job_title": "Risk Officer (Credit Assessment)", "description": "Risk Officer (Credit Assessment) (Job ID: 3294)\n\nResponsibilities\n\nTo be a team member of Credit Risk Management Department\nTo perform independent credit assessment and make recommendations according to credit guidelines and policies\nTo assist in the formulation and review of credit policies and guidelines\nTo support daily administration and ad hoc projects as required\n\nRequirements\n\nUniversity graduate in Risk Management, Finance, Business, Economics or related discipline\nKnowledge of financial analysis techniques and 1-2 years of working experience in the banking industry or financial institution will be an advantage\nGood communication, presentation, analytical and time management skills\nA good team player, responsible with positive working attitude\nGood command of both spoken and written English and Chinese\nProficient with Microsoft Office application including Word and Excel\n\nPlease apply online via the BEA Careers website at https://careers.hkbea.com/psp/hcmprd/EMPLOYEE/HRMS/c/HRS_HRAM.HRS_APP_SCHJOB.GBL?Page=HRS_APP_JBPST&Action=U&FOCUS=Applicant&SiteId=1&JobOpeningId=3294&PostingSeq=1 or by clicking the Apply Now button. Kindly note that if you are a new user, you have to first create your User Profile before you can apply.\n\nPersonal data provided by job applicants will be used for recruitment purposes only and will be treated in accordance with the Bank's Personal Data Policy, which is available upon request. Applicants who are not invited for interviews within six weeks may consider their applications unsuccessful and the personal data collected will be destroyed after six months.", "employment_types": ["Full Time", "Permanent"], "selling_points": ["Perform independent credit assessment", "Formulate & review credit policies and guidelines", "University graduates with 1-2 yrs' exp in banking"], "locations": ["Kwun Tong"], "categories": ["Banking / Finance", "Credit Analysis / Approval", "Financial Services", "Others"], "post_time": "2022-01-15T03:50:46Z", "salary": {"currency": null, "max": null, "min": null, "period": null, "term": null}, "salary_visible": false, "title_keywords": ["officer"], "responsibilities": ["make recommendations", "management", "guidelines", "policies", "review", "ad hoc projects", "administration"], "requirements": {"degrees": ["university graduate"], "majors": ["finance", "risk management", "business", "economics"], "languages": ["english", "chinese"], "language_level": ["good command"], "hard_skills": ["excel", "microsoft office", "word", "financial analysis", "c"], "soft_skills": ["good team player", "responsible", "time management skills", "communication", "positive working attitude", "presentation"], "languages_combined": [{"language": "english", "language_level": ["good command"]}, {"language": "chinese", "language_level": ["good command"]}]}, "experience_required": {"duration": ["1-2 years"], "field": ["banking industry", "financial"]}}, {"job_id": "100003009050874", "location_code": "hk", "company": "Manpower Services (Hong Kong) Limited", "job_title": "Credit & Trade Finance Specialist (25-40K)", "description": "Responsibilities:\n\nProcessing import LC / amendments issuances and import collections and the related acceptances and payments\nProcessing Back to back, Front to back, Standby LC/amendments & Trade-related Bank Guarantee and Shipping Guarantee issuance/redemption and the related acceptances and payments\nProcessing export LC/amendments advising, confirmation, transfer and export negotiations/collections and the related acceptance and payments\nHandling Import and Export collection bills under DA/DP\nHandling of import and export loans and discounting loans, roll-over, payments and past due loans\nHandling of funded and unfunded participations in system and payments\nPerform KYC validation and Anti-money Laundering Checks on trade finance transactions;\nInput trade finance transactions into related systems and generate entries and customer advices;\nInput payment and other SWIFT messages into related systems\nSend emails/faxes to customers, sorting of documents, matching of SWIFT messages, photocopy of documents and filing duties;\nScanning of documents to outsourcing center for checking\nSending out export documents to LC issuing banks / negotiating banks\nAttend to Customer queries on trade finance activities covered\nEscalate to team leaders, team head or Head, Trade Finance Support Services for any exception, problem, error and abnormal transaction identified during processing.\nAll other job duties as and when assigned by team leaders, team head or Head, Trade Finance Support Services.\u00a0\u00a0\u00a0\u00a0\u00a0\u00a0\u00a0\u00a0\u00a0\n\nJob Requirements\n\n3 years relevant experience in Corporate / Commodities Trade Finance BO services\nGood attitude and interpersonal skills.\nFluent written and spoken English\nSpoken Mandarin & Cantonese, Written Chinese an advantage\nKnowledge in trade finance product is key. UCP 600, International trade and the\u00a0Incoterms 2020 rules, URC 522, ISBP, ISP, URDG & URR 725\nFamiliar with Microsoft Windows (Excel, Word, PowerPoint)\n\nInterested parties please send your full resume with expected salary to yan.chan@manpowergrc.hk\u00a0or by clicking \"Apply Now\".", "employment_types": ["Contract"], "selling_points": ["Corporate / Commodities Trade Finance BO services", "LC Issuance", "3 years relevant experience"], "locations": ["Aberdeen"], "categories": ["Banking / Finance", "Corporate Banking", "Credit Analysis / Approval", "Financial Services"], "post_time": "2022-01-14T11:36:22Z", "salary": {"currency": null, "max": null, "min": null, "period": "monthly", "term": null}, "salary_visible": false, "title_keywords": ["specialist"], "responsibilities": ["scanning", "shipping", "systems", "support services", "checking", "transactions", "payment", "payments", "kyc", "customer queries"], "requirements": {"degrees": [], "majors": [], "languages": ["cantonese", "english", "chinese", "mandarin"], "language_level": ["advantage", "fluent"], "hard_skills": ["excel", "word", "powerpoint"], "soft_skills": ["interpersonal skills"], "languages_combined": [{"language": "cantonese", "language_level": []}, {"language": "english", "language_level": ["fluent"]}, {"language": "chinese", "language_level": ["advantage"]}, {"language": "mandarin", "language_level": []}]}, "experience_required": {"duration": ["3 years"], "field": ["finance", "relevant experience"]}}, {"job_id": "100003009042887", "location_code": "hk", "company": "Industrial and Commercial Bank of China (Asia) Limited", "job_title": "Senior / Credit Analyst (Corporate Banking)", "description": "Job Responsibilities\nAssess all underlying risk of credit applications\nConduct cashflow analysis, projection, peer comparison, if applicable, with reference to the relevant information gathered from internal and external sources\nCoordinate with Corporate/Business Managers for any matters related to credit applications, further elaborate and clarify with respective commercial officers if needed\nGive comments if any special approvals and date postponement are required\nKeep track on any credit issues that need to be followed up and conduct interim review of any accounts if required\nMonitor turnaround timeframe for processing of credit proposals\nApprove credit applications within the delegated authority\nPerform other duties delegated by the Section Head\nRequirements\nUniversity graduate\nExperience in credit analyst with relevant credit analysis and bills operation trainings\nSound knowledge of local economic/industrial conditions, banking laws & practices, in-depth knowledge of import & export operations and related lending products offered by Banks\nACIB, Certified Banker (CB) or other relevant professional qualifications are preferred\nGood analytical & report writing skills with logical credit judgment\nSelf-motivated and able to work independently & under pressure with limited time constraints\nGood problem solving ability and tactful inter-personal & communication skills\nGood knowledge in PC skills\nGood command of written & spoken English & Chinese\nCandidate with more experience will be considered as Senior Manager / AVP", "employment_types": ["Full Time"], "selling_points": [], "locations": ["Not Specified"], "categories": ["Banking / Finance", "Credit Analysis / Approval"], "post_time": "2022-01-12T09:07:16Z", "salary": {"currency": null, "max": null, "min": null, "period": null, "term": null}, "salary_visible": false, "title_keywords": ["credit analyst"], "responsibilities": ["perform other duties", "credit issues", "analysis", "review", "comments", "coordinate with", "monitor"], "requirements": {"degrees": ["university graduate"], "majors": [], "languages": ["english", "chinese"], "language_level": ["good command"], "hard_skills": ["professional qualifications", "writing skills", "problem solving", "credit analysis", "pc skills", "banking laws"], "soft_skills": ["communication skills", "self-motivated", "work independently", "under pressure", "inter-personal", "writing skills", "problem solving", "tactful"], "languages_combined": [{"language": "english", "language_level": ["good command"]}, {"language": "chinese", "language_level": ["good command"]}]}, "experience_required": {"duration": [], "field": ["operation"]}}, {"job_id": "100003009049337", "location_code": "hk", "company": "Shanghai Commercial Bank Ltd", "job_title": "Assistant Vice President, Credit Review", "description": "Responsibilities:\n\nPrepare credit facility review with focus on property development, construction financing, and syndication to identify and assess potential problematic credit accounts\nConduct risk evaluation and make recommendation on credit facilities on large scale customers\nEnsure compliance with of bank policy and regulatory requirements\nAssist in formulating credit policies, guidelines and procedures of credit activities undertaken by the bank\nExperience in handling regulatory and external/internal audit onsite examination an advantage\nHandle ad-hoc credit tasks as assigned\nCollaborate with business units and assess various market information/event and internal & external early warning signal to detect potential problem accounts for close & early management\nTake immediate action to manage & mitigate account irregularity and credit risk\nRequirements:\n\nDegree holder in Business Administration, Finance, Risk Management or related disciplines\nHolder of ECF-CRM certification an advantage\nMinimum 8 5 years of experience of solid experience in commercial / corporate/ listed companies' credit analysis (in terms of credit risk aspects and financial viability) and credit risk management in banking industry, experience in supervisory role an advantage.\nStrong understanding of legal and regulatory requirements and banking practices on credit risk management\nSelf-motivated with good analytical skill and risk control knowledge\nGood command of written and spoken English and Chinese\n\nAttractive remuneration package will be offered to the right candidates. Interested parties please click \"Apply Now\" to submit your full resume with current and expected salary to the Human Resources Division.\n\nPlease visit us at www.shacombank.com.hk for more information about our Bank.\n\nAll personal data collected will be used for recruitment related purposes strictly in accordance with the Bank's personal data policies, a copy of which will be provided immediately upon request by contacting our Personal Data Compliance Officer. Applicants who are not contacted within two months may consider their applications unsuccessful and the personal data collected from the applicants will be retained for no longer than two years from the date of rejection during which the applicants may be considered for other suitable positions within the Bank.", "employment_types": ["Full Time", "Permanent"], "selling_points": ["Prepare credit facility review", "Conduct risk evaluation and make recommendation", "Formulate credit policies, guidelines & procedures"], "locations": ["North Point"], "categories": ["Banking / Finance", "Credit Analysis / Approval", "Others", "Risk Management"], "post_time": "2022-01-15T03:50:19Z", "salary": {"currency": null, "max": null, "min": null, "period": "monthly", "term": null}, "salary_visible": false, "title_keywords": ["assistant vice president"], "responsibilities": ["ad-hoc", "collaborate with", "management", "market information", "make recommendation", "internal audit", "guidelines", "regulatory requirements", "policies", "review", "procedures", "ensure compliance", "evaluation", "credit facility"], "requirements": {"degrees": ["degree holder"], "majors": ["related disciplines", "finance", "business administration", "risk management"], "languages": ["english", "chinese"], "language_level": ["good command"], "hard_skills": ["credit analysis", "analytical skill"], "soft_skills": ["self-motivated", "analytical skill"], "languages_combined": [{"language": "english", "language_level": ["good command"]}, {"language": "chinese", "language_level": ["good command"]}]}, "experience_required": {"duration": ["5 years"], "field": ["banking industry", "management", "supervisory", "commercial", "credit risk", "financial"]}}, {"job_id": "100003009046096", "location_code": "hk", "company": "Zero Finance Hong Kong Limited", "job_title": "Senior Credit Officer / Assistant Manager - Mortgage Loan", "description": "In this role, you will perform:\n\nResponsible for proactively follow up with related parties\nExecute properties appraisal on the new mortgage loans and refinance applications\nMaintain close relationship with agency and solicitors\u2019 firms\nEnsure the correctness of loan contracts before corporate approval\nImplement business plan to achieve sales targets\n\nTo be successful in this role, you should meet the following requirements:\u00a0\n\nTertiary education or above, finance or other business related disciplines are preferred\nPreferably 5 years relevant experience in Money Lending Industry\nGood command of spoken & written English, Cantonese and Mandarin\nStrong adaptability and flexibility\nProficient in MS Word, MS Excel and Chinese Word Processing\nLess experience will be considered as Senior Officer\n\nCompany Website: https://www.zerofinance.hk/zh/\u00a0\n\nAttractive remuneration package will be offered to the right candidate. Please apply with full resume stating present and expected salary to us by\u00a0clicking \u201cAPPLY NOW\u201d.\n\n(Personal data collected will be used for recruitment purpose only.)", "employment_types": ["Full Time", "Permanent"], "selling_points": ["Mortgage loans operation", "Credit administration", "5 days work, bank holidays"], "locations": ["Sheung Wan"], "categories": ["Banking / Finance", "Credit Analysis / Approval", "Loan", "Mortgage"], "post_time": "2022-01-13T09:36:31Z", "salary": {"currency": null, "max": null, "min": null, "period": "monthly", "term": null}, "salary_visible": false, "title_keywords": ["officer", "assistant manager"], "responsibilities": ["contracts", "maintain", "recruitment", "business plan", "personal data", "company website"], "requirements": {"degrees": [], "majors": [], "languages": ["cantonese", "english", "chinese", "mandarin"], "language_level": ["good command", "proficient"], "hard_skills": ["ms excel", "chinese word processing", "ms word"], "soft_skills": ["adaptability", "responsible"], "languages_combined": [{"language": "cantonese", "language_level": ["good command"]}, {"language": "english", "language_level": ["good command"]}, {"language": "chinese", "language_level": ["proficient"]}, {"language": "mandarin", "language_level": ["good command"]}]}, "experience_required": {"duration": ["5 years"], "field": ["relevant experience"]}}, {"job_id": "100003009053978", "location_code": "hk", "company": "Hang Seng Bank Ltd", "job_title": "Director Signature/ Associate Director Signature", "description": "Retail Distribution\n\nHang Seng's Retail Distribution focuses on personal wealth management and financial services. Our one-stop wealth management initiatives are designed for both our affluent and mass integrated account customers. With more than 290 branches and automated banking centers, including around 60 Prestige Banking Centers for our high-end personal customers, we serve over half of the adult population in Hong Kong while offering an extensive range of products to our valued customers.\n\nWe are currently seeking high caliber professionals to join our department as\u00a0Director Signature/\u00a0Associate Director Signature\n\nPrincipal responsibilities\nProvide professional financial planning services to high-net-worth / top-tier Prestige Signature customers\nProvide personalized and all-rounded wealth management service for this segment of customers to build and maintain good relationships\nPromote holistic wealth management service for optimizing new business opportunities\nAssist the team head in providing coaching to Relationship Managers\nManage operational risk and observe the relevant policies / guidelines and compliance requirements\n\u00a0\u00a0\n\n\nHang Seng Bank Relationship Manager Virtual Recruitment Talk\u00a0\n\nIf you are keen to find out more about the working culture and how we nurture our Relationship Managers for their success at Hang Seng Bank, please join our Virtual Recruitment Talk\u00a0to hear the candid sharing from our Branch Networks business leaders and also our RMs. You will also find out our progressive career ladder for RMs from entry-level RM Trainee to Signature and Executive RM.\n\nDate:\u00a026 January 2022 (Wed)\n\nTime: 6:00 - 7:00 PM\n\nLocation:\u00a0Virtual Session \u2013 Dial in details will be provided upon registration\n\nRegister your place before 26 Jan 2022 by clicking\u00a0https://hsbc.zoom.us/webinar/register/WN_KABEhwC-RJqmSR07NkIS2g\u00a0\u00a0\n\nRequirements\nUniversity degree in a related discipline OR professional qualifications such as CFA, CFP or CFMP is preferred\nPasses in the Insurance Intermediaries Qualifying Examinations / Hong Kong Securities Institute Licensing Examinations\nFulfilment of the competency requirements to carry out relevant regulated activities as defined under the Securities and Futures Ordinance\nMinimum of five years' experience in selling investment, insurance and banking products\nStrong sales and customer orientation, with good communication and interpersonal skills\nStrong self-motivation and ability to work under pressure\nProficiency in both English and Chinese, with proficiency in Putonghua an advantage\nHigh level of customer centricity mindset and ability to manage complex interactions effectively\nShown strong situation awareness, strong desire to learn and able to work in Agile environment\nBe curious and with passion to think deeply and rationally\n\nIf you would like to explore other opportunities at Hang Seng Hong Kong, please visit\u00a0www.hangseng.com/careers/\u00a0for details.\n\nThe health and safety of our employees and candidates is very important to us. Due to the current situation related to the Novel Coronavirus (2019-nCoV), we\u2019re leveraging our digital capabilities to ensure we can continue to recruit top talent at the HSBC Group.\u00a0 As your application progresses, you may be asked to use one of our digital tools to help you through your recruitment journey.\u00a0 If so, one of our\u00a0 Resourcing colleagues will explain how our video-interviewing technology will be used throughout the recruitment process and will be on hand to answer any questions you might have.\nAll information provided by applicants will be used only for recruitment purposes and will be used strictly in accordance with the Bank's personal data policies, a copy of which may be obtained by the applicant upon request. Unless otherwise instructed in writing by the applicant concerned, applicants may be considered for other suitable positions within the Bank and its related companies. The personal data of unsuccessful job applicants may be retained for a maximum of two years from the date when the job application is rejected and such data may be retained for a longer period if there is a subsisting reason that obliges the Bank to do so, after which the personal data will be destroyed.", "employment_types": ["Full Time", "Permanent"], "selling_points": [], "locations": ["Not Specified"], "categories": ["Banking / Finance", "Credit Analysis / Approval", "Retail Banking", "Credit Collection"], "post_time": "2022-01-17T07:54:17Z", "salary": {"currency": null, "max": null, "min": null, "period": "monthly", "term": null}, "salary_visible": false, "title_keywords": ["associate director", "director"], "responsibilities": ["management", "guidelines", "policies", "business opportunities", "compliance", "maintain", "recruitment", "planning"], "requirements": {"degrees": ["university degree"], "majors": [], "languages": ["putonghua", "english", "chinese"], "language_level": ["advantage", "proficiency"], "hard_skills": ["agile", "professional qualifications", "cfa", "securities and futures ordinance", "reason"], "soft_skills": ["agile", "communication and interpersonal skills", "self-motivation", "novel", "work under pressure"], "languages_combined": [{"language": "putonghua", "language_level": ["proficiency", "advantage"]}, {"language": "english", "language_level": ["proficiency", "proficiency", "advantage"]}, {"language": "chinese", "language_level": ["proficiency", "proficiency", "advantage"]}]}, "experience_required": {"duration": ["minimum of five years"], "field": ["insurance", "investment", "banking"]}}, {"job_id": "100003009045317", "location_code": "hk", "company": "AXA Region Insurance Company Limited", "job_title": "\u6bcf\u54684\u5929\u5de5\u4f5c\u4e0d\u8a2d\u696d\u7e3e\u58d3\u529b / \u8ca1\u5bcc\u7406\u8ca1\u7d93\u7406 Wealth Management Manager/ \u5f37\u7a4d\u91d1\u6574\u5408\u5c08\u54e1 MPF Consultant", "description": "\u6211\u5011\u63d0\u4f9b\u5168\u9762\u4e00\u7ad9\u5f0f\u7406\u8ca1\u670d\u52d9\uff1a\u5305\u62ec: \u8ca1\u5bcc\u7ba1\u7406\uff0c\u8cc7\u7522\u50b3\u627f\uff0c\u9000\u7a05\u81ea\u9858\u91ab\u4fdd\uff0c\u5371\u75be\u4fdd\u969c\u3001\u77ed\u671f\u9ad8\u5132\u755c\u7522\u54c1\u3001\u5f37\u7a4d\u91d1\u6574\u5408\uff0c\u9000\u7a05\u5e74\u91d1\u9000\u4f11\u7b56\u5283\u3001\u4e00\u822c\u4fdd\u96aa\u3001\u516c\u53f8\u5718\u9ad4\u91ab\u7642\uff0c\u4f01\u696d\u4fdd\u96aa\n\n\u6211\u5011\u62db\u52df\u6709\u610f\u5275\u696d\u6216\u767c\u5c55\u500b\u4eba\u4e8b\u696d\u7684\u60a8\uff0c\u4ee5\u96f6\u6210\u672c\u6253\u9020\u4e00\u500b\u7531\u60a8\u81ea\u5df1\u8a71\u4e8b\u7684\u8ca1\u7b56\u672a\u4f86\uff01\n\n\u5982\u679c\u4f60\u662f\n\n\u5177\u4f01\u696d\u5bb6\u614b\u5ea6\uff0c\u6709\u5fd7\u5c0b\u627e\u9ad8\u6536\u5165\n\u4e8b\u696d\u505c\u6eef\u4e0d\u524d\uff0c\u6c92\u6709\u767c\u5c55\u7a7a\u9593\n\u5617\u8a66\u4e00\u500b\u65b0\u7684\u884c\u696d\u6311\u6230\uff0c\u6539\u8b8a\u73fe\u72c0\n\u5de5\u4f5c\u91cd\u8986\u6c89\u60b6\n\u559c\u6b61\u5f48\u6027\u81ea\u4e3b\u5de5\u4f5c\u6a21\u5f0f\n\u597d\u62fc\u640f\u4f46\u662f\u6536\u5165\u8207\u52aa\u529b\u4e0d\u6210\u6b63\u6bd4\n\n\u5982\u679c\u4f60\u52e4\u596e\u9032\u53d6\uff0c\u4fdd\u96aa\u7406\u8ca1\u4e8b\u696d\u7d55\u5c0d\u662f\u4e00\u4efd\u975e\u5e38\u6709\u6311\u6230\u6027\u7684\u5de5\u4f5c\uff0c\u7d55\u5c0d\u591a\u52de\u591a\u5f97\n\n\u52a0\u5165\u6211\u5011AXA\u5b89\u76db !!\u00a0\n\n\u5de5\u4f5c\u7bc4\u570d\u00a0\n\n\u70ba\u5ba2\u6236\u5ea6\u8eab\u5b9a\u505a\u9069\u5207\u7406\u8ca1\u65b9\u6848\uff0c\u5305\u62ec\u4fdd\u96aa, \u6559\u80b2\u57fa\u91d1, \u9000\u4f11\uff0c\u50b3\u627f\uff0c\u6295\u8cc7\u7b49\u65b9\u6848\n\u4e00\u822c\u4fdd\u96aa\u7522\u54c1\u54a8\u8a62\u53ca\u5831\u50f9\u670d\u52d9\u00a0\u00a0\n\u5f37\u7a4d\u91d1\u670d\u52d9\n\u4f01\u696d\u4fdd\u96aa\uff0c\u5718\u9ad4\u91ab\u7642\n\n\u5165\u8077\u8981\u6c42\n\n\u5927\u5c08\u6216\u5927\u5b78\u4ee5\u4e0a\uff0c\u85aa\u91d1\u7279\u512a\u00a0\n\u9999\u6e2f\u4e2d\u4e94\u6216\u4ee5\u4e0a\u7a0b\u5ea6 \uff0c\u570b\u5167\u9ad8\u8003\u5b78\u6b77\u6216\u4ee5\u4e0a\u00a0\n\u7121\u9700\u5de5\u4f5c\u7d93\u9a57\uff0c\u6b61\u8fce\u570b\u5167\u50d1\u80de\uff0c\u65b0\u79fb\u6c11\uff0c\u6301 IANG \u7c3d\u8b49\u5c08\u624d\u52a0\u76df\n\u6b61\u8fce\u4fdd\u96aa\u540c\u696d, \u9280\u884c\u8077\u54e1\u8f49\u8077, \u53ef\u76f4\u63a5\u5b89\u6392\u7ba1\u7406\u8077\u4f4d\u53ca\u7279\u512a\u5f85\u9047 (\u8f49\u8077\u88dc\u511f\u91d1)\n\u826f\u597d\u4eba\u969b\u95dc\u4fc2\uff0c\u6e9d\u901a\u6280\u5de7\u00a0\n\u826f\u597d\u7684\u5718\u968a\u5408\u4f5c\u7cbe\u795e\uff0c\u80fd\u5920\u5728\u58d3\u529b\u4e0b\u7368\u7acb\u5de5\u4f5c\u00a0\n\u52e4\u596e\u5916\u5411\uff0c\u71b1\u8aa0\uff0c\u8cac\u4efb\u611f\u00a0\n\n\u6211\u5011\u63d0\u4f9b\uff1a\u00a0\n\n\u514d\u8cbb\u8003\u8a66\u5377\u4e00\u5377\u4e09\u00a0\n24\u500b\u6708\u8ca1\u52d9\u652f\u63f4\uff08\u6bcf\u6708\u6d25\u8cbc $10,000- $40,000\uff09+ \u7121\u4e0a\u9650\u4f63\u91d1 \uff0b9\u500b\u82b1\u7d05 \uff0b\u767e\u842c\u5713\u684c\u6703\u82b1\u7d05\n\u89c0\u5858\u7532\u7d1a\u5beb\u5b57\u6a13\n\u5b8c\u5584\u5728\u8077\u57f9\u8a13\n\u63d0\u4f9b\u6a5f\u6703\u8003\u53d6\u300a\u6838\u51c6\u9000\u4f11\u9867\u554fQRA\u300b\u300a\u4eba\u58fd\u4fdd\u96aa\u6838\u4fdd\u8b49\u66f8\u300b\u7b49\u5c08\u696d\u8cc7\u683c\u00a0\n\nMDRT\u5718\u968a\u57f9\u8a13\u5e2b\uff0c\u884c\u696d\u5091\u51fa\u63a8\u92b7\u54e1\u734e(DSA)\u51a0\u8ecd\u57f9\u8a13\u5e2b\u5718\u968a\n\u52a9\u4f60\u6210\u70ba\u884c\u696d\u7cbe\u82f1\uff0c\u6210\u70baMDRT\uff0c\u7279\u5feb\u767c\u5c55\u5c6c\u65bc\u81ea\u5df1\u7684\u7406\u8ca1\u7b56\u5283\u4e8b\u696d!", "employment_types": ["Full Time"], "selling_points": ["\u6bcf\u6708\u6d25\u8cbc $10,000- $40,000 + \u7121\u4e0a\u9650\u4f63\u91d1 \uff0b9\u500b\u82b1\u7d05", "\u6bcf\u5e74\u696d\u7e3e\u734e\u8cde\u74b0\u7403\u65c5\u904a \uff0c\u5718\u9ad4\u91ab\u7642\u798f\u5229", "\u7279\u5feb\u5347\u8077\u6a5f\u6703"], "locations": ["Kwun Tong"], "categories": ["Banking / Finance", "Credit Analysis / Approval", "Admin & HR", "Training & Development", "Others", "Student / Fresh Graduate / No Experience"], "post_time": "2022-01-13T07:36:33Z", "salary": {"currency": null, "max": null, "min": null, "period": "monthly", "term": null}, "salary_visible": false, "title_keywords": ["wealth management manager", "mpf consultant"], "responsibilities": [], "requirements": {"degrees": [], "majors": [], "languages": [], "language_level": [], "hard_skills": [], "soft_skills": [], "languages_combined": []}, "experience_required": {"duration": [], "field": []}}, {"job_id": "100003009047719", "location_code": "hk", "company": "Public Bank (Hong Kong) Limited", "job_title": "Senior Credit Analyst (Ref: JD-SCA)", "description": "Perform credit evaluation and risk assessment on commercial and retail credit proposals and periodic reviews\nIdentify and assess credit risks and potential problems, and make recommendations for appropriate lending authority\u2019s consideration and approval\nEnsure efficient turnaround of credit processing\nDegree holder with minimum 5 years of solid experience in commercial credit\u00a0and risk management functions in banking industry\nExcellent interpersonal and communication skills in both English and Chinese\nCandidate with less experience will be considered as Credit Analyst\nWith Enhanced Competency Framework (ECF) qualification is preferable\n\nTo apply, interested parties please follow the application methods available in the Bank\u2019s career website https://www.publicbank.com.hk/en/aboutus/careeropportunities. You can send us your resume quoting our job reference number together with present & expected salary (a must) to the Human Resources Department by email or fax at 2815 3157 or by post to Human Resources Department, 12/F, Public Bank Centre, 120 Des Voeux Road Central, Hong Kong. You may also visit our career website for other career opportunities available within our Group.\n\nPersonal data collected will be used for recruitment purpose only and will be treated in accordance with the Bank\u2019s Personal Information Collection Statement, a copy of which has been available in the Bank\u2019s career website.", "employment_types": ["Full Time", "Permanent"], "selling_points": [], "locations": ["Not Specified"], "categories": ["Banking / Finance", "Credit Analysis / Approval", "Loan", "Mortgage"], "post_time": "2022-01-15T03:48:59Z", "salary": {"currency": null, "max": null, "min": null, "period": null, "term": null}, "salary_visible": false, "title_keywords": ["credit analyst"], "responsibilities": ["make recommendations", "management", "evaluation", "communication", "banking"], "requirements": {"degrees": ["degree holder"], "majors": ["risk management"], "languages": ["english", "chinese"], "language_level": ["excellent"], "hard_skills": ["make", "credit processing"], "soft_skills": ["make recommendations", "communication skills", "interpersonal", "efficient"], "languages_combined": [{"language": "english", "language_level": ["excellent"]}, {"language": "chinese", "language_level": ["excellent"]}]}, "experience_required": {"duration": ["minimum 5 years"], "field": ["commercial", "banking industry", "risk management"]}}, {"job_id": "100003009049036", "location_code": "hk", "company": "Industrial and Commercial", "job_title": "Assistant Manager to Senior Manager,  Corporate Credit Policy, CMD", "description": "Job Responsibilities\nFormulate, review and update credit policies for corporate banking in line with regulatory requirements and internal guidelines\nWork with business departments, approval department and back offices to collect their feedback on policy updating arrangements\nKeep abreast of the latest regulatory and market developments on credit matters\nPerform regular portfolio credit risk analysis and other ad hoc report\nJob Requirements\nUniversity graduate\nMinimum 3 years Corporate/Commercial/SME banking experience\nSelf-motivated with good communication skills\nProficient in MS Office applications, including Word, Excel and PowerPoint\nGood command of Chinese and English with knowledge of Putonghua", "employment_types": ["Full Time"], "selling_points": [], "locations": ["Central"], "categories": ["Banking / Finance", "Credit Analysis / Approval"], "post_time": "2022-01-14T07:57:32Z", "salary": {"currency": null, "max": null, "min": null, "period": "monthly", "term": null}, "salary_visible": false, "title_keywords": ["senior manager", "assistant manager"], "responsibilities": ["guidelines", "policies", "regulatory requirements", "review", "ad hoc report", "risk analysis", "banking"], "requirements": {"degrees": ["university graduate"], "majors": [], "languages": ["putonghua", "english", "chinese"], "language_level": ["good command"], "hard_skills": ["excel", "word", "powerpoint", "ms office"], "soft_skills": ["communication skills", "self-motivated"], "languages_combined": [{"language": "putonghua", "language_level": ["good command"]}, {"language": "english", "language_level": ["good command"]}, {"language": "chinese", "language_level": ["good command"]}]}, "experience_required": {"duration": ["minimum 3 years"], "field": ["commercial", "banking experience"]}}, {"job_id": "100003009049333", "location_code": "hk", "company": "Shanghai Commercial Bank Ltd", "job_title": "Assistant Vice President/ Manager, Credit Appraisal (Corp/Commercial - HK & China)", "description": "Responsibilities:\n\nAnalyse and review complex and sizeable loans in HK and the Mainland to ensure that they adhere to existing policy guidelines\nLiaise with business units to resolve credit issues and expedite the process\nAssist in collecting market intelligence through various channels\nPrepare various MIS reports for the management's review\nEnsure credit facilities adhere to the Bank's internal credit policies/guidelines as well as external regulatory requirements\nConduct site visits for customers in China\nRequirements:\n\nDegree holder in Finance, Risk Management or related disciplines.\u00a0 Professional qualifications, such as CFA, CPA, ECF-CRM, etc., are preferred.\nMinimum 8 years of experience in credit approval for both HK and China SME and Corporates\nSound knowledge in lending and hedging products\nGood understanding of market practice and banking regulations in HK and China\nSelf-motivated and detail-minded with strong risk control senses and analytical skills\nStrong in written and spoken English and Chinese, proficiency in Putonghua is preferable\nTravelling to China for site visits is occasionally required\n(Candidates with substantial experience may be considered for VP level)\n\n\nAttractive remuneration package will be offered to the right candidates. Interested parties please click \"Apply Now\" to submit your full resume with current and expected salary to the Human Resources Division.\n\nPlease visit us at www.shacombank.com.hk for more information about our Bank.\n\nAll personal data collected will be used for recruitment related purposes strictly in accordance with the Bank's personal data policies, a copy of which will be provided immediately upon request by contacting our Personal Data Compliance Officer. Applicants who are not contacted within two months may consider their applications unsuccessful and the personal data collected from the applicants will be retained for no longer than two years from the date of rejection during which the applicants may be considered for other suitable positions within the Bank.", "employment_types": ["Full Time"], "selling_points": ["Analyse and review complex and sizeable loans", "Resolve credit issues and expedite the process", "Assist in collecting market intelligence"], "locations": ["Central"], "categories": ["Banking / Finance", "Credit Analysis / Approval", "Others"], "post_time": "2022-01-15T03:50:18Z", "salary": {"currency": null, "max": null, "min": null, "period": "monthly", "term": null}, "salary_visible": false, "title_keywords": ["manager", "assistant vice president"], "responsibilities": ["management", "guidelines", "credit issues", "policies", "review", "regulatory requirements", "reports", "liaise with", "analyse"], "requirements": {"degrees": ["degree holder"], "majors": ["related disciplines", "finance", "risk management"], "languages": ["putonghua", "english", "chinese"], "language_level": ["proficiency"], "hard_skills": ["cfa", "cpa", "analytical skills", "professional qualifications"], "soft_skills": ["detail-minded", "self-motivated", "analytical skills"], "languages_combined": [{"language": "putonghua", "language_level": ["proficiency"]}, {"language": "english", "language_level": ["proficiency"]}, {"language": "chinese", "language_level": ["proficiency"]}]}, "experience_required": {"duration": ["minimum 8 years"], "field": []}}, {"job_id": "100003009050747", "location_code": "hk", "company": "Dah Sing Financial Group", "job_title": "OK Finance - Branch Officer", "description": "Job Purpose:\n\n\nDirect and supervise the junior staff in performing the loan processing and administration including conduct loan interviews, data input into the system and loan disbursement.\nMain Responsibilities:\nAssist in day-to-day management of branch operation and ensure to deliver high quality service to customers.\nPerform credit analysis, evaluation and recommend loan approval according to the established credit guideline.\nCoach and train junior staff on delivering both quality service and sale support activity.\nIncumbent Requirements:\nForm 5 / Matriculated or above.\nAt least 3 years' experience in Finance/ Banking industry specialized in Consumer Finance business.\nFamiliar with branch operation & loan application processing\nGood interpersonal and communication skill.\nGood knowledge of MS office.\nGood command of written & spoken English and Chinese.\nCandidates with more experiences may be considered as Senior Branch Officer.\nPlease note that only shortlisted candidates will be notified.", "employment_types": ["Full Time", "Permanent"], "selling_points": ["Day-to-day management of branch operation", "Form 5 / Matriculated or above", "At least 3 years' experience in Finance/ Banking"], "locations": ["Not Specified"], "categories": ["Banking / Finance", "Credit Analysis / Approval", "Loan", "Order Processing & Operation / Settlement"], "post_time": "2022-01-14T11:15:46Z", "salary": {"currency": null, "max": null, "min": null, "period": "monthly", "term": null}, "salary_visible": false, "title_keywords": ["officer"], "responsibilities": ["day-to-day management", "analysis", "quality", "evaluation"], "requirements": {"degrees": ["form 5"], "majors": [], "languages": ["english", "chinese"], "language_level": ["good command"], "hard_skills": ["processing", "ms office"], "soft_skills": ["communication skill", "interpersonal"], "languages_combined": [{"language": "english", "language_level": ["good command"]}, {"language": "chinese", "language_level": ["good command"]}]}, "experience_required": {"duration": ["at least 3 years"], "field": ["finance", "business", "banking industry"]}}, {"job_id": "100003009053354", "location_code": "hk", "company": "Hang Seng Bank Ltd", "job_title": "Executive Customer Relationship Manager", "description": "Retail Distribution\n\nHang Seng's Retail Distribution focuses on personal wealth management and financial services. Our one-stop wealth management initiatives are designed for both our affluent and mass integrated account customers. With more than 170 branches and automated banking centres, including over 50 Prestige Banking Centres for our high-end personal customers, we serve over half of the adult population, offering an extensive range of products.\n\nWe are currently seeking a high caliber professional to join our team as\u00a0Executive Customer Relationship Manager.\n\nPrincipal responsibilities\n\nProvide financial planning services to high-net-worth customers\nProvide personalised service for this segment of customers to build and maintain good relationships\nPromote investment, insurance and banking products for optimising new business opportunities\nAssist the team head in providing coaching to Relationship Managers\nManage operational risk and observe the relevant policies /guidelines and compliance requirements\n\nHang Seng Bank Relationship Manager Virtual Recruitment Talk\u00a0\n\nIf you are keen to find out more about the working culture and how we nurture our Relationship Managers for their success at Hang Seng Bank, please join our Virtual Recruitment Talk\u00a0to hear the candid sharing from our Branch Networks business leaders and also our RMs. You will also find out our progressive career ladder for RMs from entry-level RM Trainee to Signature and Executive RM.\n\nDate:\u00a026 January 2022 (Wed)\n\nTime: 6:00 - 7:00 PM\n\nLocation:\u00a0Virtual Session \u2013 Dial in details will be provided upon registration\n\nRegister your place before 26 Jan 2022 by clicking\u00a0https://hsbc.zoom.us/webinar/register/WN_KABEhwC-RJqmSR07NkIS2g\u00a0\u00a0\n\n\n\nRequirements\n\nUniversity degree in a related discipline OR professional qualifications such as CFA, CFP or CFMP is preferred\nPasses in the Insurance Intermediaries Qualifying Examinations / Hong Kong Securities Institute Licensing Examinations\nFulfilment of the competency requirements to carry out relevant regulated activities as defined under the Securities and Futures Ordinance\nMinimum of five years' experience in selling investment, insurance and banking products\nStrong sales and customer orientation, with good communication and interpersonal skills\nStrong self-motivation and ability to work under pressure\nProficiency in both English and Chinese, with proficiency in Putonghua an advantage\nHigh level of customer centricity mindset with dedication to deliver exceptional quality services for customers\nIf you would like to explore other opportunities at Hang Seng Hong Kong, please visit\u00a0www.hangseng.com/careers/\u00a0for details.\n\n\n\n\nThe health and safety of our employees and candidates is very important to us. Due to the current situation related to the Novel Coronavirus (2019-nCoV), we\u2019re leveraging our digital capabilities to ensure we can continue to recruit top talent at the HSBC Group.\u00a0 As your application progresses, you may be asked to use one of our digital tools to help you through your recruitment journey.\u00a0 If so, one of our\u00a0 Resourcing colleagues will explain how our video-interviewing technology will be used throughout the recruitment process and will be on hand to answer any questions you might have.\n\n\n\nAll information provided by applicants will be used only for recruitment purposes and will be used strictly in accordance with the Bank's personal data policies, a copy of which may be obtained by the applicant upon request. Unless otherwise instructed in writing by the applicant concerned, applicants may be considered for other suitable positions within the Bank and its related companies. The personal data of unsuccessful job applicants may be retained for a maximum of two years from the date when the job application is rejected and such data may be retained for a longer period if there is a subsisting reason that obliges the Bank to do so, after which the personal data will be destroyed.", "employment_types": ["Full Time", "Permanent"], "selling_points": [], "locations": ["Not Specified"], "categories": ["Banking / Finance", "Credit Analysis / Approval", "Retail Banking", "Credit Collection"], "post_time": "2022-01-17T06:49:50Z", "salary": {"currency": null, "max": null, "min": null, "period": "monthly", "term": null}, "salary_visible": false, "title_keywords": ["executive", "relationship manager"], "responsibilities": ["guidelines", "policies", "business opportunities", "compliance", "maintain", "recruitment", "banking", "insurance", "planning"], "requirements": {"degrees": ["university degree"], "majors": [], "languages": ["putonghua", "english", "chinese"], "language_level": ["advantage", "proficiency"], "hard_skills": ["cfa", "reason", "securities and futures ordinance", "professional qualifications"], "soft_skills": ["novel", "communication and interpersonal skills", "self-motivation", "work under pressure"], "languages_combined": [{"language": "putonghua", "language_level": ["proficiency", "advantage"]}, {"language": "english", "language_level": ["proficiency", "proficiency", "advantage"]}, {"language": "chinese", "language_level": ["proficiency", "proficiency", "advantage"]}]}, "experience_required": {"duration": ["minimum of five years"], "field": ["insurance", "investment", "banking"]}}, {"job_id": "100003009050553", "location_code": "hk", "company": "Page Personnel", "job_title": "PB Credit Risk Transformation Project Manager - Top HK Bank!", "description": "Our client is a leading public bank in Hong Kong and they are currently looking for a role of Private Banking Credit Risk Transformation Program Manager to join the Risk Transformation team to conduct end to end review and drive transformation initiatives for the management of private bank credit risk for Asia Pacific. The candidate should have rich working experience in Credit Risk/ risk transformation within banking industry.\n\nClient Details\n\nOur client is one of Hong Kong's largest listed banks and they are now seeking a position of Private Banking Credit Risk Transformation Program Manager to join the Risk Transformation team to conduct end to end review and drive transformation initiatives for the management of private bank credit risk for Asia Pacific. This role will be supporting the \"Risk 2025\" Programme ('R2025') and Financial Risk Enhancement Programme ('FREP'), a multi-year programme mobilised to fundamentally transform and modernize the bank's approach to managing financial risks, across the first and second lines of defence. As such it will focus on driving the change necessary within the BAU environment to deliver against the objectives of the R2025 and FREP Programme and constituent workstreams as they relate to Private Banking.\n\nDescription\n\nResponsible for driving the delivery of the transformation initiatives while maintaining alignment with Business-led change priorities as well as ensuring interlock with Global Risk programmes such as R2025 and FREP related to Credit Risk\nPartner with the PB Business to drive initiatives related to credit process streamlining and system for risk management. Proactively engage stakeholders and internal customers by understanding the needs and challenges and sharing vision, best practice, and potential solutions; and work collaboratively with Risk IT and Risk Transformation to define new solutions and processes to enhance credit risk management\nDrive change within PB Credit Risk geared towards strategic R2025/FREP Programme objectives. Work within PB Credit Risk and Transformation to deliver a holistic, forward looking & globally integrated Credit Risk Management capability\nIn collaboration with the Global and other Regional Credit Risk teams, design and deliver solutions on a number of Risk Management initiatives including (but not limited to):\nReview opportunities for automating existing PB reports.\n* Support discussions with the Business for infrastructure and data requirements to ensure Risk's requirements are incorporated.\n* To align ASP PB data requirements into the group data management programme (as applicable) and assess/leverage global solutions for data infrastructure, sourcing, and data integrity.\nIdentify streamlining opportunities in the policies and processes for PB Credit Risk including exploring innovative technologies, e.g. Chatbot\nReview current state of services performed by PB Credit Risk and consider opportunities for realignment\nAssess the site and Centre of Excellence ('CoE') delegation authorities and work with relevant stakeholders to review and enable the CoE structure for the future\n\nProfile\n\nBachelor's Degree with major in Business Administration, Risk, Finance, IT or relevant discipline\n10 year of working experience in credit risk or risk transformation in Private Banking or other relevant line of business including Commercial Banking or Global Banking. Experience in Asia Pacific region is preferred\nExperience in projects leading to process efficiency in the customer credit process and internal cost reduction\nStrong English communication skills both verbal and written\nExcellent interpersonal skills, able to manage stakeholders proactively with excellent negotiation and influencing skills\nStrong problem-solving skills and able to work independently under pressure\nStrong self-motivation with sense of ownership and accountability\n\nJob Offer\n\nStimulating and challenging work\nDynamic working environment\nHuge global exposure\n15 days AL\n\nTo apply online please click the 'Apply' button below. For a confidential discussion about this role please contact Esther Liu on +852 2258 3537", "employment_types": ["Full Time", "Permanent"], "selling_points": ["Stimulating and challenging work", "Dynamic working environment", "Huge global exposure"], "locations": ["Not Specified"], "categories": ["Banking / Finance", "Credit Analysis / Approval", "Private Banking", "Risk Management"], "post_time": "2022-01-14T10:43:03Z", "salary": {"currency": null, "max": null, "min": null, "period": "monthly", "term": null}, "salary_visible": false, "title_keywords": ["project manager"], "responsibilities": ["management", "cost", "maintaining", "data", "policies", "review", "teams", "infrastructure", "design", "communication", "reports", "contact", "banking", "administration"], "requirements": {"degrees": ["degree", "bachelor"], "majors": ["finance", "it", "business administration"], "languages": ["english"], "language_level": [], "hard_skills": ["problem-solving skills", "focus", "dynamic", "data management"], "soft_skills": ["communication skills", "work independently", "under pressure", "negotiation", "responsible", "accountability", "integrity", "self-motivation", "interpersonal skills", "dynamic", "problem-solving skills", "focus", "innovative"], "languages_combined": [{"language": "english", "language_level": []}]}, "experience_required": {"duration": ["10 year"], "field": ["banking industry", "commercial", "business", "banking", "credit risk"]}}, {"job_id": "100003009050286", "location_code": "hk", "company": "Nanyang Commercial Bank", "job_title": "Risk Management Manager - Credit Risk Modelling (Ref: OG8007-CRM-JDB)", "description": "Responsible for the development, implementation and enhancement of credit risk rating models and systems. Monitor and report model performance. Formulate policies and procedures to facilitate the credit risk models implementation.\n\nRequirements:\n\n\nBachelor Degree holder or above in Risk Management, Statistics, Quantitative Finance or related disciplines preferably with professional qualification in ACCA / CPA / CFA / FRM / PRM;\nIn-depth knowledge in Basel regulatory requirements and banking practices in credit risk management is essential;\nAt least 4 years experience in the development of credit risk internal ratings-based system is preferred;\nSound knowledge in statistical and quantitative analysis and familiar with SAS, Excel VBA, SQL and MS office;\n\u00a0Analytical, independent, possession of good communication and interpersonal skills;\nProficient in both spoken and written English and Chinese, fluent in Putonghua is preferable.\n\nCandidate with less relevant experience will be considered as Assistant\u00a0Risk Management Manager.)\n\nIf you are flexible enough and zeal for a harmonious and supportive working environment where enables you to grow and succeed professionally, please send a full resume indicating your public examination results (HKCEE and HKALE / HKDSE), your present and expected salary and quoting reference number attention to Talent Acquisition Division, Nanyang Commercial Bank, 151 Des Voeux Road Central, Hong Kong or apply through email. For details, please visit https://www.ncb.com.hk/ and select the page Recruit.\n\nWe are an Equal Opportunities Employer. Data collected would be used for recruitment purposes only. Applicants who do not hear from us within 8 weeks may consider their applications unsuccessful and their data will be destroyed within 12 months of receipt.", "employment_types": ["Full Time", "Permanent"], "selling_points": ["Responsible for the development, implementation", "Monitor and report model performance", "At least 4 years relevant experience"], "locations": ["Central & Western Area"], "categories": ["Banking / Finance", "Analyst", "Credit Analysis / Approval"], "post_time": "2022-01-15T03:50:56Z", "salary": {"currency": null, "max": null, "min": null, "period": "monthly", "term": null}, "salary_visible": false, "title_keywords": ["risk management manager"], "responsibilities": ["management", "data", "policies", "regulatory requirements", "systems", "monitor", "implementation", "procedures", "analysis", "communication", "recruitment", "banking", "report"], "requirements": {"degrees": ["hkdse", "bachelor degree holder"], "majors": ["finance", "risk management", "related disciplines", "statistics"], "languages": ["putonghua", "english", "chinese"], "language_level": ["fluent", "proficient"], "hard_skills": ["excel", "acca", "vba", "sas", "cfa", "analysis", "sql", "cpa", "frm", "ms office"], "soft_skills": ["flexible", "supportive", "independent", "harmonious", "responsible", "communication and interpersonal skills"], "languages_combined": [{"language": "putonghua", "language_level": ["fluent", "proficient"]}, {"language": "english", "language_level": ["fluent", "proficient"]}, {"language": "chinese", "language_level": ["fluent", "proficient"]}]}, "experience_required": {"duration": ["at least 4 years"], "field": ["development", "relevant experience", "credit risk", "risk management"]}}, {"job_id": "100003009054791", "location_code": "hk", "company": "Public Finance Limited", "job_title": "Relief Branch Manager", "description": "Responsibilities:\nPerform relief/acting duties in branches and assist to manage the operations of the branches such as loan processing, credit approval, promotion of loan products etc.\nRequirements:\n5 years experience in banking / finance industry of which 3 years at supervisory level\nExperienced in preparing credit proposal or promoting banking / financial products e.g. personal loan, credit card, etc.\nResult-oriented, energetic, mature with good communication skills\nBenefits\nDouble Pay\nDiscretionary Bonus\nInsurance Benefits\nStudy subsidy\nApplication Method:\nBy E-mail via \"Apply Now\"\n\nPersonal data collected will be treated in the strictest confidence in accordance with our\u00a0Personal Information Collection Statement\u00a0and\u00a0Privacy Policy\u00a0and will be handled by authorized personnel for recruitment-related purposes only. All applications will be kept for a maximum period of one year as may be considered for other suitable positions within Public Finance Ltd. and its associated companies. For details, please visit the Company\u2019s website\u00a0http://www.publicfinance.com.hk", "employment_types": ["Full Time", "Permanent"], "selling_points": [], "locations": ["Not Specified"], "categories": ["Banking / Finance", "Credit Analysis / Approval", "Loan", "Financial Services"], "post_time": "2022-01-17T11:05:42Z", "salary": {"currency": null, "max": null, "min": null, "period": "monthly", "term": null}, "salary_visible": false, "title_keywords": ["manager"], "responsibilities": ["operations"], "requirements": {"degrees": [], "majors": [], "languages": [], "language_level": [], "hard_skills": [], "soft_skills": ["communication skills", "energetic", "result-oriented", "mature"], "languages_combined": []}, "experience_required": {"duration": ["5 years", "3 years"], "field": ["supervisory level", "finance industry", "banking"]}}, {"job_id": "100003009042692", "location_code": "hk", "company": "Conners Consulting Limited", "job_title": "Credit Analyst and Approver (multiple bank openings $40k - $90k)", "description": "Our clients are well-known and fast expanding banks and now looking for high calibre to join their group.\n\n\n\nResponsibilities\n\nPrepare comprehensive credit assessment for corporate and cross border clients\nApprove and review credit facilities following bank credit policies and authority\u00a0\nReview and formulate credit risk policy to cope with regulatory changes\u00a0\nMonitor limit and conduct investigation or exceptional approval for high risk accounts/clients\nEnsure all approval process and internal credit policies & procedures are aligned with regulatory requirements\nMonitor portfolio quality and submit regular MIS report for management review\n\nRequirements\n\nBachelor\u2019s degree in Accounting, Finance or related disciplines\nMinimum 3 years\u2019 credit analysis, approval or risk monitoring in banking industry\nProficiency in written and spoken English & Chinese\nGood PC skills in MS Word and Excel\n\nTo apply, please send your detailed resume to winnie[at]connersconsulting[dot]com or contact Winnie Lai at 3618 8348 for a confidential discussion.\n\nOnly shortlisted candidates will be notified.\n\nApplicants who are not contacted within two weeks may consider their applications unsuccessful.\n\nAll data collected will be used for recruitment purpose only & will be used strictly confidential.\n\nConners Consulting Limited\n\n2005 Kai Tak Commercial Building 317 Des Voeux Road Central Hong Kong\n\nTel: (852) 3996 8090\nWebsite:\u00a0www.connersconsulting.com", "employment_types": ["Full Time"], "selling_points": ["Credit Approval / Credit Analyst", "Attractive package and bonus scheme", "Multiple bank openings"], "locations": ["Central & Western Area"], "categories": ["Banking / Finance", "Analyst", "Credit Analysis / Approval", "Risk Management"], "post_time": "2022-01-12T08:24:57Z", "salary": {"currency": null, "max": null, "min": null, "period": "monthly", "term": null}, "salary_visible": false, "title_keywords": ["credit analyst"], "responsibilities": ["policies", "regulatory requirements", "review", "monitor", "procedures", "investigation", "quality", "management review", "report"], "requirements": {"degrees": ["degree", "bachelor"], "majors": ["related disciplines", "finance", "accounting"], "languages": ["english", "chinese"], "language_level": ["proficiency"], "hard_skills": ["credit analysis", "excel", "pc skills", "ms word"], "soft_skills": ["detailed"], "languages_combined": [{"language": "english", "language_level": ["proficiency"]}, {"language": "chinese", "language_level": ["proficiency"]}]}, "experience_required": {"duration": [], "field": []}}, {"job_id": "100003009047718", "location_code": "hk", "company": "Public Bank (Hong Kong) Ltd", "job_title": "Unit Head of Credit Analysis (Ref: JD-HCA)", "description": "Review and comment on credit applications, including but not limited to accounts with larger exposures and of complexity to ensure a high credit quality standard of the bank\u2019s loan portfolio\nLiaise with marketing units for information as may be required for Credit\u2019s review and appropriate lending authority\u2019s consideration purposes\nEnsure the lending terms and conditions of the credit applications are complied with the bank\u2019s policies and highlight any deviations or non-compliance for the consideration of higher lending authority\nPerform the supervisory functions over the credit analysis unit, and provide staff planning, development and on-the-job training to staff\nRegularly review on the procedure and turnaround time of credit proposals submitted to Credit Department to enhance the efficiency of workflow\nDegree holder with minimum 8 years\u2019 experience in credit assessment, financial analysis or risk management functions in financial institutions of which at least 4 years at managerial level\nConversant with financial analysis, bank lending and bills operations\nExcellent communication skills with good command of written and spoken English and Chinese\nWith Enhanced Competency Framework (ECF) qualification is preferable\n\n\n\nTo apply, interested parties please follow the application methods available in the Bank\u2019s career website https://www.publicbank.com.hk/en/aboutus/careeropportunities. You can send us your resume quoting our job reference number together with present & expected salary (a must) to the Human Resources Department by email or fax at 2815 3157 or by post to Human Resources Department, 12/F, Public Bank Centre, 120 Des Voeux Road Central, Hong Kong. You may also visit our career website for other career opportunities available within our Group.\n\nPersonal data collected will be used for recruitment purpose only and will be treated in accordance with the Bank\u2019s Personal Information Collection Statement, a copy of which has been available in the Bank\u2019s career website.", "employment_types": ["Full Time", "Permanent"], "selling_points": [], "locations": ["Not Specified"], "categories": ["Banking / Finance", "Corporate Banking", "Credit Analysis / Approval", "Loan"], "post_time": "2022-01-15T03:48:58Z", "salary": {"currency": null, "max": null, "min": null, "period": null, "term": null}, "salary_visible": false, "title_keywords": [], "responsibilities": ["management", "bank\u2019s policies", "operations", "analysis", "compliance", "review", "quality", "financial analysis", "communication", "liaise with", "planning"], "requirements": {"degrees": ["degree holder"], "majors": ["risk management"], "languages": ["english", "chinese"], "language_level": ["excellent", "good command"], "hard_skills": ["credit analysis", "financial analysis"], "soft_skills": ["communication skills"], "languages_combined": [{"language": "english", "language_level": ["excellent", "good command"]}, {"language": "chinese", "language_level": ["excellent", "good command"]}]}, "experience_required": {"duration": ["minimum 8 years", "at least 4 years"], "field": ["risk management", "financial institutions", "managerial", "financial"]}}, {"job_id": "100003009049923", "location_code": "hk", "company": "Nanyang Commercial Bank", "job_title": "Credit Monitoring Manager (Ref: OH8020-00-JDB)", "description": "Perform portfolio analysis to identify potential credit risks and provide professional advice on risk mitigation. Gather and analyse market information, monitor the performance of credit facilities utilization to identify early signs of credit deterioration.\u00a0Perform impairment assessment, conduct procedural reviews and relevant MIS reports. Make recommendations and review on credit risk management strategies to comply with relevant regulatory requirements.\n\nRequirements:\n\nDegree holder in Risk Management, Finance, Economics, Accounting, Information System or related disciplines;\nAt least 3 years experience in credit risk management and monitoring;\nSound knowledge in legal and regulatory requirements, Basel III and banking practices on credit risk management;\nHands-on experience of MS Excel, PowerPoint (Knowledge in database management and statistical computer applications is an advantage);\nAnalytical, independent with good communication skills;\nProficient in both spoken and written English and Chinese.\n\n(Candidate with less experience will be considered as Assistant Credit Monitoring Manager.)\n\nIf you are flexible enough and zeal for a harmonious and supportive working environment where enables you to grow and succeed professionally, please send a full resume indicating your public examination results (HKCEE and HKALE / HKDSE), your present and expected salary and quoting reference number attention to\u00a0Talent Acquisition Division, Nanyang Commercial Bank, 151 Des Voeux Road Central, Hong Kong or apply through email. For details, please visit https://www.ncb.com.hk/ and select the page Recruit.\n\nWe are an Equal Opportunities Employer. Data collected would be used for recruitment purposes only. Applicants who do not hear from us within 8 weeks may consider their applications unsuccessful and their data will be destroyed within 12 months of receipt.", "employment_types": ["Full Time", "Permanent"], "selling_points": ["Perform portfolio analysis to identify risks", "Analyse and review market information", "At least 4 years relevant working experience"], "locations": ["Central & Western Area"], "categories": ["Accounting", "Credit Control", "Banking / Finance", "Credit Analysis / Approval"], "post_time": "2022-01-15T03:50:41Z", "salary": {"currency": null, "max": null, "min": null, "period": "monthly", "term": null}, "salary_visible": false, "title_keywords": ["manager"], "responsibilities": ["make recommendations", "management", "market information", "data", "regulatory requirements", "analysis", "review", "monitoring", "communication", "reports", "monitor the performance", "database", "banking", "computer applications", "recruitment", "analyse"], "requirements": {"degrees": ["hkdse", "degree holder"], "majors": ["risk management", "finance", "economics", "related disciplines", "accounting"], "languages": ["english", "chinese"], "language_level": ["proficient"], "hard_skills": ["analysis", "information system", "powerpoint", "make", "ms excel"], "soft_skills": ["make recommendations", "communication skills", "flexible", "supportive", "independent", "harmonious", "hands-on"], "languages_combined": [{"language": "english", "language_level": ["proficient"]}, {"language": "chinese", "language_level": ["proficient"]}]}, "experience_required": {"duration": ["at least 3 years"], "field": ["management", "database management", "credit risk"]}}, {"job_id": "100003009047717", "location_code": "hk", "company": "Public Bank (Hong Kong) Limited", "job_title": "Assistant Manager - Special Projects Unit (Credit Department) (Ref: JD-AMSPU)", "description": "Assist in implementing credit risk management systems\nPrepare/ Review reports related to credit risk management for identification/ evaluation of potential risks\nAssist in development of electronic systems to enhance the Bank's loan delivery process\nAssist in managing credit-related projects\nUniversity Degree with minimum 6 years of banking experience, of which minimum 3 years in credit risk management function\nKnowledgeable in credit risk modeling and banking products\nStrong credit sense and conversant with financial analysis\nProficiency in data analysis using MS Excel\nWith Enhanced Competency Framework (ECF) qualification is preferable\n\nTo apply, interested parties please follow the application methods available in the Bank\u2019s career website https://www.publicbank.com.hk/en/aboutus/careeropportunities. You can send us your resume quoting our job reference number together with present & expected salary (a must) to the Human Resources Department by email or fax at 2815 3157 or by post to Human Resources Department, 12/F, Public Bank Centre, 120 Des Voeux Road Central, Hong Kong. You may also visit our career website for other career opportunities available within our Group.\n\nPersonal data collected will be used for recruitment purpose only and will be treated in accordance with the Bank\u2019s Personal Information Collection Statement, a copy of which has been available in the Bank\u2019s career website.", "employment_types": ["Full Time", "Permanent"], "selling_points": [], "locations": ["Not Specified"], "categories": ["Banking / Finance", "Credit Analysis / Approval", "Loan", "Mortgage"], "post_time": "2022-01-15T03:48:58Z", "salary": {"currency": null, "max": null, "min": null, "period": null, "term": null}, "salary_visible": false, "title_keywords": ["assistant manager"], "responsibilities": ["management", "review", "systems", "banking", "financial analysis", "data analysis", "reports", "evaluation"], "requirements": {"degrees": ["university degree"], "majors": ["risk management"], "languages": [], "language_level": [], "hard_skills": ["financial analysis", "analysis", "ms excel"], "soft_skills": [], "languages_combined": []}, "experience_required": {"duration": ["minimum 6 years", "minimum 3 years"], "field": ["credit risk", "management", "banking experience"]}}, {"job_id": "100003009053876", "location_code": "hk", "company": "JAC Recruitment Hong Kong Co., Limited", "job_title": "Credit Analyst Manager (VP) - Local Corp & Blue-Chips Coverage", "description": "Our client is a top-tier foreign bank. They are\u00a0looking for candidates to join as\u00a0Credit Analyst covering Local Corp & Blue-Chips Coverage.\u00a0\n\nResponsibilities:\n\n- Conduct credit analysis and prepare credit proposals for Corporate SOE and POE clients; Local Listed Companies, and some FI related clients.\n\n- Clients are being referred from mainland's branches with sales turnover above HKD 10b. As a Credit Manager, you would pro-actively perform on-going credit monitoring and risk management on clients and prepare industry reports.\n\n- Make sure the internal credit policies and procedures are followed to and help to enhance those policies and procedures, and to ensure compliance with regulatory standard.\n\n- Work closely with front-line\u00a0RM staff, credit admin, and credit approvers.\n\nRequirements:\n- University graduate in Business Administration, Accounting, Finance, Economics or related disciplines\n\n- 3-10 years' solid experience in corporate credit & lending experience\n\n- Experience in handling Corporate Banking Clients (FI / Local Corp. / China Corporates, SOE, POE / Blue-Chips) is an advantage\n\n- Good credit analysis, report writing and communication skills\n\n- Proficient in both spoken and written English and Chinese, Mandarin is preferred\n\n*We offer*\nAttractive remuneration packages along with annual discretionary bonus and generous employee benefits to the right candidates\n\n\"Interested candidates, please send an updated CV to kelvin.lam @jac-recruitment.com and CC jac.hk @jac-recruitment.com\"\n\nPlease contact Kelvin, Commercial & Corporate Banking Consultant at 2585 6731 for further discussion\n\nPersonal data collected will be used for employment-related purpose only. We regret to inform that only shortlisted candidates will be notified.\n\n", "employment_types": ["Full Time"], "selling_points": ["Leading Foreign Corporate Bank", "Great Career Development Plan", "Great salary increment"], "locations": ["Central & Western Area"], "categories": ["Banking / Finance", "Corporate Banking", "Credit Analysis / Approval", "Corporate Finance"], "post_time": "2022-01-17T07:40:32Z", "salary": {"currency": null, "max": null, "min": null, "period": "monthly", "term": null}, "salary_visible": false, "title_keywords": ["manager", "credit analyst"], "responsibilities": ["management", "policies", "analysis", "monitoring", "procedures", "ensure compliance", "reports"], "requirements": {"degrees": ["university graduate"], "majors": ["business administration", "finance", "economics", "related disciplines", "accounting"], "languages": ["english", "chinese", "mandarin"], "language_level": ["proficient"], "hard_skills": ["credit analysis"], "soft_skills": ["communication skills"], "languages_combined": [{"language": "english", "language_level": ["proficient"]}, {"language": "chinese", "language_level": ["proficient"]}, {"language": "mandarin", "language_level": ["proficient"]}]}, "experience_required": {"duration": ["3-10 years"], "field": ["banking"]}}, {"job_id": "100003009047344", "location_code": "hk", "company": "Asia One Credit Limited", "job_title": "Credit Officer", "description": "Responsibilities\n\nHandle daily loan operation from application, credit assessment to disbursement\nHandle portfolio management e.g. repayment monitoring, due diligence, refinancing, regularly reporting\nHandle general inquiries and maintain a good relationship with customers and business partners\nAssist in system maintenance and operational manual update\nRegularly review credit policies, procedures & market updates\nRequirements:\n\nBachelor degree holder in Accounting, Finance, Economic or related discipline\nMinimum of 3-year experiences in load operation and credit analysis\nAble to analyze complex financial data and willing to learn\nDetail-minded, able to work independently and good team player\nGood command of both spoken and written English, Chinese and Mandarin\nImmediate available is highly preferred.\n\nWe offer competitive remuneration package with comprehensive fringe benefits to the right candidates:\n\n- Birthday Leave / Marriage Leave / Paternity Leave / Examination Leave\n- Staff Care Programme\n- Career Development Programme\n\n\n\nContact us\n\nQualified candidate, please email your full resume with academic credentials, working experience, expected salary and availability by clicking the \"apply now\" button as below.\n", "employment_types": ["Full Time", "Permanent"], "selling_points": ["3-yrs exp in commercial/ financial institution/b", "Able to analyze complex financial info", "5-days work, discretionary bonus, birthday leave"], "locations": ["Cheung Sha Wan"], "categories": ["Banking / Finance", "Credit Analysis / Approval", "Loan", "Financial Services"], "post_time": "2022-01-14T02:51:56Z", "salary": {"currency": null, "max": null, "min": null, "period": "monthly", "term": null}, "salary_visible": false, "title_keywords": ["officer"], "responsibilities": ["due diligence", "management", "reporting", "maintenance", "policies", "monitoring", "review", "procedures", "good relationship", "maintain"], "requirements": {"degrees": ["bachelor degree holder"], "majors": ["finance", "accounting"], "languages": ["english", "chinese", "mandarin"], "language_level": ["good command"], "hard_skills": ["credit analysis"], "soft_skills": ["detail-minded", "good team player", "work independently", "willing to learn"], "languages_combined": [{"language": "english", "language_level": ["good command"]}, {"language": "chinese", "language_level": ["good command"]}, {"language": "mandarin", "language_level": ["good command"]}]}, "experience_required": {"duration": ["minimum of 3-year"], "field": ["operation"]}}, {"job_id": "100003009048256", "location_code": "hk", "company": "Charterhouse Partnership", "job_title": "AVP, Credit and Portfolio Monitoring", "description": "Responsibilities:\n\nClosely monitor and handle all credit-related matters for accounts of SPDA-CPM HK\u2019s credit portfolio including, but not limited to, borrower\u2019s waiver/ amendment requests, self-assessment, periodical/ad-hoc credit reviews, legal/ financial analysis of the Borrowers, and timely reporting on any credit related matter required by Management.\nMaintain strong working relationship with front office/ marketing groups to support closing of new transactions as well as ongoing portfolio management.\nReview loan documentation against internal framework to ensure internal and local compliance requirements are complied with as well as credit conditions are appropriately documented.\nHandle certain administrative matters normally considered as middle office job, and to monitor overall settlement procedure, on the accounts responsible for.\nKeep regular contact with Borrower/ Sponsors/ Participants to maintain relationship and source information\nEngage and work with auditors/examiners from bank\u2019s headquarter/banking authorities/central banks in line with our compliance rule, preparing for materials requested by auditors/ examiners.\n\nRequirements:\n\nUniversity Graduate, with a finance background, with at least 6-8 years\u2019 relevant experience\nStrong familiarity with real estate and leverage finance transactions, in HK/Greater China\nProven track record to manage credit related matters of real estate and leverage finance transactions\nGeneral understanding of the Chinese regulations and security principles\nPossess analytical mind with good working knowledge of financial models\nA team player who is also able to establish good inter-Dept relations\nStrong ability to assess financial statements in English and Chinese\n\nIf you are interested in finding out more about this career opportunity, please email your resume to Nestor Roldan, nestor.roldan@ charterhouse.com.hk Web: www.charterhouse.com.hk\n\nCharterhouse Partnership Hong Kong is here to assist you in your job search. Our experienced recruitment consultants will provide you with career advice and assist you to develop a tailored job search strategy.", "employment_types": ["Full Time"], "selling_points": ["Strong credit skills in large corp", "A leading top Corporate Bank", "Credit writing and analysis, portfolio management"], "locations": ["Not Specified"], "categories": ["Banking / Finance", "Corporate Banking", "Credit Analysis / Approval", "Corporate Finance"], "post_time": "2022-01-14T06:04:01Z", "salary": {"currency": null, "max": null, "min": null, "period": "monthly", "term": null}, "salary_visible": false, "title_keywords": [], "responsibilities": ["ad-hoc", "reporting", "management", "review", "monitor", "compliance", "transactions", "financial analysis", "maintain", "contact", "banking", "documentation"], "requirements": {"degrees": ["university graduate"], "majors": ["finance"], "languages": ["english", "chinese"], "language_level": [], "hard_skills": ["web"], "soft_skills": ["interested in", "team player", "analytical mind"], "languages_combined": [{"language": "english", "language_level": []}, {"language": "chinese", "language_level": []}]}, "experience_required": {"duration": ["at least 6-8 years"], "field": ["finance", "relevant experience"]}}, {"job_id": "100003009044710", "location_code": "hk", "company": "UOB Kay Hian (Hong Kong) Limited", "job_title": "Credit Officer/ Credit Assistant", "description": "Responsibilities:\n\nAssist in automating existing credit risk report production through Excel visual basic enhancement\nAssist in IPO booking, manage trade confirmations and allotment result notification process\nInvolve in preparation of group exposure risk analysis\nCoordinate risk management projects for credit departments\nTake up ad-hoc assignments and related tasks as required\nRequirements:\n\n\nUniversity graduate with a degree in science, finance or accounting\nProficient in programming skills (Python, VBA)\nPrior experience in financial services industry is preferred\nKeen interest in developing a career in financial risk management\nMin. 2 years\u00a0relevant experience preferred\n*Candidates with less experience will be considered as Credit Assistant\n\nInterested candidates are invited to send a comprehensive resume stating current and expected salaries to\u00a0Head of Human Resources, UOB Kay Hian (Hong Kong) Limited, 6/F Harcourt House, 39 Gloucester Road, Hong Kong\u00a0or email by clicking the below\u00a0\"Apply Now\"\u00a0button", "employment_types": ["Full Time", "Permanent"], "selling_points": [], "locations": ["Wan Chai"], "categories": ["Banking / Finance", "Credit Analysis / Approval", "Financial Services", "Credit Collection"], "post_time": "2022-01-13T05:40:41Z", "salary": {"currency": null, "max": null, "min": null, "period": "monthly", "term": null}, "salary_visible": false, "title_keywords": ["officer", "assistant"], "responsibilities": ["management", "ad-hoc assignments", "coordinate", "booking", "risk analysis", "visual", "report"], "requirements": {"degrees": ["university graduate", "degree"], "majors": ["finance", "science", "accounting"], "languages": [], "language_level": [], "hard_skills": ["python", "vba", "programming"], "soft_skills": ["keen"], "languages_combined": []}, "experience_required": {"duration": ["2 years"], "field": ["financial services industry", "relevant experience"]}}, {"job_id": "100003009040168", "location_code": "hk", "company": "CASH Financial Services Group Limited", "job_title": "Senior Officer/ Assistant Manager, Risk Management & Credit Control", "description": "As our Senior Officer/ Assistant Manager, Risk Management & Credit Control, you will be leading a team to monitor, analyze, and manage credit risks in our equities and derivatives trading business. Responsibilities include but not limited to:\n\nMonitor daily trading activities to ensure all activities are complied with the Company\u2019s credit risk management policies & guidelines and external regulatory requirements;\nMonitor daily market movements; identify market & liquidity risk exposures and promptly submit escalation report of any irregularities and limit excesses;\nReview, assess, and approve credit facility & trading limits applications;\nMonitor the credit risks of margin financing portfolios, and ensure margin control actions & procedures are performed in a timely fashion;\nConduct simulations and stress testing on selected risk factors/ investment portfolios on regular and ad-hoc basis;\nReview and assess product risk;\nIdentify possible operational risks and provide recommendations to address the control weakness\nKeep abreast of latest rules and regulations related to credit risk management; review, update, and revise risk management guidelines, policies, and procedures on a timely basis;\nPrepare daily and monthly credit risk analysis reports to management;\nAssist in other ad-hoc projects as assigned.\n\nRequirements:\n\nDegree holder in Risk Management, Finance or related disciplines;\nAt least 3 years of solid risk management and credit control experiences in securities firms\u00a0with field experience\u00a0in handling\u00a0different asset classes trading across\u00a0multiple\u00a0markets\nSolid experiences in credit/margin control with SFC RA1 license\u00a0is an \u00a0advantage;\u00a0In-depth understanding of legal and regulatory requirements on credit risk management;\nConscious thought in compliance and control\nStrong analytical, numerical, report writing and problem solving skills;\nKnowledge in market risk system, such as Bloomberg, Reuters;\nExcellent interpersonal, communication and negotiation skills;\nExperience in leading a small team in risk management and credit control\nAdvanced level on Excel VBA and Access or other statistics software;\nGood command of spoken and written English and Chinese (Cantonese & Putonghua).\nCandidates with more experience would be considered as Assistant Manager, RMC.\n\nPlease apply in confidence with\u00a0full resume, current and expected\u00a0salary\u00a0in the subject line to the Human Resources Department, CASH Financial Services Group Limited, 22/F, Manhattan Place, 23 Wang Tai Road, Kowloon Bay, Hong Kong.", "employment_types": ["Full Time", "Permanent"], "selling_points": ["3 years of solid risk management", "Solid experiences in credit/margin control", "Excel VBA and Access"], "locations": ["Kowloon Bay"], "categories": ["Banking / Finance", "Credit Analysis / Approval", "Financial Services", "Risk Management"], "post_time": "2022-01-12T01:44:12Z", "salary": {"currency": null, "max": null, "min": null, "period": "monthly", "term": null}, "salary_visible": false, "title_keywords": ["senior officer", "assistant manager,"], "responsibilities": ["ad-hoc", "regulations", "regulatory requirements", "ad-hoc projects", "control", "investment portfolios", "monitor", "testing", "reports", "report", "management", "review", "procedures", "provide recommendations", "irregularities", "guidelines", "policies", "risk analysis", "credit facility"], "requirements": {"degrees": ["degree holder"], "majors": ["finance", "risk management", "related disciplines"], "languages": ["cantonese", "putonghua", "english", "chinese"], "language_level": ["good command"], "hard_skills": ["small", "excel", "vba", "bloomberg", "problem solving skills"], "soft_skills": ["confidence", "advanced", "communication", "negotiation skills", "problem solving skills", "interpersonal"], "languages_combined": [{"language": "cantonese", "language_level": ["good command"]}, {"language": "putonghua", "language_level": ["good command"]}, {"language": "english", "language_level": ["good command"]}, {"language": "chinese", "language_level": ["good command"]}]}, "experience_required": {"duration": ["at least 3 years"], "field": ["risk management", "trading", "securities firms", "team"]}}, {"job_id": "100003009042885", "location_code": "hk", "company": "Industrial and Commercial Bank of China (Asia) Limited", "job_title": "Deputy Manager to Senior Manager, Mortgage Credit (Ref: CAD-MC-752)", "description": "Job Responsibilities\n\nPerform credit risk assessment and approval function for retail lending products with focus on mortgage loans\nRecommend credit policy guidelines / workflow simplification to achieve operational efficiency\nEnsure the compliance of regulatory requirement as well as credit policy guidelines in credit assessment\nWork with business departments and front line sales staff in solving issues arising from mortgage loan applications and able to put up with workable recommendation / solutions Support user acceptance test on Loan Application Processing System\nParticipate in ad hoc projects as required\nJob Requirements\n\nUniversity graduate with major in Business Administration, Finance or related disciplines\nAt least 5 years of solid experience in assessing and under-writing mortgage loan applications covering residential and commercial properties in a bank or mortgage under-writing agency\nFamiliar with the end to end mortgage loan application process, mortgage loan under-writing / process platform\nThorough knowledge, understanding and application of mortgage loan credit policy and regulatory requirements\nGood product knowledge and risk exposure in retail banking\nAble to deal with front line sales staff in resolving issues arising from the loan applications and providing workable solutions\nA team player but able to work independently with minimal supervision\nGood communication and interpersonal skills\nProficiency in PC software operations such as MS Office\nGood command in both spoken & written English and Chinese\nInterested\u00a0parties,\u00a0please\u00a0click\u00a0\"Apply\u00a0Now\"\u00a0for\u00a0application.\nPersonal\u00a0data\u00a0collected\u00a0will\u00a0be\u00a0used\u00a0for\u00a0recruitment\u00a0purpose\u00a0only.", "employment_types": ["Full Time", "Permanent"], "selling_points": [], "locations": ["Kwun Tong"], "categories": ["Banking / Finance", "Credit Analysis / Approval", "Mortgage", "Retail Banking"], "post_time": "2022-01-12T09:07:15Z", "salary": {"currency": null, "max": null, "min": null, "period": null, "term": null}, "salary_visible": false, "title_keywords": ["senior manager", "deputy manager"], "responsibilities": ["guidelines", "ad hoc projects", "compliance of regulatory"], "requirements": {"degrees": ["university graduate"], "majors": ["related disciplines", "finance", "business administration"], "languages": ["english", "chinese"], "language_level": ["good command"], "hard_skills": ["pc", "ms office"], "soft_skills": ["team player", "communication and interpersonal skills", "thorough", "work independently"], "languages_combined": [{"language": "english", "language_level": ["good command"]}, {"language": "chinese", "language_level": ["good command"]}]}, "experience_required": {"duration": ["at least 5 years"], "field": ["agency", "commercial", "writing"]}}, {"job_id": "100003009053338", "location_code": "hk", "company": "Hang Seng Bank Ltd", "job_title": "Customer Relationship Manager", "description": "Retail Distribution\n\nHang Seng's Retail Distribution focuses on personal wealth management and financial services. Our one-stop wealth management initiatives are designed for both our affluent and mass integrated account customers.\u00a0With more than\u00a0290\u00a0branches\u00a0and automated banking centres, including\u00a0around 60\u00a0Prestige\u00a0Banking Centres\u00a0for our high-end personal customers, we serve over half of the adult population in Hong Kong while offering an extensive range of products to our valued customers.\n\nWe are currently seeking a high caliber professional to join our team as\u00a0Customer Relationship Manager.\n\nPrincipal responsibilities\n\nProvide financial planning services to high-net-worth customers\nProvide personalised service for this segment of customers to build and maintain good relationships\nPromote investment, insurance and banking products for optimising new business opportunities\nManage operational risk and observe the relevant policies /guidelines and compliance requirements\u00a0\n\u00a0\n\nHang Seng Bank Relationship Manager Virtual Recruitment Talk\u00a0\n\nIf you are keen to find out more about the working culture and how we nurture our Relationship Managers for their success at Hang Seng Bank, please join our Virtual Recruitment Talk\u00a0to hear the candid sharing from our Branch Networks business leaders and also our RMs. You will also find out our progressive career ladder for RMs from entry-level RM Trainee to Signature and Executive RM.\n\nDate:\u00a026 January 2022 (Wed)\n\nTime: 6:00 - 7:00 PM\n\nLocation:\u00a0Virtual Session \u2013 Dial in details will be provided upon registration\n\nRegister your place before 26 Jan 2022 by clicking\u00a0https://hsbc.zoom.us/webinar/register/WN_KABEhwC-RJqmSR07NkIS2g\u00a0\u00a0\n\n\n\nRequirements\n\nUniversity level education is an advantage OR\nHKCEE / HKDSE (with at least passes in Chinese and Mathematics OR English and Mathematics at Grade E / Level 2 / \"Attained\" or above) plus relevant work experience\nPasses in the Insurance Intermediaries Qualifying Examinations / Hong Kong Securities Institute Licensing Examinations\u00a0\nFulfilment of the competency requirements to carry out relevant regulated activities as defined under the Securities and Futures Ordinance\nMinimum of two years' experience in selling investment, insurance and banking products\nStrong sales and customer orientation, with good communication and interpersonal skills\nStrong self-motivation and ability to work under pressure\nProficiency in both English and Chinese, with proficiency in Putonghua an advantage\nHigh level of customer centricity mindset and ability to manage complex interactions effectively\nShown strong situation awareness, strong desire to learn and able to work in Agile environment\nBe curious and with passion to think deeply and rationally\n\n(Candidates with less experience will be considered for the position of\u00a0Senior Customer Relationship Officer)\n\nIf you would like to explore other opportunities at Hang Seng Hong Kong, please visit www.hangseng.com/careers/ for details.\n\nThe health and safety of our employees and candidates is very important to us. Due to the current situation related to the Novel Coronavirus (2019-nCoV), we\u2019re leveraging our digital capabilities to ensure we can continue to recruit top talent at the HSBC Group.\u00a0 As your application progresses, you may be asked to use one of our digital tools to help you through your recruitment journey.\u00a0 If so, one of our\u00a0 Resourcing colleagues will explain how our video-interviewing technology will be used throughout the recruitment process and will be on hand to answer any questions you might have.\n\nAll information provided by applicants will be used only for recruitment purposes and will be used strictly in accordance with the Bank's personal data policies, a copy of which may be obtained by the applicant upon request. Unless otherwise instructed in writing by the applicant concerned, applicants may be considered for other suitable positions within the Bank and its related companies. The personal data of unsuccessful job applicants may be retained for a maximum of two years from the date when the job application is rejected and such data may be retained for a longer period if there is a subsisting reason that obliges the Bank to do so, after which the personal data will be destroyed.", "employment_types": ["Full Time", "Permanent"], "selling_points": [], "locations": ["Not Specified"], "categories": ["Banking / Finance", "Credit Analysis / Approval", "Retail Banking", "Credit Collection"], "post_time": "2022-01-17T06:48:17Z", "salary": {"currency": null, "max": null, "min": null, "period": "monthly", "term": null}, "salary_visible": false, "title_keywords": ["relationship manager"], "responsibilities": ["guidelines", "policies", "business opportunities", "compliance", "maintain", "recruitment", "banking", "insurance", "planning"], "requirements": {"degrees": ["hkdse"], "majors": ["mathematics"], "languages": ["putonghua", "english", "chinese"], "language_level": ["advantage", "proficiency"], "hard_skills": ["plus", "securities and futures ordinance", "agile", "reason"], "soft_skills": ["agile", "communication and interpersonal skills", "self-motivation", "novel", "work under pressure"], "languages_combined": [{"language": "putonghua", "language_level": ["proficiency", "advantage"]}, {"language": "english", "language_level": ["proficiency", "proficiency", "advantage"]}, {"language": "chinese", "language_level": ["proficiency", "proficiency", "advantage"]}]}, "experience_required": {"duration": ["minimum of two years"], "field": ["insurance", "investment", "banking"]}}, {"job_id": "100003009047774", "location_code": "hk", "company": "Public Bank (Hong Kong) Limited", "job_title": "Officer Trainee (Ref: JD-IOT)", "description": "Assist to handle the daily operations of designated departments of the Bank\nDegree holder in Accounting, Mathematic Statistics, Banking & Finance or related disciplines\nPrevious related working experience in data consolidation or analysis would be an advantage\nSelf-motivated, proactive and eager to learn\nGood spoken and writing skills in both English and Chinese\nGood knowledge in MS Office applications, especially Excel application will be an advantage\n\nTo apply, interested parties please follow the application methods available in the Bank\u2019s career website\u00a0https://www.publicbank.com.hk/en/aboutus/careeropportunities.You can send us your resume quoting our job reference number together with present &\u00a0expected salary (a must)\u00a0to the Human Resources Department by email or fax at\u00a02815 3157\u00a0or by post to\u00a0Human Resources Department, 12/F, Public Bank Centre, 120 Des Voeux Road Central, Hong Kong. You may also visit our career website for other career opportunities available within our Group.\n\nPersonal data collected will be used for recruitment purpose only and will be treated in accordance with the Bank\u2019s Personal Information Collection Statement, a copy of which has been available in the Bank\u2019s career website.\u00a0", "employment_types": ["Full Time", "Permanent"], "selling_points": [], "locations": ["Not Specified"], "categories": ["Banking / Finance", "Credit Analysis / Approval", "Financial Services", "Others", "Student / Fresh Graduate / No Experience"], "post_time": "2022-01-15T03:49:08Z", "salary": {"currency": null, "max": null, "min": null, "period": null, "term": null}, "salary_visible": false, "title_keywords": ["officer trainee"], "responsibilities": ["daily operations", "analysis", "data", "banking"], "requirements": {"degrees": ["degree holder"], "majors": ["related disciplines", "finance", "accounting", "statistics"], "languages": ["english", "chinese"], "language_level": ["good"], "hard_skills": ["excel", "analysis", "writing skills", "ms office"], "soft_skills": ["eager to learn", "self-motivated", "proactive", "writing skills"], "languages_combined": [{"language": "english", "language_level": ["good"]}, {"language": "chinese", "language_level": ["good"]}]}, "experience_required": {"duration": [], "field": ["related", "consolidation"]}}, {"job_id": "100003009053877", "location_code": "hk", "company": "JAC Recruitment Hong Kong Co., Limited", "job_title": "Product Manager (VP - Team Head) - ESG (Environmental, Social & Governance) - Corporate Banking", "description": "Our client is a fast growing foreign bank. They are looking for someone to join as a Product Manager (VP - Team Head) - ESG (Environmental, Social & Governance) - Corporate Banking.\u00a0\n\nKey Responsibilities\n\n\n- To help RMs to structure and joint pitch SLL and green loans.\u00a0\n\n- Ideally, being able to help the bank's Greater China's region to set up ESG product manual, writeups for various ESG presentations.\u00a0\n\n-\u00a0Promote Corporate Banking products e.g.\u00a0Syndicated-Loan, Club Loan, Bilateral Loan, and Structured Finance\n\n-\u00a0Knowledge in banking facilities and credit proposal\n\n\n\n\nRequirements\n\n- Around 4-12 years (Manager - Team Head) experience in Corporate Banking,\u00a0specializing in ESG.\u00a0\n\n-\u00a0Degree holder in Business Administration or related disciplines;\n\n-\u00a0Fluent in English, Cantonese and Mandarin\n\n\n*We offer*\n\n\"Interested candidates, please send an updated CV to kelvin.lam @jac-recruitment.com and CC jac.hk @jac-recruitment.com\"\n\nPersonal data collected will be used for employment-related purpose only. We regret to inform that only shortlisted candidates will be notified.", "employment_types": ["Full Time"], "selling_points": ["A fast growing Foreign Bank", "ESG (Environmental, Social & Governance)", "Syndicated-Loan, Club Loan, Bilateral Loan"], "locations": ["Central & Western Area"], "categories": ["Banking / Finance", "Corporate Banking", "Credit Analysis / Approval", "Loan"], "post_time": "2022-01-17T07:40:32Z", "salary": {"currency": null, "max": null, "min": null, "period": "monthly", "term": null}, "salary_visible": false, "title_keywords": ["product manager"], "responsibilities": ["presentations", "banking"], "requirements": {"degrees": ["degree holder"], "majors": ["related disciplines", "business administration"], "languages": ["cantonese", "english", "mandarin"], "language_level": ["fluent"], "hard_skills": [], "soft_skills": [], "languages_combined": [{"language": "cantonese", "language_level": ["fluent"]}, {"language": "english", "language_level": ["fluent"]}, {"language": "mandarin", "language_level": ["fluent"]}]}, "experience_required": {"duration": ["4-12 years"], "field": ["banking", "team"]}}, {"job_id": "100003009050892", "location_code": "hk", "company": "Bank of Communications Co., Ltd. Hong Kong Branch", "job_title": "Risk Management Officer (Quantitative Analysis) \u2013 1 year contract", "description": "Career Level\nEntry Level\nQualification\nDegree\nJob Type\nFull Time, Contract\nJob Functions\nBanking / Finance, Credit Analysis / Approval, Others, Student / Fresh Graduate / No Experience, Risk Management", "employment_types": ["Full Time", "Contract"], "selling_points": [], "locations": ["Not Specified"], "categories": ["Banking / Finance", "Credit Analysis / Approval", "Others", "Student / Fresh Graduate / No Experience", "Risk Management"], "post_time": "2022-01-14T11:40:20Z", "salary": {"currency": null, "max": null, "min": null, "period": "monthly", "term": null}, "salary_visible": false, "title_keywords": ["risk management officer"], "responsibilities": ["analysis", "management", "banking"], "requirements": {"degrees": ["degree", "fresh graduate"], "majors": ["finance", "risk management"], "languages": [], "language_level": [], "hard_skills": ["credit analysis", "no"], "soft_skills": [], "languages_combined": []}, "experience_required": {"duration": [], "field": ["finance", "risk management", "banking"]}}, {"job_id": "100003009038566", "location_code": "hk", "company": "Welab Bank Limited", "job_title": "Credit Approval Manager/Assistant Manager (Virtual Bank)", "description": "WeLab is a leading fintech company in Asia, \u00a0which operates one of first licensed digital banks in Asia \u2013 WeLab Bank, as well as multiple leading online financial services businesses including WeLend and WeLab Bank in Hong Kong, WeLab Digital (\u6211\u6765\u6570\u79d1), Taoxinji (\u6dd8\u65b0\u673a), Wallet Gugu (\u94b1\u5939\u8c37\u8c37) and Tianmian Tech (\u5929\u5195\u79d1\u6280) in Mainland China and Maucash in Indonesia. WeLab aims to bring joy to everyone\u2019s financial journey. We strive to improve people\u2019s lives by reinventing financial services through game-changing technology. We put our people first, whether it\u2019s our customers or our employees.\n\nAs the only homegrown Hong Kong fintech to receive a virtual banking license, we aim to reinvent and redefine the banking experience by building a bank we love.\n\nWe are an energetic and passionate team that can deliver and execute. We are looking for other intellectually curious, open-minded and smart-working individuals who are just as passionate as we are about making financial services enjoyable. Now you have the opportunity to join us on our journey to achieve our vision and be part of building a better financial future for everyone.\n\nAbout you:\n\nYou're a go-getter with mad juggling skills (or multiple hats) who can thrive in a fast-paced, agile environment\nYou have a strong thirst for knowledge and are driven to find solutions that don't exist yet\nYou are comfortable with ambiguity and extremely resourceful (in your past life you could've been a detective)\nYou always find a way to get things done without sacrificing the quality of your work, integrity and values. No task is off limits for you.\nYou are humble and prioritize the success of the team over your own with an eagerness to help those around you\nYou don't shy away from challenges and have the ability to bounce back from setbacks\n\nWhat you\u2019ll do and what success looks like in this role\u00a0\n\nReview customer's financial status, credit bureau report and internal credit history to recommend approval decision for personal installment loan applications\nHandle credit applications according to credit policies and underwriting standards\nManage and monitor loan portfolio to ensure credit quality and full compliance of internal policies and lending guidelines\nPerform verification to detect fraud application and prevent fraud\nParticipate in projects to improve and optimize the credit operation and process\n\nWhat is required and what we\u2019re looking for\u00a0\n\nHigher Diploma or above\nMinimum 5 years related experience in personal loan products. With approval delegation is preferred\nSelf-initiative and good team player\nMulti-tasking and ability to manage deliverables within tight deadlines\nExcellent interpersonal and communication skills\nGood command of both written and spoken English and Chinese\nCandidates with less experience will be considered as Assistant Manager\n\nWeLab perks:\n\nCompetitive salary\nLearning and development stipend, because we value lifelong learning and believe the best way to invest in our employees is to encourage them to continue to learn\nWork hard and laugh lots (chicken wings and french toast, etc.) with a high-performing, fun and diverse team\nHappiness Dollars for spending on anything that makes you happy\nCoffee stipend\nConveniently located office surrounded by diverse and delicious lunch options\nLively office with gaming consoles and a ping pong table\nFun extracurricular activities with your colleagues like hiking, yoga, badminton, wine tasting, dragon boat racing, rock climbing, etc.\nEmployee referral bonuses\n\nAwards & recognition:\n\nFinancial Times (FT) 2020 Asia-Pacific High-Growth Companies \u2013 #2 ranked company\n2020 CNBC Disruptor 50 List \u2013 #11, only company included from Hong Kong and just one of five from Asia\u00a0\nWe offer competitive salary package to the successful candidate.\u00a0 If you are interested in joining this exciting team, please apply with resume via the \"Apply\" button.\n\nAll information provided by applicants will be used for recruitment purposes only. Information of unsuccessful applicants will be destroyed within 24 months of receipt.", "employment_types": ["Full Time", "Permanent"], "selling_points": ["Review customer's financial status", "Handle credit applications", "Manage and monitor loan portfolio"], "locations": ["Quarry Bay"], "categories": ["Banking / Finance", "Credit Analysis / Approval", "Financial Services"], "post_time": "2022-01-11T07:22:40Z", "salary": {"currency": null, "max": null, "min": null, "period": "monthly", "term": null}, "salary_visible": false, "title_keywords": ["assistant manager", "manager"], "responsibilities": ["guidelines", "policies", "review", "quality", "monitor", "compliance", "communication", "banking", "report"], "requirements": {"degrees": ["higher diploma or above"], "majors": [], "languages": ["english", "french", "chinese"], "language_level": ["good command"], "hard_skills": ["no", "loan products", "joy", "agile", "fun", "go", "mad"], "soft_skills": ["passionate", "communication skills", "good team player", "agile", "resourceful", "interpersonal", "open-minded", "integrity", "prioritize", "diverse", "multi-tasking", "learning", "self-initiative", "energetic", "driven"], "languages_combined": [{"language": "english", "language_level": ["good command"]}, {"language": "french", "language_level": []}, {"language": "chinese", "language_level": ["good command"]}]}, "experience_required": {"duration": ["minimum 5 years"], "field": ["related", "banking experience", "banking"]}}, {"job_id": "100003009042761", "location_code": "hk", "company": "ExcelNet Total HR Solutions", "job_title": "Bank Credit Facilities Specialist", "description": "Our client is looking for a high-caliber candidate to fill up the captioned position.\n\nJob Responsibilities :\n\n\nWork with the front office and in-house legal to review facility and security agreements and ensure terms and conditions are in compliance with credit approval\nMonitor underwriting commitment and assist front office on pre-signing administrative tasks\nTo ensure all conditions precedent documents are fulfilled before approval the Back Office team to proceed with funding and loan payment\nMonitor facility closing, initial drawdown fees settlement, and conditions subsequent, if any\nCheck and verify facility and security documents signed and returned by customers with relevant supporting documentation\nEnsure the perfection on security documents and monitor periodical revaluation and the expiry of ongoing collateral and securities\nHandle credit matters and daily portfolio monitoring and covenant checking for designated portfolio across all business lines\nHandle facility limits, collateral, covenants set up, modification and deletion timely in the system\nJob Requirements :\n\nUniversity graduate\nMinimum 3-5 years relevant experience with an International Bank\nKnowledge and experience covenant monitoring is essential\nExperience in handling specialized lending or structured finance facilities\nGood interpersonal and communications skills and able to work under pressure\nInterested parties, please click \"APPLY NOW\" or refer to the Company Overview below to submit your application.", "employment_types": ["Full Time", "Contract"], "selling_points": ["Exp in Lending or Structured Finance Facilities", "Familiar with handle covenant monitoring", "Attractive salary"], "locations": ["Not Specified"], "categories": ["Banking / Finance", "Credit Analysis / Approval", "Others", "Credit Collection"], "post_time": "2022-01-12T08:47:19Z", "salary": {"currency": null, "max": null, "min": null, "period": "monthly", "term": null}, "salary_visible": false, "title_keywords": ["specialist"], "responsibilities": ["documentation", "compliance", "review", "monitor", "back office", "monitoring", "checking", "payment", "administrative tasks"], "requirements": {"degrees": ["university graduate"], "majors": [], "languages": [], "language_level": [], "hard_skills": [], "soft_skills": ["structured", "interpersonal", "work under pressure"], "languages_combined": []}, "experience_required": {"duration": ["minimum 3-5 years"], "field": ["finance", "relevant experience"]}}, {"job_id": "100003009044110", "location_code": "hk", "company": "Bank of Shanghai (Hong Kong) Limited", "job_title": "Assistant Vice President/Assistant Manager, Risk Management", "description": "Job Responsibilities\n\n\nThe candidate would be mainly involved in credit risk related area and support other risk areas. The candidate would report to Head of Credit Risk for credit risk related area and assist Chief Risk Officer to monitor/operate the credit monitoring control function. The job would mainly cover the followings:\n\na) Credit Risk and Monitoring:\n\nReview the credit application and provide recommendation to higher level authority for credit approval.\n\u00a0Monitor and control various credit limits of the credit portfolio against risk appetite and risk limits of the Bank.\nPerform credit monitoring and post loan monitoring on clients as 2nd line of defence.\nGather market information, monitor the performance of credit facilities to identify early signs of credit deterioration.\nParticipate in and provide credit advice for pre-deal transaction discussion with Business.\nUpdate credit policies for adherence to relevant regulatory requirements and changing market environment.\nPrepare risk portfolio report and act as secretary for Credit Committee on rotation basis.\nInvolve in ad hoc credit risk projects and deal with HKMA / auditors on credit risk issues.\nEngage in the post-approval monitoring process and carry out credit administrative works on rotation basis.\nReview the major credit terms of the loan documentation and give comments on the standard templates.\nManage NPL with Business Control team on needed basis.\n\nb) Credit Monitoring Control :\n\nMonitor watch list portfolio review system and coordinate periodic watch list account review meeting for the purpose of identifying early warning signal on the existing portfolio.\nPrepare regular credit monitoring reports to senior management.\n\n\u00a0Job Requirements\n\nDegree holder in any disciplines.\nMore than 5 years (for Assistant Manager post) or 8 years (for Assistant Vice President post) of experience in corporate/FI credit risk, either as credit analyst from risk/credit management department or as a relationship manager in the frontline in preparing credit application.\nStrong analytical mind with sound presentation skill.\nFluency in English and Cantonese, Fluent Putonghua is an added advantage.\nExperience in other risk areas (e.g. special assets management, risk policy and procedure review, post-approval monitoring, loan documentation, etc) would be an added advantage.\n\nWe offer successful candidates an attractive remuneration package and the opportunity to work in a dynamic and exciting environment.\nPersonal data collected will be used for recruitment purposes only.", "employment_types": ["Full Time", "Permanent"], "selling_points": ["Review the credit application", "Monitor watch list portfolio review system", "Prepare regular credit monitoring reports"], "locations": ["Central"], "categories": ["Banking / Finance", "Corporate Banking", "Credit Analysis / Approval", "Risk Management"], "post_time": "2022-01-13T03:05:25Z", "salary": {"currency": null, "max": null, "min": null, "period": "monthly", "term": null}, "salary_visible": false, "title_keywords": ["assistant manager,", "assistant vice president"], "responsibilities": ["control", "market information", "ad hoc", "policies", "regulatory requirements", "review", "monitoring", "monitor", "comments", "provide recommendation", "coordinate", "reports", "monitor the performance", "documentation", "senior management", "report"], "requirements": {"degrees": ["degree holder"], "majors": ["any disciplines"], "languages": ["cantonese", "putonghua", "english"], "language_level": ["fluency", "advantage", "fluent"], "hard_skills": ["presentation skill", "documentation"], "soft_skills": ["presentation skill", "analytical mind"], "languages_combined": [{"language": "cantonese", "language_level": ["advantage"]}, {"language": "putonghua", "language_level": ["fluent", "fluency", "advantage"]}, {"language": "english", "language_level": ["advantage"]}]}, "experience_required": {"duration": ["5 years", "8 years"], "field": ["management", "credit risk"]}}, {"job_id": "100003009042870", "location_code": "hk", "company": "Chong Hing Bank Ltd", "job_title": "SRM / RM - Hong Kong Corporates/ Mainland Corporates", "description": "Career Level\nMiddle\nQualification\nDegree\nYears of Experience\n3 years\nJob Type\nFull Time, Permanent\nJob Functions\nBanking / Finance, Analyst, Corporate Banking, Credit Analysis / Approval", "employment_types": ["Full Time", "Permanent"], "selling_points": ["Build and manage a customer portfolio", "Prepare comprehensive credit proposals", "Discretionary performance bonus, Life insurance"], "locations": ["Central"], "categories": ["Banking / Finance", "Analyst", "Credit Analysis / Approval", "Corporate Finance"], "post_time": "2022-01-12T09:04:45Z", "salary": {"currency": null, "max": null, "min": null, "period": null, "term": null}, "salary_visible": false, "title_keywords": [], "responsibilities": ["analysis", "banking"], "requirements": {"degrees": ["degree"], "majors": [], "languages": [], "language_level": [], "hard_skills": ["credit analysis"], "soft_skills": [], "languages_combined": []}, "experience_required": {"duration": [], "field": []}}, {"job_id": "100003009035322", "location_code": "hk", "company": "Page Personnel", "job_title": "Credit Admin Assistant Manager - Large Corporate Bank", "description": "Our client is a renowned Asian corporate bank. They are now looking for candidate who is with at least 3 years' experience working in credit control/administration duties.\n\nClient Details\n\nOur client is a renowned corporate bank. With a very mature and well-established business in Asia, they have more than 400 people in their business in Hong Kong office. They are famous for providing excellent services in wide array of financial services, such as financial advisory, project financing, M&A, structured financing etc.\n\nTo support their business expansion, they are looking for candidate with at least 3 years' experience from banking to join them. Candidate would be expected to manage the full-cycle of the credit administration/operation process duty. The company provides attractive benefits package with excellent working environment.\n\nDescription\n\nRegister credit facility and review credit documents.\nPrepare periodic management reporting.\nPerform due diligence checking on letter of credit.\nSupport agency function for syndicated loans.\nAssist system enhancement project.\n\nProfile\n\nBachelor degree holder.\nAt least 3 years experience from bank working on credit control or loan agency.\nHands-on credit control experience from corporate bank.\nTeam player who is with good communication skills in both Chinese and English.\n\nJob Offer\n\nStrong Reputation\nAnnual Leave: 14 days up\nBirthday Leave\nMedical Benefits\nDental Benefits\nLife Insurance\nDiscretionary Year-end Bonus\n\nTo apply online please click the 'Apply' button below. For a confidential discussion about this role please contact Ellen Fung on +852 3602 2447.", "employment_types": ["Full Time", "Permanent"], "selling_points": ["Syndicated Loan Agency", "Excellent Benefit", "All-rounded Process Control"], "locations": ["Not Specified"], "categories": ["Banking / Finance", "Corporate Banking", "Credit Analysis / Approval", "Loan"], "post_time": "2022-01-10T06:49:17Z", "salary": {"currency": null, "max": null, "min": null, "period": "monthly", "term": null}, "salary_visible": false, "title_keywords": ["admin assistant", "manager"], "responsibilities": ["control", "banking", "administration"], "requirements": {"degrees": [], "majors": [], "languages": [], "language_level": [], "hard_skills": [], "soft_skills": ["structured", "mature"], "languages_combined": []}, "experience_required": {"duration": ["at least 3 years"], "field": ["business", "banking", "administration"]}}, {"job_id": "100003009047494", "location_code": "hk", "company": "O-Bank Co., Ltd", "job_title": "Junior Relationship Manager", "description": "Requirements:\n\nDegree or above in Business Administration or Finance.\nMin. 1 year experience in banking industry or Auditing firm. (Fresh Graduate will also be considered)\nGood communication / interpersonal skills with fluent in speaking and writing English & Chinese (Including Mandarin and Cantonese), self motivated and able to work under pressure.Willing to travel to PRC as required.\n\nResponsibilities:\n\nAssist Relationship Manager to market banking products.\nPrepare credit review application, monitor credit and risk profiles.\nHandle account opening, drawdown and repayment of loans.\nCollect credit proposals through different credit sources, analyze financial statements, and prepare credit reports for RM / Credit Officer.\n\nApply Methods\nApplicants may send C.V. indicating expected salary by clicking \"Apply Now\"\n\nFor other vacancies, please visit our website at http://www.o-bank.com/", "employment_types": ["Full Time", "Permanent"], "selling_points": [], "locations": ["Tsim Sha Tsui"], "categories": ["Banking / Finance", "Corporate Banking", "Credit Analysis / Approval"], "post_time": "2022-01-14T03:19:48Z", "salary": {"currency": null, "max": null, "min": null, "period": "monthly", "term": null}, "salary_visible": false, "title_keywords": ["relationship manager", "junior"], "responsibilities": ["account opening", "review", "monitor", "website", "financial statements", "reports", "banking"], "requirements": {"degrees": ["degree or above", "fresh graduate"], "majors": ["finance", "business administration"], "languages": ["cantonese", "english", "chinese", "mandarin"], "language_level": ["fluent", "good"], "hard_skills": [], "soft_skills": ["communication", "interpersonal skills", "self motivated", "work under pressure"], "languages_combined": [{"language": "cantonese", "language_level": ["fluent", "good"]}, {"language": "english", "language_level": ["fluent", "good"]}, {"language": "chinese", "language_level": ["fluent", "good"]}, {"language": "mandarin", "language_level": ["fluent", "good"]}]}, "experience_required": {"duration": ["1 year"], "field": ["banking industry"]}}, {"job_id": "100003009042895", "location_code": "hk", "company": "Chong Hing Bank Ltd", "job_title": "Assistant Vice President - Credit Analytics & Modeling", "description": "Responsibilities:\nAssist supervisor in leading and managing the credit risk modeling and credit analytics team;\nMaintain credit rating models for measurement and management of credit risk for the Bank\u2019s portfolio;\nLiaise with different units to formulate credit MIS processes, support stress testing of regulatory capital, data management projects and implementation of new initiatives such as IFRS9, BELR, ICAAP, and SA-CCR;\nManage the credit portfolio reporting and the associated MIS; and\nPerform other ad hoc projects or assignments.\nRequirements:\nUniversity graduate in Finance, Economics, Accounting, Risk Management, Statistics or related disciplines;\nCFA, Accountant and/or FRM is a plus; and HKIB ECF-CRM preferable;\nMinimum of 7 years\u2019 solid bank experience in credit risk management; project management experience is a plus;\nExpansive knowledge of credit risk requirement and credit policy; and familiar with credit risk stress testing, IFRS9, ICAAP and SA-CCR rating models (PD) and LGD/EAD measurement;\nStrong self-motivation and creativity, with excellent communication and analytical skills;\nDemonstrated ability to rapidly build relationships with key stakeholders; and\nCandidate with more experience will be considered as Vice President.\nWe offer competitive remuneration package and promising career opportunities to the successful candidates. Interested parties, please send full resume with current & expected salary and the date of availability to The HR Division, G.P.O. Box 2535, HK , or by clicking Apply Now. Please quote reference on your application. Information provided will be treated in strict confidence and only be used for recruitment purposes. Personal data of unsuccessful applications will be destroyed 24 months after the completion of the recruitment and selection exercise.", "employment_types": ["Full Time", "Permanent"], "selling_points": ["Credit rating models", "IFRS9, BELR, ICAAP, and SA-CCR", "Credit portfolio reporting and MIS"], "locations": ["Kowloon Bay"], "categories": ["Banking / Finance", "Credit Analysis / Approval", "Financial Services"], "post_time": "2022-01-12T09:09:40Z", "salary": {"currency": null, "max": null, "min": null, "period": "monthly", "term": null}, "salary_visible": false, "title_keywords": ["assistant vice president"], "responsibilities": ["reporting", "management", "data", "measurement", "implementation", "testing", "maintain", "ad hoc projects", "liaise with"], "requirements": {"degrees": ["university graduate"], "majors": ["risk management", "finance", "economics", "statistics", "related disciplines", "accounting"], "languages": [], "language_level": [], "hard_skills": ["plus", "cfa", "analytical skills", "project management", "frm"], "soft_skills": ["communication", "project management", "self-motivation", "analytical skills"], "languages_combined": []}, "experience_required": {"duration": ["minimum of 7 years"], "field": ["project management", "management", "credit risk"]}}, {"job_id": "100003009050444", "location_code": "hk", "company": "China Construction Bank (Asia) Corporation Limited", "job_title": "Syndication Professional", "description": "Job Descriptions:\n\nSupport the Head of Syndication on pitching and execution of syndication mandates\nSolicit potential clients for syndicated loan\nAssess the credit worthiness of prospective borrowers, conduct market comparable analysis, due diligence, prepare syndication risk analysis and perform cashflow analysis\nPrepare information memorandum and presentation materials by obtaining relevant market information and liaison with customers directly\nFormulate syndication strategy based on research on market appetite, competing deal(s) and market depth analysis\nNegotiate with borrower, legal counsel and lenders on loan agreement\nPerform special duties as assigned by the Head of Syndication from time to time\nSupport co-marketing with Head Office / other branches as needed\n\nRequirements:\n\nBachelor degree or above in leading university\nMinimum 4 years relevant experience in loan syndication. Candidate with less experience in loan syndication will be considered as Assistant Vice President\nProven financial, commercial and business acumen\nStrong analytical skills and highly numerate and articulate\nGood presentation skills. A team player with strong communication, interpersonal and project management skills\nCan work efficiently and independently under minimal supervision. Able to work under pressure and meet tight deadlines\nKnowledge of MS applications including Excel and Power Point and good PC skills\nExcellent command of written and spoken English and Chinese including Putonghua\nWilling to travel occasionally\n\nTo apply, please send the detailed resume to the designated email address.\n\nApplicants who are not contacted within 8 weeks may consider their applications unsuccessful and their personal data will be retained by the bank for a period up to two years.\n\nAll information provided by applicants will be used for recruitment purposes only and will be used strictly in accordance with the bank\u2019s personal data policies, a copy of which will be provided upon request.", "employment_types": ["Full Time", "Permanent"], "selling_points": ["Loan syndication", "Prepare information memorandum & loan agreement", "Pitching and execution of syndication mandates"], "locations": ["Central"], "categories": ["Banking / Finance", "Corporate Banking", "Credit Analysis / Approval", "Corporate Finance"], "post_time": "2022-01-14T10:26:38Z", "salary": {"currency": null, "max": null, "min": null, "period": "monthly", "term": null}, "salary_visible": false, "title_keywords": [], "responsibilities": ["due diligence", "analysis", "market information", "risk analysis"], "requirements": {"degrees": ["degree or above", "bachelor"], "majors": [], "languages": ["putonghua", "english", "chinese"], "language_level": ["excellent"], "hard_skills": ["excel", "ms applications", "analytical skills", "project management", "power point", "pc skills", "acumen"], "soft_skills": ["meet tight deadlines", "independently", "project management skills", "detailed", "analytical skills", "communication", "presentation skills", "business acumen", "articulate", "team player", "interpersonal", "work under pressure"], "languages_combined": [{"language": "putonghua", "language_level": ["excellent"]}, {"language": "english", "language_level": ["excellent"]}, {"language": "chinese", "language_level": ["excellent"]}]}, "experience_required": {"duration": ["minimum 4 years"], "field": ["relevant experience"]}}, {"job_id": "100003009050873", "location_code": "hk", "company": "Manpower Services (Hong Kong) Limited", "job_title": "Bank Security and Facility Specialist", "description": "Responsibilities and duties of the role:\n\nWork with front office and in-house legal to review facility and security agreements and ensure terms and conditions are in compliance with credit approval.\nMonitor underwriting commitment and assist front office on pre-signing administrative tasks.\nTo ensure all conditions precedent documents are fulfilled before approving the BO team to proceed funding and loan payment.\nMonitor facility closing, initial drawdown, fees settlement and conditions subsequent, if any.\nCheck and verify facility and security documentation signed and returned by customers with relevant supporting documentation.\nEnsure the perfection on security documents and monitor periodical revaluation and the expiry of ongoing collateral and securities.\nHandle credit matters and daily portfolio monitoring and covenant checking for designated portfolio across all Business Lines.\nHandle facility limits, collateral, covenants set up, modification and deletion timely in system.\nHandle other tasks assigned by the Team Lead &/or Manager.\n\nJob Requirements\n\nUniversity degree, minimum of 3-5 years relevant experiences with an international bank.\nKnowledge and experience in handling covenant monitoring is essential.\nExperience in handling Specialized Lending or Structured Finance Facilities.\nGood interpersonal and communication skills are required and able to work under pressure.\nWritten and Spoken English, Spoken Mandarin & Cantonese\n\nInterested parties please send your full resume with expected salary to yan.chan@manpowergrc.hk\u00a0or by clicking \"Apply Now\".", "employment_types": ["Contract"], "selling_points": ["Covenant monitoring", "Specialized Lending/Structured Finance Facilities", "3-5 years relevant experiences"], "locations": ["Yau Tsim Mong Area"], "categories": ["Banking / Finance", "Credit Analysis / Approval", "Others", "Credit Collection"], "post_time": "2022-01-14T11:36:17Z", "salary": {"currency": null, "max": null, "min": null, "period": "monthly", "term": null}, "salary_visible": false, "title_keywords": ["specialist"], "responsibilities": ["documentation", "compliance", "review", "monitor", "monitoring", "checking", "other tasks", "payment", "administrative tasks"], "requirements": {"degrees": ["university degree"], "majors": [], "languages": ["cantonese", "english", "mandarin"], "language_level": [], "hard_skills": [], "soft_skills": ["communication skills", "structured", "interpersonal", "work under pressure"], "languages_combined": [{"language": "cantonese", "language_level": []}, {"language": "english", "language_level": []}, {"language": "mandarin", "language_level": []}]}, "experience_required": {"duration": ["minimum of 3-5 years"], "field": ["finance"]}}, {"job_id": "100003009036216", "location_code": "hk", "company": "BOCOM International Holdings Company Limited", "job_title": "Associate/ Senior Associate, Credit Risk", "description": "Responsibilities:\n\nConduct daily report review and account monitoring and liaise with Account Executives (AE) to obtain relevant information for credit due diligence\nCommunicate effectively with sales team on the follow-up action on credit control related issues\nConduct and comment assessments on credit limit proposals and act as a maker to adjust the client approved limit in the trading system\nObtain the proper approval for those accounts in accordance with credit policies and procedures\nSet up or create templates for reporting\nCollect the statistical data on credit risk analysis\nPerform ad hoc assignments and handle special projects with credit related issues from time to time required by management\nCompile daily, weekly and monthly reports on time and perform clerical duty\n\nRequirement\n\nUniversity degree in Finance / Risk Management / other related disciplines (FRM or CFA preferred). Minimum 5-6 years relevant working experience is required if the candidate is not a degree holder\nMinimum 3 years experience in credit risk management, preferably in financial institutions\nGood knowledge in equity market and derivatives products\nPossess strong credit analytical skills\nStrong proficiency in VBA and Excel-Macro\nProficient in MS Office application and Chinese word processing\nGood communication skills and good telephone manner\nGood command of written and spoken English and Chinese with fluency in Mandarin; knowledge of Simplified Chinese a plus\nEfficient, self-motivated, independent and able to work under pressure\nMore experience will be offered as Senior Associate\nImmediate Available is highly preferred\n\nApplication:\n\nWe offer an attractive remuneration package including a performance bonus, medical insurance covering dependants, MPF, Life and AD&D insurance, annual leave, birthday leave, marriage leave and training subsidy, etc. to the right candidate.\u00a0\n\nIf you are interested in this opportunity, please send your application with a detailed resume including current and expected salary, latest bonus and availability by clicking \"Apply Now\". Applications without required information will NOT be considered.\n\n*Information provided by applicants will be treated in the strictest confidence and will be solely used for recruitment purposes.", "employment_types": ["Full Time", "Permanent"], "selling_points": ["Credit Risk", "Strong in Excel (VBA, Macro)", "Margin Financing"], "locations": ["Central"], "categories": ["Banking / Finance", "Credit Analysis / Approval", "Credit Collection", "Risk Management"], "post_time": "2022-01-10T09:40:28Z", "salary": {"currency": null, "max": null, "min": null, "period": "monthly", "term": null}, "salary_visible": false, "title_keywords": ["senior associate", "associate"], "responsibilities": ["due diligence", "control", "reporting", "management", "data", "policies", "monitoring", "review", "procedures", "liaise with", "sales team", "risk analysis", "ad hoc assignments", "daily report", "weekly and monthly reports"], "requirements": {"degrees": ["university degree", "degree holder"], "majors": ["related disciplines", "finance", "risk management"], "languages": ["english", "chinese", "mandarin"], "language_level": ["fluency", "good command", "proficient"], "hard_skills": ["vba", "excel", "macro", "chinese word processing", "plus", "cfa", "credit analytical skills", "frm", "ms office"], "soft_skills": ["efficient", "communication skills", "self-motivated", "confidence", "independent", "interested in", "detailed", "analytical skills", "telephone manner", "work under pressure"], "languages_combined": [{"language": "english", "language_level": ["fluency", "good command"]}, {"language": "chinese", "language_level": ["fluency", "good command", "proficient"]}, {"language": "mandarin", "language_level": ["fluency", "good command"]}]}, "experience_required": {"duration": ["minimum 5-6 years", "minimum 3 years"], "field": ["financial institutions", "management", "relevant working experience", "credit risk"]}}, {"job_id": "100003009042898", "location_code": "hk", "company": "Chong Hing Bank Ltd", "job_title": "Vice President - Credit Analytics & Modeling", "description": "Responsibilities:\nLead and manage the credit risk modeling and credit analytics team;\nMaintain credit rating models for measurement and management of credit risk for the Bank\u2019s portfolio;\nLiaise with different units to formulate credit MIS processes, support stress testing of regulatory capital, data management projects and implementation of new initiatives such as IFRS9, BELR, ICAAP, and SA-CCR;\nManage the credit portfolio reporting and the associated MIS; and\nPerform other ad hoc projects or assignments.\nRequirements:\n\nUniversity graduate in Finance, Economics, Accounting, Risk Management, Statistics or related disciplines;\nHKIB ECF-CRM;\nCFA, Accountant and/or FRM is a plus; \u00a0\nMinimum of 8 years\u2019 solid bank experience in credit risk management; project management experience preferred;\nExpansive knowledge of credit risk requirement and credit policy; and familiar with credit risk stress testing, IFRS9, ICAAP and SA-CCR rating models (PD) and LGD/EAD measurement;\nStrong self-motivation and creativity, with excellent communication and analytical skills;\nDemonstrated ability to rapidly build relationships with key stakeholders; and\nCandidate with less experience will be considered as Assistant Vice President.\nWe offer competitive remuneration package and promising career opportunities to the successful candidates. Interested parties, please send full resume with current & expected salary and the date of availability to The HR Division, G.P.O. Box 2535, HK , or by clicking Apply Now. Please quote reference on your application. Information provided will be treated in strict confidence and only be used for recruitment purposes. Personal data of unsuccessful applications will be destroyed 24 months after the completion of the recruitment and selection exercise.", "employment_types": ["Full Time", "Permanent"], "selling_points": ["Lead credit risk modeling/ analytics team", "Credit rating models, IFRS9, BELR, ICAAP, & SA-CCR", "Credit portfolio reporting and MIS"], "locations": ["Kowloon Bay"], "categories": ["Banking / Finance", "Credit Analysis / Approval", "Financial Services", "Others"], "post_time": "2022-01-12T09:10:24Z", "salary": {"currency": null, "max": null, "min": null, "period": "monthly", "term": null}, "salary_visible": false, "title_keywords": ["vice president"], "responsibilities": ["reporting", "management", "data", "measurement", "implementation", "testing", "maintain", "ad hoc projects", "liaise with"], "requirements": {"degrees": ["university graduate"], "majors": ["risk management", "finance", "economics", "statistics", "related disciplines", "accounting"], "languages": [], "language_level": [], "hard_skills": ["plus", "cfa", "analytical skills", "project management", "frm"], "soft_skills": ["communication", "project management", "self-motivation", "analytical skills"], "languages_combined": []}, "experience_required": {"duration": ["minimum of 8 years"], "field": ["project management", "management", "credit risk"]}}, {"job_id": "100003009046295", "location_code": "hk", "company": "Ambition", "job_title": "Risk Manager, Quant Modelling", "description": "Our client is a well-established financial institution with a strong presence in Hong Kong. With their team expanding, they are looking for Quant Risk professional to join their team.\n\nResponsibilities\n\n\n\nProvide key modelling elements including model assumptions, limitations, inputs & outputs, methodology, implementation, monitoring and control, etc.\nEnsure any identified model risk issues are effectively communicated with model stakeholders and appropriately remediated\nCreate new tools/techniques that can enhance the group level risk monitoring and quantification.\nMaintain up to date knowledge of risk management practices\n\nRequirements\n\n\n\nBachelor's degree in business administration or other related disciplines\nAdvanced degree/ FRM / CFA qualification is an advantage\nMinimum 3-5years' relevant experience in market, credit, or liquidity risk models\nStrong programming skill (VBA/Python/SQL) is an advantage\nStrong communication and writing skills in Chinese and English\n\nIf this job isn't quite right for you, but you know someone who would be great at this role, why not take advantage of our referral scheme? We offer HKD1000 in Apple gift cards for every referred candidate who we place in a role. Terms & Conditions Apply. https://www.ambition.com.hk/refer-a-friend", "employment_types": ["Full Time", "Permanent"], "selling_points": ["Excellent career prospect", "Market risk, quantitative risk or model risk", "Fast expanding team"], "locations": ["Not Specified"], "categories": ["Banking / Finance", "Credit Analysis / Approval", "Others", "Risk Management"], "post_time": "2022-01-13T10:21:53Z", "salary": {"currency": "HKD", "max": 69999, "min": 45000, "period": "monthly", "term": null}, "salary_visible": true, "title_keywords": ["manager"], "responsibilities": ["control", "management", "monitoring", "implementation", "risk monitoring", "maintain"], "requirements": {"degrees": ["degree", "bachelor"], "majors": ["related disciplines", "business administration"], "languages": ["english", "chinese"], "language_level": [], "hard_skills": ["vba", "cfa", "scheme", "writing skills", "sql", "programming", "python", "frm"], "soft_skills": ["communication", "advanced", "writing skills"], "languages_combined": [{"language": "english", "language_level": []}, {"language": "chinese", "language_level": []}]}, "experience_required": {"duration": [], "field": ["relevant experience"]}}, {"job_id": "100003009043428", "location_code": "hk", "company": "Industrial and Commercial Bank of China (Asia) Limited", "job_title": "Assistant Manager to Manager, Risk & System Management (AML), Credit Card Centre, CFD", "description": "Responsibilities:-\n\nFormulate fraud control strategies / policies to assist business growth and minimize the bank\u2019s financial losses.\nIdentify and design MIS report to ensure sound fraud risk control and comply with internal & external regulatory requirements.\nConduct case investigation in comprehensive manner and investigation reports writing\nReview and maintain procedure guidelines relevant to Credit Card AML to ensure the effectiveness and compliance with the Bank's policy and procedures.\nMonitor AML MIS reports to ensure proper actions are taken in timely manner according to relevant guidelines.\n\nRequirements:\n\nUniversity or equivalent\nMinimum 5 years\u2019 solid fraud control experience in credit card\nMinimum 3 years experience in AML transaction monitoring and STR reporting\nFamiliar with fraud risk control and relevanet regulatory requirement\nGood knowledge on the Issuing Fraud is a plus\nSelf-motivating and can work independently\nGood command of spoken and written English and Chinese, including Putonghua\n\nPersonal data collected will be used for recruitment purposes only", "employment_types": ["Full Time", "Permanent"], "selling_points": [], "locations": ["Kwun Tong"], "categories": ["Banking / Finance", "Credit Analysis / Approval", "Others", "Risk Management"], "post_time": "2022-01-12T11:39:30Z", "salary": {"currency": null, "max": null, "min": null, "period": null, "term": null}, "salary_visible": false, "title_keywords": ["assistant manager", "manager"], "responsibilities": ["control", "aml", "guidelines", "policies", "regulatory requirements", "review", "compliance", "procedures", "design", "investigation", "monitor", "maintain", "reports", "report"], "requirements": {"degrees": [], "majors": [], "languages": ["putonghua", "english", "chinese"], "language_level": ["good command"], "hard_skills": ["plus", "aml"], "soft_skills": ["work independently"], "languages_combined": [{"language": "putonghua", "language_level": ["good command"]}, {"language": "english", "language_level": ["good command"]}, {"language": "chinese", "language_level": ["good command"]}]}, "experience_required": {"duration": ["minimum 5 years", "minimum 3 years"], "field": ["credit card"]}}, {"job_id": "100003009045548", "location_code": "hk", "company": "Hang Seng Bank Ltd", "job_title": "Manager, Collections OPS", "description": "WPB Chief Operating Office \u2013 Fraud and Credit Control Services\n\nWe are currently seeking a high caliber professional to join our department as\u00a0Manager, Collections OPS.\n\n\nPrinciple responsibilities\n\nLead a team of staff to manage all activities related to project management, system development and implementation.\nPlan, direct and manage the development and production of quality MIs.\nProvide prompt responses and recommendations on credit policies and collections strategy to adapt to the fast and changing market.\nLead and drive new initiatives / projects including process streamlining, system enhancement and service migration to improve operational efficiencies and copy with business needs.\nRequirements\nUniversity degree in Business or a related discipline OR other relevant qualifications/experience\nMinimum 5 years' relevant experience in project management, analytics, debt collections or credit risk.\nSound knowledge of retail banking, operational risk management, financial crime compliance or other related areas an advantage\nGood knowledge of application software (Skills in SAS, MS Word, Excel, Powerpoint and Access)\nStrong business acumen with good problem solving, communication and analytical skills\nGreat sense of ownership and servicing mindset to ensure efficient and effective customer service processes\nProficiency in both English and Chinese, fluency in Putonghua an advantage\n\u00a0\n\nIf you would like to explore other opportunities at Hang Seng Hong Kong, please visit\u00a0www.hangseng.com/careers/\u00a0for details.\n\nThe health and safety of our employees and candidates is very important to us. Due to the current situation related to the Novel Coronavirus (2019-nCoV), we\u2019re leveraging our digital capabilities to ensure we can continue to recruit top talent at the HSBC Group. \u00a0As your application progresses, you may be asked to use one of our digital tools to help you through your recruitment journey. \u00a0If so, one of our Resourcing colleagues will explain how our video-interviewing technology will be used throughout the recruitment process and will be on hand to answer any questions you might have.\n\nAll information provided by applicants will be used only for recruitment purposes and will be used strictly in accordance with the Bank's personal data policies, a copy of which may be obtained by the applicant upon request. Unless otherwise instructed in writing by the applicant concerned, applicants may be considered for other suitable positions within the Bank and its related companies. The personal data of unsuccessful job applicants may be retained for a maximum of two years from the date when the job application is rejected and such data may be retained for a longer period if there is a subsisting reason that obliges the Bank to do so, after which the personal data will be destroyed.", "employment_types": ["Full Time", "Permanent"], "selling_points": [], "locations": ["Not Specified"], "categories": ["Banking / Finance", "Credit Analysis / Approval", "Retail Banking", "Credit Collection"], "post_time": "2022-01-13T08:03:46Z", "salary": {"currency": null, "max": null, "min": null, "period": "monthly", "term": null}, "salary_visible": false, "title_keywords": ["manager"], "responsibilities": ["policies", "quality", "implementation", "lead a team", "project management", "plan", "migration"], "requirements": {"degrees": ["university degree"], "majors": ["business"], "languages": ["putonghua", "english", "chinese"], "language_level": ["fluency", "advantage", "proficiency"], "hard_skills": ["excel", "sas", "powerpoint", "acumen", "problem solving", "project management", "analytical skills", "reason", "ms word"], "soft_skills": ["efficient", "analytical skills", "communication", "project management", "problem solving", "customer service", "business acumen", "novel"], "languages_combined": [{"language": "putonghua", "language_level": ["fluency"]}, {"language": "english", "language_level": ["proficiency", "fluency", "advantage"]}, {"language": "chinese", "language_level": ["proficiency", "fluency", "advantage"]}]}, "experience_required": {"duration": ["minimum 5 years"], "field": ["related", "project management", "business", "relevant experience", "credit risk"]}}, {"job_id": "100003009050671", "location_code": "hk", "company": "China Construction Bank (Asia) Corporation Limited", "job_title": "AVP/ Manager, Enterprise Risk", "description": "Responsibilities:\n\nConduct regular estimation on IFRS 9 expected credit losses\n\nPrepare regular credit MIS and analysis to support business needs\n\nEnsure the accuracy and timeliness of MIS Report\n\nAssist on the enhancement of IFRS 9 impairment models (e.g, Probability of Default (PD) models)\n\nPerform credit risk analytics on the bank\u2019s portfolio\n\nStreamline workflows by using SAS and Excel and VBA and/or other database management techniques\n\nPerform ad-hoc analysis\n\n\u00a0\u00a0\u00a0\u00a0\u00a0\u00a0\u00a0 Requirements\n\n\n\u00a0\u00a0\u00a0\u00a0\u00a0\u00a0\u00a0\u00a0 4+ years of relevant experience in credit risk management or related risk management field\n\u00a0\u00a0\u00a0\u00a0\u00a0\u00a0\u00a0\u00a0 Bachelor degree in statistics, risk management or quantitative sciences or related areas\n\u00a0\u00a0\u00a0\u00a0\u00a0\u00a0\u00a0\u00a0 Advanced degree in quantitative sciences is preferred\n\u00a0\u00a0\u00a0\u00a0\u00a0\u00a0\u00a0\u00a0 Hands on experience in data analytics and SAS programming\n\u00a0\u00a0\u00a0\u00a0\u00a0\u00a0\u00a0\u00a0 Independent, detail-oriented and able to meet tight deadlines\n\u00a0\u00a0\u00a0\u00a0\u00a0\u00a0\u00a0\u00a0 Experience with SAS is essential and FRM qualification is preferable\n\u00a0\u00a0\u00a0\u00a0\u00a0\u00a0\u00a0\u00a0 Good team player and able to deal with large amount of data\n\u00a0\u00a0\u00a0\u00a0\u00a0\u00a0\u00a0\u00a0 Good command of both English and Chinese, including Putonghua\n\u00a0\u00a0\u00a0\u00a0\u00a0\u00a0\u00a0\u00a0 Candidates with less experience will be considered as Manager grade", "employment_types": ["Full Time", "Permanent"], "selling_points": ["regular estimation on IFRS 9 expected credit loss", "Prepare regular credit MIS and analysis", "4+ years of experience in credit risk management"], "locations": ["Kowloon Bay"], "categories": ["Banking / Finance", "Credit Analysis / Approval", "Financial Services", "Risk Management"], "post_time": "2022-01-14T11:09:20Z", "salary": {"currency": null, "max": null, "min": null, "period": "monthly", "term": null}, "salary_visible": false, "title_keywords": ["manager"], "responsibilities": ["ad-hoc", "management", "analysis", "database", "support business needs", "report"], "requirements": {"degrees": ["degree", "bachelor"], "majors": ["risk management", "statistics"], "languages": ["putonghua", "english", "chinese"], "language_level": ["good command"], "hard_skills": ["data analytics", "frm qualification", "programming", "sas"], "soft_skills": ["meet tight deadlines", "good team player", "independent", "advanced", "detail-oriented", "hands on"], "languages_combined": [{"language": "putonghua", "language_level": ["good command"]}, {"language": "english", "language_level": ["good command"]}, {"language": "chinese", "language_level": ["good command"]}]}, "experience_required": {"duration": ["4+ years"], "field": ["risk management", "management", "related", "relevant experience", "programming", "credit risk"]}}, {"job_id": "100003009037631", "location_code": "hk", "company": "China CITIC Bank International Limited", "job_title": "Manager, Credit Risk Methodologies and Analytics", "description": "Job Purpose\n\nAssist in regular credit impairment report to meet HKFRS-9 requirements and assess the movement of credit impairment to drive methodology enhancement.\n\n\n\nKey Responsibilities\n\nEnhance the methodology, risk parameters and systems for the impairment provision estimation under IFRS-9 requirements.\nMonitor\u00a0the credit risk RWA calculation and provide judgement on credit RWA as appropriate.\nContribute in new product discussion and implementation, advise on Return of Allocate Capital (ROAC) and initiate relevant system changes.\nManage\u00a0stress testing methodology to meet regulatory requirements.\nPerform data validation, prepare monitoring and variance analysis of credit impairment provision movement.\nPrepare ICAAP reporting and support risk analytics projects in respect to requests from regulatory bodies and management.\nAssist to liaise with regulators, auditors, external parties and credit rating agencies\u00a0to provide explanations and clarifications on the credit risk methodologies adopted by the Bank.\n\nRequirements\n\n\nDegree holder in Finance, Accounting, Statistics or related disciplines.\nAt least 4\u00a0years' of relevant experience in bank or related industry.\nFamiliar with Basel frameworks, credit risk approaches and HKMA capital banking rules.\nProficiency in credit risk quantitative modeling, expected loss computations, data & risk analysis and stress testing.\nProfessional qualification like Associate Credit Risk Management Professional (ACRP), CFA, FRM, ACCA, etc. is preferred.\nSelf-motivated, independent, with good communication skills, able to communicate effectively at all levels.\nGood command of written and spoken English and Chinese including Putonghua.\nCandidate with\u00a0more experience will be considered\u00a0for the role of\u00a0Senior Manager.\n\nFor more details about career opportunities with the Bank, please visit our website http://www.cncbinternational.com/careers/en/index.jsp. Please apply with full resume stating current and expected salaries via https://careers.cncbinternational.com.\n\nPersonal data collected will be used for recruitment related purposes only. Applicants not invited for interview within 6 weeks may consider their applications unsuccessful. However, applicants may be considered for other suitable positions within the Group for a period of not more than 2 years. Personal data will be destroyed at any time after 3 months.\n\nChina CITIC Bank International is committed to being an equal opportunities employer and intends to provide a work environment free of unlawful discrimination or harassment. All employment decisions will be made in a non-discriminatory manner.", "employment_types": ["Full Time", "Permanent"], "selling_points": ["4 years of work experience in credit risk models", "Knowledge of Basel & IFRS9", "Experience in SAS"], "locations": ["Tsim Sha Tsui"], "categories": ["Banking / Finance", "Credit Analysis / Approval", "Professional Services", "Business Analysis / Data Analysis", "Risk Management"], "post_time": "2022-01-11T03:19:57Z", "salary": {"currency": null, "max": null, "min": null, "period": "monthly", "term": null}, "salary_visible": false, "title_keywords": ["manager"], "responsibilities": ["reporting", "management", "data", "regulatory requirements", "systems", "monitor", "implementation", "monitoring", "testing", "external parties", "variance analysis", "liaise with", "system changes"], "requirements": {"degrees": ["degree holder"], "majors": ["related disciplines", "finance", "accounting", "statistics"], "languages": ["putonghua", "english", "chinese"], "language_level": ["good command"], "hard_skills": ["acca", "hkma", "cfa", "analysis", "frm"], "soft_skills": ["communication skills", "self-motivated", "committed", "independent"], "languages_combined": [{"language": "putonghua", "language_level": ["good command"]}, {"language": "english", "language_level": ["good command"]}, {"language": "chinese", "language_level": ["good command"]}]}, "experience_required": {"duration": ["at least 4 years"], "field": ["related", "relevant experience"]}}, {"job_id": "100003009033645", "location_code": "hk", "company": "OCBC Wing Hang Bank Limited", "job_title": "Associate, Credit RWA Solutions", "description": "Responsibilities\nPerform the data reconciliation\nPrepare the Credit RWA and Credit Portfolio MIS reports for the submission to senior management\u00a0\nPrepare user requirements and conduct the user acceptance test\nConduct the Credit Risk Stress Test (includes Climate Risk Stress Test)\nLiaise with business units and other relevant parities on Credit RWA and stress test issues\nParticipate in Basel IRB related initiatives\nRequirements\n\u200bBachelor\u2019s degree or above with major in Risk Management, Finance, Business, Economics, and other relevant disciplines\nAround 2 years\u2019 relevant experiences, fresh graduate will also be considered.\u00a0\nProficient in MS Office, especially MS Excel\nSound knowledge of SQL and SAS\nKnowledge of Basel 3 Credit RWA regulations will be an advantage\nStrong communication and presentation skill\nAble to work independently and a good team player\n\nAttractive remuneration package will be offered to the right candidate. Please apply with full resume stating present & expected salary and contact phone number\u00a0to\u00a0The Human Resources Manager, 10/F, 161 Queen\u2019s Road Central, Hong Kong.\u00a0Please quote the reference.\n\nPersonal data collected will be used for recruitment purpose only. For more information, please visit our website:\u00a0http://www.ocbcwhhk.com.", "employment_types": ["Full Time", "Permanent"], "selling_points": ["Credit RWA", "Risk Management", "Data Analytics"], "locations": ["Sheung Wan"], "categories": ["Banking / Finance", "Credit Analysis / Approval", "Retail Banking", "Risk Management"], "post_time": "2022-01-10T01:27:57Z", "salary": {"currency": null, "max": null, "min": null, "period": "monthly", "term": null}, "salary_visible": false, "title_keywords": ["associate"], "responsibilities": ["liaise with", "senior management", "reports", "data"], "requirements": {"degrees": ["degree or above", "fresh graduate"], "majors": ["finance", "risk management", "business", "economics"], "languages": [], "language_level": [], "hard_skills": ["presentation skill", "sas", "sql", "ms excel", "ms office"], "soft_skills": ["communication", "good team player", "presentation skill", "work independently"], "languages_combined": []}, "experience_required": {"duration": ["2 years"], "field": []}}, {"job_id": "100003009044695", "location_code": "hk", "company": "Chong Hing Bank Ltd", "job_title": "Manager, Fraud Control - Card Business & Payment Solutions Department", "description": "Responsibilities:\n\nMonitor daily MIS reports and prepare suspicious transactions report to Compliance Department when suspicious transactions or irregular credit card activities are detected\nHandle trigger event / regular review on existing credit card customers\nMonitor daily fraud detection reports for credit card activities\nHandle At-Risk Accounts Alert (Common Purchase Point \u2013 CPP, Visa, MasterCard and UnionPay Alert etc.) & Fraud Alert Notice (Fraud Application, Account Takeover, newly Detected Merchant etc.)\nScan Anti-Money Laundering cases\nCommunicate and collaborate with Card Associations / Law Enforcement Agencies\nPrepare customer information / document to other departments\nParticipate in UAT for any system enhancement pertaining to fraud control aspects\nStay alert and monitor daily tasks to identify risk issues\nReport to senior management and Operational & IT Risk Management Department (ZRMD) promptly once identify issues with risk\n\n\n\nRequirements:\n\nUniversity graduate in Business Administration or related disciplines\nAt least 5 years of relevant banking experience\nFamiliar with regulatory requirements in banking industry\nFamiliar with credit card authorization, operations and chargeback process\nUnderstand the situation and the trend of current market risk\nUnderstanding of bank\u2019s products and have experience in operational risk management\nBe proactive, vigilant and paying attentions to details\nAbility to multi-task and have strong project management skills\nStrong analytical mind in fraud detection system, MIS and investigation skills\nStrong interpersonal skills and coordinate with related units are required", "employment_types": ["Full Time", "Permanent"], "selling_points": ["At least 5 years of relevant banking experience", "Familiar with regulatory requirements", "Familiar with credit card authorization"], "locations": ["Not Specified"], "categories": ["Banking / Finance", "Credit Analysis / Approval", "Financial Services"], "post_time": "2022-01-13T05:32:29Z", "salary": {"currency": null, "max": null, "min": null, "period": null, "term": null}, "salary_visible": false, "title_keywords": ["manager"], "responsibilities": ["collaborate with", "control", "management", "uat", "compliance", "monitor", "transactions", "regular review", "purchase", "reports", "senior management", "report"], "requirements": {"degrees": ["university graduate"], "majors": ["related disciplines", "business administration"], "languages": [], "language_level": [], "hard_skills": ["project management"], "soft_skills": ["multi-task", "project management skills", "analytical mind", "interpersonal skills", "proactive"], "languages_combined": []}, "experience_required": {"duration": ["at least 5 years"], "field": ["risk management", "banking experience"]}}, {"job_id": "100003009032375", "location_code": "hk", "company": "Welend Limited", "job_title": "Credit Approval Manager", "description": "WeLab is a leading fintech company in Asia, \u00a0which operates one of first licensed digital banks in Asia \u2013 WeLab Bank, as well as multiple leading online financial services businesses including WeLend and WeLab Bank in Hong Kong, WeLab Digital (\u6211\u6765\u6570\u79d1), Taoxinji (\u6dd8\u65b0\u673a), Wallet Gugu (\u94b1\u5939\u8c37\u8c37) and Tianmian Tech (\u5929\u5195\u79d1\u6280)\u00a0in Mainland China and Maucash in Indonesia. WeLab aims to bring joy to everyone\u2019s financial journey. We strive to improve people\u2019s lives by reinventing financial services through game-changing technology. We put our people first, whether it\u2019s our customers or our employees.\n\nWe are an energetic and passionate team that can deliver and execute. We are looking for other intellectually curious, open-minded and smart-working individuals who are just as passionate as we are about making financial services enjoyable. Now you have the opportunity to join us on our journey to achieve our vision and be part of building a better financial future for everyone.\n\nAbout you:\n\nYou're a go-getter with mad juggling skills (or multiple hats) who can thrive in a fast-paced, agile environment\nYou have a strong thirst for knowledge and are driven to find solutions that don't exist yet\nYou are comfortable with ambiguity and extremely resourceful (in your past life you could've been a detective)\nYou always find a way to get things done without sacrificing the quality of your work, integrity and values. No task is off limits for you.\nYou are humble and prioritize the success of the team over your own with an eagerness to help those around you\nYou don't shy away from challenges and have the ability to bounce back from setbacks\n\nWhat you\u2019ll do and what success looks like in this role\n\nLead a team of credit officers to review and approve credit applications with the designated credit authority\nProcess credit applications according to credit policies and underwriting standards\nManage and monitor loan portfolio to ensure credit quality and full compliance of internal policies and lending guidelines\nParticipate in projects with the aim of optimizing the credit operation and process\nPerform fraud detection on applications and prevent fraud\n\nWhat is required and what we\u2019re looking for\n\nHigher Diploma or above\nMinimum 5 year related experience in unsecured credit products. Personal loan experience is an advantage\nStrong understanding in key market and industry dynamics of Hong Kong\nSelf-initiative and good team player\nExcellent interpersonal and communication skills\n\nWeLab perks:\n\nCompetitive salary\nLearning and development stipend, because we value lifelong learning and believe the best way to invest in our employees is to encourage them to continue to learn\nWork hard and laugh lots (chicken wings and french toast, etc.) with a high-performing, fun and diverse team\nHappiness Dollars for spending on anything that makes you happy\nCoffee stipend\nConveniently located office surrounded by diverse and delicious lunch options\nLively office with gaming consoles and a ping pong table\nFun extracurricular activities with your colleagues like hiking, yoga, badminton, wine tasting, dragon boat racing, rock climbing, etc.\nEmployee referral bonuses\n\nAwards & recognition:\n\nFinancial Times (FT) 2020 Asia-Pacific High-Growth Companies \u2013 #2 ranked company\n2020 CNBC Disruptor 50 List \u2013 #11, only company included from Hong Kong and just one of five from Asia\n\nWe offer competitive salary package to the successful candidate.\u00a0 If you are interested in joining this exciting team, please apply with resume via the \"Apply\" button below.\n\nAll information provided by applicants will be used for recruitment purposes only. Information of unsuccessful applicants will be destroyed within 24 months of receipt.", "employment_types": ["Full Time", "Permanent"], "selling_points": ["Process credit applications", "Review and approve credit applications", "Minimum 5 year related experience"], "locations": ["Quarry Bay"], "categories": ["Banking / Finance", "Credit Analysis / Approval", "Loan", "Sales, CS & Business Devpt", "Others"], "post_time": "2022-01-07T10:57:14Z", "salary": {"currency": null, "max": null, "min": null, "period": "monthly", "term": null}, "salary_visible": false, "title_keywords": ["manager"], "responsibilities": ["guidelines", "policies", "review", "monitor", "quality", "compliance", "communication", "lead a team"], "requirements": {"degrees": ["higher diploma or above"], "majors": [], "languages": ["french"], "language_level": [], "hard_skills": ["no", "joy", "agile", "fun", "go", "mad"], "soft_skills": ["passionate", "communication skills", "good team player", "agile", "resourceful", "interpersonal", "open-minded", "integrity", "prioritize", "diverse", "learning", "self-initiative", "energetic", "driven"], "languages_combined": [{"language": "french", "language_level": []}]}, "experience_required": {"duration": ["minimum 5 year"], "field": ["related"]}}, {"job_id": "100003009042386", "location_code": "hk", "company": "Page Personnel", "job_title": "Top Bank - Actuarial Analyst (Fresh Graduates Welcome!)", "description": "Our client is looking for an Actuarial Analyst to join their growing team. The successful candidate will have 1 - 2 years of actuarial experience within banking.\n\nClient Details\n\nOur client is one of Hong Kong's largest banks with more than 80 years of history. Its main services include private banking, retail banking, investment services and wealth management. The bank provides a massive network of more than 200 service outlets in Hong Kong and has established its network in most major cities in mainland China.\n\nDescription\n\n* Responsible for financial reporting and other actuarial analytic related issues\n* Valuation reporting on IFRS basis, local statutory basis and new business\n* Responsible for earning analysis and stress test\n* Conduct experience analysis, regulatory filling, annual operating plan and business forecast\n\nProfile\n\n1-2 years of actuarial work experience\nEducation background: Business / Economics / Finance / Statistics / Mathematics\nGood progress with actuarial examinations\nKnowledge on computer programming language and Actuarial Software preferred\nProficiency in both English and Chinese\n\nJob Offer\n\nWorking days: Mon - Fri; 0900 - 1800\nExcellent exposure and great learning environment\nReputable Bank in Hong Kong\nGreat work-life balance\n\nTo apply online please click the 'Apply' button below. For a confidential discussion about this role please contact Kira Tang on +852 2258 3538.", "employment_types": ["Full Time", "Permanent"], "selling_points": ["Excellent exposure and great learning environment", "Reputable Bank in Hong Kong", "Great work-life balance"], "locations": ["Not Specified"], "categories": ["Banking / Finance", "Analyst", "Credit Analysis / Approval", "Retail Banking"], "post_time": "2022-01-12T07:15:44Z", "salary": {"currency": null, "max": null, "min": null, "period": "monthly", "term": null}, "salary_visible": false, "title_keywords": ["actuarial analyst"], "responsibilities": ["valuation", "management", "reporting", "software", "analysis", "financial reporting", "plan", "banking", "forecast", "contact"], "requirements": {"degrees": [], "majors": [], "languages": ["english", "chinese"], "language_level": ["proficiency"], "hard_skills": ["ifrs", "analysis", "programming"], "soft_skills": ["learning", "responsible"], "languages_combined": [{"language": "english", "language_level": ["proficiency"]}, {"language": "chinese", "language_level": ["proficiency"]}]}, "experience_required": {"duration": ["1 - 2 years", "1-2 years"], "field": ["business", "banking"]}}, {"job_id": "100003009033765", "location_code": "hk", "company": "Bank of Communications Co., Ltd. Hong Kong Branch", "job_title": "Risk Management Officer (Quantitative Analysis) \u2013 1 year contract", "description": "Career Level\nEntry Level\nQualification\nDegree\nJob Type\nFull Time, Contract\nJob Functions\nBanking / Finance, Credit Analysis / Approval, Others, Student / Fresh Graduate / No Experience, Risk Management", "employment_types": ["Full Time", "Contract"], "selling_points": [], "locations": ["Not Specified"], "categories": ["Banking / Finance", "Credit Analysis / Approval", "Others", "Student / Fresh Graduate / No Experience", "Risk Management"], "post_time": "2022-01-10T01:46:42Z", "salary": {"currency": null, "max": null, "min": null, "period": "monthly", "term": null}, "salary_visible": false, "title_keywords": ["risk management officer"], "responsibilities": ["analysis", "management", "banking"], "requirements": {"degrees": ["degree", "fresh graduate"], "majors": ["finance", "risk management"], "languages": [], "language_level": [], "hard_skills": ["credit analysis", "no"], "soft_skills": [], "languages_combined": []}, "experience_required": {"duration": [], "field": ["finance", "risk management", "banking"]}}, {"job_id": "100003009045775", "location_code": "hk", "company": "JAC Recruitment Hong Kong Co., Limited", "job_title": "Team Head - Trade & Supply Chain Finance - Trade Finance Department", "description": "Our client is a top tier foreign bank. They are looking for someone to join as a\u00a0Team Head - Trade & Supply Chain Finance - Trade Finance Department\n\nKey Responsibilities\n\n- Manage Financial Institution clients for the Trade & Supply Chain Finance Team.\n\n- Lead and guide junior teammates to expand and maintain current trade and receivable finance portfolio of Chinese, APAC, and Western MNCs clients\n\n- Promote cross-regional collaboration and cross-selling of other bank products with strong focus in Greater China Region\n\n- Responsible for the credit quality\n\nRequirements\n\n- University Degree Holder in Business, Economics or related disciplines\n\n- Minimum of 10 years\u2019 relevant experience in trade finance with a preference with regional Trade Supply Chain Finance experience.\u00a0\n\n- Good credit\u00a0knowledge in Trade Finance\n\n- Fluent in English, Cantonese and Mandarin\n\n- Prior team management experience\n\n\n*We offer*\n\n\"Interested candidates, please send an updated CV to kelvin.lam @jac-recruitment.com\n\nPersonal data collected will be used for employment-related purpose only. We regret to inform that only shortlisted candidates will be notified.", "employment_types": ["Full Time"], "selling_points": ["Top tier foreign bank", "Trade & Supply Chain Finance", "Trade Finance"], "locations": ["Central & Western Area"], "categories": ["Banking / Finance", "Corporate Banking", "Credit Analysis / Approval", "Loan"], "post_time": "2022-01-13T08:39:34Z", "salary": {"currency": null, "max": null, "min": null, "period": "monthly", "term": null}, "salary_visible": false, "title_keywords": [], "responsibilities": ["maintain", "quality", "finance team"], "requirements": {"degrees": ["university degree"], "majors": ["related disciplines", "economics", "business"], "languages": ["cantonese", "english", "mandarin"], "language_level": ["fluent"], "hard_skills": [], "soft_skills": [], "languages_combined": [{"language": "cantonese", "language_level": ["fluent"]}, {"language": "english", "language_level": ["fluent"]}, {"language": "mandarin", "language_level": ["fluent"]}]}, "experience_required": {"duration": ["minimum of 10 years"], "field": ["management", "finance", "supply chain", "relevant experience", "team"]}}, {"job_id": "100003009036751", "location_code": "hk", "company": "Industrial and Commercial Bank of China (Asia) Limited", "job_title": "Senior Relationship Manager, Non-Bank Business", "description": "Job Responsibilities\n\nResponsible for promoting and marketing banking products\nEnlarge business scope via cross-selling banking products\nMaintain close relationship and have good customer services to clients\nComply with all internal procedures and all external regulations\nIdentify and report any policy breaches to supervisors\nJob Requirements\n\nBachelor Degree Holder, in Finance, Accounting, Economics, Commerce and Marketing disciplines.\nRelevant Individuals of RA Type 1 and 4.\nAt least 5 years\u2019 experience in Banking / Securities Firms / Asset Management Firms. Experience in handling sales and marketing to Non-bank Fis is preferable\nGood relationship management skills\nFamiliar with Banking products and market\nGood team spirit and cooperative\nOpen minded, patient and able to work under pressure\nExcellent in written and spoken English and Chinese, including Putonghua", "employment_types": ["Full Time", "Permanent"], "selling_points": [], "locations": ["Central & Western Area"], "categories": ["Banking / Finance", "Corporate Banking", "Credit Analysis / Approval", "Corporate Finance"], "post_time": "2022-01-10T13:34:07Z", "salary": {"currency": null, "max": null, "min": null, "period": null, "term": null}, "salary_visible": false, "title_keywords": ["senior relationship manager"], "responsibilities": ["regulations", "procedures", "customer services", "maintain", "banking", "report"], "requirements": {"degrees": ["bachelor degree holder"], "majors": ["finance", "accounting", "economics", "marketing"], "languages": ["putonghua", "english", "chinese"], "language_level": ["excellent"], "hard_skills": ["ra type"], "soft_skills": ["team spirit", "cooperative", "open minded", "patient", "work under pressure"], "languages_combined": [{"language": "putonghua", "language_level": ["excellent"]}, {"language": "english", "language_level": ["excellent"]}, {"language": "chinese", "language_level": ["excellent"]}]}, "experience_required": {"duration": ["at least 5 years"], "field": ["asset management", "marketing", "securities firms", "banking"]}}, {"job_id": "100003009028779", "location_code": "hk", "company": "FundPark Limited", "job_title": "Manager \u2013 Senior Credit Underwriter / Senior Credit Analyst", "description": "Responsibilities:\n\nAssist CCO to lead a team of credit analyst to conduct credit analysis and underwriting on new potential clients and regular review of existing clients, preparation of credit underwriting reports on a timely basis with minimal supervision and ensure timely reporting of related credit information and reports of subordinates;\nFormulate and review Risk Framework, Credit Policy, development and enhancement of adequate credit underwriting procedures;\nAssist Risk Management to conduct portfolio risk management and to ensure effective risk monitoring and special assets management, including early warning mechanisms, contingency and debt collection plans;\nConduct fraud prevention measurements to ensure the underlying assets of the Trade Finance Projects are of good credit quality;\nTo participate in project development and liaise with different department;\nAssist to implement automation of credit underwriting procedures;\nPerform other ad-hoc tasks and assist in daily operation.\n\nRequirements:\n\nUniversity degree or high diploma in Finance, Accounting, Banking, Risk Management or related discipline;\nAt least 5 to 8 year experience in credit analysis earned from banking or finance sector;\nKnowledge in Trade Finance with experience in E-commerce industry will be an advantage\nFluent in both spoken and written English and Chinese (Cantonese and Mandarin a plus);\nA team player with strong interpersonal and relationship building skills with internal and external business partners;\nSelf-motivated, proactive and results oriented;\nAble to work in a fast-paced start-up environment, with multi-tasking and keen to details;\nBeing creative and tech-savvy on new apps development and new solutions, can think outside the box for better solutions.", "employment_types": ["Full Time"], "selling_points": ["Credit Underwriter/ Credit Analyst", "Risk Management", "Trade Finance/ E-commerce"], "locations": ["Ngau Tau Kok"], "categories": ["Banking / Finance", "Credit Analysis / Approval", "Financial Services", "Others"], "post_time": "2022-01-07T03:09:02Z", "salary": {"currency": null, "max": null, "min": null, "period": "monthly", "term": null}, "salary_visible": false, "title_keywords": ["manager", "credit analyst"], "responsibilities": ["reporting", "management", "analysis", "review", "procedures", "quality", "ad-hoc tasks", "daily operation", "regular review", "lead a team", "risk monitoring", "debt collection", "reports", "liaise with", "plans"], "requirements": {"degrees": ["high diploma", "university degree"], "majors": ["finance", "accounting", "risk management"], "languages": ["cantonese", "english", "chinese", "mandarin"], "language_level": ["fluent"], "hard_skills": ["credit analysis", "plus", "e-commerce"], "soft_skills": ["self-motivated", "creative", "keen", "multi-tasking", "team player", "proactive", "interpersonal"], "languages_combined": [{"language": "cantonese", "language_level": []}, {"language": "english", "language_level": ["fluent"]}, {"language": "chinese", "language_level": ["fluent"]}, {"language": "mandarin", "language_level": []}]}, "experience_required": {"duration": ["at least 5 to 8 year"], "field": ["finance", "e-commerce", "banking"]}}, {"job_id": "100003009028969", "location_code": "hk", "company": "The Bank of East Asia, Limited", "job_title": "Credit Manager, Credit Assessment Team", "description": "Credit Manager, Credit Assessment Team (Job ID3238)\nResponsibilities\nTo be a team member of Corporate Risk & Compliance Department\nTo perform credit assessment and revision of credit applications\nTo make recommendation to resolve complex credit issues\nTo formulate credit policies\nTo ensure that all procedures are in compliance with all policies, rules, guidelines, and requirements prescribed by regulators as well as the Bank\nTo advise Relationship Managers with respect to credit policies and lending guidelines\nTo alert and report on account irregularities, breach of guidelines, and potential credit risks\nTo take up ad hoc projects and assignments when required\nRequirements\nUniversity degree, preferably major in risk management, finance or related discipline\nMinimum 3 years of experience in banking field with strong knowledge on credit risk management and analysis\nAnalytical, independent, hardworking with positive working attitude\nGood knowledge of the Bank\u2019s lending policies and standards\nGood command of both spoken and written English and Chinese. Fluent in Putonghua is preferable\nProficient with Microsoft Office application including Word and Excel\nPlease apply online via the BEA Careers website at\u00a0https://careers.hkbea.com/psp/hcmprd/EMPLOYEE/HRMS/c/HRS_HRAM.HRS_APP_SCHJOB.GBL?Page=HRS_APP_JBPST&Action=UFOCUS=Applicant&SiteId=1&JobOpeningId=3238&PostingSeq=1 or by clicking the \"Apply Now\" button below. Kindly note that if you are a new user, you have to first create your User Profile before you can apply.\nPersonal data provided by job applicants will be used for recruitment purposes only and will be treated in accordance with the Bank's Personal Information Collection (Employees) Statement and Privacy Policy Statement. Applicants who are not invited for interviews within six weeks may consider their applications unsuccessful and the personal data collected will be destroyed after six months.", "employment_types": ["Full Time"], "selling_points": ["To alert and report on account irregularities", "University degree", "Minimum 3 years of experience in banking"], "locations": ["Not Specified"], "categories": ["Banking / Finance", "Credit Analysis / Approval", "Others", "Risk Management"], "post_time": "2022-01-07T03:43:42Z", "salary": {"currency": null, "max": null, "min": null, "period": "monthly", "term": null}, "salary_visible": false, "title_keywords": ["manager"], "responsibilities": ["make recommendation", "irregularities", "credit issues", "policies", "guidelines", "compliance", "procedures", "ad hoc projects", "report"], "requirements": {"degrees": ["university degree"], "majors": ["finance", "risk management"], "languages": ["putonghua", "english", "chinese"], "language_level": ["good command", "fluent"], "hard_skills": ["excel", "microsoft office", "analysis", "word", "c"], "soft_skills": ["positive working attitude", "independent", "hardworking"], "languages_combined": [{"language": "putonghua", "language_level": ["fluent"]}, {"language": "english", "language_level": ["good command"]}, {"language": "chinese", "language_level": ["good command"]}]}, "experience_required": {"duration": ["minimum 3 years"], "field": ["management", "credit risk", "banking"]}}, {"job_id": "100003009038023", "location_code": "hk", "company": "Hong Kong Job Consulting", "job_title": "(Assistant) Marketing Manager, Credit Card", "description": "\u00a0 \u00a0 A reputable local Bank in Hong Kong with a well-established Branch Network is looking for a dynamic Manager to join her Card Business & Business Development in Retail Banking Division, responsible for implement card usage campaigns for existing credit card customers and achieve business target on account receivable, point-of-sales and fee income growth\n\nResponsibilities:\n\nAssist in the development and execution of card usage marketing programs and partnership development with merchants to deliver business targets\nSupport digital payment programs and innovative projects to stimulate card usage and enhance customer experience\u00a0\nCoordinate with internal parties, partners, or vendors to deliver marketing campaigns in a quality and timely manner\nLiaise with advertising agency and to produce quality marketing collateral (including webpage maintenance)\nMonitor campaign response and prepare the program result tracking\nBudget and expenses management (including invoice settlement)\u00a0\n\n\u00a0Requirements:\n\nBachelor\u2019s degree holder, preferably in Business Administration or Marketing\nWith at least 5 years of experience in marketing\u00a0\nExperience in product management of retail banking or credit card products is preferable\nGood team player, detail oriented and strong communication skills\nAble to work under pressure and tight schedule\nLess experience candidate will be considered as Assistant Manager\n\n\u00a0 \u00a0 \u00a0 Interested parties please send your resume to \"APPLY NOW\u201d\n\n\u00a0 ***Personal data collected will be used for recruitment purposes only***", "employment_types": ["Full Time", "Permanent"], "selling_points": ["Experience in Marketing or Retail Banking", "Card Usage Campaign for Credit Card Customers", "Card Business & Business Development"], "locations": ["Not Specified"], "categories": ["Banking / Finance", "Credit Analysis / Approval", "Retail Banking", "Marketing / Public Relations", "Marketing - Brand / Product Management"], "post_time": "2022-01-11T04:37:39Z", "salary": {"currency": null, "max": null, "min": null, "period": "monthly", "term": null}, "salary_visible": false, "title_keywords": ["marketing manager", "assistant"], "responsibilities": ["management", "advertising", "maintenance", "invoice", "budget", "quality", "coordinate with", "monitor", "expenses", "payment", "marketing campaigns", "liaise with", "internal parties", "tracking"], "requirements": {"degrees": ["bachelor", "degree holder"], "majors": ["marketing", "business administration"], "languages": [], "language_level": [], "hard_skills": [], "soft_skills": ["communication skills", "detail oriented", "good team player", "work under pressure"], "languages_combined": []}, "experience_required": {"duration": ["at least 5 years"], "field": ["product management", "retail banking", "marketing", "credit card"]}}, {"job_id": "100003009023249", "location_code": "hk", "company": "MUFG Bank, Ltd.", "job_title": "Analyst (Credit Officer) - Japanese Corporate Banking Division", "description": "Key Responsibilities:\n\nResponsible for assisting Relationship Managers of Japanese Corporate Banking Division to prepare credit related applications and reports and resolving credit processes or credit operational issues, as well as preparation of customer\u2019s documentation and reports accurately and timely to identify and mitigate credit risks and to monitor credit risks of the assigned credit customers.\nDevelop and maintain strong stakeholder management with key stakeholders both internally and externally.\nWork in partnership with colleagues across departments of the Branch or primary offices to deliver an integrated service for our customers.\nWork in partnership with credit middle departments of the Branch to ensure credit control and procedures is in line with the Branch guidelines and policies.\nContact or visit customers or primary offices in charge of parent company of customers to obtain necessary information for purpose of preparation of credit related applications and reports to identify and mitigate credit risks and monitor credit risks of customers in accordance with internal credit policies and guidelines and credit control procedures.\nCooperate with Credit Examiners and Internal or External Audit to support inspections on credit portfolio and credit risk management.\nSupport Credit Team Leader in implementation and delivery of improvement initiatives for the department according to the predetermined schedule.\nMaintain good working knowledge of industry trends, products, internal rules and procedures, relevant laws and regulations.\nAdhere to all company policies as well as guidelines.\n\n\u00a0 \u00a0 \u00a0 \u00a0 \u00a0 \u00a0 \u00a0 \u00a0\u00a0\nJob Requirements:\u00a0 \u00a0 \u00a0 \u00a0 \u00a0 \u00a0 \u00a0 \u00a0 \u00a0\u00a0 \u00a0 \u00a0 \u00a0 \u00a0 \u00a0 \u00a0 \u00a0 \u00a0 \u00a0 \u00a0 \u00a0 \u00a0 \u00a0 \u00a0 \u00a0 \u00a0 \u00a0 \u00a0 \u00a0 \u00a0 \u00a0 \u00a0 \u00a0 \u00a0 \u00a0 \u00a0 \u00a0 \u00a0 \u00a0 \u00a0 \u00a0 \u00a0 \u00a0 \u00a0 \u00a0 \u00a0 \u00a0\n\nDegree holder with minimum of 2 years' relevant experience.\nExcellent organisation and analytical skills and attention to detail.\nGood knowledge of accounting and credit analysis.\nGood knowledge of industries and economic environment in the region.\nProficient in written and spoken English and Chinese, knowledge in Japanese is an advantage.\n\nWe regret to inform that only shortlisted applicants will be notified. Personal data collected will be used for recruitment purposes only.\u00a0For our Privacy Policy, please visit:\u00a0https://www.mufgamericas.com/candidate-privacy-policies-by-country", "employment_types": ["Full Time", "Permanent"], "selling_points": ["Multinational Bank", "Attractive benefits", "Stable environment"], "locations": ["Central"], "categories": ["Banking / Finance", "Corporate Banking", "Credit Analysis / Approval"], "post_time": "2022-01-05T07:54:21Z", "salary": {"currency": null, "max": null, "min": null, "period": null, "term": null}, "salary_visible": false, "title_keywords": ["analyst", "officer"], "responsibilities": ["regulations", "audit", "maintain", "personal data", "cooperate with", "control", "monitor", "implementation", "develop", "reports", "schedule", "banking", "management", "procedures", "contact", "documentation", "guidelines", "policies", "analysis", "recruitment"], "requirements": {"degrees": ["degree holder"], "majors": [], "languages": ["japanese", "english", "chinese"], "language_level": ["advantage", "proficient"], "hard_skills": ["documentation", "inform", "credit analysis", "analytical skills"], "soft_skills": ["responsible", "timely", "analytical skills", "attention to detail", "organisation"], "languages_combined": [{"language": "japanese", "language_level": ["advantage", "proficient"]}, {"language": "english", "language_level": ["advantage", "proficient"]}, {"language": "chinese", "language_level": ["advantage", "proficient"]}]}, "experience_required": {"duration": ["minimum of 2 years"], "field": ["relevant experience"]}}, {"job_id": "100003009034333", "location_code": "hk", "company": "Page Personnel", "job_title": "Execution Analyst - Debt Capital Markets", "description": "Perform a range of corporate functions for debt capital markets.\nHandling financial modelling and due diligence.\n\nClient Details\n\nMy client is one of the leading Chinese commercial banks with a strong presence in capital markets. They are operating under SFC Type 1,4,6,9 license. They provide a range of financial services to commercial and corporate clients and are now looking for a Junior Execution Analyst to join their IBD team.\n\nDescription\n\nResponsible for performing a wide range of corporate finance functions for debt financing business such as developing financial models and financial due diligence, preparing pitch books and presenting proposals to clients;\nProvide financial advisory to clients, and be involved in client meetings and road shows\nPerform financial analysis on various industries within Asia\nOriginate and execute proposals for Chinese clients\nDrafting documentations and presentations\n\nProfile\n\nUniversity Degree with excellent academic background, preferably with CPA or CFA qualification\nWith over 1-2 years work experience in similar capacity; work experience in credit rating agencies is highly preferred\nExcellent analytical, financial modelling, research, communication and presentation skills\nAble to work under pressure and meet tight deadlines\nAttention to details and ability to work in teams\nProficiency in MS Excel, PowerPoint and Word\nProficient in using Bloomberg and other financial information providers\nStrong written and spoken English and Chinese (Putonghua and Cantonese)\n\nJob Offer\n\n18 Annual Leave\nMPF\nMedical\nOther good benefits\n\nTo apply online please click the 'Apply' button below. For a confidential discussion about this role please contact Matt O'Shaughnessy on +852 3602 2438", "employment_types": ["Full Time", "Permanent"], "selling_points": ["High performing Chinese investment bank divison", "Junior role open to 1-2 years experience", "Attractive package and brand name"], "locations": ["Not Specified"], "categories": ["Banking / Finance", "Credit Analysis / Approval", "Corporate Finance", "Equities / Capital Markets"], "post_time": "2022-01-10T03:11:18Z", "salary": {"currency": "HKD", "max": 34999, "min": 30000, "period": "monthly", "term": null}, "salary_visible": true, "title_keywords": ["analyst"], "responsibilities": ["due diligence", "mpf", "financial models", "teams", "developing", "presentations", "financial analysis", "communication", "work under pressure"], "requirements": {"degrees": ["university degree"], "majors": [], "languages": ["cantonese", "putonghua", "english", "chinese"], "language_level": [], "hard_skills": ["bloomberg", "cfa", "word", "presentations", "powerpoint", "financial analysis", "cpa", "ms excel", "documentations"], "soft_skills": ["meet tight deadlines", "responsible", "communication", "presentation skills", "attention to details", "work under pressure"], "languages_combined": [{"language": "cantonese", "language_level": []}, {"language": "putonghua", "language_level": []}, {"language": "english", "language_level": []}, {"language": "chinese", "language_level": []}]}, "experience_required": {"duration": ["1-2 years"], "field": []}}, {"job_id": "100003009040541", "location_code": "hk", "company": "Nova Credit Limited", "job_title": "Senior Product Manager / Product Manager (Fintech)", "description": "We are looking for an experienced and passionate Senior Product Manager to join us.\n\nThe Team:\u00a0We leverage data/analytics/Fintech products to 1) provide solutions for financial institutions to help them meet the demands of today\u2019s ever-changing environment; 2) provide innovative products and services to consumers to help them better manage their credit.\n\nResponsibilities:\n\nDirectly contribute to the successful execution of the product development and go-to-market strategies of solutions that solve for the needs of our clients\nUnderstand retail banking and credit cycle\nConduct market, company and competitor research on new products\nPropose new business opportunities to form product proposition through being in touch with the industry and regulatory trends in credit industry, data/analytics businesses, Fintech development;\nWork with internal and external stakeholders to understand needs, define features, write product specifications;\nCreate product manual, training materials and commercial education to inspire clients;\nWork with marketing and sales team to increase products acceptance\n\nRequirements:\n\nBachelor degree or above\n5 or more years of experience in financial industry (banking or lending business background is advantageous)\nPassionate for creating customer-centric solutions\nA mature team player with strong presentation and communications skills\nSound Project Management mindset and skills\nProficient in Cantonese, English and Mandarin\nCandidates with demonstrated strong track record of leadership and experience will be considered for the Senior Product Manager position\n\n", "employment_types": ["Full Time", "Permanent"], "selling_points": [], "locations": ["Cheung Sha Wan"], "categories": ["Banking / Finance", "Credit Analysis / Approval", "Information Technology (IT)", "Product Management / Business Analyst", "Risk Management"], "post_time": "2022-01-12T02:45:09Z", "salary": {"currency": null, "max": null, "min": null, "period": "monthly", "term": null}, "salary_visible": false, "title_keywords": ["senior product manager", "product manager"], "responsibilities": ["data", "business opportunities", "specifications", "sales team", "banking"], "requirements": {"degrees": ["degree or above", "bachelor"], "majors": [], "languages": ["cantonese", "english", "mandarin"], "language_level": ["proficient"], "hard_skills": ["project management"], "soft_skills": ["passionate", "mature", "project management", "team player", "leadership", "presentation"], "languages_combined": [{"language": "cantonese", "language_level": ["proficient"]}, {"language": "english", "language_level": ["proficient"]}, {"language": "mandarin", "language_level": ["proficient"]}]}, "experience_required": {"duration": [], "field": ["business", "financial industry", "banking"]}}, {"job_id": "100003009035546", "location_code": "hk", "company": "E.SUN Commercial Bank, Ltd.", "job_title": "Assistant Relationship Manager - Large Corporates Team", "description": "Job Duties:\n\nPrepare financial and business analysis, case presentation and credit application reports.\nPerform account opening, KYC/ AML related work, deal execution and documentation.\nProvide good customer services to clients and handle daily operational and administration works.\n\n\u00a0Requirement:\n\nAt least 1-2 years of banking experience, preferably in corporate/commercial banking with trade finance, syndicated loans or cash management\u00a0\nBachelor Degree in Economics/Finance/Accounting or related disciplines\u00a0\nProficiency in both English and Chinese, fluency in Putonghua is an advantage\nA good team player but able to work independently\u00a0\nPositive attitude, responsible, willingness to learn\nGood communication and presentation skills.\u00a0Analytical skill of financial statement is a plus\n\nWe offer attractive remuneration package including five-day work week, double pay, medical insurance coverage, performance bonus, OT allowance, public holiday, excellent career development opportunities and others benefit package to the right candidate. Interested parties please forward your resume with current and expected salary to Human Resources Department by \"APPLY NOW\".\u00a0\n\nPlease visit our website at https://www.esunbank.com.tw/bank/corporate/overseas-branch/overseas-branch/hong-kong for more information.\u00a0\n\nAll information received will be kept strictly confidential and only for employment-related purposes.", "employment_types": ["Full Time", "Permanent"], "selling_points": ["Work under Corporate Banking Department", "Young and Energetic Working Culture", "One of the leading banks in Taiwan"], "locations": ["Tsim Sha Tsui"], "categories": ["Banking / Finance", "Corporate Banking", "Credit Analysis / Approval", "Sales, CS & Business Devpt", "Account Servicing"], "post_time": "2022-01-10T07:36:40Z", "salary": {"currency": null, "max": null, "min": null, "period": "monthly", "term": null}, "salary_visible": false, "title_keywords": ["assistant relationship manager"], "responsibilities": ["aml", "account opening", "customer services", "financial and business analysis", "reports", "kyc", "documentation", "administration"], "requirements": {"degrees": ["degree", "bachelor"], "majors": ["related disciplines", "finance", "economics", "accounting"], "languages": ["putonghua", "english", "chinese"], "language_level": ["fluency", "advantage", "proficiency"], "hard_skills": ["analytical skill", "plus"], "soft_skills": ["good team player", "work independently", "analytical skill", "responsible", "positive attitude", "communication", "presentation skills"], "languages_combined": [{"language": "putonghua", "language_level": ["fluency", "advantage"]}, {"language": "english", "language_level": ["proficiency", "fluency", "advantage"]}, {"language": "chinese", "language_level": ["proficiency", "fluency", "advantage"]}]}, "experience_required": {"duration": ["at least 1-2 years"], "field": ["management", "banking experience", "finance", "commercial", "banking"]}}, {"job_id": "100003009038554", "location_code": "hk", "company": "China CITIC Bank International Limited", "job_title": "Assistant Vice President, Medium Enterprise", "description": "Job Purpose\n\nResponsible for building relationships with ME customers and exploring new sales opportunities\n\nKey Responsibilities\n\nExplore new business opportunities of commercial banking products through different business networks and channels to achieve designated business targets\nCross-sell retail banking product to ME customers\nManage account portfolio and maintain close relationship with customers for business retention and referrals\nPrepare credit proposals by negotiation of credit terms, pricing and collateral requirements in accordance with the bank\u2019s guidelines\nIdentify and minimize credit risk within the portfolio through regular credit reviews\nMonitor loan repayment of customers; follow up and collect overdue payment\nPerform annual review of high risk / unsuitable customers timely\n\nRequirements\n\nPreferably a Degree holder or equivalent in Business or related disciplines\nMinimum 5 years of credit and marketing experience in commercial banking environment with proven record in new customer cultivation\nPreferably possess / obtain Core or Professional level of qualification under the HKMA Enhanced Competency Framework (ECF) on Credit Risk Management (CRM)\nStrong analytical mind and proactive\nGood interpersonal and people management skills\nGood command of written and spoken English and Chinese (including Putonghua)", "employment_types": ["Full Time", "Permanent"], "selling_points": ["Explore new business opportunities", "Cross-sell retail banking product to ME customers", "Min. 5 years of relevant experience"], "locations": ["Quarry Bay"], "categories": ["Banking / Finance", "Credit Analysis / Approval", "Retail Banking"], "post_time": "2022-01-11T07:19:42Z", "salary": {"currency": null, "max": null, "min": null, "period": "monthly", "term": null}, "salary_visible": false, "title_keywords": ["assistant vice president"], "responsibilities": ["explore new business opportunities", "guidelines", "review", "monitor", "payment", "maintain", "banking"], "requirements": {"degrees": ["degree holder"], "majors": ["related disciplines", "business"], "languages": ["putonghua", "english", "chinese"], "language_level": ["good command"], "hard_skills": ["hkma"], "soft_skills": ["analytical mind", "proactive", "interpersonal"], "languages_combined": [{"language": "putonghua", "language_level": ["good command"]}, {"language": "english", "language_level": ["good command"]}, {"language": "chinese", "language_level": ["good command"]}]}, "experience_required": {"duration": ["minimum 5 years"], "field": ["commercial", "marketing", "banking"]}}, {"job_id": "100003009032082", "location_code": "hk", "company": "Randstad Hong Kong Limited", "job_title": "Counterparty Credit Risk, VP/SVP - Investment Bank", "description": "about the company\n\nOur client is a prestigious foreign investment bank provides capital markets, global markets, corporate finance and securities services to institutional clients across the globe.\n\nabout the team.\n\nThe Bank promotes work-life balance and stability. You will work with colleagues from all over the world, an international and dynamic work culture.\n\nabout the job\n\nYou will:\n\nAssess credit risk associated with business propositions across the region\nFormulate and develop credit risk management policies and procedures\nPerform high quality risk assessment on counterparty risk based on financial environment and credit background of clients\nDaily control and monitoring of credit exposure against limits and parameters\nSet up the counterparty credit risk desk for other regions\nskills & experiences required\nMinimum 8 years experience in credit risk management preferable from Global Markets and Banking\nGood knowledge in equity products, fixed income and derivatives\nExcellent project management experience\nGood command of English and Chinese", "employment_types": ["Full Time", "Permanent"], "selling_points": [], "locations": ["Not Specified"], "categories": ["Banking / Finance", "Credit Analysis / Approval", "Equities / Capital Markets", "Risk Management"], "post_time": "2022-01-07T10:11:45Z", "salary": {"currency": "HKD", "max": 89999, "min": 70000, "period": "monthly", "term": null}, "salary_visible": true, "title_keywords": [], "responsibilities": ["management", "control", "policies", "monitoring", "procedures", "quality", "develop", "project management", "banking"], "requirements": {"degrees": [], "majors": [], "languages": ["english", "chinese"], "language_level": ["good command"], "hard_skills": ["project management", "dynamic"], "soft_skills": ["project management", "dynamic"], "languages_combined": [{"language": "english", "language_level": ["good command"]}, {"language": "chinese", "language_level": ["good command"]}]}, "experience_required": {"duration": ["minimum 8 years"], "field": ["project management", "management", "credit risk", "banking"]}}, {"job_id": "100003009036354", "location_code": "hk", "company": "KeeReal Consulting Limited", "job_title": "Corporate Loan - Senior Officer", "description": "Our client is a well-established MNC bank and recently seeking a flexible candidate for the Corporate Loan - Senior Officer position to join their newly expanded branch.\u00a0\n\nResponsibilities:\n\nPerform Syndication Agency function and loan administration as an officer;\u00a0\nReview structured & syndicated loan documentation drafts, and to ensure all terms and conditions are align with the bank\u2019s policy.\nTo work closely with internal and external parties for loan draw down and credit administration work;\nPerform customer due diligent (KYC);\nMonitor & follow up documentation deficiency and outstanding loan documents;\nRequirements:\n\nDegree holder or above\nSelf-motivating, flexible and can-do attitude preferred\nAt least 3 years\u2019 experience in credit process / monitoring of Corporate Banking industry\nProficient in English\u00a0", "employment_types": ["Full Time", "Permanent"], "selling_points": ["Well-established MNC bank in Asia", "At least 3 years\u2019 experience in credit monitoring", "Directly reporting to Senior Manager"], "locations": ["Central & Western Area"], "categories": ["Banking / Finance", "Corporate Banking", "Credit Analysis / Approval", "Loan"], "post_time": "2022-01-10T16:27:23Z", "salary": {"currency": null, "max": null, "min": null, "period": "monthly", "term": null}, "salary_visible": false, "title_keywords": ["senior officer"], "responsibilities": ["syndicated loan documentation", "review", "internal and external parties", "monitor", "kyc", "documentation", "administration"], "requirements": {"degrees": ["degree holder"], "majors": [], "languages": ["english"], "language_level": ["proficient"], "hard_skills": [], "soft_skills": ["flexible", "can-do attitude"], "languages_combined": [{"language": "english", "language_level": ["proficient"]}]}, "experience_required": {"duration": ["at least 3 years"], "field": ["banking industry"]}}, {"job_id": "100003009033659", "location_code": "hk", "company": "Bank of Communications (Hong Kong) Limited", "job_title": "Officer, Settlement (Credit Card)", "description": "Responsible for processing daily settlement operations for Credit Card & CUP Card\nReview and formulate internal operation policies and procedures, as well as participate in different ad hoc assignments relating to system enhancement\nReports preparation for internal and external parties\nDegree holder or above with minimum 2 years\u2019 relevant experience, preferably with financial analysis experience\nKnowledge in credit card system like Cardpac & Vision Plus\nKnowledge in Access or VBA is an advantage\nGood interpersonal skills and ability to work under pressure\nGood command of written and spoken English, Chinese and Putonghua\nCandidates with more experience will be considered as Assistant Manager, Settlement\n\nWe offer attractive remuneration package to the right candidates. Please send your full resume with expected salary to The Human Resources Manager, Bank of Communications Co., Ltd., 10/F, Bank of Communications Tower, 231-235 Gloucester Road, Wan Chai, Hong Kong, or fax to 2838 9209, or e-mail by clicking \"Apply Now\".\n\nAll personal data of unsuccessful applicants will be destroyed after the recruitment exercise.", "employment_types": ["Full Time"], "selling_points": ["Reports preparation for internal and external part", "Knowledge in Access or VBA is an advantage", "2 years\u2019 relevant experience"], "locations": ["Not Specified"], "categories": ["Banking / Finance", "Credit Analysis / Approval", "Order Processing & Operation / Settlement"], "post_time": "2022-01-10T01:30:47Z", "salary": {"currency": null, "max": null, "min": null, "period": null, "term": null}, "salary_visible": false, "title_keywords": ["officer"], "responsibilities": ["operations", "policies", "review", "procedures", "internal and external parties", "financial analysis", "reports", "ad hoc assignments", "work under pressure"], "requirements": {"degrees": ["degree holder"], "majors": [], "languages": ["putonghua", "english", "chinese"], "language_level": ["good command"], "hard_skills": ["financial analysis", "vba", "plus", "processing"], "soft_skills": ["interpersonal skills", "responsible", "work under pressure"], "languages_combined": [{"language": "putonghua", "language_level": ["good command"]}, {"language": "english", "language_level": ["good command"]}, {"language": "chinese", "language_level": ["good command"]}]}, "experience_required": {"duration": ["minimum 2 years"], "field": ["relevant experience", "financial"]}}, {"job_id": "100003009028253", "location_code": "hk", "company": "Dah Sing Financial Group", "job_title": "Senior Manager, Credit", "description": "Reporting to the Head of Commercial Credit Approval, you will be responsible for providing an independent assessment of credit proposals originated from the bank\u2019s Commercial Banking Division, ensuring that they adhere to regulatory and policy guidelines and meet the bank\u2019s credit standards, before approving or supporting to higher levels for approval. You will also be responsible for post-approval monitoring of the relevant client portfolio and other credit-related duties.\nTo meet the challenge, you should have the following qualifications and attributes:\nDegree holder with minimum 8 years of credit related experience in commercial banking\nSelf-motivated and independent with an analytical mindset\nComfortable to deal with details\nGood credit assessment skill, with sound knowledge in commercial banking loan products and proficiency in analyzing complex groups\nGood verbal and written communication skills, and good team player\nPlease note that only shortlisted candidates will be notified.", "employment_types": ["Permanent"], "selling_points": ["Providing an independent assessment of credit", "Degree holder", "8 years of credit related experience"], "locations": ["North Point"], "categories": ["Banking / Finance", "Credit Analysis / Approval", "Others", "Credit Collection"], "post_time": "2022-01-07T01:53:55Z", "salary": {"currency": null, "max": null, "min": null, "period": "monthly", "term": null}, "salary_visible": false, "title_keywords": ["senior manager"], "responsibilities": ["reporting", "guidelines", "monitoring", "communication", "banking"], "requirements": {"degrees": ["degree holder"], "majors": [], "languages": [], "language_level": [], "hard_skills": ["loan products"], "soft_skills": ["communication skills", "self-motivated", "good team player", "independent", "responsible"], "languages_combined": []}, "experience_required": {"duration": ["minimum 8 years"], "field": ["related", "commercial", "banking"]}}, {"job_id": "100003009039482", "location_code": "hk", "company": "Taishin International Bank Co Ltd", "job_title": "\u52a9\u7406\u5ba2\u6236\u95dc\u4fc2\u7d93\u7406(Assistant Relationship Manager- Corporate Banking)", "description": "\u5de5\u4f5c\u8077\u8cac\uff1a\n\n\u64b0\u5beb\u4f01\u696d\u5ba2\u6236\u5fb5\u3001\u6388\u4fe1\u5831\u544a(\u542b\u8ca1\u52d9\u5831\u8868\u5206\u6790)\u53ca\u76f8\u95dc\u8cc7\u6599\u6536\u96c6\u3002\n\u64a5\u6b3e\u53ca\u5404\u9805\u4ea4\u6613\u4f5c\u696d\u8655\u7406\u3002\n\u638c\u63e1\u5ba2\u6236\u4e4b\u7d93\u71df\u72c0\u6cc1\u53ca\u5404\u9805\u8ca1\u52d9\u6bd4\u7387\u8b8a\u5316\uff0c\u4ee5\u63a7\u5236\u6388\u4fe1\u98a8\u96aa\u3002\n\u5354\u52a9RM(Relationship Manager)\u958b\u767c\u6f5b\u5728\u5ba2\u6236\uff0c\u4e26\u9069\u6642\u63a8\u52d5\u5404\u9805\u65b0\u7522\u54c1\u4e4b\u92b7\u552e\u696d\u52d9\u3002\n\u63d0\u4f9b\u5ba2\u6236\u554f\u984c\u89e3\u6c7a\u8aee\u8a62\u670d\u52d9\u53ca\u7dad\u8b77\u95dc\u4fc2\u3002\n\n\n\u8077\u4f4d\u8981\u6c42\uff1a\n\n\u5927\u5b78\u7562\u696d\n2\u5e74\u4ee5\u4e0a\u5de5\u4f5c\u7d93\u9a57\u53ca\u5177\u6703\u8a08\u5831\u8868\u5206\u6790\u57fa\u672c\u80fd\u529b\n\u64cd\u6d41\u5229\u666e\u901a\u8a71\n\u4e3b\u52d5\u7a4d\u6975\uff0c\u5177\u4f01\u5716\u5fc3\uff0c\u6e9d\u901a\u80fd\u529b\u826f\u597d\uff0c\u80fd\u914d\u5408\u5de5\u4f5c\u9700\u6c42\u51fa\u5dee", "employment_types": ["Full Time", "Permanent"], "selling_points": ["\u5927\u5b78\u7562\u696d", "2\u5e74\u4ee5\u4e0a\u5de5\u4f5c\u7d93\u9a57\u53ca\u5177\u6703\u8a08\u5831\u8868\u5206\u6790\u57fa\u672c\u80fd\u529b", "\u64cd\u6d41\u5229\u666e\u901a\u8a71\u3002 \u4e3b\u52d5\u7a4d\u6975\uff0c\u5177\u4f01\u5716\u5fc3\uff0c\u6e9d\u901a\u80fd\u529b\u826f\u597d\uff0c\u80fd\u914d\u5408\u5de5\u4f5c\u9700\u6c42\u51fa\u5dee"], "locations": ["Yau Tsim Mong Area"], "categories": ["Banking / Finance", "Corporate Banking", "Credit Analysis / Approval", "Financial Services"], "post_time": "2022-01-11T09:54:42Z", "salary": {"currency": null, "max": null, "min": null, "period": "monthly", "term": null}, "salary_visible": false, "title_keywords": ["relationship manager"], "responsibilities": [], "requirements": {"degrees": [], "majors": [], "languages": [], "language_level": [], "hard_skills": [], "soft_skills": [], "languages_combined": []}, "experience_required": {"duration": [], "field": []}}, {"job_id": "100003009032511", "location_code": "hk", "company": "\u5fc5\u9ad8\u4eba\u4e8b\u9867\u554f\u6709\u9650\u516c\u53f8", "job_title": "Credit Loan Officer (Personal loan/ Mortgage loan/ Consumer loan - Multiple roles)", "description": "Our clients are global bank corporations who are looking for loan officers, we are working for multiple roles, if you would like to advance your career and join in a promising company, please apply for the following:\n\nJob responsibilities:\n\n\n\u200bHandle loan application processing, including loan drawdown & disbursement\nCommunicate with customer on loan offering and any other outstanding issues\nProvide administrative support and assist in all operational matters\nAnalyze credit proposals of auto and equipment financing and Mortgage loan\nConduct annual reviews on existing customers' portfolios\nPrepare credit analysis report for management\u2019s approval\nHandle customer enquiries\nPerform ad hoc task as assigned\nJob requirements:\n\nHigher Diploma or above\nMinimum 2 years\u2019 relevant experience in financial industry\nAble to work under pressure and independently\nGood interpersonal and communication skills\nGood PC skills, fast and accurate typing\nProficient in writing and speaking in Cantonese, English and Mandarin\nInterested parties please forward your CV in word format with current and expected salaries to\u00a0PICCO Bent Consultancy Limited.\u00a0\n[All applications will be treated with strict confidential and will be used for recruitment purposes only]\n", "employment_types": ["Full Time"], "selling_points": ["Money lender; loan; personal loan; bank; sales", "mortgage; customer service; clients; drawdown;", "lending; credit analysis; credit proposal; finance"], "locations": ["Central"], "categories": ["Banking / Finance", "Credit Analysis / Approval", "Loan", "Mortgage"], "post_time": "2022-01-07T11:22:33Z", "salary": {"currency": null, "max": null, "min": null, "period": "monthly", "term": null}, "salary_visible": false, "title_keywords": ["officer", "personal"], "responsibilities": ["communicate with", "management", "handle customer enquiries", "ad hoc", "analysis report", "provide administrative support", "operational matters"], "requirements": {"degrees": ["higher diploma or above"], "majors": [], "languages": ["cantonese", "english", "mandarin"], "language_level": ["proficient"], "hard_skills": ["pc skills", "typing"], "soft_skills": ["communication skills", "independently", "accurate", "interpersonal", "work under pressure"], "languages_combined": [{"language": "cantonese", "language_level": ["proficient"]}, {"language": "english", "language_level": ["proficient"]}, {"language": "mandarin", "language_level": ["proficient"]}]}, "experience_required": {"duration": ["minimum 2 years"], "field": ["financial industry", "relevant experience"]}}, {"job_id": "100003009038727", "location_code": "hk", "company": "China Construction Bank (Asia) Corporation Limited", "job_title": "Relationship Manager, Commercial Banking (Ref no: SRM/CMB/JDB)", "description": "Job Descriptions:\n\nManage a portfolio of commercial clients who need financial services and customized products to meet their financial needs\nProspect and generate new business by focusing on enhancing existing relationships, and identifying opportunities for uptiering\nInterview prospective clients to collect information concerning their business needs, desires, abilities, and earnings to determine the business opportunities\nUse analytical skills and knowledge of credit policies required to evaluate the financial condition of the clients, make credit recommendations for Management\u2019s approval\n\nRequirements:\n\nDegree holder in Business, Economics or related disciplines is preferred\nMinimum 5 years of banking experience in trade financing and commercial banking;\u00a0\n\nQualifications in IIQE/HKSI related areas are preferred\n\nKnowledge of the principles of commercial credit and lending policies and standards\nStrong business development skills and proficiency in the financial services/products offered to middle market companies\nGood communication skills in both English and Chinese (Cantonese & Putonghua)\n* Candidates with less experience will be considered as Relationship Manager.\n\n\nTo apply, please send the detailed resume to the designated email address or by fax at 3718 2910.\n\nApplicants who are not contacted within 8 weeks may consider their applications unsuccessful and their personal data will be retained by the bank for a period up to two years.\n\nAll information provided by applicants will be used for recruitment purposes only and will be used strictly in accordance with the bank\u2019s personal data policies, a copy of which will be provided upon request.", "employment_types": ["Full Time", "Permanent"], "selling_points": ["Medium-Sized Enterprises / List Co.", "Portfolio management & new business generation", "Bachelor degree with min. 5 yrs of RM experience"], "locations": ["Kowloon Bay"], "categories": ["Banking / Finance", "Corporate Banking", "Credit Analysis / Approval", "Sales, CS & Business Devpt", "Business Development"], "post_time": "2022-01-11T07:41:23Z", "salary": {"currency": null, "max": null, "min": null, "period": "monthly", "term": null}, "salary_visible": false, "title_keywords": ["relationship manager"], "responsibilities": ["evaluate", "policies", "business opportunities", "management"], "requirements": {"degrees": ["degree holder"], "majors": ["related disciplines", "economics", "business"], "languages": ["cantonese", "putonghua", "english", "chinese"], "language_level": ["good"], "hard_skills": ["iiqe", "hksi"], "soft_skills": ["communication skills", "detailed"], "languages_combined": [{"language": "cantonese", "language_level": ["good"]}, {"language": "putonghua", "language_level": ["good"]}, {"language": "english", "language_level": ["good"]}, {"language": "chinese", "language_level": ["good"]}]}, "experience_required": {"duration": ["minimum 5 years"], "field": ["commercial", "financing", "banking experience", "banking"]}}, {"job_id": "100003009027226", "location_code": "hk", "company": "DBS Bank Ltd", "job_title": "VP, Specialist, Credit Risk Management, SME Banking", "description": "Career Level\nEntry Level\nQualification\nDegree\nYears of Experience\n1 year\nJob Type\nFull Time, Permanent\nJob Functions\nBanking / Finance, Private Banking, Others", "employment_types": ["Full Time"], "selling_points": ["Pension Fund Scheme", "Medical Coverage for Family", "Flexible Working Arrangement"], "locations": ["Others"], "categories": ["Accounting", "Credit Control", "Banking / Finance", "Credit Analysis / Approval", "Credit Collection"], "post_time": "2022-01-06T09:25:41Z", "salary": {"currency": null, "max": null, "min": null, "period": "monthly", "term": null}, "salary_visible": false, "title_keywords": ["specialist", "credit risk management"], "responsibilities": ["banking"], "requirements": {"degrees": ["degree"], "majors": [], "languages": [], "language_level": [], "hard_skills": [], "soft_skills": [], "languages_combined": []}, "experience_required": {"duration": [], "field": []}}, {"job_id": "100003009026827", "location_code": "hk", "company": "Bangkok Bank Public Co Ltd", "job_title": "Assistant Credit Manager (Ref: CAU-08/166/240-DB)", "description": "Responsible for processing daily settlement operations for Credit Card & CUP Card\nReview and formulate internal operation policies and procedures, as well as participate in different ad hoc assignments relating to system enhancement\nReports preparation for internal and external parties\nDegree holder or above with minimum 2 years\u2019 relevant experience, preferably with financial analysis experience\nKnowledge in credit card system like Cardpac & Vision Plus\nKnowledge in Access or VBA is an advantage\nGood interpersonal skills and ability to work under pressure\nGood command of written and spoken English, Chinese and Putonghua\nCandidates with more experience will be considered as Assistant Manager, Settlement\n\nWe offer attractive remuneration package to the right candidates. Please send your full resume with expected salary to The Human Resources Manager, Bank of Communications Co., Ltd., 10/F, Bank of Communications Tower, 231-235 Gloucester Road, Wan Chai, Hong Kong, or fax to 2838 9209, or e-mail by clicking \"Apply Now\".\n\nAll personal data of unsuccessful applicants will be destroyed after the recruitment exercise.", "employment_types": ["Full Time"], "selling_points": [], "locations": ["Central"], "categories": ["Banking / Finance", "Corporate Banking", "Credit Analysis / Approval", "Others"], "post_time": "2022-01-06T08:44:23Z", "salary": {"currency": null, "max": null, "min": null, "period": "monthly", "term": null}, "salary_visible": false, "title_keywords": ["manager", "assistant"], "responsibilities": ["operations", "policies", "review", "procedures", "internal and external parties", "financial analysis", "reports", "ad hoc assignments", "work under pressure"], "requirements": {"degrees": ["degree holder"], "majors": [], "languages": ["putonghua", "english", "chinese"], "language_level": ["good command"], "hard_skills": ["financial analysis", "vba", "plus", "processing"], "soft_skills": ["interpersonal skills", "responsible", "work under pressure"], "languages_combined": [{"language": "putonghua", "language_level": ["good command"]}, {"language": "english", "language_level": ["good command"]}, {"language": "chinese", "language_level": ["good command"]}]}, "experience_required": {"duration": ["minimum 2 years"], "field": ["relevant experience", "financial"]}}, {"job_id": "100003009024170", "location_code": "hk", "company": "Ambition", "job_title": "Relationship Manager - Commercial Banking", "description": "Responsibilities:\n\nDevelop and manage a corporate client portfolio by providing financial solutions and cross-selling suitable products/services\nSolicit new-to-bank clients to expand the bank's clients portfolio\nTo develop and maintain relationships with corporate customers and financial institutions\nProvide quality and value-added services to clients for cultivating a long-term business relationship\nPrepare comprehensive credit proposals and reviews for assessing customers' credit worthiness and react to market changes from time to time\n\nRequirements\n\nDegree holder or equivalent\nMinimum 2 years' experience in mortgage loan sales\nCommitted and self-motivated with positive attitude and can work independently\nExcellent selling technique and customer service skills\nA good team player and be able to work under pressure\nProficient in both written and spoken English and Chinese\n\nContact Winnie Cheung on (852) 3103 4369/ winnie.cheung@ambition.com.hk quoting reference number or APPLY NOW here\nhttp://www.ambition.com.hk\nData provided is for recruitment purposes only\n\nIf this job isn't quite right for you, but you know someone who would be great at this role, why not take advantage of our referral scheme? We offer HKD1000 in Apple gift cards for every referred candidate who we place in a role. Terms & Conditions Apply. https://www.ambition.com.hk/refer-a-friend", "employment_types": ["Full Time", "Permanent"], "selling_points": ["Attractive salary package & quarterly commission", "Provide banking service to high-net-worth", "Wealth Management Products & Services"], "locations": ["Not Specified"], "categories": ["Banking / Finance", "Credit Analysis / Approval", "Loan", "Retail Banking"], "post_time": "2022-01-05T11:03:20Z", "salary": {"currency": null, "max": null, "min": null, "period": "monthly", "term": null}, "salary_visible": false, "title_keywords": ["relationship manager"], "responsibilities": ["maintain relationships", "quality", "develop"], "requirements": {"degrees": ["degree holder"], "majors": [], "languages": ["english", "chinese"], "language_level": ["proficient"], "hard_skills": ["scheme"], "soft_skills": ["customer service skills", "self-motivated", "work independently", "good team player", "positive attitude", "committed", "work under pressure"], "languages_combined": [{"language": "english", "language_level": ["proficient"]}, {"language": "chinese", "language_level": ["proficient"]}]}, "experience_required": {"duration": ["minimum 2 years"], "field": []}}, {"job_id": "100003009028384", "location_code": "hk", "company": "BDO Financial Services Limited", "job_title": "System Analyst / Analyst Programmer (MNC Professional Service Firm)", "description": "Job Description:\n\nOur client is a MNC Global Information and insights company. To support their growth, they are looking for System Analyst/Analyst Programmer to join their team.\n\nJob Duties:\n\nWork closely with the Product and Sales team to explore the market demand, and transform it into application service\nParticipate / lead in the entire System Development Life Cycle (SDLC) for project delivery and system support tasks\nProvide technical advice to the team regarding system development/enhancement\nAnalyze, evaluate, modify new/existing programs and systems\nHandle any ad hoc tasks assigned by management\n\nRequirements:\n\nDegree in Computer Science, Engineering or other related discipline\nAt least 4 years application development experience or above\nExperience in C/C++, JAVA, Perl and Linux Shell Scripts\nUnderstanding of architectures such as micro-services, API first design\nRDBMS (Informix / DB2 / Oracle / PostgreSQL) experience is essential, NoSQL is plus\nHands on in automation and collaboration tools building such as Jenkins/Artifactory/Maven/Sonarqube is plus\nGood to have experience with Spring Framework, Hibernate, AWS, Docker/Kubernetes, Kafka and Redis\nSelf-starter who is also willing to learn\nGood in written and spoken English and Cantonese\n\nInterested parties please send your application with full career history, current and expected salary by clicking Apply Now button. Applications will be treated in strict confidence. Personal data collected will be used for recruitment purposes only.", "employment_types": ["Full Time", "Contract"], "selling_points": ["MNC Exposure", "C/C++, Java, Perl & Linux Shell Scripts", "RDBMS (Informix/DB2/Oracle/PostgreSQL)"], "locations": ["Tsim Sha Tsui"], "categories": ["Banking / Finance", "Credit Analysis / Approval", "Information Technology (IT)", "Application Specialist - Software", "Software Development"], "post_time": "2022-01-07T02:10:27Z", "salary": {"currency": null, "max": null, "min": null, "period": "monthly", "term": null}, "salary_visible": false, "title_keywords": ["analyst programmer", "system analyst"], "responsibilities": ["management", "technical advice", "systems", "ad hoc tasks", "evaluate", "sales team"], "requirements": {"degrees": ["degree"], "majors": ["engineering", "computer science"], "languages": ["cantonese", "english"], "language_level": ["good"], "hard_skills": ["linux", "java", "informix", "oracle", "plus", "c++", "jenkins", "hibernate", "aws", "c", "spring", "perl"], "soft_skills": ["hands on", "willing to learn"], "languages_combined": [{"language": "cantonese", "language_level": ["good"]}, {"language": "english", "language_level": ["good"]}]}, "experience_required": {"duration": ["at least 4 years"], "field": ["application development"]}}, {"job_id": "100003009012557", "location_code": "hk", "company": "China Everbright Bank Company Limited", "job_title": "Assistant Relationship Manager, Corporate Banking", "description": "Key Responsibilities\n\nImplement effective internal controls to ensure daily activities of Treasury traders and marketers are in compliance to regulators\u2019 guidelines and the Bank\u2019s internal procedures.\nWork with internal parties to review and update on Treasury related workflows, procedures and guidelines.\nNegotiate, review and execute master agreements, including but not limited to ISDA Schedule, CSA, GMRA, with financial institutions and corporate clients.\nLead in template development and work with internal legal & compliance and external legal counsel to facilitate business needs.\nParticipate in projects or discussion where amendments of contracts/agreements are necessary.\nRequirements\u00a0\n\n\nDegree holder in Law, Business, Economics,\u00a0 Finance or related discipline.\nMinimum 5 years related experience in banking industry. Experience in negotiating global markets documentation and ISDA Master Agreements is preferred.\nSound knowledge in treasury products and related regulatory guidelines and familiar with ISDA definitions and their developments.\nGood interpersonal and communication skills.\nGood command of written and spoken English and Chinese (including Putonghua).\n\nFor more details about career opportunities with the Bank, please visit our website http://www.cncbinternational.com/careers/en/index.jsp. Please apply with full resume stating current and expected salaries.\nPersonal data collected will be used for recruitment related purposes only. Applicants not invited for interview within 6 weeks may consider their applications unsuccessful. However, applicants may be considered for other suitable positions within the Group for a period of not more than 2 years. Personal data will be destroyed at any time after 3 months.\nChina CITIC Bank International is committed to being an equal opportunities employer and intends to provide a work environment free of unlawful discrimination or harassment. All employment decisions will be made in a non-discriminatory manner.", "employment_types": ["Full Time", "Permanent"], "selling_points": ["Assist RM in managing corporate client portfolio", "Perform credit analysis", "Minimum 5 years of relevant experience"], "locations": ["Admiralty"], "categories": ["Banking / Finance", "Corporate Banking", "Credit Analysis / Approval", "Financial Services"], "post_time": "2022-01-01T02:41:19Z", "salary": {"currency": null, "max": null, "min": null, "period": "monthly", "term": null}, "salary_visible": false, "title_keywords": ["assistant relationship manager"], "responsibilities": ["guidelines", "contracts", "review", "compliance", "procedures", "schedule", "internal parties"], "requirements": {"degrees": ["master", "degree holder"], "majors": ["finance", "economics", "business", "law"], "languages": ["putonghua", "english", "chinese"], "language_level": ["good command"], "hard_skills": ["documentation"], "soft_skills": ["communication skills", "committed", "interpersonal"], "languages_combined": [{"language": "putonghua", "language_level": ["good command"]}, {"language": "english", "language_level": ["good command"]}, {"language": "chinese", "language_level": ["good command"]}]}, "experience_required": {"duration": ["minimum 5 years"], "field": ["related", "banking industry"]}}, {"job_id": "100003009011695", "location_code": "hk", "company": "Industrial and Commercial Bank of China (Asia) Limited", "job_title": "Fixed Income Researcher, Hong Kong Treasury Centre - Hong Kong Branch", "description": "Job Descriptions\n\n\nMonitor and analyze the global economy and financial markets consistently, collect\u00a0data as required to provide support for daily transactions\nLearn relevant research methods and assist the team in conducting credit analysis and market analysis\nWrite commentaries and forecast on the economy and financial markets and make recommendation on investment strategies for our department and the top management\nCooperate with the team to carry out research work on related topics\nRequirements\nBachelor degree or above in Economics, Finance or related disciplines\n1- 2 years\u2019 experience in credit analysis or credit risk management is preferred\nCFA / FRM\u00a0 qualifications will be an advantage\nGood understanding of global economics and financial markets\nIndependent and excellent report writing skills in both Chinese and English\nSelf-motivated with strong communication, interpersonal skills\nProficient to advanced skills with MS Office (Excel, PowerPoint, Word), familiarity with Bloomberg is preferred\nApplicants might attach past research samples while submitting job applications\n\nPersonal data collected will be used for recruitment purpose only", "employment_types": ["Full Time", "Permanent"], "selling_points": [], "locations": ["Central & Western Area"], "categories": ["Banking / Finance", "Analyst", "Credit Analysis / Approval", "Treasury"], "post_time": "2021-12-31T08:06:05Z", "salary": {"currency": null, "max": null, "min": null, "period": null, "term": null}, "salary_visible": false, "title_keywords": ["researcher"], "responsibilities": ["provide support", "investment strategies", "make recommendation", "management", "data", "analysis", "monitor", "transactions", "market analysis", "forecast", "cooperate with"], "requirements": {"degrees": ["degree or above", "bachelor"], "majors": ["related disciplines", "finance", "economics"], "languages": ["english", "chinese"], "language_level": ["excellent"], "hard_skills": ["excel", "bloomberg", "cfa", "word", "writing skills", "powerpoint", "credit analysis", "frm", "ms office"], "soft_skills": ["self-motivated", "independent", "advanced", "writing skills", "communication", "interpersonal skills"], "languages_combined": [{"language": "english", "language_level": ["excellent"]}, {"language": "chinese", "language_level": ["excellent"]}]}, "experience_required": {"duration": ["1- 2 years"], "field": ["management", "credit risk"]}}, {"job_id": "100003009014653", "location_code": "hk", "company": "Randstad Hong Kong Limited", "job_title": "Relationship Manager - Bank FIG", "description": "about the company.\n\nThis well-known regional bank is looking for well-focused Relationship Managers to join their institutional banking team to manage and grow their customer portfolio.With a strong growth plan and the vision to become a better leader in its field, it continues to gain market share over its competitor within APAC region\n\nabout the team.\n\nJoin this team with heavy emphasis of team work and stable career progressionn. Rich cultural dynamics and opportunity to work with regional offices. Client facing and qualitiy suggestions on business strategies will be expected to help the team move forward.\n\nabout the job.\n\nAs a influential member of the team, you will cover all aspects in supporting institutional banking departments and preparing credit proposals. Client relationship management and business strategy will be expected. Apart from serving a designated portfolio of accounts in Institutional Banking Business segment, you will also be supporting senior relationships managers in acquiring business by conducting market research, constructing business development ideas, etc.\n\nskills & experiences required.\n\nYour previous experience as a Relationship Manager within Institutional Banking will help you succeed in this role. You will have 3+ years of experience in Global / Instituional Banking. You will also be familiar with business stratgy research, market analsysis. You will be a team player in achieving team targets and also detail minded in conducting in-depth financial and credit assessment within credit policy and parameters of the bank. Due to the targeted client segment, you will be required to speak Mandarin, Cantonese and English on a daily basis.\n\nIf you're interested in this role, click 'apply now' or for more information and a confidential discussion on this role or to find out more opportunities in Corporate / Institutional Banking contact Yetta Chan at +852 2232 3415 or email yetta.chan@randstad.com.hk", "employment_types": ["Full Time", "Permanent"], "selling_points": [], "locations": ["Not Specified"], "categories": ["Banking / Finance", "Corporate Banking", "Credit Analysis / Approval"], "post_time": "2022-01-03T03:55:53Z", "salary": {"currency": null, "max": null, "min": null, "period": "monthly", "term": null}, "salary_visible": false, "title_keywords": ["relationship manager"], "responsibilities": ["management", "ideas", "market research", "contact", "plan", "banking"], "requirements": {"degrees": [], "majors": [], "languages": ["cantonese", "english", "mandarin"], "language_level": [], "hard_skills": [], "soft_skills": ["focused", "interested in", "influential", "team player", "stable"], "languages_combined": [{"language": "cantonese", "language_level": []}, {"language": "english", "language_level": []}, {"language": "mandarin", "language_level": []}]}, "experience_required": {"duration": ["3+ years"], "field": ["banking"]}}, {"job_id": "100003009001363", "location_code": "hk", "company": "Dah Sing Financial Group", "job_title": "Manager, Credit", "description": "Job Purpose:\nReview, analyze and approve credit applications; approve credit excesses and irregularities; take up credit-related projects\nKey Role and Responsibilities:\nApprove credit applications within the delegated lending authority\nAnalyze and review credit applications beyond the delegated authority for higher authority level\nMonitor compliance with credit policies and guidelines\nApprove credit excesses and irregularities within the delegated lending authority\nIdentify potential problem loan situation and, if necessary, working with relationship manager to take early remedial actions including loan/credit restructuring\nTake up credit-related projects\nJob Requirements:\nUniversity degree or above with major in Banking, Business Administration, Finance, Economics, Accountancy or related discipline\nMinimum 4 year\u2019s credit experience in corporate banking\nKnowledge of corporate banking products including trade finance\nKnowledge of relevant regulatory requirements\nGood knowledge in accounting principles and financial statement analysis\nGood analytical, communication and interpersonal skills\nPlease note that only shortlisted candidates will be notified.", "employment_types": ["Permanent"], "selling_points": ["Review, analyze and approve credit applications", "University degree or above with major in Banking", "Minimum 4 year\u2019s credit experience"], "locations": ["North Point"], "categories": ["Banking / Finance", "Corporate Banking", "Credit Analysis / Approval", "Others"], "post_time": "2021-12-28T02:21:33Z", "salary": {"currency": null, "max": null, "min": null, "period": "monthly", "term": null}, "salary_visible": false, "title_keywords": ["manager"], "responsibilities": ["irregularities", "guidelines", "policies", "compliance", "review", "monitor"], "requirements": {"degrees": ["degree or above"], "majors": ["finance", "economics", "business administration", "accountancy"], "languages": [], "language_level": [], "hard_skills": ["analysis"], "soft_skills": ["communication and interpersonal skills"], "languages_combined": []}, "experience_required": {"duration": ["minimum 4 year"], "field": ["banking"]}}, {"job_id": "100003009001762", "location_code": "hk", "company": "Hang Seng Bank Ltd", "job_title": "Assistant Business and Credit Control Manager", "description": "Global Banking Division \u2013 Financial Institutions Group\n\nHang Seng's Global Banking business provides a broad spectrum of financing solutions to large corporations and financial institutions. As a strategic financial partner to corporate customers, Hang Seng offers a comprehensive range of products and services including bilateral and syndication loans, project financing, property development financing, property investment loans, working capital financing, trade financing, cash management and treasury products. Our experienced and knowledgeable professionals understand the specific requirements of our customers and are committed to providing tailor-made financial packages in their best interests.\n\nWe are currently seeking a high caliber professional to join our department as\u00a0Assistant\u00a0Business and\u00a0Credit Control\u00a0Manager.\nPrincipal responsibilities\nTo support the business and credit control of the department with particular focus on the following aspects:\nMonitor credit limit utilization to ensure that irregularities are properly controlled;\nSupport team head to implement compliance policy and procedures to ensure the business and systems are compliant;\nPrepare various reports as required by the Group / regulatory authorities as well as review the credit procedures and control measures to ensure compliance with the Bank\u2019s credit policy;\nParticipate in the development, maintenance and enhancement of management information system as well as other ad hoc projects;\nOversee the general administrative function of the department\nRequirements\nUniversity degree in Business Administration, Finance, Accounting OR other relevant professional qualifications;\nMinimum of two years' relevant experience in credit control, risk management, accounting or management information system;\nSound knowledge of application software;\nStrong numerical aptitude, with good communication and analytical skills;\nProficiency in both English and Chinese;\nGreat sense of ownership and servicing mindset to ensure efficient and effective customer service processes\nIf you would like to explore other opportunities at Hang Seng Hong Kong, please visit\u00a0www.hangseng.com/careers/\u00a0for details.\n\nThe health and safety of our employees and candidates is very important to us. Due to the current situation related to the Novel Coronavirus (2019-nCoV), we're leveraging our digital capabilities to ensure we can continue to recruit top talent at the HSBC Group. As your application progresses, you may be asked to use one of our digital tools to help you through your recruitment journey. If so, one of our Resourcing colleagues will explain how our video interviewing technology will be used throughout the recruitment process and will be on hand to answer any questions you might have.\n\nAll information provided by applicants will be used only for recruitment purposes and will be used strictly in accordance with the Bank's personal data policies, a copy of which may be obtained by the applicant upon request. Unless otherwise instructed in writing by the applicant concerned, applicants may be considered for other suitable positions within the Bank and its related companies. The personal data of unsuccessful job applicants may be retained for a maximum of two years from the date when the job application is rejected and such data may be retained for a longer period if there is a subsisting reason that obliges the Bank to do so, after which the personal data will be destroyed.", "employment_types": ["Full Time", "Permanent"], "selling_points": [], "locations": ["Not Specified"], "categories": ["Banking / Finance", "Corporate Banking", "Credit Analysis / Approval"], "post_time": "2021-12-28T02:59:09Z", "salary": {"currency": null, "max": null, "min": null, "period": "monthly", "term": null}, "salary_visible": false, "title_keywords": ["manager", "assistant"], "responsibilities": ["control", "management", "irregularities", "maintenance", "compliance", "monitor", "procedures", "systems", "review", "ensure compliance", "reports", "ad hoc projects"], "requirements": {"degrees": ["university degree"], "majors": ["finance", "accounting", "business administration"], "languages": ["english", "chinese"], "language_level": ["proficiency"], "hard_skills": ["reason", "information system", "analytical skills", "professional qualifications"], "soft_skills": ["efficient", "analytical skills", "communication", "customer service", "novel"], "languages_combined": [{"language": "english", "language_level": ["proficiency"]}, {"language": "chinese", "language_level": ["proficiency"]}]}, "experience_required": {"duration": ["minimum of two years"], "field": ["risk management", "management", "accounting", "relevant experience"]}}, {"job_id": "100003009006790", "location_code": "hk", "company": "Hays", "job_title": "Deputy Department Head of Retail Credit, Chinese Bank", "description": "Your new company\nOne of the Top Tier Chinese Retail and Corporate Banks, covering products ranging from retail lending, corporate loans, M&A, project financing and other capital market products;\nSteadily expanding in Hong Kong and Asia as well as globally;\n\nYour new role\n\nReport directly to Department Head of Retail Credit, you will manage credit approval and credit policy team under retail credit risk function;\nResponsible for managerial role, maintain the smooth process of retail credit business;\nEnsure credit monitoring, early warming systems are in place;\nSupport on-going system enhancement for efficient approval process.\n\n\nWhat you'll need to succeed\n\n15+ years retail credit (approval, policy, portfolio management or collections) experience in reputable bank covering Retail Credit or Commercial Credit;\nSolid people management experience;\nFluent in Chinese and English\n\n\nWhat you'll get in return\n\nRare Vacancy\nCompetitive salary and high annual discretionary bonus\nManagerial role\n\n\nWhat you need to do now\nIf you're interested in this role, click 'apply now' or for further information and a confidential discussion on this role or to find out about more opportunities in Corporate Banking Credit contact Isis Yu at Hays on +852 2230 7981 or email isis.yu@hays.com.hk", "employment_types": ["Full Time", "Permanent"], "selling_points": ["Rare Vacancy", "Competitive salary and discretionary bonus", "Managerial role"], "locations": ["Not Specified"], "categories": ["Banking / Finance", "Credit Analysis / Approval", "Credit Collection", "Risk Management"], "post_time": "2021-12-29T10:28:08Z", "salary": {"currency": null, "max": null, "min": null, "period": "monthly", "term": null}, "salary_visible": false, "title_keywords": ["department head"], "responsibilities": ["management", "monitoring", "systems", "maintain", "contact", "banking", "report"], "requirements": {"degrees": [], "majors": [], "languages": ["english", "chinese"], "language_level": ["fluent"], "hard_skills": [], "soft_skills": ["efficient", "interested in", "responsible", "smooth"], "languages_combined": [{"language": "english", "language_level": ["fluent"]}, {"language": "chinese", "language_level": ["fluent"]}]}, "experience_required": {"duration": ["15+ years"], "field": ["commercial", "management", "retail", "people management"]}}, {"job_id": "100003009001950", "location_code": "hk", "company": "Conners Consulting Limited", "job_title": "Financial Institutions Relationship Manager (Multiple bank openings from Manager to Team head)", "description": "Our clients, well-known and fast expanding banks, are looking for a high caliber to join their group.\n\nResponsibilities\n\nDevelop and maintain customer relationship with FI clients\nExplore new business opportunities and actively participate in the marketing and selling of bank\u2019s corporate financial services in the areas of corporate lending, structured transactions, syndication, treasury, trade financing or other financial products\nConduct KYC and handle client onboarding procedures following regulatory requirements\nProvide professional financial solutions and conduct credit analysis and prepare credit proposals\n\nRequirements\n\nDegree holder or above in Business Administration or related disciplines\nMinimum 3 years\u2019 relationship management experience in FI or corporate banking\nStrong credit analysis and risk management skills as well as ability to analyses and make sound judgments on complex financial information\nProficient in spoken and written Chinese and English. Native Mandarin speaking is an absolute advantage.\u00a0\u00a0\n\nTo apply, please send your detailed resume or contact Winnie Lai at 3618 8348 for a confidential discussion.\n\nOnly shortlisted candidates will be notified.\n\nApplicants who are not contacted within two weeks may consider their applications unsuccessful.\n\nAll data collected will be used for recruitment purpose only & will be used strictly confidential.\n\nConners Consulting Limited\n\n2005 Kai Tak Commercial Building 317 Des Voeux Road Central Hong Kong\n\nTel: (852) 3996 8090\u00a0\u00a0\u00a0\u00a0\u00a0\u00a0 Website: www.connersconsulting.com", "employment_types": ["Full Time", "Permanent"], "selling_points": ["Excellent remuneration package and bonus scheme", "Fast expanding Chinese bank", "Work life balance"], "locations": ["Central & Western Area"], "categories": ["Banking / Finance", "Corporate Banking", "Credit Analysis / Approval", "Financial Services"], "post_time": "2021-12-28T03:26:06Z", "salary": {"currency": null, "max": null, "min": null, "period": "monthly", "term": null}, "salary_visible": false, "title_keywords": ["manager", "relationship manager"], "responsibilities": ["explore new business opportunities", "regulatory requirements", "analysis", "procedures", "transactions", "develop", "maintain", "kyc"], "requirements": {"degrees": ["degree holder"], "majors": ["related disciplines", "business administration"], "languages": ["english", "chinese", "mandarin"], "language_level": ["native", "proficient", "advantage"], "hard_skills": ["credit analysis", "make"], "soft_skills": ["detailed"], "languages_combined": [{"language": "english", "language_level": ["proficient"]}, {"language": "chinese", "language_level": ["proficient"]}, {"language": "mandarin", "language_level": ["native", "advantage"]}]}, "experience_required": {"duration": ["minimum 3 years"], "field": ["management", "banking"]}}, {"job_id": "100003009001455", "location_code": "hk", "company": "Dah Sing Financial Group", "job_title": "Manager, Internal Audit", "description": "Responsibilities:\n\nPerform the detailed design, configurations, building and testing of application and technical architecture components.\nProvide documentation of application solutions including functional & technical specifications and workflow diagrams.\nConduct user training and render support for system users\nDevelop & execute continuous improvement strategies and initiatives for process developments of key functionalities.\nAlign business requirements and ensure clear communication on features and roadmaps.\n\nRequirements\n\nBachelor\u2019s Degree in Computer Science / Information Systems or relevant discipline\nExpert developer knowledge and experience in Salesforce CRM systems and/or Marketing Cloud System\nProficiency in Salesforce programming development skills including APEX, Salesforce Object Query Language (SOQL) / Salesforce Object Search Language (SOSL), Lightning Web Components, Visual Force, API programming and JavaScript.\nSolid experience to work with key stakeholders across cloud transformation projects on Salesforce.com platforms (Commerce Cloud / Sales Cloud / Service Cloud / Marketing Cloud / Experience Cloud)\nExperience with common integration patterns used between legacy systems and Salesforce platform\nStrong communication & presentation skills\nGood command of English and Chinese including Mandarin", "employment_types": ["Permanent"], "selling_points": ["Perform critically analyze for the key risk areas", "Degree holder in Business Administration", "At least 5 years' solid experience"], "locations": ["North Point"], "categories": ["Accounting", "Audit", "Banking / Finance", "Credit Analysis / Approval", "Risk Management"], "post_time": "2021-12-28T02:28:14Z", "salary": {"currency": null, "max": null, "min": null, "period": "monthly", "term": null}, "salary_visible": false, "title_keywords": ["manager"], "responsibilities": ["design", "testing", "develop", "communication", "specifications", "documentation", "architecture"], "requirements": {"degrees": ["degree", "bachelor"], "majors": ["computer science"], "languages": ["english", "chinese", "mandarin"], "language_level": ["good command"], "hard_skills": ["salesforce", "apex", "web", "javascript", "programming", "integration"], "soft_skills": ["communication", "presentation skills"], "languages_combined": [{"language": "english", "language_level": ["good command"]}, {"language": "chinese", "language_level": ["good command"]}, {"language": "mandarin", "language_level": ["good command"]}]}, "experience_required": {"duration": [], "field": ["developer", "marketing"]}}, {"job_id": "100003008988921", "location_code": "hk", "company": "RGF HR Agent Hong Kong Limited", "job_title": "Analyst/Credit officer - Japanese Corporate Bank/ Great package", "description": "Reporting to the Line of Business, you will be responsible for developing and implementing our product management programs and initiatives, aiming to drive continual business growth and strengthen our competitive & brand positioning.\n\n\n\nResponsibilities:\n\nEngage in product management activities, including product enhancement programs, new product introduction, and portfolio management.\nActive involvement in project development and capturing new business opportunities.\nMonitor, analyze and evaluate market trend of focused applications, customer requirements, and competitor activities\nClosely collaborate with factory, sales & marketing, and overseas business partners, to ensure effective communication throughout business development. Continuously research the mobile electronics industry and be aware of the latest trends, developments and technologies\nOther ad hoc duties as assigned\n\nRequirements:\n\nBachelor Degree or above in Engineering / Business Administration or related disciplines\nMinimum 2 years of relevant experience in product and marketing management\nTechnical knowledge with business sense.\nStrong analytical thinking, business acumen and problem solving skills\nProficient in MS excel & PowerPoint is a must\nGood command of both spoken and written English and Chinese. Fluency in Putonghua is a must.\nStation in Hong Kong.\u00a0\n\n\nWe offer attractive remuneration package, 5-day work week and long-term career development opportunities to the right candidate. Please email your full resume with current and expected salary to\u00a0recruit_gpbi@ goldpeak.com.\n\nWe are an equal opportunity employer.\u00a0The information provided by you will be treated in strict confidence and used for recruitment purpose only.\u00a0\n\n\nFor more company details, please visit our website at www.gpbatteries.com.", "employment_types": ["Full Time", "Permanent"], "selling_points": ["Japanese Corporate Bank / Assist RM", "2+ yrs related exp./ Japanese is great advantage", "Knowledge of Accounting and credit analysis"], "locations": ["Not Specified"], "categories": ["Banking / Finance", "Corporate Banking", "Credit Analysis / Approval"], "post_time": "2021-12-21T02:00:00Z", "salary": {"currency": null, "max": null, "min": null, "period": "monthly", "term": null}, "salary_visible": false, "title_keywords": ["analyst", "officer"], "responsibilities": ["collaborate with", "ad hoc duties", "management", "business opportunities", "monitor", "evaluate", "communication"], "requirements": {"degrees": ["degree or above", "bachelor"], "majors": ["related disciplines", "business administration", "engineering"], "languages": ["putonghua", "english", "chinese"], "language_level": ["fluency", "good command"], "hard_skills": ["problem solving skills", "ms excel", "powerpoint", "acumen"], "soft_skills": ["business acumen", "problem solving skills", "business sense"], "languages_combined": [{"language": "putonghua", "language_level": ["fluency"]}, {"language": "english", "language_level": ["good command"]}, {"language": "chinese", "language_level": ["good command"]}]}, "experience_required": {"duration": ["minimum 2 years"], "field": ["management", "marketing", "relevant experience"]}}, {"job_id": "100003008989554", "location_code": "hk", "company": "Asia Progress Executive Limited", "job_title": "Manager,Credit Risk Monitoring  Private Banking -  Private Banking / Wealth Management $40K-60K", "description": "Our client is a reputable international Private Banking /Wealth Management To cope with the rapid business expansion, they are now inviting high caliber candidates to join the team\u00a0\n\nManager ,Credit Risk Monitoring,\u00a0Private Banking - Private Banking / Wealth Management - $40K-60K\n\n\nPosition Purpose\n\n\nPrepare and consolidate the daily and monthly risk monitoring reports on Hong Kong, Singapore and Taiwan On-Shore accounts to Risk-WM and WM Management.\nEnsure accounts operate within the guidelines or pre-approved exceptions and follow up with the Front office for action plans for new exceptions.\nReview the lending ratio on new securities and co-ordinate with Risk-WM for FR requests/ confirmations.\nCompile statistic reports for reporting or audit purpose\nCheck client\u2019s positions to determine eligibility for new placements and IPOs.\nContribute to the implementation of operational permanent control policies and procedures in day-to-day business activities, such as Control Plan\nComply with regulatory requirements and internal guideline\nContribute to the reporting of all incidents according to the Incident Management System\nUpdate monitoring templates to cater for systems upgrades.\nDaily update of Selected Key client positions based on combination of WM and CIB monitoring systems.\nContribute to process improvement, automation and other projects\nContribute to UAT of system changes\n\n\u00a0Key Responsibilities\n\n\nUndertake regular monitoring of all commitment clients under Wealth Management Hong Kong including:\u00a0\u00a0\n\u00a0Timely identification and reporting of under-margined clients.\n\u00a0Detection of limit excess and unauthorized trades.\n\u00a0Compliance with approval conditions and lending ratios.\nDaily monitoring of sensitive clients (large exposures, active trading in FX and Equity derivative transactions).\u00a0 Positions are on one-day delay basis but some clients placed on real time depending on the weaknesses identified.\nAuthorization of loan roll-overs and new drawdowns on a daily basis.\nChecking and release of security assets and funds.\nProviding ad-hoc positions of commitment clients at Relationship Managers\u2019 requests.\nDaily assessment of Pending Settlement Report to ensure clients maintains sufficient liquidity or credit facilities to meet their commitment on settlement date.\u00a0 Contacting the Relationship Managers requesting evidence of management approval for breach in procedures.\nDaily assessment of all transactions without authorized limits.\n\n\u00a0 \u00a0 \u00a0\u00a0\u00a0 \u00a0 \u00a0 \u00a0Control Aspect\n\u00a0 \u00a0 \u00a0 \u00a0 \u00a0 \u00a0 a)\u00a0 Direct contribution to operational permanent control framework.\n\u00a0 \u00a0 \u00a0 \u00a0 \u00a0 \u00a0 b)\u00a0 Contribute to the implementation of operational permanent control\n\u00a0 \u00a0 \u00a0 \u00a0 \u00a0 \u00a0 \u00a0 \u00a0 \u00a0policies\u00a0and\u00a0procedures in day-to-day business activities, such as Control\n\u00a0 \u00a0 \u00a0 \u00a0 \u00a0 \u00a0 \u00a0 \u00a0 \u00a0Plan\n\u00a0 \u00a0 \u00a0 \u00a0 \u00a0 \u00a0 c)\u00a0\u00a0Comply with regulatory requirements and internal guidelines\n\u00a0 \u00a0 \u00a0 \u00a0 \u00a0 \u00a0 d)\u00a0\u00a0Contribute to the reporting of all incidents according to the Incident\u00a0\n\u00a0 \u00a0 \u00a0 \u00a0 \u00a0 \u00a0 \u00a0 \u00a0 \u00a0Management\u00a0System\n\nCompetencies (Technical / Behavioural)\nEssential Technical Knowledge/Skills :\n\n\nGood computer skills \u2013 Word, Excel, Power Point, Macros. Knowledge of Python will be appreciated\nGood knowledge of banking and credit\nGood analytical skills\nGood command of spoken and written English, Cantonese and Mandarin\u00a0\n\n\nSpecific Qualifications Required\nQualifications and Experience:\n\n\nUniversity Graduate\nAt least 5 years\u00a0 credit\u00a0 risk Monitoring for Private Banking /Wealthmanagement\u00a0 / risk analyst experience\n\nPlease send full resume with\u00a0present & expected\u00a0salary to expedite sourcing\u00a0in\u00a0MS-WORD\u00a0format by clicking \u201cAPPLY NOW\u201d\n\nPlease quote our reference in your application\n\nPersonal data provided by job applicants will be used strictly in accordance with the employer\u2019s personal data policies, a copy of which will be provided upon request\n\nAll information provided will be used for recruitment purpose only", "employment_types": ["Full Time"], "selling_points": ["Degree 8yrs credit risk monitoring Private banking", "Credit Monitor Credit Margin clients for PBK/WM", "active trading FX & Equity derivative transaction"], "locations": ["Central & Western Area"], "categories": ["Banking / Finance", "Credit Analysis / Approval", "Private Banking", "Wealth Management"], "post_time": "2021-12-21T04:14:14Z", "salary": {"currency": null, "max": null, "min": null, "period": "monthly", "term": null}, "salary_visible": false, "title_keywords": ["wealth management", "manager", "private banking"], "responsibilities": ["ad-hoc", "co-ordinate with", "regulatory requirements", "audit", "transactions", "plan", "plans", "personal data", "daily monitoring", "control", "uat", "compliance", "implementation", "reports", "within the guidelines", "banking", "business activities", "report", "reporting", "management", "upgrades", "review", "procedures", "monitoring", "checking", "risk monitoring", "system changes", "guidelines", "policies", "systems", "recruitment"], "requirements": {"degrees": ["university graduate"], "majors": [], "languages": ["cantonese", "english", "mandarin"], "language_level": ["good command"], "hard_skills": ["excel", "ms-word", "word", "python", "analytical skills", "c", "computer skills", "rapid", "power point"], "soft_skills": ["timely", "active", "analytical skills", "sensitive"], "languages_combined": [{"language": "cantonese", "language_level": ["good command"]}, {"language": "english", "language_level": ["good command"]}, {"language": "mandarin", "language_level": ["good command"]}]}, "experience_required": {"duration": ["at least 5 years"], "field": ["banking"]}}, {"job_id": "100003008987352", "location_code": "hk", "company": "The Bank of East Asia, Limited", "job_title": "Assistant Relationship Manager, Enterprise Banking", "description": "Assistant Relationship Manager, Enterprise Banking (Job ID2735)\nResponsibilities\nTo be a team member of Enterprise Banking Department\nTo assist the Relationship Manager to build, manage and service a portfolio of corporate customers\nTo prepare credit proposals and conduct regular reviews to ensure credit quality\nTo provide administration support to the team on client portfolio regarding transactions referrals, KYC/compliance and progress status update\nTo take up ad hoc projects and assignments when required\nRequirements\nUniversity graduate in Business, Finance, or related discipline\nMinimum of 2 years' banking experience in banking / finance, with knowledge in financial analysis, commercial credit and lending policies\nMature, pleasant, outgoing, and a good team player\nStrong marketing sense with good business contacts\nSelf-motivated, independent and able to work under pressure\nGood command of both spoken and written English and Chinese, fluent in Putonghua is preferable\n(Candidates with less working experience will be considered for the position of Officer)\nPlease apply online via the BEA Careers website at\u00a0https://careers.hkbea.com/psp/hcmprd/EMPLOYEE/HRMS/c/HRS_HRAM.HRS_APP_SCHJOB.GBL?Page=HRS_APP_JBPST&Action=UFOCUS=Applicant&SiteId=1&JobOpeningId=2735&PostingSeq=1 or by clicking the \"Apply Now\" button below. Kindly note that if you are a new user, you have to first create your User Profile before you can apply.\nPersonal data provided by job applicants will be used for recruitment purposes only and will be treated in accordance with the Bank's Personal Information Collection (Employees) Statement and Privacy Policy Statement. Applicants who are not invited for interviews within six weeks may consider their applications unsuccessful and the personal data collected will be destroyed after six months.", "employment_types": ["Full Time", "Permanent"], "selling_points": ["To assist the Relationship Manager to build", "University graduate in Business, Finance", "Minimum of 2 years' banking experience"], "locations": ["Not Specified"], "categories": ["Accounting", "Financial Analyst", "Banking / Finance", "Analyst", "Credit Analysis / Approval"], "post_time": "2021-12-20T06:14:27Z", "salary": {"currency": null, "max": null, "min": null, "period": null, "term": null}, "salary_visible": false, "title_keywords": ["assistant relationship manager"], "responsibilities": ["compliance", "quality", "banking", "transactions", "ad hoc projects", "kyc", "administration"], "requirements": {"degrees": ["university graduate"], "majors": ["finance", "business"], "languages": ["putonghua", "english", "chinese"], "language_level": ["good command", "fluent"], "hard_skills": ["financial analysis", "c"], "soft_skills": ["outgoing", "good team player", "self-motivated", "marketing sense", "independent", "mature", "pleasant", "work under pressure"], "languages_combined": [{"language": "putonghua", "language_level": ["fluent", "good command"]}, {"language": "english", "language_level": ["good command"]}, {"language": "chinese", "language_level": ["good command"]}]}, "experience_required": {"duration": ["minimum of 2 years"], "field": ["banking experience", "finance", "commercial", "banking", "financial"]}}, {"job_id": "100003008988412", "location_code": "hk", "company": "Ignite Recruitment Hong Kong Limited", "job_title": "Corporate Banking, Assistant Relationship Manager (Credit) - Regional Corporate & Investment Bank", "description": "Our client is a stable and well-established regional corporate & investment bank in Hong Kong. They are currently looking for a Corporate Banking, Assistant Relationship Manager\u00a0to join their Corporate Banking Team to assist on managing a corporate banking portfolio.\n\nResponsibilities\n\n\n\nWork as a team to perform credit analysis and construct proposal on corporate client\nCoordinate with senior relationship manager, and work with other departments\u00a0to solicit new business from corporate customers\nAssist in maintaining & handling client relationship\nDraft the facility documents and review the legal documents.\nMonitor the customers\u2019 daily account operation and perform regular credit review to ensure credit quality of client portfolio\nLiaise with external stakeholder, such as legal counsel, professional valuers, and other counterparties.\n\nRequirements\n\n\nDegree or above\n1-3 years of corporate banking assistant relationship manager experience\nSolid experience on conducting credit proposal\u00a0\nGood command of written & spoken English\nTo apply online please click the 'Apply' button. For a confidential discussion about this role & other corporate banking openings please contact Alex CHEUNG at +852 2121 1418 .", "employment_types": ["Full Time", "Permanent"], "selling_points": ["Credit Analyst", "Prestigious & stable Bank", "Strong financial performance"], "locations": ["Central & Western Area"], "categories": ["Banking / Finance", "Corporate Banking", "Credit Analysis / Approval", "Corporate Finance"], "post_time": "2021-12-20T10:30:16Z", "salary": {"currency": "HKD", "max": 34999, "min": 20000, "period": "monthly", "term": null}, "salary_visible": true, "title_keywords": ["assistant relationship manager"], "responsibilities": ["maintaining", "analysis", "review", "coordinate with", "monitor", "quality", "liaise with"], "requirements": {"degrees": ["degree or above"], "majors": [], "languages": ["english"], "language_level": ["good command"], "hard_skills": [], "soft_skills": [], "languages_combined": [{"language": "english", "language_level": ["good command"]}]}, "experience_required": {"duration": ["1-3 years"], "field": ["banking"]}}, {"job_id": "100003008998528", "location_code": "hk", "company": "QBE General Insurance (Hong Kong) Limited", "job_title": "(Senior) Underwriter, Mortgage Insurance", "description": "QBE MI Asia is an international provider of credit enhancement products that promote homeownership and facilitate mortgage transactions in the capital markets.\u00a0 We provide mortgage insurance to Hong Kong lenders under QBE Mortgage Insurance Program.\u00a0 For further details please visit our website at www.qbe.com/mi\n\nMain Responsibilities:\n\nPerforms required underwriting procedures for mortgage loans\nAssess and respond to exceptions of established credit criteria guidelines\nObtains and processes information related to the loan origination process\nMaintains and updates credit and underwriting policies\nConducts periodic loan audits to ensure compliance with program guidelines\nMonitor regional economic developments that could affect business and credit decisions\nCompile and accurately report financial data as necessary\nProvide customer service support to stakeholders\n\nQualifications:\n\nDegree holder with minimum 3-5 years\u2019 loan underwriting experience\nKnowledge and experience of the Mortgage Insurance Program (MIP) preferred\nStrong analytical skills and clear communications\nExcellent command of both written and spoken English\n*More experienced candidates will be considered as Senior Underwriter.", "employment_types": ["Full Time"], "selling_points": ["Mortgage", "Global Insurance Company", "Competitive Salary"], "locations": ["Quarry Bay"], "categories": ["Banking / Finance", "Credit Analysis / Approval", "Insurance", "Underwriter"], "post_time": "2021-12-24T03:42:14Z", "salary": {"currency": null, "max": null, "min": null, "period": "monthly", "term": null}, "salary_visible": false, "title_keywords": [], "responsibilities": ["transactions"], "requirements": {"degrees": [], "majors": [], "languages": [], "language_level": [], "hard_skills": [], "soft_skills": [], "languages_combined": []}, "experience_required": {"duration": [], "field": []}}, {"job_id": "100003008985334", "location_code": "hk", "company": "Hang Seng Bank Ltd", "job_title": "Assistant Business and Credit Control Manager", "description": "Global Banking Division \u2013 Financial Institutions Group\n\n\nHang Seng's Global Banking business provides a broad spectrum of financing solutions to large corporations and financial institutions. As a strategic financial partner to corporate customers, Hang Seng offers a comprehensive range of products and services including bilateral and syndication loans, project financing, property development financing, property investment loans, working capital financing, trade financing, cash management and treasury products. Our experienced and knowledgeable professionals understand the specific requirements of our customers and are committed to providing tailor-made financial packages in their best interests.\n\n\nWe are currently seeking a high caliber professional to join our department as\u00a0Assistant\u00a0Business and\u00a0Credit Control\u00a0Manager.\nPrincipal responsibilities\n\nTo support the business and credit control of the department with particular focus on the following aspects:\n\nMonitor credit limit utilization to ensure that irregularities are properly controlled;\nSupport team head to implement compliance policy and procedures to ensure the business and systems are compliant;\nPrepare various reports as required by the Group / regulatory authorities as well as review the credit procedures and control measures to ensure compliance with the Bank\u2019s credit policy;\nParticipate in the development, maintenance and enhancement of management information system as well as other ad hoc projects;\nOversee the general administrative function of the department\nRequirements\nUniversity degree in Business Administration, Finance, Accounting OR other relevant professional qualifications;\nMinimum of two years' relevant experience in credit control, risk management, accounting or management information system;\nSound knowledge of application software;\nStrong numerical aptitude, with good communication and analytical skills;\nProficiency in both English and Chinese;\nGreat sense of ownership and servicing mindset to ensure efficient and effective customer service processes\n\nIf you would like to explore other opportunities at Hang Seng Hong Kong, please visit www.hangseng.com/careers/ for details.\n\n\nThe health and safety of our employees and candidates is very important to us. Due to the current situation related to the Novel Coronavirus (2019-nCoV), we\u2019re leveraging our digital capabilities to ensure we can continue to recruit top talent at the HSBC Group. \u00a0As your application progresses, you may be asked to use one of our digital tools to help you through your recruitment journey. \u00a0If so, one of our Resourcing colleagues will explain how our video-interviewing technology will be used throughout the recruitment process and will be on hand to answer any questions you might have\n\n\nAll information provided by applicants will be used only for recruitment purposes and will be used strictly in accordance with the Bank's personal data policies, a copy of which may be obtained by the applicant upon request. Unless otherwise instructed in writing by the applicant concerned, applicants may be considered for other suitable positions within the Bank and its related companies. The personal data of unsuccessful job applicants may be retained for a maximum of two years from the date when the job application is rejected and such data may be retained for a longer period if there is a subsisting reason that obliges the Bank to do so, after which the personal data will be destroyed.", "employment_types": ["Full Time", "Permanent"], "selling_points": [], "locations": ["Not Specified"], "categories": ["Banking / Finance", "Corporate Banking", "Credit Analysis / Approval"], "post_time": "2021-12-18T03:49:24Z", "salary": {"currency": null, "max": null, "min": null, "period": "monthly", "term": null}, "salary_visible": false, "title_keywords": ["manager", "assistant"], "responsibilities": ["control", "management", "irregularities", "maintenance", "compliance", "monitor", "procedures", "systems", "review", "ensure compliance", "reports", "ad hoc projects"], "requirements": {"degrees": ["university degree"], "majors": ["finance", "accounting", "business administration"], "languages": ["english", "chinese"], "language_level": ["proficiency"], "hard_skills": ["reason", "information system", "analytical skills", "professional qualifications"], "soft_skills": ["efficient", "analytical skills", "communication", "customer service", "novel"], "languages_combined": [{"language": "english", "language_level": ["proficiency"]}, {"language": "chinese", "language_level": ["proficiency"]}]}, "experience_required": {"duration": ["minimum of two years"], "field": ["risk management", "management", "accounting", "relevant experience"]}}, {"job_id": "100003008992362", "location_code": "hk", "company": "Public Finance Limited", "job_title": "Relief Branch Manager", "description": "Responsibilities:\nPerform relief/acting duties in branches and assist to manage the operations of the branches such as loan processing, credit approval, promotion of loan products etc.\nRequirements:\n5 years experience in banking / finance industry of which 3 years at supervisory level\nExperienced in preparing credit proposal or promoting banking / financial products e.g. personal loan, credit card, etc.\nResult-oriented, energetic, mature with good communication skills\nBenefits\nDouble Pay\nDiscretionary Bonus\nInsurance Benefits\nStudy subsidy\nApplication Method:\nBy E-mail via \"Apply Now\"\n\nPersonal data collected will be treated in the strictest confidence in accordance with our\u00a0Personal Information Collection Statement\u00a0and\u00a0Privacy Policy\u00a0and will be handled by authorized personnel for recruitment-related purposes only. All applications will be kept for a maximum period of one year as may be considered for other suitable positions within Public Finance Ltd. and its associated companies. For details, please visit the Company\u2019s website\u00a0http://www.publicfinance.com.hk", "employment_types": ["Full Time", "Permanent"], "selling_points": [], "locations": ["Not Specified"], "categories": ["Banking / Finance", "Credit Analysis / Approval", "Loan", "Financial Services"], "post_time": "2021-12-22T04:45:35Z", "salary": {"currency": null, "max": null, "min": null, "period": "monthly", "term": null}, "salary_visible": false, "title_keywords": ["manager"], "responsibilities": ["operations"], "requirements": {"degrees": [], "majors": [], "languages": [], "language_level": [], "hard_skills": [], "soft_skills": ["communication skills", "energetic", "result-oriented", "mature"], "languages_combined": []}, "experience_required": {"duration": ["5 years", "3 years"], "field": ["supervisory level", "finance industry", "banking"]}}, {"job_id": "100003008993570", "location_code": "hk", "company": "Sino Group", "job_title": "ASSISTANT MANAGER (GROUP TREASURY)(Ref: AM-GT/JDB)", "description": "The successful candidate will be responsible for managing the daily operation, ensuring the completion of the month-end closing timely, preparing cashflow reports, budgeting, financial reports, and performing other duties and ad hoc projects as required. He/she will assist Section Head to supervise subordinates, identify process improvement and provide advice and solutions to enhance efficiency on the operation, treasury, taxation, and reporting processes.\n\nRequirements:\n\nBachelor\u2019s degree holder or equivalent\nQualified member of ACCA, HKICPA, or equivalent\nMinimum 5 years' relevant experience with 3 years' auditing experience in a sizeable accounting firm\nFamiliar with accounting standards and statutory requirements\nStrong sense of responsibility, self-motivation, and independence\nDetail-oriented and be able to work under pressure\nProficient in spoken and written English and Chinese\nCandidate with less experience will be considered as a Senior Accountant\nWe offer attractive remuneration packages commensurate with experience and qualifications. If you aspire to an exciting and rewarding career, send your resume immediately, quoting your present and expected salaries by clicking the button \u201cApply Now\u201d.\nIf the applicant does not receive a response by 21\u00a0January 2022, the application will be considered unsuccessful. Before submitting your application, please read the Personal Data (Privacy) Policy and Personal Information Collection Statement at our Company website. Information provided by applicants will be treated in strict confidence and used for recruitment purposes only.", "employment_types": ["Full Time"], "selling_points": [], "locations": ["Not Specified"], "categories": ["Accounting", "Treasurer", "Banking / Finance", "Credit Analysis / Approval", "Loan"], "post_time": "2021-12-22T08:25:17Z", "salary": {"currency": null, "max": null, "min": null, "period": null, "term": null}, "salary_visible": false, "title_keywords": ["assistant manager"], "responsibilities": ["taxation", "financial reports", "reporting", "other duties", "budgeting", "daily operation", "statutory requirements", "month-end closing", "reports", "ad hoc projects", "provide advice", "auditing", "work under pressure"], "requirements": {"degrees": ["bachelor", "degree holder"], "majors": [], "languages": ["english", "chinese"], "language_level": ["proficient"], "hard_skills": ["acca", "hkicpa"], "soft_skills": ["responsible", "sense of responsibility", "timely", "detail-oriented", "self-motivation", "work under pressure"], "languages_combined": [{"language": "english", "language_level": ["proficient"]}, {"language": "chinese", "language_level": ["proficient"]}]}, "experience_required": {"duration": ["3 years", "minimum 5 years"], "field": ["accounting", "relevant experience", "senior accountant"]}}, {"job_id": "100003009004882", "location_code": "hk", "company": "Nova Credit Limited", "job_title": "Senior Product Manager / Product Manager (Fintech)", "description": "We are looking for an experienced and passionate Senior Product Manager to join us.\n\nThe Team: We leverage data/analytics/Fintech products to 1) provide solutions for financial institutions to help them meet the demands of today\u2019s ever-changing environment; 2) provide innovative products and services to consumers to help them better manage their credit.\n\nResponsibilities:\n\nDirectly contribute to the successful execution of the product development and go-to-market strategies of solutions that solve for the needs of our clients\nUnderstand retail banking and credit cycle\nConduct market, company and competitor research on new products\nPropose new business opportunities to form product proposition through being in touch with the industry and regulatory trends in credit industry, data/analytics businesses, Fintech development;\nWork with internal and external stakeholders to understand needs, define features, write product specifications;\nCreate product manual, training materials and commercial education to inspire clients;\nWork with marketing and sales team to increase products acceptance\n\nRequirements:\n\nBachelor degree or above\n5 or more years of experience in financial industry (banking or lending business background is advantageous)\nPassionate for creating customer-centric solutions\nA mature team player with strong presentation and communications skills\nSound Project Management mindset and skills\nProficient in Cantonese, English and Mandarin\nCandidates with demonstrated strong track record of leadership and experience will be considered for the Senior Product Manager position", "employment_types": ["Full Time", "Permanent"], "selling_points": [], "locations": ["Cheung Sha Wan"], "categories": ["Banking / Finance", "Credit Analysis / Approval", "Information Technology (IT)", "Product Management / Business Analyst", "Risk Management"], "post_time": "2021-12-29T03:10:37Z", "salary": {"currency": null, "max": null, "min": null, "period": "monthly", "term": null}, "salary_visible": false, "title_keywords": ["senior product manager", "product manager"], "responsibilities": ["data", "business opportunities", "specifications", "sales team", "banking"], "requirements": {"degrees": ["degree or above", "bachelor"], "majors": [], "languages": ["cantonese", "english", "mandarin"], "language_level": ["proficient"], "hard_skills": ["project management"], "soft_skills": ["passionate", "mature", "project management", "team player", "leadership", "presentation"], "languages_combined": [{"language": "cantonese", "language_level": ["proficient"]}, {"language": "english", "language_level": ["proficient"]}, {"language": "mandarin", "language_level": ["proficient"]}]}, "experience_required": {"duration": [], "field": ["business", "financial industry", "banking"]}}, {"job_id": "100003008993453", "location_code": "hk", "company": "China Construction Bank (Asia) Corporation Limited", "job_title": "VP, Relationship Manager, Commercial Banking (Ref no: SRM/CMB/JDB)", "description": "Job Descriptions:\n\nManage a portfolio of commercial clients who need financial services and customized products to meet their financial needs\nProspect and generate new business by focusing on enhancing existing relationships, and identifying opportunities for uptiering\nInterview prospective clients to collect information concerning their business needs, desires, abilities, and earnings to determine the business opportunities\nUse analytical skills and knowledge of credit policies required to evaluate the financial condition of the clients, make credit recommendations for Management\u2019s approval\n\nRequirements:\n\nDegree holder in Business, Economics or related disciplines is preferred\nMinimum 5 years of banking experience in trade financing and commercial banking;\u00a0\n\nQualifications in IIQE/HKSI related areas are preferred\n\nKnowledge of the principles of commercial credit and lending policies and standards\nStrong business development skills and proficiency in the financial services/products offered to middle market companies\nGood communication skills in both English and Chinese (Cantonese & Putonghua)\n* Candidates with less experience will be considered as Relationship Manager.\n\n\nTo apply, please send the detailed resume to the designated email address or by fax at 3718 2910.\n\nApplicants who are not contacted within 8 weeks may consider their applications unsuccessful and their personal data will be retained by the bank for a period up to two years.\n\nAll information provided by applicants will be used for recruitment purposes only and will be used strictly in accordance with the bank\u2019s personal data policies, a copy of which will be provided upon request.", "employment_types": ["Full Time", "Permanent"], "selling_points": ["Medium-Sized Enterprises / List Co.", "Portfolio management & new business generation", "Bachelor degree with min. 5 yrs of RM experience"], "locations": ["Kowloon Bay"], "categories": ["Banking / Finance", "Corporate Banking", "Credit Analysis / Approval", "Sales, CS & Business Devpt", "Business Development"], "post_time": "2021-12-22T08:00:22Z", "salary": {"currency": null, "max": null, "min": null, "period": "monthly", "term": null}, "salary_visible": false, "title_keywords": ["relationship manager"], "responsibilities": ["evaluate", "policies", "business opportunities", "management"], "requirements": {"degrees": ["degree holder"], "majors": ["related disciplines", "economics", "business"], "languages": ["cantonese", "putonghua", "english", "chinese"], "language_level": ["good"], "hard_skills": ["iiqe", "hksi"], "soft_skills": ["communication skills", "detailed"], "languages_combined": [{"language": "cantonese", "language_level": ["good"]}, {"language": "putonghua", "language_level": ["good"]}, {"language": "english", "language_level": ["good"]}, {"language": "chinese", "language_level": ["good"]}]}, "experience_required": {"duration": ["minimum 5 years"], "field": ["commercial", "financing", "banking experience", "banking"]}}]